Workbook

Sheet KPIs_v1
B2: # | C2: Ítem | D2: Unidad | E2: 45474 | F2: 45505 | G2: 45536 | H2: 45566 | I2: 45597 | J2: 45627 | K2: Q4-24 | L2: Media Q4 2024 | M2: S1 | N2: S2 | O2: S3 | P2: S4 | Q2: 45658 | R2: S1 feb-25 | S2: Media | U2: Observaciones:
B3: 1 | C3: Propuestas emitidas | D3: # | E3: =8+8 -> 16 | G3: 6 | H3: =8+H5 -> 12 | I3: =9+I5 -> 15 | J3: =7+J5 -> 15 | K3: =+SUM(H3:J3) -> 42 | L3: =+K4/K3 -> 236.30952 | M3: 1 | N3: 3 | O3: 3 | P3: 1 | Q3: =+M3+N3+O3+P3 -> 8 | R3: 3 | S3: =+R4/R3 -> 323.66667
D4: kUS$ | E4: =1062+E6 -> 1735 | G4: =453+300 -> 753 | H4: =1600+H6 -> 1999 | I4: =2455+I6 -> 3967 | J4: =2600+J6 -> 3959 | K4: =+SUM(H4:J4) -> 9925 | M4: 200 | N4: 1400 | O4: 470 | P4: 142 | Q4: =+M4+N4+O4+P4 -> 2212 | R4: 971
B5: 2 | C5: Propuestas adjudicadas | D5: # | E5: 8 | F5: 6 | G5: 3 | H5: 4 | I5: 6 | J5: 8 | K5: =+SUM(H5:J5) -> 18 | L5: =+K6/K5 -> 181.66667 | M5: 4 | N5: 2 | O5: 2 | P5: 0 | Q5: =+M5+N5+O5+P5 -> 8 | R5: 1 | S5: =+R6/R5 -> 1045
D6: kUS$ | E6: 673 | F6: 524 | G6: 300 | H6: 399 | I6: =+Respaldo!I25 -> 1512 | J6: =+Respaldo!I31 -> 1359 | K6: =+SUM(H6:J6) -> 3270 | M6: 690 | N6: 240 | O6: 395 | P6: 0 | Q6: =+M6+N6+O6+P6 -> 1325 | R6: 1045
C7: Plazo Medio Adjudicado | D7: Meses | Q7: =+M7 -> 0
C8: Relación Monto/plazo | D8: US$/mes | Q8: =+M8 -> 0
C9: Saldo de Contratos (Por Ejecutar) | D9: kUS$ | Q9: =+M9 -> 0
B10: 3 | C10: Propuestas iniciadas c/ KOM | D10: # | H10: 4 | I10: 6 | J10: 5 | K10: =+SUM(H10:J10) -> 15 | L10: =+K11/K10 -> 193 | M10: 0 | N10: 1 | Q10: =+N10+M10+O10+P10 -> 1 | R10: 0 | S10: 0
D11: kUS$ | H11: 399 | I11: 1012 | J11: 1484 | K11: =+SUM(H11:J11) -> 2895 | M11: 0 | N11: 345 | Q11: =+N11+M11+O11+P11 -> 345 | R11: 0
D12: #(KOM interno) | H12: 1 | I12: 3 | J12: 4 | K12: =+SUM(H12:J12) -> 8 | Q12: =+M12 -> 0
B13: 4 | C13: POM Mensual | D13: # | H13: 14 | I13: 24 | J13: 23 | K13: =+SUM(H13:J13) -> 61 | L13: =+K14/K13 -> 31.95082 | M13: 22 | N13: 22 | O13: 22 | P13: 22 | Q13: =+P13 -> 22 | R13: 16 | S13: =+R14/R13 -> 35.1875
D14: kUS$ | H14: 516 | I14: 652 | J14: 781 | K14: =+SUM(H14:J14) -> 1949 | M14: 762 | N14: 754 | O14: 718 | P14: 718 | Q14: =+P14 -> 718 | R14: 563
B15: 5 | C15: EDP Emitidos | D15: # | H15: 16 | I15: 17 | J15: 19 | K15: =+SUM(H15:J15) -> 52 | L15: =+K16/K15 -> 34.384615 | M15: 0 | N15: 2 | O15: 8 | P15: 10 | Q15: =M15+N15+O15+P15 -> 20 | R15: 0 | S15: 0
D16: kUS$ | H16: 527 | I16: 429 | J16: =770+62 -> 832 | K16: =+SUM(H16:J16) -> 1788 | M16: 0 | N16: 86 | O16: 261 | P16: 354 | Q16: =M16+N16+O16+P16 -> 701 | R16: 0
B17: 6 | C17: EDP Facturados | D17: # | H17: 23 | I17: 17 | J17: 18 | K17: =+SUM(H17:J17) -> 58 | L17: =+K18/K17 -> 32.37931 | M17: 12 | N17: 1 | O17: 1 | P17: 4 | Q17: =+N17+M17+O17+P17 -> 18 | R17: 0 | S17: 0
D18: kUS$ | H18: 864 | I18: 493 | J18: 521 | K18: =+SUM(H18:J18) -> 1878 | M18: 427 | N18: 82 | O18: 35 | P18: 142 | Q18: =+N18+M18+O18+P18 -> 686 | R18: 0
B19: 7 | C19: EDP Pendientes (En proceso de aprobación) | D19: # | M19: 4 | N19: 2 | O19: 2 | P19: 0 | Q19: =+P19 -> 0 | R19: 10 | S19: =+R20/R19 -> 17.5
D20: kUS$ | M20: 192 | N20: 43 | O20: 43 | P20: 0 | Q20: =+P20 -> 0 | R20: 175
B21: 8 | C21: EDP Rezagados (emitidos no aprobados) | D21: # | I21: 1 | J21: 3 | K21: =+SUM(H21:J21) -> 4 | L21: =+K22/K21 -> 23.5 | M21: 2 | N21: 2 | O21: 1 | P21: 1 | Q21: =+P21 -> 1 | R21: 1 | S21: =+R22/R21 -> 35
D22: kUS$ | I22: 35 | J22: 59 | K22: =+SUM(H22:J22) -> 94 | M22: 70 | N22: 70 | O22: 35 | P22: 35 | Q22: =+P22 -> 35 | R22: 35
C23: Facturación | D23: kUS$ | H23: 864 | I23: 493 | J23: 551 | K23: =+SUM(H23:J23) -> 1908 | L23: =+K23/3 -> 636 | Q23: =+M23 -> 0
C24: Facturas por cobrar | D24: # | Q24: =+M24 -> 0
D25: kUS$ | Q25: =+M25 -> 0
B26: 9 | C26: Facturas Pagadas (Ingreso Operacional) | D26: # | H26: 25 | I26: 15 | J26: 15 | K26: =+SUM(H26:J26) -> 55 | L26: =+K27/K26 -> 38.109091 | M26: 4 | N26: 4 | O26: 8 | P26: 4 | Q26: =+N26+M26+O26+P26 -> 20 | R26: 2 | S26: =+R27/R26 -> 23 | T26: =+T27-Q27 -> 0 | W26: 175.000 adjudicada birchlake | X26: 175
D27: kUS$ | H27: 1004 | I27: 616 | J27: 476 | K27: =+SUM(H27:J27) -> 2096 | M27: 197 | N27: 83 | O27: 269 | P27: 157 | Q27: =+N27+M27+O27+P27 -> 706 | R27: 46 | T27: 706 | W27: Revisión de validación reportes R&R (15 assets) | X27: 220
B28: 10 | C28: Facturas Vencidas | D28: # | J28: 8 | K28: =+SUM(H28:J28) -> 8 | L28: =+K29/K28 -> 35.75 | M28: 5 | N28: 3 | O28: 2 | P28: 5 | Q28: =+P28 -> 5 | R28: 5 | S28: =+R29/R28 -> 50.8 | U28: Enviado | V28: Candelaria Zublin
D29: KUS$ | J29: 286 | K29: =+SUM(H29:J29) -> 286 | M29: 110 | N29: 60 | O29: 26.8 | P29: =227+27 -> 254 | Q29: =+P29 -> 254 | R29: 254 | V29: Cadelaria | W29: 80
B30: 11 | C30: Cumplimiento POM vs EDP | D30: % | H30: =+IFERROR(H16/H14,0) -> 1.0213178 | I30: =+IFERROR(I16/I14,0) -> 0.65797546 | J30: =+IFERROR(J16/J14,0) -> 1.0653009 | K30: =+AVERAGE(H30:J30) -> 0.91486473 | L30: - | M30: - | N30: =+IFERROR(N16/N14,0) -> 0.11405836 | O30: =+IFERROR(O16/O14,0) -> 0.36350975 | P30: =+IFERROR(P16/P14,0) -> 0.49303621 | Q30: =+IFERROR(Q16/Q14,0) -> 0.97632312 | R30: 0 | S30: 0 | W30: 240
B31: 12 | C31: Adherencia POM vs EDP | D31: % | H31: 0.73 | I31: 0.67 | J31: 0.76 | K31: =+AVERAGE(H31:J31) -> 0.72 | L31: - | M31: - | N31: - | O31: - | P31: - | Q31: 0.84 | R31: 0 | S31: 0 | W31: 150

Sheet Respaldo
B3: ID | C3: Proyecto | D3: US$ | E3: Fecha Inicio | F3: Mes | G3: KOM con cliente | H3: KOM Interno Realizado
B4: 1 | C4: BHP – MEL​-Modelo predictivo Pozos de drenaje | D4: 190 | F4: Julio | I4: =+SUM(D4:D11) -> 673
B5: 2 | C5: BHP - Spence​-Análisis de cumplimiento del plan | D5: 75 | F5: Julio
B6: 3 | C6: Mosaic – Cajati​-Actualización análisis de Estabilidad OP​ | D6: 90 | F6: Julio
B7: 4 | C7: CMP – Los Colorados​-“Plan Minero Base Escenario Brownfield MLC​ | D7: 43 | F7: Julio
B8: 5 | C8: CMP – Tofo Norte​-Tofo Norte, modularizado​ | D8: 50 | F8: Julio
B9: 6 | C9: CMP – CNN/LC​-Apoyo LOM 2024 Faenas MLC y CNN​ | D9: 95 | F9: Julio
B10: 7 | C10: Mosaic – Cajati​-Evaluación cumplimiento plan OP | D10: 60 | F10: Julio
B11: 8 | C11: Minsur – San Rafael​-Evaluación de recursos marginales​ | D11: 70 | F11: Julio
B12: 9 | C12: Minsur – Mina Justa​-Proyecto Achupallas | D12: 133 | F12: Agosto | I12: =+SUM(D12:D17) -> 524
B13: 10 | C13: Codelco - DCH​-Analisis opciones de vaciado | D13: 85 | F13: Septiembre
B14: 11 | C14: CMP –Algarrobo​-Algarrobo Finos | D14: 100 | F14: Octubre
B15: 12 | C15: CMP – CNN​-Mejoras operacionales | D15: 100 | F15: Noviembre
B16: 13 | C16: Lundin – Candelaria​-Diagnóstico de gaps de planificación y operaciones | D16: 66 | F16: Diciembre
B17: 14 | C17: Lhg - Autazes​-Taller y evaluación de información | D17: 40 | F17: Enero
B18: 15 | C18: Tantahuatay​ - servicio de capacitación en DBS y SIMPLAN​ | D18: 20 | F18: Septiembre | I18: =+SUM(D18:D20) -> 300
B19: 16 | C19: BHP - Escondida​-Tunel exploratorio​ | D19: 160 | F19: Septiembre
B20: 17 | C20: Lundin – Caserones​-Evaluación opciones de mejora de planificación | D20: 120 | F20: Septiembre
B21: 18 | C21: Estudio Conceptual Sierra Norte (Opción Óxidos) | D21: 250 | E21: 45572 | F21: Octubre | G21: Si | H21: Si | I21: =+SUM(D21:D24) -> 398.5 | J21: Propuesta Iniciadas c/KOM | K21: #
B22: 19 | C22: FEL3 CNN | D22: 100 | E22: 45579 | F22: Octubre | G22: Si | H22: No | K22: kUS$
B23: 20 | C23: Capacitacion DBS Buenaventura | D23: 20 | E23: 45579 | F23: Octubre | G23: Si | H23: No
B24: 21 | C24: Soporte Minero en Litigio OT - Gobierno Mongolia | D24: 28.5 | E24: 45586 | F24: Octubre | G24: Si | H24: No
B25: 22 | C25: Pre-PFS Twin Metals Birch Lake - Maturi | D25: 480 | E25: 45600 | F25: Noviembre | G25: Si | H25: Si | I25: =+SUM(D25:D31) -> 1512
B26: 23 | C26: Analisis de Capacidad Optima Tofo Norte | D26: 45 | E26: 45600 | F26: Noviembre | G26: Si | H26: No
B27: 24 | C27: Fase 2 CTV: Modelamiento Recursos, Geomecanica y LOM actualizado | D27: 355 | E27: 45600 | F27: Noviembre | G27: Si | H27: Si
B28: 25 | C28: Revision Normativa Recursos y Reservas Codelco (NCC-31) | D28: 80 | E28: 45614 | F28: Noviembre | G28: Si | H28: No
B29: 26 | C29: Servicio de Apoyo a la doc. De corto Plazo - RT | D29: 14 | E29: 45614 | F29: Noviembre | G29: Si | H29: No
B30: 27 | C30: RT: Análisis de Estándar cierre topográfico | D30: 38 | E30: 45614 | F30: Noviembre | G30: Si | H30: Si
B31: 28 | C31: Analisis Innovación Tecnologica Distrito Centinela | D31: 500 | E31: 45649 | F31: Noviembre | G31: Si | H31: Si | I31: =+SUM(D32:D38) -> 1359
B32: 29 | C32: Análisis Conceptual - Aura UG | D32: 224 | E32: 45642 | F32: Diciembre | G32: Si | H32: Si
B33: 30 | C33: Resolution: MinePlan Review (Scoping) | D33: 260 | E33: 45635 | F33: Diciembre | G33: Si | H33: Si
B34: 31 | C34: Raura: Analisis Plan LOM 2025 | D34: 50 | E34: 45642 | F34: Diciembre | G34: Si | H34: Si
B35: 32 | C35: Cerro Colorado: Diseño Cierre de Botaderos | D35: 450 | E35: 45649 | F35: Diciembre | G35: Si | H35: No
B36: 33 | C36: INGENIERÍA EXPLORATORIA DEL PROYECTO DMH NORTE | D36: 75 | E36: 45635 | F36: Diciembre | H36: Si
B37: 34 | C37: Los Calatos Pre-FP Study (V3) | D37: 270 | E37: - | F37: Diciembre | H37: Si
B38: 35 | C38: BCG: Evaluación de la planificación de Codelco | D38: 30 | F38: Diciembre | G38: NO | H38: No
C39: Cumplimiento | D39: =+SUM(D21:D38) -> 3269.5 | H39: 0.53
C41: Diciembre | D41: Anglo American | E41: Los Bronces | F41: Estudio de productividad | G41: 100000
C42: Diciembre | D42: BHP | E42: Spence | F42: Análisis de confiabilidad y detección de cuellos de botella del LoA 25 – Proyecto SCUT | G42: 45000
C43: Diciembre | D43: Vale | F43: Servicio IQS para nueve assets | G43: 1600000
C44: Diciembre | D44: Anglo American | E44: Los Bronces | F44: Ing. Pre factibilidad perforación DHH | G44: 240000
C45: Diciembre | D45: First Quantum | E45: Cobre Panama | F45: Lom estrategico | G45: 220000
C46: Diciembre | D46: Minsur | E46: San Rafael | F46: Preparación IV MEIA San German | G46: 180000
C47: Diciembre | D47: Volcan | F47: Revisión de validación reportes R&R (15 assets) | G47: 200000
C48: Noviembre | D48: Atlas Mining | F48: Plan LOM de distintas estrategias de crecimiento de la planta | G48: 425000
C49: Noviembre | D49: CAP | E49: Guarelo | F49: Estudio integral de LOM Mina Guarelo: Acompañamiento desde el plan de captura de información hasta el LOM | G49: 60000
C50: Noviembre | D50: Minera Reliquias | F50: Due Diligence Mina-Planta | G50: 250000
C51: Noviembre | D51: Anglo American | E51: Andina | F51: Due Diligence Higlevel Mina-Planta-Infraestrutura de Andina | G51: 150000
C52: Noviembre | D52: McCarthy Abogados | E52: Alio Gold | F52: Technical Expert Support of the plaintiff’s allegation to Alio Gold Inc | G52: 340000
C53: Noviembre | D53: EMCO | F53: Optimización de rutas de transporte, Simulación, Modelos geotécnico y monitoreo | G53: 334000
C54: Noviembre | D54: Seprocal | F54: Ingenieria de detalle de fortificación de piques | G54: 160000
C55: Noviembre | D55: CMP | E55: Algarrobo | F55: Evaluación caso de negocio explotación SLS | G55: 170000
C56: Noviembre | D56: Rio Tinto | E56: Oyu Tolgoi | F56: Soporte caso de litigio Rio Tinto vs Gobierno Mongolia | G56: 566000
C57: Octubre | D57: Hudbay Perú S.A.C | E57: Constancia | F57: Estudio de Factibilidad del WRF y Tajo Constancia para la 4ta MEIA | G57: 190000
C58: Octubre | D58: Las Bambas | E58: Ferrobamba | F58: PFS Ferrobamba Deep | G58: 1100000
C59: Octubre | D59: Carola | E59: Carola | F59: Apoyo en la planificación de Corto Plazo (SIMPREP) | G59: 66000
C60: Octubre | D60: Sierra Metals | E60: Yauricocha | F60: ESTUDIO DE VENTILACIÓN UNIDAD MINERA YAURICOCHA | G60: 250000
C61: Septiembre | D61: OCP | E61: OCP - Cobriza ​ | F61: Diagnostico operacional y construcción de planes alternativos (Blue Sky y potencial)​ | G61: 180
C62: Septiembre | D62: Rockhaven​ | E62: Rockhaven​ | F62: Mining Trade Off Study​ | G62: 173
C63: Septiembre | D63: Codelco | E63: Codelco – DRT​ | F63: Análisis y cuantificación de cobre en riesgo por expansión del OP​ | G63: 100
C64: Julio | D64: Hudbay Perú S.A.C | E64: Hudbay - Constancia​ | F64: Análisis de estabilidad OP​ | G64: 81
C65: Julio | D65: Cementarion | E65: Cementation - First Majestic​ | F65: FS Study: LOM that can be used for economic evaluation of the Jerritt Canyon mine site​ | G65: 500
C66: Julio | D66: CMP | E66: CMP​ | F66: Contrato Marco de Ingeniería – Gerencia de Planificación & Desarrollo CMP​ | G66: -​
C67: Julio | D67: Codelco | E67: Codelco – DRT​ | F67: Revisión independiente modelo de recursos DRT​ | G67: 45
C68: Julio | D68: Minsur | E68: Minsur - Raura​ | F68: Estandarización, control y seguimiento de KPIs/resultados de corto/mediano plazo para Minsur ​ | G68: 125
C69: Julio | D69: Seligar | E69: Seligdar​ | F69: Construccion de wireframes de cuerpo mineral y modelos de bloque de 2 yacimientos​ | G69: 150
C70: Julio | D70: Minera Tres valles​ | E70: Minera Tres valles​ | F70: Modelo de flujo gravitacional​ | G70: 81
C71: Julio | D71: Buenaventura | E71: Buenaventura – El Brocal​ | F71: Estudio de ingeniería de factibilidad para la Ampliación del Tajo Norte​ | G71: 80

Sheet KPI´s de negocio 2024
B2: # | C2: Ítem | D2: Unidad | E2: 45474 | F2: 45505 | G2: 45536 | H2: 45566 | I2: 45597 | J2: 45627 | K2: Acumulado | L2: Media kUS$ | N2: Cantidad de Proyectos | O2: 24
B3: 1 | C3: Propuestas emitidas | D3: # | H3: =8+H5 -> 12 | I3: =9+I5 -> 15 | J3: =7+J5 -> 15 | K3: =+SUM(H3:J3) -> 42 | L3: =+K4/K3 -> 236.30952
D4: kUS$ | H4: =1600+H6 -> 1999 | I4: =2455+I6 -> 3467 | J4: =2600+J6 -> 4459 | K4: =+SUM(H4:J4) -> 9925
B5: 2 | C5: Propuestas adjudicadas | D5: # | H5: 4 | I5: 6 | J5: 8 | K5: =+SUM(H5:J5) -> 18 | L5: =+K6/K5 -> 181.66667
D6: kUS$ | H6: 399 | I6: 1012 | J6: 1859 | K6: =+SUM(H6:J6) -> 3270
B7: 3 | C7: Propuestas iniciadas c/ KOM | D7: # | H7: 4 | I7: 6 | J7: 5 | K7: =+SUM(H7:J7) -> 15 | L7: =+K8/K7 -> 193
D8: kUS$ | H8: 399 | I8: 1012 | J8: 1484 | K8: =+SUM(H8:J8) -> 2895
D9: #(KOM interno) | H9: 1 | I9: 3 | J9: 4 | K9: =+SUM(H9:J9) -> 8
B10: 4 | C10: POM Mensual | D10: # | H10: 14 | I10: 24 | J10: 23 | K10: =+SUM(H10:J10) -> 61 | L10: =+K11/K10 -> 31.95082
D11: kUS$ | H11: 516 | I11: 652 | J11: 781 | K11: =+SUM(H11:J11) -> 1949
B12: 5 | C12: EDP Mensual | D12: # | H12: 16 | I12: 17 | J12: 19 | K12: =+SUM(H12:J12) -> 52 | L12: =+K13/K12 -> 34.384615 | N12: =+L12*O2 -> 825.23077 | O12: =+N12*12 -> 9902.7692
D13: kUS$ | H13: 527 | I13: 429 | J13: =770+62 -> 832 | K13: =+SUM(H13:J13) -> 1788 | N13: Considera 25 EDP | O13: Proyecta 10,3 MUS$
B14: 6 | C14: Facturación | D14: kUS$ | H14: 864 | I14: 493 | J14: 551 | K14: =+SUM(H14:J14) -> 1908 | L14: =+K14/3 -> 636
B15: 7 | C15: Ingresos Operacionales | D15: kUS$ | H15: 1004 | I15: 616 | J15: 476 | K15: =+SUM(H15:J15) -> 2096 | L15: =+K15/3 -> 698.66667
B16: 8 | C16: Cumplimiento POM vs EDP | D16: % | H16: =+IFERROR(H13/H11,0) -> 1.0213178 | I16: =+IFERROR(I13/I11,0) -> 0.65797546 | J16: =+IFERROR(J13/J11,0) -> 1.0653009 | K16: =+AVERAGE(H16:J16) -> 0.91486473 | L16: -
B17: 9 | C17: Adherencia POM vs EDP | D17: % | H17: 0.73 | I17: 0.67 | J17: 0.76 | K17: =+AVERAGE(H17:J17) -> 0.72 | L17: -

Sheet KPI´s de negocio REDCO
B2: Resp. | C2: # | D2: Ítem | E2: Unidad | F2: 45474 | G2: 45505 | H2: 45536 | I2: 45566 | J2: 45597 | K2: 45627 | L2: Q4-24 | M2: Media Q4 2024 | N2: S1 | O2: S2 | P2: S3 | Q2: S4 | R2: 45658 | S2: S1 feb-25 | T2: S2 feb-25 | U2: S3 feb-25 | V2: S4 feb-25 | W2: 45689 | X2: S1 mar-25 | Y2: S2 mar-25 | Z2: S3 mar-25 | AA2: S4 mar-25 | AB2: 45717 | AC2: S1 abr-25 | AD2: S2 abr-25 | AE2: S3 abr-25 | AF2: S4 abr-25 | AG2: S5 abril-25 | AH2: 45748 | AI2: S1 may-25 | AJ2: S2 may-25 | AK2: S3 may-25 | AL2: S4 may-25 | AM2: 45778 | AN2: S1 Jun-25 | AO2: S2 Jun-25 | AP2: S3 Jun-25 | AQ2: S4 Jun-25 | AR2: 45809 | AS2: S1 Jul-25 | AT2: S2 Jul-25 | AU2: S3 Jul-25 | AV2: S4 Jul-25 | AW2: S5 Jul-25 | AX2: 45839 | AY2: S1 ago-25 | AZ2: S2 ago-25 | BA2: S3 ago-25 | BB2: S4 ago-25 | BC2: 45870 | BD2: S1 sep-25 | BE2: S2 sep-25 | BF2: S3 sep-25 | BG2: S4 sep-25 | BH2: 45901 | BI2: S1 oct-25 | BJ2: S2 oct-25 | BK2: S3 oct-25 | BL2: S4 oct-25 | BM2: 45931 | BN2: Media oct | BO2: Acum. 2025 | BP2: Media Acum. | BR2: Observaciones:
B3: PA | C3: 1 | D3: Propuestas Emitidas | E3: # | F3: =8+8 -> 16 | H3: 6 | I3: =8+I5 -> 12 | J3: =9+J5 -> 15 | K3: =7+K5 -> 15 | L3: =+SUM(I3:K3) -> 42 | M3: =+L4/L3 -> 236.30952 | N3: 1 | O3: 3 | P3: 3 | Q3: 1 | R3: =+N3+O3+P3+Q3 -> 8 | S3: 3 | T3: 2 | U3: 2 | V3: 3 | W3: =+S3+T3+U3+V3 -> 10 | X3: 5 | Y3: 2 | Z3: 3 | AA3: 1 | AB3: =+X3+Y3+Z3+AA3 -> 11 | AC3: 0 | AD3: 9 | AE3: 2 | AF3: 5 | AG3: 2 | AH3: =+AC3+AD3+AE3+AF3+AG3 -> 18 | AI3: 2 | AJ3: 2 | AK3: 3 | AL3: 1 | AM3: =+AI3+AJ3+AK3+AL3 -> 8 | AN3: 3 | AO3: 9 | AP3: 3 | AQ3: 6 | AR3: =+AN3+AO3+AP3+AQ3 -> 21 | AS3: 4 | AT3: 4 | AU3: 6 | AV3: 3 | AW3: 3 | AX3: =+AS3+AT3+AU3+AV3+AW3 -> 20 | AY3: 4 | AZ3: 2 | BA3: 5 | BB3: 1 | BC3: =+AY3+AZ3+BA3+BB3 -> 12 | BD3: 2 | BE3: 5 | BF3: 2 | BG3: 1 | BH3: =+BD3+BE3+BF3+BG3 -> 10 | BI3: 0 | BJ3: 4 | BK3: 2 | BL3: 2 | BM3: =+BI3+BJ3+BK3+BL3 -> 8 | BN3: =+IFERROR(BM4/BM3,0) -> 416.25 | BO3: =+R3+W3+AB3+AH3+AM3+AR3+AX3+BC3+BH3+BM3 -> 126 | BP3: =+BO4/BO3 -> 280.65873 | BR3: 9
E4: kUS$ | F4: =1062+F6 -> 1735 | H4: =453+300 -> 753 | I4: =1600+I6 -> 1999 | J4: =2455+J6 -> 3967 | K4: =2600+K6 -> 3959 | L4: =+SUM(I4:K4) -> 9925 | N4: 200 | O4: 1400 | P4: 470 | Q4: 142 | R4: =+N4+O4+P4+Q4 -> 2212 | S4: 971 | T4: 100 | U4: =950+150 -> 1100 | V4: 400 | W4: =+S4+T4+U4+V4 -> 2571 | X4: 570 | Y4: 200 | Z4: 1500 | AA4: 3860 | AB4: =+X4+Y4+Z4+AA4 -> 6130 | AC4: 0 | AD4: 1288 | AE4: 500 | AF4: 2225 | AG4: =165+200 -> 365 | AH4: =+AC4+AD4+AE4+AF4+AG4 -> 4378 | AI4: 537 | AJ4: =180+190 -> 370 | AK4: =1500+150+21 -> 1671 | AL4: 448 | AM4: =+AI4+AJ4+AK4+AL4 -> 3026 | AN4: 625 | AO4: 6230 | AP4: 440 | AQ4: 770 | AR4: =+AN4+AO4+AP4+AQ4 -> 8065 | AS4: 345 | AT4: 530 | AU4: 800 | AV4: 360 | AW4: 262 | AX4: =+AS4+AT4+AU4+AV4+AW4 -> 2297 | AY4: 638 | AZ4: 124 | BA4: 975 | BB4: 52 | BC4: =+AY4+AZ4+BA4+BB4 -> 1789 | BD4: =380+84 -> 464 | BE4: 637 | BF4: =590-226 -> 364 | BG4: 100 | BH4: =+BD4+BE4+BF4+BG4 -> 1565 | BI4: 0 | BJ4: 665 | BK4: 2365 | BL4: =125+175 -> 300 | BM4: =+BI4+BJ4+BK4+BL4 -> 3330 | BO4: =+R4+W4+AB4+AH4+AM4+AR4+AX4+BC4+BH4+BM4 -> 35363 | BQ4: =+AVERAGE(R4,W4,AB4,AH4,AM4,AR4,AX4,BC4,BH4,BM4) -> 3536.3 | BR4: 1465 | BS4: =+BR4-BH4 -> -100
B5: PA | C5: 2 | D5: Propuestas Adjudicadas | E5: # | F5: 8 | G5: 6 | H5: 3 | I5: 4 | J5: 6 | K5: 8 | L5: =+SUM(I5:K5) -> 18 | M5: =+L6/L5 -> 181.66667 | N5: 4 | O5: 2 | P5: 2 | Q5: 0 | R5: =+N5+O5+P5+Q5 -> 8 | S5: 2 | T5: 3 | V5: 1 | W5: =+S5+T5+U5+V5 -> 6 | X5: 1 | Y5: 1 | Z5: 4 | AA5: 2 | AB5: =+X5+Y5+Z5+AA5 -> 8 | AC5: 0 | AD5: 2 | AE5: 1 | AF5: 1 | AG5: 3 | AH5: =+AC5+AD5+AE5+AF5+AG5 -> 7 | AI5: 1 | AJ5: 1 | AK5: 1 | AL5: 1 | AM5: =+AI5+AJ5+AK5+AL5 -> 4 | AN5: 0 | AO5: 3 | AP5: 1 | AQ5: 4 | AR5: =+AN5+AO5+AP5+AQ5 -> 8 | AS5: 1 | AT5: 1 | AU5: 3 | AV5: 2 | AW5: 2 | AX5: =+AS5+AT5+AU5+AV5+AW5 -> 9 | AY5: 1 | AZ5: 2 | BA5: 3 | BB5: 2 | BC5: =+AY5+AZ5+BA5+BB5 -> 8 | BD5: 0 | BE5: 3 | BF5: 0 | BG5: 1 | BH5: =+BD5+BE5+BF5+BG5 -> 4 | BI5: 0 | BJ5: 1 | BK5: 0 | BL5: 2 | BM5: =+BI5+BJ5+BK5+BL5 -> 3 | BN5: =+IFERROR(BM6/BM5,0) -> 115 | BO5: =+R5+W5+AB5+AH5+AM5+AR5+AX5+BC5+BH5+BM5 -> 65 | BP5: =+BO6/BO5 -> 126.95385 | BR5: 4
E6: kUS$ | F6: 673 | G6: 524 | H6: 300 | I6: 399 | J6: =+Respaldo!I25 -> 1512 | K6: =+Respaldo!I31 -> 1359 | L6: =+SUM(I6:K6) -> 3270 | N6: 690 | O6: 240 | P6: 126 | Q6: 0 | R6: =+N6+O6+P6+Q6 -> 1056 | S6: =1035+120 -> 1155 | T6: 91 | V6: 0 | W6: =+S6+T6+U6+V6 -> 1246 | X6: 20 | Y6: 65 | Z6: 563 | AA6: 88 | AB6: =+X6+Y6+Z6+AA6 -> 736 | AC6: 0 | AD6: 94 | AE6: 60 | AF6: =1114-650-60-94 -> 310 | AG6: =300+200+50 -> 550 | AH6: =+AC6+AD6+AE6+AF6+AG6 -> 1014 | AI6: 490 | AJ6: 262 | AK6: 21 | AL6: 195 | AM6: =+AI6+AJ6+AK6+AL6 -> 968 | AN6: 0 | AO6: 348 | AP6: 25 | AQ6: =286+37 -> 323 | AR6: =+AN6+AO6+AP6+AQ6 -> 696 | AS6: 80 | AT6: 23 | AU6: 119 | AV6: 113 | AW6: 324 | AX6: =+AS6+AT6+AU6+AV6+AW6 -> 659 | AY6: 135 | AZ6: =140+16 -> 156 | BA6: 485 | BB6: 120 | BC6: =+AY6+AZ6+BA6+BB6 -> 896 | BD6: 0 | BE6: 446 | BF6: 0 | BG6: 190 | BH6: =+BD6+BE6+BF6+BG6 -> 636 | BI6: 0 | BJ6: 140 | BK6: 0 | BL6: 205 | BM6: =+BI6+BJ6+BK6+BL6 -> 345 | BO6: =+R6+W6+AB6+AH6+AM6+AR6+AX6+BC6+BH6+BM6 -> 8252 | BQ6: =+AVERAGE(R6,W6,AB6,AH6,AM6,AR6,AX6,BC6,BH6,BM6) -> 825.2 | BR6: 636 | BS6: =+BR6-BH6 -> 0
D7: Plazo Medio Adjudicado | E7: Meses | R7: =+N7 -> 0 | W7: =+S7+T7 -> 0 | AM7: =+AI7+AJ7+AK7+AL7 -> 0 | AR7: =+AN7+AO7 -> 0 | BC7: =+AY7+AZ7+BA7+BB7 -> 0 | BH7: =+BD7+BE7 -> 0 | BM7: =+BI7+BJ7+BK7+BL7 -> 0
D8: Relación Monto/plazo | E8: US$/mes | R8: =+N8 -> 0 | W8: =+S8+T8 -> 0 | AM8: =+AI8+AJ8+AK8+AL8 -> 0 | AR8: =+AN8+AO8 -> 0 | BC8: =+AY8+AZ8+BA8+BB8 -> 0 | BH8: =+BD8+BE8 -> 0 | BM8: =+BI8+BJ8+BK8+BL8 -> 0
D9: Saldo de Contratos (Por Ejecutar) | E9: kUS$ | R9: =+N9 -> 0 | W9: =+S9+T9 -> 0 | AM9: =+AI9+AJ9+AK9+AL9 -> 0 | AR9: =+AN9+AO9 -> 0 | BC9: =+AY9+AZ9+BA9+BB9 -> 0 | BH9: =+BD9+BE9 -> 0 | BM9: =+BI9+BJ9+BK9+BL9 -> 0
B10: EC | D10: Propuestas iniciadas c/ KOM | E10: # | I10: 4 | J10: 6 | K10: 5 | L10: =+SUM(I10:K10) -> 15 | M10: =+L11/L10 -> 193 | N10: 0 | O10: 1 | R10: =+O10+N10+P10+Q10 -> 1 | S10: 0 | T10: 0 | U10: 0 | V10: 5 | W10: =+S10+T10+U10+V10 -> 5 | X10: 1 | Y10: 0 | Z10: =1+1 -> 2 | AA10: 0 | AB10: =+X10+Y10+Z10+AA10 -> 3 | AC10: 0 | AD10: 0 | AE10: 1 | AF10: 1 | AG10: 0 | AH10: =+AC10+AD10+AE10+AF10+AG10 -> 2 | AI10: 1 | AJ10: 0 | AM10: =+AI10+AJ10+AK10+AL10 -> 1 | AR10: =+AN10+AO10 -> 0 | BC10: =+AY10+AZ10+BA10+BB10 -> 0 | BH10: =+BD10+BE10 -> 0 | BM10: =+BI10+BJ10+BK10+BL10 -> 0 | BN10: =+IFERROR(AM11/AM10,0) -> 490 | BO10: =+R10+W10+AB10+AH10+AM10 -> 12 | BP10: =+BO11/BO10 -> 210.58333
E11: kUS$ | I11: 399 | J11: 1012 | K11: 1484 | L11: =+SUM(I11:K11) -> 2895 | N11: 0 | O11: 345 | R11: =+O11+N11+P11+Q11 -> 345 | S11: 0 | T11: 0 | U11: 0 | V11: 960 | W11: =+S11+T11+U11+V11 -> 960 | X11: 132 | Y11: 0 | Z11: =198+141 -> 339 | AA11: 0 | AB11: =+X11+Y11+Z11+AA11 -> 471 | AC11: 0 | AD11: 0 | AE11: 108 | AF11: 153 | AG11: 0 | AH11: =+AC11+AD11+AE11+AF11+AG11 -> 261 | AI11: 490 | AJ11: 0 | AM11: =+AI11+AJ11+AK11+AL11 -> 490 | AR11: =+AN11+AO11 -> 0 | BC11: =+AY11+AZ11+BA11+BB11 -> 0 | BH11: =+BD11+BE11 -> 0 | BM11: =+BI11+BJ11+BK11+BL11 -> 0 | BO11: =+R11+W11+AB11+AH11+AM11 -> 2527
E12: #(KOM interno) | I12: 1 | J12: 3 | K12: 4 | L12: =+SUM(I12:K12) -> 8 | R12: =+N12 -> 0 | W12: =+S12+T12 -> 0 | AM12: =+AI12+AJ12+AK12+AL12 -> 0 | AR12: =+AN12+AO12 -> 0 | BC12: =+AY12+AZ12+BA12+BB12 -> 0 | BH12: =+BD12+BE12 -> 0 | BM12: =+BI12+BJ12+BK12+BL12 -> 0
B13: EC | C13: 3 | D13: POM Mensual | E13: # | I13: 14 | J13: 24 | K13: 23 | L13: =+SUM(I13:K13) -> 61 | M13: =+L14/L13 -> 31.95082 | N13: 22 | O13: 22 | P13: 22 | Q13: 21 | R13: =+Q13 -> 21 | S13: 16 | T13: 5 | U13: 0 | V13: 0 | W13: =+S13+T13+U13+V13 -> 21 | X13: 19 | Y13: 3 | Z13: 0 | AA13: 0 | AB13: =+X13+Y13+Z13+AA13 -> 22 | AC13: 9 | AD13: 4 | AE13: 0 | AF13: 0 | AG13: 0 | AH13: =AC13+AD13+AE13+AF13+AG13 -> 13 | AI13: 14 | AJ13: 3 | AK13: 0 | AL13: 0 | AM13: =+AI13+AJ13+AK13+AL13 -> 17 | AN13: 12 | AO13: 2 | AP13: 0 | AQ13: 0 | AR13: =+AN13+AO13+AP13+AQ13 -> 14 | AS13: 18 | AT13: 0 | AU13: 0 | AV13: 0 | AW13: 0 | AX13: =+AS13+AT13+AU13+AV13+AW13 -> 18 | AY13: 22 | AZ13: 0 | BA13: 0 | BB13: 0 | BC13: =+AY13+AZ13+BA13+BB13 -> 22 | BD13: 25 | BE13: 1 | BF13: 0 | BG13: -2 | BH13: =+BD13+BE13+BF13+BG13 -> 24 | BI13: 23 | BJ13: -4 | BK13: 4 | BL13: -2 | BM13: =+BI13+BJ13+BK13+BL13 -> 21 | BN13: =+IFERROR(BM14/BM13,0) -> 33.571429 | BO13: =+R13+W13+AB13+AH13+AM13+AR13+AX13+BC13+BH13+BM13 -> 193 | BP13: =+BO14/BO13 -> 41.274611 | BR13: 23 | BS13: =+BR13-BM13 -> 2
E14: kUS$ | I14: 516 | J14: 652 | K14: 781 | L14: =+SUM(I14:K14) -> 1949 | N14: 762 | O14: 754 | P14: 718 | Q14: 718 | R14: =+Q14 -> 718 | S14: 563 | T14: 310 | U14: 0 | V14: 0 | W14: =+S14+T14+U14+V14 -> 873 | X14: 678 | Y14: 133 | Z14: 0 | AA14: 0 | AB14: =+X14+Y14+Z14+AA14 -> 811 | AC14: 466 | AD14: 145 | AE14: 0 | AF14: 0 | AG14: 0 | AH14: =AC14+AD14+AE14+AF14+AG14 -> 611 | AI14: 734 | AJ14: 100 | AK14: 0 | AL14: 0 | AM14: =+AI14+AJ14+AK14+AL14 -> 834 | AN14: 780 | AO14: 130 | AP14: 0 | AQ14: 0 | AR14: =+AN14+AO14+AP14+AQ14 -> 910 | AS14: 787 | AT14: 0 | AU14: 0 | AV14: 0 | AW14: 0 | AX14: =+AS14+AT14+AU14+AV14+AW14 -> 787 | AY14: 922 | AZ14: 0 | BA14: 0 | BB14: 0 | BC14: =+AY14+AZ14+BA14+BB14 -> 922 | BD14: 923 | BE14: 52 | BF14: 0 | BG14: -180 | BH14: =+BD14+BE14+BF14+BG14 -> 795 | BI14: 679 | BJ14: -131 | BK14: 219 | BL14: =-50-12 -> -62 | BM14: =+BI14+BJ14+BK14+BL14 -> 705 | BO14: =+R14+W14+AB14+AH14+AM14+AR14+AX14+BC14+BH14+BM14 -> 7966 | BQ14: =+AVERAGE(R14,W14,AB14,AH14,AM14,AR14,AX14,BC14,BH14,BM14) -> 796.6 | BR14: 767 | BS14: =+BR14-BM14 -> 62
B15: EC | C15: 4 | D15: EDP Emitidos (Mes en curso) | E15: # | I15: 16 | J15: 17 | K15: 19 | L15: =+SUM(I15:K15) -> 52 | M15: =+L16/L15 -> 34.384615 | N15: 0 | O15: 2 | P15: 8 | Q15: 9 | R15: =N15+O15+P15+Q15 -> 19 | S15: 0 | T15: 0 | U15: 0 | V15: 20 | W15: =+S15+T15+U15+V15 -> 20 | X15: 0 | Y15: 0 | Z15: 3 | AA15: =8+1+4+1 -> 14 | AB15: =+X15+Y15+Z15+AA15 -> 17 | AC15: 0 | AD15: 1 | AE15: 1 | AF15: 3 | AG15: 10 | AH15: =+AC15+AD15+AE15+AF15+AG15 -> 15 | AI15: 0 | AJ15: 1 | AK15: 1 | AL15: 14 | AM15: =+AI15+AJ15+AK15+AL15 -> 16 | AN15: 0 | AO15: 1 | AP15: 3 | AQ15: =8+3-1 -> 10 | AR15: =+AN15+AO15+AP15+AQ15 -> 14 | AS15: 0 | AT15: 0 | AU15: 6 | AV15: 4 | AW15: =2+1+1+1 -> 5 | AX15: =+AS15+AT15+AU15+AV15+AW15 -> 15 | AY15: 0 | AZ15: 0 | BA15: 9 | BB15: =7+1 -> 8 | BC15: =+AY15+AZ15+BA15+BB15 -> 17 | BD15: 0 | BE15: 5 | BF15: 2 | BG15: =3+6+3 -> 12 | BH15: =+BD15+BE15+BF15+BG15 -> 19 | BI15: 0 | BJ15: 1 | BK15: 8 | BL15: 7 | BM15: =+BI15+BJ15+BK15+BL15 -> 16 | BN15: =+IFERROR(BM16/BM15,0) -> 39.8 | BO15: =+R15+W15+AB15+AH15+AM15+AR15+AX15+BC15+BH15+BM15 -> 168 | BP15: =+BO16/BO15 -> 46.028571 | BR15: 16 | BS15: =+BR15-BM15 -> 0
E16: kUS$ | I16: 527 | J16: 429 | K16: =770+62 -> 832 | L16: =+SUM(I16:K16) -> 1788 | N16: 0 | O16: 86 | P16: 261 | Q16: =354-34+2 -> 322 | R16: =N16+O16+P16+Q16 -> 669 | S16: 0 | T16: 0 | U16: 0 | V16: 892 | W16: =+S16+T16+U16+V16 -> 892 | X16: 0 | Y16: 0 | Z16: 56 | AA16: =424+59+81+74 -> 638 | AB16: =+X16+Y16+Z16+AA16 -> 694 | AC16: 0 | AD16: 65 | AE16: 39 | AF16: 128 | AG16: =548+5-70+7-18 -> 472 | AH16: =+AC16+AD16+AE16+AF16+AG16 -> 704 | AI16: 0 | AJ16: 39 | AK16: 67 | AL16: =511+690-96-39-416-26 -> 624 | AM16: =+AI16+AJ16+AK16+AL16 -> 730 | AN16: 0 | AO16: 81 | AP16: 171 | AQ16: =540+340+73-27 -> 926 | AR16: =+AN16+AO16+AP16+AQ16 -> 1178 | AS16: 0 | AT16: 0 | AU16: 157 | AV16: =165+100+36 -> 301 | AW16: =39+70+126+35+35-20 -> 285 | AX16: =+AS16+AT16+AU16+AV16+AW16 -> 743 | AY16: 0 | AZ16: 0 | BA16: 306 | BB16: =375+150-46 -> 479 | BC16: =+AY16+AZ16+BA16+BB16 -> 785 | BD16: 0 | BE16: 183 | BF16: 50 | BG16: =71+312+85 -> 468 | BH16: =+BD16+BE16+BF16+BG16 -> 701 | BI16: 0 | BJ16: 3.8 | BK16: 257 | BL16: 376 | BM16: =+BI16+BJ16+BK16+BL16 -> 636.8 | BO16: =+R16+W16+AB16+AH16+AM16+AR16+AX16+BC16+BH16+BM16 -> 7732.8 | BQ16: =+AVERAGE(R16,W16,AB16,AH16,AM16,AR16,AX16,BC16,BH16,BM16) -> 773.28 | BR16: 637 | BS16: =+BR16-BM16 -> 0.2 | BV16: 1000
B17: IM | C17: 5 | D17: EDP Facturados (Facturas emitidas) | E17: # | I17: 23 | J17: 17 | K17: 18 | L17: =+SUM(I17:K17) -> 58 | M17: =+L18/L17 -> 32.37931 | N17: 12 | O17: 1 | P17: 1 | Q17: =4+4 -> 8 | R17: 22 | S17: 0 | T17: 0 | U17: 1 | V17: 8 | W17: 9 | X17: 2 | Y17: =1+2+3 -> 6 | Z17: 6 | AA17: =1+1+1 -> 3 | AB17: =+X17+Y17+Z17+AA17 -> 17 | AC17: 4 | AD17: 2 | AE17: 2 | AF17: 5 | AG17: 4 | AH17: 16 | AI17: 8 | AJ17: 3 | AK17: 2 | AL17: 8 | AM17: =+AI17+AJ17+AK17+AL17 -> 21 | AN17: 6 | AO17: 4 | AP17: 1 | AQ17: 6 | AR17: =+AN17+AO17+AP17+AQ17 -> 17 | AS17: 4 | AT17: 5 | AU17: 3 | AV17: 3 | AW17: =2+1 -> 3 | AX17: =+AS17+AT17+AU17+AV17+AW17 -> 18 | AY17: 7 | AZ17: 2 | BA17: 8 | BB17: =3+3 -> 6 | BC17: =+AY17+AZ17+BA17+BB17 -> 23 | BD17: 3 | BE17: 2 | BF17: 2 | BG17: 8 | BH17: =+BD17+BE17+BF17+BG17 -> 15 | BI17: 1 | BJ17: 4 | BK17: 5 | BL17: 5 | BM17: =+BI17+BJ17+BK17+BL17 -> 15 | BN17: =+IFERROR(BM18/BM17,0) -> 50.733333 | BO17: =+R17+W17+AB17+AH17+AM17+AR17+AX17+BC17+BH17+BM17 -> 173 | BP17: =+BO18/BO17 -> 46.404624 | BR17: 15 | BS17: =+BR17-BM17 -> 0 | BV17: 45658 | BW17: 45689 | BX17: 45717 | BY17: 45748 | BZ17: 45778 | CA17: 45809 | CB17: 45839
E18: kUS$ | I18: 864 | J18: 493 | K18: 521 | L18: =+SUM(I18:K18) -> 1878 | N18: 427 | O18: 82 | P18: 35 | Q18: =142+173 -> 315 | R18: 823 | S18: 0 | T18: 0 | U18: 96 | V18: 298 | W18: 313 | X18: =0+0+0+47 -> 47 | Y18: =84.795+106+248 -> 438.795 | Z18: 239.205 | AA18: =25+11 -> 36 | AB18: 798 | AC18: 182 | AD18: 39 | AE18: 38 | AF18: 122 | AG18: 344 | AH18: 702 | AI18: 201 | AJ18: 134 | AK18: 35 | AL18: =563+38 -> 601 | AM18: 916 | AN18: 111 | AO18: 176 | AP18: 15 | AQ18: =470+47-16-21 -> 480 | AR18: =+AN18+AO18+AP18+AQ18 -> 782 | AS18: 144 | AT18: 345 | AU18: 70 | AV18: 201 | AW18: =35+99 -> 134 | AX18: =+AS18+AT18+AU18+AV18+AW18 -> 894 | AY18: 752 | AZ18: 145 | BA18: 217 | BB18: =155+65 -> 220 | BC18: =+AY18+AZ18+BA18+BB18 -> 1334 | BD18: 55 | BE18: 171 | BF18: 102 | BG18: 377 | BH18: =+BD18+BE18+BF18+BG18 -> 705 | BI18: 34 | BJ18: 116 | BK18: 251 | BL18: 360 | BM18: =+BI18+BJ18+BK18+BL18 -> 761 | BO18: =+R18+W18+AB18+AH18+AM18+AR18+AX18+BC18+BH18+BM18 -> 8028 | BQ18: =+AVERAGE(R18,W18,AB18,AH18,AM18,AR18,AX18,BC18,BH18,BM18) -> 802.8 | BR18: 761 | BS18: =+BR18-BM18 -> 0 | BU18: EDP | BV18: 669.095 | BW18: 891.9687 | BX18: 693.81329 | BY18: 722.43473 | BZ18: 755.657 | CA18: 1204.9966 | CB18: 762.70685 | CC18: 5700.6722
B19: EC | C19: 6 | E19: #
E20: kUS$
B21: EC | C21: 6.1 | D21: Pendientes (En proceso de aprobación) | E21: # | M21: 0 | N21: 4 | O21: 2 | P21: 2 | Q21: 0 | R21: =+Q21 -> 0 | S21: 10 | T21: 7 | U21: 7 | V21: 17 | W21: =+V21 -> 17 | X21: 14 | Y21: 12 | Z21: 6 | AA21: 6 | AB21: =+AA21 -> 6 | AC21: 11 | AD21: 8 | AE21: 9 | AF21: 5 | AG21: 2 | AH21: =+AG21 -> 2 | AI21: 6 | AJ21: 5 | AK21: 5 | AL21: 4 | AM21: =+AL21 -> 4 | AN21: 10 | AO21: 8 | AP21: 6 | AQ21: 3 | AR21: =+AQ21 -> 3 | AS21: 10 | AT21: 6 | AU21: 4 | AV21: 2 | AW21: 2 | AX21: =+AW21 -> 2 | AY21: 5 | AZ21: 3 | BA21: 3 | BB21: 2 | BC21: =+BB21 -> 2 | BD21: 7 | BE21: 7 | BF21: 5 | BG21: 3 | BH21: =+BG21 -> 3 | BI21: 7 | BJ21: 10 | BK21: 8 | BL21: 6 | BM21: =+BL21 -> 6 | BN21: =+IFERROR(BM22/BM21,0) -> 21.333333 | BO21: =+BM21 -> 6 | BP21: =+BO22/BO21 -> 21.333333
E22: kUS$ | N22: 192 | O22: 43 | P22: 43 | Q22: 0 | R22: =+Q22 -> 0 | S22: 175 | T22: 158 | U22: 158 | V22: 831 | W22: =+V22 -> 831 | X22: 653 | Y22: 568 | Z22: 250 | AA22: 250 | AB22: =+AA22 -> 250 | AC22: 478 | AD22: 430 | AE22: 440 | AF22: 285 | AG22: 73 | AH22: =+AG22 -> 73 | AI22: 330 | AJ22: 259 | AK22: 259 | AL22: 183 | AM22: =+AL22 -> 183 | AN22: 1037 | AO22: 953 | AP22: 834 | AQ22: 681 | AR22: =+AQ22 -> 681 | AS22: 801 | AT22: 692 | AU22: 633 | AV22: 568 | AW22: 568 | AX22: =+AW22 -> 568 | AY22: 254 | AZ22: 84 | BA22: 84 | BB22: 50 | BC22: =+BB22 -> 50 | BD22: 351 | BE22: 478 | BF22: 258 | BG22: 53 | BH22: =+BG22 -> 53 | BI22: 334 | BJ22: 419 | BK22: 360 | BL22: 128 | BM22: =+BL22 -> 128 | BO22: =+BM22 -> 128 | BU22: Factura | BV22: 822.535 | BW22: 313.029 | BX22: 798.15916 | BY22: 702.12786 | BZ22: 916.262 | CA22: 802.653 | CB22: 795.33726 | CC22: 751.57259
B23: EC | C23: 6.2 | D23: Rezagados | E23: # | J23: 1 | K23: 3 | L23: =+SUM(I23:K23) -> 4 | M23: =+L24/L23 -> 23.5 | N23: 2 | O23: 2 | P23: 1 | Q23: 1 | R23: =+Q23 -> 1 | S23: 1 | T23: 2 | U23: 1 | V23: =1+6 -> 7 | W23: =+V23 -> 7 | X23: =1+5 -> 6 | Y23: 5 | Z23: 5 | AA23: 5 | AB23: =+AA23 -> 5 | AC23: 10 | AD23: 9 | AE23: 5 | AF23: 5 | AG23: 4 | AH23: =+AG23 -> 4 | AI23: 3 | AJ23: 2 | AK23: 2 | AL23: 2 | AM23: =+AL23 -> 2 | AN23: 6 | AO23: 4 | AP23: 4 | AQ23: 4 | AR23: =+AQ23 -> 4 | AS23: 5 | AT23: 4 | AU23: 4 | AV23: 3 | AW23: 3 | AX23: =+AW23 -> 3 | AY23: 4 | AZ23: 1 | BA23: 1 | BB23: 1 | BC23: =+BB23 -> 1 | BD23: 3 | BE23: 3 | BF23: 3 | BG23: 3 | BH23: =+BG23 -> 3 | BI23: 6 | BJ23: 4 | BK23: 4 | BL23: 4 | BM23: =+BL23 -> 4 | BN23: =+IFERROR(BM24/BM23,0) -> 15.5 | BO23: =+BM23 -> 4 | BP23: =+BO24/BO23 -> 15.5
E24: kUS$ | J24: 35 | K24: 59 | L24: =+SUM(I24:K24) -> 94 | N24: 70 | O24: 70 | P24: 35 | Q24: 35 | R24: =+Q24 -> 35 | S24: 35 | T24: =35+71 -> 106 | U24: 35 | V24: =35+124 -> 159 | W24: =+V24 -> 159 | X24: =35+100 -> 135 | Y24: 101 | Z24: 101 | AA24: 101 | AB24: =+AA24 -> 101 | AC24: 326 | AD24: 276 | AE24: 201 | AF24: 201 | AG24: 88 | AH24: =+AG24 -> 88 | AI24: 67 | AJ24: =29+15 -> 44 | AK24: 44 | AL24: 44 | AM24: =+AL24 -> 44 | AN24: 227 | AO24: =29+113 -> 142 | AP24: 142 | AQ24: =113+29 -> 142 | AR24: =+AQ24 -> 142 | AS24: 548 | AT24: 493 | AU24: 493 | AV24: 76.3 | AW24: 76 | AX24: =+AW24 -> 76 | AY24: 190 | AZ24: 29 | BA24: 29 | BB24: 29 | BC24: =+BB24 -> 29 | BD24: 79 | BE24: 79 | BF24: 79 | BG24: 79 | BH24: =+BG24 -> 79 | BI24: 132 | BJ24: 62 | BK24: 62 | BL24: 62 | BM24: =+BL24 -> 62 | BO24: =+BM24 -> 62 | BU24: Ingreso | BV24: 724.71915 | BW24: 932.41047 | BX24: 785.48233 | BY24: 611.32257 | BZ24: 666.9483 | CA24: 796.9543 | CB24: 894.28984
B25: IM | C25: 7 | D25: Gasto Operacional | E25: kUS$ | R25: 522 | W25: 534 | AB25: 618 | AH25: 555 | AM25: 566 | AR25: 640 | AX25: 630 | BC25: 665 | BD25: 0 | BE25: 0 | BF25: 0 | BG25: 0 | BH25: 648 | BM25: 581 | BN25: =+BM25 -> 581 | BO25: =+R25+W25+AB25+AH25+AM25+AR25+AX25+BC25+BH25+BM25 -> 5959 | BP25: =+BO25/10 -> 595.9 | BQ25: =+AVERAGE(R25,W25,AB25,AH25,AM25,AR25,AX25,BC25,BH25,BM25) -> 595.9
B26: IM | C26: 8 | D26: Facturas Pagadas (Ingreso Operacional) | E26: # | I26: 25 | J26: 15 | K26: 15 | L26: =+SUM(I26:K26) -> 55 | M26: =+L27/L26 -> 38.109091 | N26: 4 | O26: 4 | P26: 8 | Q26: 4 | R26: 22 | S26: 2 | T26: 6 | U26: =5+2 -> 7 | V26: =3+3+1 -> 7 | W26: 20 | X26: 3 | Y26: 5 | Z26: 4 | AA26: =3+2+1 -> 6 | AB26: 16 | AC26: 2 | AD26: =5-1 -> 4 | AE26: 1 | AF26: 4 | AG26: 1 | AH26: =+AC26+AD26+AE26+AF26+AG26 -> 12 | AI26: 2 | AJ26: 3 | AK26: 7 | AL26: 8 | AM26: =+AI26+AJ26+AK26+AL26 -> 20 | AN26: 4 | AO26: 4 | AP26: 5 | AQ26: 5 | AR26: =+AN26+AO26+AP26+AQ26 -> 18 | AS26: 5 | AT26: 5 | AU26: 3 | AV26: 2 | AW26: =2+1 -> 3 | AX26: =+AS26+AT26+AU26+AV26+AW26 -> 18 | AY26: 5 | AZ26: 2 | BA26: 4 | BB26: 7 | BC26: =+AY26+AZ26+BA26+BB26 -> 18 | BD26: 1 | BE26: 3 | BF26: 5 | BG26: =6 -> 6 | BH26: =+BD26+BE26+BF26+BG26 -> 15 | BI26: 0 | BJ26: 0 | BK26: 7 | BL26: 9 | BM26: =+BI26+BJ26+BK26+BL26 -> 16 | BN26: =+IFERROR(BM27/BM26,0) -> 45.5625 | BO26: =+R26+W26+AB26+AH26+AM26+AR26+AX26+BC26+BH26+BM26 -> 175 | BP26: =+BO27/BO26 -> 43.32 | BR26: 16 | BS26: =+BR26-BM26 -> 0
E27: kUS$ | I27: 1004 | J27: 616 | K27: 476 | L27: =+SUM(I27:K27) -> 2096 | N27: 197 | O27: 83 | P27: 269 | Q27: 157 | R27: 724 | S27: 46 | T27: 261 | U27: =181+160 -> 341 | V27: =152+87+22 -> 261 | W27: 932 | X27: =96270/1000 -> 96.27 | Y27: 132 | Z27: 253.73 | AA27: =197+51+29 -> 277 | AB27: =785-5 -> 780 | AC27: 35 | AD27: 346 | AE27: 42 | AF27: 105 | AG27: 83 | AH27: =+AC27+AD27+AE27+AF27+AG27-10 -> 601 | AI27: 123 | AJ27: 121 | AK27: 171 | AL27: 233 | AM27: =667-39 -> 628 | AN27: 345 | AO27: 121 | AP27: 195 | AQ27: 125 | AR27: 797 | AS27: 219 | AT27: 123 | AU27: 241 | AV27: 47 | AW27: =127+137 -> 264 | AX27: =+AS27+AT27+AU27+AV27+AW27-67 -> 827 | AY27: 163 | AZ27: 59 | BA27: 550 | BB27: 213 | BC27: =+AY27+AZ27+BA27+BB27-36 -> 949 | BD27: 112 | BE27: 103 | BF27: 308 | BG27: =33+61-3 -> 91 | BH27: =+BD27+BE27+BF27+BG27 -> 614 | BI27: 0 | BJ27: 0 | BK27: 307 | BL27: 422 | BM27: =+BI27+BJ27+BK27+BL27 -> 729 | BO27: =+R27+W27+AB27+AH27+AM27+AR27+AX27+BC27+BH27+BM27 -> 7581 | BQ27: =+AVERAGE(R27,W27,AB27,AH27,AM27,AR27,AX27,BC27,BH27,BM27) -> 758.1 | BR27: 729 | BS27: =+BR27-BM27 -> 0
B28: IM | C28: 9 | D28: Facturas Vencidas | E28: # | K28: 8 | L28: =+SUM(I28:K28) -> 8 | M28: =+L29/L28 -> 35.75 | N28: 5 | O28: 3 | P28: 2 | Q28: 5 | R28: =+Q28 -> 5 | S28: 5 | T28: 6 | U28: 3 | V28: 3 | W28: =+V28 -> 3 | X28: 3 | Y28: 1 | Z28: 2 | AA28: 2 | AB28: =+AA28 -> 2 | AC28: 2 | AD28: 2 | AE28: 2 | AF28: 2 | AG28: 2 | AH28: =+AG28 -> 2 | AI28: 2 | AJ28: 6 | AK28: 4 | AL28: 3 | AM28: =+AL28 -> 3 | AN28: 3 | AO28: 6 | AP28: 5 | AQ28: 3 | AR28: =+AQ28 -> 3 | AS28: 2 | AT28: 1 | AU28: 1 | AV28: 1 | AW28: 4 | AX28: =+AW28 -> 4 | AY28: 2 | AZ28: 5 | BA28: 4 | BB28: 4 | BC28: =+BB28 -> 4 | BD28: 4 | BE28: 6 | BF28: 6 | BG28: 5 | BH28: =+BG28 -> 5 | BI28: 5 | BJ28: 5 | BK28: 6 | BL28: 5 | BM28: =+BL28 -> 5 | BN28: =+IFERROR(BM29/BM28,0) -> 65.4 | BO28: =+BM28 -> 5 | BP28: =+IFERROR(BO29/BO28,0) -> 65.4
E29: KUS$ | K29: 286 | L29: =+SUM(I29:K29) -> 286 | N29: 110 | O29: 60 | P29: 26.8 | Q29: =227+27 -> 254 | R29: =+Q29 -> 254 | S29: 254 | T29: 213 | U29: 109 | V29: 109 | W29: =+V29 -> 109 | X29: 109 | Y29: 5.2 | Z29: 29 | AA29: 29 | AB29: =+AA29 -> 29 | AC29: 29 | AD29: 29 | AE29: 29 | AF29: 29 | AG29: 29 | AH29: =+AG29 -> 29 | AI29: 29 | AJ29: 198 | AK29: 162 | AL29: 61 | AM29: =+AL29 -> 61 | AN29: 61 | AO29: 225 | AP29: 99 | AQ29: 83 | AR29: =+AQ29 -> 83 | AS29: 10 | AT29: 5 | AU29: 5 | AV29: 5 | AW29: 78 | AX29: =+AW29 -> 78 | AY29: 15 | AZ29: 261 | BA29: 239 | BB29: 239 | BC29: =+BB29 -> 239 | BD29: 218 | BE29: 406 | BF29: 406 | BG29: 367 | BH29: =+BG29 -> 367 | BI29: 367 | BJ29: 367 | BK29: 387 | BL29: 327 | BM29: =+BL29 -> 327 | BO29: =+BM29 -> 327
B30: EC | C30: 10 | D30: Cumplimiento POM vs EDP | E30: % | I30: =+IFERROR(I16/I14,0) -> 1.0213178 | J30: =+IFERROR(J16/J14,0) -> 0.65797546 | K30: =+IFERROR(K16/K14,0) -> 1.0653009 | L30: =+AVERAGE(I30:K30) -> 0.91486473 | M30: =+L30 -> 0.91486473 | N30: - | O30: =+IFERROR(O16/O14,0) -> 0.11405836 | P30: =+IFERROR(P16/P14,0) -> 0.36350975 | Q30: =+IFERROR(Q16/Q14,0) -> 0.44846797 | R30: =+IFERROR(R16/R14,0) -> 0.93175487 | S30: 0 | T30: 0 | U30: 0 | V30: 0 | W30: =+IFERROR(W16/W14,0) -> 1.021764 | X30: 0 | Y30: 0 | Z30: 0 | AA30: 0 | AB30: =+IFERROR(AB16/AB14,0) -> 0.85573366 | AC30: 0 | AD30: 0 | AE30: 0 | AF30: 0 | AG30: 0 | AH30: =+IFERROR(AH16/AH14,0) -> 1.1522095 | AI30: 0 | AJ30: 0 | AK30: 0 | AL30: 0 | AM30: =+IFERROR(AM16/AM14,0) -> 0.87529976 | AN30: 0 | AO30: 0 | AP30: 0 | AQ30: 0 | AR30: =+IFERROR(AR16/AR14,0) -> 1.2945055 | AS30: 0 | AT30: 0 | AU30: 0 | AV30: 0 | AW30: 0 | AX30: =+IFERROR(AX16/AX14,0) -> 0.94409149 | AY30: 0 | AZ30: 0 | BA30: 0 | BB30: 0 | BC30: =+IFERROR(BC16/BC14,0) -> 0.85140998 | BD30: 0 | BE30: 0 | BF30: 0 | BG30: 0 | BH30: =+IFERROR(BH16/BH14,0) -> 0.88176101 | BI30: 0 | BJ30: 0 | BK30: 0 | BL30: 0 | BM30: =+IFERROR(BM16/BM14,0) -> 0.90326241 | BN30: =+BM30 -> 0.90326241 | BO30: =+AVERAGE(R30,W30,AB30,AH30,AM30,AR30,AX30,BC30,BH30,BM30) -> 0.97117922 | BP30: =+BO30 -> 0.97117922
B31: EC | C31: 11 | D31: Adherencia POM vs EDP | E31: % | I31: 0.73 | J31: 0.67 | K31: 0.76 | L31: =+AVERAGE(I31:K31) -> 0.72 | M31: =+L31 -> 0.72 | N31: - | O31: - | P31: - | Q31: - | R31: 0.81 | S31: 0 | T31: 0 | U31: 0 | V31: 0 | W31: 0.83 | X31: 0 | Y31: 0 | Z31: 0 | AA31: 0 | AB31: 0.7 | AC31: 0 | AD31: 0 | AE31: 0 | AF31: 0 | AG31: 0 | AH31: 0.69 | AI31: 0 | AJ31: 0 | AK31: 0 | AL31: 0 | AM31: 0.77 | AN31: 0 | AO31: 0 | AP31: 0 | AQ31: 0 | AR31: 0.92 | AS31: 0 | AT31: 0 | AU31: 0 | AV31: 0 | AW31: 0 | AX31: 0.65 | AY31: 0 | AZ31: 0 | BA31: 0 | BB31: 0 | BC31: 0.54 | BD31: 0 | BE31: 0 | BF31: 0 | BG31: 0 | BH31: 0.59 | BI31: 0 | BJ31: 0 | BK31: 0 | BL31: 0 | BM31: 0.68 | BN31: =+BM31 -> 0.68 | BO31: =+AVERAGE(R31,W31,AB31,AH31,AM31,AR31,AX31,BC31,BH31,BM31) -> 0.718 | BP31: =+BO31 -> 0.718
AC33: 2 | AD33: 6 | AE33: 1 | AF33: 4
AC34: 98 | AD34: 346 | AE34: 42 | AF34: 65 | BO34: =+BO27-BO25 -> 1622
BO35: =+BO34/BO27 -> 0.21395594
AO38: =6677-6537 -> 140

Sheet Modulo 2025
B1: 45566 | C1: 45597 | D1: 45627 | E1: 45658 | F1: 45689 | G1: 45717
A2: Emitido | B2: 527 | C2: 429 | D2: 832 | E2: 667 | F2: 928 | G2: 718 | H2: =+AVERAGE(B2:F2) -> 676.6 | J2: =+H2*12 -> 8119.2
A3: Facturado | B3: 864 | C3: 493 | D3: 521 | E3: 859 | F3: 394 | G3: 788 | H3: =+AVERAGE(B3:F3) -> 626.2 | J3: =+H3*12 -> 7514.4
A4: Ingresado | B4: 1004 | C4: 616 | D4: 476 | E4: 706 | F4: 887 | G4: 403 | H4: =+AVERAGE(B4:F4) -> 737.8 | J4: =+H4*12 -> 8853.6
A6: Remanente | D6: 2900 | E6: 2300 | F6: 3541 | G6: =+F6-G2 -> 2823
B28: Item | C28: Módulo | D28: Liquido USD | E28: Bruto USD | F28: Módulo USD | G28: % | I28: Dotación | J28: Meses
B29: Director | C29: 0.3 | D29: 6500 | E29: =+D29*1.3 -> 8450 | F29: =+C29*E29 -> 2535 | I29: =+ROUNDUP(C29*$F$47,0) -> 8 | J29: 12 | L29: 7.5
B30: Ing Ppal | C30: 0.5 | D30: 4500 | E30: =+D30*1.3 -> 5850 | F30: =+C30*E30 -> 2925 | I30: =+ROUNDUP(C30*$F$47,0) -> 13 | L30: 12.5
B31: Ing Proy | C31: 1.76 | D31: 2500 | E31: =+D31*1.3 -> 3250 | F31: =+C31*E31 -> 5720 | I31: =+ROUNDUP(C31*$F$47,0) -> 44 | L31: 44
B32: Ing Senior | C32: 0.3 | D32: 4000 | E32: =+D32*1.3 -> 5200 | F32: =+C32*E32 -> 1560 | I32: =+ROUNDUP(C32*$F$47,0) -> 8 | L32: 7.5
B33: Gerente | C33: 0.1 | D33: 7500 | E33: =+D33*1.3 -> 9750 | F33: =+C33*E33 -> 975 | I33: =+ROUNDUP(C33*$F$47,0) -> 3 | L33: 2.5
B34: Total | F34: =SUM(F29:F33) -> 13715 | I34: =SUM(I29:I33) -> 76
N35: Sueldos | O35: 380000 | P35: 1
E36: COSTO TOTAL MÓDULO
E37: Item | F37: USD | G37: % | N37: Overhead | O37: 70000 | P37: =+O37/O35 -> 0.18421053 | Q37: =+Q39*P37/P39 -> 3096.9355
E38: Directo | F38: =SUM(F34) -> 13715 | G38: 0.82 | I38: =+F38*$F$47 -> 342875
E39: Overhead | F39: =+F38*P37/P39 -> 3096.9355 | G39: 0.18 | I39: =+F39*$F$47 -> 77423.387 | N39: Ingeniería | O39: =+O35-O37 -> 310000 | P39: =1-P37 -> 0.81578947 | Q39: =+F38 -> 13715
E40: MO | F40: =SUM(F38:F39) -> 16811.935 | G40: 0.7 | I40: =+F40*$F$47 -> 420298.39
E41: Tercero | F41: =+F40*G41/G40 -> 2401.7051 | G41: 0.1 | I41: =+F41*$F$47 -> 60042.627
E42: Operación | F42: =+F40*G42/G40 -> 3122.2166 | G42: 0.13 | I42: =+F42*$F$47 -> 78055.415
E43: Admin | F43: =+F40*G43/G40 -> 1200.8525 | G43: 0.05 | I43: =+F43*$F$47 -> 30021.313
E44: Otros | F44: =+F40*G44/G40 -> 480.34101 | G44: 0.02 | I44: =+F44*$F$47 -> 12008.525
E45: TOTAL | F45: =SUM(F40:F44) -> 24017.051 | G45: =SUM(G40:G44) -> 1
E47: Modulos | F47: 25
E49: Gasto | F49: =+F45*F47 -> 600426.27 | G49: =+F49*J29 -> 7205115.2 | I49: =+SUM(F41:F44)*F47 -> 180127.88 | L49: =+G40*$G$49 -> 5043580.6
L50: =+G41*$G$49 -> 720511.52
E51: Ingreso | F51: =+I51*F47 -> 800000 | G51: =+F51*J29 -> 9600000 | I51: =9600000/(J29*F47) -> 32000 | L51: =+G42*$G$49 -> 936664.98
L52: =+G43*$G$49 -> 360255.76
E53: EBITDA | F53: =+F51-F49 -> 199573.73 | G53: =+F53/F51 -> 0.24946717 | L53: =+G44*$G$49 -> 144102.3

Sheet Compromisos
A1: # | B1: Acción | C1: Responsable | D1: Fecha | E1: Estatus
A2: 1 | B2: Replantear el enfoque de reunión comercial con Country Managers | C2: A.Fraser | D2: 46020 | E2: En proceso
A3: =1+A2 -> 2 | B3: Definir estrategia para abordar Paloma Sulfato (internamente) | C3: A.Fraser | D3: 46021 | E3: Pendiente
A4: =1+A3 -> 3 | B4: Enviar términos y condiciones de propuestas comerciales | C4: A.Fraser | D4: 46013 | E4: Realizado
A5: =1+A4 -> 4 | B5: Actualizar información comercial (adjudicado y cierre contractual) | C5: P.Aguiluz | D5: 46020 | E5: Realizado
A6: =1+A5 -> 5 | B6: Aplicar cuociente monto/meses a propuestas comerciales en seguimiento | C6: P.Aguiluz | D6: 46020 | E6: En proceso
A7: =1+A6 -> 6 | B7: Asignar prioridades a propuestas comerciales enviadas para definir foco | C7: P.Aguiluz | D7: 46020 | E7: Realizado

Sheet KPI´s de negocio 2025
B2: Resp. | C2: # | D2: Ítem | E2: Unidad | F2: 45474 | G2: 45505 | H2: 45536 | I2: 45566 | J2: 45597 | K2: 45627 | L2: Q4-24 | M2: Media Q4 2024 | N2: S1 | O2: S2 | P2: S3 | Q2: S4 | R2: 45658 | S2: S1 feb-25 | T2: S2 feb-25 | U2: S3 feb-25 | V2: S4 feb-25 | W2: 45689 | X2: S1 mar-25 | Y2: S2 mar-25 | Z2: S3 mar-25 | AA2: S4 mar-25 | AB2: 45717 | AC2: S1 abr-25 | AD2: S2 abr-25 | AE2: S3 abr-25 | AF2: S4 abr-25 | AG2: S5 abril-25 | AH2: 45748 | AI2: S1 may-25 | AJ2: S2 may-25 | AK2: S3 may-25 | AL2: S4 may-25 | AM2: 45778 | AN2: S1 Jun-25 | AO2: S2 Jun-25 | AP2: S3 Jun-25 | AQ2: S4 Jun-25 | AR2: 45809 | AS2: S1 Jul-25 | AT2: S2 Jul-25 | AU2: S3 Jul-25 | AV2: S4 Jul-25 | AW2: S5 Jul-25 | AX2: 45839 | AY2: S1 ago-25 | AZ2: S2 ago-25 | BA2: S3 ago-25 | BB2: S4 ago-25 | BC2: 45870 | BD2: S1 sep-25 | BE2: S2 sep-25 | BF2: S3 sep-25 | BG2: S4 sep-25 | BH2: 45901 | BI2: S1 oct-25 | BJ2: S2 oct-25 | BK2: S3 oct-25 | BL2: S4 oct-25 | BM2: S5 oct-25 | BN2: 45931 | BO2: S1 | BP2: S2 | BQ2: S3 | BR2: S4 | BS2: 45962 | BT2: S1 | BU2: S2 | BV2: S3 | BW2: S4 | BX2: S5 | BY2: 45992 | BZ2: Media dic | CA2: Acum. 2025 | CB2: Media Acum. | CC2: =+CA4/CA3 -> 266.19512 | CG2: Item | CH2: kUS$ | CI2: Rezagado
B3: PA | C3: 1 | D3: Propuestas Emitidas | E3: # | F3: =8+8 -> 16 | H3: 6 | I3: =8+I5 -> 12 | J3: =9+J5 -> 15 | K3: =7+K5 -> 15 | L3: =+SUM(I3:K3) -> 42 | M3: =+L4/L3 -> 236.30952 | N3: 1 | O3: 3 | P3: 3 | Q3: 1 | R3: =+N3+O3+P3+Q3 -> 8 | S3: 3 | T3: 2 | U3: 2 | V3: 3 | W3: =+S3+T3+U3+V3 -> 10 | X3: 5 | Y3: 2 | Z3: 3 | AA3: 1 | AB3: =+X3+Y3+Z3+AA3 -> 11 | AC3: 0 | AD3: 9 | AE3: 2 | AF3: 5 | AG3: 2 | AH3: =+AC3+AD3+AE3+AF3+AG3 -> 18 | AI3: 2 | AJ3: 2 | AK3: 3 | AL3: 1 | AM3: =+AI3+AJ3+AK3+AL3 -> 8 | AN3: 3 | AO3: 9 | AP3: 3 | AQ3: 6 | AR3: =+AN3+AO3+AP3+AQ3 -> 21 | AS3: 4 | AT3: 4 | AU3: 6 | AV3: 3 | AW3: 3 | AX3: =+AS3+AT3+AU3+AV3+AW3 -> 20 | AY3: 4 | AZ3: 2 | BA3: 5 | BB3: 1 | BC3: =+AY3+AZ3+BA3+BB3 -> 12 | BD3: 2 | BE3: 5 | BF3: 2 | BG3: 1 | BH3: =+BD3+BE3+BF3+BG3 -> 10 | BI3: 0 | BJ3: 4 | BK3: 2 | BL3: 2 | BM3: 1 | BN3: =+BI3+BJ3+BK3+BL3+BM3 -> 9 | BO3: 3 | BP3: 2 | BQ3: 6 | BR3: 8 | BS3: =+BO3+BP3+BQ3+BR3 -> 19 | BT3: 6 | BU3: 6 | BV3: 5 | BW3: 0 | BX3: 1 | BY3: =+BT3+BU3+BV3+BW3+BX3 -> 18 | BZ3: =+IFERROR(BY4/BY3,0) -> 203.5 | CA3: =+R3+W3+AB3+AH3+AM3+AR3+AX3+BC3+BH3+BN3+BS3+BY3 -> 164 | CB3: =+CA4/CA3 -> 266.19512 | CD3: 9 | CG3: Ingreso Operacional | CH3: =+CA14 -> 9025
E4: kUS$ | F4: =1062+F6 -> 1735 | H4: =453+300 -> 753 | I4: =1600+I6 -> 1999 | J4: =2455+J6 -> 3967 | K4: =2600+K6 -> 3959 | L4: =+SUM(I4:K4) -> 9925 | N4: 200 | O4: 1400 | P4: 470 | Q4: 142 | R4: =+N4+O4+P4+Q4 -> 2212 | S4: 971 | T4: 100 | U4: =950+150 -> 1100 | V4: 400 | W4: =+S4+T4+U4+V4 -> 2571 | X4: 570 | Y4: 200 | Z4: 1500 | AA4: 3860 | AB4: =+X4+Y4+Z4+AA4 -> 6130 | AC4: 0 | AD4: 1288 | AE4: 500 | AF4: 2225 | AG4: =165+200 -> 365 | AH4: =+AC4+AD4+AE4+AF4+AG4 -> 4378 | AI4: 537 | AJ4: =180+190 -> 370 | AK4: =1500+150+21 -> 1671 | AL4: 448 | AM4: =+AI4+AJ4+AK4+AL4 -> 3026 | AN4: 625 | AO4: 6230 | AP4: 440 | AQ4: 770 | AR4: =+AN4+AO4+AP4+AQ4 -> 8065 | AS4: 345 | AT4: 530 | AU4: 800 | AV4: 360 | AW4: 262 | AX4: =+AS4+AT4+AU4+AV4+AW4 -> 2297 | AY4: 638 | AZ4: 124 | BA4: 975 | BB4: 52 | BC4: =+AY4+AZ4+BA4+BB4 -> 1789 | BD4: =380+84 -> 464 | BE4: 637 | BF4: =590-226 -> 364 | BG4: 100 | BH4: =+BD4+BE4+BF4+BG4 -> 1565 | BI4: 0 | BJ4: 665 | BK4: 2365 | BL4: =125+175 -> 300 | BM4: 185 | BN4: =+BI4+BJ4+BK4+BL4+BM4 -> 3515 | BO4: 1295 | BP4: =180+48 -> 228 | BQ4: 1077 | BR4: 1845 | BS4: =+BO4+BP4+BQ4+BR4 -> 4445 | BT4: 1410 | BU4: 1065 | BV4: 688 | BW4: 0 | BX4: 500 | BY4: =+BT4+BU4+BV4+BW4+BX4 -> 3663 | CA4: =+R4+W4+AB4+AH4+AM4+AR4+AX4+BC4+BH4+BN4+BS4+BY4 -> 43656 | CC4: =+AVERAGE(R4,W4,AB4,AH4,AM4,AR4,AX4,BC4,BH4,BN4,BS4) -> 3635.7273 | CD4: 1465 | CE4: =+CD4-BH4 -> -100 | CG4: Facturas por cobrar | CH4: =+CA25 -> 1462 | CI4: =+BY27 -> 822
B5: PA | C5: 2 | D5: Propuestas Adjudicadas | E5: # | F5: 8 | G5: 6 | H5: 3 | I5: 4 | J5: 6 | K5: 8 | L5: =+SUM(I5:K5) -> 18 | M5: =+L6/L5 -> 181.66667 | N5: 4 | O5: 2 | P5: 2 | Q5: 0 | R5: =+N5+O5+P5+Q5 -> 8 | S5: 2 | T5: 3 | V5: 1 | W5: =+S5+T5+U5+V5 -> 6 | X5: 1 | Y5: 1 | Z5: 4 | AA5: 2 | AB5: =+X5+Y5+Z5+AA5 -> 8 | AC5: 0 | AD5: 2 | AE5: 1 | AF5: 1 | AG5: 3 | AH5: =+AC5+AD5+AE5+AF5+AG5 -> 7 | AI5: 1 | AJ5: 1 | AK5: 1 | AL5: 1 | AM5: =+AI5+AJ5+AK5+AL5 -> 4 | AN5: 0 | AO5: 3 | AP5: 1 | AQ5: 4 | AR5: =+AN5+AO5+AP5+AQ5 -> 8 | AS5: 1 | AT5: 1 | AU5: 3 | AV5: 2 | AW5: 2 | AX5: =+AS5+AT5+AU5+AV5+AW5 -> 9 | AY5: 1 | AZ5: 2 | BA5: 3 | BB5: 2 | BC5: =+AY5+AZ5+BA5+BB5 -> 8 | BD5: 0 | BE5: 3 | BF5: 0 | BG5: 1 | BH5: =+BD5+BE5+BF5+BG5 -> 4 | BI5: 0 | BJ5: 1 | BK5: 0 | BL5: 2 | BM5: 3 | BN5: =+BI5+BJ5+BK5+BL5+BM5 -> 6 | BO5: 0 | BP5: 0 | BQ5: 2 | BR5: 1 | BS5: =+BO5+BP5+BQ5+BR5 -> 3 | BT5: 1 | BU5: 2 | BV5: 2 | BW5: 1 | BX5: 1 | BY5: =+BT5+BU5+BV5+BW5+BX5 -> 7 | BZ5: =+IFERROR(BY6/BY5,0) -> 186.57143 | CA5: =+R5+W5+AB5+AH5+AM5+AR5+AX5+BC5+BH5+BN5+BS5+BY5 -> 78 | CB5: =+CA6/CA5 -> 131.74359 | CD5: 4 | CG5: EDP por facturar | CH5: =+CA19 -> 245 | CI5: =+BY23 -> 159
E6: kUS$ | F6: 673 | G6: 524 | H6: 300 | I6: 399 | J6: =+Respaldo!I25 -> 1512 | K6: =+Respaldo!I31 -> 1359 | L6: =+SUM(I6:K6) -> 3270 | N6: 690 | O6: 240 | P6: 126 | Q6: 0 | R6: =+N6+O6+P6+Q6 -> 1056 | S6: =1035+120 -> 1155 | T6: 91 | V6: 0 | W6: =+S6+T6+U6+V6 -> 1246 | X6: 20 | Y6: 65 | Z6: 563 | AA6: 88 | AB6: =+X6+Y6+Z6+AA6 -> 736 | AC6: 0 | AD6: 94 | AE6: 60 | AF6: =1114-650-60-94 -> 310 | AG6: =300+200+50 -> 550 | AH6: =+AC6+AD6+AE6+AF6+AG6 -> 1014 | AI6: 490 | AJ6: 262 | AK6: 21 | AL6: 195 | AM6: =+AI6+AJ6+AK6+AL6 -> 968 | AN6: 0 | AO6: 348 | AP6: 25 | AQ6: =286+37 -> 323 | AR6: =+AN6+AO6+AP6+AQ6 -> 696 | AS6: 80 | AT6: 23 | AU6: 119 | AV6: 113 | AW6: 324 | AX6: =+AS6+AT6+AU6+AV6+AW6 -> 659 | AY6: 135 | AZ6: =140+16 -> 156 | BA6: 485 | BB6: 120 | BC6: =+AY6+AZ6+BA6+BB6 -> 896 | BD6: 0 | BE6: 446 | BF6: 0 | BG6: 190 | BH6: =+BD6+BE6+BF6+BG6 -> 636 | BI6: 0 | BJ6: 140 | BK6: 0 | BL6: 205 | BM6: 118 | BN6: =+BI6+BJ6+BK6+BL6+BM6 -> 463 | BO6: 0 | BP6: 0 | BQ6: 249 | BR6: 351 | BS6: =+BO6+BP6+BQ6+BR6 -> 600 | BT6: 445 | BU6: 251 | BV6: 295 | BW6: 285 | BX6: 30 | BY6: =+BT6+BU6+BV6+BW6+BX6 -> 1306 | CA6: =+R6+W6+AB6+AH6+AM6+AR6+AX6+BC6+BH6+BN6+BS6+BY6 -> 10276 | CC6: =+AVERAGE(R6,W6,AB6,AH6,AM6,AR6,AX6,BC6,BH6,BN6,BS6) -> 815.45455 | CD6: 991 | CE6: =+CD6-BY6 -> -315 | CG6: Total | CH6: =SUM(CH3:CH5) -> 10732 | CI6: =SUM(CI3:CI5) -> 981
B7: EC | C7: 3 | D7: POM | E7: # | I7: 14 | J7: 24 | K7: 23 | L7: =+SUM(I7:K7) -> 61 | M7: =+L8/L7 -> 31.95082 | N7: 22 | O7: 22 | P7: 22 | Q7: 21 | R7: =+Q7 -> 21 | S7: 16 | T7: 5 | U7: 0 | V7: 0 | W7: =+S7+T7+U7+V7 -> 21 | X7: 19 | Y7: 3 | Z7: 0 | AA7: 0 | AB7: =+X7+Y7+Z7+AA7 -> 22 | AC7: 9 | AD7: 4 | AE7: 0 | AF7: 0 | AG7: 0 | AH7: =AC7+AD7+AE7+AF7+AG7 -> 13 | AI7: 14 | AJ7: 3 | AK7: 0 | AL7: 0 | AM7: =+AI7+AJ7+AK7+AL7 -> 17 | AN7: 12 | AO7: 2 | AP7: 0 | AQ7: 0 | AR7: =+AN7+AO7+AP7+AQ7 -> 14 | AS7: 18 | AT7: 0 | AU7: 0 | AV7: 0 | AW7: 0 | AX7: =+AS7+AT7+AU7+AV7+AW7 -> 18 | AY7: 22 | AZ7: 0 | BA7: 0 | BB7: 0 | BC7: =+AY7+AZ7+BA7+BB7 -> 22 | BD7: 25 | BE7: 1 | BF7: 0 | BG7: -2 | BH7: =+BD7+BE7+BF7+BG7 -> 24 | BI7: 23 | BJ7: -4 | BK7: 4 | BL7: -2 | BM7: 0 | BN7: =+BI7+BJ7+BK7+BL7+BM7 -> 21 | BO7: 18 | BP7: 0 | BQ7: 0 | BR7: 0 | BS7: =+BO7+BP7+BQ7+BR7 -> 18 | BT7: 13 | BU7: 0 | BV7: -2 | BW7: 0 | BX7: 0 | BY7: =+BT7+BU7+BV7+BW7+BX7 -> 11 | BZ7: =+IFERROR(BY8/BY7,0) -> 38.454545 | CA7: =+R7+W7+AB7+AH7+AM7+AR7+AX7+BC7+BH7+BN7+BS7+BY7 -> 222 | CB7: =+CA8/CA7 -> 40.707207 | CD7: 11 | CE7: =+CD7-BY7 -> 0
E8: kUS$ | I8: 516 | J8: 652 | K8: 781 | L8: =+SUM(I8:K8) -> 1949 | N8: 762 | O8: 754 | P8: 718 | Q8: 718 | R8: =+Q8 -> 718 | S8: 563 | T8: 310 | U8: 0 | V8: 0 | W8: =+S8+T8+U8+V8 -> 873 | X8: 678 | Y8: 133 | Z8: 0 | AA8: 0 | AB8: =+X8+Y8+Z8+AA8 -> 811 | AC8: 466 | AD8: 145 | AE8: 0 | AF8: 0 | AG8: 0 | AH8: =AC8+AD8+AE8+AF8+AG8 -> 611 | AI8: 734 | AJ8: 100 | AK8: 0 | AL8: 0 | AM8: =+AI8+AJ8+AK8+AL8 -> 834 | AN8: 780 | AO8: 130 | AP8: 0 | AQ8: 0 | AR8: =+AN8+AO8+AP8+AQ8 -> 910 | AS8: 787 | AT8: 0 | AU8: 0 | AV8: 0 | AW8: 0 | AX8: =+AS8+AT8+AU8+AV8+AW8 -> 787 | AY8: 922 | AZ8: 0 | BA8: 0 | BB8: 0 | BC8: =+AY8+AZ8+BA8+BB8 -> 922 | BD8: 923 | BE8: 52 | BF8: 0 | BG8: -180 | BH8: =+BD8+BE8+BF8+BG8 -> 795 | BI8: 679 | BJ8: -131 | BK8: 219 | BL8: =-50-12 -> -62 | BM8: 0 | BN8: =+BI8+BJ8+BK8+BL8+BM8 -> 705 | BO8: 648 | BP8: 0 | BQ8: 0 | BR8: 0 | BS8: =+BO8+BP8+BQ8+BR8 -> 648 | BT8: 480 | BU8: 0 | BV8: -57 | BW8: 0 | BX8: 0 | BY8: =+BT8+BU8+BV8+BW8+BX8 -> 423 | CA8: =+R8+W8+AB8+AH8+AM8+AR8+AX8+BC8+BH8+BN8+BS8+BY8 -> 9037 | CC8: =+AVERAGE(R8,W8,AB8,AH8,AM8,AR8,AX8,BC8,BH8,BN8,BS8) -> 783.09091 | CD8: 423 | CE8: =+CD8-BY8 -> 0
B9: EC | C9: 4 | D9: EDP Emitidos (Estados de pago) | E9: # | I9: 16 | J9: 17 | K9: 19 | L9: =+SUM(I9:K9) -> 52 | M9: =+L10/L9 -> 34.384615 | N9: 0 | O9: 2 | P9: 8 | Q9: 9 | R9: =N9+O9+P9+Q9 -> 19 | S9: 0 | T9: 0 | U9: 0 | V9: 20 | W9: =+S9+T9+U9+V9 -> 20 | X9: 0 | Y9: 0 | Z9: 3 | AA9: =8+1+4+1 -> 14 | AB9: =+X9+Y9+Z9+AA9 -> 17 | AC9: 0 | AD9: 1 | AE9: 1 | AF9: 3 | AG9: 10 | AH9: =+AC9+AD9+AE9+AF9+AG9 -> 15 | AI9: 0 | AJ9: 1 | AK9: 1 | AL9: 14 | AM9: =+AI9+AJ9+AK9+AL9 -> 16 | AN9: 0 | AO9: 1 | AP9: 3 | AQ9: =8+3-1 -> 10 | AR9: =+AN9+AO9+AP9+AQ9 -> 14 | AS9: 0 | AT9: 0 | AU9: 6 | AV9: 4 | AW9: =2+1+1+1 -> 5 | AX9: =+AS9+AT9+AU9+AV9+AW9 -> 15 | AY9: 0 | AZ9: 0 | BA9: 9 | BB9: =7+1 -> 8 | BC9: =+AY9+AZ9+BA9+BB9 -> 17 | BD9: 0 | BE9: 5 | BF9: 2 | BG9: =3+6+3-1 -> 11 | BH9: =+BD9+BE9+BF9+BG9 -> 18 | BI9: 0 | BJ9: 1 | BK9: 8 | BL9: 7 | BM9: =4+1 -> 5 | BN9: =+BI9+BJ9+BK9+BL9+BM9 -> 21 | BO9: 0 | BP9: 5 | BQ9: 3 | BR9: 11 | BS9: =+BO9+BP9+BQ9+BR9 -> 19 | BT9: 0 | BU9: 0 | BV9: 5 | BW9: 4 | BX9: 4 | BY9: =+BT9+BU9+BV9+BW9+BX9 -> 13 | BZ9: =+IFERROR(BY10/BY9,0) -> 47 | CA9: =+R9+W9+AB9+AH9+AM9+AR9+AX9+BC9+BH9+BN9+BS9+BY9 -> 204 | CB9: =+CA10/CA9 -> 45.849956 | CD9: 13 | CE9: =+CD9-BY9 -> 0
E10: kUS$ | I10: 527 | J10: 429 | K10: =770+62 -> 832 | L10: =+SUM(I10:K10) -> 1788 | N10: 0 | O10: 86 | P10: 261 | Q10: =354-34+2 -> 322 | R10: =N10+O10+P10+Q10 -> 669 | S10: 0 | T10: 0 | U10: 0 | V10: 892 | W10: =+S10+T10+U10+V10 -> 892 | X10: 0 | Y10: 0 | Z10: 56 | AA10: =424+59+81+74 -> 638 | AB10: =+X10+Y10+Z10+AA10 -> 694 | AC10: 0 | AD10: 65 | AE10: 39 | AF10: 128 | AG10: =548+5-70+7-18 -> 472 | AH10: =+AC10+AD10+AE10+AF10+AG10 -> 704 | AI10: 0 | AJ10: 39 | AK10: 67 | AL10: =511+690-96-39-416-26 -> 624 | AM10: =+AI10+AJ10+AK10+AL10 -> 730 | AN10: 0 | AO10: 81 | AP10: 171 | AQ10: =540+340+73-27 -> 926 | AR10: =+AN10+AO10+AP10+AQ10 -> 1178 | AS10: 0 | AT10: 0 | AU10: 157 | AV10: =165+100+36 -> 301 | AW10: =39+70+126+35+35-20 -> 285 | AX10: =+AS10+AT10+AU10+AV10+AW10 -> 743 | AY10: 0 | AZ10: 0 | BA10: 306 | BB10: =375+150-46 -> 479 | BC10: =+AY10+AZ10+BA10+BB10 -> 785 | BD10: 0 | BE10: 183 | BF10: 50 | BG10: =71+312+85-22.409 -> 445.591 | BH10: =+BD10+BE10+BF10+BG10 -> 678.591 | BI10: 0 | BJ10: 3.8 | BK10: 257 | BL10: 376 | BM10: =185+41 -> 226 | BN10: =+BI10+BJ10+BK10+BL10+BM10 -> 862.8 | BO10: 0 | BP10: 319 | BQ10: 102 | BR10: 385 | BS10: =+BO10+BP10+BQ10+BR10 -> 806 | BT10: 0 | BU10: 0 | BV10: 291 | BW10: 257 | BX10: 63 | BY10: =+BT10+BU10+BV10+BW10+BX10 -> 611 | CA10: =+R10+W10+AB10+AH10+AM10+AR10+AX10+BC10+BH10+BN10+BS10+BY10 -> 9353.391 | CC10: =+AVERAGE(R10,W10,AB10,AH10,AM10,AR10,AX10,BC10,BH10,BN10,BS10,BY10) -> 779.44925 | CD10: 611 | CE10: =+CD10-BY10 -> 0
B11: IM | C11: 5 | D11: EDP Facturados (Facturación) | E11: # | I11: 23 | J11: 17 | K11: 18 | L11: =+SUM(I11:K11) -> 58 | M11: =+L12/L11 -> 32.37931 | N11: 12 | O11: 1 | P11: 1 | Q11: =4+4 -> 8 | R11: 22 | S11: 0 | T11: 0 | U11: 1 | V11: 8 | W11: 9 | X11: 2 | Y11: =1+2+3 -> 6 | Z11: 6 | AA11: =1+1+1 -> 3 | AB11: =+X11+Y11+Z11+AA11 -> 17 | AC11: 4 | AD11: 2 | AE11: 2 | AF11: 5 | AG11: 4 | AH11: 16 | AI11: 8 | AJ11: 3 | AK11: 2 | AL11: 8 | AM11: =+AI11+AJ11+AK11+AL11 -> 21 | AN11: 6 | AO11: 4 | AP11: 1 | AQ11: 6 | AR11: =+AN11+AO11+AP11+AQ11 -> 17 | AS11: 4 | AT11: 5 | AU11: 3 | AV11: 3 | AW11: =2+1 -> 3 | AX11: =+AS11+AT11+AU11+AV11+AW11 -> 18 | AY11: 7 | AZ11: 2 | BA11: 8 | BB11: =3+3 -> 6 | BC11: =+AY11+AZ11+BA11+BB11 -> 23 | BD11: 3 | BE11: 2 | BF11: 2 | BG11: =8+1 -> 9 | BH11: =+BD11+BE11+BF11+BG11 -> 16 | BI11: 1 | BJ11: 4 | BK11: 5 | BL11: 5 | BM11: 8 | BN11: =+BI11+BJ11+BK11+BL11+BM11 -> 23 | BO11: 2 | BP11: 4 | BQ11: 6 | BR11: 4 | BS11: =+BO11+BP11+BQ11+BR11 -> 16 | BT11: 2 | BU11: 3 | BV11: 8 | BW11: 5 | BX11: 3 | BY11: =+BT11+BU11+BV11+BW11+BX11 -> 21 | BZ11: =+IFERROR(BY12/BY11,0) -> 42.190476 | CA11: =+R11+W11+AB11+AH11+AM11+AR11+AX11+BC11+BH11+BN11+BS11+BY11 -> 219 | CB11: =+CA12/CA11 -> 44.726027 | CD11: 21 | CE11: =+CD11-BY11 -> 0
E12: kUS$ | I12: 864 | J12: 493 | K12: 521 | L12: =+SUM(I12:K12) -> 1878 | N12: 427 | O12: 82 | P12: 35 | Q12: =142+173 -> 315 | R12: 823 | S12: 0 | T12: 0 | U12: 96 | V12: 298 | W12: 313 | X12: =0+0+0+47 -> 47 | Y12: =84.795+106+248 -> 438.795 | Z12: 239.205 | AA12: =25+11 -> 36 | AB12: 798 | AC12: 182 | AD12: 39 | AE12: 38 | AF12: 122 | AG12: 344 | AH12: 702 | AI12: 201 | AJ12: 134 | AK12: 35 | AL12: =563+38 -> 601 | AM12: 916 | AN12: 111 | AO12: 176 | AP12: 15 | AQ12: =470+47-16-21 -> 480 | AR12: =+AN12+AO12+AP12+AQ12 -> 782 | AS12: 144 | AT12: 345 | AU12: 70 | AV12: 201 | AW12: =35+99 -> 134 | AX12: =+AS12+AT12+AU12+AV12+AW12 -> 894 | AY12: 752 | AZ12: 145 | BA12: 217 | BB12: =155+65 -> 220 | BC12: =+AY12+AZ12+BA12+BB12 -> 1334 | BD12: 55 | BE12: 171 | BF12: 102 | BG12: =377+22 -> 399 | BH12: =+BD12+BE12+BF12+BG12 -> 727 | BI12: 34 | BJ12: 116 | BK12: 251 | BL12: 360 | BM12: 194 | BN12: 884 | BO12: 62 | BP12: 271 | BQ12: 138 | BR12: 317 | BS12: 736 | BT12: 16 | BU12: 169 | BV12: 427 | BW12: 191 | BX12: 83 | BY12: =+BT12+BU12+BV12+BW12+BX12 -> 886 | CA12: =+R12+W12+AB12+AH12+AM12+AR12+AX12+BC12+BH12+BN12+BS12+BY12 -> 9795 | CC12: =+AVERAGE(R12,W12,AB12,AH12,AM12,AR12,AX12,BC12,BH12,BN12,BS12) -> 809.90909 | CD12: 886 | CE12: =+CD12-BY12 -> 0
B13: IM | C13: 6 | D13: EDP Pagados (Ingreso Operacional) | E13: # | I13: 25 | J13: 15 | K13: 15 | L13: =+SUM(I13:K13) -> 55 | M13: =+L14/L13 -> 38.109091 | N13: 4 | O13: 4 | P13: 8 | Q13: 4 | R13: 22 | S13: 2 | T13: 6 | U13: =5+2 -> 7 | V13: =3+3+1 -> 7 | W13: 20 | X13: 3 | Y13: 5 | Z13: 4 | AA13: =3+2+1 -> 6 | AB13: 16 | AC13: 2 | AD13: =5-1 -> 4 | AE13: 1 | AF13: 4 | AG13: 1 | AH13: =+AC13+AD13+AE13+AF13+AG13 -> 12 | AI13: 2 | AJ13: 3 | AK13: 7 | AL13: 8 | AM13: =+AI13+AJ13+AK13+AL13 -> 20 | AN13: 4 | AO13: 4 | AP13: 5 | AQ13: 5 | AR13: =+AN13+AO13+AP13+AQ13 -> 18 | AS13: 5 | AT13: 5 | AU13: 3 | AV13: 2 | AW13: =2+1 -> 3 | AX13: =+AS13+AT13+AU13+AV13+AW13 -> 18 | AY13: 5 | AZ13: 2 | BA13: 4 | BB13: 7 | BC13: =+AY13+AZ13+BA13+BB13 -> 18 | BD13: 1 | BE13: 3 | BF13: 5 | BG13: =6 -> 6 | BH13: =+BD13+BE13+BF13+BG13 -> 15 | BI13: 0 | BJ13: 0 | BK13: 7 | BL13: 9 | BM13: =1+2 -> 3 | BN13: =+BI13+BJ13+BK13+BL13+BM13 -> 19 | BO13: 3 | BP13: 4 | BQ13: 12 | BR13: 2 | BS13: =+BO13+BP13+BQ13+BR13 -> 21 | BT13: 4 | BU13: 3 | BV13: 6 | BW13: 2 | BX13: 2 | BY13: =+BT13+BU13+BV13+BW13+BX13 -> 17 | BZ13: =+IFERROR(BY14/BY13,0) -> 47.882353 | CA13: =+R13+W13+AB13+AH13+AM13+AR13+AX13+BC13+BH13+BN13+BS13+BY13 -> 216 | CB13: =+CA14/CA13 -> 41.782407 | CD13: 17 | CE13: =+CD13-BY13 -> 0
E14: kUS$ | I14: 1004 | J14: 616 | K14: 476 | L14: =+SUM(I14:K14) -> 2096 | N14: 197 | O14: 83 | P14: 269 | Q14: 157 | R14: 724 | S14: 46 | T14: 261 | U14: =181+160 -> 341 | V14: =152+87+22 -> 261 | W14: 932 | X14: =96270/1000 -> 96.27 | Y14: 132 | Z14: 253.73 | AA14: =197+51+29 -> 277 | AB14: =785-5 -> 780 | AC14: 35 | AD14: 346 | AE14: 42 | AF14: 105 | AG14: 83 | AH14: =+AC14+AD14+AE14+AF14+AG14-10 -> 601 | AI14: 123 | AJ14: 121 | AK14: 171 | AL14: 233 | AM14: =667-39 -> 628 | AN14: 345 | AO14: 121 | AP14: 195 | AQ14: 125 | AR14: 797 | AS14: 219 | AT14: 123 | AU14: 241 | AV14: 47 | AW14: =127+137 -> 264 | AX14: =+AS14+AT14+AU14+AV14+AW14-67 -> 827 | AY14: 163 | AZ14: 59 | BA14: 550 | BB14: 213 | BC14: =+AY14+AZ14+BA14+BB14-36 -> 949 | BD14: 112 | BE14: 103 | BF14: 308 | BG14: =33+61-3 -> 91 | BH14: =+BD14+BE14+BF14+BG14 -> 614 | BI14: 0 | BJ14: 0 | BK14: 307 | BL14: 422 | BM14: =5+52 -> 57 | BN14: =+BI14+BJ14+BK14+BL14+BM14 -> 786 | BO14: 53 | BP14: 117 | BQ14: 354 | BR14: 49 | BS14: =+BO14+BP14+BQ14+BR14 -> 573 | BT14: 63 | BU14: 271 | BV14: 224 | BW14: 178 | BX14: 78 | BY14: =+BT14+BU14+BV14+BW14+BX14 -> 814 | CA14: =+R14+W14+AB14+AH14+AM14+AR14+AX14+BC14+BH14+BN14+BS14+BY14 -> 9025 | CC14: =+AVERAGE(R14,W14,AB14,AH14,AM14,AR14,AX14,BC14,BH14,BN14,BS14) -> 746.45455 | CD14: 814 | CE14: =+CD14-BY14 -> 0
B15: IM | C15: 7 | D15: Gasto Operacional | E15: kUS$ | R15: 477 | W15: 500 | AB15: 536 | AH15: 518 | AM15: 534 | AR15: 614 | AX15: 526 | BC15: 585 | BD15: 0 | BE15: 0 | BF15: 0 | BG15: 0 | BH15: 605 | BN15: 621 | BS15: 623 | BY15: 651 | BZ15: =+BY15 -> 651 | CA15: =+R15+W15+AB15+AH15+AM15+AR15+AX15+BC15+BH15+BN15+BS15+BY15 -> 6790 | CB15: =+CA15/12 -> 565.83333 | CC15: =+AVERAGE(R15,W15,AB15,AH15,AM15,AR15,AX15,BC15,BH15,BN15,BS15) -> 558.09091
B16: EC | C16: 8 | D16: Cumplimiento POM vs EDP | E16: % | I16: =+IFERROR(I10/I8,0) -> 1.0213178 | J16: =+IFERROR(J10/J8,0) -> 0.65797546 | K16: =+IFERROR(K10/K8,0) -> 1.0653009 | L16: =+AVERAGE(I16:K16) -> 0.91486473 | M16: =+L16 -> 0.91486473 | N16: - | O16: =+IFERROR(O10/O8,0) -> 0.11405836 | P16: =+IFERROR(P10/P8,0) -> 0.36350975 | Q16: =+IFERROR(Q10/Q8,0) -> 0.44846797 | R16: =+IFERROR(R10/R8,0) -> 0.93175487 | S16: 0 | T16: 0 | U16: 0 | V16: 0 | W16: =+IFERROR(W10/W8,0) -> 1.021764 | X16: 0 | Y16: 0 | Z16: 0 | AA16: 0 | AB16: =+IFERROR(AB10/AB8,0) -> 0.85573366 | AC16: 0 | AD16: 0 | AE16: 0 | AF16: 0 | AG16: 0 | AH16: =+IFERROR(AH10/AH8,0) -> 1.1522095 | AI16: 0 | AJ16: 0 | AK16: 0 | AL16: 0 | AM16: =+IFERROR(AM10/AM8,0) -> 0.87529976 | AN16: 0 | AO16: 0 | AP16: 0 | AQ16: 0 | AR16: =+IFERROR(AR10/AR8,0) -> 1.2945055 | AS16: 0 | AT16: 0 | AU16: 0 | AV16: 0 | AW16: 0 | AX16: =+IFERROR(AX10/AX8,0) -> 0.94409149 | AY16: 0 | AZ16: 0 | BA16: 0 | BB16: 0 | BC16: =+IFERROR(BC10/BC8,0) -> 0.85140998 | BD16: 0 | BE16: 0 | BF16: 0 | BG16: 0 | BH16: =+IFERROR(BH10/BH8,0) -> 0.85357358 | BI16: 0 | BJ16: 0 | BK16: 0 | BL16: 0 | BM16: 0 | BN16: =+IFERROR(BN10/BN8,0) -> 1.2238298 | BO16: 0 | BP16: 0 | BQ16: 0 | BR16: 0 | BS16: =+IFERROR(BS10/BS8,0) -> 1.2438272 | BT16: =+IFERROR(BT10/BT8,0) -> 0 | BU16: 0 | BV16: 0 | BW16: 0 | BX16: 0 | BY16: =+IFERROR(BY10/BY8,0) -> 1.4444444 | BZ16: =+BY16 -> 1.4444444 | CA16: =+AVERAGE(R16,W16,AB16,AH16,AM16,AR16,AX16,BC16,BH16,BN16,BS16,BY16) -> 1.0577036 | CB16: =+CA16 -> 1.0577036
B17: EC | C17: 9 | D17: Adherencia POM vs EDP | E17: % | I17: 0.73 | J17: 0.67 | K17: 0.76 | L17: =+AVERAGE(I17:K17) -> 0.72 | M17: =+L17 -> 0.72 | N17: - | O17: - | P17: - | Q17: - | R17: 0.81 | S17: 0 | T17: 0 | U17: 0 | V17: 0 | W17: 0.83 | X17: 0 | Y17: 0 | Z17: 0 | AA17: 0 | AB17: 0.7 | AC17: 0 | AD17: 0 | AE17: 0 | AF17: 0 | AG17: 0 | AH17: 0.69 | AI17: 0 | AJ17: 0 | AK17: 0 | AL17: 0 | AM17: 0.77 | AN17: 0 | AO17: 0 | AP17: 0 | AQ17: 0 | AR17: 0.92 | AS17: 0 | AT17: 0 | AU17: 0 | AV17: 0 | AW17: 0 | AX17: 0.65 | AY17: 0 | AZ17: 0 | BA17: 0 | BB17: 0 | BC17: 0.54 | BD17: 0 | BE17: 0 | BF17: 0 | BG17: 0 | BH17: 0.62 | BI17: 0 | BJ17: 0 | BK17: 0 | BL17: 0 | BM17: 0 | BN17: 0.87 | BO17: 0 | BP17: 0 | BQ17: 0 | BR17: 0 | BS17: 0.81 | BT17: 0 | BU17: 0 | BV17: 0 | BW17: 0 | BX17: 0 | BY17: 0.79 | BZ17: =+BY17 -> 0.79 | CA17: =+AVERAGE(R17,W17,AB17,AH17,AM17,AR17,AX17,BC17,BH17,BN17,BS17,BY17) -> 0.75 | CB17: =+CA17 -> 0.75
B18: EC | C18: 10 | D18: Backlog EDP (por facturar) | E18: # | R18: =+R20+R22 -> 1 | W18: =+W20+W22 -> 24 | AB18: =+AB20+AB22 -> 11 | AH18: =+AH20+AH22 -> 6 | AM18: =+AM20+AM22 -> 6 | AR18: =+AR20+AR22 -> 7 | AX18: =+AX20+AX22 -> 5 | BC18: =+BC20+BC22 -> 3 | BH18: =+BH20+BH22 -> 6 | BN18: =+BN20+BN22 -> 16 | BO18: =+BO20+BO22 -> 15 | BP18: =+BP20+BP22 -> 13 | BQ18: =+BQ20+BQ22 -> 9 | BR18: =+BR20+BR22 -> 7 | BS18: =+BS20+BS22 -> 7 | BT18: =+BT20+BT22 -> 18 | BU18: =+BU20+BU22 -> 15 | ... BY18: =+BY20+BY22 -> 9 | BZ18: =+IFERROR(BY19/BY18,0) -> 27.222222 | CA18: =+BY18 -> 9 | CB18: =+IFERROR(CA19/CA18,0) -> 27.222222
E19: kUS$ | R19: =+R21+R23 -> 35 | W19: =+W21+W23 -> 990 | AB19: =+AB21+AB23 -> 351 | AH19: =+AH21+AH23 -> 161 | AM19: =+AM21+AM23 -> 227 | AR19: =+AR21+AR23 -> 823 | AX19: =+AX21+AX23 -> 644 | BC19: =+BC21+BC23 -> 79 | BH19: =+BH21+BH23 -> 132 | BN19: =+BN21+BN23 -> 591 | BO19: =+BO21+BO23 -> 570 | BP19: =+BP21+BP23 -> 327 | BQ19: =+BQ21+BQ23 -> 262 | BR19: =+BR21+BR23 -> 179 | BS19: =+BS21+BS23 -> 179 | BT19: =+BT21+BT23 -> 640 | BU19: =+BU21+BU23 -> 594 | ... BY19: =+BY21+BY23 -> 245 | CA19: =+BY19 -> 245
B20: EC | C20: 10.1 | D20: Pendientes | E20: # | M20: 0 | N20: 4 | O20: 2 | P20: 2 | Q20: 0 | R20: =+Q20 -> 0 | S20: 10 | T20: 7 | U20: 7 | V20: 17 | W20: =+V20 -> 17 | X20: 14 | Y20: 12 | Z20: 6 | AA20: 6 | AB20: =+AA20 -> 6 | AC20: 11 | AD20: 8 | AE20: 9 | AF20: 5 | AG20: 2 | AH20: =+AG20 -> 2 | AI20: 6 | AJ20: 5 | AK20: 5 | AL20: 4 | AM20: =+AL20 -> 4 | AN20: 10 | AO20: 8 | AP20: 6 | AQ20: 3 | AR20: =+AQ20 -> 3 | AS20: 10 | AT20: 6 | AU20: 4 | AV20: 2 | AW20: 2 | AX20: =+AW20 -> 2 | AY20: 5 | AZ20: 3 | BA20: 3 | BB20: 2 | BC20: =+BB20 -> 2 | BD20: 7 | BE20: 7 | BF20: 5 | BG20: 3 | BH20: =+BG20 -> 3 | BI20: 7 | BJ20: 10 | BK20: 8 | BL20: 6 | BM20: 10 | BN20: =+BM20 -> 10 | BO20: 9 | BP20: 7 | BQ20: 6 | BR20: 3 | BS20: =+BR20 -> 3 | BT20: 11 | BU20: 8 | BV20: 5 | BW20: 5 | BX20: 3 | BY20: =+BX20 -> 3 | BZ20: =+IFERROR(BY21/BY20,0) -> 28.666667 | CA20: =+BY20 -> 3 | CB20: =+CA21/CA20 -> 28.666667
E21: kUS$ | N21: 192 | O21: 43 | P21: 43 | Q21: 0 | R21: =+Q21 -> 0 | S21: 175 | T21: 158 | U21: 158 | V21: 831 | W21: =+V21 -> 831 | X21: 653 | Y21: 568 | Z21: 250 | AA21: 250 | AB21: =+AA21 -> 250 | AC21: 478 | AD21: 430 | AE21: 440 | AF21: 285 | AG21: 73 | AH21: =+AG21 -> 73 | AI21: 330 | AJ21: 259 | AK21: 259 | AL21: 183 | AM21: =+AL21 -> 183 | AN21: 1037 | AO21: 953 | AP21: 834 | AQ21: 681 | AR21: =+AQ21 -> 681 | AS21: 801 | AT21: 692 | AU21: 633 | AV21: 568 | AW21: 568 | AX21: =+AW21 -> 568 | AY21: 254 | AZ21: 84 | BA21: 84 | BB21: 50 | BC21: =+BB21 -> 50 | BD21: 351 | BE21: 478 | BF21: 258 | BG21: 53 | BH21: =+BG21 -> 53 | BI21: 334 | BJ21: 419 | BK21: 360 | BL21: 128 | BM21: 486 | BN21: =+BM21 -> 486 | BO21: 465 | BP21: 222 | BQ21: 201 | BR21: 61 | BS21: =+BR21 -> 61 | BT21: 460 | BU21: 414 | BV21: 148 | BW21: 148 | BX21: 86 | BY21: =+BX21 -> 86 | CA21: =+BY21 -> 86
B22: EC | C22: 10.2 | D22: Rezagados | E22: # | J22: 1 | K22: 3 | L22: =+SUM(I22:K22) -> 4 | M22: =+L23/L22 -> 23.5 | N22: 2 | O22: 2 | P22: 1 | Q22: 1 | R22: =+Q22 -> 1 | S22: 1 | T22: 2 | U22: 1 | V22: =1+6 -> 7 | W22: =+V22 -> 7 | X22: =1+5 -> 6 | Y22: 5 | Z22: 5 | AA22: 5 | AB22: =+AA22 -> 5 | AC22: 10 | AD22: 9 | AE22: 5 | AF22: 5 | AG22: 4 | AH22: =+AG22 -> 4 | AI22: 3 | AJ22: 2 | AK22: 2 | AL22: 2 | AM22: =+AL22 -> 2 | AN22: 6 | AO22: 4 | AP22: 4 | AQ22: 4 | AR22: =+AQ22 -> 4 | AS22: 5 | AT22: 4 | AU22: 4 | AV22: 3 | AW22: 3 | AX22: =+AW22 -> 3 | AY22: 4 | AZ22: 1 | BA22: 1 | BB22: 1 | BC22: =+BB22 -> 1 | BD22: 3 | BE22: 3 | BF22: 3 | BG22: 3 | BH22: =+BG22 -> 3 | BI22: 6 | BJ22: 4 | BK22: 4 | BL22: 4 | BM22: 6 | BN22: =+BM22 -> 6 | BO22: 6 | BP22: 6 | BQ22: 3 | BR22: 4 | BS22: =+BR22 -> 4 | BT22: 7 | BU22: 7 | BV22: 7 | BW22: 7 | BX22: 6 | BY22: =+BX22 -> 6 | BZ22: =+IFERROR(BY23/BY22,0) -> 26.5 | CA22: =+BY22 -> 6 | CB22: =+CA23/CA22 -> 26.5
E23: kUS$ | J23: 35 | K23: 59 | L23: =+SUM(I23:K23) -> 94 | N23: 70 | O23: 70 | P23: 35 | Q23: 35 | R23: =+Q23 -> 35 | S23: 35 | T23: =35+71 -> 106 | U23: 35 | V23: =35+124 -> 159 | W23: =+V23 -> 159 | X23: =35+100 -> 135 | Y23: 101 | Z23: 101 | AA23: 101 | AB23: =+AA23 -> 101 | AC23: 326 | AD23: 276 | AE23: 201 | AF23: 201 | AG23: 88 | AH23: =+AG23 -> 88 | AI23: 67 | AJ23: =29+15 -> 44 | AK23: 44 | AL23: 44 | AM23: =+AL23 -> 44 | AN23: 227 | AO23: =29+113 -> 142 | AP23: 142 | AQ23: =113+29 -> 142 | AR23: =+AQ23 -> 142 | AS23: 548 | AT23: 493 | AU23: 493 | AV23: 76.3 | AW23: 76 | AX23: =+AW23 -> 76 | AY23: 190 | AZ23: 29 | BA23: 29 | BB23: 29 | BC23: =+BB23 -> 29 | BD23: 79 | BE23: 79 | BF23: 79 | BG23: 79 | BH23: =+BG23 -> 79 | BI23: 132 | BJ23: 62 | BK23: 62 | BL23: 62 | BM23: 105 | BN23: =+BM23 -> 105 | BO23: 105 | BP23: 105 | BQ23: 61 | BR23: 118 | BS23: =+BR23 -> 118 | BT23: 180 | BU23: 180 | BV23: 180 | BW23: 180 | BX23: 159 | BY23: =+BX23 -> 159 | CA23: =+BY23 -> 159
B24: EC | C24: 11 | D24: Backlog Facturas (Por cobrar) | E24: # | BL24: 27 | BM24: 32 | BN24: =+BM24 -> 32 | BO24: 31 | BP24: 31 | BQ24: 26 | BR24: 28 | BS24: =+BR24 -> 28 | BT24: 26 | BU24: 25 | BV24: 24 | BW24: 27 | BX24: 26 | BY24: =+BX24 -> 26 | BZ24: =+IFERROR(BY25/BY24,0) -> 56.230769 | CA24: =+BY24 -> 26 | CB24: =+IFERROR(CA25/CA24,0) -> 56.230769
E25: kUS$ | BL25: 1205 | BM25: 1393 | BN25: =+BM25 -> 1393 | BO25: 1401 | BP25: 1555 | BQ25: 1379 | BR25: 1627 | BS25: =+BR25 -> 1627 | BT25: 1579 | BU25: 1340 | BV25: 1485 | BW25: 1500 | BX25: 1462 | BY25: =+BX25 -> 1462 | CA25: =+BY25 -> 1462
B26: IM | C26: 11.1 | D26: Facturas Vencidas | E26: # | K26: 8 | L26: =+SUM(I26:K26) -> 8 | M26: =+L27/L26 -> 35.75 | N26: 5 | O26: 3 | P26: 2 | Q26: 5 | R26: =+Q26 -> 5 | S26: 5 | T26: 6 | U26: 3 | V26: 3 | W26: =+V26 -> 3 | X26: 3 | Y26: 1 | Z26: 2 | AA26: 2 | AB26: =+AA26 -> 2 | AC26: 2 | AD26: 2 | AE26: 2 | AF26: 2 | AG26: 2 | AH26: =+AG26 -> 2 | AI26: 2 | AJ26: 6 | AK26: 4 | AL26: 3 | AM26: =+AL26 -> 3 | AN26: 3 | AO26: 6 | AP26: 5 | AQ26: 3 | AR26: =+AQ26 -> 3 | AS26: 2 | AT26: 1 | AU26: 1 | AV26: 1 | AW26: 4 | AX26: =+AW26 -> 4 | AY26: 2 | AZ26: 5 | BA26: 4 | BB26: 4 | BC26: =+BB26 -> 4 | BD26: 4 | BE26: 6 | BF26: 6 | BG26: 5 | BH26: =+BG26 -> 5 | BI26: 5 | BJ26: 5 | BK26: 6 | BL26: 5 | BM26: 5 | BN26: =+BM26 -> 5 | BO26: 5 | BP26: 5 | BQ26: 8 | BR26: 9 | BS26: =+BR26 -> 9 | BT26: 9 | BU26: 6 | BV26: 8 | BW26: 9 | BX26: 11 | BY26: =+BX26 -> 11 | BZ26: =+IFERROR(BY27/BY26,0) -> 74.727273 | CA26: =+BY26 -> 11 | CB26: =+IFERROR(CA27/CA26,0) -> 74.727273
E27: KUS$ | K27: 286 | L27: =+SUM(I27:K27) -> 286 | N27: 110 | O27: 60 | P27: 26.8 | Q27: =227+27 -> 254 | R27: =+Q27 -> 254 | S27: 254 | T27: 213 | U27: 109 | V27: 109 | W27: =+V27 -> 109 | X27: 109 | Y27: 5.2 | Z27: 29 | AA27: 29 | AB27: =+AA27 -> 29 | AC27: 29 | AD27: 29 | AE27: 29 | AF27: 29 | AG27: 29 | AH27: =+AG27 -> 29 | AI27: 29 | AJ27: 198 | AK27: 162 | AL27: 61 | AM27: =+AL27 -> 61 | AN27: 61 | AO27: 225 | AP27: 99 | AQ27: 83 | AR27: =+AQ27 -> 83 | AS27: 10 | AT27: 5 | AU27: 5 | AV27: 5 | AW27: 78 | AX27: =+AW27 -> 78 | AY27: 15 | AZ27: 261 | BA27: 239 | BB27: 239 | BC27: =+BB27 -> 239 | BD27: 218 | BE27: 406 | BF27: 406 | BG27: 367 | BH27: =+BG27 -> 367 | BI27: 367 | BJ27: 367 | BK27: 387 | BL27: 328 | BM27: 362 | BN27: =+BM27 -> 362 | BO27: 362 | BP27: 362 | BQ27: 468 | BR27: 622 | BS27: =+BR27 -> 622 | BT27: 622 | BU27: 510 | BV27: 701 | BW27: 789 | BX27: 822 | BY27: =+BX27 -> 822 | CA27: =+BY27 -> 822
AC31: 2 | AD31: 6 | AE31: 1 | AF31: 4
AC32: 98 | AD32: 346 | AE32: 42 | AF32: 65
BU33: Perú | BV33: Resource Development Plan (RDP)
BU34: Chile | BV34: Auditoría R&R (modelo de recursos, hidrogeología y geomecanica)
AO36: =6677-6537 -> 140

Sheet KPI´s de negocio 2026
B2: Resp. | C2: # | D2: Ítem | E2: Unidad | F2: 2025 | G2: Media 2025 | H2: S1 | I2: S2 | J2: S3 | K2: S4 | L2: 46023 | M2: S1 | N2: S2 | O2: S3 | P2: S4 | Q2: 46054 | R2: S1 | S2: S2 | T2: S3 | U2: S4 | V2: 46082 | W2: S1 | X2: S2 | Y2: S3 | Z2: S4 | AA2: S5 | AB2: 46113 | AC2: S1 | AD2: S2 | AE2: S3 | AF2: S4 | AG2: 46143 | AH2: S1 | AI2: S2 | AJ2: S3 | AK2: S4 | AL2: 46174 | AM2: S1 | AN2: S2 | AO2: S3 | AP2: S4 | AQ2: S5 | AR2: 46204 | AS2: S1 | AT2: S2 | AU2: S3 | AV2: S4 | AW2: 46235 | AX2: S1 | AY2: S2 | AZ2: S3 | BA2: S4 | BB2: 46266 | BC2: S1 | BD2: S2 | BE2: S3 | BF2: S4 | BG2: S5 | BH2: 46296 | BI2: S1 | BJ2: S2 | BK2: S3 | BL2: S4 | BM2: 46327 | BN2: S1 | BO2: S2 | BP2: S3 | BQ2: S4 | BR2: S5 | BS2: 46357 | BT2: Media jun | BU2: Acum. 2026 | BV2: Media Acum. | CA2: Item | CB2: kUS$ | CC2: Rezagado | CD2: %
B3: PA | C3: 1 | D3: Propuestas Emitidas | E3: # | F3: 164 | G3: =+F4/F3 -> 266.19512 | K3: 13 | L3: =+H3+I3+J3+K3 -> 13 | P3: 16 | Q3: =+M3+N3+O3+P3 -> 16 | U3: 21 | V3: =+R3+S3+T3+U3 -> 21 | W3: 2 | X3: 6 | Y3: 5 | Z3: 2 | AA3: 4 | AB3: =+W3+X3+Y3+Z3+AA3 -> 19 | AC3: 5 | AD3: 1 | AE3: 5 | AF3: 3 | AG3: =+AC3+AD3+AE3+AF3 -> 14 | AH3: 3 | AL3: =+AH3+AI3+AJ3+AK3 -> 3 | AR3: =+AM3+AN3+AO3+AP3+AQ3 -> 0 | AW3: =+AS3+AT3+AU3+AV3 -> 0 | BB3: =+AX3+AY3+AZ3+BA3 -> 0 | BH3: =+BC3+BD3+BE3+BF3+BG3 -> 0 | BM3: =+BI3+BJ3+BK3+BL3 -> 0 | BS3: =+BN3+BO3+BP3+BQ3+BR3 -> 0 | BT3: =+IFERROR(AL4/AL3,0) -> 959.75867 | BU3: =+L3+Q3+V3+AB3+AG3+AL3 -> 86 | BV3: =+IFERROR(BU4/BU3,0) -> 221.94141 | CA3: Ingreso Operacional | CB3: =+BU14 -> 3253 | CD3: =+CB3/$CB$6 -> 0.582453
E4: kUS$ | F4: 43656 | K4: 2370 | L4: =+H4+I4+J4+K4 -> 2370 | P4: 4175 | Q4: =+M4+N4+O4+P4 -> 4175 | U4: 3958 | V4: =+R4+S4+T4+U4 -> 3958 | W4: 110 | X4: 1960 | Y4: 230 | Z4: 440 | AA4: 450 | AB4: =+W4+X4+Y4+Z4+AA4 -> 3190 | AC4: 364.125 | AD4: 70.2 | AE4: 1302.02 | AF4: 778.34 | AG4: =+AC4+AD4+AE4+AF4 -> 2514.685 | AH4: 2879.276 | AL4: =+AH4+AI4+AJ4+AK4 -> 2879.276 | AR4: =+AM4+AN4+AO4+AP4+AQ4 -> 0 | AW4: =+AS4+AT4+AU4+AV4 -> 0 | BB4: =+AX4+AY4+AZ4+BA4 -> 0 | BH4: =+BC4+BD4+BE4+BF4+BG4 -> 0 | BM4: =+BI4+BJ4+BK4+BL4 -> 0 | BS4: =+BN4+BO4+BP4+BQ4+BR4 -> 0 | BU4: =+L4+Q4+V4+AB4+AG4+AL4 -> 19086.961 | BW4: 1683 | BX4: =+BW4-AG4 -> -831.685 | CA4: Facturas por cobrar | CB4: =+BU25 -> 1517 | CC4: =+AL27 -> 72 | CD4: =+CB4/$CB$6 -> 0.27162041
B5: PA | C5: 2 | D5: Propuestas Adjudicadas | E5: # | F5: 78 | G5: =+F6/F5 -> 131.74359 | K5: 6 | L5: =+H5+I5+J5+K5 -> 6 | P5: 4 | Q5: =+M5+N5+O5+P5 -> 4 | U5: 11 | V5: =+R5+S5+T5+U5 -> 11 | W5: 1 | X5: 1 | Y5: 3 | Z5: 1 | AA5: 1 | AB5: =+W5+X5+Y5+Z5+AA5 -> 7 | AC5: 2 | AD5: 3 | AE5: 0 | AF5: 1 | AG5: =+AC5+AD5+AE5+AF5 -> 6 | AH5: 0 | AL5: =+AH5+AI5+AJ5+AK5 -> 0 | AR5: =+AM5+AN5+AO5+AP5+AQ5 -> 0 | AW5: =+AS5+AT5+AU5+AV5 -> 0 | BB5: =+AX5+AY5+AZ5+BA5 -> 0 | BH5: =+BC5+BD5+BE5+BF5+BG5 -> 0 | BM5: =+BI5+BJ5+BK5+BL5 -> 0 | BS5: =+BN5+BO5+BP5+BQ5+BR5 -> 0 | BT5: =+IFERROR(AL6/AL5,0) -> 0 | BU5: =+L5+Q5+V5+AB5+AG5+AL5 -> 34 | BV5: =+IFERROR(BU6/BU5,0) -> 119.14471 | CA5: EDP por facturar | CB5: =+BU19 -> 815 | CC5: =+AL23 -> 189 | CD5: =+CB5/$CB$6 -> 0.14592659
E6: kUS$ | F6: 10276 | K6: 804 | L6: =+H6+I6+J6+K6 -> 804 | P6: 371 | Q6: =+M6+N6+O6+P6 -> 371 | U6: 1406 | V6: =+R6+S6+T6+U6 -> 1406 | W6: 45 | X6: 235 | Y6: 382 | Z6: 343 | AA6: 55 | AB6: =+W6+X6+Y6+Z6+AA6 -> 1060 | AC6: 211 | AD6: 187 | AE6: 0 | AF6: 11.92 | AG6: =+AC6+AD6+AE6+AF6 -> 409.92 | AH6: 0 | AL6: =+AH6+AI6+AJ6+AK6 -> 0 | AR6: =+AM6+AN6+AO6+AP6+AQ6 -> 0 | AW6: =+AS6+AT6+AU6+AV6 -> 0 | BB6: =+AX6+AY6+AZ6+BA6 -> 0 | BH6: =+BC6+BD6+BE6+BF6+BG6 -> 0 | BM6: =+BI6+BJ6+BK6+BL6 -> 0 | BS6: =+BN6+BO6+BP6+BQ6+BR6 -> 0 | BU6: =+L6+Q6+V6+AB6+AG6+AL6 -> 4050.92 | CA6: Total | CB6: =SUM(CB3:CB5) -> 5585 | CC6: =SUM(CC3:CC5) -> 261
B7: EC | C7: 3 | D7: POM | E7: # | F7: 222 | G7: =+F8/F7 -> 40.707207 | K7: =17-1 -> 16 | L7: =+H7+I7+J7+K7 -> 16 | P7: 15 | Q7: =+M7+N7+O7+P7 -> 15 | U7: 19 | V7: =+R7+S7+T7+U7 -> 19 | W7: 24 | X7: 2 | Y7: 0 | Z7: 0 | AA7: 0 | AB7: =W7+X7+Y7+Z7+AA7 -> 26 | AC7: 20 | AD7: 0 | AE7: 0 | AF7: 0 | AG7: =+AC7+AD7+AE7+AF7 -> 20 | AH7: 13 | AL7: =+AH7+AI7+AJ7+AK7 -> 13 | AR7: =+AM7+AN7+AO7+AP7+AQ7 -> 0 | AW7: =+AS7+AT7+AU7+AV7 -> 0 | BB7: =+AX7+AY7+AZ7+BA7 -> 0 | BH7: =+BC7+BD7+BE7+BF7+BG7 -> 0 | BM7: =+BI7+BJ7+BK7+BL7 -> 0 | BS7: =+BN7+BO7+BP7+BQ7+BR7 -> 0 | BT7: =+IFERROR(AL8/AL7,0) -> 47.384615 | BU7: =+L7+Q7+V7+AB7+AG7+AL7 -> 109 | BV7: =+IFERROR(BU8/BU7,0) -> 38.592742 | BW7: 20 | BX7: =+BW7-AG7 -> 0
E8: kUS$ | F8: 9037 | K8: =(1785615.6862/1000)-1218 -> 567.61569 | L8: =+H8+I8+J8+K8 -> 567.61569 | P8: =778370.215074722/1000 -> 778.37022 | Q8: =+M8+N8+O8+P8 -> 778.37022 | U8: =814623/1000 -> 814.623 | V8: =+R8+S8+T8+U8 -> 814.623 | W8: 669 | X8: 62 | Y8: -3 | Z8: 0 | AA8: 0 | AB8: =W8+X8+Y8+Z8+AA8 -> 728 | AC8: 700 | AD8: 2 | AE8: 0 | AF8: 0 | AG8: =+AC8+AD8+AE8+AF8 -> 702 | AH8: 616 | AL8: =+AH8+AI8+AJ8+AK8 -> 616 | AR8: =+AM8+AN8+AO8+AP8+AQ8 -> 0 | AW8: =+AS8+AT8+AU8+AV8 -> 0 | BB8: =+AX8+AY8+AZ8+BA8 -> 0 | BH8: =+BC8+BD8+BE8+BF8+BG8 -> 0 | BM8: =+BI8+BJ8+BK8+BL8 -> 0 | BS8: =+BN8+BO8+BP8+BQ8+BR8 -> 0 | BU8: =+L8+Q8+V8+AB8+AG8+AL8 -> 4206.6089 | BW8: 702 | BX8: =+BW8-AG8 -> 0
B9: EC | C9: 4 | D9: EDP Emitidos (Estados de pago) | E9: # | F9: 204 | G9: =+F10/F9 -> 45.849956 | K9: 10 | L9: =+H9+I9+J9+K9 -> 10 | P9: 17 | Q9: =+M9+N9+O9+P9 -> 17 | U9: =19+1 -> 20 | V9: =+R9+S9+T9+U9 -> 20 | X9: 0 | Y9: 0 | Z9: =7+2 -> 9 | AA9: =11+1 -> 12 | AB9: =+W9+X9+Y9+Z9+AA9 -> 21 | AC9: 0 | AD9: 1 | AE9: 5 | AF9: =7+5 -> 12 | AG9: =+AC9+AD9+AE9+AF9 -> 18 | AH9: 0 | AL9: =+AH9+AI9+AJ9+AK9 -> 0 | AR9: =+AM9+AN9+AO9+AP9+AQ9 -> 0 | AW9: =+AS9+AT9+AU9+AV9 -> 0 | BB9: =+AX9+AY9+AZ9+BA9 -> 0 | BH9: =+BC9+BD9+BE9+BF9+BG9 -> 0 | BM9: =+BI9+BJ9+BK9+BL9 -> 0 | BS9: =+BN9+BO9+BP9+BQ9+BR9 -> 0 | BT9: =+IFERROR(AL10/AL9,0) -> 0 | BU9: =+L9+Q9+V9+AB9+AG9+AL9 -> 86 | BV9: =+IFERROR(BU10/BU9,0) -> 41.840125 | BW9: 18 | BX9: =+BW9-AG9 -> 0 | CA9: Mes | CB9: POM | CC9: EDP Emitidos | CD9: EDP Facturados | CE9: EDP Pagados
E10: kUS$ | F10: 9353.391 | K10: =319250.709904762/1000 -> 319.25071 | L10: =+H10+I10+J10+K10 -> 319.25071 | P10: 606 | Q10: =+M10+N10+O10+P10 -> 606 | U10: =1004+400 -> 1404 | V10: =+R10+S10+T10+U10 -> 1404 | X10: 0 | Y10: 0 | Z10: =198+85 -> 283 | AA10: =295+60+70 -> 425 | AB10: =+W10+X10+Y10+Z10+AA10 -> 708 | AC10: 0 | AD10: 13 | AE10: 101 | AF10: =151+106+190 -> 447 | AG10: =+AC10+AD10+AE10+AF10 -> 561 | AH10: 0 | AL10: =+AH10+AI10+AJ10+AK10 -> 0 | AR10: =+AM10+AN10+AO10+AP10+AQ10 -> 0 | AW10: =+AS10+AT10+AU10+AV10 -> 0 | BB10: =+AX10+AY10+AZ10+BA10 -> 0 | BH10: =+BC10+BD10+BE10+BF10+BG10 -> 0 | BM10: =+BI10+BJ10+BK10+BL10 -> 0 | BS10: =+BN10+BO10+BP10+BQ10+BR10 -> 0 | BU10: =+L10+Q10+V10+AB10+AG10+AL10 -> 3598.2507 | BW10: 561 | BX10: =+BW10-AG10 -> 0 | CA10: Ene | CB10: =L7 -> 16 | CC10: =L9 -> 10 | CD10: =L11 -> 12 | CE10: =L13 -> 27
B11: IM | C11: 5 | D11: EDP Facturados (Facturación) | E11: # | F11: 219 | G11: =+F12/F11 -> 44.726027 | K11: 12 | L11: =+H11+I11+J11+K11 -> 12 | P11: 12 | Q11: =+M11+N11+O11+P11 -> 12 | U11: =15+1 -> 16 | V11: =+R11+S11+T11+U11 -> 16 | X11: 8 | Y11: 3 | Z11: =5+2 -> 7 | AA11: =3 -> 3 | AB11: =+W11+X11+Y11+Z11+AA11 -> 21 | AC11: 5 | AD11: 3 | AE11: 2 | AF11: 5 | AG11: =+AC11+AD11+AE11+AF11 -> 15 | AH11: 1 | AL11: =+AH11+AI11+AJ11+AK11 -> 1 | AR11: =+AM11+AN11+AO11+AP11+AQ11 -> 0 | AW11: =+AS11+AT11+AU11+AV11 -> 0 | BB11: =+AX11+AY11+AZ11+BA11 -> 0 | BH11: =+BC11+BD11+BE11+BF11+BG11 -> 0 | BM11: =+BI11+BJ11+BK11+BL11 -> 0 | BS11: =+BN11+BO11+BP11+BQ11+BR11 -> 0 | BT11: =+IFERROR(AL12/AL11,0) -> 76 | BU11: =+L11+Q11+V11+AB11+AG11+AL11 -> 77 | BV11: =+IFERROR(BU12/BU11,0) -> 41.694139 | BW11: 15 | BX11: =+BW11-AG11 -> 0 | CA11: Feb | CB11: =Q7 -> 15 | CC11: =Q9 -> 17 | CD11: =Q11 -> 12 | CE11: =Q13 -> 10
E12: kUS$ | F12: 9795 | K12: =452448.719370441/1000 -> 452.44872 | L12: =+H12+I12+J12+K12 -> 452.44872 | P12: 392 | Q12: =+M12+N12+O12+P12 -> 392 | U12: =623+400 -> 1023 | V12: =+R12+S12+T12+U12 -> 1023 | X12: 256 | Y12: 166 | Z12: =128+60 -> 188 | AA12: =78 -> 78 | AB12: =+W12+X12+Y12+Z12+AA12 -> 688 | AC12: 138 | AD12: 282 | AE12: 71 | AF12: 88 | AG12: =+AC12+AD12+AE12+AF12 -> 579 | AH12: 76 | AL12: =+AH12+AI12+AJ12+AK12 -> 76 | AR12: =+AM12+AN12+AO12+AP12+AQ12 -> 0 | AW12: =+AS12+AT12+AU12+AV12 -> 0 | BB12: =+AX12+AY12+AZ12+BA12 -> 0 | BH12: =+BC12+BD12+BE12+BF12+BG12 -> 0 | BM12: =+BI12+BJ12+BK12+BL12 -> 0 | BS12: =+BN12+BO12+BP12+BQ12+BR12 -> 0 | BU12: =+L12+Q12+V12+AB12+AG12+AL12 -> 3210.4487 | BW12: 579 | BX12: =+BW12-AG12 -> 0 | CA12: Mar | CB12: =V7 -> 19 | CC12: =V9 -> 20 | CD12: =V11 -> 16 | CE12: =V13 -> 15
B13: IM | C13: 6 | D13: EDP Pagados (Ingreso Operacional) | E13: # | F13: 216 | G13: =+F14/F13 -> 41.782407 | K13: 27 | L13: =+H13+I13+J13+K13 -> 27 | P13: 10 | Q13: =+M13+N13+O13+P13 -> 10 | U13: 15 | V13: =+R13+S13+T13+U13 -> 15 | X13: 1 | Y13: 11 | Z13: 0 | AA13: 5 | AB13: =+W13+X13+Y13+Z13+AA13 -> 17 | AC13: 4 | AD13: 3 | AE13: 2 | AF13: 1 | AG13: =+AC13+AD13+AE13+AF13 -> 10 | AH13: 3 | AL13: =+AH13+AI13+AJ13+AK13 -> 3 | AR13: =+AM13+AN13+AO13+AP13+AQ13 -> 0 | AW13: =+AS13+AT13+AU13+AV13 -> 0 | BB13: =+AX13+AY13+AZ13+BA13 -> 0 | BH13: =+BC13+BD13+BE13+BF13+BG13 -> 0 | BM13: =+BI13+BJ13+BK13+BL13 -> 0 | BS13: =+BN13+BO13+BP13+BQ13+BR13 -> 0 | BT13: =+IFERROR(AL14/AL13,0) -> 16.333333 | BU13: =+L13+Q13+V13+AB13+AG13+AL13 -> 82 | BV13: =+IFERROR(BU14/BU13,0) -> 39.670732 | BW13: 10 | BX13: =+BW13-AG13 -> 0 | CA13: Abr | CB13: =AB7 -> 26 | CC13: =AB9 -> 21 | CD13: =AB11 -> 21 | CE13: =AB13 -> 17
E14: kUS$ | F14: 9025 | K14: 1645 | L14: =+H14+I14+J14+K14 -> 1645 | P14: 239 | Q14: =+M14+N14+O14+P14 -> 239 | U14: 422 | V14: =+R14+S14+T14+U14 -> 422 | X14: 64 | Y14: 323 | Z14: 0 | AA14: 85 | AB14: =+W14+X14+Y14+Z14+AA14 -> 472 | AC14: 145 | AD14: 106 | AE14: 72 | AF14: 103 | AG14: =+AC14+AD14+AE14+AF14 -> 426 | AH14: 49 | AL14: =+AH14+AI14+AJ14+AK14 -> 49 | AR14: =+AM14+AN14+AO14+AP14+AQ14 -> 0 | AW14: =+AS14+AT14+AU14+AV14 -> 0 | BB14: =+AX14+AY14+AZ14+BA14 -> 0 | BH14: =+BC14+BD14+BE14+BF14+BG14 -> 0 | BM14: =+BI14+BJ14+BK14+BL14 -> 0 | BS14: =+BN14+BO14+BP14+BQ14+BR14 -> 0 | BU14: =+L14+Q14+V14+AB14+AG14+AL14 -> 3253 | BW14: 426 | BX14: =+BW14-AG14 -> 0 | BY14: 1323 | BZ14: =+BU14+BY14 -> 4576 | CA14: May | CB14: =AG7 -> 20 | CC14: =AG9 -> 18 | CD14: =AG11 -> 15 | CE14: =AG13 -> 10
B15: IM | C15: 7 | D15: Gasto Operacional | E15: kUS$ | F15: 6790 | G15: =+F15/12 -> 565.83333 | K15: 941 | L15: 715 | P15: 552 | Q15: 565 | U15: 546 | V15: =+R15+S15+T15+U15 -> 546 | Z15: 585 | AA15: 585 | AB15: =+AA15 -> 585 | AC15: 569 | AD15: 0 | AE15: =494*1.1 -> 543.4 | AF15: 543 | AG15: =+AF15 -> 543 | AH15: 500 | AL15: =+AH15 -> 500 | AR15: 0 | AW15: 0 | BB15: 0 | BH15: 0 | BM15: 0 | BS15: 0 | BT15: =+AL15 -> 500 | BU15: =+L15+Q15+V15+AB15+AG15+AL15 -> 3454 | BV15: =+BU15/6 -> 575.66667 | CA15: Jun | CB15: =AL7 -> 13 | CC15: =AL9 -> 0 | CD15: =AL11 -> 1 | CE15: =AL13 -> 3
B16: EC | C16: 8 | D16: Cumplimiento POM vs EDP | E16: % | F16: 1.0577036 | G16: 1.06 | K16: =+IFERROR(K10/K8,0) -> 0.56244166 | L16: =+IFERROR(L10/L8,0) -> 0.56244166 | P16: =+IFERROR(P10/P8,0) -> 0.77854983 | Q16: =+IFERROR(Q10/Q8,0) -> 0.77854983 | U16: =+IFERROR(U10/U8,0) -> 1.7234966 | V16: =+IFERROR(V10/V8,0) -> 1.7234966 | Z16: 0 | AA16: 0 | AB16: =+IFERROR(AB10/AB8,0) -> 0.97252747 | AC16: 0 | AD16: 0 | AE16: 0 | AF16: 0 | AG16: =+IFERROR(AG10/AG8,0) -> 0.7991453 | AH16: 0 | AL16: =+IFERROR(AL10/AL8,0) -> 0 | AR16: =+IFERROR(AR10/AR8,0) -> 0 | AW16: =+IFERROR(AW10/AW8,0) -> 0 | BB16: =+IFERROR(BB10/BB8,0) -> 0 | BH16: =+IFERROR(BH10/BH8,0) -> 0 | BM16: =+IFERROR(BM10/BM8,0) -> 0 | BS16: =+IFERROR(BS10/BS8,0) -> 0 | BT16: =+AL16 -> 0 | BU16: =+AVERAGE(L16,Q16,V16,AB16,AG16) -> 0.96723218 | BV16: =+BU16 -> 0.96723218 | CA16: Jul | CB16: =AR7 -> 0 | CC16: =AR9 -> 0 | CD16: =AR11 -> 0 | CE16: =AR13 -> 0
B17: EC | C17: 9 | D17: Adherencia POM vs EDP | E17: % | F17: 0.75 | G17: 0.75 | K17: 0.42 | L17: =+K17 -> 0.42 | P17: 0.69 | Q17: =+P17 -> 0.69 | U17: 0.72 | V17: =+U17 -> 0.72 | Z17: 0 | AA17: 0 | AB17: 0.75 | AC17: 0 | AD17: 0 | AE17: 0 | AF17: 0 | AG17: 0.73 | AH17: 0 | AL17: 0 | AR17: 0 | AW17: 0 | BB17: 0 | BH17: 0 | BM17: 0 | BS17: 0 | BT17: =+AL17 -> 0 | BU17: =+AVERAGE(L17,Q17,V17,AB17,AG17) -> 0.662 | BV17: =+BU17 -> 0.662 | CA17: Ago | CB17: =AW7 -> 0 | CC17: =AW9 -> 0 | CD17: =AW11 -> 0 | CE17: =AW13 -> 0
B18: EC | C18: 10 | D18: Backlog EDP (por facturar) | E18: # | F18: 9 | G18: =+F19/F18 -> 27.222222 | L18: =+L20+L22 -> 0 | Q18: =+Q20+Q22 -> 0 | U18: =+U20+U22 -> 6 | V18: =+V20+V22 -> 6 | X18: =+X20+X22 -> 13 | Y18: =+Y20+Y22 -> 10 | Z18: =+Z20+Z22 -> 10 | AA18: =+AA20+AA22 -> 21 | AB18: =+AA18 -> 21 | AC18: =+AC20+AC22 -> 18 | AD18: =+AD20+AD22 -> 16 | AE18: =+AE20+AE22 -> 19 | AF18: =+AF20+AF22 -> 21 | AG18: =+AG20+AG22 -> 21 | AH18: =+AH20+AH22 -> 24 | AL18: =+AL20+AL22 -> 24 | AR18: =+AR20+AR22 -> 0 | AW18: =+AW20+AW22 -> 0 | BB18: =+BB20+BB22 -> 0 | BH18: =+BH20+BH22 -> 0 | BM18: =+BM20+BM22 -> 0 | BS18: =+BS20+BS22 -> 0 | BT18: =+IFERROR(AL19/AL18,0) -> 33.958333 | BU18: =+AL18 -> 24 | BV18: =+IFERROR(BU19/BU18,0) -> 33.958333 | CA18: Sep | CB18: =BB7 -> 0 | CC18: =BB9 -> 0 | CD18: =BB11 -> 0 | CE18: =BB13 -> 0
E19: kUS$ | F19: 245 | L19: =+L21+L23 -> 0 | Q19: =+Q21+Q23 -> 0 | U19: =+U21+U23 -> 235 | V19: =+V21+V23 -> 235 | X19: =+X21+X23 -> 648 | Y19: =+Y21+Y23 -> 481 | Z19: =+Z21+Z23 -> 493 | AA19: =+AA21+AA23 -> 777 | AB19: =+AA19 -> 777 | AC19: =+AC21+AC23 -> 717 | AD19: =+AD21+AD23 -> 517 | AE19: =+AE21+AE23 -> 547 | AF19: =+AF21+AF23 -> 706 | AG19: =+AG21+AG23 -> 706 | AH19: =+AH21+AH23 -> 815 | AL19: =+AL21+AL23 -> 815 | AR19: =+AR21+AR23 -> 0 | AW19: =+AW21+AW23 -> 0 | BB19: =+BB21+BB23 -> 0 | BH19: =+BH21+BH23 -> 0 | BM19: =+BM21+BM23 -> 0 | BS19: =+BS21+BS23 -> 0 | BU19: =+AL19 -> 815 | CA19: Oct | CB19: =BH7 -> 0 | CC19: =BH9 -> 0 | CD19: =BH11 -> 0 | CE19: =BH13 -> 0
B20: EC | C20: 10.1 | D20: Pendientes aprobación | E20: # | F20: 3 | L20: =+H20 -> 0 | Q20: =+P20 -> 0 | U20: 4 | V20: =+U20 -> 4 | X20: 11 | Y20: 8 | Z20: 9 | AA20: 21 | AB20: =+AA20 -> 21 | AC20: 18 | AD20: 16 | AE20: 16 | AF20: 16 | AG20: =+AF20 -> 16 | AH20: 21 | AL20: =+AH20 -> 21 | AR20: =+AQ20 -> 0 | AW20: =+AV20 -> 0 | BB20: =+BA20 -> 0 | BH20: =+BG20 -> 0 | BM20: =+BL20 -> 0 | BS20: =+BR20 -> 0 | BT20: =+IFERROR(AL21/AL20,0) -> 29.809524 | BU20: =+AL20 -> 21 | BV20: =+IFERROR(BU21/BU20,0) -> 29.809524 | CA20: Nov | CB20: =BM7 -> 0 | CC20: =BM9 -> 0 | CD20: =BM11 -> 0 | CE20: =BM13 -> 0
E21: kUS$ | F21: 86 | L21: =+H21 -> 0 | Q21: =+P21 -> 0 | U21: 114 | V21: =+U21 -> 114 | X21: 527 | Y21: 447 | Z21: 476 | AA21: 777 | AB21: =+AA21 -> 777 | AC21: 717 | AD21: 517 | AE21: 399 | AF21: 436 | AG21: =+AF21 -> 436 | AH21: 626 | AL21: =+AH21 -> 626 | AR21: =+AQ21 -> 0 | AW21: =+AV21 -> 0 | BB21: =+BA21 -> 0 | BH21: =+BG21 -> 0 | BM21: =+BL21 -> 0 | BS21: =+BR21 -> 0 | BU21: =+AL21 -> 626 | CA21: Dic | CB21: =BS7 -> 0 | CC21: =BS9 -> 0 | CD21: =BS11 -> 0 | CE21: =BS13 -> 0
B22: EC | C22: 10.2 | D22: Aprobados por facturar | E22: # | F22: 6 | L22: =+H22 -> 0 | Q22: =+P22 -> 0 | U22: 2 | V22: =+U22 -> 2 | X22: 2 | Y22: 2 | Z22: 1 | AA22: 0 | AB22: =+AA22 -> 0 | AC22: 0 | AD22: 0 | AE22: 3 | AF22: 5 | AG22: =+AF22 -> 5 | AH22: 3 | AL22: =+AH22 -> 3 | AR22: =+AQ22 -> 0 | AW22: =+AV22 -> 0 | BB22: =+BA22 -> 0 | BH22: =+BG22 -> 0 | BM22: =+BL22 -> 0 | BS22: =+BR22 -> 0 | BT22: =+IFERROR(AL23/AL22,0) -> 63 | BU22: =+AL22 -> 3 | BV22: =+IFERROR(BU23/BU22,0) -> 63
E23: kUS$ | F23: 159 | L23: =+H23 -> 0 | Q23: =+P23 -> 0 | U23: =103+18 -> 121 | V23: =+U23 -> 121 | X23: =18+103 -> 121 | Y23: =17+17 -> 34 | Z23: 17 | AA23: 0 | AB23: =+AA23 -> 0 | AC23: 0 | AD23: 0 | AE23: 148 | AF23: 270 | AG23: =+AF23 -> 270 | AH23: 189 | AL23: =+AH23 -> 189 | AR23: =+AQ23 -> 0 | AW23: =+AV23 -> 0 | BB23: =+BA23 -> 0 | BH23: =+BG23 -> 0 | BM23: =+BL23 -> 0 | BS23: =+BR23 -> 0 | BU23: =+AL23 -> 189
B24: EC | C24: 11 | D24: Backlog Facturas (Por cobrar) | E24: # | F24: 26 | G24: =+F25/F24 -> 56.230769 | L24: =+H24 -> 0 | Q24: =+P24 -> 0 | U24: 17 | V24: =+U24 -> 17 | X24: 22 | Y24: 15 | Z24: 21 | AA24: 16 | AB24: =+AA24 -> 16 | AC24: 20 | AD24: 20 | AE24: 21 | AF24: 25 | AG24: =+AF24 -> 25 | AH24: 23 | AL24: =+AH24 -> 23 | BH24: =+BG24 -> 0 | BM24: =+BL24 -> 0 | BS24: =+BR24 -> 0 | BT24: =+IFERROR(AL25/AL24,0) -> 65.956522 | BU24: =+AL24 -> 23 | BV24: =+IFERROR(BU25/BU24,0) -> 65.956522
E25: kUS$ | F25: 1462 | L25: =+H25 -> 0 | Q25: =+P25 -> 0 | U25: 741 | V25: =+U25 -> 741 | X25: 891 | Y25: 726 | Z25: 914 | AA25: 847 | AB25: =+AA25 -> 847 | AC25: 1298 | AD25: 1475 | AE25: 1505 | AF25: 1490 | AG25: =+AF25 -> 1490 | AH25: 1517 | AL25: =+AH25 -> 1517 | BH25: =+BG25 -> 0 | BM25: =+BL25 -> 0 | BS25: =+BR25 -> 0 | BU25: =+AL25 -> 1517
B26: IM | C26: 11.1 | D26: Facturas Vencidas | E26: # | F26: 11 | L26: =+H26 -> 0 | Q26: =+P26 -> 0 | U26: 0 | V26: =+U26 -> 0 | X26: 0 | Y26: 0 | Z26: 0 | AA26: 0 | AB26: =+AA26 -> 0 | AC26: 1 | AD26: 0 | AE26: 5 | AF26: 7 | AG26: =+AF26 -> 7 | AH26: 2 | AL26: =+AH26 -> 2 | AR26: =+AQ26 -> 0 | AW26: =+AV26 -> 0 | BB26: =+BA26 -> 0 | BH26: =+BG26 -> 0 | BM26: =+BL26 -> 0 | BS26: =+BR26 -> 0 | BT26: =+IFERROR(AL27/AL26,0) -> 36 | BU26: =+AL26 -> 2 | BV26: =+IFERROR(BU27/BU26,0) -> 36
E27: KUS$ | F27: 822 | L27: =+H27 -> 0 | Q27: =+P27 -> 0 | U27: 0 | V27: =+U27 -> 0 | X27: 0 | Y27: 0 | Z27: 0 | AA27: 0 | AB27: =+AA27 -> 0 | AC27: 31 | AD27: 0 | AE27: 636 | AF27: 805 | AG27: =+AF27 -> 805 | AH27: 72 | AL27: =+AH27 -> 72 | AR27: =+AQ27 -> 0 | AW27: =+AV27 -> 0 | BB27: =+BA27 -> 0 | BH27: =+BG27 -> 0 | BM27: =+BL27 -> 0 | BS27: =+BR27 -> 0 | BU27: =+AL27 -> 72
BO33: Perú | BP33: Resource Development Plan (RDP)
BO34: Chile | BP34: Auditoría R&R (modelo de recursos, hidrogeología y geomecanica)

Sheet Ventas 2026
A1: # | B1: Fecha | C1: País | D1: Cliente | E1: Proyecto | F1: Monto USD
A2: 1 | B2: 46023 | E2: Proyecto 1
A3: 2 | B3: 46023 | E3: Proyecto 2
A4: 3 | B4: 46023 | E4: Proyecto 3
A5: 4 | B5: 46023 | E5: Proyecto 4
A6: 5 | B6: 46023 | E6: Proyecto 5
A7: 6 | B7: 46023 | E7: Proyecto 6
A8: 7 | B8: 46023 | E8: Proyecto 7
F9: Total

Sheet Análisis Comparativo
B2: ANÁLISIS COMPARATIVO DE KPIs DE NEGOCIO
B3: REDCO Mining Consultants | Enero – Mayo 2025 vs 2026
B4: Fecha de generación: 31 de mayo de 2026
B6: PROP. ADJUDICADAS | D6: POM | G6: EDP EMITIDOS | J6: EDP FACTURADOS | M6: EDP PAGADOS
B8: =TEXT(E37,"#.##0")&" kUS$ ("&E36&" #)" -> 4.051 kUS$ (34 #) | D8: =TEXT(E39,"#.##0")&" kUS$ ("&E38&" #)" -> 3.591 kUS$ (96 #) | G8: =TEXT(E41,"#.##0")&" kUS$ ("&E40&" #)" -> 3.598 kUS$ (86 #) | J8: =TEXT(E43,"#.##0")&" kUS$ ("&E42&" #)" -> 3.134 kUS$ (76 #) | M8: =TEXT(E45,"#.##0")&" kUS$ ("&E44&" #)" -> 3.204 kUS$ (79 #)
B9: ="vs "&TEXT(D37,"#.##0")&" kUS$ en 2025" -> vs 5.020 kUS$ en 2025 | D9: ="vs "&TEXT(D39,"#.##0")&" kUS$ en 2025" -> vs 3.847 kUS$ en 2025 | G9: ="vs "&TEXT(D41,"#.##0")&" kUS$ en 2025" -> vs 3.689 kUS$ en 2025 | J9: ="vs "&TEXT(D43,"#.##0")&" kUS$ en 2025" -> vs 3.552 kUS$ en 2025 | M9: ="vs "&TEXT(D45,"#.##0")&" kUS$ en 2025" -> vs 3.665 kUS$ en 2025
B10: =IF(G37<0,"▼ ","▲ ")&TEXT(ABS(G37),"0,0%") -> ▼ 19,3% | D10: =IF(G39<0,"▼ ","▲ ")&TEXT(ABS(G39),"0,0%") -> ▼ 6,7% | G10: =IF(G41<0,"▼ ","▲ ")&TEXT(ABS(G41),"0,0%") -> ▼ 2,5% | J10: =IF(G43<0,"▼ ","▲ ")&TEXT(ABS(G43),"0,0%") -> ▼ 11,8% | M10: =IF(G45<0,"▼ ","▲ ")&TEXT(ABS(G45),"0,0%") -> ▼ 12,6%
B13: 1. COMPARATIVO MENSUAL
B15: KPI | C15: Unidad | D15: Ene 25 | E15: Ene 26 | F15: Δ% | G15: Feb 25 | H15: Feb 26 | I15: Δ% | J15: Mar 25 | K15: Mar 26 | L15: Δ% | M15: Abr 25 | N15: Abr 26 | O15: Δ% | P15: May 25 | Q15: May 26 | R15: Δ%
B16: Propuestas Emitidas | C16: # | D16: ='KPI´s de negocio 2025'!R3 -> 8 | E16: ='KPI´s de negocio 2026'!L3 -> 13 | F16: =IFERROR((E16-D16)/D16,"-") -> 0.625 | G16: ='KPI´s de negocio 2025'!W3 -> 10 | H16: ='KPI´s de negocio 2026'!Q3 -> 16 | I16: =IFERROR((H16-G16)/G16,"-") -> 0.6 | J16: ='KPI´s de negocio 2025'!AB3 -> 11 | K16: ='KPI´s de negocio 2026'!V3 -> 21 | L16: =IFERROR((K16-J16)/J16,"-") -> 0.90909091 | M16: ='KPI´s de negocio 2025'!AH3 -> 18 | N16: ='KPI´s de negocio 2026'!AB3 -> 19 | O16: =IFERROR((N16-M16)/M16,"-") -> 0.055555556 | P16: ='KPI´s de negocio 2025'!AM3 -> 8 | Q16: ='KPI´s de negocio 2026'!AG3 -> 14 | R16: =IFERROR((Q16-P16)/P16,"-") -> 0.75
B17: Propuestas Emitidas | C17: kUS$ | D17: ='KPI´s de negocio 2025'!R4 -> 2212 | E17: ='KPI´s de negocio 2026'!L4 -> 2370 | F17: =IFERROR((E17-D17)/D17,"-") -> 0.071428571 | G17: ='KPI´s de negocio 2025'!W4 -> 2571 | H17: ='KPI´s de negocio 2026'!Q4 -> 4175 | I17: =IFERROR((H17-G17)/G17,"-") -> 0.62388176 | J17: ='KPI´s de negocio 2025'!AB4 -> 6130 | K17: ='KPI´s de negocio 2026'!V4 -> 3958 | L17: =IFERROR((K17-J17)/J17,"-") -> -0.354323 | M17: ='KPI´s de negocio 2025'!AH4 -> 4378 | N17: ='KPI´s de negocio 2026'!AB4 -> 3190 | O17: =IFERROR((N17-M17)/M17,"-") -> -0.27135678 | P17: ='KPI´s de negocio 2025'!AM4 -> 3026 | Q17: ='KPI´s de negocio 2026'!AG4 -> 2514.685 | R17: =IFERROR((Q17-P17)/P17,"-") -> -0.16897389
B18: Propuestas Adjudicadas | C18: # | D18: ='KPI´s de negocio 2025'!R5 -> 8 | E18: ='KPI´s de negocio 2026'!L5 -> 6 | F18: =IFERROR((E18-D18)/D18,"-") -> -0.25 | G18: ='KPI´s de negocio 2025'!W5 -> 6 | H18: ='KPI´s de negocio 2026'!Q5 -> 4 | I18: =IFERROR((H18-G18)/G18,"-") -> -0.33333333 | J18: ='KPI´s de negocio 2025'!AB5 -> 8 | K18: ='KPI´s de negocio 2026'!V5 -> 11 | L18: =IFERROR((K18-J18)/J18,"-") -> 0.375 | M18: ='KPI´s de negocio 2025'!AH5 -> 7 | N18: ='KPI´s de negocio 2026'!AB5 -> 7 | O18: =IFERROR((N18-M18)/M18,"-") -> 0 | P18: ='KPI´s de negocio 2025'!AM5 -> 4 | Q18: ='KPI´s de negocio 2026'!AG5 -> 6 | R18: =IFERROR((Q18-P18)/P18,"-") -> 0.5
B19: Propuestas Adjudicadas | C19: kUS$ | D19: ='KPI´s de negocio 2025'!R6 -> 1056 | E19: ='KPI´s de negocio 2026'!L6 -> 804 | F19: =IFERROR((E19-D19)/D19,"-") -> -0.23863636 | G19: ='KPI´s de negocio 2025'!W6 -> 1246 | H19: ='KPI´s de negocio 2026'!Q6 -> 371 | I19: =IFERROR((H19-G19)/G19,"-") -> -0.70224719 | J19: ='KPI´s de negocio 2025'!AB6 -> 736 | K19: ='KPI´s de negocio 2026'!V6 -> 1406 | L19: =IFERROR((K19-J19)/J19,"-") -> 0.91032609 | M19: ='KPI´s de negocio 2025'!AH6 -> 1014 | N19: ='KPI´s de negocio 2026'!AB6 -> 1060 | O19: =IFERROR((N19-M19)/M19,"-") -> 0.045364892 | P19: ='KPI´s de negocio 2025'!AM6 -> 968 | Q19: ='KPI´s de negocio 2026'!AG6 -> 409.92 | R19: =IFERROR((Q19-P19)/P19,"-") -> -0.57652893
B20: POM | C20: # | D20: ='KPI´s de negocio 2025'!R7 -> 21 | E20: ='KPI´s de negocio 2026'!L7 -> 16 | F20: =IFERROR((E20-D20)/D20,"-") -> -0.23809524 | G20: ='KPI´s de negocio 2025'!W7 -> 21 | H20: ='KPI´s de negocio 2026'!Q7 -> 15 | I20: =IFERROR((H20-G20)/G20,"-") -> -0.28571429 | J20: ='KPI´s de negocio 2025'!AB7 -> 22 | K20: ='KPI´s de negocio 2026'!V7 -> 19 | L20: =IFERROR((K20-J20)/J20,"-") -> -0.13636364 | M20: ='KPI´s de negocio 2025'!AH7 -> 13 | N20: ='KPI´s de negocio 2026'!AB7 -> 26 | O20: =IFERROR((N20-M20)/M20,"-") -> 1 | P20: ='KPI´s de negocio 2025'!AM7 -> 17 | Q20: ='KPI´s de negocio 2026'!AG7 -> 20 | R20: =IFERROR((Q20-P20)/P20,"-") -> 0.17647059
B21: POM | C21: kUS$ | D21: ='KPI´s de negocio 2025'!R8 -> 718 | E21: ='KPI´s de negocio 2026'!L8 -> 567.61569 | F21: =IFERROR((E21-D21)/D21,"-") -> -0.20944891 | G21: ='KPI´s de negocio 2025'!W8 -> 873 | H21: ='KPI´s de negocio 2026'!Q8 -> 778.37022 | I21: =IFERROR((H21-G21)/G21,"-") -> -0.10839609 | J21: ='KPI´s de negocio 2025'!AB8 -> 811 | K21: ='KPI´s de negocio 2026'!V8 -> 814.623 | L21: =IFERROR((K21-J21)/J21,"-") -> 0.0044673243 | M21: ='KPI´s de negocio 2025'!AH8 -> 611 | N21: ='KPI´s de negocio 2026'!AB8 -> 728 | O21: =IFERROR((N21-M21)/M21,"-") -> 0.19148936 | P21: ='KPI´s de negocio 2025'!AM8 -> 834 | Q21: ='KPI´s de negocio 2026'!AG8 -> 702 | R21: =IFERROR((Q21-P21)/P21,"-") -> -0.15827338
B22: EDP Emitidos | C22: # | D22: ='KPI´s de negocio 2025'!R9 -> 19 | E22: ='KPI´s de negocio 2026'!L9 -> 10 | F22: =IFERROR((E22-D22)/D22,"-") -> -0.47368421 | G22: ='KPI´s de negocio 2025'!W9 -> 20 | H22: ='KPI´s de negocio 2026'!Q9 -> 17 | I22: =IFERROR((H22-G22)/G22,"-") -> -0.15 | J22: ='KPI´s de negocio 2025'!AB9 -> 17 | K22: ='KPI´s de negocio 2026'!V9 -> 20 | L22: =IFERROR((K22-J22)/J22,"-") -> 0.17647059 | M22: ='KPI´s de negocio 2025'!AH9 -> 15 | N22: ='KPI´s de negocio 2026'!AB9 -> 21 | O22: =IFERROR((N22-M22)/M22,"-") -> 0.4 | P22: ='KPI´s de negocio 2025'!AM9 -> 16 | Q22: ='KPI´s de negocio 2026'!AG9 -> 18 | R22: =IFERROR((Q22-P22)/P22,"-") -> 0.125
B23: EDP Emitidos | C23: kUS$ | D23: ='KPI´s de negocio 2025'!R10 -> 669 | E23: ='KPI´s de negocio 2026'!L10 -> 319.25071 | F23: =IFERROR((E23-D23)/D23,"-") -> -0.52279416 | G23: ='KPI´s de negocio 2025'!W10 -> 892 | H23: ='KPI´s de negocio 2026'!Q10 -> 606 | I23: =IFERROR((H23-G23)/G23,"-") -> -0.3206278 | J23: ='KPI´s de negocio 2025'!AB10 -> 694 | K23: ='KPI´s de negocio 2026'!V10 -> 1404 | L23: =IFERROR((K23-J23)/J23,"-") -> 1.0230548 | M23: ='KPI´s de negocio 2025'!AH10 -> 704 | N23: ='KPI´s de negocio 2026'!AB10 -> 708 | O23: =IFERROR((N23-M23)/M23,"-") -> 0.0056818182 | P23: ='KPI´s de negocio 2025'!AM10 -> 730 | Q23: ='KPI´s de negocio 2026'!AG10 -> 561 | R23: =IFERROR((Q23-P23)/P23,"-") -> -0.23150685
B24: EDP Facturados | C24: # | D24: ='KPI´s de negocio 2025'!R11 -> 22 | E24: ='KPI´s de negocio 2026'!L11 -> 12 | F24: =IFERROR((E24-D24)/D24,"-") -> -0.45454545 | G24: ='KPI´s de negocio 2025'!W11 -> 9 | H24: ='KPI´s de negocio 2026'!Q11 -> 12 | I24: =IFERROR((H24-G24)/G24,"-") -> 0.33333333 | J24: ='KPI´s de negocio 2025'!AB11 -> 17 | K24: ='KPI´s de negocio 2026'!V11 -> 16 | L24: =IFERROR((K24-J24)/J24,"-") -> -0.058823529 | M24: ='KPI´s de negocio 2025'!AH11 -> 16 | N24: ='KPI´s de negocio 2026'!AB11 -> 21 | O24: =IFERROR((N24-M24)/M24,"-") -> 0.3125 | P24: ='KPI´s de negocio 2025'!AM11 -> 21 | Q24: ='KPI´s de negocio 2026'!AG11 -> 15 | R24: =IFERROR((Q24-P24)/P24,"-") -> -0.28571429
B25: EDP Facturados | C25: kUS$ | D25: ='KPI´s de negocio 2025'!R12 -> 823 | E25: ='KPI´s de negocio 2026'!L12 -> 452.44872 | F25: =IFERROR((E25-D25)/D25,"-") -> -0.45024457 | G25: ='KPI´s de negocio 2025'!W12 -> 313 | H25: ='KPI´s de negocio 2026'!Q12 -> 392 | I25: =IFERROR((H25-G25)/G25,"-") -> 0.25239617 | J25: ='KPI´s de negocio 2025'!AB12 -> 798 | K25: ='KPI´s de negocio 2026'!V12 -> 1023 | L25: =IFERROR((K25-J25)/J25,"-") -> 0.28195489 | M25: ='KPI´s de negocio 2025'!AH12 -> 702 | N25: ='KPI´s de negocio 2026'!AB12 -> 688 | O25: =IFERROR((N25-M25)/M25,"-") -> -0.01994302 | P25: ='KPI´s de negocio 2025'!AM12 -> 916 | Q25: ='KPI´s de negocio 2026'!AG12 -> 579 | R25: =IFERROR((Q25-P25)/P25,"-") -> -0.36790393
B26: EDP Pagados (Ingreso Op.) | C26: # | D26: ='KPI´s de negocio 2025'!R13 -> 22 | E26: ='KPI´s de negocio 2026'!L13 -> 27 | F26: =IFERROR((E26-D26)/D26,"-") -> 0.22727273 | G26: ='KPI´s de negocio 2025'!W13 -> 20 | H26: ='KPI´s de negocio 2026'!Q13 -> 10 | I26: =IFERROR((H26-G26)/G26,"-") -> -0.5 | J26: ='KPI´s de negocio 2025'!AB13 -> 16 | K26: ='KPI´s de negocio 2026'!V13 -> 15 | L26: =IFERROR((K26-J26)/J26,"-") -> -0.0625 | M26: ='KPI´s de negocio 2025'!AH13 -> 12 | N26: ='KPI´s de negocio 2026'!AB13 -> 17 | O26: =IFERROR((N26-M26)/M26,"-") -> 0.41666667 | P26: ='KPI´s de negocio 2025'!AM13 -> 20 | Q26: ='KPI´s de negocio 2026'!AG13 -> 10 | R26: =IFERROR((Q26-P26)/P26,"-") -> -0.5
B27: EDP Pagados (Ingreso Op.) | C27: kUS$ | D27: ='KPI´s de negocio 2025'!R14 -> 724 | E27: ='KPI´s de negocio 2026'!L14 -> 1645 | F27: =IFERROR((E27-D27)/D27,"-") -> 1.2720994 | G27: ='KPI´s de negocio 2025'!W14 -> 932 | H27: ='KPI´s de negocio 2026'!Q14 -> 239 | I27: =IFERROR((H27-G27)/G27,"-") -> -0.74356223 | J27: ='KPI´s de negocio 2025'!AB14 -> 780 | K27: ='KPI´s de negocio 2026'!V14 -> 422 | L27: =IFERROR((K27-J27)/J27,"-") -> -0.45897436 | M27: ='KPI´s de negocio 2025'!AH14 -> 601 | N27: ='KPI´s de negocio 2026'!AB14 -> 472 | O27: =IFERROR((N27-M27)/M27,"-") -> -0.21464226 | P27: ='KPI´s de negocio 2025'!AM14 -> 628 | Q27: ='KPI´s de negocio 2026'!AG14 -> 426 | R27: =IFERROR((Q27-P27)/P27,"-") -> -0.32165605
... B29: Cumplimiento POM vs EDP | C29: % | D29: ='KPI´s de negocio 2025'!R16 -> 0.93175487 | E29: ='KPI´s de negocio 2026'!L16 -> 0.56244166 | F29: =IFERROR((E29-D29)/D29,"-") -> -0.39636306 | G29: ='KPI´s de negocio 2025'!W16 -> 1.021764 | H29: ='KPI´s de negocio 2026'!Q16 -> 0.77854983 | I29: =IFERROR((H29-G29)/G29,"-") -> -0.23803363 | J29: ='KPI´s de negocio 2025'!AB16 -> 0.85573366 | K29: ='KPI´s de negocio 2026'!V16 -> 1.7234966 | L29: =IFERROR((K29-J29)/J29,"-") -> 1.0140573 | M29: ='KPI´s de negocio 2025'!AH16 -> 1.1522095 | N29: ='KPI´s de negocio 2026'!AB16 -> 0.97252747 | O29: =IFERROR((N29-M29)/M29,"-") -> -0.15594562 | P29: ='KPI´s de negocio 2025'!AM16 -> 0.87529976 | Q29: ='KPI´s de negocio 2026'!AG16 -> 0.7991453 | R29: =IFERROR((Q29-P29)/P29,"-") -> -0.087003864
B31: 2. ACUMULADO ENERO – MAYO
B33: KPI | C33: Unidad | D33: Acum. 2025 | E33: Acum. 2026 | F33: Δ Abs. | G33: Δ% | H33: Media 25 | I33: Media 26
B34: Propuestas Emitidas | C34: # | D34: =D16+G16+J16+M16+P16 -> 55 | E34: =E16+H16+K16+N16+Q16 -> 83 | F34: =E34-D34 -> 28 | G34: =IFERROR((E34-D34)/D34,"-") -> 0.50909091 | H34: =D34/5 -> 11 | I34: =E34/5 -> 16.6
B35: Propuestas Emitidas | C35: kUS$ | D35: =D17+G17+J17+M17+P17 -> 18317 | E35: =E17+H17+K17+N17+Q17 -> 16207.685 | F35: =E35-D35 -> -2109.315 | G35: =IFERROR((E35-D35)/D35,"-") -> -0.11515614 | H35: =D35/5 -> 3663.4 | I35: =E35/5 -> 3241.537
B36: Propuestas Adjudicadas | C36: # | D36: =D18+G18+J18+M18+P18 -> 33 | E36: =E18+H18+K18+N18+Q18 -> 34 | F36: =E36-D36 -> 1 | G36: =IFERROR((E36-D36)/D36,"-") -> 0.03030303 | H36: =D36/5 -> 6.6 | I36: =E36/5 -> 6.8
B37: Propuestas Adjudicadas | C37: kUS$ | D37: =D19+G19+J19+M19+P19 -> 5020 | E37: =E19+H19+K19+N19+Q19 -> 4050.92 | F37: =E37-D37 -> -969.08 | G37: =IFERROR((E37-D37)/D37,"-") -> -0.19304382 | H37: =D37/5 -> 1004 | I37: =E37/5 -> 810.184
B38: POM | C38: # | D38: =D20+G20+J20+M20+P20 -> 94 | E38: =E20+H20+K20+N20+Q20 -> 96 | F38: =E38-D38 -> 2 | G38: =IFERROR((E38-D38)/D38,"-") -> 0.021276596 | H38: =D38/5 -> 18.8 | I38: =E38/5 -> 19.2
B39: POM | C39: kUS$ | D39: =D21+G21+J21+M21+P21 -> 3847 | E39: =E21+H21+K21+N21+Q21 -> 3590.6089 | F39: =E39-D39 -> -256.3911 | G39: =IFERROR((E39-D39)/D39,"-") -> -0.066647023 | H39: =D39/5 -> 769.4 | I39: =E39/5 -> 718.12178
B40: EDP Emitidos | C40: # | D40: =D22+G22+J22+M22+P22 -> 87 | E40: =E22+H22+K22+N22+Q22 -> 86 | F40: =E40-D40 -> -1 | G40: =IFERROR((E40-D40)/D40,"-") -> -0.011494253 | H40: =D40/5 -> 17.4 | I40: =E40/5 -> 17.2
B41: EDP Emitidos | C41: kUS$ | D41: =D23+G23+J23+M23+P23 -> 3689 | E41: =E23+H23+K23+N23+Q23 -> 3598.2507 | F41: =E41-D41 -> -90.74929 | G41: =IFERROR((E41-D41)/D41,"-") -> -0.02459997 | H41: =D41/5 -> 737.8 | I41: =E41/5 -> 719.65014
B42: EDP Facturados | C42: # | D42: =D24+G24+J24+M24+P24 -> 85 | E42: =E24+H24+K24+N24+Q24 -> 76 | F42: =E42-D42 -> -9 | G42: =IFERROR((E42-D42)/D42,"-") -> -0.10588235 | H42: =D42/5 -> 17 | I42: =E42/5 -> 15.2
B43: EDP Facturados | C43: kUS$ | D43: =D25+G25+J25+M25+P25 -> 3552 | E43: =E25+H25+K25+N25+Q25 -> 3134.4487 | F43: =E43-D43 -> -417.55128 | G43: =IFERROR((E43-D43)/D43,"-") -> -0.11755385 | H43: =D43/5 -> 710.4 | I43: =E43/5 -> 626.88974
B44: EDP Pagados (Ingreso Op.) | C44: # | D44: =D26+G26+J26+M26+P26 -> 90 | E44: =E26+H26+K26+N26+Q26 -> 79 | F44: =E44-D44 -> -11 | G44: =IFERROR((E44-D44)/D44,"-") -> -0.12222222 | H44: =D44/5 -> 18 | I44: =E44/5 -> 15.8
B45: EDP Pagados (Ingreso Op.) | C45: kUS$ | D45: =D27+G27+J27+M27+P27 -> 3665 | E45: =E27+H27+K27+N27+Q27 -> 3204 | F45: =E45-D45 -> -461 | G45: =IFERROR((E45-D45)/D45,"-") -> -0.12578445 | H45: =D45/5 -> 733 | I45: =E45/5 -> 640.8
B46: Gasto Operacional | C46: kUS$ | D46: =D28+G28+J28+M28+P28 -> 2565 | E46: =E28+H28+K28+N28+Q28 -> 2954 | F46: =E46-D46 -> 389 | G46: =IFERROR((E46-D46)/D46,"-") -> 0.15165692 | H46: =D46/5 -> 513 | I46: =E46/5 -> 590.8
B47: Cumplimiento POM vs EDP | C47: % | D47: =AVERAGE(D29,G29,J29,M29,P29) -> 0.96735236 | E47: =AVERAGE(E29,H29,K29,N29,Q29) -> 0.96723218 | F47: =E47-D47 -> -0.00012018408 | G47: =IFERROR((E47-D47)/D47,"-") -> -0.00012424023
B49: 3. ANÁLISIS ESTADÍSTICO (kUS$ mensuales, Ene–May)
B51: KPI (kUS$) | C51: Año | D51: Media | E51: Desv. Est. (σ) | F51: CV (%) | G51: Mínimo | H51: Máximo | I51: Rango | J51: Tendencia
B52: Propuestas Emitidas | C52: 2025 | D52: =AVERAGE(D17,G17,J17,M17,P17) -> 3663.4 | E52: =STDEV(D17,G17,J17,M17,P17) -> 1604.7544 | F52: =IFERROR(E52/D52,"-") -> 0.43805056 | G52: =MIN(D17,G17,J17,M17,P17) -> 2212 | H52: =MAX(D17,G17,J17,M17,P17) -> 6130 | I52: =H52-G52 -> 3918 | J52: =(P17-D17)/4 -> 203.5
C53: 2026 | D53: =AVERAGE(E17,H17,K17,N17,Q17) -> 3241.537 | E53: =STDEV(E17,H17,K17,N17,Q17) -> 817.80484 | F53: =IFERROR(E53/D53,"-") -> 0.25228922 | G53: =MIN(E17,H17,K17,N17,Q17) -> 2370 | H53: =MAX(E17,H17,K17,N17,Q17) -> 4175 | I53: =H53-G53 -> 1805 | J53: =(Q17-E17)/4 -> 36.17125
B54: Prop. Adjudicadas | C54: 2025 | D54: =AVERAGE(D19,G19,J19,M19,P19) -> 1004 | E54: =STDEV(D19,G19,J19,M19,P19) -> 183.36303 | F54: =IFERROR(E54/D54,"-") -> 0.1826325 | G54: =MIN(D19,G19,J19,M19,P19) -> 736 | H54: =MAX(D19,G19,J19,M19,P19) -> 1246 | I54: =H54-G54 -> 510 | J54: =(P19-D19)/4 -> -22
C55: 2026 | D55: =AVERAGE(E19,H19,K19,N19,Q19) -> 810.184 | E55: =STDEV(E19,H19,K19,N19,Q19) -> 438.90114 | F55: =IFERROR(E55/D55,"-") -> 0.5417302 | G55: =MIN(E19,H19,K19,N19,Q19) -> 371 | H55: =MAX(E19,H19,K19,N19,Q19) -> 1406 | I55: =H55-G55 -> 1035 | J55: =(Q19-E19)/4 -> -98.52
B56: EDP Emitidos | C56: 2025 | D56: =AVERAGE(D23,G23,J23,M23,P23) -> 737.8 | E56: =STDEV(D23,G23,J23,M23,P23) -> 88.928061 | F56: =IFERROR(E56/D56,"-") -> 0.12053139 | G56: =MIN(D23,G23,J23,M23,P23) -> 669 | H56: =MAX(D23,G23,J23,M23,P23) -> 892 | I56: =H56-G56 -> 223 | J56: =(P23-D23)/4 -> 15.25
C57: 2026 | D57: =AVERAGE(E23,H23,K23,N23,Q23) -> 719.65014 | E57: =STDEV(E23,H23,K23,N23,Q23) -> 408.3125 | F57: =IFERROR(E57/D57,"-") -> 0.56737639 | G57: =MIN(E23,H23,K23,N23,Q23) -> 319.25071 | H57: =MAX(E23,H23,K23,N23,Q23) -> 1404 | I57: =H57-G57 -> 1084.7493 | J57: =(Q23-E23)/4 -> 60.437323
B58: EDP Facturados | C58: 2025 | D58: =AVERAGE(D25,G25,J25,M25,P25) -> 710.4 | E58: =STDEV(D25,G25,J25,M25,P25) -> 234.85166 | F58: =IFERROR(E58/D58,"-") -> 0.33059073 | G58: =MIN(D25,G25,J25,M25,P25) -> 313 | H58: =MAX(D25,G25,J25,M25,P25) -> 916 | I58: =H58-G58 -> 603 | J58: =(P25-D25)/4 -> 23.25
C59: 2026 | D59: =AVERAGE(E25,H25,K25,N25,Q25) -> 626.88974 | E59: =STDEV(E25,H25,K25,N25,Q25) -> 249.26597 | F59: =IFERROR(E59/D59,"-") -> 0.3976233 | G59: =MIN(E25,H25,K25,N25,Q25) -> 392 | H59: =MAX(E25,H25,K25,N25,Q25) -> 1023 | I59: =H59-G59 -> 631 | J59: =(Q25-E25)/4 -> 31.63782
B60: Ingreso Operacional | C60: 2025 | D60: =AVERAGE(D27,G27,J27,M27,P27) -> 733 | E60: =STDEV(D27,G27,J27,M27,P27) -> 132.60845 | F60: =IFERROR(E60/D60,"-") -> 0.18091193 | G60: =MIN(D27,G27,J27,M27,P27) -> 601 | H60: =MAX(D27,G27,J27,M27,P27) -> 932 | I60: =H60-G60 -> 331 | J60: =(P27-D27)/4 -> -24
C61: 2026 | D61: =AVERAGE(E27,H27,K27,N27,Q27) -> 640.8 | E61: =STDEV(E27,H27,K27,N27,Q27) -> 568.41156 | F61: =IFERROR(E61/D61,"-") -> 0.88703427 | G61: =MIN(E27,H27,K27,N27,Q27) -> 239 | H61: =MAX(E27,H27,K27,N27,Q27) -> 1645 | I61: =H61-G61 -> 1406 | J61: =(Q27-E27)/4 -> -304.75
B62: Gasto Operacional | C62: 2025 | D62: =AVERAGE(D28,G28,J28,M28,P28) -> 513 | E62: =STDEV(D28,G28,J28,M28,P28) -> 24.799194 | F62: =IFERROR(E62/D62,"-") -> 0.048341508 | G62: =MIN(D28,G28,J28,M28,P28) -> 477 | H62: =MAX(D28,G28,J28,M28,P28) -> 536 | I62: =H62-G62 -> 59 | J62: =(P28-D28)/4 -> 14.25
C63: 2026 | D63: =AVERAGE(E28,H28,K28,N28,Q28) -> 590.8 | E63: =STDEV(E28,H28,K28,N28,Q28) -> 71.443684 | F63: =IFERROR(E63/D63,"-") -> 0.12092702 | G63: =MIN(E28,H28,K28,N28,Q28) -> 543 | H63: =MAX(E28,H28,K28,N28,Q28) -> 715 | I63: =H63-G63 -> 172 | J63: =(Q28-E28)/4 -> -43
B65: 4. VISUALIZACIÓN COMPARATIVA
B106: Datos gráficas
B107: Mes | C107: Adj. 25 | D107: Adj. 26 | F107: Mes | G107: Cumpl. 25 | H107: Cumpl. 26 | J107: Mes | K107: Ing. Op. 25 | L107: Ing. Op. 26 | N107: Mes | O107: Gasto Op. 25 | P107: Gasto Op. 26
B108: Ene | C108: =D19 -> 1056 | D108: =E19 -> 804 | F108: Ene | G108: =D29 -> 0.93175487 | H108: =E29 -> 0.56244166 | J108: Ene | K108: =D27 -> 724 | L108: =E27 -> 1645 | N108: Ene | O108: =D28 -> 477 | P108: =E28 -> 715
B109: Feb | C109: =G19 -> 1246 | D109: =H19 -> 371 | F109: Feb | G109: =G29 -> 1.021764 | H109: =H29 -> 0.77854983 | J109: Feb | K109: =G27 -> 932 | L109: =H27 -> 239 | N109: Feb | O109: =G28 -> 500 | P109: =H28 -> 565
B110: Mar | C110: =J19 -> 736 | D110: =K19 -> 1406 | F110: Mar | G110: =J29 -> 0.85573366 | H110: =K29 -> 1.7234966 | J110: Mar | K110: =J27 -> 780 | L110: =K27 -> 422 | N110: Mar | O110: =J28 -> 536 | P110: =K28 -> 546
B111: Abr | C111: =M19 -> 1014 | D111: =N19 -> 1060 | F111: Abr | G111: =M29 -> 1.1522095 | H111: =N29 -> 0.97252747 | J111: Abr | K111: =M27 -> 601 | L111: =N27 -> 472 | N111: Abr | O111: =M28 -> 518 | P111: =N28 -> 585
B112: May | C112: =P19 -> 968 | D112: =Q19 -> 409.92 | F112: May | G112: =P29 -> 0.87529976 | H112: =Q29 -> 0.7991453 | J112: May | K112: =P27 -> 628 | L112: =Q27 -> 426 | N112: May | O112: =P28 -> 534 | P112: =Q28 -> 543

Sheet Dashboard 2026
B1: DASHBOARD EJECUTIVO — KPIs DE NEGOCIO 2026
B2: REDCO Mining Consultants · Actualización Abril 2026
B4: INDICADORES DE CANTIDAD (#)
B5: PROPUESTAS ADJUDICADAS | D5: POM | F5: EDP EMITIDOS | H5: EDP FACTURADOS | J5: EDP PAGADOS | L5: GASTO | N5: CUMPLIMIENTO | P5: ADHERENCIA
B6: ='KPI´s de negocio 2026'!BU5 -> 34 | D6: ='KPI´s de negocio 2026'!BU7 -> 109 | F6: ='KPI´s de negocio 2026'!BU9 -> 86 | H6: ='KPI´s de negocio 2026'!BU11 -> 77 | J6: ='KPI´s de negocio 2026'!BU13 -> 82 | L6: - | N6: - | P6: -
B7: ="vs 2025: "&TEXT('KPI´s de negocio 2026'!F5,"#.##0") -> vs 2025: 78 | D7: ="vs 2025: "&TEXT('KPI´s de negocio 2026'!F7,"#.##0") -> vs 2025: 222 | F7: ="vs 2025: "&TEXT('KPI´s de negocio 2026'!F9,"#.##0") -> vs 2025: 204 | H7: ="vs 2025: "&TEXT('KPI´s de negocio 2026'!F11,"#.##0") -> vs 2025: 219 | J7: ="vs 2025: "&TEXT('KPI´s de negocio 2026'!F13,"#.##0") -> vs 2025: 216
B8: INDICADORES DE MONTO (kUS$)
B9: PROPUESTAS ADJUDICADAS | D9: POM | F9: EDP EMITIDOS | H9: EDP FACTURADOS | J9: EDP PAGADOS | L9: GASTO | N9: CUMPLIMIENTO | P9: ADHERENCIA
B10: ='KPI´s de negocio 2026'!BU6 -> 4050.92 | D10: ='KPI´s de negocio 2026'!BU8 -> 4206.6089 | F10: ='KPI´s de negocio 2026'!BU10 -> 3598.2507 | H10: ='KPI´s de negocio 2026'!BU12 -> 3210.4487 | J10: ='KPI´s de negocio 2026'!BU14 -> 3253 | L10: - | N10: - | P10: -
B11: ="vs 2025: kUS$ "&TEXT(ROUND('KPI´s de negocio 2026'!F6,0),"#.##0") -> vs 2025: kUS$ 10.276 | D11: ="vs 2025: kUS$ "&TEXT(ROUND('KPI´s de negocio 2026'!F8,0),"#.##0") -> vs 2025: kUS$ 9.037 | F11: ="vs 2025: kUS$ "&TEXT(ROUND('KPI´s de negocio 2026'!F10,0),"#.##0") -> vs 2025: kUS$ 9.353 | H11: ="vs 2025: kUS$ "&TEXT(ROUND('KPI´s de negocio 2026'!F12,0),"#.##0") -> vs 2025: kUS$ 9.795 | J11: ="vs 2025: kUS$ "&TEXT(ROUND('KPI´s de negocio 2026'!F14,0),"#.##0") -> vs 2025: kUS$ 9.025
B13: TENDENCIAS MENSUALES
B53: — Datos fuente (no modificar) —
B54: Mes | C54: POM (#) | D54: EDP Emitidos (#) | E54: EDP Facturados (#) | F54: EDP Pagados (#) | H54: Mes | I54: POM (kUS$) | K54: Categoría | L54: kUS$ | N54: Mes | O54: EDP Emitidos (kUS$) | P54: EDP Facturados (kUS$) | Q54: EDP Pagados (kUS$)
B55: Ene | C55: ='KPI´s de negocio 2026'!L7 -> 16 | D55: ='KPI´s de negocio 2026'!L9 -> 10 | E55: ='KPI´s de negocio 2026'!L11 -> 12 | F55: ='KPI´s de negocio 2026'!L13 -> 27 | H55: Ene | I55: ='KPI´s de negocio 2026'!L8 -> 567.61569 | K55: Ingreso Operacional | L55: ='KPI´s de negocio 2026'!CB3 -> 3253 | N55: Ene | O55: ='KPI´s de negocio 2026'!L10 -> 319.25071 | P55: ='KPI´s de negocio 2026'!L12 -> 452.44872 | Q55: ='KPI´s de negocio 2026'!L14 -> 1645
B56: Feb | C56: ='KPI´s de negocio 2026'!Q7 -> 15 | D56: ='KPI´s de negocio 2026'!Q9 -> 17 | E56: ='KPI´s de negocio 2026'!Q11 -> 12 | F56: ='KPI´s de negocio 2026'!Q13 -> 10 | H56: Feb | I56: ='KPI´s de negocio 2026'!Q8 -> 778.37022 | K56: Facturas por cobrar | L56: ='KPI´s de negocio 2026'!CB4 -> 1517 | N56: Feb | O56: ='KPI´s de negocio 2026'!Q10 -> 606 | P56: ='KPI´s de negocio 2026'!Q12 -> 392 | Q56: ='KPI´s de negocio 2026'!Q14 -> 239
B57: Mar | C57: ='KPI´s de negocio 2026'!V7 -> 19 | D57: ='KPI´s de negocio 2026'!V9 -> 20 | E57: ='KPI´s de negocio 2026'!V11 -> 16 | F57: ='KPI´s de negocio 2026'!V13 -> 15 | H57: Mar | I57: ='KPI´s de negocio 2026'!V8 -> 814.623 | K57: EDP por facturar | L57: ='KPI´s de negocio 2026'!CB5 -> 815 | N57: Mar | O57: ='KPI´s de negocio 2026'!V10 -> 1404 | P57: ='KPI´s de negocio 2026'!V12 -> 1023 | Q57: ='KPI´s de negocio 2026'!V14 -> 422
B58: Abr | C58: ='KPI´s de negocio 2026'!AB7 -> 26 | D58: ='KPI´s de negocio 2026'!AB9 -> 21 | E58: ='KPI´s de negocio 2026'!AB11 -> 21 | F58: ='KPI´s de negocio 2026'!AB13 -> 17 | H58: Abr | I58: ='KPI´s de negocio 2026'!AB8 -> 728 | N58: Abr | O58: ='KPI´s de negocio 2026'!AB10 -> 708 | P58: ='KPI´s de negocio 2026'!AB12 -> 688 | Q58: ='KPI´s de negocio 2026'!AB14 -> 472

Sheet Vasos comunicantes
T1: Flujo de Efectivo REDCO: Vasos Comunicantes
T3: Etapa | U3: Monto (kUS$) | V3: Tipo | X3: Concepto | Y3: kUS$
T4: 0. Remanente Contratos | U4: 2680 | V4: Base | X4: Proyectado (POM) | Y4: 634
T5: 1. Proyectado actual (POM) | U5: -634 | V5: Flujo en proceso | X5: Emitido por aprobar | Y5: 777
T6: 2. Emitido por aprobar | U6: -777 | V6: Flujo en proceso | X6: Aprobado por facturar | Y6: 0
T7: 3. Aprobado por facturar | U7: 0 | V7: Flujo en proceso | X7: Facturado por pagar | Y7: 847
T8: 4. Facturado por pagar | U8: -847 | V8: Flujo en proceso | X8: Ingreso proy. mayo | Y8: 845
T9: 5. Ingreso acumulado | U9: 2770 | V9: Subtotal | X9: Ingreso acumulado | Y9: 2770
T10: Ingreso proyectado mayo | U10: 845 | V10: Incremento
T11: Ingreso Operacional Efectivo | U11: 3620 | V11: Total
X14: NOTAS:
X15: • Venta proyectada: 1,55 MUS$
X16: • Flujo en cañería (Etapas 2+3+4): 1,62 MUSD
X17: • No considera Seligdar (+1,34 MUSD)
X18: • Monto remanente al 30/04, incluye adjudicación Xavantina
X19: • No considera retenciones de CMP pendientes < 40 kUS$
B41: Flujo de Efectivo REDCO — Vasos Comunicantes | L41: Mayo 2026 | Cifras en kUS$
B44: REMANENTE CONTRATOS | E44: FLUJO EN CAÑERÍA | H44: INGRESO ACUMULADO | K44: INGRESO OPERACIONAL
B45: 2680 | E45: 1624 | H45: 2770 | K45: 3615
B46: kUS$ (saldo al 30/04) | E46: kUS$ (etapas 1-4) | H46: kUS$ (cobrado) | K46: kUS$ (meta caja)
B48: Etapa | C48: Descripción | E48: kUS$ | F48: % Remanente | H48: Concepto | K48: kUS$
B49: 0 | C49: Remanente Contratos | E49: 2680 | H49: Ingreso acumulado | K49: 2770
B50: 1 | C50: Proyectado actual (POM) | E50: 634 | F50: =E50/$E$49 -> 0.23656716 | H50: (+) Ingreso proy. mayo | K50: 845
B51: 2 | C51: Emitido por aprobar | E51: 777 | F51: =E51/$E$49 -> 0.28992537
B52: 3 | C52: Aprobado por facturar | E52: 0 | F52: =E52/$E$49 -> 0
B53: 4 | C53: Facturado por pagar | E53: 847 | F53: =E53/$E$49 -> 0.31604478
C54: Flujo en cañería (1+2+3+4) | E54: =SUM(E50:E53) -> 2258 | F54: =E54/$E$49 -> 0.84253731 | H54: Ingreso Operacional | K54: =K49+K50 -> 3615
B59: • Venta proyectada: 1,55 MUS$ • Flujo en cañería (Etapas 2+3+4): 1,62 MUSD • No considera Seligdar (+1,34 MUSD)
B60: • Monto remanente al 30/04, incluye adjudicación Xavantina • No considera retenciones CMP pendientes < 40 kUS$
B63: REDCO — Gerencia de Operaciones | M63: Confidencial
