Workbook

Sheet Formato reporte EDP_2024
B10: Nombre fantasía | C10: Cliente | D10: Nombre Proyecto | E10: Director | F10: Ing Principal | G10: Real | H10: Otros | J10: EDP Real | K10: EDP POM | L10: EDP Curva S | M10: Dif. USD | N10: Var. % | O10: Saldo Actual | P10: Saldo Proy | Q10: Comentarios | R10: Tipo 1 | S10: Tipo 2 | T10: Estatus
B11: Gran total | C11: Gran total | D11: Gran total | E11: Todos | F11: Todos | G11: =+SUM(G12:G13) -> 985703.15 | H11: =+SUM(H12:H13) -> 0 | I11: =+SUM(G11:H11) -> 985703.15 | J11: =+SUM(J12:J13) -> 985703.15 | K11: =+SUM(K12:K13) -> 550910.74 | L11: =+SUM(L12:L13) -> 1054085.7 | M11: =+J11-L11 -> -68382.556 | N11: =+IFERROR(((J11-L11)/L11),0) -> -0.064873811 | O11: =+SUM(O12:O13) -> 267749.45 | P11: =+O11-L11 -> -786336.25 | R11: Todos | S11: Todos | T11: Todos | U11: =+I11=J11 -> TRUE
B12: En Proceso | C12: En Proceso | D12: En Proceso | E12: En Proceso | F12: En Proceso | G12: =+IF($B12="En Proceso",1*SUMIF($T21:$T10018,$B12,$G21:$G10018),0) -> 945703.15 | H12: =+IF($B12="En Proceso",1*SUMIF($T21:$T10018,$B12,$H21:$H10018),0) -> 0 | I12: =+SUM(G12:H12) -> 945703.15 | J12: =+G12+H12 -> 945703.15 | K12: =+IF(B12="En proceso",SUMIF(T17:T1018,B12,K$17:K$1048576),0) -> 550910.74 | L12: =+IF(B12="En proceso",SUMIF(T17:T1018,B12,L$17:L$1048576),0) -> 1054085.7 | M12: =+J12-L12 -> -108382.56 | N12: =+IFERROR(((J12-L12)/L12),0) -> -0.10282139 | O12: =+IF($B12="En Proceso",1*SUMIF(T21:T10018,$B12,O21:O10018),0) -> 261703.47 | P12: =+O12-L12 -> -792382.23 | R12: En Proceso | S12: En Proceso | T12: En Proceso | U12: =+I12=J12 -> TRUE | X12: SI($B12="En Proceso";SUMAR.SI($P:$P;$B12;$I:$I);0)
B13: Terminado | C13: Terminado | D13: Terminado | E13: Terminado | F13: Terminado | G13: =+IF($B13="Terminado",1*SUMIF($T21:$T10018,$B13,$G21:$G10018),0) -> 40000 | H13: =+IF($B13="Terminado",1*SUMIF($T21:$T10018,$B13,$H21:$H10018),0) -> 0 | I13: =+SUM(G13:H13) -> 40000 | J13: =+G13+H13 -> 40000 | K13: =+IF(B13="Terminado",SUMIF(T20:T1018,B13,K$20:K$1048576),0) -> 0 | L13: =+IF(B13="Terminado",SUMIF(T20:T1018,B13,L$20:L$1048576),0) -> 0 | M13: =+J13-L13 -> 40000 | N13: =+IFERROR(((J13-L13)/L13),0) -> 0 | O13: =+IF($B13="Terminado",1*SUMIF(T21:T10018,$B13,O21:O10018),0) -> 6045.98 | P13: =+O13-L13 -> 6045.98 | R13: Terminado | S13: Terminado | T13: Terminado | U13: =+I13=J13 -> TRUE
B14: Ejecución | C14: Ejecución | D14: Ejecución | E14: Ejecución | F14: Ejecución | G14: =+IF($B14="Ejecución",1*SUMIF($S21:$S10018,$B14,$G21:$G10018),0) -> 887997.15 | H14: =+IF($B14="Ejecución",1*SUMIF($S21:$S10018,$B14,$H21:$H10018),0) -> 0 | I14: =+SUM(G14:H14) -> 887997.15 | J14: =+G14+H14 -> 887997.15 | K14: =+IF(B14="Ejecución",SUMIF(S20:S1020,B14,K$20:K$1048576),0) -> 550910.74 | L14: =+IF(B14="Ejecución",SUMIF(S20:S1020,B14,L$20:L$1048576),0) -> 1006721.6 | M14: =+J14-L14 -> -118724.47 | N14: =+IFERROR(((J14-L14)/L14),0) -> -0.11793178 | O14: =+IF($B14="Ejecución",1*SUMIF(S21:S10018,$B14,O21:O10018),0) -> 258208.39 | P14: =+O14-L14 -> -748513.23 | R14: Ejecución | S14: Ejecución | T14: Ejecución | U14: =+I14=J14 -> TRUE
B15: Terminal | C15: Terminal | D15: Terminal | E15: Terminal | F15: Terminal | G15: =+IF($B15="Terminal",1*SUMIF($S21:$S10018,$B15,$G21:$G10018),0) -> 57706 | H15: =+IF($B15="Terminal",1*SUMIF($S21:$S10018,$B15,$H21:$H10018),0) -> 0 | I15: =+SUM(G15:H15) -> 57706 | J15: =+G15+H15 -> 57706 | K15: =+IF(B15="Terminal",SUMIF(S20:S1021,B15,K$20:K$1048576),0) -> 0 | L15: =+IF(B15="Terminal",SUMIF(S20:S1021,B15,L$20:L$1048576),0) -> 47364.082 | M15: =+J15-L15 -> 10341.918 | N15: =+IFERROR(((J15-L15)/L15),0) -> 0.21834939 | O15: =+IF($B15="Terminal",1*SUMIF(S21:S10018,$B15,O21:O10018),0) -> 3495.0816 | P15: =+O15-L15 -> -43869 | R15: Terminal | S15: Terminal | T15: Terminal | U15: =+I15=J15 -> TRUE
B16: Rezagado | C16: Rezagado | D16: Rezagado | E16: Rezagado | F16: Rezagado | G16: =+IF($B16="Rezagado",1*SUMIF($S21:$S10018,$B16,$G21:$G10018),0) -> 40000 | H16: =+IF($B16="Rezagado",1*SUMIF($S21:$S10018,$B16,$H21:$H10018),0) -> 0 | I16: =+SUM(G16:H16) -> 40000 | J16: =+G16+H16 -> 40000 | K16: =+IF(B16="Rezagado",SUMIF(S20:S1022,B16,K$20:K$1048576),0) -> 0 | L16: =+IF(B16="Rezagado",SUMIF(S20:S1022,B16,L$20:L$1048576),0) -> 0 | M16: =+J16-L16 -> 40000 | N16: =+IFERROR(((J16-L16)/L16),0) -> 0 | O16: =+IF($B16="Rezagado",1*SUMIF(S21:S10018,$B16,O21:O10018),0) -> 6045.98 | P16: =+O16-L16 -> 6045.98 | R16: Rezagado | S16: Rezagado | T16: Rezagado | U16: =+I16=J16 -> TRUE
C20: =+C10 -> Cliente | D20: =+D10 -> Nombre Proyecto | E20: =+E10 -> Director | F20: =+F10 -> Ing Principal | G20: =+G10 -> Real | H20: =+H10 -> Otros | I20: =+I10 -> 0 | J20: =+J10 -> EDP Real | ... Q20: =+Q10 -> Comentarios | R20: Tipo 1 | S20: Tipo 2 | T20: Estatus
B21: Mosaic_Cajati | C21: =+_xlfn.XLOOKUP(B21,'[1]Proyectos (NO FILTRAR)'!$F:$F,'[1]Proyectos (NO FILTRAR)'!$I:$I) -> Mosaic | D21: Modelo geomecanico de esfuerzos + FS P1 y PFS P2 - Mina Cajati | E21: =+_xlfn.XLOOKUP(B21,'POM 2024'!B:B,'POM 2024'!F:F,"!",0,1) -> Alex Figueroa | F21: =+_xlfn.XLOOKUP(B21,'POM 2024'!B:B,'POM 2024'!H:H,"!",0,1) -> Pablo Quiero | G21: =+J21 -> 15442 | H21: 0 | I21: =+SUM(G21:H21) -> 15442 | J21: =VLOOKUP(B21,'POM 2024'!$B$2:$BI$64,48,FALSE) -> 15442 | K21: =+_xlfn.XLOOKUP($B21,'POM 2024'!B:B,'POM 2024'!AV:AV,"!",0,1) -> 22988.54 | L21: =+_xlfn.XLOOKUP($B21,'POM 2024'!B:B,'POM 2024'!AU:AU,"!",0,1) -> 22988.54 | M21: =+J21-L21 -> -7546.54 | N21: =+IFERROR(((J21-K21)/K21),0) -> -0.328274 | O21: =IF(_xlfn.XLOOKUP($B21,'POM 2024'!B:B,'POM 2024'!L:L,"!",0,1)<0,0,_xlfn.XLOOKUP($B21,'POM 2024'!B:B,'POM 2024'!L:L,"!",0,1)) -> 7546.54 | P21: =+O21-L21 -> -15442 | R21: Técnico | S21: Ejecución | T21: En Proceso | U21: =+I21=J21 -> TRUE
B22: CMP_Los Colorados Adelantamiento Planta | C22: =+_xlfn.XLOOKUP(B22,'[1]Proyectos (NO FILTRAR)'!$F:$F,'[1]Proyectos (NO FILTRAR)'!$I:$I) -> CMP | D22: Adelantamiento Planta Los Colorados | E22: =+_xlfn.XLOOKUP(B22,'POM 2024'!B:B,'POM 2024'!F:F,"!",0,1) -> Alex Figueroa | F22: =+_xlfn.XLOOKUP(B22,'POM 2024'!B:B,'POM 2024'!H:H,"!",0,1) -> Felipe Matamoros | G22: =+J22 -> 0 | H22: 0 | I22: =+SUM(G22:H22) -> 0 | J22: =VLOOKUP(B22,'POM 2024'!$B$2:$BI$64,48,FALSE) -> 0 | K22: =+_xlfn.XLOOKUP($B22,'POM 2024'!B:B,'POM 2024'!AV:AV,"!",0,1) -> 0 | L22: =+_xlfn.XLOOKUP($B22,'POM 2024'!B:B,'POM 2024'!AU:AU,"!",0,1) -> 0 | M22: =+J22-L22 -> 0 | N22: =+IFERROR(((J22-K22)/K22),0) -> 0 | O22: =IF(_xlfn.XLOOKUP($B22,'POM 2024'!B:B,'POM 2024'!L:L,"!",0,1)<0,0,_xlfn.XLOOKUP($B22,'POM 2024'!B:B,'POM 2024'!L:L,"!",0,1)) -> 0 | P22: =+O22-L22 -> 0 | R22: Técnico | S22: Ejecución | T22: En Proceso | U22: =+I22=J22 -> TRUE
B23: CSH_LOM Mina Guarello | C23: Siderúrgica Huachipato | D23: Plan de largo plazo Mina Guarello | E23: =+_xlfn.XLOOKUP(B23,'POM 2024'!B:B,'POM 2024'!F:F,"!",0,1) -> Matias Fuentes | F23: =+_xlfn.XLOOKUP(B23,'POM 2024'!B:B,'POM 2024'!H:H,"!",0,1) -> TBD | G23: =+J23 -> 19065 | H23: 0 | I23: =+SUM(G23:H23) -> 19065 | J23: =VLOOKUP(B23,'POM 2024'!$B$2:$BI$64,48,FALSE) -> 19065 | K23: =+_xlfn.XLOOKUP($B23,'POM 2024'!B:B,'POM 2024'!AV:AV,"!",0,1) -> 0 | L23: =+_xlfn.XLOOKUP($B23,'POM 2024'!B:B,'POM 2024'!AU:AU,"!",0,1) -> 0 | M23: =+J23-L23 -> 19065 | N23: =+IFERROR(((J23-K23)/K23),0) -> 0 | O23: =IF(_xlfn.XLOOKUP($B23,'POM 2024'!B:B,'POM 2024'!L:L,"!",0,1)<0,0,_xlfn.XLOOKUP($B23,'POM 2024'!B:B,'POM 2024'!L:L,"!",0,1)) -> 0 | P23: =+O23-L23 -> 0 | R23: Administrativo | S23: Ejecución | T23: En Proceso | U23: =+I23=J23 -> TRUE
B24: PFS Los Calatos | C24: Minera Hampton | D24: PFS Los Calatos Project | E24: =+_xlfn.XLOOKUP(B24,'POM 2024'!B:B,'POM 2024'!F:F,"!",0,1) -> Alex Figueroa | F24: =+_xlfn.XLOOKUP(B24,'POM 2024'!B:B,'POM 2024'!H:H,"!",0,1) -> Jorman Barrera | G24: =+J24 -> 85235 | H24: 0 | I24: =+SUM(G24:H24) -> 85235 | J24: =VLOOKUP(B24,'POM 2024'!$B$2:$BI$64,48,FALSE) -> 85235 | K24: =+_xlfn.XLOOKUP($B24,'POM 2024'!B:B,'POM 2024'!AV:AV,"!",0,1) -> 90000 | L24: =+_xlfn.XLOOKUP($B24,'POM 2024'!B:B,'POM 2024'!AU:AU,"!",0,1) -> 110447.1 | M24: =+J24-L24 -> -25212.1 | N24: =+IFERROR(((J24-K24)/K24),0) -> -0.052944444 | O24: =IF(_xlfn.XLOOKUP($B24,'POM 2024'!B:B,'POM 2024'!L:L,"!",0,1)<0,0,_xlfn.XLOOKUP($B24,'POM 2024'!B:B,'POM 2024'!L:L,"!",0,1)) -> 0 | P24: =+O24-L24 -> -110447.1 | R24: Técnico | S24: Ejecución | T24: En Proceso | U24: =+I24=J24 -> TRUE
B25: IvanhoeElectric_Santa-Cruz_PrePFS | C25: =+_xlfn.XLOOKUP(B25,'[1]Proyectos (NO FILTRAR)'!$F:$F,'[1]Proyectos (NO FILTRAR)'!$I:$I) -> Ivanhoe Electric | D25: Pre PFS Santa Cruz Project | E25: =+_xlfn.XLOOKUP(B25,'POM 2024'!B:B,'POM 2024'!F:F,"!",0,1) -> Matias Fuentes | F25: =+_xlfn.XLOOKUP(B25,'POM 2024'!B:B,'POM 2024'!H:H,"!",0,1) -> Carlos Morante | G25: =+J25 -> 0 | H25: 0 | I25: =+SUM(G25:H25) -> 0 | J25: =VLOOKUP(B25,'POM 2024'!$B$2:$BI$64,48,FALSE) -> 0 | K25: =+_xlfn.XLOOKUP($B25,'POM 2024'!B:B,'POM 2024'!AV:AV,"!",0,1) -> 0 | L25: =+_xlfn.XLOOKUP($B25,'POM 2024'!B:B,'POM 2024'!AU:AU,"!",0,1) -> 0 | M25: =+J25-L25 -> 0 | N25: =+IFERROR(((J25-K25)/K25),0) -> 0 | O25: =IF(_xlfn.XLOOKUP($B25,'POM 2024'!B:B,'POM 2024'!L:L,"!",0,1)<0,0,_xlfn.XLOOKUP($B25,'POM 2024'!B:B,'POM 2024'!L:L,"!",0,1)) -> 0 | P25: =+O25-L25 -> 0 | R25: Técnico | S25: Ejecución | T25: En Proceso | U25: =+I25=J25 -> TRUE
B26: LasBambas_Ferrobamba_OP_UG | C26: =+_xlfn.XLOOKUP(B26,'[1]Proyectos (NO FILTRAR)'!$F:$F,'[1]Proyectos (NO FILTRAR)'!$I:$I) -> MMG Las Bambas | D26: Ferrobamba UG Scoping Study | E26: =+_xlfn.XLOOKUP(B26,'POM 2024'!B:B,'POM 2024'!F:F,"!",0,1) -> Matias Fuentes | F26: =+_xlfn.XLOOKUP(B26,'POM 2024'!B:B,'POM 2024'!H:H,"!",0,1) -> Pablo Quiero | G26: =+J26 -> 45952 | H26: 0 | I26: =+SUM(G26:H26) -> 45952 | J26: =VLOOKUP(B26,'POM 2024'!$B$2:$BI$64,48,FALSE) -> 45952 | K26: =+_xlfn.XLOOKUP($B26,'POM 2024'!B:B,'POM 2024'!AV:AV,"!",0,1) -> 0 | L26: =+_xlfn.XLOOKUP($B26,'POM 2024'!B:B,'POM 2024'!AU:AU,"!",0,1) -> 45951.005 | M26: =+J26-L26 -> 0.9952 | N26: =+IFERROR(((J26-K26)/K26),0) -> 0 | O26: =IF(_xlfn.XLOOKUP($B26,'POM 2024'!B:B,'POM 2024'!L:L,"!",0,1)<0,0,_xlfn.XLOOKUP($B26,'POM 2024'!B:B,'POM 2024'!L:L,"!",0,1)) -> 0 | P26: =+O26-L26 -> -45951.005 | R26: Técnico | S26: Ejecución | T26: En Proceso | U26: =+I26=J26 -> TRUE
B27: CMP_Romeral Estabilización + UG PFS | C27: =+_xlfn.XLOOKUP(B27,'[1]Proyectos (NO FILTRAR)'!$F:$F,'[1]Proyectos (NO FILTRAR)'!$I:$I) -> CMP | D27: LOM Estabilizado, gestion de plan mensual, PFS UG y link con largo plazo del Valle; Mina Romeral | E27: =+_xlfn.XLOOKUP(B27,'POM 2024'!B:B,'POM 2024'!F:F,"!",0,1) -> Alex Figueroa | F27: =+_xlfn.XLOOKUP(B27,'POM 2024'!B:B,'POM 2024'!H:H,"!",0,1) -> Felipe Matamoros | G27: =+J27 -> 0 | H27: 0 | I27: =+SUM(G27:H27) -> 0 | J27: =VLOOKUP(B27,'POM 2024'!$B$2:$BI$64,48,FALSE) -> 0 | K27: =+_xlfn.XLOOKUP($B27,'POM 2024'!B:B,'POM 2024'!AV:AV,"!",0,1) -> 0 | L27: =+_xlfn.XLOOKUP($B27,'POM 2024'!B:B,'POM 2024'!AU:AU,"!",0,1) -> 88555.4 | M27: =+J27-L27 -> -88555.4 | N27: =+IFERROR(((J27-K27)/K27),0) -> 0 | O27: =IF(_xlfn.XLOOKUP($B27,'POM 2024'!B:B,'POM 2024'!L:L,"!",0,1)<0,0,_xlfn.XLOOKUP($B27,'POM 2024'!B:B,'POM 2024'!L:L,"!",0,1)) -> 0 | P27: =+O27-L27 -> -88555.4 | R27: Técnico | S27: Ejecución | T27: En Proceso | U27: =+I27=J27 -> TRUE
B28: Lundin_Candelaria_EstudiosCugep | C28: =+_xlfn.XLOOKUP(B28,'[1]Proyectos (NO FILTRAR)'!$F:$F,'[1]Proyectos (NO FILTRAR)'!$I:$I) -> Lundin | D28: Ingeniería de valor para Robustecer el Proyecto CUGEP | E28: =+_xlfn.XLOOKUP(B28,'POM 2024'!B:B,'POM 2024'!F:F,"!",0,1) -> Mauricio Melendez | F28: =+_xlfn.XLOOKUP(B28,'POM 2024'!B:B,'POM 2024'!H:H,"!",0,1) -> Freddy Diaz | G28: =+J28 -> 71980 | H28: 0 | I28: =+SUM(G28:H28) -> 71980 | J28: =VLOOKUP(B28,'POM 2024'!$B$2:$BI$64,48,FALSE) -> 71980 | K28: =+_xlfn.XLOOKUP($B28,'POM 2024'!B:B,'POM 2024'!AV:AV,"!",0,1) -> 50337.7 | L28: =+_xlfn.XLOOKUP($B28,'POM 2024'!B:B,'POM 2024'!AU:AU,"!",0,1) -> 173030 | M28: =+J28-L28 -> -101050 | N28: =+IFERROR(((J28-K28)/K28),0) -> 0.42994217 | O28: =IF(_xlfn.XLOOKUP($B28,'POM 2024'!B:B,'POM 2024'!L:L,"!",0,1)<0,0,_xlfn.XLOOKUP($B28,'POM 2024'!B:B,'POM 2024'!L:L,"!",0,1)) -> 6695 | P28: =+O28-L28 -> -166335 | S28: Ejecución | T28: En Proceso | U28: =+I28=J28 -> TRUE
B29: AMSA_Asesoria Centinela | C29: =+_xlfn.XLOOKUP(B29,'[1]Proyectos (NO FILTRAR)'!$F:$F,'[1]Proyectos (NO FILTRAR)'!$I:$I) -> AMSA | D29: Asesoría Plan 2024 y quinquenio 2024-2028 | E29: =+_xlfn.XLOOKUP(B29,'POM 2024'!B:B,'POM 2024'!F:F,"!",0,1) -> Cristian Quezada | F29: =+_xlfn.XLOOKUP(B29,'POM 2024'!B:B,'POM 2024'!H:H,"!",0,1) -> Nicolás Ayarza | G29: =+J29 -> 8760 | H29: 0 | I29: =+SUM(G29:H29) -> 8760 | J29: =VLOOKUP(B29,'POM 2024'!$B$2:$BI$64,48,FALSE) -> 8760 | K29: =+_xlfn.XLOOKUP($B29,'POM 2024'!B:B,'POM 2024'!AV:AV,"!",0,1) -> 8509.5 | L29: =+_xlfn.XLOOKUP($B29,'POM 2024'!B:B,'POM 2024'!AU:AU,"!",0,1) -> 8509.5 | M29: =+J29-L29 -> 250.5 | N29: =+IFERROR(((J29-K29)/K29),0) -> 0.029437687 | O29: =IF(_xlfn.XLOOKUP($B29,'POM 2024'!B:B,'POM 2024'!L:L,"!",0,1)<0,0,_xlfn.XLOOKUP($B29,'POM 2024'!B:B,'POM 2024'!L:L,"!",0,1)) -> 0 | P29: =+O29-L29 -> -8509.5 | S29: Ejecución | T29: En Proceso | U29: =+I29=J29 -> TRUE
B30: AMSA_Estandares Minimos | C30: =+_xlfn.XLOOKUP(B30,'[1]Proyectos (NO FILTRAR)'!$F:$F,'[1]Proyectos (NO FILTRAR)'!$I:$I) -> AMSA | D30: Desarrollo de Manuales de Minimos Estandares | E30: =+_xlfn.XLOOKUP(B30,'POM 2024'!B:B,'POM 2024'!F:F,"!",0,1) -> Alex Figueroa | F30: =+_xlfn.XLOOKUP(B30,'POM 2024'!B:B,'POM 2024'!H:H,"!",0,1) -> Cristian Alarcón | G30: =+J30 -> 15305 | H30: 0 | I30: =+SUM(G30:H30) -> 15305 | J30: =VLOOKUP(B30,'POM 2024'!$B$2:$BI$64,48,FALSE) -> 15305 | K30: =+_xlfn.XLOOKUP($B30,'POM 2024'!B:B,'POM 2024'!AV:AV,"!",0,1) -> 0 | L30: =+_xlfn.XLOOKUP($B30,'POM 2024'!B:B,'POM 2024'!AU:AU,"!",0,1) -> 35286.5 | M30: =+J30-L30 -> -19981.5 | N30: =+IFERROR(((J30-K30)/K30),0) -> 0 | O30: =IF(_xlfn.XLOOKUP($B30,'POM 2024'!B:B,'POM 2024'!L:L,"!",0,1)<0,0,_xlfn.XLOOKUP($B30,'POM 2024'!B:B,'POM 2024'!L:L,"!",0,1)) -> 3008 | P30: =+O30-L30 -> -32278.5 | S30: Ejecución | T30: En Proceso | U30: =+I30=J30 -> TRUE
B31: Glencore_Coroccohuayco_OptimizacionLOM | C31: =+_xlfn.XLOOKUP(B31,'[1]Proyectos (NO FILTRAR)'!$F:$F,'[1]Proyectos (NO FILTRAR)'!$I:$I) -> Glencore | D31: Estudios mineros complementarios para la PFS | E31: =+_xlfn.XLOOKUP(B31,'POM 2024'!B:B,'POM 2024'!F:F,"!",0,1) -> Cristian Quezada | F31: =+_xlfn.XLOOKUP(B31,'POM 2024'!B:B,'POM 2024'!H:H,"!",0,1) -> Kevin Rios | G31: =+J31 -> 42188.15 | H31: 0 | I31: =+SUM(G31:H31) -> 42188.15 | J31: =VLOOKUP(B31,'POM 2024'!$B$2:$BI$64,48,FALSE) -> 42188.15 | K31: =+_xlfn.XLOOKUP($B31,'POM 2024'!B:B,'POM 2024'!AV:AV,"!",0,1) -> 38000 | L31: =+_xlfn.XLOOKUP($B31,'POM 2024'!B:B,'POM 2024'!AU:AU,"!",0,1) -> 42188.15 | M31: =+J31-L31 -> 0 | N31: =+IFERROR(((J31-K31)/K31),0) -> 0.11021447 | O31: =IF(_xlfn.XLOOKUP($B31,'POM 2024'!B:B,'POM 2024'!L:L,"!",0,1)<0,0,_xlfn.XLOOKUP($B31,'POM 2024'!B:B,'POM 2024'!L:L,"!",0,1)) -> 0 | P31: =+O31-L31 -> -42188.15 | S31: Ejecución | T31: En Proceso | U31: =+I31=J31 -> TRUE
B32: Coripuno_Metodos de Minado | C32: =+_xlfn.XLOOKUP(B32,'[1]Proyectos (NO FILTRAR)'!$F:$F,'[1]Proyectos (NO FILTRAR)'!$I:$I) -> Coripuno | D32: Alternativas método de minado proyecto Torremani | E32: =+_xlfn.XLOOKUP(B32,'POM 2024'!B:B,'POM 2024'!F:F,"!",0,1) -> Claudio Hernández | F32: =+_xlfn.XLOOKUP(B32,'POM 2024'!B:B,'POM 2024'!H:H,"!",0,1) -> Pablo Quiero | G32: =+J32 -> 105000 | H32: 0 | I32: =+SUM(G32:H32) -> 105000 | J32: =VLOOKUP(B32,'POM 2024'!$B$2:$BI$64,48,FALSE) -> 105000 | K32: =+_xlfn.XLOOKUP($B32,'POM 2024'!B:B,'POM 2024'!AV:AV,"!",0,1) -> 20185 | L32: =+_xlfn.XLOOKUP($B32,'POM 2024'!B:B,'POM 2024'!AU:AU,"!",0,1) -> 105060 | M32: =+J32-L32 -> -60 | N32: =+IFERROR(((J32-K32)/K32),0) -> 4.2018826 | O32: =IF(_xlfn.XLOOKUP($B32,'POM 2024'!B:B,'POM 2024'!L:L,"!",0,1)<0,0,_xlfn.XLOOKUP($B32,'POM 2024'!B:B,'POM 2024'!L:L,"!",0,1)) -> 0 | P32: =+O32-L32 -> -105060 | S32: Ejecución | T32: En Proceso | U32: =+I32=J32 -> TRUE
B33: Minsur_Mejoramiento datos geotecnicos SR | C33: =+_xlfn.XLOOKUP(B33,'[1]Proyectos (NO FILTRAR)'!$F:$F,'[1]Proyectos (NO FILTRAR)'!$I:$I) -> Minsur | D33: Apoyo Planificacion Geomecanica | E33: =+_xlfn.XLOOKUP(B33,'POM 2024'!B:B,'POM 2024'!F:F,"!",0,1) -> Claudio Hernández | F33: =+_xlfn.XLOOKUP(B33,'POM 2024'!B:B,'POM 2024'!H:H,"!",0,1) -> TBD | G33: =+J33 -> 24551 | H33: 0 | I33: =+SUM(G33:H33) -> 24551 | J33: =VLOOKUP(B33,'POM 2024'!$B$2:$BI$64,48,FALSE) -> 24551 | K33: =+_xlfn.XLOOKUP($B33,'POM 2024'!B:B,'POM 2024'!AV:AV,"!",0,1) -> 0 | L33: =+_xlfn.XLOOKUP($B33,'POM 2024'!B:B,'POM 2024'!AU:AU,"!",0,1) -> 0 | M33: =+J33-L33 -> 24551 | N33: =+IFERROR(((J33-K33)/K33),0) -> 0 | O33: =IF(_xlfn.XLOOKUP($B33,'POM 2024'!B:B,'POM 2024'!L:L,"!",0,1)<0,0,_xlfn.XLOOKUP($B33,'POM 2024'!B:B,'POM 2024'!L:L,"!",0,1)) -> 0 | P33: =+O33-L33 -> 0 | S33: Ejecución | T33: En Proceso | U33: =+I33=J33 -> TRUE
B34: BHP_Tunel Exploratorio | C34: =+_xlfn.XLOOKUP(B34,'[1]Proyectos (NO FILTRAR)'!$F:$F,'[1]Proyectos (NO FILTRAR)'!$I:$I) -> BHP | D34: Estudio FEL1 de evaluación de opciones de acceso exploratrio para el cuerpo Escondida East Deep, de BHP Minerals America. | E34: =+_xlfn.XLOOKUP(B34,'POM 2024'!B:B,'POM 2024'!F:F,"!",0,1) -> Mauricio Melendez | F34: =+_xlfn.XLOOKUP(B34,'POM 2024'!B:B,'POM 2024'!H:H,"!",0,1) -> Freddy Diaz | G34: =+J34 -> 0 | H34: 0 | I34: =+SUM(G34:H34) -> 0 | J34: =VLOOKUP(B34,'POM 2024'!$B$2:$BI$64,48,FALSE) -> 0 | K34: =+_xlfn.XLOOKUP($B34,'POM 2024'!B:B,'POM 2024'!AV:AV,"!",0,1) -> 0 | L34: =+_xlfn.XLOOKUP($B34,'POM 2024'!B:B,'POM 2024'!AU:AU,"!",0,1) -> 0 | M34: =+J34-L34 -> 0 | N34: =+IFERROR(((J34-K34)/K34),0) -> 0 | O34: =IF(_xlfn.XLOOKUP($B34,'POM 2024'!B:B,'POM 2024'!L:L,"!",0,1)<0,0,_xlfn.XLOOKUP($B34,'POM 2024'!B:B,'POM 2024'!L:L,"!",0,1)) -> 0 | P34: =+O34-L34 -> 0 | S34: Ejecución | T34: En Proceso | U34: =+I34=J34 -> TRUE
B35: J&F_Urucrum_RecuperacionPilares | C35: J&F | D35: Recuperación de Pilares Mina Urucrum | E35: Alex Figueroa | F35: Freddy Diaz | G35: =+J35 -> 0 | H35: 0 | I35: =+SUM(G35:H35) -> 0 | J35: =VLOOKUP(B35,'POM 2024'!$B$2:$BI$64,48,FALSE) -> 0 | K35: =+_xlfn.XLOOKUP($B35,'POM 2024'!B:B,'POM 2024'!AV:AV,"!",0,1) -> 0 | L35: =+_xlfn.XLOOKUP($B35,'POM 2024'!B:B,'POM 2024'!AU:AU,"!",0,1) -> 56177.69 | M35: =+J35-L35 -> -56177.69 | N35: =+IFERROR(((J35-K35)/K35),0) -> 0 | O35: =IF(_xlfn.XLOOKUP($B35,'POM 2024'!B:B,'POM 2024'!L:L,"!",0,1)<0,0,_xlfn.XLOOKUP($B35,'POM 2024'!B:B,'POM 2024'!L:L,"!",0,1)) -> 31049 | P35: =+O35-L35 -> -25128.69 | S35: Ejecución | T35: En Proceso | U35: =+I35=J35 -> TRUE
B36: Eurochem_Himmelfarb Deposit | C36: =+_xlfn.XLOOKUP(B36,'[1]Proyectos (NO FILTRAR)'!$F:$F,'[1]Proyectos (NO FILTRAR)'!$I:$I) -> Eurochem | D36: Auditoría técnica y optimización de soluciones para el "Estudio exploratorio sobre la extracción y el tratamiento de recursos minerales de fosforita potencialmente recuperables en el yacimiento de Himmelfarb". | E36: =+_xlfn.XLOOKUP(B36,'POM 2024'!B:B,'POM 2024'!F:F,"!",0,1) -> Ricardo Miranda | F36: =+_xlfn.XLOOKUP(B36,'POM 2024'!B:B,'POM 2024'!H:H,"!",0,1) -> Gerson Alfaro | G36: =+J36 -> 76050 | H36: 0 | I36: =+SUM(G36:H36) -> 76050 | J36: =VLOOKUP(B36,'POM 2024'!$B$2:$BI$64,48,FALSE) -> 76050 | K36: =+_xlfn.XLOOKUP($B36,'POM 2024'!B:B,'POM 2024'!AV:AV,"!",0,1) -> 91260 | L36: =+_xlfn.XLOOKUP($B36,'POM 2024'!B:B,'POM 2024'!AU:AU,"!",0,1) -> 105398.64 | M36: =+J36-L36 -> -29348.64 | N36: =+IFERROR(((J36-K36)/K36),0) -> -0.16666667 | O36: =IF(_xlfn.XLOOKUP($B36,'POM 2024'!B:B,'POM 2024'!L:L,"!",0,1)<0,0,_xlfn.XLOOKUP($B36,'POM 2024'!B:B,'POM 2024'!L:L,"!",0,1)) -> 0 | P36: =+O36-L36 -> -105398.64 | S36: Ejecución | T36: En Proceso | U36: =+I36=J36 -> TRUE
B37: Seligdar_Kyuchus | C37: =+_xlfn.XLOOKUP(B37,'[1]Proyectos (NO FILTRAR)'!$F:$F,'[1]Proyectos (NO FILTRAR)'!$I:$I) -> Seligdar | D37: Estudio de Prefactibilidad Explotación Proyecto Minero, Rusia. | E37: =+_xlfn.XLOOKUP(B37,'POM 2024'!B:B,'POM 2024'!F:F,"!",0,1) -> Ricardo Miranda | F37: =+_xlfn.XLOOKUP(B37,'POM 2024'!B:B,'POM 2024'!H:H,"!",0,1) -> Gerson Alfaro | G37: =+J37 -> 0 | H37: 0 | I37: =+SUM(G37:H37) -> 0 | J37: =VLOOKUP(B37,'POM 2024'!$B$2:$BI$64,48,FALSE) -> 0 | K37: =+_xlfn.XLOOKUP($B37,'POM 2024'!B:B,'POM 2024'!AV:AV,"!",0,1) -> 0 | L37: =+_xlfn.XLOOKUP($B37,'POM 2024'!B:B,'POM 2024'!AU:AU,"!",0,1) -> 0 | M37: =+J37-L37 -> 0 | N37: =+IFERROR(((J37-K37)/K37),0) -> 0 | O37: =IF(_xlfn.XLOOKUP($B37,'POM 2024'!B:B,'POM 2024'!L:L,"!",0,1)<0,0,_xlfn.XLOOKUP($B37,'POM 2024'!B:B,'POM 2024'!L:L,"!",0,1)) -> 0 | P37: =+O37-L37 -> 0 | R37: Administrativo | S37: Ejecución | T37: En Proceso | U37: =+I37=J37 -> TRUE
B38: MCI_Mine Plan Review Los Bronces | C38: Mitsubichi | D38: Revisión y evaluación de oportunidades para el plan minero de largo plazo de Los Bronces (LB) | E38: Cristian Quezada | F38: TBD | G38: =+J38 -> 0 | H38: 0 | I38: =+SUM(G38:H38) -> 0 | J38: =VLOOKUP(B38,'POM 2024'!$B$2:$BI$64,48,FALSE) -> 0 | K38: =+_xlfn.XLOOKUP($B38,'POM 2024'!B:B,'POM 2024'!AV:AV,"!",0,1) -> 0 | L38: =+_xlfn.XLOOKUP($B38,'POM 2024'!B:B,'POM 2024'!AU:AU,"!",0,1) -> 69250 | M38: =+J38-L38 -> -69250 | N38: =+IFERROR(((J38-K38)/K38),0) -> 0 | O38: =IF(_xlfn.XLOOKUP($B38,'POM 2024'!B:B,'POM 2024'!L:L,"!",0,1)<0,0,_xlfn.XLOOKUP($B38,'POM 2024'!B:B,'POM 2024'!L:L,"!",0,1)) -> 23720 | P38: =+O38-L38 -> -45530 | Q38: Se generará el seungo EDP cuando el avance fisico alcance el 50% | S38: Ejecución | T38: En Proceso | U38: =+I38=J38 -> TRUE
B39: MEIA Coripuno | C39: Coripuno | D39: Coripuno MEIA | E39: Matias Fuentes | F39: Jhonny Pacheco | G39: =+J39 -> 23980 | H39: 0 | I39: =+SUM(G39:H39) -> 23980 | J39: =VLOOKUP(B39,'POM 2024'!$B$2:$BI$64,48,FALSE) -> 23980 | K39: =+_xlfn.XLOOKUP($B39,'POM 2024'!B:B,'POM 2024'!AV:AV,"!",0,1) -> 23980 | L39: =+_xlfn.XLOOKUP($B39,'POM 2024'!B:B,'POM 2024'!AU:AU,"!",0,1) -> 47960 | M39: =+J39-L39 -> -23980 | N39: =+IFERROR(((J39-K39)/K39),0) -> 0 | O39: =IF(_xlfn.XLOOKUP($B39,'POM 2024'!B:B,'POM 2024'!L:L,"!",0,1)<0,0,_xlfn.XLOOKUP($B39,'POM 2024'!B:B,'POM 2024'!L:L,"!",0,1)) -> 2398 | P39: =+O39-L39 -> -45562 | S39: Ejecución | T39: En Proceso | U39: =+I39=J39 -> TRUE
B40: EMX_Metallurgical expert for review | C40: EMX | D40: Metallurgical expert for review | E40: Matias Fuentes | F40: Fernando Rodriguez | G40: =+J40 -> 0 | H40: 0 | I40: =+SUM(G40:H40) -> 0 | J40: =VLOOKUP(B40,'POM 2024'!$B$2:$BI$64,48,FALSE) -> 0 | K40: =+_xlfn.XLOOKUP($B40,'POM 2024'!B:B,'POM 2024'!AV:AV,"!",0,1) -> 0 | L40: =+_xlfn.XLOOKUP($B40,'POM 2024'!B:B,'POM 2024'!AU:AU,"!",0,1) -> 0 | M40: =+J40-L40 -> 0 | N40: =+IFERROR(((J40-K40)/K40),0) -> 0 | O40: =IF(_xlfn.XLOOKUP($B40,'POM 2024'!B:B,'POM 2024'!L:L,"!",0,1)<0,0,_xlfn.XLOOKUP($B40,'POM 2024'!B:B,'POM 2024'!L:L,"!",0,1)) -> 0 | P40: =+O40-L40 -> 0 | S40: Ejecución | T40: En Proceso | U40: =+I40=J40 -> TRUE
B41: EMX_Due Diligence de Chapi | C41: =+_xlfn.XLOOKUP(B41,'[1]Proyectos (NO FILTRAR)'!$F:$F,'[1]Proyectos (NO FILTRAR)'!$I:$I) -> EMX Royalty | D41: Revisión para oportunidades de negocio Proyecto Chapi | E41: Fernando Rodriguez | F41: - | G41: =+J41 -> 26649 | H41: 0 | I41: =+SUM(G41:H41) -> 26649 | J41: =VLOOKUP(B41,'POM 2024'!$B$2:$BI$130,48,FALSE) -> 26649 | K41: =+_xlfn.XLOOKUP($B41,'POM 2024'!B:B,'POM 2024'!AV:AV,"!",0,1) -> 0 | L41: =+_xlfn.XLOOKUP($B41,'POM 2024'!B:B,'POM 2024'!AU:AU,"!",0,1) -> 0 | M41: =+J41-L41 -> 26649 | N41: =+IFERROR(((J41-K41)/K41),0) -> 0 | O41: =IF(_xlfn.XLOOKUP($B41,'POM 2024'!B:B,'POM 2024'!L:L,"!",0,1)<0,0,_xlfn.XLOOKUP($B41,'POM 2024'!B:B,'POM 2024'!L:L,"!",0,1)) -> 0 | S41: Ejecución | T41: En Proceso | U41: =+I41=J41 -> TRUE
B42: IvanhoeElectric_Mine Planning Support | C42: =+_xlfn.XLOOKUP(B42,'[1]Proyectos (NO FILTRAR)'!$F:$F,'[1]Proyectos (NO FILTRAR)'!$I:$I) -> Ivanhoe Electric | D42: Mine Planning Support | E42: Matias Fuentes | F42: Carlos Morante | G42: =+J42 -> 38146 | H42: 0 | I42: =+SUM(G42:H42) -> 38146 | J42: =VLOOKUP(B42,'POM 2024'!$B$2:$BI$130,48,FALSE) -> 38146 | K42: =+_xlfn.XLOOKUP($B42,'POM 2024'!B:B,'POM 2024'!AV:AV,"!",0,1) -> 0 | L42: =+_xlfn.XLOOKUP($B42,'POM 2024'!B:B,'POM 2024'!AU:AU,"!",0,1) -> 0 | M42: =+J42-L42 -> 38146 | N42: =+IFERROR(((J42-K42)/K42),0) -> 0 | O42: =IF(_xlfn.XLOOKUP($B42,'POM 2024'!B:B,'POM 2024'!L:L,"!",0,1)<0,0,_xlfn.XLOOKUP($B42,'POM 2024'!B:B,'POM 2024'!L:L,"!",0,1)) -> 41413 | S42: Ejecución | T42: En Proceso | U42: =+I42=J42 -> TRUE
B43: J&F_Autazes Due Diligence | C43: =+_xlfn.XLOOKUP(B43,'[1]Proyectos (NO FILTRAR)'!$F:$F,'[1]Proyectos (NO FILTRAR)'!$I:$I) -> J&F | D43: Revisión para evaluar posibles oportunidades de negocio de LHG Mining | E43: =+_xlfn.XLOOKUP(B43,'POM 2024'!B:B,'POM 2024'!F:F,"!",0,1) -> - | F43: =+_xlfn.XLOOKUP(B43,'POM 2024'!B:B,'POM 2024'!H:H,"!",0,1) -> Kevin Rios | G43: =+J43 -> 72664 | H43: 0 | I43: =+SUM(G43:H43) -> 72664 | J43: =VLOOKUP(B43,'POM 2024'!$B$2:$BI$129,48,FALSE) -> 72664 | K43: =+_xlfn.XLOOKUP($B43,'POM 2024'!B:B,'POM 2024'!AV:AV,"!",0,1) -> 0 | L43: =+_xlfn.XLOOKUP($B43,'POM 2024'!B:B,'POM 2024'!AU:AU,"!",0,1) -> 70000 | M43: =+J43-L43 -> 2664 | N43: =+IFERROR(((J43-K43)/K43),0) -> 0 | O43: =IF(_xlfn.XLOOKUP($B43,'POM 2024'!B:B,'POM 2024'!L:L,"!",0,1)<0,0,_xlfn.XLOOKUP($B43,'POM 2024'!B:B,'POM 2024'!L:L,"!",0,1)) -> 1791 | S43: Ejecución | T43: En Proceso | U43: =+I43=J43 -> TRUE
B44: SierraMetals_Update MEIA Yauricocha | C44: =+_xlfn.XLOOKUP(B44,'[1]Proyectos (NO FILTRAR)'!$F:$F,'[1]Proyectos (NO FILTRAR)'!$I:$I) -> Sierra metals | D44: MEIA- Actualización de los dieños de labores y envolvente | E44: =+_xlfn.XLOOKUP(B44,'POM 2024'!B:B,'POM 2024'!F:F,"!",0,1) -> - | F44: =+_xlfn.XLOOKUP(B44,'POM 2024'!B:B,'POM 2024'!H:H,"!",0,1) -> - | G44: =+J44 -> 20941 | H44: 0 | I44: =+SUM(G44:H44) -> 20941 | J44: =VLOOKUP(B44,'POM 2024'!$B$2:$BI$129,48,FALSE) -> 20941 | K44: =+_xlfn.XLOOKUP($B44,'POM 2024'!B:B,'POM 2024'!AV:AV,"!",0,1) -> 0 | L44: =+_xlfn.XLOOKUP($B44,'POM 2024'!B:B,'POM 2024'!AU:AU,"!",0,1) -> 25919.1 | M44: =+J44-L44 -> -4978.1 | N44: =+IFERROR(((J44-K44)/K44),0) -> 0 | O44: =IF(_xlfn.XLOOKUP($B44,'POM 2024'!B:B,'POM 2024'!L:L,"!",0,1)<0,0,_xlfn.XLOOKUP($B44,'POM 2024'!B:B,'POM 2024'!L:L,"!",0,1)) -> 5647 | Q44: Kevin Rios | S44: Ejecución | T44: En Proceso | U44: =+I44=J44 -> TRUE
B45: CMP_LOM CNN 2024 | C45: =+_xlfn.XLOOKUP(B45,'[1]Proyectos (NO FILTRAR)'!$F:$F,'[1]Proyectos (NO FILTRAR)'!$I:$I) -> CMP | D45: LOM CNN 2024 | E45: =+_xlfn.XLOOKUP(B45,'POM 2024'!B:B,'POM 2024'!F:F,"!",0,1) -> Cristian Quezada | F45: =+_xlfn.XLOOKUP(B45,'POM 2024'!B:B,'POM 2024'!H:H,"!",0,1) -> TBD | G45: =+J45 -> 34041 | H45: 0 | I45: =+SUM(G45:H45) -> 34041 | J45: =VLOOKUP(B45,'POM 2024'!$B$2:$BI$73,48,FALSE) -> 34041 | K45: =+_xlfn.XLOOKUP($B45,'POM 2024'!B:B,'POM 2024'!AV:AV,"!",0,1) -> 36850 | L45: =+_xlfn.XLOOKUP($B45,'POM 2024'!B:B,'POM 2024'!AU:AU,"!",0,1) -> 0 | M45: =+J45-L45 -> 34041 | N45: =+IFERROR(((J45-K45)/K45),0) -> -0.076227951 | O45: =IF(_xlfn.XLOOKUP($B45,'POM 2024'!B:B,'POM 2024'!L:L,"!",0,1)<0,0,_xlfn.XLOOKUP($B45,'POM 2024'!B:B,'POM 2024'!L:L,"!",0,1)) -> 2164 | P45: =+O45-L45 -> 2164 | S45: Ejecución | T45: En Proceso | U45: =+I45=J45 -> TRUE
B46: CMP_LOM MLC 2024 | C46: =+_xlfn.XLOOKUP(B46,'[1]Proyectos (NO FILTRAR)'!$F:$F,'[1]Proyectos (NO FILTRAR)'!$I:$I) -> CMP | D46: LOM MLC 2024 | E46: =+_xlfn.XLOOKUP(B46,'POM 2024'!B:B,'POM 2024'!F:F,"!",0,1) -> Cristian Quezada | F46: =+_xlfn.XLOOKUP(B46,'POM 2024'!B:B,'POM 2024'!H:H,"!",0,1) -> TBD | G46: =+J46 -> 26563 | H46: 0 | I46: =+SUM(G46:H46) -> 26563 | J46: =VLOOKUP(B46,'POM 2024'!$B$2:$BI$73,48,FALSE) -> 26563 | K46: =+_xlfn.XLOOKUP($B46,'POM 2024'!B:B,'POM 2024'!AV:AV,"!",0,1) -> 28800 | L46: =+_xlfn.XLOOKUP($B46,'POM 2024'!B:B,'POM 2024'!AU:AU,"!",0,1) -> 0 | M46: =+J46-L46 -> 26563 | N46: =+IFERROR(((J46-K46)/K46),0) -> -0.077673611 | O46: =IF(_xlfn.XLOOKUP($B46,'POM 2024'!B:B,'POM 2024'!L:L,"!",0,1)<0,0,_xlfn.XLOOKUP($B46,'POM 2024'!B:B,'POM 2024'!L:L,"!",0,1)) -> 1836 | P46: =+O46-L46 -> 1836 | S46: Ejecución | T46: En Proceso | U46: =+I46=J46 -> TRUE
B47: CMP_Puesta en marcha SLS Romeral | C47: =+_xlfn.XLOOKUP(B47,'[1]Proyectos (NO FILTRAR)'!$F:$F,'[1]Proyectos (NO FILTRAR)'!$I:$I) -> CMP | D47: Puesta en marcha SLS Romeral | E47: =+_xlfn.XLOOKUP(B47,'POM 2024'!B:B,'POM 2024'!F:F,"!",0,1) -> Ricardo Miranda | F47: =+_xlfn.XLOOKUP(B47,'POM 2024'!B:B,'POM 2024'!H:H,"!",0,1) -> Pablo Quiero | G47: =+J47 -> 135485 | H47: 0 | I47: =+SUM(G47:H47) -> 135485 | J47: =VLOOKUP(B47,'POM 2024'!$B$2:$BI$73,48,FALSE) -> 135485 | K47: =+_xlfn.XLOOKUP($B47,'POM 2024'!B:B,'POM 2024'!AV:AV,"!",0,1) -> 140000 | L47: =+_xlfn.XLOOKUP($B47,'POM 2024'!B:B,'POM 2024'!AU:AU,"!",0,1) -> 0 | M47: =+J47-L47 -> 135485 | N47: =+IFERROR(((J47-K47)/K47),0) -> -0.03225 | O47: =IF(_xlfn.XLOOKUP($B47,'POM 2024'!B:B,'POM 2024'!L:L,"!",0,1)<0,0,_xlfn.XLOOKUP($B47,'POM 2024'!B:B,'POM 2024'!L:L,"!",0,1)) -> 130940.85 | P47: =+O47-L47 -> 130940.85 | S47: Ejecución | T47: En Proceso | U47: =+I47=J47 -> TRUE
G48: =+SUM(G21:G47) -> 887997.15 | H48: =+SUM(H21:H47) -> 0 | I48: =+SUM(I21:I47) -> 887997.15 | J48: =+SUM(J21:J47) -> 887997.15 | K48: =+SUM(K21:K47) -> 550910.74 | L48: =+SUM(L21:L47) -> 1006721.6 | M48: =+SUM(M21:M47) -> -118724.47 | N48: =+IFERROR(((J48-K48)/K48),0) -> 0.61187119 | O48: =+SUM(O21:O47) -> 258208.39 | P48: =+SUM(P21:P40) -> -836385.98
C52: =+C20 -> Cliente | D52: =+D20 -> Nombre Proyecto | E52: =+E20 -> Director | F52: =+F20 -> Ing Principal | G52: =+G20 -> Real | H52: =+H20 -> Otros | I52: =+I20 -> 0 | J52: =+J20 -> EDP Real | ... Q52: =+Q20 -> Comentarios | R52: Tipo 1 | S52: Tipo 2 | T52: Estatus
B53: CMP - FEL 2A | C53: CMP | D53: FEL2A Valle Elqui Norte | E53: =+_xlfn.XLOOKUP(B53,'POM 2024'!B:B,'POM 2024'!F:F,"!",0,1) -> Alex Figueroa | F53: =+_xlfn.XLOOKUP(B53,'POM 2024'!B:B,'POM 2024'!H:H,"!",0,1) -> Felipe Lira | G53: =+J53 -> 0 | H53: 0 | I53: =+SUM(G53:H53) -> 0 | J53: =VLOOKUP(B53,'POM 2024'!$B$2:$BI$64,48,FALSE) -> 0 | K53: =+_xlfn.XLOOKUP($B53,'POM 2024'!B:B,'POM 2024'!AP:AP,"!",0,1) -> 0 | L53: =+_xlfn.XLOOKUP($B53,'POM 2024'!B:B,'POM 2024'!AU:AU,"!",0,1) -> 0 | M53: =+J53-L53 -> 0 | N53: =+IFERROR(((J53-K53)/K53),0) -> 0 | O53: =IF(_xlfn.XLOOKUP($B53,'POM 2024'!B:B,'POM 2024'!L:L,"!",0,1)<0,0,_xlfn.XLOOKUP($B53,'POM 2024'!B:B,'POM 2024'!L:L,"!",0,1)) -> 0 | P53: =+O53-L53 -> 0 | R53: Técnico | S53: Terminal | T53: En Proceso | U53: =+I53=J53 -> TRUE
B54: CMP - FEL 2A | C54: CMP | D54: FEL2A Valle Elqui Norte - Update de modelos | E54: =+_xlfn.XLOOKUP(B54,'POM 2024'!B:B,'POM 2024'!F:F,"!",0,1) -> Alex Figueroa | F54: =+_xlfn.XLOOKUP(B54,'POM 2024'!B:B,'POM 2024'!H:H,"!",0,1) -> Felipe Lira | G54: =+J54 -> 0 | H54: 0 | I54: =+SUM(G54:H54) -> 0 | J54: ='POM 2024'!AT22 -> 0 | K54: =+_xlfn.XLOOKUP($B54,'POM 2024'!B:B,'POM 2024'!AP:AP,"!",0,1) -> 0 | L54: 0 | M54: =+J54-L54 -> 0 | N54: =+IFERROR(((J54-K54)/K54),0) -> 0 | O54: =IF(_xlfn.XLOOKUP($B54,'POM 2024'!B:B,'POM 2024'!L:L,"!",0,-1)<0,0,_xlfn.XLOOKUP($B54,'POM 2024'!B:B,'POM 2024'!L:L,"!",0,-1)) -> 0 | P54: =+O54-L54 -> 0 | R54: Técnico | S54: Terminal | T54: En Proceso | U54: =+I54=J54 -> TRUE
B55: Codelco_Capacitacion Deswik DET | C55: Codelco | D55: Capacitación y construcción de modelos de preparación minera usando software DESWIK | E55: =+_xlfn.XLOOKUP(B55,'POM 2024'!B:B,'POM 2024'!F:F,"!",0,1) -> Mauricio Melendez | F55: =+_xlfn.XLOOKUP(B55,'POM 2024'!B:B,'POM 2024'!H:H,"!",0,1) -> Felipe Lira | G55: =+J55 -> 13837 | H55: 0 | I55: =+SUM(G55:H55) -> 13837 | J55: =VLOOKUP(B55,'POM 2024'!$B$2:$BI$64,48,FALSE) -> 13837 | K55: =+_xlfn.XLOOKUP($B55,'POM 2024'!B:B,'POM 2024'!AP:AP,"!",0,1) -> 0 | L55: =+_xlfn.XLOOKUP($B55,'POM 2024'!B:B,'POM 2024'!AU:AU,"!",0,1) -> 0 | M55: =+J55-L55 -> 13837 | N55: =+IFERROR(((J55-K55)/K55),0) -> 0 | O55: =IF(_xlfn.XLOOKUP($B55,'POM 2024'!B:B,'POM 2024'!L:L,"!",0,1)<0,0,_xlfn.XLOOKUP($B55,'POM 2024'!B:B,'POM 2024'!L:L,"!",0,1)) -> 0 | P55: =+O55-L55 -> 0 | R55: Técnico | S55: Terminal | T55: En Proceso | U55: =+I55=J55 -> TRUE
B56: NEXA_FEL2 Aripuana | C56: =+_xlfn.XLOOKUP(B56,'[1]Proyectos (NO FILTRAR)'!$F:$F,'[1]Proyectos (NO FILTRAR)'!$I:$I) -> Nexa | D56: Mina Ambrex y Babacu Proyecto conceptual - FEL2 | E56: =+_xlfn.XLOOKUP(B56,'POM 2024'!B:B,'POM 2024'!F:F,"!",0,1) -> Matias Fuentes | F56: =+_xlfn.XLOOKUP(B56,'POM 2024'!B:B,'POM 2024'!H:H,"!",0,1) -> Andres Budini | G56: =+J56 -> 43869 | H56: 0 | I56: =+SUM(G56:H56) -> 43869 | J56: =VLOOKUP(B56,'POM 2024'!$B$2:$BI$64,48,FALSE) -> 43869 | K56: =+_xlfn.XLOOKUP($B56,'POM 2024'!B:B,'POM 2024'!AP:AP,"!",0,1) -> 0 | L56: =+_xlfn.XLOOKUP($B56,'POM 2024'!B:B,'POM 2024'!AU:AU,"!",0,1) -> 47364.082 | M56: =+J56-L56 -> -3495.0816 | N56: =+IFERROR(((J56-K56)/K56),0) -> 0 | O56: =IF(_xlfn.XLOOKUP($B56,'POM 2024'!B:B,'POM 2024'!L:L,"!",0,1)<0,0,_xlfn.XLOOKUP($B56,'POM 2024'!B:B,'POM 2024'!L:L,"!",0,1)) -> 3495.0816 | P56: =+O56-L56 -> -43869 | R56: Técnico | S56: Terminal | T56: En Proceso | U56: =+I56=J56 -> TRUE
G57: =+SUM(G53:G56) -> 57706 | H57: =+SUM(H53:H56) -> 0 | I57: =+SUM(I53:I56) -> 57706 | J57: =+SUM(J53:J56) -> 57706 | K57: =+SUM(K53:K56) -> 0 | L57: =+SUM(L53:L56) -> 47364.082 | M57: =+SUM(M53:M56) -> 10341.918 | N57: =+IFERROR(((J57-K57)/K57),0) -> 0 | O57: =+SUM(O53:O56) -> 3495.0816 | P57: =+SUM(P53:P56) -> -43869
C61: =+C52 -> Cliente | D61: =+D52 -> Nombre Proyecto | E61: =+E52 -> Director | F61: =+F52 -> Ing Principal | G61: =+G52 -> Real | H61: =+H52 -> Otros | I61: =+I52 -> 0 | J61: =+J52 -> EDP Real | ... Q61: =+Q52 -> Comentarios | R61: Tipo 1 | S61: Tipo 2 | T61: Estatus
B62: Algarrobo | C62: =+_xlfn.XLOOKUP(B62,'[1]Proyectos (NO FILTRAR)'!$F:$F,'[1]Proyectos (NO FILTRAR)'!$I:$I) -> CMP | D62: Proyecto Algarrobo Finos | E62: =+_xlfn.XLOOKUP(B62,'POM 2024'!B:B,'POM 2024'!F:F,"!",0,1) -> 0 | F62: =+_xlfn.XLOOKUP(B62,'POM 2024'!B:B,'POM 2024'!H:H,"!",0,1) -> Emilio Sánchez | G62: =+J62 -> 0 | H62: =+J62 -> 0 | I62: =+SUM(G62:H62) -> 0 | J62: =VLOOKUP(B62,'POM 2024'!$B$2:$BI$64,48,FALSE) -> 0 | K62: =+_xlfn.XLOOKUP($B62,'POM 2024'!B:B,'POM 2024'!AV:AV,"!",0,1) -> 0 | L62: =+_xlfn.XLOOKUP($B62,'POM 2024'!B:B,'POM 2024'!AU:AU,"!",0,1) -> 0 | M62: =+J62-L62 -> 0 | N62: =+IFERROR(((J62-K62)/K62),0) -> 0 | O62: =IF(_xlfn.XLOOKUP($B62,'POM 2024'!B:B,'POM 2024'!L:L,"!",0,1)<0,0,_xlfn.XLOOKUP($B62,'POM 2024'!B:B,'POM 2024'!L:L,"!",0,1)) -> 6045.98 | P62: =+O62-L62 -> 6045.98 | R62: Administrativo | S62: Rezagado | T62: Terminado | U62: =+I62=J62 -> TRUE
B63: Boston_Inmaculada Hochschild II | C63: =+_xlfn.XLOOKUP(B63,'[1]Proyectos (NO FILTRAR)'!$F:$F,'[1]Proyectos (NO FILTRAR)'!$I:$I) -> Boston Consulting | D63: Asesoría técnica para la planificación e implementación de las oportunidades de mejora identificadas en la etapa de diagnóstico de Mina Inmaculada | E63: =+_xlfn.XLOOKUP(B63,'POM 2024'!B:B,'POM 2024'!F:F,"!",0,1) -> Claudio Hernández | F63: =+_xlfn.XLOOKUP(B63,'POM 2024'!B:B,'POM 2024'!H:H,"!",0,1) -> Claudio Hernández | G63: =+J63 -> 40000 | H63: 0 | I63: =+SUM(G63:H63) -> 40000 | J63: =VLOOKUP(B63,'POM 2024'!$B$2:$BI$64,48,FALSE) -> 40000 | K63: =+_xlfn.XLOOKUP($B63,'POM 2024'!B:B,'POM 2024'!AP:AP,"!",0,1) -> 0 | L63: =+_xlfn.XLOOKUP($B63,'POM 2024'!B:B,'POM 2024'!AU:AU,"!",0,1) -> 0 | M63: =+J63-K63 -> 40000 | N63: =+IFERROR(((J63-K63)/K63),0) -> 0 | O63: =IF(_xlfn.XLOOKUP($B63,'POM 2024'!B:B,'POM 2024'!L:L,"!",0,1)<0,0,_xlfn.XLOOKUP($B63,'POM 2024'!B:B,'POM 2024'!L:L,"!",0,1)) -> 0 | P63: =+O63-L63 -> 0 | S63: Rezagado | T63: Terminado | U63: =+I63=J63 -> TRUE
B64: Spence_Confiabilidad Plan 2YB 2025 | C64: =+_xlfn.XLOOKUP(B64,'[1]Proyectos (NO FILTRAR)'!$F:$F,'[1]Proyectos (NO FILTRAR)'!$I:$I) -> BHP | D64: Estudio Confiabilidad Plan 2YB 2025 | E64: =+_xlfn.XLOOKUP(B64,'POM 2024'!B:B,'POM 2024'!F:F,"!",0,1) -> - | F64: =+_xlfn.XLOOKUP(B64,'POM 2024'!B:B,'POM 2024'!H:H,"!",0,1) -> Felipe Matamoros | G64: =+J64 -> 0 | H64: 0 | I64: =+SUM(G64:H64) -> 0 | J64: =VLOOKUP(B64,'POM 2024'!$B$2:$BI$64,48,FALSE) -> 0 | K64: =+_xlfn.XLOOKUP($B64,'POM 2024'!B:B,'POM 2024'!AP:AP,"!",0,1) -> 0 | L64: =+_xlfn.XLOOKUP($B64,'POM 2024'!B:B,'POM 2024'!AU:AU,"!",0,1) -> 0 | M64: =+J64-K64 -> 0 | N64: =+IFERROR(((J64-K64)/K64),0) -> 0 | O64: =IF(_xlfn.XLOOKUP($B64,'POM 2024'!B:B,'POM 2024'!L:L,"!",0,1)<0,0,_xlfn.XLOOKUP($B64,'POM 2024'!B:B,'POM 2024'!L:L,"!",0,1)) -> 0 | P64: =+O64-L64 -> 0 | S64: Rezagado | T64: Terminado | U64: =+I64=J64 -> TRUE
B65: Minsur_Apoyo MEIA Raura | C65: =+_xlfn.XLOOKUP(B65,'[1]Proyectos (NO FILTRAR)'!$F:$F,'[1]Proyectos (NO FILTRAR)'!$I:$I) -> Minsur | D65: Apoyo MEIA Raura | E65: =+_xlfn.XLOOKUP(B65,'POM 2024'!B:B,'POM 2024'!F:F,"!",0,1) -> Claudio Hernández | F65: =+_xlfn.XLOOKUP(B65,'POM 2024'!B:B,'POM 2024'!H:H,"!",0,1) -> TBD | G65: =+J65 -> 0 | H65: 0 | I65: =+SUM(G65:H65) -> 0 | J65: =VLOOKUP(B65,'POM 2024'!$B$2:$BI$64,48,FALSE) -> 0 | K65: =+_xlfn.XLOOKUP($B65,'POM 2024'!B:B,'POM 2024'!AP:AP,"!",0,1) -> 0 | L65: =+_xlfn.XLOOKUP($B65,'POM 2024'!B:B,'POM 2024'!AU:AU,"!",0,1) -> 0 | M65: =+J65-K65 -> 0 | N65: =+IFERROR(((J65-K65)/K65),0) -> 0 | O65: =IF(_xlfn.XLOOKUP($B65,'POM 2024'!B:B,'POM 2024'!L:L,"!",0,1)<0,0,_xlfn.XLOOKUP($B65,'POM 2024'!B:B,'POM 2024'!L:L,"!",0,1)) -> 0 | P65: =+O65-L65 -> 0 | S65: Rezagado | T65: Terminado | U65: =+I65=J65 -> TRUE
B66: Romeral | C66: =+_xlfn.XLOOKUP(B66,'[1]Proyectos (NO FILTRAR)'!$F:$F,'[1]Proyectos (NO FILTRAR)'!$I:$I) -> CMP | D66: Proyecto Estabilización y Optimización de Romeral | E66: =+_xlfn.XLOOKUP(B66,#REF!,#REF!,"!",0,1) -> #REF! | F66: =+_xlfn.XLOOKUP(B66,#REF!,#REF!,"!",0,1) -> #REF! | G66: 0 | H66: =+J66 -> 0 | I66: =+SUM(G66:H66) -> 0 | J66: =VLOOKUP(B66,'POM 2024'!$B$2:$BI$59,42,FALSE) -> 0 | K66: =+_xlfn.XLOOKUP($B66,'POM 2024'!B:B,'POM 2024'!AP:AP,"!",0,1) -> 0 | L66: =+_xlfn.XLOOKUP($B66,'POM 2024'!B:B,'POM 2024'!AO:AO,"!",0,1) -> 0 | M66: =+J66-K66 -> 0 | N66: =+IFERROR(((J66-K66)/K66),0) -> 0 | O66: =IF(_xlfn.XLOOKUP($B66,'POM 2024'!B:B,'POM 2024'!L:L,"!",0,1)<0,0,_xlfn.XLOOKUP($B66,'POM 2024'!B:B,'POM 2024'!L:L,"!",0,1)) -> 0 | P66: =+O66-L66 -> 0 | Q66: Gastos reembolsables y residual de tratamiento aguas | R66: Administrativo | S66: Rezagado | T66: Terminado | U66: =+I66=J66 -> TRUE
G67: =+SUM(G62:G66) -> 40000 | H67: =+SUM(H62:H66) -> 0 | I67: =+SUM(I62:I66) -> 40000 | J67: =+SUM(J62:J66) -> 40000 | K67: =+SUM(K62:K66) -> 0 | L67: =+SUM(L62:L66) -> 0 | M67: =+SUM(M62:M66) -> 40000 | N67: =+IFERROR(((J67-K67)/K67),0) -> 0 | O67: =+SUM(O62:O66) -> 6045.98 | P67: =+SUM(P62:P66) -> 6045.98
C71: =+C61 -> Cliente | D71: =+D61 -> Nombre Proyecto | E71: =+E61 -> Director | F71: =+F61 -> Ing Principal | G71: =+G61 -> Real | H71: =+H61 -> Otros | I71: =+I61 -> 0 | J71: =+J61 -> EDP Real | ... P71: =+P61 -> Saldo Proy | Q71: =+Q52 -> Comentarios | R71: Tipo 1 | S71: Tipo 2 | T71: Estatus
B72: Banco Santander_Yauricocha y Bolivar | C72: =+_xlfn.XLOOKUP(B72,'[1]Proyectos (NO FILTRAR)'!$F:$F,'[1]Proyectos (NO FILTRAR)'!$I:$I) -> Banco Santander | D72: Gap Analisis & Auditoria de Recursos - Yauricocha y Bolivar | E72: =+_xlfn.XLOOKUP(B72,'POM 2024'!B:B,'POM 2024'!F:F,"!",0,1) -> Emilio Sánchez | F72: =+_xlfn.XLOOKUP(B72,'POM 2024'!B:B,'POM 2024'!H:H,"!",0,1) -> TBD | G72: =+J72 -> 0 | H72: 0 | I72: =+SUM(G72:H72) -> 0 | J72: =VLOOKUP(B72,'POM 2024'!$B$2:$BI$64,48,FALSE) -> 0 | K72: =+_xlfn.XLOOKUP($B72,'POM 2024'!B:B,'POM 2024'!AP:AP,"!",0,1) -> 0 | L72: =+_xlfn.XLOOKUP($B72,'POM 2024'!B:B,'POM 2024'!AU:AU,"!",0,1) -> 0 | M72: =+J72-K72 -> 0 | N72: =+IFERROR(((J72-K72)/K72),0) -> 0 | O72: =IF(_xlfn.XLOOKUP($B72,'POM 2024'!B:B,'POM 2024'!L:L,"!",0,1)<0,0,_xlfn.XLOOKUP($B72,'POM 2024'!B:B,'POM 2024'!L:L,"!",0,1)) -> 0 | P72: =+O72-L72 -> 0 | S72: Ejecución | T72: Terminado | U72: =+I72=J72 -> TRUE
B73: Glencore_MineHaul y MinePlan Lomas Bayas | C73: =+_xlfn.XLOOKUP(B73,'[1]Proyectos (NO FILTRAR)'!$F:$F,'[1]Proyectos (NO FILTRAR)'!$I:$I) -> Glencore | D73: MineHaul y MinePlan Lomas Bayas | E73: =+_xlfn.XLOOKUP(B73,'POM 2024'!B:B,'POM 2024'!F:F,"!",0,1) -> Cristian Quezada | F73: =+_xlfn.XLOOKUP(B73,'POM 2024'!B:B,'POM 2024'!H:H,"!",0,1) -> - | G73: =+J73 -> 0 | H73: 0 | I73: =+SUM(G73:H73) -> 0 | J73: =VLOOKUP(B73,'POM 2024'!$B$2:$BI$73,48,FALSE) -> 0 | K73: =+_xlfn.XLOOKUP($B73,'POM 2024'!B:B,'POM 2024'!AV:AV,"!",0,1) -> 0 | L73: =+_xlfn.XLOOKUP($B73,'POM 2024'!B:B,'POM 2024'!AU:AU,"!",0,1) -> 4800 | M73: =+J73-L73 -> -4800 | N73: =+IFERROR(((J73-K73)/K73),0) -> 0 | O73: =IF(_xlfn.XLOOKUP($B73,'POM 2024'!B:B,'POM 2024'!L:L,"!",0,1)<0,0,_xlfn.XLOOKUP($B73,'POM 2024'!B:B,'POM 2024'!L:L,"!",0,1)) -> 0 | Q73: KOM esta semana, aun no tiene inicio el estudio. | U73: =+I73=J73 -> TRUE
B74: Minsur_LOM San Rafael 2025 | C74: =+_xlfn.XLOOKUP(B74,'[1]Proyectos (NO FILTRAR)'!$F:$F,'[1]Proyectos (NO FILTRAR)'!$I:$I) -> Minsur | D74: Actualización del LOM San Rafael | E74: =+_xlfn.XLOOKUP(B74,'POM 2024'!B:B,'POM 2024'!F:F,"!",0,1) -> - | F74: =+_xlfn.XLOOKUP(B74,'POM 2024'!B:B,'POM 2024'!H:H,"!",0,1) -> Kevin Rios | G74: =+J74 -> 84801.87 | H74: 0 | I74: =+SUM(G74:H74) -> 84801.87 | J74: =VLOOKUP(B74,'POM 2024'!$B$2:$BI$73,48,FALSE) -> 84801.87 | K74: =+_xlfn.XLOOKUP($B74,'POM 2024'!B:B,'POM 2024'!AV:AV,"!",0,1) -> 0 | L74: =+_xlfn.XLOOKUP($B74,'POM 2024'!B:B,'POM 2024'!AU:AU,"!",0,1) -> 0 | M74: =+J74-L74 -> 84801.87 | N74: =+IFERROR(((J74-K74)/K74),0) -> 0 | O74: =IF(_xlfn.XLOOKUP($B74,'POM 2024'!B:B,'POM 2024'!L:L,"!",0,1)<0,0,_xlfn.XLOOKUP($B74,'POM 2024'!B:B,'POM 2024'!L:L,"!",0,1)) -> 0 | Q74: No se han emitido EDP
B75: Mosaic_Actualizacion geotecnica OP | C75: =+_xlfn.XLOOKUP(B75,'[1]Proyectos (NO FILTRAR)'!$F:$F,'[1]Proyectos (NO FILTRAR)'!$I:$I) -> Mosaic | D75: Actualización del estudio de estabilidad física del tajo abierto de Cajati | E75: =+_xlfn.XLOOKUP(B75,'POM 2024'!B:B,'POM 2024'!F:F,"!",0,1) -> - | F75: =+_xlfn.XLOOKUP(B75,'POM 2024'!B:B,'POM 2024'!H:H,"!",0,1) -> - | G75: =+J75 -> 0 | H75: 0 | I75: =+SUM(G75:H75) -> 0 | J75: =VLOOKUP(B75,'POM 2024'!$B$2:$BI$73,48,FALSE) -> 0 | K75: =+_xlfn.XLOOKUP($B75,'POM 2024'!B:B,'POM 2024'!AV:AV,"!",0,1) -> 0 | L75: =+_xlfn.XLOOKUP($B75,'POM 2024'!B:B,'POM 2024'!AU:AU,"!",0,1) -> 0 | M75: =+J75-L75 -> 0 | N75: =+IFERROR(((J75-K75)/K75),0) -> 0 | O75: =IF(_xlfn.XLOOKUP($B75,'POM 2024'!B:B,'POM 2024'!L:L,"!",0,1)<0,0,_xlfn.XLOOKUP($B75,'POM 2024'!B:B,'POM 2024'!L:L,"!",0,1)) -> 4771 | Q75: Aun no comienza no va a tener EDO
B76: BHP_Plan e Iniciativas LoA25-26 | C76: =+_xlfn.XLOOKUP(B76,'[1]Proyectos (NO FILTRAR)'!$F:$F,'[1]Proyectos (NO FILTRAR)'!$I:$I) -> BHP | D76: Análisis de confiabilidad y detección de cuellos de botella del LoA 2025-26 | E76: =+_xlfn.XLOOKUP(B76,'POM 2024'!B:B,'POM 2024'!F:F,"!",0,1) -> - | F76: =+_xlfn.XLOOKUP(B76,'POM 2024'!B:B,'POM 2024'!H:H,"!",0,1) -> - | G76: =+J76 -> 0 | H76: 0 | I76: =+SUM(G76:H76) -> 0 | J76: =VLOOKUP(B76,'POM 2024'!$B$2:$BI$73,48,FALSE) -> 0 | K76: =+_xlfn.XLOOKUP($B76,'POM 2024'!B:B,'POM 2024'!AV:AV,"!",0,1) -> 0 | L76: =+_xlfn.XLOOKUP($B76,'POM 2024'!B:B,'POM 2024'!AU:AU,"!",0,1) -> 0 | M76: =+J76-L76 -> 0 | N76: =+IFERROR(((J76-K76)/K76),0) -> 0 | O76: =IF(_xlfn.XLOOKUP($B76,'POM 2024'!B:B,'POM 2024'!L:L,"!",0,1)<0,0,_xlfn.XLOOKUP($B76,'POM 2024'!B:B,'POM 2024'!L:L,"!",0,1)) -> 23795 | Q76: Carlos Morante (revisar)
B77: CMP_Nuevos alcances Algarrobo | C77: =+_xlfn.XLOOKUP(B77,'[1]Proyectos (NO FILTRAR)'!$F:$F,'[1]Proyectos (NO FILTRAR)'!$I:$I) -> CMP | D77: Nuevos alcances de “Estudio de Factibilidad de la explotación de stocks de mineral marginal de Algarrobo” | E77: =+_xlfn.XLOOKUP(B77,'POM 2024'!B:B,'POM 2024'!F:F,"!",0,1) -> Claudio Hernández | F77: =+_xlfn.XLOOKUP(B77,'POM 2024'!B:B,'POM 2024'!H:H,"!",0,1) -> Jorman Barrera | G77: =+J77 -> 0 | H77: 0 | I77: =+SUM(G77:H77) -> 0 | J77: =VLOOKUP(B77,'POM 2024'!$B$2:$BI$73,48,FALSE) -> 0 | K77: =+_xlfn.XLOOKUP($B77,'POM 2024'!B:B,'POM 2024'!AV:AV,"!",0,1) -> 0 | L77: =+_xlfn.XLOOKUP($B77,'POM 2024'!B:B,'POM 2024'!AU:AU,"!",0,1) -> 0 | M77: =+J77-L77 -> 0 | N77: =+IFERROR(((J77-K77)/K77),0) -> 0 | O77: =IF(_xlfn.XLOOKUP($B77,'POM 2024'!B:B,'POM 2024'!L:L,"!",0,1)<0,0,_xlfn.XLOOKUP($B77,'POM 2024'!B:B,'POM 2024'!L:L,"!",0,1)) -> 112506 | Q77: Claudio Hernandez
B78: Minsur_Apoyo Planificacion San Rafael | C78: =+_xlfn.XLOOKUP(B78,'[1]Proyectos (NO FILTRAR)'!$F:$F,'[1]Proyectos (NO FILTRAR)'!$I:$I) -> Minsur | D78: Apoyo a la planificación de San Rafael | E78: =+_xlfn.XLOOKUP(B78,'POM 2024'!B:B,'POM 2024'!F:F,"!",0,1) -> Matias Fuentes | F78: =+_xlfn.XLOOKUP(B78,'POM 2024'!B:B,'POM 2024'!H:H,"!",0,1) -> Kevin Rios | G78: =+J78 -> 32242 | H78: 0 | I78: =+SUM(G78:H78) -> 32242 | J78: =VLOOKUP(B78,'POM 2024'!$B$2:$BI$73,48,FALSE) -> 32242 | K78: =+_xlfn.XLOOKUP($B78,'POM 2024'!B:B,'POM 2024'!AV:AV,"!",0,1) -> 0 | L78: =+_xlfn.XLOOKUP($B78,'POM 2024'!B:B,'POM 2024'!AU:AU,"!",0,1) -> 47545.26 | M78: =+J78-L78 -> -15303.26 | N78: =+IFERROR(((J78-K78)/K78),0) -> 0 | O78: =IF(_xlfn.XLOOKUP($B78,'POM 2024'!B:B,'POM 2024'!L:L,"!",0,1)<0,0,_xlfn.XLOOKUP($B78,'POM 2024'!B:B,'POM 2024'!L:L,"!",0,1)) -> 0 | P78: =+O78-L78 -> -47545.26 | Q78: Correo enviado | U78: =+I78=J78 -> TRUE
B79: Capstone Copper_Estimacion confiabilidad de planes | C79: =+_xlfn.XLOOKUP(B79,'[1]Proyectos (NO FILTRAR)'!$F:$F,'[1]Proyectos (NO FILTRAR)'!$I:$I) -> Capstone Copper | D79: Estimación de confiabilidad de planes mineros | E79: =+_xlfn.XLOOKUP(B79,'POM 2024'!B:B,'POM 2024'!F:F,"!",0,1) -> Cristian Quezada | F79: =+_xlfn.XLOOKUP(B79,'POM 2024'!B:B,'POM 2024'!H:H,"!",0,1) -> TBD | G79: =+J79 -> 62422 | H79: 0 | I79: =+SUM(G79:H79) -> 62422 | J79: =VLOOKUP(B79,'POM 2024'!$B$2:$BI$73,48,FALSE) -> 62422 | K79: =+_xlfn.XLOOKUP($B79,'POM 2024'!B:B,'POM 2024'!AV:AV,"!",0,1) -> 0 | L79: =+_xlfn.XLOOKUP($B79,'POM 2024'!B:B,'POM 2024'!AU:AU,"!",0,1) -> 54551.28 | M79: =+J79-L79 -> 7870.72 | N79: =+IFERROR(((J79-K79)/K79),0) -> 0 | O79: =IF(_xlfn.XLOOKUP($B79,'POM 2024'!B:B,'POM 2024'!L:L,"!",0,1)<0,0,_xlfn.XLOOKUP($B79,'POM 2024'!B:B,'POM 2024'!L:L,"!",0,1)) -> 200 | P79: =+O79-L79 -> -54351.28 | Q79: Con Pedro Aguiluz - Nico y Gonzalo Diaz | U79: =+I79=J79 -> TRUE
B80: Minsur_Rampa de acceso San German | C80: =+_xlfn.XLOOKUP(B80,'[1]Proyectos (NO FILTRAR)'!$F:$F,'[1]Proyectos (NO FILTRAR)'!$I:$I) -> Minsur | D80: Estudio conceptual justificación rampa de acceso sector San German | E80: =+_xlfn.XLOOKUP(B80,'POM 2024'!B:B,'POM 2024'!F:F,"!",0,1) -> Matias Fuentes | F80: =+_xlfn.XLOOKUP(B80,'POM 2024'!B:B,'POM 2024'!H:H,"!",0,1) -> Kevin Rios | G80: =+J80 -> 53339 | H80: 0 | I80: =+SUM(G80:H80) -> 53339 | J80: =VLOOKUP(B80,'POM 2024'!$B$2:$BI$73,48,FALSE) -> 53339 | K80: =+_xlfn.XLOOKUP($B80,'POM 2024'!B:B,'POM 2024'!AV:AV,"!",0,1) -> 0 | L80: =+_xlfn.XLOOKUP($B80,'POM 2024'!B:B,'POM 2024'!AU:AU,"!",0,1) -> 64710 | M80: =+J80-L80 -> -11371 | N80: =+IFERROR(((J80-K80)/K80),0) -> 0 | O80: =IF(_xlfn.XLOOKUP($B80,'POM 2024'!B:B,'POM 2024'!L:L,"!",0,1)<0,0,_xlfn.XLOOKUP($B80,'POM 2024'!B:B,'POM 2024'!L:L,"!",0,1)) -> 0 | P80: =+O80-L80 -> -64710 | Q80: Kevin Rios | U80: =+I80=J80 -> TRUE
B81: McCarthy_Litigio Rio Tinto | C81: =+_xlfn.XLOOKUP(B81,'[1]Proyectos (NO FILTRAR)'!$F:$F,'[1]Proyectos (NO FILTRAR)'!$I:$I) -> McCarthy | D81: Soporte técnico experto - Proyecto Oyu Tolgoi UG | E81: =+_xlfn.XLOOKUP(B81,'POM 2024'!B:B,'POM 2024'!F:F,"!",0,1) -> Mauricio Melendez | F81: =+_xlfn.XLOOKUP(B81,'POM 2024'!B:B,'POM 2024'!H:H,"!",0,1) -> TBD | G81: =+J81 -> 283900 | H81: 0 | I81: =+SUM(G81:H81) -> 283900 | J81: =VLOOKUP(B81,'POM 2024'!$B$2:$BI$73,48,FALSE) -> 283900 | K81: =+_xlfn.XLOOKUP($B81,'POM 2024'!B:B,'POM 2024'!AV:AV,"!",0,1) -> 0 | L81: =+_xlfn.XLOOKUP($B81,'POM 2024'!B:B,'POM 2024'!AU:AU,"!",0,1) -> 0 | M81: =+J81-L81 -> 283900 | N81: =+IFERROR(((J81-K81)/K81),0) -> 0 | O81: =IF(_xlfn.XLOOKUP($B81,'POM 2024'!B:B,'POM 2024'!L:L,"!",0,1)<0,0,_xlfn.XLOOKUP($B81,'POM 2024'!B:B,'POM 2024'!L:L,"!",0,1)) -> 38700 | P81: =+O81-L81 -> 38700 | Q81: Pedro Aguiluz y con Mauricio Melendez | U81: =+I81=J81 -> TRUE
G82: =+SUM(G72:G81) -> 516704.87 | H82: =+SUM(H72:H81) -> 0 | I82: =+SUM(I72:I81) -> 516704.87 | J82: =+SUM(J72:J81) -> 516704.87 | K82: =+SUM(K72:K81) -> 0 | L82: =+SUM(L72:L81) -> 171606.54 | M82: =+SUM(M72:M81) -> 345098.33 | N82: =+IFERROR(((J82-K82)/K82),0) -> 0 | O82: =+SUM(O72:O81) -> 179972 | P82: =+SUM(P72:P81) -> -127906.54

Sheet Curva S
A1: Código | B1: Proyectos | C1: 45139 | D1: 45170 | E1: 45200 | F1: 45231 | G1: 45261 | H1: 45292 | I1: 45323 | J1: 45352 | K1: 45383 | L1: 45413 | M1: 45444 | N1: 45474 | O1: 45505 | P1: 45536 | Q1: 45566 | R1: 45597 | S1: 45627
B2: Actualización LoM Raura | C2: 0 | D2: 1 | E2: 1 | F2: 1 | G2: 1 | H2: 1
B3: Candelaria (Estandar y Planificacion) | C3: 0.56 | D3: 0.56 | E3: 0.56 | F3: 0.56 | G3: 0.56 | H3: 0.56
B4: CMP - FEL 2A | C4: 0.94 | D4: 0.9560571 | E4: 1 | F4: 1 | G4: 1 | H4: 1 | I4: 1 | J4: 1 | K4: 1 | L4: 1 | M4: 1 | N4: 1 | O4: 1 | P4: 1 | Q4: 1 | R4: 1 | S4: 1
B5: Adrianita -Raúl | C5: 1 | D5: 1 | E5: 1 | F5: 1 | G5: 1 | H5: 1
B6: Codelco_Falla Oeste | C6: 0.16 | D6: 0.66 | E6: 0.88 | F6: 1 | G6: 1 | H6: 1
B7: Codelco_Panel Central | C7: 0.22 | D7: 0.63 | E7: 0.85 | F7: 1 | G7: 1 | H7: 1
B8: Diagnóstico Operacional Candelaria | C8: 0.95 | D8: 1 | E8: 1 | F8: 1 | G8: 1 | H8: 1
B9: Sierra Metals_Plan de Minado MEIA | C9: 0 | D9: 0.49 | E9: 0.78 | F9: 1 | G9: 1 | H9: 1 | I9: 1
B10: Mosaic_Cajati | C10: 0.34 | D10: 0.45313995 | E10: 0.24 | F10: 0.52 | G10: 0.8 | H10: 0.6 | I10: 0.76 | J10: 0.9 | K10: 1 | L10: 1 | M10: 1 | N10: 1 | O10: 1 | P10: 1 | Q10: 1 | R10: 1 | S10: 1
B11: Mosaic_Taquari Vassouras | C11: 0 | D11: 0.06 | E11: 0.41 | F11: 0.62 | G11: 0.88 | H11: 1 | I11: 1 | J11: 1 | K11: 1
B12: NEXA_FEL2 Aripuana | C12: 0 | D12: 0.09 | E12: 0.43 | F12: 0.44 | G12: 1 | H12: 1 | I12: 1 | J12: 1 | K12: 1 | L12: 1 | M12: 1 | N12: 1 | O12: 1 | P12: 1 | Q12: 1 | R12: 1 | S12: 1
B13: Romeral | C13: 0.89 | D13: 1 | E13: 1 | F13: 1 | G13: 1 | H13: 1
B14: Minsur_Forecast_Budget24 | C14: 0 | D14: 0.69 | E14: 1 | F14: 1 | G14: 1 | H14: 1
B15: San Rafael: Gestión del Corto Plazo | C15: 0.09 | D15: 0.24 | E15: 0.85 | F15: 1 | G15: 1 | H15: 1
B16: Lomas Bayas - LoA24 | C16: 1 | D16: 1 | E16: 1 | F16: 1 | G16: 1 | H16: 1
B17: Pilares Mineros - Candelaria | C17: 1 | D17: 1 | E17: 1 | F17: 1 | G17: 1 | H17: 1
B18: LOM CNN 2023 | C18: 1 | D18: 1 | E18: 1 | F18: 1 | G18: 1 | H18: 1
B19: LOM MLC 2023 | C19: 1 | D19: 1 | E19: 1 | F19: 1 | G19: 1 | H19: 1
B20: Algarrobo | C20: 1 | D20: 1 | E20: 1 | F20: 0.4 | G20: 1 | H20: 1
B21: CMP - FEL 2A | C21: 0 | D21: 0.12 | E21: 0.3 | F21: 1 | G21: 1 | H21: 1 | I21: 1 | J21: 1 | K21: 1 | L21: 1 | M21: 1 | N21: 1 | O21: 1 | P21: 1 | Q21: 1 | R21: 1 | S21: 1 | T21: Update de Modelos
B22: RDP | C22: 1 | D22: 1 | E22: 1 | F22: 1 | G22: 1 | H22: 1
B23: San Rafael Gestión Operativa | C23: 1 | D23: 1 | E23: 1 | F23: 1 | G23: 1 | H23: 1
B24: NorGold | C24: 1 | D24: 1 | E24: 1 | F24: 1 | G24: 1 | H24: 1
B25: Marcobre - Minajusta | C25: 1 | D25: 1 | E25: 1 | F25: 1 | G25: 1 | H25: 1
B26: PFS Los Calatos | F26: 0.1 | G26: 0.19 | H26: 0.22 | I26: 0.23 | J26: 0.34 | K26: 0.49 | L26: 0.54 | M26: 0.7 | N26: 0.82 | O26: =94% -> 0.94 | P26: 1 | Q26: 1 | R26: 1 | S26: 1
B27: CSH_LOM Mina Guarello
B28: AMSA_Planificacion | F28: 0.15 | G28: 0.92 | H28: 1
B29: MEIA Coripuno | E29: 0.24 | F29: 0.89 | G29: 1 | N29: 1
B30: Codelco_Capacitacion Deswik DET | F30: 0.43 | G30: 0.87 | H30: 1 | I30: 0.89 | K30: 0.94 | L30: 1
B31: Codelco_Drenaje QT | H31: 0.6 | I31: 0.84 | J31: 1
B32: MiskiMayo_LOM | H32: 0.5 | I32: 0.65 | J32: 0.87 | K32: 0.85 | L32: 1
B33: CMP_CNN Update plan LOM | H33: 1 | I33: 1 | J33: 1
B34: CMP_Los Colorados Adelantamiento Planta | H34: 0.43 | I34: 1 | J34: 1 | K34: 1 | L34: 1
B35: LasBambas_Ferrobamba_OP_UG | H35: 0.5 | I35: 0.63 | J35: 0.79 | K35: 0.54 | L35: 0.82 | M35: 0.91 | N35: 1
B36: CMP_Romeral Estabilización + UG PFS | H36: 0.08 | I36: 0.31 | J36: 0.53 | K36: 0.67 | L36: 0.56 | M36: 0.9 | N36: 1
B37: Codelco_Cluster Toki | H37: 1 | I37: 1 | J37: 1
B38: IvanhoeElectric_Santa-Cruz_PrePFS | H38: 0.34 | I38: 0.61 | J38: 0.87 | K38: 0.93 | L38: 1 | M38: 1
B39: Boston_Inmaculada Hochschild | J39: 1
B40: Minsur_Update LOM San Rafael | I40: 1
B41: Lundin_Candelaria_EstudiosCugep | J41: 0.06 | K41: 0.62 | L41: 0.93 | M41: 1 | N41: 1
B42: Seligdar_Kyuchus | J42: 0.03 | K42: 0.06 | M42: 0.21 | N42: 0.26 | O42: 0.31 | P42: 0.38 | Q42: 0.42 | R42: 0.48 | S42: 0.62
B43: BHP_Tunel Exploratorio
B44: AMSA_Asesoria Centinela | J44: 0.276 | K44: 0.71 | L44: 1 | M44: 1 | N44: 1
B45: AMSA_Estandares Minimos | K45: 0.6 | L45: 0.7 | M45: 0.71 | N45: 0.97 | O45: 1
B46: Glencore_Coroccohuayco_OptimizacionLOM | K46: 0.37 | L46: 0.85 | M46: 1 | N46: 1
B47: Coripuno_Metodos de Minado | K47: 0.06 | L47: 0.55 | M47: 0.76 | N47: 1
B48: =+'POM 2024'!B49 -> Banco Santander_Yauricocha y Bolivar | L48: =AVERAGE(0.1,0.15,0.21) -> 0.15333333 | M48: =AVERAGE(0.1,0.15,0.21) -> 0.15333333 | N48: =AVERAGE(0.3,0.58,0.62) -> 0.5 | O48: =AVERAGE(0.84,0.82,0.69) -> 0.78333333 | P48: 1
B49: =+'POM 2024'!B50 -> Minsur_Apoyo Planificacion San Rafael | L49: =AVERAGE(0.14,0.17,0.11) -> 0.14 | M49: =AVERAGE(0.14,0.17,0.11) -> 0.14 | N49: =AVERAGE(0.38,0.57,0.24) -> 0.39666667 | O49: =AVERAGE(0.8,0.65,0.47) -> 0.64 | P49: =AVERAGE(0.89,0.71,0.58) -> 0.72666667 | Q49: =AVERAGE(0.96,0.77,0.78) -> 0.83666667 | R49: 1
B50: J&F_Urucrum_RecuperacionPilares | L50: 0.23 | M50: 0.5 | N50: 0.71 | O50: 0.76 | P50: 0.85 | Q50: 0.96 | R50: 1
B51: =+'POM 2024'!B51 -> Capstone Copper_Estimacion confiabilidad de planes | N51: 0.28 | O51: 0.59 | P51: 0.79 | Q51: 1
B52: =+'POM 2024'!B52 -> Minsur_Rampa de acceso San German | L52: =AVERAGE(0.1,0.2,0.53) -> 0.27666667 | M52: 0.89 | N52: 1
B53: =+'POM 2024'!B53 -> McCarthy_Litigio Rio Tinto | L53: 0.14 | M53: 0.14 | N53: 0.39666667 | O53: 0.64 | P53: 0.72666667 | Q53: 0.83666667 | R53: 1 | V53: =40-14 -> 26
B54: =+'POM 2024'!B54 -> Eurochem_Himmelfarb Deposit | L54: 0.03 | M54: 0.1 | N54: 0.68 | O54: 0.97 | P54: 1
B55: =+'POM 2024'!B55 -> J&F_Urucrum_RecuperacionPilares | L55: 0.2 | M55: 0.55
B56: =+'POM 2024'!B56 -> Boston_Inmaculada Hochschild II | M56: 1
B57: =+'POM 2024'!B57 -> Spence_Confiabilidad Plan 2YB 2025 | L57: 1
B58: =+'POM 2024'!B58 -> Minsur_Mejoramiento datos geotecnicos SR
B59: =+'POM 2024'!B59 -> Minsur_Apoyo MEIA Raura | L59: 1
B60: =+'POM 2024'!B60 -> LOM CNN 2023
B61: =+'POM 2024'!B61 -> CMP_LOM MLC 2024
B62: =+'POM 2024'!B62 -> CMP_Puesta en marcha SLS Romeral
B63: MCI_Mine Plan Review Los Bronces | M63: 0.28 | N63: 0.59 | O63: 0.79 | P63: 1
B64: Minsur_LOM San Rafael 2025
B65: EMX_Due Diligence de Chapi
B66: IvanhoeElectric_Mine Planning Support
B67: J&F_Autazes Due Diligence | N67: 1
B68: SierraMetals_Update MEIA Yauricocha | N68: 0.31 | O68: 0.83 | P68: 1
B69: Glencore_MineHaul y MinePlan Lomas Bayas | N69: 0.4 | O69: 1
B70: EMX_Due Diligence de Chapi
B71: Minsur_LOM San Rafael 2025
B72: Mosaic_Actualizacion geotecnica OP
B73: BHP_Plan e Iniciativas LoA25-26
B74: Permiología Algarrobo

Sheet Formato Backlog_Sept25
F1: =SUM(F22:F25) -> 366737 | G1: =SUM(G22:G25) -> 297004 | H1: =+G1/F1 -> 0.80985556 | I1: =SUM(I22:I25) -> 69733 | J1: =+I1/F1 -> 0.19014444
A3: Código | B3: Proyecto | C3: País | D3: Año Inicio | E3: Director | F3: Contrato US$ | G3: Emitido US$ | H3: Avance Financiero% | I3: Saldo US$ | J3: Saldo % | K3: Saldo Acum% | L3: Saldo Acum
A4: BR-EQG-UG-FEL03-172-A | B4: EQUINOX_Actualización Ing. Básica UG | C4: Brasil | D4: 2025 | E4: Alex Figueroa | F4: 330237.61 | G4: 12415 | H4: =+G4/F4 -> 0.037594143 | I4: =+F4-G4 -> 317822.61 | J4: =+I4/F4 -> 0.96240586 | K4: =+L4/$L$24 -> 0.14236106 | L4: =+I4 -> 317822.61
A5: BR-ERC-UG-FEL00-152-A | B5: EroCopper_Scoping Proyecto Furnas | C5: Brasil | D5: 2025 | E5: Alex Figueroa | F5: 484000 | G5: 223644 | H5: =+G5/F5 -> 0.46207438 | I5: =+F5-G5 -> 260356 | J5: =+I5/F5 -> 0.53792562 | K5: =+L5/$L$24 -> 0.25898133 | L5: =+L4+I5 -> 578178.61
A6: PE-MMG-UG-FEL2A-143-A | B6: LasBambas_Ferrobamba PFS | C6: Perú | D6: 2025 | E6: JF San Martin | F6: 920000 | G6: 665060.59 | H6: =+G6/F6 -> 0.72289195 | I6: =+F6-G6 -> 254939.41 | J6: =+I6/F6 -> 0.27710805 | K6: =+L6/$L$24 -> 0.37317536 | L6: =+L5+I6 -> 833118.02
A7: OT-RES-CS-OTR00-178-A | B7: Resolution_General Review | C7: Otros | D7: 2025 | E7: Carolina Arcos | F7: 185615 | G7: 0 | H7: =+G7/F7 -> 0 | I7: =+F7-G7 -> 185615 | J7: =+I7/F7 -> 1 | K7: =+L7/$L$24 -> 0.45631717 | L7: =+L6+I7 -> 1018733
A8: PE-ALP-GM-FEL00-156-A | B8: Alpayana_Estudio de Sismicidad | C8: Perú | D8: 2025 | E8: Claudio Hernández | F8: 197494 | G8: 43788 | H8: =+G8/F8 -> 0.22171813 | I8: =+F8-G8 -> 153706 | J8: =+I8/F8 -> 0.77828187 | K8: =+L8/$L$24 -> 0.52516611 | L8: =+L7+I8 -> 1172439
A9: CH-AMS-OP-FEL00-171-A | B9: AMSA_RIINO BC - Centinela | C9: Chile | D9: 2025 | E9: Felipe Rojas | F9: 141656.26 | G9: 0 | H9: =+G9/F9 -> 0 | I9: =+F9-G9 -> 141656.26 | J9: =+I9/F9 -> 1 | K9: =+L9/$L$24 -> 0.58861766 | L9: =+L8+I9 -> 1314095.3
A10: CH-CRF-CS-FEL00-169-A | B10: CORFO_Valorización Boquerón Chañar | C10: Chile | D10: 2025 | E10: Carolina Arcos | F10: 123838.96 | G10: 0 | H10: =+G10/F10 -> 0 | I10: =+F10-G10 -> 123838.96 | J10: =+I10/F10 -> 1 | K10: =+L10/$L$24 -> 0.64408837 | L10: =+L9+I10 -> 1437934.2
A11: PE-SPM-UG-FEL03-160-A | B11: SPM_FS Labores Subterraneas 2da MEIA | C11: Perú | D11: 2025 | E11: Sin Director | F11: 99244 | G11: 0 | H11: =+G11/F11 -> 0 | I11: =+F11-G11 -> 99244 | J11: =+I11/F11 -> 1 | K11: =+L11/$L$24 -> 0.68854235 | L11: =+L10+I11 -> 1537178.2
A12: BR-MOS-UG-OTR00-098-A | B12: Mosaic_Taquari Vassouras Fase II | C12: Brasil | D12: 2024 | E12: Claudio Hernández | F12: 330410 | G12: 242146.09 | H12: =+G12/F12 -> 0.7328655 | I12: =+F12-G12 -> 88263.91 | J12: =+I12/F12 -> 0.2671345 | K12: =+L12/$L$24 -> 0.72807807 | L12: =+L11+I12 -> 1625442.1
A13: PE-NEX-GM-FEL00-167-A | B13: NEXA_Estudio Geomecánico AT y EP | C13: Perú | D13: 2025 | E13: Claudio Hernández | F13: 80283 | G13: 0 | H13: =+G13/F13 -> 0 | I13: =+F13-G13 -> 80283 | J13: =+I13/F13 -> 1 | K13: =+L13/$L$24 -> 0.76403892 | L13: =+L12+I13 -> 1705725.1
A14: CH-AMS-CS-OTR00-165-A | B14: AMSA_Mejoras Planificación Centinela | C14: Chile | D14: 2025 | E14: Felipe Rojas | F14: 80125 | G14: 0 | H14: =+G14/F14 -> 0 | I14: =+F14-G14 -> 80125 | J14: =+I14/F14 -> 1 | K14: =+L14/$L$24 -> 0.79992901 | L14: =+L13+I14 -> 1785850.1
A15: CH-CCO-CS-OTR00-159-A | B15: Capstone Copper_Production at Risk | C15: Chile | D15: 2025 | E15: Gonzalo Díaz | F15: 148240 | G15: 88297 | H15: =+G15/F15 -> 0.59563546 | I15: =+F15-G15 -> 59943 | J15: =+I15/F15 -> 0.40436454 | K15: =+L15/$L$24 -> 0.82677905 | L15: =+L14+I15 -> 1845793.1
A16: CH-AAM-CS-OTR00-179-A | B16: Anglo_Production at Risk Mina Rio | C16: Chile | D16: 2025 | E16: Gonzalo Díaz | F16: 84870 | G16: 26973 | H16: =+G16/F16 -> 0.31781548 | I16: =+F16-G16 -> 57897 | J16: =+I16/F16 -> 0.68218452 | K16: =+L16/$L$24 -> 0.85271263 | L16: =+L15+I16 -> 1903690.1
... A24: PE-MSR-UG-FEL00-142-A | B24: Minsur_San Rafael Estudio V MEIA | C24: Perú | D24: 2025 | E24: JF San Martin | F24: 231021 | G24: 222625 | H24: =+G24/F24 -> 0.96365698 | I24: =+F24-G24 -> 8396 | J24: =+I24/F24 -> 0.036343016 | K24: =+L24/$L$24 -> 1 | L24: =+L23+I24 -> 2232510.8
A29: Etiquetas de fila | B29: Suma de Saldo US$ | C29: %
A30: Brasil | B30: 747122.17 | C30: =+B30/$B$34 -> 0.33465557
A31: Perú | B31: 626284.41 | C31: =+B31/$B$34 -> 0.28052917
A32: Chile | B32: 621089.22 | C32: =+B32/$B$34 -> 0.27820211
A33: Otros | B33: 238015 | C33: =+B33/$B$34 -> 0.10661315
A34: Total general | B34: 2232510.8 | C34: =+B34/$B$34 -> 1
A37: Etiquetas de fila | B37: Suma de Saldo US$ | C37: Cuenta de Saldo US$2
A38: Alex Figueroa | B38: 627237.26 | C38: 3
A39: Claudio Hernández | B39: 351968.91 | C39: 4
A40: Carolina Arcos | B40: 341074.96 | C40: 3
A41: Felipe Rojas | B41: 324917.26 | C41: 4
A42: JF San Martin | B42: 263335.41 | C42: 2
A43: Sin Director | B43: 206137 | C43: 3
A44: Gonzalo Díaz | B44: 117840 | C44: 2
A45: Total general | B45: 2232510.8 | C45: 21
A51: Etiquetas de fila | B51: Suma de Saldo US$ | C51: Cuenta de Saldo US$2
A52: Alex Figueroa | B52: 627237.26 | C52: 3 | D52: =+B52/$B$59 -> 0.28095598
A53: Claudio Hernández | B53: 351968.91 | C53: 4 | D53: =+B53/$B$59 -> 0.15765608
A54: Carolina Arcos | B54: 341074.96 | C54: 3 | D54: =+B54/$B$59 -> 0.1527764
A55: Felipe Rojas | B55: 324917.26 | C55: 4 | D55: =+B55/$B$59 -> 0.14553894
A56: JF San Martin | B56: 263335.41 | C56: 2 | D56: =+B56/$B$59 -> 0.11795482
A57: Sin Director | B57: 206137 | C57: 3 | D57: =+B57/$B$59 -> 0.092334156
A58: Gonzalo Díaz | B58: 117840 | C58: 2 | D58: =+B58/$B$59 -> 0.052783619
B59: =SUM(B52:B58) -> 2232510.8 | C59: =SUM(C52:C58) -> 21
A62: Etiquetas de fila | B62: Suma de Contrato US$ | C62: Cuenta de Contrato US$2
A63: JF San Martin | B63: 1151021 | C63: 2
A64: Alex Figueroa | B64: 892245.26 | C64: 3
A65: Claudio Hernández | B65: 637903 | C65: 4
A66: Felipe Rojas | B66: 573543.26 | C66: 4
A67: Carolina Arcos | B67: 415453.96 | C67: 3
A68: Gonzalo Díaz | B68: 233110 | C68: 2
A69: Sin Director | B69: 229644 | C69: 3
A70: Total general | B70: 4132920.5 | C70: 21
A72: Etiquetas de fila | B72: Suma de Contrato US$ | C72: Cuenta de Contrato US$2
A73: JF San Martin | B73: 1151021 | C73: 2 | D73: =+B73/$B$80 -> 0.27850064
A74: Alex Figueroa | B74: 892245.26 | C74: 3 | D74: =+B74/$B$80 -> 0.21588735
A75: Claudio Hernández | B75: 637903 | C75: 4 | D75: =+B75/$B$80 -> 0.15434679
A76: Felipe Rojas | B76: 573543.26 | C76: 4 | D76: =+B76/$B$80 -> 0.13877433
A77: Carolina Arcos | B77: 415453.96 | C77: 3 | D77: =+B77/$B$80 -> 0.1005231
A78: Gonzalo Díaz | B78: 233110 | C78: 2 | D78: =+B78/$B$80 -> 0.056403214
A79: Sin Director | B79: 229644 | C79: 3 | D79: =+B79/$B$80 -> 0.055564582
B80: =SUM(B73:B79) -> 4132920.5 | C80: =SUM(C73:C79) -> 21

Sheet POM 2024
AE1: =+COUNTIF(AE3:AE88,">0") -> 15 | AF1: =+COUNTIF(AF3:AF73,">0") -> 17 | AG1: =+COUNTIF(AG3:AG73,">0") -> 17 | AH1: =+COUNTIF(AH3:AH88,">0") -> 15 | AI1: =+COUNTIF(AI3:AI73,">0") -> 17 | AJ1: =+COUNTIF(AJ3:AJ73,">0") -> 15 | AK1: =+COUNTIF(AK3:AK88,">0") -> 11 | AL1: =+COUNTIF(AL3:AL73,">0") -> 17 | AM1: =+COUNTIF(AM3:AM73,">0") -> 17 | AN1: =+COUNTIF(AN3:AN88,">0") -> 14 | AO1: =+COUNTIF(AO3:AO73,">0") -> 16 | AP1: =+COUNTIF(AP3:AP73,">0") -> 0 | AQ1: =+COUNTIF(AQ3:AQ88,">0") -> 12 | AR1: =+COUNTIF(AR3:AR73,">0") -> 18 | AS1: =+COUNTIF(AS3:AS73,">0") -> 13 | AT1: =+COUNTIF(AT3:AT88,">0") -> 12 | AU1: =+COUNTIF(AU3:AU73,">0") -> 20 | AV1: =+COUNTIF(AV3:AV73,">0") -> 11 | AW1: =+COUNTIF(AW3:AW88,">0") -> 28 | AX1: =+COUNTIF(AX3:AX48,">0") -> 3 | AY1: =+COUNTIF(AY3:AY48,">0") -> 0 | AZ1: =+COUNTIF(AZ3:AZ88,">0") -> 17 | BA1: =+COUNTIF(BA3:BA48,">0") -> 3 | BB1: =+COUNTIF(BB3:BB48,">0") -> 0 | BC1: =+COUNTIF(BC3:BC88,">0") -> 18 | BD1: =+COUNTIF(BD3:BD48,">0") -> 1 | BE1: =+COUNTIF(BE3:BE94,">0") -> 16 | BF1: =+COUNTIF(BF3:BF94,">0") -> 24 | BG1: =+COUNTIF(BG3:BG94,">0") -> 18 | BH1: =+COUNTIF(BH3:BH96,">0") -> 23 | BI1: =+COUNTIF(BI3:BI94,">0") -> 19
A2: Código | B2: Proyecto | C2: País | D2: Estado Comercial | E2: Estado Operativo | F2: Director | G2: Consultor | H2: Ingeniero Principal | I2: Monto Contrato (USD) | J2: Emitido Acumulado Actual [USD] | K2: Avance Financiero Actual % | L2: Saldo actual [USD] | M2: Saldo actual % | N2: Acumulado Proyectado (USD) | O2: Avance Proyectado % | P2: Saldo Proyectado (USD) | Q2: Emitido Acumulado 2023 | R2: Saldo 2024 (USD) | S2: SEPT POM | T2: SEPT R | U2: OCT RESAGADO | V2: OCT F | W2: OCT R | X2: NOV F | Y2: NOV R | Z2: DIC F | AA2: DIC P | AB2: DIC R | AC2: ENE F | AD2: ENE P | AE2: ENE R | AF2: FEB F | AG2: FEB P | AH2: FEB R | AI2: MAR F | AJ2: MAR P | AK2: MAR R | AL2: ABR F | AM2: ABR P | AN2: ABR R | AO2: MAY F | AP2: MAY P | AQ2: MAY R | AR2: JUN F | AS2: JUN P | AT2: JUN R | AU2: JUL F | AV2: JUL P | AW2: JUL R | AX2: AGO F | AY2: AGO P | AZ2: AGO R | BA2: SEP F | BB2: SEP P | BC2: SEP R | BD2: OCT P | BE2: OCT R | BF2: NOV P | BG2: NOV R | BH2: DIC P | BI2: DIC R | BK2: Oct | BL2: Nov | BM2: Dic
A3: =+_xlfn.XLOOKUP(B3,'[1]Proyectos (NO FILTRAR)'!$F:$F,'[1]Proyectos (NO FILTRAR)'!$B:$B,0,0,1) -> PE-MSR-UG-FEL03-008-A | B3: Actualización LoM Raura | C3: =+_xlfn.XLOOKUP(A3,'[1]Proyectos (NO FILTRAR)'!$B:$B,'[1]Proyectos (NO FILTRAR)'!$G:$G,"error",0,1) -> Perú | D3: Adjudicado | E3: Terminado | G3: Matias Fuentes | H3: Jorman Barrera | I3: 165237 | J3: =+Q3+AE3+AH3+AK3+AN3+AQ3+AT3+AW3+AZ3+BC3+BE3+BG3+BI3 -> 165237 | K3: =+IFERROR(J3/I3,0) -> 1 | L3: =+I3-J3 -> 0 | M3: =+IFERROR(L3/I3,0) -> 0 | O3: =IFERROR(N3/I3,0) -> 0 | P3: =+I3-N3 -> 165237 | Q3: 165237 | R3: =+I3-Q3 -> 0 | S3: 165237 | T3: 165237 | U3: 0 | V3: 0 | W3: 0 | X3: 0 | Z3: 0 | AA3: 0 | AC3: 0 | AF3: 0 | AI3: 0 | AL3: 0 | AO3: 0 | AR3: 0 | AU3: 0 | AX3: =+IF((_xlfn.XLOOKUP($B3,'Curva S'!$B$2:$B$100,'Curva S'!$O$2:$O$100,0,0,1)*$I3-$J3)<0,0,(_xlfn.XLOOKUP($B3,'Curva S'!$B$2:$B$100,'Curva S'!$O$2:$O$100,0,0,1)*$I3-$J3)) -> 0 | BA3: =+IF((_xlfn.XLOOKUP($B3,'Curva S'!$B$2:$B$100,'Curva S'!$P$2:$P$100,0,0,1)*$I3-$J3)<0,0,(_xlfn.XLOOKUP($B3,'Curva S'!$B$2:$B$100,'Curva S'!$P$2:$P$100,0,0,1)*$I3-$J3)) -> 0 | BK3: =+IF(AND(BD3>0,BE3=""),0,IF(BE3="","",IF(BE3>=BD3,1,BE3/BD3))) | BL3: =+IF(AND(BF3>0,BG3=""),0,IF(BG3="","",IF(BG3>=BF3,1,BG3/BF3))) | BM3: =+IF(AND(BH3>0,BI3=""),0,IF(BI3="","",IF(BI3>=BH3,1,BI3/BH3)))
A4: =+_xlfn.XLOOKUP(B4,'[1]Proyectos (NO FILTRAR)'!$F:$F,'[1]Proyectos (NO FILTRAR)'!$B:$B,0,0,1) -> CH-LUN-CS-OTR00-004-A | B4: Candelaria (Estandar y Planificacion) | C4: =+_xlfn.XLOOKUP(A4,'[1]Proyectos (NO FILTRAR)'!$B:$B,'[1]Proyectos (NO FILTRAR)'!$G:$G,"error",0,1) -> Chile | D4: Adjudicado | E4: Terminado | G4: Ricardo Miranda | H4: Felipe Matamoros | I4: 139847.12 | J4: =+Q4+AE4+AH4+AK4+AN4+AQ4+AT4+AW4+AZ4+BC4+BE4+BG4+BI4 -> 139847.12 | K4: =+IFERROR(J4/I4,0) -> 1 | L4: =+I4-J4 -> 0 | M4: =+IFERROR(L4/I4,0) -> 0 | O4: =IFERROR(N4/I4,0) -> 0 | P4: =+I4-N4 -> 139847.12 | Q4: 139847.12 | R4: =+I4-Q4 -> 0 | S4: 0 | T4: 0 | U4: 0 | V4: 0 | W4: 0 | X4: 0 | Z4: 0 | AA4: 0 | AC4: 0 | AF4: 0 | AI4: 0 | AL4: 0 | AO4: 0 | AR4: 0 | AU4: 0 | AX4: =+IF((_xlfn.XLOOKUP($B4,'Curva S'!$B$2:$B$100,'Curva S'!$O$2:$O$100,0,0,1)*$I4-$J4)<0,0,(_xlfn.XLOOKUP($B4,'Curva S'!$B$2:$B$100,'Curva S'!$O$2:$O$100,0,0,1)*$I4-$J4)) -> 0 | BA4: 0 | BK4: =+IF(AND(BD4>0,BE4=""),0,IF(BE4="","",IF(BE4>=BD4,1,BE4/BD4))) | BL4: =+IF(AND(BF4>0,BG4=""),0,IF(BG4="","",IF(BG4>=BF4,1,BG4/BF4))) | BM4: =+IF(AND(BH4>0,BI4=""),0,IF(BI4="","",IF(BI4>=BH4,1,BI4/BH4)))
A5: =+_xlfn.XLOOKUP(B5,'[1]Proyectos (NO FILTRAR)'!$F:$F,'[1]Proyectos (NO FILTRAR)'!$B:$B,0,0,1) -> CH-CMP-OU-FEL2A-033-A | B5: CMP - FEL 2A | C5: =+_xlfn.XLOOKUP(A5,'[1]Proyectos (NO FILTRAR)'!$B:$B,'[1]Proyectos (NO FILTRAR)'!$G:$G,"error",0,1) -> Chile | D5: Adjudicado | E5: En Proceso | F5: Alex Figueroa | G5: Felipe Rojas | H5: Felipe Lira | I5: 610108.79 | J5: =+Q5+AE5+AH5+AK5+AN5+AQ5+AT5+AW5+AZ5+BC5+BE5+BG5+BI5 -> 610108.79 | K5: =+IFERROR(J5/I5,0) -> 1 | L5: =+I5-J5 -> 0 | M5: =+IFERROR(L5/I5,0) -> 0 | O5: =IFERROR(N5/I5,0) -> 0 | P5: =+I5-N5 -> 610108.79 | Q5: 558961.99 | R5: =+I5-Q5 -> 51146.8 | S5: 37300 | T5: 21340 | U5: 15960 | V5: 25588.89 | W5: 9211.06 | X5: 28678.52 | Y5: =31481-Y22 -> 1672.39 | Z5: 27006.13 | AA5: 27006.13 | AB5: 7306 | AC5: 19700.13 | AD5: 19700.13 | AE5: 16995 | AF5: 2705.13 | AG5: 2705 | AH5: 2022.8 | AI5: 15886.33 | AJ5: 0 | AL5: 15886.33 | AM5: 10691 | AN5: 1896 | AO5: 13990.33 | AQ5: =10289-1314 -> 8975 | AR5: 25170.52 | AS5: 21258 | AT5: 21258 | AU5: 0 | AX5: =+IF((_xlfn.XLOOKUP($B5,'Curva S'!$B$2:$B$100,'Curva S'!$O$2:$O$100,0,0,1)*$I5-$J5)<0,0,(_xlfn.XLOOKUP($B5,'Curva S'!$B$2:$B$100,'Curva S'!$O$2:$O$100,0,0,1)*$I5-$J5)) -> 0 | BA5: 0 | BK5: =+IF(AND(BD5>0,BE5=""),0,IF(BE5="","",IF(BE5>=BD5,1,BE5/BD5))) | BL5: =+IF(AND(BF5>0,BG5=""),0,IF(BG5="","",IF(BG5>=BF5,1,BG5/BF5))) | BM5: =+IF(AND(BH5>0,BI5=""),0,IF(BI5="","",IF(BI5>=BH5,1,BI5/BH5)))
A6: =+_xlfn.XLOOKUP(B6,'[1]Proyectos (NO FILTRAR)'!$F:$F,'[1]Proyectos (NO FILTRAR)'!$B:$B,0,0,1) -> CH-CMP-OU-FEL00-001-A | B6: Adrianita -Raúl | C6: =+_xlfn.XLOOKUP(A6,'[1]Proyectos (NO FILTRAR)'!$B:$B,'[1]Proyectos (NO FILTRAR)'!$G:$G,"error",0,1) -> Chile | D6: Adjudicado | E6: Terminado | G6: Ricardo Miranda | H6: Ricardo Miranda | I6: 261767.16 | J6: =+Q6+AE6+AH6+AK6+AN6+AQ6+AT6+AW6+AZ6+BC6+BE6+BG6+BI6 -> 261767.16 | K6: =+IFERROR(J6/I6,0) -> 1 | L6: =+I6-J6 -> 0 | M6: =+IFERROR(L6/I6,0) -> 0 | O6: =IFERROR(N6/I6,0) -> 0 | P6: =+I6-N6 -> 261767.16 | Q6: 261767.16 | R6: =+I6-Q6 -> 0 | S6: 1136.0975 | T6: 274 | U6: 51143 | V6: 0 | W6: 51143 | X6: 0 | Z6: 0 | AA6: 0 | AC6: 0 | AF6: 0 | AI6: 0 | AL6: 0 | AO6: 0 | AR6: 0 | AU6: 0 | AX6: =+IF((_xlfn.XLOOKUP($B6,'Curva S'!$B$2:$B$100,'Curva S'!$O$2:$O$100,0,0,1)*$I6-$J6)<0,0,(_xlfn.XLOOKUP($B6,'Curva S'!$B$2:$B$100,'Curva S'!$O$2:$O$100,0,0,1)*$I6-$J6)) -> 0 | BA6: 0 | BK6: =+IF(AND(BD6>0,BE6=""),0,IF(BE6="","",IF(BE6>=BD6,1,BE6/BD6))) | BL6: =+IF(AND(BF6>0,BG6=""),0,IF(BG6="","",IF(BG6>=BF6,1,BG6/BF6))) | BM6: =+IF(AND(BH6>0,BI6=""),0,IF(BI6="","",IF(BI6>=BH6,1,BI6/BH6)))
A7: =+_xlfn.XLOOKUP(B7,'[1]Proyectos (NO FILTRAR)'!$F:$F,'[1]Proyectos (NO FILTRAR)'!$B:$B,0,0,1) -> CH-COD-UG-FEL01-031-A | B7: Codelco_Falla Oeste | C7: =+_xlfn.XLOOKUP(A7,'[1]Proyectos (NO FILTRAR)'!$B:$B,'[1]Proyectos (NO FILTRAR)'!$G:$G,"error",0,1) -> Chile | D7: Adjudicado | E7: Terminado | G7: Mauricio Melendez | H7: Freddy Diaz | I7: 93503 | J7: =+Q7+AE7+AH7+AK7+AN7+AQ7+AT7+AW7+AZ7+BC7+BE7+BG7+BI7 -> 93503 | K7: =+IFERROR(J7/I7,0) -> 1 | L7: =+I7-J7 -> 0 | M7: =+IFERROR(L7/I7,0) -> 0 | O7: =IFERROR(N7/I7,0) -> 0 | P7: =+I7-N7 -> 93503 | Q7: 93503 | R7: =+I7-Q7 -> 0 | S7: 61711.98 | T7: 67556 | U7: 0 | V7: 20570.66 | W7: 19139 | X7: 6808 | Y7: 6808 | Z7: 0 | AA7: 0 | AC7: 0 | AF7: 0 | AI7: 0 | AL7: 0 | AO7: 0 | AR7: 0 | AU7: 0 | AX7: =+IF((_xlfn.XLOOKUP($B7,'Curva S'!$B$2:$B$100,'Curva S'!$O$2:$O$100,0,0,1)*$I7-$J7)<0,0,(_xlfn.XLOOKUP($B7,'Curva S'!$B$2:$B$100,'Curva S'!$O$2:$O$100,0,0,1)*$I7-$J7)) -> 0 | BA7: 0 | BK7: =+IF(AND(BD7>0,BE7=""),0,IF(BE7="","",IF(BE7>=BD7,1,BE7/BD7))) | BL7: =+IF(AND(BF7>0,BG7=""),0,IF(BG7="","",IF(BG7>=BF7,1,BG7/BF7))) | BM7: =+IF(AND(BH7>0,BI7=""),0,IF(BI7="","",IF(BI7>=BH7,1,BI7/BH7)))
A8: =+_xlfn.XLOOKUP(B8,'[1]Proyectos (NO FILTRAR)'!$F:$F,'[1]Proyectos (NO FILTRAR)'!$B:$B,0,0,1) -> CH-COD-UG-FEL01-032-A | B8: Codelco_Panel Central | C8: =+_xlfn.XLOOKUP(A8,'[1]Proyectos (NO FILTRAR)'!$B:$B,'[1]Proyectos (NO FILTRAR)'!$G:$G,"error",0,1) -> Chile | D8: Adjudicado | E8: Terminado | G8: Mauricio Melendez | H8: Freddy Diaz | I8: 88171 | J8: =+Q8+AE8+AH8+AK8+AN8+AQ8+AT8+AW8+AZ8+BC8+BE8+BG8+BI8 -> 88171 | K8: =+IFERROR(J8/I8,0) -> 1 | L8: =+I8-J8 -> 0 | M8: =+IFERROR(L8/I8,0) -> 0 | O8: =IFERROR(N8/I8,0) -> 0 | P8: =+I8-N8 -> 88171 | Q8: 88171 | R8: =+I8-Q8 -> 0 | S8: 55585.53 | T8: 62838 | U8: 0 | V8: 19410.82 | W8: 17202 | X8: 8191 | Y8: 8131 | Z8: 0 | AA8: 0 | AC8: 0 | AF8: 0 | AI8: 0 | AL8: 0 | AO8: 0 | AR8: 0 | AU8: 0 | AX8: =+IF((_xlfn.XLOOKUP($B8,'Curva S'!$B$2:$B$100,'Curva S'!$O$2:$O$100,0,0,1)*$I8-$J8)<0,0,(_xlfn.XLOOKUP($B8,'Curva S'!$B$2:$B$100,'Curva S'!$O$2:$O$100,0,0,1)*$I8-$J8)) -> 0 | BA8: 0 | BK8: =+IF(AND(BD8>0,BE8=""),0,IF(BE8="","",IF(BE8>=BD8,1,BE8/BD8))) | BL8: =+IF(AND(BF8>0,BG8=""),0,IF(BG8="","",IF(BG8>=BF8,1,BG8/BF8))) | BM8: =+IF(AND(BH8>0,BI8=""),0,IF(BI8="","",IF(BI8>=BH8,1,BI8/BH8)))
A9: =+_xlfn.XLOOKUP(B9,'[1]Proyectos (NO FILTRAR)'!$F:$F,'[1]Proyectos (NO FILTRAR)'!$B:$B,0,0,1) -> CH-LUN-CS-OTR00-007-A | B9: Diagnóstico Operacional Candelaria | C9: =+_xlfn.XLOOKUP(A9,'[1]Proyectos (NO FILTRAR)'!$B:$B,'[1]Proyectos (NO FILTRAR)'!$G:$G,"error",0,1) -> Chile | D9: Adjudicado | E9: Terminado | G9: Ricardo Miranda | H9: Emilio Sánchez | I9: 178540.96 | J9: =+Q9+AE9+AH9+AK9+AN9+AQ9+AT9+AW9+AZ9+BC9+BE9+BG9+BI9 -> 178540.96 | K9: =+IFERROR(J9/I9,0) -> 1 | L9: =+I9-J9 -> 0 | M9: =+IFERROR(L9/I9,0) -> 0 | O9: =IFERROR(N9/I9,0) -> 0 | P9: =+I9-N9 -> 178540.96 | Q9: 178540.96 | R9: =+I9-Q9 -> 0 | S9: 21776.04 | T9: 29101 | U9: 0 | V9: 0 | W9: 0 | X9: 0 | Z9: 0 | AA9: 0 | AC9: 0 | AF9: 0 | AI9: 0 | AL9: 0 | AO9: 0 | AR9: 0 | AU9: 0 | AX9: =+IF((_xlfn.XLOOKUP($B9,'Curva S'!$B$2:$B$100,'Curva S'!$O$2:$O$100,0,0,1)*$I9-$J9)<0,0,(_xlfn.XLOOKUP($B9,'Curva S'!$B$2:$B$100,'Curva S'!$O$2:$O$100,0,0,1)*$I9-$J9)) -> 0 | BA9: 0 | BK9: =+IF(AND(BD9>0,BE9=""),0,IF(BE9="","",IF(BE9>=BD9,1,BE9/BD9))) | BL9: =+IF(AND(BF9>0,BG9=""),0,IF(BG9="","",IF(BG9>=BF9,1,BG9/BF9))) | BM9: =+IF(AND(BH9>0,BI9=""),0,IF(BI9="","",IF(BI9>=BH9,1,BI9/BH9)))
A10: =+_xlfn.XLOOKUP(B10,'[1]Proyectos (NO FILTRAR)'!$F:$F,'[1]Proyectos (NO FILTRAR)'!$B:$B,0,0,1) -> PE-SME-UG-FEL2A-046-A | B10: Sierra Metals_Plan de Minado MEIA | C10: =+_xlfn.XLOOKUP(A10,'[1]Proyectos (NO FILTRAR)'!$B:$B,'[1]Proyectos (NO FILTRAR)'!$G:$G,"error",0,1) -> Perú | D10: Adjudicado | E10: Terminado | G10: Matias Fuentes | H10: Carlos Catalán | I10: 56629 | J10: =+Q10+AE10+AH10+AK10+AN10+AQ10+AT10+AW10+AZ10+BC10+BE10+BG10+BI10 -> 56629 | K10: =+IFERROR(J10/I10,0) -> 1 | L10: =+I10-J10 -> 0 | M10: =+IFERROR(L10/I10,0) -> 0 | O10: =IFERROR(N10/I10,0) -> 0 | P10: =+I10-N10 -> 56629 | Q10: 36682 | R10: =+I10-Q10 -> 19947 | S10: 27748.7 | T10: 0 | U10: 11178.7 | V10: 16422.7 | W10: 0 | X10: 18705 | Y10: 36682 | Z10: 0 | AA10: 0 | AC10: 0 | AD10: 0 | AF10: 19948 | AG10: 19948 | AH10: 14729 | AI10: 0 | AL10: 0 | AO10: 0 | AR10: 0 | AU10: 0 | AX10: =+IF((_xlfn.XLOOKUP($B10,'Curva S'!$B$2:$B$100,'Curva S'!$O$2:$O$100,0,0,1)*$I10-$J10)<0,0,(_xlfn.XLOOKUP($B10,'Curva S'!$B$2:$B$100,'Curva S'!$O$2:$O$100,0,0,1)*$I10-$J10)) -> 0 | AZ10: 5218 | BA10: 0 | BK10: =+IF(AND(BD10>0,BE10=""),0,IF(BE10="","",IF(BE10>=BD10,1,BE10/BD10))) | BL10: =+IF(AND(BF10>0,BG10=""),0,IF(BG10="","",IF(BG10>=BF10,1,BG10/BF10))) | BM10: =+IF(AND(BH10>0,BI10=""),0,IF(BI10="","",IF(BI10>=BH10,1,BI10/BH10)))
A11: =+_xlfn.XLOOKUP(B11,'[1]Proyectos (NO FILTRAR)'!$F:$F,'[1]Proyectos (NO FILTRAR)'!$B:$B,0,0,1) -> BR-MOS-OU-FEL03-026-A | B11: Mosaic_Cajati | C11: =+_xlfn.XLOOKUP(A11,'[1]Proyectos (NO FILTRAR)'!$B:$B,'[1]Proyectos (NO FILTRAR)'!$G:$G,"error",0,1) -> Brasil | D11: Adjudicado | E11: Terminado | F11: Alex Figueroa | G11: Alex Figueroa | H11: Pablo Quiero | I11: =647241+78000 -> 725241 | J11: =+Q11+AE11+AH11+AK11+AN11+AQ11+AT11+AW11+AZ11+BC11+BE11+BG11+BI11 -> 717694.46 | K11: =+IFERROR(J11/I11,0) -> 0.98959444 | L11: =+I11-J11 -> 7546.54 | M11: =+IFERROR(L11/I11,0) -> 0.010405562 | O11: =IFERROR(N11/I11,0) -> 0 | P11: =+I11-N11 -> 725241 | Q11: 368694.46 | R11: =+I11-Q11 -> 356546.54 | S11: 132966.72 | T11: 29306 | U11: 103660.72 | W11: 23474 | X11: 175963.6 | Y11: 103264 | Z11: 188102.03 | AA11: 188102.03 | AB11: =36629+12172 -> 48801 | AC11: 111795.92 | AD11: 20000 | AE11: 31463 | AF11: 176976.29 | AG11: 40000 | AH11: 72122 | AI11: 78758.44 | AJ11: 127854.49 | AK11: =186908+11425 -> 198333 | AL11: 35947.54 | AM11: 25111.86 | AN11: 31640 | AO11: 22988.54 | AR11: 22988.54 | AS11: 0 | AU11: 22988.54 | AV11: 22988.54 | AW11: 15442 | AX11: =+IF((_xlfn.XLOOKUP($B11,'Curva S'!$B$2:$B$100,'Curva S'!$O$2:$O$100,0,0,1)*$I11-$J11)<0,0,(_xlfn.XLOOKUP($B11,'Curva S'!$B$2:$B$100,'Curva S'!$O$2:$O$100,0,0,1)*$I11-$J11)) -> 7546.54 | BA11: 7546.54 | BK11: =+IF(AND(BD11>0,BE11=""),0,IF(BE11="","",IF(BE11>=BD11,1,BE11/BD11))) | BL11: =+IF(AND(BF11>0,BG11=""),0,IF(BG11="","",IF(BG11>=BF11,1,BG11/BF11))) | BM11: =+IF(AND(BH11>0,BI11=""),0,IF(BI11="","",IF(BI11>=BH11,1,BI11/BH11)))
A12: =+_xlfn.XLOOKUP(B12,'[1]Proyectos (NO FILTRAR)'!$F:$F,'[1]Proyectos (NO FILTRAR)'!$B:$B,0,0,1) -> BR-MOS-UG-FEL01-028-A | B12: Mosaic_Taquari Vassouras | C12: =+_xlfn.XLOOKUP(A12,'[1]Proyectos (NO FILTRAR)'!$B:$B,'[1]Proyectos (NO FILTRAR)'!$G:$G,"error",0,1) -> Brasil | D12: Adjudicado | E12: En Proceso | F12: Mauricio Melendez | G12: Alex Figueroa | H12: Kevin Rios | I12: 284632.92 | J12: =+Q12+AE12+AH12+AK12+AN12+AQ12+AT12+AW12+AZ12+BC12+BE12+BG12+BI12 -> 284632.92 | K12: =+IFERROR(J12/I12,0) -> 1 | L12: =+I12-J12 -> 0 | M12: =+IFERROR(L12/I12,0) -> 0 | O12: =IFERROR(N12/I12,0) -> 0 | P12: =+I12-N12 -> 284632.92 | Q12: 232261.92 | R12: =+I12-Q12 -> 52371 | S12: 16907.22 | T12: 34067 | U12: 0 | V12: 81465.67 | W12: 39226 | X12: 129266.28 | Y12: 92850.92 | Z12: 101765.91 | AA12: 93670.895 | AB12: 66118 | AC12: 52371.08 | AD12: 52371.08 | AE12: 41400 | AF12: 10971.08 | AG12: 10971 | AH12: =6798 -> 6798 | AI12: 0 | AJ12: 4173.08 | AL12: 4173.08 | AM12: 4173 | AN12: 4173 | AO12: 0 | AR12: 0 | AU12: 0 | AX12: =+IF((_xlfn.XLOOKUP($B12,'Curva S'!$B$2:$B$100,'Curva S'!$O$2:$O$100,0,0,1)*$I12-$J12)<0,0,(_xlfn.XLOOKUP($B12,'Curva S'!$B$2:$B$100,'Curva S'!$O$2:$O$100,0,0,1)*$I12-$J12)) -> 0 | BA12: 0 | BK12: =+IF(AND(BD12>0,BE12=""),0,IF(BE12="","",IF(BE12>=BD12,1,BE12/BD12))) | BL12: =+IF(AND(BF12>0,BG12=""),0,IF(BG12="","",IF(BG12>=BF12,1,BG12/BF12))) | BM12: =+IF(AND(BH12>0,BI12=""),0,IF(BI12="","",IF(BI12>=BH12,1,BI12/BH12)))
A13: =+_xlfn.XLOOKUP(B13,'[1]Proyectos (NO FILTRAR)'!$F:$F,'[1]Proyectos (NO FILTRAR)'!$B:$B,0,0,1) -> BR-NEX-UG-FEL2A-027-A | B13: NEXA_FEL2 Aripuana | C13: =+_xlfn.XLOOKUP(A13,'[1]Proyectos (NO FILTRAR)'!$B:$B,'[1]Proyectos (NO FILTRAR)'!$G:$G,"error",0,1) -> Brasil | D13: Adjudicado | E13: Terminado | F13: Matias Fuentes | G13: Matias Fuentes | H13: Andres Budini | I13: 207726.08 | J13: =+Q13+AE13+AH13+AK13+AN13+AQ13+AT13+AW13+AZ13+BC13+BE13+BG13+BI13 -> 204231 | K13: =+IFERROR(J13/I13,0) -> 0.98317457 | L13: =+I13-J13 -> 3495.0816 | M13: =+IFERROR(L13/I13,0) -> 0.016825435 | O13: =IFERROR(N13/I13,0) -> 0 | P13: =+I13-N13 -> 207726.08 | Q13: 128437 | R13: =+I13-Q13 -> 79289.082 | S13: 24763.59 | T13: 11644 | U13: 13119.59 | V13: 93551.34 | W13: 16248 | X13: 71041.96 | Y13: 29518 | Z13: 112739 | AA13: 112739 | AB13: 71027 | AC13: 68900 | AD13: 71918 | AE13: 31925 | AF13: 43247 | AG13: 36975 | AI13: 43247 | AJ13: 46417 | AL13: 43247 | AM13: 43247 | AO13: 43247 | AR13: 0 | AU13: 47364.082 | AW13: 43869 | AX13: =+IF((_xlfn.XLOOKUP($B13,'Curva S'!$B$2:$B$100,'Curva S'!$O$2:$O$100,0,0,1)*$I13-$J13)<0,0,(_xlfn.XLOOKUP($B13,'Curva S'!$B$2:$B$100,'Curva S'!$O$2:$O$100,0,0,1)*$I13-$J13)) -> 3495.0816 | BA13: 3495.0816 | BK13: =+IF(AND(BD13>0,BE13=""),0,IF(BE13="","",IF(BE13>=BD13,1,BE13/BD13))) | BL13: =+IF(AND(BF13>0,BG13=""),0,IF(BG13="","",IF(BG13>=BF13,1,BG13/BF13))) | BM13: =+IF(AND(BH13>0,BI13=""),0,IF(BI13="","",IF(BI13>=BH13,1,BI13/BH13)))
A14: =+_xlfn.XLOOKUP(B14,'[1]Proyectos (NO FILTRAR)'!$F:$F,'[1]Proyectos (NO FILTRAR)'!$B:$B,0,0,1) -> CH-CMP-OP-OTR00-018-A | B14: Romeral | C14: =+_xlfn.XLOOKUP(A14,'[1]Proyectos (NO FILTRAR)'!$B:$B,'[1]Proyectos (NO FILTRAR)'!$G:$G,"error",0,1) -> Chile | D14: Adjudicado | E14: Terminado | G14: Ricardo Miranda | H14: Felipe Matamoros | I14: 645045.4 | J14: =+Q14+AE14+AH14+AK14+AN14+AQ14+AT14+AW14+AZ14+BC14+BE14+BG14+BI14 -> 645045.4 | K14: =+IFERROR(J14/I14,0) -> 1 | L14: =+I14-J14 -> 0 | M14: =+IFERROR(L14/I14,0) -> 0 | O14: =IFERROR(N14/I14,0) -> 0 | P14: =+I14-N14 -> 645045.4 | Q14: 635530.4 | R14: =+I14-Q14 -> 9515 | S14: 61272.138 | T14: 38387 | U14: 22885.138 | V14: 0 | W14: 21231 | X14: 1654.1375 | Y14: 90409 | Z14: 0 | AA14: 0 | AC14: 0 | AD14: 0 | AE14: 9515 | AF14: 0 | AI14: 0 | AL14: 0 | AO14: 0 | AR14: 0 | AU14: 0 | AX14: =+IF((_xlfn.XLOOKUP($B14,'Curva S'!$B$2:$B$100,'Curva S'!$O$2:$O$100,0,0,1)*$I14-$J14)<0,0,(_xlfn.XLOOKUP($B14,'Curva S'!$B$2:$B$100,'Curva S'!$O$2:$O$100,0,0,1)*$I14-$J14)) -> 0 | BA14: 0 | BK14: =+IF(AND(BD14>0,BE14=""),0,IF(BE14="","",IF(BE14>=BD14,1,BE14/BD14))) | BL14: =+IF(AND(BF14>0,BG14=""),0,IF(BG14="","",IF(BG14>=BF14,1,BG14/BF14))) | BM14: =+IF(AND(BH14>0,BI14=""),0,IF(BI14="","",IF(BI14>=BH14,1,BI14/BH14)))
A15: =+_xlfn.XLOOKUP(B15,'[1]Proyectos (NO FILTRAR)'!$F:$F,'[1]Proyectos (NO FILTRAR)'!$B:$B,0,0,1) -> PE-MSR-UG-FEL03-036-A | B15: Minsur_Forecast_Budget24 | C15: =+_xlfn.XLOOKUP(A15,'[1]Proyectos (NO FILTRAR)'!$B:$B,'[1]Proyectos (NO FILTRAR)'!$G:$G,"error",0,1) -> Perú | D15: Adjudicado | E15: Terminado | G15: Matias Fuentes | H15: Kevin Rios | I15: =+_xlfn.XLOOKUP(B15,[2]BDD_Proyectos_REDCO!$D$2:$D$29,[2]BDD_Proyectos_REDCO!$L$2:$L$29) -> 65088 | J15: =+Q15+AE15+AH15+AK15+AN15+AQ15+AT15+AW15+AZ15+BC15+BE15+BG15+BI15 -> 65088 | K15: =+IFERROR(J15/I15,0) -> 1 | L15: =+I15-J15 -> 0 | M15: =+IFERROR(L15/I15,0) -> 0 | O15: =IFERROR(N15/I15,0) -> 0 | P15: =+I15-N15 -> 65088 | Q15: 65088 | R15: =+I15-Q15 -> 0 | S15: 44910.72 | T15: 0 | U15: 0 | V15: 20177.28 | W15: 0 | X15: 2672 | Y15: 0 | Z15: 0 | AA15: 0 | AB15: 65088 | AC15: 0 | AF15: 0 | AI15: 0 | AL15: 0 | AO15: 0 | AR15: 0 | AU15: 0 | AX15: =+IF((_xlfn.XLOOKUP($B15,'Curva S'!$B$2:$B$100,'Curva S'!$O$2:$O$100,0,0,1)*$I15-$J15)<0,0,(_xlfn.XLOOKUP($B15,'Curva S'!$B$2:$B$100,'Curva S'!$O$2:$O$100,0,0,1)*$I15-$J15)) -> 0 | BA15: 0 | BK15: =+IF(AND(BD15>0,BE15=""),0,IF(BE15="","",IF(BE15>=BD15,1,BE15/BD15))) | BL15: =+IF(AND(BF15>0,BG15=""),0,IF(BG15="","",IF(BG15>=BF15,1,BG15/BF15))) | BM15: =+IF(AND(BH15>0,BI15=""),0,IF(BI15="","",IF(BI15>=BH15,1,BI15/BH15)))
A16: =+_xlfn.XLOOKUP(B16,'[1]Proyectos (NO FILTRAR)'!$F:$F,'[1]Proyectos (NO FILTRAR)'!$B:$B,0,0,1) -> PE-MSR-UG-OTR00-045-A | B16: San Rafael: Gestión del Corto Plazo | C16: =+_xlfn.XLOOKUP(A16,'[1]Proyectos (NO FILTRAR)'!$B:$B,'[1]Proyectos (NO FILTRAR)'!$G:$G,"error",0,1) -> Perú | D16: Adjudicado | E16: Terminado | G16: Mauricio Melendez | H16: Kevin Rios | I16: 82439 | J16: =+Q16+AE16+AH16+AK16+AN16+AQ16+AT16+AW16+AZ16+BC16+BE16+BG16+BI16 -> 82439 | K16: =+IFERROR(J16/I16,0) -> 1 | L16: =+I16-J16 -> 0 | M16: =+IFERROR(L16/I16,0) -> 0 | O16: =IFERROR(N16/I16,0) -> 0 | P16: =+I16-N16 -> 82439 | Q16: 82439 | R16: =+I16-Q16 -> 0 | S16: 19714.56 | T16: 19013 | U16: 701.56 | V16: 50107.84 | W16: 32480 | X16: 30651 | Y16: 11297 | Z16: 19354 | AA16: 19354 | AB16: 19649 | AC16: 0 | AF16: 0 | AI16: 0 | AL16: 0 | AO16: 0 | AR16: 0 | AU16: 0 | AX16: =+IF((_xlfn.XLOOKUP($B16,'Curva S'!$B$2:$B$100,'Curva S'!$O$2:$O$100,0,0,1)*$I16-$J16)<0,0,(_xlfn.XLOOKUP($B16,'Curva S'!$B$2:$B$100,'Curva S'!$O$2:$O$100,0,0,1)*$I16-$J16)) -> 0 | BA16: 0 | BK16: =+IF(AND(BD16>0,BE16=""),0,IF(BE16="","",IF(BE16>=BD16,1,BE16/BD16))) | BL16: =+IF(AND(BF16>0,BG16=""),0,IF(BG16="","",IF(BG16>=BF16,1,BG16/BF16))) | BM16: =+IF(AND(BH16>0,BI16=""),0,IF(BI16="","",IF(BI16>=BH16,1,BI16/BH16)))
A17: =+_xlfn.XLOOKUP(B17,'[1]Proyectos (NO FILTRAR)'!$F:$F,'[1]Proyectos (NO FILTRAR)'!$B:$B,0,0,1) -> CH-GLE-OP-FEL01-012-A | B17: Lomas Bayas - LoA24 | C17: =+_xlfn.XLOOKUP(A17,'[1]Proyectos (NO FILTRAR)'!$B:$B,'[1]Proyectos (NO FILTRAR)'!$G:$G,"error",0,1) -> Chile | D17: Adjudicado | E17: Terminado | G17: Felipe Rojas | H17: Guillermo Valdés | I17: 258540.53 | J17: =+Q17+AE17+AH17+AK17+AN17+AQ17+AT17+AW17+AZ17+BC17+BE17+BG17+BI17 -> 258540.53 | K17: =+IFERROR(J17/I17,0) -> 1 | L17: =+I17-J17 -> 0 | M17: =+IFERROR(L17/I17,0) -> 0 | O17: =IFERROR(N17/I17,0) -> 0 | P17: =+I17-N17 -> 258540.53 | Q17: 258540.53 | R17: =+I17-Q17 -> 0 | S17: 42259.82 | T17: 0 | U17: 42259.82 | V17: 0 | W17: 3577 | X17: 0 | Z17: 0 | AA17: 0 | AC17: 0 | AF17: 0 | AI17: 0 | AL17: 0 | AO17: 0 | AR17: 0 | AU17: 0 | AX17: =+IF((_xlfn.XLOOKUP($B17,'Curva S'!$B$2:$B$100,'Curva S'!$O$2:$O$100,0,0,1)*$I17-$J17)<0,0,(_xlfn.XLOOKUP($B17,'Curva S'!$B$2:$B$100,'Curva S'!$O$2:$O$100,0,0,1)*$I17-$J17)) -> 0 | BA17: 0 | BK17: =+IF(AND(BD17>0,BE17=""),0,IF(BE17="","",IF(BE17>=BD17,1,BE17/BD17))) | BL17: =+IF(AND(BF17>0,BG17=""),0,IF(BG17="","",IF(BG17>=BF17,1,BG17/BF17))) | BM17: =+IF(AND(BH17>0,BI17=""),0,IF(BI17="","",IF(BI17>=BH17,1,BI17/BH17)))
A18: =+_xlfn.XLOOKUP(B18,'[1]Proyectos (NO FILTRAR)'!$F:$F,'[1]Proyectos (NO FILTRAR)'!$B:$B,0,0,1) -> CH-LUN-GM-OTR00-005-A | B18: Pilares Mineros - Candelaria | C18: =+_xlfn.XLOOKUP(A18,'[1]Proyectos (NO FILTRAR)'!$B:$B,'[1]Proyectos (NO FILTRAR)'!$G:$G,"error",0,1) -> Chile | D18: Adjudicado | E18: Terminado | G18: Ricardo Miranda | H18: Carlos Morante | I18: 74080.2 | J18: =+Q18+AE18+AH18+AK18+AN18+AQ18+AT18+AW18+AZ18+BC18+BE18+BG18+BI18 -> 74080.2 | K18: =+IFERROR(J18/I18,0) -> 1 | L18: =+I18-J18 -> 0 | M18: =+IFERROR(L18/I18,0) -> 0 | O18: =IFERROR(N18/I18,0) -> 0 | P18: =+I18-N18 -> 74080.2 | Q18: 74080.2 | R18: =+I18-Q18 -> 0 | S18: 972.8 | T18: 973 | U18: 0 | V18: 0 | W18: 0 | X18: 0 | Z18: 0 | AA18: 0 | AC18: 0 | AF18: 0 | AI18: 0 | AL18: 0 | AO18: 0 | AR18: 0 | AU18: 0 | AX18: =+IF((_xlfn.XLOOKUP($B18,'Curva S'!$B$2:$B$100,'Curva S'!$O$2:$O$100,0,0,1)*$I18-$J18)<0,0,(_xlfn.XLOOKUP($B18,'Curva S'!$B$2:$B$100,'Curva S'!$O$2:$O$100,0,0,1)*$I18-$J18)) -> 0 | BA18: 0 | BK18: =+IF(AND(BD18>0,BE18=""),0,IF(BE18="","",IF(BE18>=BD18,1,BE18/BD18))) | BL18: =+IF(AND(BF18>0,BG18=""),0,IF(BG18="","",IF(BG18>=BF18,1,BG18/BF18))) | BM18: =+IF(AND(BH18>0,BI18=""),0,IF(BI18="","",IF(BI18>=BH18,1,BI18/BH18)))
A19: =+_xlfn.XLOOKUP(B19,'[1]Proyectos (NO FILTRAR)'!$F:$F,'[1]Proyectos (NO FILTRAR)'!$B:$B,0,0,1) -> CH-CMP-CS-FEL00-040-A | B19: CMP_CNN Update plan LOM | C19: =+_xlfn.XLOOKUP(A19,'[1]Proyectos (NO FILTRAR)'!$B:$B,'[1]Proyectos (NO FILTRAR)'!$G:$G,"error",0,1) -> Chile | D19: Adjudicado | E19: En Proceso | F19: Matias Fuentes | G19: Felipe Rojas | H19: TBD | I19: =+_xlfn.XLOOKUP(B19,'[1]Proyectos (NO FILTRAR)'!$F:$F,'[1]Proyectos (NO FILTRAR)'!$O:$O,"!",0,1) -> 18800 | J19: =+Q19+AE19+AH19+AK19+AN19+AQ19+AT19+AW19+AZ19+BC19+BE19+BG19+BI19 -> 18800 | K19: =+IFERROR(J19/I19,0) -> 1 | L19: =+I19-J19 -> 0 | M19: =+IFERROR(L19/I19,0) -> 0 | O19: =IFERROR(N19/I19,0) -> 0 | P19: =+I19-N19 -> 18800 | Q19: 0 | R19: =+I19-Q19 -> 18800 | W19: 0 | X19: 1880 | Y19: 0 | Z19: 16920 | AA19: 18800 | AB19: 0 | AC19: 18800 | AD19: 18800 | AF19: 18800 | AG19: 18800 | AI19: 18800 | AJ19: 5642 | AL19: 0 | AO19: 0 | AR19: 0 | AU19: 0 | AW19: 18800 | AX19: =+IF((_xlfn.XLOOKUP($B19,'Curva S'!$B$2:$B$100,'Curva S'!$O$2:$O$100,0,0,1)*$I19-$J19)<0,0,(_xlfn.XLOOKUP($B19,'Curva S'!$B$2:$B$100,'Curva S'!$O$2:$O$100,0,0,1)*$I19-$J19)) -> 0 | BA19: 0 | BK19: =+IF(AND(BD19>0,BE19=""),0,IF(BE19="","",IF(BE19>=BD19,1,BE19/BD19))) | BL19: =+IF(AND(BF19>0,BG19=""),0,IF(BG19="","",IF(BG19>=BF19,1,BG19/BF19))) | BM19: =+IF(AND(BH19>0,BI19=""),0,IF(BI19="","",IF(BI19>=BH19,1,BI19/BH19)))
A20: =+_xlfn.XLOOKUP(B20,'[1]Proyectos (NO FILTRAR)'!$F:$F,'[1]Proyectos (NO FILTRAR)'!$B:$B,0,0,1) -> CH-CMP-OP-FEL03-011-A | B20: LOM MLC 2023 | C20: =+_xlfn.XLOOKUP(A20,'[1]Proyectos (NO FILTRAR)'!$B:$B,'[1]Proyectos (NO FILTRAR)'!$G:$G,"error",0,1) -> Chile | D20: Adjudicado | E20: Terminado | G20: Felipe Rojas | H20: Guillermo Valdés | I20: 27467 | J20: =+Q20+AE20+AH20+AK20+AN20+AQ20+AT20+AW20+AZ20+BC20+BE20+BG20+BI20 -> 27467 | K20: =+IFERROR(J20/I20,0) -> 1 | L20: =+I20-J20 -> 0 | M20: =+IFERROR(L20/I20,0) -> 0 | O20: =IFERROR(N20/I20,0) -> 0 | P20: =+I20-N20 -> 27467 | Q20: 27467 | R20: =+I20-Q20 -> 0 | S20: 25796 | T20: 27467 | U20: 0 | V20: 0 | W20: 0 | X20: 0 | Z20: 0 | AA20: 0 | AC20: 0 | AF20: 0 | AI20: 0 | AL20: 0 | AO20: 0 | AR20: 0 | AU20: 0 | AX20: =+IF((_xlfn.XLOOKUP($B20,'Curva S'!$B$2:$B$100,'Curva S'!$O$2:$O$100,0,0,1)*$I20-$J20)<0,0,(_xlfn.XLOOKUP($B20,'Curva S'!$B$2:$B$100,'Curva S'!$O$2:$O$100,0,0,1)*$I20-$J20)) -> 0 | BA20: 0 | BK20: =+IF(AND(BD20>0,BE20=""),0,IF(BE20="","",IF(BE20>=BD20,1,BE20/BD20))) | BL20: =+IF(AND(BF20>0,BG20=""),0,IF(BG20="","",IF(BG20>=BF20,1,BG20/BF20))) | BM20: =+IF(AND(BH20>0,BI20=""),0,IF(BI20="","",IF(BI20>=BH20,1,BI20/BH20)))
A21: =+_xlfn.XLOOKUP(B21,'[1]Proyectos (NO FILTRAR)'!$F:$F,'[1]Proyectos (NO FILTRAR)'!$B:$B,0,0,1) -> CH-CMP-OT-FEL03-002-A | B21: Algarrobo | C21: =+_xlfn.XLOOKUP(A21,'[1]Proyectos (NO FILTRAR)'!$B:$B,'[1]Proyectos (NO FILTRAR)'!$G:$G,"error",0,1) -> Chile | D21: Adjudicado | E21: En Proceso | G21: Felipe Rojas | H21: Emilio Sánchez | I21: 266973.98 | J21: =+Q21+AE21+AH21+AK21+AN21+AQ21+AT21+AW21+AZ21+BC21+BE21+BG21+BI21 -> 260928 | K21: =+IFERROR(J21/I21,0) -> 0.97735367 | L21: =+I21-J21 -> 6045.98 | M21: =+IFERROR(L21/I21,0) -> 0.022646327 | O21: =IFERROR(N21/I21,0) -> 0 | P21: =+I21-N21 -> 266973.98 | Q21: 186687 | R21: =+I21-Q21 -> 80286.98 | S21: 266973.98 | T21: 0 | U21: 266973.98 | V21: 0 | W21: 58723 | X21: 83300.392 | Y21: 64612 | Z21: 143638.98 | AA21: 57455.592 | AB21: 63352 | AC21: 80286.98 | AD21: 80286.98 | AF21: 0 | AH21: 11925 | AI21: 0 | AL21: 0 | AM21: 0 | AN21: 37470 | AO21: 0 | AR21: 0 | AS21: 0 | AU21: 0 | AX21: =+IF((_xlfn.XLOOKUP($B21,'Curva S'!$B$2:$B$100,'Curva S'!$O$2:$O$100,0,0,1)*$I21-$J21)<0,0,(_xlfn.XLOOKUP($B21,'Curva S'!$B$2:$B$100,'Curva S'!$O$2:$O$100,0,0,1)*$I21-$J21)) -> 0 | BA21: 0 | BC21: 24846 | BK21: =+IF(AND(BD21>0,BE21=""),0,IF(BE21="","",IF(BE21>=BD21,1,BE21/BD21))) | BL21: =+IF(AND(BF21>0,BG21=""),0,IF(BG21="","",IF(BG21>=BF21,1,BG21/BF21))) | BM21: =+IF(AND(BH21>0,BI21=""),0,IF(BI21="","",IF(BI21>=BH21,1,BI21/BH21)))
A22: =+_xlfn.XLOOKUP(B22,'[1]Proyectos (NO FILTRAR)'!$F:$F,'[1]Proyectos (NO FILTRAR)'!$B:$B,0,0,1) -> CH-CMP-OU-FEL2A-033-A | B22: CMP - FEL 2A | C22: =+_xlfn.XLOOKUP(A22,'[1]Proyectos (NO FILTRAR)'!$B:$B,'[1]Proyectos (NO FILTRAR)'!$G:$G,"error",0,1) -> Chile | D22: Adjudicado | E22: En Proceso | F22: Alex Figueroa | G22: Felipe Rojas | H22: Felipe Lira | I22: 95128.12 | J22: =+Q22+AE22+AH22+AK22+AN22+AQ22+AT22+AW22+AZ22+BC22+BE22+BG22+BI22 -> 95128.12 | K22: =+IFERROR(J22/I22,0) -> 1 | L22: =+I22-J22 -> 0 | M22: =+IFERROR(L22/I22,0) -> 0 | O22: =IFERROR(N22/I22,0) -> 0 | P22: =+I22-N22 -> 95128.12 | Q22: 83625.2 | R22: =+I22-Q22 -> 11502.92 | S22: 7777.5636 | T22: 20148 | U22: 0 | V22: 11666.345 | W22: 25529.59 | X22: 49450.54 | Y22: 29808.61 | Z22: 19641.93 | AA22: 19641.93 | AB22: 8139 | AC22: 11502.93 | AD22: 11502.93 | AE22: 251 | AF22: 11251.93 | AG22: 11252 | AH22: 8091.2 | AI22: 3160.73 | AJ22: 3160.73 | AK22: 1846.72 | AL22: 1314.01 | AM22: 1314 | AO22: 1314.01 | AQ22: 1314 | AR22: 0.01 | AU22: 0 | AX22: =+IF((_xlfn.XLOOKUP($B22,'Curva S'!$B$2:$B$100,'Curva S'!$O$2:$O$100,0,0,1)*$I22-$J22)<0,0,(_xlfn.XLOOKUP($B22,'Curva S'!$B$2:$B$100,'Curva S'!$O$2:$O$100,0,0,1)*$I22-$J22)) -> 0 | BA22: 0 | BK22: =+IF(AND(BD22>0,BE22=""),0,IF(BE22="","",IF(BE22>=BD22,1,BE22/BD22))) | BL22: =+IF(AND(BF22>0,BG22=""),0,IF(BG22="","",IF(BG22>=BF22,1,BG22/BF22))) | BM22: =+IF(AND(BH22>0,BI22=""),0,IF(BI22="","",IF(BI22>=BH22,1,BI22/BH22)))
A23: =+_xlfn.XLOOKUP(B23,'[1]Proyectos (NO FILTRAR)'!$F:$F,'[1]Proyectos (NO FILTRAR)'!$B:$B,0,0,1) -> CH-CMP-OT-OTR00-025-A | B23: RDP | C23: =+_xlfn.XLOOKUP(A23,'[1]Proyectos (NO FILTRAR)'!$B:$B,'[1]Proyectos (NO FILTRAR)'!$G:$G,"error",0,1) -> Chile | D23: Adjudicado | E23: Terminado | G23: Felipe Rojas | H23: Felipe Rojas | I23: 44990 | J23: =+Q23+AE23+AH23+AK23+AN23+AQ23+AT23+AW23+AZ23+BC23+BE23+BG23+BI23 -> 44990 | K23: =+IFERROR(J23/I23,0) -> 1 | L23: =+I23-J23 -> 0 | M23: =+IFERROR(L23/I23,0) -> 0 | O23: =IFERROR(N23/I23,0) -> 0 | P23: =+I23-N23 -> 44990 | Q23: 44990 | R23: =+I23-Q23 -> 0 | S23: 34790 | T23: 0 | U23: 34790 | V23: 0 | W23: 44990 | X23: 0 | Z23: 0 | AA23: 0 | AC23: 0 | AF23: 0 | AI23: 0 | AL23: 0 | AO23: 0 | AR23: 0 | AU23: 0 | AX23: =+IF((_xlfn.XLOOKUP($B23,'Curva S'!$B$2:$B$100,'Curva S'!$O$2:$O$100,0,0,1)*$I23-$J23)<0,0,(_xlfn.XLOOKUP($B23,'Curva S'!$B$2:$B$100,'Curva S'!$O$2:$O$100,0,0,1)*$I23-$J23)) -> 0 | BA23: 0 | BK23: =+IF(AND(BD23>0,BE23=""),0,IF(BE23="","",IF(BE23>=BD23,1,BE23/BD23))) | BL23: =+IF(AND(BF23>0,BG23=""),0,IF(BG23="","",IF(BG23>=BF23,1,BG23/BF23))) | BM23: =+IF(AND(BH23>0,BI23=""),0,IF(BI23="","",IF(BI23>=BH23,1,BI23/BH23)))
A24: =+_xlfn.XLOOKUP(B24,'[1]Proyectos (NO FILTRAR)'!$F:$F,'[1]Proyectos (NO FILTRAR)'!$B:$B,0,0,1) -> PE-MSR-UG-OTR00-044-A | B24: San Rafael Gestión Operativa | C24: =+_xlfn.XLOOKUP(A24,'[1]Proyectos (NO FILTRAR)'!$B:$B,'[1]Proyectos (NO FILTRAR)'!$G:$G,"error",0,1) -> Perú | D24: Adjudicado | E24: Terminado | G24: Matias Fuentes | H24: Kevin Rios | I24: 264624 | J24: =+Q24+AE24+AH24+AK24+AN24+AQ24+AT24+AW24+AZ24+BC24+BE24+BG24+BI24 -> 264624 | K24: =+IFERROR(J24/I24,0) -> 1 | L24: =+I24-J24 -> 0 | M24: =+IFERROR(L24/I24,0) -> 0 | O24: =IFERROR(N24/I24,0) -> 0 | P24: =+I24-N24 -> 264624 | Q24: 264624 | R24: =+I24-Q24 -> 0 | S24: 0 | T24: 0 | U24: 0 | V24: 0 | W24: 0 | X24: 0 | Z24: 0 | AA24: 0 | AC24: 0 | AF24: 0 | AI24: 0 | AL24: 0 | AO24: 0 | AR24: 0 | AU24: 0 | AX24: =+IF((_xlfn.XLOOKUP($B24,'Curva S'!$B$2:$B$100,'Curva S'!$O$2:$O$100,0,0,1)*$I24-$J24)<0,0,(_xlfn.XLOOKUP($B24,'Curva S'!$B$2:$B$100,'Curva S'!$O$2:$O$100,0,0,1)*$I24-$J24)) -> 0 | BA24: 0 | BK24: =+IF(AND(BD24>0,BE24=""),0,IF(BE24="","",IF(BE24>=BD24,1,BE24/BD24))) | BL24: =+IF(AND(BF24>0,BG24=""),0,IF(BG24="","",IF(BG24>=BF24,1,BG24/BF24))) | BM24: =+IF(AND(BH24>0,BI24=""),0,IF(BI24="","",IF(BI24>=BH24,1,BI24/BH24)))
A25: =+_xlfn.XLOOKUP(B25,'[1]Proyectos (NO FILTRAR)'!$F:$F,'[1]Proyectos (NO FILTRAR)'!$B:$B,0,0,1) -> RU-OTR-UG-FEL2A-015-A | B25: NorGold | C25: =+_xlfn.XLOOKUP(A25,'[1]Proyectos (NO FILTRAR)'!$B:$B,'[1]Proyectos (NO FILTRAR)'!$G:$G,"error",0,1) -> Rusia | D25: Adjudicado | E25: Terminado | G25: Olesya | H25: Felipe Lira | I25: 43371 | J25: =+Q25+AE25+AH25+AK25+AN25+AQ25+AT25+AW25+AZ25+BC25+BE25+BG25+BI25 -> 43371 | K25: =+IFERROR(J25/I25,0) -> 1 | L25: =+I25-J25 -> 0 | M25: =+IFERROR(L25/I25,0) -> 0 | O25: =IFERROR(N25/I25,0) -> 0 | P25: =+I25-N25 -> 43371 | Q25: 43371 | R25: =+I25-Q25 -> 0 | S25: 0 | T25: 0 | U25: 0 | V25: 0 | W25: 0 | X25: 0 | Z25: 0 | AA25: 0 | AC25: 0 | AF25: 0 | AI25: 0 | AL25: 0 | AO25: 0 | AR25: 0 | AU25: 0 | AX25: =+IF((_xlfn.XLOOKUP($B25,'Curva S'!$B$2:$B$100,'Curva S'!$O$2:$O$100,0,0,1)*$I25-$J25)<0,0,(_xlfn.XLOOKUP($B25,'Curva S'!$B$2:$B$100,'Curva S'!$O$2:$O$100,0,0,1)*$I25-$J25)) -> 0 | BA25: 0 | BK25: =+IF(AND(BD25>0,BE25=""),0,IF(BE25="","",IF(BE25>=BD25,1,BE25/BD25))) | BL25: =+IF(AND(BF25>0,BG25=""),0,IF(BG25="","",IF(BG25>=BF25,1,BG25/BF25))) | BM25: =+IF(AND(BH25>0,BI25=""),0,IF(BI25="","",IF(BI25>=BH25,1,BI25/BH25)))
A26: =+_xlfn.XLOOKUP(B26,'[1]Proyectos (NO FILTRAR)'!$F:$F,'[1]Proyectos (NO FILTRAR)'!$B:$B,0,0,1) -> PE-MSR-OP-OTR00-024-A | B26: Marcobre - Minajusta | C26: =+_xlfn.XLOOKUP(A26,'[1]Proyectos (NO FILTRAR)'!$B:$B,'[1]Proyectos (NO FILTRAR)'!$G:$G,"error",0,1) -> Perú | D26: Adjudicado | E26: Terminado | G26: Felipe Rojas | H26: Nicolás Ayarza | I26: 137832 | J26: =+Q26+AE26+AH26+AK26+AN26+AQ26+AT26+AW26+AZ26+BC26+BE26+BG26+BI26 -> 137832 | K26: =+IFERROR(J26/I26,0) -> 1 | L26: =+I26-J26 -> 0 | M26: =+IFERROR(L26/I26,0) -> 0 | O26: =IFERROR(N26/I26,0) -> 0 | P26: =+I26-N26 -> 137832 | Q26: 137832 | R26: =+I26-Q26 -> 0 | S26: 0 | T26: 0 | U26: 0 | V26: 0 | W26: 0 | X26: 0 | Z26: 0 | AA26: 0 | AC26: 0 | AF26: 0 | AI26: 0 | AL26: 0 | AO26: 0 | AR26: 0 | AU26: 0 | AX26: =+IF((_xlfn.XLOOKUP($B26,'Curva S'!$B$2:$B$100,'Curva S'!$O$2:$O$100,0,0,1)*$I26-$J26)<0,0,(_xlfn.XLOOKUP($B26,'Curva S'!$B$2:$B$100,'Curva S'!$O$2:$O$100,0,0,1)*$I26-$J26)) -> 0 | BA26: 0 | BK26: =+IF(AND(BD26>0,BE26=""),0,IF(BE26="","",IF(BE26>=BD26,1,BE26/BD26))) | BL26: =+IF(AND(BF26>0,BG26=""),0,IF(BG26="","",IF(BG26>=BF26,1,BG26/BF26))) | BM26: =+IF(AND(BH26>0,BI26=""),0,IF(BI26="","",IF(BI26>=BH26,1,BI26/BH26)))
A27: =+_xlfn.XLOOKUP(B27,'[1]Proyectos (NO FILTRAR)'!$F:$F,'[1]Proyectos (NO FILTRAR)'!$B:$B,0,0,1) -> PE-CSC-UG-FEL2A-023-A | B27: PFS Los Calatos | C27: =+_xlfn.XLOOKUP(A27,'[1]Proyectos (NO FILTRAR)'!$B:$B,'[1]Proyectos (NO FILTRAR)'!$G:$G,"error",0,1) -> Perú | D27: Adjudicado | E27: En Proceso | F27: Alex Figueroa | G27: Americo Zuzunaga | H27: Jorman Barrera | I27: 1039661.3 | J27: =+Q27+AE27+AH27+AK27+AN27+AQ27+AT27+AW27+AZ27+BC27+BE27+BG27+BI27 -> 1039661.3 | K27: =+IFERROR(J27/I27,0) -> 1 | L27: =+I27-J27 -> 0 | M27: =+IFERROR(L27/I27,0) -> 0 | O27: =IFERROR(N27/I27,0) -> 0 | P27: =+I27-N27 -> 1039661.3 | Q27: 221948.3 | R27: =+I27-Q27 -> 817713 | S27: 0 | T27: 0 | U27: 0 | V27: 0 | W27: 91731.3 | X27: 82558.17 | Y27: 100441 | Z27: 137776.73 | AA27: 137776.79 | AB27: 29776 | AC27: 152980.23 | AD27: 60000 | AE27: 70005 | AF27: 151113.84 | AG27: 58000 | AH27: 29387 | AI27: 81165.8 | AJ27: 61467 | AL27: 143655 | AM27: =83831+41184 -> 125015 | AN27: 50531 | AO27: 140572.5 | AQ27: 177527 | AR27: 114880.7 | AS27: 74185 | AT27: 110053 | AU27: 110447.1 | AV27: 90000 | AW27: 85235 | AX27: =+IF((_xlfn.XLOOKUP($B27,'Curva S'!$B$2:$B$100,'Curva S'!$O$2:$O$100,0,0,1)*$I27-$J27)<0,0,(_xlfn.XLOOKUP($B27,'Curva S'!$B$2:$B$100,'Curva S'!$O$2:$O$100,0,0,1)*$I27-$J27)) -> 0 | AZ27: 112468 | BA27: 85511.7 | BC27: 93254 | BD27: 35762 | BE27: 67403 | BF27: 17901 | BG27: 17153 | BH27: =_xlfn.XLOOKUP(A27,'[3]Resumen POM'!$I:$I,'[3]Resumen POM'!$D:$D,"",0,1) -> 4697 | BI27: 4697 | BK27: =+IF(AND(BD27>0,BE27=""),0,IF(BE27="","",IF(BE27>=BD27,1,BE27/BD27))) -> 1 | BL27: =+IF(AND(BF27>0,BG27=""),0,IF(BG27="","",IF(BG27>=BF27,1,BG27/BF27))) -> 0.95821462 | BM27: =+IF(AND(BH27>0,BI27=""),0,IF(BI27="","",IF(BI27>=BH27,1,BI27/BH27))) -> 1
A28: =+_xlfn.XLOOKUP(B28,'[1]Proyectos (NO FILTRAR)'!$F:$F,'[1]Proyectos (NO FILTRAR)'!$B:$B,0,0,1) -> CH-CSH-OP-FEL00-034-A | B28: CSH_LOM Mina Guarello | C28: =+_xlfn.XLOOKUP(A28,'[1]Proyectos (NO FILTRAR)'!$B:$B,'[1]Proyectos (NO FILTRAR)'!$G:$G,"error",0,1) -> Chile | D28: Adjudicado | E28: En Proceso | F28: Matias Fuentes | G28: Matias Fuentes | H28: TBD | I28: 114390 | J28: =+Q28+AE28+AH28+AK28+AN28+AQ28+AT28+AW28+AZ28+BC28+BE28+BG28+BI28 -> 114390 | K28: =+IFERROR(J28/I28,0) -> 1 | L28: =+I28-J28 -> 0 | M28: =+IFERROR(L28/I28,0) -> 0 | O28: =IFERROR(N28/I28,0) -> 0 | P28: =+I28-N28 -> 114390 | Q28: 19065 | R28: =+I28-Q28 -> 95325 | S28: 0 | T28: 0 | U28: 0 | V28: 0 | W28: 0 | X28: 0 | Z28: 19065 | AA28: 19065 | AB28: 19065 | AC28: 19065 | AD28: 19065 | AE28: 19065 | AF28: 19065 | AG28: 19065 | AH28: 19065 | AI28: 19065 | AJ28: 19065 | AK28: 19065 | AL28: 19065 | AM28: 19065 | AN28: 19065 | AO28: 19065 | AR28: 0 | AU28: 0 | AW28: 19065 | AX28: =+IF((_xlfn.XLOOKUP($B28,'Curva S'!$B$2:$B$100,'Curva S'!$O$2:$O$100,0,0,1)*$I28-$J28)<0,0,(_xlfn.XLOOKUP($B28,'Curva S'!$B$2:$B$100,'Curva S'!$O$2:$O$100,0,0,1)*$I28-$J28)) -> 0 | BA28: 0 | BK28: =+IF(AND(BD28>0,BE28=""),0,IF(BE28="","",IF(BE28>=BD28,1,BE28/BD28))) | BL28: =+IF(AND(BF28>0,BG28=""),0,IF(BG28="","",IF(BG28>=BF28,1,BG28/BF28))) | BM28: =+IF(AND(BH28>0,BI28=""),0,IF(BI28="","",IF(BI28>=BH28,1,BI28/BH28)))
A29: =+_xlfn.XLOOKUP(B29,'[1]Proyectos (NO FILTRAR)'!$F:$F,'[1]Proyectos (NO FILTRAR)'!$B:$B,0,0,1) -> CH-AMS-CS-OTR00-029-A | B29: AMSA_Planificacion | C29: =+_xlfn.XLOOKUP(A29,'[1]Proyectos (NO FILTRAR)'!$B:$B,'[1]Proyectos (NO FILTRAR)'!$G:$G,"error",0,1) -> Chile | D29: Adjudicado | E29: Terminado | F29: Matias Fuentes | G29: Patricio Vergara | H29: Nicolás Ayarza | I29: 427230 | J29: =+Q29+AE29+AH29+AK29+AN29+AQ29+AT29+AW29+AZ29+BC29+BE29+BG29+BI29 -> 427230 | K29: =+IFERROR(J29/I29,0) -> 1 | L29: =+I29-J29 -> 0 | M29: =+IFERROR(L29/I29,0) -> 0 | O29: =IFERROR(N29/I29,0) -> 0 | P29: =+I29-N29 -> 427230 | Q29: 427230 | R29: =+I29-Q29 -> 0 | S29: 0 | T29: 30338 | U29: 0 | V29: 40000 | W29: 105098 | X29: 43769.1 | Y29: 60311 | Z29: 212964.36 | AA29: 172360 | AB29: =186082+45401 -> 231483 | AL29: 0 | AO29: 0 | AR29: 0 | AU29: 0 | AX29: =+IF((_xlfn.XLOOKUP($B29,'Curva S'!$B$2:$B$100,'Curva S'!$O$2:$O$100,0,0,1)*$I29-$J29)<0,0,(_xlfn.XLOOKUP($B29,'Curva S'!$B$2:$B$100,'Curva S'!$O$2:$O$100,0,0,1)*$I29-$J29)) -> 0 | BA29: 0 | BK29: =+IF(AND(BD29>0,BE29=""),0,IF(BE29="","",IF(BE29>=BD29,1,BE29/BD29))) | BL29: =+IF(AND(BF29>0,BG29=""),0,IF(BG29="","",IF(BG29>=BF29,1,BG29/BF29))) | BM29: =+IF(AND(BH29>0,BI29=""),0,IF(BI29="","",IF(BI29>=BH29,1,BI29/BH29)))
A30: =+_xlfn.XLOOKUP(B30,'[1]Proyectos (NO FILTRAR)'!$F:$F,'[1]Proyectos (NO FILTRAR)'!$B:$B,0,0,1) -> PE-COR-UG-FEL2A-035-A | B30: MEIA Coripuno | C30: =+_xlfn.XLOOKUP(A30,'[1]Proyectos (NO FILTRAR)'!$B:$B,'[1]Proyectos (NO FILTRAR)'!$G:$G,"error",0,1) -> Perú | D30: Adjudicado | E30: En Proceso | F30: Claudio Hernández | G30: Matias Fuentes | H30: Johnny Pacheco | I30: =+_xlfn.XLOOKUP(B30,'[1]Proyectos (NO FILTRAR)'!$F:$F,'[1]Proyectos (NO FILTRAR)'!$O:$O,"!",0,1) -> 47960 | J30: =+Q30+AE30+AH30+AK30+AN30+AQ30+AT30+AW30+AZ30+BC30+BE30+BG30+BI30 -> 45562 | K30: =+IFERROR(J30/I30,0) -> 0.95 | L30: =+I30-J30 -> 2398 | M30: =+IFERROR(L30/I30,0) -> 0.05 | O30: =IFERROR(N30/I30,0) -> 0 | P30: =+I30-N30 -> 47960 | Q30: 0 | R30: =+I30-Q30 -> 47960 | S30: 0 | T30: 0 | U30: 0 | V30: 11510.4 | W30: 0 | X30: 42684.4 | Y30: 0 | Z30: 47960 | AA30: 0 | AB30: 0 | AC30: 0 | AF30: 0 | AI30: 0 | AL30: 0 | AO30: 0 | AR30: 0 | AS30: 28296 | AU30: 47960 | AV30: 23980 | AW30: 23980 | AX30: =+IF((_xlfn.XLOOKUP($B30,'Curva S'!$B$2:$B$100,'Curva S'!$O$2:$O$100,0,0,1)*$I30-$J30)<0,0,(_xlfn.XLOOKUP($B30,'Curva S'!$B$2:$B$100,'Curva S'!$O$2:$O$100,0,0,1)*$I30-$J30)) -> 0 | BA30: 0 | BC30: 21582 | BK30: =+IF(AND(BD30>0,BE30=""),0,IF(BE30="","",IF(BE30>=BD30,1,BE30/BD30))) | BL30: =+IF(AND(BF30>0,BG30=""),0,IF(BG30="","",IF(BG30>=BF30,1,BG30/BF30))) | BM30: =+IF(AND(BH30>0,BI30=""),0,IF(BI30="","",IF(BI30>=BH30,1,BI30/BH30)))
A31: =+_xlfn.XLOOKUP(B31,'[1]Proyectos (NO FILTRAR)'!$F:$F,'[1]Proyectos (NO FILTRAR)'!$B:$B,0,0,1) -> CH-COD-OT-OTR00-030-A | B31: Codelco_Capacitacion Deswik DET | C31: =+_xlfn.XLOOKUP(A31,'[1]Proyectos (NO FILTRAR)'!$B:$B,'[1]Proyectos (NO FILTRAR)'!$G:$G,"error",0,1) -> Chile | D31: Adjudicado | E31: En Proceso | F31: Mauricio Melendez | G31: Mauricio Melendez | H31: Felipe Lira | I31: 56123 | J31: =+Q31+AE31+AH31+AK31+AN31+AQ31+AT31+AW31+AZ31+BC31+BE31+BG31+BI31 -> 56123 | K31: =+IFERROR(J31/I31,0) -> 1 | L31: =+I31-J31 -> 0 | M31: =+IFERROR(L31/I31,0) -> 0 | O31: =IFERROR(N31/I31,0) -> 0 | P31: =+I31-N31 -> 56123 | Q31: 29752 | R31: =+I31-Q31 -> 26371 | W31: 0 | X31: 32250 | Y31: 0 | Z31: 57799.32 | AA31: 21600 | AB31: 29752 | AC31: 45248 | AD31: 45248 | AF31: 34741.15 | AG31: 14600 | AH31: 12534 | AI31: 0 | AL31: 28214 | AM31: 26714 | AO31: 4359 | AR31: 0 | AS31: 0 | AU31: 0 | AW31: 13837 | AX31: =+IF((_xlfn.XLOOKUP($B31,'Curva S'!$B$2:$B$100,'Curva S'!$O$2:$O$100,0,0,1)*$I31-$J31)<0,0,(_xlfn.XLOOKUP($B31,'Curva S'!$B$2:$B$100,'Curva S'!$O$2:$O$100,0,0,1)*$I31-$J31)) -> 0 | BA31: 0 | BK31: =+IF(AND(BD31>0,BE31=""),0,IF(BE31="","",IF(BE31>=BD31,1,BE31/BD31))) | BL31: =+IF(AND(BF31>0,BG31=""),0,IF(BG31="","",IF(BG31>=BF31,1,BG31/BF31))) | BM31: =+IF(AND(BH31>0,BI31=""),0,IF(BI31="","",IF(BI31>=BH31,1,BI31/BH31)))
A32: =+_xlfn.XLOOKUP(B32,'[1]Proyectos (NO FILTRAR)'!$F:$F,'[1]Proyectos (NO FILTRAR)'!$B:$B,0,0,1) -> CH-COD-UG-FEL01-039-A | B32: Codelco_Drenaje QT | C32: =+_xlfn.XLOOKUP(A32,'[1]Proyectos (NO FILTRAR)'!$B:$B,'[1]Proyectos (NO FILTRAR)'!$G:$G,"error",0,1) -> Chile | D32: Adjudicado | E32: En Proceso | F32: Mauricio Melendez | G32: Mauricio Melendez | H32: Freddy Diaz | I32: 133386 | J32: =+Q32+AE32+AH32+AK32+AN32+AQ32+AT32+AW32+AZ32+BC32+BE32+BG32+BI32 -> 133386 | K32: =+IFERROR(J32/I32,0) -> 1 | L32: =+I32-J32 -> 0 | M32: =+IFERROR(L32/I32,0) -> 0 | O32: =IFERROR(N32/I32,0) -> 0 | P32: =+I32-N32 -> 133386 | Q32: 14688 | R32: =+I32-Q32 -> 118698 | W32: 0 | X32: 7500 | Y32: 14688 | Z32: 40593.6 | AA32: 45000 | AB32: 0 | AC32: 63612 | AD32: 63612 | AE32: 77671 | AF32: 42458.64 | AG32: 42458.64 | AI32: 40141 | AJ32: 37545 | AK32: 41027 | AL32: 0 | AO32: 0 | AR32: 0 | AU32: 0 | AX32: =+IF((_xlfn.XLOOKUP($B32,'Curva S'!$B$2:$B$100,'Curva S'!$O$2:$O$100,0,0,1)*$I32-$J32)<0,0,(_xlfn.XLOOKUP($B32,'Curva S'!$B$2:$B$100,'Curva S'!$O$2:$O$100,0,0,1)*$I32-$J32)) -> 0 | BA32: 0 | BK32: =+IF(AND(BD32>0,BE32=""),0,IF(BE32="","",IF(BE32>=BD32,1,BE32/BD32))) | BL32: =+IF(AND(BF32>0,BG32=""),0,IF(BG32="","",IF(BG32>=BF32,1,BG32/BF32))) | BM32: =+IF(AND(BH32>0,BI32=""),0,IF(BI32="","",IF(BI32>=BH32,1,BI32/BH32)))
A33: =+_xlfn.XLOOKUP(B33,'[1]Proyectos (NO FILTRAR)'!$F:$F,'[1]Proyectos (NO FILTRAR)'!$B:$B,0,0,1) -> PE-MMA-OP-FEL00-047-A | B33: MiskiMayo_LOM | C33: =+_xlfn.XLOOKUP(A33,'[1]Proyectos (NO FILTRAR)'!$B:$B,'[1]Proyectos (NO FILTRAR)'!$G:$G,"error",0,1) -> Perú | D33: Adjudicado | E33: En Proceso | F33: Cristian Quezada | G33: Americo Zuzunaga | H33: Kevin Rios | I33: =+_xlfn.XLOOKUP(B33,'[1]Proyectos (NO FILTRAR)'!$F:$F,'[1]Proyectos (NO FILTRAR)'!$O:$O,"!",0,1) -> 115136 | J33: =+Q33+AE33+AH33+AK33+AN33+AQ33+AT33+AW33+AZ33+BC33+BE33+BG33+BI33 -> 115136 | K33: =+IFERROR(J33/I33,0) -> 1 | L33: =+I33-J33 -> 0 | M33: =+IFERROR(L33/I33,0) -> 0 | O33: =IFERROR(N33/I33,0) -> 0 | P33: =+I33-N33 -> 115136 | Q33: 50473 | R33: =+I33-Q33 -> 64663 | W33: 0 | X33: 9666.6667 | Y33: 0 | Z33: 23027.2 | AA33: 23027.2 | AB33: 50473 | AC33: 32331.5 | AD33: 32331.5 | AE33: 11222 | AF33: 34736.65 | AG33: 33133.42 | AH33: 7526 | AI33: 30947.32 | AJ33: 30481 | AK33: 15246 | AL33: 13398.6 | AM33: 22893 | AN33: 30669 | AO33: 0 | AR33: 0 | AU33: 0 | AX33: =+IF((_xlfn.XLOOKUP($B33,'Curva S'!$B$2:$B$100,'Curva S'!$O$2:$O$100,0,0,1)*$I33-$J33)<0,0,(_xlfn.XLOOKUP($B33,'Curva S'!$B$2:$B$100,'Curva S'!$O$2:$O$100,0,0,1)*$I33-$J33)) -> 0 | BA33: 0 | BK33: =+IF(AND(BD33>0,BE33=""),0,IF(BE33="","",IF(BE33>=BD33,1,BE33/BD33))) | BL33: =+IF(AND(BF33>0,BG33=""),0,IF(BG33="","",IF(BG33>=BF33,1,BG33/BF33))) | BM33: =+IF(AND(BH33>0,BI33=""),0,IF(BI33="","",IF(BI33>=BH33,1,BI33/BH33)))
A34: =+_xlfn.XLOOKUP(B34,'[1]Proyectos (NO FILTRAR)'!$F:$F,'[1]Proyectos (NO FILTRAR)'!$B:$B,0,0,1) -> CH-CMP-OP-OTR00-083-A | B34: CMP_LOM CNN 2024 | C34: =+_xlfn.XLOOKUP(A34,'[1]Proyectos (NO FILTRAR)'!$B:$B,'[1]Proyectos (NO FILTRAR)'!$G:$G,"error",0,1) -> Chile | D34: Adjudicado | E34: En Proceso | F34: Cristian Quezada | H34: TBD | I34: =+_xlfn.XLOOKUP(B34,'[1]Proyectos (NO FILTRAR)'!$F:$F,'[1]Proyectos (NO FILTRAR)'!$O:$O,"!",0,1) -> 36205 | J34: =+Q34+AE34+AH34+AK34+AN34+AQ34+AT34+AW34+AZ34+BC34+BE34+BG34+BI34 -> 34041 | K34: =+IFERROR(J34/I34,0) -> 0.94022925 | L34: =+I34-J34 -> 2164 | M34: =+IFERROR(L34/I34,0) -> 0.05977075 | O34: =IFERROR(N34/I34,0) -> 0 | P34: =+I34-N34 -> 36205 | Q34: 0 | R34: =+I34-Q34 -> 36205 | AO34: 0 | AR34: 0 | AS34: 0 | AU34: 0 | AV34: 36850 | AW34: 34041 | AX34: =+IF((_xlfn.XLOOKUP($B34,'Curva S'!$B$2:$B$100,'Curva S'!$O$2:$O$100,0,0,1)*$I34-$J34)<0,0,(_xlfn.XLOOKUP($B34,'Curva S'!$B$2:$B$100,'Curva S'!$O$2:$O$100,0,0,1)*$I34-$J34)) -> 0 | BA34: 0 | BK34: =+IF(AND(BD34>0,BE34=""),0,IF(BE34="","",IF(BE34>=BD34,1,BE34/BD34))) | BL34: =+IF(AND(BF34>0,BG34=""),0,IF(BG34="","",IF(BG34>=BF34,1,BG34/BF34))) | BM34: =+IF(AND(BH34>0,BI34=""),0,IF(BI34="","",IF(BI34>=BH34,1,BI34/BH34)))
A35: =+_xlfn.XLOOKUP(B35,'[1]Proyectos (NO FILTRAR)'!$F:$F,'[1]Proyectos (NO FILTRAR)'!$B:$B,0,0,1) -> CH-CMP-CS-FEL00-038-A | B35: CMP_Los Colorados Adelantamiento Planta | C35: =+_xlfn.XLOOKUP(A35,'[1]Proyectos (NO FILTRAR)'!$B:$B,'[1]Proyectos (NO FILTRAR)'!$G:$G,"error",0,1) -> Chile | D35: Adjudicado | E35: En Proceso | F35: Alex Figueroa | G35: Felipe Rojas | H35: Felipe Matamoros | I35: 92830.61 | J35: =+Q35+AE35+AH35+AK35+AN35+AQ35+AT35+AW35+AZ35+BC35+BE35+BG35+BI35 -> 92830.61 | K35: =+IFERROR(J35/I35,0) -> 1 | L35: =+I35-J35 -> 0 | M35: =+IFERROR(L35/I35,0) -> 0 | O35: =IFERROR(N35/I35,0) -> 0 | P35: =+I35-N35 -> 92830.61 | Q35: 33661 | R35: =+I35-Q35 -> 59169.61 | W35: 0 | X35: 10000 | Y35: 0 | Z35: 50000 | AA35: 0 | AB35: 33661 | AC35: 93025.77 | AD35: 93025.77 | AE35: 16145.61 | AF35: 42562.92 | AG35: 42562.92 | AH35: 25645 | AI35: 16917.92 | AJ35: 12000 | AK35: 4969 | AL35: 11948.92 | AM35: 8629.34 | AN35: 9436 | AO35: 2512.92 | AQ35: 2974 | AR35: 0 | AU35: 0 | AX35: =+IF((_xlfn.XLOOKUP($B35,'Curva S'!$B$2:$B$100,'Curva S'!$O$2:$O$100,0,0,1)*$I35-$J35)<0,0,(_xlfn.XLOOKUP($B35,'Curva S'!$B$2:$B$100,'Curva S'!$O$2:$O$100,0,0,1)*$I35-$J35)) -> 0 | BA35: 0 | BK35: =+IF(AND(BD35>0,BE35=""),0,IF(BE35="","",IF(BE35>=BD35,1,BE35/BD35))) | BL35: =+IF(AND(BF35>0,BG35=""),0,IF(BG35="","",IF(BG35>=BF35,1,BG35/BF35))) | BM35: =+IF(AND(BH35>0,BI35=""),0,IF(BI35="","",IF(BI35>=BH35,1,BI35/BH35)))
A36: =+_xlfn.XLOOKUP(B36,'[1]Proyectos (NO FILTRAR)'!$F:$F,'[1]Proyectos (NO FILTRAR)'!$B:$B,0,0,1) -> PE-MMG-OU-FEL00-022-A | B36: LasBambas_Ferrobamba_OP_UG | C36: =+_xlfn.XLOOKUP(A36,'[1]Proyectos (NO FILTRAR)'!$B:$B,'[1]Proyectos (NO FILTRAR)'!$G:$G,"error",0,1) -> Perú | D36: Adjudicado | E36: En Proceso | F36: Matias Fuentes | G36: Ricardo Miranda | H36: Pablo Quiero | I36: 229952 | J36: =+Q36+AE36+AH36+AK36+AN36+AQ36+AT36+AW36+AZ36+BC36+BE36+BG36+BI36 -> 229952 | K36: =+IFERROR(J36/I36,0) -> 1 | L36: =+I36-J36 -> 0 | M36: =+IFERROR(L36/I36,0) -> 0 | O36: =IFERROR(N36/I36,0) -> 0 | P36: =+I36-N36 -> 229952 | Q36: 40393.995 | R36: =+I36-Q36 -> 189558 | W36: 0 | X36: 5300 | Y36: 28416.995 | Z36: 32895.751 | AA36: 30053 | AB36: 11977 | AC36: 62697.502 | AD36: 45000 | AE36: 31780 | AF36: 58977.453 | AG36: 40000 | AH36: 23974 | AI36: 34825.315 | AJ36: 35000 | AL36: 13986.085 | AM36: 13986 | AN36: 15573 | AO36: 55519.645 | AQ36: 56860 | AR36: 17015.325 | AS36: 37470 | AT36: =19506-4087 -> 15419 | AU36: 45951.005 | AW36: 45952 | AX36: =+IF((_xlfn.XLOOKUP($B36,'Curva S'!$B$2:$B$100,'Curva S'!$O$2:$O$100,0,0,1)*$I36-$J36)<0,0,(_xlfn.XLOOKUP($B36,'Curva S'!$B$2:$B$100,'Curva S'!$O$2:$O$100,0,0,1)*$I36-$J36)) -> 0 | BA36: 0 | BK36: =+IF(AND(BD36>0,BE36=""),0,IF(BE36="","",IF(BE36>=BD36,1,BE36/BD36))) | BL36: =+IF(AND(BF36>0,BG36=""),0,IF(BG36="","",IF(BG36>=BF36,1,BG36/BF36))) | BM36: =+IF(AND(BH36>0,BI36=""),0,IF(BI36="","",IF(BI36>=BH36,1,BI36/BH36)))
A37: =+_xlfn.XLOOKUP(B37,'[1]Proyectos (NO FILTRAR)'!$F:$F,'[1]Proyectos (NO FILTRAR)'!$B:$B,0,0,1) -> CH-CMP-OU-FEL2A-041-A | B37: CMP_Romeral Estabilización + UG PFS | C37: =+_xlfn.XLOOKUP(A37,'[1]Proyectos (NO FILTRAR)'!$B:$B,'[1]Proyectos (NO FILTRAR)'!$G:$G,"error",0,1) -> Chile | D37: Adjudicado | E37: En Proceso | F37: Alex Figueroa | G37: Ricardo Miranda | H37: Felipe Matamoros | I37: 370323.6 | J37: =+Q37+AE37+AH37+AK37+AN37+AQ37+AT37+AW37+AZ37+BC37+BE37+BG37+BI37 -> 370323.6 | K37: =+IFERROR(J37/I37,0) -> 1 | L37: =+I37-J37 -> 0 | M37: =+IFERROR(L37/I37,0) -> 0 | O37: =IFERROR(N37/I37,0) -> 0 | P37: =+I37-N37 -> 370323.6 | Q37: 0 | R37: =+I37-Q37 -> 370323.6 | W37: 0 | X37: 0 | Y37: 0 | Z37: 0 | AA37: 0 | AB37: 0 | AC37: 29619.6 | AD37: 29619.6 | AE37: 61460.7 | AF37: 95723.133 | AG37: 80000 | AH37: 61831 | AI37: 72938.15 | AJ37: 80000 | AK37: 61641 | AL37: 63311.45 | AM37: 6872 | AN37: 61831 | AO37: 61831 | AQ37: 34925.9 | AR37: 51530.9 | AS37: 0 | AU37: 88555.4 | AX37: =+IF((_xlfn.XLOOKUP($B37,'Curva S'!$B$2:$B$100,'Curva S'!$O$2:$O$100,0,0,1)*$I37-$J37)<0,0,(_xlfn.XLOOKUP($B37,'Curva S'!$B$2:$B$100,'Curva S'!$O$2:$O$100,0,0,1)*$I37-$J37)) -> 0 | AZ37: 60227 | BA37: 0 | BC37: 28407 | BK37: =+IF(AND(BD37>0,BE37=""),0,IF(BE37="","",IF(BE37>=BD37,1,BE37/BD37))) | BL37: =+IF(AND(BF37>0,BG37=""),0,IF(BG37="","",IF(BG37>=BF37,1,BG37/BF37))) | BM37: =+IF(AND(BH37>0,BI37=""),0,IF(BI37="","",IF(BI37>=BH37,1,BI37/BH37)))
A38: =+_xlfn.XLOOKUP(B38,'[1]Proyectos (NO FILTRAR)'!$F:$F,'[1]Proyectos (NO FILTRAR)'!$B:$B,0,0,1) -> CH-COD-UG-FEL00-037-A | B38: Codelco_Cluster Toki | C38: =+_xlfn.XLOOKUP(A38,'[1]Proyectos (NO FILTRAR)'!$B:$B,'[1]Proyectos (NO FILTRAR)'!$G:$G,"error",0,1) -> Chile | D38: Adjudicado | E38: Terminado | F38: Mauricio Melendez | G38: Mauricio Melendez | H38: Freddy Diaz | I38: =+_xlfn.XLOOKUP(B38,'[1]Proyectos (NO FILTRAR)'!$F:$F,'[1]Proyectos (NO FILTRAR)'!$O:$O,"!",0,1) -> 82787 | J38: =+Q38+AE38+AH38+AK38+AN38+AQ38+AT38+AW38+AZ38+BC38+BE38+BG38+BI38 -> 82787 | K38: =+IFERROR(J38/I38,0) -> 1 | L38: =+I38-J38 -> 0 | M38: =+IFERROR(L38/I38,0) -> 0 | O38: =IFERROR(N38/I38,0) -> 0 | P38: =+I38-N38 -> 82787 | Q38: 79847 | R38: =+I38-Q38 -> 2940 | W38: 0 | X38: 5000 | Y38: 41755 | Z38: 18097.5 | AA38: 37700 | AB38: 38092 | AC38: 2940 | AD38: 2940 | AE38: 2940 | AF38: 0 | AG38: 0 | AI38: 0 | AL38: 0 | AO38: 0 | AR38: 0 | AU38: 0 | AX38: =+IF((_xlfn.XLOOKUP($B38,'Curva S'!$B$2:$B$100,'Curva S'!$O$2:$O$100,0,0,1)*$I38-$J38)<0,0,(_xlfn.XLOOKUP($B38,'Curva S'!$B$2:$B$100,'Curva S'!$O$2:$O$100,0,0,1)*$I38-$J38)) -> 0 | BA38: 0 | BK38: =+IF(AND(BD38>0,BE38=""),0,IF(BE38="","",IF(BE38>=BD38,1,BE38/BD38))) | BL38: =+IF(AND(BF38>0,BG38=""),0,IF(BG38="","",IF(BG38>=BF38,1,BG38/BF38))) | BM38: =+IF(AND(BH38>0,BI38=""),0,IF(BI38="","",IF(BI38>=BH38,1,BI38/BH38)))
A39: =+_xlfn.XLOOKUP(B39,'[1]Proyectos (NO FILTRAR)'!$F:$F,'[1]Proyectos (NO FILTRAR)'!$B:$B,0,0,1) -> OT-IEL-UG-FEL2A-060-A | B39: IvanhoeElectric_Santa-Cruz_PrePFS | C39: =+_xlfn.XLOOKUP(A39,'[1]Proyectos (NO FILTRAR)'!$B:$B,'[1]Proyectos (NO FILTRAR)'!$G:$G,"error",0,1) -> Otros | D39: Adjudicado | E39: En Proceso | F39: Matias Fuentes | G39: Patricio Vergara | H39: Carlos Morante | I39: 565759 | J39: =+Q39+AE39+AH39+AK39+AN39+AQ39+AT39+AW39+AZ39+BC39+BE39+BG39+BI39 -> 565759 | K39: =+IFERROR(J39/I39,0) -> 1 | L39: =+I39-J39 -> 0 | M39: =+IFERROR(L39/I39,0) -> 0 | O39: =IFERROR(N39/I39,0) -> 0 | P39: =+I39-N39 -> 565759 | Q39: 119468 | R39: =+I39-Q39 -> 446291 | W39: 0 | X39: 26000 | Y39: 47539 | Z39: 35720 | AA39: 35720 | AB39: 60309 | AC39: 145711.08 | AD39: 96554 | AE39: 96319 | AF39: 202668.23 | AG39: 118000 | AH39: 94543 | AI39: 167966.7 | AJ39: 118010 | AK39: 118166 | AL39: 78598.3 | AM39: 101918 | AN39: 82732 | AO39: 36802 | AQ39: 44291 | AR39: 0 | AS39: =I39-526170 -> 39589 | AT39: 10240 | AU39: 0 | AX39: =+IF((_xlfn.XLOOKUP($B39,'Curva S'!$B$2:$B$100,'Curva S'!$O$2:$O$100,0,0,1)*$I39-$J39)<0,0,(_xlfn.XLOOKUP($B39,'Curva S'!$B$2:$B$100,'Curva S'!$O$2:$O$100,0,0,1)*$I39-$J39)) -> 0 | BA39: 0 | BK39: =+IF(AND(BD39>0,BE39=""),0,IF(BE39="","",IF(BE39>=BD39,1,BE39/BD39))) | BL39: =+IF(AND(BF39>0,BG39=""),0,IF(BG39="","",IF(BG39>=BF39,1,BG39/BF39))) | BM39: =+IF(AND(BH39>0,BI39=""),0,IF(BI39="","",IF(BI39>=BH39,1,BI39/BH39)))
A40: =+_xlfn.XLOOKUP(B40,'[1]Proyectos (NO FILTRAR)'!$F:$F,'[1]Proyectos (NO FILTRAR)'!$B:$B,0,0,1) -> CH-BSC-UG-OTR00-073-A | B40: Boston_Inmaculada Hochschild | C40: =+_xlfn.XLOOKUP(A40,'[1]Proyectos (NO FILTRAR)'!$B:$B,'[1]Proyectos (NO FILTRAR)'!$G:$G,"error",0,1) -> Chile | D40: Adjudicado | E40: En Proceso | F40: Claudio Hernández | H40: TBD | I40: 54706 | J40: =+Q40+AE40+AH40+AK40+AN40+AQ40+AT40+AW40+AZ40+BC40+BE40+BG40+BI40 -> 54706 | K40: =+IFERROR(J40/I40,0) -> 1 | L40: =+I40-J40 -> 0 | M40: =+IFERROR(L40/I40,0) -> 0 | O40: =IFERROR(N40/I40,0) -> 0 | P40: =+I40-N40 -> 54706 | Q40: 0 | R40: =+I40-Q40 -> 54706 | AI40: 65109 | AJ40: 50000 | AK40: 54706 | AL40: 0 | AO40: 0 | AR40: 0 | AU40: 0 | AX40: =+IF((_xlfn.XLOOKUP($B40,'Curva S'!$B$2:$B$100,'Curva S'!$O$2:$O$100,0,0,1)*$I40-$J40)<0,0,(_xlfn.XLOOKUP($B40,'Curva S'!$B$2:$B$100,'Curva S'!$O$2:$O$100,0,0,1)*$I40-$J40)) -> 0 | BA40: 0 | BK40: =+IF(AND(BD40>0,BE40=""),0,IF(BE40="","",IF(BE40>=BD40,1,BE40/BD40))) | BL40: =+IF(AND(BF40>0,BG40=""),0,IF(BG40="","",IF(BG40>=BF40,1,BG40/BF40))) | BM40: =+IF(AND(BH40>0,BI40=""),0,IF(BI40="","",IF(BI40>=BH40,1,BI40/BH40)))
A41: =+_xlfn.XLOOKUP(B41,'[1]Proyectos (NO FILTRAR)'!$F:$F,'[1]Proyectos (NO FILTRAR)'!$B:$B,0,0,1) -> PE-MSR-UG-FEL00-071-A | B41: Minsur_Update LOM San Rafael | C41: =+_xlfn.XLOOKUP(A41,'[1]Proyectos (NO FILTRAR)'!$B:$B,'[1]Proyectos (NO FILTRAR)'!$G:$G,"error",0,1) -> Perú | D41: Adjudicado | E41: Terminado | G41: Mauricio Melendez | H41: Kevin Rios | I41: =+_xlfn.XLOOKUP(B41,'[1]Proyectos (NO FILTRAR)'!$F:$F,'[1]Proyectos (NO FILTRAR)'!$O:$O,"!",0,1) -> 25600 | J41: =+Q41+AE41+AH41+AK41+AN41+AQ41+AT41+AW41+AZ41+BC41+BE41+BG41+BI41 -> 25600 | K41: =+IFERROR(J41/I41,0) -> 1 | L41: =+I41-J41 -> 0 | M41: =+IFERROR(L41/I41,0) -> 0 | O41: =IFERROR(N41/I41,0) -> 0 | P41: =+I41-N41 -> 25600 | Q41: 0 | R41: =+I41-Q41 -> 25600 | AF41: 25600 | AG41: 25600 | AH41: 25600 | AI41: 0 | AL41: 0 | AM41: 0 | AO41: 0 | AR41: 0 | AU41: 0 | AX41: =+IF((_xlfn.XLOOKUP($B41,'Curva S'!$B$2:$B$100,'Curva S'!$O$2:$O$100,0,0,1)*$I41-$J41)<0,0,(_xlfn.XLOOKUP($B41,'Curva S'!$B$2:$B$100,'Curva S'!$O$2:$O$100,0,0,1)*$I41-$J41)) -> 0 | BA41: 0 | BK41: =+IF(AND(BD41>0,BE41=""),0,IF(BE41="","",IF(BE41>=BD41,1,BE41/BD41))) | BL41: =+IF(AND(BF41>0,BG41=""),0,IF(BG41="","",IF(BG41>=BF41,1,BG41/BF41))) | BM41: =+IF(AND(BH41>0,BI41=""),0,IF(BI41="","",IF(BI41>=BH41,1,BI41/BH41)))
A42: =+_xlfn.XLOOKUP(B42,'[1]Proyectos (NO FILTRAR)'!$F:$F,'[1]Proyectos (NO FILTRAR)'!$B:$B,0,0,1) -> CH-LUN-CS-OTR00-069-A | B42: Lundin_Candelaria_EstudiosCugep | C42: =+_xlfn.XLOOKUP(A42,'[1]Proyectos (NO FILTRAR)'!$B:$B,'[1]Proyectos (NO FILTRAR)'!$G:$G,"error",0,1) -> Chile | D42: Adjudicado | E42: En Proceso | F42: Mauricio Melendez | G42: Ricardo Miranda | H42: Freddy Diaz | I42: =+_xlfn.XLOOKUP(B42,'[1]Proyectos (NO FILTRAR)'!$F:$F,'[1]Proyectos (NO FILTRAR)'!$O:$O,"!",0,1) -> 199645 | J42: =+Q42+AE42+AH42+AK42+AN42+AQ42+AT42+AW42+AZ42+BC42+BE42+BG42+BI42 -> 192950 | K42: =+IFERROR(J42/I42,0) -> 0.96646548 | L42: =+I42-J42 -> 6695 | M42: =+IFERROR(L42/I42,0) -> 0.033534524 | O42: =IFERROR(N42/I42,0) -> 0 | P42: =+I42-N42 -> 199645 | Q42: 0 | R42: =+I42-Q42 -> 199645 | AI42: 11978.7 | AJ42: 19917 | AK42: 26615 | AL42: 97732.9 | AM42: 93740 | AO42: 87074.85 | AR42: 101050 | AS42: 14698 | AU42: 173030 | AV42: =71911*0.7 -> 50337.7 | AW42: 71980 | AX42: =+IF((_xlfn.XLOOKUP($B42,'Curva S'!$B$2:$B$100,'Curva S'!$O$2:$O$100,0,0,1)*$I42-$J42)<0,0,(_xlfn.XLOOKUP($B42,'Curva S'!$B$2:$B$100,'Curva S'!$O$2:$O$100,0,0,1)*$I42-$J42)) -> 0 | AZ42: 60342 | BA42: 0 | BF42: 39000 | BG42: 34013 | BK42: =+IF(AND(BD42>0,BE42=""),0,IF(BE42="","",IF(BE42>=BD42,1,BE42/BD42))) | BL42: =+IF(AND(BF42>0,BG42=""),0,IF(BG42="","",IF(BG42>=BF42,1,BG42/BF42))) -> 0.87212821 | BM42: =+IF(AND(BH42>0,BI42=""),0,IF(BI42="","",IF(BI42>=BH42,1,BI42/BH42)))
A43: =+_xlfn.XLOOKUP(B43,'[1]Proyectos (NO FILTRAR)'!$F:$F,'[1]Proyectos (NO FILTRAR)'!$B:$B,0,0,1) -> RU-SEL-UG-FEL2A-072-A | B43: Seligdar_Kyuchus | C43: =+_xlfn.XLOOKUP(A43,'[1]Proyectos (NO FILTRAR)'!$B:$B,'[1]Proyectos (NO FILTRAR)'!$G:$G,"error",0,1) -> Rusia | D43: Adjudicado | E43: En Proceso | F43: Ricardo Miranda | G43: Ricardo Miranda | H43: Gerson Alfaro | I43: 0 | J43: =+Q43+AE43+AH43+AK43+AN43+AQ43+AT43+AW43+AZ43+BC43+BE43+BG43+BI43 -> 0 | K43: =+IFERROR(J43/I43,0) -> 0 | L43: =+I43-J43 -> 0 | M43: =+IFERROR(L43/I43,0) -> 0 | O43: =IFERROR(N43/I43,0) -> 0 | P43: =+I43-N43 -> 0 | Q43: 0 | R43: =+I43-Q43 -> 0 | AI43: 72000 | AL43: 0 | AM43: 0 | AO43: 0 | AR43: 0 | AU43: 0 | AX43: =+IF((_xlfn.XLOOKUP($B43,'Curva S'!$B$2:$B$100,'Curva S'!$O$2:$O$100,0,0,1)*$I43-$J43)<0,0,(_xlfn.XLOOKUP($B43,'Curva S'!$B$2:$B$100,'Curva S'!$O$2:$O$100,0,0,1)*$I43-$J43)) -> 0 | BA43: 0 | BK43: =+IF(AND(BD43>0,BE43=""),0,IF(BE43="","",IF(BE43>=BD43,1,BE43/BD43))) | BL43: =+IF(AND(BF43>0,BG43=""),0,IF(BG43="","",IF(BG43>=BF43,1,BG43/BF43))) | BM43: =+IF(AND(BH43>0,BI43=""),0,IF(BI43="","",IF(BI43>=BH43,1,BI43/BH43)))
A44: =+_xlfn.XLOOKUP(B44,'[1]Proyectos (NO FILTRAR)'!$F:$F,'[1]Proyectos (NO FILTRAR)'!$B:$B,0,0,1) -> CH-BHP-UG-FEL01-074-A | B44: BHP_Tunel Exploratorio | C44: =+_xlfn.XLOOKUP(A44,'[1]Proyectos (NO FILTRAR)'!$B:$B,'[1]Proyectos (NO FILTRAR)'!$G:$G,"error",0,1) -> Chile | D44: Adjudicado | E44: En Proceso | F44: Mauricio Melendez | G44: Patricio Vergara | H44: Freddy Diaz | I44: 35036 | J44: =+Q44+AE44+AH44+AK44+AN44+AQ44+AT44+AW44+AZ44+BC44+BE44+BG44+BI44 -> 35036 | K44: =+IFERROR(J44/I44,0) -> 1 | L44: =+I44-J44 -> 0 | M44: =+IFERROR(L44/I44,0) -> 0 | O44: =IFERROR(N44/I44,0) -> 0 | P44: =+I44-N44 -> 35036 | Q44: 0 | R44: =+I44-Q44 -> 35036 | AI44: 65618.85 | AL44: 0 | AO44: 0 | AQ44: 35036 | AR44: 0 | AU44: 0 | AX44: =+IF((_xlfn.XLOOKUP($B44,'Curva S'!$B$2:$B$100,'Curva S'!$O$2:$O$100,0,0,1)*$I44-$J44)<0,0,(_xlfn.XLOOKUP($B44,'Curva S'!$B$2:$B$100,'Curva S'!$O$2:$O$100,0,0,1)*$I44-$J44)) -> 0 | BA44: 0 | BK44: =+IF(AND(BD44>0,BE44=""),0,IF(BE44="","",IF(BE44>=BD44,1,BE44/BD44))) | BL44: =+IF(AND(BF44>0,BG44=""),0,IF(BG44="","",IF(BG44>=BF44,1,BG44/BF44))) | BM44: =+IF(AND(BH44>0,BI44=""),0,IF(BI44="","",IF(BI44>=BH44,1,BI44/BH44)))
A45: =+_xlfn.XLOOKUP(B45,'[1]Proyectos (NO FILTRAR)'!$F:$F,'[1]Proyectos (NO FILTRAR)'!$B:$B,0,0,1) -> CH-AMS-CS-OTR00-075-A | B45: AMSA_Asesoria Centinela | C45: =+_xlfn.XLOOKUP(A45,'[1]Proyectos (NO FILTRAR)'!$B:$B,'[1]Proyectos (NO FILTRAR)'!$G:$G,"error",0,1) -> Chile | D45: Adjudicado | E45: En Proceso | F45: Cristian Quezada | G45: Felipe Rojas | H45: Nicolás Ayarza | I45: 225450.5 | J45: =+Q45+AE45+AH45+AK45+AN45+AQ45+AT45+AW45+AZ45+BC45+BE45+BG45+BI45 -> 225450.5 | K45: =+IFERROR(J45/I45,0) -> 1 | L45: =+I45-J45 -> 0 | M45: =+IFERROR(L45/I45,0) -> 0 | O45: =IFERROR(N45/I45,0) -> 0 | P45: =+I45-N45 -> 225450.5 | Q45: 0 | R45: =+I45-Q45 -> 225450.5 | AI45: 0 | AJ45: 0 | AK45: 62047.5 | AL45: 61812.5 | AM45: 61813 | AN45: 44853 | AO45: 118299.5 | AQ45: 35250 | AR45: 83049.5 | AS45: 74540 | AT45: 74540 | AU45: 8509.5 | AV45: 8509.5 | AW45: 8760 | AX45: =+IF((_xlfn.XLOOKUP($B45,'Curva S'!$B$2:$B$100,'Curva S'!$O$2:$O$100,0,0,1)*$I45-$J45)<0,0,(_xlfn.XLOOKUP($B45,'Curva S'!$B$2:$B$100,'Curva S'!$O$2:$O$100,0,0,1)*$I45-$J45)) -> 0 | BA45: 0 | BK45: =+IF(AND(BD45>0,BE45=""),0,IF(BE45="","",IF(BE45>=BD45,1,BE45/BD45))) | BL45: =+IF(AND(BF45>0,BG45=""),0,IF(BG45="","",IF(BG45>=BF45,1,BG45/BF45))) | BM45: =+IF(AND(BH45>0,BI45=""),0,IF(BI45="","",IF(BI45>=BH45,1,BI45/BH45)))
A46: =+_xlfn.XLOOKUP(B46,'[1]Proyectos (NO FILTRAR)'!$F:$F,'[1]Proyectos (NO FILTRAR)'!$B:$B,0,0,1) -> CH-AMS-CS-OTR00-063-A | B46: AMSA_Estandares Minimos | C46: =+_xlfn.XLOOKUP(A46,'[1]Proyectos (NO FILTRAR)'!$B:$B,'[1]Proyectos (NO FILTRAR)'!$G:$G,"error",0,1) -> Chile | D46: Adjudicado | E46: En Proceso | F46: Alex Figueroa | G46: Felipe Rojas | H46: Cristian Alarcón | I46: =+_xlfn.XLOOKUP(B46,'[1]Proyectos (NO FILTRAR)'!$F:$F,'[1]Proyectos (NO FILTRAR)'!$O:$O,"!",0,1) -> 91650 | J46: =+Q46+AE46+AH46+AK46+AN46+AQ46+AT46+AW46+AZ46+BC46+BE46+BG46+BI46 -> 88642 | K46: =+IFERROR(J46/I46,0) -> 0.96717949 | L46: =+I46-J46 -> 3008 | M46: =+IFERROR(L46/I46,0) -> 0.032820513 | O46: =IFERROR(N46/I46,0) -> 0 | P46: =+I46-N46 -> 91650 | Q46: 0 | R46: =+I46-Q46 -> 91650 | AL46: 54990 | AM46: 54990 | AN46: 31730 | AO46: 32425 | AR46: 33341.5 | AS46: 21884 | AT46: 21884 | AU46: 35286.5 | AW46: 15305 | AX46: =+IF((_xlfn.XLOOKUP($B46,'Curva S'!$B$2:$B$100,'Curva S'!$O$2:$O$100,0,0,1)*$I46-$J46)<0,0,(_xlfn.XLOOKUP($B46,'Curva S'!$B$2:$B$100,'Curva S'!$O$2:$O$100,0,0,1)*$I46-$J46)) -> 3008 | BA46: 0 | BC46: 19723 | BK46: =+IF(AND(BD46>0,BE46=""),0,IF(BE46="","",IF(BE46>=BD46,1,BE46/BD46))) | BL46: =+IF(AND(BF46>0,BG46=""),0,IF(BG46="","",IF(BG46>=BF46,1,BG46/BF46))) | BM46: =+IF(AND(BH46>0,BI46=""),0,IF(BI46="","",IF(BI46>=BH46,1,BI46/BH46)))
A47: =+_xlfn.XLOOKUP(B47,'[1]Proyectos (NO FILTRAR)'!$F:$F,'[1]Proyectos (NO FILTRAR)'!$B:$B,0,0,1) -> PE-GLE-OP-FEL2A-054-A | B47: Glencore_Coroccohuayco_OptimizacionLOM | C47: =+_xlfn.XLOOKUP(A47,'[1]Proyectos (NO FILTRAR)'!$B:$B,'[1]Proyectos (NO FILTRAR)'!$G:$G,"error",0,1) -> Perú | D47: Adjudicado | E47: En Proceso | F47: Cristian Quezada | H47: Kevin Rios | I47: =+_xlfn.XLOOKUP(B47,'[1]Proyectos (NO FILTRAR)'!$F:$F,'[1]Proyectos (NO FILTRAR)'!$O:$O,"!",0,1) -> 198000 | J47: =+Q47+AE47+AH47+AK47+AN47+AQ47+AT47+AW47+AZ47+BC47+BE47+BG47+BI47 -> 198000 | K47: =+IFERROR(J47/I47,0) -> 1 | L47: =+I47-J47 -> 0 | M47: =+IFERROR(L47/I47,0) -> 0 | O47: =IFERROR(N47/I47,0) -> 0 | P47: =+I47-N47 -> 198000 | Q47: 0 | R47: =+I47-Q47 -> 198000 | AL47: 73260 | AM47: 88024 | AN47: 85103.1 | AO47: 83196.9 | AQ47: 70708.75 | AR47: 42188.15 | AS47: 0 | AU47: 42188.15 | AV47: 38000 | AW47: 42188.15 | AX47: =+IF((_xlfn.XLOOKUP($B47,'Curva S'!$B$2:$B$100,'Curva S'!$O$2:$O$100,0,0,1)*$I47-$J47)<0,0,(_xlfn.XLOOKUP($B47,'Curva S'!$B$2:$B$100,'Curva S'!$O$2:$O$100,0,0,1)*$I47-$J47)) -> 0 | BA47: 0 | BK47: =+IF(AND(BD47>0,BE47=""),0,IF(BE47="","",IF(BE47>=BD47,1,BE47/BD47))) | BL47: =+IF(AND(BF47>0,BG47=""),0,IF(BG47="","",IF(BG47>=BF47,1,BG47/BF47))) | BM47: =+IF(AND(BH47>0,BI47=""),0,IF(BI47="","",IF(BI47>=BH47,1,BI47/BH47)))
A48: =+_xlfn.XLOOKUP(B48,'[1]Proyectos (NO FILTRAR)'!$F:$F,'[1]Proyectos (NO FILTRAR)'!$B:$B,0,0,1) -> PE-COR-UG-FEL00-076-A | B48: Coripuno_Metodos de Minado | C48: =+_xlfn.XLOOKUP(A48,'[1]Proyectos (NO FILTRAR)'!$B:$B,'[1]Proyectos (NO FILTRAR)'!$G:$G,"error",0,1) -> Perú | D48: Adjudicado | E48: En Proceso | F48: Claudio Hernández | H48: Pablo Quiero | I48: =+_xlfn.XLOOKUP(B48,'[1]Proyectos (NO FILTRAR)'!$F:$F,'[1]Proyectos (NO FILTRAR)'!$O:$O,"!",0,1) -> 105000 | J48: =+Q48+AE48+AH48+AK48+AN48+AQ48+AT48+AW48+AZ48+BC48+BE48+BG48+BI48 -> 105000 | K48: =+IFERROR(J48/I48,0) -> 1 | L48: =+I48-J48 -> 0 | M48: =+IFERROR(L48/I48,0) -> 0 | O48: =IFERROR(N48/I48,0) -> 0 | P48: =+I48-N48 -> 105000 | Q48: 0 | R48: =+I48-Q48 -> 105000 | AL48: 0 | AM48: 0 | AO48: 46933 | AR48: 17462.6 | AS48: 22492 | AU48: 105060 | AV48: 20185 | AW48: 105000 | AX48: =+IF((_xlfn.XLOOKUP($B48,'Curva S'!$B$2:$B$100,'Curva S'!$O$2:$O$100,0,0,1)*$I48-$J48)<0,0,(_xlfn.XLOOKUP($B48,'Curva S'!$B$2:$B$100,'Curva S'!$O$2:$O$100,0,0,1)*$I48-$J48)) -> 0 | BA48: 0 | BK48: =+IF(AND(BD48>0,BE48=""),0,IF(BE48="","",IF(BE48>=BD48,1,BE48/BD48))) | BL48: =+IF(AND(BF48>0,BG48=""),0,IF(BG48="","",IF(BG48>=BF48,1,BG48/BF48))) | BM48: =+IF(AND(BH48>0,BI48=""),0,IF(BI48="","",IF(BI48>=BH48,1,BI48/BH48)))
A49: =+_xlfn.XLOOKUP(B49,'[1]Proyectos (NO FILTRAR)'!$F:$F,'[1]Proyectos (NO FILTRAR)'!$B:$B,0,0,1) -> CH-BSA-CS-OTR00-052-A | B49: Banco Santander_Yauricocha y Bolivar | C49: =+_xlfn.XLOOKUP(A49,'[1]Proyectos (NO FILTRAR)'!$B:$B,'[1]Proyectos (NO FILTRAR)'!$G:$G,"error",0,1) -> Chile | D49: Adjudicado | E49: En Proceso | F49: Emilio Sánchez | H49: TBD | I49: 88166 | J49: =+Q49+AE49+AH49+AK49+AN49+AQ49+AT49+AW49+AZ49+BC49+BE49+BG49+BI49 -> 88166 | K49: =+IFERROR(J49/I49,0) -> 1 | L49: =+I49-J49 -> 0 | M49: =+IFERROR(L49/I49,0) -> 0 | O49: =IFERROR(N49/I49,0) -> 0 | P49: =+I49-N49 -> 88166 | Q49: 0 | R49: =+I49-Q49 -> 88166 | AO49: 0 | AR49: 13340 | AS49: 88166 | AT49: 88166 | AU49: 0 | AX49: =+IF((_xlfn.XLOOKUP($B49,'Curva S'!$B$2:$B$100,'Curva S'!$O$2:$O$100,0,0,1)*$I49-$J49)<0,0,(_xlfn.XLOOKUP($B49,'Curva S'!$B$2:$B$100,'Curva S'!$O$2:$O$100,0,0,1)*$I49-$J49)) -> 0 | BA49: 0 | BK49: =+IF(AND(BD49>0,BE49=""),0,IF(BE49="","",IF(BE49>=BD49,1,BE49/BD49))) | BL49: =+IF(AND(BF49>0,BG49=""),0,IF(BG49="","",IF(BG49>=BF49,1,BG49/BF49))) | BM49: =+IF(AND(BH49>0,BI49=""),0,IF(BI49="","",IF(BI49>=BH49,1,BI49/BH49)))
A50: =+_xlfn.XLOOKUP(B50,'[1]Proyectos (NO FILTRAR)'!$F:$F,'[1]Proyectos (NO FILTRAR)'!$B:$B,0,0,1) -> PE-MSR-UG-OTR00-077-A | B50: Minsur_Apoyo Planificacion San Rafael | C50: =+_xlfn.XLOOKUP(A50,'[1]Proyectos (NO FILTRAR)'!$B:$B,'[1]Proyectos (NO FILTRAR)'!$G:$G,"error",0,1) -> Perú | D50: Adjudicado | E50: En Proceso | F50: Matias Fuentes | H50: Kevin Rios | I50: 119893 | J50: =+Q50+AE50+AH50+AK50+AN50+AQ50+AT50+AW50+AZ50+BC50+BE50+BG50+BI50 -> 119893 | K50: =+IFERROR(J50/I50,0) -> 1 | L50: =+I50-J50 -> 0 | M50: =+IFERROR(L50/I50,0) -> 0 | O50: =IFERROR(N50/I50,0) -> 0 | P50: =+I50-N50 -> 119893 | Q50: 0 | R50: =+I50-Q50 -> 119893 | AO50: 0 | AR50: 16780.68 | AS50: 0 | AU50: 47545.26 | AW50: 32242 | AX50: =+IF((_xlfn.XLOOKUP($B50,'Curva S'!$B$2:$B$100,'Curva S'!$O$2:$O$100,0,0,1)*$I50-$J50)<0,0,(_xlfn.XLOOKUP($B50,'Curva S'!$B$2:$B$100,'Curva S'!$O$2:$O$100,0,0,1)*$I50-$J50)) -> 0 | AZ50: 82138 | BA50: 0 | BC50: 5513 | BK50: =+IF(AND(BD50>0,BE50=""),0,IF(BE50="","",IF(BE50>=BD50,1,BE50/BD50))) | BL50: =+IF(AND(BF50>0,BG50=""),0,IF(BG50="","",IF(BG50>=BF50,1,BG50/BF50))) | BM50: =+IF(AND(BH50>0,BI50=""),0,IF(BI50="","",IF(BI50>=BH50,1,BI50/BH50)))
A51: =+_xlfn.XLOOKUP(B51,'[1]Proyectos (NO FILTRAR)'!$F:$F,'[1]Proyectos (NO FILTRAR)'!$B:$B,0,0,1) -> CH-CCO-OP-FEL00-078-A | B51: Capstone Copper_Estimacion confiabilidad de planes | C51: =+_xlfn.XLOOKUP(A51,'[1]Proyectos (NO FILTRAR)'!$B:$B,'[1]Proyectos (NO FILTRAR)'!$G:$G,"error",0,1) -> Chile | D51: Adjudicado | E51: En Proceso | F51: Cristian Quezada | H51: TBD | I51: =+_xlfn.XLOOKUP(B51,'[1]Proyectos (NO FILTRAR)'!$F:$F,'[1]Proyectos (NO FILTRAR)'!$O:$O,"!",0,1) -> 261986 | J51: =+Q51+AE51+AH51+AK51+AN51+AQ51+AT51+AW51+AZ51+BC51+BE51+BG51+BI51 -> 261786 | K51: =+IFERROR(J51/I51,0) -> 0.9992366 | L51: =+I51-J51 -> 200 | M51: =+IFERROR(L51/I51,0) -> 0.00076339957 | O51: =IFERROR(N51/I51,0) -> 0 | P51: =+I51-N51 -> 261986 | Q51: 0 | R51: =+I51-Q51 -> 261986 | AO51: 0 | AR51: 0 | AS51: 0 | AU51: 54551.28 | AW51: 62422 | AX51: =+IF((_xlfn.XLOOKUP($B51,'Curva S'!$B$2:$B$100,'Curva S'!$O$2:$O$100,0,0,1)*$I51-$J51)<0,0,(_xlfn.XLOOKUP($B51,'Curva S'!$B$2:$B$100,'Curva S'!$O$2:$O$100,0,0,1)*$I51-$J51)) -> 0 | AZ51: 82409 | BA51: 9081.54 | BC51: 37000 | BD51: 12795 | BE51: 12795 | BF51: 12795 | BG51: 45478 | BH51: =_xlfn.XLOOKUP(A51,'[3]Resumen POM'!$I:$I,'[3]Resumen POM'!$D:$D,"",0,1) -> 21702 | BI51: 21682 | BK51: =+IF(AND(BD51>0,BE51=""),0,IF(BE51="","",IF(BE51>=BD51,1,BE51/BD51))) -> 1 | BL51: =+IF(AND(BF51>0,BG51=""),0,IF(BG51="","",IF(BG51>=BF51,1,BG51/BF51))) -> 1 | BM51: =+IF(AND(BH51>0,BI51=""),0,IF(BI51="","",IF(BI51>=BH51,1,BI51/BH51))) -> 0.99907843
A52: =+_xlfn.XLOOKUP(B52,'[1]Proyectos (NO FILTRAR)'!$F:$F,'[1]Proyectos (NO FILTRAR)'!$B:$B,0,0,1) -> PE-MSR-UG-FEL00-079-A | B52: Minsur_Rampa de acceso San German | C52: =+_xlfn.XLOOKUP(A52,'[1]Proyectos (NO FILTRAR)'!$B:$B,'[1]Proyectos (NO FILTRAR)'!$G:$G,"error",0,1) -> Perú | D52: Adjudicado | E52: En Proceso | F52: Matias Fuentes | H52: Kevin Rios | I52: =+_xlfn.XLOOKUP(B52,'[1]Proyectos (NO FILTRAR)'!$F:$F,'[1]Proyectos (NO FILTRAR)'!$O:$O,"!",0,1) -> 53339 | J52: =+Q52+AE52+AH52+AK52+AN52+AQ52+AT52+AW52+AZ52+BC52+BE52+BG52+BI52 -> 53339 | K52: =+IFERROR(J52/I52,0) -> 1 | L52: =+I52-J52 -> 0 | M52: =+IFERROR(L52/I52,0) -> 0 | O52: =IFERROR(N52/I52,0) -> 0 | P52: =+I52-N52 -> 53339 | Q52: 0 | R52: =+I52-Q52 -> 53339 | AO52: 0 | AR52: 57591.9 | AS52: 0 | AU52: 64710 | AW52: 53339 | AX52: =+IF((_xlfn.XLOOKUP($B52,'Curva S'!$B$2:$B$100,'Curva S'!$O$2:$O$100,0,0,1)*$I52-$J52)<0,0,(_xlfn.XLOOKUP($B52,'Curva S'!$B$2:$B$100,'Curva S'!$O$2:$O$100,0,0,1)*$I52-$J52)) -> 0 | BA52: 0 | BK52: =+IF(AND(BD52>0,BE52=""),0,IF(BE52="","",IF(BE52>=BD52,1,BE52/BD52))) | BL52: =+IF(AND(BF52>0,BG52=""),0,IF(BG52="","",IF(BG52>=BF52,1,BG52/BF52))) | BM52: =+IF(AND(BH52>0,BI52=""),0,IF(BI52="","",IF(BI52>=BH52,1,BI52/BH52)))
A53: =+_xlfn.XLOOKUP(B53,'[1]Proyectos (NO FILTRAR)'!$F:$F,'[1]Proyectos (NO FILTRAR)'!$B:$B,0,0,1) -> OT-MCA-CS-OTR00-080-A | B53: McCarthy_Litigio Rio Tinto | C53: =+_xlfn.XLOOKUP(A53,'[1]Proyectos (NO FILTRAR)'!$B:$B,'[1]Proyectos (NO FILTRAR)'!$G:$G,"error",0,1) -> Otros | D53: Adjudicado | E53: En Proceso | F53: Mauricio Melendez | H53: TBD | I53: =+_xlfn.XLOOKUP(B53,'[1]Proyectos (NO FILTRAR)'!$F:$F,'[1]Proyectos (NO FILTRAR)'!$O:$O,"!",0,1) -> 611100 | J53: =+Q53+AE53+AH53+AK53+AN53+AQ53+AT53+AW53+AZ53+BC53+BE53+BG53+BI53 -> 572400 | K53: =+IFERROR(J53/I53,0) -> 0.93667158 | L53: =+I53-J53 -> 38700 | M53: =+IFERROR(L53/I53,0) -> 0.063328424 | O53: =IFERROR(N53/I53,0) -> 0 | P53: =+I53-N53 -> 611100 | Q53: 0 | R53: =+I53-Q53 -> 611100 | AO53: 0 | AR53: 85554 | AS53: 0 | AT53: 288500 | AU53: 0 | AW53: 283900 | AX53: =+IF((_xlfn.XLOOKUP($B53,'Curva S'!$B$2:$B$100,'Curva S'!$O$2:$O$100,0,0,1)*$I53-$J53)<0,0,(_xlfn.XLOOKUP($B53,'Curva S'!$B$2:$B$100,'Curva S'!$O$2:$O$100,0,0,1)*$I53-$J53)) -> 0 | BA53: 0 | BK53: =+IF(AND(BD53>0,BE53=""),0,IF(BE53="","",IF(BE53>=BD53,1,BE53/BD53))) | BL53: =+IF(AND(BF53>0,BG53=""),0,IF(BG53="","",IF(BG53>=BF53,1,BG53/BF53))) | BM53: =+IF(AND(BH53>0,BI53=""),0,IF(BI53="","",IF(BI53>=BH53,1,BI53/BH53)))
A54: =+_xlfn.XLOOKUP(B54,'[1]Proyectos (NO FILTRAR)'!$F:$F,'[1]Proyectos (NO FILTRAR)'!$B:$B,0,0,1) -> RU-ECH-UG-FEL00-081-A | B54: Eurochem_Himmelfarb Deposit | C54: =+_xlfn.XLOOKUP(A54,'[1]Proyectos (NO FILTRAR)'!$B:$B,'[1]Proyectos (NO FILTRAR)'!$G:$G,"error",0,1) -> Rusia | D54: Adjudicado | E54: En Proceso | F54: Ricardo Miranda | H54: Gerson Alfaro | I54: =+_xlfn.XLOOKUP(B54,'[1]Proyectos (NO FILTRAR)'!$F:$F,'[1]Proyectos (NO FILTRAR)'!$O:$O,"!",0,1) -> 152100 | J54: =+Q54+AE54+AH54+AK54+AN54+AQ54+AT54+AW54+AZ54+BC54+BE54+BG54+BI54 -> 152100 | K54: =+IFERROR(J54/I54,0) -> 1 | L54: =+I54-J54 -> 0 | M54: =+IFERROR(L54/I54,0) -> 0 | O54: =IFERROR(N54/I54,0) -> 0 | P54: =+I54-N54 -> 152100 | Q54: 0 | R54: =+I54-Q54 -> 152100 | AO54: 0 | AR54: 15499.8 | AS54: 0 | AU54: 105398.64 | AV54: 91260 | AW54: 76050 | AX54: =+IF((_xlfn.XLOOKUP($B54,'Curva S'!$B$2:$B$100,'Curva S'!$O$2:$O$100,0,0,1)*$I54-$J54)<0,0,(_xlfn.XLOOKUP($B54,'Curva S'!$B$2:$B$100,'Curva S'!$O$2:$O$100,0,0,1)*$I54-$J54)) -> 0 | BA54: 78948 | BD54: 78851 | BF54: 78881 | BH54: =_xlfn.XLOOKUP(A54,'[3]Resumen POM'!$I:$I,'[3]Resumen POM'!$D:$D,"",0,1) -> 78880.5 | BI54: 76050 | BK54: =+IF(AND(BD54>0,BE54=""),0,IF(BE54="","",IF(BE54>=BD54,1,BE54/BD54))) -> 0 | BL54: =+IF(AND(BF54>0,BG54=""),0,IF(BG54="","",IF(BG54>=BF54,1,BG54/BF54))) -> 0 | BM54: =+IF(AND(BH54>0,BI54=""),0,IF(BI54="","",IF(BI54>=BH54,1,BI54/BH54))) -> 0.96411661
A55: =+_xlfn.XLOOKUP(B55,'[1]Proyectos (NO FILTRAR)'!$F:$F,'[1]Proyectos (NO FILTRAR)'!$B:$B,0,0,1) -> BR-J&F-UG-FEL03-048-A | B55: J&F_Urucrum_RecuperacionPilares | C55: =+_xlfn.XLOOKUP(A55,'[1]Proyectos (NO FILTRAR)'!$B:$B,'[1]Proyectos (NO FILTRAR)'!$G:$G,"error",0,1) -> Brasil | D55: Adjudicado | E55: En Proceso | F55: Alex Figueroa | H55: Freddy Diaz | I55: =+_xlfn.XLOOKUP(B55,'[1]Proyectos (NO FILTRAR)'!$F:$F,'[1]Proyectos (NO FILTRAR)'!$O:$O,"!",0,1) -> 239308 | J55: =+Q55+AE55+AH55+AK55+AN55+AQ55+AT55+AW55+AZ55+BC55+BE55+BG55+BI55 -> 208259 | K55: =+IFERROR(J55/I55,0) -> 0.87025507 | L55: =+I55-J55 -> 31049 | M55: =+IFERROR(L55/I55,0) -> 0.12974493 | O55: =IFERROR(N55/I55,0) -> 0 | P55: =+I55-N55 -> 239308 | Q55: 0 | R55: =+I55-Q55 -> 239308 | AO55: 0 | AR55: 131619.5 | AS55: 130722 | AT55: 130722 | AU55: 56177.69 | AX55: =+IF((_xlfn.XLOOKUP($B55,'Curva S'!$B$2:$B$100,'Curva S'!$O$2:$O$100,0,0,1)*$I55-$J55)<0,0,(_xlfn.XLOOKUP($B55,'Curva S'!$B$2:$B$100,'Curva S'!$O$2:$O$100,0,0,1)*$I55-$J55)) -> 0 | AZ55: 27947 | BA55: 65084.15 | BC55: 26332 | BD55: 20000 | BE55: 11169 | BF55: 12000 | BG55: 12089 | BK55: =+IF(AND(BD55>0,BE55=""),0,IF(BE55="","",IF(BE55>=BD55,1,BE55/BD55))) -> 0.55845 | BL55: =+IF(AND(BF55>0,BG55=""),0,IF(BG55="","",IF(BG55>=BF55,1,BG55/BF55))) -> 1 | BM55: =+IF(AND(BH55>0,BI55=""),0,IF(BI55="","",IF(BI55>=BH55,1,BI55/BH55)))
A56: =+_xlfn.XLOOKUP(B56,'[1]Proyectos (NO FILTRAR)'!$F:$F,'[1]Proyectos (NO FILTRAR)'!$B:$B,0,0,1) -> CH-BSC-UG-OTR00-082-A | B56: Boston_Inmaculada Hochschild II | C56: =+_xlfn.XLOOKUP(A56,'[1]Proyectos (NO FILTRAR)'!$B:$B,'[1]Proyectos (NO FILTRAR)'!$G:$G,"error",0,1) -> Chile | D56: Adjudicado | E56: En Proceso | F56: Claudio Hernández | H56: Claudio Hernández | I56: 40000 | J56: =+Q56+AE56+AH56+AK56+AN56+AQ56+AT56+AW56+AZ56+BC56+BE56+BG56+BI56 -> 40000 | K56: =+IFERROR(J56/I56,0) -> 1 | L56: =+I56-J56 -> 0 | M56: =+IFERROR(L56/I56,0) -> 0 | O56: =IFERROR(N56/I56,0) -> 0 | P56: =+I56-N56 -> 40000 | Q56: 0 | R56: =+I56-Q56 -> 40000 | AO56: 0 | AR56: 30000 | AS56: 30000 | AU56: 0 | AW56: 40000 | AX56: =+IF((_xlfn.XLOOKUP($B56,'Curva S'!$B$2:$B$100,'Curva S'!$O$2:$O$100,0,0,1)*$I56-$J56)<0,0,(_xlfn.XLOOKUP($B56,'Curva S'!$B$2:$B$100,'Curva S'!$O$2:$O$100,0,0,1)*$I56-$J56)) -> 0 | BA56: 0 | BK56: =+IF(AND(BD56>0,BE56=""),0,IF(BE56="","",IF(BE56>=BD56,1,BE56/BD56))) | BL56: =+IF(AND(BF56>0,BG56=""),0,IF(BG56="","",IF(BG56>=BF56,1,BG56/BF56))) | BM56: =+IF(AND(BH56>0,BI56=""),0,IF(BI56="","",IF(BI56>=BH56,1,BI56/BH56)))
A57: =+_xlfn.XLOOKUP(B57,'[1]Proyectos (NO FILTRAR)'!$F:$F,'[1]Proyectos (NO FILTRAR)'!$B:$B,0,0,1) -> CH-BHP-OP-OTR00-085-A | B57: Spence_Confiabilidad Plan 2YB 2025 | C57: =+_xlfn.XLOOKUP(A57,'[1]Proyectos (NO FILTRAR)'!$B:$B,'[1]Proyectos (NO FILTRAR)'!$G:$G,"error",0,1) -> Chile | D57: Adjudicado | E57: En Proceso | F57: - | G57: Felipe Rojas | H57: Felipe Matamoros | I57: 34950 | J57: =+Q57+AE57+AH57+AK57+AN57+AQ57+AT57+AW57+AZ57+BC57+BE57+BG57+BI57 -> 34950 | K57: =+IFERROR(J57/I57,0) -> 1 | L57: =+I57-J57 -> 0 | M57: =+IFERROR(L57/I57,0) -> 0 | O57: =IFERROR(N57/I57,0) -> 0 | P57: =+I57-N57 -> 34950 | Q57: 0 | R57: =+I57-Q57 -> 34950 | AO57: 0 | AQ57: 34950 | AR57: 0 | AU57: 0 | AX57: =+IF((_xlfn.XLOOKUP($B57,'Curva S'!$B$2:$B$100,'Curva S'!$O$2:$O$100,0,0,1)*$I57-$J57)<0,0,(_xlfn.XLOOKUP($B57,'Curva S'!$B$2:$B$100,'Curva S'!$O$2:$O$100,0,0,1)*$I57-$J57)) -> 0 | BA57: 0 | BK57: =+IF(AND(BD57>0,BE57=""),0,IF(BE57="","",IF(BE57>=BD57,1,BE57/BD57))) | BL57: =+IF(AND(BF57>0,BG57=""),0,IF(BG57="","",IF(BG57>=BF57,1,BG57/BF57))) | BM57: =+IF(AND(BH57>0,BI57=""),0,IF(BI57="","",IF(BI57>=BH57,1,BI57/BH57)))
A58: =+_xlfn.XLOOKUP(B58,'[1]Proyectos (NO FILTRAR)'!$F:$F,'[1]Proyectos (NO FILTRAR)'!$B:$B,0,0,1) -> PE-MSR-GM-OTR00-092-A | B58: Minsur_Mejoramiento datos geotecnicos SR | C58: =+_xlfn.XLOOKUP(A58,'[1]Proyectos (NO FILTRAR)'!$B:$B,'[1]Proyectos (NO FILTRAR)'!$G:$G,"error",0,1) -> Perú | D58: Adjudicado | E58: En Proceso | F58: Claudio Hernández | H58: TBD | I58: 24551 | J58: =+Q58+AE58+AH58+AK58+AN58+AQ58+AT58+AW58+AZ58+BC58+BE58+BG58+BI58 -> 24551 | K58: =+IFERROR(J58/I58,0) -> 1 | L58: =+I58-J58 -> 0 | M58: =+IFERROR(L58/I58,0) -> 0 | O58: =IFERROR(N58/I58,0) -> 0 | P58: =+I58-N58 -> 24551 | Q58: 0 | R58: =+I58-Q58 -> 24551 | AO58: 0 | AR58: 0 | AU58: 0 | AW58: 24551 | AX58: =+IF((_xlfn.XLOOKUP($B58,'Curva S'!$B$2:$B$100,'Curva S'!$O$2:$O$100,0,0,1)*$I58-$J58)<0,0,(_xlfn.XLOOKUP($B58,'Curva S'!$B$2:$B$100,'Curva S'!$O$2:$O$100,0,0,1)*$I58-$J58)) -> 0 | BA58: 0 | BK58: =+IF(AND(BD58>0,BE58=""),0,IF(BE58="","",IF(BE58>=BD58,1,BE58/BD58))) | BL58: =+IF(AND(BF58>0,BG58=""),0,IF(BG58="","",IF(BG58>=BF58,1,BG58/BF58))) | BM58: =+IF(AND(BH58>0,BI58=""),0,IF(BI58="","",IF(BI58>=BH58,1,BI58/BH58)))
A59: =+_xlfn.XLOOKUP(B59,'[1]Proyectos (NO FILTRAR)'!$F:$F,'[1]Proyectos (NO FILTRAR)'!$B:$B,0,0,1) -> PE-MSR-CS-OTR00-090-A | B59: Minsur_Apoyo MEIA Raura | C59: =+_xlfn.XLOOKUP(A59,'[1]Proyectos (NO FILTRAR)'!$B:$B,'[1]Proyectos (NO FILTRAR)'!$G:$G,"error",0,1) -> Perú | D59: Adjudicado | E59: En Proceso | F59: Claudio Hernández | H59: TBD | I59: 8262 | J59: =+Q59+AE59+AH59+AK59+AN59+AQ59+AT59+AW59+AZ59+BC59+BE59+BG59+BI59 -> 8262 | K59: =+IFERROR(J59/I59,0) -> 1 | L59: =+I59-J59 -> 0 | M59: =+IFERROR(L59/I59,0) -> 0 | O59: =IFERROR(N59/I59,0) -> 0 | P59: =+I59-N59 -> 8262 | Q59: 0 | R59: =+I59-Q59 -> 8262 | AO59: 0 | AQ59: 8262 | AR59: 0 | AU59: 0 | AX59: =+IF((_xlfn.XLOOKUP($B59,'Curva S'!$B$2:$B$100,'Curva S'!$O$2:$O$100,0,0,1)*$I59-$J59)<0,0,(_xlfn.XLOOKUP($B59,'Curva S'!$B$2:$B$100,'Curva S'!$O$2:$O$100,0,0,1)*$I59-$J59)) -> 0 | BA59: 0 | BK59: =+IF(AND(BD59>0,BE59=""),0,IF(BE59="","",IF(BE59>=BD59,1,BE59/BD59))) | BL59: =+IF(AND(BF59>0,BG59=""),0,IF(BG59="","",IF(BG59>=BF59,1,BG59/BF59))) | BM59: =+IF(AND(BH59>0,BI59=""),0,IF(BI59="","",IF(BI59>=BH59,1,BI59/BH59)))
A60: =+_xlfn.XLOOKUP(B60,'[1]Proyectos (NO FILTRAR)'!$F:$F,'[1]Proyectos (NO FILTRAR)'!$B:$B,0,0,1) -> CH-CMP-OP-FEL03-010-A | B60: LOM CNN 2023 | C60: =+_xlfn.XLOOKUP(A60,'[1]Proyectos (NO FILTRAR)'!$B:$B,'[1]Proyectos (NO FILTRAR)'!$G:$G,"error",0,1) -> Chile | D60: Adjudicado | E60: Terminado | G60: Felipe Rojas | H60: Guillermo Valdés | I60: 40233 | J60: =+Q60+AE60+AH60+AK60+AN60+AQ60+AT60+AW60+AZ60+BC60+BE60+BG60+BI60 -> 40233 | K60: =+IFERROR(J60/I60,0) -> 1 | L60: =+I60-J60 -> 0 | M60: =+IFERROR(L60/I60,0) -> 0 | O60: =IFERROR(N60/I60,0) -> 0 | P60: =+I60-N60 -> 40233 | Q60: 40233 | R60: =+I60-Q60 -> 0 | S60: 37831 | T60: 40233 | U60: 0 | V60: 0 | W60: 0 | X60: 0 | Z60: 0 | AA60: 0 | AC60: 0 | AF60: 0 | AI60: 0 | AL60: 0 | AO60: 0 | AR60: 0 | AU60: 0 | AX60: =+IF((_xlfn.XLOOKUP($B60,'Curva S'!$B$2:$B$100,'Curva S'!$O$2:$O$100,0,0,1)*$I60-$J60)<0,0,(_xlfn.XLOOKUP($B60,'Curva S'!$B$2:$B$100,'Curva S'!$O$2:$O$100,0,0,1)*$I60-$J60)) -> 0 | BA60: 0 | BK60: =+IF(AND(BD60>0,BE60=""),0,IF(BE60="","",IF(BE60>=BD60,1,BE60/BD60))) | BL60: =+IF(AND(BF60>0,BG60=""),0,IF(BG60="","",IF(BG60>=BF60,1,BG60/BF60))) | BM60: =+IF(AND(BH60>0,BI60=""),0,IF(BI60="","",IF(BI60>=BH60,1,BI60/BH60)))
A61: =+_xlfn.XLOOKUP(B61,'[1]Proyectos (NO FILTRAR)'!$F:$F,'[1]Proyectos (NO FILTRAR)'!$B:$B,0,0,1) -> CH-CMP-OP-OTR00-084-A | B61: CMP_LOM MLC 2024 | C61: =+_xlfn.XLOOKUP(A61,'[1]Proyectos (NO FILTRAR)'!$B:$B,'[1]Proyectos (NO FILTRAR)'!$G:$G,"error",0,1) -> Chile | D61: Adjudicado | E61: En Proceso | F61: Cristian Quezada | H61: TBD | I61: =+_xlfn.XLOOKUP(B61,'[1]Proyectos (NO FILTRAR)'!$F:$F,'[1]Proyectos (NO FILTRAR)'!$O:$O,"!",0,1) -> 62985 | J61: =+Q61+AE61+AH61+AK61+AN61+AQ61+AT61+AW61+AZ61+BC61+BE61+BG61+BI61 -> 61149 | K61: =+IFERROR(J61/I61,0) -> 0.9708502 | L61: =+I61-J61 -> 1836 | M61: =+IFERROR(L61/I61,0) -> 0.029149798 | O61: =IFERROR(N61/I61,0) -> 0 | P61: =+I61-N61 -> 62985 | Q61: 0 | R61: =+I61-Q61 -> 62985 | AO61: 0 | AR61: 0 | AS61: 0 | AU61: 0 | AV61: 28800 | AW61: 26563 | AX61: =+IF((_xlfn.XLOOKUP($B61,'Curva S'!$B$2:$B$100,'Curva S'!$O$2:$O$100,0,0,1)*$I61-$J61)<0,0,(_xlfn.XLOOKUP($B61,'Curva S'!$B$2:$B$100,'Curva S'!$O$2:$O$100,0,0,1)*$I61-$J61)) -> 0 | BA61: 0 | BE61: 34586 | BK61: =+IF(AND(BD61>0,BE61=""),0,IF(BE61="","",IF(BE61>=BD61,1,BE61/BD61))) -> 1 | BL61: =+IF(AND(BF61>0,BG61=""),0,IF(BG61="","",IF(BG61>=BF61,1,BG61/BF61))) | BM61: =+IF(AND(BH61>0,BI61=""),0,IF(BI61="","",IF(BI61>=BH61,1,BI61/BH61)))
A62: =+_xlfn.XLOOKUP(B62,'[1]Proyectos (NO FILTRAR)'!$F:$F,'[1]Proyectos (NO FILTRAR)'!$B:$B,0,0,1) -> CH-CMP-UG-FEL03-093-A | B62: CMP_Puesta en marcha SLS Romeral | C62: =+_xlfn.XLOOKUP(A62,'[1]Proyectos (NO FILTRAR)'!$B:$B,'[1]Proyectos (NO FILTRAR)'!$G:$G,"error",0,1) -> Chile | D62: Adjudicado | E62: En Proceso | F62: Ricardo Miranda | H62: Pablo Quiero | I62: =+_xlfn.XLOOKUP(B62,'[1]Proyectos (NO FILTRAR)'!$F:$F,'[1]Proyectos (NO FILTRAR)'!$O:$O,"!",0,1) -> 900007.88 | J62: =+Q62+AE62+AH62+AK62+AN62+AQ62+AT62+AW62+AZ62+BC62+BE62+BG62+BI62 -> 769067.03 | K62: =+IFERROR(J62/I62,0) -> 0.85451144 | L62: =+I62-J62 -> 130940.85 | M62: =+IFERROR(L62/I62,0) -> 0.14548856 | O62: =IFERROR(N62/I62,0) -> 0 | P62: =+I62-N62 -> 900007.88 | Q62: 0 | R62: =+I62-Q62 -> 900007.88 | AO62: 0 | AR62: 0 | AS62: 0 | AU62: 0 | AV62: 140000 | AW62: 135485 | AX62: =+IF((_xlfn.XLOOKUP($B62,'Curva S'!$B$2:$B$100,'Curva S'!$O$2:$O$100,0,0,1)*$I62-$J62)<0,0,(_xlfn.XLOOKUP($B62,'Curva S'!$B$2:$B$100,'Curva S'!$O$2:$O$100,0,0,1)*$I62-$J62)) -> 0 | AZ62: 237714 | BA62: 0 | BC62: 108299 | BD62: 120000 | BE62: 86735 | BF62: 85000 | BG62: 81961.67 | BH62: =_xlfn.XLOOKUP(A62,'[3]Resumen POM'!$I:$I,'[3]Resumen POM'!$D:$D,"",0,1) -> 120000 | BI62: 118872.36 | BK62: =+IF(AND(BD62>0,BE62=""),0,IF(BE62="","",IF(BE62>=BD62,1,BE62/BD62))) -> 0.72279167 | BL62: =+IF(AND(BF62>0,BG62=""),0,IF(BG62="","",IF(BG62>=BF62,1,BG62/BF62))) -> 0.96425494 | BM62: =+IF(AND(BH62>0,BI62=""),0,IF(BI62="","",IF(BI62>=BH62,1,BI62/BH62))) -> 0.990603
A63: =+_xlfn.XLOOKUP(B63,'[1]Proyectos (NO FILTRAR)'!$F:$F,'[1]Proyectos (NO FILTRAR)'!$B:$B,0,0,1) -> OT-EMX-CS-OTR00-091-A | B63: EMX_Metallurgical expert for review | C63: =+_xlfn.XLOOKUP(A63,'[1]Proyectos (NO FILTRAR)'!$B:$B,'[1]Proyectos (NO FILTRAR)'!$G:$G,"error",0,1) -> Otros | D63: Adjudicado | E63: En Proceso | F63: Matias Fuentes | H63: Fernando Rodriguez | I63: =+_xlfn.XLOOKUP(B63,'[1]Proyectos (NO FILTRAR)'!$F:$F,'[1]Proyectos (NO FILTRAR)'!$O:$O,"!",0,1) -> 14850 | J63: =+Q63+AE63+AH63+AK63+AN63+AQ63+AT63+AW63+AZ63+BC63+BE63+BG63+BI63 -> 14850 | K63: =+IFERROR(J63/I63,0) -> 1 | L63: =+I63-J63 -> 0 | M63: =+IFERROR(L63/I63,0) -> 0 | O63: =IFERROR(N63/I63,0) -> 0 | P63: =+I63-N63 -> 14850 | Q63: 0 | R63: =+I63-Q63 -> 14850 | AR63: 0 | AS63: 15000 | AT63: 14850 | AU63: 0 | AX63: =+IF((_xlfn.XLOOKUP($B63,'Curva S'!$B$2:$B$100,'Curva S'!$O$2:$O$100,0,0,1)*$I63-$J63)<0,0,(_xlfn.XLOOKUP($B63,'Curva S'!$B$2:$B$100,'Curva S'!$O$2:$O$100,0,0,1)*$I63-$J63)) -> 0 | BA63: 0 | BK63: =+IF(AND(BD63>0,BE63=""),0,IF(BE63="","",IF(BE63>=BD63,1,BE63/BD63))) | BL63: =+IF(AND(BF63>0,BG63=""),0,IF(BG63="","",IF(BG63>=BF63,1,BG63/BF63))) | BM63: =+IF(AND(BH63>0,BI63=""),0,IF(BI63="","",IF(BI63>=BH63,1,BI63/BH63)))
A64: =+_xlfn.XLOOKUP(B64,'[1]Proyectos (NO FILTRAR)'!$F:$F,'[1]Proyectos (NO FILTRAR)'!$B:$B,0,0,1) -> CH-MCI-OP-OTR00-089-A | B64: MCI_Mine Plan Review Los Bronces | C64: =+_xlfn.XLOOKUP(A64,'[1]Proyectos (NO FILTRAR)'!$B:$B,'[1]Proyectos (NO FILTRAR)'!$G:$G,"error",0,1) -> Chile | D64: Adjudicado | E64: En Proceso | F64: Cristian Quezada | H64: TBD | I64: =+_xlfn.XLOOKUP(B64,'[1]Proyectos (NO FILTRAR)'!$F:$F,'[1]Proyectos (NO FILTRAR)'!$O:$O,"!",0,1) -> 239000 | J64: =+Q64+AE64+AH64+AK64+AN64+AQ64+AT64+AW64+AZ64+BC64+BE64+BG64+BI64 -> 215280 | K64: =+IFERROR(J64/I64,0) -> 0.90075314 | L64: =+I64-J64 -> 23720 | M64: =+IFERROR(L64/I64,0) -> 0.099246862 | O64: =IFERROR(N64/I64,0) -> 0 | P64: =+I64-N64 -> 239000 | Q64: 0 | R64: =+I64-Q64 -> 239000 | AT64: 71760 | AU64: 69250 | AX64: =+IF((_xlfn.XLOOKUP($B64,'Curva S'!$B$2:$B$100,'Curva S'!$O$2:$O$100,0,0,1)*$I64-$J64)<0,0,(_xlfn.XLOOKUP($B64,'Curva S'!$B$2:$B$100,'Curva S'!$O$2:$O$100,0,0,1)*$I64-$J64)) -> 0 | BA64: 167240 | BC64: 71760 | BE64: 71760 | BH64: =_xlfn.XLOOKUP(A64,'[3]Resumen POM'!$I:$I,'[3]Resumen POM'!$D:$D,"",0,1) -> 23500 | BK64: =+IF(AND(BD64>0,BE64=""),0,IF(BE64="","",IF(BE64>=BD64,1,BE64/BD64))) -> 1 | BL64: =+IF(AND(BF64>0,BG64=""),0,IF(BG64="","",IF(BG64>=BF64,1,BG64/BF64))) | BM64: =+IF(AND(BH64>0,BI64=""),0,IF(BI64="","",IF(BI64>=BH64,1,BI64/BH64))) -> 0
A65: =+_xlfn.XLOOKUP(B65,'[1]Proyectos (NO FILTRAR)'!$F:$F,'[1]Proyectos (NO FILTRAR)'!$B:$B,0,0,1) -> PE-MSR-UG-FEL00-086-A | B65: Minsur_LOM San Rafael 2025 | C65: =+_xlfn.XLOOKUP(A65,'[1]Proyectos (NO FILTRAR)'!$B:$B,'[1]Proyectos (NO FILTRAR)'!$G:$G,"error",0,1) -> Perú | D65: Adjudicado | E65: En Proceso | F65: - | H65: Kevin Rios | I65: 95282.87 | J65: =+Q65+AE65+AH65+AK65+AN65+AQ65+AT65+AW65+AZ65+BC65+BE65+BG65+BI65 -> 95282.87 | K65: =+IFERROR(J65/I65,0) -> 1 | L65: =+I65-J65 -> 0 | M65: =+IFERROR(L65/I65,0) -> 0 | O65: =IFERROR(N65/I65,0) -> 0 | P65: =+I65-N65 -> 95282.87 | Q65: 0 | R65: =+I65-Q65 -> 95282.87 | AU65: 0 | AW65: 84801.87 | AX65: =+IF((_xlfn.XLOOKUP($B65,'Curva S'!$B$2:$B$100,'Curva S'!$O$2:$O$100,0,0,1)*$I65-$J65)<0,0,(_xlfn.XLOOKUP($B65,'Curva S'!$B$2:$B$100,'Curva S'!$O$2:$O$100,0,0,1)*$I65-$J65)) -> 0 | AZ65: 10481 | BA65: 0 | BK65: =+IF(AND(BD65>0,BE65=""),0,IF(BE65="","",IF(BE65>=BD65,1,BE65/BD65))) | BL65: =+IF(AND(BF65>0,BG65=""),0,IF(BG65="","",IF(BG65>=BF65,1,BG65/BF65))) | BM65: =+IF(AND(BH65>0,BI65=""),0,IF(BI65="","",IF(BI65>=BH65,1,BI65/BH65)))
A66: =+_xlfn.XLOOKUP(B66,'[1]Proyectos (NO FILTRAR)'!$F:$F,'[1]Proyectos (NO FILTRAR)'!$B:$B,0,0,1) -> OT-EMX-CS-OTR00-087-A | B66: EMX_Due Diligence de Chapi | C66: =+_xlfn.XLOOKUP(A66,'[1]Proyectos (NO FILTRAR)'!$B:$B,'[1]Proyectos (NO FILTRAR)'!$G:$G,"error",0,1) -> Otros | D66: Adjudicado | E66: En Proceso | F66: Fernando Rodriguez | H66: - | I66: =+_xlfn.XLOOKUP(B66,'[1]Proyectos (NO FILTRAR)'!$F:$F,'[1]Proyectos (NO FILTRAR)'!$O:$O,"!",0,1) -> 159694 | J66: =+Q66+AE66+AH66+AK66+AN66+AQ66+AT66+AW66+AZ66+BC66+BE66+BG66+BI66 -> 159694 | K66: =+IFERROR(J66/I66,0) -> 1 | L66: =+I66-J66 -> 0 | M66: =+IFERROR(L66/I66,0) -> 0 | O66: =IFERROR(N66/I66,0) -> 0 | P66: =+I66-N66 -> 159694 | Q66: 0 | R66: =+I66-Q66 -> 159694 | AU66: 0 | AW66: 26649 | AX66: =+IF((_xlfn.XLOOKUP($B66,'Curva S'!$B$2:$B$100,'Curva S'!$O$2:$O$100,0,0,1)*$I66-$J66)<0,0,(_xlfn.XLOOKUP($B66,'Curva S'!$B$2:$B$100,'Curva S'!$O$2:$O$100,0,0,1)*$I66-$J66)) -> 0 | AZ66: 133045 | BA66: 0 | BK66: =+IF(AND(BD66>0,BE66=""),0,IF(BE66="","",IF(BE66>=BD66,1,BE66/BD66))) | BL66: =+IF(AND(BF66>0,BG66=""),0,IF(BG66="","",IF(BG66>=BF66,1,BG66/BF66))) | BM66: =+IF(AND(BH66>0,BI66=""),0,IF(BI66="","",IF(BI66>=BH66,1,BI66/BH66)))
A67: =+_xlfn.XLOOKUP(B67,'[1]Proyectos (NO FILTRAR)'!$F:$F,'[1]Proyectos (NO FILTRAR)'!$B:$B,0,0,1) -> OT-IEL-UG-FEL2A-088-A | B67: IvanhoeElectric_Mine Planning Support | C67: =+_xlfn.XLOOKUP(A67,'[1]Proyectos (NO FILTRAR)'!$B:$B,'[1]Proyectos (NO FILTRAR)'!$G:$G,"error",0,1) -> Otros | D67: Adjudicado | E67: En Proceso | F67: - | H67: Carlos Morante | I67: =+_xlfn.XLOOKUP(B67,'[1]Proyectos (NO FILTRAR)'!$F:$F,'[1]Proyectos (NO FILTRAR)'!$O:$O,"!",0,1) -> 196720 | J67: =+Q67+AE67+AH67+AK67+AN67+AQ67+AT67+AW67+AZ67+BC67+BE67+BG67+BI67 -> 155307 | K67: =+IFERROR(J67/I67,0) -> 0.78948251 | L67: =+I67-J67 -> 41413 | M67: =+IFERROR(L67/I67,0) -> 0.21051749 | O67: =IFERROR(N67/I67,0) -> 0 | P67: =+I67-N67 -> 196720 | Q67: 0 | R67: =+I67-Q67 -> 196720 | AU67: 0 | AW67: =16776+21370 -> 38146 | AX67: =+IF((_xlfn.XLOOKUP($B67,'Curva S'!$B$2:$B$100,'Curva S'!$O$2:$O$100,0,0,1)*$I67-$J67)<0,0,(_xlfn.XLOOKUP($B67,'Curva S'!$B$2:$B$100,'Curva S'!$O$2:$O$100,0,0,1)*$I67-$J67)) -> 0 | AZ67: 24596 | BA67: 0 | BC67: 45925 | BE67: 46640 | BK67: =+IF(AND(BD67>0,BE67=""),0,IF(BE67="","",IF(BE67>=BD67,1,BE67/BD67))) -> 1 | BL67: =+IF(AND(BF67>0,BG67=""),0,IF(BG67="","",IF(BG67>=BF67,1,BG67/BF67))) | BM67: =+IF(AND(BH67>0,BI67=""),0,IF(BI67="","",IF(BI67>=BH67,1,BI67/BH67)))
A68: =+_xlfn.XLOOKUP(B68,'[1]Proyectos (NO FILTRAR)'!$F:$F,'[1]Proyectos (NO FILTRAR)'!$B:$B,0,0,1) -> BR-J&F-CS-OTR00-100-A | B68: J&F_Autazes Due Diligence | C68: =+_xlfn.XLOOKUP(A68,'[1]Proyectos (NO FILTRAR)'!$B:$B,'[1]Proyectos (NO FILTRAR)'!$G:$G,"error",0,1) -> Brasil | D68: Adjudicado | E68: En Proceso | F68: - | H68: Kevin Rios | I68: =+_xlfn.XLOOKUP(B68,'[1]Proyectos (NO FILTRAR)'!$F:$F,'[1]Proyectos (NO FILTRAR)'!$O:$O,"!",0,1) -> 112664 | J68: =+Q68+AE68+AH68+AK68+AN68+AQ68+AT68+AW68+AZ68+BC68+BE68+BG68+BI68 -> 110873 | K68: =+IFERROR(J68/I68,0) -> 0.98410317 | L68: =+I68-J68 -> 1791 | M68: =+IFERROR(L68/I68,0) -> 0.015896826 | O68: =IFERROR(N68/I68,0) -> 0 | P68: =+I68-N68 -> 112664 | Q68: 0 | R68: =+I68-Q68 -> 112664 | S68: 1 | T68: =+K68-S68 -> -0.015896826 | U68: 2 | V68: =+M68-U68 -> -1.9841032 | W68: 3 | X68: =+O68-W68 -> -3 | Y68: 4 | Z68: =+Q68-Y68 -> -4 | AA68: 5 | AB68: =+S68-AA68 -> -4 | AU68: 70000 | AW68: 72664 | AX68: =+IF((_xlfn.XLOOKUP($B68,'Curva S'!$B$2:$B$100,'Curva S'!$O$2:$O$100,0,0,1)*$I68-$J68)<0,0,(_xlfn.XLOOKUP($B68,'Curva S'!$B$2:$B$100,'Curva S'!$O$2:$O$100,0,0,1)*$I68-$J68)) -> 0 | BA68: 0 | BE68: 38209 | BK68: =+IF(AND(BD68>0,BE68=""),0,IF(BE68="","",IF(BE68>=BD68,1,BE68/BD68))) -> 1 | BL68: =+IF(AND(BF68>0,BG68=""),0,IF(BG68="","",IF(BG68>=BF68,1,BG68/BF68))) | BM68: =+IF(AND(BH68>0,BI68=""),0,IF(BI68="","",IF(BI68>=BH68,1,BI68/BH68)))
A69: =+_xlfn.XLOOKUP(B69,'[1]Proyectos (NO FILTRAR)'!$F:$F,'[1]Proyectos (NO FILTRAR)'!$B:$B,0,0,1) -> PE-SME-CS-OTR00-099-A | B69: SierraMetals_Update MEIA Yauricocha | C69: =+_xlfn.XLOOKUP(A69,'[1]Proyectos (NO FILTRAR)'!$B:$B,'[1]Proyectos (NO FILTRAR)'!$G:$G,"error",0,1) -> Perú | D69: Adjudicado | E69: En Proceso | F69: - | H69: - | I69: =+_xlfn.XLOOKUP(B69,'[1]Proyectos (NO FILTRAR)'!$F:$F,'[1]Proyectos (NO FILTRAR)'!$O:$O,"!",0,1) -> 83610 | J69: =+Q69+AE69+AH69+AK69+AN69+AQ69+AT69+AW69+AZ69+BC69+BE69+BG69+BI69 -> 77963 | K69: =+IFERROR(J69/I69,0) -> 0.93246023 | L69: =+I69-J69 -> 5647 | M69: =+IFERROR(L69/I69,0) -> 0.067539768 | O69: =IFERROR(N69/I69,0) -> 0 | P69: =+I69-N69 -> 83610 | Q69: 0 | R69: =+I69-Q69 -> 83610 | AU69: 25919.1 | AW69: 20941 | AX69: =+IF((_xlfn.XLOOKUP($B69,'Curva S'!$B$2:$B$100,'Curva S'!$O$2:$O$100,0,0,1)*$I69-$J69)<0,0,(_xlfn.XLOOKUP($B69,'Curva S'!$B$2:$B$100,'Curva S'!$O$2:$O$100,0,0,1)*$I69-$J69)) -> 0 | AZ69: 32848 | BA69: 29821 | BC69: 24174 | BK69: =+IF(AND(BD69>0,BE69=""),0,IF(BE69="","",IF(BE69>=BD69,1,BE69/BD69))) | BL69: =+IF(AND(BF69>0,BG69=""),0,IF(BG69="","",IF(BG69>=BF69,1,BG69/BF69))) | BM69: =+IF(AND(BH69>0,BI69=""),0,IF(BI69="","",IF(BI69>=BH69,1,BI69/BH69)))
A70: =+_xlfn.XLOOKUP(B70,'[1]Proyectos (NO FILTRAR)'!$F:$F,'[1]Proyectos (NO FILTRAR)'!$B:$B,0,0,1) -> CH-GLE-CS-OTR00-094-A | B70: Glencore_MineHaul y MinePlan Lomas Bayas | C70: =+_xlfn.XLOOKUP(A70,'[1]Proyectos (NO FILTRAR)'!$B:$B,'[1]Proyectos (NO FILTRAR)'!$G:$G,"error",0,1) -> Chile | D70: Adjudicado | E70: En Proceso | F70: Cristian Quezada | H70: - | I70: =+_xlfn.XLOOKUP(B70,'[1]Proyectos (NO FILTRAR)'!$F:$F,'[1]Proyectos (NO FILTRAR)'!$O:$O,"!",0,1) -> 12000 | J70: =+Q70+AE70+AH70+AK70+AN70+AQ70+AT70+AW70+AZ70+BC70+BE70+BG70+BI70 -> 12000 | K70: =+IFERROR(J70/I70,0) -> 1 | L70: =+I70-J70 -> 0 | M70: =+IFERROR(L70/I70,0) -> 0 | O70: =IFERROR(N70/I70,0) -> 0 | P70: =+I70-N70 -> 12000 | Q70: 0 | R70: =+I70-Q70 -> 12000 | AU70: 4800 | AX70: =+IF((_xlfn.XLOOKUP($B70,'Curva S'!$B$2:$B$100,'Curva S'!$O$2:$O$100,0,0,1)*$I70-$J70)<0,0,(_xlfn.XLOOKUP($B70,'Curva S'!$B$2:$B$100,'Curva S'!$O$2:$O$100,0,0,1)*$I70-$J70)) -> 0 | AZ70: 12000 | BA70: 0 | BK70: =+IF(AND(BD70>0,BE70=""),0,IF(BE70="","",IF(BE70>=BD70,1,BE70/BD70))) | BL70: =+IF(AND(BF70>0,BG70=""),0,IF(BG70="","",IF(BG70>=BF70,1,BG70/BF70))) | BM70: =+IF(AND(BH70>0,BI70=""),0,IF(BI70="","",IF(BI70>=BH70,1,BI70/BH70)))
A71: =+_xlfn.XLOOKUP(B71,'[1]Proyectos (NO FILTRAR)'!$F:$F,'[1]Proyectos (NO FILTRAR)'!$B:$B,0,0,1) -> BR-MOS-OP-FEL2A-102-A | B71: Mosaic_Actualizacion geotecnica OP | C71: =+_xlfn.XLOOKUP(A71,'[1]Proyectos (NO FILTRAR)'!$B:$B,'[1]Proyectos (NO FILTRAR)'!$G:$G,"error",0,1) -> Brasil | D71: Adjudicado | E71: En Proceso | F71: - | H71: - | I71: =+_xlfn.XLOOKUP(B71,'[1]Proyectos (NO FILTRAR)'!$F:$F,'[1]Proyectos (NO FILTRAR)'!$O:$O,"!",0,1) -> 79900 | J71: =+Q71+AE71+AH71+AK71+AN71+AQ71+AT71+AW71+AZ71+BC71+BE71+BG71+BI71 -> 75129 | K71: =+IFERROR(J71/I71,0) -> 0.94028786 | L71: =+I71-J71 -> 4771 | M71: =+IFERROR(L71/I71,0) -> 0.05971214 | O71: =IFERROR(N71/I71,0) -> 0 | P71: =+I71-N71 -> 79900 | Q71: 0 | R71: =+I71-Q71 -> 79900 | AU71: 0 | AX71: =+IF((_xlfn.XLOOKUP($B71,'Curva S'!$B$2:$B$100,'Curva S'!$O$2:$O$100,0,0,1)*$I71-$J71)<0,0,(_xlfn.XLOOKUP($B71,'Curva S'!$B$2:$B$100,'Curva S'!$O$2:$O$100,0,0,1)*$I71-$J71)) -> 0 | BA71: 0 | BD71: 30000 | BE71: 31426 | BF71: 28000 | BG71: 43703 | BH71: =_xlfn.XLOOKUP(A71,'[3]Resumen POM'!$I:$I,'[3]Resumen POM'!$D:$D,"",0,1) -> 5000 | BK71: =+IF(AND(BD71>0,BE71=""),0,IF(BE71="","",IF(BE71>=BD71,1,BE71/BD71))) -> 1 | BL71: =+IF(AND(BF71>0,BG71=""),0,IF(BG71="","",IF(BG71>=BF71,1,BG71/BF71))) -> 1 | BM71: =+IF(AND(BH71>0,BI71=""),0,IF(BI71="","",IF(BI71>=BH71,1,BI71/BH71))) -> 0
A72: =+_xlfn.XLOOKUP(B72,'[1]Proyectos (NO FILTRAR)'!$F:$F,'[1]Proyectos (NO FILTRAR)'!$B:$B,0,0,1) -> CH-BHP-OP-FEL00-103-A | B72: BHP_Plan e Iniciativas LoA25-26 | C72: =+_xlfn.XLOOKUP(A72,'[1]Proyectos (NO FILTRAR)'!$B:$B,'[1]Proyectos (NO FILTRAR)'!$G:$G,"error",0,1) -> Chile | D72: Adjudicado | E72: En Proceso | F72: - | H72: - | I72: =+_xlfn.XLOOKUP(B72,'[1]Proyectos (NO FILTRAR)'!$F:$F,'[1]Proyectos (NO FILTRAR)'!$O:$O,"!",0,1) -> 70000 | J72: =+Q72+AE72+AH72+AK72+AN72+AQ72+AT72+AW72+AZ72+BC72+BE72+BG72+BI72 -> 46205 | K72: =+IFERROR(J72/I72,0) -> 0.66007143 | L72: =+I72-J72 -> 23795 | M72: =+IFERROR(L72/I72,0) -> 0.33992857 | O72: =IFERROR(N72/I72,0) -> 0 | P72: =+I72-N72 -> 70000 | Q72: 0 | R72: =+I72-Q72 -> 70000 | AU72: 0 | AX72: =+IF((_xlfn.XLOOKUP($B72,'Curva S'!$B$2:$B$100,'Curva S'!$O$2:$O$100,0,0,1)*$I72-$J72)<0,0,(_xlfn.XLOOKUP($B72,'Curva S'!$B$2:$B$100,'Curva S'!$O$2:$O$100,0,0,1)*$I72-$J72)) -> 0 | AZ72: 24680 | BA72: 0 | BC72: 13842 | BE72: 7683 | BH72: =_xlfn.XLOOKUP(A72,'[3]Resumen POM'!$I:$I,'[3]Resumen POM'!$D:$D,"",0,1) -> 11278 | BK72: =+IF(AND(BD72>0,BE72=""),0,IF(BE72="","",IF(BE72>=BD72,1,BE72/BD72))) -> 1 | BL72: =+IF(AND(BF72>0,BG72=""),0,IF(BG72="","",IF(BG72>=BF72,1,BG72/BF72))) | BM72: =+IF(AND(BH72>0,BI72=""),0,IF(BI72="","",IF(BI72>=BH72,1,BI72/BH72))) -> 0
A73: =+_xlfn.XLOOKUP(B73,'[1]Proyectos (NO FILTRAR)'!$F:$F,'[1]Proyectos (NO FILTRAR)'!$B:$B,0,0,1) -> CH-CMP-OT-OTR00-107-A | B73: CMP_Nuevos alcances Algarrobo | C73: =+_xlfn.XLOOKUP(A73,'[1]Proyectos (NO FILTRAR)'!$B:$B,'[1]Proyectos (NO FILTRAR)'!$G:$G,"error",0,1) -> Chile | D73: Adjudicado | E73: En Proceso | F73: Claudio Hernández | H73: Jorman Barrera | I73: =+_xlfn.XLOOKUP(B73,'[1]Proyectos (NO FILTRAR)'!$F:$F,'[1]Proyectos (NO FILTRAR)'!$O:$O,"!",0,1) -> 112506 | J73: =+Q73+AE73+AH73+AK73+AN73+AQ73+AT73+AW73+AZ73+BC73+BE73+BG73+BI73 -> 0 | K73: =+IFERROR(J73/I73,0) -> 0 | L73: =+I73-J73 -> 112506 | M73: =+IFERROR(L73/I73,0) -> 1 | O73: =IFERROR(N73/I73,0) -> 0 | P73: =+I73-N73 -> 112506 | Q73: 0 | R73: =+I73-Q73 -> 112506 | AU73: 0 | AX73: =+IF((_xlfn.XLOOKUP($B73,'Curva S'!$B$2:$B$100,'Curva S'!$O$2:$O$100,0,0,1)*$I73-$J73)<0,0,(_xlfn.XLOOKUP($B73,'Curva S'!$B$2:$B$100,'Curva S'!$O$2:$O$100,0,0,1)*$I73-$J73)) -> 0 | BA73: 0 | BD73: 60000 | BK73: =+IF(AND(BD73>0,BE73=""),0,IF(BE73="","",IF(BE73>=BD73,1,BE73/BD73))) -> 0 | BL73: =+IF(AND(BF73>0,BG73=""),0,IF(BG73="","",IF(BG73>=BF73,1,BG73/BF73))) | BM73: =+IF(AND(BH73>0,BI73=""),0,IF(BI73="","",IF(BI73>=BH73,1,BI73/BH73)))
A74: =+_xlfn.XLOOKUP(B74,'[1]Proyectos (NO FILTRAR)'!$F:$F,'[1]Proyectos (NO FILTRAR)'!$B:$B,0,0,1) -> PE-MSR-GM-OTR00-109-A | B74: Minsur_Integracion Planeamiento Geomecanica | C74: =+_xlfn.XLOOKUP(A74,'[1]Proyectos (NO FILTRAR)'!$B:$B,'[1]Proyectos (NO FILTRAR)'!$G:$G,"error",0,1) -> Perú | D74: Adjudicado | E74: Terminado | F74: Claudio Hernández | I74: =+_xlfn.XLOOKUP(B74,'[1]Proyectos (NO FILTRAR)'!$F:$F,'[1]Proyectos (NO FILTRAR)'!$O:$O,"!",0,1) -> 13797 | J74: =+Q74+AE74+AH74+AK74+AN74+AQ74+AT74+AW74+AZ74+BC74+BE74+BG74+BI74 -> 13797 | K74: =+IFERROR(J74/I74,0) -> 1 | L74: =+I74-J74 -> 0 | M74: =+IFERROR(L74/I74,0) -> 0 | O74: =IFERROR(N74/I74,0) -> 0 | P74: =+I74-N74 -> 13797 | Q74: 0 | R74: =+I74-Q74 -> 13797 | AT74: 13797 | AX74: =+IF((_xlfn.XLOOKUP($B74,'Curva S'!$B$2:$B$100,'Curva S'!$O$2:$O$100,0,0,1)*$I74-$J74)<0,0,(_xlfn.XLOOKUP($B74,'Curva S'!$B$2:$B$100,'Curva S'!$O$2:$O$100,0,0,1)*$I74-$J74)) -> 0 | BA74: 0 | BK74: =+IF(AND(BD74>0,BE74=""),0,IF(BE74="","",IF(BE74>=BD74,1,BE74/BD74))) | BL74: =+IF(AND(BF74>0,BG74=""),0,IF(BG74="","",IF(BG74>=BF74,1,BG74/BF74))) | BM74: =+IF(AND(BH74>0,BI74=""),0,IF(BI74="","",IF(BI74>=BH74,1,BI74/BH74)))
A75: =+_xlfn.XLOOKUP(B75,'[1]Proyectos (NO FILTRAR)'!$F:$F,'[1]Proyectos (NO FILTRAR)'!$B:$B,0,0,1) -> CH-AMS-OT-OTR00-108-A | B75: AMSA_Contrato Marco | C75: =+_xlfn.XLOOKUP(A75,'[1]Proyectos (NO FILTRAR)'!$B:$B,'[1]Proyectos (NO FILTRAR)'!$G:$G,"error",0,1) -> Chile | D75: Adjudicado | E75: En Proceso | F75: Gonzalo Díaz | H75: Nicolás Ayarza | I75: =+_xlfn.XLOOKUP(B75,'[1]Proyectos (NO FILTRAR)'!$F:$F,'[1]Proyectos (NO FILTRAR)'!$O:$O,"!",0,1) -> 191000 | J75: =+Q75+AE75+AH75+AK75+AN75+AQ75+AT75+AW75+AZ75+BC75+BE75+BG75+BI75 -> 76524.88 | K75: =+IFERROR(J75/I75,0) -> 0.40065382 | L75: =+I75-J75 -> 114475.12 | M75: =+IFERROR(L75/I75,0) -> 0.59934618 | O75: =IFERROR(N75/I75,0) -> 0 | P75: =+I75-N75 -> 191000 | Q75: 0 | R75: =+I75-Q75 -> 191000 | AZ75: 34347 | BC75: 18000 | BD75: 30640 | BF75: 15160 | BG75: 11820.81 | BH75: =_xlfn.XLOOKUP(A75,'[3]Resumen POM'!$I:$I,'[3]Resumen POM'!$D:$D,"",0,1) -> 6101.1021 | BI75: 12357.07 | BK75: =+IF(AND(BD75>0,BE75=""),0,IF(BE75="","",IF(BE75>=BD75,1,BE75/BD75))) -> 0 | BL75: =+IF(AND(BF75>0,BG75=""),0,IF(BG75="","",IF(BG75>=BF75,1,BG75/BF75))) -> 0.77973681 | BM75: =+IF(AND(BH75>0,BI75=""),0,IF(BI75="","",IF(BI75>=BH75,1,BI75/BH75))) -> 1
A76: =+_xlfn.XLOOKUP(B76,'[1]Proyectos (NO FILTRAR)'!$F:$F,'[1]Proyectos (NO FILTRAR)'!$B:$B,0,0,1) -> CH-COD-OU-FEL00-112-A | B76: Codelco_Opciones vaciado mineral via OP | C76: =+_xlfn.XLOOKUP(A76,'[1]Proyectos (NO FILTRAR)'!$B:$B,'[1]Proyectos (NO FILTRAR)'!$G:$G,"error",0,1) -> Chile | D76: Adjudicado | E76: En Proceso | F76: Mauricio Melendez | H76: Freddy Diaz | I76: =+_xlfn.XLOOKUP(B76,'[1]Proyectos (NO FILTRAR)'!$F:$F,'[1]Proyectos (NO FILTRAR)'!$O:$O,"!",0,1) -> 85362.89 | J76: =+Q76+AE76+AH76+AK76+AN76+AQ76+AT76+AW76+AZ76+BC76+BE76+BG76+BI76 -> 75127 | K76: =+IFERROR(J76/I76,0) -> 0.8800897 | L76: =+I76-J76 -> 10235.89 | M76: =+IFERROR(L76/I76,0) -> 0.1199103 | O76: =IFERROR(N76/I76,0) -> 0 | P76: =+I76-N76 -> 85362.89 | Q76: 0 | R76: =+I76-Q76 -> 85362.89 | BC76: 40000 | BD76: 30000 | BE76: 35127 | BF76: 10000 | BH76: =_xlfn.XLOOKUP(A76,'[3]Resumen POM'!$I:$I,'[3]Resumen POM'!$D:$D,"",0,1) -> 10587.789 | BK76: =+IF(AND(BD76>0,BE76=""),0,IF(BE76="","",IF(BE76>=BD76,1,BE76/BD76))) -> 1 | BL76: =+IF(AND(BF76>0,BG76=""),0,IF(BG76="","",IF(BG76>=BF76,1,BG76/BF76))) -> 0 | BM76: =+IF(AND(BH76>0,BI76=""),0,IF(BI76="","",IF(BI76>=BH76,1,BI76/BH76))) -> 0
A77: =+_xlfn.XLOOKUP(B77,'[1]Proyectos (NO FILTRAR)'!$F:$F,'[1]Proyectos (NO FILTRAR)'!$B:$B,0,0,1) -> PE-MAR-OU-FEL01-114-A | B77: Marcobre_Ingeniería de Perfil Achupallas | C77: =+_xlfn.XLOOKUP(A77,'[1]Proyectos (NO FILTRAR)'!$B:$B,'[1]Proyectos (NO FILTRAR)'!$G:$G,"error",0,1) -> Perú | D77: Adjudicado | E77: En Proceso | F77: Rodrigo Baez | H77: Eduardo Sanchez | I77: =+_xlfn.XLOOKUP(B77,'[1]Proyectos (NO FILTRAR)'!$F:$F,'[1]Proyectos (NO FILTRAR)'!$O:$O,"!",0,1) -> 161778 | J77: =+Q77+AE77+AH77+AK77+AN77+AQ77+AT77+AW77+AZ77+BC77+BE77+BG77+BI77 -> 73833 | K77: =+IFERROR(J77/I77,0) -> 0.45638468 | L77: =+I77-J77 -> 87945 | M77: =+IFERROR(L77/I77,0) -> 0.54361532 | O77: =IFERROR(N77/I77,0) -> 0 | P77: =+I77-N77 -> 161778 | Q77: 0 | R77: =+I77-Q77 -> 161778 | BD77: 19979 | BE77: 33000 | BF77: 20000 | BG77: 21062 | BH77: =_xlfn.XLOOKUP(A77,'[3]Resumen POM'!$I:$I,'[3]Resumen POM'!$D:$D,"",0,1) -> 42080 | BI77: 19771 | BK77: =+IF(AND(BD77>0,BE77=""),0,IF(BE77="","",IF(BE77>=BD77,1,BE77/BD77))) -> 1 | BL77: =+IF(AND(BF77>0,BG77=""),0,IF(BG77="","",IF(BG77>=BF77,1,BG77/BF77))) -> 1 | BM77: =+IF(AND(BH77>0,BI77=""),0,IF(BI77="","",IF(BI77>=BH77,1,BI77/BH77))) -> 0.46984316
A78: =+_xlfn.XLOOKUP(B78,'[1]Proyectos (NO FILTRAR)'!$F:$F,'[1]Proyectos (NO FILTRAR)'!$B:$B,0,0,1) -> PE-MSR-UG-OTR00-097-A | B78: Minsur_Evaluacion recursos marginales | C78: =+_xlfn.XLOOKUP(A78,'[1]Proyectos (NO FILTRAR)'!$B:$B,'[1]Proyectos (NO FILTRAR)'!$G:$G,"error",0,1) -> Perú | D78: Adjudicado | E78: En Proceso | F78: Matías Fuentes | H78: Kevin Ríos | I78: =+_xlfn.XLOOKUP(B78,'[1]Proyectos (NO FILTRAR)'!$F:$F,'[1]Proyectos (NO FILTRAR)'!$O:$O,"!",0,1) -> 64935 | J78: =+Q78+AE78+AH78+AK78+AN78+AQ78+AT78+AW78+AZ78+BC78+BE78+BG78+BI78 -> 64935 | K78: =+IFERROR(J78/I78,0) -> 1 | L78: =+I78-J78 -> 0 | M78: =+IFERROR(L78/I78,0) -> 0 | O78: =IFERROR(N78/I78,0) -> 0 | P78: =+I78-N78 -> 64935 | Q78: 0 | R78: =+I78-Q78 -> 64935 | BD78: 22078 | BE78: 26104 | BF78: 25325 | BG78: 25519 | BH78: =_xlfn.XLOOKUP(A78,'[3]Resumen POM'!$I:$I,'[3]Resumen POM'!$D:$D,"",0,1) -> 13312 | BI78: 13312 | BK78: =+IF(AND(BD78>0,BE78=""),0,IF(BE78="","",IF(BE78>=BD78,1,BE78/BD78))) -> 1 | BL78: =+IF(AND(BF78>0,BG78=""),0,IF(BG78="","",IF(BG78>=BF78,1,BG78/BF78))) -> 1 | BM78: =+IF(AND(BH78>0,BI78=""),0,IF(BI78="","",IF(BI78>=BH78,1,BI78/BH78))) -> 1
A79: =+_xlfn.XLOOKUP(B79,'[1]Proyectos (NO FILTRAR)'!$F:$F,'[1]Proyectos (NO FILTRAR)'!$B:$B,0,0,1) -> CH-LUN-OP-FEL00-110-A | B79: Lundin_Oportunidades mejoras Caserones | C79: =+_xlfn.XLOOKUP(A79,'[1]Proyectos (NO FILTRAR)'!$B:$B,'[1]Proyectos (NO FILTRAR)'!$G:$G,"error",0,1) -> Chile | D79: Adjudicado | E79: En Proceso | F79: Rodrigo Baez | H79: Kevin Ríos | I79: =+_xlfn.XLOOKUP(B79,'[1]Proyectos (NO FILTRAR)'!$F:$F,'[1]Proyectos (NO FILTRAR)'!$O:$O,"!",0,1) -> 123240 | J79: =+Q79+AE79+AH79+AK79+AN79+AQ79+AT79+AW79+AZ79+BC79+BE79+BG79+BI79 -> 120155.94 | K79: =+IFERROR(J79/I79,0) -> 0.97497517 | L79: =+I79-J79 -> 3084.06 | M79: =+IFERROR(L79/I79,0) -> 0.02502483 | O79: =IFERROR(N79/I79,0) -> 0 | P79: =+I79-N79 -> 123240 | Q79: 0 | R79: =+I79-Q79 -> 123240 | BC79: 20675 | BD79: 19870 | BE79: 17060 | BF79: 50000 | BH79: =_xlfn.XLOOKUP(A79,'[3]Resumen POM'!$I:$I,'[3]Resumen POM'!$D:$D,"",0,1) -> 26759.52 | BI79: 82420.94 | BK79: =+IF(AND(BD79>0,BE79=""),0,IF(BE79="","",IF(BE79>=BD79,1,BE79/BD79))) -> 0.85858078 | BL79: =+IF(AND(BF79>0,BG79=""),0,IF(BG79="","",IF(BG79>=BF79,1,BG79/BF79))) -> 0 | BM79: =+IF(AND(BH79>0,BI79=""),0,IF(BI79="","",IF(BI79>=BH79,1,BI79/BH79))) -> 1
A80: =+_xlfn.XLOOKUP(B80,'[1]Proyectos (NO FILTRAR)'!$F:$F,'[1]Proyectos (NO FILTRAR)'!$B:$B,0,0,1) -> CH-LUN-CS-OTR00-113-A | B80: Lundin_Gaps Planificación y Operación UG | C80: =+_xlfn.XLOOKUP(A80,'[1]Proyectos (NO FILTRAR)'!$B:$B,'[1]Proyectos (NO FILTRAR)'!$G:$G,"error",0,1) -> Chile | D80: Adjudicado | E80: En Proceso | F80: Alex Figueroa | H80: Pablo Quiero | I80: =+_xlfn.XLOOKUP(B80,'[1]Proyectos (NO FILTRAR)'!$F:$F,'[1]Proyectos (NO FILTRAR)'!$O:$O,"!",0,1) -> 61650 | J80: =+Q80+AE80+AH80+AK80+AN80+AQ80+AT80+AW80+AZ80+BC80+BE80+BG80+BI80 -> 66652 | K80: =+IFERROR(J80/I80,0) -> 1.0811354 | L80: =+I80-J80 -> -5002 | M80: =+IFERROR(L80/I80,0) -> -0.081135442 | O80: =IFERROR(N80/I80,0) -> 0 | P80: =+I80-N80 -> 61650 | Q80: 0 | R80: =+I80-Q80 -> 61650 | BF80: 65000 | BH80: =_xlfn.XLOOKUP(A80,'[3]Resumen POM'!$I:$I,'[3]Resumen POM'!$D:$D,"",0,1) -> 65000 | BI80: =61650+5002 -> 66652 | BK80: =+IF(AND(BD80>0,BE80=""),0,IF(BE80="","",IF(BE80>=BD80,1,BE80/BD80))) | BL80: =+IF(AND(BF80>0,BG80=""),0,IF(BG80="","",IF(BG80>=BF80,1,BG80/BF80))) -> 0 | BM80: =+IF(AND(BH80>0,BI80=""),0,IF(BI80="","",IF(BI80>=BH80,1,BI80/BH80))) -> 1
A81: =+_xlfn.XLOOKUP(B81,'[1]Proyectos (NO FILTRAR)'!$F:$F,'[1]Proyectos (NO FILTRAR)'!$B:$B,0,0,1) -> BR-MOS-CS-OTR00-115-A | B81: Mosaic_Secuencia Operaciones Cajati | C81: =+_xlfn.XLOOKUP(A81,'[1]Proyectos (NO FILTRAR)'!$B:$B,'[1]Proyectos (NO FILTRAR)'!$G:$G,"error",0,1) -> Brasil | D81: Adjudicado | E81: En Proceso | F81: Alex Figueroa | H81: Nicolas Ayarza | I81: =+_xlfn.XLOOKUP(B81,'[1]Proyectos (NO FILTRAR)'!$F:$F,'[1]Proyectos (NO FILTRAR)'!$O:$O,"!",0,1) -> 60100.34 | J81: =+Q81+AE81+AH81+AK81+AN81+AQ81+AT81+AW81+AZ81+BC81+BE81+BG81+BI81 -> 25514 | K81: =+IFERROR(J81/I81,0) -> 0.42452339 | L81: =+I81-J81 -> 34586.34 | M81: =+IFERROR(L81/I81,0) -> 0.57547661 | O81: =IFERROR(N81/I81,0) -> 0 | P81: =+I81-N81 -> 60100.34 | Q81: 0 | R81: =+I81-Q81 -> 60100.34 | BF81: 10000 | BG81: 8053 | BH81: =_xlfn.XLOOKUP(A81,'[3]Resumen POM'!$I:$I,'[3]Resumen POM'!$D:$D,"",0,1) -> 17300 | BI81: 17461 | BK81: =+IF(AND(BD81>0,BE81=""),0,IF(BE81="","",IF(BE81>=BD81,1,BE81/BD81))) | BL81: =+IF(AND(BF81>0,BG81=""),0,IF(BG81="","",IF(BG81>=BF81,1,BG81/BF81))) -> 0.8053 | BM81: =+IF(AND(BH81>0,BI81=""),0,IF(BI81="","",IF(BI81>=BH81,1,BI81/BH81))) -> 1
A82: =+_xlfn.XLOOKUP(B82,'[1]Proyectos (NO FILTRAR)'!$F:$F,'[1]Proyectos (NO FILTRAR)'!$B:$B,0,0,1) -> CH-CMP-UG-OTR00-095-A | B82: CMP_Estrategia Crecimiento Tofo Norte | C82: =+_xlfn.XLOOKUP(A82,'[1]Proyectos (NO FILTRAR)'!$B:$B,'[1]Proyectos (NO FILTRAR)'!$G:$G,"error",0,1) -> Chile | D82: Adjudicado | E82: En Proceso | F82: Ricardo Miranda | H82: Gerson Alfaro | I82: =+_xlfn.XLOOKUP(B82,'[1]Proyectos (NO FILTRAR)'!$F:$F,'[1]Proyectos (NO FILTRAR)'!$O:$O,"!",0,1) -> 94854 | J82: =+Q82+AE82+AH82+AK82+AN82+AQ82+AT82+AW82+AZ82+BC82+BE82+BG82+BI82 -> 79951 | K82: =+IFERROR(J82/I82,0) -> 0.84288485 | L82: =+I82-J82 -> 14903 | M82: =+IFERROR(L82/I82,0) -> 0.15711515 | O82: =IFERROR(N82/I82,0) -> 0 | P82: =+I82-N82 -> 94854 | Q82: 0 | R82: =+I82-Q82 -> 94854 | AZ82: =6500+2406 -> 8906 | BC82: 13808 | BD82: 6177 | BE82: 3212 | BF82: 24389 | BG82: 17309 | BH82: =_xlfn.XLOOKUP(A82,'[3]Resumen POM'!$I:$I,'[3]Resumen POM'!$D:$D,"",0,1) -> 27000 | BI82: 36716 | BK82: =+IF(AND(BD82>0,BE82=""),0,IF(BE82="","",IF(BE82>=BD82,1,BE82/BD82))) -> 0.51999352 | BL82: =+IF(AND(BF82>0,BG82=""),0,IF(BG82="","",IF(BG82>=BF82,1,BG82/BF82))) -> 0.70970519 | BM82: =+IF(AND(BH82>0,BI82=""),0,IF(BI82="","",IF(BI82>=BH82,1,BI82/BH82))) -> 1
A83: =+_xlfn.XLOOKUP(B83,'[1]Proyectos (NO FILTRAR)'!$F:$F,'[1]Proyectos (NO FILTRAR)'!$B:$B,0,0,1) -> CH-CMP-OP-OTR00-096-A | B83: CMP_Plan minero base MLC | C83: =+_xlfn.XLOOKUP(A83,'[1]Proyectos (NO FILTRAR)'!$B:$B,'[1]Proyectos (NO FILTRAR)'!$G:$G,"error",0,1) -> Chile | D83: Adjudicado | E83: En Proceso | F83: Cristian Quezada | H83: Rodrigo Cori | I83: 64095 | J83: =+Q83+AE83+AH83+AK83+AN83+AQ83+AT83+AW83+AZ83+BC83+BE83+BG83+BI83 -> 55137.5 | K83: =+IFERROR(J83/I83,0) -> 0.86024651 | L83: =+I83-J83 -> 8957.5 | M83: =+IFERROR(L83/I83,0) -> 0.13975349 | O83: =IFERROR(N83/I83,0) -> 0 | P83: =+I83-N83 -> 64095 | Q83: 0 | R83: =+I83-Q83 -> 64095 | AZ83: =5300+2406 -> 7706 | BC83: 4603 | BD83: 29400 | BE83: 3705 | BF83: 5000 | BG83: 4391.5 | BH83: =_xlfn.XLOOKUP(A83,'[3]Resumen POM'!$I:$I,'[3]Resumen POM'!$D:$D,"",0,1) -> 40106 | BI83: 34732 | BK83: =+IF(AND(BD83>0,BE83=""),0,IF(BE83="","",IF(BE83>=BD83,1,BE83/BD83))) -> 0.12602041 | BL83: =+IF(AND(BF83>0,BG83=""),0,IF(BG83="","",IF(BG83>=BF83,1,BG83/BF83))) -> 0.8783 | BM83: =+IF(AND(BH83>0,BI83=""),0,IF(BI83="","",IF(BI83>=BH83,1,BI83/BH83))) -> 0.86600509
A84: =+_xlfn.XLOOKUP(B84,'[1]Proyectos (NO FILTRAR)'!$F:$F,'[1]Proyectos (NO FILTRAR)'!$B:$B,0,0,1) -> CH-CMP-OP-FEL00-106-A | B84: CMP_Mejoras Operacionales CNN | C84: =+_xlfn.XLOOKUP(A84,'[1]Proyectos (NO FILTRAR)'!$B:$B,'[1]Proyectos (NO FILTRAR)'!$G:$G,"error",0,1) -> Chile | D84: Adjudicado | E84: En Proceso | F84: Matías Fuentes | H84: Fernando Sagastegui | I84: =+_xlfn.XLOOKUP(B84,'[1]Proyectos (NO FILTRAR)'!$F:$F,'[1]Proyectos (NO FILTRAR)'!$O:$O,"!",0,1) -> 121038.49 | J84: =+Q84+AE84+AH84+AK84+AN84+AQ84+AT84+AW84+AZ84+BC84+BE84+BG84+BI84 -> 46214.27 | K84: =+IFERROR(J84/I84,0) -> 0.38181466 | L84: =+I84-J84 -> 74824.22 | M84: =+IFERROR(L84/I84,0) -> 0.61818534 | O84: =IFERROR(N84/I84,0) -> 0 | P84: =+I84-N84 -> 121038.49 | Q84: 0 | R84: =+I84-Q84 -> 121038.49 | BF84: 15000 | BH84: =_xlfn.XLOOKUP(A84,'[3]Resumen POM'!$I:$I,'[3]Resumen POM'!$D:$D,"",0,1) -> 22500 | BI84: 46214.27 | BK84: =+IF(AND(BD84>0,BE84=""),0,IF(BE84="","",IF(BE84>=BD84,1,BE84/BD84))) | BL84: =+IF(AND(BF84>0,BG84=""),0,IF(BG84="","",IF(BG84>=BF84,1,BG84/BF84))) -> 0 | BM84: =+IF(AND(BH84>0,BI84=""),0,IF(BI84="","",IF(BI84>=BH84,1,BI84/BH84))) -> 1
A85: =+_xlfn.XLOOKUP(B85,'[1]Proyectos (NO FILTRAR)'!$F:$F,'[1]Proyectos (NO FILTRAR)'!$B:$B,0,0,1) -> CH-AMS-CS-OTR00-116-A | B85: AMSA_Trade Off Tecnologico NGD | C85: =+_xlfn.XLOOKUP(A85,'[1]Proyectos (NO FILTRAR)'!$B:$B,'[1]Proyectos (NO FILTRAR)'!$G:$G,"error",0,1) -> Chile | D85: Adjudicado | E85: En Proceso | F85: Gonzalo Díaz | H85: Nicolas Ayarza | I85: =+_xlfn.XLOOKUP(B85,'[1]Proyectos (NO FILTRAR)'!$F:$F,'[1]Proyectos (NO FILTRAR)'!$O:$O,"!",0,1) -> 134445.67 | J85: =+Q85+AE85+AH85+AK85+AN85+AQ85+AT85+AW85+AZ85+BC85+BE85+BG85+BI85 -> 0 | K85: =+IFERROR(J85/I85,0) -> 0 | L85: =+I85-J85 -> 134445.67 | M85: =+IFERROR(L85/I85,0) -> 1 | O85: =IFERROR(N85/I85,0) -> 0 | P85: =+I85-N85 -> 134445.67 | Q85: 0 | R85: =+I85-Q85 -> 134445.67 | BF85: 10000 | BH85: =_xlfn.XLOOKUP(A85,'[3]Resumen POM'!$I:$I,'[3]Resumen POM'!$D:$D,"",0,1) -> 20000 | BI85: 0 | BK85: =+IF(AND(BD85>0,BE85=""),0,IF(BE85="","",IF(BE85>=BD85,1,BE85/BD85))) | BL85: =+IF(AND(BF85>0,BG85=""),0,IF(BG85="","",IF(BG85>=BF85,1,BG85/BF85))) -> 0 | BM85: =+IF(AND(BH85>0,BI85=""),0,IF(BI85="","",IF(BI85>=BH85,1,BI85/BH85))) -> 0
A86: =+_xlfn.XLOOKUP(B86,'[1]Proyectos (NO FILTRAR)'!$F:$F,'[1]Proyectos (NO FILTRAR)'!$B:$B,0,0,1) -> CH-CCO-CS-FEL00-117-A | B86: Capstone Copper_Estudio Sierra Norte | C86: =+_xlfn.XLOOKUP(A86,'[1]Proyectos (NO FILTRAR)'!$B:$B,'[1]Proyectos (NO FILTRAR)'!$G:$G,"error",0,1) -> Chile | D86: Adjudicado | E86: En Proceso | F86: Matías Fuentes | H86: Nicolas Ayarza | I86: =+_xlfn.XLOOKUP(B86,'[1]Proyectos (NO FILTRAR)'!$F:$F,'[1]Proyectos (NO FILTRAR)'!$O:$O,"!",0,1) -> 196000.3 | J86: =+Q86+AE86+AH86+AK86+AN86+AQ86+AT86+AW86+AZ86+BC86+BE86+BG86+BI86 -> 160223 | K86: =+IFERROR(J86/I86,0) -> 0.81746303 | L86: =+I86-J86 -> 35777.3 | M86: =+IFERROR(L86/I86,0) -> 0.18253697 | O86: =IFERROR(N86/I86,0) -> 0 | P86: =+I86-N86 -> 196000.3 | Q86: 0 | R86: =+I86-Q86 -> 196000.3 | BF86: 20320 | BG86: 31291 | BH86: =_xlfn.XLOOKUP(A86,'[3]Resumen POM'!$I:$I,'[3]Resumen POM'!$D:$D,"",0,1) -> 64052 | BI86: 128932 | BK86: =+IF(AND(BD86>0,BE86=""),0,IF(BE86="","",IF(BE86>=BD86,1,BE86/BD86))) | BL86: =+IF(AND(BF86>0,BG86=""),0,IF(BG86="","",IF(BG86>=BF86,1,BG86/BF86))) -> 1 | BM86: =+IF(AND(BH86>0,BI86=""),0,IF(BI86="","",IF(BI86>=BH86,1,BI86/BH86))) -> 1
A87: =+_xlfn.XLOOKUP(B87,'[1]Proyectos (NO FILTRAR)'!$F:$F,'[1]Proyectos (NO FILTRAR)'!$B:$B,0,0,1) -> PE-CMC-CD-OTR00-118-A | B87: CMC_Capacitación DBS y SIMPLAN | C87: =+_xlfn.XLOOKUP(A87,'[1]Proyectos (NO FILTRAR)'!$B:$B,'[1]Proyectos (NO FILTRAR)'!$G:$G,"error",0,1) -> Perú | D87: Adjudicado | E87: En Proceso | F87: Jorman Barrera | H87: Rodrigo Cori | I87: =+_xlfn.XLOOKUP(B87,'[1]Proyectos (NO FILTRAR)'!$F:$F,'[1]Proyectos (NO FILTRAR)'!$O:$O,"!",0,1) -> 19700 | J87: =+Q87+AE87+AH87+AK87+AN87+AQ87+AT87+AW87+AZ87+BC87+BE87+BG87+BI87 -> 19700 | K87: =+IFERROR(J87/I87,0) -> 1 | L87: =+I87-J87 -> 0 | M87: =+IFERROR(L87/I87,0) -> 0 | O87: =IFERROR(N87/I87,0) -> 0 | P87: =+I87-N87 -> 19700 | Q87: 0 | R87: =+I87-Q87 -> 19700 | BF87: 12000 | BG87: 12843 | BH87: =_xlfn.XLOOKUP(A87,'[3]Resumen POM'!$I:$I,'[3]Resumen POM'!$D:$D,"",0,1) -> 6857 | BI87: 6857 | BK87: =+IF(AND(BD87>0,BE87=""),0,IF(BE87="","",IF(BE87>=BD87,1,BE87/BD87))) | BL87: =+IF(AND(BF87>0,BG87=""),0,IF(BG87="","",IF(BG87>=BF87,1,BG87/BF87))) -> 1 | BM87: =+IF(AND(BH87>0,BI87=""),0,IF(BI87="","",IF(BI87>=BH87,1,BI87/BH87))) -> 1
A88: =+_xlfn.XLOOKUP(B88,'[1]Proyectos (NO FILTRAR)'!$F:$F,'[1]Proyectos (NO FILTRAR)'!$B:$B,0,0,1) -> OT-TWM-CS-FEL00-119-A | B88: Twin Metals_Pre PFS Birch Lake Maturi | C88: =+_xlfn.XLOOKUP(A88,'[1]Proyectos (NO FILTRAR)'!$B:$B,'[1]Proyectos (NO FILTRAR)'!$G:$G,"error",0,1) -> Otros | D88: Adjudicado | E88: En Proceso | F88: Jorman Barrera | H88: Eduardo Sanchez | I88: =+_xlfn.XLOOKUP(B88,'[1]Proyectos (NO FILTRAR)'!$F:$F,'[1]Proyectos (NO FILTRAR)'!$O:$O,"!",0,1) -> 481541 | J88: =+Q88+AE88+AH88+AK88+AN88+AQ88+AT88+AW88+AZ88+BC88+BE88+BG88+BI88 -> 112740.6 | K88: =+IFERROR(J88/I88,0) -> 0.23412461 | L88: =+I88-J88 -> 368800.4 | M88: =+IFERROR(L88/I88,0) -> 0.76587539 | O88: =IFERROR(N88/I88,0) -> 0 | P88: =+I88-N88 -> 481541 | Q88: 0 | R88: =+I88-Q88 -> 481541 | BF88: 41000 | BG88: 51319 | BH88: =_xlfn.XLOOKUP(A88,'[3]Resumen POM'!$I:$I,'[3]Resumen POM'!$D:$D,"",0,1) -> 90959 | BI88: 61421.6 | BK88: =+IF(AND(BD88>0,BE88=""),0,IF(BE88="","",IF(BE88>=BD88,1,BE88/BD88))) | BL88: =+IF(AND(BF88>0,BG88=""),0,IF(BG88="","",IF(BG88>=BF88,1,BG88/BF88))) -> 1 | BM88: =+IF(AND(BH88>0,BI88=""),0,IF(BI88="","",IF(BI88>=BH88,1,BI88/BH88))) -> 0.67526688
A89: =+_xlfn.XLOOKUP(B89,'[1]Proyectos (NO FILTRAR)'!$F:$F,'[1]Proyectos (NO FILTRAR)'!$B:$B,0,0,1) -> OT-THC-CS-OTR00-122-A | B89: ThreeCrowns_Litigio Oyu Tolgoi | C89: =+_xlfn.XLOOKUP(A89,'[1]Proyectos (NO FILTRAR)'!$B:$B,'[1]Proyectos (NO FILTRAR)'!$G:$G,"error",0,1) -> Otros | D89: Adjudicado | E89: En Proceso | F89: TBD | H89: TBD | I89: =+_xlfn.XLOOKUP(B89,'[1]Proyectos (NO FILTRAR)'!$F:$F,'[1]Proyectos (NO FILTRAR)'!$O:$O,"!",0,1) -> 645700 | J89: =+Q89+AE89+AH89+AK89+AN89+AQ89+AT89+AW89+AZ89+BC89+BE89+BG89+BI89 -> 0 | K89: =+IFERROR(J89/I89,0) -> 0 | L89: =+I89-J89 -> 645700 | M89: =+IFERROR(L89/I89,0) -> 1 | O89: =IFERROR(N89/I89,0) -> 0 | P89: =+I89-N89 -> 645700 | Q89: 0 | R89: =+I89-Q89 -> 645700 | BK89: =+IF(AND(BD89>0,BE89=""),0,IF(BE89="","",IF(BE89>=BD89,1,BE89/BD89))) | BL89: =+IF(AND(BF89>0,BG89=""),0,IF(BG89="","",IF(BG89>=BF89,1,BG89/BF89))) | BM89: =+IF(AND(BH89>0,BI89=""),0,IF(BI89="","",IF(BI89>=BH89,1,BI89/BH89)))
A90: =+_xlfn.XLOOKUP(B90,'[1]Proyectos (NO FILTRAR)'!$F:$F,'[1]Proyectos (NO FILTRAR)'!$B:$B,0,0,1) -> CH-COD-CS-OTR00-128-A | B90: Codelco_Estándar cierre topográfico | C90: =+_xlfn.XLOOKUP(A90,'[1]Proyectos (NO FILTRAR)'!$B:$B,'[1]Proyectos (NO FILTRAR)'!$G:$G,"error",0,1) -> Chile | D90: Adjudicado | E90: En Proceso | F90: Mauricio Melendez | H90: Rodrigo Baez | I90: =+_xlfn.XLOOKUP(B90,'[1]Proyectos (NO FILTRAR)'!$F:$F,'[1]Proyectos (NO FILTRAR)'!$O:$O,"!",0,1) -> 36418 | J90: =+Q90+AE90+AH90+AK90+AN90+AQ90+AT90+AW90+AZ90+BC90+BE90+BG90+BI90 -> 29155 | K90: =+IFERROR(J90/I90,0) -> 0.80056565 | L90: =+I90-J90 -> 7263 | M90: =+IFERROR(L90/I90,0) -> 0.19943435 | O90: =IFERROR(N90/I90,0) -> 0 | P90: =+I90-N90 -> 36418 | Q90: 0 | R90: =+I90-Q90 -> 36418 | BF90: 11000 | BG90: 11004 | BH90: =_xlfn.XLOOKUP(A90,'[3]Resumen POM'!$I:$I,'[3]Resumen POM'!$D:$D,"",0,1) -> 26296.62 | BI90: 18151 | BK90: =+IF(AND(BD90>0,BE90=""),0,IF(BE90="","",IF(BE90>=BD90,1,BE90/BD90))) | BL90: =+IF(AND(BF90>0,BG90=""),0,IF(BG90="","",IF(BG90>=BF90,1,BG90/BF90))) -> 1 | BM90: =+IF(AND(BH90>0,BI90=""),0,IF(BI90="","",IF(BI90>=BH90,1,BI90/BH90))) -> 0.6902408
A91: =+_xlfn.XLOOKUP(B91,'[1]Proyectos (NO FILTRAR)'!$F:$F,'[1]Proyectos (NO FILTRAR)'!$B:$B,0,0,1) -> BR-MOS-UG-FEL2A-064-A | B91: Mosaic_Taquari Vassouras Fase II CP | C91: =+_xlfn.XLOOKUP(A91,'[1]Proyectos (NO FILTRAR)'!$B:$B,'[1]Proyectos (NO FILTRAR)'!$G:$G,"error",0,1) -> Brasil | D91: Adjudicado | E91: En Proceso | F91: Alex Figueroa | H91: Kevin Ríos | I91: =+_xlfn.XLOOKUP(B91,'[1]Proyectos (NO FILTRAR)'!$F:$F,'[1]Proyectos (NO FILTRAR)'!$O:$O,"!",0,1) -> 52744 | J91: =+Q91+AE91+AH91+AK91+AN91+AQ91+AT91+AW91+AZ91+BC91+BE91+BG91+BI91 -> 52744 | K91: =+IFERROR(J91/I91,0) -> 1 | L91: =+I91-J91 -> 0 | M91: =+IFERROR(L91/I91,0) -> 0 | O91: =IFERROR(N91/I91,0) -> 0 | P91: =+I91-N91 -> 52744 | Q91: 0 | R91: =+I91-Q91 -> 52744 | BC91: 52744 | BK91: =+IF(AND(BD91>0,BE91=""),0,IF(BE91="","",IF(BE91>=BD91,1,BE91/BD91))) | BL91: =+IF(AND(BF91>0,BG91=""),0,IF(BG91="","",IF(BG91>=BF91,1,BG91/BF91))) | BM91: =+IF(AND(BH91>0,BI91=""),0,IF(BI91="","",IF(BI91>=BH91,1,BI91/BH91)))
A92: =+_xlfn.XLOOKUP(B92,'[1]Proyectos (NO FILTRAR)'!$F:$F,'[1]Proyectos (NO FILTRAR)'!$B:$B,0,0,1) -> CH-COD-CS-OTR00-129-A | B92: Codelco_Actualización norma NCC-31 | C92: =+_xlfn.XLOOKUP(A92,'[1]Proyectos (NO FILTRAR)'!$B:$B,'[1]Proyectos (NO FILTRAR)'!$G:$G,"error",0,1) -> Chile | D92: Adjudicado | E92: En Proceso | F92: Mauricio Melendez | H92: TBD | I92: =+_xlfn.XLOOKUP(B92,'[1]Proyectos (NO FILTRAR)'!$F:$F,'[1]Proyectos (NO FILTRAR)'!$O:$O,"!",0,1) -> 63381.37 | J92: =+Q92+AE92+AH92+AK92+AN92+AQ92+AT92+AW92+AZ92+BC92+BE92+BG92+BI92 -> 23268 | K92: =+IFERROR(J92/I92,0) -> 0.36711103 | L92: =+I92-J92 -> 40113.37 | M92: =+IFERROR(L92/I92,0) -> 0.63288897 | O92: =IFERROR(N92/I92,0) -> 0 | P92: =+I92-N92 -> 63381.37 | Q92: 0 | R92: =+I92-Q92 -> 63381.37 | BH92: =_xlfn.XLOOKUP(A92,'[3]Resumen POM'!$I:$I,'[3]Resumen POM'!$D:$D,"",0,1) -> 37177.579 | BI92: 23268 | BK92: =+IF(AND(BD92>0,BE92=""),0,IF(BE92="","",IF(BE92>=BD92,1,BE92/BD92))) | BL92: =+IF(AND(BF92>0,BG92=""),0,IF(BG92="","",IF(BG92>=BF92,1,BG92/BF92))) | BM92: =+IF(AND(BH92>0,BI92=""),0,IF(BI92="","",IF(BI92>=BH92,1,BI92/BH92))) -> 0.62586109
A93: =+_xlfn.XLOOKUP(B93,'[1]Proyectos (NO FILTRAR)'!$F:$F,'[1]Proyectos (NO FILTRAR)'!$B:$B,0,0,1) -> CH-COD-CS-OTR00-124-A | B93: Codelco_Prácticas de Planificación DMH | C93: =+_xlfn.XLOOKUP(A93,'[1]Proyectos (NO FILTRAR)'!$B:$B,'[1]Proyectos (NO FILTRAR)'!$G:$G,"error",0,1) -> Chile | D93: Adjudicado | E93: En Proceso | I93: =+_xlfn.XLOOKUP(B93,'[1]Proyectos (NO FILTRAR)'!$F:$F,'[1]Proyectos (NO FILTRAR)'!$O:$O,"!",0,1) -> 14342 | J93: =+Q93+AE93+AH93+AK93+AN93+AQ93+AT93+AW93+AZ93+BC93+BE93+BG93+BI93 -> 14342 | K93: =+IFERROR(J93/I93,0) -> 1 | L93: =+I93-J93 -> 0 | M93: =+IFERROR(L93/I93,0) -> 0 | O93: =IFERROR(N93/I93,0) -> 0 | P93: =+I93-N93 -> 14342 | Q93: 0 | R93: =+I93-Q93 -> 14342 | BF93: 14000 | BG93: 14342 | BK93: =+IF(AND(BD93>0,BE93=""),0,IF(BE93="","",IF(BE93>=BD93,1,BE93/BD93))) | BL93: =+IF(AND(BF93>0,BG93=""),0,IF(BG93="","",IF(BG93>=BF93,1,BG93/BF93))) -> 1 | BM93: =+IF(AND(BH93>0,BI93=""),0,IF(BI93="","",IF(BI93>=BH93,1,BI93/BH93)))
A94: =+_xlfn.XLOOKUP(B94,'[1]Proyectos (NO FILTRAR)'!$F:$F,'[1]Proyectos (NO FILTRAR)'!$B:$B,0,0,1) -> BR-MOS-UG-OTR00-098-A | B94: Mosaic_Taquari Vassouras Fase II | C94: =+_xlfn.XLOOKUP(A94,'[1]Proyectos (NO FILTRAR)'!$B:$B,'[1]Proyectos (NO FILTRAR)'!$G:$G,"error",0,1) -> Brasil | D94: Adjudicado | E94: En Proceso | I94: =+_xlfn.XLOOKUP(B94,'[1]Proyectos (NO FILTRAR)'!$F:$F,'[1]Proyectos (NO FILTRAR)'!$O:$O,"!",0,1) -> 330410 | J94: =+Q94+AE94+AH94+AK94+AN94+AQ94+AT94+AW94+AZ94+BC94+BE94+BG94+BI94 -> 45337 | K94: =+IFERROR(J94/I94,0) -> 0.13721437 | L94: =+I94-J94 -> 285073 | M94: =+IFERROR(L94/I94,0) -> 0.86278563 | O94: =IFERROR(N94/I94,0) -> 0 | P94: =+I94-N94 -> 330410 | Q94: 0 | R94: =+I94-Q94 -> 330410 | BF94: 30000 | BG94: 31337 | BI94: 14000 | BK94: =+IF(AND(BD94>0,BE94=""),0,IF(BE94="","",IF(BE94>=BD94,1,BE94/BD94))) | BL94: =+IF(AND(BF94>0,BG94=""),0,IF(BG94="","",IF(BG94>=BF94,1,BG94/BF94))) -> 1 | BM94: =+IF(AND(BH94>0,BI94=""),0,IF(BI94="","",IF(BI94>=BH94,1,BI94/BH94))) -> 1
A95: BR-AUM-OU-FEL00-130-A | B95: AuraMinerals_Expansión Mina Paiol OP-UG | C95: =+_xlfn.XLOOKUP(A95,'[1]Proyectos (NO FILTRAR)'!$B:$B,'[1]Proyectos (NO FILTRAR)'!$G:$G,"error",0,1) -> Brasil | D95: Adjudicado | E95: En Proceso | F95: Alex Figueroa | H95: Pablo Quiero | I95: =+_xlfn.XLOOKUP(B95,'[1]Proyectos (NO FILTRAR)'!$F:$F,'[1]Proyectos (NO FILTRAR)'!$O:$O,"!",0,1) -> 310000 | J95: =+Q95+AE95+AH95+AK95+AN95+AQ95+AT95+AW95+AZ95+BC95+BE95+BG95+BI95 -> 0 | K95: =+IFERROR(J95/I95,0) -> 0 | L95: =+I95-J95 -> 310000 | M95: =+IFERROR(L95/I95,0) -> 1 | O95: =IFERROR(N95/I95,0) -> 0 | P95: =+I95-N95 -> 310000 | Q95: 0 | R95: =+I95-Q95 -> 310000 | BK95: =+IF(AND(BD95>0,BE95=""),0,IF(BE95="","",IF(BE95>=BD95,1,BE95/BD95))) | BL95: =+IF(AND(BF95>0,BG95=""),0,IF(BG95="","",IF(BG95>=BF95,1,BG95/BF95))) | BM95: =+IF(AND(BH95>0,BI95=""),0,IF(BI95="","",IF(BI95>=BH95,1,BI95/BH95)))
A96: OT-RES-CS-OTR00-131-A | B96: Resolution_MinePlan Review | C96: =+_xlfn.XLOOKUP(A96,'[1]Proyectos (NO FILTRAR)'!$B:$B,'[1]Proyectos (NO FILTRAR)'!$G:$G,"error",0,1) -> Otros | D96: Adjudicado | E96: En Proceso | F96: Mauricio Melendez | H96: Freddy Diaz | I96: =+_xlfn.XLOOKUP(B96,'[1]Proyectos (NO FILTRAR)'!$F:$F,'[1]Proyectos (NO FILTRAR)'!$O:$O,"!",0,1) -> 254012 | J96: =+Q96+AE96+AH96+AK96+AN96+AQ96+AT96+AW96+AZ96+BC96+BE96+BG96+BI96 -> 0 | K96: =+IFERROR(J96/I96,0) -> 0 | L96: =+I96-J96 -> 254012 | M96: =+IFERROR(L96/I96,0) -> 1 | O96: =IFERROR(N96/I96,0) -> 0 | P96: =+I96-N96 -> 254012 | Q96: 0 | R96: =+I96-Q96 -> 254012 | BK96: =+IF(AND(BD96>0,BE96=""),0,IF(BE96="","",IF(BE96>=BD96,1,BE96/BD96))) | BL96: =+IF(AND(BF96>0,BG96=""),0,IF(BG96="","",IF(BG96>=BF96,1,BG96/BF96))) | BM96: =+IF(AND(BH96>0,BI96=""),0,IF(BI96="","",IF(BI96>=BH96,1,BI96/BH96)))
A97: PE-MSR-UG-OTR00-134-A | B97: Minsur_Raura Análisis LOM25 | C97: =+_xlfn.XLOOKUP(A97,'[1]Proyectos (NO FILTRAR)'!$B:$B,'[1]Proyectos (NO FILTRAR)'!$G:$G,"error",0,1) -> Perú | D97: Adjudicado | E97: En Proceso | F97: Matias Fuentes | H97: Jorman Barrera | I97: =+_xlfn.XLOOKUP(B97,'[1]Proyectos (NO FILTRAR)'!$F:$F,'[1]Proyectos (NO FILTRAR)'!$O:$O,"!",0,1) -> 51870 | J97: =+Q97+AE97+AH97+AK97+AN97+AQ97+AT97+AW97+AZ97+BC97+BE97+BG97+BI97 -> 0 | K97: =+IFERROR(J97/I97,0) -> 0 | L97: =+I97-J97 -> 51870 | M97: =+IFERROR(L97/I97,0) -> 1 | O97: =IFERROR(N97/I97,0) -> 0 | P97: =+I97-N97 -> 51870 | Q97: 0 | R97: =+I97-Q97 -> 51870
A98: CH-BHP-OP-FEL00-135-A | B98: BHP_Medidas de Cierre Botaderos | C98: =+_xlfn.XLOOKUP(A98,'[1]Proyectos (NO FILTRAR)'!$B:$B,'[1]Proyectos (NO FILTRAR)'!$G:$G,"error",0,1) -> Chile | D98: Adjudicado | E98: En Proceso | F98: Ricardo Miranda | H98: Gerson Alfaro | I98: =+_xlfn.XLOOKUP(B98,'[1]Proyectos (NO FILTRAR)'!$F:$F,'[1]Proyectos (NO FILTRAR)'!$O:$O,"!",0,1) -> 904853 | J98: =+Q98+AE98+AH98+AK98+AN98+AQ98+AT98+AW98+AZ98+BC98+BE98+BG98+BI98 -> 0 | K98: =+IFERROR(J98/I98,0) -> 0 | L98: =+I98-J98 -> 904853 | M98: =+IFERROR(L98/I98,0) -> 1 | O98: =IFERROR(N98/I98,0) -> 0 | P98: =+I98-N98 -> 904853 | Q98: 0 | R98: =+I98-Q98 -> 904853
A99: PE-CSC-UG-FEL2A-133-A | B99: PFS Los Calatos V3 | C99: =+_xlfn.XLOOKUP(A99,'[1]Proyectos (NO FILTRAR)'!$B:$B,'[1]Proyectos (NO FILTRAR)'!$G:$G,"error",0,1) -> Perú | D99: Adjudicado | E99: En Proceso | F99: Alex Figueroa | H99: Jorman Barrera | I99: =+_xlfn.XLOOKUP(B99,'[1]Proyectos (NO FILTRAR)'!$F:$F,'[1]Proyectos (NO FILTRAR)'!$O:$O,"!",0,1) -> 295769 | J99: =+Q99+AE99+AH99+AK99+AN99+AQ99+AT99+AW99+AZ99+BC99+BE99+BG99+BI99 -> 0 | K99: =+IFERROR(J99/I99,0) -> 0 | L99: =+I99-J99 -> 295769 | M99: =+IFERROR(L99/I99,0) -> 1 | O99: =IFERROR(N99/I99,0) -> 0 | P99: =+I99-N99 -> 295769 | Q99: 0 | R99: =+I99-Q99 -> 295769
B100: Sub total Adjudicado | I100: =SUBTOTAL(9,I3:I99) -> 17728759 | J100: =SUBTOTAL(9,J3:J99) -> 13603352 | K100: =+IFERROR(J100/I100,0) -> 0.76730423 | L100: =SUBTOTAL(9,L3:L99) -> 4125407.3 | M100: =+L100/I100 -> 0.23269577 | N100: =SUBTOTAL(9,N3:N94) -> 0 | O100: =IFERROR(N100/I100,0) -> 0 | P100: =SUBTOTAL(9,P3:P99) -> 17728759 | Q100: =SUBTOTAL(9,Q3:Q94) -> 5233137.2 | R100: =SUBTOTAL(9,R3:R94) -> 10679118 | S100: =+SUM(S3:S45) -> 1049600.5 | T100: =+SUM(T3:T45) -> 557689 | U100: =+SUM(U3:U45) -> 562672.51 | V100: =+SUM(V3:V45) -> 390471.95 | W100: =+SUM(W3:W45) -> 559002.95 | X100: =+SUM(X3:X45) -> 872990.77 | Y100: =+SUM(Y3:Y45) -> 768203.92 | Z100: =+SUM(Z3:Z45) -> 1305067.4 | ... AB100: =+SUM(AB3:AB45) -> 854068 | AC100: =+SUM(AC3:AC59) -> 1010587.7 | AD100: =+SUM(AD3:AD59) -> 761974.99 | AE100: =+SUM(AE3:AE87) -> 518157.31 | AF100: =+SUM(AF3:AF87) -> 991546.45 | AG100: =+SUM(AG3:AG87) -> 614070.98 | AH100: =+SUM(AH3:AH87) -> 415793 | AI100: =+SUM(AI3:AI87) -> 838526.25 | AJ100: =+SUM(AJ3:AJ87) -> 650732.3 | AK100: =+SUM(AK3:AK87) -> 603662.22 | AL100: =+SUM(AL3:AL87) -> 760540.71 | ... AV100: =+SUM(AV3:AV87) -> 550910.74 | AW100: =+SUM(AW3:AW94) -> 1521208 | AX100: =+SUM(AX3:AX87) -> 14049.622 | AY100: =+SUM(AY3:AY87) -> 0 | AZ100: =+SUM(AZ3:AZ94) -> 957072 | BA100: =+SUM(BA3:BA87) -> 446728.01 | BB100: =+SUM(BB3:BB87) -> 0 | BC100: =+SUM(BC3:BC94) -> 670487 | BD100: =+SUM(BD3:BD96) -> 515552 | BE100: =+SUM(BE3:BE96) -> 526614 | BF100: =+SUM(BF3:BF96) -> 651771 | BG100: =+SUM(BG3:BG99) -> 474688.98 | BH100: =+SUM(BH3:BH96) -> 781146.11 | BI100: =+SUM(BI3:BI96) -> 803567.24 | BK100: =+AVERAGE(BK3:BK96) -> 0.72557034 | BL100: =+AVERAGE(BL3:BL96) -> 0.70698499 | BM100: =+AVERAGE(BM3:BM96) -> 0.72004229

Sheet POM 2025__old
A1: 1 | B1: 2 | C1: 3 | D1: 4 | E1: 5 | F1: 6 | G1: 7 | H1: 8 | I1: 9 | J1: 10 | S1: =+COUNTIF(S3:S74,">0") -> 21 | T1: =+COUNTIF(T3:T74,">0") -> 19 | U1: =+COUNTIF(U3:U74,">0") -> 21 | V1: =+COUNTIF(V3:V74,">0") -> 20 | W1: =+COUNTIF(W3:W74,">0") -> 22 | X1: =+COUNTIF(X3:X74,">0") -> 17 | Y1: =+COUNTIF(Y3:Y74,">0") -> 13 | Z1: =+COUNTIF(Z3:Z74,">0") -> 15 | ... AP1: =+COUNTIF(AP3:AP74,">0") -> 13
A2: Código | B2: Proyecto | C2: País | D2: Año Inicio | E2: Estado Operativo | F2: Director / Jefe de Proyecto | G2: Gerente | H2: Ingeniero Principal | I2: Monto Contrato (USD) | J2: Emitido Acumulado Actual [USD] | K2: Avance Financiero Actual % | L2: Saldo actual [USD] | M2: Saldo actual % | N2: Acumulado Proyectado (USD) | O2: Avance Proyectado % | P2: Saldo Proyectado (USD) | Q2: Emitido Acumulado 2024 | R2: Saldo 2024 (USD) | S2: ENE P | T2: ENE R | U2: FEB P | V2: FEB R | W2: MAR P | X2: MAR R | Y2: ABR P | Z2: ABR R | AA2: MAY P | AB2: MAY R | AC2: JUN P | AD2: JUN R | AE2: JUL P | AF2: JUL R | AG2: AGO P | AH2: AGO R | AI2: SEP P | AJ2: SEP R | AK2: OCT P | AL2: OCT R | AM2: NOV P | AN2: NOV R | AO2: DIC P | AP2: DIC R
A3: CH-BHP-OP-FEL00-135-A | B3: BHP_Medidas de Cierre Botaderos | C3: =+_xlfn.XLOOKUP(A3,'[1]Proyectos (NO FILTRAR)'!$B:$B,'[1]Proyectos (NO FILTRAR)'!$G:$G,"error",0,1) -> Chile | D3: 2024 | E3: Finalizado | F3: Ricardo Miranda | H3: Gerson Alfaro | I3: =+_xlfn.XLOOKUP(B3,'[1]Proyectos (NO FILTRAR)'!$F:$F,'[1]Proyectos (NO FILTRAR)'!$O:$O,"!",0,1) -> 904853 | J3: =+Q3+T3+V3+X3+Z3+AB3+AD3+AF3+AH3+AJ3+AL3+AN3+AP3 -> 904853 | K3: =+IFERROR(J3/I3,0) -> 1 | M3: =+IFERROR(L3/I3,0) -> 0 | N3: =+J3+AO3 -> 904853 | O3: =IFERROR(N3/I3,0) -> 1 | R3: =+I3-Q3 -> 904853 | S3: 70000 | T3: 81369 | U3: =_xlfn.XLOOKUP(B3,'[4]Resumen EDP POM'!$B:$B,'[4]Resumen EDP POM'!$E:$E,"!",0,1) -> 65000 | V3: 127260.39 | W3: 60000 | X3: 87736 | Y3: 124000 | Z3: 70761 | AA3: 110000 | AB3: 196358 | AC3: 100000 | AD3: 137233.17 | AE3: 120000 | AF3: 159375.44 | AG3: 47515 | AH3: 4640 | AI3: 20000 | AJ3: 40120 | AO3: =+_xlfn.XLOOKUP(A3,'[5]Resumen POM'!$O:$O,'[5]Resumen POM'!$J:$J,0,0,1) -> 0 | AQ3: =+IF(AND(L3>0,AC3=0),"!","")
A4: =+_xlfn.XLOOKUP(B4,'[1]Proyectos (NO FILTRAR)'!$F:$F,'[1]Proyectos (NO FILTRAR)'!$B:$B,0,0,1) -> CH-CMP-UG-FEL03-093-A | B4: CMP_Puesta en marcha SLS Romeral | C4: =+_xlfn.XLOOKUP(A4,'[1]Proyectos (NO FILTRAR)'!$B:$B,'[1]Proyectos (NO FILTRAR)'!$G:$G,"error",0,1) -> Chile | D4: 2024 | E4: Finalizado | F4: Ricardo Miranda | H4: Pablo Quiero | I4: =+_xlfn.XLOOKUP(B4,'[1]Proyectos (NO FILTRAR)'!$F:$F,'[1]Proyectos (NO FILTRAR)'!$O:$O,"!",0,1) -> 900007.88 | J4: =+Q4+T4+V4+X4+Z4+AB4+AD4+AF4+AH4+AJ4+AL4+AN4+AP4 -> 911717.88 | K4: =+IFERROR(J4/I4,0) -> 1.013011 | M4: =+IFERROR(L4/I4,0) -> 0 | N4: =+J4+AO4 -> 911717.88 | O4: =IFERROR(N4/I4,0) -> 1.013011 | Q4: 769067.03 | R4: =+I4-Q4 -> 130940.85 | S4: 35466 | T4: 31918 | U4: =_xlfn.XLOOKUP(B4,'[4]Resumen EDP POM'!$B:$B,'[4]Resumen EDP POM'!$E:$E,"!",0,1) -> 40000 | V4: 41743.85 | W4: 15000 | AB4: 47495 | AN4: 21494 | AO4: =+_xlfn.XLOOKUP(A4,'[5]Resumen POM'!$O:$O,'[5]Resumen POM'!$J:$J,0,0,1) -> 0 | AQ4: =+IF(AND(L4>0,AC4=0),"!","")
A5: =+_xlfn.XLOOKUP(B5,'[1]Proyectos (NO FILTRAR)'!$F:$F,'[1]Proyectos (NO FILTRAR)'!$B:$B,0,0,1) -> OT-THC-CS-OTR00-122-A | B5: ThreeCrowns_Litigio Oyu Tolgoi | C5: =+_xlfn.XLOOKUP(A5,'[1]Proyectos (NO FILTRAR)'!$B:$B,'[1]Proyectos (NO FILTRAR)'!$G:$G,"error",0,1) -> Otros | D5: 2025 | E5: Finalizado | F5: Matias Fuentes | I5: =+_xlfn.XLOOKUP(B5,'[1]Proyectos (NO FILTRAR)'!$F:$F,'[1]Proyectos (NO FILTRAR)'!$O:$O,"!",0,1) -> 645700 | J5: =+Q5+T5+V5+X5+Z5+AB5+AD5+AF5+AH5+AJ5+AL5+AN5+AP5 -> 645700 | K5: =+IFERROR(J5/I5,0) -> 1 | M5: =+IFERROR(L5/I5,0) -> 0 | N5: =+J5+AO5 -> 645700 | O5: =IFERROR(N5/I5,0) -> 1 | AA5: 50000 | AB5: 74100 | AC5: 100000 | AD5: 129000 | AE5: 50000 | AF5: 114100 | AG5: 50000 | AH5: 150000 | AI5: 100000 | AJ5: 178500 | AO5: =+_xlfn.XLOOKUP(A5,'[5]Resumen POM'!$O:$O,'[5]Resumen POM'!$J:$J,0,0,1) -> 0 | AQ5: =+IF(AND(L5>0,AC5=0),"!","")
A6: =+_xlfn.XLOOKUP(B6,'[1]Proyectos (NO FILTRAR)'!$F:$F,'[1]Proyectos (NO FILTRAR)'!$B:$B,0,0,1) -> OT-TWM-CS-FEL00-119-A | B6: Twin Metals_Pre PFS Birch Lake Maturi | C6: =+_xlfn.XLOOKUP(A6,'[1]Proyectos (NO FILTRAR)'!$B:$B,'[1]Proyectos (NO FILTRAR)'!$G:$G,"error",0,1) -> Otros | D6: 2024 | E6: Finalizado | F6: Patricio Vergara | H6: Eduardo Sanchez | I6: =+_xlfn.XLOOKUP(B6,'[1]Proyectos (NO FILTRAR)'!$F:$F,'[1]Proyectos (NO FILTRAR)'!$O:$O,"!",0,1) -> 481541 | J6: =+Q6+T6+V6+X6+Z6+AB6+AD6+AF6+AH6+AJ6+AL6+AN6+AP6 -> 481541 | K6: =+IFERROR(J6/I6,0) -> 1 | M6: =+IFERROR(L6/I6,0) -> 0 | N6: =+J6+AO6 -> 481541 | O6: =IFERROR(N6/I6,0) -> 1 | Q6: 112740.6 | R6: =+I6-Q6 -> 368800.4 | S6: 82000 | T6: 80209.4 | U6: =_xlfn.XLOOKUP(B6,'[4]Resumen EDP POM'!$B:$B,'[4]Resumen EDP POM'!$E:$E,"!",0,1) -> 133000 | V6: 112981 | W6: 62689 | Y6: 74025 | Z6: =101319+60296 -> 161615 | AA6: 15454 | AB6: 13995 | AO6: =+_xlfn.XLOOKUP(A6,'[5]Resumen POM'!$O:$O,'[5]Resumen POM'!$J:$J,0,0,1) -> 0 | AQ6: =+IF(AND(L6>0,AC6=0),"!","")
A7: =+_xlfn.XLOOKUP(B7,'[1]Proyectos (NO FILTRAR)'!$F:$F,'[1]Proyectos (NO FILTRAR)'!$B:$B,0,0,1) -> BR-MOS-UG-OTR00-098-A | B7: Mosaic_Taquari Vassouras Fase II | C7: =+_xlfn.XLOOKUP(A7,'[1]Proyectos (NO FILTRAR)'!$B:$B,'[1]Proyectos (NO FILTRAR)'!$G:$G,"error",0,1) -> Brasil | D7: 2024 | E7: Finalizado | F7: Claudio Hernández | I7: =+_xlfn.XLOOKUP(B7,'[1]Proyectos (NO FILTRAR)'!$F:$F,'[1]Proyectos (NO FILTRAR)'!$O:$O,"!",0,1) -> 330410 | J7: =+Q7+T7+V7+X7+Z7+AB7+AD7+AF7+AH7+AJ7+AL7+AN7+AP7 -> 267019.09 | K7: =+IFERROR(J7/I7,0) -> 0.8081447 | M7: =+IFERROR(L7/I7,0) -> 0 | N7: =+J7+AO7 -> 267019.09 | O7: =IFERROR(N7/I7,0) -> 0.8081447 | Q7: 45337 | R7: =+I7-Q7 -> 285073 | S7: 14900 | T7: 22947.84 | U7: =_xlfn.XLOOKUP(B7,'[4]Resumen EDP POM'!$B:$B,'[4]Resumen EDP POM'!$E:$E,"!",0,1) -> 12081.563 | V7: 10292.71 | W7: 24353.773 | X7: 5393 | Y7: 15000 | Z7: 11237 | AA7: 30000 | AB7: 32693 | AC7: 30000 | AD7: 34273 | AE7: 30000 | AF7: 21033 | AG7: 37000 | AH7: 25049.54 | AI7: 30000 | AJ7: 33890 | AK7: 32000 | AL7: 24873 | AO7: =+_xlfn.XLOOKUP(A7,'[5]Resumen POM'!$O:$O,'[5]Resumen POM'!$J:$J,0,0,1) -> 0 | AQ7: =+IF(AND(L7>0,AC7=0),"!","")
A8: BR-AUM-OU-FEL00-130-A | B8: AuraMinerals_Expansión Mina Paiol OP-UG | C8: =+_xlfn.XLOOKUP(A8,'[1]Proyectos (NO FILTRAR)'!$B:$B,'[1]Proyectos (NO FILTRAR)'!$G:$G,"error",0,1) -> Brasil | D8: 2024 | E8: Finalizado | F8: Alex Figueroa | H8: Pablo Quiero | I8: =+_xlfn.XLOOKUP(B8,'[1]Proyectos (NO FILTRAR)'!$F:$F,'[1]Proyectos (NO FILTRAR)'!$O:$O,"!",0,1) -> 310000 | J8: =+Q8+T8+V8+X8+Z8+AB8+AD8+AF8+AH8+AJ8+AL8+AN8+AP8 -> 310000.41 | K8: =+IFERROR(J8/I8,0) -> 1.0000013 | M8: =+IFERROR(L8/I8,0) -> 0 | N8: =+J8+AO8 -> 310000.41 | O8: =IFERROR(N8/I8,0) -> 1.0000013 | R8: =+I8-Q8 -> 310000 | S8: 40000 | T8: 54144 | U8: =_xlfn.XLOOKUP(B8,'[4]Resumen EDP POM'!$B:$B,'[4]Resumen EDP POM'!$E:$E,"!",0,1) -> 46000 | V8: 58804.41 | W8: 44000 | X8: 20261 | Z8: 46562 | AA8: 34381.816 | AB8: 23599 | AC8: 33400 | AD8: 30544 | AE8: 30000 | AF8: 29078 | AG8: 22000 | AH8: 19194 | AI8: 12280.702 | AJ8: 16193 | AK8: 11620.59 | AL8: 11621 | AO8: =+_xlfn.XLOOKUP(A8,'[5]Resumen POM'!$O:$O,'[5]Resumen POM'!$J:$J,0,0,1) -> 0 | AQ8: =+IF(AND(L8>0,AC8=0),"!","")
A9: =+_xlfn.XLOOKUP(B9,'[1]Proyectos (NO FILTRAR)'!$F:$F,'[1]Proyectos (NO FILTRAR)'!$B:$B,0,0,1) -> CH-LUN-CS-OTR00-154-A | B9: Lundin_Análisis Estratégico Caserones | C9: =+_xlfn.XLOOKUP(A9,'[1]Proyectos (NO FILTRAR)'!$B:$B,'[1]Proyectos (NO FILTRAR)'!$G:$G,"error",0,1) -> Chile | D9: 2025 | E9: Finalizado | F9: Felipe Rojas | I9: =+_xlfn.XLOOKUP(B9,'[1]Proyectos (NO FILTRAR)'!$F:$F,'[1]Proyectos (NO FILTRAR)'!$O:$O,"!",0,1) -> 299270 | J9: =+Q9+T9+V9+X9+Z9+AB9+AD9+AF9+AH9+AJ9+AL9+AN9+AP9 -> 299270 | K9: =+IFERROR(J9/I9,0) -> 1 | M9: =+IFERROR(L9/I9,0) -> 0 | N9: =+J9+AO9 -> 299270 | O9: =IFERROR(N9/I9,0) -> 1 | AC9: 55000 | AD9: 54620 | AE9: 70000 | AF9: 70025 | AG9: 65000 | AH9: 70020 | AI9: 54000 | AJ9: 53961 | AK9: 35000 | AL9: 31113 | AM9: 19531 | AN9: 19531 | AO9: =+_xlfn.XLOOKUP(A9,'[5]Resumen POM'!$O:$O,'[5]Resumen POM'!$J:$J,0,0,1) -> 0 | AQ9: =+IF(AND(L9>0,AC9=0),"!","")
A10: PE-CSC-UG-FEL2A-133-A | B10: PFS Los Calatos V3 | C10: =+_xlfn.XLOOKUP(A10,'[1]Proyectos (NO FILTRAR)'!$B:$B,'[1]Proyectos (NO FILTRAR)'!$G:$G,"error",0,1) -> Perú | D10: 2024 | E10: Finalizado | F10: Alex Figueroa | H10: Jorman Barrera | I10: =+_xlfn.XLOOKUP(B10,'[1]Proyectos (NO FILTRAR)'!$F:$F,'[1]Proyectos (NO FILTRAR)'!$O:$O,"!",0,1) -> 295769 | J10: =+Q10+T10+V10+X10+Z10+AB10+AD10+AF10+AH10+AJ10+AL10+AN10+AP10 -> 336553.92 | K10: =+IFERROR(J10/I10,0) -> 1.1378945 | M10: =+IFERROR(L10/I10,0) -> 0 | N10: =+J10+AO10 -> 336553.92 | O10: =IFERROR(N10/I10,0) -> 1.1378945 | R10: =+I10-Q10 -> 295769 | S10: 25500 | T10: 36175 | U10: =_xlfn.XLOOKUP(B10,'[4]Resumen EDP POM'!$B:$B,'[4]Resumen EDP POM'!$E:$E,"!",0,1) -> 44000 | V10: 47631 | W10: 37000 | X10: 34217 | Y10: 25127 | Z10: 25392 | AA10: 48700.336 | AB10: 57648 | AC10: 50800 | AD10: 59126 | AE10: 35579 | AF10: 30279.917 | AG10: 5299 | AH10: 5300 | AL10: 40785 | AO10: =+_xlfn.XLOOKUP(A10,'[5]Resumen POM'!$O:$O,'[5]Resumen POM'!$J:$J,0,0,1) -> 0 | AQ10: =+IF(AND(L10>0,AC10=0),"!","")
A11: =+_xlfn.XLOOKUP(B11,'[1]Proyectos (NO FILTRAR)'!$F:$F,'[1]Proyectos (NO FILTRAR)'!$B:$B,0,0,1) -> CH-D&P-CS-OTR00-137-A | B11: Estrategia Cobre Panama | C11: =+_xlfn.XLOOKUP(A11,'[1]Proyectos (NO FILTRAR)'!$B:$B,'[1]Proyectos (NO FILTRAR)'!$G:$G,"error",0,1) -> Chile | D11: 2025 | E11: Finalizado | F11: Gonzalo Díaz | I11: =+_xlfn.XLOOKUP(B11,'[1]Proyectos (NO FILTRAR)'!$F:$F,'[1]Proyectos (NO FILTRAR)'!$O:$O,"!",0,1) -> 272200.6 | J11: =+Q11+T11+V11+X11+Z11+AB11+AD11+AF11+AH11+AJ11+AL11+AN11+AP11 -> 272201 | K11: =+IFERROR(J11/I11,0) -> 1.0000015 | M11: =+IFERROR(L11/I11,0) -> 0 | N11: =+J11+AO11 -> 272201 | O11: =IFERROR(N11/I11,0) -> 1.0000015 | U11: =_xlfn.XLOOKUP(B11,'[4]Resumen EDP POM'!$B:$B,'[4]Resumen EDP POM'!$E:$E,"!",0,1) -> 79200 | V11: 82681.2 | W11: 80500 | X11: 89646.3 | Y11: 46270 | Z11: 0 | AF11: 99873.5 | AO11: =+_xlfn.XLOOKUP(A11,'[5]Resumen POM'!$O:$O,'[5]Resumen POM'!$J:$J,0,0,1) -> 0 | AQ11: =+IF(AND(L11>0,AC11=0),"!","")
A12: OT-RES-CS-OTR00-131-A | B12: Resolution_MinePlan Review | C12: =+_xlfn.XLOOKUP(A12,'[1]Proyectos (NO FILTRAR)'!$B:$B,'[1]Proyectos (NO FILTRAR)'!$G:$G,"error",0,1) -> Otros | D12: 2024 | E12: Finalizado | F12: Carolina Arcos | H12: Freddy Diaz | I12: =+_xlfn.XLOOKUP(B12,'[1]Proyectos (NO FILTRAR)'!$F:$F,'[1]Proyectos (NO FILTRAR)'!$O:$O,"!",0,1) -> 254012 | J12: =+Q12+T12+V12+X12+Z12+AB12+AD12+AF12+AH12+AJ12+AL12+AN12+AP12 -> 254012 | K12: =+IFERROR(J12/I12,0) -> 1 | M12: =+IFERROR(L12/I12,0) -> 0 | N12: =+J12+AO12 -> 254012 | O12: =IFERROR(N12/I12,0) -> 1 | R12: =+I12-Q12 -> 254012 | S12: 115000 | T12: 130412 | U12: =_xlfn.XLOOKUP(B12,'[4]Resumen EDP POM'!$B:$B,'[4]Resumen EDP POM'!$E:$E,"!",0,1) -> 95000 | V12: 84975 | W12: 28325 | X12: 38625 | AO12: =+_xlfn.XLOOKUP(A12,'[5]Resumen POM'!$O:$O,'[5]Resumen POM'!$J:$J,0,0,1) -> 0 | AQ12: =+IF(AND(L12>0,AC12=0),"!","")
A13: =+_xlfn.XLOOKUP(B13,'[1]Proyectos (NO FILTRAR)'!$F:$F,'[1]Proyectos (NO FILTRAR)'!$B:$B,0,0,1) -> BR-J&F-UG-FEL03-048-A | B13: J&F_Urucrum_RecuperacionPilares | C13: =+_xlfn.XLOOKUP(A13,'[1]Proyectos (NO FILTRAR)'!$B:$B,'[1]Proyectos (NO FILTRAR)'!$G:$G,"error",0,1) -> Brasil | D13: 2024 | E13: Finalizado | F13: Claudio Hernández | H13: Freddy Diaz | I13: =+_xlfn.XLOOKUP(B13,'[1]Proyectos (NO FILTRAR)'!$F:$F,'[1]Proyectos (NO FILTRAR)'!$O:$O,"!",0,1) -> 239308 | J13: =+Q13+T13+V13+X13+Z13+AB13+AD13+AF13+AH13+AJ13+AL13+AN13+AP13 -> 216351 | K13: =+IFERROR(J13/I13,0) -> 0.90406923 | M13: =+IFERROR(L13/I13,0) -> 0 | N13: =+J13+AO13 -> 216351 | O13: =IFERROR(N13/I13,0) -> 0.90406923 | Q13: 208259 | R13: =+I13-Q13 -> 31049 | X13: 8092 | AO13: =+_xlfn.XLOOKUP(A13,'[5]Resumen POM'!$O:$O,'[5]Resumen POM'!$J:$J,0,0,1) -> 0 | AQ13: =+IF(AND(L13>0,AC13=0),"!","")
A14: =+_xlfn.XLOOKUP(B14,'[1]Proyectos (NO FILTRAR)'!$F:$F,'[1]Proyectos (NO FILTRAR)'!$B:$B,0,0,1) -> CH-MCI-OP-OTR00-089-A | B14: MCI_Mine Plan Review Los Bronces | C14: =+_xlfn.XLOOKUP(A14,'[1]Proyectos (NO FILTRAR)'!$B:$B,'[1]Proyectos (NO FILTRAR)'!$G:$G,"error",0,1) -> Chile | D14: 2024 | E14: Finalizado | F14: Gonzalo Díaz | H14: TBD | I14: =+_xlfn.XLOOKUP(B14,'[1]Proyectos (NO FILTRAR)'!$F:$F,'[1]Proyectos (NO FILTRAR)'!$O:$O,"!",0,1) -> 239000 | J14: =+Q14+T14+V14+X14+Z14+AB14+AD14+AF14+AH14+AJ14+AL14+AN14+AP14 -> 239000 | K14: =+IFERROR(J14/I14,0) -> 1 | M14: =+IFERROR(L14/I14,0) -> 0 | N14: =+J14+AO14 -> 239000 | O14: =IFERROR(N14/I14,0) -> 1 | Q14: 215280 | R14: =+I14-Q14 -> 23720 | S14: 23720 | T14: 23720 | AO14: =+_xlfn.XLOOKUP(A14,'[5]Resumen POM'!$O:$O,'[5]Resumen POM'!$J:$J,0,0,1) -> 0 | AQ14: =+IF(AND(L14>0,AC14=0),"!","")
A15: =+_xlfn.XLOOKUP(B15,'[1]Proyectos (NO FILTRAR)'!$F:$F,'[1]Proyectos (NO FILTRAR)'!$B:$B,0,0,1) -> CH-BHP-UG-FEL01-074-A | B15: BHP_Tunel Exploratorio | C15: =+_xlfn.XLOOKUP(A15,'[1]Proyectos (NO FILTRAR)'!$B:$B,'[1]Proyectos (NO FILTRAR)'!$G:$G,"error",0,1) -> Chile | D15: 2025 | E15: Finalizado | F15: Carolina Arcos | I15: =+_xlfn.XLOOKUP(B15,'[1]Proyectos (NO FILTRAR)'!$F:$F,'[1]Proyectos (NO FILTRAR)'!$O:$O,"!",0,1) -> 198920 | J15: =+Q15+T15+V15+X15+Z15+AB15+AD15+AF15+AH15+AJ15+AL15+AN15+AP15 -> 198920 | K15: =+IFERROR(J15/I15,0) -> 1 | M15: =+IFERROR(L15/I15,0) -> 0 | N15: =+J15+AO15 -> 198920 | O15: =IFERROR(N15/I15,0) -> 1 | Q15: 35036 | R15: =+I15-Q15 -> 163884 | Y15: 40000 | Z15: 48790 | AA15: 40000 | AB15: 32748 | AC15: 38000 | AD15: 40426 | AE15: 39000 | AF15: 30025 | AG15: 11895 | AH15: 11895 | AO15: =+_xlfn.XLOOKUP(A15,'[5]Resumen POM'!$O:$O,'[5]Resumen POM'!$J:$J,0,0,1) -> 0 | AQ15: =+IF(AND(L15>0,AC15=0),"!","")
A16: =+_xlfn.XLOOKUP(B16,'[1]Proyectos (NO FILTRAR)'!$F:$F,'[1]Proyectos (NO FILTRAR)'!$B:$B,0,0,1) -> CH-CCO-CS-FEL00-117-A | B16: Capstone Copper_Estudio Sierra Norte | C16: =+_xlfn.XLOOKUP(A16,'[1]Proyectos (NO FILTRAR)'!$B:$B,'[1]Proyectos (NO FILTRAR)'!$G:$G,"error",0,1) -> Chile | D16: 2024 | E16: Finalizado | F16: Gonzalo Díaz | H16: Nicolas Ayarza | I16: =+_xlfn.XLOOKUP(B16,'[1]Proyectos (NO FILTRAR)'!$F:$F,'[1]Proyectos (NO FILTRAR)'!$O:$O,"!",0,1) -> 196000.3 | J16: =+Q16+T16+V16+X16+Z16+AB16+AD16+AF16+AH16+AJ16+AL16+AN16+AP16 -> 196000.3 | K16: =+IFERROR(J16/I16,0) -> 1 | M16: =+IFERROR(L16/I16,0) -> 0 | N16: =+J16+AO16 -> 196000.3 | O16: =IFERROR(N16/I16,0) -> 1 | Q16: 160223 | R16: =+I16-Q16 -> 35777.3 | S16: 35777 | T16: 31129.3 | U16: =_xlfn.XLOOKUP(B16,'[4]Resumen EDP POM'!$B:$B,'[4]Resumen EDP POM'!$E:$E,"!",0,1) -> 4648 | V16: 4648 | AO16: =+_xlfn.XLOOKUP(A16,'[5]Resumen POM'!$O:$O,'[5]Resumen POM'!$J:$J,0,0,1) -> 0 | AQ16: =+IF(AND(L16>0,AC16=0),"!","")
