Workbook

Sheet Flujo Redco 2025 v1
B1: INGENIERÍA REDCO LTDA.
B3: 2025
B6: FLUJO EFECTIVO OPERACIONAL DE ENERO A DICIEMBRE 2025 | C6: REAL | D6: REAL | E6: ESTIMACION
B8: RESUMEN | C8: 45658 | D8: 45689 | E8: 45717
B9: SALDO CTA. CTE. INICIAL | C9: =SUM(C43+C44) -> 48703652 | D9: =SUM(D43+D44) -> 154486282 | E9: =SUM(E43+E44) -> 282096553
B10: INGRESOS OPERACIONALES | C10: =+C81 -> 382405283 | D10: =+D81 -> 615898051 | E10: =+E81 -> 251774915
B11: INGRESO NO OPERACIONAL (IVA DEBITO) | C11: =+C85 -> 73201311 | D11: =+D85 -> 97684687 | E11: =+E85 -> 47837233
B12: Rescate Fondos Mutuos
B13: Otros Ingresos No Operacioanles (dev.proveedor)
B14: Crédito Bco.Chile - Pmo. Redco Perú
B15: OTROS INGRESOS NO OPERACIONALES | C15: =+C99 -> 119395962 | D15: =+D99 -> 9692163 | E15: =+E99 -> -7470050
B16: TOTAL INGRESOS | C16: =SUM(C9:C15) -> 623706208 | D16: =SUM(D9:D15) -> 877761183 | E16: =SUM(E9:E15) -> 574238651
B18: SUELDOS OPERACIONALES | C18: =SUM(C167) -> 278812947 | D18: =SUM(D167) -> 205478739 | E18: =SUM(E167) -> 206804053
B19: HONORARIOS OPERACIONALES | C19: =SUM(C199) -> 28678785 | D19: =SUM(D199) -> 95836510 | E19: =SUM(E199) -> 18385968
B20: GASTOS OPERACIONALES | C20: =SUM(C261) -> 43582698 | D20: =SUM(D261) -> 32950339 | E20: =SUM(E261) -> 71518398
B21: ACTIVO FIJO- EQUIPOS COMPUTACIONALES | C21: =SUM(C266) -> 0 | D21: =SUM(D266) -> 9258153 | E21: =SUM(E266) -> 1400000
B22: TOTAL COSTOS OPERACIONALES | C22: =SUM(C18:C21) -> 3.5107443e+08 | D22: =SUM(D18:D21) -> 343523741 | E22: =SUM(E18:E21) -> 298108419
B23: SUELDOS ADMINISTRATIVOS | C23: =SUM(C280) -> 9731942 | D23: =SUM(D280) -> 35844455 | E23: =SUM(E280) -> 34501236
B24: GASTOS DE ADMINISTRACION | C24: =SUM(C306) -> 3572717 | D24: =SUM(D306) -> 15591695 | E24: =SUM(E306) -> 7866800
B25: TOTAL COSTO ADMINISTRATIVO | C25: =SUM(C23:C24) -> 13304659 | D25: =SUM(D23:D24) -> 51436150 | E25: =SUM(E23:E24) -> 42368036
B26: IMPUESTOS PPM-IVA-IMPTO.ADICIONAL | C26: =SUM(C314) -> 32600739 | D26: =SUM(D314) -> 58964333 | E26: =SUM(E314) -> 14300000
B27: CREDITOS BCO.CHILE | C27: =SUM(C320) -> 25722767 | D27: =SUM(D320) -> 25698938 | E27: =SUM(E320) -> 25750000
B28: GTOS. EXTRAORDINARIOS DIRECTOR REDCO | C28: =SUM(C327) -> 172475 | D28: =SUM(D327) -> 1220320 | E28: =SUM(E327) -> 1221063
B29: CTA.CTE. EERR | C29: =SUM(C337) -> 46257039 | D29: =SUM(D337) -> 114821148 | E29: =SUM(E337) -> 57713026
B30: TOTAL OTROS FLUJOS | C30: =SUM(C26:C29) -> 104753020 | D30: =SUM(D26:D29) -> 200704739 | E30: =SUM(E26:E29) -> 98984089
B32: TOTAL COSTOS Y FLUJOS ANUAL | C32: =SUM(C30,C25,C22) -> 4.6913211e+08 | D32: =SUM(D30,D25,D22) -> 595664630 | E32: =SUM(E30,E25,E22) -> 439460544
C33: =SUM(C339-C32) -> 0 | D33: =SUM(D339-D32) -> 0 | E33: =SUM(E339-E32) -> 0
B34: SALDO NETO FLUJO | C34: =SUM(C16-C32) -> 1.545741e+08 | D34: =SUM(D16-D32) -> 282096553 | E34: =SUM(E16-E32) -> 134778107
C35: =SUM(C34-C341) -> 0 | D35: =SUM(D34-D341) -> 0 | E35: =SUM(E34-E341) -> 0
C41: REAL | D41: REAL | E41: ESTIMACION
C42: 45658 | D42: 45689 | E42: 45717
B43: SDO.CTA.CTE. BCO. CHILE CLP 01-01-25 | C43: 48372971 | D43: =+C343 -> 59978095 | E43: =+D343 -> 201419874
B44: SDO.CTA.CTE. BCO. CHILE DOLARES 01-01-25 | C44: 330681 | D44: 94508187 | E44: =+D344 -> 80676679
B47: INGRESOS INGENIERÍA CHILE | C47: 45658 | D47: 45689 | E47: 45717
B48: CLIENTE | C48: MONTO $ | D48: MONTO $ | E48: MONTO $
B49: CPM Plan LOM Estabilizado. PFS UG y LINK LP del Valle; El Romeral | C49: 83858385
B50: CMP S.A. Estudio Implem. Mina UG-SLS en ROM y Consoli.LOM 2024 en CNN y MLC | C50: 82670896 | D50: =+'Facturas e Ingresos 2025'!E20+'Facturas e Ingresos 2025'!E28 -> 150942195 | E50: 44047733
B51: CMP S.A. Consolidación LOM 2024 en CNN y MLC | C51: 80377561
B52: CMP S.A. Analisis de Factibilidad Minera mejoras OP CNN y Desarr caso Exp | C52: 41976916 | D52: =+'Facturas e Ingresos 2025'!E31 -> 9265729
B53: CODELCO Servicio Opti. Sondajes para DRT mediante DRX- FACT. REDTEC | D53: =+'Facturas e Ingresos 2025'!I17 -> 43972803
B54: CODELCO Servicio Optimización Sondajes para DSL mediante DRX - FACT. REDTEC. | D54: =+'Facturas e Ingresos 2025'!I18 -> 61831751
B55: CODELCO EdP01 Estudio análisis opciones de vaciado mineral mina subte.
B56: CODELCO EdP01 Serv. Apoyo documentación pract.planif. | D56: =+'Facturas e Ingresos 2025'!E22 -> 14077368
B57: CODELCO EdP01 Serv. Estudio de modif. Para actualización | D57: =+'Facturas e Ingresos 2025'!E23 -> 32070646
B58: CODELCO EdP01 y EDP02 Serv. Estandar y Procesamiento cierre topográfico | D58: =+'Facturas e Ingresos 2025'!E24+'Facturas e Ingresos 2025'!E25 -> 28803159
B59: M. Candelaria Servicios de Ingeniería de Valor Proyecto CUGEP | D59: =+'Facturas e Ingresos 2025'!E21 -> 34170570
B60: MEL - Contrato Servicio Enoteca
B61: Antofagasta Mineral
B62: Lomas Bayas Ampl. Servicio Consultoría Planificación LOA UP
B63: CEOM - Servicios de ingenieria
B64: AMSA - Asesoria Centinela
B65: AMSA - Construcción Manuales Minimo Standares
B66: AMSA - Servicio de Apoyo a Gerencia de Minería 2024-2025 | D66: =+'Facturas e Ingresos 2025'!E27 -> 14564501 | E66: 7736812
B67: AMSA - Trade O Tecnológico nueva generación de Distrito | E67: 30291258
B68: BHP Chile INC S.A. Análisis de confiabi. e Identif.cuellos de botella Plan 2YB25
B69: BHP CHILE INC S.A. Aseso.y Rev.de alto nivel Escondida UG
B70: BHP Chile INC S. A. Analisis confiabilidad de cuellos de botella del LoA 2025-26
B71: MC Inversiones Limitada - 30% de 239.200 USD Pago 01 Los Bronces Mine Plan Review
B72: CMP S.A. -Actualización evaluación técnica Proy. Mejoras Op. CNN
B73: CMP S.A. -Estrategia Minera MLC Brownfield y TN Modular | D73: =+'Facturas e Ingresos 2025'!E33 -> 67426546
B74: MANTOS COPPER Estimación Confiabilidad de Planes Mineros | C74: 48838310
B75: SCM MINERA LUMINA COPPER ServicIos de Asesorìa y Estudios de Ingeniería | E75: 81846288
B76: CIA.MINERA SIERRA NORTE | D76: =+'Facturas e Ingresos 2025'!E14+'Facturas e Ingresos 2025'!E15 -> 158772783
B77: CIA.MINERA CERRO COLORADO Diseño medidas de cierre Botadeeros Lastre | E77: 82945096
B78: ANGLO AMERICAN SUR Ing.tilizació Tecnología HDD Capt.Aguas Claras | E78: 4907728
B79: MC Inversiones Saldo + adic. Los Bronces Mine Plan Review
B80: MEL - EdP01 fy24-25 Servicio Enoteca Redtec | C80: 44683215
B81: INGRESOS OPERACIONALES | C81: =SUM(C49:C80) -> 382405283 | D81: =SUM(D49:D80) -> 615898051 | E81: =SUM(E49:E80) -> 251774915
B83: IVA DEBITO FISCAL | C83: 45658 | D83: 45689 | E83: 45717
B84: CLIENTE | C84: MONTO $ | D84: MONTO $ | E84: MONTO $
B85: IVA DEBITO FISCAL | C85: 73201311 | D85: =+'Facturas e Ingresos 2025'!F14+'Facturas e Ingresos 2025'!F15+'Facturas e Ingresos 2025'!F20+'Facturas e Ingresos 2025'!F21+'Facturas e Ingresos 2025'!F22+'Facturas e Ingresos 2025'!F23+'Facturas e Ingresos 2025'!F24+'Facturas e Ingresos 2025'!F25+'Facturas e Ingresos 2025'!F27+'Facturas e Ingresos 2025'!F28+'Facturas e Ingresos 2025'!F31+'Facturas e Ingresos 2025'!F33 -> 97684687 | E85: 47837233
B87: SUMAS | C87: =SUM(C85:C86) -> 73201311 | D87: =SUM(D85:D86) -> 97684687 | E87: =SUM(E85:E86) -> 47837233
B89: INGRESOS EXTRAORDINARIOS | C89: 45658 | D89: 45689 | E89: 45717
B90: CLIENTE
B91: Dev.Cta.Cte. Redtec
B92: Dev.Cta.Cte. Redcross
B93: Otros ingresos vrs. (recup.gtos of,1502) | C93: 655462
B94: Dev. Bta. Garantía CMP | D94: 9692163
B95: PRESTAMO/ devolucion CTA.CTE. BVI | E95: =18529950+74000000 -> 92529950
B96: Fact.Redco Perú (US$100.000)- Dev. Cta.cte. Redco perú | C96: 118740500
B97: Rescate FFMM pesos
B98: Aportes FFMM dólares | E98: -100000000
B99: SUMAS | C99: =SUM(C91:C98) -> 119395962 | D99: =SUM(D91:D98) -> 9692163 | E99: =SUM(E91:E98) -> -7470050
B101: PERIODO 2023 | C101: 45658 | D101: 45689 | E101: 45717
C102: MONTO $ | D102: MONTO $ | E102: MONTO $
B103: TOTAL INGRESOS MES | C103: =SUM(C81+C87+C99) -> 575002556 | D103: =SUM(D81+D87+D99) -> 723274901 | E103: =SUM(E81+E87+E99) -> 292142098
C105: 45658 | D105: 45689 | E105: 45717
B106: TOTAL INGRESOS + SALDO CTA.CTE. | C106: MONTO $ | D106: MONTO $ | E106: MONTO $
C107: =SUM(C43+C44+C103) -> 623706208 | D107: =SUM(D43+D44+D103) -> 877761183 | E107: =SUM(E43+E44+E103) -> 574238651
B109: REMUNERACIONES OPERACIONAL | C109: 45658 | D109: 45689 | E109: 45717
B110: DETALLE | C110: MONTO $ | D110: MONTO $ | E110: MONTO $
B111: Alex Figueroa | C111: 6528940 | D111: =6524626+92330 -> 6616956 | E111: =6524626+92330 -> 6616956
B112: Alex Pacheco C. | C112: 2030713 | D112: 2032649 | E112: 2032649
B113: Benjamin Baeza | C113: 763792 | D113: 1303261 | E113: 1303261
B114: Bastian Astudillo Quilaqueo | C114: 2578131 | D114: 62516 | E114: 0
B115: Carolina Arcos | C115: 3920299 | D115: 5980691 | E115: 5980691
B116: Claudio Delgado Soto | C116: 4192268 | D116: 4947612 | E116: 4947612
B117: Claudio Hernandez | C117: 7136286 | D117: 7132161 | E117: 7132161
B118: Cristián Alarcón | C118: 1813861 | D118: 1817095 | E118: 1817095
B119: Cristobal Concha Yutronic | C119: 910450 | D119: 1100602 | E119: 1100602
...

Sheet Bono Anual 2024
K20: 151765177
K21: -3130000
K22: -2408000
K23: =SUM(K20:K22) -> 146227177

Sheet Resumen Flujo consolidado 
B2: CONTROL GESTION GLOBAL FLUJO CAJA
C3: 2025
C4: MUS$
B5: Flujos de efectivo procedentes de (utilizados en) actividades de operación
B6: Ingresos operacionales | C6: =+'Flujo Consolidado por mes'!L12 -> #REF! | E6: SALDOS CTAS.CTES. 21-03-2025
B7: Clases de pagos: | E7: EMPRESA | F7: US$ | G7: FFMM US$
B8: Pago Remuneraciones | C8: =-'Flujo Consolidado por mes'!L15 -> -2995748.8 | E8: REDCO CHILE | F8: 422165 | G8: 220817
B9: Pago servicios Externos | C9: =-'Flujo Consolidado por mes'!L16 -> -1085852.5 | E9: REDCO PERU | F9: 134500
B10: Pago viajes,ropa coorp., ases.gestión, int.bg | C10: =-'Flujo Consolidado por mes'!L17 -> -507164.32 | E10: REDCO BRASIL | F10: 158418
B11: Pagos Remuneraciones-otros R+ | C11: =-'Flujo Redco Chile'!#REF! -> #REF! | E11: REDCO USA | F11: 468406
B12: Pagos Remuneraciones-honorarios administración | E12: SUMA | F12: =SUM(F8:F11) -> 1183489
B13: Otras entradas de efectivo | C13: 0
B14: Flujos de efectivo netos procedentes de (utilizados en) actividades de operación | C14: =SUM(C5:C13) -> #REF! | D14: =SUM(C14/C6) -> #REF!
B16: Flujos de efectivo procedentes de (utilizados en) actividades de administración
B17: Gastos Administraticos | C17: =-'Flujo Consolidado por mes'!L23 -> -703088.83
B18: Compra activo fijo | C18: =-'Flujo Consolidado por mes'!L25 -> -134744.68
B19: Flujos de efectivo procedentes de (utilizados en) actividades de administración | C19: =SUM(C17:C18) -> -837833.51 | D19: =SUM(C19/C6)*-1 -> #REF!
B21: Flujos de efectivo netos procedentes de (utilizados en) actividades no operacionales | C21: =SUM(C14+C19) -> #REF! | D21: =SUM(C21/C6) -> #REF!
B23: Flujos de efectivo (utilizados en) procedentes de actividades de financiación
B24: Ingreso por devolución boleta garantía | C24: =+'Flujo Consolidado por mes'!L31 -> 21714.461
B25: Aporte FFMM | C25: =-'Flujo Redco Chile'!F48 -> 0
B26: Pagos de créditos | C26: =-'Flujo Redco Chile'!F45-'Flujo Redco Chile'!F46-'Flujo Redco Chile'!F47 -> -31866.891
B27: Ingresos recuperación gastos | C27: =+'Flujo Consolidado por mes'!L33 -> 695515.28
B28: Flujos de efectivo netos(utilizados en) procedentes de actividades de financiación | C28: =SUM(C24:C27) -> 685362.85
B30: Flujos de efectivo (utilizados en) procedentes de actividades empresas relacionadas RELACIONADAS
B31: Otras entradas facturación por cuenta Redtec | C31: =+'Flujo Redco Chile'!F32 -> 146563.3
B32: Ingresos cuenta corriente EERR (Redco Perú) | C32: =+'Flujo Redco Chile'!F35-'Flujo Redco Chile'!F55 -> 0
B33: Pago facturación Redtec | C33: =-'Flujo Redco Chile'!F53 -> -140964.71
B34: Egreso por cta. BVI | C34: =+'Flujo Redco Chile'!F36-'Flujo Redco Chile'!F52 -> -14882.192
B35: Ingresos cuenta corriente EERR (Redco USA) | C35: =-'Flujo Redco Chile'!F54+'Flujo Redco Chile'!F37 -> 0
B36: Flujos de efectivo (utilizados en) procedentes de actividades EERR | C36: =SUM(C31:C35) -> -9283.5998
B38: Ingresos por IVA (débito-crédito) | C38: =+'Flujo Consolidado por mes'!L30 -> 930965.53
B39: Egresos pago Imptos retenidos/Débito | C39: =-'Flujo Consolidado por mes'!L37 -> -826022.35
B40: Flujo positivo IVA Débito Fiscal | C40: =SUM(C38:C39) -> 104943.18
B42: Aumento neto de efectivo y equivalentes al efectivo | C42: =SUM(C14+C19+C28+C36+C40) -> #REF!
B43: Efectivo y equivalentes al efectivo al principio del período | C43: =+'Flujo Consolidado por mes'!L47 -> 253992.16
B44: Efectivo y equivalentes al efectivo al final del período 31-03-2025 | C44: =SUM(C42:C43) -> #REF!
C45: =SUM(C44-'Flujo Consolidado por mes'!L48) -> #REF!

Sheet Tabla Análisis (2)
A2: País | B2: (Todas)
A4: Suma de Monto | C4: Meses (Fecha)
A5: Categoría | B5: Detalle | C5: ene | D5: feb | E5: mar | F5: abr | G5: may | H5: jun | I5: jul | J5: ago | K5: sept | L5: oct | M5: nov | N5: dic | O5: Total general
A6: Operacional | C6: 55815.879 | D6: 41890.363 | E6: 48925.263 | F6: 65992.216 | G6: 58191.892 | H6: 75589.438 | I6: 52328.506 | J6: 104511.27 | K6: 79579.002 | L6: 104137.1 | M6: 41028.986 | N6: 77538.835 | O6: 805528.74
A7: Administración | C7: 12027.719 | D7: 22080.862 | E7: 21292.178 | F7: 30224.079 | G7: 13707.694 | H7: 24521.868 | I7: 25233.887 | J7: 32104.548 | K7: 21154.016 | L7: 19672.344 | M7: 18556.384 | N7: 20054.299 | O7: 260629.88
A8: REDTEC | C8: 9720 | D8: 2711 | E8: 9675 | F8: 17383 | G8: 11056 | H8: 8453 | I8: 7808 | J8: 6464 | K8: 9114 | L8: 13294 | M8: 13325 | N8: 21627 | O8: 130630
A9: REDCROSS | C9: 0 | D9: 13948.498 | E9: 13948.498 | F9: 13948.498 | G9: 13948.498 | H9: 13948.498 | I9: 13948.498 | J9: 13948.498 | K9: 13948.498 | L9: 0 | M9: 0 | N9: 0 | O9: 111587.98
A10: Total general | C10: 77563.598 | D10: 80630.722 | E10: 93840.939 | F10: 127547.79 | G10: 96904.084 | H10: 122512.8 | I10: 99318.892 | J10: 157028.31 | K10: 123795.52 | L10: 137103.44 | M10: 72910.37 | N10: 119220.13 | O10: 1308376.6
P13: =+N13-M13 -> 0
P15: =+N15-M15 -> 0
P16: =+N16-M16 -> 0
P17: =+N17-M17 -> 0
P19: =+N19-M19 -> 0
P22: =+N22-M22 -> 0
P23: =+N23-M23 -> 0
P24: =+N24-M24 -> 0
P29: =+N29-M29 -> 0
P30: =+N30-M30 -> 0
P31: =+N31-M31 -> 0
P33: =+N33-M33 -> 0
... P91: =+N91-M91 -> 0

Sheet Ppto vs Real_Nov
B1: TC | C1: 920
B3: Item 1 | C3: Descripción | D3: 45658 | E3: 45689 | F3: 45717 | G3: 45748 | H3: 45778 | I3: 45809 | J3: 45839 | K3: 45870 | L3: 45901 | M3: 45931 | N3: 45962 | O3: 45992 | P3: Total (KUS$)
B4: Resumen gastos | C4: Total gastos | D4: 688.03016 | E4: 472.25504 | F4: 437.9579 | G4: 351.0094 | H4: 522.76343 | I4: 394.83649 | J4: 526.62049 | K4: 538.31008 | L4: 383.77724 | M4: 519.01289 | N4: 452.20354 | O4: 681.06638 | P4: 5967.843 | Q4: 5967.843
B5: Chile | C5: Sub total 1 | D5: 476.29051 | E5: 313.31492 | F5: 275.86855 | G5: 231.52127 | H5: 317.17005 | I5: 288.14494 | J5: 292.12749 | K5: 299.21779 | L5: 267.60024 | M5: 356.05444 | N5: 318.27454 | O5: 334.87696 | P5: 3770.4617 | Q5: 0.63179639
B6: Peru | C6: Sub total 2 | D6: 167.14016 | E6: 109.66978 | F6: 119.90377 | G6: 98.13241 | H6: 125.25863 | I6: 82.824806 | J6: 139.674 | K6: 152.09422 | L6: 73.594 | M6: 88.14845 | N6: 112.788 | O6: 159.18262 | P6: 1428.4109 | Q6: 0.23935128
B7: Brasil | C7: Sub total 3 | D7: 44.59949 | E7: 49.27034 | F7: 12.37958 | G7: 21.355715 | H7: 46.92575 | I7: 15.35474 | J7: 23.351 | K7: 25.03507 | L7: 27.683 | M7: 42.455 | N7: 13.641 | O7: 36.3368 | P7: 358.38748 | Q7: 0.060053102
B8: EEUU | C8: Sub total 4 | D8: 0 | E8: 0 | F8: 29.806 | G8: 0 | H8: 33.409 | I8: 8.512 | J8: 71.468 | K8: 61.963 | L8: 14.9 | M8: 32.355 | N8: 7.5 | O8: 150.67 | P8: 410.583 | Q8: 0.068799229
B11: Item 2 | C11: Descripción | D11: ene-25 | E11: feb-25 | F11: mar-25 | G11: abr-25 | H11: may-25 | I11: jun-25 | J11: jul-25 | K11: ago-25 | L11: sept-25 | M11: oct-25 | N11: nov-25 | O11: dic-25 | P11: Total (KUS$)
B12: Sueldo | C12: REDCO | D12: 231.52655 | E12: 238.52655 | F12: 245.02655 | G12: 245.02655 | H12: 278.82421 | I12: 259.58655 | J12: 316.80787 | K12: 264.00655 | L12: 264.00655 | M12: 264.00655 | N12: 290.40721 | O12: 316.80787 | P12: 3214.5596
B13: Sueldo | C13: REDCROSS | D13: 22.138493 | E13: 22.138493 | F13: 22.138493 | G13: 22.138493 | H13: 22.138493 | I13: 22.138493 | J13: 22.138493 | K13: 22.138493 | L13: 22.138493 | M13: 22.138493 | N13: 22.138493 | O13: 22.138493 | P13: 265.66192
B14: Sueldo | C14: R+ | D14: 68.529744 | E14: 75.029744 | F14: 75.029744 | G14: 88.679744 | H14: 88.679744 | I14: 88.679744 | J14: 88.679744 | K14: 88.679744 | L14: 88.679744 | M14: 88.679744 | N14: 88.679744 | O14: 88.679744 | P14: 1016.7069
B15: Sueldo | C15: REDTEC | D15: 8.964027 | E15: 8.964027 | F15: 8.964027 | G15: 8.964027 | H15: 9.8604297 | I15: 8.964027 | J15: 10.756832 | K15: 8.964027 | L15: 8.964027 | M15: 8.964027 | N15: 9.8604297 | O15: 10.756832 | P15: 112.94674
B16: Sueldo | C16: Bonos | D16: 200 | E16: 0 | F16: 0 | G16: 0 | H16: 0 | I16: 0 | J16: 0 | K16: 0 | L16: 0 | M16: 0 | N16: 0 | O16: 0 | P16: 200
B17: Externo | C17: Servicios | D17: 52.9 | E17: 52.9 | F17: 52.9 | G17: 52.9 | H17: 52.9 | I17: 52.9 | J17: 52.9 | K17: 52.9 | L17: 52.9 | M17: 52.9 | N17: 52.9 | O17: 52.9 | P17: 634.8
B18: Operacional | C18: Cumplimiento Legal | D18: 0.2173913 | E18: 0.2173913 | F18: 0.2173913 | G18: 0.2173913 | H18: 0.2173913 | I18: 0.2173913 | J18: 0.2173913 | K18: 0.2173913 | L18: 0.2173913 | M18: 0.2173913 | N18: 0.2173913 | O18: 0.2173913 | P18: 2.6086957
B19: Operacional | C19: Servicios personal | D19: 5.4347826 | E19: 0.2173913 | F19: 0 | G19: 0 | H19: 0.2173913 | I19: 0 | J19: 0 | K19: 0.2173913 | L19: 0 | M19: 0 | N19: 5.6521739 | O19: 0 | P19: 11.73913
B20: Operacional | C20: Reclutamiento | D20: 5 | E20: 0 | F20: 0 | G20: 0 | H20: 0 | I20: 0 | J20: 0 | K20: 0 | L20: 0 | M20: 0 | N20: 0 | O20: 0 | P20: 5
B21: Operacional | C21: Capacitación | D21: 0 | E21: 15 | F21: 15 | G21: 0 | H21: 0 | I21: 15 | J21: 0 | K21: 0 | L21: 0 | M21: 15 | N21: 0 | O21: 0 | P21: 60
B22: Operacional | C22: Recompensas | D22: 0 | E22: 0 | F22: 5 | G22: 0 | H22: 0 | I22: 5 | J22: 0 | K22: 0 | L22: 5 | M22: 0 | N22: 0 | O22: 5 | P22: 20
B23: Operacional | C23: Bienestar | D23: 4 | E23: 0.28804348 | F23: 0.50543478 | G23: 0.72282609 | H23: 0.28804348 | I23: 0.28804348 | J23: 0.72282609 | K23: 10.61413 | L23: 0.28804348 | M23: 0.72282609 | N23: 0.28804348 | O23: 3.0054348 | P23: 21.733696
... B60: Operacional | C60: Eventos | D60: 5.8 | E60: 5.8 | F60: 5.8 | G60: 5.8 | H60: 5.8 | I60: 5.8 | J60: 5.8 | K60: 5.8 | L60: 5.8 | M60: 5.8 | N60: 5.8 | O60: 5.8 | P60: 69.6
B62: Resumen gastos | C62: Total gastos | D62: 45658 | E62: 45689 | F62: 45717 | G62: 45748 | H62: 45778 | I62: 45809 | J62: 45839 | K62: 45870 | L62: 45901 | M62: 45931 | N62: 45962 | O62: 45992 | P62: Total (kUS$) | Q62: Distribución
B63: Resumen gastos | C63: Total gastos | D63: 695.28316 | E63: 507.61468 | F63: 519.11468 | G63: 514.39511 | H63: 547.45874 | I63: 547.10729 | J63: 590.31705 | K63: 542.07076 | L63: 536.52729 | M63: 550.87511 | N63: 564.47652 | O63: 593.83879 | P63: 6709.0792 | Q63: 1
B64: Chile | C64: Sub total 1 | D64: 439.27739 | E64: 320.70912 | F64: 327.97478 | G64: 324.99298 | H64: 345.88245 | I64: 345.66041 | J64: 372.96019 | K64: 342.47835 | L64: 338.976 | M64: 348.04091 | N64: 356.63423 | O64: 375.18521 | P64: 4238.772 | Q64: 0.63179639
B65: Peru | C65: Sub total 2 | D65: 166.41691 | E65: 121.49822 | F65: 124.25076 | G65: 123.12113 | H65: 131.03495 | I65: 130.95083 | J65: 141.29314 | K65: 129.74533 | L65: 128.41849 | M65: 131.85266 | N65: 135.10818 | O65: 142.13607 | P65: 1605.8267 | Q65: 0.23935128
B66: Brasil | C66: Sub total 3 | D66: 41.75391 | E66: 30.483836 | F66: 31.174446 | G66: 30.891022 | H66: 32.876595 | I66: 32.855489 | J66: 35.45037 | K66: 32.553031 | L66: 32.220128 | M66: 33.081759 | N66: 33.898566 | O66: 35.661861 | P66: 402.90101 | Q66: 0.060053102
B67: EEUU | C67: Sub total 4 | D67: 47.834945 | E67: 34.923498 | F67: 35.71469 | G67: 35.389987 | H67: 37.664739 | I67: 37.640559 | J67: 40.613358 | K67: 37.294051 | L67: 36.912664 | M67: 37.899783 | N67: 38.835549 | O67: 40.855651 | P67: 461.57947 | Q67: 0.068799229
B69: Resumen gastos | C69: Total gastos | D69: 45658 | E69: 45689 | F69: 45717 | G69: 45748 | H69: 45778 | I69: 45809 | J69: 45839 | K69: 45870 | L69: 45901 | M69: 45931 | N69: 45962 | O69: 45992 | P69: Total (kUS$) | Q69: Distribución
B70: Resumen gastos | C70: Total gastos | D70: 695.28316 | E70: 507.61468 | F70: 519.11468 | G70: 514.39511 | H70: 547.45874 | I70: 547.10729 | J70: 590.31705 | K70: 542.07076 | L70: 536.52729 | M70: 550.87511 | N70: 564.47652 | O70: 593.83879 | P70: 6709.0792 | Q70: 1
B71: Sueldos | C71: Sub total 1 | D71: 531.15882 | E71: 344.65882 | F71: 351.15882 | G71: 364.80882 | H71: 399.50288 | I71: 379.36882 | J71: 438.38294 | K71: 383.78882 | L71: 383.78882 | M71: 383.78882 | N71: 411.08588 | O71: 438.38294 | P71: 4809.8752 | Q71: 0.71692032
B72: Impuestos | C72: Sub total 2 | D72: 0 | E72: 0 | F72: 0 | G72: 0 | H72: 0 | I72: 0 | J72: 0 | K72: 0 | L72: 0 | M72: 0 | N72: 0 | O72: 0 | P72: 0 | Q72: 0
B73: Oficina | C73: Sub total 3 | D73: 52.11 | E73: 51.61 | F73: 51.61 | G73: 51.61 | H73: 51.61 | I73: 51.61 | J73: 52.11 | K73: 51.61 | L73: 51.61 | M73: 51.61 | N73: 51.61 | O73: 51.61 | P73: 620.32 | Q73: 0.092459782
B74: RRHH | C74: Sub total 4 | D74: 19.891304 | E74: 19.222826 | F74: 24.222826 | G74: 5.8532609 | H74: 4.2228261 | I74: 24.005435 | J74: 7.701087 | K74: 14.548913 | L74: 9.0054348 | M74: 23.353261 | N74: 9.6576087 | O74: 11.722826 | P74: 173.40761 | Q74: 0.025846708
B75: Externo | C75: Sub total 5 | D75: 52.9 | E75: 52.9 | F75: 52.9 | G75: 52.9 | H75: 52.9 | I75: 52.9 | J75: 52.9 | K75: 52.9 | L75: 52.9 | M75: 52.9 | N75: 52.9 | O75: 52.9 | P75: 634.8 | Q75: 0.094618052
B76: Viajes | C76: Sub total 6 | D76: 12 | E76: 12 | F76: 12 | G76: 12 | H76: 12 | I76: 12 | J76: 12 | K76: 12 | L76: 12 | M76: 12 | N76: 12 | O76: 12 | P76: 144 | Q76: 0.021463452
B77: Otros | C77: Sub total 7 | D77: 19.423033 | E77: 19.423033 | F77: 19.423033 | G77: 19.423033 | H77: 19.423033 | I77: 19.423033 | J77: 19.423033 | K77: 19.423033 | L77: 19.423033 | M77: 19.423033 | N77: 19.423033 | O77: 19.423033 | P77: 233.07639 | Q77: 0.034740444
B78: Comercial | C78: Sub total 8 | D78: 7.8 | E78: 7.8 | F78: 7.8 | G78: 7.8 | H78: 7.8 | I78: 7.8 | J78: 7.8 | K78: 7.8 | L78: 7.8 | M78: 7.8 | N78: 7.8 | O78: 7.8 | P78: 93.6 | Q78: 0.013951244
B83: Resumen gastos | C83: Total (kUS$)
B84: Resumen gastos | C84: 6709.0792
B85: Sueldos | C85: 4809.8752
B86: Oficina | C86: 620.32
B87: RRHH | C87: 173.40761
B88: Externo | C88: 634.8
B89: Viajes | C89: 144
B90: Otros | C90: 233.07639
B91: Comercial | C91: 93.6
W94: Factor | X94: 0.98490094 | AC94: A Noviembre
A95: Suma de Monto | B95: Etiquetas de columna | AC95: Categoría | AD95: Detalle | AE95: Suma de Monto | AF95: KUS$ | AH95: Categoría | AI95: Detalle | AJ95: Suma de Monto
A96: Etiquetas de fila | B96: ene | C96: feb | D96: mar | E96: abr | F96: may | G96: jun | H96: jul | I96: ago | J96: sept | K96: oct | L96: nov | M96: dic | N96: Total general | P96: Item | Q96: Budget | R96: Real | S96: Dif. | V96: Gasto Edu | W96: Gasto Isa | X96: Dif. | Y96: Gasto ajustado | Z96: kUS$ | AC96: Sueldo | AE96: =+_xlfn.XLOOKUP(AC96,'Tabla Análisis (2)'!A:A,'Tabla Análisis (2)'!O:O,0,0,1) -> 0 | AF96: =+AE96/1000 -> 0 | AH96: Sueldo | AJ96: 499868.52
A97: Sueldo | B97: 531.1588 | C97: 344.6588 | D97: 351.1588 | E97: 364.8088 | F97: 399.5028 | G97: 379.3688 | H97: 438.3829 | I97: 383.7888 | J97: 383.7888 | K97: 383.7888 | L97: 411.0858 | M97: 438.3829 | N97: 4809.8748 | P97: Operacional | Q97: 861.5273 | R97: 805.52874 | S97: =+R97-Q97 -> -55.998558 | U97: Sueldo | V97: 3894498 | Y97: =+V97*$X$94 -> 3835694.8 | Z97: =+Y97/1000 -> 3835.6948 | AC97: Operacional | AE97: =+_xlfn.XLOOKUP(AC97,'Tabla Análisis (2)'!A:A,'Tabla Análisis (2)'!O:O,0,0,1) -> 805528.74 | AF97: =+AE97/1000 -> 805.52874 | AH97: Externo | AJ97: 49247.88
A98: Operacional | B98: 77.6513 | C98: 76.4828 | D98: 81.4828 | E98: 63.1132 | F98: 61.4828 | G98: 81.2654 | H98: 65.4611 | I98: 71.8089 | J98: 66.2654 | K98: 80.6132 | L98: 66.9176 | M98: 68.9828 | N98: 861.5273 | P98: REDCROSS/REDTEC | Q98: 233.076 | R98: 242.21798 | S98: =+R98-Q98 -> 9.1419832 | U98: Operacional | V98: 649069.66 | Y98: =+V98*$X$94 -> 639269.32 | Z98: =+Y98/1000 -> 639.26932 | AC98: Externo | AE98: =+_xlfn.XLOOKUP(AC98,'Tabla Análisis (2)'!A:A,'Tabla Análisis (2)'!O:O,0,0,1) -> 0 | AF98: =+AE98/1000 -> 0 | AH98: Operacional | AJ98: 41786.269
A99: Externo | B99: 52.9 | C99: 52.9 | D99: 52.9 | E99: 52.9 | F99: 52.9 | G99: 52.9 | H99: 52.9 | I99: 52.9 | J99: 52.9 | K99: 52.9 | L99: 52.9 | M99: 52.9 | N99: 634.8 | P99: Administración | Q99: 169.8 | R99: 260.62988 | S99: =+R99-Q99 -> 90.82988 | U99: Externo | V99: 548352.26 | Y99: =+V99*$X$94 -> 540072.66 | Z99: =+Y99/1000 -> 540.07266 | AC99: Administración | AE99: =+_xlfn.XLOOKUP(AC99,'Tabla Análisis (2)'!A:A,'Tabla Análisis (2)'!O:O,0,0,1) -> 260629.88 | AF99: =+AE99/1000 -> 260.62988 | AH99: Administración | AJ99: 18510.821
A100: REDCROSS/REDTEC | B100: 19.423 | C100: 19.423 | D100: 19.423 | E100: 19.423 | F100: 19.423 | G100: 19.423 | H100: 19.423 | I100: 19.423 | J100: 19.423 | K100: 19.423 | L100: 19.423 | M100: 19.423 | N100: 233.076 | P100: Externo | Q100: 634.8 | R100: 893.88561 | S100: =+R100-Q100 -> 259.08562 | U100: REDCROSS/REDTEC | V100: 205047.24 | Y100: =+V100*$X$94 -> 201951.22 | Z100: =+Y100/1000 -> 201.95122 | AC100: REDCROSS | AE100: =+_xlfn.XLOOKUP(AC100,'Tabla Análisis (2)'!A:A,'Tabla Análisis (2)'!O:O,0,0,1) -> 111587.98 | AF100: =+AE100/1000 -> 111.58798 | AH100: REDTEC | AJ100: 13325
A101: Administración | B101: 14.15 | C101: 14.15 | D101: 14.15 | E101: 14.15 | F101: 14.15 | G101: 14.15 | H101: 14.15 | I101: 14.15 | J101: 14.15 | K101: 14.15 | L101: 14.15 | M101: 14.15 | N101: 169.8 | P101: Sueldo | Q101: 4809.8748 | R101: 5232.4623 | S101: =+R101-Q101 -> 422.58746 | U101: Administración | V101: 218241.98 | Y101: =+V101*$X$94 -> 214946.73 | Z101: =+Y101/1000 -> 214.94673 | AC101: REDTEC | AE101: =+_xlfn.XLOOKUP(AC101,'Tabla Análisis (2)'!A:A,'Tabla Análisis (2)'!O:O,0,0,1) -> 130630 | AF101: =+AE101/1000 -> 130.63 | AH101: REDCROSS | AJ101: 0
A102: Total general | B102: 695.2831 | C102: 507.6146 | D102: 519.1146 | E102: 514.395 | F102: 547.4586 | G102: 547.1072 | H102: 590.317 | I102: 542.0707 | J102: 536.5272 | K102: 550.875 | L102: 564.4764 | M102: 593.8387 | N102: 6709.0781 | P102: Total | Q102: =SUM(Q97:Q101) -> 6709.0781 | R102: =SUM(R97:R101) -> 7434.7245 | S102: =+R102-Q102 -> 725.64638 | V102: =SUM(V97:V101) -> 5515209.2 | W102: =+'Tabla datos unidades_Sept'!L18 -> 5426599.1 | X102: =+W102-V102 -> -88610.008 | Y102: =SUM(Y97:Y101) -> 5431934.7 | Z102: =SUM(Z97:Z101) -> 5431.9347 | AC102: Total general | AE102: =SUM(AE96:AE101) -> 1308376.6 | AF102: =SUM(AF96:AF101) -> 1308.3766 | AH102: Total general | AJ102: 622738.49
S103: =+S102/Q102 -> 0.10815888 | V103: 368950 | Y103: =+V103*$X$94 -> 363379.2 | Z103: =+Y103/1000 -> 363.3792 | AA103: No externos
V104: 274256 | Y104: =+V104*$X$94 -> 270114.99 | Z104: =+Y104/1000 -> 270.11499 | AA104: Impuestos
P105: Budget | Q105: =+Q102 -> 6709.0781 | Y105: =+SUM(Y102:Y104) -> 6065428.9 | Z105: =+Y105/1000 -> 6065.4289
P106: Operacional | Q106: -55.998558
P107: REDCROSS/REDTEC | Q107: 9.1419832 | V107: 210307 | Y107: =+V107*$X$94 -> 207131.56 | Z107: =+Y107/1000 -> 207.13156
P108: Administración | Q108: 90.82988 | V108: 54382 | Y108: =+V108*$X$94 -> 53560.883 | Z108: =+Y108/1000 -> 53.560883
P109: Externo | Q109: 259.08562 | V109: 104261 | Y109: =+V109*$X$94 -> 102686.76 | Z109: =+Y109/1000 -> 102.68676
P110: Sueldo | Q110: 422.58746
P111: Comparable Budget | Q111: =SUM(Q105:Q110) -> 7434.7245
P112: Inversión | Q112: 209 | V112: 36821 | Y112: =+V112*$X$94 -> 36265.038 | Z112: =+Y112/1000 -> 36.265038
P113: Adicionales | Q113: 144
P114: Gran Total | Q114: =+SUM(Q111:Q113) -> 7787.7245 | V114: 153058 | Y114: =+V114*$X$94 -> 150746.97 | Z114: =+Y114/1000 -> 150.74697
V115: 117436 | Y115: =+V115*$X$94 -> 115662.83 | Z115: =+Y115/1000 -> 115.66283
V116: 3761.7533 | Y116: =+V116*$X$94 -> 3704.9544 | Z116: =+Y116/1000 -> 3.7049544

Sheet Tabla datos unidades_Dic
L1: 6853202.5 | M1: =+L10-L1 -> 73593.425 | N1: =+M1/L10 -> 0.010624454 | Q1: =+P6*0.2 -> 319418.44
J2: =+J17/1000 -> 641.80299 | K2: =+K17/1000 -> 678.99571 | L2: =+L17/1000 -> 666.97613 | M2: =+M17/1000 -> 729.50446 | N2: =+N17/1000 -> 586.01155 | O2: =+O17/1000 -> 976.72234
B3: País | C3: Concepto | D3: 45658 | E3: 45689 | F3: 45717 | G3: 45748 | H3: 45778 | I3: 45809 | J3: 45839 | K3: 45870 | L3: 45901 | M3: 45931 | N3: 45962 | O3: 45992 | P3: Total | R3: País | S3: Concepto | T3: 45658
B4: Chile | C4: INGRESOS OP | D4: =+'Flujo Redco Chile'!C12 -> 362362.73 | E4: =+'Flujo Redco Chile'!D12 -> 547310.62 | F4: =+'Flujo Redco Chile'!E12 -> 389727.46 | G4: =+'Flujo Redco Chile'!F12 -> 237434.48 | H4: =+'Flujo Redco Chile'!G12 -> 272631.08 | I4: =+'Flujo Redco Chile'!H12 -> 277419.07 | J4: =+'Flujo Redco Chile'!I12 -> 475570.75 | K4: =+'Flujo Redco Chile'!J12 -> 151482.74 | ... O4: =+'Flujo Redco Chile'!N12 -> 173207.55 | P4: =SUM(D4:O4) -> 3592126.9 | Q4: =+P4/$P$9 -> 0.39255574 | R4: Chile | S4: SALDO INICIAL | T4: =+'Flujo Redco Chile'!C8 -> 52257.137
B5: Perú | C5: INGRESOS OP | D5: =+'Flujo Redco Perú'!C13 -> 123848 | E5: =+'Flujo Redco Perú'!D13 -> 62454 | F5: =+'Flujo Redco Perú'!E13 -> 105377 | G5: =+'Flujo Redco Perú'!F13 -> 110077 | H5: =+'Flujo Redco Perú'!G13 -> 142610 | I5: =+'Flujo Redco Perú'!H13 -> 229588 | J5: =+'Flujo Redco Perú'!I13 -> 251702 | K5: =+'Flujo Redco Perú'!J13 -> 641573 | ... O5: =+'Flujo Redco Perú'!N13 -> 269432 | P5: =SUM(D5:O5) -> 2417353 | Q5: =+P5/$P$9 -> 0.26417379 | R5: Perú | S5: SALDO INICIAL | T5: =+'Flujo Redco Perú'!C9 -> 136767.69
B6: Brasil | C6: INGRESOS OP | D6: =+'Flujo Redco Brasil'!C14 -> 80502 | E6: =+'Flujo Redco Brasil'!D14 -> 59683 | F6: =+'Flujo Redco Brasil'!E14 -> 96322 | G6: =+'Flujo Redco Brasil'!F14 -> 97209.7 | H6: =+'Flujo Redco Brasil'!G14 -> 37074 | I6: =+'Flujo Redco Brasil'!H14 -> 66563 | J6: =+'Flujo Redco Brasil'!I14 -> 47717 | K6: =+'Flujo Redco Brasil'!J14 -> 119652 | ... O6: =+'Flujo Redco Brasil'!N14 -> 224116.51 | P6: =SUM(D6:O6) -> 1597092.2 | Q6: =+P6/$P$9 -> 0.17453384 | R6: Brasil | S6: SALDO INICIAL | T6: =+'Flujo Redco Brasil'!C9 -> 9622.33
B7: USA | C7: INGRESOS OP | D7: =+'Flujo Redco USA'!C13 -> 150453 | E7: =+'Flujo Redco USA'!D13 -> 243465.21 | F7: =+'Flujo Redco USA'!E13 -> 141526 | G7: =+'Flujo Redco USA'!F13 -> 169200 | H7: =+'Flujo Redco USA'!G13 -> 195090 | I7: =+'Flujo Redco USA'!H13 -> 61796 | J7: =+'Flujo Redco USA'!I13 -> 0 | K7: =+'Flujo Redco USA'!J13 -> 20000 | ... O7: =+'Flujo Redco USA'!N13 -> 178785 | P7: =SUM(D7:O7) -> 1205315.2 | Q7: =+P7/$P$9 -> 0.13171957 | R7: USA | S7: SALDO INICIAL | T7: =+'Flujo Redco USA'!C9 -> 55345
B8: Otros | C8: INGRESOS OP | D8: =+'Flujo Redco BVI'!C13 -> 0 | E8: =+'Flujo Redco BVI'!D13 -> 21682 | F8: =+'Flujo Redco BVI'!E13 -> 45478 | G8: =+'Flujo Redco BVI'!F13 -> 0 | H8: =+'Flujo Redco BVI'!G13 -> 0 | I8: =+'Flujo Redco BVI'!H13 -> 172045 | J8: =+'Flujo Redco BVI'!I13 -> 0 | K8: =+'Flujo Redco BVI'!J13 -> 99524 | ... O8: =+'Flujo Redco BVI'!N13 -> 0 | P8: =SUM(D8:O8) -> 338729 | Q8: =+P8/$P$9 -> 0.037017069 | R8: BVI | S8: SALDO INICIAL | T8: =+'Flujo Redco BVI'!S13 -> 0
B9: TOTAL | C9: INGRESOS OP | D9: =SUM(D4:D8) -> 717165.73 | E9: =SUM(E4:E8) -> 934594.83 | F9: =SUM(F4:F8) -> 778430.46 | G9: =SUM(G4:G8) -> 613921.18 | H9: =SUM(H4:H8) -> 647405.08 | I9: =SUM(I4:I8) -> 807411.07 | J9: =SUM(J4:J8) -> 774989.75 | K9: =SUM(K4:K8) -> 1032231.7 | ... P9: =SUM(P4:P8) -> 9150616.3 | R9: CAJA FINAL | S9: CAJA FINAL | T9: =SUM(T4:T8) -> 253992.16
C10: INGRESOS OP ACUM | D10: =+SUM($D$9:D9) -> 717165.73 | E10: =+SUM($D$9:E9) -> 1651760.6 | F10: =+SUM($D$9:F9) -> 2430191 | G10: =+SUM($D$9:G9) -> 3044112.2 | H10: =+SUM($D$9:H9) -> 3691517.3 | I10: =+SUM($D$9:I9) -> 4498928.4 | J10: =+SUM($D$9:J9) -> 5273918.1 | K10: =+SUM($D$9:K9) -> 6306149.8 | ... O10: =+SUM($D$9:O9) -> 9150616.3
B11: País | C11: Concepto | D11: 45658 | E11: 45689 | F11: 45717 | G11: 45748 | H11: 45778 | I11: 45809 | J11: 45839 | K11: 45870 | L11: 45901 | M11: 45931 | N11: 45962 | O11: 45992 | P11: Total
B12: Chile | C12: COSTOS OP | D12: =+'Flujo Redco Chile'!C18+'Flujo Redco Chile'!C23+'Flujo Redco Chile'!C25 -> 397276.65 | E12: =+'Flujo Redco Chile'!D18+'Flujo Redco Chile'!D23+'Flujo Redco Chile'!D25 -> 422126.64 | F12: =+'Flujo Redco Chile'!E18+'Flujo Redco Chile'!E23+'Flujo Redco Chile'!E25 -> 439899.18 | G12: =+'Flujo Redco Chile'!F18+'Flujo Redco Chile'!F23+'Flujo Redco Chile'!F25 -> 341507.35 | H12: =+'Flujo Redco Chile'!G18+'Flujo Redco Chile'!G23+'Flujo Redco Chile'!G25 -> 340134.8 | I12: =+'Flujo Redco Chile'!H18+'Flujo Redco Chile'!H23+'Flujo Redco Chile'!H25 -> 380566.17 | J12: =+'Flujo Redco Chile'!I18+'Flujo Redco Chile'!I23+'Flujo Redco Chile'!I25 -> 395727.19 | K12: =+'Flujo Redco Chile'!J18+'Flujo Redco Chile'!J23+'Flujo Redco Chile'!J25 -> 425248.91 | ... O12: =+'Flujo Redco Chile'!N18+'Flujo Redco Chile'!N23+'Flujo Redco Chile'!N25 -> 495505.54 | P12: =SUM(D12:O12) -> 4999267.5
B13: Perú | C13: COSTOS OP | D13: =+'Flujo Redco Perú'!C19+'Flujo Redco Perú'!C26+'Flujo Redco Perú'!C28 -> 89462.85 | E13: =+'Flujo Redco Perú'!D19+'Flujo Redco Perú'!D26+'Flujo Redco Perú'!D28 -> 81597 | F13: =+'Flujo Redco Perú'!E19+'Flujo Redco Perú'!E26+'Flujo Redco Perú'!E28 -> 92755 | G13: =+'Flujo Redco Perú'!F19+'Flujo Redco Perú'!F26+'Flujo Redco Perú'!F28 -> 137672.3 | H13: =+'Flujo Redco Perú'!G19+'Flujo Redco Perú'!G26+'Flujo Redco Perú'!G28 -> 128924 | I13: =+'Flujo Redco Perú'!H19+'Flujo Redco Perú'!H26+'Flujo Redco Perú'!H28 -> 167995 | J13: =+'Flujo Redco Perú'!I19+'Flujo Redco Perú'!I26+'Flujo Redco Perú'!I28 -> 199355 | K13: =+'Flujo Redco Perú'!J19+'Flujo Redco Perú'!J26+'Flujo Redco Perú'!J28 -> 225572 | ... O13: =+'Flujo Redco Perú'!N19+'Flujo Redco Perú'!N26+'Flujo Redco Perú'!N28 -> 234121 | P13: =SUM(D13:O13) -> 1731862.8
B14: Brasil | C14: COSTOS OP | D14: =+'Flujo Redco Brasil'!C20+'Flujo Redco Brasil'!C25+'Flujo Redco Brasil'!C27 -> 21023 | E14: =+'Flujo Redco Brasil'!D20+'Flujo Redco Brasil'!D25+'Flujo Redco Brasil'!D27 -> 27812 | F14: =+'Flujo Redco Brasil'!E20+'Flujo Redco Brasil'!E25+'Flujo Redco Brasil'!E27 -> 26425 | G14: =+'Flujo Redco Brasil'!F20+'Flujo Redco Brasil'!F25+'Flujo Redco Brasil'!F27 -> 52004.4 | H14: =+'Flujo Redco Brasil'!G20+'Flujo Redco Brasil'!G25+'Flujo Redco Brasil'!G27 -> 33329 | I14: =+'Flujo Redco Brasil'!H20+'Flujo Redco Brasil'!H25+'Flujo Redco Brasil'!H27 -> 76286 | J14: =+'Flujo Redco Brasil'!I20+'Flujo Redco Brasil'!I25+'Flujo Redco Brasil'!I27 -> 31019 | K14: =+'Flujo Redco Brasil'!J20+'Flujo Redco Brasil'!J25+'Flujo Redco Brasil'!J27 -> 21475 | ... O14: =+'Flujo Redco Brasil'!N20+'Flujo Redco Brasil'!N25+'Flujo Redco Brasil'!N27 -> 23001 | P14: =SUM(D14:O14) -> 451717.4
B15: USA | C15: COSTOS OP | D15: =+'Flujo Redco USA'!C19+'Flujo Redco USA'!C27+'Flujo Redco USA'!C29 -> 15 | E15: =+'Flujo Redco USA'!D19+'Flujo Redco USA'!D27+'Flujo Redco USA'!D29 -> 2025 | F15: =+'Flujo Redco USA'!E19+'Flujo Redco USA'!E27+'Flujo Redco USA'!E29 -> 58728 | G15: =+'Flujo Redco USA'!F19+'Flujo Redco USA'!F27+'Flujo Redco USA'!F29 -> 9898 | H15: =+'Flujo Redco USA'!G19+'Flujo Redco USA'!G27+'Flujo Redco USA'!G29 -> 47666 | I15: =+'Flujo Redco USA'!H19+'Flujo Redco USA'!H27+'Flujo Redco USA'!H29 -> 4178 | J15: =+'Flujo Redco USA'!I19+'Flujo Redco USA'!I27+'Flujo Redco USA'!I29 -> 10017 | K15: =+'Flujo Redco USA'!J19+'Flujo Redco USA'!J27+'Flujo Redco USA'!J29 -> 1015 | ... O15: =+'Flujo Redco USA'!N19+'Flujo Redco USA'!N27+'Flujo Redco USA'!N29 -> 218410 | P15: =SUM(D15:O15) -> 442363
B16: Otros | C16: COSTOS OP | D16: =+'Flujo Redco BVI'!C19+'Flujo Redco BVI'!C27+'Flujo Redco BVI'!C29 -> 14044 | E16: =+'Flujo Redco BVI'!D19+'Flujo Redco BVI'!D27+'Flujo Redco BVI'!D29 -> 0 | F16: =+'Flujo Redco BVI'!E19+'Flujo Redco BVI'!E27+'Flujo Redco BVI'!E29 -> 0 | G16: =+'Flujo Redco BVI'!F19+'Flujo Redco BVI'!F27+'Flujo Redco BVI'!F29 -> 14380 | H16: =+'Flujo Redco BVI'!G19+'Flujo Redco BVI'!G27+'Flujo Redco BVI'!G29 -> 16000 | I16: =+'Flujo Redco BVI'!H19+'Flujo Redco BVI'!H27+'Flujo Redco BVI'!H29 -> 15094 | J16: =+'Flujo Redco BVI'!I19+'Flujo Redco BVI'!I27+'Flujo Redco BVI'!I29 -> 5684.8 | K16: =+'Flujo Redco BVI'!J19+'Flujo Redco BVI'!J27+'Flujo Redco BVI'!J29 -> 5684.8 | ... O16: =+'Flujo Redco BVI'!N19+'Flujo Redco BVI'!N27+'Flujo Redco BVI'!N29 -> 5684.8 | P16: =SUM(D16:O16) -> 93626.8
B17: TOTAL | C17: COSTOS OP | D17: =SUM(D12:D16) -> 521821.5 | E17: =SUM(E12:E16) -> 533560.64 | F17: =SUM(F12:F16) -> 617807.18 | G17: =SUM(G12:G16) -> 555462.05 | H17: =SUM(H12:H16) -> 566053.8 | I17: =SUM(I12:I16) -> 644119.17 | J17: =SUM(J12:J16) -> 641802.99 | K17: =SUM(K12:K16) -> 678995.71 | ... O17: =SUM(O12:O16) -> 976722.34 | P17: =SUM(D17:O17) -> 7718837.5
C18: COSTOS OP ACUM | D18: =+SUM($D$17:D17) -> 521821.5 | E18: =+SUM($D$17:E17) -> 1055382.1 | F18: =+SUM($D$17:F17) -> 1673189.3 | G18: =+SUM($D$17:G17) -> 2228651.4 | H18: =+SUM($D$17:H17) -> 2794705.2 | I18: =+SUM($D$17:I17) -> 3438824.3 | J18: =+SUM($D$17:J17) -> 4080627.3 | K18: =+SUM($D$17:K17) -> 4759623 | ... O18: =+SUM($D$17:O17) -> 7718837.5
B19: País | C19: Concepto | D19: 45658 | E19: 45689 | F19: 45717 | G19: 45748 | H19: 45778 | I19: 45809 | J19: 45839 | K19: 45870 | L19: 45901 | M19: 45931 | N19: 45962 | O19: 45992 | P19: Total
B20: Chile | C20: RESULTADO OP. | D20: =+D4-D12 -> -34913.914 | E20: =+E4-E12 -> 125183.98 | F20: =+F4-F12 -> -50171.722 | G20: =+G4-G12 -> -104072.86 | H20: =+H4-H12 -> -67503.719 | I20: =+I4-I12 -> -103147.1 | J20: =+J4-J12 -> 79843.563 | K20: =+K4-K12 -> -273766.17 | ... O20: =+O4-O12 -> -322297.98 | P20: =SUM(D20:O20) -> -1407140.6
B21: Perú | C21: RESULTADO OP. | D21: =+D5-D13 -> 34385.15 | E21: =+E5-E13 -> -19143 | F21: =+F5-F13 -> 12622 | G21: =+G5-G13 -> -27595.3 | H21: =+H5-H13 -> 13686 | I21: =+I5-I13 -> 61593 | J21: =+J5-J13 -> 52347 | K21: =+K5-K13 -> 416001 | ... O21: =+O5-O13 -> 35311 | P21: =SUM(D21:O21) -> 685490.21
B22: Brasil | C22: RESULTADO OP. | D22: =+D6-D14 -> 59479 | E22: =+E6-E14 -> 31871 | F22: =+F6-F14 -> 69897 | G22: =+G6-G14 -> 45205.3 | H22: =+H6-H14 -> 3745 | I22: =+I6-I14 -> -9723 | J22: =+J6-J14 -> 16698 | K22: =+K6-K14 -> 98177 | ... O22: =+O6-O14 -> 201115.51 | P22: =SUM(D22:O22) -> 1145374.8
B23: USA | C23: RESULTADO OP. | D23: =+D7-D15 -> 150438 | E23: =+E7-E15 -> 241440.21 | F23: =+F7-F15 -> 82798 | G23: =+G7-G15 -> 159302 | H23: =+H7-H15 -> 147424 | I23: =+I7-I15 -> 57618 | J23: =+J7-J15 -> -10017 | K23: =+K7-K15 -> 18985 | ... O23: =+O7-O15 -> -39625 | P23: =SUM(D23:O23) -> 762952.21
B24: Otros | C24: RESULTADO OP. | D24: =+D8-D16 -> -14044 | E24: =+E8-E16 -> 21682 | F24: =+F8-F16 -> 45478 | G24: =+G8-G16 -> -14380 | H24: =+H8-H16 -> -16000 | I24: =+I8-I16 -> 156951 | J24: =+J8-J16 -> -5684.8 | K24: =+K8-K16 -> 93839.2 | ... O24: =+O8-O16 -> -5684.8 | P24: =SUM(D24:O24) -> 245102.2
B25: TOTAL | C25: RESULTADO OP. | D25: =SUM(D20:D24) -> 195344.24 | E25: =SUM(E20:E24) -> 401034.19 | F25: =SUM(F20:F24) -> 160623.28 | G25: =SUM(G20:G24) -> 58459.138 | H25: =SUM(H20:H24) -> 81351.281 | I25: =SUM(I20:I24) -> 163291.9 | J25: =SUM(J20:J24) -> 133186.76 | K25: =SUM(K20:K24) -> 353236.03 | ... P25: =SUM(P20:P24) -> 1431778.8
D26: =+SUM($D$25:D25) -> 195344.24 | E26: =+SUM($D$25:E25) -> 596378.43 | F26: =+SUM($D$25:F25) -> 757001.71 | G26: =+SUM($D$25:G25) -> 815460.84 | H26: =+SUM($D$25:H25) -> 896812.13 | I26: =+SUM($D$25:I25) -> 1060104 | J26: =+SUM($D$25:J25) -> 1193290.8 | K26: =+SUM($D$25:K25) -> 1546526.8 | ... O26: =+SUM($D$25:O25) -> 1431778.8
B27: País | C27: Concepto | D27: 45658 | E27: 45689 | F27: 45717 | G27: 45748 | H27: 45778 | I27: 45809 | J27: 45839 | K27: 45870 | L27: 45901 | M27: 45931 | N27: 45962 | O27: 45992 | P27: Total
B28: Chile | C28: INGRESO IVA DEBITO | D28: =+'Flujo Redco Chile'!C31 -> 69432.94 | E28: =+'Flujo Redco Chile'!D31 -> 104811.9 | F28: =+'Flujo Redco Chile'!E31 -> 75208.024 | G28: =+'Flujo Redco Chile'!F31 -> 47094.724 | H28: =+'Flujo Redco Chile'!G31 -> 62773.513 | I28: =+'Flujo Redco Chile'!H31+'Flujo Redco Chile'!H34 -> 53789.215 | J28: =+'Flujo Redco Chile'!I31 -> 103658.78 | K28: =+'Flujo Redco Chile'!J31 -> 35825.605 | L28: =+'Flujo Redco Chile'!K31 -> 57280.832 | M28: =+'Flujo Redco Chile'!L31 -> 32498.942 | N28: =+'Flujo Redco Chile'!M31 -> 37753.16 | O28: =+'Flujo Redco Chile'!N31 -> 32909.433 | P28: =SUM(D28:O28) -> 713037.07
B29: Perú | C29: INGRESO IVA DEBITO | D29: =+'Flujo Redco Perú'!C35 -> 11907 | E29: =+'Flujo Redco Perú'!D35 -> 16500 | F29: =+'Flujo Redco Perú'!E35 -> 20068 | G29: =+'Flujo Redco Perú'!F35 -> 28529 | H29: =+'Flujo Redco Perú'!G35 -> 31304 | I29: =+'Flujo Redco Perú'!H35 -> 36127 | J29: =+'Flujo Redco Perú'!I35 -> 34183 | K29: =+'Flujo Redco Perú'!J35 -> 126435 | ... O29: =+'Flujo Redco Perú'!N35 -> 75885 | P29: =SUM(D29:O29) -> 544185
B30: Chile | C30: OTROS INGRESOS | D30: =+'Flujo Redco Chile'!C38+'Flujo Redco Chile'!C39+'Flujo Redco Chile'!E42+'Flujo Redco Chile'!C34 -> 703.28541 | E30: =+'Flujo Redco Chile'!D38+'Flujo Redco Chile'!D39+'Flujo Redco Chile'!D34 -> 10399.317 | F30: =+'Flujo Redco Chile'!E38+'Flujo Redco Chile'!E39+'Flujo Redco Chile'!E34 -> 5265.8026 | G30: =+'Flujo Redco Chile'!F38+'Flujo Redco Chile'!F39+'Flujo Redco Chile'!F34 -> 21747.626 | H30: =+'Flujo Redco Chile'!G38+'Flujo Redco Chile'!G39+'Flujo Redco Chile'!G34 -> 55661.029 | I30: =+'Flujo Redco Chile'!H38+'Flujo Redco Chile'!H39+'Flujo Redco Chile'!H34 -> 0 | J30: =+'Flujo Redco Chile'!I38+'Flujo Redco Chile'!I39+'Flujo Redco Chile'!I34 -> 68680.616 | K30: =+'Flujo Redco Chile'!J38+'Flujo Redco Chile'!J39+'Flujo Redco Chile'!J34 -> 37073.082 | L30: =+'Flujo Redco Chile'!K38+'Flujo Redco Chile'!K39+'Flujo Redco Chile'!K34 -> 4069.9474 | ... O30: =+'Flujo Redco Chile'!N38+'Flujo Redco Chile'!N39+'Flujo Redco Chile'!N34 -> 119.83584 | P30: =SUM(D30:O30) -> 227205.51
B31: Brasil | C31: OTROS INGRESOS | D31: =+'Flujo Redco Brasil'!C34 -> 6388 | E31: =+'Flujo Redco Brasil'!D34 -> 363 | F31: =+'Flujo Redco Brasil'!E34 -> 0 | G31: =+'Flujo Redco Brasil'!F34 -> 0 | H31: =+'Flujo Redco Brasil'!G34 -> 1526 | I31: =+'Flujo Redco Brasil'!H34 -> 0 | J31: =+'Flujo Redco Brasil'!I34 -> 0 | K31: =+'Flujo Redco Brasil'!J34 -> 0 | ... O31: =+'Flujo Redco Brasil'!N34 -> 0 | P31: =SUM(D31:O31) -> 11702
B32: Chile | C32: INGRESO CTA.CTE. EERR | D32: =+'Flujo Redco Chile'!C35+'Flujo Redco Chile'!C36+'Flujo Redco Chile'!C37 -> 134087.98 | E32: =+'Flujo Redco Chile'!D35+'Flujo Redco Chile'!D36+'Flujo Redco Chile'!D37 -> 0 | F32: =+'Flujo Redco Chile'!E35+'Flujo Redco Chile'!E36+'Flujo Redco Chile'!E37 -> 19816.29 | G32: =+'Flujo Redco Chile'!F35+'Flujo Redco Chile'!F36+'Flujo Redco Chile'!F37 -> 48275.16 | H32: =+'Flujo Redco Chile'!G35+'Flujo Redco Chile'!G36+'Flujo Redco Chile'!G37 -> 32259.954 | I32: =+'Flujo Redco Chile'!H35+'Flujo Redco Chile'!H36+'Flujo Redco Chile'!H37 -> 0 | J32: =+'Flujo Redco Chile'!I35+'Flujo Redco Chile'!I36+'Flujo Redco Chile'!I37 -> 46679.406 | K32: =+'Flujo Redco Chile'!J35+'Flujo Redco Chile'!J36+'Flujo Redco Chile'!J37 -> 459872.82 | ... M32: =+'Flujo Redco Chile'!L35+'Flujo Redco Chile'!L36+'Flujo Redco Chile'!L37 -> 154199.14 | N32: =+'Flujo Redco Chile'!M35+'Flujo Redco Chile'!M36+'Flujo Redco Chile'!M37+'Flujo Redco Chile'!M33 -> 147113.87 | O32: =+'Flujo Redco Chile'!N35+'Flujo Redco Chile'!N36+'Flujo Redco Chile'!N37+'Flujo Redco Chile'!N33 -> 395829.61 | P32: =SUM(D32:O32) -> 1438134.2
B33: Chile | C33: CTA.CTE. EERR (REDTEC) | D33: =+'Flujo Redco Chile'!C32 -> 57052.603 | E33: =+'Flujo Redco Chile'!D32 -> 113524.2 | F33: =+'Flujo Redco Chile'!E32 -> 0 | G33: =+'Flujo Redco Chile'!F32 -> 146563.3 | H33: =+'Flujo Redco Chile'!G32 -> 9291.9936 | I33: =+'Flujo Redco Chile'!H32 -> 0 | J33: =+'Flujo Redco Chile'!I32 -> 0 | K33: =+'Flujo Redco Chile'!J32 -> 0 | ... O33: =+'Flujo Redco Chile'!N32 -> 0 | P33: =SUM(D33:O33) -> 353646.46
B34: Perú | C34: CTA.CTE. EERR (REDTEC) | D34: =+'Flujo Redco Perú'!C36 -> 0 | E34: =+'Flujo Redco Perú'!D36 -> 0 | F34: =+'Flujo Redco Perú'!E36 -> 51893 | G34: =+'Flujo Redco Perú'!F36 -> 0 | H34: =+'Flujo Redco Perú'!G36 -> 0 | I34: =+'Flujo Redco Perú'!H36 -> 0 | J34: =+'Flujo Redco Perú'!I36 -> 0 | K34: =+'Flujo Redco Perú'!J36 -> 0 | ... O34: =+'Flujo Redco Perú'!N36 -> 0 | P34: =SUM(D34:O34) -> 51893
B35: Chile | C35: RESCATE FFMM BANCHILE | D35: =+'Flujo Redco Chile'!C40 -> 0 | E35: =+'Flujo Redco Chile'!D40 -> 0 | F35: =+'Flujo Redco Chile'!E40 -> 0 | G35: =+'Flujo Redco Chile'!F40 -> 0 | H35: =+'Flujo Redco Chile'!G40 -> 0 | I35: =+'Flujo Redco Chile'!H40 -> 89784.033 | J35: =+'Flujo Redco Chile'!I40 -> 0 | K35: =+'Flujo Redco Chile'!J40 -> 0 | ... O35: =+'Flujo Redco Chile'!N40 -> 0 | P35: =SUM(D35:O35) -> 171414.93
B36: Otros | C36: INGRESO CTA.CTE. EERR | D36: =+'Flujo Redco BVI'!C36 -> 0 | E36: =+'Flujo Redco BVI'!D36 -> 0 | F36: =+'Flujo Redco BVI'!E36 -> 0 | G36: =+'Flujo Redco BVI'!F36 -> 0 | H36: =+'Flujo Redco BVI'!G36 -> 415568 | I36: =+'Flujo Redco BVI'!H36 -> 0 | J36: =+'Flujo Redco BVI'!I36 -> 0 | K36: =+'Flujo Redco BVI'!J36 -> 0 | ... O36: =+'Flujo Redco BVI'!N36 -> 349514 | P36: =SUM(D36:O36) -> 1154049
B37: TOTAL | C37: SUMA OTROS INGRESOS | D37: =SUM(D28:D36) -> 279571.81 | E37: =SUM(E28:E36) -> 245598.41 | F37: =SUM(F28:F36) -> 172251.12 | G37: =SUM(G28:G36) -> 292209.81 | H37: =SUM(H28:H36) -> 608384.49 | I37: =SUM(I28:I36) -> 179700.25 | J37: =SUM(J28:J36) -> 253201.81 | K37: =SUM(K28:K36) -> 659206.51 | ... P37: =SUM(P28:P36) -> 4665267.2
B39: Chile | C39: EGRESO IVA DEBITO | D39: =+'Flujo Redco Chile'!C44*-1 -> -34979.334 | E39: =+'Flujo Redco Chile'!D44*-1 -> -63266.452 | F39: =+'Flujo Redco Chile'!E44*-1 -> -11946.348 | G39: =+'Flujo Redco Chile'!F44*-1 -> -31666.326 | H39: =+'Flujo Redco Chile'!G44*-1 -> -65886.451 | I39: =+'Flujo Redco Chile'!H44*-1 -> -41468.266 | J39: =+'Flujo Redco Chile'!I44*-1 -> -8884.088 | K39: =+'Flujo Redco Chile'!J44*-1 -> -86387.474 | ... O39: =+'Flujo Redco Chile'!N44*-1 -> -24253.626 | P39: =SUM(D39:O39) -> -489115.1
B40: Chile | C40: EGRESO CREDITOS | D40: =(+'Flujo Redco Chile'!C45+'Flujo Redco Chile'!C46+'Flujo Redco Chile'!C47)*-1 -> -27599.535 | E40: =(+'Flujo Redco Chile'!D45+'Flujo Redco Chile'!D46+'Flujo Redco Chile'!D47)*-1 -> -38631.281 | F40: =(+'Flujo Redco Chile'!E45+'Flujo Redco Chile'!E46+'Flujo Redco Chile'!E47)*-1 -> -30686.726 | G40: =(+'Flujo Redco Chile'!F45+'Flujo Redco Chile'!F46+'Flujo Redco Chile'!F47)*-1 -> -31866.891 | H40: =(+'Flujo Redco Chile'!G45+'Flujo Redco Chile'!G46+'Flujo Redco Chile'!G47)*-1 -> -32660.93 | I40: =(+'Flujo Redco Chile'!H45+'Flujo Redco Chile'!H46+'Flujo Redco Chile'!H47)*-1 -> -27706.253 | J40: =(+'Flujo Redco Chile'!I45+'Flujo Redco Chile'!I46+'Flujo Redco Chile'!I47)*-1 -> -31882.783 | K40: =(+'Flujo Redco Chile'!J45+'Flujo Redco Chile'!J46+'Flujo Redco Chile'!J47)*-1 -> -30717.742 | ... O40: =(+'Flujo Redco Chile'!N45+'Flujo Redco Chile'!N46+'Flujo Redco Chile'!N47)*-1 -> -30784.118 | P40: =SUM(D40:O40) -> -373754.78
B41: Chile | C41: CTA.CTE. EERR | D41: =(+'Flujo Redco Chile'!C52+'Flujo Redco Chile'!C54+'Flujo Redco Chile'!C55+'Flujo Redco Chile'!C56+'Flujo Redco Chile'!C57)*-1 -> -21128.81 | E41: =(+'Flujo Redco Chile'!D52+'Flujo Redco Chile'!D54+'Flujo Redco Chile'!D55+'Flujo Redco Chile'!D56+'Flujo Redco Chile'!D57)*-1 -> -5335.2929 | F41: =(+'Flujo Redco Chile'!E52+'Flujo Redco Chile'!E54+'Flujo Redco Chile'!E55+'Flujo Redco Chile'!E56+'Flujo Redco Chile'!E57)*-1 -> -20323.139 | G41: =(+'Flujo Redco Chile'!F52+'Flujo Redco Chile'!F54+'Flujo Redco Chile'!F55+'Flujo Redco Chile'!F56+'Flujo Redco Chile'!F57)*-1 -> -68310.75 | H41: =(+'Flujo Redco Chile'!G52+'Flujo Redco Chile'!G54+'Flujo Redco Chile'!G55+'Flujo Redco Chile'!G56+'Flujo Redco Chile'!G57)*-1 -> -25408.954 | I41: =(+'Flujo Redco Chile'!H52+'Flujo Redco Chile'!H54+'Flujo Redco Chile'!H55+'Flujo Redco Chile'!H56+'Flujo Redco Chile'!H57)*-1 -> -19313.305 | J41: =(+'Flujo Redco Chile'!I52+'Flujo Redco Chile'!I54+'Flujo Redco Chile'!I55+'Flujo Redco Chile'!I56+'Flujo Redco Chile'!I57)*-1 -> -66329.145 | K41: =(+'Flujo Redco Chile'!J52+'Flujo Redco Chile'!J54+'Flujo Redco Chile'!J55+'Flujo Redco Chile'!J56+'Flujo Redco Chile'!J57)*-1 -> -7645.6223 | ... O41: =(+'Flujo Redco Chile'!N52+'Flujo Redco Chile'!N54+'Flujo Redco Chile'!N55+'Flujo Redco Chile'!N56+'Flujo Redco Chile'!N57)*-1 -> -47905.397 | P41: =SUM(D41:O41) -> -289705.24
B42: Chile | C42: CTA.CTE. EERR (REDTEC) | D42: =+'Flujo Redco Chile'!C53*-1 -> -24259.657 | E42: =+'Flujo Redco Chile'!D53*-1 -> -113524.2 | F42: =+'Flujo Redco Chile'!E53*-1 -> -57052.603 | G42: =+'Flujo Redco Chile'!F53*-1 -> -140964.71 | H42: =+'Flujo Redco Chile'!G53*-1 -> -9291.9936 | I42: =+'Flujo Redco Chile'!H53*-1 -> 0 | J42: =+'Flujo Redco Chile'!I53*-1 -> 0 | K42: =+'Flujo Redco Chile'!J53*-1 -> 0 | ... O42: =+'Flujo Redco Chile'!N53*-1 -> -388.07725 | P42: =SUM(D42:O42) -> -372695.6
B43: Perú | C43: EGRESO IVA DEBITO | D43: =+'Flujo Redco Perú'!C44*-1 -> -42494 | E43: =+'Flujo Redco Perú'!D44*-1 -> 0 | F43: =+'Flujo Redco Perú'!E44*-1 -> -5448 | G43: =+'Flujo Redco Perú'!F44*-1 -> -1998 | H43: =+'Flujo Redco Perú'!G44*-1 -> -49989 | I43: =+'Flujo Redco Perú'!H44*-1 -> -41625 | J43: =+'Flujo Redco Perú'!I44*-1 -> -37651 | K43: =+'Flujo Redco Perú'!J44*-1 -> -102790 | ... O43: =+'Flujo Redco Perú'!N44*-1 -> -36493 | P43: =SUM(D43:O43) -> -409309
B44: Perú | C44: CTA.CTE. EERR | D44: =+'Flujo Redco Perú'!C54*-1 -> 0 | E44: =+'Flujo Redco Perú'!D54*-1 -> 0 | F44: =+'Flujo Redco Perú'!E54*-1 -> -14000 | G44: =+'Flujo Redco Perú'!F54*-1 -> 0 | H44: =+'Flujo Redco Perú'!G54*-1 -> 0 | I44: =+'Flujo Redco Perú'!H54*-1 -> -14000 | J44: =+'Flujo Redco Perú'!I54*-1 -> 0 | K44: =+'Flujo Redco Perú'!J54*-1 -> -472152 | ... O44: =+'Flujo Redco Perú'!N54*-1 -> -100000 | P44: =SUM(D44:O44) -> -928209
B45: Brasil | C45: EGRESO IVA DEBITO | D45: =+'Flujo Redco Brasil'!C37*-1 -> -13957 | E45: =+'Flujo Redco Brasil'!D37*-1 -> -15243 | F45: =+'Flujo Redco Brasil'!E37*-1 -> -7945 | G45: =+'Flujo Redco Brasil'!F37*-1 -> -26398 | H45: =+'Flujo Redco Brasil'!G37*-1 -> -9411 | I45: =+'Flujo Redco Brasil'!H37*-1 -> -12454 | J45: =+'Flujo Redco Brasil'!I37*-1 -> -18530 | K45: =+'Flujo Redco Brasil'!J37*-1 -> -27561 | ... O45: =+'Flujo Redco Brasil'!N37*-1 -> -95607 | P45: =SUM(D45:O45) -> -375161
B46: Brasil | C46: CTA.CTE. EERR | D46: =+'Flujo Redco Brasil'!C43*-1 -> 0 | E46: =+'Flujo Redco Brasil'!D43*-1 -> 0 | F46: =+'Flujo Redco Brasil'!E43*-1 -> 0 | G46: =+'Flujo Redco Brasil'!F43*-1 -> 0 | H46: =+'Flujo Redco Brasil'!G43*-1 -> -133710 | I46: =+'Flujo Redco Brasil'!H43*-1 -> 0 | J46: =+'Flujo Redco Brasil'!I43*-1 -> 0 | K46: =+'Flujo Redco Brasil'!J43*-1 -> 0 | ... O46: =+'Flujo Redco Brasil'!N43*-1 -> 0 | P46: =SUM(D46:O46) -> -411923
B47: USA | C47: CTA.CTE. EERR | D47: =+'Flujo Redco USA'!C46*-1 -> 0 | E47: =+'Flujo Redco USA'!D46*-1 -> 0 | F47: =+'Flujo Redco USA'!E46*-1 -> 0 | G47: =+'Flujo Redco USA'!F46*-1 -> 0 | H47: =+'Flujo Redco USA'!G46*-1 -> -281858 | I47: =+'Flujo Redco USA'!H46*-1 -> 0 | J47: =+'Flujo Redco USA'!I46*-1 -> 0 | K47: =+'Flujo Redco USA'!J46*-1 -> 0 | ... O47: =+'Flujo Redco USA'!N46*-1 -> -349514 | P47: =SUM(D47:O47) -> -742126
B48: USA | C48: EGRESO IVA DEBITO | N48: =+'Flujo Redco USA'!M41*-1 -> -6408 | O48: =+'Flujo Redco USA'!N41*-1 -> 0
B49: TOTAL | C49: SUMA OTROS EGRESOS | D49: =SUM(D39:D48) -> -164418.34 | E49: =SUM(E39:E48) -> -236000.23 | F49: =SUM(F39:F48) -> -147401.82 | G49: =SUM(G39:G48) -> -301204.68 | H49: =SUM(H39:H48) -> -608216.33 | I49: =SUM(I39:I48) -> -156566.82 | J49: =SUM(J39:J48) -> -163277.02 | K49: =SUM(K39:K48) -> -727253.84 | ... P49: =SUM(P39:P48) -> -4391998.7
B51: País | C51: Concepto | D51: 45658 | E51: 45689 | F51: 45717 | G51: 45748 | H51: 45778 | I51: 45809 | J51: 45839 | K51: 45870 | L51: 45901 | M51: 45931 | N51: 45962 | O51: 45992 | P51: Total
B52: Chile | C52: RESULTADO CAJA | D52: =SUM(D20+D28+D30+D32+D33+D35+D39+D41+D42+D40) -> 118395.56 | E52: =SUM(E20+E28+E30+E32+E33+E35+E39+E41+E42+E40) -> 133162.17 | F52: =SUM(F20+F28+F30+F32+F33+F35+F39+F41+F42+F40) -> -69890.423 | G52: =SUM(G20+G28+G30+G32+G33+G35+G39+G41+G42+G40) -> -113200.73 | H52: =SUM(H20+H28+H30+H32+H33+H35+H39+H41+H42+H40) -> -40765.558 | I52: =SUM(I20+I28+I30+I32+I33+I35+I39+I41+I42+I40) -> -48061.672 | J52: =SUM(J20+J28+J30+J32+J33+J35+J39+J41+J42+J40) -> 191766.35 | K52: =SUM(K20+K28+K30+K32+K33+K35+K39+K41+K42+K40) -> 134254.5 | ... O52: =SUM(O20+O28+O30+O32+O33+O35+O39+O41+O42+O40) -> 3229.6803 | P52: =SUM(D52:O52) -> -28973.08 | R52: =+SUM(D52:L52) -> 149134.32
B53: Perú | C53: RESULTADO CAJA | D53: =+D21+D29+D34+D43+D44 -> 3798.15 | E53: =+E21+E29+E34+E43+E44 -> -2643 | F53: =+F21+F29+F34+F43+F44 -> 65135 | G53: =+G21+G29+G34+G43+G44 -> -1064.3 | H53: =+H21+H29+H34+H43+H44 -> -4999 | I53: =+I21+I29+I34+I43+I44 -> 42095 | J53: =+J21+J29+J34+J43+J44 -> 48879 | K53: =+K21+K29+K34+K43+K44 -> -32506 | ... O53: =+O21+O29+O34+O43+O44 -> -25297 | P53: =SUM(D53:O53) -> -55949.79 | R53: =+SUM(D53:L53) -> 79991.85
B54: Brasil | C54: RESULTADO CAJA | D54: =+D22+D31+D45 -> 51910 | E54: =+E22+E31+E45 -> 16991 | F54: =+F22+F31+F45 -> 61952 | G54: =+G22+G31+G45 -> 18807.3 | H54: =+H22+H31+H45+H46 -> -137850 | I54: =+I22+I31+I45+I46 -> -22177 | J54: =+J22+J31+J45+J46 -> -1832 | K54: =+K22+K31+K45+K46 -> 70616 | L54: =+L22+L31+L45+L46 -> 104282 | M54: =+M22+M31+M45+M46 -> 244856 | N54: =+N22+N31+N45+N46 -> -143071 | O54: =+O22+O31+O45+O46 -> 105508.51 | P54: =SUM(D54:O54) -> 369992.81 | R54: =+SUM(D54:L54) -> 162699.3
B55: USA | C55: RESULTADO CAJA | D55: =SUM(D23+D47) -> 150438 | E55: =SUM(E23+E47) -> 241440.21 | F55: =SUM(F23+F47) -> 82798 | G55: =SUM(G23+G47) -> 159302 | H55: =SUM(H23+H47) -> -134434 | I55: =SUM(I23+I47) -> 57618 | J55: =SUM(J23+J47) -> -10017 | K55: =SUM(K23+K47) -> 18985 | ... M55: =SUM(M23+M47) -> -154165 | N55: =SUM(N23+N47+N48) -> -7408 | O55: =SUM(O23+O47) -> -389139 | P55: =SUM(D55:O55) -> 14418.21 | R55: =+SUM(D55:L55) -> 565130.21
B56: Otros | C56: RESULTADO CAJA | D56: =+D24+D36 -> -14044 | E56: =+E24+E36 -> 21682 | F56: =+F24+F36 -> 45478 | G56: =+G24+G36 -> -14380 | H56: =+H24+H36 -> 399568 | I56: =+I24+I36 -> 156951 | J56: =+J24+J36 -> -5684.8 | K56: =+K24+K36 -> 93839.2 | ... O56: =+O24+O36 -> 343829.2 | P56: =SUM(D56:O56) -> 1399151.2 | R56: =+SUM(D56:L56) -> 677724.6
B57: TOTAL | C57: RESULTADO CAJA | D57: =SUM(D52:D56) -> 310497.71 | E57: =SUM(E52:E56) -> 410632.38 | F57: =SUM(F52:F56) -> 185472.58 | G57: =SUM(G52:G56) -> 49464.274 | H57: =SUM(H52:H56) -> 81519.442 | I57: =SUM(I52:I56) -> 186425.33 | J57: =SUM(J52:J56) -> 223111.55 | K57: =SUM(K52:K56) -> 285188.7 | ... O57: =SUM(O52:O56) -> 38131.39 | P57: =SUM(D57:O57) -> 1698639.3 | R57: =SUM(R52:R56) -> 1634680.3
B59: CAJA FINAL | C59: CAJA FINAL | D59: =+D57+T9 -> 564489.87 | E59: =+D59+E57 -> 975122.25 | F59: =+E59+F57 -> 1160594.8 | G59: =+F59+G57 -> 1210059.1 | H59: =+G59+H57 -> 1291578.5 | I59: =+H59+I57 -> 1478003.9 | J59: =+I59+J57 -> 1701115.4 | K59: =+J59+K57 -> 1986304.1 | L59: =+K59+L57 -> 1888672.4 | ... O59: =+N59+O57 -> 1952631.5 | P59: =+O59 -> 1952631.5
B61: País | C61: Concepto | D61: 45658 | E61: 45689 | F61: 45717 | G61: 45748 | H61: 45778 | I61: 45809 | J61: 45839 | K61: 45870 | L61: 45901 | M61: 45931 | N61: 45962 | O61: 45992 | P61: Total | R61: País | S61: Total
B62: Chile | C62: TOTAL CAJA | D62: =+D52+T4 -> 170652.7 | E62: =+D62+E52 -> 303814.87 | F62: =+E62+F52 -> 233924.45 | G62: =+F62+G52 -> 120723.72 | H62: =+G62+H52 -> 79958.162 | I62: =+H62+I52 -> 31896.49 | J62: =+I62+J52 -> 223662.84 | K62: =+J62+K52 -> 357917.35 | L62: =+K62+L52 -> 201391.46 | ... O62: =+N62+O52 -> 23284.057 | P62: =+O62 -> 23284.057 | R62: Otros | S62: =+_xlfn.XLOOKUP(R62,$B$62:$B$66,$O$62:$O$66,0,0,1)/1000 -> 1399.1512
B63: Perú | C63: TOTAL CAJA | D63: =+D53+T5 -> 140565.84 | E63: =+D63+E53 -> 137922.84 | F63: =+E63+F53 -> 203057.84 | G63: =+F63+G53 -> 201993.54 | H63: =+G63+H53 -> 196994.54 | I63: =+H63+I53 -> 239089.54 | J63: =+I63+J53 -> 287968.54 | K63: =+J63+K53 -> 255462.54 | L63: =+K63+L53 -> 216759.54 | ... O63: =+N63+O53 -> 80817.904 | P63: =+O63 -> 80817.904 | R63: Brasil | S63: =+_xlfn.XLOOKUP(R63,$B$62:$B$66,$O$62:$O$66,0,0,1)/1000 -> 389.08814
B64: Brasil | C64: TOTAL CAJA | D64: =+D54+T6 -> 61532.33 | E64: =+D64+E54 -> 78523.33 | F64: =+E64+F54 -> 140475.33 | G64: =+F64+G54 -> 159282.63 | H64: =+G64+H54 -> 21432.63 | I64: =+H64+I54 -> -744.37 | J64: =+I64+J54 -> -2576.37 | K64: =+J64+K54 -> 68039.63 | L64: =+(K64+L54+'Flujo Redco Brasil'!K47) -> 179973.63 | M64: =+L64+M54+'Flujo Redco Brasil'!L47 -> 426650.63 | N64: =+M64+N54 -> 283579.63 | O64: =+N64+O54 -> 389088.14 | P64: =+O64 -> 389088.14 | R64: Perú | S64: =+_xlfn.XLOOKUP(R64,$B$62:$B$66,$O$62:$O$66,0,0,1)/1000 -> 80.817904
B65: USA | C65: TOTAL CAJA | D65: =+D55+T7 -> 205783 | E65: =+D65+E55 -> 447223.21 | F65: =+E65+F55 -> 530021.21 | G65: =+F65+G55 -> 689323.21 | H65: =+G65+H55 -> 554889.21 | I65: =+H65+I55 -> 612507.21 | J65: =+I65+J55 -> 602490.21 | K65: =+J65+K55 -> 621475.21 | L65: =+K65+L55 -> 620475.21 | ... O65: =+N65+O55 -> 69763.21 | P65: =+O65 -> 69763.21 | R65: USA | S65: =+_xlfn.XLOOKUP(R65,$B$62:$B$66,$O$62:$O$66,0,0,1)/1000 -> 69.76321
B66: Otros | C66: TOTAL CAJA | D66: =+D56+T8 -> -14044 | E66: =+D66+E56 -> 7638 | F66: =+E66+F56 -> 53116 | G66: =+F66+G56 -> 38736 | H66: =+G66+H56 -> 438304 | I66: =+H66+I56 -> 595255 | J66: =+I66+J56 -> 589570.2 | K66: =+J66+K56 -> 683409.4 | L66: =+K66+L56 -> 677724.6 | ... O66: =+N66+O56 -> 1399151.2 | P66: =+O66 -> 1399151.2 | R66: Chile | S66: =+_xlfn.XLOOKUP(R66,$B$62:$B$66,$O$62:$O$66,0,0,1)/1000 -> 23.284057
B67: SALDO CAJA | C67: SALDO CAJA | D67: =SUM(D62:D66) -> 564489.87 | E67: =SUM(E62:E66) -> 975122.25 | F67: =SUM(F62:F66) -> 1160594.8 | G67: =SUM(G62:G66) -> 1210059.1 | H67: =SUM(H62:H66) -> 1291578.5 | I67: =SUM(I62:I66) -> 1478003.9 | J67: =SUM(J62:J66) -> 1701115.4 | K67: =SUM(K62:K66) -> 1986304.1 | ... P67: =SUM(P62:P66) -> 1962104.5 | R67: Total | S67: =SUM(S62:S66) -> 1962.1045

Sheet Tabla datos unidades_Sept
L1: 6853202.5 | M1: =+L10-L1 -> 73593.425 | N1: =+M1/L10 -> 0.010624454
J2: =+J17/1000 -> 641.80299 | K2: =+K17/1000 -> 678.99571 | L2: =+L17/1000 -> 666.97613 | M2: =+M17/1000 -> 639.22703 | N2: =+N17/1000 -> 617.98793 | O2: =+O17/1000 -> 842.67783
B3: País | C3: Concepto | D3: 45658 | E3: 45689 | F3: 45717 | G3: 45748 | H3: 45778 | I3: 45809 | J3: 45839 | K3: 45870 | L3: 45901 | M3: 45931 | N3: 45962 | O3: 45992 | P3: Total | R3: País | S3: Concepto | T3: 45658
B4: Chile | C4: INGRESOS OP | D4: =+'Flujo Redco Chile'!C12 -> 362362.73 | E4: =+'Flujo Redco Chile'!D12 -> 547310.62 | F4: =+'Flujo Redco Chile'!E12 -> 389727.46 | G4: =+'Flujo Redco Chile'!F12 -> 237434.48 | H4: =+'Flujo Redco Chile'!G12 -> 272631.08 | I4: =+'Flujo Redco Chile'!H12 -> 277419.07 | J4: =+'Flujo Redco Chile'!I12 -> 475570.75 | K4: =+'Flujo Redco Chile'!J12 -> 151482.74 | ... O4: =+'Flujo Redco Chile'!N12 -> 173207.55 | P4: =SUM(D4:O4) -> 3592126.9 | R4: Chile | S4: SALDO INICIAL | T4: =+'Flujo Redco Chile'!C8 -> 52257.137
B5: Perú | C5: INGRESOS OP | D5: =+'Flujo Redco Perú'!C13 -> 123848 | E5: =+'Flujo Redco Perú'!D13 -> 62454 | F5: =+'Flujo Redco Perú'!E13 -> 105377 | G5: =+'Flujo Redco Perú'!F13 -> 110077 | H5: =+'Flujo Redco Perú'!G13 -> 142610 | I5: =+'Flujo Redco Perú'!H13 -> 229588 | J5: =+'Flujo Redco Perú'!I13 -> 251702 | K5: =+'Flujo Redco Perú'!J13 -> 641573 | ... O5: =+'Flujo Redco Perú'!N13 -> 269432 | P5: =SUM(D5:O5) -> 2417353 | R5: Perú | S5: SALDO INICIAL | T5: =+'Flujo Redco Perú'!C9 -> 136767.69
B6: Brasil | C6: INGRESOS OP | D6: =+'Flujo Redco Brasil'!C14 -> 80502 | E6: =+'Flujo Redco Brasil'!D14 -> 59683 | F6: =+'Flujo Redco Brasil'!E14 -> 96322 | G6: =+'Flujo Redco Brasil'!F14 -> 97209.7 | H6: =+'Flujo Redco Brasil'!G14 -> 37074 | I6: =+'Flujo Redco Brasil'!H14 -> 66563 | J6: =+'Flujo Redco Brasil'!I14 -> 47717 | K6: =+'Flujo Redco Brasil'!J14 -> 119652 | ... O6: =+'Flujo Redco Brasil'!N14 -> 224116.51 | P6: =SUM(D6:O6) -> 1597092.2 | R6: Brasil | S6: SALDO INICIAL | T6: =+'Flujo Redco Brasil'!C9 -> 9622.33
B7: USA | C7: INGRESOS OP | D7: =+'Flujo Redco USA'!C13 -> 150453 | E7: =+'Flujo Redco USA'!D13 -> 243465.21 | F7: =+'Flujo Redco USA'!E13 -> 141526 | G7: =+'Flujo Redco USA'!F13 -> 169200 | H7: =+'Flujo Redco USA'!G13 -> 195090 | I7: =+'Flujo Redco USA'!H13 -> 61796 | J7: =+'Flujo Redco USA'!I13 -> 0 | K7: =+'Flujo Redco USA'!J13 -> 20000 | ... O7: =+'Flujo Redco USA'!N13 -> 178785 | P7: =SUM(D7:O7) -> 1205315.2 | R7: USA | S7: SALDO INICIAL | T7: =+'Flujo Redco USA'!C9 -> 55345
B8: Otros | C8: INGRESOS OP | D8: =+'Flujo Redco BVI'!C13 -> 0 | E8: =+'Flujo Redco BVI'!D13 -> 21682 | F8: =+'Flujo Redco BVI'!E13 -> 45478 | G8: =+'Flujo Redco BVI'!F13 -> 0 | H8: =+'Flujo Redco BVI'!G13 -> 0 | I8: =+'Flujo Redco BVI'!H13 -> 172045 | J8: =+'Flujo Redco BVI'!I13 -> 0 | K8: =+'Flujo Redco BVI'!J13 -> 99524 | ... O8: =+'Flujo Redco BVI'!N13 -> 0 | P8: =SUM(D8:O8) -> 338729 | Q8: 415000 | R8: BVI | S8: SALDO INICIAL | T8: =+'Flujo Redco BVI'!S13 -> 0
B9: TOTAL | C9: INGRESOS OP | D9: =SUM(D4:D8) -> 717165.73 | E9: =SUM(E4:E8) -> 934594.83 | F9: =SUM(F4:F8) -> 778430.46 | G9: =SUM(G4:G8) -> 613921.18 | H9: =SUM(H4:H8) -> 647405.08 | I9: =SUM(I4:I8) -> 807411.07 | J9: =SUM(J4:J8) -> 774989.75 | K9: =SUM(K4:K8) -> 1032231.7 | ... P9: =SUM(P4:P8) -> 9150616.3 | R9: CAJA FINAL | S9: CAJA FINAL | T9: =SUM(T4:T8) -> 253992.16
C10: INGRESOS OP ACUM | D10: =+SUM($D$9:D9) -> 717165.73 | E10: =+SUM($D$9:E9) -> 1651760.6 | F10: =+SUM($D$9:F9) -> 2430191 | G10: =+SUM($D$9:G9) -> 3044112.2 | H10: =+SUM($D$9:H9) -> 3691517.3 | I10: =+SUM($D$9:I9) -> 4498928.4 | J10: =+SUM($D$9:J9) -> 5273918.1 | K10: =+SUM($D$9:K9) -> 6306149.8 | ... O10: =+SUM($D$9:O9) -> 9150616.3
B11: País | C11: Concepto | D11: 45658 | E11: 45689 | F11: 45717 | G11: 45748 | H11: 45778 | I11: 45809 | J11: 45839 | K11: 45870 | L11: 45901 | M11: 45931 | N11: 45962 | O11: 45992 | P11: Total
B12: Chile | C12: COSTOS OP | D12: =+'Flujo Redco Chile'!C18+'Flujo Redco Chile'!C23+'Flujo Redco Chile'!C25 -> 397276.65 | E12: =+'Flujo Redco Chile'!D18+'Flujo Redco Chile'!D23+'Flujo Redco Chile'!D25 -> 422126.64 | F12: =+'Flujo Redco Chile'!E18+'Flujo Redco Chile'!E23+'Flujo Redco Chile'!E25 -> 439899.18 | G12: =+'Flujo Redco Chile'!F18+'Flujo Redco Chile'!F23+'Flujo Redco Chile'!F25 -> 341507.35 | H12: =+'Flujo Redco Chile'!G18+'Flujo Redco Chile'!G23+'Flujo Redco Chile'!G25 -> 340134.8 | I12: =+'Flujo Redco Chile'!H18+'Flujo Redco Chile'!H23+'Flujo Redco Chile'!H25 -> 380566.17 | J12: =+'Flujo Redco Chile'!I18+'Flujo Redco Chile'!I23+'Flujo Redco Chile'!I25 -> 395727.19 | K12: =+'Flujo Redco Chile'!J18+'Flujo Redco Chile'!J23+'Flujo Redco Chile'!J25 -> 425248.91 | L12: =+'Flujo Redco Chile'!K18+'Flujo Redco Chile'!K23+'Flujo Redco Chile'!K25 -> 455871.33 | M12: 425000 | N12: 425000 | O12: 425000 | P12: =SUM(D12:O12) -> 4873358.2
B13: Perú | C13: COSTOS OP | D13: =+'Flujo Redco Perú'!C19+'Flujo Redco Perú'!C26+'Flujo Redco Perú'!C28 -> 89462.85 | E13: =+'Flujo Redco Perú'!D19+'Flujo Redco Perú'!D26+'Flujo Redco Perú'!D28 -> 81597 | F13: =+'Flujo Redco Perú'!E19+'Flujo Redco Perú'!E26+'Flujo Redco Perú'!E28 -> 92755 | G13: =+'Flujo Redco Perú'!F19+'Flujo Redco Perú'!F26+'Flujo Redco Perú'!F28 -> 137672.3 | H13: =+'Flujo Redco Perú'!G19+'Flujo Redco Perú'!G26+'Flujo Redco Perú'!G28 -> 128924 | I13: =+'Flujo Redco Perú'!H19+'Flujo Redco Perú'!H26+'Flujo Redco Perú'!H28 -> 167995 | J13: =+'Flujo Redco Perú'!I19+'Flujo Redco Perú'!I26+'Flujo Redco Perú'!I28 -> 199355 | K13: =+'Flujo Redco Perú'!J19+'Flujo Redco Perú'!J26+'Flujo Redco Perú'!J28 -> 225572 | L13: =+'Flujo Redco Perú'!K19+'Flujo Redco Perú'!K26+'Flujo Redco Perú'!K28 -> 127097 | M13: 106082.23 | N13: 138332.13 | O13: 170582.03 | P13: =SUM(D13:O13) -> 1665426.5
B14: Brasil | C14: COSTOS OP | D14: =+'Flujo Redco Brasil'!C20+'Flujo Redco Brasil'!C25+'Flujo Redco Brasil'!C27 -> 21023 | E14: =+'Flujo Redco Brasil'!D20+'Flujo Redco Brasil'!D25+'Flujo Redco Brasil'!D27 -> 27812 | F14: =+'Flujo Redco Brasil'!E20+'Flujo Redco Brasil'!E25+'Flujo Redco Brasil'!E27 -> 26425 | G14: =+'Flujo Redco Brasil'!F20+'Flujo Redco Brasil'!F25+'Flujo Redco Brasil'!F27 -> 52004.4 | H14: =+'Flujo Redco Brasil'!G20+'Flujo Redco Brasil'!G25+'Flujo Redco Brasil'!G27 -> 33329 | I14: =+'Flujo Redco Brasil'!H20+'Flujo Redco Brasil'!H25+'Flujo Redco Brasil'!H27 -> 76286 | J14: =+'Flujo Redco Brasil'!I20+'Flujo Redco Brasil'!I25+'Flujo Redco Brasil'!I27 -> 31019 | K14: =+'Flujo Redco Brasil'!J20+'Flujo Redco Brasil'!J25+'Flujo Redco Brasil'!J27 -> 21475 | ... O14: =+'Flujo Redco Brasil'!N20+'Flujo Redco Brasil'!N25+'Flujo Redco Brasil'!N27 -> 23001 | P14: =SUM(D14:O14) -> 451717.4
B15: USA | C15: COSTOS OP | D15: =+'Flujo Redco USA'!C19+'Flujo Redco USA'!C27+'Flujo Redco USA'!C29 -> 15 | E15: =+'Flujo Redco USA'!D19+'Flujo Redco USA'!D27+'Flujo Redco USA'!D29 -> 2025 | F15: =+'Flujo Redco USA'!E19+'Flujo Redco USA'!E27+'Flujo Redco USA'!E29 -> 58728 | G15: =+'Flujo Redco USA'!F19+'Flujo Redco USA'!F27+'Flujo Redco USA'!F29 -> 9898 | H15: =+'Flujo Redco USA'!G19+'Flujo Redco USA'!G27+'Flujo Redco USA'!G29 -> 47666 | I15: =+'Flujo Redco USA'!H19+'Flujo Redco USA'!H27+'Flujo Redco USA'!H29 -> 4178 | J15: =+'Flujo Redco USA'!I19+'Flujo Redco USA'!I27+'Flujo Redco USA'!I29 -> 10017 | K15: =+'Flujo Redco USA'!J19+'Flujo Redco USA'!J27+'Flujo Redco USA'!J29 -> 1015 | ... O15: =+'Flujo Redco USA'!N19+'Flujo Redco USA'!N27+'Flujo Redco USA'!N29 -> 218410 | P15: =SUM(D15:O15) -> 442363
B16: Otros | C16: COSTOS OP | D16: =+'Flujo Redco BVI'!C19+'Flujo Redco BVI'!C27+'Flujo Redco BVI'!C29 -> 14044 | E16: =+'Flujo Redco BVI'!D19+'Flujo Redco BVI'!D27+'Flujo Redco BVI'!D29 -> 0 | F16: =+'Flujo Redco BVI'!E19+'Flujo Redco BVI'!E27+'Flujo Redco BVI'!E29 -> 0 | G16: =+'Flujo Redco BVI'!F19+'Flujo Redco BVI'!F27+'Flujo Redco BVI'!F29 -> 14380 | H16: =+'Flujo Redco BVI'!G19+'Flujo Redco BVI'!G27+'Flujo Redco BVI'!G29 -> 16000 | I16: =+'Flujo Redco BVI'!H19+'Flujo Redco BVI'!H27+'Flujo Redco BVI'!H29 -> 15094 | J16: =+'Flujo Redco BVI'!I19+'Flujo Redco BVI'!I27+'Flujo Redco BVI'!I29 -> 5684.8 | K16: =+'Flujo Redco BVI'!J19+'Flujo Redco BVI'!J27+'Flujo Redco BVI'!J29 -> 5684.8 | ... O16: =+'Flujo Redco BVI'!N19+'Flujo Redco BVI'!N27+'Flujo Redco BVI'!N29 -> 5684.8 | P16: =SUM(D16:O16) -> 93626.8
B17: TOTAL | C17: COSTOS OP | D17: =SUM(D12:D16) -> 521821.5 | E17: =SUM(E12:E16) -> 533560.64 | F17: =SUM(F12:F16) -> 617807.18 | G17: =SUM(G12:G16) -> 555462.05 | H17: =SUM(H12:H16) -> 566053.8 | I17: =SUM(I12:I16) -> 644119.17 | J17: =SUM(J12:J16) -> 641802.99 | K17: =SUM(K12:K16) -> 678995.71 | ... O17: =SUM(O12:O16) -> 842677.83 | P17: =SUM(D17:O17) -> 7526491.9
C18: COSTOS OP ACUM | D18: =+SUM($D$17:D17) -> 521821.5 | E18: =+SUM($D$17:E17) -> 1055382.1 | F18: =+SUM($D$17:F17) -> 1673189.3 | G18: =+SUM($D$17:G17) -> 2228651.4 | H18: =+SUM($D$17:H17) -> 2794705.2 | I18: =+SUM($D$17:I17) -> 3438824.3 | J18: =+SUM($D$17:J17) -> 4080627.3 | K18: =+SUM($D$17:K17) -> 4759623 | ... O18: =+SUM($D$17:O17) -> 7526491.9
B19: País | C19: Concepto | D19: 45658 | E19: 45689 | F19: 45717 | G19: 45748 | H19: 45778 | I19: 45809 | J19: 45839 | K19: 45870 | L19: 45901 | M19: 45931 | N19: 45962 | O19: 45992 | P19: Total
B20: Chile | C20: RESULTADO OP. | D20: =+D4-D12 -> -34913.914 | E20: =+E4-E12 -> 125183.98 | F20: =+F4-F12 -> -50171.722 | G20: =+G4-G12 -> -104072.86 | H20: =+H4-H12 -> -67503.719 | I20: =+I4-I12 -> -103147.1 | J20: =+J4-J12 -> 79843.563 | K20: =+K4-K12 -> -273766.17 | ... O20: =+O4-O12 -> -251792.45 | P20: =SUM(D20:O20) -> -1281231.3
B21: Perú | C21: RESULTADO OP. | D21: =+D5-D13 -> 34385.15 | E21: =+E5-E13 -> -19143 | F21: =+F5-F13 -> 12622 | G21: =+G5-G13 -> -27595.3 | H21: =+H5-H13 -> 13686 | I21: =+I5-I13 -> 61593 | J21: =+J5-J13 -> 52347 | K21: =+K5-K13 -> 416001 | ... O21: =+O5-O13 -> 98849.97 | P21: =SUM(D21:O21) -> 751926.46
B22: Brasil | C22: RESULTADO OP. | D22: =+D6-D14 -> 59479 | E22: =+E6-E14 -> 31871 | F22: =+F6-F14 -> 69897 | G22: =+G6-G14 -> 45205.3 | H22: =+H6-H14 -> 3745 | I22: =+I6-I14 -> -9723 | J22: =+J6-J14 -> 16698 | K22: =+K6-K14 -> 98177 | ... O22: =+O6-O14 -> 201115.51 | P22: =SUM(D22:O22) -> 1145374.8
B23: USA | C23: RESULTADO OP. | D23: =+D7-D15 -> 150438 | E23: =+E7-E15 -> 241440.21 | F23: =+F7-F15 -> 82798 | G23: =+G7-G15 -> 159302 | H23: =+H7-H15 -> 147424 | I23: =+I7-I15 -> 57618 | J23: =+J7-J15 -> -10017 | K23: =+K7-K15 -> 18985 | ... O23: =+O7-O15 -> -39625 | P23: =SUM(D23:O23) -> 762952.21
B24: Otros | C24: RESULTADO OP. | D24: =+D8-D16 -> -14044 | E24: =+E8-E16 -> 21682 | F24: =+F8-F16 -> 45478 | G24: =+G8-G16 -> -14380 | H24: =+H8-H16 -> -16000 | I24: =+I8-I16 -> 156951 | J24: =+J8-J16 -> -5684.8 | K24: =+K8-K16 -> 93839.2 | ... O24: =+O8-O16 -> -5684.8 | P24: =SUM(D24:O24) -> 245102.2
B25: TOTAL | C25: RESULTADO OP. | D25: =SUM(D20:D24) -> 195344.24 | E25: =SUM(E20:E24) -> 401034.19 | F25: =SUM(F20:F24) -> 160623.28 | G25: =SUM(G20:G24) -> 58459.138 | H25: =SUM(H20:H24) -> 81351.281 | I25: =SUM(I20:I24) -> 163291.9 | J25: =SUM(J20:J24) -> 133186.76 | K25: =SUM(K20:K24) -> 353236.03 | ... P25: =SUM(P20:P24) -> 1624124.4
D26: =+SUM($D$25:D25) -> 195344.24 | E26: =+SUM($D$25:E25) -> 596378.43 | F26: =+SUM($D$25:F25) -> 757001.71 | G26: =+SUM($D$25:G25) -> 815460.84 | H26: =+SUM($D$25:H25) -> 896812.13 | I26: =+SUM($D$25:I25) -> 1060104 | J26: =+SUM($D$25:J25) -> 1193290.8 | K26: =+SUM($D$25:K25) -> 1546526.8 | L26: =+SUM($D$25:L25) -> 1500196.7 | M26: =+L26/L10 -> 0.21657874
B27: País | C27: Concepto | D27: 45658 | E27: 45689 | F27: 45717 | G27: 45748 | H27: 45778 | I27: 45809 | J27: 45839 | K27: 45870 | L27: 45901 | M27: 45931 | N27: 45962 | O27: 45992 | P27: Total
B28: Chile | C28: INGRESO IVA DEBITO | D28: =+'Flujo Redco Chile'!C31 -> 69432.94 | E28: =+'Flujo Redco Chile'!D31 -> 104811.9 | F28: =+'Flujo Redco Chile'!E31 -> 75208.024 | G28: =+'Flujo Redco Chile'!F31 -> 47094.724 | H28: =+'Flujo Redco Chile'!G31 -> 62773.513 | I28: =+'Flujo Redco Chile'!H31+'Flujo Redco Chile'!H34 -> 53789.215 | J28: =+'Flujo Redco Chile'!I31 -> 103658.78 | K28: =+'Flujo Redco Chile'!J31 -> 35825.605 | L28: =+'Flujo Redco Chile'!K31 -> 57280.832 | M28: =+'Flujo Redco Chile'!L31 -> 32498.942 | N28: =+'Flujo Redco Chile'!M31 -> 37753.16 | O28: =+'Flujo Redco Chile'!N31 -> 32909.433 | P28: =SUM(D28:O28) -> 713037.07
B29: Perú | C29: INGRESO IVA DEBITO | D29: =+'Flujo Redco Perú'!C35 -> 11907 | E29: =+'Flujo Redco Perú'!D35 -> 16500 | F29: =+'Flujo Redco Perú'!E35 -> 20068 | G29: =+'Flujo Redco Perú'!F35 -> 28529 | H29: =+'Flujo Redco Perú'!G35 -> 31304 | I29: =+'Flujo Redco Perú'!H35 -> 36127 | J29: =+'Flujo Redco Perú'!I35 -> 34183 | K29: =+'Flujo Redco Perú'!J35 -> 126435 | ... O29: =+'Flujo Redco Perú'!N35 -> 75885 | P29: =SUM(D29:O29) -> 544185
B30: Chile | C30: OTROS INGRESOS | D30: =+'Flujo Redco Chile'!C38+'Flujo Redco Chile'!C39+'Flujo Redco Chile'!E42+'Flujo Redco Chile'!C34 -> 703.28541 | E30: =+'Flujo Redco Chile'!D38+'Flujo Redco Chile'!D39+'Flujo Redco Chile'!D34 -> 10399.317 | F30: =+'Flujo Redco Chile'!E38+'Flujo Redco Chile'!E39+'Flujo Redco Chile'!E34 -> 5265.8026 | G30: =+'Flujo Redco Chile'!F38+'Flujo Redco Chile'!F39+'Flujo Redco Chile'!F34 -> 21747.626 | H30: =+'Flujo Redco Chile'!G38+'Flujo Redco Chile'!G39+'Flujo Redco Chile'!G34 -> 55661.029 | I30: =+'Flujo Redco Chile'!H38+'Flujo Redco Chile'!H39+'Flujo Redco Chile'!H34+'Flujo Redco Chile'!H40 -> 89784.033 | J30: =+'Flujo Redco Chile'!I38+'Flujo Redco Chile'!I39+'Flujo Redco Chile'!I34 -> 68680.616 | K30: =+'Flujo Redco Chile'!J38+'Flujo Redco Chile'!J39+'Flujo Redco Chile'!J34 -> 37073.082 | L30: =+'Flujo Redco Chile'!K38+'Flujo Redco Chile'!K39+'Flujo Redco Chile'!K34 -> 4069.9474 | M30: =+'Flujo Redco Chile'!L38+'Flujo Redco Chile'!L39 -> 13.927039 | N30: =+'Flujo Redco Chile'!M38+'Flujo Redco Chile'!M39 -> 415.80687 | O30: =+'Flujo Redco Chile'!N38+'Flujo Redco Chile'!N39 -> 119.83584 | P30: =SUM(D30:O30) -> 293934.31
B31: Brasil | C31: OTROS INGRESOS | D31: =+'Flujo Redco Brasil'!C34 -> 6388 | E31: =+'Flujo Redco Brasil'!D34 -> 363 | F31: =+'Flujo Redco Brasil'!E34 -> 0 | G31: =+'Flujo Redco Brasil'!F34 -> 0 | H31: =+'Flujo Redco Brasil'!G34 -> 1526 | I31: =+'Flujo Redco Brasil'!H34 -> 0 | J31: =+'Flujo Redco Brasil'!I34 -> 0 | K31: =+'Flujo Redco Brasil'!J34 -> 0 | ... O31: =+'Flujo Redco Brasil'!N34 -> 0 | P31: =SUM(D31:O31) -> 11702
B32: Chile | C32: INGRESO CTA.CTE. EERR | D32: =+'Flujo Redco Chile'!C35+'Flujo Redco Chile'!C36+'Flujo Redco Chile'!C37 -> 134087.98 | E32: =+'Flujo Redco Chile'!D35+'Flujo Redco Chile'!D36+'Flujo Redco Chile'!D37 -> 0 | F32: =+'Flujo Redco Chile'!E35+'Flujo Redco Chile'!E36+'Flujo Redco Chile'!E37 -> 19816.29 | G32: =+'Flujo Redco Chile'!F35+'Flujo Redco Chile'!F36+'Flujo Redco Chile'!F37 -> 48275.16 | H32: =+'Flujo Redco Chile'!G35+'Flujo Redco Chile'!G36+'Flujo Redco Chile'!G37 -> 32259.954 | I32: =+'Flujo Redco Chile'!H35+'Flujo Redco Chile'!H36+'Flujo Redco Chile'!H37 -> 0 | J32: =+'Flujo Redco Chile'!I35+'Flujo Redco Chile'!I36+'Flujo Redco Chile'!I37 -> 46679.406 | K32: =+'Flujo Redco Chile'!J35+'Flujo Redco Chile'!J36+'Flujo Redco Chile'!J37 -> 459872.82 | ... O32: =+'Flujo Redco Chile'!N35+'Flujo Redco Chile'!N36+'Flujo Redco Chile'!N37 -> 390966.74 | P32: =SUM(D32:O32) -> 1406447.3
B33: Chile | C33: CTA.CTE. EERR (REDTEC) | D33: =+'Flujo Redco Chile'!C32 -> 57052.603 | E33: =+'Flujo Redco Chile'!D32 -> 113524.2 | F33: =+'Flujo Redco Chile'!E32 -> 0 | G33: =+'Flujo Redco Chile'!F32 -> 146563.3 | H33: =+'Flujo Redco Chile'!G32 -> 9291.9936 | I33: =+'Flujo Redco Chile'!H32 -> 0 | J33: =+'Flujo Redco Chile'!I32 -> 0 | K33: =+'Flujo Redco Chile'!J32 -> 0 | ... O33: =+'Flujo Redco Chile'!N32 -> 0 | P33: =SUM(D33:O33) -> 353646.46
B34: Perú | C34: CTA.CTE. EERR (REDTEC) | D34: =+'Flujo Redco Perú'!C36 -> 0 | E34: =+'Flujo Redco Perú'!D36 -> 0 | F34: =+'Flujo Redco Perú'!E36 -> 51893 | G34: =+'Flujo Redco Perú'!F36 -> 0 | H34: =+'Flujo Redco Perú'!G36 -> 0 | I34: =+'Flujo Redco Perú'!H36 -> 0 | J34: =+'Flujo Redco Perú'!I36 -> 0 | K34: =+'Flujo Redco Perú'!J36 -> 0 | ... O34: =+'Flujo Redco Perú'!N36 -> 0 | P34: =SUM(D34:O34) -> 51893
B35: Chile | C35: RESCATE FFMM BANCHILE | P35: =SUM(D35:O35) -> 0
B36: Otros | C36: INGRESO CTA.CTE. EERR | D36: =+'Flujo Redco BVI'!C36 -> 0 | E36: =+'Flujo Redco BVI'!D36 -> 0 | F36: =+'Flujo Redco BVI'!E36 -> 0 | G36: =+'Flujo Redco BVI'!F36 -> 0 | H36: =+'Flujo Redco BVI'!G36 -> 415568 | I36: =+'Flujo Redco BVI'!H36 -> 0 | J36: =+'Flujo Redco BVI'!I36 -> 0 | K36: =+'Flujo Redco BVI'!J36 -> 0 | ... O36: =+'Flujo Redco BVI'!N36 -> 349514 | P36: =SUM(D36:O36) -> 1154049
B37: TOTAL | C37: SUMA OTROS INGRESOS | D37: =SUM(D28:D36) -> 279571.81 | E37: =SUM(E28:E36) -> 245598.41 | F37: =SUM(F28:F36) -> 172251.12 | G37: =SUM(G28:G36) -> 292209.81 | H37: =SUM(H28:H36) -> 608384.49 | I37: =SUM(I28:I36) -> 179700.25 | J37: =SUM(J28:J36) -> 253201.81 | K37: =SUM(K28:K36) -> 659206.51 | ... P37: =SUM(P28:P36) -> 4528894.2
B39: Chile | C39: EGRESO IVA DEBITO | D39: =+'Flujo Redco Chile'!C44*-1 -> -34979.334 | E39: =+'Flujo Redco Chile'!D44*-1 -> -63266.452 | F39: =+'Flujo Redco Chile'!E44*-1 -> -11946.348 | G39: =+'Flujo Redco Chile'!F44*-1 -> -31666.326 | H39: =+'Flujo Redco Chile'!G44*-1 -> -65886.451 | I39: =+'Flujo Redco Chile'!H44*-1 -> -41468.266 | J39: =+'Flujo Redco Chile'!I44*-1 -> -8884.088 | K39: =+'Flujo Redco Chile'!J44*-1 -> -86387.474 | ... O39: =+'Flujo Redco Chile'!N44*-1 -> -24253.626 | P39: =SUM(D39:O39) -> -489115.1
B40: Chile | C40: EGRESO CREDITOS | D40: =(+'Flujo Redco Chile'!C45+'Flujo Redco Chile'!C46+'Flujo Redco Chile'!C47)*-1 -> -27599.535 | E40: =(+'Flujo Redco Chile'!D45+'Flujo Redco Chile'!D46+'Flujo Redco Chile'!D47)*-1 -> -38631.281 | F40: =(+'Flujo Redco Chile'!E45+'Flujo Redco Chile'!E46+'Flujo Redco Chile'!E47)*-1 -> -30686.726 | G40: =(+'Flujo Redco Chile'!F45+'Flujo Redco Chile'!F46+'Flujo Redco Chile'!F47)*-1 -> -31866.891 | H40: =(+'Flujo Redco Chile'!G45+'Flujo Redco Chile'!G46+'Flujo Redco Chile'!G47)*-1 -> -32660.93 | I40: =(+'Flujo Redco Chile'!H45+'Flujo Redco Chile'!H46+'Flujo Redco Chile'!H47)*-1 -> -27706.253 | J40: =(+'Flujo Redco Chile'!I45+'Flujo Redco Chile'!I46+'Flujo Redco Chile'!I47)*-1 -> -31882.783 | K40: =(+'Flujo Redco Chile'!J45+'Flujo Redco Chile'!J46+'Flujo Redco Chile'!J47)*-1 -> -30717.742 | ... O40: =(+'Flujo Redco Chile'!N45+'Flujo Redco Chile'!N46+'Flujo Redco Chile'!N47)*-1 -> -30784.118 | P40: =SUM(D40:O40) -> -373754.78
B41: Chile | C41: CTA.CTE. EERR | D41: =(+'Flujo Redco Chile'!C52+'Flujo Redco Chile'!C54+'Flujo Redco Chile'!C55+'Flujo Redco Chile'!C56+'Flujo Redco Chile'!C57)*-1 -> -21128.81 | E41: =(+'Flujo Redco Chile'!D52+'Flujo Redco Chile'!D54+'Flujo Redco Chile'!D55+'Flujo Redco Chile'!D56+'Flujo Redco Chile'!D57)*-1 -> -5335.2929 | F41: =(+'Flujo Redco Chile'!E52+'Flujo Redco Chile'!E54+'Flujo Redco Chile'!E55+'Flujo Redco Chile'!E56+'Flujo Redco Chile'!E57)*-1 -> -20323.139 | G41: =(+'Flujo Redco Chile'!F52+'Flujo Redco Chile'!F54+'Flujo Redco Chile'!F55+'Flujo Redco Chile'!F56+'Flujo Redco Chile'!F57)*-1 -> -68310.75 | H41: =(+'Flujo Redco Chile'!G52+'Flujo Redco Chile'!G54+'Flujo Redco Chile'!G55+'Flujo Redco Chile'!G56+'Flujo Redco Chile'!G57)*-1 -> -25408.954 | I41: =(+'Flujo Redco Chile'!H52+'Flujo Redco Chile'!H54+'Flujo Redco Chile'!H55+'Flujo Redco Chile'!H56+'Flujo Redco Chile'!H57)*-1 -> -19313.305 | J41: =(+'Flujo Redco Chile'!I52+'Flujo Redco Chile'!I54+'Flujo Redco Chile'!I55+'Flujo Redco Chile'!I56+'Flujo Redco Chile'!I57)*-1 -> -66329.145 | K41: =(+'Flujo Redco Chile'!J52+'Flujo Redco Chile'!J54+'Flujo Redco Chile'!J55+'Flujo Redco Chile'!J56+'Flujo Redco Chile'!J57)*-1 -> -7645.6223 | ... O41: =(+'Flujo Redco Chile'!N52+'Flujo Redco Chile'!N54+'Flujo Redco Chile'!N55+'Flujo Redco Chile'!N56+'Flujo Redco Chile'!N57)*-1 -> -47905.397 | P41: =SUM(D41:O41) -> -289705.24
B42: Chile | C42: CTA.CTE. EERR (REDTEC) | D42: =+'Flujo Redco Chile'!C53*-1 -> -24259.657 | E42: =+'Flujo Redco Chile'!D53*-1 -> -113524.2 | F42: =+'Flujo Redco Chile'!E53*-1 -> -57052.603 | G42: =+'Flujo Redco Chile'!F53*-1 -> -140964.71 | H42: =+'Flujo Redco Chile'!G53*-1 -> -9291.9936 | I42: =+'Flujo Redco Chile'!H53*-1 -> 0 | J42: =+'Flujo Redco Chile'!I53*-1 -> 0 | K42: =+'Flujo Redco Chile'!J53*-1 -> 0 | ... O42: =+'Flujo Redco Chile'!N53*-1 -> -388.07725 | P42: =SUM(D42:O42) -> -372695.6
B43: Perú | C43: EGRESO IVA DEBITO | D43: =+'Flujo Redco Perú'!C44*-1 -> -42494 | E43: =+'Flujo Redco Perú'!D44*-1 -> 0 | F43: =+'Flujo Redco Perú'!E44*-1 -> -5448 | G43: =+'Flujo Redco Perú'!F44*-1 -> -1998 | H43: =+'Flujo Redco Perú'!G44*-1 -> -49989 | I43: =+'Flujo Redco Perú'!H44*-1 -> -41625 | J43: =+'Flujo Redco Perú'!I44*-1 -> -37651 | K43: =+'Flujo Redco Perú'!J44*-1 -> -102790 | ... O43: =+'Flujo Redco Perú'!N44*-1 -> -36493 | P43: =SUM(D43:O43) -> -409309
B44: Perú | C44: CTA.CTE. EERR | D44: =+'Flujo Redco Perú'!C54*-1 -> 0 | E44: =+'Flujo Redco Perú'!D54*-1 -> 0 | F44: =+'Flujo Redco Perú'!E54*-1 -> -14000 | G44: =+'Flujo Redco Perú'!F54*-1 -> 0 | H44: =+'Flujo Redco Perú'!G54*-1 -> 0 | I44: =+'Flujo Redco Perú'!H54*-1 -> -14000 | J44: =+'Flujo Redco Perú'!I54*-1 -> 0 | K44: =+'Flujo Redco Perú'!J54*-1 -> -472152 | ... O44: =+'Flujo Redco Perú'!N54*-1 -> -100000 | P44: =SUM(D44:O44) -> -928209
B45: Brasil | C45: EGRESO IVA DEBITO | D45: =+'Flujo Redco Brasil'!C37*-1 -> -13957 | E45: =+'Flujo Redco Brasil'!D37*-1 -> -15243 | F45: =+'Flujo Redco Brasil'!E37*-1 -> -7945 | G45: =+'Flujo Redco Brasil'!F37*-1 -> -26398 | H45: =+'Flujo Redco Brasil'!G37*-1 -> -9411 | I45: =+'Flujo Redco Brasil'!H37*-1 -> -12454 | J45: =+'Flujo Redco Brasil'!I37*-1 -> -18530 | K45: =+'Flujo Redco Brasil'!J37*-1 -> -27561 | ... O45: =+'Flujo Redco Brasil'!N37*-1 -> -95607 | P45: =SUM(D45:O45) -> -375161
B46: Brasil | C46: CTA.CTE. EERR | H46: =+'Flujo Redco Brasil'!G43*-1 -> -133710 | I46: =+'Flujo Redco Brasil'!H43*-1 -> 0 | P46: =SUM(D46:O46) -> -133710
B47: USA | C47: CTA.CTE. EERR | H47: =+'Flujo Redco USA'!G46*-1 -> -281858 | P47: =SUM(D47:O47) -> -281858
B48: TOTAL | C48: SUMA OTROS EGRESOS | D48: =SUM(D39:D47) -> -164418.34 | E48: =SUM(E39:E47) -> -236000.23 | F48: =SUM(F39:F47) -> -147401.82 | G48: =SUM(G39:G47) -> -301204.68 | H48: =SUM(H39:H47) -> -608216.33 | I48: =SUM(I39:I47) -> -156566.82 | J48: =SUM(J39:J47) -> -163277.02 | K48: =SUM(K39:K47) -> -727253.84 | ... P48: =SUM(P39:P47) -> -3653517.7
B50: País | C50: Concepto | D50: 45658 | E50: 45689 | F50: 45717 | G50: 45748 | H50: 45778 | I50: 45809 | J50: 45839 | K50: 45870 | L50: 45901 | M50: 45931 | N50: 45962 | O50: 45992 | P50: Total
B51: Chile | C51: RESULTADO CAJA | D51: =SUM(D20+D28+D30+D32+D33+D35+D39+D41+D42+D40) -> 118395.56 | E51: =SUM(E20+E28+E30+E32+E33+E35+E39+E41+E42+E40) -> 133162.17 | F51: =SUM(F20+F28+F30+F32+F33+F35+F39+F41+F42+F40) -> -69890.423 | G51: =SUM(G20+G28+G30+G32+G33+G35+G39+G41+G42+G40) -> -113200.73 | H51: =SUM(H20+H28+H30+H32+H33+H35+H39+H41+H42+H40) -> -40765.558 | I51: =SUM(I20+I28+I30+I32+I33+I35+I39+I41+I42+I40) -> -48061.672 | J51: =SUM(J20+J28+J30+J32+J33+J35+J39+J41+J42+J40) -> 191766.35 | K51: =SUM(K20+K28+K30+K32+K33+K35+K39+K41+K42+K40) -> 134254.5 | ... O51: =SUM(O20+O28+O30+O32+O33+O35+O39+O41+O42+O40) -> 68872.34 | P51: =SUM(D51:O51) -> -39436.821 | R51: =+SUM(D51:L51) -> 149134.32
B52: Perú | C52: RESULTADO CAJA | D52: =+D21+D29+D34+D43+D44 -> 3798.15 | E52: =+E21+E29+E34+E43+E44 -> -2643 | F52: =+F21+F29+F34+F43+F44 -> 65135 | G52: =+G21+G29+G34+G43+G44 -> -1064.3 | H52: =+H21+H29+H34+H43+H44 -> -4999 | I52: =+I21+I29+I34+I43+I44 -> 42095 | J52: =+J21+J29+J34+J43+J44 -> 48879 | K52: =+K21+K29+K34+K43+K44 -> -32506 | ... O52: =+O21+O29+O34+O43+O44 -> 38241.97 | P52: =SUM(D52:O52) -> 10486.46 | R52: =+SUM(D52:L52) -> 79991.85
B53: Brasil | C53: RESULTADO CAJA | D53: =+D22+D31+D45 -> 51910 | E53: =+E22+E31+E45 -> 16991 | F53: =+F22+F31+F45 -> 61952 | G53: =+G22+G31+G45 -> 18807.3 | H53: =+H22+H31+H45+H46 -> -137850 | I53: =+I22+I31+I45+I46 -> -22177 | J53: =+J22+J31+J45+J46 -> -1832 | K53: =+K22+K31+K45+K46 -> 70616 | L53: =+L22+L31+L45+L46 -> 104282 | M53: =+M22+M31+M45+M46 -> 244856 | N53: =+N22+N31+N45+N46 -> 135142 | O53: =+O22+O31+O45+O46 -> 105508.51 | P53: =SUM(D53:O53) -> 648205.81 | R53: =+SUM(D53:L53) -> 162699.3
B54: USA | C54: RESULTADO CAJA | D54: =SUM(D23) -> 150438 | E54: =SUM(E23) -> 241440.21 | F54: =SUM(F23) -> 82798 | G54: =SUM(G23) -> 159302 | H54: =SUM(H23+H47) -> -134434 | I54: =SUM(I23+I47) -> 57618 | J54: =SUM(J23) -> -10017 | K54: =SUM(K23) -> 18985 | L54: =SUM(L23) -> -1000 | M54: =SUM(M23) -> -43411 | N54: =SUM(N23) -> -1000 | O54: =SUM(O23) -> -39625 | P54: =SUM(D54:O54) -> 481094.21 | R54: =+SUM(D54:L54) -> 565130.21
B55: Otros | C55: RESULTADO CAJA | D55: =+D24+D36 -> -14044 | E55: =+E24+E36 -> 21682 | F55: =+F24+F36 -> 45478 | G55: =+G24+G36 -> -14380 | H55: =+H24+H36 -> 399568 | I55: =+I24+I36 -> 156951 | J55: =+J24+J36 -> -5684.8 | K55: =+K24+K36 -> 93839.2 | ... O55: =+O24+O36 -> 343829.2 | P55: =SUM(D55:O55) -> 1399151.2 | R55: =+SUM(D55:L55) -> 677724.6
B56: TOTAL | C56: RESULTADO CAJA | D56: =SUM(D51:D55) -> 310497.71 | E56: =SUM(E51:E55) -> 410632.38 | F56: =SUM(F51:F55) -> 185472.58 | G56: =SUM(G51:G55) -> 49464.274 | H56: =SUM(H51:H55) -> 81519.442 | I56: =SUM(I51:I55) -> 186425.33 | J56: =SUM(J51:J55) -> 223111.55 | K56: =SUM(K51:K55) -> 285188.7 | ... O56: =SUM(O51:O55) -> 516827.02 | P56: =SUM(D56:O56) -> 2499500.9 | R56: =SUM(R51:R55) -> 1634680.3
B58: CAJA FINAL | C58: CAJA FINAL | D58: =+D56+T9 -> 564489.87 | E58: =+D58+E56 -> 975122.25 | F58: =+E58+F56 -> 1160594.8 | G58: =+F58+G56 -> 1210059.1 | H58: =+G58+H56 -> 1291578.5 | I58: =+H58+I56 -> 1478003.9 | J58: =+I58+J56 -> 1701115.4 | K58: =+J58+K56 -> 1986304.1 | L58: =+K58+L56 -> 1888672.4 | ... O58: =+N58+O56 -> 2753493 | P58: =+O58 -> 2753493
B60: País | C60: Concepto | D60: 45658 | E60: 45689 | F60: 45717 | G60: 45748 | H60: 45778 | I60: 45809 | J60: 45839 | K60: 45870 | L60: 45901 | M60: 45931 | N60: 45962 | O60: 45992 | P60: Total | R60: País | S60: Total
B61: Chile | C61: TOTAL CAJA | D61: =+D51+T4 -> 170652.7 | E61: =+D61+E51 -> 303814.87 | F61: =+E61+F51 -> 233924.45 | G61: =+F61+G51 -> 120723.72 | H61: =+G61+H51 -> 79958.162 | I61: =+H61+I51 -> 31896.49 | J61: =+I61+J51 -> 223662.84 | K61: =+J61+K51 -> 357917.35 | L61: =+K61+L51 -> 201391.46 | ... O61: =+N61+O51 -> 12820.317 | P61: =+O61 -> 12820.317 | R61: USA | S61: 1202.541
B62: Perú | C62: TOTAL CAJA | D62: =+D52+T5 -> 140565.84 | E62: =+D62+E52 -> 137922.84 | F62: =+E62+F52 -> 203057.84 | G62: =+F62+G52 -> 201993.54 | H62: =+G62+H52 -> 196994.54 | I62: =+H62+I52 -> 239089.54 | J62: =+I62+J52 -> 287968.54 | K62: =+J62+K52 -> 255462.54 | L62: =+K62+L52 -> 216759.54 | ... O62: =+N62+O52 -> 147254.15 | P62: =+O62 -> 147254.15 | R62: Brasil | S62: 741.72933
B63: Brasil | C63: TOTAL CAJA | D63: =+D53+T6 -> 61532.33 | E63: =+D63+E53 -> 78523.33 | F63: =+E63+F53 -> 140475.33 | G63: =+F63+G53 -> 159282.63 | H63: =+G63+H53 -> 21432.63 | I63: =+H63+I53 -> -744.37 | J63: =+I63+J53 -> -2576.37 | K63: =+J63+K53 -> 68039.63 | L63: =+K63+L53 -> 172321.63 | ... O63: =+N63+O53 -> 657828.14 | P63: =+O63 -> 657828.14 | R63: Otros | S63: 670.0794
B64: USA | C64: TOTAL CAJA | D64: =+D54+T7 -> 205783 | E64: =+D64+E54 -> 447223.21 | F64: =+E64+F54 -> 530021.21 | G64: =+F64+G54 -> 689323.21 | H64: =+G64+H54 -> 554889.21 | I64: =+H64+I54 -> 612507.21 | J64: =+I64+J54 -> 602490.21 | K64: =+J64+K54 -> 621475.21 | L64: =+K64+L54 -> 620475.21 | ... O64: =+N64+O54 -> 536439.21 | P64: =+O64 -> 536439.21 | R64: Perú | S64: 384.33119
B65: Otros | C65: TOTAL CAJA | D65: =+D55+T8 -> -14044 | E65: =+D65+E55 -> 7638 | F65: =+E65+F55 -> 53116 | G65: =+F65+G55 -> 38736 | H65: =+G65+H55 -> 438304 | I65: =+H65+I55 -> 595255 | J65: =+I65+J55 -> 589570.2 | K65: =+J65+K55 -> 683409.4 | L65: =+K65+L55 -> 677724.6 | ... O65: =+N65+O55 -> 1399151.2 | P65: =+O65 -> 1399151.2 | R65: Chile | S65: -407.13954
B66: SALDO CAJA | C66: SALDO CAJA | D66: =SUM(D61:D65) -> 564489.87 | E66: =SUM(E61:E65) -> 975122.25 | F66: =SUM(F61:F65) -> 1160594.8 | G66: =SUM(G61:G65) -> 1210059.1 | H66: =SUM(H61:H65) -> 1291578.5 | I66: =SUM(I61:I65) -> 1478003.9 | J66: =SUM(J61:J65) -> 1701115.4 | K66: =SUM(K61:K65) -> 1986304.1 | ... P66: =SUM(P61:P65) -> 2753493 | R66: Total | S66: =SUM(S61:S65) -> 2591.5414

Sheet Tabla datos unidades
L1: 6853202.5 | M1: =+L10-L1 -> 73593.425 | N1: =+M1/L10 -> 0.010624454
J2: =+J17/1000 -> 641.80299 | K2: =+K17/1000 -> 678.99571 | L2: =+L17/1000 -> 666.97613 | M2: =+M17/1000 -> 729.50446 | N2: =+N17/1000 -> 586.01155 | O2: =+O17/1000 -> 976.72234 | V2: enro a septiembre 2025
B3: País | C3: Concepto | D3: 45658 | E3: 45689 | F3: 45717 | G3: 45748 | H3: 45778 | I3: 45809 | J3: 45839 | K3: 45870 | L3: 45901 | M3: 45931 | N3: 45962 | O3: 45992 | P3: Total | R3: País | S3: Concepto | T3: 45658 | V3: PAIS | W3: CONCEPTO | X3: MUS$
B4: Chile | C4: INGRESOS OP | D4: =+'Flujo Redco Chile'!C12 -> 362362.73 | E4: =+'Flujo Redco Chile'!D12 -> 547310.62 | F4: =+'Flujo Redco Chile'!E12 -> 389727.46 | G4: =+'Flujo Redco Chile'!F12 -> 237434.48 | H4: =+'Flujo Redco Chile'!G12 -> 272631.08 | I4: =+'Flujo Redco Chile'!H12 -> 277419.07 | J4: =+'Flujo Redco Chile'!I12 -> 475570.75 | K4: =+'Flujo Redco Chile'!J12 -> 151482.74 | ... O4: =+'Flujo Redco Chile'!N12 -> 173207.55 | P4: =SUM(D4:O4) -> 3592126.9 | R4: Chile | S4: SALDO INICIAL | T4: =+'Flujo Redco Chile'!C8 -> 52257.137 | V4: Chile | W4: INGRESO NETO | X4: =SUM(D4:L4) -> 3011864
B5: Perú | C5: INGRESOS OP | D5: =+'Flujo Redco Perú'!C13 -> 123848 | E5: =+'Flujo Redco Perú'!D13 -> 62454 | F5: =+'Flujo Redco Perú'!E13 -> 105377 | G5: =+'Flujo Redco Perú'!F13 -> 110077 | H5: =+'Flujo Redco Perú'!G13 -> 142610 | I5: =+'Flujo Redco Perú'!H13 -> 229588 | J5: =+'Flujo Redco Perú'!I13 -> 251702 | K5: =+'Flujo Redco Perú'!J13 -> 641573 | ... O5: =+'Flujo Redco Perú'!N13 -> 269432 | P5: =SUM(D5:O5) -> 2417353 | R5: Perú | S5: SALDO INICIAL | T5: =+'Flujo Redco Perú'!C9 -> 136767.69 | V5: Perú | W5: INGRESO NETO | X5: =SUM(D5:L5) -> 1786362
B6: Brasil | C6: INGRESOS OP | D6: =+'Flujo Redco Brasil'!C14 -> 80502 | E6: =+'Flujo Redco Brasil'!D14 -> 59683 | F6: =+'Flujo Redco Brasil'!E14 -> 96322 | G6: =+'Flujo Redco Brasil'!F14 -> 97209.7 | H6: =+'Flujo Redco Brasil'!G14 -> 37074 | I6: =+'Flujo Redco Brasil'!H14 -> 66563 | J6: =+'Flujo Redco Brasil'!I14 -> 47717 | K6: =+'Flujo Redco Brasil'!J14 -> 119652 | ... O6: =+'Flujo Redco Brasil'!N14 -> 224116.51 | P6: =SUM(D6:O6) -> 1597092.2 | R6: Brasil | S6: SALDO INICIAL | T6: =+'Flujo Redco Brasil'!C9 -> 9622.33 | W6: SUMA | X6: =SUM(X4:X5) -> 4798226
B7: USA | C7: INGRESOS OP | D7: =+'Flujo Redco USA'!C13 -> 150453 | E7: =+'Flujo Redco USA'!D13 -> 243465.21 | F7: =+'Flujo Redco USA'!E13 -> 141526 | G7: =+'Flujo Redco USA'!F13 -> 169200 | H7: =+'Flujo Redco USA'!G13 -> 195090 | I7: =+'Flujo Redco USA'!H13 -> 61796 | J7: =+'Flujo Redco USA'!I13 -> 0 | K7: =+'Flujo Redco USA'!J13 -> 20000 | ... O7: =+'Flujo Redco USA'!N13 -> 178785 | P7: =SUM(D7:O7) -> 1205315.2 | R7: USA | S7: SALDO INICIAL | T7: =+'Flujo Redco USA'!C9 -> 55345
B8: BVI | C8: INGRESOS OP | D8: =+'Flujo Redco BVI'!C13 -> 0 | E8: =+'Flujo Redco BVI'!D13 -> 21682 | F8: =+'Flujo Redco BVI'!E13 -> 45478 | G8: =+'Flujo Redco BVI'!F13 -> 0 | H8: =+'Flujo Redco BVI'!G13 -> 0 | I8: =+'Flujo Redco BVI'!H13 -> 172045 | J8: =+'Flujo Redco BVI'!I13 -> 0 | K8: =+'Flujo Redco BVI'!J13 -> 99524 | ... O8: =+'Flujo Redco BVI'!N13 -> 0 | P8: =SUM(D8:O8) -> 338729 | R8: BVI | S8: SALDO INICIAL | T8: =+'Flujo Redco BVI'!S13 -> 0
B9: TOTAL | C9: INGRESOS OP | D9: =SUM(D4:D8) -> 717165.73 | E9: =SUM(E4:E8) -> 934594.83 | F9: =SUM(F4:F8) -> 778430.46 | G9: =SUM(G4:G8) -> 613921.18 | H9: =SUM(H4:H8) -> 647405.08 | I9: =SUM(I4:I8) -> 807411.07 | J9: =SUM(J4:J8) -> 774989.75 | K9: =SUM(K4:K8) -> 1032231.7 | ... P9: =SUM(P4:P8) -> 9150616.3 | R9: CAJA FINAL | S9: CAJA FINAL | T9: =SUM(T4:T8) -> 253992.16
C10: INGRESOS OP ACUM | D10: =+SUM($D$9:D9) -> 717165.73 | E10: =+SUM($D$9:E9) -> 1651760.6 | F10: =+SUM($D$9:F9) -> 2430191 | G10: =+SUM($D$9:G9) -> 3044112.2 | H10: =+SUM($D$9:H9) -> 3691517.3 | I10: =+SUM($D$9:I9) -> 4498928.4 | J10: =+SUM($D$9:J9) -> 5273918.1 | K10: =+SUM($D$9:K9) -> 6306149.8 | ... O10: =+SUM($D$9:O9) -> 9150616.3
B11: País | C11: Concepto | D11: 45658 | E11: 45689 | F11: 45717 | G11: 45748 | H11: 45778 | I11: 45809 | J11: 45839 | K11: 45870 | L11: 45901 | M11: 45931 | N11: 45962 | O11: 45992 | P11: Total
B12: Chile | C12: COSTOS OP | D12: =+'Flujo Redco Chile'!C18+'Flujo Redco Chile'!C23+'Flujo Redco Chile'!C25 -> 397276.65 | E12: =+'Flujo Redco Chile'!D18+'Flujo Redco Chile'!D23+'Flujo Redco Chile'!D25 -> 422126.64 | F12: =+'Flujo Redco Chile'!E18+'Flujo Redco Chile'!E23+'Flujo Redco Chile'!E25 -> 439899.18 | G12: =+'Flujo Redco Chile'!F18+'Flujo Redco Chile'!F23+'Flujo Redco Chile'!F25 -> 341507.35 | H12: =+'Flujo Redco Chile'!G18+'Flujo Redco Chile'!G23+'Flujo Redco Chile'!G25 -> 340134.8 | I12: =+'Flujo Redco Chile'!H18+'Flujo Redco Chile'!H23+'Flujo Redco Chile'!H25 -> 380566.17 | J12: =+'Flujo Redco Chile'!I18+'Flujo Redco Chile'!I23+'Flujo Redco Chile'!I25 -> 395727.19 | K12: =+'Flujo Redco Chile'!J18+'Flujo Redco Chile'!J23+'Flujo Redco Chile'!J25 -> 425248.91 | ... O12: =+'Flujo Redco Chile'!N18+'Flujo Redco Chile'!N23+'Flujo Redco Chile'!N25 -> 495505.54 | P12: =SUM(D12:O12) -> 4999267.5
B13: Perú | C13: COSTOS OP | D13: =+'Flujo Redco Perú'!C19+'Flujo Redco Perú'!C26+'Flujo Redco Perú'!C28 -> 89462.85 | E13: =+'Flujo Redco Perú'!D19+'Flujo Redco Perú'!D26+'Flujo Redco Perú'!D28 -> 81597 | F13: =+'Flujo Redco Perú'!E19+'Flujo Redco Perú'!E26+'Flujo Redco Perú'!E28 -> 92755 | G13: =+'Flujo Redco Perú'!F19+'Flujo Redco Perú'!F26+'Flujo Redco Perú'!F28 -> 137672.3 | H13: =+'Flujo Redco Perú'!G19+'Flujo Redco Perú'!G26+'Flujo Redco Perú'!G28 -> 128924 | I13: =+'Flujo Redco Perú'!H19+'Flujo Redco Perú'!H26+'Flujo Redco Perú'!H28 -> 167995 | J13: =+'Flujo Redco Perú'!I19+'Flujo Redco Perú'!I26+'Flujo Redco Perú'!I28 -> 199355 | K13: =+'Flujo Redco Perú'!J19+'Flujo Redco Perú'!J26+'Flujo Redco Perú'!J28 -> 225572 | ... O13: =+'Flujo Redco Perú'!N19+'Flujo Redco Perú'!N26+'Flujo Redco Perú'!N28 -> 234121 | P13: =SUM(D13:O13) -> 1731862.8
B14: Brasil | C14: COSTOS OP | D14: =+'Flujo Redco Brasil'!C20+'Flujo Redco Brasil'!C25+'Flujo Redco Brasil'!C27 -> 21023 | E14: =+'Flujo Redco Brasil'!D20+'Flujo Redco Brasil'!D25+'Flujo Redco Brasil'!D27 -> 27812 | F14: =+'Flujo Redco Brasil'!E20+'Flujo Redco Brasil'!E25+'Flujo Redco Brasil'!E27 -> 26425 | G14: =+'Flujo Redco Brasil'!F20+'Flujo Redco Brasil'!F25+'Flujo Redco Brasil'!F27 -> 52004.4 | H14: =+'Flujo Redco Brasil'!G20+'Flujo Redco Brasil'!G25+'Flujo Redco Brasil'!G27 -> 33329 | I14: =+'Flujo Redco Brasil'!H20+'Flujo Redco Brasil'!H25+'Flujo Redco Brasil'!H27 -> 76286 | J14: =+'Flujo Redco Brasil'!I20+'Flujo Redco Brasil'!I25+'Flujo Redco Brasil'!I27 -> 31019 | K14: =+'Flujo Redco Brasil'!J20+'Flujo Redco Brasil'!J25+'Flujo Redco Brasil'!J27 -> 21475 | ... O14: =+'Flujo Redco Brasil'!N20+'Flujo Redco Brasil'!N25+'Flujo Redco Brasil'!N27 -> 23001 | P14: =SUM(D14:O14) -> 451717.4
B15: USA | C15: COSTOS OP | D15: =+'Flujo Redco USA'!C19+'Flujo Redco USA'!C27+'Flujo Redco USA'!C29 -> 15 | E15: =+'Flujo Redco USA'!D19+'Flujo Redco USA'!D27+'Flujo Redco USA'!D29 -> 2025 | F15: =+'Flujo Redco USA'!E19+'Flujo Redco USA'!E27+'Flujo Redco USA'!E29 -> 58728 | G15: =+'Flujo Redco USA'!F19+'Flujo Redco USA'!F27+'Flujo Redco USA'!F29 -> 9898 | H15: =+'Flujo Redco USA'!G19+'Flujo Redco USA'!G27+'Flujo Redco USA'!G29 -> 47666 | I15: =+'Flujo Redco USA'!H19+'Flujo Redco USA'!H27+'Flujo Redco USA'!H29 -> 4178 | J15: =+'Flujo Redco USA'!I19+'Flujo Redco USA'!I27+'Flujo Redco USA'!I29 -> 10017 | K15: =+'Flujo Redco USA'!J19+'Flujo Redco USA'!J27+'Flujo Redco USA'!J29 -> 1015 | ... O15: =+'Flujo Redco USA'!N19+'Flujo Redco USA'!N27+'Flujo Redco USA'!N29 -> 218410 | P15: =SUM(D15:O15) -> 442363
B16: BVI | C16: COSTOS OP | D16: =+'Flujo Redco BVI'!C19+'Flujo Redco BVI'!C27+'Flujo Redco BVI'!C29 -> 14044 | E16: =+'Flujo Redco BVI'!D19+'Flujo Redco BVI'!D27+'Flujo Redco BVI'!D29 -> 0 | F16: =+'Flujo Redco BVI'!E19+'Flujo Redco BVI'!E27+'Flujo Redco BVI'!E29 -> 0 | G16: =+'Flujo Redco BVI'!F19+'Flujo Redco BVI'!F27+'Flujo Redco BVI'!F29 -> 14380 | H16: =+'Flujo Redco BVI'!G19+'Flujo Redco BVI'!G27+'Flujo Redco BVI'!G29 -> 16000 | I16: =+'Flujo Redco BVI'!H19+'Flujo Redco BVI'!H27+'Flujo Redco BVI'!H29 -> 15094 | J16: =+'Flujo Redco BVI'!I19+'Flujo Redco BVI'!I27+'Flujo Redco BVI'!I29 -> 5684.8 | K16: =+'Flujo Redco BVI'!J19+'Flujo Redco BVI'!J27+'Flujo Redco BVI'!J29 -> 5684.8 | ... O16: =+'Flujo Redco BVI'!N19+'Flujo Redco BVI'!N27+'Flujo Redco BVI'!N29 -> 5684.8 | P16: =SUM(D16:O16) -> 93626.8
B17: TOTAL | C17: COSTOS OP | D17: =SUM(D12:D16) -> 521821.5 | E17: =SUM(E12:E16) -> 533560.64 | F17: =SUM(F12:F16) -> 617807.18 | G17: =SUM(G12:G16) -> 555462.05 | H17: =SUM(H12:H16) -> 566053.8 | I17: =SUM(I12:I16) -> 644119.17 | J17: =SUM(J12:J16) -> 641802.99 | K17: =SUM(K12:K16) -> 678995.71 | ... O17: =SUM(O12:O16) -> 976722.34 | P17: =SUM(D17:O17) -> 7718837.5
C18: COSTOS OP ACUM | D18: =+SUM($D$17:D17) -> 521821.5 | E18: =+SUM($D$17:E17) -> 1055382.1 | F18: =+SUM($D$17:F17) -> 1673189.3 | G18: =+SUM($D$17:G17) -> 2228651.4 | H18: =+SUM($D$17:H17) -> 2794705.2 | I18: =+SUM($D$17:I17) -> 3438824.3 | J18: =+SUM($D$17:J17) -> 4080627.3 | K18: =+SUM($D$17:K17) -> 4759623 | ... O18: =+SUM($D$17:O17) -> 7718837.5
B19: País | C19: Concepto | D19: 45658 | E19: 45689 | F19: 45717 | G19: 45748 | H19: 45778 | I19: 45809 | J19: 45839 | K19: 45870 | L19: 45901 | M19: 45931 | N19: 45962 | O19: 45992 | P19: Total
B20: Chile | C20: RESULTADO OP. | D20: =+D4-D12 -> -34913.914 | E20: =+E4-E12 -> 125183.98 | F20: =+F4-F12 -> -50171.722 | G20: =+G4-G12 -> -104072.86 | H20: =+H4-H12 -> -67503.719 | I20: =+I4-I12 -> -103147.1 | J20: =+J4-J12 -> 79843.563 | K20: =+K4-K12 -> -273766.17 | ... O20: =+O4-O12 -> -322297.98 | P20: =SUM(D20:O20) -> -1407140.6
B21: Perú | C21: RESULTADO OP. | D21: =+D5-D13 -> 34385.15 | E21: =+E5-E13 -> -19143 | F21: =+F5-F13 -> 12622 | G21: =+G5-G13 -> -27595.3 | H21: =+H5-H13 -> 13686 | I21: =+I5-I13 -> 61593 | J21: =+J5-J13 -> 52347 | K21: =+K5-K13 -> 416001 | L21: =+L5-L13 -> -7964 | M21: =+M5-M12 -> -247736.66 | N21: =+N5-N13 -> -43027.64 | O21: =+O5-O13 -> 35311 | P21: =SUM(D21:O21) -> 280478.55
B22: Brasil | C22: RESULTADO OP. | D22: =+D6-D14 -> 59479 | E22: =+E6-E14 -> 31871 | F22: =+F6-F14 -> 69897 | G22: =+G6-G14 -> 45205.3 | H22: =+H6-H14 -> 3745 | I22: =+I6-I14 -> -9723 | J22: =+J6-J14 -> 16698 | K22: =+K6-K14 -> 98177 | ... O22: =+O6-O14 -> 201115.51 | P22: =SUM(D22:O22) -> 1145374.8
B23: USA | C23: RESULTADO OP. | D23: =+D7-D15 -> 150438 | E23: =+E7-E15 -> 241440.21 | F23: =+F7-F15 -> 82798 | G23: =+G7-G15 -> 159302 | H23: =+H7-H15 -> 147424 | I23: =+I7-I15 -> 57618 | J23: =+J7-J15 -> -10017 | K23: =+K7-K15 -> 18985 | ... O23: =+O7-O15 -> -39625 | P23: =SUM(D23:O23) -> 762952.21
B24: BVI | C24: RESULTADO OP. | D24: =+D8-D16 -> -14044 | E24: =+E8-E16 -> 21682 | F24: =+F8-F16 -> 45478 | G24: =+G8-G16 -> -14380 | H24: =+H8-H16 -> -16000 | I24: =+I8-I16 -> 156951 | J24: =+J8-J16 -> -5684.8 | K24: =+K8-K16 -> 93839.2 | ... O24: =+O8-O16 -> -5684.8 | P24: =SUM(D24:O24) -> 245102.2
B25: TOTAL | C25: RESULTADO OP. | D25: =SUM(D20:D24) -> 195344.24 | E25: =SUM(E20:E24) -> 401034.19 | F25: =SUM(F20:F24) -> 160623.28 | G25: =SUM(G20:G24) -> 58459.138 | H25: =SUM(H20:H24) -> 81351.281 | I25: =SUM(I20:I24) -> 163291.9 | J25: =SUM(J20:J24) -> 133186.76 | K25: =SUM(K20:K24) -> 353236.03 | ... P25: =SUM(P20:P24) -> 1026767.2
D26: =+D25/D9 -> 0.27238367 | E26: =+E25/E9 -> 0.42909952 | F26: =+F25/F9 -> 0.20634249 | G26: =+G25/G9 -> 0.095222546 | H26: =+H25/H9 -> 0.12565746 | I26: =+I25/I9 -> 0.20224135 | J26: =+J25/J9 -> 0.17185616 | K26: =+K25/K9 -> 0.34220613 | L26: =+L25/L9 -> -0.074648142
B27: País | C27: Concepto | D27: 45658 | E27: 45689 | F27: 45717 | G27: 45748 | H27: 45778 | I27: 45809 | J27: 45839 | K27: 45870 | L27: 45901 | M27: 45931 | N27: 45962 | O27: 45992 | P27: Total
B28: Chile | C28: INGRESO IVA DEBITO | D28: =+'Flujo Redco Chile'!C31 -> 69432.94 | E28: =+'Flujo Redco Chile'!D31 -> 104811.9 | F28: =+'Flujo Redco Chile'!E31 -> 75208.024 | G28: =+'Flujo Redco Chile'!F31 -> 47094.724 | H28: =+'Flujo Redco Chile'!G31 -> 62773.513 | I28: =+'Flujo Redco Chile'!H31+'Flujo Redco Chile'!H34 -> 53789.215 | J28: =+'Flujo Redco Chile'!I31 -> 103658.78 | K28: =+'Flujo Redco Chile'!J31 -> 35825.605 | L28: =+'Flujo Redco Chile'!K31 -> 57280.832 | M28: =+'Flujo Redco Chile'!L31 -> 32498.942 | N28: =+'Flujo Redco Chile'!M31 -> 37753.16 | O28: =+'Flujo Redco Chile'!N31 -> 32909.433 | P28: =SUM(D28:O28) -> 713037.07
B29: Perú | C29: INGRESO IVA DEBITO | D29: =+'Flujo Redco Perú'!C35 -> 11907 | E29: =+'Flujo Redco Perú'!D35 -> 16500 | F29: =+'Flujo Redco Perú'!E35 -> 20068 | G29: =+'Flujo Redco Perú'!F35 -> 28529 | H29: =+'Flujo Redco Perú'!G35 -> 31304 | I29: =+'Flujo Redco Perú'!H35 -> 36127 | J29: =+'Flujo Redco Perú'!I35 -> 34183 | K29: =+'Flujo Redco Perú'!J35 -> 126435 | ... O29: =+'Flujo Redco Perú'!N35 -> 75885 | P29: =SUM(D29:O29) -> 544185
B30: Chile | C30: OTROS INGRESOS | D30: =+'Flujo Redco Chile'!C38+'Flujo Redco Chile'!C39+'Flujo Redco Chile'!E42+'Flujo Redco Chile'!C34 -> 703.28541 | E30: =+'Flujo Redco Chile'!D38+'Flujo Redco Chile'!D39+'Flujo Redco Chile'!D34 -> 10399.317 | F30: =+'Flujo Redco Chile'!E38+'Flujo Redco Chile'!E39+'Flujo Redco Chile'!E34 -> 5265.8026 | G30: =+'Flujo Redco Chile'!F38+'Flujo Redco Chile'!F39+'Flujo Redco Chile'!F34 -> 21747.626 | H30: =+'Flujo Redco Chile'!G38+'Flujo Redco Chile'!G39+'Flujo Redco Chile'!G34 -> 55661.029 | I30: =+'Flujo Redco Chile'!H38+'Flujo Redco Chile'!H39+'Flujo Redco Chile'!H34+'Flujo Redco Chile'!H40 -> 89784.033 | J30: =+'Flujo Redco Chile'!I38+'Flujo Redco Chile'!I39+'Flujo Redco Chile'!I34 -> 68680.616 | K30: =+'Flujo Redco Chile'!J38+'Flujo Redco Chile'!J39+'Flujo Redco Chile'!J34 -> 37073.082 | L30: =+'Flujo Redco Chile'!K38+'Flujo Redco Chile'!K39+'Flujo Redco Chile'!K34 -> 4069.9474 | M30: =+'Flujo Redco Chile'!L38+'Flujo Redco Chile'!L39 -> 13.927039 | N30: =+'Flujo Redco Chile'!M38+'Flujo Redco Chile'!M39 -> 415.80687 | O30: =+'Flujo Redco Chile'!N38+'Flujo Redco Chile'!N39 -> 119.83584 | P30: =SUM(D30:O30) -> 293934.31
B31: Brasil | C31: OTROS INGRESOS | D31: =+'Flujo Redco Brasil'!C34 -> 6388 | E31: =+'Flujo Redco Brasil'!D34 -> 363 | F31: =+'Flujo Redco Brasil'!E34 -> 0 | G31: =+'Flujo Redco Brasil'!F34 -> 0 | H31: =+'Flujo Redco Brasil'!G34 -> 1526 | I31: =+'Flujo Redco Brasil'!H34 -> 0 | J31: =+'Flujo Redco Brasil'!I34 -> 0 | K31: =+'Flujo Redco Brasil'!J34 -> 0 | ... O31: =+'Flujo Redco Brasil'!N34 -> 0 | P31: =SUM(D31:O31) -> 11702
B32: Chile | C32: INGRESO CTA.CTE. EERR | D32: =+'Flujo Redco Chile'!C35+'Flujo Redco Chile'!C36+'Flujo Redco Chile'!C37 -> 134087.98 | E32: =+'Flujo Redco Chile'!D35+'Flujo Redco Chile'!D36+'Flujo Redco Chile'!D37 -> 0 | F32: =+'Flujo Redco Chile'!E35+'Flujo Redco Chile'!E36+'Flujo Redco Chile'!E37 -> 19816.29 | G32: =+'Flujo Redco Chile'!F35+'Flujo Redco Chile'!F36+'Flujo Redco Chile'!F37 -> 48275.16 | H32: =+'Flujo Redco Chile'!G35+'Flujo Redco Chile'!G36+'Flujo Redco Chile'!G37 -> 32259.954 | I32: =+'Flujo Redco Chile'!H35+'Flujo Redco Chile'!H36+'Flujo Redco Chile'!H37 -> 0 | J32: =+'Flujo Redco Chile'!I35+'Flujo Redco Chile'!I36+'Flujo Redco Chile'!I37 -> 46679.406 | K32: =+'Flujo Redco Chile'!J35+'Flujo Redco Chile'!J36+'Flujo Redco Chile'!J37 -> 459872.82 | ... O32: =+'Flujo Redco Chile'!N35+'Flujo Redco Chile'!N36+'Flujo Redco Chile'!N37 -> 390966.74 | P32: =SUM(D32:O32) -> 1406447.3
B33: Chile | C33: CTA.CTE. EERR (REDTEC) | D33: =+'Flujo Redco Chile'!C32 -> 57052.603 | E33: =+'Flujo Redco Chile'!D32 -> 113524.2 | F33: =+'Flujo Redco Chile'!E32 -> 0 | G33: =+'Flujo Redco Chile'!F32 -> 146563.3 | H33: =+'Flujo Redco Chile'!G32 -> 9291.9936 | I33: =+'Flujo Redco Chile'!H32 -> 0 | J33: =+'Flujo Redco Chile'!I32 -> 0 | K33: =+'Flujo Redco Chile'!J32 -> 0 | ... O33: =+'Flujo Redco Chile'!N32 -> 0 | P33: =SUM(D33:O33) -> 353646.46
B34: Perú | C34: CTA.CTE. EERR (REDTEC) | D34: =+'Flujo Redco Perú'!C36 -> 0 | E34: =+'Flujo Redco Perú'!D36 -> 0 | F34: =+'Flujo Redco Perú'!E36 -> 51893 | G34: =+'Flujo Redco Perú'!F36 -> 0 | H34: =+'Flujo Redco Perú'!G36 -> 0 | I34: =+'Flujo Redco Perú'!H36 -> 0 | J34: =+'Flujo Redco Perú'!I36 -> 0 | K34: =+'Flujo Redco Perú'!J36 -> 0 | ... O34: =+'Flujo Redco Perú'!N36 -> 0 | P34: =SUM(D34:O34) -> 51893
B35: Chile | C35: RESCATE FFMM BANCHILE | P35: =SUM(D35:O35) -> 0
B36: BVI | C36: INGRESO CTA.CTE. EERR | D36: =+'Flujo Redco BVI'!C36 -> 0 | E36: =+'Flujo Redco BVI'!D36 -> 0 | F36: =+'Flujo Redco BVI'!E36 -> 0 | G36: =+'Flujo Redco BVI'!F36 -> 0 | H36: =+'Flujo Redco BVI'!G36 -> 415568 | I36: =+'Flujo Redco BVI'!H36 -> 0 | J36: =+'Flujo Redco BVI'!I36 -> 0 | K36: =+'Flujo Redco BVI'!J36 -> 0 | ... O36: =+'Flujo Redco BVI'!N36 -> 349514 | P36: =SUM(D36:O36) -> 1154049
B37: TOTAL | C37: SUMA OTROS INGRESOS | D37: =SUM(D28:D36) -> 279571.81 | E37: =SUM(E28:E36) -> 245598.41 | F37: =SUM(F28:F36) -> 172251.12 | G37: =SUM(G28:G36) -> 292209.81 | H37: =SUM(H28:H36) -> 608384.49 | I37: =SUM(I28:I36) -> 179700.25 | J37: =SUM(J28:J36) -> 253201.81 | K37: =SUM(K28:K36) -> 659206.51 | ... P37: =SUM(P28:P36) -> 4528894.2
B39: Chile | C39: EGRESO IVA DEBITO | D39: =+'Flujo Redco Chile'!C44*-1 -> -34979.334 | E39: =+'Flujo Redco Chile'!D44*-1 -> -63266.452 | F39: =+'Flujo Redco Chile'!E44*-1 -> -11946.348 | G39: =+'Flujo Redco Chile'!F44*-1 -> -31666.326 | H39: =+'Flujo Redco Chile'!G44*-1 -> -65886.451 | I39: =+'Flujo Redco Chile'!H44*-1 -> -41468.266 | J39: =+'Flujo Redco Chile'!I44*-1 -> -8884.088 | K39: =+'Flujo Redco Chile'!J44*-1 -> -86387.474 | ... O39: =+'Flujo Redco Chile'!N44*-1 -> -24253.626 | P39: =SUM(D39:O39) -> -489115.1
B40: Chile | C40: EGRESO CREDITOS | D40: =(+'Flujo Redco Chile'!C45+'Flujo Redco Chile'!C46+'Flujo Redco Chile'!C47)*-1 -> -27599.535 | E40: =(+'Flujo Redco Chile'!D45+'Flujo Redco Chile'!D46+'Flujo Redco Chile'!D47)*-1 -> -38631.281 | F40: =(+'Flujo Redco Chile'!E45+'Flujo Redco Chile'!E46+'Flujo Redco Chile'!E47)*-1 -> -30686.726 | G40: =(+'Flujo Redco Chile'!F45+'Flujo Redco Chile'!F46+'Flujo Redco Chile'!F47)*-1 -> -31866.891 | H40: =(+'Flujo Redco Chile'!G45+'Flujo Redco Chile'!G46+'Flujo Redco Chile'!G47)*-1 -> -32660.93 | I40: =(+'Flujo Redco Chile'!H45+'Flujo Redco Chile'!H46+'Flujo Redco Chile'!H47)*-1 -> -27706.253 | J40: =(+'Flujo Redco Chile'!I45+'Flujo Redco Chile'!I46+'Flujo Redco Chile'!I47)*-1 -> -31882.783 | K40: =(+'Flujo Redco Chile'!J45+'Flujo Redco Chile'!J46+'Flujo Redco Chile'!J47)*-1 -> -30717.742 | ... O40: =(+'Flujo Redco Chile'!N45+'Flujo Redco Chile'!N46+'Flujo Redco Chile'!N47)*-1 -> -30784.118 | P40: =SUM(D40:O40) -> -373754.78
B41: Chile | C41: CTA.CTE. EERR | D41: =(+'Flujo Redco Chile'!C52+'Flujo Redco Chile'!C54+'Flujo Redco Chile'!C55+'Flujo Redco Chile'!C56+'Flujo Redco Chile'!C57)*-1 -> -21128.81 | E41: =(+'Flujo Redco Chile'!D52+'Flujo Redco Chile'!D54+'Flujo Redco Chile'!D55+'Flujo Redco Chile'!D56+'Flujo Redco Chile'!D57)*-1 -> -5335.2929 | F41: =(+'Flujo Redco Chile'!E52+'Flujo Redco Chile'!E54+'Flujo Redco Chile'!E55+'Flujo Redco Chile'!E56+'Flujo Redco Chile'!E57)*-1 -> -20323.139 | G41: =(+'Flujo Redco Chile'!F52+'Flujo Redco Chile'!F54+'Flujo Redco Chile'!F55+'Flujo Redco Chile'!F56+'Flujo Redco Chile'!F57)*-1 -> -68310.75 | H41: =(+'Flujo Redco Chile'!G52+'Flujo Redco Chile'!G54+'Flujo Redco Chile'!G55+'Flujo Redco Chile'!G56+'Flujo Redco Chile'!G57)*-1 -> -25408.954 | I41: =(+'Flujo Redco Chile'!H52+'Flujo Redco Chile'!H54+'Flujo Redco Chile'!H55+'Flujo Redco Chile'!H56+'Flujo Redco Chile'!H57)*-1 -> -19313.305 | J41: =(+'Flujo Redco Chile'!I52+'Flujo Redco Chile'!I54+'Flujo Redco Chile'!I55+'Flujo Redco Chile'!I56+'Flujo Redco Chile'!I57)*-1 -> -66329.145 | K41: =(+'Flujo Redco Chile'!J52+'Flujo Redco Chile'!J54+'Flujo Redco Chile'!J55+'Flujo Redco Chile'!J56+'Flujo Redco Chile'!J57)*-1 -> -7645.6223 | ... O41: =(+'Flujo Redco Chile'!N52+'Flujo Redco Chile'!N54+'Flujo Redco Chile'!N55+'Flujo Redco Chile'!N56+'Flujo Redco Chile'!N57)*-1 -> -47905.397 | P41: =SUM(D41:O41) -> -289705.24
B42: Chile | C42: CTA.CTE. EERR (REDTEC) | D42: =+'Flujo Redco Chile'!C53*-1 -> -24259.657 | E42: =+'Flujo Redco Chile'!D53*-1 -> -113524.2 | F42: =+'Flujo Redco Chile'!E53*-1 -> -57052.603 | G42: =+'Flujo Redco Chile'!F53*-1 -> -140964.71 | H42: =+'Flujo Redco Chile'!G53*-1 -> -9291.9936 | I42: =+'Flujo Redco Chile'!H53*-1 -> 0 | J42: =+'Flujo Redco Chile'!I53*-1 -> 0 | K42: =+'Flujo Redco Chile'!J53*-1 -> 0 | ... O42: =+'Flujo Redco Chile'!N53*-1 -> -388.07725 | P42: =SUM(D42:O42) -> -372695.6
B43: Perú | C43: EGRESO IVA DEBITO | D43: =+'Flujo Redco Perú'!C44*-1 -> -42494 | E43: =+'Flujo Redco Perú'!D44*-1 -> 0 | F43: =+'Flujo Redco Perú'!E44*-1 -> -5448 | G43: =+'Flujo Redco Perú'!F44*-1 -> -1998 | H43: =+'Flujo Redco Perú'!G44*-1 -> -49989 | I43: =+'Flujo Redco Perú'!H44*-1 -> -41625 | J43: =+'Flujo Redco Perú'!I44*-1 -> -37651 | K43: =+'Flujo Redco Perú'!J44*-1 -> -102790 | ... O43: =+'Flujo Redco Perú'!N44*-1 -> -36493 | P43: =SUM(D43:O43) -> -409309
B44: Perú | C44: CTA.CTE. EERR | D44: =+'Flujo Redco Perú'!C54*-1 -> 0 | E44: =+'Flujo Redco Perú'!D54*-1 -> 0 | F44: =+'Flujo Redco Perú'!E54*-1 -> -14000 | G44: =+'Flujo Redco Perú'!F54*-1 -> 0 | H44: =+'Flujo Redco Perú'!G54*-1 -> 0 | I44: =+'Flujo Redco Perú'!H54*-1 -> -14000 | J44: =+'Flujo Redco Perú'!I54*-1 -> 0 | K44: =+'Flujo Redco Perú'!J54*-1 -> -472152 | ... O44: =+'Flujo Redco Perú'!N54*-1 -> -100000 | P44: =SUM(D44:O44) -> -928209
B45: Brasil | C45: EGRESO IVA DEBITO | D45: =+'Flujo Redco Brasil'!C37*-1 -> -13957 | E45: =+'Flujo Redco Brasil'!D37*-1 -> -15243 | F45: =+'Flujo Redco Brasil'!E37*-1 -> -7945 | G45: =+'Flujo Redco Brasil'!F37*-1 -> -26398 | H45: =+'Flujo Redco Brasil'!G37*-1 -> -9411 | I45: =+'Flujo Redco Brasil'!H37*-1 -> -12454 | J45: =+'Flujo Redco Brasil'!I37*-1 -> -18530 | K45: =+'Flujo Redco Brasil'!J37*-1 -> -27561 | ... O45: =+'Flujo Redco Brasil'!N37*-1 -> -95607 | P45: =SUM(D45:O45) -> -375161
B46: Brasil | C46: CTA.CTE. EERR | H46: =+'Flujo Redco Brasil'!G43*-1 -> -133710 | I46: =+'Flujo Redco Brasil'!H43*-1 -> 0 | P46: =SUM(D46:O46) -> -133710
B47: Brasil | C47: CTA.CTE. EERR | H47: =+'Flujo Redco USA'!G46*-1 -> -281858 | P47: =SUM(D47:O47) -> -281858
B48: TOTAL | C48: SUMA OTROS EGRESOS | D48: =SUM(D39:D47) -> -164418.34 | E48: =SUM(E39:E47) -> -236000.23 | F48: =SUM(F39:F47) -> -147401.82 | G48: =SUM(G39:G47) -> -301204.68 | H48: =SUM(H39:H47) -> -608216.33 | I48: =SUM(I39:I47) -> -156566.82 | J48: =SUM(J39:J47) -> -163277.02 | K48: =SUM(K39:K47) -> -727253.84 | ... P48: =SUM(P39:P47) -> -3653517.7
B50: País | C50: Concepto | D50: 45658 | E50: 45689 | F50: 45717 | G50: 45748 | H50: 45778 | I50: 45809 | J50: 45839 | K50: 45870 | L50: 45901 | M50: 45931 | N50: 45962 | O50: 45992 | P50: Total
B51: Chile | C51: RESULTADO CAJA | D51: =SUM(D20+D28+D30+D32+D33+D35+D39+D41+D42+D40) -> 118395.56 | E51: =SUM(E20+E28+E30+E32+E33+E35+E39+E41+E42+E40) -> 133162.17 | F51: =SUM(F20+F28+F30+F32+F33+F35+F39+F41+F42+F40) -> -69890.423 | G51: =SUM(G20+G28+G30+G32+G33+G35+G39+G41+G42+G40) -> -113200.73 | H51: =SUM(H20+H28+H30+H32+H33+H35+H39+H41+H42+H40) -> -40765.558 | I51: =SUM(I20+I28+I30+I32+I33+I35+I39+I41+I42+I40) -> -48061.672 | J51: =SUM(J20+J28+J30+J32+J33+J35+J39+J41+J42+J40) -> 191766.35 | K51: =SUM(K20+K28+K30+K32+K33+K35+K39+K41+K42+K40) -> 134254.5 | ... O51: =SUM(O20+O28+O30+O32+O33+O35+O39+O41+O42+O40) -> -1633.1953 | P51: =SUM(D51:O51) -> -165346.13
B52: Perú | C52: RESULTADO CAJA | D52: =+D21+D29+D34+D43+D44 -> 3798.15 | E52: =+E21+E29+E34+E43+E44 -> -2643 | F52: =+F21+F29+F34+F43+F44 -> 65135 | G52: =+G21+G29+G34+G43+G44 -> -1064.3 | H52: =+H21+H29+H34+H43+H44 -> -4999 | I52: =+I21+I29+I34+I43+I44 -> 42095 | J52: =+J21+J29+J34+J43+J44 -> 48879 | K52: =+K21+K29+K34+K43+K44 -> -32506 | ... O52: =+O21+O29+O34+O43+O44 -> -25297 | P52: =SUM(D52:O52) -> -460961.45
B53: Brasil | C53: RESULTADO CAJA | D53: =+D22+D31+D45 -> 51910 | E53: =+E22+E31+E45 -> 16991 | F53: =+F22+F31+F45 -> 61952 | G53: =+G22+G31+G45 -> 18807.3 | H53: =+H22+H31+H45+H46 -> -137850 | I53: =+I22+I31+I45+I46 -> -22177 | J53: =+J22+J31+J45+J46 -> -1832 | K53: =+K22+K31+K45+K46 -> 70616 | L53: =+L22+L31+L45+L46 -> 104282 | M53: =+M22+M31+M45+M46 -> 244856 | N53: =+N22+N31+N45+N46 -> 135142 | O53: =+O22+O31+O45+O46 -> 105508.51 | P53: =SUM(D53:O53) -> 648205.81
B54: USA | C54: RESULTADO CAJA | D54: =SUM(D23) -> 150438 | E54: =SUM(E23) -> 241440.21 | F54: =SUM(F23) -> 82798 | G54: =SUM(G23) -> 159302 | H54: =SUM(H23+H47) -> -134434 | I54: =SUM(I23+I47) -> 57618 | J54: =SUM(J23) -> -10017 | K54: =SUM(K23) -> 18985 | L54: =SUM(L23) -> -1000 | M54: =SUM(M23) -> -43411 | N54: =SUM(N23) -> -1000 | O54: =SUM(O23) -> -39625 | P54: =SUM(D54:O54) -> 481094.21
B55: BVI | C55: RESULTADO CAJA | D55: =+D24+D36 -> -14044 | E55: =+E24+E36 -> 21682 | F55: =+F24+F36 -> 45478 | G55: =+G24+G36 -> -14380 | H55: =+H24+H36 -> 399568 | I55: =+I24+I36 -> 156951 | J55: =+J24+J36 -> -5684.8 | K55: =+K24+K36 -> 93839.2 | ... O55: =+O24+O36 -> 343829.2 | P55: =SUM(D55:O55) -> 1399151.2
B56: TOTAL | C56: RESULTADO CAJA | D56: =SUM(D51:D55) -> 310497.71 | E56: =SUM(E51:E55) -> 410632.38 | F56: =SUM(F51:F55) -> 185472.58 | G56: =SUM(G51:G55) -> 49464.274 | H56: =SUM(H51:H55) -> 81519.442 | I56: =SUM(I51:I55) -> 186425.33 | J56: =SUM(J51:J55) -> 223111.55 | K56: =SUM(K51:K55) -> 285188.7 | ... O56: =SUM(O51:O55) -> 382782.51 | P56: =SUM(D56:O56) -> 1902143.6
B58: CAJA FINAL | C58: CAJA FINAL | D58: =+D56+T9 -> 564489.87 | E58: =+D58+E56 -> 975122.25 | F58: =+E58+F56 -> 1160594.8 | G58: =+F58+G56 -> 1210059.1 | H58: =+G58+H56 -> 1291578.5 | I58: =+H58+I56 -> 1478003.9 | J58: =+I58+J56 -> 1701115.4 | K58: =+J58+K56 -> 1986304.1 | L58: =+K58+L56 -> 1888672.4 | ... O58: =+N58+O56 -> 2156135.8 | P58: =+O58 -> 2156135.8
B60: País | C60: Concepto | D60: 45658 | E60: 45689 | F60: 45717 | G60: 45748 | H60: 45778 | I60: 45809 | J60: 45839 | K60: 45870 | L60: 45901 | M60: 45931 | N60: 45962 | O60: 45992 | P60: Total
B61: Chile | C61: TOTAL CAJA | D61: =+'Flujo Redco Chile'!C62 -> 170652.7 | E61: =+'Flujo Redco Chile'!D62 -> 303814.87 | F61: =+'Flujo Redco Chile'!E62 -> 233924.45 | G61: =+'Flujo Redco Chile'!F62 -> 120723.72 | H61: =+'Flujo Redco Chile'!G62 -> 79958.162 | I61: =+'Flujo Redco Chile'!H62 -> 31896.49 | J61: =+'Flujo Redco Chile'!I62 -> 223662.84 | K61: =+'Flujo Redco Chile'!J62 -> 357917.35 | ... O61: =+'Flujo Redco Chile'!N62 -> 23284.057 | P61: =+O61 -> 23284.057
B62: Perú | C62: TOTAL CAJA | D62: =+'Flujo Redco Perú'!C58 -> 140565.84 | E62: =+'Flujo Redco Perú'!D58 -> 137922.84 | F62: =+'Flujo Redco Perú'!E58 -> 203057.84 | G62: =+'Flujo Redco Perú'!F58 -> 201993.54 | H62: =+'Flujo Redco Perú'!G58 -> 196994.54 | I62: =+'Flujo Redco Perú'!H58 -> 239089.54 | J62: =+'Flujo Redco Perú'!I58 -> 287968.54 | K62: =+'Flujo Redco Perú'!J58 -> 255462.54 | ... O62: =+'Flujo Redco Perú'!N58 -> 80817.904 | P62: =+O62 -> 80817.904
B63: Brasil | C63: TOTAL CAJA | D63: =+'Flujo Redco Brasil'!C49 -> 61532.33 | E63: =+'Flujo Redco Brasil'!D49 -> 78523.33 | F63: =+'Flujo Redco Brasil'!E49 -> 140475.33 | G63: =+'Flujo Redco Brasil'!F49 -> 159282.63 | H63: =+'Flujo Redco Brasil'!G49 -> 21432.63 | I63: =+'Flujo Redco Brasil'!H49 -> -744.37 | J63: =+'Flujo Redco Brasil'!I49 -> -2576.37 | K63: =+'Flujo Redco Brasil'!J49 -> 68039.63 | ... O63: =+'Flujo Redco Brasil'!N49 -> 389088.14 | P63: =+O63 -> 389088.14
B64: USA | C64: TOTAL CAJA | D64: =+'Flujo Redco USA'!C51 -> 205783 | E64: =+'Flujo Redco USA'!D51 -> 447223.21 | F64: =+'Flujo Redco USA'!E51 -> 530021.21 | G64: =+'Flujo Redco USA'!F51 -> 689323.21 | H64: =+'Flujo Redco USA'!G51 -> 554889.21 | I64: =+'Flujo Redco USA'!H51 -> 612507.21 | J64: =+'Flujo Redco USA'!I51 -> 602490.21 | K64: =+'Flujo Redco USA'!J51 -> 621475.21 | ... O64: =+'Flujo Redco USA'!N51 -> 69763.21 | P64: =+O64 -> 69763.21
B65: BVI | C65: TOTAL CAJA | D65: =+'Flujo Redco BVI'!C51 -> -14044 | E65: =+'Flujo Redco BVI'!D51 -> 7638 | F65: =+'Flujo Redco BVI'!E51 -> 53116 | G65: =+'Flujo Redco BVI'!F51 -> 38736 | H65: =+'Flujo Redco BVI'!G51 -> 438304 | I65: =+'Flujo Redco BVI'!H51 -> 595255 | J65: =+'Flujo Redco BVI'!I51 -> 589570.2 | K65: =+'Flujo Redco BVI'!J51 -> 683409.4 | L65: =+'Flujo Redco BVI'!K51-1 -> 677723.6 | M65: =+'Flujo Redco BVI'!L51 -> 782793.8 | N65: =+'Flujo Redco BVI'!M51 -> 1055322 | O65: =+'Flujo Redco BVI'!N51 -> 1399151.2 | P65: =+O65 -> 1399151.2
B66: SALDO CAJA | C66: SALDO CAJA | D66: =SUM(D61:D65) -> 564489.87 | E66: =SUM(E61:E65) -> 975122.25 | F66: =SUM(F61:F65) -> 1160594.8 | G66: =SUM(G61:G65) -> 1210059.1 | H66: =SUM(H61:H65) -> 1291578.5 | I66: =SUM(I61:I65) -> 1478003.9 | J66: =SUM(J61:J65) -> 1701115.4 | K66: =SUM(K61:K65) -> 1986304.1 | ... P66: =SUM(P61:P65) -> 1962104.5 | R66: =+P66-P58 -> -194031.29

Sheet Flujo Anual por unidad 2025
B3: FLUJO CAJA CONSOLIDADO GESTION POR EMPRESA
B5: FLUJO OPERACIONAL ACUMULADA POR EMPRES 2025 | C5: US$ | H5: ACUMULADO
B6: RESUMEN | C6: CHILE | D6: PERU | E6: BRASIL | F6: USA | G6: BVI | H6: año 2025
B7: TOTAL INGRESOS OPERACIONALES PEND. 2024 | C7: =+'Flujo Redco Chile'!O10 -> 487680.19 | D7: =+'Flujo Redco Perú'!O11 -> 132119 | E7: =+'Flujo Redco Brasil'!O12 -> 182679 | F7: =+'Flujo Redco USA'!O11 -> 150453 | G7: =+'Flujo Redco BVI'!O11 -> 67160 | H7: =+SUM(C7:G7) -> 1020091.2
B8: TOTAL INGRESOS OPERACIONALES 2025 | C8: =+'Flujo Redco Chile'!O11 -> 3104446.7 | D8: =+'Flujo Redco Perú'!O12 -> 2285234 | E8: =+'Flujo Redco Brasil'!O13 -> 1414413.2 | F8: =+'Flujo Redco USA'!O12 -> 1054862.2 | G8: =+'Flujo Redco BVI'!O12 -> 271569 | H8: =SUM(C8:G8) -> 8130525.2
B9: SUMA TOTAL INGRESOS 2025 | C9: =SUM(C7:C8) -> 3592126.9 | D9: =SUM(D7:D8) -> 2417353 | E9: =SUM(E7:E8) -> 1597092.2 | F9: =SUM(F7:F8) -> 1205315.2 | G9: =SUM(G7:G8) -> 338729 | H9: =SUM(H7:H8) -> 9150616.3
B11: COSTOS OPERACIONALES
B12: SUELDOS OPERACIONALES | C12: =+'Flujo Redco Chile'!O15 -> 3082559.8 | D12: =+'Flujo Redco Perú'!O16 -> 983242 | E12: =+'Flujo Redco Brasil'!O17 -> 133388 | F12: =+'Flujo Redco USA'!O16 -> 0 | G12: =+'Flujo Redco BVI'!O16 -> 0 | H12: =SUM(C12:G12) -> 4199189.8
B13: HONORARIOS OPERACIONALES | C13: =+'Flujo Redco Chile'!O16 -> 731847.19 | D13: =+'Flujo Redco Perú'!O17 -> 361181.94 | E13: =+'Flujo Redco Brasil'!O18 -> 159204 | F13: =+'Flujo Redco USA'!O17 -> 420945 | G13: =+'Flujo Redco BVI'!O17 -> 77626.8 | H13: =SUM(C13:G13) -> 1750804.9
B14: GASTOS OPERACIONALES | C14: =+'Flujo Redco Chile'!O17 -> 520272.6 | D14: =+'Flujo Redco Perú'!O18 -> 53547.85 | E14: =+'Flujo Redco Brasil'!O19 -> 78515.4 | F14: =+'Flujo Redco USA'!O18 -> 5320 | G14: =+'Flujo Redco BVI'!O18 -> 0 | H14: =SUM(C14:G14) -> 657655.85
B15: TOTAL COSTOS OPERACIONALES | C15: =SUM(C12:C14) -> 4334679.6 | D15: =SUM(D12:D14) -> 1397971.8 | E15: =SUM(E12:E14) -> 371107.4 | F15: =SUM(F12:F14) -> 426265 | G15: =SUM(G12:G14) -> 77626.8 | H15: =SUM(H12:H14) -> 6607650.6
B17: COSTOS ADMINISTRATIVOS
B18: SUELDOS ADMINISTRACION | C18: =+'Flujo Redco Chile'!O21 -> 363398.77 | D18: ='Flujo Redco Perú'!O24 -> 0 | E18: ='Flujo Redco Brasil'!O23 -> 16816 | F18: ='Flujo Redco USA'!O25 -> 0 | G18: ='Flujo Redco BVI'!O25 -> 0 | H18: =SUM(C18:G18) -> 380214.77
B19: GASTOS DE ADMINISTRACION | C19: =+'Flujo Redco Chile'!O22 -> 279135.48 | D19: ='Flujo Redco Perú'!O25 -> 181782 | E19: ='Flujo Redco Brasil'!O24 -> 60943 | F19: ='Flujo Redco USA'!O26 -> 16098 | G19: ='Flujo Redco BVI'!O26 -> 0 | H19: =SUM(C19:G19) -> 537958.48
B20: TOTAL COSTOS ADMINISTRATIVOS | C20: =SUM(C18:C19) -> 642534.25 | D20: =SUM(D18:D19) -> 181782 | E20: =SUM(E18:E19) -> 77759 | F20: =SUM(F18:F19) -> 16098 | G20: =SUM(G18:G19) -> 0 | H20: =SUM(H18:H19) -> 918173.25
B22: ACTIVO FIJO+REMODELACIONES | C22: =+'Flujo Redco Chile'!O25 -> 22053.685 | D22: =+'Flujo Redco Perú'!O28 -> 152109 | E22: =+'Flujo Redco Brasil'!O27 -> 2851 | F22: =+'Flujo Redco USA'!O29 -> 0 | G22: =+'Flujo Redco BVI'!O29 -> 16000 | H22: =SUM(C22:G22) -> 193013.68
B24: RESULTADO OPERACIONAL | C24: =SUM(C9-C15-C20-C22) -> -1407140.6 | D24: =SUM(D9-D15-D20-D22) -> 685490.21 | E24: =SUM(E9-E15-E20-E22) -> 1145374.8 | F24: =SUM(F9-F15-F20-F22) -> 762952.21 | G24: =SUM(G9-G15-G20-G22) -> 245102.2 | H24: =SUM(H9-H15-H20-H22) -> 1431778.8
B26: OTROS INGRESOS NO OPERACIONALES | C26: CHILE | D26: PERU | E26: BRASIL | F26: USA | G26: BVI | H26: ACUMULADO
B27: INGRESO IVA DEBITO FACTURACION | C27: =+'Flujo Redco Chile'!O31 -> 713037.07 | D27: =+'Flujo Redco Perú'!O35 -> 544185 | E27: 0 | F27: 0 | G27: 0 | H27: =SUM(C27:G27) -> 1257222.1
B28: INGRESO CUENTA CORRIENTE EERR | C28: =+'Flujo Redco Chile'!O32+'Flujo Redco Chile'!O35+'Flujo Redco Chile'!O36+'Flujo Redco Chile'!O37+'Flujo Redco Chile'!O34 -> 1947186.9 | D28: =+'Flujo Redco Perú'!O36 -> 51893 | E28: 0 | F28: 0 | G28: 0 | H28: =SUM(C28:G28) -> 1999079.9
B29: DEVOLUCION BOLETA DE GARANTIA CMP | C29: =+'Flujo Redco Chile'!O38 -> 21714.461 | E29: 0 | F29: 0 | G29: 0 | H29: =SUM(C29:G29) -> 21714.461
B30: OTROS INGRESOS NO OP. | C30: =+'Flujo Redco Chile'!O39+'Flujo Redco Chile'!O40 -> 189812.87 | E30: =+'Flujo Redco Brasil'!O34 -> 11702 | F30: =+'Flujo Redco USA'!O38 -> 0 | G30: =+'Flujo Redco BVI'!O38 -> 1154049 | H30: =SUM(C30:G30) -> 1355563.9
B31: OTROS INGRESOS NO OPERACIONALES | C31: =SUM(C27:C30) -> 2871751.3 | D31: =SUM(D27:D30) -> 596078 | E31: =SUM(E27:E30) -> 11702 | F31: =SUM(F27:F30) -> 0 | G31: =SUM(G27:G30) -> 1154049 | H31: =SUM(H27:H30) -> 4633580.3
B33: OTROS EGRESOS NO OPERACIONALES
B34: IMPUESTOS PPM-IVA-IMPTO.ADICIONAL | C34: =+'Flujo Redco Chile'!O44 -> 489115.1 | D34: =+'Flujo Redco Perú'!O44 -> 409309 | E34: =+'Flujo Redco Brasil'!O37 -> 375161 | F34: =+'Flujo Redco USA'!O41 -> 6408 | G34: =+'Flujo Redco BVI'!O41 -> 0 | H34: =SUM(C34:G34) -> 1279993.1
B35: PAGOS DE CREDITOS | C35: =+'Flujo Redco Chile'!O45+'Flujo Redco Chile'!O46+'Flujo Redco Chile'!O47 -> 373754.78 | D35: =+SUM('Flujo Redco Perú'!O45:O47) -> 0 | H35: =SUM(C35:G35) -> 373754.78
B36: APORTE FFMM | C36: =SUM('Flujo Redco Chile'!F48) -> 0 | H36: =SUM(C36:F36) -> 0
B37: TOTAL EGRESOS NO OPERACIONALES | C37: =SUM(C34:C36) -> 862869.88 | D37: =SUM(D34:D35) -> 409309 | E37: =SUM(E34:E35) -> 375161 | F37: =SUM(F34:F35) -> 6408 | G37: =SUM(G34:G35) -> 0 | H37: =SUM(H34:H36) -> 1653747.9
B39: OTROS EGRESOS CTA.CTE. EERR | C39: =+'Flujo Redco Chile'!O58 -> 662400.84 | D39: =+'Flujo Redco Perú'!O54 -> 928209 | E39: =+'Flujo Redco Brasil'!O43 -> 411923 | F39: =+'Flujo Redco USA'!O47 -> 742126 | G39: =+'Flujo Redco BVI'!O47 -> 0 | H39: =SUM(C39:G39) -> 2744658.8
B41: RESULTADO NO OPERACIONAL | C41: =SUM(C31-C37-C39) -> 1346480.6 | D41: =SUM(D31-D37-D39) -> -741440 | E41: =SUM(E31-E37-E39) -> -775382 | F41: =SUM(F31-F37-F39) -> -748534 | G41: =SUM(G31-G37-G39) -> 1154049 | H41: =SUM(H31-H37-H39) -> 235173.59
B43: SALDO FLUJO 2025 | C43: =SUM(C24+C41) -> -60659.99 | D43: =SUM(D24+D41) -> -55949.79 | E43: =SUM(E24+E41) -> 369992.81 | F43: =SUM(F24+F41) -> 14418.21 | G43: =SUM(G24+G41) -> 1399151.2 | H43: =SUM(H24+H41) -> 1666952.4
B44: SALDO INICIAL 01-01-2025 | C44: =+'Flujo Redco Chile'!C8 -> 52257.137 | D44: =+'Flujo Redco Perú'!C9 -> 136767.69 | E44: =+'Flujo Redco Brasil'!C9 -> 9622.33 | F44: =+'Flujo Redco USA'!C9 -> 55345 | G44: =+'Flujo Redco BVI'!C9 -> 0 | H44: =+C44+D44+E44+F44 -> 253992.16
B45: SALDO CAJA CIERRE 2025 | C45: =SUM(C43:C44) -> -8402.853 | D45: =SUM(D43:D44) -> 80817.904 | E45: =SUM(E43:E44) -> 379615.14 | F45: =SUM(F43:F44) -> 69763.21 | G45: =SUM(G43:G44) -> 1399151.2 | H45: =SUM(H43:H44) -> 1920944.6
C46: =+'Flujo Redco Chile'!O62 -> 23284.057 | D46: =+'Flujo Redco Perú'!O58 -> 80817.904 | E46: =+'Flujo Redco Brasil'!O49 -> 389088.14 | F46: =+'Flujo Redco USA'!O51 -> 69763.21 | G46: =+'Flujo Redco BVI'!O51 -> 1399151.2 | H46: =+'Tabla datos unidades'!P66 -> 1962104.5

Sheet Flujo Consolidado por mes
B3: FLUJO CAJA MENSUAL CONSOLIDADO
B4: 2025
B6: FLUJO OPERACIONAL MENSUAL 2025 | C6: US$ | P6: 1000 | AL6: 1000
B7: RESUMEN | C7: 45658 | D7: 45689 | E7: 45717 | F7: 45748 | G7: 45778 | H7: 45809 | I7: 45839 | J7: 45870 | K7: 45901 | L7: ACUMULADO
O9: Ítem | P9: 45688 | Q9: 45716 | R9: 45747 | S9: 45777 | T9: 45808 | U9: 45838 | V9: Total | W9: Promedio | Z9: Ítem | AA9: 45688 | AB9: 45716 | AC9: 45747 | AD9: 45777 | AE9: 45808 | AF9: 45838 | AG9: Total | AH9: Promedio | AK9: Ítem | AL9: Chile | AM9: Perú | AN9: Brasil | AO9: USA | AP9: Total
B10: TOTAL INGRESOS OPERACIONALES PEND. 2024 | C10: =+'Flujo Redco Chile'!C10+'Flujo Redco Perú'!C11+'Flujo Redco Brasil'!C12+'Flujo Redco USA'!C11+'Flujo Redco BVI'!C11 -> 658814.12 | D10: =+'Flujo Redco Chile'!D10+'Flujo Redco Perú'!D11+'Flujo Redco Brasil'!D12+'Flujo Redco USA'!D11+'Flujo Redco BVI'!D11 -> 273304.06 | E10: =+'Flujo Redco Chile'!E10+'Flujo Redco Perú'!E11+'Flujo Redco Brasil'!E12+'Flujo Redco USA'!E11+'Flujo Redco BVI'!E11 -> 87972 | F10: =+'Flujo Redco Chile'!F10+'Flujo Redco Perú'!F11+'Flujo Redco Brasil'!F12+'Flujo Redco USA'!F11+'Flujo Redco BVI'!F11 -> 0 | G10: =+'Flujo Redco Chile'!G10+'Flujo Redco Perú'!G11+'Flujo Redco Brasil'!G12+'Flujo Redco USA'!G11+'Flujo Redco BVI'!G11 -> 0 | H10: =+'Flujo Redco Chile'!H10+'Flujo Redco Perú'!H11+'Flujo Redco Brasil'!H12+'Flujo Redco USA'!H11+'Flujo Redco BVI'!H11 -> 0 | I10: =+'Flujo Redco Chile'!I10+'Flujo Redco Perú'!I11+'Flujo Redco Brasil'!I12+'Flujo Redco USA'!I11+'Flujo Redco BVI'!I11 -> 0 | J10: =+'Flujo Redco Chile'!J10+'Flujo Redco Perú'!J11+'Flujo Redco Brasil'!J12+'Flujo Redco USA'!J11+'Flujo Redco BVI'!J11 -> 0 | K10: =+'Flujo Redco Chile'!K10+'Flujo Redco Perú'!K11+'Flujo Redco Brasil'!K12+'Flujo Redco USA'!K11+'Flujo Redco BVI'!K11-1 -> 0 | L10: =SUM(C10:K10) -> 1020090.2 | O10: Sueldos | P10: =(+C15)/1000 -> 357.04875 | Q10: =(+D15)/1000 -> 288.64786 | R10: =(+E15)/1000 -> 295.05654 | S10: =(+F15)/1000 -> 303.79496 | T10: =(+G15)/1000 -> 317.00841 | U10: =(+H15)/1000 -> 332.72499 | V10: =+SUM(P10:U10) -> 1894.2815 | W10: =+AVERAGE(P10:U10) -> 315.71359 | X10: =+W10/$W$16 -> 0.55085149 | Z10: Sueldos | AA10: =+P10-99 -> 258.04875 | AB10: =+Q10 -> 288.64786 | AC10: =+R10 -> 295.05654 | AD10: =+S10 -> 303.79496 | AE10: =+T10 -> 317.00841 | AF10: =+U10 -> 332.72499 | AG10: =+SUM(AA10:AF10) -> 1795.2815 | AH10: =+AVERAGE(AA10:AF10) -> 299.21359 | AK10: Sueldos | AL10: =1467.08134549356-99 -> 1368.0813 | AM10: 388.098 | AN10: 43.03 | AO10: 0 | AP10: =SUM(AL10:AO10) -> 1799.2093
B11: TOTAL INGRESOS OPERACIONALES 2025 | C11: =+'Flujo Redco Chile'!C11+'Flujo Redco Perú'!C12+'Flujo Redco Brasil'!C13+'Flujo Redco USA'!C12+'Flujo Redco BVI'!C12 -> 58351.609 | D11: =+'Flujo Redco Chile'!D11+'Flujo Redco Perú'!D12+'Flujo Redco Brasil'!D13+'Flujo Redco USA'!D12+'Flujo Redco BVI'!D12 -> 661290.77 | E11: =+'Flujo Redco Chile'!E11+'Flujo Redco Perú'!E12+'Flujo Redco Brasil'!E13+'Flujo Redco USA'!E12+'Flujo Redco BVI'!E12 -> 690458.46 | F11: =+'Flujo Redco Chile'!F11+'Flujo Redco Perú'!F12+'Flujo Redco Brasil'!F13+'Flujo Redco USA'!F12+'Flujo Redco BVI'!F12 -> 613921.18 | G11: =+'Flujo Redco Chile'!G11+'Flujo Redco Perú'!G12+'Flujo Redco Brasil'!G13+'Flujo Redco USA'!G12+'Flujo Redco BVI'!G12 -> 647405.08 | H11: =+'Flujo Redco Chile'!H11+'Flujo Redco Perú'!H12+'Flujo Redco Brasil'!H13+'Flujo Redco USA'!H12+'Flujo Redco BVI'!H12 -> 807411.07 | I11: =+'Flujo Redco Chile'!I11+'Flujo Redco Perú'!I12+'Flujo Redco Brasil'!I13+'Flujo Redco USA'!I12+'Flujo Redco BVI'!I12 -> 774989.75 | J11: =+'Flujo Redco Chile'!J11+'Flujo Redco Perú'!J12+'Flujo Redco Brasil'!J13+'Flujo Redco USA'!J12+'Flujo Redco BVI'!#REF! -> #REF! | K11: =+'Flujo Redco Chile'!K11+'Flujo Redco Perú'!K12+'Flujo Redco Brasil'!K13+'Flujo Redco USA'!K12+'Flujo Redco BVI'!J12 -> 720169.05 | L11: =SUM(C11:K11) -> #REF! | O11: Honorarios | P11: =(+C16)/1000 -> 58.297763 | Q11: =(+D16)/1000 -> 115.21987 | R11: =(+E16)/1000 -> 127.98133 | S11: =(+F16)/1000 -> 97.673125 | T11: =(+G16)/1000 -> 122.48897 | U11: =(+H16)/1000 -> 167.93195 | V11: =+SUM(P11:U11) -> 689.593 | W11: =+AVERAGE(P11:U11) -> 114.93217 | X11: =+W11/$W$16 -> 0.20053162 | Z11: Sueldos administrativos | AA11: =+P13+28 -> 43.122477 | AB11: =+Q13 -> 42.528748 | AC11: =+R13 -> 40.494749 | AD11: =+S13 -> 39.99907 | AE11: =+T13 -> 35.904985 | AF11: =+U13 -> 36.031018 | AG11: =+SUM(AA11:AF11) -> 238.08105 | AH11: =+AVERAGE(AA11:AF11) -> 39.680175 | AK11: Sueldos administrativos | AL11: =185.446213519313+28 -> 213.44621 | AM11: 0 | AN11: 2.867 | AO11: 0 | AP11: =SUM(AL11:AO11) -> 216.31321
B12: SUMA TOTAL INGRESOS 2025 | C12: =SUM(C10:C11) -> 717165.73 | D12: =SUM(D10:D11) -> 934594.83 | E12: =SUM(E10:E11) -> 778430.46 | F12: =SUM(F10:F11) -> 613921.18 | G12: =SUM(G10:G11) -> 647405.08 | H12: =SUM(H10:H11) -> 807411.07 | I12: =SUM(I10:I11) -> 774989.75 | J12: =SUM(J10:J11) -> #REF! | ... L12: =SUM(L10:L11) -> #REF! | O12: Gasto Operacional | P12: =(+C17)/1000 -> 55.146402 | Q12: =(+D17)/1000 -> 43.459546 | R12: =(+E17)/1000 -> 107.99125 | S12: =(+F17)/1000 -> 43.218217 | T12: =(+G17)/1000 -> 19.887892 | U12: =(+H17)/1000 -> 48.528438 | V12: =+SUM(P12:U12) -> 318.23174 | W12: =+AVERAGE(P12:U12) -> 53.038624 | X12: =+W12/$W$16 -> 0.092540855 | Z12: Gasto Administrativo | AA12: =+P14+4+4 -> 25.728622 | AB12: =+Q14-4 -> 34.142619 | AC12: =+R14 -> 36.608313 | AD12: =+S14 -> 53.393674 | AE12: =+T14 -> 34.088224 | AF12: =+U14-25 -> 25.449773 | AG12: =+SUM(AA12:AF12) -> 209.41123 | AH12: =+AVERAGE(AA12:AF12) -> 34.901871 | AK12: Gasto Administrativo | AL12: =127.745530042918+8-4-25+1 -> 107.74553 | AM12: 81.734 | AN12: 30.67 | AO12: 8.551 | AP12: =SUM(AL12:AO12) -> 228.70053
O13: Sueldos administrativos | P13: =(+C21)/1000 -> 15.122477 | Q13: =(+D21)/1000 -> 42.528748 | R13: =(+E21)/1000 -> 40.494749 | S13: =(+F21)/1000 -> 39.99907 | T13: =(+G21)/1000 -> 35.904985 | U13: =(+H21)/1000 -> 36.031018 | V13: =+SUM(P13:U13) -> 210.08105 | W13: =+AVERAGE(P13:U13) -> 35.013508 | X13: =+W13/$W$16 -> 0.061090951 | Z13: Total | AA13: =SUM(AA10:AA12) -> 326.89985 | AB13: =SUM(AB10:AB12) -> 365.31922 | AC13: =SUM(AC10:AC12) -> 372.1596 | AD13: =SUM(AD10:AD12) -> 397.1877 | AE13: =SUM(AE10:AE12) -> 387.00162 | AF13: =SUM(AF10:AF12) -> 394.20578 | AG13: =+SUM(AA13:AF13) -> 2242.7738 | AH13: =+AVERAGE(AA13:AF13) -> 373.79563 | AK13: Total | AL13: =SUM(AL10:AL12) -> 1689.2731 | AM13: =SUM(AM10:AM12) -> 469.832 | AN13: =SUM(AN10:AN12) -> 76.567 | AO13: =SUM(AO10:AO12) -> 8.551 | AP13: =SUM(AL13:AO13) -> 2244.2231
B14: COSTOS OPERACIONALES | O14: Gasto Administrativo | P14: =(+C22)/1000 -> 17.728622 | Q14: =(+D22)/1000 -> 38.142619 | R14: =(+E22)/1000 -> 36.608313 | S14: =(+F22)/1000 -> 53.393674 | T14: =(+G22)/1000 -> 34.088224 | U14: =(+H22)/1000 -> 50.449773 | V14: =+SUM(P14:U14) -> 230.41123 | W14: =+AVERAGE(P14:U14) -> 38.401871 | X14: =+W14/$W$16 -> 0.067002907 | AI14: =+W16-AH13 -> 199.34176
B15: SUELDOS OPERACIONALES | C15: =+'Flujo Redco Chile'!C15+'Flujo Redco Perú'!C16+'Flujo Redco Brasil'!C17+'Flujo Redco USA'!C16+'Flujo Redco BVI'!C16 -> 357048.75 | D15: =+'Flujo Redco Chile'!D15+'Flujo Redco Perú'!D16+'Flujo Redco Brasil'!D17+'Flujo Redco USA'!D16+'Flujo Redco BVI'!D16 -> 288647.86 | E15: =+'Flujo Redco Chile'!E15+'Flujo Redco Perú'!E16+'Flujo Redco Brasil'!E17+'Flujo Redco USA'!E16+'Flujo Redco BVI'!E16 -> 295056.54 | F15: =+'Flujo Redco Chile'!F15+'Flujo Redco Perú'!F16+'Flujo Redco Brasil'!F17+'Flujo Redco USA'!F16+'Flujo Redco BVI'!F16 -> 303794.96 | G15: =+'Flujo Redco Chile'!G15+'Flujo Redco Perú'!G16+'Flujo Redco Brasil'!G17+'Flujo Redco USA'!G16+'Flujo Redco BVI'!G16 -> 317008.41 | H15: =+'Flujo Redco Chile'!H15+'Flujo Redco Perú'!H16+'Flujo Redco Brasil'!H17+'Flujo Redco USA'!H16+'Flujo Redco BVI'!H16 -> 332724.99 | I15: =+'Flujo Redco Chile'!I15+'Flujo Redco Perú'!I16+'Flujo Redco Brasil'!I17+'Flujo Redco USA'!I16+'Flujo Redco BVI'!I16 -> 364882.71 | J15: =+'Flujo Redco Chile'!J15+'Flujo Redco Perú'!J16+'Flujo Redco Brasil'!J17+'Flujo Redco USA'!J16+'Flujo Redco BVI'!J16 -> 345533.61 | K15: =+'Flujo Redco Chile'!K15+'Flujo Redco Perú'!K16+'Flujo Redco Brasil'!K17+'Flujo Redco USA'!K16+'Flujo Redco BVI'!K16 -> 391050.99 | L15: =SUM(C15:K15) -> 2995748.8 | O15: Activos | P15: =(+C25)/1000 -> 18.477487 | Q15: =(+D25)/1000 -> 5.562 | R15: =(+E25)/1000 -> 9.675 | S15: =(+F25)/1000 -> 17.383 | T15: =(+G25)/1000 -> 36.675314 | U15: =(+H25)/1000 -> 8.453 | V15: =+SUM(P15:U15) -> 96.225802 | W15: =+AVERAGE(P15:U15) -> 16.037634 | X15: =+W15/$W$16 -> 0.02798218 | AI15: =+AH13/W16 -> 0.65219202
B16: HONORARIOS OPERACIONALES | C16: =+'Flujo Redco Chile'!C16+'Flujo Redco Perú'!C17+'Flujo Redco Brasil'!C18+'Flujo Redco USA'!C17+'Flujo Redco BVI'!C17 -> 58297.763 | D16: =+'Flujo Redco Chile'!D16+'Flujo Redco Perú'!D17+'Flujo Redco Brasil'!D18+'Flujo Redco USA'!D17+'Flujo Redco BVI'!D17 -> 115219.87 | E16: =+'Flujo Redco Chile'!E16+'Flujo Redco Perú'!E17+'Flujo Redco Brasil'!E18+'Flujo Redco USA'!E17+'Flujo Redco BVI'!E17 -> 127981.33 | F16: =+'Flujo Redco Chile'!F16+'Flujo Redco Perú'!F17+'Flujo Redco Brasil'!F18+'Flujo Redco USA'!F17+'Flujo Redco BVI'!F17 -> 97673.125 | G16: =+'Flujo Redco Chile'!G16+'Flujo Redco Perú'!G17+'Flujo Redco Brasil'!G18+'Flujo Redco USA'!G17+'Flujo Redco BVI'!G17 -> 122488.97 | H16: =+'Flujo Redco Chile'!H16+'Flujo Redco Perú'!H17+'Flujo Redco Brasil'!H18+'Flujo Redco USA'!H17+'Flujo Redco BVI'!H17 -> 167931.95 | I16: =+'Flujo Redco Chile'!I16+'Flujo Redco Perú'!I17+'Flujo Redco Brasil'!I18+'Flujo Redco USA'!I17+'Flujo Redco BVI'!I17 -> 150747.83 | J16: =+'Flujo Redco Chile'!J16+'Flujo Redco Perú'!J17+'Flujo Redco Brasil'!J18+'Flujo Redco USA'!J17+'Flujo Redco BVI'!J17 -> 140211.47 | K16: =+'Flujo Redco Chile'!K16+'Flujo Redco Perú'!K17+'Flujo Redco Brasil'!K18+'Flujo Redco USA'!K17+'Flujo Redco BVI'!K17 -> 105300.18 | L16: =SUM(C16:K16) -> 1085852.5 | O16: Total | P16: =SUM(P10:P15) -> 521.8215 | Q16: =SUM(Q10:Q15) -> 533.56064 | R16: =SUM(R10:R15) -> 617.80718 | S16: =SUM(S10:S15) -> 555.46205 | T16: =SUM(T10:T15) -> 566.0538 | U16: =SUM(U10:U15) -> 644.11917 | V16: =+SUM(P16:U16) -> 3438.8243 | W16: =+AVERAGE(P16:U16) -> 573.13739 | X16: =SUM(X10:X15) -> 1 | AI16: =+AI14/W16 -> 0.34780798
B17: GASTOS OPERACIONALES | C17: =+'Flujo Redco Chile'!C17+'Flujo Redco Perú'!C18+'Flujo Redco Brasil'!C19+'Flujo Redco USA'!C18+'Flujo Redco BVI'!C18 -> 55146.402 | D17: =+'Flujo Redco Chile'!D17+'Flujo Redco Perú'!D18+'Flujo Redco Brasil'!D19+'Flujo Redco USA'!D18+'Flujo Redco BVI'!D18 -> 43459.546 | E17: =+'Flujo Redco Chile'!E17+'Flujo Redco Perú'!E18+'Flujo Redco Brasil'!E19+'Flujo Redco USA'!E18+'Flujo Redco BVI'!E18 -> 107991.25 | F17: =+'Flujo Redco Chile'!F17+'Flujo Redco Perú'!F18+'Flujo Redco Brasil'!F19+'Flujo Redco USA'!F18+'Flujo Redco BVI'!F18 -> 43218.217 | G17: =+'Flujo Redco Chile'!G17+'Flujo Redco Perú'!G18+'Flujo Redco Brasil'!G19+'Flujo Redco USA'!G18+'Flujo Redco BVI'!G18 -> 19887.892 | H17: =+'Flujo Redco Chile'!H17+'Flujo Redco Perú'!H18+'Flujo Redco Brasil'!H19+'Flujo Redco USA'!H18+'Flujo Redco BVI'!H18 -> 48528.438 | I17: =+'Flujo Redco Chile'!I17+'Flujo Redco Perú'!I18+'Flujo Redco Brasil'!I19+'Flujo Redco USA'!I18+'Flujo Redco BVI'!I18 -> 29408.506 | J17: =+'Flujo Redco Chile'!J17+'Flujo Redco Perú'!J18+'Flujo Redco Brasil'!J19+'Flujo Redco USA'!J18+'Flujo Redco BVI'!J18 -> 86643.267 | K17: =+'Flujo Redco Chile'!K17+'Flujo Redco Perú'!K18+'Flujo Redco Brasil'!K19+'Flujo Redco USA'!K18+'Flujo Redco BVI'!K18 -> 72880.804 | L17: =SUM(C17:K17) -> 507164.32
B18: TOTAL COSTOS OPERACIONALES | C18: =SUM(C15:C17) -> 470492.91 | D18: =SUM(D15:D17) -> 447327.27 | E18: =SUM(E15:E17) -> 531029.12 | F18: =SUM(F15:F17) -> 444686.3 | G18: =SUM(G15:G17) -> 459385.28 | H18: =SUM(H15:H17) -> 549185.38 | I18: =SUM(I15:I17) -> 545039.05 | J18: =SUM(J15:J17) -> 572388.35 | ... L18: =SUM(L15:L17) -> 4588765.6
B20: COSTOS ADMINISTRATIVOS
B21: SUELDOS ADMINISTRACION | C21: =+'Flujo Redco Chile'!C21+'Flujo Redco Perú'!C24+'Flujo Redco Brasil'!C23+'Flujo Redco USA'!C25+'Flujo Redco BVI'!C25 -> 15122.477 | D21: =+'Flujo Redco Chile'!D21+'Flujo Redco Perú'!D24+'Flujo Redco Brasil'!D23+'Flujo Redco USA'!D25+'Flujo Redco BVI'!D25 -> 42528.748 | E21: =+'Flujo Redco Chile'!E21+'Flujo Redco Perú'!E24+'Flujo Redco Brasil'!E23+'Flujo Redco USA'!E25+'Flujo Redco BVI'!E25 -> 40494.749 | F21: =+'Flujo Redco Chile'!F21+'Flujo Redco Perú'!F24+'Flujo Redco Brasil'!F23+'Flujo Redco USA'!F25+'Flujo Redco BVI'!F25 -> 39999.07 | G21: =+'Flujo Redco Chile'!G21+'Flujo Redco Perú'!G24+'Flujo Redco Brasil'!G23+'Flujo Redco USA'!G25+'Flujo Redco BVI'!G25 -> 35904.985 | H21: =+'Flujo Redco Chile'!H21+'Flujo Redco Perú'!H24+'Flujo Redco Brasil'!H23+'Flujo Redco USA'!H25+'Flujo Redco BVI'!H25 -> 36031.018 | I21: =+'Flujo Redco Chile'!I21+'Flujo Redco Perú'!I24+'Flujo Redco Brasil'!I23+'Flujo Redco USA'!I25+'Flujo Redco BVI'!I25 -> 36652.865 | J21: =+'Flujo Redco Chile'!J21+'Flujo Redco Perú'!J24+'Flujo Redco Brasil'!J23+'Flujo Redco USA'!J25+'Flujo Redco BVI'!J25 -> 40060.344 | K21: =+'Flujo Redco Chile'!K21+'Flujo Redco Perú'!K24+'Flujo Redco Brasil'!K23+'Flujo Redco USA'!K25+'Flujo Redco BVI'!K25 -> 41046.159 | L21: =SUM(C21:K21) -> 327840.42
B22: GASTOS DE ADMINISTRACION | C22: =+'Flujo Redco Chile'!C22+'Flujo Redco Perú'!C25+'Flujo Redco Brasil'!C24+'Flujo Redco USA'!C26+'Flujo Redco BVI'!C26 -> 17728.622 | D22: =+'Flujo Redco Chile'!D22+'Flujo Redco Perú'!D25+'Flujo Redco Brasil'!D24+'Flujo Redco USA'!D26+'Flujo Redco BVI'!D26 -> 38142.619 | E22: =+'Flujo Redco Chile'!E22+'Flujo Redco Perú'!E25+'Flujo Redco Brasil'!E24+'Flujo Redco USA'!E26+'Flujo Redco BVI'!E26 -> 36608.313 | F22: =+'Flujo Redco Chile'!F22+'Flujo Redco Perú'!F25+'Flujo Redco Brasil'!F24+'Flujo Redco USA'!F26+'Flujo Redco BVI'!F26 -> 53393.674 | G22: =+'Flujo Redco Chile'!G22+'Flujo Redco Perú'!G25+'Flujo Redco Brasil'!G24+'Flujo Redco USA'!G26+'Flujo Redco BVI'!G26 -> 34088.224 | H22: =+'Flujo Redco Chile'!H22+'Flujo Redco Perú'!H25+'Flujo Redco Brasil'!H24+'Flujo Redco USA'!H26+'Flujo Redco BVI'!H26 -> 50449.773 | I22: =+'Flujo Redco Chile'!I22+'Flujo Redco Perú'!I25+'Flujo Redco Brasil'!I24+'Flujo Redco USA'!I26+'Flujo Redco BVI'!I26 -> 52303.067 | J22: =+'Flujo Redco Chile'!J22+'Flujo Redco Perú'!J25+'Flujo Redco Brasil'!J24+'Flujo Redco USA'!J26+'Flujo Redco BVI'!J26 -> 51172.129 | K22: =+'Flujo Redco Chile'!K22+'Flujo Redco Perú'!K25+'Flujo Redco Brasil'!K24+'Flujo Redco USA'!K26+'Flujo Redco BVI'!K26 -> 41361.99 | L22: =SUM(C22:K22) -> 375248.41
B23: TOTAL COSTOS ADMINISTRATIVOS | C23: =SUM(C21:C22)+1 -> 32852.1 | D23: =SUM(D21:D22)+1 -> 80672.367 | E23: =SUM(E21:E22)-1 -> 77102.062 | F23: =SUM(F21:F22) -> 93392.744 | G23: =SUM(G21:G22) -> 69993.209 | H23: =SUM(H21:H22) -> 86480.791 | I23: =SUM(I21:I22) -> 88955.931 | J23: =SUM(J21:J22) -> 91232.473 | K23: =SUM(K21:K22) -> 82408.149 | L23: =SUM(L21:L22) -> 703088.83
B25: ACTIVO: REMODELACION PROP.AJENA OF. 1502 | C25: =+'Flujo Redco Chile'!C25+'Flujo Redco Perú'!C28+'Flujo Redco Brasil'!C27+'Flujo Redco USA'!C29+'Flujo Redco BVI'!C29 -> 18477.487 | D25: =+'Flujo Redco Chile'!D25+'Flujo Redco Perú'!D28+'Flujo Redco Brasil'!D27+'Flujo Redco USA'!D29+'Flujo Redco BVI'!D29 -> 5562 | E25: =+'Flujo Redco Chile'!E25+'Flujo Redco Perú'!E28+'Flujo Redco Brasil'!E27+'Flujo Redco USA'!E29+'Flujo Redco BVI'!E29 -> 9675 | F25: =+'Flujo Redco Chile'!F25+'Flujo Redco Perú'!F28+'Flujo Redco Brasil'!F27+'Flujo Redco USA'!F29+'Flujo Redco BVI'!F29 -> 17383 | G25: =+'Flujo Redco Chile'!G25+'Flujo Redco Perú'!G28+'Flujo Redco Brasil'!G27+'Flujo Redco USA'!G29+'Flujo Redco BVI'!G29 -> 36675.314 | H25: =+'Flujo Redco Chile'!H25+'Flujo Redco Perú'!H28+'Flujo Redco Brasil'!H27+'Flujo Redco USA'!H29+'Flujo Redco BVI'!H29 -> 8453 | I25: =+'Flujo Redco Chile'!I25+'Flujo Redco Perú'!I28+'Flujo Redco Brasil'!I27+'Flujo Redco USA'!I29+'Flujo Redco BVI'!I29 -> 7808 | J25: =+'Flujo Redco Chile'!J25+'Flujo Redco Perú'!J28+'Flujo Redco Brasil'!J27+'Flujo Redco USA'!J29+'Flujo Redco BVI'!J29 -> 15374.883 | K25: =+'Flujo Redco Chile'!K25+'Flujo Redco Perú'!K28+'Flujo Redco Brasil'!K27+'Flujo Redco USA'!K29+'Flujo Redco BVI'!K29 -> 15336 | L25: =SUM(C25:K25) -> 134744.68
B27: RESULTADO OPERACIONAL | C27: =SUM(C12-C18-C23-C25)+1 -> 195344.24 | D27: =SUM(D12-D18-D23-D25) -> 401033.19 | E27: =SUM(E12-E18-E23-E25) -> 160624.28 | F27: =SUM(F12-F18-F23-F25) -> 58459.138 | G27: =SUM(G12-G18-G23-G25) -> 81351.281 | H27: =SUM(H12-H18-H23-H25) -> 163291.9 | I27: =SUM(I12-I18-I23-I25) -> 133186.76 | J27: =SUM(J12-J18-J23-J25) -> #REF! | K27: =SUM(K12-K18-K23-K25) -> 53192.925 | L27: =SUM(L12-L18-L23-L25) -> #REF!
B29: OTROS INGRESOS NO OPERACIONALES
B30: INGRESO IVA DEBITO FACTURACION | C30: =+'Flujo Redco Chile'!C31+'Flujo Redco Perú'!C35 -> 81339.94 | D30: =+'Flujo Redco Chile'!D31+'Flujo Redco Perú'!D35 -> 121311.9 | E30: =+'Flujo Redco Chile'!E31+'Flujo Redco Perú'!E35 -> 95276.024 | F30: =+'Flujo Redco Chile'!F31+'Flujo Redco Perú'!F35 -> 75623.724 | G30: =+'Flujo Redco Chile'!G31+'Flujo Redco Perú'!G35 -> 94077.513 | H30: =+'Flujo Redco Chile'!H31+'Flujo Redco Perú'!H35 -> 89916.215 | I30: =+'Flujo Redco Chile'!I31+'Flujo Redco Perú'!I35 -> 137841.78 | J30: =+'Flujo Redco Chile'!J31+'Flujo Redco Perú'!J35 -> 162260.61 | K30: =+'Flujo Redco Chile'!K31+'Flujo Redco Perú'!K35 -> 73317.832 | L30: =SUM(C30:K30) -> 930965.53
B31: DEVOLUCION BOLETA DE GARANTIA CMP | C31: =+'Flujo Redco Chile'!C38 -> 0 | D31: =+'Flujo Redco Chile'!D38 -> 10399.317 | E31: =+'Flujo Redco Chile'!E38 -> 0 | F31: =+'Flujo Redco Chile'!F38 -> 11315.145 | G31: =+'Flujo Redco Chile'!G38 -> 0 | H31: =+'Flujo Redco Chile'!H38 -> 0 | I31: =+'Flujo Redco Chile'!I38 -> 0 | J31: =+'Flujo Redco Chile'!J38 -> 0 | K31: =+'Flujo Redco Chile'!K38 -> 0 | L31: =SUM(C31:K31) -> 21714.461
B32: INGRESO CUENTA CORRIENTE EERR | C32: =+'Flujo Redco Chile'!C32+'Flujo Redco Chile'!C35+'Flujo Redco Chile'!C36+'Flujo Redco Chile'!C37+'Flujo Redco Perú'!C36+'Flujo Redco Perú'!C37+'Flujo Redco Perú'!C38 -> 191140.59 | D32: =+'Flujo Redco Chile'!D32+'Flujo Redco Chile'!D35+'Flujo Redco Chile'!D36+'Flujo Redco Chile'!D37+'Flujo Redco Perú'!D36+'Flujo Redco Perú'!D37+'Flujo Redco Perú'!D38 -> 113524.2 | E32: =+'Flujo Redco Chile'!E32+'Flujo Redco Chile'!E35+'Flujo Redco Chile'!E36+'Flujo Redco Chile'!E37+'Flujo Redco Perú'!E36+'Flujo Redco Perú'!E37+'Flujo Redco Perú'!E38 -> 71709.29 | F32: =+'Flujo Redco Chile'!F32+'Flujo Redco Chile'!F35+'Flujo Redco Chile'!F36+'Flujo Redco Chile'!F37+'Flujo Redco Perú'!F36+'Flujo Redco Perú'!F37+'Flujo Redco Perú'!F38 -> 194838.46 | G32: =+'Flujo Redco Chile'!G32+'Flujo Redco Chile'!G35+'Flujo Redco Chile'!G36+'Flujo Redco Chile'!G37+'Flujo Redco Perú'!G36+'Flujo Redco Perú'!G37+'Flujo Redco Perú'!G38 -> 41551.947 | H32: =+'Flujo Redco Chile'!H32+'Flujo Redco Chile'!H35+'Flujo Redco Chile'!H36+'Flujo Redco Chile'!H37+'Flujo Redco Perú'!H36+'Flujo Redco Perú'!H37+'Flujo Redco Perú'!H38 -> 0 | I32: =+'Flujo Redco Chile'!I32+'Flujo Redco Chile'!I35+'Flujo Redco Chile'!I36+'Flujo Redco Chile'!I37+'Flujo Redco Perú'!I36+'Flujo Redco Perú'!I37+'Flujo Redco Perú'!I38 -> 46679.406 | J32: =+'Flujo Redco Chile'!J32+'Flujo Redco Chile'!J35+'Flujo Redco Chile'!J36+'Flujo Redco Chile'!J37+'Flujo Redco Perú'!J36+'Flujo Redco Perú'!J37+'Flujo Redco Perú'!J38 -> 459872.82 | K32: =+'Flujo Redco Chile'!K32+'Flujo Redco Chile'!K35+'Flujo Redco Chile'!K36+'Flujo Redco Chile'!K37+'Flujo Redco Perú'!K36+'Flujo Redco Perú'!K37+'Flujo Redco Perú'!K38 -> 27214.364 | L32: =SUM(C32:K32) -> 1146531.1
B33: OTROS INGRESOS | C33: =+'Flujo Redco Chile'!C39+'Flujo Redco Chile'!C40+'Flujo Redco Perú'!C40+'Flujo Redco Brasil'!C34+'Flujo Redco USA'!C38+'Flujo Redco BVI'!C38 -> 7091.2854 | D33: =+'Flujo Redco Chile'!D39+'Flujo Redco Chile'!D40+'Flujo Redco Perú'!D40+'Flujo Redco Brasil'!D34+'Flujo Redco USA'!D38+'Flujo Redco BVI'!D38 -> 363 | E33: =+'Flujo Redco Chile'!E39+'Flujo Redco Chile'!E40+'Flujo Redco Perú'!E40+'Flujo Redco Brasil'!E34+'Flujo Redco USA'!E38+'Flujo Redco BVI'!E38+'Flujo Redco Chile'!E34 -> 5265.8026 | F33: =+'Flujo Redco Chile'!F39+'Flujo Redco Chile'!F40+'Flujo Redco Perú'!F40+'Flujo Redco Brasil'!F34+'Flujo Redco USA'!F38+'Flujo Redco BVI'!F38+'Flujo Redco Chile'!F34 -> 10432.481 | G33: =+'Flujo Redco Chile'!G39+'Flujo Redco Chile'!G40+'Flujo Redco Perú'!G40+'Flujo Redco Brasil'!G34+'Flujo Redco USA'!G38+'Flujo Redco BVI'!G38+'Flujo Redco Chile'!G34 -> 472755.03 | H33: =+'Flujo Redco Chile'!H39+'Flujo Redco Chile'!H40+'Flujo Redco Perú'!H40+'Flujo Redco Brasil'!H34+'Flujo Redco USA'!H38+'Flujo Redco BVI'!H38+'Flujo Redco Chile'!H34 -> 89784.033 | I33: =+'Flujo Redco Chile'!I39+'Flujo Redco Chile'!I40+'Flujo Redco Perú'!I40+'Flujo Redco Brasil'!I34+'Flujo Redco USA'!I38+'Flujo Redco BVI'!I38+'Flujo Redco Chile'!I34 -> 68680.616 | J33: =+'Flujo Redco Chile'!J39+'Flujo Redco Chile'!J40+'Flujo Redco Perú'!J40+'Flujo Redco Brasil'!J34+'Flujo Redco USA'!J38+'Flujo Redco BVI'!J38+'Flujo Redco Chile'!J34 -> 37073.082 | K33: =+'Flujo Redco Chile'!K39+'Flujo Redco Chile'!K40+'Flujo Redco Perú'!K40+'Flujo Redco Brasil'!K34+'Flujo Redco USA'!K38+'Flujo Redco BVI'!K38+'Flujo Redco Chile'!K34 -> 4069.9474 | L33: =SUM(C33:K33) -> 695515.28
B34: OTROS INGRESOS NO OPERACIONALES | C34: =SUM(C30:C33) -> 279571.81 | D34: =SUM(D30:D33) -> 245598.41 | E34: =SUM(E30:E33) -> 172251.12 | F34: =SUM(F30:F33) -> 292209.81 | G34: =SUM(G30:G33) -> 608384.49 | H34: =SUM(H30:H33) -> 179700.25 | I34: =SUM(I30:I33) -> 253201.81 | J34: =SUM(J30:J33) -> 659206.51 | ... L34: =SUM(L30:L33) -> 2794726.3
B36: OTROS EGRESOS NO OPERACIONALES
B37: IMPUESTOS PPM-IVA-IMPTO.ADICIONAL | C37: =+'Flujo Redco Chile'!C44+'Flujo Redco Perú'!C44+'Flujo Redco Brasil'!C37+'Flujo Redco USA'!C41+'Flujo Redco BVI'!C41 -> 91430.334 | D37: =+'Flujo Redco Chile'!D44+'Flujo Redco Perú'!D44+'Flujo Redco Brasil'!D37+'Flujo Redco USA'!D41+'Flujo Redco BVI'!D41 -> 78509.452 | E37: =+'Flujo Redco Chile'!E44+'Flujo Redco Perú'!E44+'Flujo Redco Brasil'!E37+'Flujo Redco USA'!E41+'Flujo Redco BVI'!E41 -> 25339.348 | F37: =+'Flujo Redco Chile'!F44+'Flujo Redco Perú'!F44+'Flujo Redco Brasil'!F37+'Flujo Redco USA'!F41+'Flujo Redco BVI'!F41 -> 60062.326 | G37: =+'Flujo Redco Chile'!G44+'Flujo Redco Perú'!G44+'Flujo Redco Brasil'!G37+'Flujo Redco USA'!G41+'Flujo Redco BVI'!G41 -> 125286.45 | H37: =+'Flujo Redco Chile'!H44+'Flujo Redco Perú'!H44+'Flujo Redco Brasil'!H37+'Flujo Redco USA'!H41+'Flujo Redco BVI'!H41 -> 95547.266 | I37: =+'Flujo Redco Chile'!I44+'Flujo Redco Perú'!I44+'Flujo Redco Brasil'!I37+'Flujo Redco USA'!I41+'Flujo Redco BVI'!I41 -> 65065.088 | J37: =+'Flujo Redco Chile'!J44+'Flujo Redco Perú'!J44+'Flujo Redco Brasil'!J37+'Flujo Redco USA'!J41+'Flujo Redco BVI'!J41 -> 216738.47 | K37: =+'Flujo Redco Chile'!K44+'Flujo Redco Perú'!K44+'Flujo Redco Brasil'!K37+'Flujo Redco USA'!K41+'Flujo Redco BVI'!K41 -> 68043.615 | L37: =SUM(C37:K37) -> 826022.35
B38: CREDITOS | C38: =+SUM('Flujo Redco Chile'!C45:C47)+SUM('Flujo Redco Perú'!C45:C47) -> 27599.535 | D38: =+SUM('Flujo Redco Chile'!D45:D47)+SUM('Flujo Redco Perú'!D45:D47) -> 38631.281 | E38: =+SUM('Flujo Redco Chile'!E45:E47)+SUM('Flujo Redco Perú'!E45:E47) -> 30686.726 | F38: =+SUM('Flujo Redco Chile'!F45:F47)+SUM('Flujo Redco Perú'!F45:F47) -> 31866.891 | G38: =+SUM('Flujo Redco Chile'!G45:G47)+SUM('Flujo Redco Perú'!G45:G47) -> 32660.93 | H38: =+SUM('Flujo Redco Chile'!H45:H47)+SUM('Flujo Redco Perú'!H45:H47) -> 27706.253 | I38: =+SUM('Flujo Redco Chile'!I45:I47)+SUM('Flujo Redco Perú'!I45:I47) -> 31882.783 | J38: =+SUM('Flujo Redco Chile'!J45:J47)+SUM('Flujo Redco Perú'!J45:J47) -> 30717.742 | K38: =+SUM('Flujo Redco Chile'!K45:K47)+SUM('Flujo Redco Perú'!K45:K47) -> 29655.452 | L38: =SUM(C38:K38) -> 281407.59
B39: APORTE FFMM | C39: =+'Flujo Redco Chile'!C48+'Flujo Redco Perú'!C40 -> 0 | D39: =+'Flujo Redco Chile'!D48+'Flujo Redco Perú'!D40 -> 0 | E39: =+'Flujo Redco Chile'!E48+'Flujo Redco Perú'!E40 -> 0 | F39: =+'Flujo Redco Chile'!F48+'Flujo Redco Perú'!F40 -> 0 | G39: =+'Flujo Redco Chile'!G48+'Flujo Redco Perú'!G40 -> 0 | H39: =+'Flujo Redco Chile'!H48+'Flujo Redco Perú'!H40 -> 0 | I39: =+'Flujo Redco Chile'!I48+'Flujo Redco Perú'!I40 -> 0 | J39: =+'Flujo Redco Chile'!J48+'Flujo Redco Perú'!J40 -> 0 | K39: =+'Flujo Redco Chile'!K48+'Flujo Redco Perú'!K40 -> 0 | L39: =SUM(C39:K39) -> 0
B40: TOTAL EGRESOS NO OPERACIONALES | C40: =SUM(C37:C39) -> 119029.87 | D40: =SUM(D37:D39) -> 117140.73 | E40: =SUM(E37:E39) -> 56026.074 | F40: =SUM(F37:F39) -> 91929.217 | G40: =SUM(G37:G39) -> 157947.38 | H40: =SUM(H37:H39) -> 123253.52 | I40: =SUM(I37:I39) -> 96947.871 | J40: =SUM(J37:J39) -> 247456.22 | ... L40: =SUM(L37:L39) -> 1107429.9
B42: OTROS EGRESOS CTA.CTE. EERR | C42: =+'Flujo Redco Chile'!C58+'Flujo Redco Perú'!C54+'Flujo Redco Brasil'!C43+'Flujo Redco USA'!C47+'Flujo Redco BVI'!C47 -> 45388.467 | D42: =+'Flujo Redco Chile'!D58+'Flujo Redco Perú'!D54+'Flujo Redco Brasil'!D43+'Flujo Redco USA'!D47+'Flujo Redco BVI'!D47 -> 118859.49 | E42: =+'Flujo Redco Chile'!E58+'Flujo Redco Perú'!E54+'Flujo Redco Brasil'!E43+'Flujo Redco USA'!E47+'Flujo Redco BVI'!E47 -> 91375.742 | F42: =+'Flujo Redco Chile'!F58+'Flujo Redco Perú'!F54+'Flujo Redco Brasil'!F43+'Flujo Redco USA'!F47+'Flujo Redco BVI'!F47 -> 209275.46 | G42: =+'Flujo Redco Chile'!G58+'Flujo Redco Perú'!G54+'Flujo Redco Brasil'!G43+'Flujo Redco USA'!G47+'Flujo Redco BVI'!G47 -> 450268.95 | H42: =+'Flujo Redco Chile'!H58+'Flujo Redco Perú'!H54+'Flujo Redco Brasil'!H43+'Flujo Redco USA'!H47+'Flujo Redco BVI'!H47 -> 33313.305 | I42: =+'Flujo Redco Chile'!I58+'Flujo Redco Perú'!I54+'Flujo Redco Brasil'!I43+'Flujo Redco USA'!I47+'Flujo Redco BVI'!I47 -> 66329.145 | J42: =+'Flujo Redco Chile'!J58+'Flujo Redco Perú'!J54+'Flujo Redco Brasil'!J43+'Flujo Redco USA'!J47+'Flujo Redco BVI'!J47 -> 479797.62 | K42: =+'Flujo Redco Chile'!K58+'Flujo Redco Perú'!K54+'Flujo Redco Brasil'!K43+'Flujo Redco USA'!K47+'Flujo Redco BVI'!K47 -> 58204.691 | L42: =SUM(C42:K42) -> 1552812.9
B44: OTROS EGRESOS CTA.CTE. EERR | C44: =+C34-C40-C42 -> 115153.48 | D44: =+D34-D40-D42 -> 9598.1867 | E44: =+E34-E40-E42 -> 24849.299 | F44: =+F34-F40-F42 -> -8994.8648 | G44: =+G34-G40-G42 -> 168.16094 | H44: =+H34-H40-H42 -> 23133.424 | I44: =+I34-I40-I42 -> 89924.79 | J44: =+J34-J40-J42 -> -68047.329 | K44: =+K34-K40-K42 -> -51301.615 | L44: =SUM(C44:K44) -> 134483.53
B46: SALDO FLUJO MENSUAL | C46: =+C27+C44 -> 310497.71 | D46: =+D27+D44 -> 410631.38 | E46: =+E27+E44 -> 185473.58 | F46: =+F27+F44 -> 49464.274 | G46: =+G27+G44 -> 81519.442 | H46: =+H27+H44 -> 186425.33 | I46: =+I27+I44 -> 223111.55 | J46: =+J27+J44 -> #REF! | ... L46: =+L27+L44 -> #REF!
B47: SALDO CTA. CTE. INICIAL 01-01-2025 | C47: =+'Flujo Redco Chile'!C8+'Flujo Redco Perú'!C9+'Flujo Redco Brasil'!C9+'Flujo Redco USA'!C9+'Flujo Redco BVI'!C9 -> 253992.16 | D47: =+'Flujo Redco Chile'!D8+'Flujo Redco Perú'!D9+'Flujo Redco Brasil'!D9+'Flujo Redco USA'!D9+'Flujo Redco BVI'!D9 -> 564489.87 | E47: =+'Flujo Redco Chile'!E8+'Flujo Redco Perú'!E9+'Flujo Redco Brasil'!E9+'Flujo Redco USA'!E9+'Flujo Redco BVI'!E9 -> 975122.25 | F47: =+'Flujo Redco Chile'!F8+'Flujo Redco Perú'!F9+'Flujo Redco Brasil'!F9+'Flujo Redco USA'!F9+'Flujo Redco BVI'!F9 -> 1160594.8 | G47: =+'Flujo Redco Chile'!G8+'Flujo Redco Perú'!G9+'Flujo Redco Brasil'!G9+'Flujo Redco USA'!G9+'Flujo Redco BVI'!G9 -> 1210059.1 | H47: =+'Flujo Redco Chile'!H8+'Flujo Redco Perú'!H9+'Flujo Redco Brasil'!H9+'Flujo Redco USA'!H9+'Flujo Redco BVI'!H9 -> 1291578.5 | I47: =+'Flujo Redco Chile'!I8+'Flujo Redco Perú'!I9+'Flujo Redco Brasil'!I9+'Flujo Redco USA'!I9+'Flujo Redco BVI'!I9 -> 1478003.9 | J47: =+'Flujo Redco Chile'!J8+'Flujo Redco Perú'!J9+'Flujo Redco Brasil'!J9+'Flujo Redco USA'!J9+'Flujo Redco BVI'!J9 -> 1701115.4 | K47: =+'Flujo Redco Chile'!K8+'Flujo Redco Perú'!K9+'Flujo Redco Brasil'!K9+'Flujo Redco USA'!K9+'Flujo Redco BVI'!K9 -> 1986304.1 | L47: =SUM(C47) -> 253992.16
B48: SALDO FLUJO CIERRE MENSUAL | C48: =SUM(C46:C47) -> 564489.87 | D48: =SUM(D46:D47) -> 975121.25 | E48: =SUM(E46:E47) -> 1160595.8 | F48: =SUM(F46:F47) -> 1210059.1 | G48: =SUM(G46:G47) -> 1291578.5 | H48: =SUM(H46:H47) -> 1478003.9 | I48: =SUM(I46:I47) -> 1701115.4 | J48: =SUM(J46:J47) -> #REF! | ... L48: =SUM(L46:L47) -> #REF!
C49: =+'Flujo Redco Chile'!C62+'Flujo Redco Perú'!C58+'Flujo Redco Brasil'!C49+'Flujo Redco USA'!C51+'Flujo Redco BVI'!C51 -> 564489.87 | D49: =+'Flujo Redco Chile'!D62+'Flujo Redco Perú'!D58+'Flujo Redco Brasil'!D49+'Flujo Redco USA'!D51+'Flujo Redco BVI'!D51 -> 975122.25 | E49: =+'Flujo Redco Chile'!E62+'Flujo Redco Perú'!E58+'Flujo Redco Brasil'!E49+'Flujo Redco USA'!E51+'Flujo Redco BVI'!E51 -> 1160594.8 | F49: =+'Flujo Redco Chile'!F62+'Flujo Redco Perú'!F58+'Flujo Redco Brasil'!F49+'Flujo Redco USA'!F51+'Flujo Redco BVI'!F51 -> 1210059.1 | G49: =+'Flujo Redco Chile'!G62+'Flujo Redco Perú'!G58+'Flujo Redco Brasil'!G49+'Flujo Redco USA'!G51+'Flujo Redco BVI'!G51 -> 1291578.5 | H49: =+'Flujo Redco Chile'!H62+'Flujo Redco Perú'!H58+'Flujo Redco Brasil'!H49+'Flujo Redco USA'!H51+'Flujo Redco BVI'!H51 -> 1478003.9 | I49: =+'Flujo Redco Chile'!I62+'Flujo Redco Perú'!I58+'Flujo Redco Brasil'!I49+'Flujo Redco USA'!I51+'Flujo Redco BVI'!I51 -> 1701115.4 | J49: =+'Flujo Redco Chile'!J62+'Flujo Redco Perú'!J58+'Flujo Redco Brasil'!J49+'Flujo Redco USA'!J51+'Flujo Redco BVI'!J51 -> 1986304.1 | K49: =+'Flujo Redco Chile'!K62+'Flujo Redco Perú'!K58+'Flujo Redco Brasil'!K49+'Flujo Redco USA'!K51+'Flujo Redco BVI'!K51-1 -> 1896323.4
B50: CAJA OPERACIONAL DEL MES
B51: CHILE | C51: =+'Flujo Redco Chile'!C60 -> 118395.56 | D51: =+'Flujo Redco Chile'!D60 -> 133162.17 | E51: =+'Flujo Redco Chile'!E60 -> -69890.423 | F51: =+'Flujo Redco Chile'!F60 -> -113200.73 | G51: =+'Flujo Redco Chile'!G60 -> -40765.558 | H51: =+'Flujo Redco Chile'!H60 -> -48061.672
B52: PERU | C52: =+'Flujo Redco Perú'!C274 -> 3798.15 | D52: =+'Flujo Redco Perú'!D274 -> -2643 | E52: =+'Flujo Redco Perú'!E274 -> 65135 | F52: =+'Flujo Redco Perú'!F274 -> -1064.3 | G52: =+'Flujo Redco Perú'!G274 -> -4999 | H52: =+'Flujo Redco Perú'!H274 -> 42095
B53: BRASIL | C53: =+'Flujo Redco Brasil'!C45 -> 51910 | D53: =+'Flujo Redco Brasil'!D45 -> 16991 | E53: =+'Flujo Redco Brasil'!E45 -> 61952 | F53: =+'Flujo Redco Brasil'!F45 -> 18807.3 | G53: =+'Flujo Redco Brasil'!G45 -> -137850 | H53: =+'Flujo Redco Brasil'!H45 -> -22177
B54: EEUU | C54: =+'Flujo Redco USA'!C49 -> 150438 | D54: =+'Flujo Redco USA'!D49 -> 241440.21 | E54: =+'Flujo Redco USA'!E49 -> 82798 | F54: =+'Flujo Redco USA'!F49 -> 159302 | G54: =+'Flujo Redco USA'!G49 -> -134434 | H54: =+'Flujo Redco USA'!H49 -> 57618
B55: BBVI | C55: =+'Flujo Redco BVI'!C49 -> -14044 | D55: =+'Flujo Redco BVI'!D49 -> 21682 | E55: =+'Flujo Redco BVI'!E49 -> 45478 | F55: =+'Flujo Redco BVI'!F49 -> -14380 | G55: =+'Flujo Redco BVI'!G49 -> 399568 | H55: =+'Flujo Redco BVI'!H49 -> 156951
B56: TOTAL MAYO | C56: =SUM(C51:C55) -> 310497.71 | D56: =SUM(D51:D55) -> 410632.38 | E56: =SUM(E51:E55) -> 185472.58 | F56: =SUM(F51:F55) -> 49464.274 | G56: =SUM(G51:G55) -> 81519.442 | H56: =SUM(H51:H55) -> 186425.33
B59: SALDO CAJA ACUMULADA (Considerando saldo inicial)
B60: CHILE | C60: =+'Flujo Redco Chile'!C62 -> 170652.7 | D60: =+'Flujo Redco Chile'!D62 -> 303814.87 | E60: =+'Flujo Redco Chile'!E62 -> 233924.45 | F60: =+'Flujo Redco Chile'!F62 -> 120723.72 | G60: =+'Flujo Redco Chile'!G62 -> 79958.162 | H60: =+'Flujo Redco Chile'!H62 -> 31896.49
B61: PERU | C61: ='Flujo Redco Perú'!C58 -> 140565.84 | D61: ='Flujo Redco Perú'!D58 -> 137922.84 | E61: ='Flujo Redco Perú'!E58 -> 203057.84 | F61: ='Flujo Redco Perú'!F58 -> 201993.54 | G61: ='Flujo Redco Perú'!G58 -> 196994.54 | H61: ='Flujo Redco Perú'!H58 -> 239089.54
B62: BRASIL | C62: ='Flujo Redco Brasil'!C49 -> 61532.33 | D62: ='Flujo Redco Brasil'!D49 -> 78523.33 | E62: ='Flujo Redco Brasil'!E49 -> 140475.33 | F62: ='Flujo Redco Brasil'!F49 -> 159282.63 | G62: ='Flujo Redco Brasil'!G49 -> 21432.63 | H62: ='Flujo Redco Brasil'!H49 -> -744.37
B63: EEUU | C63: ='Flujo Redco USA'!C51 -> 205783 | D63: ='Flujo Redco USA'!D51 -> 447223.21 | E63: ='Flujo Redco USA'!E51 -> 530021.21 | F63: ='Flujo Redco USA'!F51 -> 689323.21 | G63: ='Flujo Redco USA'!G51 -> 554889.21 | H63: ='Flujo Redco USA'!H51 -> 612507.21
C64: =+'Flujo Redco BVI'!C51 -> -14044 | D64: =+'Flujo Redco BVI'!D51 -> 7638 | E64: =+'Flujo Redco BVI'!E51 -> 53116 | F64: =+'Flujo Redco BVI'!F51 -> 38736 | G64: =+'Flujo Redco BVI'!G51 -> 438304 | H64: =+'Flujo Redco BVI'!H51 -> 595255
B65: TOTAL MAYO | C65: =SUM(C60:C64) -> 564489.87 | D65: =SUM(D60:D64)-1 -> 975121.25 | E65: =SUM(E60:E64)+1 -> 1160595.8 | F65: =SUM(F60:F64) -> 1210059.1 | G65: =SUM(G60:G64) -> 1291578.5 | H65: =SUM(H60:H64) -> 1478003.9
C66: =SUM(C48-C65) -> 1.1641532e-10 | D66: =SUM(D48-D65) -> -1.1641532e-10 | E66: =SUM(E48-E65) -> 0 | F66: =SUM(F48-F65) -> 0 | G66: =SUM(G48-G65) -> 0

Sheet Flujo por empresa acum.
B3: FLUJO CAJA CONSOLIDADO GESTION POR EMPRESA
B5: FLUJO OPERACIONAL ACUMULADA POR EMPRES 2025 | C5: US$ | H5: ACUMULADO
B6: RESUMEN | C6: CHILE | D6: PERU | E6: BRASIL | F6: USA | G6: BVI | H6: 45901
B7: TOTAL INGRESOS OPERACIONALES PEND. 2024 | C7: =+'Flujo Redco Chile'!P10 -> 487680.19 | D7: =+'Flujo Redco Perú'!P11 -> 132119 | E7: =+'Flujo Redco Brasil'!P12 -> 182679 | F7: =+'Flujo Redco USA'!P11 -> 150453 | G7: =+'Flujo Redco BVI'!P11 -> 67160 | H7: =+SUM(C7:G7) -> 1020091.2
B8: TOTAL INGRESOS OPERACIONALES 2025 | C8: =+'Flujo Redco Chile'!P11 -> 2524183.8 | D8: =+'Flujo Redco Perú'!P12 -> 1654243 | E8: =+'Flujo Redco Brasil'!P13 -> 625631.7 | F8: =+'Flujo Redco USA'!P12 -> 831077.21 | G8: =+'Flujo Redco BVI'!P12 -> 271569 | H8: =SUM(C8:G8) -> 5906704.7
B9: SUMA TOTAL INGRESOS 2025 | C9: =SUM(C7:C8) -> 3011864 | D9: =SUM(D7:D8) -> 1786362 | E9: =SUM(E7:E8) -> 808310.7 | F9: =SUM(F7:F8) -> 981530.21 | G9: =SUM(G7:G8) -> 338729 | H9: =SUM(H7:H8) -> 6926795.9 | I9: 5412000 | J9: =+H9-I9 -> 1514795.9 | K9: =+J9/H9 -> 0.21868638
B11: COSTOS OPERACIONALES
B12: SUELDOS OPERACIONALES | C12: =+'Flujo Redco Chile'!P15 -> 2211147.8 | D12: =+'Flujo Redco Perú'!P16 -> 663451 | E12: =+'Flujo Redco Brasil'!P17 -> 121150 | F12: =+'Flujo Redco USA'!P16 -> 0 | G12: =+'Flujo Redco BVI'!P16 -> 0 | H12: =SUM(C12:G12) -> 2995748.8
B13: HONORARIOS OPERACIONALES | C13: =+'Flujo Redco Chile'!P16 -> 485462.78 | D13: =+'Flujo Redco Perú'!P17 -> 313297.3 | E13: =+'Flujo Redco Brasil'!P18 -> 113396 | F13: =+'Flujo Redco USA'!P17 -> 113124 | G13: =+'Flujo Redco BVI'!P17 -> 60572.4 | H13: =SUM(C13:G13) -> 1085852.5
B14: GASTOS OPERACIONALES | C14: =+'Flujo Redco Chile'!P17 -> 387411.07 | D14: =+'Flujo Redco Perú'!P18 -> 48883.85 | E14: =+'Flujo Redco Brasil'!P19 -> 65549.4 | F14: =+'Flujo Redco USA'!P18 -> 5320 | G14: =+'Flujo Redco BVI'!P18 -> 0 | H14: =SUM(C14:G14) -> 507164.32
B15: TOTAL COSTOS OPERACIONALES | C15: =SUM(C12:C14) -> 3084021.7 | D15: =SUM(D12:D14) -> 1025632.2 | E15: =SUM(E12:E14) -> 300095.4 | F15: =SUM(F12:F14) -> 118444 | G15: =SUM(G12:G14) -> 60572.4 | H15: =SUM(H12:H14) -> 4588765.6
B17: COSTOS ADMINISTRATIVOS
B18: SUELDOS ADMINISTRACION | C18: =+'Flujo Redco Chile'!P21 -> 316458.42 | D18: ='Flujo Redco Perú'!P24 -> 0 | E18: ='Flujo Redco Brasil'!P23 -> 11382 | F18: ='Flujo Redco USA'!P25 -> 0 | G18: ='Flujo Redco BVI'!P25 -> 0 | H18: =SUM(C18:G18) -> 327840.42
B19: GASTOS DE ADMINISTRACION | C19: =+'Flujo Redco Chile'!P22 -> 175824.41 | D19: ='Flujo Redco Perú'!P25 -> 130958 | E19: ='Flujo Redco Brasil'!P24 -> 52368 | F19: ='Flujo Redco USA'!P26 -> 16098 | G19: ='Flujo Redco BVI'!P26 -> 0 | H19: =SUM(C19:G19) -> 375248.41
B20: TOTAL COSTOS ADMINISTRATIVOS | C20: =SUM(C18:C19) -> 492282.83 | D20: =SUM(D18:D19) -> 130958 | E20: =SUM(E18:E19) -> 63750 | F20: =SUM(F18:F19) -> 16098 | G20: =SUM(G18:G19) -> 0 | H20: =SUM(H18:H19) -> 703088.83
B22: ACTIVO FIJO+REMODELACIONES | C22: =+'Flujo Redco Chile'!P25 -> 22053.685 | D22: =+'Flujo Redco Perú'!P28 -> 93840 | E22: =+'Flujo Redco Brasil'!P27 -> 2851 | F22: =+'Flujo Redco USA'!P29 -> 0 | G22: =+'Flujo Redco BVI'!P29 -> 16000 | H22: =SUM(C22:G22) -> 134744.68
B24: RESULTADO OPERACIONAL | C24: =SUM(C9-C15-C20-C22) -> -586494.21 | D24: =SUM(D9-D15-D20-D22) -> 535931.85 | E24: =SUM(E9-E15-E20-E22) -> 441614.3 | F24: =SUM(F9-F15-F20-F22) -> 846988.21 | G24: =SUM(G9-G15-G20-G22) -> 262156.6 | H24: =SUM(H9-H15-H20-H22) -> 1500196.7
B26: OTROS INGRESOS NO OPERACIONALES | C26: CHILE | D26: PERU | E26: BRASIL | F26: USA | G26: BVI | H26: ACUMULADO
B27: INGRESO IVA DEBITO FACTURACION | C27: =+'Flujo Redco Chile'!P31 -> 609875.53 | D27: =+'Flujo Redco Perú'!P35 -> 321090 | E27: 0 | F27: 0 | G27: 0 | H27: =SUM(C27:G27) -> 930965.53
B28: INGRESO CUENTA CORRIENTE EERR | C28: =+'Flujo Redco Chile'!P32+'Flujo Redco Chile'!P35+'Flujo Redco Chile'!P36+'Flujo Redco Chile'!P37 -> 1094638.1 | D28: =+'Flujo Redco Perú'!P36 -> 51893 | E28: 0 | F28: 0 | G28: 0 | H28: =SUM(C28:G28) -> 1146531.1
B29: DEVOLUCION BOLETA DE GARANTIA CMP | C29: =+'Flujo Redco Chile'!P38 -> 21714.461 | E29: 0 | F29: 0 | G29: 0 | H29: =SUM(C29:G29) -> 21714.461
B30: OTROS INGRESOS | C30: =+'Flujo Redco Chile'!P39+'Flujo Redco Chile'!P40+'Flujo Redco Chile'!P34 -> 271670.28 | E30: =+'Flujo Redco Brasil'!P34 -> 8277 | F30: =+'Flujo Redco USA'!P38 -> 0 | G30: =+'Flujo Redco BVI'!P38 -> 415568 | H30: =SUM(C30:G30) -> 695515.28
B31: OTROS INGRESOS NO OPERACIONALES | C31: =SUM(C27:C30) -> 1997898.3 | D31: =SUM(D27:D30) -> 372983 | E31: =SUM(E27:E30) -> 8277 | F31: =SUM(F27:F30) -> 0 | G31: =SUM(G27:G30) -> 415568 | H31: =SUM(H27:H30) -> 2794726.3
B33: OTROS EGRESOS NO OPERACIONALES
B34: IMPUESTOS PPM-IVA-IMPTO.ADICIONAL | C34: =+'Flujo Redco Chile'!P44 -> 371769.35 | D34: =+'Flujo Redco Perú'!P44 -> 300771 | E34: =+'Flujo Redco Brasil'!P37 -> 153482 | F34: =+'Flujo Redco USA'!P41 -> 0 | G34: =+'Flujo Redco BVI'!P41 -> 0 | H34: =SUM(C34:G34) -> 826022.35
B35: PAGOS DE CREDITOS | C35: =+'Flujo Redco Chile'!P45+'Flujo Redco Chile'!P46+'Flujo Redco Chile'!P47 -> 281407.59 | D35: =+SUM('Flujo Redco Perú'!P45:P47) -> 0 | H35: =SUM(C35:G35) -> 281407.59
B36: APORTE FFMM | C36: =SUM('Flujo Redco Chile'!F48) -> 0 | H36: =SUM(C36:F36) -> 0
B37: TOTAL EGRESOS NO OPERACIONALES | C37: =SUM(C34:C36) -> 653176.95 | D37: =SUM(D34:D35) -> 300771 | E37: =SUM(E34:E35) -> 153482 | F37: =SUM(F34:F35) -> 0 | G37: =SUM(G34:G35) -> 0 | H37: =SUM(H34:H36) -> 1107429.9
B39: OTROS EGRESOS CTA.CTE. EERR | C39: =+'Flujo Redco Chile'!P58 -> 609092.87 | D39: =+'Flujo Redco Perú'!P54 -> 528152 | E39: =+'Flujo Redco Brasil'!P43 -> 133710 | F39: =+'Flujo Redco USA'!P47 -> 281858 | G39: =+'Flujo Redco BVI'!P47 -> 0 | H39: =SUM(C39:G39) -> 1552812.9
B41: RESULTADO NO OPERACIONAL | C41: =SUM(C31-C37-C39) -> 735628.53 | D41: =SUM(D31-D37-D39) -> -455940 | E41: =SUM(E31-E37-E39) -> -278915 | F41: =SUM(F31-F37-F39) -> -281858 | G41: =SUM(G31-G37-G39) -> 415568 | H41: =SUM(H31-H37-H39) -> 134483.53
B43: SALDO FLUJO ACUMULADO SEPTIEMBRE | C43: =SUM(C24+C41) -> 149134.32 | D43: =SUM(D24+D41) -> 79991.85 | E43: =SUM(E24+E41) -> 162699.3 | F43: =SUM(F24+F41) -> 565130.21 | G43: =SUM(G24+G41) -> 677724.6 | H43: =SUM(H24+H41) -> 1634680.3
B44: SALDO INICIAL 01-01-2025 | C44: =+'Flujo Redco Chile'!C8 -> 52257.137 | D44: =+'Flujo Redco Perú'!C9 -> 136767.69 | E44: =+'Flujo Redco Brasil'!C9 -> 9622.33 | F44: =+'Flujo Redco USA'!C9 -> 55345 | G44: =+'Flujo Redco BVI'!C9 -> 0 | H44: =+C44+D44+E44+F44 -> 253992.16
B45: SALDO FLUJO CIERRE SEPTIEMBRE | C45: =SUM(C43:C44) -> 201391.46 | D45: =SUM(D43:D44) -> 216759.54 | E45: =SUM(E43:E44) -> 172321.63 | F45: =SUM(F43:F44) -> 620475.21 | G45: =SUM(G43:G44) -> 677724.6 | H45: =SUM(H43:H44)-1 -> 1888671.4
C46: =+'Flujo Redco Chile'!P62 -> 201391.46 | D46: =+'Flujo Redco Perú'!P58 -> 216759.54 | E46: =+'Flujo Redco Brasil'!K276 -> 179973.63 | F46: =+'Flujo Redco USA'!P51 -> 620475.21 | G46: =+'Flujo Redco BVI'!P51 -> 677724.6 | H46: =+'Flujo Consolidado por mes'!L48 -> #REF!

Sheet Tabla Análisis
A1: País | B1: Perú
A3: Suma de Monto | C3: Meses (Fecha)
A4: Categoría | B4: Detalle | C4: ene | D4: feb | E4: mar | F4: abr | G4: may | H4: jun | I4: jul | J4: ago | K4: sept | L4: oct | M4: nov | N4: dic | O4: Total general
A5: Sueldo | C5: 56167 | D5: 68951 | E5: 65846 | F5: 74395.3 | G5: 80078 | H5: 83448 | I5: 110998 | J5: 103781 | K5: 65332 | L5: 51905 | M5: 108888.64 | N5: 176448 | O5: 1046237.9 | P5: =+O5/$O$11 -> #DIV/0!
A6: Externo | C6: 2656 | D6: 700 | E6: 0 | F6: 27486 | G6: 21514 | H6: 54577 | I6: 64701 | J6: 72469 | K6: 23649 | L6: 14178 | M6: 1442 | N6: 14814 | O6: 298186 | P6: =+O6/$O$11 -> #DIV/0!
A7: Operacional | C7: 17654.85 | D7: 6859 | E7: 13939 | F7: 15401 | G7: 12265 | H7: 15122 | I7: 10676 | J7: 31713 | K7: 23787 | L7: 22073 | M7: 8692 | N7: 14389 | O7: 192570.85 | P7: =+O7/$O$11 -> #DIV/0!
A8: REDTEC | C8: 9720 | D8: 2711 | E8: 9675 | F8: 17383 | G8: 11056 | H8: 8453 | I8: 7808 | J8: 6464 | K8: 9114 | L8: 13294 | M8: 13325 | N8: 21627 | O8: 130630 | P8: =+O8/$O$11 -> #DIV/0!
A9: Administración | C9: 3265 | D9: 2376 | E9: 3295 | F9: 3007 | G9: 4011 | H9: 6395 | I9: 5172 | J9: 11145 | K9: 5215 | L9: 6724 | M9: 6790 | N9: 6843 | O9: 64238 | P9: =+O9/$O$11 -> #DIV/0!
A10: Total general | C10: 89462.85 | D10: 81597 | E10: 92755 | F10: 137672.3 | G10: 128924 | H10: 167995 | I10: 199355 | J10: 225572 | K10: 127097 | L10: 108174 | M10: 139137.64 | N10: 234121 | O10: 1731862.8 | P10: =+O10/$O$11 -> #DIV/0!
A14: País | B14: (Varios elementos)
A16: Suma de Monto | C16: Meses (Fecha)
A17: Categoría | B17: Detalle | C17: Total general
A18: Total general
C20: =C13+C18 -> 0 | D20: =D13+D18 -> 0 | E20: =E13+E18 -> 0 | F20: =F13+F18 -> 0 | G20: =G13+G18 -> 0 | H20: =H13+H18 -> 0 | I20: =I13+I18 -> 0 | J20: =J13+J18 -> 0 | ... N20: =N13+N18 -> 0 | O20: =O10+O18 -> 1731862.8
A23: País | B23: (Todas)
A25: Suma de Monto | C25: Meses (Fecha)
A26: Categoría | B26: Detalle | C26: ene | D26: feb | E26: mar | F26: abr | G26: may | H26: jun | I26: jul | J26: ago | K26: sept | L26: oct | M26: nov | N26: dic | O26: Total general
A27: EERR | C27: 45388.467 | D27: 118859.49 | E27: 91375.743 | F27: 209275.46 | G27: 450268.95 | H27: 33313.305 | I27: 66329.145 | J27: 479797.62 | K27: 58204.691 | L27: 265471.6 | M27: 428566.9 | N27: 694247.47 | O27: 2941098.8
A28: Impuesto | C28: 91430.334 | D28: 78509.452 | E28: 25339.348 | F28: 60062.326 | G28: 125286.45 | H28: 95547.266 | I28: 65065.088 | J28: 216738.47 | K28: 68043.615 | L28: 144886.94 | M28: 148061.18 | N28: 156353.63 | O28: 1275324.1
A29: Crédito | C29: 27599.535 | D29: 38631.281 | E29: 30686.726 | F29: 31866.891 | G29: 32660.93 | H29: 27706.253 | I29: 31882.783 | J29: 30717.742 | K29: 29655.452 | L29: 31895.06 | M29: 29668.007 | N29: 30784.118 | O29: 373754.78
A30: Total general | C30: 164418.34 | D30: 236000.23 | E30: 147401.82 | F30: 301204.68 | G30: 608216.33 | H30: 156566.82 | I30: 163277.02 | J30: 727253.84 | K30: 155903.76 | L30: 442253.6 | M30: 606296.08 | N30: 881385.22 | O30: 4590177.7

Sheet Gasto Operacional_Dic
A2: Categoría | B2: (Varios elementos)
A4: Suma de Monto | B4: Meses (Fecha)
A5: País | B5: ene | C5: feb | D5: mar | E5: abr | F5: may | G5: jun | H5: jul | I5: ago | J5: sept | K5: oct | L5: nov | M5: dic | N5: Total general
A6: Chile | B6: 378436.76 | C6: 398340 | D6: 357973.32 | E6: 335882.01 | F6: 324752.96 | G6: 375198.26 | H6: 351835.74 | I6: 410938.04 | J6: 431239.15 | K6: 442721.53 | L6: 361293.55 | M6: 478326.17 | N6: 4646937.5
A7: Perú | B7: 89462.85 | C7: 81597 | D7: 92755 | E7: 137672.3 | F7: 128924 | G7: 167995 | H7: 199355 | I7: 225572 | J7: 127097 | K7: 108174 | L7: 139137.64 | M7: 234121 | N7: 1731862.8
A8: Brasil | B8: 21023 | C8: 27812 | D8: 26425 | E8: 52004.4 | F8: 33329 | G8: 76286 | H8: 31019 | I8: 21475 | J8: 77323 | K8: 14049 | L8: 116188 | M8: 23001 | N8: 519934.4
A9: USA | B9: 15 | C9: 2025 | D9: 58728 | E9: 9898 | F9: 47666 | G9: 4178 | H9: 10017 | I9: 1015 | J9: 1000 | K9: 88411 | L9: 1000 | M9: 218410 | N9: 442363
A10: BVI | B10: 14044 | C10: 0 | D10: 0 | E10: 14380 | F10: 16000 | G10: 15094 | H10: 5684.8 | I10: 5684.8 | J10: 5684.8 | K10: 5684.8 | L10: 5684.8 | M10: 5684.8 | N10: 93626.8
A11: Total general | B11: 502981.61 | C11: 509774 | D11: 535881.32 | E11: 549836.71 | F11: 550671.96 | G11: 638751.26 | H11: 597911.54 | I11: 664684.84 | J11: 642343.95 | K11: 659040.33 | L11: 623303.99 | M11: 959542.97 | N11: 7434724.5
A17: País | B17: 45658 | C17: 45689 | D17: 45717 | E17: 45748 | F17: 45778 | G17: 45809 | H17: 45839 | I17: 45870 | J17: 45901 | K17: 45931 | L17: 45962 | M17: 45992 | N17: Total | O17: %
A18: Chile | B18: =B6 -> 378436.76 | C18: =C6 -> 398340 | D18: =D6 -> 357973.32 | E18: =E6 -> 335882.01 | F18: =F6 -> 324752.96 | G18: =G6 -> 375198.26 | H18: =H6 -> 351835.74 | I18: =I6 -> 410938.04 | ... M18: =M6 -> 478326.17 | N18: =SUM(B18:M18) -> 4646937.5 | O18: =+N18/$N$23 -> 0.62503157
A19: Perú | B19: =B7 -> 89462.85 | C19: =C7 -> 81597 | D19: =D7 -> 92755 | E19: =E7 -> 137672.3 | F19: =F7 -> 128924 | G19: =G7 -> 167995 | H19: =H7 -> 199355 | I19: =I7 -> 225572 | ... M19: =M7 -> 234121 | N19: =SUM(B19:M19) -> 1731862.8 | O19: =+N19/$N$23 -> 0.23294243
A20: Brasil | B20: =B8 -> 21023 | C20: =C8 -> 27812 | D20: =D8 -> 26425 | E20: =E8 -> 52004.4 | F20: =F8 -> 33329 | G20: =G8 -> 76286 | H20: =H8 -> 31019 | I20: =I8 -> 21475 | ... M20: =M8 -> 23001 | N20: =SUM(B20:M20) -> 519934.4 | O20: =+N20/$N$23 -> 0.069933244
A21: USA | B21: =B9 -> 15 | C21: =C9 -> 2025 | D21: =D9 -> 58728 | E21: =E9 -> 9898 | F21: =F9 -> 47666 | G21: =G9 -> 4178 | H21: =H9 -> 10017 | I21: =I9 -> 1015 | ... M21: =M9 -> 218410 | N21: =SUM(B21:M21) -> 442363 | O21: =+N21/$N$23 -> 0.059499582
A22: Otros | B22: =B10 -> 14044 | C22: =C10 -> 0 | D22: =D10 -> 0 | E22: =E10 -> 14380 | F22: =F10 -> 16000 | G22: =G10 -> 15094 | H22: =H10 -> 5684.8 | I22: =I10 -> 5684.8 | ... M22: =M10 -> 5684.8 | N22: =SUM(B22:M22) -> 93626.8 | O22: =+N22/$N$23 -> 0.012593177
A23: Total | B23: =SUM(B18:B22) -> 502981.61 | C23: =SUM(C18:C22) -> 509774 | D23: =SUM(D18:D22) -> 535881.32 | E23: =SUM(E18:E22) -> 549836.71 | F23: =SUM(F18:F22) -> 550671.96 | G23: =SUM(G18:G22) -> 638751.26 | H23: =SUM(H18:H22) -> 597911.54 | I23: =SUM(I18:I22) -> 664684.84 | ... M23: =SUM(M18:M22) -> 959542.97 | N23: =SUM(B23:M23) -> 7434724.5 | O23: =SUM(O18:O22) -> 1
A25: Gasto Acumulado | B25: =+SUM($B$23:B23) -> 502981.61 | C25: =+SUM($B$23:C23) -> 1012755.6 | D25: =+SUM($B$23:D23) -> 1548636.9 | E25: =+SUM($B$23:E23) -> 2098473.6 | F25: =+SUM($B$23:F23) -> 2649145.6 | G25: =+SUM($B$23:G23) -> 3287896.9 | H25: =+SUM($B$23:H23) -> 3885808.4 | I25: =+SUM($B$23:I23) -> 4550493.2 | ... M25: =+SUM($B$23:M23) -> 7434724.5
A28: País | B28: 45658 | C28: 45689 | D28: 45717 | E28: 45748 | F28: 45778 | G28: 45809 | H28: 45839 | I28: 45870 | J28: 45901 | K28: 45931 | L28: 45962 | M28: 45992 | N28: Total
A29: Chile | B29: =+'Tabla datos unidades_Dic'!D4-B18 -> -16074.025 | C29: =+'Tabla datos unidades_Dic'!E4-C18 -> 148970.62 | D29: =+'Tabla datos unidades_Dic'!F4-D18 -> 31754.14 | E29: =+'Tabla datos unidades_Dic'!G4-E18 -> -98447.529 | F29: =+'Tabla datos unidades_Dic'!H4-F18 -> -52121.875 | G29: =+'Tabla datos unidades_Dic'!I4-G18 -> -97779.191 | H29: =+'Tabla datos unidades_Dic'!J4-H18 -> 123735.01 | I29: =+'Tabla datos unidades_Dic'!K4-I18 -> -259455.3 | ... M29: =+'Tabla datos unidades_Dic'!O4-M18 -> -305118.62 | N29: =SUM(B29:M29) -> -1054810.6
A30: Perú | B30: =+'Tabla datos unidades_Dic'!D5-B19 -> 34385.15 | C30: =+'Tabla datos unidades_Dic'!E5-C19 -> -19143 | D30: =+'Tabla datos unidades_Dic'!F5-D19 -> 12622 | E30: =+'Tabla datos unidades_Dic'!G5-E19 -> -27595.3 | F30: =+'Tabla datos unidades_Dic'!H5-F19 -> 13686 | G30: =+'Tabla datos unidades_Dic'!I5-G19 -> 61593 | H30: =+'Tabla datos unidades_Dic'!J5-H19 -> 52347 | I30: =+'Tabla datos unidades_Dic'!K5-I19 -> 416001 | ... M30: =+'Tabla datos unidades_Dic'!O5-M19 -> 35311 | N30: =SUM(B30:M30) -> 685490.21
A31: Brasil | B31: =+'Tabla datos unidades_Dic'!D6-B20 -> 59479 | C31: =+'Tabla datos unidades_Dic'!E6-C20 -> 31871 | D31: =+'Tabla datos unidades_Dic'!F6-D20 -> 69897 | E31: =+'Tabla datos unidades_Dic'!G6-E20 -> 45205.3 | F31: =+'Tabla datos unidades_Dic'!H6-F20 -> 3745 | G31: =+'Tabla datos unidades_Dic'!I6-G20 -> -9723 | H31: =+'Tabla datos unidades_Dic'!J6-H20 -> 16698 | I31: =+'Tabla datos unidades_Dic'!K6-I20 -> 98177 | ... M31: =+'Tabla datos unidades_Dic'!O6-M20 -> 201115.51 | N31: =SUM(B31:M31) -> 1077157.8
A32: USA | B32: =+'Tabla datos unidades_Dic'!D7-B21 -> 150438 | C32: =+'Tabla datos unidades_Dic'!E7-C21 -> 241440.21 | D32: =+'Tabla datos unidades_Dic'!F7-D21 -> 82798 | E32: =+'Tabla datos unidades_Dic'!G7-E21 -> 159302 | F32: =+'Tabla datos unidades_Dic'!H7-F21 -> 147424 | G32: =+'Tabla datos unidades_Dic'!I7-G21 -> 57618 | H32: =+'Tabla datos unidades_Dic'!J7-H21 -> -10017 | I32: =+'Tabla datos unidades_Dic'!K7-I21 -> 18985 | ... M32: =+'Tabla datos unidades_Dic'!O7-M21 -> -39625 | N32: =SUM(B32:M32) -> 762952.21
A33: Otros | B33: =+'Tabla datos unidades_Dic'!D8-B22 -> -14044 | C33: =+'Tabla datos unidades_Dic'!E8-C22 -> 21682 | D33: =+'Tabla datos unidades_Dic'!F8-D22 -> 45478 | E33: =+'Tabla datos unidades_Dic'!G8-E22 -> -14380 | F33: =+'Tabla datos unidades_Dic'!H8-F22 -> -16000 | G33: =+'Tabla datos unidades_Dic'!I8-G22 -> 156951 | H33: =+'Tabla datos unidades_Dic'!J8-H22 -> -5684.8 | I33: =+'Tabla datos unidades_Dic'!K8-I22 -> 93839.2 | ... M33: =+'Tabla datos unidades_Dic'!O8-M22 -> -5684.8 | N33: =SUM(B33:M33) -> 245102.2
A34: Total | B34: =SUM(B29:B33) -> 214184.13 | C34: =SUM(C29:C33) -> 424820.83 | D34: =SUM(D29:D33) -> 242549.14 | E34: =SUM(E29:E33) -> 64084.471 | F34: =SUM(F29:F33) -> 96733.125 | G34: =SUM(G29:G33) -> 168659.81 | H34: =SUM(H29:H33) -> 177078.21 | I34: =SUM(I29:I33) -> 367546.9 | ... M34: =SUM(M29:M33) -> -114001.91 | N34: =SUM(B34:M34) -> 1715891.9
M38: País | N38: Total
M39: Chile | N39: -746597.6
M40: Otros | N40: 245102.2
M41: USA | N41: 824515.21
M42: Perú | N42: 1006671.5
M43: Brasil | N43: 1070905.6
M44: Total | N44: =SUM(N39:N43) -> 2400596.9

Sheet Flujo Redco Chile
B2: INGENIERÍA REDCO LTDA.
B5: 2025 | C5: 932 | D5: 932 | E5: 932 | F5: 932 | G5: 932 | H5: 932 | I5: 932 | J5: 932 | K5: 932 | L5: 932 | M5: 932 | N5: 932
B6: FLUJO OPERACIONAL MENSUAL 2025 | C6: USD | L6: ESTIMACION | O6: Cierre 2025 | P6: Acumulado septimbre
B7: RESUMEN | C7: 45658 | D7: 45689 | E7: 45717 | F7: 45748 | G7: 45778 | H7: 45809 | I7: 45839 | J7: 45870 | K7: 45901 | L7: 45931 | M7: 45962 | N7: 45992
B8: SALDO CTA. CTE. INICIAL 01-01-2025 | C8: 52257.137 | D8: 170652.7 | E8: 303814.87 | F8: 233924.45 | G8: =+F62 -> 120723.72 | H8: =+G62 -> 79958.162 | I8: =+H62 -> 31896.49 | J8: =+I62 -> 223662.84 | K8: =+J62 -> 357917.35 | L8: =+K62 -> 201391.46 | M8: =+L62 -> 55700.807 | N8: =+M62 -> 20054.377 | O8: =SUM(C8) -> 52257.137 | P8: =+C8 -> 52257.137
B10: TOTAL INGRESOS OPERACIONALES PEND. 2024 | C10: =295745152/$C$5 -> 317323.12 | D10: =158772783/D5 -> 170357.06 | O10: =SUM(C10:N10) -> 487680.19 | P10: =SUM(C10:K10) -> 487680.19 | R10: =SUM(C10:K10) -> 487680.19
B11: TOTAL INGRESOS OPERACIONALES 2025 | C11: =41976916/C5 -> 45039.609 | D11: =351320714/D5 -> 376953.56 | E11: =+E108/E5 -> 389727.46 | F11: =+F108/932 -> 237434.48 | G11: =+G108/932 -> 272631.08 | H11: =+H108/H5 -> 277419.07 | I11: =+I108/I5 -> 475570.75 | J11: =+J108/J5 -> 151482.74 | K11: =+K108/K5 -> 297925.05 | L11: =+L108/L5 -> 158266.46 | M11: =+M108/M5 -> 248788.93 | N11: =+N108/N5 -> 173207.55 | O11: =SUM(C11:N11) -> 3104446.7 | P11: =SUM(C11:K11) -> 2524183.8 | R11: =SUM(C11:K11) -> 2524183.8
B12: SUMA INGRESOS | C12: =SUM(C10:C11) -> 362362.73 | D12: =SUM(D10:D11) -> 547310.62 | E12: =SUM(E10:E11) -> 389727.46 | F12: =SUM(F10:F11) -> 237434.48 | G12: =SUM(G10:G11) -> 272631.08 | H12: =SUM(H10:H11) -> 277419.07 | I12: =SUM(I10:I11) -> 475570.75 | J12: =SUM(J10:J11) -> 151482.74 | ... P12: =SUM(P10:P11) -> 3011864 | R12: =SUM(R10:R11) -> 3011864
B14: COSTOS OPERACIONALES
B15: SUELDOS OPERACIONALES | C15: =C219/C$5 -> 296365.75 | D15: =D219/D$5 -> 217677.86 | E15: =E219/E$5 -> 233021.54 | F15: =F219/F$5 -> 228394.96 | G15: =G219/G$5 -> 231362.41 | H15: =H219/H$5 -> 243495.99 | I15: =I219/I$5 -> 245077.71 | J15: =J219/J$5 -> 243804.61 | ... N15: =N219/N$5 -> 328358.27 | O15: =SUM(C15:N15) -> 3082559.8 | P15: =SUM(C15:K15) -> 2211147.8
B16: HONORARIOS OPERACIONALES | C16: =C264/C$5 -> 32187.763 | D16: =D264/D$5 -> 101834.87 | E16: =E264/E$5 -> 53183.325 | F16: =F264/F$5 -> 21195.825 | G16: =G264/G$5 -> 36226.974 | H16: =H264/H$5 -> 61268.946 | I16: =I264/I$5 -> 66938.033 | J16: =J264/J$5 -> 48980.67 | ... N16: =N264/N$5 -> 59812.345 | O16: =SUM(C16:N16) -> 731847.19 | P16: =SUM(C16:K16) -> 485462.78
B17: GASTOS OPERACIONALES | C17: =C313/C$5 -> 46762.552 | D17: =D313/D$5 -> 34449.546 | E17: =E313/E$5 -> 97328.251 | F17: =F313/F$5 -> 30391.817 | G17: =G313/G$5 -> 12830.892 | H17: =H313/H$5 -> 19747.438 | I17: =I313/I$5 -> 23151.506 | J17: =J313/J$5 -> 61059.267 | ... N17: =N313/N$5 -> 49351.835 | O17: =SUM(C17:N17) -> 520272.6 | P17: =SUM(C17:K17) -> 387411.07
B18: TOTAL COSTOS OPERACIONALES | C18: =SUM(C15:C17) -> 375316.06 | D18: =SUM(D15:D17) -> 353962.27 | E18: =SUM(E15:E17) -> 383533.12 | F18: =SUM(F15:F17) -> 279982.6 | G18: =SUM(G15:G17) -> 280420.28 | H18: =SUM(H15:H17) -> 324512.38 | I18: =SUM(I15:I17) -> 335167.25 | J18: =SUM(J15:J17) -> 353844.55 | ... P18: =SUM(P15:P17) -> 3084021.7
B20: COSTOS ADMINISTRATIVOS
B21: SUELDOS ADMINISTRACION | C21: =+C337/C$5 -> 13124.477 | D21: =+D337/D$5 -> 41659.748 | E21: =+E337/E$5 -> 39422.749 | F21: =+F337/F$5 -> 38934.07 | G21: =+G337/G$5 -> 34836.985 | H21: =+H337/H$5 -> 34231.018 | I21: =+I337/I$5 -> 35772.865 | J21: =+J337/J$5 -> 38882.344 | ... N21: =+N337/N$5 -> 32452.514 | O21: =SUM(C21:N21) -> 363398.77 | P21: =SUM(C21:K21) -> 316458.42
B22: GASTOS DE ADMINISTRACION | C22: =+C382/C$5 -> 5312.6223 | D22: =+D382/D$5 -> 26504.619 | E22: =+E382/E$5 -> 16943.313 | F22: =+F382/F$5 -> 22590.674 | G22: =+G382/G$5 -> 15258.224 | H22: =+H382/H$5 -> 21822.773 | I22: =+I382/I$5 -> 24787.067 | J22: =+J382/J$5 -> 23611.129 | ... N22: =+N382/N$5 -> 25530.576 | O22: =SUM(C22:N22) -> 279135.48 | P22: =SUM(C22:K22) -> 175824.41
B23: TOTAL COSTOS ADMINISTRATIVOS | C23: =SUM(C21:C22) -> 18437.1 | D23: =SUM(D21:D22) -> 68164.367 | E23: =SUM(E21:E22) -> 56366.062 | F23: =SUM(F21:F22) -> 61524.744 | G23: =SUM(G21:G22) -> 50095.209 | H23: =SUM(H21:H22) -> 56053.791 | I23: =SUM(I21:I22) -> 60559.931 | J23: =SUM(J21:J22) -> 62493.473 | ... P23: =SUM(P21:P22) -> 492282.83
B25: ACTIVO: REMODELACION PROP.AJENA OF. 1502 | C25: =+C317/C$5 -> 3523.4871 | D25: =+D317/D$5 -> 0 | E25: =+E317/E$5 -> 0 | F25: =+F317/F$5 -> 0 | G25: =+G317/G$5 -> 9619.3144 | H25: =+H317/H$5 -> 0 | I25: =+I317/I$5 -> 0 | J25: =+J317/J$5 -> 8910.883 | ... N25: =+N317/N$5 -> 0 | O25: =SUM(C25:N25) -> 22053.685 | P25: =SUM(C25:K25) -> 22053.685
B27: RESULTADO OPERACIONALES | C27: =SUM(C12-C18-C23-C25) -> -34913.914 | D27: =SUM(D12-D18-D23-D25) -> 125183.98 | E27: =SUM(E12-E18-E23-E25) -> -50171.722 | F27: =SUM(F12-F18-F23-F25) -> -104072.86 | G27: =SUM(G12-G18-G23-G25) -> -67503.719 | H27: =SUM(H12-H18-H23-H25) -> -103147.1 | I27: =SUM(I12-I18-I23-I25) -> 79843.563 | J27: =SUM(J12-J18-J23-J25) -> -273766.17 | ... P27: =SUM(P12-P18-P23-P25) -> -586494.21
B30: OTROS INGRESOS NO OPERACIONALES
B31: INGRESO IVA DEBITO FACTURACION | C31: =+C112/C5 -> 69432.94 | D31: =+D112/D5 -> 104811.9 | E31: =+E112/E5 -> 75208.024 | F31: =+F112/932 -> 47094.724 | G31: =+G112/932 -> 62773.513 | H31: =+H112/H5 -> 53789.215 | I31: =+I112/I5 -> 103658.78 | J31: =+J112/J5 -> 35825.605 | K31: =+K112/K5 -> 57280.832 | L31: =+L112/L5 -> 32498.942 | M31: =+M112/M5 -> 37753.16 | N31: =+N112/N5 -> 32909.433 | O31: =SUM(C31:N31) -> 713037.07 | P31: =SUM(C31:K31) -> 609875.53
B32: INGRESO FACTURACION POR REDTEC | C32: =+C127/C5 -> 57052.603 | D32: =+D127/D5 -> 113524.2 | F32: =(+F127+F122)/932 -> 146563.3 | G32: =+G127/932 -> 9291.9936 | H32: =+H127/932 -> 0 | I32: =+I127/932 -> 0 | J32: =+J127/932 -> 0 | K32: =+K127/932 -> 27214.364 | L32: =+L127/932 -> 0 | M32: =+M127/932 -> 0 | N32: =+N127/932 -> 0 | O32: =SUM(C32:N32) -> 353646.46 | P32: =SUM(C32:K32) -> 353646.46
B33: CTA.CTE. EERR REDCROSS S.A. | M33: =+M125/932 -> 26824.034 | N33: =+N125/932 -> 4862.8755 | O33: =SUM(C33:N33) -> 31686.91 | P33: =SUM(C33:K33) -> 0
B34: ANGLO AMERICAN Ing.tilizació Tecnología HDD | C34: =+C118 -> 0 | D34: =+D118 -> 0 | E34: =+E118/E5 -> 5265.8026 | F34: =+F118/F5 -> 10432.481 | G34: =+G118/G5 -> 40299.51 | H34: =+H118/H5 -> 0 | I34: =+I118/I5 -> 67413.998 | J34: =+J118/J5 -> 37073.082 | K34: =+K118/K5 -> 3553.0075 | L34: =+L118/L5 -> 23055.238 | ... N34: =+N118/N5 -> 0 | O34: =SUM(C34:N34) -> 187093.12 | P34: =SUM(C34:K34) -> 164037.88
B35: INGRESO CTA. CTE. REDCO PERU | C35: =+C121/C5 -> 134087.98 | E35: =+E121/D5 -> 0 | F35: =+F121/E5 -> 0 | G35: =+G121/F5 -> 0 | H35: =+H121/G5 -> 0 | I35: =+I121/H5 -> 0 | J35: =+J119/J5 -> 459872.82 | K35: =+K119/K5 -> 0 | L35: =+L119/L5 -> 154199.14 | M35: =+M121/M5 -> 120289.84 | N35: =+N121/N5 -> 0 | O35: =SUM(C35:N35) -> 868449.79 | P35: =SUM(C35:K35) -> 593960.81
B36: INGRESO CTA.CTE. BVI (Rend. viaje P.A) | E36: =(+E117)/E5 -> 14640.397 | F36: =+F117/F5 -> 48275.16 | G36: =+G117/932 -> 32259.954 | H36: =+H117/932 -> 0 | I36: =+I117/932 -> 46679.406 | J36: =+J117/932 -> 0 | K36: =+K117/932 -> 0 | L36: =+L117/932 -> 0 | M36: =+M117/932 -> 0 | N36: =+N117/932 -> 390966.74 | O36: =SUM(C36:N36) -> 532821.65 | P36: =SUM(C36:K36) -> 141854.92
B37: INGRESO CTA.CTE. USA (C.Caro viaje) | E37: =+E120/E5 -> 5175.8927 | F37: =+F120/F5 -> 0 | G37: =+G120/G5 -> 0 | H37: =+H120/H5 -> 0 | I37: =+I120/I5 -> 0 | J37: =+J120/J5 -> 0 | K37: =+K120/K5 -> 0 | L37: =+L120/L5 -> 0 | ... N37: =+N120/N5 -> 0 | O37: =SUM(C37:N37) -> 5175.8927 | P37: =SUM(C37:K37) -> 5175.8927
B38: DEVOLUCION BOLETA GARANTIA CMP | D38: =+D124/D5 -> 10399.317 | F38: =+F124/932 -> 11315.145 | O38: =SUM(C38:N38) -> 21714.461 | P38: =SUM(C38:K38) -> 21714.461
B39: RECUPERACION GASTOS / OTROS INGRESOS | C39: =+C123/C5 -> 703.28541 | G39: =(+G123+G124)/932 -> 15361.519 | H39: =(+H123+H124)/932 -> 0 | I39: =(+I123+I124)/932 -> 1266.618 | J39: =(+J123+J124)/932 -> 0 | K39: =(+K123+K124)/932 -> 516.93991 | L39: =(+L123+L124)/932 -> 13.927039 | M39: =(+M123+M124)/932 -> 415.80687 | N39: =(+N123+N124)/932 -> 119.83584 | O39: =SUM(C39:N39) -> 18397.932 | P39: =SUM(C39:K39) -> 17848.363
B40: RESCATE FFMM BANCHILE | E40: 0 | F40: 0 | G40: 0 | H40: =+H126/H5 -> 89784.033 | I40: =+I126/I5 -> 0 | J40: =+J126/J5 -> 0 | K40: =+K126/K5 -> 0 | L40: =+L126/L5 -> 81630.901 | M40: =+M126/M5 -> 0 | N40: =+N126/N5 -> 0 | O40: =SUM(C40:N40) -> 171414.93 | P40: =SUM(C40:K40) -> 89784.033
B41: OTROS INGRESOS NO OPERACIONALES | C41: =SUM(C31:C40) -> 261276.81 | D41: =SUM(D31:D40) -> 228735.41 | E41: =SUM(E31:E40) -> 100290.12 | F41: =SUM(F31:F40) -> 263680.81 | G41: =SUM(G31:G40) -> 159986.49 | H41: =SUM(H31:H40) -> 143573.25 | I41: =SUM(I31:I40) -> 219018.81 | J41: =SUM(J31:J40) -> 532771.51 | ... P41: =SUM(P31:P40) -> 1997898.3
C42: =+'Tabla datos unidades'!D2 -> 0
B43: OTROS EGRESOS NO OPERACIONALES
B44: IMPUESTOS PPM-IVA-IMPTO.ADICIONAL | C44: =SUM(C390)/$C$5 -> 34979.334 | D44: =SUM(+D390/$D$5) -> 63266.452 | E44: =SUM(E390)/$E$5 -> 11946.348 | F44: =SUM(F390)/$E$5 -> 31666.326 | G44: =SUM(G390)/$E$5 -> 65886.451 | H44: =(+H387+H388)/932 -> 41468.266 | I44: =(+I387+I388)/932 -> 8884.088 | J44: =(+J387+J388)/932 -> 86387.474 | K44: =(+K387+K388)/932 -> 27284.615 | L44: =(+L387+L388)/932 -> 47891.939 | M44: =(+M387+M388)/932 -> 45200.18 | N44: =(+N387+N388)/932 -> 24253.626 | O44: =SUM(C44:N44) -> 489115.1 | P44: =SUM(C44:K44) -> 371769.35
B45: CREDITO HIPOTECARIO | C45: =+C394/$C$5 -> 7459.9185 | D45: =+D394/$D$5 -> 7447.9721 | E45: =+E394/$E$5 -> 7527.5021 | F45: =+F394/932 -> 7557.47 | G45: =+G394/932 -> 7593.5633 | H45: =+H394/932 -> 7608.8283 | I45: =+I394/932 -> 7622.1137 | J45: =+J394/932 -> 7593.1609 | K45: =+K394/932 -> 7660.0676 | L45: =+L394/932 -> 7660.6148 | M45: =+M394/932 -> 7689.823 | N45: =+N394/932 -> 7690.1234 | O45: =SUM(C45:N45) -> 91111.158 | P45: =SUM(C45:K45) -> 68070.597
B46: CREDITO FINANCIAMIENTO | C46: =+C395/$C$5 -> 20139.617 | D46: =+D395/$D$5 -> 20125.996 | E46: =+E395/$E$5 -> 20113.231 | F46: =+F395/932 -> 20118.032 | G46: =+G395/932 -> 20099.053 | H46: =+H395/932 -> 20097.425 | I46: =+I395/932 -> 20091.003 | J46: =+J395/932 -> 20078.588 | K46: =+K395/932 -> 20073.063 | L46: =+L395/932 -> 20064.779 | M46: =+M395/932 -> 20055.863 | N46: =+N395/932 -> 20047.678 | O46: =SUM(C46:N46) -> 241104.33 | P46: =SUM(C46:K46) -> 180936.01
B47: CREDITO VEHICULOS | C47: =+C396 -> 0 | D47: =+D396/D5 -> 11057.313 | E47: =+E396/E5 -> 3045.9936 | F47: =+F396/932 -> 4191.3884 | G47: =+G396/932 -> 4968.3144 | H47: =+H396/932 -> 0 | I47: =+I396/932 -> 4169.6663 | J47: =+J396/932 -> 3045.9936 | K47: =+K396/932 -> 1922.3208 | L47: =+L396/932 -> 4169.6663 | M47: =+M396/932 -> 1922.3208 | N47: =+N396/932 -> 3046.3165 | O47: =SUM(C47:N47) -> 41539.294 | P47: =SUM(C47:K47) -> 32400.99
B48: APORTE FFMM BANCHILE | E48: =E126/E5*-1 -> 0 | F48: =F126/F5*-1 -> 0 | G48: =G126/G5*-1 -> 0 | O48: =SUM(C48:N48) -> 0 | P48: =SUM(C48:K48) -> 0
B49: TOTAL EGRESOS NO OPERACIONALES | C49: =SUM(C44:C48) -> 62578.869 | D49: =SUM(D44:D48) -> 101897.73 | E49: =SUM(E44:E48) -> 42633.074 | F49: =SUM(F44:F48) -> 63533.217 | G49: =SUM(G44:G48) -> 98547.381 | H49: =SUM(H44:H48) -> 69174.519 | I49: =SUM(I44:I48) -> 40766.871 | J49: =SUM(J44:J48) -> 117105.22 | ... P49: =SUM(P44:P48) -> 653176.95
B51: OTROS EGRESOS CTA.CTE. EERR
B52: CTA. CTE. BVI - PAGO SUECOS | C52: =SUM(C400/932) -> 21128.81 | E52: =+E400/E5 -> 15004.844 | F52: =+F400/F5 -> 63157.352 | G52: =+G400/G5 -> 21578.873 | H52: =+H400/932 -> 19313.305 | I52: =+I400/932 -> 56691.818 | J52: =+J400/932 -> 7645.6223 | K52: =+K400/932 -> 0 | L52: =+L400/932 -> 0 | M52: =+M400/932 -> 0 | N52: =+N400/932 -> 0 | O52: =SUM(C52:N52) -> 204520.62 | P52: =SUM(C52:K52) -> 204520.62
B53: CTA. CTE. REDTEC - DEV. FACT.REDCO | C53: =(11900000+10710000)/C5 -> 24259.657 | D53: =+D401/E5 -> 113524.2 | E53: =+E401/E5 -> 57052.603 | F53: =+F401/F5 -> 140964.71 | G53: =+G401/G5 -> 9291.9936 | H53: =+H401/932 -> 0 | I53: =+I401/932 -> 0 | J53: =+J401/932 -> 0 | K53: =+K401/932 -> 27214.364 | L53: =+L401/932 -> 0 | M53: =+M401/932 -> 0 | N53: =+N401/932 -> 388.07725 | O53: =SUM(C53:N53) -> 372695.6 | P53: =SUM(C53:K53) -> 372307.53
B54: CTA. CTE. REDCO USA | E54: =+E403/E5 -> 5318.2951 | F54: =+F403/F5 -> 0 | G54: =+G403/G5 -> 0 | H54: =+H402/H5 -> 0 | I54: =+I402/I5 -> 0 | J54: =+J402/J5 -> 0 | K54: =+K403/K5 -> 1851.8798 | L54: =+L403/L5 -> 0 | M54: =+M403/M5 -> 0 | N54: =+N403/N5 -> 0 | O54: =SUM(C54:N54) -> 7170.1749 | P54: =SUM(C54:K54) -> 7170.1749
B55: CTA. CTE. REDCO PERU | D55: =+D404/E5 -> 5335.2929 | N55: 46749.957 | O55: =SUM(C55:N55) -> 52085.25 | P55: =SUM(C55:K55) -> 5335.2929
B56: CTA. CTE. REDTEC/ Patente R+ julio | F56: =(+F402)/932 -> 4860.6942 | G56: =(+G402)/932 -> 0 | H56: 0 | I56: =+I404/I5 -> 126.67918 | J56: =+J404/J5 -> 0 | K56: =+K404/K5 -> 0 | L56: =+L404/L5 -> 0 | M56: =+M404/M5 -> 0 | N56: =+N404/N5 -> 0 | O56: =SUM(C56:N56) -> 4987.3734 | P56: =SUM(C56:K56) -> 4987.3734
B57: DIFERENCIA DE CAMBIO | F57: =+F405/932 -> 292.70386 | G57: =+G405/932 -> 3830.0805 | H57: =+H405/932 -> 0 | I57: =+I405/932 -> 9510.6481 | J57: =+J405/932 -> 0 | K57: =+K405/932 -> 1138.4474 | L57: =+L405/932 -> 2382.5966 | M57: =+M405/932 -> 2631.897 | N57: =+N405/932 -> 1155.4399 | O57: =SUM(C57:N57) -> 20941.813 | P57: =SUM(C57:K57) -> 14771.88
B58: TOTAL PAGOS CTA.CTE. EERR | C58: =SUM(C52:C56) -> 45388.467 | D58: =SUM(D52:D56) -> 118859.49 | E58: =SUM(E52:E56) -> 77375.742 | F58: =SUM(F52:F57) -> 209275.46 | G58: =SUM(G52:G57) -> 34700.947 | H58: =SUM(H52:H57) -> 19313.305 | I58: =SUM(I52:I57) -> 66329.145 | J58: =SUM(J52:J57) -> 7645.6223 | K58: =SUM(K52:K57) -> 30204.691 | L58: =SUM(L52:L57) -> 2382.5966 | M58: =SUM(M52:M57) -> 2631.897 | ... P58: =SUM(P52:P57) -> 609092.87
B60: SALDO FLUJO REDCO MENSUAL | C60: =SUM(C27+C41-C49-C58) -> 118395.56 | D60: =SUM(D27+D41-D49-D58) -> 133162.17 | E60: =SUM(E27+E41-E49-E58) -> -69890.423 | F60: =SUM(F27+F41-F49-F58) -> -113200.73 | G60: =SUM(G27+G41-G49-G58) -> -40765.558 | H60: =SUM(H27+H41-H49-H58) -> -48061.672 | I60: =SUM(I27+I41-I49-I58) -> 191766.35 | J60: =SUM(J27+J41-J49-J58) -> 134254.5 | ... P60: =SUM(P27+P41-P49-P58) -> 149134.32
B62: SALDO FLUJO REDCO + SALDO INCIAL | C62: =SUM(C8+C60) -> 170652.7 | D62: =SUM(D8+D60) -> 303814.87 | E62: =SUM(E8+E60) -> 233924.45 | F62: =SUM(F8+F60) -> 120723.72 | G62: =SUM(G8+G60) -> 79958.162 | H62: =SUM(H8+H60) -> 31896.49 | I62: =SUM(I8+I60) -> 223662.84 | J62: =SUM(J8+J60) -> 357917.35 | ... P62: =SUM(P8+P60) -> 201391.46
C63: =+C412/C5 -> 170652.7 | D63: =+D412/D5 -> 303814.87 | E63: =+E412/E5 -> 233924.45 | F63: =+F412/F5 -> 120723.72 | G63: =+G412/932 -> 79958.162 | H63: =+H412/H5 -> 31896.49 | I63: =+I412/I5 -> 223662.84 | J63: =+J412/J5 -> 357917.34 | K63: =+K412/K5 -> 201391.45
B70: INGRESOS INGENIERÍA CHILE | C70: 45658 | D70: 45689 | E70: 45717 | F70: 45748 | G70: 45778 | H70: 45809 | I70: 45839 | J70: 45870 | K70: 45901 | L70: 45931 | M70: 45962 | N70: 45992
B71: CLIENTE | C71: MONTO $ | D71: MONTO $ | E71: MONTO $ | F71: MONTO $ | G71: MONTO $ | H71: MONTO $ | I71: MONTO $ | J71: MONTO $ | K71: MONTO $ | L71: MONTO $ | M71: MONTO $ | N71: MONTO $
B72: CMP Dev.5% Estudio Explot.Stock de Minerales de Hierro | L72: 11254887 | M72: 47414137 | N72: 0
B73: CPM Plan LOM Estabilizado. PFS UG y LINK LP del Valle; El Romeral | C73: 83858385 | N73: 0
B74: CPM Ing. Básico Proy. Algarrobo Finos | H74: 100617860 | N74: 0
B75: CMP S.A. Estudio Implem. Mina UG-SLS en ROM y Consoli.LOM 2024 en CNN y MLC | C75: 82670896 | D75: =+'Facturas e Ingresos 2025'!E20+'Facturas e Ingresos 2025'!E28 -> 150942195 | E75: 44047733 | F75: 39685751 | N75: 0
B76: CMP S.A. Consolidación LOM 2024 en CNN y MLC | C76: 80377561 | N76: 0
B77: CMP S.A. Analisis de Factibilidad Minera mejoras OP CNN y Desarr caso Exp | C77: 41976916 | D77: =+'Facturas e Ingresos 2025'!E31 -> 9265729 | E77: 14847194 | G77: 10870940 | I77: 27818176 | N77: 0
B78: CMP S.A. Análisis de Estabilidad de Botadero Romeral UG. | H78: 14385310 | N78: 0
B79: CMP S.A. Puesta en Marcha Galería de Exploración Romeral CMP | H79: 29985727 | N79: 0
B80: CMP S.A. Actualización casos base 55,60 y 68 KTDP | L80: 31899667 | N80: 0
B81: CODELCO Serv. Apoyo documentación pract.planif. | D81: =+'Facturas e Ingresos 2025'!E22 -> 14077368 | K81: =29125728+10941351 -> 40067079 | N81: 0
B82: CODELCO Serv. Estudio de modif. Para actualización | D82: =+'Facturas e Ingresos 2025'!E23 -> 32070646 | N82: 0
B83: CODELCO Serv. Estandar y Procesamiento cierre topográfico | D83: =+'Facturas e Ingresos 2025'!E24+'Facturas e Ingresos 2025'!E25 -> 28803159 | K83: 7369894 | N83: 0
B84: CODELCO Análisis Opciones de vaciado mineral Mina Subterránea vía rajo | I84: 10349857 | N84: 0
B85: M. Candelaria Servicios de Ingeniería de Valor Proyecto CUGEP | D85: =+'Facturas e Ingresos 2025'!E21 -> 34170570 | N85: 0
B86: MEL - Estudio FEL 1 Op. de acceso exploratorio - Escondida East Deep | G86: =33123735+45871382 -> 78995117 | H86: 30833224 | I86: 37510072 | J86: 29180697 | K86: 11473679 | N86: 0
B87: AMSA - Servicio de Apoyo a Gerencia de Minería 2024-2025 | D87: =+'Facturas e Ingresos 2025'!E27 -> 14564501 | E87: 7736812 | F87: =+'Facturas e Ingresos 2025'!E45 -> 10399331 | G87: 12800016 | N87: 0
B88: AMSA - Trade O Tecnológico nueva generación de Distrito | E88: 30291258 | F88: =30539742+29761659 -> 60301401 | I88: 36881600 | N88: 0
B89: BHP Chile INC EdP01 Análisis de confiabilidad del Plan 2YB (2026-2027) | E89: 34324224 | N89: 0
B90: CMP S.A. -Estrategia Minera MLC Brownfield y TN Modular | D90: =+'Facturas e Ingresos 2025'!E33 -> 67426546 | G90: 30733290 | I90: 13211845 | N90: 0
B91: CMP S.A. - Actualización de caso de negocios de CNN | I91: 4794805 | N91: 0
B92: CMP S.A. EdP01 Actualización de caso de negocios de CNN | M92: 13908694 | N92: 0
B93: CMP S.A. EdP01 ÚNICO Apoyo respuesta ICSARA DIA MER | M93: 20231452 | N93: 0
B94: MANTOS COPPER Estimación Confiabilidad de Planes Mineros | C94: 48838310 | N94: 40381474
B95: MANTOVERDE S.A. Confiabilidad de Planes Budget 2026 | L95: 23657641 | N95: 11683334
B96: MANTOS COPPER S.A. Confiabilidad de Planes Budget 2026 | L96: 13946282 | N96: 0
B97: SCM MINERA LUMINA COPPER ServicIos de Asesorìa y Estudios de Ingeniería | F97: =+'Facturas e Ingresos 2025'!E41 -> 81486288 | N97: 0
B98: SCM MINERA LUMINA COPPER Serv.estrategia de crecimiento distrito caserones | J98: 52829556 | K98: 67578326 | L98: 66745864 | M98: 51011492 | N98: 29232841
B99: CIA.MINERA SIERRA NORTE | D99: =+'Facturas e Ingresos 2025'!E14+'Facturas e Ingresos 2025'!E15 -> 158772783 | G99: 33825290 | N99: 0
B100: MINERA COLLAHUASI EdP01 Servicios de análisis Mine Compliance | M100: 31516089 | N100: 7092334
B101: CIA.MINERA CERRO COLORADO Diseño medidas de cierre Botaderos Lastre | E101: =82945096+120957046 -> 203902142 | G101: 86867518 | H101: 66180796 | I101: 312665583 | K101: 151177169 | M101: 40818500 | N101: 0
B102: ANGLO AMERICAN Estudio Productividda Transp | J102: 59171658 | N102: 0
B103: ANGLO AMERICAN Technial Producc.At Ris Minas Rios | N103: 73039454
B104: MC Inversiones Saldo + adic. Los Bronces Mine Plan Review | F104: 29416169 | N104: 0
B105: Minera Spence análisis factibilidad y detecc. Cuello de botella del LoA | E105: 28076627 | H105: =5986363+10565296 -> 16551659 | N105: 0
B106: The Boston EdP Unico Apoyo de Análisis Normas y Guías Planif.CODELCO | M106: 17260200 | N106: 0
B107: Soc. Punta del Cobre EdP01 Acompañamiento resrevas Tovaku de Pucobre | M107: 9710715 | N107: 0
B108: INGRESOS OPERACIONALES | C108: =SUM(C72:C107) -> 337722068 | D108: =SUM(D72:D107) -> 510093497 | E108: =SUM(E72:E107) -> 363225990 | F108: =SUM(F72:F107) -> 221288940 | G108: =SUM(G72:G107) -> 254092171 | H108: =SUM(H72:H107) -> 258554576 | I108: =SUM(I72:I107) -> 443231938 | J108: =SUM(J72:J107) -> 141181911 | ... N108: =SUM(N72:N107) -> 161429437
B110: IVA DEBITO FISCAL | C110: 45658 | D110: 45689 | E110: 45717 | F110: 45748 | G110: 45778 | H110: 45809 | I110: 45839 | J110: 45870 | K110: 45901 | L110: 45931 | M110: 45962 | N110: 45992
B111: CLIENTE | C111: MONTO $ | D111: MONTO $ | E111: MONTO $ | F111: MONTO $ | G111: MONTO $ | H111: MONTO $ | I111: MONTO $ | J111: MONTO $ | K111: MONTO $ | L111: MONTO $ | M111: MONTO $ | N111: MONTO $
B112: IVA DEBITO FISCAL | C112: =73201311-8489811 -> 64711500 | D112: =114577851-16893164 -> 97684687 | E112: 70093878 | F112: =64868779-20976496 -> 43892283 | G112: 58504914 | H112: 50131548 | I112: 96609987 | J112: =19931892+10037616+3419956 -> 33389464 | K112: 53385735 | L112: 30289014 | M112: 35185945 | N112: 30671592
B113: SUMAS | C113: =SUM(C112:C112) -> 64711500 | D113: =SUM(D112:D112) -> 97684687 | E113: =SUM(E112:E112) -> 70093878 | F113: =SUM(F112:F112) -> 43892283 | G113: =SUM(G112:G112) -> 58504914 | H113: =SUM(H112:H112) -> 50131548 | I113: =SUM(I112:I112) -> 96609987 | J113: =SUM(J112:J112) -> 33389464 | ... N113: =SUM(N112:N112) -> 30671592
B115: INGRESOS EXTRAORDINARIOS | C115: 45658 | D115: 45689 | E115: 45717 | F115: 45748 | G115: 45778 | H115: 45809 | I115: 45839 | J115: 45870 | K115: 45901 | L115: 45931 | M115: 45962 | N115: 45992
B116: CLIENTE
B117: Ingresos cta. cte. BVI | E117: 13644850 | F117: 44992449 | G117: 30066277 | I117: 43505206 | L117: 0 | M117: 0 | N117: 364381000
B118: ANGLO AMERICAN Ing.tilizació Tecnología HDD Capt.Aguas Claras | E118: 4907728 | F118: 9723072 | G118: 37559143 | I118: 62829846 | J118: 34552112 | K118: 3311403 | L118: 21487482 | M118: 0 | N118: 0
B119: Factura Redco Global Perú SAC | J119: 428601471 | L119: 1.437136e+08 | M119: 0 | N119: 0
B120: Dev.Cta.Cte. Redco USA | E120: 4823932 | L120: 0 | M120: 0 | N120: 0
B121: Dev. Cta.cte. Redco Perú | C121: 124970002 | L121: 0 | M121: 112110131 | N121: 0
...

Sheet Flujo Redco Perú
B1: INGENIERIA REDCO GLOBAL PERU SAC
B3: 2025
B6: FLUJO OPERACIONAL MENSUAL 2025 | C6: REAL | D6: REAL | E6: REAL | F6: REAL | G6: REAL | H6: REAL | I6: REAL | J6: REAL | K6: REAL | L6: REAL | M6: REAL
P7: =SUM(P6-O14) -> 0
B8: RESUMEN | C8: 45658 | D8: 45689 | E8: 45717 | F8: 45748 | G8: 45778 | H8: 45809 | I8: 45839 | J8: 45870 | K8: 45901 | L8: 45931 | M8: 45962 | N8: 45992 | O8: Cierre 2025 | P8: Acumulado septimbre
B9: SALDO CTA. CTE. INICIAL 01-01-2025 | C9: =+C70 -> 136767.69 | D9: =+C58 -> 140565.84 | E9: =+D58 -> 137922.84 | F9: =+E58 -> 203057.84 | G9: =+F58 -> 201993.54 | H9: =+G58 -> 196994.54 | I9: =+H58 -> 239089.54 | J9: =+I58 -> 287968.54 | K9: =+J58 -> 255462.54 | ... N9: =+M58 -> 106114.9 | O9: =+C9 -> 136767.69 | P9: =+C9 -> 136767.69
B11: TOTAL INGRESOS OPERACIONALES PEND. 2024 | C11: =+C88-C74 -> 110536 | D11: =+D79 -> 21582 | E11: 0 | F11: 0 | G11: 0 | H11: 0 | I11: 0 | J11: 0 | K11: 1 | O11: =SUM(C11:N11) -> 132119 | P11: =SUM(C11:K11) -> 132119
B12: TOTAL INGRESOS OPERACIONALES 2025 | C12: =+C74 -> 13312 | D12: =+D75 -> 40872 | E12: =+E88-E80 -> 105377 | F12: =+F88 -> 110077 | G12: =+G88-G80 -> 142610 | H12: =+H88-H80 -> 229588 | I12: =+I88 -> 251702 | J12: =+J88 -> 641573 | K12: =+K88 -> 119132 | L12: =+L88 -> 265449 | M12: =+M88 -> 96110 | N12: =+N88 -> 269432 | O12: =SUM(C12:N12) -> 2285234 | P12: =SUM(C12:K12) -> 1654243
B13: TOTAL INGRESOS | C13: =SUM(C11:C12) -> 123848 | D13: =SUM(D11:D12) -> 62454 | E13: =SUM(E11:E12) -> 105377 | F13: =SUM(F11:F12) -> 110077 | G13: =SUM(G11:G12) -> 142610 | H13: =SUM(H11:H12) -> 229588 | I13: =SUM(I11:I12) -> 251702 | J13: =SUM(J11:J12) -> 641573 | ... P13: =SUM(P11:P12) -> 1786362
B15: COSTOS OPERACIONALES | C15: 45658 | D15: 45689 | E15: 45717 | F15: 45748 | G15: 45778 | H15: 45809 | I15: 45839 | J15: 45870 | K15: 45901 | L15: 45931 | M15: 45962 | N15: 45992 | O15: 2025 | P15: ACUMULADO
B16: SUELDOS OPERACIONALES | C16: =+C142+C246 -> 52457 | D16: =+D142+D246 -> 66972 | E16: =+E142+E246 -> 58024 | F16: =+F142+F246 -> 68560 | G16: =+G142+G246 -> 76486 | H16: =+H142+H246 -> 80010 | I16: =+I142+I246 -> 105334 | J16: =+J142+J246 -> 96619 | ... N16: =+N142+N246 -> 169943 | O16: =SUM(C16:N16) -> 983242 | P16: =+SUM(C16:K16) -> 663451
B17: HONORARIOS OPERACIONALES | C17: =+C182 -> 6366 | D17: =+D182 -> 2679 | E17: =+E182 -> 7822 | F17: =+F182 -> 33321.3 | G17: =+G182 -> 25106 | H17: =+H182 -> 58015 | I17: =+I182 -> 70365 | J17: =+J182 -> 79631 | ... N17: =+N182 -> 21319 | O17: =SUM(C17:N17) -> 361181.94 | P17: =+SUM(C17:K17) -> 313297.3
B18: GASTOS OPERACIONALES | C18: =+C223 -> 4852.85 | D18: =+D223 -> -153 | E18: =+E223 -> 4112 | F18: =+F223 -> 5313 | G18: =+G223 -> 2038 | H18: =+H223 -> 459 | I18: =+I223 -> 2551 | J18: =+J223 -> 21976 | ... N18: =+N223 -> 0 | O18: =SUM(C18:N18) -> 53547.85 | P18: =+SUM(C18:K18) -> 48883.85
B19: TOTAL COSTOS OPERACIONALES | C19: =SUM(C16:C18) -> 63675.85 | D19: =SUM(D16:D18) -> 69498 | E19: =SUM(E16:E18) -> 69958 | F19: =SUM(F16:F18) -> 107194.3 | G19: =SUM(G16:G18) -> 103630 | H19: =SUM(H16:H18) -> 138484 | I19: =SUM(I16:I18) -> 178250 | J19: =SUM(J16:J18) -> 198226 | ... P19: =SUM(P16:P18) -> 1025632.2
B21: RESULTADO OPERACIONALES | C21: =SUM(C13-C19) -> 60172.15 | D21: =SUM(D13-D19) -> -7044 | E21: =SUM(E13-E19) -> 35419 | F21: =SUM(F13-F19) -> 2882.7 | G21: =SUM(G13-G19) -> 38980 | H21: =SUM(H13-H19) -> 91104 | I21: =SUM(I13-I19) -> 73452 | J21: =SUM(J13-J19) -> 443347 | ... P21: =SUM(P13-P19) -> 760729.85
B23: COSTOS ADMINISTRATIVOS
B24: SUELDOS ADMINISTRACION | C24: =SUM(C301) -> 0 | D24: =SUM(D301) -> 0 | E24: =SUM(E301) -> 0 | F24: =SUM(F301) -> 0 | G24: =SUM(G301) -> 0 | H24: =SUM(H301) -> 0 | I24: =SUM(I301) -> 0 | J24: =SUM(J301) -> 0 | ... N24: =SUM(N301) -> 0 | O24: =SUM(C24:N24) -> 0 | P24: =+SUM(C24:K24) -> 0
B25: GASTOS DE ADMINISTRACION | C25: =+C233 -> 10833 | D25: =+D233 -> 9388 | E25: =+E233 -> 13122 | F25: =+F233 -> 13095 | G25: =+G233 -> 14238 | H25: =+H233 -> 21058 | I25: =+I233 -> 13297 | J25: =+J233 -> 20882 | ... N25: =+N233 -> 21232 | O25: =SUM(C25:N25) -> 181782 | P25: =+SUM(C25:K25) -> 130958
B26: TOTAL COSTOS ADMINISTRATIVOS | C26: =SUM(C24:C25) -> 10833 | D26: =SUM(D24:D25) -> 9388 | E26: =SUM(E24:E25) -> 13122 | F26: =SUM(F24:F25) -> 13095 | G26: =SUM(G24:G25) -> 14238 | H26: =SUM(H24:H25) -> 21058 | I26: =SUM(I24:I25) -> 13297 | J26: =SUM(J24:J25) -> 20882 | ... P26: =SUM(P24:P25) -> 130958
B28: ACTIVO: EQUIPOS-ACTIVO REDTEC | C28: =+C239 -> 14954 | D28: =+D239 -> 2711 | E28: =+E239 -> 9675 | F28: =+F239 -> 17383 | G28: =+G239 -> 11056 | H28: =+H239 -> 8453 | I28: =+I239 -> 7808 | J28: =+J239 -> 6464 | ... N28: =+N239 -> 21627 | O28: =SUM(C28:N28) -> 152109 | P28: =+SUM(C28:K28) -> 93840
B30: TOTAL OTROS COSTOS NO OPERACIONALES | C30: =SUM(+C26+C28) -> 25787 | D30: =SUM(+D26+D28) -> 12099 | E30: =SUM(+E26+E28) -> 22797 | F30: =SUM(+F26+F28) -> 30478 | G30: =SUM(+G26+G28) -> 25294 | H30: =SUM(H26+H28) -> 29511 | I30: =SUM(I26+I28) -> 21105 | J30: =SUM(J26+J28) -> 27346 | K30: =SUM(K26+K28) -> 30381 | L30: =SUM(L26+L28) -> 39669 | M30: =SUM(M26+M28) -> 26565 | N30: =SUM(N26+N28) -> 42859 | O30: =SUM(O26+O28) -> 333891 | P30: =SUM(P26+P28) -> 224798
B32: RESULTADO NO OPERACIONAL | C32: =SUM(C21-C30) -> 34385.15 | D32: =SUM(D21-D30) -> -19143 | E32: =SUM(E21-E30) -> 12622 | F32: =SUM(F21-F30) -> -27595.3 | G32: =SUM(G21-G30) -> 13686 | H32: =SUM(H21-H30) -> 61593 | I32: =SUM(I21-I30) -> 52347 | J32: =SUM(J21-J30) -> 416001 | ... P32: =SUM(P21-P30) -> 535931.85
B34: OTROS INGRESOS NO OPERACIONALES
B35: INGRESO IVA DEBITO FACTURACION | C35: =+C95 -> 11907 | D35: =+D95 -> 16500 | E35: =+E95 -> 20068 | F35: =+F95 -> 28529 | G35: =+G95 -> 31304 | H35: =+H95 -> 36127 | I35: =+I95 -> 34183 | J35: =+J95 -> 126435 | ... N35: =+N95 -> 75885 | O35: =SUM(C35:N35) -> 544185 | P35: =+SUM(C35:K35) -> 321090
B36: INGRESO FACTURACION EERR | E36: =+E80 -> 51893 | O36: =SUM(C36:N36) -> 51893 | P36: =+SUM(C36:K36) -> 51893
B37: INGRESO CTA. CTE. EERR REDCO PERU | O37: =SUM(C37:N37) -> 0 | P37: =+SUM(C37:K37) -> 0
