Workbook
Name RutaCarpeta: #REF!

Sheet Resumen Forecast 25´
A1: Ítem | B1: 45658 | C1: 45689 | D1: 45717 | E1: 45748 | F1: 45778 | G1: 45809 | H1: 45839 | I1: 45870 | J1: 45901 | K1: 45931 | L1: 45962 | M1: 45992 | O1: Ítem | P1: Total | Q1: Promedio
A2: Propuestas | B2: 2212 | C2: 2571 | D2: 6130 | E2: 4378 | F2: 3026 | G2: =+G3/0.43 -> 1618.6047 | H2: =+H3/0.43 -> 1531.6279 | I2: =+I3/0.43 -> 2046.5116 | J2: =+J3/0.43 -> 1472.093 | K2: =+K3/0.43 -> 1006.9767 | L2: =+L3/0.43 -> 1393.0233 | M2: =+M3/0.43 -> 3037.2093 | O2: Propuestas | P2: =+SUM(B2:M2) -> 30423.047 | Q2: =+AVERAGE(B2:M2) -> 2535.2539
A3: Ventas | B3: 1056 | C3: 1246 | D3: 736 | E3: 1013 | F3: 968 | G3: 696 | H3: 658.6 | I3: 880 | J3: 633 | K3: 433 | L3: 599 | M3: 1306 | O3: Ventas | P3: =+SUM(B3:M3) -> 10224.6 | Q3: =+AVERAGE(B3:M3) -> 852.05 | V3: Factor EDP | W3: 1.2279086
A4: EDP | B4: =+O34 -> 669.095 | C4: =+P34 -> 891.9687 | D4: =+Q34 -> 693.81329 | E4: =+R34 -> 704.04973 | F4: =+S34 -> 730.257 | G4: =+T34 -> 1177.5466 | H4: =+U34 -> 742.58685 | I4: =+V34 -> 784.663 | ... M4: =+Z34 -> 611.272 | O4: EDP | P4: =+SUM(B4:M4) -> 9344.8999 | Q4: =+AVERAGE(B4:M4) -> 778.74166 | S4: 10596.552 | T4: =+S4-SUM(B4:H4) -> 4987.2348 | V4: Factor Factura | W4: 0.98376235
A5: Facturación | B5: =+O37 -> 822.535 | C5: =+P37 -> 313.029 | D5: =+Q37 -> 798.15916 | E5: =+R37 -> 702.12786 | F5: =+S37 -> 916.262 | G5: =+T37 -> 782.343 | H5: =+U37 -> 894.86126 | I5: =+V37 -> 1334.0146 | ... M5: =+Z37 -> 886.41968 | O5: Facturación | P5: =+SUM(B5:M5) -> 9796.9289 | Q5: =+AVERAGE(B5:M5) -> 816.41074 | S5: 10440.257 | T5: =+T4/5 -> 997.44697
A6: Ingresos | B6: =+O28 -> 717.16573 | C6: =+P28 -> 934.59483 | D6: =+Q28 -> 778.43046 | E6: =+R28 -> 613.92118 | F6: =+S28 -> 647.40508 | G6: =+T28 -> 807.41107 | H6: =+U28 -> 774.98975 | I6: =+V28 -> 1032.2317 | ... M6: =+Z28 -> 845.54106 | O6: Ingresos | P6: =+SUM(B6:M6) -> 9150.6163 | Q6: =+AVERAGE(B6:M6) -> 762.55136 | T6: 845 | U6: =+T5/T6 -> 1.1804106
A7: Gasto | B7: =+O31 -> 502.98161 | C7: =+P31 -> 509.774 | D7: =+Q31 -> 535.88132 | E7: =+R31 -> 549.83671 | F7: =+S31 -> 550.67196 | G7: =+T31 -> 638.75126 | H7: =+U31 -> 597.91154 | I7: =+V31 -> 664.68484 | ... M7: =+Z31 -> 959.54297 | O7: Gasto | P7: =+SUM(B7:M7) -> 7434.7245 | Q7: =+AVERAGE(B7:M7) -> 619.56037 | S7: =+SUM(B5:H5) -> 5229.3173 | T7: =+S5-S7 -> 5210.9399 | U7: =+T7/5 -> 1042.188
A8: Beneficio | B8: =+B6-B7 -> 214.18413 | C8: =+C6-C7 -> 424.82083 | D8: =+D6-D7 -> 242.54914 | E8: =+E6-E7 -> 64.084471 | F8: =+F6-F7 -> 96.733125 | G8: =+G6-G7 -> 168.65981 | H8: =+H6-H7 -> 177.07821 | I8: =+I6-I7 -> 367.5469 | ... M8: =+M6-M7 -> -114.00191 | O8: Beneficio | P8: =+SUM(B8:M8) -> 1715.8919 | Q8: =+AVERAGE(B8:M8) -> 142.99099 | T8: =+SUM(I5:M5) -> 4567.6116 | U8: 845
A9: Margen % | B9: =+B8/B6 -> 0.2986536 | C9: =+C8/C6 -> 0.45455081 | D9: =+D8/D6 -> 0.31158742 | E9: =+E8/E6 -> 0.1043855 | F9: =+F8/F6 -> 0.14941669 | G9: =+G8/G6 -> 0.20888964 | H9: =+H8/H6 -> 0.22849103 | I9: =+I8/I6 -> 0.35607014 | ... M9: =+M8/M6 -> -0.13482717 | O9: Margen % | P9: =+P8/P6 -> 0.18751653 | Q9: =+AVERAGE(B9:M9) -> 0.17046786 | T9: =+T7/T8 -> 1.1408457 | U9: =+U7/U8 -> 1.2333585
B10: =+SUM($B$8:B8) -> 214.18413 | C10: =+SUM($B$8:C8) -> 639.00496 | D10: =+SUM($B$8:D8) -> 881.5541 | E10: =+SUM($B$8:E8) -> 945.63857 | F10: =+SUM($B$8:F8) -> 1042.3717 | G10: =+SUM($B$8:G8) -> 1211.0315 | H10: =+SUM($B$8:H8) -> 1388.1097 | I10: =+SUM($B$8:I8) -> 1755.6566 | ... M10: =+SUM($B$8:M8) -> 1715.8919
S11: =+S5*'Resumen Budget 25´'!S4 -> 10596.552
V15: =+P6*Resumen!G36 -> 9169.226 | W15: =+V15-SUM(B5:K5) -> 994.48769 | Y15: =+P5*Resumen!G35 -> 9943.5928 | Z15: =+Y15-SUM(B4:K4) -> 2013.2078
W16: =+W15/2 -> 497.24384 | Z16: =+Z15/2 -> 1006.6039
W17: =+'Resumen Budget 25´'!K5 -> 845 | Z17: 845
W18: =+W16/W17 -> 0.58845425 | Z18: =+Z16/Z17 -> 1.1912472
N27: Ingreso | O27: 717165.73 | P27: 934594.83 | Q27: 778430.46 | R27: 613921.18 | S27: 647405.08 | T27: 807411.07 | U27: 774989.75 | V27: 1032231.7 | W27: 620646.05 | X27: 793777.46 | Y27: 584501.93 | Z27: 845541.06 | AA27: =+SUM(O27:Z27) -> 9150616.3
O28: =+O27/1000 -> 717.16573 | P28: =+P27/1000 -> 934.59483 | Q28: =+Q27/1000 -> 778.43046 | R28: =+R27/1000 -> 613.92118 | S28: =+S27/1000 -> 647.40508 | T28: =+T27/1000 -> 807.41107 | U28: =+U27/1000 -> 774.98975 | V28: =+V27/1000 -> 1032.2317 | ... Z28: =+Z27/1000 -> 845.54106
N30: Gasto | O30: 502981.61 | P30: 509774 | Q30: 535881.32 | R30: 549836.71 | S30: 550671.96 | T30: 638751.26 | U30: 597911.54 | V30: 664684.84 | W30: 642343.95 | X30: 659040.33 | Y30: 623303.99 | Z30: 959542.97 | AA30: =+SUM(O30:Z30) -> 7434724.5
O31: =+O30/1000 -> 502.98161 | P31: =+P30/1000 -> 509.774 | Q31: =+Q30/1000 -> 535.88132 | R31: =+R30/1000 -> 549.83671 | S31: =+S30/1000 -> 550.67196 | T31: =+T30/1000 -> 638.75126 | U31: =+U30/1000 -> 597.91154 | V31: =+V30/1000 -> 664.68484 | ... Z31: =+Z30/1000 -> 959.54297
A33: Item | B33: Acum | N33: EDP | O33: 669095 | P33: 891968.7 | Q33: 693813.29 | R33: 704049.73 | S33: 730257 | T33: 1177546.6 | U33: 742586.85 | V33: 784663 | W33: 676238.04 | X33: 860166.81 | Y33: 803242.9 | Z33: 611272 | AA33: =+SUM(O33:Z33) -> 9344899.9
A34: Propuestas | B34: =+SUM($B2:F2) -> 18317 | O34: =+O33/1000 -> 669.095 | P34: =+P33/1000 -> 891.9687 | Q34: =+Q33/1000 -> 693.81329 | R34: =+R33/1000 -> 704.04973 | S34: =+S33/1000 -> 730.257 | T34: =+T33/1000 -> 1177.5466 | U34: =+U33/1000 -> 742.58685 | V34: =+V33/1000 -> 784.663 | ... Z34: =+Z33/1000 -> 611.272
A35: Ventas | B35: =+SUM($B3:F3) -> 5019
A36: EDP | B36: =+SUM($B4:F4) -> 3689.1837 | N36: Facturación | O36: 822535 | P36: 313029 | Q36: 798159.16 | R36: 702127.86 | S36: 916262 | T36: 782343 | U36: 894861.26 | V36: 1334014.6 | W36: 726924.49 | X36: 884482 | Y36: 735770.82 | Z36: 886419.68 | AA36: =+SUM(O36:Z36) -> 9796928.9
A37: Facturación | B37: =+SUM($B5:F5) -> 3552.113 | O37: =+O36/1000 -> 822.535 | P37: =+P36/1000 -> 313.029 | Q37: =+Q36/1000 -> 798.15916 | R37: =+R36/1000 -> 702.12786 | S37: =+S36/1000 -> 916.262 | T37: =+T36/1000 -> 782.343 | U37: =+U36/1000 -> 894.86126 | V37: =+V36/1000 -> 1334.0146 | ... Z37: =+Z36/1000 -> 886.41968
A38: Ingresos | B38: =+SUM($B6:F6) -> 3691.5173
A39: Gasto | B39: =+SUM($B7:F7) -> 2649.1456
A40: Beneficio | B40: =+SUM($B8:F8) -> 1042.3717
A41: Margen % | B41: =+B40/B38 -> 0.28236945

Sheet Resumen Budget 25´
A1: Ítem | B1: 45658 | C1: 45689 | D1: 45717 | E1: 45748 | F1: 45778 | G1: 45809 | H1: 45839 | I1: 45870 | J1: 45901 | K1: 45931 | L1: 45962 | M1: 45992 | O1: Ítem | P1: Total | Q1: Promedio
A2: Propuestas | B2: =+B3/0.43 -> 2162.7907 | C2: =+C3/0.43 -> 2344.186 | D2: =+D3/0.43 -> 3697.6744 | E2: =+E3/0.43 -> 3269.7674 | F2: =+F3/0.43 -> 1703.1395 | G2: =+G3/0.43 -> 1703.1395 | H2: =+H3/0.43 -> 1703.1395 | I2: =+I3/0.43 -> 1703.1395 | ... M2: =+M3/0.43 -> 1247.907 | O2: Propuestas | P2: =+SUM(B2:M2) -> 25116.279 | Q2: =+AVERAGE(B2:M2) -> 2093.0233
A3: Ventas | B3: 930 | C3: 1008 | D3: 1590 | E3: 1406 | F3: 732.35 | G3: 732.35 | H3: 732.35 | I3: 732.35 | J3: 800 | K3: 800 | L3: 800 | M3: 536.6 | O3: Ventas | P3: =+SUM(B3:M3) -> 10800 | Q3: =+AVERAGE(B3:M3) -> 900
A4: EDP | B4: =+'[1]Resumen 2025'!C11 -> 753.937 | C4: =+'[1]Resumen 2025'!D11 -> 843.38067 | D4: =+'[1]Resumen 2025'!E11 -> 899.04433 | E4: =+'[1]Resumen 2025'!F11 -> 1040.236 | F4: =+'[1]Resumen 2025'!G11 -> 859.26633 | G4: =+'[1]Resumen 2025'!H11 -> 724.37967 | H4: =+'[1]Resumen 2025'!I11 -> 845 | I4: =+'[1]Resumen 2025'!J11 -> 845 | ... M4: =+'[1]Resumen 2025'!N11 -> 656.522 | O4: POM | P4: =+SUM(B4:M4) -> 10001.766 | Q4: =+AVERAGE(B4:M4) -> 833.4805 | S4: =+P4/P5 -> 1.0149704
A5: Facturación | B5: =+'[1]Resumen 2025'!C12 -> 509 | C5: =+'[1]Resumen 2025'!D12 -> 753.937 | D5: =+'[1]Resumen 2025'!E12 -> 843.38067 | E5: =+'[1]Resumen 2025'!F12 -> 899.04433 | F5: =+'[1]Resumen 2025'!G12 -> 1040.236 | G5: =+'[1]Resumen 2025'!H12 -> 859.26633 | H5: =+'[1]Resumen 2025'!I12 -> 724.37967 | I5: =+'[1]Resumen 2025'!J12 -> 845 | ... M5: =+'[1]Resumen 2025'!N12 -> 845 | O5: Facturación | P5: =+SUM(B5:M5) -> 9854.244 | Q5: =+AVERAGE(B5:M5) -> 821.187
A6: Ingresos | B6: =+'[1]Resumen 2025'!C13 -> 825 | C6: =+'[1]Resumen 2025'!D13 -> 509 | D6: =+'[1]Resumen 2025'!E13 -> 753.937 | E6: =+'[1]Resumen 2025'!F13 -> 843.38067 | F6: =+'[1]Resumen 2025'!G13 -> 899.04433 | G6: =+'[1]Resumen 2025'!H13 -> 1040.236 | H6: =+'[1]Resumen 2025'!I13 -> 859.26633 | I6: =+'[1]Resumen 2025'!J13 -> 724.37967 | ... M6: =+'[1]Resumen 2025'!N13 -> 845 | O6: Ingresos | P6: =+SUM(B6:M6) -> 9834.244 | Q6: =+AVERAGE(B6:M6) -> 819.52033
A7: Gasto | B7: =+'[1]Resumen 2025'!C15 -> 695.28316 | C7: =+'[1]Resumen 2025'!D15 -> 507.61468 | D7: =+'[1]Resumen 2025'!E15 -> 519.11468 | E7: =+'[1]Resumen 2025'!F15 -> 514.39511 | F7: =+'[1]Resumen 2025'!G15 -> 547.45874 | G7: =+'[1]Resumen 2025'!H15 -> 547.10729 | H7: =+'[1]Resumen 2025'!I15 -> 590.31705 | I7: =+'[1]Resumen 2025'!J15 -> 542.07076 | ... M7: =+'[1]Resumen 2025'!N15 -> 593.83879 | O7: Gasto | P7: =+SUM(B7:M7) -> 6709.0792 | Q7: =+AVERAGE(B7:M7) -> 559.08993
A8: Beneficio | B8: =+B6-B7 -> 129.71684 | C8: =+C6-C7 -> 1.3853225 | D8: =+D6-D7 -> 234.82232 | E8: =+E6-E7 -> 328.98555 | F8: =+F6-F7 -> 351.5856 | G8: =+G6-G7 -> 493.12871 | H8: =+H6-H7 -> 268.94928 | I8: =+I6-I7 -> 182.3089 | ... M8: =+M6-M7 -> 251.16121 | O8: Beneficio | P8: =+SUM(B8:M8) -> 3125.1648 | Q8: =+AVERAGE(B8:M8) -> 260.4304
A9: Margen % | B9: =+B8/B6 -> 0.15723254 | C9: =+C8/C6 -> 0.0027216553 | D9: =+D8/D6 -> 0.31146147 | E9: =+E8/E6 -> 0.39007955 | F9: =+F8/F6 -> 0.39106592 | G9: =+G8/G6 -> 0.47405465 | H9: =+H8/H6 -> 0.31299874 | I9: =+I8/I6 -> 0.2516759 | ... M9: =+M8/M6 -> 0.2972322 | O9: Margen % | P9: =+P8/P6 -> 0.31778394 | Q9: =+AVERAGE(B9:M9) -> 0.30280303
B10: =+SUM($B$8:B8) -> 129.71684 | C10: =+SUM($B$8:C8) -> 131.10217 | D10: =+SUM($B$8:D8) -> 365.92449 | E10: =+SUM($B$8:E8) -> 694.91004 | F10: =+SUM($B$8:F8) -> 1046.4956 | G10: =+SUM($B$8:G8) -> 1539.6244 | H10: =+SUM($B$8:H8) -> 1808.5736 | I10: =+SUM($B$8:I8) -> 1990.8825 | ... M10: =+SUM($B$8:M8) -> 3125.1648
A33: Propuestas | B33: =+SUM($B2:F2) -> 13177.558
A34: Ventas | B34: =+SUM($B3:F3) -> 5666.35
A35: EDP | B35: =+SUM($B4:F4) -> 4395.8643
A36: Facturación | B36: =+SUM($B5:F5) -> 4045.598
A37: Ingresos | B37: =+SUM($B6:F6) -> 3830.362
A38: Gasto | B38: =+SUM($B7:F7) -> 2783.8664
A39: Beneficio | B39: =+SUM($B8:F8) -> 1046.4956
A40: Margen % | B40: =+B39/B37 -> 0.27321064

Sheet Resumen
A1: RESUMEN GESTIÓN
A3: Item | B3: 45687 | C3: 45716 | D3: 45745 | E3: 45774 | F3: 45803 | G3: 45832 | H3: 45862 | I3: 45893 | J3: 45924 | K3: 45954 | L3: 45985 | M3: 46015 | N3: Total Acum | O3: Promedio | P3: Var.% mes
A4: Venta Budget | B4: =+'Resumen Budget 25´'!B3 -> 930 | C4: =+'Resumen Budget 25´'!C3 -> 1008 | D4: =+'Resumen Budget 25´'!D3 -> 1590 | E4: =+'Resumen Budget 25´'!E3 -> 1406 | F4: =+'Resumen Budget 25´'!F3 -> 732.35 | G4: =+'Resumen Budget 25´'!G3 -> 732.35 | H4: =+'Resumen Budget 25´'!H3 -> 732.35 | I4: =+'Resumen Budget 25´'!I3 -> 732.35 | ... M4: =+'Resumen Budget 25´'!M3 -> 536.6 | N4: =+SUM(B4:M4) -> 10800 | O4: =+AVERAGE(B4:M4) -> 900 | P4: =+K5-K4 -> -367
A5: Venta Real | B5: =+'Resumen Forecast 25´'!B3 -> 1056 | C5: =+'Resumen Forecast 25´'!C3 -> 1246 | D5: =+'Resumen Forecast 25´'!D3 -> 736 | E5: =+'Resumen Forecast 25´'!E3 -> 1013 | F5: =+'Resumen Forecast 25´'!F3 -> 968 | G5: =+'Resumen Forecast 25´'!G3 -> 696 | H5: =+'Resumen Forecast 25´'!H3 -> 658.6 | I5: =+'Resumen Forecast 25´'!I3 -> 880 | ... M5: =+'Resumen Forecast 25´'!M3 -> 1306 | N5: =+SUM(B5:M5) -> 10224.6 | O5: =+AVERAGE(B5:M5) -> 852.05 | P5: =+P4/K4 -> -0.45875
A6: EDP Budget | B6: 753.937 | C6: 843.38067 | D6: 899.04433 | E6: 1040.236 | F6: 859.26633 | G6: 724.37967 | H6: 845 | I6: =+'Resumen Budget 25´'!I4 -> 845 | J6: =+'Resumen Budget 25´'!J4 -> 845 | K6: =+'Resumen Budget 25´'!K4 -> 845 | L6: =+'Resumen Budget 25´'!L4 -> 845 | M6: =+'Resumen Budget 25´'!M4 -> 656.522 | N6: =+SUM(B6:M6) -> 10001.766 | O6: =+AVERAGE(B6:M6) -> 833.4805 | P6: =+K7-K6 -> 15.166813
A7: EDP Real | B7: =+'Resumen Forecast 25´'!B4 -> 669.095 | C7: =+'Resumen Forecast 25´'!C4 -> 891.9687 | D7: =+'Resumen Forecast 25´'!D4 -> 693.81329 | E7: =+'Resumen Forecast 25´'!E4 -> 704.04973 | F7: =+'Resumen Forecast 25´'!F4 -> 730.257 | G7: =+'Resumen Forecast 25´'!G4 -> 1177.5466 | H7: =+'Resumen Forecast 25´'!H4 -> 742.58685 | I7: =+'Resumen Forecast 25´'!I4 -> 784.663 | ... M7: =+'Resumen Forecast 25´'!M4 -> 611.272 | N7: =+SUM(B7:M7) -> 9344.8999 | O7: =+AVERAGE(B7:M7) -> 778.74166 | P7: =+P6/K6 -> 0.017948891
A8: Facturación Budget | B8: 509 | C8: 753.937 | D8: 843.38067 | E8: 899.04433 | F8: 1040.236 | G8: 859.26633 | H8: 724.37967 | I8: =+'Resumen Budget 25´'!I5 -> 845 | J8: =+'Resumen Budget 25´'!J5 -> 845 | K8: =+'Resumen Budget 25´'!K5 -> 845 | L8: =+'Resumen Budget 25´'!L5 -> 845 | M8: =+'Resumen Budget 25´'!M5 -> 845 | N8: =+SUM(B8:M8) -> 9854.244 | O8: =+AVERAGE(B8:M8) -> 821.187 | P8: =+K9-K8 -> 39.482
A9: Facturación Real | B9: =+'Resumen Forecast 25´'!B5 -> 822.535 | C9: =+'Resumen Forecast 25´'!C5 -> 313.029 | D9: =+'Resumen Forecast 25´'!D5 -> 798.15916 | E9: =+'Resumen Forecast 25´'!E5 -> 702.12786 | F9: =+'Resumen Forecast 25´'!F5 -> 916.262 | G9: =+'Resumen Forecast 25´'!G5 -> 782.343 | H9: =+'Resumen Forecast 25´'!H5 -> 894.86126 | I9: =+'Resumen Forecast 25´'!I5 -> 1334.0146 | ... M9: =+'Resumen Forecast 25´'!M5 -> 886.41968 | N9: =+SUM(B9:M9) -> 9796.9289 | O9: =+AVERAGE(B9:M9) -> 816.41074 | P9: =+P8/K8 -> 0.04672426
A10: Ingresos Budget | B10: 825 | C10: 509 | D10: 753.937 | E10: 843.38067 | F10: 899.04433 | G10: 1040.236 | H10: 859 | I10: =+'Resumen Budget 25´'!I6 -> 724.37967 | J10: =+'Resumen Budget 25´'!J6 -> 845 | K10: =+'Resumen Budget 25´'!K6 -> 845 | L10: =+'Resumen Budget 25´'!L6 -> 845 | M10: =+'Resumen Budget 25´'!M6 -> 845 | N10: =+SUM(B10:M10) -> 9833.9777 | O10: =+AVERAGE(B10:M10) -> 819.49814 | P10: =+K11-K10 -> -51.22254
A11: Ingresos Real | B11: =+'Resumen Forecast 25´'!B6 -> 717.16573 | C11: =+'Resumen Forecast 25´'!C6 -> 934.59483 | D11: =+'Resumen Forecast 25´'!D6 -> 778.43046 | E11: =+'Resumen Forecast 25´'!E6 -> 613.92118 | F11: =+'Resumen Forecast 25´'!F6 -> 647.40508 | G11: =+'Resumen Forecast 25´'!G6 -> 807.41107 | H11: =+'Resumen Forecast 25´'!H6 -> 774.98975 | I11: =+'Resumen Forecast 25´'!I6 -> 1032.2317 | ... M11: =+'Resumen Forecast 25´'!M6 -> 845.54106 | N11: =+SUM(B11:M11) -> 9150.6163 | O11: =+AVERAGE(B11:M11) -> 762.55136 | P11: =+P10/K10 -> -0.06061839
A12: Gastos Budget | B12: 695.28316 | C12: 507.61468 | D12: 519.11468 | E12: 514.39511 | F12: 547.45874 | G12: 547.10729 | H12: 590.31705 | I12: =+'Resumen Budget 25´'!I7 -> 542.07076 | J12: =+'Resumen Budget 25´'!J7 -> 536.52729 | K12: =+'Resumen Budget 25´'!K7 -> 550.87511 | L12: =+'Resumen Budget 25´'!L7 -> 564.47652 | M12: =+'Resumen Budget 25´'!M7 -> 593.83879 | N12: =+SUM(B12:M12) -> 6709.0792 | O12: =+AVERAGE(B12:M12) -> 559.08993 | P12: =+K13-K12 -> 108.16522
A13: Gastos Real | B13: =+'Resumen Forecast 25´'!B7 -> 502.98161 | C13: =+'Resumen Forecast 25´'!C7 -> 509.774 | D13: =+'Resumen Forecast 25´'!D7 -> 535.88132 | E13: =+'Resumen Forecast 25´'!E7 -> 549.83671 | F13: =+'Resumen Forecast 25´'!F7 -> 550.67196 | G13: =+'Resumen Forecast 25´'!G7 -> 638.75126 | H13: =+'Resumen Forecast 25´'!H7 -> 597.91154 | I13: =+'Resumen Forecast 25´'!I7 -> 664.68484 | ... M13: =+'Resumen Forecast 25´'!M7 -> 959.54297 | N13: =+SUM(B13:M13) -> 7434.7245 | O13: =+AVERAGE(B13:M13) -> 619.56037 | P13: =+P12/K12 -> 0.19635162
A14: Margen Operativo Budget | B14: =+B10-B12 -> 129.71684 | C14: =+C10-C12 -> 1.3853225 | D14: =+D10-D12 -> 234.82232 | E14: =+E10-E12 -> 328.98555 | F14: =+F10-F12 -> 351.5856 | G14: =+G10-G12 -> 493.12871 | H14: =+H10-H12 -> 268.68295 | I14: =+I10-I12 -> 182.3089 | ... M14: =+M10-M12 -> 251.16121 | N14: =+SUM(B14:M14) -> 3124.8985 | O14: =+AVERAGE(B14:M14) -> 260.40821 | P14: =+K15-K14 -> -159.38776
A15: Margen Operativo Real | B15: =+B11-B13 -> 214.18413 | C15: =+C11-C13 -> 424.82083 | D15: =+D11-D13 -> 242.54914 | E15: =+E11-E13 -> 64.084471 | F15: =+F11-F13 -> 96.733125 | G15: =+G11-G13 -> 168.65981 | H15: =+H11-H13 -> 177.07821 | I15: =+I11-I13 -> 367.5469 | ... M15: =+M11-M13 -> -114.00191 | N15: =+SUM(B15:M15) -> 1715.8919 | O15: =+AVERAGE(B15:M15) -> 142.99099 | P15: =+P14/K14 -> -0.54190504
A16: % Margen Op. Budget | B16: =+B14/B10 -> 0.15723254 | C16: =+C14/C10 -> 0.0027216553 | D16: =+D14/D10 -> 0.31146147 | E16: =+E14/E10 -> 0.39007955 | F16: =+F14/F10 -> 0.39106592 | G16: =+G14/G10 -> 0.47405465 | H16: =+H14/H10 -> 0.31278573 | I16: =+I14/I10 -> 0.2516759 | ... N16: =+N14/N10 -> 0.31776547 | O16: =+AVERAGE(B16:M16) -> 0.30278528
A17: % Margen Op. Real | B17: =+B15/B11 -> 0.2986536 | C17: =+C15/C11 -> 0.45455081 | D17: =+D15/D11 -> 0.31158742 | E17: =+E15/E11 -> 0.1043855 | F17: =+F15/F11 -> 0.14941669 | G17: =+G15/G11 -> 0.20888964 | H17: =+H15/H11 -> 0.22849103 | I17: =+I15/I11 -> 0.35607014 | ... N17: =+N15/N11 -> 0.18751653 | O17: =+AVERAGE(B17:M17) -> 0.17046786
A19: Caja Real REDCO | N19: =+F19 -> 0
A21: TABLA COMPARATIVA A DICIEMBRE 2025
B22: Budget | C22: Real Acum | D22: Dif. | E22: Var.% | G22: CumpMimiento A NOV | I22: CumpMimiento aM 2025
A23: Ventas | B23: =+N4 -> 10800 | C23: =+N5 -> 10224.6 | D23: =+C23-B23 -> -575.4 | E23: =+D23/B23 -> -0.053277778 | G23: =+C23/B23 -> 0.94672222 | I23: =+C23/B34 -> 0.94672222
A24: EDP | B24: =+N6 -> 10001.766 | C24: =+N7 -> 9344.8999 | D24: =+C24-B24 -> -656.86609 | E24: =+D24/B24 -> -0.065675011 | G24: =+C24/B24 -> 0.93432499 | I24: =+C24/B35 -> 0.93432499
A25: Facturación | B25: =+N8 -> 9854.244 | C25: =+N9 -> 9796.9289 | D25: =+C25-B25 -> -57.315149 | E25: =+D25/B25 -> -0.0058162908 | G25: =+C25/B25 -> 0.99418371 | I25: =+C25/B36 -> 0.99418371
A26: Ingresos | B26: =+N10 -> 9833.9777 | C26: =+N11 -> 9150.6163 | D26: =+C26-B26 -> -683.36132 | E26: =+D26/B26 -> -0.069489818 | G26: =+C26/B26 -> 0.93051018 | I26: =+C26/B37 -> 0.93048498
A27: Gastos | B27: =+N12 -> 6709.0792 | C27: =+N13 -> 7434.7245 | D27: =+C27-B27 -> 725.64531 | E27: =+D27/B27 -> 0.1081587 | G27: =+C27/B27 -> 1.1081587 | I27: =+C27/B38 -> 1.1081587
A28: Margen Operativo | B28: =+B26-B27 -> 3124.8985 | C28: =+C26-C27 -> 1715.8919 | D28: =+C28-B28 -> -1409.0066 | E28: =+D28/B28 -> -0.45089677 | G28: =+C28/B28 -> 0.54910323 | I28: =+C28/B39 -> 0.54905644
A29: % Margen OP. | B29: =+B28/B26 -> 0.31776547 | C29: =+C28/C26 -> 0.18751653 | D29: =+C29-B29 -> -0.13024893 | E29: =+D29/B29 -> -0.40989014
A32: TABMA COMPARATIVA AÑO 2025
B33: Budget 25 | C33: Forecast 25 | D33: Dif. | E33: Var.%
A34: Ventas | B34: 10800 | C34: =+'Resumen Forecast 25´'!P3 -> 10224.6 | D34: =+C34-B34 -> -575.4 | E34: =+D34/B34 -> -0.053277778
A35: EDP | B35: 10001.766 | C35: =+'Resumen Forecast 25´'!P4 -> 9344.8999 | D35: =+C35-B35 -> -656.86609 | E35: =+D35/B35 -> -0.065675011 | G35: =+B35/B36 -> 1.0149704
A36: Facturación | B36: 9854.244 | C36: =+'Resumen Forecast 25´'!P5 -> 9796.9289 | D36: =+C36-B36 -> -57.315149 | E36: =+D36/B36 -> -0.0058162908 | G36: =+B36/B37 -> 1.0020337 | O36: =+B36*O37 -> 9169.226 | P36: =+O36-N9 -> -627.70281 | Q36: =+P36/8 -> -78.462851
A37: Ingresos | B37: 9834.244 | C37: =+'Resumen Forecast 25´'!P6 -> 9150.6163 | D37: =+C37-B37 -> -683.62765 | E37: =+D37/B37 -> -0.069515019 | O37: =+C37/B37 -> 0.93048498
A38: Gastos | B38: 6709.0792 | C38: =+'Resumen Forecast 25´'!P7 -> 7434.7245 | D38: =+C38-B38 -> 725.64531 | E38: =+D38/B38 -> 0.1081587
A39: Margen Operativo | B39: =+B37-B38 -> 3125.1648 | C39: =+C37-C38 -> 1715.8919 | D39: =+C39-B39 -> -1409.273 | E39: =+D39/B39 -> -0.45094356
A40: % Margen OP. | B40: =+B39/B37 -> 0.31778394 | C40: =+C39/C37 -> 0.18751653 | D40: =+C40-B40 -> -0.13026741 | E40: =+D40/B40 -> -0.40992445
B42: =+B35/B36 -> 1.0149704 | C42: =+C36*B42 -> 9943.5928
A43: RESUMEN GESTIÓN
A45: Item | B45: 45687 | C45: 45716 | D45: 45746 | E45: 45777 | F45: 45808 | G45: 45838 | H45: 45869 | I45: 45900 | J45: 45930 | K45: 45961 | L45: 45991 | M45: 46022
A46: Venta Budget | B46: =+SUM($B$4:B4) -> 930 | C46: =+SUM($B$4:C4) -> 1938 | D46: =+SUM($B$4:D4) -> 3528 | E46: =+SUM($B$4:E4) -> 4934 | F46: =+SUM($B$4:F4) -> 5666.35 | G46: =+SUM($B$4:G4) -> 6398.7 | H46: =+SUM($B$4:H4) -> 7131.05 | I46: =+SUM($B$4:I4) -> 7863.4 | ... M46: =+SUM($B$4:M4) -> 10800
A47: Venta Real | B47: =+SUM($B$5:B5) -> 1056 | C47: =+SUM($B$5:C5) -> 2302 | D47: =+SUM($B$5:D5) -> 3038 | E47: =+SUM($B$5:E5) -> 4051 | F47: =+SUM($B$5:F5) -> 5019 | G47: =+SUM($B$5:G5) -> 5715 | H47: =+SUM($B$5:H5) -> 6373.6 | I47: =+SUM($B$5:I5) -> 7253.6 | ... M47: =+SUM($B$5:M5) -> 10224.6
A48: EDP Budget | B48: =+SUM($B$6:B6) -> 753.937 | C48: =+SUM($B$6:C6) -> 1597.3177 | D48: =+SUM($B$6:D6) -> 2496.362 | E48: =+SUM($B$6:E6) -> 3536.598 | F48: =+SUM($B$6:F6) -> 4395.8643 | G48: =+SUM($B$6:G6) -> 5120.244 | H48: =+SUM($B$6:H6) -> 5965.244 | I48: =+SUM($B$6:I6) -> 6810.244 | ... M48: =+SUM($B$6:M6) -> 10001.766
A49: EDP Real | B49: =+SUM($B$7:B7) -> 669.095 | C49: =+SUM($B$7:C7) -> 1561.0637 | D49: =+SUM($B$7:D7) -> 2254.877 | E49: =+SUM($B$7:E7) -> 2958.9267 | F49: =+SUM($B$7:F7) -> 3689.1837 | G49: =+SUM($B$7:G7) -> 4866.7303 | H49: =+SUM($B$7:H7) -> 5609.3172 | I49: =+SUM($B$7:I7) -> 6393.9802 | ... M49: =+SUM($B$7:M7) -> 9344.8999
A50: Facturación Budget | B50: =+SUM($B$8:B8) -> 509 | C50: =+SUM($B$8:C8) -> 1262.937 | D50: =+SUM($B$8:D8) -> 2106.3177 | E50: =+SUM($B$8:E8) -> 3005.362 | F50: =+SUM($B$8:F8) -> 4045.598 | G50: =+SUM($B$8:G8) -> 4904.8643 | H50: =+SUM($B$8:H8) -> 5629.244 | I50: =+SUM($B$8:I8) -> 6474.244 | ... M50: =+SUM($B$8:M8) -> 9854.244
A51: Facturación Real | B51: =+SUM($B$9:B9) -> 822.535 | C51: =+SUM($B$9:C9) -> 1135.564 | D51: =+SUM($B$9:D9) -> 1933.7232 | E51: =+SUM($B$9:E9) -> 2635.851 | F51: =+SUM($B$9:F9) -> 3552.113 | G51: =+SUM($B$9:G9) -> 4334.456 | H51: =+SUM($B$9:H9) -> 5229.3173 | I51: =+SUM($B$9:I9) -> 6563.3319 | ... M51: =+SUM($B$9:M9) -> 9796.9289
A52: Ingresos Budget | B52: =+SUM($B$10:B10) -> 825 | C52: =+SUM($B$10:C10) -> 1334 | D52: =+SUM($B$10:D10) -> 2087.937 | E52: =+SUM($B$10:E10) -> 2931.3177 | F52: =+SUM($B$10:F10) -> 3830.362 | G52: =+SUM($B$10:G10) -> 4870.598 | H52: =+SUM($B$10:H10) -> 5729.598 | I52: =+SUM($B$10:I10) -> 6453.9777 | ... M52: =+SUM($B$10:M10) -> 9833.9777
A53: Ingresos Real | B53: =+SUM($B$11:B11) -> 717.16573 | C53: =+SUM($B$11:C11) -> 1651.7606 | D53: =+SUM($B$11:D11) -> 2430.191 | E53: =+SUM($B$11:E11) -> 3044.1122 | F53: =+SUM($B$11:F11) -> 3691.5173 | G53: =+SUM($B$11:G11) -> 4498.9284 | H53: =+SUM($B$11:H11) -> 5273.9181 | I53: =+SUM($B$11:I11) -> 6306.1498 | ... M53: =+SUM($B$11:M11) -> 9150.6163
A54: Gastos Budget | B54: =+SUM($B$12:B12) -> 695.28316 | C54: =+SUM($B$12:C12) -> 1202.8978 | D54: =+SUM($B$12:D12) -> 1722.0125 | E54: =+SUM($B$12:E12) -> 2236.4076 | F54: =+SUM($B$12:F12) -> 2783.8664 | G54: =+SUM($B$12:G12) -> 3330.9736 | H54: =+SUM($B$12:H12) -> 3921.2907 | I54: =+SUM($B$12:I12) -> 4463.3615 | ... M54: =+SUM($B$12:M12) -> 6709.0792
A55: Gastos Real | B55: =+SUM($B$13:B13) -> 502.98161 | C55: =+SUM($B$13:C13) -> 1012.7556 | D55: =+SUM($B$13:D13) -> 1548.6369 | E55: =+SUM($B$13:E13) -> 2098.4736 | F55: =+SUM($B$13:F13) -> 2649.1456 | G55: =+SUM($B$13:G13) -> 3287.8969 | H55: =+SUM($B$13:H13) -> 3885.8084 | I55: =+SUM($B$13:I13) -> 4550.4932 | ... M55: =+SUM($B$13:M13) -> 7434.7245
A56: Margen Operativo Budget | B56: =+SUM($B$14:B14) -> 129.71684 | C56: =+SUM($B$14:C14) -> 131.10217 | D56: =+SUM($B$14:D14) -> 365.92449 | E56: =+SUM($B$14:E14) -> 694.91004 | F56: =+SUM($B$14:F14) -> 1046.4956 | G56: =+SUM($B$14:G14) -> 1539.6244 | H56: =+SUM($B$14:H14) -> 1808.3073 | I56: =+SUM($B$14:I14) -> 1990.6162 | ... M56: =+SUM($B$14:M14) -> 3124.8985
A57: Margen Operativo Real | B57: =+SUM($B$15:B15) -> 214.18413 | C57: =+SUM($B$15:C15) -> 639.00496 | D57: =+SUM($B$15:D15) -> 881.5541 | E57: =+SUM($B$15:E15) -> 945.63857 | F57: =+SUM($B$15:F15) -> 1042.3717 | G57: =+SUM($B$15:G15) -> 1211.0315 | H57: =+SUM($B$15:H15) -> 1388.1097 | I57: =+SUM($B$15:I15) -> 1755.6566 | ... M57: =+SUM($B$15:M15) -> 1715.8919
A58: % Margen Op. Budget | B58: =+B56/B52 -> 0.15723254 | C58: =+C56/C52 -> 0.098277486 | D58: =+D56/D52 -> 0.17525648 | E58: =+E56/E52 -> 0.23706405 | F58: =+F56/F52 -> 0.27321064 | G58: =+G56/G52 -> 0.31610582 | H58: =+H56/H52 -> 0.31560806 | I58: =+I56/I52 -> 0.30843246 | ... M58: =+M56/M52 -> 0.31776547
A59: % Margen Op. Real | B59: =+B57/B53 -> 0.2986536 | C59: =+C57/C53 -> 0.38686295 | D59: =+D57/D53 -> 0.36275095 | E59: =+E57/E53 -> 0.31064511 | F59: =+F57/F53 -> 0.28236945 | G59: =+G57/G53 -> 0.26918222 | H59: =+H57/H53 -> 0.26320274 | I59: =+I57/I53 -> 0.27840388 | ... M59: =+M57/M53 -> 0.18751653
A63: TABLA COMPARATIVA DICIEMBRE 2025
B64: Budget | C64: ReaM | D64: Dif. | E64: Var.%
A65: Ventas | B65: =+M4 -> 536.6 | C65: =+M5 -> 1306 | D65: =+C65-B65 -> 769.4 | E65: =+D65/B65 -> 1.4338427
A66: EDP | B66: =+M6 -> 656.522 | C66: =+M7 -> 611.272 | D66: =+C66-B66 -> -45.25 | E66: =+D66/B66 -> -0.068923814
A67: Facturación | B67: =+M8 -> 845 | C67: =+M9 -> 886.41968 | D67: =+C67-B67 -> 41.419677 | E67: =+D67/B67 -> 0.04901737
A68: Ingresos | B68: =+M10 -> 845 | C68: =+M11 -> 845.54106 | D68: =+C68-B68 -> 0.54106043 | E68: =+D68/B68 -> 0.0006403082
A69: Gastos | B69: =+M12 -> 593.83879 | C69: =+M13 -> 959.54297 | D69: =+C69-B69 -> 365.70418 | E69: =+D69/B69 -> 0.61583073
A70: Margen Operativo | B70: =+B68-B69 -> 251.16121 | C70: =+C68-C69 -> -114.00191 | D70: =+C70-B70 -> -365.16312 | E70: =+D70/B70 -> -1.4538994
A71: % Margen OP. | B71: =+B70/B68 -> 0.2972322 | C71: =+C70/C68 -> -0.13482717 | D71: =+C71-B71 -> -0.43205937 | E71: =+D71/B71 -> -1.4536089

Sheet Dashboard
L2: Modelo de Flujo REDCO
L3: 2025
L4: Dashboard de Decisiones y Resultados
DL8: Casos | DN8: Actual | DO8: Asignado | DP8: No Asignado
C9: Proyectos Contemplados | N9: Personal Proyectado | AA9: Personal Proyectado Chile | AO9: Personal Proyectado Perú | BC9: Personal Proyectado Brasil | BQ9: Personal Proyectado USA | CE9: Personal Proyectado Otros | CS9: Ferias | DL9: Considerar (Si=1; No=0) | DN9: 1 | DO9: 1 | DP9: 1
B10: Año venta | C10: Nombre Proyecto | D10: Nombre Compañía | E10: País Origen | F10: =+'Gantt Proyectos'!L96 -> Monto Contrato | G10: Nivel de Ingeniería | H10: Status General | I10: % Ingreso En base a Pbb Comercial | J10: Activo (1)/ Inactivo (0) | N10: Gerencia General (incluye RRHH) | O10: Gerencia Comercial | P10: Gerentes Ingeniera | Q10: Director de Proyecto | R10: Ingeniero Principal | S10: Ingeniero Senior | T10: Ingeniero de Proyecto | U10: Ingeniero Junior | V10: Ingeniero P&C | W10: Gerencia Contabilidad y Administracion | X10: Total | AA10: Gerencia General (incluye RRHH) | AB10: Gerencia Comercial | AC10: Gerencia Ingeniera | AD10: Gerentes Ingeniera | AE10: Director de Proyecto | AF10: Ingeniero Principal | AG10: Ingeniero Senior | AH10: Ingeniero de Proyecto | AI10: Ingeniero Junior | AJ10: Ingeniero P&C | AK10: Gerencia Contabilidad y Administracion | AL10: Total | AO10: Gerencia General (incluye RRHH) | AP10: Gerencia Comercial | AQ10: Gerencia Ingeniera | AR10: Gerentes Ingeniera | AS10: Director de Proyecto | AT10: Ingeniero Principal | AU10: Ingeniero Senior | AV10: Ingeniero de Proyecto | AW10: Ingeniero Junior | AX10: Ingeniero P&C | AY10: Gerencia Contabilidad y Administracion | AZ10: Total | BC10: Gerencia General (incluye RRHH) | BD10: Gerencia Comercial | BE10: Gerencia Ingeniera | BF10: Gerentes Ingeniera | BG10: Director de Proyecto | BH10: Ingeniero Principal | BI10: Ingeniero Senior | BJ10: Ingeniero de Proyecto | BK10: Ingeniero Junior | BL10: Ingeniero P&C | BM10: Gerencia Contabilidad y Administracion | BN10: Total | BQ10: Gerencia General (incluye RRHH) | BR10: Gerencia Comercial | BS10: Gerencia Ingeniera | BT10: Gerentes Ingeniera | BU10: Director de Proyecto | BV10: Ingeniero Principal | BW10: Ingeniero Senior | BX10: Ingeniero de Proyecto | BY10: Ingeniero Junior | BZ10: Ingeniero P&C | CA10: Gerencia Contabilidad y Administracion | CB10: Total | CE10: Gerencia General (incluye RRHH) | CF10: Gerencia Comercial | CG10: Gerencia Ingeniera | CH10: Gerentes Ingeniera | CI10: Director de Proyecto | CJ10: Ingeniero Principal | CK10: Ingeniero Senior | CL10: Ingeniero de Proyecto | CM10: Ingeniero Junior | CN10: Ingeniero P&C | CO10: Gerencia Contabilidad y Administracion | CP10: Total | CS10: Item | CT10: Feria | CU10: Monto | CV10: Mes | CW10: Aplica (1), No Aplica (2) | DI10: 1. Resultados Flujo de Caja (Proyección desde Mayo)
C11: =+'Gantt Proyectos'!D97 -> CMP: Estrategia Minera para MLC Brownfield | D11: =+'Gantt Proyectos'!E97 -> CMP | E11: =+'Gantt Proyectos'!F97 -> Chile | F11: =+'Gantt Proyectos'!L97 -> 36143 | G11: =+'Gantt Proyectos'!AC97 -> Estudio Conceptual / LOM | H11: =+'Gantt Proyectos'!AD97 -> Actual | I11: 1 | J11: 1 | L11: Actual --> | M11: 45748 | N11: =+'Listas y Parametros'!Q78 -> 6 | O11: =+'Listas y Parametros'!Q79 -> 4 | P11: =+'Listas y Parametros'!Q81 -> 2 | Q11: =+'Listas y Parametros'!Q82 -> 7 | R11: =+'Listas y Parametros'!Q83 -> 8 | S11: =+'Listas y Parametros'!Q84 -> 12 | T11: =+'Listas y Parametros'!Q85 -> 21 | U11: =+'Listas y Parametros'!Q86 -> 13 | V11: =+'Listas y Parametros'!Q87 -> 3 | W11: =+'Listas y Parametros'!Q88 -> 5 | X11: =+SUM(N11:W11) -> 81 | Z11: 45748 | AA11: {=TRANSPOSE('Listas y Parametros'!L78:L88)} -> 2 | AB11: 3 | AC11: 46 | AD11: 2 | AE11: 6 | AF11: 6 | AG11: 9 | AH11: 13 | AI11: 8 | AJ11: 2 | AK11: 4 | AL11: =+SUM(AA11:AB11,AD11:AK11) -> 55 | AN11: 45748 | AO11: {=+TRANSPOSE('Listas y Parametros'!M78:M88)} -> 1 | AP11: 1 | AQ11: 19 | AR11: 0 | AS11: 0 | AT11: 2 | AU11: 3 | AV11: 8 | AW11: 5 | AX11: 1 | AY11: 0 | AZ11: =+SUM(AO11:AP11,AR11:AY11) -> 21 | BB11: 45748 | BC11: {=+TRANSPOSE('Listas y Parametros'!N78:N88)} -> 2 | BD11: 0 | BE11: 1 | BF11: 0 | BG11: 1 | BH11: 0 | BI11: 0 | BJ11: 0 | BK11: 0 | BL11: 0 | BM11: 1 | BN11: =+SUM(BC11:BD11,BF11:BM11) -> 4 | BP11: 45748 | BQ11: {=+TRANSPOSE('Listas y Parametros'!O78:O88)} -> 1 | BR11: 0 | BS11: 0 | BT11: 0 | BU11: 0 | BV11: 0 | BW11: 0 | BX11: 0 | BY11: 0 | BZ11: 0 | CA11: 0 | CB11: =+SUM(BQ11:BR11,BT11:CA11) -> 1 | CD11: 45748 | CE11: {=+TRANSPOSE('Listas y Parametros'!P78:P88)} -> 0 | CF11: 0 | CG11: 0 | CH11: 0 | CI11: 0 | CJ11: 0 | CK11: 0 | CL11: 0 | CM11: 0 | CN11: 0 | CO11: 0 | CP11: =+SUM(CE11:CF11,CH11:CO11) -> 0 | CS11: Chile | CT11: =+'Listas y Parametros'!C219 -> The Electric Mine | CU11: =+'Listas y Parametros'!D219 -> 2000 | CV11: =+'Listas y Parametros'!E219 -> 45777 | CW11: 1 | DI11: Ingreso | DJ11: Total | DK11: Acumulado | DL11: 45687 | DM11: 45716 | DN11: 45746 | DO11: 45777 | DP11: 45807 | DQ11: 45838 | DR11: 45868 | DS11: 45899 | DT11: 45930 | DU11: 45960 | DV11: 45991 | DW11: 46021
C12: =+'Gantt Proyectos'!D98 -> Spence: Analisis proyecto SCUT | D12: =+'Gantt Proyectos'!E98 -> BHP | E12: =+'Gantt Proyectos'!F98 -> Chile | F12: =+'Gantt Proyectos'!L98 -> 47590 | G12: =+'Gantt Proyectos'!AC98 -> Confiabilidad Planes | H12: =+'Gantt Proyectos'!AD98 -> Actual | I12: 1 | J12: 1 | M12: 45778 | N12: =+AA12+AO12+BC12+BQ12+CE12 -> 6 | O12: =+AB12+AP12+BD12+BR12+CF12 -> 4 | P12: =+AD12+AR12+BF12+BT12+CH12 -> 2 | Q12: =+AE12+AS12+BG12+BU12+CI12 -> 7 | R12: =+AF12+AT12+BH12+BV12+CJ12 -> 8 | S12: =+AG12+AU12+BI12+BW12+CK12 -> 12 | T12: =+AH12+AV12+BJ12+BX12+CL12 -> 21 | U12: =+AI12+AW12+BK12+BY12+CM12 -> 13 | V12: =+AJ12+AX12+BL12+BZ12+CN12 -> 3 | W12: =+AK12+AY12+BM12+CA12+CO12 -> 5 | X12: =+SUM(N12:W12) -> 81 | Z12: 45778 | AA12: 2 | AB12: 3 | AC12: 46 | AD12: 2 | AE12: 6 | AF12: 6 | AG12: 9 | AH12: 13 | AI12: 8 | AJ12: 2 | AK12: 4 | AL12: =+SUM(AA12:AB12,AD12:AK12) -> 55 | AN12: 45778 | AO12: 1 | AP12: 1 | AQ12: 19 | AR12: 0 | AS12: 0 | AT12: 2 | AU12: 3 | AV12: 8 | AW12: 5 | AX12: 1 | AY12: 0 | AZ12: =+SUM(AO12:AP12,AR12:AY12) -> 21 | BB12: 45778 | BC12: 2 | BD12: 0 | BE12: 1 | BF12: 0 | BG12: 1 | BH12: 0 | BI12: 0 | BJ12: 0 | BK12: 0 | BL12: 0 | BM12: 1 | BN12: =+SUM(BC12:BD12,BF12:BM12) -> 4 | BP12: 45778 | BQ12: 1 | BR12: 0 | BS12: 0 | BT12: 0 | BU12: 0 | BV12: 0 | BW12: 0 | BX12: 0 | BY12: 0 | BZ12: 0 | CA12: 0 | CB12: =+SUM(BQ12:BR12,BT12:CA12) -> 1 | CD12: 45778 | CE12: 0 | CF12: 0 | CG12: 0 | CH12: 0 | CI12: 0 | CJ12: 0 | CK12: 0 | CL12: 0 | CM12: 0 | CN12: 0 | CO12: 0 | CP12: =+SUM(CE12:CF12,CH12:CO12) -> 0 | CT12: =+'Listas y Parametros'!C220 -> Gecamin-Mineplanning | CU12: =+'Listas y Parametros'!D220 -> 9000 | CV12: =+'Listas y Parametros'!E220 -> 45777 | CW12: 1 | DI12: Chile | DJ12: =+SUM(DL12:DW12) -> 3351934.6 | DK12: =+SUM(DL12:DS12) -> 2874423.8 | DL12: 362362.73 | DM12: 547310.62 | DN12: 394993.26 | DO12: 247866.97 | DP12: 312930.59 | DQ12: 277419.07 | DR12: 542984.75 | DS12: 188555.82 | DT12: =+'Flujo Caja'!M14 -> 168877.69 | DU12: =+'Flujo Caja'!N14 -> 168877.69 | DV12: =+'Flujo Caja'!O14 -> 69877.689 | DW12: =+'Flujo Caja'!P14 -> 69877.689
C13: =+'Gantt Proyectos'!D99 -> Resolution: MinePlan Review (Scoping) | D13: =+'Gantt Proyectos'!E99 -> BHP | E13: =+'Gantt Proyectos'!F99 -> Chile | F13: =+'Gantt Proyectos'!L99 -> 254012 | G13: =+'Gantt Proyectos'!AC99 -> Scoping | H13: =+'Gantt Proyectos'!AD99 -> Actual | I13: 1 | J13: 1 | M13: 45809 | N13: =+AA13+AO13+BC13+BQ13+CE13 -> 6 | O13: =+AB13+AP13+BD13+BR13+CF13 -> 4 | P13: =+AD13+AR13+BF13+BT13+CH13 -> 2 | Q13: =+AE13+AS13+BG13+BU13+CI13 -> 7 | R13: =+AF13+AT13+BH13+BV13+CJ13 -> 8 | S13: =+AG13+AU13+BI13+BW13+CK13 -> 12 | T13: =+AH13+AV13+BJ13+BX13+CL13 -> 21 | U13: =+AI13+AW13+BK13+BY13+CM13 -> 13 | V13: =+AJ13+AX13+BL13+BZ13+CN13 -> 3 | W13: =+AK13+AY13+BM13+CA13+CO13 -> 5 | X13: =+SUM(N13:W13) -> 81 | Z13: 45809 | AA13: 2 | AB13: 3 | AC13: 46 | AD13: 2 | AE13: 6 | AF13: 6 | AG13: 9 | AH13: 13 | AI13: 8 | AJ13: 2 | AK13: 4 | AL13: =+SUM(AA13:AB13,AD13:AK13) -> 55 | AN13: 45809 | AO13: 1 | AP13: 1 | AQ13: 19 | AR13: 0 | AS13: 0 | AT13: 2 | AU13: 3 | AV13: 8 | AW13: 5 | AX13: 1 | AY13: 0 | AZ13: =+SUM(AO13:AP13,AR13:AY13) -> 21 | BB13: 45809 | BC13: 2 | BD13: 0 | BE13: 1 | BF13: 0 | BG13: 1 | BH13: 0 | BI13: 0 | BJ13: 0 | BK13: 0 | BL13: 0 | BM13: 1 | BN13: =+SUM(BC13:BD13,BF13:BM13) -> 4 | BP13: 45809 | BQ13: 1 | BR13: 0 | BS13: 0 | BT13: 0 | BU13: 0 | BV13: 0 | BW13: 0 | BX13: 0 | BY13: 0 | BZ13: 0 | CA13: 0 | CB13: =+SUM(BQ13:BR13,BT13:CA13) -> 1 | CD13: 45809 | CE13: 0 | CF13: 0 | CG13: 0 | CH13: 0 | CI13: 0 | CJ13: 0 | CK13: 0 | CL13: 0 | CM13: 0 | CN13: 0 | CO13: 0 | CP13: =+SUM(CE13:CF13,CH13:CO13) -> 0 | CT13: =+'Listas y Parametros'!C221 -> Congreso - IIMCH | CU13: =+'Listas y Parametros'!D222 -> 13000 | CV13: =+'Listas y Parametros'!E221 -> 45960 | CW13: 1 | DI13: Perú | DJ13: =+SUM(DL13:DW13) -> 3049795.6 | DK13: =+SUM(DL13:DS13) -> 1667229 | DL13: 123848 | DM13: 62454 | DN13: 105377 | DO13: 110077 | DP13: 142610 | DQ13: 229588 | DR13: 251702 | DS13: 641573 | DT13: =+'Flujo Caja'!M17 -> 393534.51 | DU13: =+'Flujo Caja'!N17 -> 420617.85 | DV13: =+'Flujo Caja'!O17 -> 285332.13 | DW13: =+'Flujo Caja'!P17 -> 283082.13
C14: =+'Gantt Proyectos'!D100 -> Twin Metals: Analisis integrado con Northmet | D14: =+'Gantt Proyectos'!E100 -> Twin Metals | E14: =+'Gantt Proyectos'!F100 -> Chile | F14: =+'Gantt Proyectos'!L100 -> 132000 | G14: =+'Gantt Proyectos'!AC100 -> Estudio Conceptual / LOM | H14: =+'Gantt Proyectos'!AD100 -> Actual | I14: 1 | J14: 1 | M14: 45839 | N14: =+AA14+AO14+BC14+BQ14+CE14 -> 6 | O14: =+AB14+AP14+BD14+BR14+CF14 -> 4 | P14: =+AD14+AR14+BF14+BT14+CH14 -> 2 | Q14: =+AE14+AS14+BG14+BU14+CI14 -> 7 | R14: =+AF14+AT14+BH14+BV14+CJ14 -> 8 | S14: =+AG14+AU14+BI14+BW14+CK14 -> 12 | T14: =+AH14+AV14+BJ14+BX14+CL14 -> 21 | U14: =+AI14+AW14+BK14+BY14+CM14 -> 13 | V14: =+AJ14+AX14+BL14+BZ14+CN14 -> 3 | W14: =+AK14+AY14+BM14+CA14+CO14 -> 5 | X14: =+SUM(N14:W14) -> 81 | Z14: 45839 | AA14: 2 | AB14: 3 | AC14: 46 | AD14: 2 | AE14: 6 | AF14: 6 | AG14: 9 | AH14: 13 | AI14: 8 | AJ14: 2 | AK14: 4 | AL14: =+SUM(AA14:AB14,AD14:AK14) -> 55 | AN14: 45839 | AO14: 1 | AP14: 1 | AQ14: 19 | AR14: 0 | AS14: 0 | AT14: 2 | AU14: 3 | AV14: 8 | AW14: 5 | AX14: 1 | AY14: 0 | AZ14: =+SUM(AO14:AP14,AR14:AY14) -> 21 | BB14: 45839 | BC14: 2 | BD14: 0 | BE14: 1 | BF14: 0 | BG14: 1 | BH14: 0 | BI14: 0 | BJ14: 0 | BK14: 0 | BL14: 0 | BM14: 1 | BN14: =+SUM(BC14:BD14,BF14:BM14) -> 4 | BP14: 45839 | BQ14: 1 | BR14: 0 | BS14: 0 | BT14: 0 | BU14: 0 | BV14: 0 | BW14: 0 | BX14: 0 | BY14: 0 | BZ14: 0 | CA14: 0 | CB14: =+SUM(BQ14:BR14,BT14:CA14) -> 1 | CD14: 45839 | CE14: 0 | CF14: 0 | CG14: 0 | CH14: 0 | CI14: 0 | CJ14: 0 | CK14: 0 | CL14: 0 | CM14: 0 | CN14: 0 | CO14: 0 | CP14: =+SUM(CE14:CF14,CH14:CO14) -> 0 | CT14: =+'Listas y Parametros'!C222 -> Mines and money UK | CU14: =+'Listas y Parametros'!D223 -> 10000 | CV14: =+'Listas y Parametros'!E222 -> 45960 | CW14: 1 | DI14: Brasil | DJ14: =+SUM(DL14:DW14) -> 1790095.8 | DK14: =+SUM(DL14:DS14) -> 604565 | DL14: 80502 | DM14: 59683 | DN14: 96322 | DO14: 97147 | DP14: 37074 | DQ14: 66468 | DR14: 47717 | DS14: 119652 | DT14: =+'Flujo Caja'!M20 -> 358235.47 | DU14: =+'Flujo Caja'!N20 -> 316934.22 | DV14: =+'Flujo Caja'!O20 -> 301513.89 | DW14: =+'Flujo Caja'!P20 -> 208847.22
C15: =+'Gantt Proyectos'!D101 -> FEL3 CNN | D15: =+'Gantt Proyectos'!E101 -> CMP | E15: =+'Gantt Proyectos'!F101 -> Chile | F15: =+'Gantt Proyectos'!L101 -> 121038.49 | G15: =+'Gantt Proyectos'!AC101 -> PFS | H15: =+'Gantt Proyectos'!AD101 -> Actual | I15: 1 | J15: 1 | M15: 45870 | N15: =+AA15+AO15+BC15+BQ15+CE15 -> 6 | O15: =+AB15+AP15+BD15+BR15+CF15 -> 4 | P15: =+AD15+AR15+BF15+BT15+CH15 -> 2 | Q15: =+AE15+AS15+BG15+BU15+CI15 -> 7 | R15: =+AF15+AT15+BH15+BV15+CJ15 -> 8 | S15: =+AG15+AU15+BI15+BW15+CK15 -> 12 | T15: =+AH15+AV15+BJ15+BX15+CL15 -> 21 | U15: =+AI15+AW15+BK15+BY15+CM15 -> 13 | V15: =+AJ15+AX15+BL15+BZ15+CN15 -> 3 | W15: =+AK15+AY15+BM15+CA15+CO15 -> 5 | X15: =+SUM(N15:W15) -> 81 | Z15: 45870 | AA15: 2 | AB15: 3 | AC15: 46 | AD15: 2 | AE15: 6 | AF15: 6 | AG15: 9 | AH15: 13 | AI15: 8 | AJ15: 2 | AK15: 4 | AL15: =+SUM(AA15:AB15,AD15:AK15) -> 55 | AN15: 45870 | AO15: 1 | AP15: 1 | AQ15: 19 | AR15: 0 | AS15: 0 | AT15: 2 | AU15: 3 | AV15: 8 | AW15: 5 | AX15: 1 | AY15: 0 | AZ15: =+SUM(AO15:AP15,AR15:AY15) -> 21 | BB15: 45870 | BC15: 2 | BD15: 0 | BE15: 1 | BF15: 0 | BG15: 1 | BH15: 0 | BI15: 0 | BJ15: 0 | BK15: 0 | BL15: 0 | BM15: 1 | BN15: =+SUM(BC15:BD15,BF15:BM15) -> 4 | BP15: 45870 | BQ15: 1 | BR15: 0 | BS15: 0 | BT15: 0 | BU15: 0 | BV15: 0 | BW15: 0 | BX15: 0 | BY15: 0 | BZ15: 0 | CA15: 0 | CB15: =+SUM(BQ15:BR15,BT15:CA15) -> 1 | CD15: 45870 | CE15: 0 | CF15: 0 | CG15: 0 | CH15: 0 | CI15: 0 | CJ15: 0 | CK15: 0 | CL15: 0 | CM15: 0 | CN15: 0 | CO15: 0 | CP15: =+SUM(CE15:CF15,CH15:CO15) -> 0 | CT15: =+'Listas y Parametros'!C223 -> Argentina Mining | CU15: =+'Listas y Parametros'!D224 -> 15000 | CV15: =+'Listas y Parametros'!E223 -> 45868 | CW15: 1 | DI15: USA | DJ15: =+SUM(DL15:DW15) -> 998673.07 | DK15: =+SUM(DL15:DS15) -> 981530.21 | DL15: 150453 | DM15: 243465.21 | DN15: 141526 | DO15: 169200 | DP15: 195090 | DQ15: 61796 | DR15: 0 | DS15: 20000 | DT15: =+'Flujo Caja'!M23 -> 4285.7143 | DU15: =+'Flujo Caja'!N23 -> 4285.7143 | DV15: =+'Flujo Caja'!O23 -> 4285.7143 | DW15: =+'Flujo Caja'!P23 -> 4285.7143
C16: =+'Gantt Proyectos'!D102 -> Estudio de Factibilidad Mina Romeral UG - Acceso Mina SLS | D16: =+'Gantt Proyectos'!E102 -> CMP | E16: =+'Gantt Proyectos'!F102 -> Chile | F16: =+'Gantt Proyectos'!L102 -> 900007.88 | G16: =+'Gantt Proyectos'!AC102 -> FS e Ing. Basica | H16: =+'Gantt Proyectos'!AD102 -> Actual | I16: 1 | J16: 1 | M16: 45901 | N16: =+AA16+AO16+BC16+BQ16+CE16 -> 6 | O16: =+AB16+AP16+BD16+BR16+CF16 -> 4 | P16: =+AD16+AR16+BF16+BT16+CH16 -> 2 | Q16: =+AE16+AS16+BG16+BU16+CI16 -> 7 | R16: =+AF16+AT16+BH16+BV16+CJ16 -> 8 | S16: =+AG16+AU16+BI16+BW16+CK16 -> 12 | T16: =+AH16+AV16+BJ16+BX16+CL16 -> 21 | U16: =+AI16+AW16+BK16+BY16+CM16 -> 13 | V16: =+AJ16+AX16+BL16+BZ16+CN16 -> 3 | W16: =+AK16+AY16+BM16+CA16+CO16 -> 5 | X16: =+SUM(N16:W16) -> 81 | Z16: 45901 | AA16: 2 | AB16: 3 | AC16: 46 | AD16: 2 | AE16: 6 | AF16: 6 | AG16: 9 | AH16: 13 | AI16: 8 | AJ16: 2 | AK16: 4 | AL16: =+SUM(AA16:AB16,AD16:AK16) -> 55 | AN16: 45901 | AO16: 1 | AP16: 1 | AQ16: 19 | AR16: 0 | AS16: 0 | AT16: 2 | AU16: 3 | AV16: 8 | AW16: 5 | AX16: 1 | AY16: 0 | AZ16: =+SUM(AO16:AP16,AR16:AY16) -> 21 | BB16: 45901 | BC16: 2 | BD16: 0 | BE16: 1 | BF16: 0 | BG16: 1 | BH16: 0 | BI16: 0 | BJ16: 0 | BK16: 0 | BL16: 0 | BM16: 1 | BN16: =+SUM(BC16:BD16,BF16:BM16) -> 4 | BP16: 45901 | BQ16: 1 | BR16: 0 | BS16: 0 | BT16: 0 | BU16: 0 | BV16: 0 | BW16: 0 | BX16: 0 | BY16: 0 | BZ16: 0 | CA16: 0 | CB16: =+SUM(BQ16:BR16,BT16:CA16) -> 1 | CD16: 45901 | CE16: 0 | CF16: 0 | CG16: 0 | CH16: 0 | CI16: 0 | CJ16: 0 | CK16: 0 | CL16: 0 | CM16: 0 | CN16: 0 | CO16: 0 | CP16: =+SUM(CE16:CF16,CH16:CO16) -> 0 | CS16: Perú | CT16: =+'Listas y Parametros'!C224 -> PERUMIN 36 | CU16: =+'Listas y Parametros'!D224 -> 15000 | CV16: =+'Listas y Parametros'!E224 -> 45777 | CW16: 1 | DI16: Otros | DJ16: =+SUM(DL16:DW16) -> 338205 | DK16: =+SUM(DL16:DS16) -> 338205 | DL16: 0 | DM16: 21682 | DN16: 45478 | DO16: 0 | DP16: 0 | DQ16: 172045 | DR16: 0 | DS16: 99000 | DT16: =+'Flujo Caja'!M26 -> 0 | DU16: =+'Flujo Caja'!N26 -> 0 | DV16: =+'Flujo Caja'!O26 -> 0 | DW16: =+'Flujo Caja'!P26 -> 0
C17: =+'Gantt Proyectos'!D103 -> Cobre Panamá: Evaluación estratégica del activo | D17: =+'Gantt Proyectos'!E103 -> Debevoise&Plimpton | E17: =+'Gantt Proyectos'!F103 -> Chile | F17: =+'Gantt Proyectos'!L103 -> 272200.6 | G17: =+'Gantt Proyectos'!AC103 -> Estudio Conceptual / LOM | H17: =+'Gantt Proyectos'!AD103 -> Actual | I17: 1 | J17: 1 | M17: 45931 | N17: =+AA17+AO17+BC17+BQ17+CE17 -> 6 | O17: =+AB17+AP17+BD17+BR17+CF17 -> 4 | P17: =+AD17+AR17+BF17+BT17+CH17 -> 2 | Q17: =+AE17+AS17+BG17+BU17+CI17 -> 7 | R17: =+AF17+AT17+BH17+BV17+CJ17 -> 8 | S17: =+AG17+AU17+BI17+BW17+CK17 -> 12 | T17: =+AH17+AV17+BJ17+BX17+CL17 -> 21 | U17: =+AI17+AW17+BK17+BY17+CM17 -> 13 | V17: =+AJ17+AX17+BL17+BZ17+CN17 -> 3 | W17: =+AK17+AY17+BM17+CA17+CO17 -> 5 | X17: =+SUM(N17:W17) -> 81 | Z17: 45931 | AA17: 2 | AB17: 3 | AC17: 46 | AD17: 2 | AE17: 6 | AF17: 6 | AG17: 9 | AH17: 13 | AI17: 8 | AJ17: 2 | AK17: 4 | AL17: =+SUM(AA17:AB17,AD17:AK17) -> 55 | AN17: 45931 | AO17: 1 | AP17: 1 | AQ17: 19 | AR17: 0 | AS17: 0 | AT17: 2 | AU17: 3 | AV17: 8 | AW17: 5 | AX17: 1 | AY17: 0 | AZ17: =+SUM(AO17:AP17,AR17:AY17) -> 21 | BB17: 45931 | BC17: 2 | BD17: 0 | BE17: 1 | BF17: 0 | BG17: 1 | BH17: 0 | BI17: 0 | BJ17: 0 | BK17: 0 | BL17: 0 | BM17: 1 | BN17: =+SUM(BC17:BD17,BF17:BM17) -> 4 | BP17: 45931 | BQ17: 1 | BR17: 0 | BS17: 0 | BT17: 0 | BU17: 0 | BV17: 0 | BW17: 0 | BX17: 0 | BY17: 0 | BZ17: 0 | CA17: 0 | CB17: =+SUM(BQ17:BR17,BT17:CA17) -> 1 | CD17: 45931 | CE17: 0 | CF17: 0 | CG17: 0 | CH17: 0 | CI17: 0 | CJ17: 0 | CK17: 0 | CL17: 0 | CM17: 0 | CN17: 0 | CO17: 0 | CP17: =+SUM(CE17:CF17,CH17:CO17) -> 0 | CT17: =+'Listas y Parametros'!C225 -> 0 | CU17: =+'Listas y Parametros'!D225 -> 0 | CV17: =+'Listas y Parametros'!E225 -> 0 | CW17: 1 | DI17: Total | DJ17: =+SUM(DL17:DW17) -> 9528704.1 | DK17: =+SUM(DK12:DK16) -> 6465953 | DL17: =+SUM(DL12:DL16) -> 717165.73 | DM17: =+SUM(DM12:DM16) -> 934594.83 | DN17: =+SUM(DN12:DN16) -> 783696.26 | DO17: =+SUM(DO12:DO16) -> 624290.97 | DP17: =+SUM(DP12:DP16) -> 687704.59 | DQ17: =+SUM(DQ12:DQ16) -> 807316.07 | DR17: =+SUM(DR12:DR16) -> 842403.75 | ... DW17: =+SUM(DW12:DW16) -> 566092.76
C18: =+'Gantt Proyectos'!D104 -> Ferrobamba Scoping Study: Escenarios de sensibilidad | D18: =+'Gantt Proyectos'!E104 -> Las Bambas | E18: =+'Gantt Proyectos'!F104 -> Perú | F18: =+'Gantt Proyectos'!L104 -> 87520 | G18: =+'Gantt Proyectos'!AC104 -> Estudio Conceptual / LOM | H18: =+'Gantt Proyectos'!AD104 -> Actual | I18: 1 | J18: 1 | M18: 45962 | N18: =+AA18+AO18+BC18+BQ18+CE18 -> 6 | O18: =+AB18+AP18+BD18+BR18+CF18 -> 4 | P18: =+AD18+AR18+BF18+BT18+CH18 -> 2 | Q18: =+AE18+AS18+BG18+BU18+CI18 -> 7 | R18: =+AF18+AT18+BH18+BV18+CJ18 -> 8 | S18: =+AG18+AU18+BI18+BW18+CK18 -> 12 | T18: =+AH18+AV18+BJ18+BX18+CL18 -> 21 | U18: =+AI18+AW18+BK18+BY18+CM18 -> 13 | V18: =+AJ18+AX18+BL18+BZ18+CN18 -> 3 | W18: =+AK18+AY18+BM18+CA18+CO18 -> 5 | X18: =+SUM(N18:W18) -> 81 | Z18: 45962 | AA18: 2 | AB18: 3 | AC18: 46 | AD18: 2 | AE18: 6 | AF18: 6 | AG18: 9 | AH18: 13 | AI18: 8 | AJ18: 2 | AK18: 4 | AL18: =+SUM(AA18:AB18,AD18:AK18) -> 55 | AN18: 45962 | AO18: 1 | AP18: 1 | AQ18: 19 | AR18: 0 | AS18: 0 | AT18: 2 | AU18: 3 | AV18: 8 | AW18: 5 | AX18: 1 | AY18: 0 | AZ18: =+SUM(AO18:AP18,AR18:AY18) -> 21 | BB18: 45962 | BC18: 2 | BD18: 0 | BE18: 1 | BF18: 0 | BG18: 1 | BH18: 0 | BI18: 0 | BJ18: 0 | BK18: 0 | BL18: 0 | BM18: 1 | BN18: =+SUM(BC18:BD18,BF18:BM18) -> 4 | BP18: 45962 | BQ18: 1 | BR18: 0 | BS18: 0 | BT18: 0 | BU18: 0 | BV18: 0 | BW18: 0 | BX18: 0 | BY18: 0 | BZ18: 0 | CA18: 0 | CB18: =+SUM(BQ18:BR18,BT18:CA18) -> 1 | CD18: 45962 | CE18: 0 | CF18: 0 | CG18: 0 | CH18: 0 | CI18: 0 | CJ18: 0 | CK18: 0 | CL18: 0 | CM18: 0 | CN18: 0 | CO18: 0 | CP18: =+SUM(CE18:CF18,CH18:CO18) -> 0 | CT18: =+'Listas y Parametros'!C226 -> 0 | CU18: =+'Listas y Parametros'!D226 -> 0 | CV18: =+'Listas y Parametros'!E226 -> 0 | CW18: 1
C19: =+'Gantt Proyectos'!D105 -> Pre-PFS Twin Metals Birch Lake - Maturi | D19: =+'Gantt Proyectos'!E105 -> Twin Metals | E19: =+'Gantt Proyectos'!F105 -> USA | F19: =+'Gantt Proyectos'!L105 -> 481541 | G19: =+'Gantt Proyectos'!AC105 -> PFS | H19: =+'Gantt Proyectos'!AD105 -> Actual | I19: 1 | J19: 1 | M19: 45992 | N19: =+AA19+AO19+BC19+BQ19+CE19 -> 6 | O19: =+AB19+AP19+BD19+BR19+CF19 -> 4 | P19: =+AD19+AR19+BF19+BT19+CH19 -> 2 | Q19: =+AE19+AS19+BG19+BU19+CI19 -> 7 | R19: =+AF19+AT19+BH19+BV19+CJ19 -> 8 | S19: =+AG19+AU19+BI19+BW19+CK19 -> 12 | T19: =+AH19+AV19+BJ19+BX19+CL19 -> 21 | U19: =+AI19+AW19+BK19+BY19+CM19 -> 13 | V19: =+AJ19+AX19+BL19+BZ19+CN19 -> 3 | W19: =+AK19+AY19+BM19+CA19+CO19 -> 5 | X19: =+SUM(N19:W19) -> 81 | Z19: 45992 | AA19: 2 | AB19: 3 | AC19: 46 | AD19: 2 | AE19: 6 | AF19: 6 | AG19: 9 | AH19: 13 | AI19: 8 | AJ19: 2 | AK19: 4 | AL19: =+SUM(AA19:AB19,AD19:AK19) -> 55 | AN19: 45992 | AO19: 1 | AP19: 1 | AQ19: 19 | AR19: 0 | AS19: 0 | AT19: 2 | AU19: 3 | AV19: 8 | AW19: 5 | AX19: 1 | AY19: 0 | AZ19: =+SUM(AO19:AP19,AR19:AY19) -> 21 | BB19: 45992 | BC19: 2 | BD19: 0 | BE19: 1 | BF19: 0 | BG19: 1 | BH19: 0 | BI19: 0 | BJ19: 0 | BK19: 0 | BL19: 0 | BM19: 1 | BN19: =+SUM(BC19:BD19,BF19:BM19) -> 4 | BP19: 45992 | BQ19: 1 | BR19: 0 | BS19: 0 | BT19: 0 | BU19: 0 | BV19: 0 | BW19: 0 | BX19: 0 | BY19: 0 | BZ19: 0 | CA19: 0 | CB19: =+SUM(BQ19:BR19,BT19:CA19) -> 1 | CD19: 45992 | CE19: 0 | CF19: 0 | CG19: 0 | CH19: 0 | CI19: 0 | CJ19: 0 | CK19: 0 | CL19: 0 | CM19: 0 | CN19: 0 | CO19: 0 | CP19: =+SUM(CE19:CF19,CH19:CO19) -> 0 | CT19: =+'Listas y Parametros'!C227 -> 0 | CU19: =+'Listas y Parametros'!D227 -> 0 | CV19: =+'Listas y Parametros'!E227 -> 0 | CW19: 1 | DI19: Costo | DJ19: Total | DK19: Acumulado | DL19: 45687 | DM19: 45716 | DN19: 45746 | DO19: 45777 | DP19: 45807 | DQ19: 45838 | DR19: 45868 | DS19: 45899 | DT19: 45930 | DU19: 45960 | DV19: 45991 | DW19: 46021
C20: =+'Gantt Proyectos'!D106 -> Análisis Conceptual - Aura UG | D20: =+'Gantt Proyectos'!E106 -> Aura Minerals | E20: =+'Gantt Proyectos'!F106 -> Brasil | F20: =+'Gantt Proyectos'!L106 -> 310000 | G20: =+'Gantt Proyectos'!AC106 -> Scoping | H20: =+'Gantt Proyectos'!AD106 -> Actual | I20: 1 | J20: 1 | CS20: Brasil | CT20: =+'Listas y Parametros'!C228 -> Exposibram 2025 | CU20: =+'Listas y Parametros'!D228 -> 20000 | CV20: =+'Listas y Parametros'!E228 -> 45868 | CW20: 1 | DI20: Chile | DJ20: =+SUM(DL20:DW20) -> 4602714.4 | DK20: =+SUM(DL20:DS20) -> 3161800.2 | DL20: 397276.65 | DM20: 422126.64 | DN20: 439899.18 | DO20: 341507.35 | DP20: 340134.8 | DQ20: 399879.47 | DR20: 395727.19 | DS20: 425248.91 | DT20: =+'Flujo Caja'!M15 -> 378739.92 | DU20: =+'Flujo Caja'!N15 -> 359012.64 | DV20: =+'Flujo Caja'!O15 -> 345012.64 | DW20: =+'Flujo Caja'!P15 -> 358149.01
C21: =+'Gantt Proyectos'!D107 -> Los Calatos - Extensión (v3) | D21: =+'Gantt Proyectos'!E107 -> CD Capital | E21: =+'Gantt Proyectos'!F107 -> Perú | F21: =+'Gantt Proyectos'!L107 -> 295769 | G21: =+'Gantt Proyectos'!AC107 -> PFS | H21: =+'Gantt Proyectos'!AD107 -> Actual | I21: 1 | J21: 1 | CT21: =+'Listas y Parametros'!C229 -> Congresso de Mineração Subterrânea | CU21: =+'Listas y Parametros'!D229 -> 5000 | CV21: =+'Listas y Parametros'!E229 -> 45868 | CW21: 1 | DI21: Perú | DJ21: =+SUM(DL21:DW21) -> 1293266.4 | DK21: =+SUM(DL21:DS21) -> 1085106.1 | DL21: 89462.85 | DM21: 81597 | DN21: 92755 | DO21: 137672.3 | DP21: 128924 | DQ21: 153584 | DR21: 189124 | DS21: 211987 | DT21: =+'Flujo Caja'!M18 -> 52040.069 | DU21: =+'Flujo Caja'!N18 -> 52040.069 | DV21: =+'Flujo Caja'!O18 -> 52040.069 | DW21: =+'Flujo Caja'!P18 -> 52040.069
C22: =+'Gantt Proyectos'!D108 -> Analisis Innovación Tecnologica Distrito Centinela | D22: =+'Gantt Proyectos'!E108 -> AMSA | E22: =+'Gantt Proyectos'!F108 -> Chile | F22: =+'Gantt Proyectos'!L108 -> 134445.67 | G22: =+'Gantt Proyectos'!AC108 -> Scoping | H22: =+'Gantt Proyectos'!AD108 -> Actual | I22: 1 | J22: 1 | CT22: =+'Listas y Parametros'!C230 -> 0 | CU22: =+'Listas y Parametros'!D230 -> 0 | CV22: =+'Listas y Parametros'!E230 -> 0 | CW22: 1 | DI22: Brasil | DJ22: =+SUM(DL22:DW22) -> 566395.52 | DK22: =+SUM(DL22:DS22) -> 289373.4 | DL22: 21023 | DM22: 27812 | DN22: 26425 | DO22: 52004.4 | DP22: 33329 | DQ22: 76286 | DR22: 31019 | DS22: 21475 | DT22: =+'Flujo Caja'!M21 -> 85164.621 | DU22: =+'Flujo Caja'!N21 -> 71437.348 | DV22: =+'Flujo Caja'!O21 -> 64573.712 | DW22: =+'Flujo Caja'!P21 -> 55846.439
C23: =+'Gantt Proyectos'!D109 -> Cerro Colorado: Diseño Cierre de Botaderos | D23: =+'Gantt Proyectos'!E109 -> BHP | E23: =+'Gantt Proyectos'!F109 -> Chile | F23: =+'Gantt Proyectos'!L109 -> 904853 | G23: =+'Gantt Proyectos'!AC109 -> FS e Ing. Basica | H23: =+'Gantt Proyectos'!AD109 -> Actual | I23: 1 | J23: 1 | CT23: =+'Listas y Parametros'!C231 -> 0 | CU23: =+'Listas y Parametros'!D231 -> 0 | CV23: =+'Listas y Parametros'!E231 -> 0 | CW23: 1 | DI23: USA | DJ23: =+SUM(DL23:DW23) -> 300763.42 | DK23: =+SUM(DL23:DS23) -> 133542 | DL23: 15 | DM23: 2025 | DN23: 58728 | DO23: 9898 | DP23: 47666 | DQ23: 4178 | DR23: 10017 | DS23: 1015 | DT23: =+'Flujo Caja'!M24 -> 40555.356 | DU23: =+'Flujo Caja'!N24 -> 40555.356 | DV23: =+'Flujo Caja'!O24 -> 40555.356 | DW23: =+'Flujo Caja'!P24 -> 45555.356
C24: =+'Gantt Proyectos'!D110 -> Analisis de Productividad Los Bronces | D24: =+'Gantt Proyectos'!E110 -> AngloAmerican | E24: =+'Gantt Proyectos'!F110 -> Chile | F24: =+'Gantt Proyectos'!L110 -> 62417 | G24: =+'Gantt Proyectos'!AC110 -> Confiabilidad Planes | H24: =+'Gantt Proyectos'!AD110 -> Actual | I24: 1 | J24: 1 | CS24: USA | CT24: =+'Listas y Parametros'!C232 -> MINExpo | CU24: =+'Listas y Parametros'!D232 -> 19500 | CV24: =+'Listas y Parametros'!E232 -> 45838 | CW24: 1 | DI24: Otros | DJ24: =+SUM(DL24:DW24) -> 61478.4 | DK24: =+SUM(DL24:DS24) -> 61478.4 | DL24: 14044 | DM24: 0 | DN24: 0 | DO24: 14380 | DP24: 16000 | DQ24: 5684.8 | DR24: 5684.8 | DS24: 5684.8 | DT24: =+'Flujo Caja'!M27 -> 0 | DU24: =+'Flujo Caja'!N27 -> 0 | DV24: =+'Flujo Caja'!O27 -> 0 | DW24: =+'Flujo Caja'!P27 -> 0
C25: =+'Gantt Proyectos'!D111 -> Ingenieria implementacion HDD Los Bronces | D25: =+'Gantt Proyectos'!E111 -> AngloAmerican | E25: =+'Gantt Proyectos'!F111 -> Chile | F25: =+'Gantt Proyectos'!L111 -> 183430 | G25: =+'Gantt Proyectos'!AC111 -> Estudio Conceptual / LOM | H25: =+'Gantt Proyectos'!AD111 -> Actual | I25: 1 | J25: 1 | CT25: =+'Listas y Parametros'!C233 -> 0 | CU25: =+'Listas y Parametros'!D233 -> 0 | CV25: =+'Listas y Parametros'!E233 -> 0 | CW25: 1 | DI25: Total | DJ25: =+ABS(SUM(DL25:DW25)) -> 6824618.2 | DK25: =+SUM(DK20:DK24) -> 4731300.1 | DL25: =SUM(DL20:DL24) -> 521821.5 | DM25: =SUM(DM20:DM24) -> 533560.64 | DN25: =SUM(DN20:DN24) -> 617807.18 | DO25: =SUM(DO20:DO24) -> 555462.05 | DP25: =SUM(DP20:DP24) -> 566053.8 | DQ25: =SUM(DQ20:DQ24) -> 639612.27 | DR25: =SUM(DR20:DR24) -> 631571.99 | DS25: =SUM(DS20:DS24) -> 665410.71 | ... DW25: =SUM(DW20:DW24) -> 511590.87
C26: =+'Gantt Proyectos'!D112 -> V MEIA San Rafael | D26: =+'Gantt Proyectos'!E112 -> Minsur | E26: =+'Gantt Proyectos'!F112 -> Perú | F26: =+'Gantt Proyectos'!L112 -> 248031 | G26: =+'Gantt Proyectos'!AC112 -> Permisos / MEIA | H26: =+'Gantt Proyectos'!AD112 -> Actual | I26: 1 | J26: 1 | CT26: =+'Listas y Parametros'!C234 -> 0 | CU26: =+'Listas y Parametros'!D234 -> 0 | CV26: =+'Listas y Parametros'!E234 -> 0 | CW26: 1 | DL26: =-DL25 -> -521821.5 | DM26: =-DM25 -> -533560.64 | DN26: =-DN25 -> -617807.18 | DO26: =-DO25 -> -555462.05 | DP26: =-DP25 -> -566053.8 | DQ26: =-DQ25 -> -639612.27 | DR26: =-DR25 -> -631571.99 | DS26: =-DS25 -> -665410.71 | ... DW26: =-DW25 -> -511590.87
C27: =+'Gantt Proyectos'!D113 -> Fase 2 CTV: Modelamiento Recursos, Geomecanica y LOM actualizado | D27: =+'Gantt Proyectos'!E113 -> Mosaic | E27: =+'Gantt Proyectos'!F113 -> Brasil | F27: =+'Gantt Proyectos'!L113 -> 330410 | G27: =+'Gantt Proyectos'!AC113 -> Scoping | H27: =+'Gantt Proyectos'!AD113 -> Actual | I27: 1 | J27: 1 | CT27: =+'Listas y Parametros'!C235 -> 0 | CU27: =+'Listas y Parametros'!D235 -> 0 | CV27: =+'Listas y Parametros'!E235 -> 0 | CW27: 1 | DI27: Margen | DJ27: Total | DK27: Acumulado | DL27: 45687 | DM27: 45716 | DN27: 45746 | DO27: 45777 | DP27: 45807 | DQ27: 45838 | DR27: 45868 | DS27: 45899 | DT27: 45930 | DU27: 45960 | DV27: 45991 | DW27: 46021
C28: =+'Gantt Proyectos'!D114 -> Estrategia de Valor para Mina Cobriza | D28: =+'Gantt Proyectos'!E114 -> OCP | E28: =+'Gantt Proyectos'!F114 -> Perú | F28: =+'Gantt Proyectos'!L114 -> 184000 | G28: =+'Gantt Proyectos'!AC114 -> Estudio Conceptual / LOM | H28: =+'Gantt Proyectos'!AD114 -> Actual | I28: 1 | J28: 1 | CS28: Otros | CT28: =+'Listas y Parametros'!C236 -> 0 | CU28: =+'Listas y Parametros'!D236 -> 0 | CV28: =+'Listas y Parametros'!E236 -> 0 | CW28: 1 | DI28: Chile | DJ28: =+SUM(DL28:DW28) -> -1250779.8 | DK28: =+SUM(DL28:DS28) -> -287376.37 | DL28: =+DL12-DL20 -> -34913.914 | DM28: =+DM12-DM20 -> 125183.98 | DN28: =+DN12-DN20 -> -44905.92 | DO28: =+DO12-DO20 -> -93640.381 | DP28: =+DP12-DP20 -> -27204.209 | DQ28: =+DQ12-DQ20 -> -122460.4 | DR28: =+DR12-DR20 -> 147257.56 | DS28: =+DS12-DS20 -> -236693.09 | DT28: =+'Flujo Caja'!M16 -> -209862.23 | DU28: =+'Flujo Caja'!N16 -> -190134.95 | DV28: =+'Flujo Caja'!O16 -> -275134.95 | DW28: =+'Flujo Caja'!P16 -> -288271.32
C29: =+'Gantt Proyectos'!D115 -> PFS Ferrobamba UG (MEIA) | D29: =+'Gantt Proyectos'!E115 -> Las Bambas | E29: =+'Gantt Proyectos'!F115 -> Perú | F29: =+'Gantt Proyectos'!L115 -> 600000 | G29: =+'Gantt Proyectos'!AC115 -> Permisos / MEIA | H29: =+'Gantt Proyectos'!AD115 -> Actual | I29: 1 | J29: 1 | CT29: =+'Listas y Parametros'!C237 -> 0 | CU29: =+'Listas y Parametros'!D237 -> 0 | CV29: =+'Listas y Parametros'!E237 -> 0 | CW29: 1 | DI29: Perú | DJ29: =+SUM(DL29:DW29) -> 1756529.2 | DK29: =+SUM(DL29:DS29) -> 582122.85 | DL29: =+DL13-DL21 -> 34385.15 | DM29: =+DM13-DM21 -> -19143 | DN29: =+DN13-DN21 -> 12622 | DO29: =+DO13-DO21 -> -27595.3 | DP29: =+DP13-DP21 -> 13686 | DQ29: =+DQ13-DQ21 -> 76004 | DR29: =+DR13-DR21 -> 62578 | DS29: =+DS13-DS21 -> 429586 | DT29: =+'Flujo Caja'!M19 -> 341494.45 | DU29: =+'Flujo Caja'!N19 -> 368577.78 | DV29: =+'Flujo Caja'!O19 -> 233292.06 | DW29: =+'Flujo Caja'!P19 -> 231042.06
C30: =+'Gantt Proyectos'!D116 -> BHP: Análisis de accesibilidad para MEL UG | D30: =+'Gantt Proyectos'!E116 -> MEL | E30: =+'Gantt Proyectos'!F116 -> Chile | F30: =+'Gantt Proyectos'!L116 -> 198920 | G30: =+'Gantt Proyectos'!AC116 -> Scoping | H30: =+'Gantt Proyectos'!AD116 -> Actual | I30: 1 | J30: 1 | CT30: =+'Listas y Parametros'!C238 -> 0 | CU30: =+'Listas y Parametros'!D238 -> 0 | CV30: =+'Listas y Parametros'!E238 -> 0 | CW30: 1 | DI30: Brasil | DJ30: =+SUM(DL30:DW30) -> 1223700.3 | DK30: =+SUM(DL30:DS30) -> 315191.6 | DL30: =+DL14-DL22 -> 59479 | DM30: =+DM14-DM22 -> 31871 | DN30: =+DN14-DN22 -> 69897 | DO30: =+DO14-DO22 -> 45142.6 | DP30: =+DP14-DP22 -> 3745 | DQ30: =+DQ14-DQ22 -> -9818 | DR30: =+DR14-DR22 -> 16698 | DS30: =+DS14-DS22 -> 98177 | DT30: =+'Flujo Caja'!M22 -> 273070.85 | DU30: =+'Flujo Caja'!N22 -> 245496.87 | DV30: =+'Flujo Caja'!O22 -> 236940.18 | DW30: =+'Flujo Caja'!P22 -> 153000.78
C31: =+'Gantt Proyectos'!D117 -> Resolution: Análisis de Proyecto Túnel 68L | D31: =+'Gantt Proyectos'!E117 -> BHP | E31: =+'Gantt Proyectos'!F117 -> Chile | F31: =+'Gantt Proyectos'!L117 -> 47808 | G31: =+'Gantt Proyectos'!AC117 -> Consultoria y Due Dilligence | H31: =+'Gantt Proyectos'!AD117 -> Actual | I31: 1 | J31: 1 | CT31: =+'Listas y Parametros'!C239 -> 0 | CU31: =+'Listas y Parametros'!D239 -> 0 | CV31: =+'Listas y Parametros'!E239 -> 0 | CW31: 1 | DI31: USA | DJ31: =+SUM(DL31:DW31) -> 697909.64 | DK31: =+SUM(DL31:DS31) -> 847988.21 | DL31: =+DL15-DL23 -> 150438 | DM31: =+DM15-DM23 -> 241440.21 | DN31: =+DN15-DN23 -> 82798 | DO31: =+DO15-DO23 -> 159302 | DP31: =+DP15-DP23 -> 147424 | DQ31: =+DQ15-DQ23 -> 57618 | DR31: =+DR15-DR23 -> -10017 | DS31: =+DS15-DS23 -> 18985 | DT31: =+'Flujo Caja'!M25 -> -36269.642 | DU31: =+'Flujo Caja'!N25 -> -36269.642 | DV31: =+'Flujo Caja'!O25 -> -36269.642 | DW31: =+'Flujo Caja'!P25 -> -41269.642
C32: =+'Gantt Proyectos'!D118 -> Cajati: Actualización Ingeniería P1 | D32: =+'Gantt Proyectos'!E118 -> Mosaic | E32: =+'Gantt Proyectos'!F118 -> Brasil | F32: =+'Gantt Proyectos'!L118 -> 147935 | G32: =+'Gantt Proyectos'!AC118 -> FS e Ing. Basica | H32: =+'Gantt Proyectos'!AD118 -> Actual | I32: 1 | J32: 1 | DI32: Otros | DJ32: =+SUM(DL32:DW32) -> 276726.6 | DK32: =+SUM(DL32:DS32) -> 276726.6 | DL32: =+DL16-DL24 -> -14044 | DM32: =+DM16-DM24 -> 21682 | DN32: =+DN16-DN24 -> 45478 | DO32: =+DO16-DO24 -> -14380 | DP32: =+DP16-DP24 -> -16000 | DQ32: =+DQ16-DQ24 -> 166360.2 | DR32: =+DR16-DR24 -> -5684.8 | DS32: =+DS16-DS24 -> 93315.2 | DT32: =+'Flujo Caja'!M28 -> 0 | DU32: =+'Flujo Caja'!N28 -> 0 | DV32: =+'Flujo Caja'!O28 -> 0 | DW32: =+'Flujo Caja'!P28 -> 0
C33: =+'Gantt Proyectos'!D119 -> LOM Integrado San Rafael: 2025 | D33: =+'Gantt Proyectos'!E119 -> Minsur | E33: =+'Gantt Proyectos'!F119 -> Perú | F33: =+'Gantt Proyectos'!L119 -> 60000 | G33: =+'Gantt Proyectos'!AC119 -> Estudio Conceptual / LOM | H33: =+'Gantt Proyectos'!AD119 -> Actual | I33: 1 | J33: 1 | DI33: Total | DJ33: =+SUM(DL33:DW33) -> 2704085.9 | DK33: =+SUM(DK28:DK32) -> 1734652.9 | DL33: =+SUM(DL28:DL32) -> 195344.24 | DM33: =+SUM(DM28:DM32) -> 401034.19 | DN33: =+SUM(DN28:DN32) -> 165889.08 | DO33: =+SUM(DO28:DO32) -> 68828.919 | DP33: =+SUM(DP28:DP32) -> 121650.79 | DQ33: =+SUM(DQ28:DQ32) -> 167703.8 | DR33: =+SUM(DR28:DR32) -> 210831.76 | ... DW33: =+SUM(DW28:DW32) -> 54501.888
C34: =+'Gantt Proyectos'!D120 -> Soporte Minero en Litigio OT - Gobierno Mongolia (Fase 2) | D34: =+'Gantt Proyectos'!E120 -> ThreeCrowns | E34: =+'Gantt Proyectos'!F120 -> USA | F34: =+'Gantt Proyectos'!L120 -> 350000 | G34: =+'Gantt Proyectos'!AC120 -> Consultoria y Due Dilligence | H34: =+'Gantt Proyectos'!AD120 -> Actual | I34: 1 | J34: 1 | DI34: % | DJ34: =+DJ33/DJ17 -> 0.28378318 | DK34: =+DK33/DK17 -> 0.2682749 | DL34: =+DL33/DL17 -> 0.27238367 | DM34: =+DM33/DM17 -> 0.42909952 | DN34: =+DN33/DN17 -> 0.21167522 | DO34: =+DO33/DO17 -> 0.11025135 | DP34: =+DP33/DP17 -> 0.17689396 | DQ34: =+DQ33/DQ17 -> 0.20773004 | ... DW34: =+DW33/DW17 -> 0.09627731
C35: =+'Gantt Proyectos'!D121 -> Aura: Ingeniería Túnel de Exploraciones | D35: =+'Gantt Proyectos'!E121 -> Aura Minerals | E35: =+'Gantt Proyectos'!F121 -> Brasil | F35: =+'Gantt Proyectos'!L121 -> 108000 | G35: =+'Gantt Proyectos'!AC121 -> Scoping | H35: =+'Gantt Proyectos'!AD121 -> Actual | I35: 1 | J35: 1
C36: =+'Gantt Proyectos'!D122 -> Los Calatos - DFS | D36: =+'Gantt Proyectos'!E122 -> CD Capital | E36: =+'Gantt Proyectos'!F122 -> Perú | F36: =+'Gantt Proyectos'!L122 -> 1100000 | G36: =+'Gantt Proyectos'!AC122 -> FS e Ing. Basica | H36: =+'Gantt Proyectos'!AD122 -> Asignado | I36: 1 | J36: 1 | DI36: Margen Acum | DJ36: Total | DK36: Acumulado | DL36: 45687 | DM36: 45716 | DN36: 45746 | DO36: 45777 | DP36: 45807 | DQ36: 45838 | DR36: 45868 | DS36: 45899 | DT36: 45930 | DU36: 45960 | DV36: 45991 | DW36: 46021
C37: =+'Gantt Proyectos'!D123 -> Ferrobamba PFS | D37: =+'Gantt Proyectos'!E123 -> Las Bambas | E37: =+'Gantt Proyectos'!F123 -> Perú | F37: =+'Gantt Proyectos'!L123 -> 600000 | G37: =+'Gantt Proyectos'!AC123 -> PFS | H37: =+'Gantt Proyectos'!AD123 -> No Asignado | I37: 0.7 | J37: 1 | DI37: Chile | DJ37: =+DW37 -> -1250779.8 | DK37: =+DP37 -> -75480.442 | DL37: =+DL28 -> -34913.914 | DM37: =+DL37+DM28 -> 90270.068 | DN37: =+DM37+DN28 -> 45364.148 | DO37: =+DN37+DO28 -> -48276.233 | DP37: =+DO37+DP28 -> -75480.442 | DQ37: =+DP37+DQ28 -> -197940.84 | DR37: =+DQ37+DR28 -> -50683.281 | DS37: =+DR37+DS28 -> -287376.37 | DT37: =+DS37+DT28 -> -497238.59 | ... DW37: =+DV37+DW28 -> -1250779.8
C38: =+'Gantt Proyectos'!D124 -> Caserones: Implementacion NSR en Corto Plazo | D38: =+'Gantt Proyectos'!E124 -> Lundin | E38: =+'Gantt Proyectos'!F124 -> Chile | F38: =+'Gantt Proyectos'!L124 -> 0 | G38: =+'Gantt Proyectos'!AC124 -> Consultoria y Due Dilligence | H38: =+'Gantt Proyectos'!AD124 -> No Asignado | I38: 0 | J38: 0 | DI38: Perú | DJ38: =+DW38 -> 1756529.2 | DK38: =+DP38 -> 13954.85 | DL38: =+DL29 -> 34385.15 | DM38: =+DL38+DM29 -> 15242.15 | DN38: =+DM38+DN29 -> 27864.15 | DO38: =+DN38+DO29 -> 268.85 | DP38: =+DO38+DP29 -> 13954.85 | DQ38: =+DP38+DQ29 -> 89958.85 | DR38: =+DQ38+DR29 -> 152536.85 | DS38: =+DR38+DS29 -> 582122.85 | DT38: =+DS38+DT29 -> 923617.3 | ... DW38: =+DV38+DW29 -> 1756529.2
C39: =+'Gantt Proyectos'!D125 -> Caserones: Análisis Estratégico | D39: =+'Gantt Proyectos'!E125 -> Lundin | E39: =+'Gantt Proyectos'!F125 -> Chile | F39: =+'Gantt Proyectos'!L125 -> 300000 | G39: =+'Gantt Proyectos'!AC125 -> Estudio Conceptual / LOM | H39: =+'Gantt Proyectos'!AD125 -> Actual | I39: 1 | J39: 1 | DI39: Brasil | DJ39: =+DW39 -> 1223700.3 | DK39: =+DP39 -> 210134.6 | DL39: =+DL30 -> 59479 | DM39: =+DL39+DM30 -> 91350 | DN39: =+DM39+DN30 -> 161247 | DO39: =+DN39+DO30 -> 206389.6 | DP39: =+DO39+DP30 -> 210134.6 | DQ39: =+DP39+DQ30 -> 200316.6 | DR39: =+DQ39+DR30 -> 217014.6 | DS39: =+DR39+DS30 -> 315191.6 | DT39: =+DS39+DT30 -> 588262.45 | ... DW39: =+DV39+DW30 -> 1223700.3
C40: =+'Gantt Proyectos'!D126 -> QuinnEmanuel: OT Allegation | D40: =+'Gantt Proyectos'!E126 -> QuinnEmanuel | E40: =+'Gantt Proyectos'!F126 -> USA | F40: =+'Gantt Proyectos'!L126 -> 300000 | G40: =+'Gantt Proyectos'!AC126 -> Consultoria y Due Dilligence | H40: =+'Gantt Proyectos'!AD126 -> No Asignado | I40: 0.1 | J40: 1 | DI40: USA | DJ40: =+DW40 -> 697909.64 | DK40: =+DP40 -> 781402.21 | DL40: =+DL31 -> 150438 | DM40: =+DL40+DM31 -> 391878.21 | DN40: =+DM40+DN31 -> 474676.21 | DO40: =+DN40+DO31 -> 633978.21 | DP40: =+DO40+DP31 -> 781402.21 | DQ40: =+DP40+DQ31 -> 839020.21 | DR40: =+DQ40+DR31 -> 829003.21 | DS40: =+DR40+DS31 -> 847988.21 | DT40: =+DS40+DT31 -> 811718.57 | ... DW40: =+DV40+DW31 -> 697909.64
C41: =+'Gantt Proyectos'!D127 -> DET: Ingeniería Perfil Sector Teniente 9 | D41: =+'Gantt Proyectos'!E127 -> Codelco | E41: =+'Gantt Proyectos'!F127 -> Chile | F41: =+'Gantt Proyectos'!L127 -> 300000 | G41: =+'Gantt Proyectos'!AC127 -> Scoping | H41: =+'Gantt Proyectos'!AD127 -> No Asignado | I41: 0.2 | J41: 1 | DI41: Otros | DJ41: =+DW41 -> 276726.6 | DK41: =+DP41 -> 22736 | DL41: =+DL32 -> -14044 | DM41: =+DL41+DM32 -> 7638 | DN41: =+DM41+DN32 -> 53116 | DO41: =+DN41+DO32 -> 38736 | DP41: =+DO41+DP32 -> 22736 | DQ41: =+DP41+DQ32 -> 189096.2 | DR41: =+DQ41+DR32 -> 183411.4 | DS41: =+DR41+DS32 -> 276726.6 | DT41: =+DS41+DT32 -> 276726.6 | ... DW41: =+DV41+DW32 -> 276726.6
C42: =+'Gantt Proyectos'!D128 -> Ingeniería Basica Sistema Manejo Materiales Candelaria | D42: =+'Gantt Proyectos'!E128 -> Lundin | E42: =+'Gantt Proyectos'!F128 -> Chile | F42: =+'Gantt Proyectos'!L128 -> 1300000 | G42: =+'Gantt Proyectos'!AC128 -> FS e Ing. Basica | H42: =+'Gantt Proyectos'!AD128 -> No Asignado | I42: 0 | J42: 0 | DI42: Total | DJ42: =+DW42 -> 2704085.9 | DK42: =+SUM(DK37:DK41) -> 952747.22 | DL42: =+SUM(DL37:DL41) -> 195344.24 | DM42: =+SUM(DM37:DM41) -> 596378.43 | DN42: =+SUM(DN37:DN41) -> 762267.51 | DO42: =+SUM(DO37:DO41) -> 831096.43 | DP42: =+SUM(DP37:DP41) -> 952747.22 | DQ42: =+SUM(DQ37:DQ41) -> 1120451 | DR42: =+SUM(DR37:DR41) -> 1331282.8 | ... DW42: =+SUM(DW37:DW41) -> 2704085.9
C43: =+'Gantt Proyectos'!D129 -> PEA Proyecto Furnas | D43: =+'Gantt Proyectos'!E129 -> Ero Copper | E43: =+'Gantt Proyectos'!F129 -> Brasil | F43: =+'Gantt Proyectos'!L129 -> 490000 | G43: =+'Gantt Proyectos'!AC129 -> PEA | H43: =+'Gantt Proyectos'!AD129 -> Actual | I43: 1 | J43: 1
C44: =+'Gantt Proyectos'!D130 -> Cerro Blanco: FS Minería + Ing Detalle componentes | D44: =+'Gantt Proyectos'!E130 -> Aura Minerals | E44: =+'Gantt Proyectos'!F130 -> Brasil | F44: =+'Gantt Proyectos'!L130 -> 2400000 | G44: =+'Gantt Proyectos'!AC130 -> FS e Ing. Basica | H44: =+'Gantt Proyectos'!AD130 -> No Asignado | I44: 0.2 | J44: 1
C45: =+'Gantt Proyectos'!D131 -> Scoping Study Algarrobo UG | D45: =+'Gantt Proyectos'!E131 -> CMP | E45: =+'Gantt Proyectos'!F131 -> Chile | F45: =+'Gantt Proyectos'!L131 -> 160000 | G45: =+'Gantt Proyectos'!AC131 -> Scoping | H45: =+'Gantt Proyectos'!AD131 -> No Asignado | I45: 0.1 | J45: 1 | DI45: Flujo Total | DJ45: Total | DK45: Acumulado | DL45: 45687 | DM45: 45716 | DN45: 45746 | DO45: 45777 | DP45: 45807 | DQ45: 45838 | DR45: 45868 | DS45: 45899 | DT45: 45930 | DU45: 45960 | DV45: 45991 | DW45: 46021
C46: =+'Gantt Proyectos'!D132 -> Soporte Romeral, construcción túnel exploratorio | D46: =+'Gantt Proyectos'!E132 -> Romeral | E46: =+'Gantt Proyectos'!F132 -> Chile | F46: =+'Gantt Proyectos'!L132 -> 500000 | G46: =+'Gantt Proyectos'!AC132 -> Consultoria y Due Dilligence | H46: =+'Gantt Proyectos'!AD132 -> No Asignado | I46: 0.3 | J46: 1 | DI46: Ingreso | DJ46: =+SUM(DL46:DW46) -> 9494893.5 | DK46: =+SUM(DL46:DP46) -> 3747452.4 | DL46: =DL17 -> 717165.73 | DM46: =DM17 -> 934594.83 | DN46: =DN17 -> 783696.26 | DO46: =DO17 -> 624290.97 | DP46: =DP17 -> 687704.59 | DQ46: =DQ17 -> 807316.07 | DR46: =+'Flujo Caja'!K29 -> 1002475.1 | DS46: =+'Flujo Caja'!L29 -> 874898.88 | DT46: =+'Flujo Caja'!M29 -> 924933.39 | DU46: =+'Flujo Caja'!N29 -> 910715.47 | DV46: =+'Flujo Caja'!O29 -> 661009.43 | DW46: =+'Flujo Caja'!P29 -> 566092.76
C47: =+'Gantt Proyectos'!D133 -> Servicios de geología y planificación (3 años) | D47: =+'Gantt Proyectos'!E133 -> Alcoa | E47: =+'Gantt Proyectos'!F133 -> Brasil | F47: =+'Gantt Proyectos'!L133 -> 890000 | G47: =+'Gantt Proyectos'!AC133 -> FS e Ing. Basica | H47: =+'Gantt Proyectos'!AD133 -> No Asignado | I47: 0.35 | J47: 1 | DI47: Costos | DJ47: =+SUM(DL47:DW47) -> 6703462.7 | DK47: =+SUM(DL47:DP47) -> 2794705.2 | DL47: =DL25 -> 521821.5 | DM47: =DM25 -> 533560.64 | DN47: =DN25 -> 617807.18 | DO47: =DO25 -> 555462.05 | DP47: =DP25 -> 566053.8 | DQ47: =DQ25 -> 639612.27 | DR47: =+'Flujo Caja'!K30 -> 632463.6 | DS47: =+'Flujo Caja'!L30 -> 543363.6 | DT47: =+'Flujo Caja'!M30 -> 556499.96 | DU47: =+'Flujo Caja'!N30 -> 523045.42 | DV47: =+'Flujo Caja'!O30 -> 502181.78 | DW47: =+'Flujo Caja'!P30 -> 511590.87
C48: =+'Gantt Proyectos'!D134 -> Evaluación de diferentes escenarios estrategicos (Cambio de producto) | D48: =+'Gantt Proyectos'!E134 -> BCG | E48: =+'Gantt Proyectos'!F134 -> Brasil | F48: =+'Gantt Proyectos'!L134 -> 180000 | G48: =+'Gantt Proyectos'!AC134 -> Consultoria y Due Dilligence | H48: =+'Gantt Proyectos'!AD134 -> No Asignado | I48: 0.9 | J48: 1 | DI48: Margen | DJ48: =+SUM(DL48:DW48) -> 2791430.8 | DK48: =+DK46-DK47 -> 952747.22 | DL48: =+DL46-DL47 -> 195344.24 | DM48: =+DM46-DM47 -> 401034.19 | DN48: =+DN46-DN47 -> 165889.08 | DO48: =+DO46-DO47 -> 68828.919 | DP48: =+DP46-DP47 -> 121650.79 | DQ48: =+DQ46-DQ47 -> 167703.8 | DR48: =+DR46-DR47 -> 370011.47 | ... DW48: =+DW46-DW47 -> 54501.888
C49: =+'Gantt Proyectos'!D135 -> Optimización proceso LOM + Implementación SIMPLAN | D49: =+'Gantt Proyectos'!E135 -> LHG | E49: =+'Gantt Proyectos'!F135 -> Brasil | F49: =+'Gantt Proyectos'!L135 -> 150000 | G49: =+'Gantt Proyectos'!AC135 -> Consultoria y Due Dilligence | H49: =+'Gantt Proyectos'!AD135 -> No Asignado | I49: 0 | J49: 0 | DL49: =-DL47 -> -521821.5 | DM49: =-DM47 -> -533560.64 | DN49: =-DN47 -> -617807.18 | DO49: =-DO47 -> -555462.05 | DP49: =-DP47 -> -566053.8 | DQ49: =-DQ47 -> -639612.27 | DR49: =-DR47 -> -632463.6 | DS49: =-DS47 -> -543363.6 | ... DW49: =-DW47 -> -511590.87
C50: =+'Gantt Proyectos'!D136 -> Servicio de Modelamiento Geotécnico Botaderos Parca | D50: =+'Gantt Proyectos'!E136 -> BHP | E50: =+'Gantt Proyectos'!F136 -> Chile | F50: =+'Gantt Proyectos'!L136 -> 300000 | G50: =+'Gantt Proyectos'!AC136 -> FS e Ing. Basica | H50: =+'Gantt Proyectos'!AD136 -> No Asignado | I50: 0 | J50: 0 | DO50: 830
C51: =+'Gantt Proyectos'!D137 -> Evaluación de cumplimiento de planes de corto plazo | D51: =+'Gantt Proyectos'!E137 -> Antamina | E51: =+'Gantt Proyectos'!F137 -> Perú | F51: =+'Gantt Proyectos'!L137 -> 180000 | G51: =+'Gantt Proyectos'!AC137 -> Consultoria y Due Dilligence | H51: =+'Gantt Proyectos'!AD137 -> No Asignado | I51: 0.05 | J51: 1
C52: =+'Gantt Proyectos'!D138 -> Actualización del Estudio Geomecánico | D52: =+'Gantt Proyectos'!E138 -> Nexa | E52: =+'Gantt Proyectos'!F138 -> Perú | F52: =+'Gantt Proyectos'!L138 -> 120000 | G52: =+'Gantt Proyectos'!AC138 -> Consultoria y Due Dilligence | H52: =+'Gantt Proyectos'!AD138 -> No Asignado | I52: 0 | J52: 0 | DH52: 2. Proyectos
C53: =+'Gantt Proyectos'!D139 -> Ing detalle infraestructura Mina | D53: =+'Gantt Proyectos'!E139 -> BR Nickel | E53: =+'Gantt Proyectos'!F139 -> Brasil | F53: =+'Gantt Proyectos'!L139 -> 700000 | G53: =+'Gantt Proyectos'!AC139 -> FS e Ing. Basica | H53: =+'Gantt Proyectos'!AD139 -> No Asignado | I53: 0 | J53: 0
C54: =+'Gantt Proyectos'!D140 -> Estudio Geomecánico de Interacción Block Caving – Chancado Primario | D54: =+'Gantt Proyectos'!E140 -> Nexa | E54: =+'Gantt Proyectos'!F140 -> Perú | F54: =+'Gantt Proyectos'!L140 -> 150000 | G54: =+'Gantt Proyectos'!AC140 -> Consultoria y Due Dilligence | H54: =+'Gantt Proyectos'!AD140 -> No Asignado | I54: 0 | J54: 0 | DI54: # Proyectos | DJ54: Total | DK54: 45777 | DL54: 45807 | DM54: 45838 | DN54: 45868 | DO54: 45899 | DP54: 45930 | DQ54: 45960 | DR54: 45991 | DS54: 46021
C55: =+'Gantt Proyectos'!D141 -> Servicio de revisón independiente de infraestructura (relaves) | D55: =+'Gantt Proyectos'!E141 -> ERG | E55: =+'Gantt Proyectos'!F141 -> Brasil | F55: =+'Gantt Proyectos'!L141 -> 490000 | G55: =+'Gantt Proyectos'!AC141 -> Consultoria y Due Dilligence | H55: =+'Gantt Proyectos'!AD141 -> No Asignado | I55: 0 | J55: 0 | DI55: Chile | DJ55: =+AVERAGE(DL55:DS55) -> 6.5 | DK55: =+COUNTIFS('Gantt Proyectos'!AF$97:AF$1048576,">"&0,'Gantt Proyectos'!$F$97:$F$1048576,Dashboard!$DI55) -> 13 | DL55: =+COUNTIFS('Gantt Proyectos'!AG$97:AG$1048576,">"&0,'Gantt Proyectos'!$F$97:$F$1048576,Dashboard!$DI55) -> 8 | DM55: =+COUNTIFS('Gantt Proyectos'!AH$97:AH$1048576,">"&0,'Gantt Proyectos'!$F$97:$F$1048576,Dashboard!$DI55) -> 6 | DN55: =+COUNTIFS('Gantt Proyectos'!AI$97:AI$1048576,">"&0,'Gantt Proyectos'!$F$97:$F$1048576,Dashboard!$DI55) -> 9 | DO55: =+COUNTIFS('Gantt Proyectos'!AJ$97:AJ$1048576,">"&0,'Gantt Proyectos'!$F$97:$F$1048576,Dashboard!$DI55) -> 8 | DP55: =+COUNTIFS('Gantt Proyectos'!AK$97:AK$1048576,">"&0,'Gantt Proyectos'!$F$97:$F$1048576,Dashboard!$DI55) -> 7 | DQ55: =+COUNTIFS('Gantt Proyectos'!AL$97:AL$1048576,">"&0,'Gantt Proyectos'!$F$97:$F$1048576,Dashboard!$DI55) -> 5 | DR55: =+COUNTIFS('Gantt Proyectos'!AM$97:AM$1048576,">"&0,'Gantt Proyectos'!$F$97:$F$1048576,Dashboard!$DI55) -> 5 | DS55: =+COUNTIFS('Gantt Proyectos'!AN$97:AN$1048576,">"&0,'Gantt Proyectos'!$F$97:$F$1048576,Dashboard!$DI55) -> 4
C56: =+'Gantt Proyectos'!D142 -> Rockhaven Klaza Project (PFS) | D56: =+'Gantt Proyectos'!E142 -> Rockhaven | E56: =+'Gantt Proyectos'!F142 -> USA | F56: =+'Gantt Proyectos'!L142 -> 1500000 | G56: =+'Gantt Proyectos'!AC142 -> PFS | H56: =+'Gantt Proyectos'!AD142 -> No Asignado | I56: 0 | J56: 0 | DI56: Perú | DJ56: =+AVERAGE(DL56:DS56) -> 6.75 | DK56: =+COUNTIFS('Gantt Proyectos'!AF$97:AF$1048576,">"&0,'Gantt Proyectos'!$F$97:$F$1048576,Dashboard!$DI56) -> 6 | DL56: =+COUNTIFS('Gantt Proyectos'!AG$97:AG$1048576,">"&0,'Gantt Proyectos'!$F$97:$F$1048576,Dashboard!$DI56) -> 6 | DM56: =+COUNTIFS('Gantt Proyectos'!AH$97:AH$1048576,">"&0,'Gantt Proyectos'!$F$97:$F$1048576,Dashboard!$DI56) -> 7 | DN56: =+COUNTIFS('Gantt Proyectos'!AI$97:AI$1048576,">"&0,'Gantt Proyectos'!$F$97:$F$1048576,Dashboard!$DI56) -> 11 | DO56: =+COUNTIFS('Gantt Proyectos'!AJ$97:AJ$1048576,">"&0,'Gantt Proyectos'!$F$97:$F$1048576,Dashboard!$DI56) -> 11 | DP56: =+COUNTIFS('Gantt Proyectos'!AK$97:AK$1048576,">"&0,'Gantt Proyectos'!$F$97:$F$1048576,Dashboard!$DI56) -> 7 | DQ56: =+COUNTIFS('Gantt Proyectos'!AL$97:AL$1048576,">"&0,'Gantt Proyectos'!$F$97:$F$1048576,Dashboard!$DI56) -> 6 | DR56: =+COUNTIFS('Gantt Proyectos'!AM$97:AM$1048576,">"&0,'Gantt Proyectos'!$F$97:$F$1048576,Dashboard!$DI56) -> 4 | DS56: =+COUNTIFS('Gantt Proyectos'!AN$97:AN$1048576,">"&0,'Gantt Proyectos'!$F$97:$F$1048576,Dashboard!$DI56) -> 2
C57: =+'Gantt Proyectos'!D143 -> HILL OF VALUE AND OPTIMIZED CUT-OFF GRADE STRATEGY ANALYSIS | D57: =+'Gantt Proyectos'!E143 -> South 32 | E57: =+'Gantt Proyectos'!F143 -> USA | F57: =+'Gantt Proyectos'!L143 -> 40000 | G57: =+'Gantt Proyectos'!AC143 -> Consultoria y Due Dilligence | H57: =+'Gantt Proyectos'!AD143 -> Asignado | I57: 1 | J57: 1 | DI57: Brasil | DJ57: =+AVERAGE(DL57:DS57) -> 5.25 | DK57: =+COUNTIFS('Gantt Proyectos'!AF$97:AF$1048576,">"&0,'Gantt Proyectos'!$F$97:$F$1048576,Dashboard!$DI57) -> 4 | DL57: =+COUNTIFS('Gantt Proyectos'!AG$97:AG$1048576,">"&0,'Gantt Proyectos'!$F$97:$F$1048576,Dashboard!$DI57) -> 5 | DM57: =+COUNTIFS('Gantt Proyectos'!AH$97:AH$1048576,">"&0,'Gantt Proyectos'!$F$97:$F$1048576,Dashboard!$DI57) -> 5 | DN57: =+COUNTIFS('Gantt Proyectos'!AI$97:AI$1048576,">"&0,'Gantt Proyectos'!$F$97:$F$1048576,Dashboard!$DI57) -> 7 | DO57: =+COUNTIFS('Gantt Proyectos'!AJ$97:AJ$1048576,">"&0,'Gantt Proyectos'!$F$97:$F$1048576,Dashboard!$DI57) -> 7 | DP57: =+COUNTIFS('Gantt Proyectos'!AK$97:AK$1048576,">"&0,'Gantt Proyectos'!$F$97:$F$1048576,Dashboard!$DI57) -> 7 | DQ57: =+COUNTIFS('Gantt Proyectos'!AL$97:AL$1048576,">"&0,'Gantt Proyectos'!$F$97:$F$1048576,Dashboard!$DI57) -> 5 | DR57: =+COUNTIFS('Gantt Proyectos'!AM$97:AM$1048576,">"&0,'Gantt Proyectos'!$F$97:$F$1048576,Dashboard!$DI57) -> 4 | DS57: =+COUNTIFS('Gantt Proyectos'!AN$97:AN$1048576,">"&0,'Gantt Proyectos'!$F$97:$F$1048576,Dashboard!$DI57) -> 2
C58: =+'Gantt Proyectos'!D144 -> Analisis de confiafilidad de plan + Entrenamiento de usuario | D58: =+'Gantt Proyectos'!E144 -> Capstone Copper | E58: =+'Gantt Proyectos'!F144 -> Chile | F58: =+'Gantt Proyectos'!L144 -> 200000 | G58: =+'Gantt Proyectos'!AC144 -> Consultoria y Due Dilligence | H58: =+'Gantt Proyectos'!AD144 -> No Asignado | I58: 0.9 | J58: 1 | DI58: USA | DJ58: =+AVERAGE(DL58:DS58) -> 2 | DK58: =+COUNTIFS('Gantt Proyectos'!AF$97:AF$1048576,">"&0,'Gantt Proyectos'!$F$97:$F$1048576,Dashboard!$DI58) -> 2 | DL58: =+COUNTIFS('Gantt Proyectos'!AG$97:AG$1048576,">"&0,'Gantt Proyectos'!$F$97:$F$1048576,Dashboard!$DI58) -> 2 | DM58: =+COUNTIFS('Gantt Proyectos'!AH$97:AH$1048576,">"&0,'Gantt Proyectos'!$F$97:$F$1048576,Dashboard!$DI58) -> 3 | DN58: =+COUNTIFS('Gantt Proyectos'!AI$97:AI$1048576,">"&0,'Gantt Proyectos'!$F$97:$F$1048576,Dashboard!$DI58) -> 1 | DO58: =+COUNTIFS('Gantt Proyectos'!AJ$97:AJ$1048576,">"&0,'Gantt Proyectos'!$F$97:$F$1048576,Dashboard!$DI58) -> 2 | DP58: =+COUNTIFS('Gantt Proyectos'!AK$97:AK$1048576,">"&0,'Gantt Proyectos'!$F$97:$F$1048576,Dashboard!$DI58) -> 2 | DQ58: =+COUNTIFS('Gantt Proyectos'!AL$97:AL$1048576,">"&0,'Gantt Proyectos'!$F$97:$F$1048576,Dashboard!$DI58) -> 2 | DR58: =+COUNTIFS('Gantt Proyectos'!AM$97:AM$1048576,">"&0,'Gantt Proyectos'!$F$97:$F$1048576,Dashboard!$DI58) -> 2 | DS58: =+COUNTIFS('Gantt Proyectos'!AN$97:AN$1048576,">"&0,'Gantt Proyectos'!$F$97:$F$1048576,Dashboard!$DI58) -> 2
C59: =+'Gantt Proyectos'!D145 -> Viabilidad Económica del proyecto | D59: =+'Gantt Proyectos'!E145 -> Minsur | E59: =+'Gantt Proyectos'!F145 -> Perú | F59: =+'Gantt Proyectos'!L145 -> 150000 | G59: =+'Gantt Proyectos'!AC145 -> Consultoria y Due Dilligence | H59: =+'Gantt Proyectos'!AD145 -> No Asignado | I59: 0 | J59: 0 | DI59: Otros | DJ59: =+AVERAGE(DL59:DS59) -> 0 | DK59: =+COUNTIFS('Gantt Proyectos'!AF$97:AF$1048576,">"&0,'Gantt Proyectos'!$F$97:$F$1048576,Dashboard!$DI59) -> 0 | DL59: =+COUNTIFS('Gantt Proyectos'!AG$97:AG$1048576,">"&0,'Gantt Proyectos'!$F$97:$F$1048576,Dashboard!$DI59) -> 0 | DM59: =+COUNTIFS('Gantt Proyectos'!AH$97:AH$1048576,">"&0,'Gantt Proyectos'!$F$97:$F$1048576,Dashboard!$DI59) -> 0 | DN59: =+COUNTIFS('Gantt Proyectos'!AI$97:AI$1048576,">"&0,'Gantt Proyectos'!$F$97:$F$1048576,Dashboard!$DI59) -> 0 | DO59: =+COUNTIFS('Gantt Proyectos'!AJ$97:AJ$1048576,">"&0,'Gantt Proyectos'!$F$97:$F$1048576,Dashboard!$DI59) -> 0 | DP59: =+COUNTIFS('Gantt Proyectos'!AK$97:AK$1048576,">"&0,'Gantt Proyectos'!$F$97:$F$1048576,Dashboard!$DI59) -> 0 | DQ59: =+COUNTIFS('Gantt Proyectos'!AL$97:AL$1048576,">"&0,'Gantt Proyectos'!$F$97:$F$1048576,Dashboard!$DI59) -> 0 | DR59: =+COUNTIFS('Gantt Proyectos'!AM$97:AM$1048576,">"&0,'Gantt Proyectos'!$F$97:$F$1048576,Dashboard!$DI59) -> 0 | DS59: =+COUNTIFS('Gantt Proyectos'!AN$97:AN$1048576,">"&0,'Gantt Proyectos'!$F$97:$F$1048576,Dashboard!$DI59) -> 0
C60: =+'Gantt Proyectos'!D146 -> Ingeniería perfil Clavelinas | D60: =+'Gantt Proyectos'!E146 -> Minsur | E60: =+'Gantt Proyectos'!F146 -> Perú | F60: =+'Gantt Proyectos'!L146 -> 180000 | G60: =+'Gantt Proyectos'!AC146 -> Scoping | H60: =+'Gantt Proyectos'!AD146 -> No Asignado | I60: 0.15 | J60: 1 | DI60: Total | DJ60: =+AVERAGE(DL60:DS60) -> 20.5 | DK60: =+SUM(DK55:DK59) -> 25 | DL60: =+SUM(DL55:DL59) -> 21 | DM60: =+SUM(DM55:DM59) -> 21 | DN60: =+SUM(DN55:DN59) -> 28 | DO60: =+SUM(DO55:DO59) -> 28 | DP60: =+SUM(DP55:DP59) -> 23 | DQ60: =+SUM(DQ55:DQ59) -> 18 | DR60: =+SUM(DR55:DR59) -> 15 | DS60: =+SUM(DS55:DS59) -> 10
C61: =+'Gantt Proyectos'!D147 -> Ingeniería de factibilidad Cristina | D61: =+'Gantt Proyectos'!E147 -> Insideo | E61: =+'Gantt Proyectos'!F147 -> Perú | F61: =+'Gantt Proyectos'!L147 -> 350000 | G61: =+'Gantt Proyectos'!AC147 -> FS e Ing. Basica | H61: =+'Gantt Proyectos'!AD147 -> No Asignado | I61: 0.1 | J61: 1
C62: =+'Gantt Proyectos'!D148 -> Conceptual Chalcobamba UG | D62: =+'Gantt Proyectos'!E148 -> Las Bambas | E62: =+'Gantt Proyectos'!F148 -> Perú | F62: =+'Gantt Proyectos'!L148 -> 91000 | G62: =+'Gantt Proyectos'!AC148 -> Estudio Conceptual / LOM | H62: =+'Gantt Proyectos'!AD148 -> Asignado | I62: 1 | J62: 1
C63: =+'Gantt Proyectos'!D149 -> Ingeniería a nivel factibilidad de desarrollo y profundización de labores subterráneas segunda meiad | D63: =+'Gantt Proyectos'!E149 -> Cerro Pasco | E63: =+'Gantt Proyectos'!F149 -> Perú | F63: =+'Gantt Proyectos'!L149 -> 100000 | G63: =+'Gantt Proyectos'!AC149 -> FS e Ing. Basica | H63: =+'Gantt Proyectos'!AD149 -> Asignado | I63: 1 | J63: 1
C64: =+'Gantt Proyectos'!D150 -> Corto plazo | D64: =+'Gantt Proyectos'!E150 -> CMDIC | E64: =+'Gantt Proyectos'!F150 -> Chile | F64: =+'Gantt Proyectos'!L150 -> 120000 | G64: =+'Gantt Proyectos'!AC150 -> Estudio Conceptual / LOM | H64: =+'Gantt Proyectos'!AD150 -> No Asignado | I64: 0.3 | J64: 1
C65: =+'Gantt Proyectos'!D151 -> Corto plazo | D65: =+'Gantt Proyectos'!E151 -> AMSA | E65: =+'Gantt Proyectos'!F151 -> Chile | F65: =+'Gantt Proyectos'!L151 -> 120000 | G65: =+'Gantt Proyectos'!AC151 -> Estudio Conceptual / LOM | H65: =+'Gantt Proyectos'!AD151 -> No Asignado | I65: 0.3 | J65: 1 | DI65: # Proyectos | DJ65: Total | DK65: 45777 | DL65: 45807 | DM65: 45838 | DN65: 45868 | DO65: 45899 | DP65: 45930 | DQ65: 45960 | DR65: 45991 | DS65: 46021
C66: =+'Gantt Proyectos'!D152 -> Acompañamiento simplan Cajati | D66: =+'Gantt Proyectos'!E152 -> Mosaic | E66: =+'Gantt Proyectos'!F152 -> Brasil | F66: =+'Gantt Proyectos'!L152 -> 85000 | G66: =+'Gantt Proyectos'!AC152 -> Consultoria y Due Dilligence | H66: =+'Gantt Proyectos'!AD152 -> No Asignado | I66: 0.5 | J66: 1 | DI66: Actual | DJ66: =+AVERAGE(DL66:DS66) -> 7.25 | DK66: =+COUNTIFS('Gantt Proyectos'!AF$97:AF$1048576,">"&0,'Gantt Proyectos'!$AD$97:$AD$1048576,Dashboard!$DI66) -> 25 | DL66: =+COUNTIFS('Gantt Proyectos'!AG$97:AG$1048576,">"&0,'Gantt Proyectos'!$AD$97:$AD$1048576,Dashboard!$DI66) -> 20 | DM66: =+COUNTIFS('Gantt Proyectos'!AH$97:AH$1048576,">"&0,'Gantt Proyectos'!$AD$97:$AD$1048576,Dashboard!$DI66) -> 16 | DN66: =+COUNTIFS('Gantt Proyectos'!AI$97:AI$1048576,">"&0,'Gantt Proyectos'!$AD$97:$AD$1048576,Dashboard!$DI66) -> 10 | DO66: =+COUNTIFS('Gantt Proyectos'!AJ$97:AJ$1048576,">"&0,'Gantt Proyectos'!$AD$97:$AD$1048576,Dashboard!$DI66) -> 5 | DP66: =+COUNTIFS('Gantt Proyectos'!AK$97:AK$1048576,">"&0,'Gantt Proyectos'!$AD$97:$AD$1048576,Dashboard!$DI66) -> 2 | DQ66: =+COUNTIFS('Gantt Proyectos'!AL$97:AL$1048576,">"&0,'Gantt Proyectos'!$AD$97:$AD$1048576,Dashboard!$DI66) -> 2 | DR66: =+COUNTIFS('Gantt Proyectos'!AM$97:AM$1048576,">"&0,'Gantt Proyectos'!$AD$97:$AD$1048576,Dashboard!$DI66) -> 2 | DS66: =+COUNTIFS('Gantt Proyectos'!AN$97:AN$1048576,">"&0,'Gantt Proyectos'!$AD$97:$AD$1048576,Dashboard!$DI66) -> 1
C67: =+'Gantt Proyectos'!D153 -> Actualziación LOM | D67: =+'Gantt Proyectos'!E153 -> LHG | E67: =+'Gantt Proyectos'!F153 -> Brasil | F67: =+'Gantt Proyectos'!L153 -> 145000 | G67: =+'Gantt Proyectos'!AC153 -> Estudio Conceptual / LOM | H67: =+'Gantt Proyectos'!AD153 -> No Asignado | I67: 0.8 | J67: 1 | DI67: Asignado | DJ67: =+AVERAGE(DL67:DS67) -> 2.625 | DK67: =+COUNTIFS('Gantt Proyectos'!AF$97:AF$1048576,">"&0,'Gantt Proyectos'!$AD$97:$AD$1048576,Dashboard!$DI67) -> 0 | DL67: =+COUNTIFS('Gantt Proyectos'!AG$97:AG$1048576,">"&0,'Gantt Proyectos'!$AD$97:$AD$1048576,Dashboard!$DI67) -> 1 | DM67: =+COUNTIFS('Gantt Proyectos'!AH$97:AH$1048576,">"&0,'Gantt Proyectos'!$AD$97:$AD$1048576,Dashboard!$DI67) -> 2 | DN67: =+COUNTIFS('Gantt Proyectos'!AI$97:AI$1048576,">"&0,'Gantt Proyectos'!$AD$97:$AD$1048576,Dashboard!$DI67) -> 3 | DO67: =+COUNTIFS('Gantt Proyectos'!AJ$97:AJ$1048576,">"&0,'Gantt Proyectos'!$AD$97:$AD$1048576,Dashboard!$DI67) -> 4 | DP67: =+COUNTIFS('Gantt Proyectos'!AK$97:AK$1048576,">"&0,'Gantt Proyectos'!$AD$97:$AD$1048576,Dashboard!$DI67) -> 4 | DQ67: =+COUNTIFS('Gantt Proyectos'!AL$97:AL$1048576,">"&0,'Gantt Proyectos'!$AD$97:$AD$1048576,Dashboard!$DI67) -> 4 | DR67: =+COUNTIFS('Gantt Proyectos'!AM$97:AM$1048576,">"&0,'Gantt Proyectos'!$AD$97:$AD$1048576,Dashboard!$DI67) -> 2 | DS67: =+COUNTIFS('Gantt Proyectos'!AN$97:AN$1048576,">"&0,'Gantt Proyectos'!$AD$97:$AD$1048576,Dashboard!$DI67) -> 1
C68: =+'Gantt Proyectos'!D154 -> Alpayana Estudio de Sismicidad | D68: =+'Gantt Proyectos'!E154 -> Alpayana | E68: =+'Gantt Proyectos'!F154 -> Perú | F68: =+'Gantt Proyectos'!L154 -> 197494 | G68: =+'Gantt Proyectos'!AC154 -> Estudio Conceptual / LOM | H68: =+'Gantt Proyectos'!AD154 -> Asignado | I68: 1 | J68: 1 | DI68: No Asignado | DJ68: =+AVERAGE(DL68:DS68) -> 10.625 | DK68: =+COUNTIFS('Gantt Proyectos'!AF$97:AF$1048576,">"&0,'Gantt Proyectos'!$AD$97:$AD$1048576,Dashboard!$DI68) -> 0 | DL68: =+COUNTIFS('Gantt Proyectos'!AG$97:AG$1048576,">"&0,'Gantt Proyectos'!$AD$97:$AD$1048576,Dashboard!$DI68) -> 0 | DM68: =+COUNTIFS('Gantt Proyectos'!AH$97:AH$1048576,">"&0,'Gantt Proyectos'!$AD$97:$AD$1048576,Dashboard!$DI68) -> 3 | DN68: =+COUNTIFS('Gantt Proyectos'!AI$97:AI$1048576,">"&0,'Gantt Proyectos'!$AD$97:$AD$1048576,Dashboard!$DI68) -> 15 | DO68: =+COUNTIFS('Gantt Proyectos'!AJ$97:AJ$1048576,">"&0,'Gantt Proyectos'!$AD$97:$AD$1048576,Dashboard!$DI68) -> 19 | DP68: =+COUNTIFS('Gantt Proyectos'!AK$97:AK$1048576,">"&0,'Gantt Proyectos'!$AD$97:$AD$1048576,Dashboard!$DI68) -> 17 | DQ68: =+COUNTIFS('Gantt Proyectos'!AL$97:AL$1048576,">"&0,'Gantt Proyectos'!$AD$97:$AD$1048576,Dashboard!$DI68) -> 12 | DR68: =+COUNTIFS('Gantt Proyectos'!AM$97:AM$1048576,">"&0,'Gantt Proyectos'!$AD$97:$AD$1048576,Dashboard!$DI68) -> 11 | DS68: =+COUNTIFS('Gantt Proyectos'!AN$97:AN$1048576,">"&0,'Gantt Proyectos'!$AD$97:$AD$1048576,Dashboard!$DI68) -> 8
C69: =+'Gantt Proyectos'!D155 -> Vale Gongo Soco | D69: =+'Gantt Proyectos'!E155 -> Vale | E69: =+'Gantt Proyectos'!F155 -> Brasil | F69: =+'Gantt Proyectos'!L155 -> 475000 | G69: =+'Gantt Proyectos'!AC155 -> Scoping | H69: =+'Gantt Proyectos'!AD155 -> No Asignado | I69: 0.5 | J69: 1 | DI69: Total | DJ69: =+AVERAGE(DL69:DS69) -> 20.5 | DK69: =+SUM(DK66:DK68) -> 25 | DL69: =+SUM(DL66:DL68) -> 21 | DM69: =+SUM(DM66:DM68) -> 21 | DN69: =+SUM(DN66:DN68) -> 28 | DO69: =+SUM(DO66:DO68) -> 28 | DP69: =+SUM(DP66:DP68) -> 23 | DQ69: =+SUM(DQ66:DQ68) -> 18 | DR69: =+SUM(DR66:DR68) -> 15 | DS69: =+SUM(DS66:DS68) -> 10
DH74: 3. Sobrecarga Personal (Módulos)
DI77: # Modulos Requeridos | DJ77: Total | DK77: 45777 | DL77: 45807 | DM77: 45838 | DN77: 45868 | DO77: 45899 | DP77: 45930 | DQ77: 45960 | DR77: 45991 | DS77: 46021
DI78: Actual | DJ78: =+AVERAGE(DL78:DS78) -> 9.4449105 | DK78: =+COUNTIFS('Gantt Proyectos'!AF$97:AF$1048576,">"&0,'Gantt Proyectos'!$AD$97:$AD$1048576,Dashboard!$DI78) -> 25 | DL78: =+'Gantt Proyectos'!AG11 -> 24.946309 | DM78: =+'Gantt Proyectos'!AH11 -> 21.525727 | DN78: =+'Gantt Proyectos'!AI11 -> 13.639821 | DO78: =+'Gantt Proyectos'!AJ11 -> 5.3154362 | DP78: =+'Gantt Proyectos'!AK11 -> 2.8948546 | DQ78: =+'Gantt Proyectos'!AL11 -> 2.8948546 | DR78: =+'Gantt Proyectos'!AM11 -> 2.8948546 | DS78: =+'Gantt Proyectos'!AN11 -> 1.4474273
DI79: Asignado | DJ79: =+AVERAGE(DL79:DS79) -> 4.2483221 | DK79: =+COUNTIFS('Gantt Proyectos'!AF$97:AF$1048576,">"&0,'Gantt Proyectos'!$AD$97:$AD$1048576,Dashboard!$DI79) -> 0 | DL79: =+'Gantt Proyectos'!AG13-'Gantt Proyectos'!AG11 -> 1 | DM79: =+'Gantt Proyectos'!AH13-'Gantt Proyectos'!AH11 -> 1.7203579 | DN79: =+'Gantt Proyectos'!AI13-'Gantt Proyectos'!AI11 -> 5.8210291 | DO79: =+'Gantt Proyectos'!AJ13-'Gantt Proyectos'!AJ11 -> 6.541387 | DP79: =+'Gantt Proyectos'!AK13-'Gantt Proyectos'!AK11 -> 6.541387 | DQ79: =+'Gantt Proyectos'!AL13-'Gantt Proyectos'!AL11 -> 6.541387 | DR79: =+'Gantt Proyectos'!AM13-'Gantt Proyectos'!AM11 -> 3.2706935 | DS79: =+'Gantt Proyectos'!AN13-'Gantt Proyectos'!AN11 -> 2.5503356
DI80: No Asignado | DJ80: =+AVERAGE(DL80:DS80) -> 4.946071 | DK80: =+COUNTIFS('Gantt Proyectos'!AF$97:AF$1048576,">"&0,'Gantt Proyectos'!$AD$97:$AD$1048576,Dashboard!$DI80) -> 0 | DL80: =+'Gantt Proyectos'!AG15-'Gantt Proyectos'!AG13 -> 0 | DM80: =+'Gantt Proyectos'!AH15-'Gantt Proyectos'!AH13 -> 0.24474273 | DN80: =+'Gantt Proyectos'!AI15-'Gantt Proyectos'!AI13 -> 6.8237136 | DO80: =+'Gantt Proyectos'!AJ15-'Gantt Proyectos'!AJ13 -> 8.3024609 | DP80: =+'Gantt Proyectos'!AK15-'Gantt Proyectos'!AK13 -> 8.0853468 | DQ80: =+'Gantt Proyectos'!AL15-'Gantt Proyectos'!AL13 -> 6.1268456 | DR80: =+'Gantt Proyectos'!AM15-'Gantt Proyectos'!AM13 -> 5.6268456 | DS80: =+'Gantt Proyectos'!AN15-'Gantt Proyectos'!AN13 -> 4.358613
DI81: Total | DJ81: =+AVERAGE(DL81:DS81) -> 18.639304 | DK81: =+SUM(DK78:DK80) -> 25 | DL81: =+SUM(DL78:DL80) -> 25.946309 | DM81: =+SUM(DM78:DM80) -> 23.490828 | DN81: =+SUM(DN78:DN80) -> 26.284564 | DO81: =+SUM(DO78:DO80) -> 20.159284 | DP81: =+SUM(DP78:DP80) -> 17.521588 | DQ81: =+SUM(DQ78:DQ80) -> 15.563087 | DR81: =+SUM(DR78:DR80) -> 11.792394 | DS81: =+SUM(DS78:DS80) -> 8.3563758
DI83: Personal Ingeniería | DJ83: Promedio | DK83: 45777 | DL83: 45807 | DM83: 45838 | DN83: 45868 | DO83: 45899 | DP83: 45930 | DQ83: 45960 | DR83: 45991 | DS83: 46021
DI84: Director de Proyecto | DJ84: =+AVERAGE(DL84:DS84) -> 7 | DK84: =+COUNTIFS('Gantt Proyectos'!AF$97:AF$1048576,">"&0,'Gantt Proyectos'!$AD$97:$AD$1048576,Dashboard!$DI84) -> 0 | DL84: {=+TRANSPOSE(Q12:U19)} -> 7 | DM84: 7 | DN84: 7 | DO84: 7 | DP84: 7 | DQ84: 7 | DR84: 7 | DS84: 7
DI85: Ingeniero Principal | DJ85: =+AVERAGE(DL85:DS85) -> 8 | DL85: 8 | DM85: 8 | DN85: 8 | DO85: 8 | DP85: 8 | DQ85: 8 | DR85: 8 | DS85: 8
DI86: Ingeniero Senior | DJ86: =+AVERAGE(DL86:DS86) -> 12 | DL86: 12 | DM86: 12 | DN86: 12 | DO86: 12 | DP86: 12 | DQ86: 12 | DR86: 12 | DS86: 12
DI87: Ingeniero de Proyecto | DJ87: =+AVERAGE(DL87:DS87) -> 21 | DK87: =+COUNTIFS('Gantt Proyectos'!AF$97:AF$1048576,">"&0,'Gantt Proyectos'!$AD$97:$AD$1048576,Dashboard!$DI87) -> 0 | DL87: 21 | DM87: 21 | DN87: 21 | DO87: 21 | DP87: 21 | DQ87: 21 | DR87: 21 | DS87: 21
DI88: Ingeniero Junior | DJ88: =+AVERAGE(DL88:DS88) -> 13 | DK88: =+COUNTIFS('Gantt Proyectos'!AF$97:AF$1048576,">"&0,'Gantt Proyectos'!$AD$97:$AD$1048576,Dashboard!$DI88) -> 0 | DL88: 13 | DM88: 13 | DN88: 13 | DO88: 13 | DP88: 13 | DQ88: 13 | DR88: 13 | DS88: 13
DI89: Total | DJ89: =+AVERAGE(DL89:DS89) -> 61 | DK89: =+SUM(DK84:DK88) -> 0 | DL89: =+SUM(DL84:DL88) -> 61 | DM89: =+SUM(DM84:DM88) -> 61 | DN89: =+SUM(DN84:DN88) -> 61 | DO89: =+SUM(DO84:DO88) -> 61 | DP89: =+SUM(DP84:DP88) -> 61 | DQ89: =+SUM(DQ84:DQ88) -> 61 | DR89: =+SUM(DR84:DR88) -> 61 | DS89: =+SUM(DS84:DS88) -> 61
DI90: Modulos Actuales | DJ90: =+AVERAGE(DL90:DS90) -> 26.666667 | DK90: =+SUM(DK85:DK89) -> 0 | DL90: =+AVERAGE(DL84*'Listas y Parametros'!$Q$39,'Listas y Parametros'!$Q$40*Dashboard!DL85,'Listas y Parametros'!$Q$42*Dashboard!DL87) -> 26.666667 | DM90: =+AVERAGE(DM84*'Listas y Parametros'!$Q$39,'Listas y Parametros'!$Q$40*Dashboard!DM85,'Listas y Parametros'!$Q$42*Dashboard!DM87) -> 26.666667 | DN90: =+AVERAGE(DN84*'Listas y Parametros'!$Q$39,'Listas y Parametros'!$Q$40*Dashboard!DN85,'Listas y Parametros'!$Q$42*Dashboard!DN87) -> 26.666667 | DO90: =+AVERAGE(DO84*'Listas y Parametros'!$Q$39,'Listas y Parametros'!$Q$40*Dashboard!DO85,'Listas y Parametros'!$Q$42*Dashboard!DO87) -> 26.666667 | DP90: =+AVERAGE(DP84*'Listas y Parametros'!$Q$39,'Listas y Parametros'!$Q$40*Dashboard!DP85,'Listas y Parametros'!$Q$42*Dashboard!DP87) -> 26.666667 | DQ90: =+AVERAGE(DQ84*'Listas y Parametros'!$Q$39,'Listas y Parametros'!$Q$40*Dashboard!DQ85,'Listas y Parametros'!$Q$42*Dashboard!DQ87) -> 26.666667 | DR90: =+AVERAGE(DR84*'Listas y Parametros'!$Q$39,'Listas y Parametros'!$Q$40*Dashboard!DR85,'Listas y Parametros'!$Q$42*Dashboard!DR87) -> 26.666667 | DS90: =+AVERAGE(DS84*'Listas y Parametros'!$Q$39,'Listas y Parametros'!$Q$40*Dashboard!DS85,'Listas y Parametros'!$Q$42*Dashboard!DS87) -> 26.666667
DI91: Sobrecarga | DJ91: =+AVERAGE(DL91:DS91) -> 0.69897389 | DK91: =+SUM(DK86:DK90) -> 0 | DL91: =+DL81/DL90 -> 0.97298658 | DM91: =+DM81/DM90 -> 0.88090604 | DN91: =+DN81/DN90 -> 0.98567114 | DO91: =+DO81/DO90 -> 0.75597315 | DP91: =+DP81/DP90 -> 0.65705956 | DQ91: =+DQ81/DQ90 -> 0.58361577 | DR91: =+DR81/DR90 -> 0.44221477 | DS91: =+DS81/DS90 -> 0.31336409

Sheet Calculos ->

Sheet Hoja2
A3: Cuenta de # | B3: Etiquetas de columna
A4: Etiquetas de fila | B4: Brasil | C4: Chile | D4: Perú | E4: USA | F4: Total general
A5: Aseo y Ornato | C5: 1 | F5: 1
A6: Consultor Administración
A7: Alberto Reinao | C7: 1 | F7: 1
A8: Contabilidad y Administración
A9: Isabel Marchant | C9: 1 | F9: 1
A10: Country Manager
A11: Eduardo Lama | D11: 1 | F11: 1
A12: Country Manager Brasil
A13: Isabela Camisassa | B13: 1 | F13: 1
A14: Country Manager Rusia
A15: Olesya Dashavskaya | C15: 1 | F15: 1
A16: Country Manager USA
A17: Patricio Vergara | E17: 1 | F17: 1
A18: Desarrollo de Negocios
A19: Maria Celia Fonseca | B19: 1 | F19: 1
A20: Director de Proyecto
A21: Alex Figueroa | C21: 1 | F21: 1
A22: Carolina Arcos | C22: 1 | F22: 1
A23: Claudio Hernandez | C23: 1 | F23: 1
A24: Felipe Rojas | C24: 1 | F24: 1
A25: Gonzalo Díaz | C25: 1 | F25: 1
A26: Ricardo Miranda | C26: 1 | F26: 1
A27: Ronald Leal | B27: 1 | F27: 1
A28: Gerente Comercial
A29: Rodrigo Valdes | C29: 1 | F29: 1
A30: Gerente General
A31: Enrique Rubio | C31: 1 | F31: 1
A32: Gerentes
A33: Christian Caviedes | C33: 1 | F33: 1
A34: Matias Fuentes | C34: 1 | F34: 1
A35: Ingeniero de Proyecto
A36: Arnold Tadeo | D36: 1 | F36: 1
A37: Cristian Alarcon | C37: 1 | F37: 1
A38: Cristobal Ventura | C38: 1 | F38: 1
A39: Daniela Oyarzo | C39: 1 | F39: 1
A40: Darwin Varas | C40: 1 | F40: 1
A41: Diego Muñoz | C41: 1 | F41: 1
A42: Edward Torres | D42: 1 | F42: 1
A43: Erick Sanhueza | C43: 1 | F43: 1
A44: Gino Espinoza | D44: 1 | F44: 1
A45: Isidora Figueroa | C45: 1 | F45: 1
A46: Jarold Orna | D46: 1 | F46: 1
A47: Jhonatan Huaynate | D47: 1 | F47: 1
A48: José Pizarro | C48: 1 | F48: 1
A49: Luis Chumpitaz | D49: 1 | F49: 1
A50: Marcelo Mendoza | C50: 1 | F50: 1
A51: Martin Figueroa | C51: 1 | F51: 1
A52: Mateo Villanueva | D52: 1 | F52: 1
A53: Matías Cid | C53: 1 | F53: 1
A54: Nicolás Sanzana | C54: 1 | F54: 1
A55: Victor Mohana | C55: 1 | F55: 1
A56: Walter Lupinta | D56: 1 | F56: 1
A57: Ingeniero Desarrollo de Negocios
A58: Alejandra Montalvan | D58: 1 | F58: 1
A59: Vicente Jimenez | C59: 1 | F59: 1
A60: Ingeniero Junior
A61: Benjamin Baeza | C61: 1 | F61: 1
A62: Cristobal Concha | C62: 1 | F62: 1
A63: Cristobal Poblete | C63: 1 | F63: 1
A64: Eduardo Cepeda | C64: 1 | F64: 1
A65: Gabriel Ojeda | C65: 1 | F65: 1
A66: Heidi La Rosa | D66: 1 | F66: 1
A67: Javier Salazar | C67: 1 | F67: 1
A68: Jhosep Livia | D68: 1 | F68: 1
A69: Manuel Palomino | D69: 1 | F69: 1
A70: Maria Huaman | D70: 1 | F70: 1
A71: Matias Guerrero | C71: 1 | F71: 1
A72: Mauricio Peralta | C72: 1 | F72: 1
A73: Nikolai Quispe | D73: 1 | F73: 1
A74: Ingeniero P&C
A75: Eduardo Cuevas | C75: 1 | F75: 1
A76: Roxana Avilés | C76: 1 | F76: 1
A77: Victor Arias | D77: 1 | F77: 1
A78: Ingeniero Principal
A79: Eduardo Morales | C79: 1 | F79: 1
A80: Freddy Díaz | C80: 1 | F80: 1
A81: Gerson Alfaro | C81: 1 | F81: 1
A82: Jorman Barrera | D82: 1 | F82: 1
A83: Kevin Rios | D83: 1 | F83: 1
A84: Nicolas Ayarza | C84: 1 | F84: 1
A85: Pablo Quiero | C85: 1 | F85: 1
A86: Rodrigo Baez | C86: 1 | F86: 1
A87: Ingeniero Senior
A88: Alex Pacheco | C88: 1 | F88: 1
A89: Carlos Catalan | D89: 1 | F89: 1
A90: Claudio Delgado | C90: 1 | F90: 1
A91: Emilio Sanchez | C91: 1 | F91: 1
A92: Felipe Lira | C92: 1 | F92: 1
A93: German Soto | C93: 1 | F93: 1
A94: Johnny Pacheco | D94: 1 | F94: 1
A95: Juan de Vera | C95: 1 | F95: 1
A96: Leonel Robledo | C96: 1 | F96: 1
A97: Renan Argandoña | C97: 1 | F97: 1
A98: Rodrigo Andrae | C98: 1 | F98: 1
A99: Rodrigo Cori | D99: 1 | F99: 1
A100: Jefa Administración
A101: Carol Valdenegro | C101: 1 | F101: 1
A102: Socio Consultor REDCO Brasil
...

Sheet Listas y Parametros
D3: Modelo de Flujo REDCO
D4: 2025
D5: Listas y Parametros Modificables
A11: Listas
B13: Status General | C13: Status Especifico | D13: Pais | E13: Tipo Mineria | F13: Tipo de Estudio | G13: Terceros | H13: Meses 2025
B14: Actual | C14: 7. Finalizado | D14: Chile | E14: Open Pit | F14: Estudio Conceptual / LOM | G14: Si | H14: 45777
B15: Asignado | C15: 6. Cierre: +90% | D15: Perú | E15: Subterránea | F15: Confiabilidad Planes | G15: No | H15: 45807
B16: No Asignado | C16: 5. Avance: 75% | D16: Brasil | E16: Geomecánica | F16: Scoping | H16: 45838
C17: 4. Avance: 50% | D17: USA | F17: PFS | H17: 45868
C18: 3. Avance: 25% | D18: Otros | F18: FS e Ing. Basica | H18: 45899
C19: 2. KOM | F19: Permisos / MEIA | H19: 45930
C20: 1. Proyectado: Asignado | F20: Consultoria y Due Dilligence | H20: 45960
C21: 1. Proyectado: No Asignado | F21: PEA | H21: 45991
H22: 46021
A30: Parametros
A32: Modulo + Costos
B33: Dado el tipo de estudio, me indica el nivel de participación de cada tipo de cargo
C35: PEA | D35: Scoping | E35: PFS | F35: FS e Ing. Basica | G35: Confiabilidad Planes | H35: Geomecanica | I35: Estudio Conceptual / LOM | J35: Turn Around | K35: Consultoria y Due Dilligence | L35: Permisos / MEIA
B36: Gerente | C36: 0.075 | D36: 0.075 | E36: 0.075 | F36: 0.03 | G36: 0.03 | H36: 0.03 | I36: 0.03 | J36: 0.075 | K36: 0.075 | L36: 0.03 | Q36: Maxima Cantidad de Proyectos Abordables | R36: Personal Actual | S36: Max Proyectos | T36: % Ut Modulos
B37: Consultor | P37: Gerente | Q37: 15 | R37: =+Q81 -> 2 | S37: =+R37*Q37 -> 30
B38: Director de Proyecto | C38: 0.33 | D38: 0.33 | E38: 0.5 | F38: 0.5 | G38: 0.25 | H38: 0.25 | I38: 0.25 | J38: 0.5 | K38: 0.33 | L38: 0.33 | P38: Consultor
B39: Ingeniero Principal | C39: 0.5 | D39: 0.5 | E39: 0.5 | F39: 0.67 | G39: 0.33 | H39: 0.33 | I39: 0.33 | J39: 0.5 | K39: 0.5 | L39: 0.33 | P39: Director de Proyecto | Q39: 3.5 | R39: =+Q82 -> 7 | S39: =+R39*Q39 -> 24.5 | T39: =+K38*R39 -> 2.31
B40: Ingeniero Senior | C40: 0.33 | D40: 0.33 | E40: 0.75 | F40: 1 | J40: 0.5 | K40: 0.33 | L40: 0.5 | P40: Ingeniero Principal | Q40: 3 | R40: =+Q83 -> 8 | S40: =+R40*Q40 -> 24 | T40: =+K39*R40 -> 4
B41: Ingeniero de Proyecto | C41: 1 | D41: 1 | E41: 2 | F41: 2.5 | G41: 0.5 | H41: 0.5 | I41: 0.5 | J41: 1 | K41: 1 | L41: 1 | P41: Ingeniero Senior | Q41: 4 | R41: =+Q84 -> 12 | S41: =+R41*Q41 -> 48 | T41: =+K40*R41 -> 3.96
B42: Ingeniero Junior | C42: 1 | D42: 1 | E42: 1 | F42: 1 | G42: 0.5 | H42: 0.5 | I42: 0.5 | P42: Ingeniero de Proyecto | Q42: 1.5 | R42: =+Q85 -> 21 | S42: =+R42*Q42 -> 31.5 | T42: =+K41*R42 -> 21
C43: 3.235 | D43: 3.235 | E43: 4.825 | F43: 5.7 | G43: 1.61 | H43: 1.61 | I43: 1.61 | J43: 2.575 | K43: 2.235 | L43: 2.19 | P43: Ingeniero Junior | Q43: 1 | R43: =+Q86 -> 13 | S43: =+R43*Q43 -> 13 | T43: =+K41*R43 -> 13
B44: Modulo | C44: 1.4474273 | D44: 1.4474273 | E44: 2.1588367 | F44: 2.5503356 | G44: 0.72035794 | H44: 0.72035794 | I44: 0.72035794 | J44: 1.1521253 | K44: 1 | L44: 0.97986577 | S44: =+AVERAGE(S39:S40,S42) -> 26.666667 | T44: =+SUM(T39:T43)/K43 -> 19.807606
B45: Costo | C45: 22950.645 | D45: 22950.645 | E45: 35650.483 | F45: 42832.247 | G45: 11999.746 | H45: 11999.746 | I45: 11999.746 | J45: 23766.989 | K45: 19463.097 | L45: 19375.263 | N45: =80000*8 -> 640000
B46: EDP Mínimo | C46: 35000 | D46: 35000 | E46: 75559.284 | F46: 89261.745 | G46: 25000 | H46: 25000 | I46: 25000 | J46: 40324.385 | K46: 35000 | L46: 35000 | M46: 42014.541
B47: Rentabilidad Mínima Esperada | C47: 0.3442673 | D47: 0.3442673 | E47: 0.52817865 | F47: 0.52015001 | G47: 0.52001016 | H47: 0.52001016 | I47: 0.52001016 | J47: 0.41060505 | K47: 0.44391151 | L47: 0.44642107
A48: Cantidad Actual | B48: # personal | C48: PEA | D48: Scoping | E48: PFS | F48: FS e Ing. Basica | G48: Confiabilidad Planes | H48: Geomecanica | I48: Estudio Conceptual / LOM | J48: Turn Around | K48: Consultoria y Due Dilligence | L48: Permisos | M48: Costo Base | N48: Costo Total
A49: Gerente | B49: 1.5 | C49: 20 | D49: 20 | E49: 20 | F49: 50 | G49: 50 | H49: 50 | I49: 50 | J49: 20 | K49: 20 | L49: 50 | M49: 8000 | N49: 19812
A50: Consultor | B50: 3 | C50: 0 | D50: 0 | E50: 0 | F50: 0 | G50: 0 | H50: 0 | I50: 0 | J50: 0 | K50: 0 | L50: 0 | M50: 10000 | N50: 49530
A51: Director de Proyecto | B51: 6 | C51: 18.181818 | D51: 18.181818 | E51: 12 | F51: 12 | G51: 24 | H51: 24 | I51: 24 | J51: 12 | K51: 18.181818 | L51: 18.181818 | M51: 6000 | N51: 59436
A52: Ingeniero Principal | B52: 8 | C52: 16 | D52: 16 | E52: 16 | F52: 11.940299 | G52: 24.242424 | H52: 24.242424 | I52: 24.242424 | J52: 16 | K52: 16 | L52: 24.242424 | M52: 4000 | N52: 52832
A53: Ingeniero Senior | B53: 7 | C53: 21.212121 | D53: 21.212121 | E53: 9.3333333 | F53: 7 | G53: 0 | H53: 0 | I53: 0 | J53: 14 | K53: 21.212121 | L53: 14 | M53: 3800 | N53: 43916.6
A54: Ingeniero de Proyecto | B54: 19 | C54: 19 | D54: 19 | E54: 9.5 | F54: 7.6 | G54: 38 | H54: 38 | I54: 38 | J54: 19 | K54: 19 | L54: 19 | M54: 2300 | N54: 72148.7
A55: Ingeniero Junior | B55: 6 | C55: 6 | D55: 6 | E55: 6 | F55: 6 | G55: 12 | H55: 12 | I55: 12 | J55: 0 | K55: 0 | L55: 0 | M55: 1350 | N55: 13373.1
B56: Personal Clave | C56: Ingeniero Junior | D56: Ingeniero Junior | E56: Ingeniero Junior | F56: Ingeniero Junior | G56: Ingeniero Junior | H56: Ingeniero Junior | I56: Ingeniero Junior | J56: Director de Proyecto | K56: Ingeniero Principal | L56: Ingeniero Senior | N56: 241706.4
B57: Max Cantidad de proyectos | C57: 6 | D57: 6 | E57: 6 | F57: 6 | G57: 12 | H57: 12 | I57: 12 | J57: 12 | K57: 16 | L57: 14
A60: Costos por Personal
G61: 1.28 | U61: Vectorizacion Temporal Costos
V62: 10 | W62: 11 | X62: 12 | Y62: 13 | Z62: 14 | AA62: 15 | AB62: 16 | AC62: 17 | AD62: 18
A63: # | B63: Personal | C63: Cargo | D63: Empresa | E63: País | F63: Tipo de Contrato | G63: Costo Empresa | H63: Gerencia | K63: Costo Real | L63: Chile | M63: Perú | N63: Brasil | O63: USA | P63: Otros | Q63: Total | T63: Chile | U63: Cantidad | V63: 45777 | W63: 45807 | X63: 45838 | Y63: 45868 | Z63: 45899 | AA63: 45930 | AB63: 45960 | AC63: 45991 | AD63: 46021
A64: 1 | B64: Isabela Camisassa | C64: Country Manager Brasil | D64: REDCO | E64: Brasil | F64: Indefinido | G64: 4270 | H64: Gerencia General (incluye RRHH) | K64: Gerencia General (incluye RRHH) | L64: =+SUMIFS($G$64:$G$147,$H$64:$H$147,$K64,$E$64:$E$147,L$63) -> 23284.633 | M64: =+SUMIFS($G$64:$G$147,$H$64:$H$147,$K64,$E$64:$E$147,M$63) -> 3285.76 | N64: =+SUMIFS($G$64:$G$147,$H$64:$H$147,$K64,$E$64:$E$147,N$63) -> 8920 | O64: =+SUMIFS($G$64:$G$147,$H$64:$H$147,$K64,$E$64:$E$147,O$63) -> 25000 | P64: =+SUMIFS($G$64:$G$147,$H$64:$H$147,$K64,$E$64:$E$147,P$63) -> 0 | Q64: =+SUM(L64:P64) -> 60490.393 | U64: Gerencia General (incluye RRHH) | V64: {=+$L$92:$L$102*TRANSPOSE(Dashboard!$AA$11:$AK$11)} -> 23284.633 | W64: {=+$L$92:$L$102*TRANSPOSE(Dashboard!$AA$12:$AK$12)} -> 23284.633 | X64: {=+$L$92:$L$102*TRANSPOSE(Dashboard!$AA$13:$AK$13)} -> 23284.633 | Y64: {=+$L$92:$L$102*TRANSPOSE(Dashboard!$AA$14:$AK$14)} -> 23284.633 | Z64: {=+$L$92:$L$102*TRANSPOSE(Dashboard!$AA$15:$AK$15)} -> 23284.633 | AA64: {=+$L$92:$L$102*TRANSPOSE(Dashboard!$AA$16:$AK$16)} -> 23284.633 | AB64: {=+$L$92:$L$102*TRANSPOSE(Dashboard!$AA$17:$AK$17)} -> 23284.633 | AC64: {=+$L$92:$L$102*TRANSPOSE(Dashboard!$AA$18:$AK$18)} -> 23284.633 | AD64: {=+$L$92:$L$102*TRANSPOSE(Dashboard!$AA$19:$AK$19)} -> 23284.633
A65: 2 | B65: Maria Celia Fonseca | C65: Desarrollo de Negocios | D65: REDCO | E65: Brasil | F65: Indefinido | G65: 1100 | H65: Gerencia Contabilidad y Administracion | K65: Gerencia Comercial | L65: =+SUMIFS($G$64:$G$147,$H$64:$H$147,$K65,$E$64:$E$147,L$63) -> 14221.74 | M65: =+SUMIFS($G$64:$G$147,$H$64:$H$147,$K65,$E$64:$E$147,M$63) -> 1000 | N65: =+SUMIFS($G$64:$G$147,$H$64:$H$147,$K65,$E$64:$E$147,N$63) -> 0 | O65: =+SUMIFS($G$64:$G$147,$H$64:$H$147,$K65,$E$64:$E$147,O$63) -> 0 | P65: =+SUMIFS($G$64:$G$147,$H$64:$H$147,$K65,$E$64:$E$147,P$63) -> 0 | Q65: =+SUM(L65:P65) -> 15221.74 | U65: Gerencia Comercial | V65: 14221.74 | W65: 14221.74 | X65: 14221.74 | Y65: 14221.74 | Z65: 14221.74 | AA65: 14221.74 | AB65: 14221.74 | AC65: 14221.74 | AD65: 14221.74
A66: 3 | B66: Ronald Leal | C66: Director de Proyecto | D66: REDCO | E66: Brasil | F66: Indefinido | G66: 3700 | K66: Gerencia Ingeniera | L66: =+SUM(L67:L73) -> 205941.1 | M66: =+SUM(M67:M73) -> 40862.88 | N66: =+SUM(N67:N73) -> 3700 | O66: =+SUM(O67:O73) -> 0 | P66: =+SUM(P67:P73) -> 0 | Q66: =+SUM(Q67:Q73) -> 250503.98 | U66: Gerencia Ingeniera | V66: 205941.1 | W66: 205941.1 | X66: 205941.1 | Y66: 205941.1 | Z66: 205941.1 | AA66: 205941.1 | AB66: 205941.1 | AC66: 205941.1 | AD66: 205941.1
A67: 4 | B67: Antonio Schettino | C67: Socio Consultor REDCO Brasil | D67: REDCO | E67: Brasil | F67: - | G67: 4650 | H67: Gerencia General (incluye RRHH) | K67: Gerentes | L67: =+SUMIFS($G$64:$G$147,$C$64:$C$147,$K67,$E$64:$E$147,L$63) -> 27445 | M67: =+SUMIFS($G$64:$G$147,$C$64:$C$147,$K67,$E$64:$E$147,M$63) -> 0 | N67: =+SUMIFS($G$64:$G$147,$C$64:$C$147,$K67,$E$64:$E$147,N$63) -> 0 | O67: =+SUMIFS($G$64:$G$147,$C$64:$C$147,$K67,$E$64:$E$147,O$63) -> 0 | P67: =+SUMIFS($G$64:$G$147,$C$64:$C$147,$K67,$E$64:$E$147,P$63) -> 0 | Q67: =+SUM(L67:P67) -> 27445 | U67: Gerentes | V67: 27445 | W67: 27445 | X67: 27445 | Y67: 27445 | Z67: 27445 | AA67: 27445 | AB67: 27445 | AC67: 27445 | AD67: 27445
A68: 5 | B68: Enrique Rubio | C68: Gerente General | D68: REDCO | E68: Chile | F68: Indefinido | G68: 18628.633 | H68: Gerencia General (incluye RRHH) | K68: Director de Proyecto | L68: =+SUMIFS($G$64:$G$147,$C$64:$C$147,$K68,$E$64:$E$147,L$63) -> 53592 | M68: =+SUMIFS($G$64:$G$147,$C$64:$C$147,$K68,$E$64:$E$147,M$63) -> 0 | N68: =+SUMIFS($G$64:$G$147,$C$64:$C$147,$K68,$E$64:$E$147,N$63) -> 3700 | O68: =+SUMIFS($G$64:$G$147,$C$64:$C$147,$K68,$E$64:$E$147,O$63) -> 0 | P68: =+SUMIFS($G$64:$G$147,$C$64:$C$147,$K68,$E$64:$E$147,P$63) -> 0 | Q68: =+SUM(L68:P68) -> 57292 | U68: Director de Proyecto | V68: 53592 | W68: 53592 | X68: 53592 | Y68: 53592 | Z68: 53592 | AA68: 53592 | AB68: 53592 | AC68: 53592 | AD68: 53592
A69: 6 | B69: Gladys Muñoz | C69: Aseo y Ornato | D69: REDCO | E69: Chile | F69: Indefinido | G69: 1061 | H69: Gerencia Contabilidad y Administracion | K69: Ingeniero Principal | L69: =+SUMIFS($G$64:$G$147,$C$64:$C$147,$K69,$E$64:$E$147,L$63) -> 35924 | M69: =+SUMIFS($G$64:$G$147,$C$64:$C$147,$K69,$E$64:$E$147,M$63) -> 8093.44 | N69: =+SUMIFS($G$64:$G$147,$C$64:$C$147,$K69,$E$64:$E$147,N$63) -> 0 | O69: =+SUMIFS($G$64:$G$147,$C$64:$C$147,$K69,$E$64:$E$147,O$63) -> 0 | P69: =+SUMIFS($G$64:$G$147,$C$64:$C$147,$K69,$E$64:$E$147,P$63) -> 0 | Q69: =+SUM(L69:P69) -> 44017.44 | U69: Ingeniero Principal | V69: 35924 | W69: 35924 | X69: 35924 | Y69: 35924 | Z69: 35924 | AA69: 35924 | AB69: 35924 | AC69: 35924 | AD69: 35924
A70: 7 | B70: Renan Argandoña | C70: Ingeniero Senior | D70: REDCO | E70: Chile | F70: Honorarios | G70: 4858 | K70: Ingeniero Senior | L70: =+SUMIFS($G$64:$G$147,$C$64:$C$147,$K70,$E$64:$E$147,L$63) -> 41260 | M70: =+SUMIFS($G$64:$G$147,$C$64:$C$147,$K70,$E$64:$E$147,M$63) -> 13081.6 | N70: =+SUMIFS($G$64:$G$147,$C$64:$C$147,$K70,$E$64:$E$147,N$63) -> 0 | O70: =+SUMIFS($G$64:$G$147,$C$64:$C$147,$K70,$E$64:$E$147,O$63) -> 0 | P70: =+SUMIFS($G$64:$G$147,$C$64:$C$147,$K70,$E$64:$E$147,P$63) -> 0 | Q70: =+SUM(L70:P70) -> 54341.6 | U70: Ingeniero Senior | V70: 41260 | W70: 41260 | X70: 41260 | Y70: 41260 | Z70: 41260 | AA70: 41260 | AB70: 41260 | AC70: 41260 | AD70: 41260
A71: 8 | B71: Isabel Marchant | C71: Contabilidad y Administración | D71: REDCO | E71: Chile | F71: Indefinido | G71: 3466 | H71: Gerencia Contabilidad y Administracion | K71: Ingeniero de Proyecto | L71: =+SUMIFS($G$64:$G$147,$C$64:$C$147,$K71,$E$64:$E$147,L$63) -> 28119.735 | M71: =+SUMIFS($G$64:$G$147,$C$64:$C$147,$K71,$E$64:$E$147,M$63) -> 12935.68 | N71: =+SUMIFS($G$64:$G$147,$C$64:$C$147,$K71,$E$64:$E$147,N$63) -> 0 | O71: =+SUMIFS($G$64:$G$147,$C$64:$C$147,$K71,$E$64:$E$147,O$63) -> 0 | P71: =+SUMIFS($G$64:$G$147,$C$64:$C$147,$K71,$E$64:$E$147,P$63) -> 0 | Q71: =+SUM(L71:P71) -> 41055.415 | U71: Ingeniero de Proyecto | V71: 28119.735 | W71: 28119.735 | X71: 28119.735 | Y71: 28119.735 | Z71: 28119.735 | AA71: 28119.735 | AB71: 28119.735 | AC71: 28119.735 | AD71: 28119.735
A72: 9 | B72: Alex Figueroa | C72: Director de Proyecto | D72: REDCO | E72: Chile | F72: Indefinido | G72: 8820 | K72: Ingeniero Junior | L72: =+SUMIFS($G$64:$G$147,$C$64:$C$147,$K72,$E$64:$E$147,L$63) -> 14065.366 | M72: =+SUMIFS($G$64:$G$147,$C$64:$C$147,$K72,$E$64:$E$147,M$63) -> 4243.36 | N72: =+SUMIFS($G$64:$G$147,$C$64:$C$147,$K72,$E$64:$E$147,N$63) -> 0 | O72: =+SUMIFS($G$64:$G$147,$C$64:$C$147,$K72,$E$64:$E$147,O$63) -> 0 | P72: =+SUMIFS($G$64:$G$147,$C$64:$C$147,$K72,$E$64:$E$147,P$63) -> 0 | Q72: =+SUM(L72:P72) -> 18308.726 | U72: Ingeniero Junior | V72: 14065.366 | W72: 14065.366 | X72: 14065.366 | Y72: 14065.366 | Z72: 14065.366 | AA72: 14065.366 | AB72: 14065.366 | AC72: 14065.366 | AD72: 14065.366
A73: 10 | B73: Carolina Arcos | C73: Director de Proyecto | D73: REDCO | E73: Chile | F73: Indefinido | G73: 7975 | K73: Ingeniero P&C | L73: =+SUMIFS($G$64:$G$147,$C$64:$C$147,$K73,$E$64:$E$147,L$63) -> 5535 | M73: =+SUMIFS($G$64:$G$147,$C$64:$C$147,$K73,$E$64:$E$147,M$63) -> 2508.8 | N73: =+SUMIFS($G$64:$G$147,$C$64:$C$147,$K73,$E$64:$E$147,N$63) -> 0 | O73: =+SUMIFS($G$64:$G$147,$C$64:$C$147,$K73,$E$64:$E$147,O$63) -> 0 | P73: =+SUMIFS($G$64:$G$147,$C$64:$C$147,$K73,$E$64:$E$147,P$63) -> 0 | Q73: =+SUM(L73:P73) -> 8043.8 | U73: Ingeniero P&C | V73: 5535 | W73: 5535 | X73: 5535 | Y73: 5535 | Z73: 5535 | AA73: 5535 | AB73: 5535 | AC73: 5535 | AD73: 5535
A74: 11 | B74: Claudio Hernandez | C74: Director de Proyecto | D74: REDCO | E74: Chile | F74: Indefinido | G74: 9514 | K74: Gerencia Contabilidad y Administracion | L74: =+SUMIFS($G$64:$G$147,$H$64:$H$147,$K74,$E$64:$E$147,L$63) -> 8318.9867 | M74: =+SUMIFS($G$64:$G$147,$H$64:$H$147,$K74,$E$64:$E$147,M$63) -> 0 | N74: =+SUMIFS($G$64:$G$147,$H$64:$H$147,$K74,$E$64:$E$147,N$63) -> 1100 | O74: =+SUMIFS($G$64:$G$147,$H$64:$H$147,$K74,$E$64:$E$147,O$63) -> 0 | P74: =+SUMIFS($G$64:$G$147,$H$64:$H$147,$K74,$E$64:$E$147,P$63) -> 0 | Q74: =+SUM(L74:P74) -> 9418.9867 | U74: Gerencia Contabilidad y Administracion | V74: 8318.9867 | W74: 8318.9867 | X74: 8318.9867 | Y74: 8318.9867 | Z74: 8318.9867 | AA74: 8318.9867 | AB74: 8318.9867 | AC74: 8318.9867 | AD74: 8318.9867
A75: 12 | B75: Felipe Rojas | C75: Director de Proyecto | D75: REDCO | E75: Chile | F75: Indefinido | G75: 7930 | K75: Bonificaciones | Q75: =+SUM(L75:P75) -> 0 | U75: Bonificaciones
A76: 13 | B76: Gonzalo Díaz | C76: Director de Proyecto | D76: REDCO | E76: Chile | F76: Honorarios | G76: 6000 | T76: Perú | U76: Cantidad | V76: 45777 | W76: 45807 | X76: 45838 | Y76: 45868 | Z76: 45899 | AA76: 45930 | AB76: 45960 | AC76: 45991 | AD76: 46021
A77: 14 | B77: Rodrigo Valdes | C77: Gerente Comercial | D77: REDCO | E77: Chile | F77: Indefinido | G77: 8666 | H77: Gerencia Comercial | K77: Cantidad | L77: Chile | M77: Perú | N77: Brasil | O77: USA | P77: Otros | Q77: Total | U77: Gerencia General (incluye RRHH) | V77: {=+$M$92:$M$102*TRANSPOSE(Dashboard!$AO$11:$AZ$11)} -> 3285.76 | W77: {=+$M$92:$M$102*TRANSPOSE(Dashboard!$AO$12:$AZ$12)} -> 3285.76 | X77: {=+$M$92:$M$102*TRANSPOSE(Dashboard!$AO$13:$AZ$13)} -> 3285.76 | Y77: {=+$M$92:$M$102*TRANSPOSE(Dashboard!$AO$14:$AZ$14)} -> 3285.76 | Z77: {=+$M$92:$M$102*TRANSPOSE(Dashboard!$AO$15:$AZ$15)} -> 3285.76 | AA77: {=+$M$92:$M$102*TRANSPOSE(Dashboard!$AO$16:$AZ$16)} -> 3285.76 | AB77: {=+$M$92:$M$102*TRANSPOSE(Dashboard!$AO$17:$AZ$17)} -> 3285.76 | AC77: {=+$M$92:$M$102*TRANSPOSE(Dashboard!$AO$18:$AZ$18)} -> 3285.76 | AD77: {=+$M$92:$M$102*TRANSPOSE(Dashboard!$AO$19:$AZ$19)} -> 3285.76
A78: 15 | B78: Christian Caviedes | C78: Gerentes | D78: REDCO | E78: Chile | F78: Indefinido | G78: 17249 | K78: Gerencia General (incluye RRHH) | L78: =+COUNTIFS($H$64:$H$147,$K78,$E$64:$E$147,L$63) -> 2 | M78: =+COUNTIFS($H$64:$H$147,$K78,$E$64:$E$147,M$63) -> 1 | N78: =+COUNTIFS($H$64:$H$147,$K78,$E$64:$E$147,N$63) -> 2 | O78: =+COUNTIFS($H$64:$H$147,$K78,$E$64:$E$147,O$63) -> 1 | P78: =+COUNTIFS($H$64:$H$147,$K78,$E$64:$E$147,P$63) -> 0 | Q78: =+SUM(L78:P78) -> 6 | U78: Gerencia Comercial | V78: 1000 | W78: 1000 | X78: 1000 | Y78: 1000 | Z78: 1000 | AA78: 1000 | AB78: 1000 | AC78: 1000 | AD78: 1000
A79: 16 | B79: Matias Fuentes | C79: Gerentes | D79: REDCO | E79: Chile | F79: Indefinido | G79: 10196 | K79: Gerencia Comercial | L79: =+COUNTIFS($H$64:$H$147,$K79,$E$64:$E$147,L$63) -> 3 | M79: =+COUNTIFS($H$64:$H$147,$K79,$E$64:$E$147,M$63) -> 1 | N79: =+COUNTIFS($H$64:$H$147,$K79,$E$64:$E$147,N$63) -> 0 | O79: =+COUNTIFS($H$64:$H$147,$K79,$E$64:$E$147,O$63) -> 0 | P79: =+COUNTIFS($H$64:$H$147,$K79,$E$64:$E$147,P$63) -> 0 | Q79: =+SUM(L79:P79) -> 4 | U79: Gerencia Ingeniera | V79: 40862.88 | W79: 40862.88 | X79: 40862.88 | Y79: 40862.88 | Z79: 40862.88 | AA79: 40862.88 | AB79: 40862.88 | AC79: 40862.88 | AD79: 40862.88
A80: 17 | B80: Benjamin Baeza | C80: Ingeniero Junior | D80: REDCO | E80: Chile | F80: Fijo | G80: 1735 | K80: Gerencia Ingeniera | L80: =+SUM(L81:L87) -> 46 | M80: =+SUM(M81:M87) -> 19 | N80: =+SUM(N81:N87) -> 1 | O80: =+SUM(O81:O87) -> 0 | P80: =+SUM(P81:P87) -> 0 | Q80: =+SUM(L80:P80) -> 66 | U80: Gerentes | V80: 0 | W80: 0 | X80: 0 | Y80: 0 | Z80: 0 | AA80: 0 | AB80: 0 | AC80: 0 | AD80: 0
A81: 18 | B81: Cristian Alarcon | C81: Ingeniero de Proyecto | D81: REDCO | E81: Chile | F81: Indefinido | G81: 2345.3675 | K81: Gerentes | L81: =+COUNTIFS($C$64:$C$147,$K81,$E$64:$E$147,L$63) -> 2 | M81: =+COUNTIFS($C$64:$C$147,$K81,$E$64:$E$147,M$63) -> 0 | N81: =+COUNTIFS($C$64:$C$147,$K81,$E$64:$E$147,N$63) -> 0 | O81: =+COUNTIFS($C$64:$C$147,$K81,$E$64:$E$147,O$63) -> 0 | P81: =+COUNTIFS($C$64:$C$147,$K81,$E$64:$E$147,P$63) -> 0 | Q81: =+SUM(L81:P81) -> 2 | U81: Director de Proyecto | V81: 0 | W81: 0 | X81: 0 | Y81: 0 | Z81: 0 | AA81: 0 | AB81: 0 | AC81: 0 | AD81: 0
A82: 19 | B82: Daniela Oyarzo | C82: Ingeniero de Proyecto | D82: REDCO | E82: Chile | F82: Indefinido | G82: 2345.3675 | K82: Director de Proyecto | L82: =+COUNTIFS($C$64:$C$147,$K82,$E$64:$E$147,L$63) -> 6 | M82: =+COUNTIFS($C$64:$C$147,$K82,$E$64:$E$147,M$63) -> 0 | N82: =+COUNTIFS($C$64:$C$147,$K82,$E$64:$E$147,N$63) -> 1 | O82: =+COUNTIFS($C$64:$C$147,$K82,$E$64:$E$147,O$63) -> 0 | P82: =+COUNTIFS($C$64:$C$147,$K82,$E$64:$E$147,P$63) -> 0 | Q82: =+SUM(L82:P82) -> 7 | U82: Ingeniero Principal | V82: 8093.44 | W82: 8093.44 | X82: 8093.44 | Y82: 8093.44 | Z82: 8093.44 | AA82: 8093.44 | AB82: 8093.44 | AC82: 8093.44 | AD82: 8093.44
A83: 20 | B83: Isidora Figueroa | C83: Ingeniero de Proyecto | D83: REDCO | E83: Chile | F83: Indefinido | G83: 2147 | K83: Ingeniero Principal | L83: =+COUNTIFS($C$64:$C$147,$K83,$E$64:$E$147,L$63) -> 6 | M83: =+COUNTIFS($C$64:$C$147,$K83,$E$64:$E$147,M$63) -> 2 | N83: =+COUNTIFS($C$64:$C$147,$K83,$E$64:$E$147,N$63) -> 0 | O83: =+COUNTIFS($C$64:$C$147,$K83,$E$64:$E$147,O$63) -> 0 | P83: =+COUNTIFS($C$64:$C$147,$K83,$E$64:$E$147,P$63) -> 0 | Q83: =+SUM(L83:P83) -> 8 | U83: Ingeniero Senior | V83: 13081.6 | W83: 13081.6 | X83: 13081.6 | Y83: 13081.6 | Z83: 13081.6 | AA83: 13081.6 | AB83: 13081.6 | AC83: 13081.6 | AD83: 13081.6
A84: 21 | B84: Javier Salazar | C84: Ingeniero Junior | D84: REDCO | E84: Chile | F84: Fijo | G84: 1355.3661 | K84: Ingeniero Senior | L84: =+COUNTIFS($C$64:$C$147,$K84,$E$64:$E$147,L$63) -> 9 | M84: =+COUNTIFS($C$64:$C$147,$K84,$E$64:$E$147,M$63) -> 3 | N84: =+COUNTIFS($C$64:$C$147,$K84,$E$64:$E$147,N$63) -> 0 | O84: =+COUNTIFS($C$64:$C$147,$K84,$E$64:$E$147,O$63) -> 0 | P84: =+COUNTIFS($C$64:$C$147,$K84,$E$64:$E$147,P$63) -> 0 | Q84: =+SUM(L84:P84) -> 12 | U84: Ingeniero de Proyecto | V84: 12935.68 | W84: 12935.68 | X84: 12935.68 | Y84: 12935.68 | Z84: 12935.68 | AA84: 12935.68 | AB84: 12935.68 | AC84: 12935.68 | AD84: 12935.68
A85: 22 | B85: José Pizarro | C85: Ingeniero de Proyecto | D85: REDCO | E85: Chile | F85: Indefinido | G85: 2270 | K85: Ingeniero de Proyecto | L85: =+COUNTIFS($C$64:$C$147,$K85,$E$64:$E$147,L$63) -> 13 | M85: =+COUNTIFS($C$64:$C$147,$K85,$E$64:$E$147,M$63) -> 8 | N85: =+COUNTIFS($C$64:$C$147,$K85,$E$64:$E$147,N$63) -> 0 | O85: =+COUNTIFS($C$64:$C$147,$K85,$E$64:$E$147,O$63) -> 0 | P85: =+COUNTIFS($C$64:$C$147,$K85,$E$64:$E$147,P$63) -> 0 | Q85: =+SUM(L85:P85) -> 21 | U85: Ingeniero Junior | V85: 4243.36 | W85: 4243.36 | X85: 4243.36 | Y85: 4243.36 | Z85: 4243.36 | AA85: 4243.36 | AB85: 4243.36 | AC85: 4243.36 | AD85: 4243.36
A86: 23 | B86: Martin Figueroa | C86: Ingeniero de Proyecto | D86: REDCO | E86: Chile | F86: Fijo | G86: 2001 | K86: Ingeniero Junior | L86: =+COUNTIFS($C$64:$C$147,$K86,$E$64:$E$147,L$63) -> 8 | M86: =+COUNTIFS($C$64:$C$147,$K86,$E$64:$E$147,M$63) -> 5 | N86: =+COUNTIFS($C$64:$C$147,$K86,$E$64:$E$147,N$63) -> 0 | O86: =+COUNTIFS($C$64:$C$147,$K86,$E$64:$E$147,O$63) -> 0 | P86: =+COUNTIFS($C$64:$C$147,$K86,$E$64:$E$147,P$63) -> 0 | Q86: =+SUM(L86:P86) -> 13 | U86: Ingeniero P&C | V86: 2508.8 | W86: 2508.8 | X86: 2508.8 | Y86: 2508.8 | Z86: 2508.8 | AA86: 2508.8 | AB86: 2508.8 | AC86: 2508.8 | AD86: 2508.8
A87: 24 | B87: Matías Cid | C87: Ingeniero de Proyecto | D87: REDCO | E87: Chile | F87: Indefinido | G87: 1716 | K87: Ingeniero P&C | L87: =+COUNTIFS($C$64:$C$147,$K87,$E$64:$E$147,L$63) -> 2 | M87: =+COUNTIFS($C$64:$C$147,$K87,$E$64:$E$147,M$63) -> 1 | N87: =+COUNTIFS($C$64:$C$147,$K87,$E$64:$E$147,N$63) -> 0 | O87: =+COUNTIFS($C$64:$C$147,$K87,$E$64:$E$147,O$63) -> 0 | P87: =+COUNTIFS($C$64:$C$147,$K87,$E$64:$E$147,P$63) -> 0 | Q87: =+SUM(L87:P87) -> 3 | U87: Gerencia Contabilidad y Administracion | V87: 0 | W87: 0 | X87: 0 | Y87: 0 | Z87: 0 | AA87: 0 | AB87: 0 | AC87: 0 | AD87: 0
A88: 25 | B88: Nicolás Sanzana | C88: Ingeniero de Proyecto | D88: REDCO | E88: Chile | F88: Indefinido | G88: 2152 | K88: Gerencia Contabilidad y Administracion | L88: =+COUNTIFS($H$64:$H$147,$K88,$E$64:$E$147,L$63) -> 4 | M88: =+COUNTIFS($H$64:$H$147,$K88,$E$64:$E$147,M$63) -> 0 | N88: =+COUNTIFS($H$64:$H$147,$K88,$E$64:$E$147,N$63) -> 1 | O88: =+COUNTIFS($H$64:$H$147,$K88,$E$64:$E$147,O$63) -> 0 | P88: =+COUNTIFS($H$64:$H$147,$K88,$E$64:$E$147,P$63) -> 0 | Q88: =+SUM(L88:P88) -> 5 | U88: Bonificaciones
A89: 26 | B89: Victor Mohana | C89: Ingeniero de Proyecto | D89: REDCO | E89: Chile | F89: Indefinido | G89: 2384 | K89: Bonificaciones | Q89: =+SUM(L89:P89) -> 0 | T89: Brasil | U89: Cantidad | V89: 45777 | W89: 45807 | X89: 45838 | Y89: 45868 | Z89: 45899 | AA89: 45930 | AB89: 45960 | AC89: 45991 | AD89: 46021
A90: 27 | B90: Nicolas Ayarza | C90: Ingeniero Principal | D90: REDCO | E90: Chile | F90: Indefinido | G90: 3940 | U90: Gerencia General (incluye RRHH) | V90: {=+$N$92:$N$102*TRANSPOSE(Dashboard!$BC$11:$BM$11)} -> 8920 | W90: {=+$N$92:$N$102*TRANSPOSE(Dashboard!$BC$12:$BM$12)} -> 8920 | X90: {=+$N$92:$N$102*TRANSPOSE(Dashboard!$BC$13:$BM$13)} -> 8920 | Y90: {=+$N$92:$N$102*TRANSPOSE(Dashboard!$BC$14:$BM$14)} -> 8920 | Z90: {=+$N$92:$N$102*TRANSPOSE(Dashboard!$BC$15:$BM$15)} -> 8920 | AA90: {=+$N$92:$N$102*TRANSPOSE(Dashboard!$BC$16:$BM$16)} -> 8920 | AB90: {=+$N$92:$N$102*TRANSPOSE(Dashboard!$BC$17:$BM$17)} -> 8920 | AC90: {=+$N$92:$N$102*TRANSPOSE(Dashboard!$BC$18:$BM$18)} -> 8920 | AD90: {=+$N$92:$N$102*TRANSPOSE(Dashboard!$BC$19:$BM$19)} -> 8920
A91: 28 | B91: Eduardo Cuevas | C91: Ingeniero P&C | D91: REDCO | E91: Chile | F91: Indefinido | G91: 3345 | K91: Ratio (US$/t) | L91: Chile | M91: Perú | N91: Brasil | O91: USA | P91: Otros | Q91: Total | U91: Gerencia Comercial | V91: 0 | W91: 0 | X91: 0 | Y91: 0 | Z91: 0 | AA91: 0 | AB91: 0 | AC91: 0 | AD91: 0
A92: 29 | B92: Roxana Avilés | C92: Ingeniero P&C | D92: REDCO | E92: Chile | F92: Indefinido | G92: 2190 | K92: Gerencia General (incluye RRHH) | L92: =+IFERROR(L64/L78,0) -> 11642.317 | M92: =+IFERROR(M64/M78,0) -> 3285.76 | N92: =+IFERROR(N64/N78,0) -> 4460 | O92: =+IFERROR(O64/O78,0) -> 25000 | P92: =+IFERROR(P64/P78,0) -> 0 | Q92: =+IFERROR(Q64/Q78,0) -> 10081.732 | U92: Gerencia Ingeniera | V92: 3700 | W92: 3700 | X92: 3700 | Y92: 3700 | Z92: 3700 | AA92: 3700 | AB92: 3700 | AC92: 3700 | AD92: 3700
A93: 30 | B93: Freddy Díaz | C93: Ingeniero Principal | D93: REDCO | E93: Chile | F93: Indefinido | G93: 5800 | K93: Gerencia Comercial | L93: =+IFERROR(L65/L79,0) -> 4740.58 | M93: =+IFERROR(M65/M79,0) -> 1000 | N93: =+IFERROR(N65/N79,0) -> 0 | O93: =+IFERROR(O65/O79,0) -> 0 | P93: =+IFERROR(P65/P79,0) -> 0 | Q93: =+IFERROR(Q65/Q79,0) -> 3805.435 | U93: Gerentes | V93: 0 | W93: 0 | X93: 0 | Y93: 0 | Z93: 0 | AA93: 0 | AB93: 0 | AC93: 0 | AD93: 0
A94: 31 | B94: Pablo Quiero | C94: Ingeniero Principal | D94: REDCO | E94: Chile | F94: Indefinido | G94: 5515 | K94: Gerencia Ingeniera | L94: =+IFERROR(L66/L80,0) -> 4476.9805 | M94: =+IFERROR(M66/M80,0) -> 2150.6779 | N94: =+IFERROR(N66/N80,0) -> 3700 | O94: =+IFERROR(O66/O80,0) -> 0 | P94: =+IFERROR(P66/P80,0) -> 0 | Q94: =+IFERROR(Q66/Q80,0) -> 3795.5149 | U94: Director de Proyecto | V94: 3700 | W94: 3700 | X94: 3700 | Y94: 3700 | Z94: 3700 | AA94: 3700 | AB94: 3700 | AC94: 3700 | AD94: 3700
A95: 32 | B95: Felipe Lira | C95: Ingeniero Senior | D95: REDCO | E95: Chile | F95: Indefinido | G95: 4367 | K95: Gerentes | L95: =+IFERROR(L67/L81,0) -> 13722.5 | M95: =+IFERROR(M67/M81,0) -> 0 | N95: =+IFERROR(N67/N81,0) -> 0 | O95: =+IFERROR(O67/O81,0) -> 0 | P95: =+IFERROR(P67/P81,0) -> 0 | Q95: =+IFERROR(Q67/Q81,0) -> 13722.5 | U95: Ingeniero Principal | V95: 0 | W95: 0 | X95: 0 | Y95: 0 | Z95: 0 | AA95: 0 | AB95: 0 | AC95: 0 | AD95: 0
A96: 33 | B96: Rodrigo Baez | C96: Ingeniero Principal | D96: REDCO | E96: Chile | F96: Indefinido | G96: 6698 | K96: Director de Proyecto | L96: =+IFERROR(L68/L82,0) -> 8932 | M96: =+IFERROR(M68/M82,0) -> 0 | N96: =+IFERROR(N68/N82,0) -> 3700 | O96: =+IFERROR(O68/O82,0) -> 0 | P96: =+IFERROR(P68/P82,0) -> 0 | Q96: =+IFERROR(Q68/Q82,0) -> 8184.5714 | U96: Ingeniero Senior | V96: 0 | W96: 0 | X96: 0 | Y96: 0 | Z96: 0 | AA96: 0 | AB96: 0 | AC96: 0 | AD96: 0
A97: 34 | B97: Leonel Robledo | C97: Ingeniero Senior | D97: REDCO | E97: Chile | F97: Honorarios | G97: 4444 | K97: Ingeniero Principal | L97: =+IFERROR(L69/L83,0) -> 5987.3333 | M97: =+IFERROR(M69/M83,0) -> 4046.72 | N97: =+IFERROR(N69/N83,0) -> 0 | O97: =+IFERROR(O69/O83,0) -> 0 | P97: =+IFERROR(P69/P83,0) -> 0 | Q97: =+IFERROR(Q69/Q83,0) -> 5502.18 | U97: Ingeniero de Proyecto | V97: 0 | W97: 0 | X97: 0 | Y97: 0 | Z97: 0 | AA97: 0 | AB97: 0 | AC97: 0 | AD97: 0
A98: 35 | B98: Alex Pacheco | C98: Ingeniero Senior | D98: REDCO | E98: Chile | F98: Indefinido | G98: 2704 | K98: Ingeniero Senior | L98: =+IFERROR(L70/L84,0) -> 4584.4444 | M98: =+IFERROR(M70/M84,0) -> 4360.5333 | N98: =+IFERROR(N70/N84,0) -> 0 | O98: =+IFERROR(O70/O84,0) -> 0 | P98: =+IFERROR(P70/P84,0) -> 0 | Q98: =+IFERROR(Q70/Q84,0) -> 4528.4667 | U98: Ingeniero Junior | V98: 0 | W98: 0 | X98: 0 | Y98: 0 | Z98: 0 | AA98: 0 | AB98: 0 | AC98: 0 | AD98: 0
A99: 36 | B99: Pedro Aguiluz | C99: Subgerente Comercial | D99: REDCO | E99: Chile | F99: Indefinido | G99: 3959 | H99: Gerencia Comercial | K99: Ingeniero de Proyecto | L99: =+IFERROR(L71/L85,0) -> 2163.0565 | M99: =+IFERROR(M71/M85,0) -> 1616.96 | N99: =+IFERROR(N71/N85,0) -> 0 | O99: =+IFERROR(O71/O85,0) -> 0 | P99: =+IFERROR(P71/P85,0) -> 0 | Q99: =+IFERROR(Q71/Q85,0) -> 1955.0198 | U99: Ingeniero P&C | V99: 0 | W99: 0 | X99: 0 | Y99: 0 | Z99: 0 | AA99: 0 | AB99: 0 | AC99: 0 | AD99: 0
A100: 37 | B100: Olesya Dashavskaya | C100: Country Manager Rusia | D100: R+ | E100: Chile | F100: Indefinido | G100: 4656 | H100: Gerencia General (incluye RRHH) | K100: Ingeniero Junior | L100: =+IFERROR(L72/L86,0) -> 1758.1708 | M100: =+IFERROR(M72/M86,0) -> 848.672 | N100: =+IFERROR(N72/N86,0) -> 0 | O100: =+IFERROR(O72/O86,0) -> 0 | P100: =+IFERROR(P72/P86,0) -> 0 | Q100: =+IFERROR(Q72/Q86,0) -> 1408.3635 | U100: Gerencia Contabilidad y Administracion | V100: 1100 | W100: 1100 | X100: 1100 | Y100: 1100 | Z100: 1100 | AA100: 1100 | AB100: 1100 | AC100: 1100 | AD100: 1100
A101: 38 | B101: Ricardo Miranda | C101: Director de Proyecto | D101: R+ | E101: Chile | F101: Indefinido | G101: 13353 | K101: Ingeniero P&C | L101: =+IFERROR(L73/L87,0) -> 2767.5 | M101: =+IFERROR(M73/M87,0) -> 2508.8 | N101: =+IFERROR(N73/N87,0) -> 0 | O101: =+IFERROR(O73/O87,0) -> 0 | P101: =+IFERROR(P73/P87,0) -> 0 | Q101: =+IFERROR(Q73/Q87,0) -> 2681.2667 | U101: Bonificaciones
A102: 39 | B102: Cristobal Concha | C102: Ingeniero Junior | D102: R+ | E102: Chile | F102: Fijo | G102: 1462 | K102: Gerencia Contabilidad y Administracion | L102: =+IFERROR(L74/L88,0) -> 2079.7467 | M102: =+IFERROR(M74/M88,0) -> 0 | N102: =+IFERROR(N74/N88,0) -> 1100 | O102: =+IFERROR(O74/O88,0) -> 0 | P102: =+IFERROR(P74/P88,0) -> 0 | Q102: =+IFERROR(Q74/Q88,0) -> 1883.7973 | T102: USA | U102: Cantidad | V102: 45777 | W102: 45807 | X102: 45838 | Y102: 45868 | Z102: 45899 | AA102: 45930 | AB102: 45960 | AC102: 45991 | AD102: 46021
A103: 40 | B103: Cristobal Poblete | C103: Ingeniero Junior | D103: R+ | E103: Chile | F103: Fijo | G103: 1733 | K103: Bonificaciones | L103: =+IFERROR(L75/L89,0) -> 0 | M103: =+IFERROR(M75/M89,0) -> 0 | N103: =+IFERROR(N75/N89,0) -> 0 | O103: =+IFERROR(O75/O89,0) -> 0 | P103: =+IFERROR(P75/P89,0) -> 0 | Q103: =+IFERROR(Q75/Q89,0) -> 0 | U103: Gerencia General (incluye RRHH) | V103: {=+$O$92:$O$102*TRANSPOSE(Dashboard!$BQ$11:$CA$11)} -> 25000 | W103: {=+$O$92:$O$102*TRANSPOSE(Dashboard!$BQ$12:$CA$12)} -> 25000 | X103: {=+$O$92:$O$102*TRANSPOSE(Dashboard!$BQ$13:$CA$13)} -> 25000 | Y103: {=+$O$92:$O$102*TRANSPOSE(Dashboard!$BQ$14:$CA$14)} -> 25000 | Z103: {=+$O$92:$O$102*TRANSPOSE(Dashboard!$BQ$15:$CA$15)} -> 25000 | AA103: {=+$O$92:$O$102*TRANSPOSE(Dashboard!$BQ$16:$CA$16)} -> 25000 | AB103: {=+$O$92:$O$102*TRANSPOSE(Dashboard!$BQ$17:$CA$17)} -> 25000 | AC103: {=+$O$92:$O$102*TRANSPOSE(Dashboard!$BQ$18:$CA$18)} -> 25000 | AD103: {=+$O$92:$O$102*TRANSPOSE(Dashboard!$BQ$19:$CA$19)} -> 25000
A104: 41 | B104: Cristobal Ventura | C104: Ingeniero de Proyecto | D104: R+ | E104: Chile | F104: Indefinido | G104: 1458 | U104: Gerencia Comercial | V104: 0 | W104: 0 | X104: 0 | Y104: 0 | Z104: 0 | AA104: 0 | AB104: 0 | AC104: 0 | AD104: 0
A105: 42 | B105: Darwin Varas | C105: Ingeniero de Proyecto | D105: R+ | E105: Chile | F105: Fijo | G105: 1868 | U105: Gerencia Ingeniera | V105: 0 | W105: 0 | X105: 0 | Y105: 0 | Z105: 0 | AA105: 0 | AB105: 0 | AC105: 0 | AD105: 0
A106: 43 | B106: Diego Muñoz | C106: Ingeniero de Proyecto | D106: R+ | E106: Chile | F106: Indefinido | G106: 2152 | U106: Gerentes | V106: 0 | W106: 0 | X106: 0 | Y106: 0 | Z106: 0 | AA106: 0 | AB106: 0 | AC106: 0 | AD106: 0
A107: 44 | B107: Erick Sanhueza | C107: Ingeniero de Proyecto | D107: R+ | E107: Chile | F107: Fijo | G107: 3576 | U107: Director de Proyecto | V107: 0 | W107: 0 | X107: 0 | Y107: 0 | Z107: 0 | AA107: 0 | AB107: 0 | AC107: 0 | AD107: 0
A108: 45 | B108: Gerson Alfaro | C108: Ingeniero Principal | D108: R+ | E108: Chile | F108: Indefinido | G108: 5996 | U108: Ingeniero Principal | V108: 0 | W108: 0 | X108: 0 | Y108: 0 | Z108: 0 | AA108: 0 | AB108: 0 | AC108: 0 | AD108: 0
A109: 46 | B109: Marcelo Mendoza | C109: Ingeniero de Proyecto | D109: R+ | E109: Chile | F109: Indefinido | G109: 1705 | U109: Ingeniero Senior | V109: 0 | W109: 0 | X109: 0 | Y109: 0 | Z109: 0 | AA109: 0 | AB109: 0 | AC109: 0 | AD109: 0
A110: 47 | B110: Claudio Delgado | C110: Ingeniero Senior | D110: R+ | E110: Chile | F110: Fijo | G110: 6590 | U110: Ingeniero de Proyecto | V110: 0 | W110: 0 | X110: 0 | Y110: 0 | Z110: 0 | AA110: 0 | AB110: 0 | AC110: 0 | AD110: 0
A111: 48 | B111: Eduardo Morales | C111: Ingeniero Principal | D111: R+ | E111: Chile | F111: Indefinido | G111: 7975 | U111: Ingeniero Junior | V111: 0 | W111: 0 | X111: 0 | Y111: 0 | Z111: 0 | AA111: 0 | AB111: 0 | AC111: 0 | AD111: 0
A112: 49 | B112: Eduardo Cepeda | C112: Ingeniero Junior | D112: R+ | E112: Chile | F112: Fijo | G112: 2324 | U112: Ingeniero P&C | V112: 0 | W112: 0 | X112: 0 | Y112: 0 | Z112: 0 | AA112: 0 | AB112: 0 | AC112: 0 | AD112: 0
A113: 50 | B113: Gabriel Ojeda | C113: Ingeniero Junior | D113: R+ | E113: Chile | F113: Fijo | G113: 2395 | U113: Gerencia Contabilidad y Administracion | V113: 0 | W113: 0 | X113: 0 | Y113: 0 | Z113: 0 | AA113: 0 | AB113: 0 | AC113: 0 | AD113: 0
A114: 51 | B114: Juan de Vera | C114: Ingeniero Senior | D114: R+ | E114: Chile | F114: Honorarios | G114: 4158 | U114: Bonificaciones
A115: 52 | B115: Matias Guerrero | C115: Ingeniero Junior | D115: R+ | E115: Chile | F115: Fijo | G115: 1331 | T115: Otros | U115: Cantidad | V115: 45777 | W115: 45807 | X115: 45838 | Y115: 45868 | Z115: 45899 | AA115: 45930 | AB115: 45960 | AC115: 45991 | AD115: 46021
A116: 53 | B116: Mauricio Peralta | C116: Ingeniero Junior | D116: R+ | E116: Chile | F116: Fijo | G116: 1730 | U116: Gerencia General (incluye RRHH) | V116: {=+$P$92:$P$102*TRANSPOSE(Dashboard!$CE$11:$CO$11)} -> 0 | W116: {=+$P$92:$P$102*TRANSPOSE(Dashboard!$CE$12:$CO$12)} -> 0 | X116: {=+$P$92:$P$102*TRANSPOSE(Dashboard!$CE$13:$CO$13)} -> 0 | Y116: {=+$P$92:$P$102*TRANSPOSE(Dashboard!$CE$14:$CO$14)} -> 0 | Z116: {=+$P$92:$P$102*TRANSPOSE(Dashboard!$CE$15:$CO$15)} -> 0 | AA116: {=+$P$92:$P$102*TRANSPOSE(Dashboard!$CE$16:$CO$16)} -> 0 | AB116: {=+$P$92:$P$102*TRANSPOSE(Dashboard!$CE$17:$CO$17)} -> 0 | AC116: {=+$P$92:$P$102*TRANSPOSE(Dashboard!$CE$18:$CO$18)} -> 0 | AD116: {=+$P$92:$P$102*TRANSPOSE(Dashboard!$CE$19:$CO$19)} -> 0
A117: 54 | B117: Rodrigo Andrae | C117: Ingeniero Senior | D117: R+ | E117: Chile | F117: Fijo | G117: 3295 | U117: Gerencia Comercial | V117: 0 | W117: 0 | X117: 0 | Y117: 0 | Z117: 0 | AA117: 0 | AB117: 0 | AC117: 0 | AD117: 0
A118: 55 | B118: Emilio Sanchez | C118: Ingeniero Senior | D118: R+ | E118: Chile | F118: Indefinido | G118: 5869 | U118: Gerencia Ingeniera | V118: 0 | W118: 0 | X118: 0 | Y118: 0 | Z118: 0 | AA118: 0 | AB118: 0 | AC118: 0 | AD118: 0
U119: Gerentes | V119: 0 | W119: 0 | X119: 0 | Y119: 0 | Z119: 0 | AA119: 0 | AB119: 0 | AC119: 0 | AD119: 0
...

Sheet Gantt Proyectos
D3: Modelo de Flujo REDCO
D4: 2025
D5: Proyectos
AF9: 45777 | AG9: 45807 | AH9: 45838 | AI9: 45868 | AJ9: 45899 | AK9: 45930 | AL9: 45960 | AM9: 45991 | AN9: 46021
AD10: Actual | AE10: Cantidad Proyectos | AF10: =+COUNTIFS(AF$97:AF$100005,">0",$AD$97:$AD$100005,"Actual") -> 25 | AG10: =+COUNTIFS(AG$97:AG$100005,">0",$AD$97:$AD$100005,"Actual") -> 20 | AH10: =+COUNTIFS(AH$97:AH$100005,">0",$AD$97:$AD$100005,"Actual") -> 16 | AI10: =+COUNTIFS(AI$97:AI$100005,">0",$AD$97:$AD$100005,"Actual") -> 10 | AJ10: =+COUNTIFS(AJ$97:AJ$100005,">0",$AD$97:$AD$100005,"Actual") -> 5 | AK10: =+COUNTIFS(AK$97:AK$100005,">0",$AD$97:$AD$100005,"Actual") -> 2 | AL10: =+COUNTIFS(AL$97:AL$100005,">0",$AD$97:$AD$100005,"Actual") -> 2 | AM10: =+COUNTIFS(AM$97:AM$100005,">0",$AD$97:$AD$100005,"Actual") -> 2 | AN10: =+COUNTIFS(AN$97:AN$100005,">0",$AD$97:$AD$100005,"Actual") -> 1
AE11: Cantidad de Modulos | AF11: =+SUMIFS($W$97:$W$1048576,AF$97:AF$1048576,">0",$AD$97:$AD$1048576,"Actual") -> 33.255034 | AG11: =+SUMIFS($W$97:$W$1048576,AG$97:AG$1048576,">0",$AD$97:$AD$1048576,"Actual") -> 24.946309 | AH11: =+SUMIFS($W$97:$W$1048576,AH$97:AH$1048576,">0",$AD$97:$AD$1048576,"Actual") -> 21.525727 | AI11: =+SUMIFS($W$97:$W$1048576,AI$97:AI$1048576,">0",$AD$97:$AD$1048576,"Actual") -> 13.639821 | AJ11: =+SUMIFS($W$97:$W$1048576,AJ$97:AJ$1048576,">0",$AD$97:$AD$1048576,"Actual") -> 5.3154362 | AK11: =+SUMIFS($W$97:$W$1048576,AK$97:AK$1048576,">0",$AD$97:$AD$1048576,"Actual") -> 2.8948546 | AL11: =+SUMIFS($W$97:$W$1048576,AL$97:AL$1048576,">0",$AD$97:$AD$1048576,"Actual") -> 2.8948546 | AM11: =+SUMIFS($W$97:$W$1048576,AM$97:AM$1048576,">0",$AD$97:$AD$1048576,"Actual") -> 2.8948546 | AN11: =+SUMIFS($W$97:$W$1048576,AN$97:AN$1048576,">0",$AD$97:$AD$1048576,"Actual") -> 1.4474273
AD12: Actuales + Asignados | AE12: Cantidad Proyectos | AF12: =+COUNTIFS(AF$97:AF$100005,">0",$AD$97:$AD$100005,"Actual") -> 25 | AG12: =+COUNTIFS(AG$97:AG$100005,">0",$AD$97:$AD$100005,"Actual") -> 20 | AH12: =+COUNTIFS(AH$97:AH$100005,">0",$AD$97:$AD$100005,"Actual") -> 16 | AI12: =+COUNTIFS(AI$97:AI$100005,">0",$AD$97:$AD$100005,"Actual") -> 10 | AJ12: =+COUNTIFS(AJ$97:AJ$100005,">0",$AD$97:$AD$100005,"Actual") -> 5 | AK12: =+COUNTIFS(AK$97:AK$100005,">0",$AD$97:$AD$100005,"Actual") -> 2 | AL12: =+COUNTIFS(AL$97:AL$100005,">0",$AD$97:$AD$100005,"Actual") -> 2 | AM12: =+COUNTIFS(AM$97:AM$100005,">0",$AD$97:$AD$100005,"Actual") -> 2 | AN12: =+COUNTIFS(AN$97:AN$100005,">0",$AD$97:$AD$100005,"Actual") -> 1
AE13: Cantidad de Modulos | AF13: =+SUMIFS($W$97:$W$1048576,AF$97:AF$1048576,">0",$AD$97:$AD$1048576,"Actual")+SUMIFS($W$97:$W$1048576,AF$97:AF$1048576,">0",$AD$97:$AD$1048576,"Asignado") -> 33.255034 | AG13: =+SUMIFS($W$97:$W$1048576,AG$97:AG$1048576,">0",$AD$97:$AD$1048576,"Actual")+SUMIFS($W$97:$W$1048576,AG$97:AG$1048576,">0",$AD$97:$AD$1048576,"Asignado") -> 25.946309 | AH13: =+SUMIFS($W$97:$W$1048576,AH$97:AH$1048576,">0",$AD$97:$AD$1048576,"Actual")+SUMIFS($W$97:$W$1048576,AH$97:AH$1048576,">0",$AD$97:$AD$1048576,"Asignado") -> 23.246085 | AI13: =+SUMIFS($W$97:$W$1048576,AI$97:AI$1048576,">0",$AD$97:$AD$1048576,"Actual")+SUMIFS($W$97:$W$1048576,AI$97:AI$1048576,">0",$AD$97:$AD$1048576,"Asignado") -> 19.46085 | AJ13: =+SUMIFS($W$97:$W$1048576,AJ$97:AJ$1048576,">0",$AD$97:$AD$1048576,"Actual")+SUMIFS($W$97:$W$1048576,AJ$97:AJ$1048576,">0",$AD$97:$AD$1048576,"Asignado") -> 11.856823 | AK13: =+SUMIFS($W$97:$W$1048576,AK$97:AK$1048576,">0",$AD$97:$AD$1048576,"Actual")+SUMIFS($W$97:$W$1048576,AK$97:AK$1048576,">0",$AD$97:$AD$1048576,"Asignado") -> 9.4362416 | AL13: =+SUMIFS($W$97:$W$1048576,AL$97:AL$1048576,">0",$AD$97:$AD$1048576,"Actual")+SUMIFS($W$97:$W$1048576,AL$97:AL$1048576,">0",$AD$97:$AD$1048576,"Asignado") -> 9.4362416 | AM13: =+SUMIFS($W$97:$W$1048576,AM$97:AM$1048576,">0",$AD$97:$AD$1048576,"Actual")+SUMIFS($W$97:$W$1048576,AM$97:AM$1048576,">0",$AD$97:$AD$1048576,"Asignado") -> 6.1655481 | AN13: =+SUMIFS($W$97:$W$1048576,AN$97:AN$1048576,">0",$AD$97:$AD$1048576,"Actual")+SUMIFS($W$97:$W$1048576,AN$97:AN$1048576,">0",$AD$97:$AD$1048576,"Asignado") -> 3.9977629
AD14: Actuales + Asignados + No Asignados | AE14: Cantidad Proyectos | AF14: =+COUNTIFS(AF$97:AF$100005,">0",$AD$97:$AD$100005,"Actual") -> 25 | AG14: =+COUNTIFS(AG$97:AG$100005,">0",$AD$97:$AD$100005,"Actual") -> 20 | AH14: =+COUNTIFS(AH$97:AH$100005,">0",$AD$97:$AD$100005,"Actual") -> 16 | AI14: =+COUNTIFS(AI$97:AI$100005,">0",$AD$97:$AD$100005,"Actual") -> 10 | AJ14: =+COUNTIFS(AJ$97:AJ$100005,">0",$AD$97:$AD$100005,"Actual") -> 5 | AK14: =+COUNTIFS(AK$97:AK$100005,">0",$AD$97:$AD$100005,"Actual") -> 2 | AL14: =+COUNTIFS(AL$97:AL$100005,">0",$AD$97:$AD$100005,"Actual") -> 2 | AM14: =+COUNTIFS(AM$97:AM$100005,">0",$AD$97:$AD$100005,"Actual") -> 2 | AN14: =+COUNTIFS(AN$97:AN$100005,">0",$AD$97:$AD$100005,"Actual") -> 1
AE15: Cantidad de Modulos | AF15: =+SUMIFS($W$97:$W$1048576,AF$97:AF$1048576,">0",$AD$97:$AD$1048576,"Actual")+SUMIFS($W$97:$W$1048576,AF$97:AF$1048576,">0",$AD$97:$AD$1048576,"Asignado")+SUMIFS($W$97:$W$1048576,AF$97:AF$1048576,">0",$AD$97:$AD$1048576,"No Asignado") -> 33.255034 | AG15: =+SUMIFS($W$97:$W$1048576,AG$97:AG$1048576,">0",$AD$97:$AD$1048576,"Actual")+SUMIFS($W$97:$W$1048576,AG$97:AG$1048576,">0",$AD$97:$AD$1048576,"Asignado")+SUMIFS($W$97:$W$1048576,AG$97:AG$1048576,">0",$AD$97:$AD$1048576,"No Asignado") -> 25.946309 | AH15: =+SUMIFS($W$97:$W$1048576,AH$97:AH$1048576,">0",$AD$97:$AD$1048576,"Actual")+SUMIFS($W$97:$W$1048576,AH$97:AH$1048576,">0",$AD$97:$AD$1048576,"Asignado")+SUMIFS($W$97:$W$1048576,AH$97:AH$1048576,">0",$AD$97:$AD$1048576,"No Asignado") -> 23.490828 | AI15: =+SUMIFS($W$97:$W$1048576,AI$97:AI$1048576,">0",$AD$97:$AD$1048576,"Actual")+SUMIFS($W$97:$W$1048576,AI$97:AI$1048576,">0",$AD$97:$AD$1048576,"Asignado")+SUMIFS($W$97:$W$1048576,AI$97:AI$1048576,">0",$AD$97:$AD$1048576,"No Asignado") -> 26.284564 | AJ15: =+SUMIFS($W$97:$W$1048576,AJ$97:AJ$1048576,">0",$AD$97:$AD$1048576,"Actual")+SUMIFS($W$97:$W$1048576,AJ$97:AJ$1048576,">0",$AD$97:$AD$1048576,"Asignado")+SUMIFS($W$97:$W$1048576,AJ$97:AJ$1048576,">0",$AD$97:$AD$1048576,"No Asignado") -> 20.159284 | AK15: =+SUMIFS($W$97:$W$1048576,AK$97:AK$1048576,">0",$AD$97:$AD$1048576,"Actual")+SUMIFS($W$97:$W$1048576,AK$97:AK$1048576,">0",$AD$97:$AD$1048576,"Asignado")+SUMIFS($W$97:$W$1048576,AK$97:AK$1048576,">0",$AD$97:$AD$1048576,"No Asignado") -> 17.521588 | AL15: =+SUMIFS($W$97:$W$1048576,AL$97:AL$1048576,">0",$AD$97:$AD$1048576,"Actual")+SUMIFS($W$97:$W$1048576,AL$97:AL$1048576,">0",$AD$97:$AD$1048576,"Asignado")+SUMIFS($W$97:$W$1048576,AL$97:AL$1048576,">0",$AD$97:$AD$1048576,"No Asignado") -> 15.563087 | AM15: =+SUMIFS($W$97:$W$1048576,AM$97:AM$1048576,">0",$AD$97:$AD$1048576,"Actual")+SUMIFS($W$97:$W$1048576,AM$97:AM$1048576,">0",$AD$97:$AD$1048576,"Asignado")+SUMIFS($W$97:$W$1048576,AM$97:AM$1048576,">0",$AD$97:$AD$1048576,"No Asignado") -> 11.792394 | AN15: =+SUMIFS($W$97:$W$1048576,AN$97:AN$1048576,">0",$AD$97:$AD$1048576,"Actual")+SUMIFS($W$97:$W$1048576,AN$97:AN$1048576,">0",$AD$97:$AD$1048576,"Asignado")+SUMIFS($W$97:$W$1048576,AN$97:AN$1048576,">0",$AD$97:$AD$1048576,"No Asignado") -> 8.3563758
AD16: Capacidad Actual
AE17: Actuales | AF17: =+AF11 -> 33.255034 | AG17: =+AG11 -> 24.946309 | AH17: =+AH11 -> 21.525727 | AI17: =+AI11 -> 13.639821 | AJ17: =+AJ11 -> 5.3154362 | AK17: =+AK11 -> 2.8948546 | AL17: =+AL11 -> 2.8948546 | AM17: =+AM11 -> 2.8948546 | AN17: =+AN11 -> 1.4474273
AE18: Actuales + Asignados | AF18: =+AF13 -> 33.255034 | AG18: =+AG13 -> 25.946309 | AH18: =+AH13 -> 23.246085 | AI18: =+AI13 -> 19.46085 | AJ18: =+AJ13 -> 11.856823 | AK18: =+AK13 -> 9.4362416 | AL18: =+AL13 -> 9.4362416 | AM18: =+AM13 -> 6.1655481 | AN18: =+AN13 -> 3.9977629
AE19: Actuales + Asignados + No Asignados | AF19: =+AF15 -> 33.255034 | AG19: =+AG15 -> 25.946309 | AH19: =+AH15 -> 23.490828 | AI19: =+AI15 -> 26.284564 | AJ19: =+AJ15 -> 20.159284 | AK19: =+AK15 -> 17.521588 | AL19: =+AL15 -> 15.563087 | AM19: =+AM15 -> 11.792394 | AN19: =+AN15 -> 8.3563758
AF21: 45777 | AG21: 45807 | AH21: 45838 | AI21: 45868 | AJ21: 45899 | AK21: 45930 | AL21: 45960 | AM21: 45991 | AN21: 46021
AD22: Actuales | AE22: Director de Proyecto | AF22: =+SUM(AF23:AF25) -> 3 | AG22: =+SUM(AG23:AG25) -> 3 | AH22: =+SUM(AH23:AH25) -> 2 | AI22: =+SUM(AI23:AI25) -> 2 | AJ22: =+SUM(AJ23:AJ25) -> 2 | AK22: =+SUM(AK23:AK25) -> 2 | AL22: =+SUM(AL23:AL25) -> 2 | AM22: =+SUM(AM23:AM25) -> 2 | AN22: =+SUM(AN23:AN25) -> 1
AE23: Open Pit | AF23: {=ROUNDUP(SUMPRODUCT(($I$97:$I$100005=$AE23)*($AD$97:$AD$100005="Actual")*AF$97:AF$100005*$X$97:$X$100005),0)} -> 1 | AG23: {=ROUNDUP(SUMPRODUCT(($I$97:$I$100005=$AE23)*($AD$97:$AD$100005="Actual")*AG$97:AG$100005*$X$97:$X$100005),0)} -> 1 | AH23: {=ROUNDUP(SUMPRODUCT(($I$97:$I$100005=$AE23)*($AD$97:$AD$100005="Actual")*AH$97:AH$100005*$X$97:$X$100005),0)} -> 1 | AI23: {=ROUNDUP(SUMPRODUCT(($I$97:$I$100005=$AE23)*($AD$97:$AD$100005="Actual")*AI$97:AI$100005*$X$97:$X$100005),0)} -> 1 | AJ23: {=ROUNDUP(SUMPRODUCT(($I$97:$I$100005=$AE23)*($AD$97:$AD$100005="Actual")*AJ$97:AJ$100005*$X$97:$X$100005),0)} -> 1 | AK23: {=ROUNDUP(SUMPRODUCT(($I$97:$I$100005=$AE23)*($AD$97:$AD$100005="Actual")*AK$97:AK$100005*$X$97:$X$100005),0)} -> 1 | AL23: {=ROUNDUP(SUMPRODUCT(($I$97:$I$100005=$AE23)*($AD$97:$AD$100005="Actual")*AL$97:AL$100005*$X$97:$X$100005),0)} -> 1 | AM23: {=ROUNDUP(SUMPRODUCT(($I$97:$I$100005=$AE23)*($AD$97:$AD$100005="Actual")*AM$97:AM$100005*$X$97:$X$100005),0)} -> 1 | AN23: {=ROUNDUP(SUMPRODUCT(($I$97:$I$100005=$AE23)*($AD$97:$AD$100005="Actual")*AN$97:AN$100005*$X$97:$X$100005),0)} -> 1
AE24: Subterránea | AF24: {=ROUNDUP(SUMPRODUCT(($I$97:$I$100005=$AE24)*($AD$97:$AD$100005="Actual")*AF$97:AF$100005*$X$97:$X$100005),0)} -> 2 | AG24: {=ROUNDUP(SUMPRODUCT(($I$97:$I$100005=$AE24)*($AD$97:$AD$100005="Actual")*AG$97:AG$100005*$X$97:$X$100005),0)} -> 2 | AH24: {=ROUNDUP(SUMPRODUCT(($I$97:$I$100005=$AE24)*($AD$97:$AD$100005="Actual")*AH$97:AH$100005*$X$97:$X$100005),0)} -> 1 | AI24: {=ROUNDUP(SUMPRODUCT(($I$97:$I$100005=$AE24)*($AD$97:$AD$100005="Actual")*AI$97:AI$100005*$X$97:$X$100005),0)} -> 1 | AJ24: {=ROUNDUP(SUMPRODUCT(($I$97:$I$100005=$AE24)*($AD$97:$AD$100005="Actual")*AJ$97:AJ$100005*$X$97:$X$100005),0)} -> 1 | AK24: {=ROUNDUP(SUMPRODUCT(($I$97:$I$100005=$AE24)*($AD$97:$AD$100005="Actual")*AK$97:AK$100005*$X$97:$X$100005),0)} -> 1 | AL24: {=ROUNDUP(SUMPRODUCT(($I$97:$I$100005=$AE24)*($AD$97:$AD$100005="Actual")*AL$97:AL$100005*$X$97:$X$100005),0)} -> 1 | AM24: {=ROUNDUP(SUMPRODUCT(($I$97:$I$100005=$AE24)*($AD$97:$AD$100005="Actual")*AM$97:AM$100005*$X$97:$X$100005),0)} -> 1 | AN24: {=ROUNDUP(SUMPRODUCT(($I$97:$I$100005=$AE24)*($AD$97:$AD$100005="Actual")*AN$97:AN$100005*$X$97:$X$100005),0)} -> 0
AE25: Geomecánica | AF25: {=ROUNDUP(SUMPRODUCT(($I$97:$I$100005=$AE25)*($AD$97:$AD$100005="Actual")*AF$97:AF$100005*$X$97:$X$100005),0)} -> 0 | AG25: {=ROUNDUP(SUMPRODUCT(($I$97:$I$100005=$AE25)*($AD$97:$AD$100005="Actual")*AG$97:AG$100005*$X$97:$X$100005),0)} -> 0 | AH25: {=ROUNDUP(SUMPRODUCT(($I$97:$I$100005=$AE25)*($AD$97:$AD$100005="Actual")*AH$97:AH$100005*$X$97:$X$100005),0)} -> 0 | AI25: {=ROUNDUP(SUMPRODUCT(($I$97:$I$100005=$AE25)*($AD$97:$AD$100005="Actual")*AI$97:AI$100005*$X$97:$X$100005),0)} -> 0 | AJ25: {=ROUNDUP(SUMPRODUCT(($I$97:$I$100005=$AE25)*($AD$97:$AD$100005="Actual")*AJ$97:AJ$100005*$X$97:$X$100005),0)} -> 0 | AK25: {=ROUNDUP(SUMPRODUCT(($I$97:$I$100005=$AE25)*($AD$97:$AD$100005="Actual")*AK$97:AK$100005*$X$97:$X$100005),0)} -> 0 | AL25: {=ROUNDUP(SUMPRODUCT(($I$97:$I$100005=$AE25)*($AD$97:$AD$100005="Actual")*AL$97:AL$100005*$X$97:$X$100005),0)} -> 0 | AM25: {=ROUNDUP(SUMPRODUCT(($I$97:$I$100005=$AE25)*($AD$97:$AD$100005="Actual")*AM$97:AM$100005*$X$97:$X$100005),0)} -> 0 | AN25: {=ROUNDUP(SUMPRODUCT(($I$97:$I$100005=$AE25)*($AD$97:$AD$100005="Actual")*AN$97:AN$100005*$X$97:$X$100005),0)} -> 0
AE26: Ingeniero Principal | AF26: =+SUM(AF27:AF29) -> 3 | AG26: =+SUM(AG27:AG29) -> 3 | AH26: =+SUM(AH27:AH29) -> 3 | AI26: =+SUM(AI27:AI29) -> 2 | AJ26: =+SUM(AJ27:AJ29) -> 2 | AK26: =+SUM(AK27:AK29) -> 2 | AL26: =+SUM(AL27:AL29) -> 2 | AM26: =+SUM(AM27:AM29) -> 2 | AN26: =+SUM(AN27:AN29) -> 1
AE27: Open Pit | AF27: {=ROUNDUP(SUMPRODUCT(($I$97:$I$100005=$AE27)*($AD$97:$AD$100005="Actual")*AF$97:AF$100005*$Y$97:$Y$100005),0)} -> 1 | AG27: {=ROUNDUP(SUMPRODUCT(($I$97:$I$100005=$AE27)*($AD$97:$AD$100005="Actual")*AG$97:AG$100005*$Y$97:$Y$100005),0)} -> 1 | AH27: {=ROUNDUP(SUMPRODUCT(($I$97:$I$100005=$AE27)*($AD$97:$AD$100005="Actual")*AH$97:AH$100005*$Y$97:$Y$100005),0)} -> 1 | AI27: {=ROUNDUP(SUMPRODUCT(($I$97:$I$100005=$AE27)*($AD$97:$AD$100005="Actual")*AI$97:AI$100005*$Y$97:$Y$100005),0)} -> 1 | AJ27: {=ROUNDUP(SUMPRODUCT(($I$97:$I$100005=$AE27)*($AD$97:$AD$100005="Actual")*AJ$97:AJ$100005*$Y$97:$Y$100005),0)} -> 1 | AK27: {=ROUNDUP(SUMPRODUCT(($I$97:$I$100005=$AE27)*($AD$97:$AD$100005="Actual")*AK$97:AK$100005*$Y$97:$Y$100005),0)} -> 1 | AL27: {=ROUNDUP(SUMPRODUCT(($I$97:$I$100005=$AE27)*($AD$97:$AD$100005="Actual")*AL$97:AL$100005*$Y$97:$Y$100005),0)} -> 1 | AM27: {=ROUNDUP(SUMPRODUCT(($I$97:$I$100005=$AE27)*($AD$97:$AD$100005="Actual")*AM$97:AM$100005*$Y$97:$Y$100005),0)} -> 1 | AN27: {=ROUNDUP(SUMPRODUCT(($I$97:$I$100005=$AE27)*($AD$97:$AD$100005="Actual")*AN$97:AN$100005*$Y$97:$Y$100005),0)} -> 1
AE28: Subterránea | AF28: {=ROUNDUP(SUMPRODUCT(($I$97:$I$100005=$AE28)*($AD$97:$AD$100005="Actual")*AF$97:AF$100005*$Y$97:$Y$100005),0)} -> 2 | AG28: {=ROUNDUP(SUMPRODUCT(($I$97:$I$100005=$AE28)*($AD$97:$AD$100005="Actual")*AG$97:AG$100005*$Y$97:$Y$100005),0)} -> 2 | AH28: {=ROUNDUP(SUMPRODUCT(($I$97:$I$100005=$AE28)*($AD$97:$AD$100005="Actual")*AH$97:AH$100005*$Y$97:$Y$100005),0)} -> 2 | AI28: {=ROUNDUP(SUMPRODUCT(($I$97:$I$100005=$AE28)*($AD$97:$AD$100005="Actual")*AI$97:AI$100005*$Y$97:$Y$100005),0)} -> 1 | AJ28: {=ROUNDUP(SUMPRODUCT(($I$97:$I$100005=$AE28)*($AD$97:$AD$100005="Actual")*AJ$97:AJ$100005*$Y$97:$Y$100005),0)} -> 1 | AK28: {=ROUNDUP(SUMPRODUCT(($I$97:$I$100005=$AE28)*($AD$97:$AD$100005="Actual")*AK$97:AK$100005*$Y$97:$Y$100005),0)} -> 1 | AL28: {=ROUNDUP(SUMPRODUCT(($I$97:$I$100005=$AE28)*($AD$97:$AD$100005="Actual")*AL$97:AL$100005*$Y$97:$Y$100005),0)} -> 1 | AM28: {=ROUNDUP(SUMPRODUCT(($I$97:$I$100005=$AE28)*($AD$97:$AD$100005="Actual")*AM$97:AM$100005*$Y$97:$Y$100005),0)} -> 1 | AN28: {=ROUNDUP(SUMPRODUCT(($I$97:$I$100005=$AE28)*($AD$97:$AD$100005="Actual")*AN$97:AN$100005*$Y$97:$Y$100005),0)} -> 0
AE29: Geomecánica | AF29: {=ROUNDUP(SUMPRODUCT(($I$97:$I$100005=$AE29)*($AD$97:$AD$100005="Actual")*AF$97:AF$100005*$Y$97:$Y$100005),0)} -> 0 | AG29: {=ROUNDUP(SUMPRODUCT(($I$97:$I$100005=$AE29)*($AD$97:$AD$100005="Actual")*AG$97:AG$100005*$Y$97:$Y$100005),0)} -> 0 | AH29: {=ROUNDUP(SUMPRODUCT(($I$97:$I$100005=$AE29)*($AD$97:$AD$100005="Actual")*AH$97:AH$100005*$Y$97:$Y$100005),0)} -> 0 | AI29: {=ROUNDUP(SUMPRODUCT(($I$97:$I$100005=$AE29)*($AD$97:$AD$100005="Actual")*AI$97:AI$100005*$Y$97:$Y$100005),0)} -> 0 | AJ29: {=ROUNDUP(SUMPRODUCT(($I$97:$I$100005=$AE29)*($AD$97:$AD$100005="Actual")*AJ$97:AJ$100005*$Y$97:$Y$100005),0)} -> 0 | AK29: {=ROUNDUP(SUMPRODUCT(($I$97:$I$100005=$AE29)*($AD$97:$AD$100005="Actual")*AK$97:AK$100005*$Y$97:$Y$100005),0)} -> 0 | AL29: {=ROUNDUP(SUMPRODUCT(($I$97:$I$100005=$AE29)*($AD$97:$AD$100005="Actual")*AL$97:AL$100005*$Y$97:$Y$100005),0)} -> 0 | AM29: {=ROUNDUP(SUMPRODUCT(($I$97:$I$100005=$AE29)*($AD$97:$AD$100005="Actual")*AM$97:AM$100005*$Y$97:$Y$100005),0)} -> 0 | AN29: {=ROUNDUP(SUMPRODUCT(($I$97:$I$100005=$AE29)*($AD$97:$AD$100005="Actual")*AN$97:AN$100005*$Y$97:$Y$100005),0)} -> 0
AE30: Ingeniero Senior | AF30: =+SUM(AF31:AF33) -> 3 | AG30: =+SUM(AG31:AG33) -> 3 | AH30: =+SUM(AH31:AH33) -> 2 | AI30: =+SUM(AI31:AI33) -> 2 | AJ30: =+SUM(AJ31:AJ33) -> 2 | AK30: =+SUM(AK31:AK33) -> 2 | AL30: =+SUM(AL31:AL33) -> 2 | AM30: =+SUM(AM31:AM33) -> 2 | AN30: =+SUM(AN31:AN33) -> 1
AE31: Open Pit | AF31: {=ROUNDUP(SUMPRODUCT(($I$97:$I$100005=$AE31)*($AD$97:$AD$100005="Actual")*AF$97:AF$100005*$Z$97:$Z$100005),0)} -> 1 | AG31: {=ROUNDUP(SUMPRODUCT(($I$97:$I$100005=$AE31)*($AD$97:$AD$100005="Actual")*AG$97:AG$100005*$Z$97:$Z$100005),0)} -> 1 | AH31: {=ROUNDUP(SUMPRODUCT(($I$97:$I$100005=$AE31)*($AD$97:$AD$100005="Actual")*AH$97:AH$100005*$Z$97:$Z$100005),0)} -> 1 | AI31: {=ROUNDUP(SUMPRODUCT(($I$97:$I$100005=$AE31)*($AD$97:$AD$100005="Actual")*AI$97:AI$100005*$Z$97:$Z$100005),0)} -> 1 | AJ31: {=ROUNDUP(SUMPRODUCT(($I$97:$I$100005=$AE31)*($AD$97:$AD$100005="Actual")*AJ$97:AJ$100005*$Z$97:$Z$100005),0)} -> 1 | AK31: {=ROUNDUP(SUMPRODUCT(($I$97:$I$100005=$AE31)*($AD$97:$AD$100005="Actual")*AK$97:AK$100005*$Z$97:$Z$100005),0)} -> 1 | AL31: {=ROUNDUP(SUMPRODUCT(($I$97:$I$100005=$AE31)*($AD$97:$AD$100005="Actual")*AL$97:AL$100005*$Z$97:$Z$100005),0)} -> 1 | AM31: {=ROUNDUP(SUMPRODUCT(($I$97:$I$100005=$AE31)*($AD$97:$AD$100005="Actual")*AM$97:AM$100005*$Z$97:$Z$100005),0)} -> 1 | AN31: {=ROUNDUP(SUMPRODUCT(($I$97:$I$100005=$AE31)*($AD$97:$AD$100005="Actual")*AN$97:AN$100005*$Z$97:$Z$100005),0)} -> 1
AE32: Subterránea | AF32: {=ROUNDUP(SUMPRODUCT(($I$97:$I$100005=$AE32)*($AD$97:$AD$100005="Actual")*AF$97:AF$100005*$Z$97:$Z$100005),0)} -> 2 | AG32: {=ROUNDUP(SUMPRODUCT(($I$97:$I$100005=$AE32)*($AD$97:$AD$100005="Actual")*AG$97:AG$100005*$Z$97:$Z$100005),0)} -> 2 | AH32: {=ROUNDUP(SUMPRODUCT(($I$97:$I$100005=$AE32)*($AD$97:$AD$100005="Actual")*AH$97:AH$100005*$Z$97:$Z$100005),0)} -> 1 | AI32: {=ROUNDUP(SUMPRODUCT(($I$97:$I$100005=$AE32)*($AD$97:$AD$100005="Actual")*AI$97:AI$100005*$Z$97:$Z$100005),0)} -> 1 | AJ32: {=ROUNDUP(SUMPRODUCT(($I$97:$I$100005=$AE32)*($AD$97:$AD$100005="Actual")*AJ$97:AJ$100005*$Z$97:$Z$100005),0)} -> 1 | AK32: {=ROUNDUP(SUMPRODUCT(($I$97:$I$100005=$AE32)*($AD$97:$AD$100005="Actual")*AK$97:AK$100005*$Z$97:$Z$100005),0)} -> 1 | AL32: {=ROUNDUP(SUMPRODUCT(($I$97:$I$100005=$AE32)*($AD$97:$AD$100005="Actual")*AL$97:AL$100005*$Z$97:$Z$100005),0)} -> 1 | AM32: {=ROUNDUP(SUMPRODUCT(($I$97:$I$100005=$AE32)*($AD$97:$AD$100005="Actual")*AM$97:AM$100005*$Z$97:$Z$100005),0)} -> 1 | AN32: {=ROUNDUP(SUMPRODUCT(($I$97:$I$100005=$AE32)*($AD$97:$AD$100005="Actual")*AN$97:AN$100005*$Z$97:$Z$100005),0)} -> 0
AE33: Geomecánica | AF33: {=ROUNDUP(SUMPRODUCT(($I$97:$I$100005=$AE33)*($AD$97:$AD$100005="Actual")*AF$97:AF$100005*$Z$97:$Z$100005),0)} -> 0 | AG33: {=ROUNDUP(SUMPRODUCT(($I$97:$I$100005=$AE33)*($AD$97:$AD$100005="Actual")*AG$97:AG$100005*$Z$97:$Z$100005),0)} -> 0 | AH33: {=ROUNDUP(SUMPRODUCT(($I$97:$I$100005=$AE33)*($AD$97:$AD$100005="Actual")*AH$97:AH$100005*$Z$97:$Z$100005),0)} -> 0 | AI33: {=ROUNDUP(SUMPRODUCT(($I$97:$I$100005=$AE33)*($AD$97:$AD$100005="Actual")*AI$97:AI$100005*$Z$97:$Z$100005),0)} -> 0 | AJ33: {=ROUNDUP(SUMPRODUCT(($I$97:$I$100005=$AE33)*($AD$97:$AD$100005="Actual")*AJ$97:AJ$100005*$Z$97:$Z$100005),0)} -> 0 | AK33: {=ROUNDUP(SUMPRODUCT(($I$97:$I$100005=$AE33)*($AD$97:$AD$100005="Actual")*AK$97:AK$100005*$Z$97:$Z$100005),0)} -> 0 | AL33: {=ROUNDUP(SUMPRODUCT(($I$97:$I$100005=$AE33)*($AD$97:$AD$100005="Actual")*AL$97:AL$100005*$Z$97:$Z$100005),0)} -> 0 | AM33: {=ROUNDUP(SUMPRODUCT(($I$97:$I$100005=$AE33)*($AD$97:$AD$100005="Actual")*AM$97:AM$100005*$Z$97:$Z$100005),0)} -> 0 | AN33: {=ROUNDUP(SUMPRODUCT(($I$97:$I$100005=$AE33)*($AD$97:$AD$100005="Actual")*AN$97:AN$100005*$Z$97:$Z$100005),0)} -> 0
AE34: Ingeniero de Proyecto | AF34: =+SUM(AF35:AF37) -> 6 | AG34: =+SUM(AG35:AG37) -> 6 | AH34: =+SUM(AH35:AH37) -> 4 | AI34: =+SUM(AI35:AI37) -> 3 | AJ34: =+SUM(AJ35:AJ37) -> 2 | AK34: =+SUM(AK35:AK37) -> 2 | AL34: =+SUM(AL35:AL37) -> 2 | AM34: =+SUM(AM35:AM37) -> 2 | AN34: =+SUM(AN35:AN37) -> 1
AE35: Open Pit | AF35: {=ROUNDUP(SUMPRODUCT(($I$97:$I$100005=$AE35)*($AD$97:$AD$100005="Actual")*AF$97:AF$100005*$AA$97:$AA$100005),0)} -> 2 | AG35: {=ROUNDUP(SUMPRODUCT(($I$97:$I$100005=$AE35)*($AD$97:$AD$100005="Actual")*AG$97:AG$100005*$AA$97:$AA$100005),0)} -> 2 | AH35: {=ROUNDUP(SUMPRODUCT(($I$97:$I$100005=$AE35)*($AD$97:$AD$100005="Actual")*AH$97:AH$100005*$AA$97:$AA$100005),0)} -> 1 | AI35: {=ROUNDUP(SUMPRODUCT(($I$97:$I$100005=$AE35)*($AD$97:$AD$100005="Actual")*AI$97:AI$100005*$AA$97:$AA$100005),0)} -> 1 | AJ35: {=ROUNDUP(SUMPRODUCT(($I$97:$I$100005=$AE35)*($AD$97:$AD$100005="Actual")*AJ$97:AJ$100005*$AA$97:$AA$100005),0)} -> 1 | AK35: {=ROUNDUP(SUMPRODUCT(($I$97:$I$100005=$AE35)*($AD$97:$AD$100005="Actual")*AK$97:AK$100005*$AA$97:$AA$100005),0)} -> 1 | AL35: {=ROUNDUP(SUMPRODUCT(($I$97:$I$100005=$AE35)*($AD$97:$AD$100005="Actual")*AL$97:AL$100005*$AA$97:$AA$100005),0)} -> 1 | AM35: {=ROUNDUP(SUMPRODUCT(($I$97:$I$100005=$AE35)*($AD$97:$AD$100005="Actual")*AM$97:AM$100005*$AA$97:$AA$100005),0)} -> 1 | AN35: {=ROUNDUP(SUMPRODUCT(($I$97:$I$100005=$AE35)*($AD$97:$AD$100005="Actual")*AN$97:AN$100005*$AA$97:$AA$100005),0)} -> 1
AE36: Subterránea | AF36: {=ROUNDUP(SUMPRODUCT(($I$97:$I$100005=$AE36)*($AD$97:$AD$100005="Actual")*AF$97:AF$100005*$AA$97:$AA$100005),0)} -> 4 | AG36: {=ROUNDUP(SUMPRODUCT(($I$97:$I$100005=$AE36)*($AD$97:$AD$100005="Actual")*AG$97:AG$100005*$AA$97:$AA$100005),0)} -> 4 | AH36: {=ROUNDUP(SUMPRODUCT(($I$97:$I$100005=$AE36)*($AD$97:$AD$100005="Actual")*AH$97:AH$100005*$AA$97:$AA$100005),0)} -> 3 | AI36: {=ROUNDUP(SUMPRODUCT(($I$97:$I$100005=$AE36)*($AD$97:$AD$100005="Actual")*AI$97:AI$100005*$AA$97:$AA$100005),0)} -> 2 | AJ36: {=ROUNDUP(SUMPRODUCT(($I$97:$I$100005=$AE36)*($AD$97:$AD$100005="Actual")*AJ$97:AJ$100005*$AA$97:$AA$100005),0)} -> 1 | AK36: {=ROUNDUP(SUMPRODUCT(($I$97:$I$100005=$AE36)*($AD$97:$AD$100005="Actual")*AK$97:AK$100005*$AA$97:$AA$100005),0)} -> 1 | AL36: {=ROUNDUP(SUMPRODUCT(($I$97:$I$100005=$AE36)*($AD$97:$AD$100005="Actual")*AL$97:AL$100005*$AA$97:$AA$100005),0)} -> 1 | AM36: {=ROUNDUP(SUMPRODUCT(($I$97:$I$100005=$AE36)*($AD$97:$AD$100005="Actual")*AM$97:AM$100005*$AA$97:$AA$100005),0)} -> 1 | AN36: {=ROUNDUP(SUMPRODUCT(($I$97:$I$100005=$AE36)*($AD$97:$AD$100005="Actual")*AN$97:AN$100005*$AA$97:$AA$100005),0)} -> 0
AE37: Geomecánica | AF37: {=ROUNDUP(SUMPRODUCT(($I$97:$I$100005=$AE37)*($AD$97:$AD$100005="Actual")*AF$97:AF$100005*$AA$97:$AA$100005),0)} -> 0 | AG37: {=ROUNDUP(SUMPRODUCT(($I$97:$I$100005=$AE37)*($AD$97:$AD$100005="Actual")*AG$97:AG$100005*$AA$97:$AA$100005),0)} -> 0 | AH37: {=ROUNDUP(SUMPRODUCT(($I$97:$I$100005=$AE37)*($AD$97:$AD$100005="Actual")*AH$97:AH$100005*$AA$97:$AA$100005),0)} -> 0 | AI37: {=ROUNDUP(SUMPRODUCT(($I$97:$I$100005=$AE37)*($AD$97:$AD$100005="Actual")*AI$97:AI$100005*$AA$97:$AA$100005),0)} -> 0 | AJ37: {=ROUNDUP(SUMPRODUCT(($I$97:$I$100005=$AE37)*($AD$97:$AD$100005="Actual")*AJ$97:AJ$100005*$AA$97:$AA$100005),0)} -> 0 | AK37: {=ROUNDUP(SUMPRODUCT(($I$97:$I$100005=$AE37)*($AD$97:$AD$100005="Actual")*AK$97:AK$100005*$AA$97:$AA$100005),0)} -> 0 | AL37: {=ROUNDUP(SUMPRODUCT(($I$97:$I$100005=$AE37)*($AD$97:$AD$100005="Actual")*AL$97:AL$100005*$AA$97:$AA$100005),0)} -> 0 | AM37: {=ROUNDUP(SUMPRODUCT(($I$97:$I$100005=$AE37)*($AD$97:$AD$100005="Actual")*AM$97:AM$100005*$AA$97:$AA$100005),0)} -> 0 | AN37: {=ROUNDUP(SUMPRODUCT(($I$97:$I$100005=$AE37)*($AD$97:$AD$100005="Actual")*AN$97:AN$100005*$AA$97:$AA$100005),0)} -> 0
AE38: Ingeniero Junior | AF38: =+SUM(AF39:AF41) -> 4 | AG38: =+SUM(AG39:AG41) -> 3 | AH38: =+SUM(AH39:AH41) -> 3 | AI38: =+SUM(AI39:AI41) -> 3 | AJ38: =+SUM(AJ39:AJ41) -> 2 | AK38: =+SUM(AK39:AK41) -> 2 | AL38: =+SUM(AL39:AL41) -> 2 | AM38: =+SUM(AM39:AM41) -> 2 | AN38: =+SUM(AN39:AN41) -> 1
AE39: Open Pit | AF39: {=ROUNDUP(SUMPRODUCT(($I$97:$I$100005=$AE39)*($AD$97:$AD$100005="Actual")*AF$97:AF$100005*$AB$97:$AB$100005),0)} -> 2 | AG39: {=ROUNDUP(SUMPRODUCT(($I$97:$I$100005=$AE39)*($AD$97:$AD$100005="Actual")*AG$97:AG$100005*$AB$97:$AB$100005),0)} -> 1 | AH39: {=ROUNDUP(SUMPRODUCT(($I$97:$I$100005=$AE39)*($AD$97:$AD$100005="Actual")*AH$97:AH$100005*$AB$97:$AB$100005),0)} -> 1 | AI39: {=ROUNDUP(SUMPRODUCT(($I$97:$I$100005=$AE39)*($AD$97:$AD$100005="Actual")*AI$97:AI$100005*$AB$97:$AB$100005),0)} -> 1 | AJ39: {=ROUNDUP(SUMPRODUCT(($I$97:$I$100005=$AE39)*($AD$97:$AD$100005="Actual")*AJ$97:AJ$100005*$AB$97:$AB$100005),0)} -> 1 | AK39: {=ROUNDUP(SUMPRODUCT(($I$97:$I$100005=$AE39)*($AD$97:$AD$100005="Actual")*AK$97:AK$100005*$AB$97:$AB$100005),0)} -> 1 | AL39: {=ROUNDUP(SUMPRODUCT(($I$97:$I$100005=$AE39)*($AD$97:$AD$100005="Actual")*AL$97:AL$100005*$AB$97:$AB$100005),0)} -> 1 | AM39: {=ROUNDUP(SUMPRODUCT(($I$97:$I$100005=$AE39)*($AD$97:$AD$100005="Actual")*AM$97:AM$100005*$AB$97:$AB$100005),0)} -> 1 | AN39: {=ROUNDUP(SUMPRODUCT(($I$97:$I$100005=$AE39)*($AD$97:$AD$100005="Actual")*AN$97:AN$100005*$AB$97:$AB$100005),0)} -> 1
AE40: Subterránea | AF40: {=ROUNDUP(SUMPRODUCT(($I$97:$I$100005=$AE40)*($AD$97:$AD$100005="Actual")*AF$97:AF$100005*$AB$97:$AB$100005),0)} -> 2 | AG40: {=ROUNDUP(SUMPRODUCT(($I$97:$I$100005=$AE40)*($AD$97:$AD$100005="Actual")*AG$97:AG$100005*$AB$97:$AB$100005),0)} -> 2 | AH40: {=ROUNDUP(SUMPRODUCT(($I$97:$I$100005=$AE40)*($AD$97:$AD$100005="Actual")*AH$97:AH$100005*$AB$97:$AB$100005),0)} -> 2 | AI40: {=ROUNDUP(SUMPRODUCT(($I$97:$I$100005=$AE40)*($AD$97:$AD$100005="Actual")*AI$97:AI$100005*$AB$97:$AB$100005),0)} -> 2 | AJ40: {=ROUNDUP(SUMPRODUCT(($I$97:$I$100005=$AE40)*($AD$97:$AD$100005="Actual")*AJ$97:AJ$100005*$AB$97:$AB$100005),0)} -> 1 | AK40: {=ROUNDUP(SUMPRODUCT(($I$97:$I$100005=$AE40)*($AD$97:$AD$100005="Actual")*AK$97:AK$100005*$AB$97:$AB$100005),0)} -> 1 | AL40: {=ROUNDUP(SUMPRODUCT(($I$97:$I$100005=$AE40)*($AD$97:$AD$100005="Actual")*AL$97:AL$100005*$AB$97:$AB$100005),0)} -> 1 | AM40: {=ROUNDUP(SUMPRODUCT(($I$97:$I$100005=$AE40)*($AD$97:$AD$100005="Actual")*AM$97:AM$100005*$AB$97:$AB$100005),0)} -> 1 | AN40: {=ROUNDUP(SUMPRODUCT(($I$97:$I$100005=$AE40)*($AD$97:$AD$100005="Actual")*AN$97:AN$100005*$AB$97:$AB$100005),0)} -> 0
AE41: Geomecánica | AF41: {=ROUNDUP(SUMPRODUCT(($I$97:$I$100005=$AE41)*($AD$97:$AD$100005="Actual")*AF$97:AF$100005*$AB$97:$AB$100005),0)} -> 0 | AG41: {=ROUNDUP(SUMPRODUCT(($I$97:$I$100005=$AE41)*($AD$97:$AD$100005="Actual")*AG$97:AG$100005*$AB$97:$AB$100005),0)} -> 0 | AH41: {=ROUNDUP(SUMPRODUCT(($I$97:$I$100005=$AE41)*($AD$97:$AD$100005="Actual")*AH$97:AH$100005*$AB$97:$AB$100005),0)} -> 0 | AI41: {=ROUNDUP(SUMPRODUCT(($I$97:$I$100005=$AE41)*($AD$97:$AD$100005="Actual")*AI$97:AI$100005*$AB$97:$AB$100005),0)} -> 0 | AJ41: {=ROUNDUP(SUMPRODUCT(($I$97:$I$100005=$AE41)*($AD$97:$AD$100005="Actual")*AJ$97:AJ$100005*$AB$97:$AB$100005),0)} -> 0 | AK41: {=ROUNDUP(SUMPRODUCT(($I$97:$I$100005=$AE41)*($AD$97:$AD$100005="Actual")*AK$97:AK$100005*$AB$97:$AB$100005),0)} -> 0 | AL41: {=ROUNDUP(SUMPRODUCT(($I$97:$I$100005=$AE41)*($AD$97:$AD$100005="Actual")*AL$97:AL$100005*$AB$97:$AB$100005),0)} -> 0 | AM41: {=ROUNDUP(SUMPRODUCT(($I$97:$I$100005=$AE41)*($AD$97:$AD$100005="Actual")*AM$97:AM$100005*$AB$97:$AB$100005),0)} -> 0 | AN41: {=ROUNDUP(SUMPRODUCT(($I$97:$I$100005=$AE41)*($AD$97:$AD$100005="Actual")*AN$97:AN$100005*$AB$97:$AB$100005),0)} -> 0
AE42: Total | AF42: =+AF38+AF34+AF30+AF26+AF22 -> 19 | AG42: =+AG38+AG34+AG30+AG26+AG22 -> 18 | AH42: =+AH38+AH34+AH30+AH26+AH22 -> 14 | AI42: =+AI38+AI34+AI30+AI26+AI22 -> 12 | AJ42: =+AJ38+AJ34+AJ30+AJ26+AJ22 -> 10 | AK42: =+AK38+AK34+AK30+AK26+AK22 -> 10 | AL42: =+AL38+AL34+AL30+AL26+AL22 -> 10 | AM42: =+AM38+AM34+AM30+AM26+AM22 -> 10 | AN42: =+AN38+AN34+AN30+AN26+AN22 -> 5
AD43: Actuales + Asignados | AE43: Director de Proyecto | AF43: =+SUM(AF44:AF46) -> 3 | AG43: =+SUM(AG44:AG46) -> 4 | AH43: =+SUM(AH44:AH46) -> 3 | AI43: =+SUM(AI44:AI46) -> 3 | AJ43: =+SUM(AJ44:AJ46) -> 3 | AK43: =+SUM(AK44:AK46) -> 3 | AL43: =+SUM(AL44:AL46) -> 3 | AM43: =+SUM(AM44:AM46) -> 3 | AN43: =+SUM(AN44:AN46) -> 2
AE44: Open Pit | AF44: {=ROUNDUP(SUMPRODUCT(($I$97:$I$100005=$AE44)*($AD$97:$AD$100005="Actual")*AF$97:AF$100005*$X$97:$X$100005),0)+ROUNDUP(SUMPRODUCT(($I$97:$I$100005=$AE44)*($AD$97:$AD$100005="Asignado")*AF$97:AF$100005*$X$97:$X$100005),0)} -> 1 | AG44: {=ROUNDUP(SUMPRODUCT(($I$97:$I$100005=$AE44)*($AD$97:$AD$100005="Actual")*AG$97:AG$100005*$X$97:$X$100005),0)+ROUNDUP(SUMPRODUCT(($I$97:$I$100005=$AE44)*($AD$97:$AD$100005="Asignado")*AG$97:AG$100005*$X$97:$X$100005),0)} -> 1 | AH44: {=ROUNDUP(SUMPRODUCT(($I$97:$I$100005=$AE44)*($AD$97:$AD$100005="Actual")*AH$97:AH$100005*$X$97:$X$100005),0)+ROUNDUP(SUMPRODUCT(($I$97:$I$100005=$AE44)*($AD$97:$AD$100005="Asignado")*AH$97:AH$100005*$X$97:$X$100005),0)} -> 1 | AI44: {=ROUNDUP(SUMPRODUCT(($I$97:$I$100005=$AE44)*($AD$97:$AD$100005="Actual")*AI$97:AI$100005*$X$97:$X$100005),0)+ROUNDUP(SUMPRODUCT(($I$97:$I$100005=$AE44)*($AD$97:$AD$100005="Asignado")*AI$97:AI$100005*$X$97:$X$100005),0)} -> 1 | AJ44: {=ROUNDUP(SUMPRODUCT(($I$97:$I$100005=$AE44)*($AD$97:$AD$100005="Actual")*AJ$97:AJ$100005*$X$97:$X$100005),0)+ROUNDUP(SUMPRODUCT(($I$97:$I$100005=$AE44)*($AD$97:$AD$100005="Asignado")*AJ$97:AJ$100005*$X$97:$X$100005),0)} -> 1 | AK44: {=ROUNDUP(SUMPRODUCT(($I$97:$I$100005=$AE44)*($AD$97:$AD$100005="Actual")*AK$97:AK$100005*$X$97:$X$100005),0)+ROUNDUP(SUMPRODUCT(($I$97:$I$100005=$AE44)*($AD$97:$AD$100005="Asignado")*AK$97:AK$100005*$X$97:$X$100005),0)} -> 1 | AL44: {=ROUNDUP(SUMPRODUCT(($I$97:$I$100005=$AE44)*($AD$97:$AD$100005="Actual")*AL$97:AL$100005*$X$97:$X$100005),0)+ROUNDUP(SUMPRODUCT(($I$97:$I$100005=$AE44)*($AD$97:$AD$100005="Asignado")*AL$97:AL$100005*$X$97:$X$100005),0)} -> 1 | AM44: {=ROUNDUP(SUMPRODUCT(($I$97:$I$100005=$AE44)*($AD$97:$AD$100005="Actual")*AM$97:AM$100005*$X$97:$X$100005),0)+ROUNDUP(SUMPRODUCT(($I$97:$I$100005=$AE44)*($AD$97:$AD$100005="Asignado")*AM$97:AM$100005*$X$97:$X$100005),0)} -> 1 | AN44: {=ROUNDUP(SUMPRODUCT(($I$97:$I$100005=$AE44)*($AD$97:$AD$100005="Actual")*AN$97:AN$100005*$X$97:$X$100005),0)+ROUNDUP(SUMPRODUCT(($I$97:$I$100005=$AE44)*($AD$97:$AD$100005="Asignado")*AN$97:AN$100005*$X$97:$X$100005),0)} -> 1
AE45: Subterránea | AF45: {=ROUNDUP(SUMPRODUCT(($I$97:$I$100005=$AE45)*($AD$97:$AD$100005="Actual")*AF$97:AF$100005*$X$97:$X$100005),0)+ROUNDUP(SUMPRODUCT(($I$97:$I$100005=$AE45)*($AD$97:$AD$100005="Asignado")*AF$97:AF$100005*$X$97:$X$100005),0)} -> 2 | AG45: {=ROUNDUP(SUMPRODUCT(($I$97:$I$100005=$AE45)*($AD$97:$AD$100005="Actual")*AG$97:AG$100005*$X$97:$X$100005),0)+ROUNDUP(SUMPRODUCT(($I$97:$I$100005=$AE45)*($AD$97:$AD$100005="Asignado")*AG$97:AG$100005*$X$97:$X$100005),0)} -> 3 | AH45: {=ROUNDUP(SUMPRODUCT(($I$97:$I$100005=$AE45)*($AD$97:$AD$100005="Actual")*AH$97:AH$100005*$X$97:$X$100005),0)+ROUNDUP(SUMPRODUCT(($I$97:$I$100005=$AE45)*($AD$97:$AD$100005="Asignado")*AH$97:AH$100005*$X$97:$X$100005),0)} -> 2 | AI45: {=ROUNDUP(SUMPRODUCT(($I$97:$I$100005=$AE45)*($AD$97:$AD$100005="Actual")*AI$97:AI$100005*$X$97:$X$100005),0)+ROUNDUP(SUMPRODUCT(($I$97:$I$100005=$AE45)*($AD$97:$AD$100005="Asignado")*AI$97:AI$100005*$X$97:$X$100005),0)} -> 2 | AJ45: {=ROUNDUP(SUMPRODUCT(($I$97:$I$100005=$AE45)*($AD$97:$AD$100005="Actual")*AJ$97:AJ$100005*$X$97:$X$100005),0)+ROUNDUP(SUMPRODUCT(($I$97:$I$100005=$AE45)*($AD$97:$AD$100005="Asignado")*AJ$97:AJ$100005*$X$97:$X$100005),0)} -> 2 | AK45: {=ROUNDUP(SUMPRODUCT(($I$97:$I$100005=$AE45)*($AD$97:$AD$100005="Actual")*AK$97:AK$100005*$X$97:$X$100005),0)+ROUNDUP(SUMPRODUCT(($I$97:$I$100005=$AE45)*($AD$97:$AD$100005="Asignado")*AK$97:AK$100005*$X$97:$X$100005),0)} -> 2 | AL45: {=ROUNDUP(SUMPRODUCT(($I$97:$I$100005=$AE45)*($AD$97:$AD$100005="Actual")*AL$97:AL$100005*$X$97:$X$100005),0)+ROUNDUP(SUMPRODUCT(($I$97:$I$100005=$AE45)*($AD$97:$AD$100005="Asignado")*AL$97:AL$100005*$X$97:$X$100005),0)} -> 2 | AM45: {=ROUNDUP(SUMPRODUCT(($I$97:$I$100005=$AE45)*($AD$97:$AD$100005="Actual")*AM$97:AM$100005*$X$97:$X$100005),0)+ROUNDUP(SUMPRODUCT(($I$97:$I$100005=$AE45)*($AD$97:$AD$100005="Asignado")*AM$97:AM$100005*$X$97:$X$100005),0)} -> 2 | AN45: {=ROUNDUP(SUMPRODUCT(($I$97:$I$100005=$AE45)*($AD$97:$AD$100005="Actual")*AN$97:AN$100005*$X$97:$X$100005),0)+ROUNDUP(SUMPRODUCT(($I$97:$I$100005=$AE45)*($AD$97:$AD$100005="Asignado")*AN$97:AN$100005*$X$97:$X$100005),0)} -> 1
AE46: Geomecánica | AF46: {=ROUNDUP(SUMPRODUCT(($I$97:$I$100005=$AE46)*($AD$97:$AD$100005="Actual")*AF$97:AF$100005*$X$97:$X$100005),0)+ROUNDUP(SUMPRODUCT(($I$97:$I$100005=$AE46)*($AD$97:$AD$100005="Asignado")*AF$97:AF$100005*$X$97:$X$100005),0)} -> 0 | AG46: {=ROUNDUP(SUMPRODUCT(($I$97:$I$100005=$AE46)*($AD$97:$AD$100005="Actual")*AG$97:AG$100005*$X$97:$X$100005),0)+ROUNDUP(SUMPRODUCT(($I$97:$I$100005=$AE46)*($AD$97:$AD$100005="Asignado")*AG$97:AG$100005*$X$97:$X$100005),0)} -> 0 | AH46: {=ROUNDUP(SUMPRODUCT(($I$97:$I$100005=$AE46)*($AD$97:$AD$100005="Actual")*AH$97:AH$100005*$X$97:$X$100005),0)+ROUNDUP(SUMPRODUCT(($I$97:$I$100005=$AE46)*($AD$97:$AD$100005="Asignado")*AH$97:AH$100005*$X$97:$X$100005),0)} -> 0 | AI46: {=ROUNDUP(SUMPRODUCT(($I$97:$I$100005=$AE46)*($AD$97:$AD$100005="Actual")*AI$97:AI$100005*$X$97:$X$100005),0)+ROUNDUP(SUMPRODUCT(($I$97:$I$100005=$AE46)*($AD$97:$AD$100005="Asignado")*AI$97:AI$100005*$X$97:$X$100005),0)} -> 0 | AJ46: {=ROUNDUP(SUMPRODUCT(($I$97:$I$100005=$AE46)*($AD$97:$AD$100005="Actual")*AJ$97:AJ$100005*$X$97:$X$100005),0)+ROUNDUP(SUMPRODUCT(($I$97:$I$100005=$AE46)*($AD$97:$AD$100005="Asignado")*AJ$97:AJ$100005*$X$97:$X$100005),0)} -> 0 | AK46: {=ROUNDUP(SUMPRODUCT(($I$97:$I$100005=$AE46)*($AD$97:$AD$100005="Actual")*AK$97:AK$100005*$X$97:$X$100005),0)+ROUNDUP(SUMPRODUCT(($I$97:$I$100005=$AE46)*($AD$97:$AD$100005="Asignado")*AK$97:AK$100005*$X$97:$X$100005),0)} -> 0 | AL46: {=ROUNDUP(SUMPRODUCT(($I$97:$I$100005=$AE46)*($AD$97:$AD$100005="Actual")*AL$97:AL$100005*$X$97:$X$100005),0)+ROUNDUP(SUMPRODUCT(($I$97:$I$100005=$AE46)*($AD$97:$AD$100005="Asignado")*AL$97:AL$100005*$X$97:$X$100005),0)} -> 0 | AM46: {=ROUNDUP(SUMPRODUCT(($I$97:$I$100005=$AE46)*($AD$97:$AD$100005="Actual")*AM$97:AM$100005*$X$97:$X$100005),0)+ROUNDUP(SUMPRODUCT(($I$97:$I$100005=$AE46)*($AD$97:$AD$100005="Asignado")*AM$97:AM$100005*$X$97:$X$100005),0)} -> 0 | AN46: {=ROUNDUP(SUMPRODUCT(($I$97:$I$100005=$AE46)*($AD$97:$AD$100005="Actual")*AN$97:AN$100005*$X$97:$X$100005),0)+ROUNDUP(SUMPRODUCT(($I$97:$I$100005=$AE46)*($AD$97:$AD$100005="Asignado")*AN$97:AN$100005*$X$97:$X$100005),0)} -> 0
AE47: Ingeniero Principal | AF47: =+SUM(AF48:AF50) -> 3 | AG47: =+SUM(AG48:AG50) -> 4 | AH47: =+SUM(AH48:AH50) -> 4 | AI47: =+SUM(AI48:AI50) -> 3 | AJ47: =+SUM(AJ48:AJ50) -> 3 | AK47: =+SUM(AK48:AK50) -> 3 | AL47: =+SUM(AL48:AL50) -> 3 | AM47: =+SUM(AM48:AM50) -> 3 | AN47: =+SUM(AN48:AN50) -> 2
AE48: Open Pit | AF48: {=ROUNDUP(SUMPRODUCT(($I$97:$I$100005=$AE48)*($AD$97:$AD$100005="Actual")*AF$97:AF$100005*$Y$97:$Y$100005),0)+ROUNDUP(SUMPRODUCT(($I$97:$I$100005=$AE48)*($AD$97:$AD$100005="Asignado")*AF$97:AF$100005*$Y$97:$Y$100005),0)} -> 1 | AG48: {=ROUNDUP(SUMPRODUCT(($I$97:$I$100005=$AE48)*($AD$97:$AD$100005="Actual")*AG$97:AG$100005*$Y$97:$Y$100005),0)+ROUNDUP(SUMPRODUCT(($I$97:$I$100005=$AE48)*($AD$97:$AD$100005="Asignado")*AG$97:AG$100005*$Y$97:$Y$100005),0)} -> 1 | AH48: {=ROUNDUP(SUMPRODUCT(($I$97:$I$100005=$AE48)*($AD$97:$AD$100005="Actual")*AH$97:AH$100005*$Y$97:$Y$100005),0)+ROUNDUP(SUMPRODUCT(($I$97:$I$100005=$AE48)*($AD$97:$AD$100005="Asignado")*AH$97:AH$100005*$Y$97:$Y$100005),0)} -> 1 | AI48: {=ROUNDUP(SUMPRODUCT(($I$97:$I$100005=$AE48)*($AD$97:$AD$100005="Actual")*AI$97:AI$100005*$Y$97:$Y$100005),0)+ROUNDUP(SUMPRODUCT(($I$97:$I$100005=$AE48)*($AD$97:$AD$100005="Asignado")*AI$97:AI$100005*$Y$97:$Y$100005),0)} -> 1 | AJ48: {=ROUNDUP(SUMPRODUCT(($I$97:$I$100005=$AE48)*($AD$97:$AD$100005="Actual")*AJ$97:AJ$100005*$Y$97:$Y$100005),0)+ROUNDUP(SUMPRODUCT(($I$97:$I$100005=$AE48)*($AD$97:$AD$100005="Asignado")*AJ$97:AJ$100005*$Y$97:$Y$100005),0)} -> 1 | AK48: {=ROUNDUP(SUMPRODUCT(($I$97:$I$100005=$AE48)*($AD$97:$AD$100005="Actual")*AK$97:AK$100005*$Y$97:$Y$100005),0)+ROUNDUP(SUMPRODUCT(($I$97:$I$100005=$AE48)*($AD$97:$AD$100005="Asignado")*AK$97:AK$100005*$Y$97:$Y$100005),0)} -> 1 | AL48: {=ROUNDUP(SUMPRODUCT(($I$97:$I$100005=$AE48)*($AD$97:$AD$100005="Actual")*AL$97:AL$100005*$Y$97:$Y$100005),0)+ROUNDUP(SUMPRODUCT(($I$97:$I$100005=$AE48)*($AD$97:$AD$100005="Asignado")*AL$97:AL$100005*$Y$97:$Y$100005),0)} -> 1 | AM48: {=ROUNDUP(SUMPRODUCT(($I$97:$I$100005=$AE48)*($AD$97:$AD$100005="Actual")*AM$97:AM$100005*$Y$97:$Y$100005),0)+ROUNDUP(SUMPRODUCT(($I$97:$I$100005=$AE48)*($AD$97:$AD$100005="Asignado")*AM$97:AM$100005*$Y$97:$Y$100005),0)} -> 1 | AN48: {=ROUNDUP(SUMPRODUCT(($I$97:$I$100005=$AE48)*($AD$97:$AD$100005="Actual")*AN$97:AN$100005*$Y$97:$Y$100005),0)+ROUNDUP(SUMPRODUCT(($I$97:$I$100005=$AE48)*($AD$97:$AD$100005="Asignado")*AN$97:AN$100005*$Y$97:$Y$100005),0)} -> 1
AE49: Subterránea | AF49: {=ROUNDUP(SUMPRODUCT(($I$97:$I$100005=$AE49)*($AD$97:$AD$100005="Actual")*AF$97:AF$100005*$Y$97:$Y$100005),0)+ROUNDUP(SUMPRODUCT(($I$97:$I$100005=$AE49)*($AD$97:$AD$100005="Asignado")*AF$97:AF$100005*$Y$97:$Y$100005),0)} -> 2 | AG49: {=ROUNDUP(SUMPRODUCT(($I$97:$I$100005=$AE49)*($AD$97:$AD$100005="Actual")*AG$97:AG$100005*$Y$97:$Y$100005),0)+ROUNDUP(SUMPRODUCT(($I$97:$I$100005=$AE49)*($AD$97:$AD$100005="Asignado")*AG$97:AG$100005*$Y$97:$Y$100005),0)} -> 3 | AH49: {=ROUNDUP(SUMPRODUCT(($I$97:$I$100005=$AE49)*($AD$97:$AD$100005="Actual")*AH$97:AH$100005*$Y$97:$Y$100005),0)+ROUNDUP(SUMPRODUCT(($I$97:$I$100005=$AE49)*($AD$97:$AD$100005="Asignado")*AH$97:AH$100005*$Y$97:$Y$100005),0)} -> 3 | AI49: {=ROUNDUP(SUMPRODUCT(($I$97:$I$100005=$AE49)*($AD$97:$AD$100005="Actual")*AI$97:AI$100005*$Y$97:$Y$100005),0)+ROUNDUP(SUMPRODUCT(($I$97:$I$100005=$AE49)*($AD$97:$AD$100005="Asignado")*AI$97:AI$100005*$Y$97:$Y$100005),0)} -> 2 | AJ49: {=ROUNDUP(SUMPRODUCT(($I$97:$I$100005=$AE49)*($AD$97:$AD$100005="Actual")*AJ$97:AJ$100005*$Y$97:$Y$100005),0)+ROUNDUP(SUMPRODUCT(($I$97:$I$100005=$AE49)*($AD$97:$AD$100005="Asignado")*AJ$97:AJ$100005*$Y$97:$Y$100005),0)} -> 2 | AK49: {=ROUNDUP(SUMPRODUCT(($I$97:$I$100005=$AE49)*($AD$97:$AD$100005="Actual")*AK$97:AK$100005*$Y$97:$Y$100005),0)+ROUNDUP(SUMPRODUCT(($I$97:$I$100005=$AE49)*($AD$97:$AD$100005="Asignado")*AK$97:AK$100005*$Y$97:$Y$100005),0)} -> 2 | AL49: {=ROUNDUP(SUMPRODUCT(($I$97:$I$100005=$AE49)*($AD$97:$AD$100005="Actual")*AL$97:AL$100005*$Y$97:$Y$100005),0)+ROUNDUP(SUMPRODUCT(($I$97:$I$100005=$AE49)*($AD$97:$AD$100005="Asignado")*AL$97:AL$100005*$Y$97:$Y$100005),0)} -> 2 | AM49: {=ROUNDUP(SUMPRODUCT(($I$97:$I$100005=$AE49)*($AD$97:$AD$100005="Actual")*AM$97:AM$100005*$Y$97:$Y$100005),0)+ROUNDUP(SUMPRODUCT(($I$97:$I$100005=$AE49)*($AD$97:$AD$100005="Asignado")*AM$97:AM$100005*$Y$97:$Y$100005),0)} -> 2 | AN49: {=ROUNDUP(SUMPRODUCT(($I$97:$I$100005=$AE49)*($AD$97:$AD$100005="Actual")*AN$97:AN$100005*$Y$97:$Y$100005),0)+ROUNDUP(SUMPRODUCT(($I$97:$I$100005=$AE49)*($AD$97:$AD$100005="Asignado")*AN$97:AN$100005*$Y$97:$Y$100005),0)} -> 1
AE50: Geomecánica | AF50: {=ROUNDUP(SUMPRODUCT(($I$97:$I$100005=$AE50)*($AD$97:$AD$100005="Actual")*AF$97:AF$100005*$Y$97:$Y$100005),0)+ROUNDUP(SUMPRODUCT(($I$97:$I$100005=$AE50)*($AD$97:$AD$100005="Asignado")*AF$97:AF$100005*$Y$97:$Y$100005),0)} -> 0 | AG50: {=ROUNDUP(SUMPRODUCT(($I$97:$I$100005=$AE50)*($AD$97:$AD$100005="Actual")*AG$97:AG$100005*$Y$97:$Y$100005),0)+ROUNDUP(SUMPRODUCT(($I$97:$I$100005=$AE50)*($AD$97:$AD$100005="Asignado")*AG$97:AG$100005*$Y$97:$Y$100005),0)} -> 0 | AH50: {=ROUNDUP(SUMPRODUCT(($I$97:$I$100005=$AE50)*($AD$97:$AD$100005="Actual")*AH$97:AH$100005*$Y$97:$Y$100005),0)+ROUNDUP(SUMPRODUCT(($I$97:$I$100005=$AE50)*($AD$97:$AD$100005="Asignado")*AH$97:AH$100005*$Y$97:$Y$100005),0)} -> 0 | AI50: {=ROUNDUP(SUMPRODUCT(($I$97:$I$100005=$AE50)*($AD$97:$AD$100005="Actual")*AI$97:AI$100005*$Y$97:$Y$100005),0)+ROUNDUP(SUMPRODUCT(($I$97:$I$100005=$AE50)*($AD$97:$AD$100005="Asignado")*AI$97:AI$100005*$Y$97:$Y$100005),0)} -> 0 | AJ50: {=ROUNDUP(SUMPRODUCT(($I$97:$I$100005=$AE50)*($AD$97:$AD$100005="Actual")*AJ$97:AJ$100005*$Y$97:$Y$100005),0)+ROUNDUP(SUMPRODUCT(($I$97:$I$100005=$AE50)*($AD$97:$AD$100005="Asignado")*AJ$97:AJ$100005*$Y$97:$Y$100005),0)} -> 0 | AK50: {=ROUNDUP(SUMPRODUCT(($I$97:$I$100005=$AE50)*($AD$97:$AD$100005="Actual")*AK$97:AK$100005*$Y$97:$Y$100005),0)+ROUNDUP(SUMPRODUCT(($I$97:$I$100005=$AE50)*($AD$97:$AD$100005="Asignado")*AK$97:AK$100005*$Y$97:$Y$100005),0)} -> 0 | AL50: {=ROUNDUP(SUMPRODUCT(($I$97:$I$100005=$AE50)*($AD$97:$AD$100005="Actual")*AL$97:AL$100005*$Y$97:$Y$100005),0)+ROUNDUP(SUMPRODUCT(($I$97:$I$100005=$AE50)*($AD$97:$AD$100005="Asignado")*AL$97:AL$100005*$Y$97:$Y$100005),0)} -> 0 | AM50: {=ROUNDUP(SUMPRODUCT(($I$97:$I$100005=$AE50)*($AD$97:$AD$100005="Actual")*AM$97:AM$100005*$Y$97:$Y$100005),0)+ROUNDUP(SUMPRODUCT(($I$97:$I$100005=$AE50)*($AD$97:$AD$100005="Asignado")*AM$97:AM$100005*$Y$97:$Y$100005),0)} -> 0 | AN50: {=ROUNDUP(SUMPRODUCT(($I$97:$I$100005=$AE50)*($AD$97:$AD$100005="Actual")*AN$97:AN$100005*$Y$97:$Y$100005),0)+ROUNDUP(SUMPRODUCT(($I$97:$I$100005=$AE50)*($AD$97:$AD$100005="Asignado")*AN$97:AN$100005*$Y$97:$Y$100005),0)} -> 0
AE51: Ingeniero Senior | AF51: =+SUM(AF52:AF54) -> 3 | AG51: =+SUM(AG52:AG54) -> 4 | AH51: =+SUM(AH52:AH54) -> 3 | AI51: =+SUM(AI52:AI54) -> 3 | AJ51: =+SUM(AJ52:AJ54) -> 3 | AK51: =+SUM(AK52:AK54) -> 3 | AL51: =+SUM(AL52:AL54) -> 3 | AM51: =+SUM(AM52:AM54) -> 3 | AN51: =+SUM(AN52:AN54) -> 2
AE52: Open Pit | AF52: {=ROUNDUP(SUMPRODUCT(($I$97:$I$100005=$AE52)*($AD$97:$AD$100005="Actual")*AF$97:AF$100005*$Z$97:$Z$100005),0)+ROUNDUP(SUMPRODUCT(($I$97:$I$100005=$AE52)*($AD$97:$AD$100005="Asignado")*AF$97:AF$100005*$Z$97:$Z$100005),0)} -> 1 | AG52: {=ROUNDUP(SUMPRODUCT(($I$97:$I$100005=$AE52)*($AD$97:$AD$100005="Actual")*AG$97:AG$100005*$Z$97:$Z$100005),0)+ROUNDUP(SUMPRODUCT(($I$97:$I$100005=$AE52)*($AD$97:$AD$100005="Asignado")*AG$97:AG$100005*$Z$97:$Z$100005),0)} -> 1 | AH52: {=ROUNDUP(SUMPRODUCT(($I$97:$I$100005=$AE52)*($AD$97:$AD$100005="Actual")*AH$97:AH$100005*$Z$97:$Z$100005),0)+ROUNDUP(SUMPRODUCT(($I$97:$I$100005=$AE52)*($AD$97:$AD$100005="Asignado")*AH$97:AH$100005*$Z$97:$Z$100005),0)} -> 1 | AI52: {=ROUNDUP(SUMPRODUCT(($I$97:$I$100005=$AE52)*($AD$97:$AD$100005="Actual")*AI$97:AI$100005*$Z$97:$Z$100005),0)+ROUNDUP(SUMPRODUCT(($I$97:$I$100005=$AE52)*($AD$97:$AD$100005="Asignado")*AI$97:AI$100005*$Z$97:$Z$100005),0)} -> 1 | AJ52: {=ROUNDUP(SUMPRODUCT(($I$97:$I$100005=$AE52)*($AD$97:$AD$100005="Actual")*AJ$97:AJ$100005*$Z$97:$Z$100005),0)+ROUNDUP(SUMPRODUCT(($I$97:$I$100005=$AE52)*($AD$97:$AD$100005="Asignado")*AJ$97:AJ$100005*$Z$97:$Z$100005),0)} -> 1 | AK52: {=ROUNDUP(SUMPRODUCT(($I$97:$I$100005=$AE52)*($AD$97:$AD$100005="Actual")*AK$97:AK$100005*$Z$97:$Z$100005),0)+ROUNDUP(SUMPRODUCT(($I$97:$I$100005=$AE52)*($AD$97:$AD$100005="Asignado")*AK$97:AK$100005*$Z$97:$Z$100005),0)} -> 1 | AL52: {=ROUNDUP(SUMPRODUCT(($I$97:$I$100005=$AE52)*($AD$97:$AD$100005="Actual")*AL$97:AL$100005*$Z$97:$Z$100005),0)+ROUNDUP(SUMPRODUCT(($I$97:$I$100005=$AE52)*($AD$97:$AD$100005="Asignado")*AL$97:AL$100005*$Z$97:$Z$100005),0)} -> 1 | AM52: {=ROUNDUP(SUMPRODUCT(($I$97:$I$100005=$AE52)*($AD$97:$AD$100005="Actual")*AM$97:AM$100005*$Z$97:$Z$100005),0)+ROUNDUP(SUMPRODUCT(($I$97:$I$100005=$AE52)*($AD$97:$AD$100005="Asignado")*AM$97:AM$100005*$Z$97:$Z$100005),0)} -> 1 | AN52: {=ROUNDUP(SUMPRODUCT(($I$97:$I$100005=$AE52)*($AD$97:$AD$100005="Actual")*AN$97:AN$100005*$Z$97:$Z$100005),0)+ROUNDUP(SUMPRODUCT(($I$97:$I$100005=$AE52)*($AD$97:$AD$100005="Asignado")*AN$97:AN$100005*$Z$97:$Z$100005),0)} -> 1
AE53: Subterránea | AF53: {=ROUNDUP(SUMPRODUCT(($I$97:$I$100005=$AE53)*($AD$97:$AD$100005="Actual")*AF$97:AF$100005*$Z$97:$Z$100005),0)+ROUNDUP(SUMPRODUCT(($I$97:$I$100005=$AE53)*($AD$97:$AD$100005="Asignado")*AF$97:AF$100005*$Z$97:$Z$100005),0)} -> 2 | AG53: {=ROUNDUP(SUMPRODUCT(($I$97:$I$100005=$AE53)*($AD$97:$AD$100005="Actual")*AG$97:AG$100005*$Z$97:$Z$100005),0)+ROUNDUP(SUMPRODUCT(($I$97:$I$100005=$AE53)*($AD$97:$AD$100005="Asignado")*AG$97:AG$100005*$Z$97:$Z$100005),0)} -> 3 | AH53: {=ROUNDUP(SUMPRODUCT(($I$97:$I$100005=$AE53)*($AD$97:$AD$100005="Actual")*AH$97:AH$100005*$Z$97:$Z$100005),0)+ROUNDUP(SUMPRODUCT(($I$97:$I$100005=$AE53)*($AD$97:$AD$100005="Asignado")*AH$97:AH$100005*$Z$97:$Z$100005),0)} -> 2 | AI53: {=ROUNDUP(SUMPRODUCT(($I$97:$I$100005=$AE53)*($AD$97:$AD$100005="Actual")*AI$97:AI$100005*$Z$97:$Z$100005),0)+ROUNDUP(SUMPRODUCT(($I$97:$I$100005=$AE53)*($AD$97:$AD$100005="Asignado")*AI$97:AI$100005*$Z$97:$Z$100005),0)} -> 2 | AJ53: {=ROUNDUP(SUMPRODUCT(($I$97:$I$100005=$AE53)*($AD$97:$AD$100005="Actual")*AJ$97:AJ$100005*$Z$97:$Z$100005),0)+ROUNDUP(SUMPRODUCT(($I$97:$I$100005=$AE53)*($AD$97:$AD$100005="Asignado")*AJ$97:AJ$100005*$Z$97:$Z$100005),0)} -> 2 | AK53: {=ROUNDUP(SUMPRODUCT(($I$97:$I$100005=$AE53)*($AD$97:$AD$100005="Actual")*AK$97:AK$100005*$Z$97:$Z$100005),0)+ROUNDUP(SUMPRODUCT(($I$97:$I$100005=$AE53)*($AD$97:$AD$100005="Asignado")*AK$97:AK$100005*$Z$97:$Z$100005),0)} -> 2 | AL53: {=ROUNDUP(SUMPRODUCT(($I$97:$I$100005=$AE53)*($AD$97:$AD$100005="Actual")*AL$97:AL$100005*$Z$97:$Z$100005),0)+ROUNDUP(SUMPRODUCT(($I$97:$I$100005=$AE53)*($AD$97:$AD$100005="Asignado")*AL$97:AL$100005*$Z$97:$Z$100005),0)} -> 2 | AM53: {=ROUNDUP(SUMPRODUCT(($I$97:$I$100005=$AE53)*($AD$97:$AD$100005="Actual")*AM$97:AM$100005*$Z$97:$Z$100005),0)+ROUNDUP(SUMPRODUCT(($I$97:$I$100005=$AE53)*($AD$97:$AD$100005="Asignado")*AM$97:AM$100005*$Z$97:$Z$100005),0)} -> 2 | AN53: {=ROUNDUP(SUMPRODUCT(($I$97:$I$100005=$AE53)*($AD$97:$AD$100005="Actual")*AN$97:AN$100005*$Z$97:$Z$100005),0)+ROUNDUP(SUMPRODUCT(($I$97:$I$100005=$AE53)*($AD$97:$AD$100005="Asignado")*AN$97:AN$100005*$Z$97:$Z$100005),0)} -> 1
AE54: Geomecánica | AF54: {=ROUNDUP(SUMPRODUCT(($I$97:$I$100005=$AE54)*($AD$97:$AD$100005="Actual")*AF$97:AF$100005*$Z$97:$Z$100005),0)+ROUNDUP(SUMPRODUCT(($I$97:$I$100005=$AE54)*($AD$97:$AD$100005="Asignado")*AF$97:AF$100005*$Z$97:$Z$100005),0)} -> 0 | AG54: {=ROUNDUP(SUMPRODUCT(($I$97:$I$100005=$AE54)*($AD$97:$AD$100005="Actual")*AG$97:AG$100005*$Z$97:$Z$100005),0)+ROUNDUP(SUMPRODUCT(($I$97:$I$100005=$AE54)*($AD$97:$AD$100005="Asignado")*AG$97:AG$100005*$Z$97:$Z$100005),0)} -> 0 | AH54: {=ROUNDUP(SUMPRODUCT(($I$97:$I$100005=$AE54)*($AD$97:$AD$100005="Actual")*AH$97:AH$100005*$Z$97:$Z$100005),0)+ROUNDUP(SUMPRODUCT(($I$97:$I$100005=$AE54)*($AD$97:$AD$100005="Asignado")*AH$97:AH$100005*$Z$97:$Z$100005),0)} -> 0 | AI54: {=ROUNDUP(SUMPRODUCT(($I$97:$I$100005=$AE54)*($AD$97:$AD$100005="Actual")*AI$97:AI$100005*$Z$97:$Z$100005),0)+ROUNDUP(SUMPRODUCT(($I$97:$I$100005=$AE54)*($AD$97:$AD$100005="Asignado")*AI$97:AI$100005*$Z$97:$Z$100005),0)} -> 0 | AJ54: {=ROUNDUP(SUMPRODUCT(($I$97:$I$100005=$AE54)*($AD$97:$AD$100005="Actual")*AJ$97:AJ$100005*$Z$97:$Z$100005),0)+ROUNDUP(SUMPRODUCT(($I$97:$I$100005=$AE54)*($AD$97:$AD$100005="Asignado")*AJ$97:AJ$100005*$Z$97:$Z$100005),0)} -> 0 | AK54: {=ROUNDUP(SUMPRODUCT(($I$97:$I$100005=$AE54)*($AD$97:$AD$100005="Actual")*AK$97:AK$100005*$Z$97:$Z$100005),0)+ROUNDUP(SUMPRODUCT(($I$97:$I$100005=$AE54)*($AD$97:$AD$100005="Asignado")*AK$97:AK$100005*$Z$97:$Z$100005),0)} -> 0 | AL54: {=ROUNDUP(SUMPRODUCT(($I$97:$I$100005=$AE54)*($AD$97:$AD$100005="Actual")*AL$97:AL$100005*$Z$97:$Z$100005),0)+ROUNDUP(SUMPRODUCT(($I$97:$I$100005=$AE54)*($AD$97:$AD$100005="Asignado")*AL$97:AL$100005*$Z$97:$Z$100005),0)} -> 0 | AM54: {=ROUNDUP(SUMPRODUCT(($I$97:$I$100005=$AE54)*($AD$97:$AD$100005="Actual")*AM$97:AM$100005*$Z$97:$Z$100005),0)+ROUNDUP(SUMPRODUCT(($I$97:$I$100005=$AE54)*($AD$97:$AD$100005="Asignado")*AM$97:AM$100005*$Z$97:$Z$100005),0)} -> 0 | AN54: {=ROUNDUP(SUMPRODUCT(($I$97:$I$100005=$AE54)*($AD$97:$AD$100005="Actual")*AN$97:AN$100005*$Z$97:$Z$100005),0)+ROUNDUP(SUMPRODUCT(($I$97:$I$100005=$AE54)*($AD$97:$AD$100005="Asignado")*AN$97:AN$100005*$Z$97:$Z$100005),0)} -> 0
AE55: Ingeniero de Proyecto | AF55: =+SUM(AF56:AF58) -> 6 | AG55: =+SUM(AG56:AG58) -> 7 | AH55: =+SUM(AH56:AH58) -> 5 | AI55: =+SUM(AI56:AI58) -> 4 | AJ55: =+SUM(AJ56:AJ58) -> 3 | AK55: =+SUM(AK56:AK58) -> 3 | AL55: =+SUM(AL56:AL58) -> 3 | AM55: =+SUM(AM56:AM58) -> 3 | AN55: =+SUM(AN56:AN58) -> 2
AE56: Open Pit | AF56: {=ROUNDUP(SUMPRODUCT(($I$97:$I$100005=$AE56)*($AD$97:$AD$100005="Actual")*AF$97:AF$100005*$AA$97:$AA$100005),0)+ROUNDUP(SUMPRODUCT(($I$97:$I$100005=$AE56)*($AD$97:$AD$100005="Asignado")*AF$97:AF$100005*$AA$97:$AA$100005),0)} -> 2 | AG56: {=ROUNDUP(SUMPRODUCT(($I$97:$I$100005=$AE56)*($AD$97:$AD$100005="Actual")*AG$97:AG$100005*$AA$97:$AA$100005),0)+ROUNDUP(SUMPRODUCT(($I$97:$I$100005=$AE56)*($AD$97:$AD$100005="Asignado")*AG$97:AG$100005*$AA$97:$AA$100005),0)} -> 2 | AH56: {=ROUNDUP(SUMPRODUCT(($I$97:$I$100005=$AE56)*($AD$97:$AD$100005="Actual")*AH$97:AH$100005*$AA$97:$AA$100005),0)+ROUNDUP(SUMPRODUCT(($I$97:$I$100005=$AE56)*($AD$97:$AD$100005="Asignado")*AH$97:AH$100005*$AA$97:$AA$100005),0)} -> 1 | AI56: {=ROUNDUP(SUMPRODUCT(($I$97:$I$100005=$AE56)*($AD$97:$AD$100005="Actual")*AI$97:AI$100005*$AA$97:$AA$100005),0)+ROUNDUP(SUMPRODUCT(($I$97:$I$100005=$AE56)*($AD$97:$AD$100005="Asignado")*AI$97:AI$100005*$AA$97:$AA$100005),0)} -> 1 | AJ56: {=ROUNDUP(SUMPRODUCT(($I$97:$I$100005=$AE56)*($AD$97:$AD$100005="Actual")*AJ$97:AJ$100005*$AA$97:$AA$100005),0)+ROUNDUP(SUMPRODUCT(($I$97:$I$100005=$AE56)*($AD$97:$AD$100005="Asignado")*AJ$97:AJ$100005*$AA$97:$AA$100005),0)} -> 1 | AK56: {=ROUNDUP(SUMPRODUCT(($I$97:$I$100005=$AE56)*($AD$97:$AD$100005="Actual")*AK$97:AK$100005*$AA$97:$AA$100005),0)+ROUNDUP(SUMPRODUCT(($I$97:$I$100005=$AE56)*($AD$97:$AD$100005="Asignado")*AK$97:AK$100005*$AA$97:$AA$100005),0)} -> 1 | AL56: {=ROUNDUP(SUMPRODUCT(($I$97:$I$100005=$AE56)*($AD$97:$AD$100005="Actual")*AL$97:AL$100005*$AA$97:$AA$100005),0)+ROUNDUP(SUMPRODUCT(($I$97:$I$100005=$AE56)*($AD$97:$AD$100005="Asignado")*AL$97:AL$100005*$AA$97:$AA$100005),0)} -> 1 | AM56: {=ROUNDUP(SUMPRODUCT(($I$97:$I$100005=$AE56)*($AD$97:$AD$100005="Actual")*AM$97:AM$100005*$AA$97:$AA$100005),0)+ROUNDUP(SUMPRODUCT(($I$97:$I$100005=$AE56)*($AD$97:$AD$100005="Asignado")*AM$97:AM$100005*$AA$97:$AA$100005),0)} -> 1 | AN56: {=ROUNDUP(SUMPRODUCT(($I$97:$I$100005=$AE56)*($AD$97:$AD$100005="Actual")*AN$97:AN$100005*$AA$97:$AA$100005),0)+ROUNDUP(SUMPRODUCT(($I$97:$I$100005=$AE56)*($AD$97:$AD$100005="Asignado")*AN$97:AN$100005*$AA$97:$AA$100005),0)} -> 1
AE57: Subterránea | AF57: {=ROUNDUP(SUMPRODUCT(($I$97:$I$100005=$AE57)*($AD$97:$AD$100005="Actual")*AF$97:AF$100005*$AA$97:$AA$100005),0)+ROUNDUP(SUMPRODUCT(($I$97:$I$100005=$AE57)*($AD$97:$AD$100005="Asignado")*AF$97:AF$100005*$AA$97:$AA$100005),0)} -> 4 | AG57: {=ROUNDUP(SUMPRODUCT(($I$97:$I$100005=$AE57)*($AD$97:$AD$100005="Actual")*AG$97:AG$100005*$AA$97:$AA$100005),0)+ROUNDUP(SUMPRODUCT(($I$97:$I$100005=$AE57)*($AD$97:$AD$100005="Asignado")*AG$97:AG$100005*$AA$97:$AA$100005),0)} -> 5 | AH57: {=ROUNDUP(SUMPRODUCT(($I$97:$I$100005=$AE57)*($AD$97:$AD$100005="Actual")*AH$97:AH$100005*$AA$97:$AA$100005),0)+ROUNDUP(SUMPRODUCT(($I$97:$I$100005=$AE57)*($AD$97:$AD$100005="Asignado")*AH$97:AH$100005*$AA$97:$AA$100005),0)} -> 4 | AI57: {=ROUNDUP(SUMPRODUCT(($I$97:$I$100005=$AE57)*($AD$97:$AD$100005="Actual")*AI$97:AI$100005*$AA$97:$AA$100005),0)+ROUNDUP(SUMPRODUCT(($I$97:$I$100005=$AE57)*($AD$97:$AD$100005="Asignado")*AI$97:AI$100005*$AA$97:$AA$100005),0)} -> 3 | AJ57: {=ROUNDUP(SUMPRODUCT(($I$97:$I$100005=$AE57)*($AD$97:$AD$100005="Actual")*AJ$97:AJ$100005*$AA$97:$AA$100005),0)+ROUNDUP(SUMPRODUCT(($I$97:$I$100005=$AE57)*($AD$97:$AD$100005="Asignado")*AJ$97:AJ$100005*$AA$97:$AA$100005),0)} -> 2 | AK57: {=ROUNDUP(SUMPRODUCT(($I$97:$I$100005=$AE57)*($AD$97:$AD$100005="Actual")*AK$97:AK$100005*$AA$97:$AA$100005),0)+ROUNDUP(SUMPRODUCT(($I$97:$I$100005=$AE57)*($AD$97:$AD$100005="Asignado")*AK$97:AK$100005*$AA$97:$AA$100005),0)} -> 2 | AL57: {=ROUNDUP(SUMPRODUCT(($I$97:$I$100005=$AE57)*($AD$97:$AD$100005="Actual")*AL$97:AL$100005*$AA$97:$AA$100005),0)+ROUNDUP(SUMPRODUCT(($I$97:$I$100005=$AE57)*($AD$97:$AD$100005="Asignado")*AL$97:AL$100005*$AA$97:$AA$100005),0)} -> 2 | AM57: {=ROUNDUP(SUMPRODUCT(($I$97:$I$100005=$AE57)*($AD$97:$AD$100005="Actual")*AM$97:AM$100005*$AA$97:$AA$100005),0)+ROUNDUP(SUMPRODUCT(($I$97:$I$100005=$AE57)*($AD$97:$AD$100005="Asignado")*AM$97:AM$100005*$AA$97:$AA$100005),0)} -> 2 | AN57: {=ROUNDUP(SUMPRODUCT(($I$97:$I$100005=$AE57)*($AD$97:$AD$100005="Actual")*AN$97:AN$100005*$AA$97:$AA$100005),0)+ROUNDUP(SUMPRODUCT(($I$97:$I$100005=$AE57)*($AD$97:$AD$100005="Asignado")*AN$97:AN$100005*$AA$97:$AA$100005),0)} -> 1
AE58: Geomecánica | AF58: {=ROUNDUP(SUMPRODUCT(($I$97:$I$100005=$AE58)*($AD$97:$AD$100005="Actual")*AF$97:AF$100005*$AA$97:$AA$100005),0)+ROUNDUP(SUMPRODUCT(($I$97:$I$100005=$AE58)*($AD$97:$AD$100005="Asignado")*AF$97:AF$100005*$AA$97:$AA$100005),0)} -> 0 | AG58: {=ROUNDUP(SUMPRODUCT(($I$97:$I$100005=$AE58)*($AD$97:$AD$100005="Actual")*AG$97:AG$100005*$AA$97:$AA$100005),0)+ROUNDUP(SUMPRODUCT(($I$97:$I$100005=$AE58)*($AD$97:$AD$100005="Asignado")*AG$97:AG$100005*$AA$97:$AA$100005),0)} -> 0 | AH58: {=ROUNDUP(SUMPRODUCT(($I$97:$I$100005=$AE58)*($AD$97:$AD$100005="Actual")*AH$97:AH$100005*$AA$97:$AA$100005),0)+ROUNDUP(SUMPRODUCT(($I$97:$I$100005=$AE58)*($AD$97:$AD$100005="Asignado")*AH$97:AH$100005*$AA$97:$AA$100005),0)} -> 0 | AI58: {=ROUNDUP(SUMPRODUCT(($I$97:$I$100005=$AE58)*($AD$97:$AD$100005="Actual")*AI$97:AI$100005*$AA$97:$AA$100005),0)+ROUNDUP(SUMPRODUCT(($I$97:$I$100005=$AE58)*($AD$97:$AD$100005="Asignado")*AI$97:AI$100005*$AA$97:$AA$100005),0)} -> 0 | AJ58: {=ROUNDUP(SUMPRODUCT(($I$97:$I$100005=$AE58)*($AD$97:$AD$100005="Actual")*AJ$97:AJ$100005*$AA$97:$AA$100005),0)+ROUNDUP(SUMPRODUCT(($I$97:$I$100005=$AE58)*($AD$97:$AD$100005="Asignado")*AJ$97:AJ$100005*$AA$97:$AA$100005),0)} -> 0 | AK58: {=ROUNDUP(SUMPRODUCT(($I$97:$I$100005=$AE58)*($AD$97:$AD$100005="Actual")*AK$97:AK$100005*$AA$97:$AA$100005),0)+ROUNDUP(SUMPRODUCT(($I$97:$I$100005=$AE58)*($AD$97:$AD$100005="Asignado")*AK$97:AK$100005*$AA$97:$AA$100005),0)} -> 0 | AL58: {=ROUNDUP(SUMPRODUCT(($I$97:$I$100005=$AE58)*($AD$97:$AD$100005="Actual")*AL$97:AL$100005*$AA$97:$AA$100005),0)+ROUNDUP(SUMPRODUCT(($I$97:$I$100005=$AE58)*($AD$97:$AD$100005="Asignado")*AL$97:AL$100005*$AA$97:$AA$100005),0)} -> 0 | AM58: {=ROUNDUP(SUMPRODUCT(($I$97:$I$100005=$AE58)*($AD$97:$AD$100005="Actual")*AM$97:AM$100005*$AA$97:$AA$100005),0)+ROUNDUP(SUMPRODUCT(($I$97:$I$100005=$AE58)*($AD$97:$AD$100005="Asignado")*AM$97:AM$100005*$AA$97:$AA$100005),0)} -> 0 | AN58: {=ROUNDUP(SUMPRODUCT(($I$97:$I$100005=$AE58)*($AD$97:$AD$100005="Actual")*AN$97:AN$100005*$AA$97:$AA$100005),0)+ROUNDUP(SUMPRODUCT(($I$97:$I$100005=$AE58)*($AD$97:$AD$100005="Asignado")*AN$97:AN$100005*$AA$97:$AA$100005),0)} -> 0
AE59: Ingeniero Junior | AF59: =+SUM(AF60:AF62) -> 4 | AG59: =+SUM(AG60:AG62) -> 3 | AH59: =+SUM(AH60:AH62) -> 3 | AI59: =+SUM(AI60:AI62) -> 4 | AJ59: =+SUM(AJ60:AJ62) -> 3 | AK59: =+SUM(AK60:AK62) -> 3 | AL59: =+SUM(AL60:AL62) -> 3 | AM59: =+SUM(AM60:AM62) -> 3 | AN59: =+SUM(AN60:AN62) -> 2
AE60: Open Pit | AF60: {=ROUNDUP(SUMPRODUCT(($I$97:$I$100005=$AE60)*($AD$97:$AD$100005="Actual")*AF$97:AF$100005*$AB$97:$AB$100005),0)+ROUNDUP(SUMPRODUCT(($I$97:$I$100005=$AE60)*($AD$97:$AD$100005="Asignado")*AF$97:AF$100005*$AB$97:$AB$100005),0)} -> 2 | AG60: {=ROUNDUP(SUMPRODUCT(($I$97:$I$100005=$AE60)*($AD$97:$AD$100005="Actual")*AG$97:AG$100005*$AB$97:$AB$100005),0)+ROUNDUP(SUMPRODUCT(($I$97:$I$100005=$AE60)*($AD$97:$AD$100005="Asignado")*AG$97:AG$100005*$AB$97:$AB$100005),0)} -> 1 | AH60: {=ROUNDUP(SUMPRODUCT(($I$97:$I$100005=$AE60)*($AD$97:$AD$100005="Actual")*AH$97:AH$100005*$AB$97:$AB$100005),0)+ROUNDUP(SUMPRODUCT(($I$97:$I$100005=$AE60)*($AD$97:$AD$100005="Asignado")*AH$97:AH$100005*$AB$97:$AB$100005),0)} -> 1 | AI60: {=ROUNDUP(SUMPRODUCT(($I$97:$I$100005=$AE60)*($AD$97:$AD$100005="Actual")*AI$97:AI$100005*$AB$97:$AB$100005),0)+ROUNDUP(SUMPRODUCT(($I$97:$I$100005=$AE60)*($AD$97:$AD$100005="Asignado")*AI$97:AI$100005*$AB$97:$AB$100005),0)} -> 1 | AJ60: {=ROUNDUP(SUMPRODUCT(($I$97:$I$100005=$AE60)*($AD$97:$AD$100005="Actual")*AJ$97:AJ$100005*$AB$97:$AB$100005),0)+ROUNDUP(SUMPRODUCT(($I$97:$I$100005=$AE60)*($AD$97:$AD$100005="Asignado")*AJ$97:AJ$100005*$AB$97:$AB$100005),0)} -> 1 | AK60: {=ROUNDUP(SUMPRODUCT(($I$97:$I$100005=$AE60)*($AD$97:$AD$100005="Actual")*AK$97:AK$100005*$AB$97:$AB$100005),0)+ROUNDUP(SUMPRODUCT(($I$97:$I$100005=$AE60)*($AD$97:$AD$100005="Asignado")*AK$97:AK$100005*$AB$97:$AB$100005),0)} -> 1 | AL60: {=ROUNDUP(SUMPRODUCT(($I$97:$I$100005=$AE60)*($AD$97:$AD$100005="Actual")*AL$97:AL$100005*$AB$97:$AB$100005),0)+ROUNDUP(SUMPRODUCT(($I$97:$I$100005=$AE60)*($AD$97:$AD$100005="Asignado")*AL$97:AL$100005*$AB$97:$AB$100005),0)} -> 1 | AM60: {=ROUNDUP(SUMPRODUCT(($I$97:$I$100005=$AE60)*($AD$97:$AD$100005="Actual")*AM$97:AM$100005*$AB$97:$AB$100005),0)+ROUNDUP(SUMPRODUCT(($I$97:$I$100005=$AE60)*($AD$97:$AD$100005="Asignado")*AM$97:AM$100005*$AB$97:$AB$100005),0)} -> 1 | AN60: {=ROUNDUP(SUMPRODUCT(($I$97:$I$100005=$AE60)*($AD$97:$AD$100005="Actual")*AN$97:AN$100005*$AB$97:$AB$100005),0)+ROUNDUP(SUMPRODUCT(($I$97:$I$100005=$AE60)*($AD$97:$AD$100005="Asignado")*AN$97:AN$100005*$AB$97:$AB$100005),0)} -> 1
AE61: Subterránea | AF61: {=ROUNDUP(SUMPRODUCT(($I$97:$I$100005=$AE61)*($AD$97:$AD$100005="Actual")*AF$97:AF$100005*$AB$97:$AB$100005),0)+ROUNDUP(SUMPRODUCT(($I$97:$I$100005=$AE61)*($AD$97:$AD$100005="Asignado")*AF$97:AF$100005*$AB$97:$AB$100005),0)} -> 2 | AG61: {=ROUNDUP(SUMPRODUCT(($I$97:$I$100005=$AE61)*($AD$97:$AD$100005="Actual")*AG$97:AG$100005*$AB$97:$AB$100005),0)+ROUNDUP(SUMPRODUCT(($I$97:$I$100005=$AE61)*($AD$97:$AD$100005="Asignado")*AG$97:AG$100005*$AB$97:$AB$100005),0)} -> 2 | AH61: {=ROUNDUP(SUMPRODUCT(($I$97:$I$100005=$AE61)*($AD$97:$AD$100005="Actual")*AH$97:AH$100005*$AB$97:$AB$100005),0)+ROUNDUP(SUMPRODUCT(($I$97:$I$100005=$AE61)*($AD$97:$AD$100005="Asignado")*AH$97:AH$100005*$AB$97:$AB$100005),0)} -> 2 | AI61: {=ROUNDUP(SUMPRODUCT(($I$97:$I$100005=$AE61)*($AD$97:$AD$100005="Actual")*AI$97:AI$100005*$AB$97:$AB$100005),0)+ROUNDUP(SUMPRODUCT(($I$97:$I$100005=$AE61)*($AD$97:$AD$100005="Asignado")*AI$97:AI$100005*$AB$97:$AB$100005),0)} -> 3 | AJ61: {=ROUNDUP(SUMPRODUCT(($I$97:$I$100005=$AE61)*($AD$97:$AD$100005="Actual")*AJ$97:AJ$100005*$AB$97:$AB$100005),0)+ROUNDUP(SUMPRODUCT(($I$97:$I$100005=$AE61)*($AD$97:$AD$100005="Asignado")*AJ$97:AJ$100005*$AB$97:$AB$100005),0)} -> 2 | AK61: {=ROUNDUP(SUMPRODUCT(($I$97:$I$100005=$AE61)*($AD$97:$AD$100005="Actual")*AK$97:AK$100005*$AB$97:$AB$100005),0)+ROUNDUP(SUMPRODUCT(($I$97:$I$100005=$AE61)*($AD$97:$AD$100005="Asignado")*AK$97:AK$100005*$AB$97:$AB$100005),0)} -> 2 | AL61: {=ROUNDUP(SUMPRODUCT(($I$97:$I$100005=$AE61)*($AD$97:$AD$100005="Actual")*AL$97:AL$100005*$AB$97:$AB$100005),0)+ROUNDUP(SUMPRODUCT(($I$97:$I$100005=$AE61)*($AD$97:$AD$100005="Asignado")*AL$97:AL$100005*$AB$97:$AB$100005),0)} -> 2 | AM61: {=ROUNDUP(SUMPRODUCT(($I$97:$I$100005=$AE61)*($AD$97:$AD$100005="Actual")*AM$97:AM$100005*$AB$97:$AB$100005),0)+ROUNDUP(SUMPRODUCT(($I$97:$I$100005=$AE61)*($AD$97:$AD$100005="Asignado")*AM$97:AM$100005*$AB$97:$AB$100005),0)} -> 2 | AN61: {=ROUNDUP(SUMPRODUCT(($I$97:$I$100005=$AE61)*($AD$97:$AD$100005="Actual")*AN$97:AN$100005*$AB$97:$AB$100005),0)+ROUNDUP(SUMPRODUCT(($I$97:$I$100005=$AE61)*($AD$97:$AD$100005="Asignado")*AN$97:AN$100005*$AB$97:$AB$100005),0)} -> 1
AE62: Geomecánica | AF62: {=ROUNDUP(SUMPRODUCT(($I$97:$I$100005=$AE62)*($AD$97:$AD$100005="Actual")*AF$97:AF$100005*$AB$97:$AB$100005),0)+ROUNDUP(SUMPRODUCT(($I$97:$I$100005=$AE62)*($AD$97:$AD$100005="Asignado")*AF$97:AF$100005*$AB$97:$AB$100005),0)} -> 0 | AG62: {=ROUNDUP(SUMPRODUCT(($I$97:$I$100005=$AE62)*($AD$97:$AD$100005="Actual")*AG$97:AG$100005*$AB$97:$AB$100005),0)+ROUNDUP(SUMPRODUCT(($I$97:$I$100005=$AE62)*($AD$97:$AD$100005="Asignado")*AG$97:AG$100005*$AB$97:$AB$100005),0)} -> 0 | AH62: {=ROUNDUP(SUMPRODUCT(($I$97:$I$100005=$AE62)*($AD$97:$AD$100005="Actual")*AH$97:AH$100005*$AB$97:$AB$100005),0)+ROUNDUP(SUMPRODUCT(($I$97:$I$100005=$AE62)*($AD$97:$AD$100005="Asignado")*AH$97:AH$100005*$AB$97:$AB$100005),0)} -> 0 | AI62: {=ROUNDUP(SUMPRODUCT(($I$97:$I$100005=$AE62)*($AD$97:$AD$100005="Actual")*AI$97:AI$100005*$AB$97:$AB$100005),0)+ROUNDUP(SUMPRODUCT(($I$97:$I$100005=$AE62)*($AD$97:$AD$100005="Asignado")*AI$97:AI$100005*$AB$97:$AB$100005),0)} -> 0 | AJ62: {=ROUNDUP(SUMPRODUCT(($I$97:$I$100005=$AE62)*($AD$97:$AD$100005="Actual")*AJ$97:AJ$100005*$AB$97:$AB$100005),0)+ROUNDUP(SUMPRODUCT(($I$97:$I$100005=$AE62)*($AD$97:$AD$100005="Asignado")*AJ$97:AJ$100005*$AB$97:$AB$100005),0)} -> 0 | AK62: {=ROUNDUP(SUMPRODUCT(($I$97:$I$100005=$AE62)*($AD$97:$AD$100005="Actual")*AK$97:AK$100005*$AB$97:$AB$100005),0)+ROUNDUP(SUMPRODUCT(($I$97:$I$100005=$AE62)*($AD$97:$AD$100005="Asignado")*AK$97:AK$100005*$AB$97:$AB$100005),0)} -> 0 | AL62: {=ROUNDUP(SUMPRODUCT(($I$97:$I$100005=$AE62)*($AD$97:$AD$100005="Actual")*AL$97:AL$100005*$AB$97:$AB$100005),0)+ROUNDUP(SUMPRODUCT(($I$97:$I$100005=$AE62)*($AD$97:$AD$100005="Asignado")*AL$97:AL$100005*$AB$97:$AB$100005),0)} -> 0 | AM62: {=ROUNDUP(SUMPRODUCT(($I$97:$I$100005=$AE62)*($AD$97:$AD$100005="Actual")*AM$97:AM$100005*$AB$97:$AB$100005),0)+ROUNDUP(SUMPRODUCT(($I$97:$I$100005=$AE62)*($AD$97:$AD$100005="Asignado")*AM$97:AM$100005*$AB$97:$AB$100005),0)} -> 0 | AN62: {=ROUNDUP(SUMPRODUCT(($I$97:$I$100005=$AE62)*($AD$97:$AD$100005="Actual")*AN$97:AN$100005*$AB$97:$AB$100005),0)+ROUNDUP(SUMPRODUCT(($I$97:$I$100005=$AE62)*($AD$97:$AD$100005="Asignado")*AN$97:AN$100005*$AB$97:$AB$100005),0)} -> 0
AE63: Total | AF63: =+AF59+AF55+AF51+AF47+AF43 -> 19 | AG63: =+AG59+AG55+AG51+AG47+AG43 -> 22 | AH63: =+AH59+AH55+AH51+AH47+AH43 -> 18 | AI63: =+AI59+AI55+AI51+AI47+AI43 -> 17 | AJ63: =+AJ59+AJ55+AJ51+AJ47+AJ43 -> 15 | AK63: =+AK59+AK55+AK51+AK47+AK43 -> 15 | AL63: =+AL59+AL55+AL51+AL47+AL43 -> 15 | AM63: =+AM59+AM55+AM51+AM47+AM43 -> 15 | AN63: =+AN59+AN55+AN51+AN47+AN43 -> 10
AD64: Actuales + Asignados + No Asignados | AE64: Director de Proyecto | AF64: =+SUM(AF65:AF67) -> 3 | AG64: =+SUM(AG65:AG67) -> 4 | AH64: =+SUM(AH65:AH67) -> 4 | AI64: =+SUM(AI65:AI67) -> 5 | AJ64: =+SUM(AJ65:AJ67) -> 5 | AK64: =+SUM(AK65:AK67) -> 5 | AL64: =+SUM(AL65:AL67) -> 5 | AM64: =+SUM(AM65:AM67) -> 5 | AN64: =+SUM(AN65:AN67) -> 4
AE65: Open Pit | AF65: {=ROUNDUP(SUMPRODUCT(($I$97:$I$100005=$AE65)*($AD$97:$AD$100005="Actual")*AF$97:AF$100005*$X$97:$X$100005),0)+ROUNDUP(SUMPRODUCT(($I$97:$I$100005=$AE65)*($AD$97:$AD$100005="Asignado")*AF$97:AF$100005*$X$97:$X$100005),0)+ROUNDUP(SUMPRODUCT(($I$97:$I$100005=$AE65)*($AD$97:$AD$100005="No Asignado")*AF$97:AF$100005*$X$97:$X$100005),0)} -> 1 | AG65: {=ROUNDUP(SUMPRODUCT(($I$97:$I$100005=$AE65)*($AD$97:$AD$100005="Actual")*AG$97:AG$100005*$X$97:$X$100005),0)+ROUNDUP(SUMPRODUCT(($I$97:$I$100005=$AE65)*($AD$97:$AD$100005="Asignado")*AG$97:AG$100005*$X$97:$X$100005),0)+ROUNDUP(SUMPRODUCT(($I$97:$I$100005=$AE65)*($AD$97:$AD$100005="No Asignado")*AG$97:AG$100005*$X$97:$X$100005),0)} -> 1 | AH65: {=ROUNDUP(SUMPRODUCT(($I$97:$I$100005=$AE65)*($AD$97:$AD$100005="Actual")*AH$97:AH$100005*$X$97:$X$100005),0)+ROUNDUP(SUMPRODUCT(($I$97:$I$100005=$AE65)*($AD$97:$AD$100005="Asignado")*AH$97:AH$100005*$X$97:$X$100005),0)+ROUNDUP(SUMPRODUCT(($I$97:$I$100005=$AE65)*($AD$97:$AD$100005="No Asignado")*AH$97:AH$100005*$X$97:$X$100005),0)} -> 1 | AI65: {=ROUNDUP(SUMPRODUCT(($I$97:$I$100005=$AE65)*($AD$97:$AD$100005="Actual")*AI$97:AI$100005*$X$97:$X$100005),0)+ROUNDUP(SUMPRODUCT(($I$97:$I$100005=$AE65)*($AD$97:$AD$100005="Asignado")*AI$97:AI$100005*$X$97:$X$100005),0)+ROUNDUP(SUMPRODUCT(($I$97:$I$100005=$AE65)*($AD$97:$AD$100005="No Asignado")*AI$97:AI$100005*$X$97:$X$100005),0)} -> 2 | AJ65: {=ROUNDUP(SUMPRODUCT(($I$97:$I$100005=$AE65)*($AD$97:$AD$100005="Actual")*AJ$97:AJ$100005*$X$97:$X$100005),0)+ROUNDUP(SUMPRODUCT(($I$97:$I$100005=$AE65)*($AD$97:$AD$100005="Asignado")*AJ$97:AJ$100005*$X$97:$X$100005),0)+ROUNDUP(SUMPRODUCT(($I$97:$I$100005=$AE65)*($AD$97:$AD$100005="No Asignado")*AJ$97:AJ$100005*$X$97:$X$100005),0)} -> 2 | AK65: {=ROUNDUP(SUMPRODUCT(($I$97:$I$100005=$AE65)*($AD$97:$AD$100005="Actual")*AK$97:AK$100005*$X$97:$X$100005),0)+ROUNDUP(SUMPRODUCT(($I$97:$I$100005=$AE65)*($AD$97:$AD$100005="Asignado")*AK$97:AK$100005*$X$97:$X$100005),0)+ROUNDUP(SUMPRODUCT(($I$97:$I$100005=$AE65)*($AD$97:$AD$100005="No Asignado")*AK$97:AK$100005*$X$97:$X$100005),0)} -> 2 | AL65: {=ROUNDUP(SUMPRODUCT(($I$97:$I$100005=$AE65)*($AD$97:$AD$100005="Actual")*AL$97:AL$100005*$X$97:$X$100005),0)+ROUNDUP(SUMPRODUCT(($I$97:$I$100005=$AE65)*($AD$97:$AD$100005="Asignado")*AL$97:AL$100005*$X$97:$X$100005),0)+ROUNDUP(SUMPRODUCT(($I$97:$I$100005=$AE65)*($AD$97:$AD$100005="No Asignado")*AL$97:AL$100005*$X$97:$X$100005),0)} -> 2 | AM65: {=ROUNDUP(SUMPRODUCT(($I$97:$I$100005=$AE65)*($AD$97:$AD$100005="Actual")*AM$97:AM$100005*$X$97:$X$100005),0)+ROUNDUP(SUMPRODUCT(($I$97:$I$100005=$AE65)*($AD$97:$AD$100005="Asignado")*AM$97:AM$100005*$X$97:$X$100005),0)+ROUNDUP(SUMPRODUCT(($I$97:$I$100005=$AE65)*($AD$97:$AD$100005="No Asignado")*AM$97:AM$100005*$X$97:$X$100005),0)} -> 2 | AN65: {=ROUNDUP(SUMPRODUCT(($I$97:$I$100005=$AE65)*($AD$97:$AD$100005="Actual")*AN$97:AN$100005*$X$97:$X$100005),0)+ROUNDUP(SUMPRODUCT(($I$97:$I$100005=$AE65)*($AD$97:$AD$100005="Asignado")*AN$97:AN$100005*$X$97:$X$100005),0)+ROUNDUP(SUMPRODUCT(($I$97:$I$100005=$AE65)*($AD$97:$AD$100005="No Asignado")*AN$97:AN$100005*$X$97:$X$100005),0)} -> 2
AE66: Subterránea | AF66: {=ROUNDUP(SUMPRODUCT(($I$97:$I$100005=$AE66)*($AD$97:$AD$100005="Actual")*AF$97:AF$100005*$X$97:$X$100005),0)+ROUNDUP(SUMPRODUCT(($I$97:$I$100005=$AE66)*($AD$97:$AD$100005="Asignado")*AF$97:AF$100005*$X$97:$X$100005),0)+ROUNDUP(SUMPRODUCT(($I$97:$I$100005=$AE66)*($AD$97:$AD$100005="No Asignado")*AF$97:AF$100005*$X$97:$X$100005),0)} -> 2 | AG66: {=ROUNDUP(SUMPRODUCT(($I$97:$I$100005=$AE66)*($AD$97:$AD$100005="Actual")*AG$97:AG$100005*$X$97:$X$100005),0)+ROUNDUP(SUMPRODUCT(($I$97:$I$100005=$AE66)*($AD$97:$AD$100005="Asignado")*AG$97:AG$100005*$X$97:$X$100005),0)+ROUNDUP(SUMPRODUCT(($I$97:$I$100005=$AE66)*($AD$97:$AD$100005="No Asignado")*AG$97:AG$100005*$X$97:$X$100005),0)} -> 3 | AH66: {=ROUNDUP(SUMPRODUCT(($I$97:$I$100005=$AE66)*($AD$97:$AD$100005="Actual")*AH$97:AH$100005*$X$97:$X$100005),0)+ROUNDUP(SUMPRODUCT(($I$97:$I$100005=$AE66)*($AD$97:$AD$100005="Asignado")*AH$97:AH$100005*$X$97:$X$100005),0)+ROUNDUP(SUMPRODUCT(($I$97:$I$100005=$AE66)*($AD$97:$AD$100005="No Asignado")*AH$97:AH$100005*$X$97:$X$100005),0)} -> 3 | AI66: {=ROUNDUP(SUMPRODUCT(($I$97:$I$100005=$AE66)*($AD$97:$AD$100005="Actual")*AI$97:AI$100005*$X$97:$X$100005),0)+ROUNDUP(SUMPRODUCT(($I$97:$I$100005=$AE66)*($AD$97:$AD$100005="Asignado")*AI$97:AI$100005*$X$97:$X$100005),0)+ROUNDUP(SUMPRODUCT(($I$97:$I$100005=$AE66)*($AD$97:$AD$100005="No Asignado")*AI$97:AI$100005*$X$97:$X$100005),0)} -> 3 | AJ66: {=ROUNDUP(SUMPRODUCT(($I$97:$I$100005=$AE66)*($AD$97:$AD$100005="Actual")*AJ$97:AJ$100005*$X$97:$X$100005),0)+ROUNDUP(SUMPRODUCT(($I$97:$I$100005=$AE66)*($AD$97:$AD$100005="Asignado")*AJ$97:AJ$100005*$X$97:$X$100005),0)+ROUNDUP(SUMPRODUCT(($I$97:$I$100005=$AE66)*($AD$97:$AD$100005="No Asignado")*AJ$97:AJ$100005*$X$97:$X$100005),0)} -> 3 | AK66: {=ROUNDUP(SUMPRODUCT(($I$97:$I$100005=$AE66)*($AD$97:$AD$100005="Actual")*AK$97:AK$100005*$X$97:$X$100005),0)+ROUNDUP(SUMPRODUCT(($I$97:$I$100005=$AE66)*($AD$97:$AD$100005="Asignado")*AK$97:AK$100005*$X$97:$X$100005),0)+ROUNDUP(SUMPRODUCT(($I$97:$I$100005=$AE66)*($AD$97:$AD$100005="No Asignado")*AK$97:AK$100005*$X$97:$X$100005),0)} -> 3 | AL66: {=ROUNDUP(SUMPRODUCT(($I$97:$I$100005=$AE66)*($AD$97:$AD$100005="Actual")*AL$97:AL$100005*$X$97:$X$100005),0)+ROUNDUP(SUMPRODUCT(($I$97:$I$100005=$AE66)*($AD$97:$AD$100005="Asignado")*AL$97:AL$100005*$X$97:$X$100005),0)+ROUNDUP(SUMPRODUCT(($I$97:$I$100005=$AE66)*($AD$97:$AD$100005="No Asignado")*AL$97:AL$100005*$X$97:$X$100005),0)} -> 3 | AM66: {=ROUNDUP(SUMPRODUCT(($I$97:$I$100005=$AE66)*($AD$97:$AD$100005="Actual")*AM$97:AM$100005*$X$97:$X$100005),0)+ROUNDUP(SUMPRODUCT(($I$97:$I$100005=$AE66)*($AD$97:$AD$100005="Asignado")*AM$97:AM$100005*$X$97:$X$100005),0)+ROUNDUP(SUMPRODUCT(($I$97:$I$100005=$AE66)*($AD$97:$AD$100005="No Asignado")*AM$97:AM$100005*$X$97:$X$100005),0)} -> 3 | AN66: {=ROUNDUP(SUMPRODUCT(($I$97:$I$100005=$AE66)*($AD$97:$AD$100005="Actual")*AN$97:AN$100005*$X$97:$X$100005),0)+ROUNDUP(SUMPRODUCT(($I$97:$I$100005=$AE66)*($AD$97:$AD$100005="Asignado")*AN$97:AN$100005*$X$97:$X$100005),0)+ROUNDUP(SUMPRODUCT(($I$97:$I$100005=$AE66)*($AD$97:$AD$100005="No Asignado")*AN$97:AN$100005*$X$97:$X$100005),0)} -> 2
AE67: Geomecánica | AF67: {=ROUNDUP(SUMPRODUCT(($I$97:$I$100005=$AE67)*($AD$97:$AD$100005="Actual")*AF$97:AF$100005*$X$97:$X$100005),0)+ROUNDUP(SUMPRODUCT(($I$97:$I$100005=$AE67)*($AD$97:$AD$100005="Asignado")*AF$97:AF$100005*$X$97:$X$100005),0)+ROUNDUP(SUMPRODUCT(($I$97:$I$100005=$AE67)*($AD$97:$AD$100005="No Asignado")*AF$97:AF$100005*$X$97:$X$100005),0)} -> 0 | AG67: {=ROUNDUP(SUMPRODUCT(($I$97:$I$100005=$AE67)*($AD$97:$AD$100005="Actual")*AG$97:AG$100005*$X$97:$X$100005),0)+ROUNDUP(SUMPRODUCT(($I$97:$I$100005=$AE67)*($AD$97:$AD$100005="Asignado")*AG$97:AG$100005*$X$97:$X$100005),0)+ROUNDUP(SUMPRODUCT(($I$97:$I$100005=$AE67)*($AD$97:$AD$100005="No Asignado")*AG$97:AG$100005*$X$97:$X$100005),0)} -> 0 | AH67: {=ROUNDUP(SUMPRODUCT(($I$97:$I$100005=$AE67)*($AD$97:$AD$100005="Actual")*AH$97:AH$100005*$X$97:$X$100005),0)+ROUNDUP(SUMPRODUCT(($I$97:$I$100005=$AE67)*($AD$97:$AD$100005="Asignado")*AH$97:AH$100005*$X$97:$X$100005),0)+ROUNDUP(SUMPRODUCT(($I$97:$I$100005=$AE67)*($AD$97:$AD$100005="No Asignado")*AH$97:AH$100005*$X$97:$X$100005),0)} -> 0 | AI67: {=ROUNDUP(SUMPRODUCT(($I$97:$I$100005=$AE67)*($AD$97:$AD$100005="Actual")*AI$97:AI$100005*$X$97:$X$100005),0)+ROUNDUP(SUMPRODUCT(($I$97:$I$100005=$AE67)*($AD$97:$AD$100005="Asignado")*AI$97:AI$100005*$X$97:$X$100005),0)+ROUNDUP(SUMPRODUCT(($I$97:$I$100005=$AE67)*($AD$97:$AD$100005="No Asignado")*AI$97:AI$100005*$X$97:$X$100005),0)} -> 0 | AJ67: {=ROUNDUP(SUMPRODUCT(($I$97:$I$100005=$AE67)*($AD$97:$AD$100005="Actual")*AJ$97:AJ$100005*$X$97:$X$100005),0)+ROUNDUP(SUMPRODUCT(($I$97:$I$100005=$AE67)*($AD$97:$AD$100005="Asignado")*AJ$97:AJ$100005*$X$97:$X$100005),0)+ROUNDUP(SUMPRODUCT(($I$97:$I$100005=$AE67)*($AD$97:$AD$100005="No Asignado")*AJ$97:AJ$100005*$X$97:$X$100005),0)} -> 0 | AK67: {=ROUNDUP(SUMPRODUCT(($I$97:$I$100005=$AE67)*($AD$97:$AD$100005="Actual")*AK$97:AK$100005*$X$97:$X$100005),0)+ROUNDUP(SUMPRODUCT(($I$97:$I$100005=$AE67)*($AD$97:$AD$100005="Asignado")*AK$97:AK$100005*$X$97:$X$100005),0)+ROUNDUP(SUMPRODUCT(($I$97:$I$100005=$AE67)*($AD$97:$AD$100005="No Asignado")*AK$97:AK$100005*$X$97:$X$100005),0)} -> 0 | AL67: {=ROUNDUP(SUMPRODUCT(($I$97:$I$100005=$AE67)*($AD$97:$AD$100005="Actual")*AL$97:AL$100005*$X$97:$X$100005),0)+ROUNDUP(SUMPRODUCT(($I$97:$I$100005=$AE67)*($AD$97:$AD$100005="Asignado")*AL$97:AL$100005*$X$97:$X$100005),0)+ROUNDUP(SUMPRODUCT(($I$97:$I$100005=$AE67)*($AD$97:$AD$100005="No Asignado")*AL$97:AL$100005*$X$97:$X$100005),0)} -> 0 | AM67: {=ROUNDUP(SUMPRODUCT(($I$97:$I$100005=$AE67)*($AD$97:$AD$100005="Actual")*AM$97:AM$100005*$X$97:$X$100005),0)+ROUNDUP(SUMPRODUCT(($I$97:$I$100005=$AE67)*($AD$97:$AD$100005="Asignado")*AM$97:AM$100005*$X$97:$X$100005),0)+ROUNDUP(SUMPRODUCT(($I$97:$I$100005=$AE67)*($AD$97:$AD$100005="No Asignado")*AM$97:AM$100005*$X$97:$X$100005),0)} -> 0 | AN67: {=ROUNDUP(SUMPRODUCT(($I$97:$I$100005=$AE67)*($AD$97:$AD$100005="Actual")*AN$97:AN$100005*$X$97:$X$100005),0)+ROUNDUP(SUMPRODUCT(($I$97:$I$100005=$AE67)*($AD$97:$AD$100005="Asignado")*AN$97:AN$100005*$X$97:$X$100005),0)+ROUNDUP(SUMPRODUCT(($I$97:$I$100005=$AE67)*($AD$97:$AD$100005="No Asignado")*AN$97:AN$100005*$X$97:$X$100005),0)} -> 0
AE68: Ingeniero Principal | AF68: =+SUM(AF69:AF71) -> 3 | AG68: =+SUM(AG69:AG71) -> 4 | AH68: =+SUM(AH69:AH71) -> 5 | AI68: =+SUM(AI69:AI71) -> 5 | AJ68: =+SUM(AJ69:AJ71) -> 5 | AK68: =+SUM(AK69:AK71) -> 5 | AL68: =+SUM(AL69:AL71) -> 5 | AM68: =+SUM(AM69:AM71) -> 5 | AN68: =+SUM(AN69:AN71) -> 4
