Workbook
Name _Hlk138162579: 'Base de Datos 2024'!#REF!

Sheet Reportabilidad
B2: Recuentos | E2: Recuentos Chile | H2: Recuentos Rusia | L2: Pipeline REDCO 2024 | O2: Venta REDCO (>10%) | R2: Ingresos REDCO 2024 | U2: Ingresos REDCO (>10%) 2024 | X2: Flujo de ingresos | Y2: Venta Total Posible (>10%) | Z2: Ingresos Totales Posibles (>10%) | AA2: Proyección Venta | AB2: Proyección Ingreso | AC2: Target | AF2: Ingresos 2025 | AG2: =+SUMIFS('Base de Datos 2024'!#REF!,'Base de Datos 2024'!#REF!,"Propuesta",'Base de Datos 2024'!E:E,"Adjudicada",'Base de Datos 2024'!#REF!,"=1",'Base de Datos 2024'!#REF!,"2024") -> #REF! | AI2: Tasa Adjudicación | AL2: Venta | AP2: Ingresos | AV2: 45292 | AW2: 45323 | AX2: 45352 | AY2: 45383 | AZ2: 45413 | BA2: 45444 | BB2: 45474 | BC2: 45505 | BD2: 45536 | BE2: 45566 | BF2: 45597 | BG2: 45627
B3: N° Iniciativas | C3: =COUNTIFS('Base de Datos 2024'!#REF!,"Iniciativa",'Base de Datos 2024'!#REF!,"2024",'Base de Datos 2024'!#REF!,">0,1") -> #REF! | E3: N° Iniciativas | F3: =+COUNTIFS('Base de Datos 2024'!#REF!,"Iniciativa",'Base de Datos 2024'!F:F,"Chile",'Base de Datos 2024'!#REF!,"2024") -> #REF! | H3: N° Iniciativas | I3: =+COUNTIFS('Base de Datos 2024'!#REF!,"Iniciativa",'Base de Datos 2024'!F:F,"Rusia",'Base de Datos 2024'!#REF!,"2024") -> #REF! | L3: Iniciativas | M3: =+SUMIFS('Base de Datos 2024'!K:K,'Base de Datos 2024'!#REF!,"Iniciativa",'Base de Datos 2024'!#REF!,"2024",'Base de Datos 2024'!#REF!,">0,01")/1000000 -> #REF! | O3: Iniciativas | P3: =+SUMIFS('Base de Datos 2024'!K:K,'Base de Datos 2024'!#REF!,"Iniciativa",'Base de Datos 2024'!#REF!,">0,1",'Base de Datos 2024'!#REF!,"2024")/1000000 -> #REF! | R3: Iniciativas | S3: =+SUMIFS('Base de Datos 2024'!#REF!,'Base de Datos 2024'!#REF!,"Iniciativa",'Base de Datos 2024'!#REF!,"2024")/1000000 -> #REF! | U3: Total | V3: =+SUMIFS('Base de Datos 2024'!#REF!,'Base de Datos 2024'!#REF!,"Propuesta",'Base de Datos 2024'!#REF!,">0,1",'Base de Datos 2024'!#REF!,"2024")/1000000 -> #REF! | X3: Iniciativas | Y3: =+P3 -> #REF! | Z3: =+V8 -> #REF! | AA3: =+Y3*$AJ$4 -> #REF! | AB3: =+Z3*$AJ$4 -> #REF! | AU3: Adjudicada | AV3: =+SUMIFS('Base de Datos 2024'!#REF!,'Base de Datos 2024'!#REF!,"Propuesta",'Base de Datos 2024'!$E:$E,"Adjudicada",'Base de Datos 2024'!#REF!,"2024") -> #REF! | AW3: =+SUMIFS('Base de Datos 2024'!#REF!,'Base de Datos 2024'!#REF!,"Propuesta",'Base de Datos 2024'!$E:$E,"Adjudicada",'Base de Datos 2024'!#REF!,"2024") -> #REF! | AX3: =+SUMIFS('Base de Datos 2024'!#REF!,'Base de Datos 2024'!#REF!,"Propuesta",'Base de Datos 2024'!$E:$E,"Adjudicada",'Base de Datos 2024'!#REF!,"2024") -> #REF! | AY3: =+SUMIFS('Base de Datos 2024'!#REF!,'Base de Datos 2024'!#REF!,"Propuesta",'Base de Datos 2024'!$E:$E,"Adjudicada",'Base de Datos 2024'!#REF!,"2024") -> #REF! | AZ3: =+SUMIFS('Base de Datos 2024'!#REF!,'Base de Datos 2024'!#REF!,"Propuesta",'Base de Datos 2024'!$E:$E,"Adjudicada",'Base de Datos 2024'!#REF!,"2024") -> #REF! | BA3: =+SUMIFS('Base de Datos 2024'!#REF!,'Base de Datos 2024'!#REF!,"Propuesta",'Base de Datos 2024'!$E:$E,"Adjudicada",'Base de Datos 2024'!#REF!,"2024") -> #REF! | BB3: =+SUMIFS('Base de Datos 2024'!#REF!,'Base de Datos 2024'!#REF!,"Propuesta",'Base de Datos 2024'!$E:$E,"Adjudicada",'Base de Datos 2024'!#REF!,"2024") -> #REF! | BC3: =+SUMIFS('Base de Datos 2024'!#REF!,'Base de Datos 2024'!#REF!,"Propuesta",'Base de Datos 2024'!$E:$E,"Adjudicada",'Base de Datos 2024'!#REF!,"2024") -> #REF! | ... BG3: =+SUMIFS('Base de Datos 2024'!#REF!,'Base de Datos 2024'!#REF!,"Propuesta",'Base de Datos 2024'!$E:$E,"Adjudicada",'Base de Datos 2024'!#REF!,"2024") -> #REF!
B4: N° Propuestas | C4: =+COUNTIFS('Base de Datos 2024'!#REF!,"Propuesta",'Base de Datos 2024'!#REF!,"2024",'Base de Datos 2024'!#REF!,">0,1")-C8 -> #REF! | E4: N° Propuestas | F4: =+COUNTIFS('Base de Datos 2024'!#REF!,"Propuesta",'Base de Datos 2024'!F:F,"Chile",'Base de Datos 2024'!#REF!,"2024") -> #REF! | H4: N° Propuestas | I4: =+COUNTIFS('Base de Datos 2024'!#REF!,"Propuesta",'Base de Datos 2024'!F:F,"Rusia",'Base de Datos 2024'!#REF!,"2024") -> #REF! | L4: Propuestas | M4: =+(SUMIFS('Base de Datos 2024'!K:K,'Base de Datos 2024'!#REF!,"Propuesta",'Base de Datos 2024'!#REF!,"2024"))/1000000-(M8+M9) -> #REF! | O4: Propuestas | P4: =+SUMIFS('Base de Datos 2024'!K:K,'Base de Datos 2024'!#REF!,"Propuesta",'Base de Datos 2024'!#REF!,">0,1",'Base de Datos 2024'!#REF!,"2024")/1000000-P10 -> #REF! | R4: Propuestas | S4: =+SUMIFS('Base de Datos 2024'!#REF!,'Base de Datos 2024'!#REF!,"Propuesta",'Base de Datos 2024'!#REF!,"2024")/1000000-S10 -> #REF! | U4: En Construcción | V4: =+SUMIFS('Base de Datos 2024'!#REF!,'Base de Datos 2024'!#REF!,"Propuesta",'Base de Datos 2024'!E:E,"En Construcción",'Base de Datos 2024'!#REF!,">0,1",'Base de Datos 2024'!#REF!,"2024")/1000000 -> #REF! | X4: Propuestas | Y4: =+P4 -> #REF! | Z4: =+V3 -> #REF! | AA4: =+(P7+P8)*$AJ$4+P9 -> #REF! | AB4: =(V4+V5)*$AJ$4+V6 -> #REF! | AI4: Tasa de Efectividad | AJ4: =+AJ5/(AJ6+AJ5) -> #REF! | AL4: Adjudicado | AM4: =+M8 -> #REF! | AN4: =+AM4/AM6 -> #REF! | AP4: Adjudicado | AQ4: =+V6 -> #REF! | AR4: =+AQ4/AQ6 -> #REF! | AU4: Por Adjudicar | AV4: =+SUMIFS('Base de Datos 2024'!#REF!,'Base de Datos 2024'!#REF!,">0,1",'Base de Datos 2024'!#REF!,"2024",'Base de Datos 2024'!$E:$E,"Hallazgo Inicial",'Base de Datos 2024'!$E:$E,"En Construccion (Word)",'Base de Datos 2024'!$E:$E,"En Construccion (PPT+Excel)") -> #REF! | AW4: =+SUMIFS('Base de Datos 2024'!#REF!,'Base de Datos 2024'!#REF!,">0,1",'Base de Datos 2024'!#REF!,"2024",'Base de Datos 2024'!$E:$E,"Hallazgo Inicial",'Base de Datos 2024'!$E:$E,"En Construccion (Word)",'Base de Datos 2024'!$E:$E,"En Construccion (PPT+Excel)") -> #REF! | AX4: =+SUMIFS('Base de Datos 2024'!#REF!,'Base de Datos 2024'!#REF!,">0,1",'Base de Datos 2024'!#REF!,"2024",'Base de Datos 2024'!$E:$E,"Hallazgo Inicial",'Base de Datos 2024'!$E:$E,"En Construccion (Word)",'Base de Datos 2024'!$E:$E,"En Construccion (PPT+Excel)") -> #REF! | AY4: =+SUMIFS('Base de Datos 2024'!#REF!,'Base de Datos 2024'!#REF!,">0,1",'Base de Datos 2024'!#REF!,"2024",'Base de Datos 2024'!$E:$E,"Hallazgo Inicial",'Base de Datos 2024'!$E:$E,"En Construccion (Word)",'Base de Datos 2024'!$E:$E,"En Construccion (PPT+Excel)") -> #REF! | AZ4: =+SUMIFS('Base de Datos 2024'!#REF!,'Base de Datos 2024'!#REF!,">0,1",'Base de Datos 2024'!#REF!,"2024",'Base de Datos 2024'!$E:$E,"Hallazgo Inicial",'Base de Datos 2024'!$E:$E,"En Construccion (Word)",'Base de Datos 2024'!$E:$E,"En Construccion (PPT+Excel)") -> #REF! | BA4: =+SUMIFS('Base de Datos 2024'!#REF!,'Base de Datos 2024'!#REF!,">0,1",'Base de Datos 2024'!#REF!,"2024",'Base de Datos 2024'!$E:$E,"Hallazgo Inicial",'Base de Datos 2024'!$E:$E,"En Construccion (Word)",'Base de Datos 2024'!$E:$E,"En Construccion (PPT+Excel)") -> #REF! | BB4: =+SUMIFS('Base de Datos 2024'!#REF!,'Base de Datos 2024'!#REF!,">0,1",'Base de Datos 2024'!#REF!,"2024",'Base de Datos 2024'!$E:$E,"Hallazgo Inicial",'Base de Datos 2024'!$E:$E,"En Construccion (Word)",'Base de Datos 2024'!$E:$E,"En Construccion (PPT+Excel)") -> #REF! | BC4: =+SUMIFS('Base de Datos 2024'!#REF!,'Base de Datos 2024'!#REF!,">0,1",'Base de Datos 2024'!#REF!,"2024",'Base de Datos 2024'!$E:$E,"Hallazgo Inicial",'Base de Datos 2024'!$E:$E,"En Construccion (Word)",'Base de Datos 2024'!$E:$E,"En Construccion (PPT+Excel)") -> #REF! | ... BG4: =+SUMIFS('Base de Datos 2024'!#REF!,'Base de Datos 2024'!#REF!,">0,1",'Base de Datos 2024'!#REF!,"2024",'Base de Datos 2024'!$E:$E,"Hallazgo Inicial",'Base de Datos 2024'!$E:$E,"En Construccion (Word)",'Base de Datos 2024'!$E:$E,"En Construccion (PPT+Excel)") -> #REF!
B5: Total | C5: =+C4+C3 -> #REF! | E5: N° En Construcción | F5: =+COUNTIFS('Base de Datos 2024'!E:E,"En Construcción",'Base de Datos 2024'!#REF!,"Propuesta",'Base de Datos 2024'!F:F,"Chile",'Base de Datos 2024'!#REF!,"2024") -> #REF! | H5: N° En Construcción | I5: =+COUNTIFS('Base de Datos 2024'!E:E,"En Construcción",'Base de Datos 2024'!#REF!,"Propuesta",'Base de Datos 2024'!F:F,"Rusia",'Base de Datos 2024'!#REF!,"2024") -> #REF! | L5: Total | M5: =+M4+M3 -> #REF! | O5: Total | P5: =+P4+P3 -> #REF! | R5: Total | S5: =+S4+S3 -> #REF! | U5: Enviada / Seguimiento | V5: =+SUMIFS('Base de Datos 2024'!#REF!,'Base de Datos 2024'!#REF!,"Propuesta",'Base de Datos 2024'!E:E,"Enviada / Seguimiento",'Base de Datos 2024'!#REF!,">0,1",'Base de Datos 2024'!#REF!,"2024")/1000000 -> #REF! | X5: Total | Y5: =+P5 -> #REF! | Z5: =+V9 -> #REF! | AA5: =+AA4+AA3 -> #REF! | AB5: =+AB4+AB3 -> #REF! | AF5: =+AG2 -> #REF! | AI5: Propuestas Adjudicadas | AJ5: =+C8 -> #REF! | AL5: Por adjudicar | AM5: =+SUMIFS('Base de Datos 2024'!K:K,'Base de Datos 2024'!#REF!,">0,5",'Base de Datos 2024'!#REF!,"2024")/1000000 -> #REF! | AN5: =+AM5/AM6 -> #REF! | AP5: Por adjudicar | AQ5: =+SUMIFS('Base de Datos 2024'!#REF!,'Base de Datos 2024'!#REF!,">0,5",'Base de Datos 2024'!#REF!,"2024")/1000000 -> #REF! | AR5: =+AQ5/AQ6 -> #REF! | AU5: Total | AV5: =+AV4+AV3 -> #REF! | AW5: =+AW4+AW3 -> #REF! | AX5: =+AX4+AX3 -> #REF! | AY5: =+AY4+AY3 -> #REF! | AZ5: =+AZ4+AZ3 -> #REF! | BA5: =+BA4+BA3 -> #REF! | BB5: =+BB4+BB3 -> #REF! | BC5: =+BC4+BC3 -> #REF! | ... BG5: =+BG4+BG3 -> #REF!
B6: N° En Construcción | C6: =+COUNTIFS('Base de Datos 2024'!E:E,"En Construcción",'Base de Datos 2024'!#REF!,"Propuesta",'Base de Datos 2024'!#REF!,"2024",'Base de Datos 2024'!#REF!,">0,1") -> #REF! | L6: En Construcción | M6: =+SUMIFS('Base de Datos 2024'!K:K,'Base de Datos 2024'!#REF!,"Propuesta",'Base de Datos 2024'!E:E,"En Construcción",'Base de Datos 2024'!#REF!,"2024")/1000000 -> #REF! | O6: % del Target | P6: =+P5/15 -> #REF! | U6: Adjudicada | V6: =+SUMIFS('Base de Datos 2024'!#REF!,'Base de Datos 2024'!#REF!,"Propuesta",'Base de Datos 2024'!E:E,"Adjudicada",'Base de Datos 2024'!#REF!,">0,1",'Base de Datos 2024'!#REF!,"2024")/1000000 -> #REF! | AI6: Propuetas No Adjudicadas | AJ6: =+C9 -> #REF! | AL6: Meta | AM6: =15000000/1000000 -> 15 | AP6: Meta | AQ6: 10
B7: N° Enviada / Seguimiento | C7: =+COUNTIFS('Base de Datos 2024'!E:E,"Enviada / Seguimiento",'Base de Datos 2024'!#REF!,"Propuesta",'Base de Datos 2024'!#REF!,"2024",'Base de Datos 2024'!#REF!,">0,1") -> #REF! | E7: N° Enviada / Seguimiento | F7: =+COUNTIFS('Base de Datos 2024'!E:E,"Enviada / Seguimiento",'Base de Datos 2024'!#REF!,"Propuesta",'Base de Datos 2024'!F:F,"Chile",'Base de Datos 2024'!#REF!,"2024") -> #REF! | H7: N° Enviada / Seguimiento | I7: =+COUNTIFS('Base de Datos 2024'!E:E,"Enviada / Seguimiento",'Base de Datos 2024'!#REF!,"Propuesta",'Base de Datos 2024'!F:F,"Rusia",'Base de Datos 2024'!#REF!,"2024") -> #REF! | L7: Enviada / Seguimiento | M7: =+SUMIFS('Base de Datos 2024'!K:K,'Base de Datos 2024'!#REF!,"Propuesta",'Base de Datos 2024'!E:E,"Enviada / Seguimiento",'Base de Datos 2024'!#REF!,"2024")/1000000 -> #REF! | O7: En Construcción | P7: =+SUMIFS('Base de Datos 2024'!K:K,'Base de Datos 2024'!#REF!,"Propuesta",'Base de Datos 2024'!E:E,"En Construcción",'Base de Datos 2024'!#REF!,">0,1",'Base de Datos 2024'!#REF!,"2024")/1000000 -> #REF! | R7: En Construcción | S7: =+SUMIFS('Base de Datos 2024'!#REF!,'Base de Datos 2024'!#REF!,"Propuesta",'Base de Datos 2024'!E:E,"En Construcción",'Base de Datos 2024'!#REF!,"2024")/1000000 -> #REF!
B8: N° Adjudicada | C8: =+COUNTIFS('Base de Datos 2024'!E:E,"Adjudicada",'Base de Datos 2024'!#REF!,"Propuesta",'Base de Datos 2024'!#REF!,"2024",'Base de Datos 2024'!#REF!,">0,1") -> #REF! | E8: N° Adjudicada | F8: =+COUNTIFS('Base de Datos 2024'!E:E,"Adjudicada",'Base de Datos 2024'!#REF!,"Propuesta",'Base de Datos 2024'!F:F,"Chile",'Base de Datos 2024'!#REF!,"2024") -> #REF! | H8: N° Adjudicada | I8: =+COUNTIFS('Base de Datos 2024'!E:E,"Adjudicada",'Base de Datos 2024'!#REF!,"Propuesta",'Base de Datos 2024'!F:F,"Rusia",'Base de Datos 2024'!#REF!,"2024") -> #REF! | L8: Adjudicada | M8: =+SUMIFS('Base de Datos 2024'!K:K,'Base de Datos 2024'!#REF!,"Propuesta",'Base de Datos 2024'!E:E,"Adjudicada",'Base de Datos 2024'!#REF!,"2024")/1000000 -> #REF! | O8: Enviada / Seguimiento | P8: =+SUMIFS('Base de Datos 2024'!K:K,'Base de Datos 2024'!#REF!,"Propuesta",'Base de Datos 2024'!E:E,"Enviada / Seguimiento",'Base de Datos 2024'!#REF!,">0,1",'Base de Datos 2024'!#REF!,"2024")/1000000 -> #REF! | R8: Enviada / Seguimiento | S8: =+SUMIFS('Base de Datos 2024'!#REF!,'Base de Datos 2024'!#REF!,"Propuesta",'Base de Datos 2024'!E:E,"Enviada / Seguimiento",'Base de Datos 2024'!#REF!,"2024")/1000000 -> #REF! | U8: Iniciativas | V8: =+SUMIFS('Base de Datos 2024'!#REF!,'Base de Datos 2024'!#REF!,"Iniciativa",'Base de Datos 2024'!#REF!,">0,1",'Base de Datos 2024'!#REF!,"2024")/1000000 -> #REF!
B9: N° No Adjudicada | C9: =+COUNTIFS('Base de Datos 2024'!E:E,"No Adjudicada",'Base de Datos 2024'!#REF!,"Propuesta",'Base de Datos 2024'!#REF!,"2024") -> #REF! | E9: N° No Adjudicada | F9: =+COUNTIFS('Base de Datos 2024'!E:E,"No Adjudicada",'Base de Datos 2024'!#REF!,"Propuesta",'Base de Datos 2024'!F:F,"Chile",'Base de Datos 2024'!#REF!,"2024") -> #REF! | H9: N° No Adjudicada | I9: =+COUNTIFS('Base de Datos 2024'!E:E,"No Adjudicada",'Base de Datos 2024'!#REF!,"Propuesta",'Base de Datos 2024'!F:F,"Rusia",'Base de Datos 2024'!#REF!,"2024") -> #REF! | L9: No Adjudicada | M9: =+SUMIFS('Base de Datos 2024'!K:K,'Base de Datos 2024'!#REF!,"Propuesta",'Base de Datos 2024'!E:E,"No Adjudicada",'Base de Datos 2024'!#REF!,"2024")/1000000 -> #REF! | O9: Adjudicada | P9: =+SUMIFS('Base de Datos 2024'!K:K,'Base de Datos 2024'!#REF!,"Propuesta",'Base de Datos 2024'!E:E,"Adjudicada",'Base de Datos 2024'!#REF!,">0,1",'Base de Datos 2024'!#REF!,"2024")/1000000 -> #REF! | R9: Adjudicada | S9: =+SUMIFS('Base de Datos 2024'!#REF!,'Base de Datos 2024'!#REF!,"Propuesta",'Base de Datos 2024'!E:E,"Adjudicada",'Base de Datos 2024'!#REF!,"2024")/1000000 -> #REF! | U9: Total | V9: =+V3 -> #REF!
C10: =+C4-(SUM(C6:C9)) -> #REF! | F10: =+F4-(SUM(F5:F9)) -> #REF! | I10: =+I4-(SUM(I5:I9)) -> #REF! | O10: No Adjudicada | P10: =+SUMIFS('Base de Datos 2024'!K:K,'Base de Datos 2024'!#REF!,"Propuesta",'Base de Datos 2024'!E:E,"No Adjudicada",'Base de Datos 2024'!#REF!,">0,1",'Base de Datos 2024'!#REF!,"2024")/1000000 -> #REF! | R10: No Adjudicada | S10: =+SUMIFS('Base de Datos 2024'!#REF!,'Base de Datos 2024'!#REF!,"Propuesta",'Base de Datos 2024'!E:E,"No Adjudicada",'Base de Datos 2024'!#REF!,"2024")/1000000 -> #REF! | U10: No Adjudicada | V10: =+SUMIFS('Base de Datos 2024'!#REF!,'Base de Datos 2024'!#REF!,"Propuesta",'Base de Datos 2024'!E:E,"No Adjudicada",'Base de Datos 2024'!#REF!,">0,1",'Base de Datos 2024'!#REF!,"2024")/1000000 -> #REF!
B11: Recuentos Perú | E11: Recuentos EEUU | H11: Recuentos Brasil
B12: N° Iniciativas | C12: =+COUNTIFS('Base de Datos 2024'!#REF!,"Iniciativa",'Base de Datos 2024'!F:F,"Perú",'Base de Datos 2024'!#REF!,"2024") -> #REF! | E12: N° Iniciativas | F12: =+COUNTIFS('Base de Datos 2024'!#REF!,"Iniciativa",'Base de Datos 2024'!F:F,"EEUU",'Base de Datos 2024'!#REF!,"2024") -> #REF! | H12: N° Iniciativas | I12: =+COUNTIFS('Base de Datos 2024'!#REF!,"Iniciativa",'Base de Datos 2024'!F:F,"Brasil",'Base de Datos 2024'!#REF!,"2024") -> #REF! | N12: Venta REDCO (>10%) por País | R12: Ingresos REDCO (>10%) por País 2024
B13: N° Propuestas | C13: =+COUNTIFS('Base de Datos 2024'!#REF!,"Propuesta",'Base de Datos 2024'!F:F,"Perú",'Base de Datos 2024'!#REF!,"2024") -> #REF! | E13: N° Propuestas | F13: =+COUNTIFS('Base de Datos 2024'!#REF!,"Propuesta",'Base de Datos 2024'!F:F,"EEUU",'Base de Datos 2024'!#REF!,"2024") -> #REF! | H13: N° Propuestas | I13: =+COUNTIFS('Base de Datos 2024'!#REF!,"Propuesta",'Base de Datos 2024'!F:F,"Brasil",'Base de Datos 2024'!#REF!,"2024") -> #REF! | N13: Chile | O13: Iniciativas | P13: =+SUMIFS('Base de Datos 2024'!K:K,'Base de Datos 2024'!#REF!,"Iniciativa",'Base de Datos 2024'!#REF!,">0,1",'Base de Datos 2024'!F:F,"Chile",'Base de Datos 2024'!#REF!,"2024")/1000000 -> #REF! | R13: Chile | S13: Iniciativas | T13: =+SUMIFS('Base de Datos 2024'!#REF!,'Base de Datos 2024'!#REF!,"Iniciativa",'Base de Datos 2024'!#REF!,">0,1",'Base de Datos 2024'!F:F,"Chile",'Base de Datos 2024'!#REF!,"2024")/1000000 -> #REF!
B14: N° En Construcción | C14: =+COUNTIFS('Base de Datos 2024'!E:E,"En Construcción",'Base de Datos 2024'!#REF!,"Propuesta",'Base de Datos 2024'!F:F,"Perú",'Base de Datos 2024'!#REF!,"2024") -> #REF! | E14: N° En Construcción | F14: =+COUNTIFS('Base de Datos 2024'!E:E,"En Construcción",'Base de Datos 2024'!#REF!,"Propuesta",'Base de Datos 2024'!F:F,"EEUU",'Base de Datos 2024'!#REF!,"2024") -> #REF! | H14: N° En Construcción | I14: =+COUNTIFS('Base de Datos 2024'!E:E,"En Construcción",'Base de Datos 2024'!#REF!,"Propuesta",'Base de Datos 2024'!F:F,"Brasil",'Base de Datos 2024'!#REF!,"2024") -> #REF! | O14: Propuestas | P14: =+SUMIFS('Base de Datos 2024'!K:K,'Base de Datos 2024'!#REF!,"Propuesta",'Base de Datos 2024'!#REF!,">0,1",'Base de Datos 2024'!F:F,"Chile",'Base de Datos 2024'!#REF!,"2024")/1000000 -> #REF! | S14: Propuestas | T14: =+SUMIFS('Base de Datos 2024'!#REF!,'Base de Datos 2024'!#REF!,"Propuesta",'Base de Datos 2024'!#REF!,">0,1",'Base de Datos 2024'!F:F,"Chile",'Base de Datos 2024'!#REF!,"2024")/1000000 -> #REF!
N15: EEUU | O15: Iniciativas | P15: =+SUMIFS('Base de Datos 2024'!K:K,'Base de Datos 2024'!#REF!,"Iniciativa",'Base de Datos 2024'!#REF!,">0,1",'Base de Datos 2024'!F:F,"EEUU",'Base de Datos 2024'!#REF!,"2024")/1000000 -> #REF! | R15: EEUU | S15: Iniciativas | T15: =+SUMIFS('Base de Datos 2024'!#REF!,'Base de Datos 2024'!#REF!,"Iniciativa",'Base de Datos 2024'!#REF!,">0,1",'Base de Datos 2024'!F:F,"EEUU",'Base de Datos 2024'!#REF!,"2024")/1000000 -> #REF!
B16: N° Enviada / Seguimiento | C16: =+COUNTIFS('Base de Datos 2024'!E:E,"Enviada / Seguimiento",'Base de Datos 2024'!#REF!,"Propuesta",'Base de Datos 2024'!F:F,"Perú",'Base de Datos 2024'!#REF!,"2024") -> #REF! | E16: N° Enviada / Seguimiento | F16: =+COUNTIFS('Base de Datos 2024'!E:E,"Enviada / Seguimiento",'Base de Datos 2024'!#REF!,"Propuesta",'Base de Datos 2024'!F:F,"EEUU",'Base de Datos 2024'!#REF!,"2024") -> #REF! | H16: N° Enviada / Seguimiento | I16: =+COUNTIFS('Base de Datos 2024'!E:E,"Enviada / Seguimiento",'Base de Datos 2024'!#REF!,"Propuesta",'Base de Datos 2024'!F:F,"Brasil",'Base de Datos 2024'!#REF!,"2024") -> #REF! | O16: Propuestas | P16: =+SUMIFS('Base de Datos 2024'!K:K,'Base de Datos 2024'!#REF!,"Propuesta",'Base de Datos 2024'!#REF!,">0,1",'Base de Datos 2024'!F:F,"EEUU",'Base de Datos 2024'!#REF!,"2024")/1000000 -> #REF! | S16: Propuestas | T16: =+SUMIFS('Base de Datos 2024'!#REF!,'Base de Datos 2024'!#REF!,"Propuesta",'Base de Datos 2024'!#REF!,">0,1",'Base de Datos 2024'!F:F,"EEUU",'Base de Datos 2024'!#REF!,"2024")/1000000 -> #REF!
B17: N° Adjudicada | C17: =+COUNTIFS('Base de Datos 2024'!E:E,"Adjudicada",'Base de Datos 2024'!#REF!,"Propuesta",'Base de Datos 2024'!F:F,"Perú",'Base de Datos 2024'!#REF!,"2024") -> #REF! | E17: N° Adjudicada | F17: =+COUNTIFS('Base de Datos 2024'!E:E,"Adjudicada",'Base de Datos 2024'!#REF!,"Propuesta",'Base de Datos 2024'!F:F,"EEUU",'Base de Datos 2024'!#REF!,"2024") -> #REF! | H17: N° Adjudicada | I17: =+COUNTIFS('Base de Datos 2024'!E:E,"Adjudicada",'Base de Datos 2024'!#REF!,"Propuesta",'Base de Datos 2024'!F:F,"Brasil",'Base de Datos 2024'!#REF!,"2024") -> #REF! | N17: Brasil | O17: Iniciativas | P17: =+SUMIFS('Base de Datos 2024'!K:K,'Base de Datos 2024'!#REF!,"Iniciativa",'Base de Datos 2024'!#REF!,">0,1",'Base de Datos 2024'!F:F,"Brasil",'Base de Datos 2024'!#REF!,"2024")/1000000 -> #REF! | R17: Brasil | S17: Iniciativas | T17: =+SUMIFS('Base de Datos 2024'!#REF!,'Base de Datos 2024'!#REF!,"Iniciativa",'Base de Datos 2024'!#REF!,">0,1",'Base de Datos 2024'!F:F,"Brasil",'Base de Datos 2024'!#REF!,"2024")/1000000 -> #REF!
B18: N° No Adjudicada | C18: =+COUNTIFS('Base de Datos 2024'!E:E,"No Adjudicada",'Base de Datos 2024'!#REF!,"Propuesta",'Base de Datos 2024'!F:F,"Perú",'Base de Datos 2024'!#REF!,"2024") -> #REF! | E18: N° No Adjudicada | F18: =+COUNTIFS('Base de Datos 2024'!E:E,"No Adjudicada",'Base de Datos 2024'!#REF!,"Propuesta",'Base de Datos 2024'!F:F,"EEUU",'Base de Datos 2024'!#REF!,"2024") -> #REF! | H18: N° No Adjudicada | I18: =+COUNTIFS('Base de Datos 2024'!E:E,"No Adjudicada",'Base de Datos 2024'!#REF!,"Propuesta",'Base de Datos 2024'!F:F,"Brasil",'Base de Datos 2024'!#REF!,"2024") -> #REF! | O18: Propuestas | P18: =+SUMIFS('Base de Datos 2024'!K:K,'Base de Datos 2024'!#REF!,"Propuesta",'Base de Datos 2024'!#REF!,">0,1",'Base de Datos 2024'!F:F,"Brasil",'Base de Datos 2024'!#REF!,"2024")/1000000 -> #REF! | S18: Propuestas | T18: =+SUMIFS('Base de Datos 2024'!#REF!,'Base de Datos 2024'!#REF!,"Propuesta",'Base de Datos 2024'!#REF!,">0,1",'Base de Datos 2024'!F:F,"Brasil",'Base de Datos 2024'!#REF!,"2024")/1000000 -> #REF!
C19: =+C13-(SUM(C14:C18)) -> #REF! | F19: =+F13-(SUM(F14:F18)) -> #REF! | I19: =+I13-(SUM(I14:I18)) -> #REF! | N19: Perú | O19: Iniciativas | P19: =+SUMIFS('Base de Datos 2024'!K:K,'Base de Datos 2024'!#REF!,"Iniciativa",'Base de Datos 2024'!#REF!,">0,1",'Base de Datos 2024'!F:F,"Perú",'Base de Datos 2024'!#REF!,"2024")/1000000 -> #REF! | R19: Perú | S19: Iniciativas | T19: =+SUMIFS('Base de Datos 2024'!#REF!,'Base de Datos 2024'!#REF!,"Iniciativa",'Base de Datos 2024'!#REF!,">0,1",'Base de Datos 2024'!F:F,"Perú",'Base de Datos 2024'!#REF!,"2024")/1000000 -> #REF!
B20: Validación | O20: Propuestas | P20: =+SUMIFS('Base de Datos 2024'!K:K,'Base de Datos 2024'!#REF!,"Propuesta",'Base de Datos 2024'!#REF!,">0,1",'Base de Datos 2024'!F:F,"Perú",'Base de Datos 2024'!#REF!,"2024")/1000000 -> #REF! | S20: Propuestas | T20: =+SUMIFS('Base de Datos 2024'!#REF!,'Base de Datos 2024'!#REF!,"Propuesta",'Base de Datos 2024'!#REF!,">0,1",'Base de Datos 2024'!F:F,"Perú",'Base de Datos 2024'!#REF!,"2024")/1000000 -> #REF!
B21: N° Iniciativas | C21: =+C3-(F3+I3+I12+F12+C12) -> #REF! | N21: Rusia | O21: Iniciativas | P21: =+SUMIFS('Base de Datos 2024'!K:K,'Base de Datos 2024'!#REF!,"Iniciativa",'Base de Datos 2024'!#REF!,">0,1",'Base de Datos 2024'!F:F,"Rusia",'Base de Datos 2024'!#REF!,"2024")/1000000 -> #REF! | R21: Rusia | S21: Iniciativas | T21: =+SUMIFS('Base de Datos 2024'!#REF!,'Base de Datos 2024'!#REF!,"Iniciativa",'Base de Datos 2024'!#REF!,">0,1",'Base de Datos 2024'!F:F,"Rusia",'Base de Datos 2024'!#REF!,"2024")/1000000 -> #REF!
B22: N° Propuestas | C22: =+C4-(F4+I4+I13+F13+C13) -> #REF! | O22: Propuestas | P22: =+SUMIFS('Base de Datos 2024'!K:K,'Base de Datos 2024'!#REF!,"Propuesta",'Base de Datos 2024'!#REF!,">0,1",'Base de Datos 2024'!F:F,"Rusia",'Base de Datos 2024'!#REF!,"2024")/1000000 -> #REF! | S22: Propuestas | T22: =+SUMIFS('Base de Datos 2024'!#REF!,'Base de Datos 2024'!#REF!,"Propuesta",'Base de Datos 2024'!#REF!,">0,1",'Base de Datos 2024'!F:F,"Rusia",'Base de Datos 2024'!#REF!,"2024")/1000000 -> #REF!
B23: N° En Construcción | C23: =+C6-(F5+I5+I14+F14+C14) -> #REF! | N23: Total | O23: Iniciativas | P23: =+P21+P19+P17+P15+P13 -> #REF! | R23: Total | S23: Iniciativas | T23: =+T21+T19+T17+T15+T13 -> #REF!
B24: N° Enviada / Seguimiento | C24: =+C7-(F7+I7+I16+F16+C16) -> #REF! | O24: Propuestas | P24: =+P22+P20+P18+P16+P14 -> #REF! | S24: Propuestas | T24: =+T22+T20+T18+T16+T14 -> #REF!
B25: N° Adjudicada | C25: =+C8-(F8+I8+I17+F17+C17) -> #REF! | N25: Total | P25: =+P24+P23 -> #REF! | R25: Total | T25: =+T24+T23 -> #REF!
B26: N° No Adjudicada | C26: =+C9-(F9+I9+I18+F18+C18) -> #REF!
N27: Venta REDCO (>10%) por País | R27: Ingresos por País
N28: Chile | O28: =+P13+P14 -> #REF! | R28: Chile | S28: =+T14 -> #REF!
N29: EEUU | O29: =+P15+P16 -> #REF! | R29: EEUU | S29: =+T16 -> #REF!
N30: Brasil | O30: =+P17+P18 -> #REF! | R30: Brasil | S30: =+T18 -> #REF!
N31: Perú | O31: =+P19+P20 -> #REF! | R31: Perú | S31: =+T20 -> #REF!
N32: Rusia | O32: =+P21+P22 -> #REF! | R32: Rusia | S32: =+T22 -> #REF!
R33: Total | S33: =+SUM(S28:S32) -> #REF!

Sheet Resumen Gen N°
A3: Cuenta de Descripcion Oportunidad | B3: Etiquetas de columna | I3: País | J3: Adjudicadas | K3: Seguimiento | L3: =+E4 -> No Adjudicada | M3: =+G4 -> Total general | N3: Tasa Adjudicación [%por cantidad] | O3: Propuestas Construidas [%] | R3: País | S3: Total Construidas | T3: Adjudicadas | U3: Seguimiento | V3: No adjudicas | X3: Tasa Adjudicación [%] | Y3: Propuestas Construidas [%]
A4: Etiquetas de fila | B4: Adjudicada | C4: En Construcción | D4: Enviada / Seguimiento | E4: No Adjudicada | F4: (en blanco) | G4: Total general | I4: =+A5 -> Brasil | J4: =+B5 -> 9 | K4: 2 | L4: =+E5 -> 1 | M4: =+G5 -> 12 | N4: =+J4/M4 -> 0.75 | O4: =+M4/$M$9 -> 0.081632653 | R4: =+I4 -> Brasil | S4: =+M4 -> 12 | T4: =+J4 -> 9 | U4: =+K4 -> 2 | V4: =+L4 -> 1 | X4: =+T4/(V4+T4) -> 0.9 | Y4: =+S4/$S$8 -> 0.095238095
A5: Brasil | B5: 9 | D5: 2 | E5: 1 | G5: 12 | I5: =+A6 -> Chile | J5: =+B6 -> 32 | K5: 8 | L5: =+E6 -> 20 | M5: =+G6 -> 60 | N5: =+J5/M5 -> 0.53333333 | O5: =+M5/$M$9 -> 0.40816327 | R5: =+I5 -> Chile | S5: =+M5 -> 60 | T5: =+J5 -> 32 | U5: =+K5 -> 8 | V5: =+L5 -> 20 | X5: =+T5/(V5+T5) -> 0.61538462 | Y5: =+S5/$S$8 -> 0.47619048
A6: Chile | B6: 32 | C6: 2 | D6: 6 | E6: 20 | G6: 60 | I6: =+A7 -> EEUU | J6: =+B7 -> 6 | K6: 2 | L6: =+E7 -> 11 | M6: =+G7 -> 19 | N6: =+J6/M6 -> 0.31578947 | O6: =+M6/$M$9 -> 0.1292517 | R6: =+I6 -> EEUU | S6: =+M6 -> 19 | T6: =+J6 -> 6 | U6: =+K6 -> 2 | V6: =+L6 -> 11 | X6: =+T6/(V6+T6) -> 0.35294118 | Y6: =+S6/$S$8 -> 0.15079365
A7: EEUU | B7: 6 | D7: 2 | E7: 11 | G7: 19 | I7: =+A8 -> Perú | J7: =+B8 -> 13 | K7: 4 | L7: =+E8 -> 18 | M7: =+G8 -> 35 | N7: =+J7/M7 -> 0.37142857 | O7: =+M7/$M$9 -> 0.23809524 | R7: =+I7 -> Perú | S7: =+M7 -> 35 | T7: =+J7 -> 13 | U7: =+K7 -> 4 | V7: =+L7 -> 18 | X7: =+T7/(V7+T7) -> 0.41935484 | Y7: =+S7/$S$8 -> 0.27777778
A8: Perú | B8: 13 | D8: 4 | E8: 18 | G8: 35 | I8: =+A9 -> Rusia | J8: =+B9 -> 3 | K8: 2 | L8: =+E9 -> 16 | M8: =+G9 -> 21 | N8: =+J8/M8 -> 0.14285714 | O8: =+M8/$M$9 -> 0.14285714 | R8: Total | S8: =+SUM(S4:S7) -> 126 | T8: =+SUM(T4:T7) -> 60 | U8: =+SUM(U4:U7) -> 16 | V8: =+SUM(V4:V7) -> 50 | X8: =+T8/(V8+T8) -> 0.54545455 | Y8: =+S8/$S$8 -> 1
A9: Rusia | B9: 3 | D9: 2 | E9: 16 | G9: 21 | I9: Total | J9: =+SUM(J4:J8) -> 63 | K9: 18 | L9: =+SUM(L4:L8) -> 66 | M9: =+SUM(M4:M8) -> 147 | N9: =+J9/M9 -> 0.42857143 | O9: =+M9/$M$9 -> 1
A10: (en blanco) | R10: =+I8 -> Rusia | S10: =+SUM(T10:V10) -> 21 | T10: =+J8 -> 3 | U10: =+K8 -> 2 | V10: =+L8 -> 16 | X10: =+T10/(V10+T10) -> 0.15789474 | Y10: =+S10/$S$11 -> 0.14285714
A11: Total general | B11: 63 | C11: 2 | D11: 16 | E11: 66 | G11: 147 | R11: Total | S11: =+S10+S8 -> 147 | T11: =+T10+T8 -> 63 | U11: =+U10+U8 -> 18 | V11: =+V10+V8 -> 66 | X11: =+T11/(V11+T11) -> 0.48837209 | Y11: =+S11/$S$11 -> 1
I12: Promedio Mes | J12: =+SUM(M4:M7)/12 -> 10.5 | K12: =+SUM(J4:J7)/12 -> 5
I13: Promedio Semanal | J13: =+J12/4 -> 2.625
J19: =+J12*150000 -> 1575000

Sheet Resumen Gen Monto
A4: Suma de Monto (USD) | B4: Etiquetas de columna
A5: Etiquetas de fila | B5: Adjudicada | C5: En Construcción | D5: Enviada / Seguimiento | E5: No Adjudicada | F5: (en blanco) | G5: Total general | I5: País | J5: =+G5 -> Total general | K5: Adjudicadas | L5: Seguimiento | M5: =+E5 -> No Adjudicada | O5: Tasa Adjudicación [%] | P5: Propuestas Construidas [%]
A6: Brasil | B6: 1248085 | D6: 1750000 | E6: 101000 | G6: 3099085 | I6: =+A6 -> Brasil | J6: =+SUM(K6:M6) -> 3099085 | K6: =+GETPIVOTDATA("Monto (USD)",$A$4,"Estado Propuesta","Adjudicada","País (Oficina REDCO)","Brasil") -> 1248085 | L6: =+GETPIVOTDATA("Monto (USD)",$A$4,"Estado Propuesta","En Construcción","País (Oficina REDCO)","Brasil")+GETPIVOTDATA("Monto (USD)",$A$4,"Estado Propuesta","Enviada / Seguimiento","País (Oficina REDCO)","Brasil") -> 1750000 | M6: =+GETPIVOTDATA("Monto (USD)",$A$4,"Estado Propuesta","No Adjudicada","País (Oficina REDCO)","Brasil") -> 101000 | O6: =+K6/(M6+K6) -> 0.92513444 | P6: =+J6/$J$10 -> 0.10894067
A7: Chile | B7: 4761416 | C7: 1350000 | D7: 755000 | E7: 3706500 | G7: 10572916 | I7: =+A7 -> Chile | J7: =+SUM(K7:M7) -> 10572916 | K7: =+B7 -> 4761416 | L7: =+GETPIVOTDATA("Monto (USD)",$A$4,"Estado Propuesta","En Construcción","País (Oficina REDCO)","Chile")+GETPIVOTDATA("Monto (USD)",$A$4,"Estado Propuesta","Enviada / Seguimiento","País (Oficina REDCO)","Chile") -> 2105000 | M7: =+GETPIVOTDATA("Monto (USD)",$A$4,"Estado Propuesta","No Adjudicada","País (Oficina REDCO)","Chile") -> 3706500 | O7: =+K7/(M7+K7) -> 0.562289 | P7: =+J7/$J$10 -> 0.37166473
A8: EEUU | B8: 1661000 | D8: 906000 | E8: 6111900 | G8: 8678900 | I8: =+A8 -> EEUU | J8: =+SUM(K8:M8) -> 8678900 | K8: =+B8 -> 1661000 | L8: =+GETPIVOTDATA("Monto (USD)",$A$4,"Estado Propuesta","Enviada / Seguimiento","País (Oficina REDCO)","EEUU") -> 906000 | M8: =+GETPIVOTDATA("Monto (USD)",$A$4,"Estado Propuesta","No Adjudicada","País (Oficina REDCO)","EEUU") -> 6111900 | O8: =+K8/(M8+K8) -> 0.21369116 | P8: =+J8/$J$10 -> 0.30508528
A9: Perú | B9: 1245600 | D9: 1740000 | E9: 3110955 | G9: 6096555 | I9: =+A9 -> Perú | J9: =+SUM(K9:M9) -> 6096555 | K9: =+B9 -> 1245600 | L9: =+GETPIVOTDATA("Monto (USD)",$A$4,"Estado Propuesta","Enviada / Seguimiento","País (Oficina REDCO)","Perú") -> 1740000 | M9: =+GETPIVOTDATA("Monto (USD)",$A$4,"Estado Propuesta","No Adjudicada","País (Oficina REDCO)","Perú") -> 3110955 | O9: =+K9/(M9+K9) -> 0.28591398 | P9: =+J9/$J$10 -> 0.21430932
A10: Rusia | B10: 4709980 | D10: 759000 | E10: 8080206 | G10: 13549186 | I10: Total | J10: =+SUM(K10:M10) -> 28447456 | K10: =+SUM(K6:K9) -> 8916101 | L10: =+SUM(L6:L9) -> 6501000 | M10: =+SUM(M6:M9) -> 13030355 | O10: =+K10/(M10+K10) -> 0.4062661 | P10: =+J10/$J$10 -> 1
A11: (en blanco)
A12: Total general | B12: 13626081 | C12: 1350000 | D12: 5910000 | E12: 21110561 | G12: 41996642 | I12: =+A10 -> Rusia | J12: =+SUM(K12:M12) -> 13549186 | K12: =+B10 -> 4709980 | L12: =+GETPIVOTDATA("Monto (USD)",$A$4,"Estado Propuesta","Enviada / Seguimiento","País (Oficina REDCO)","Rusia") -> 759000 | M12: =+GETPIVOTDATA("Monto (USD)",$A$4,"Estado Propuesta","No Adjudicada","País (Oficina REDCO)","Rusia") -> 8080206 | O12: =+K12/J12 -> 0.34762088 | P12: =+J12/$J$12 -> 1
I13: Total | J13: =+J12+J10 -> 41996642 | K13: =+K12+K10 -> 13626081 | L13: =+L12+L10 -> 7260000 | M13: =+M12+M10 -> 21110561 | O13: =+K13/J13 -> 0.32445644 | P13: =+J13/$J$12 -> 3.0995694
I16: País | J16: Total | K16: Adjudicadas | L16: Seguimiento | M16: No Adjudicadas
I17: =+I6 -> Brasil | J17: =+J6/1000000 -> 3.099085 | K17: =+K6/1000000 -> 1.248085 | L17: =+L6/1000000 -> 1.75 | M17: =+M6/1000000 -> 0.101 | O17: Mensual | P17: =+J10/12 -> 2370621.3
I18: =+I7 -> Chile | J18: =+J7/1000000 -> 10.572916 | K18: =+K7/1000000 -> 4.761416 | L18: =+L7/1000000 -> 2.105 | M18: =+M7/1000000 -> 3.7065
I19: =+I8 -> EEUU | J19: =+J8/1000000 -> 8.6789 | K19: =+K8/1000000 -> 1.661 | L19: =+L8/1000000 -> 0.906 | M19: =+M8/1000000 -> 6.1119 | O19: Semanal | P19: =+P17/4 -> 592655.33
I20: =+I9 -> Perú | J20: =+J9/1000000 -> 6.096555 | K20: =+K9/1000000 -> 1.2456 | L20: =+L9/1000000 -> 1.74 | M20: =+M9/1000000 -> 3.110955
I21: =+I10 -> Total | J21: =+J10/1000000 -> 28.447456 | K21: =+K10/1000000 -> 8.916101 | L21: =+L10/1000000 -> 6.501 | M21: =+M10/1000000 -> 13.030355 | O21: Adjudicado Mensual | P21: =+K21/12 -> 0.74300842
I23: =+I12 -> Rusia | J23: =+J12/1000000 -> 13.549186 | K23: =+K12/1000000 -> 4.70998 | L23: =+L12/1000000 -> 0.759 | M23: =+M12/1000000 -> 8.080206
I24: Total | J24: =+J13/1000000 -> 41.996642 | K24: =+K13/1000000 -> 13.626081 | L24: =+L13/1000000 -> 7.26 | M24: =+M13/1000000 -> 21.110561

Sheet KPIs
U1: Perú | Z1: Chile | AE1: USA | AJ1: Brasil
M2: Promedio | N2: Pendientes | O2: Promedio | P2: Promedio | R2: Promedio | S2: Promedio | U2: Promedio | V2: Pendientes | W2: Promedio | X2: Promedio | Z2: Promedio | AA2: Pendientes | AB2: Promedio | AC2: Promedio | AE2: Promedio | AF2: Pendientes | AG2: Promedio | AH2: Promedio | AJ2: Promedio | AK2: Pendientes | AL2: Promedio | AM2: Promedio | AP2: Promedio de propuestas | AQ2: Adjudicadas | AR2: Pendientes | AS2: No Adjudicadas | AT2: Total
C3: País (Oficina REDCO) | D3: (Todas) | M3: =+AVERAGE(M5:M130) -> 138676.11 | N3: =+AVERAGE(N5:N130) -> 875000 | O3: =+AVERAGE(O5:O130) -> 101000 | P3: =+AVERAGE(P5:P130) -> 258257.08 | R3: =+AVERAGE(R5:R130) -> 675000 | S3: =+AVERAGE(S5:S130) -> 125833.33 | U3: 95815.385 | V3: 435000 | W3: 172830.83 | X3: 174187.29 | Z3: 148794.25 | AA3: 263125 | AB3: 185325 | AC3: 176215.27 | AE3: =+AVERAGE(AE5:AE130) -> 276833.33 | AF3: =+AVERAGE(AF5:AF130) -> 453000 | AG3: =+AVERAGE(AG5:AG130) -> 555627.27 | AH3: =+AVERAGE(AH5:AH130) -> 456784.21 | AJ3: =+AVERAGE(AJ5:AJ130) -> 138676.11 | AK3: =+AVERAGE(AK5:AK130) -> 875000 | AL3: =+AVERAGE(AL5:AL130) -> 101000 | AM3: =+AVERAGE(AM5:AM130) -> 258257.08 | AP3: Brasil | AQ3: 138676.11 | AR3: 875000 | AS3: 101000 | AT3: 258257.08
L4: Etiquetas de fila | M4: Adjudicada | N4: Pendientes | O4: No Adjudicada | P4: Total general | R4: En Construcción | S4: Enviada / Seguimiento | U4: Adjudicada | V4: Pendientes | W4: No Adjudicada | X4: Total general | Z4: Adjudicada | AA4: Pendientes | AB4: No Adjudicada | AC4: Total general | AE4: Adjudicada | AF4: Pendientes | AG4: No Adjudicada | AH4: Total general | AJ4: Adjudicada | AK4: Pendientes | AL4: No Adjudicada | AM4: Total general | AP4: Chile | AQ4: 148794.25 | AR4: 263125 | AS4: 185325 | AT4: 176215.27
C5: Etiquetas de fila | D5: Suma de Monto (USD) | E5: OP | F5: =60/147 -> 0.40816327 | H5: =27/62 -> 0.43548387 | L5: 1 | M5: 78846.6 | P5: 78846.6 | U5: 196600 | V5: - | X5: 196600 | Z5: 200000 | AA5: - | AC5: 200000 | AE5: 612000 | AH5: 612000 | AJ5: 78846.6 | AM5: 78846.6 | AP5: EEUU | AQ5: 276833.33 | AR5: 453000 | AS5: 555627.27 | AT5: 456784.21
C6: 1 | D6: 78846.6 | E6: UG | F6: =87/147 -> 0.59183673 | H6: =35/62 -> 0.56451613 | L6: 2 | M6: 263238.4 | P6: 263238.4 | V6: - | W6: 492580 | X6: 492580 | Z6: 225000 | AA6: - | AC6: 225000 | AG6: 800000 | AH6: 800000 | AJ6: 263238.4 | AM6: 263238.4 | AP6: Perú | AQ6: 95815.385 | AR6: 435000 | AS6: 172830.83 | AT6: 174187.29
C7: 2 | D7: 263238.4 | L7: 3 | M7: 90000 | P7: 90000 | V7: - | W7: 236000 | X7: 236000 | Z7: 200000 | AA7: - | AC7: 200000 | AG7: 1650000 | AH7: 1650000 | AJ7: 90000 | AM7: 90000 | AP7: Total | AQ7: 148602 | AR7: 406313 | AS7: 260607 | AT7: 225773
C8: 3 | D8: 200000 | F8: 3 | G8: 16 | L8: 4 | O8: 101000 | P8: 101000 | U8: 105000 | V8: - | X8: 105000 | Z8: 54000 | AA8: - | AC8: 54000 | AG8: 173900 | AH8: 173900 | AL8: 101000 | AM8: 101000
C9: 4 | D9: 0 | F9: =+F8/G8 -> 0.1875 | L9: 5 | M9: 67000 | P9: 67000 | V9: - | W9: 200000 | X9: 200000 | Z9: 239000 | AA9: - | AC9: 239000 | AG9: 651000 | AH9: 651000 | AJ9: 67000 | AM9: 67000 | AP9: País | AQ9: Diferencia [%]
C10: 5 | D10: 0 | L10: 6 | M10: 60000 | P10: 60000 | V10: - | W10: 285000 | X10: 285000 | Z10: 840000 | AA10: - | AC10: 840000 | AG10: 200000 | AH10: 200000 | AJ10: 60000 | AM10: 60000 | AP10: Brasil | AQ10: =+(AQ3-$AQ$4)/$AQ$4 -> -0.068000873 | AS10: =+(AR7-AQ7)/AQ7 -> 1.7342364
C11: 6 | D11: 0 | L11: 8 | M11: 70000 | P11: 70000 | V11: - | W11: 102545 | X11: 102545 | AA11: - | AB11: 0 | AC11: 0 | AG11: 300000 | AH11: 300000 | AJ11: 70000 | AM11: 70000 | AP11: EEUU | AQ11: =+(AQ5-$AQ$4)/$AQ$4 -> 0.86051096
C12: 7 | D12: 0 | L12: 9 | M12: 40000 | P12: 40000 | V12: - | W12: 149657 | X12: 149657 | AA12: - | AB12: 130000 | AC12: 130000 | AG12: 97000 | AH12: 97000 | AJ12: 40000 | AM12: 40000 | AP12: Perú | AQ12: =+(AQ6-$AQ$4)/$AQ$4 -> -0.35605452
C13: 8 | D13: 0 | L13: 10 | N13: 150000 | P13: 150000 | V13: - | W13: 90120 | X13: 90120 | AA13: - | AB13: 250000 | AC13: 250000 | AG13: 370000 | AH13: 370000 | AK13: 150000 | AM13: 150000
C14: 9 | D14: 0 | L14: 11 | M14: 355000 | P14: 355000 | U14: 119000 | V14: - | X14: 119000 | AA14: - | AB14: 317000 | AC14: 317000 | AE14: 15000 | AH14: 15000 | AJ14: 355000 | AM14: 355000
C15: 10 | D15: 0 | L15: 12 | N15: 1600000 | P15: 1600000 | U15: 74000 | V15: - | X15: 74000 | AA15: - | AB15: 60000 | AC15: 60000 | AE15: 196000 | AH15: 196000 | AK15: 1600000 | AM15: 1600000
C16: 11 | D16: 0 | L16: 14 | M16: 224000 | P16: 224000 | V16: - | W16: 200000 | X16: 200000 | Z16: 300000 | AA16: - | AC16: 300000 | AE16: 98000 | AH16: 98000 | AJ16: 224000 | AM16: 224000
C17: 12 | D17: 0 | L17: 15 | V17: - | W17: 100000 | X17: 100000 | AA17: - | AB17: 145000 | AC17: 145000 | AG17: 70000 | AH17: 70000
C18: 13 | D18: 0 | L18: 16 | V18: - | W18: 40053 | X18: 40053 | Z18: 91650 | AA18: - | AC18: 91650 | AG18: 500000 | AH18: 500000
C19: 14 | D19: 0 | L19: 17 | V19: - | W19: 85000 | X19: 85000 | AA19: - | AB19: 78000 | AC19: 78000 | AE19: 480000 | AH19: 480000
C20: 15 | D20: 0 | L20: 19 | U20: 8000 | V20: - | X20: 8000 | AA20: - | AB20: 1100000 | AC20: 1100000 | AG20: 1300000 | AH20: 1300000
C21: 16 | D21: 0 | L21: 20 | V21: - | W21: 197000 | X21: 197000 | Z21: 88166 | AA21: - | AC21: 88166 | AF21: 566000 | AH21: 566000
C22: 17 | D22: 0 | L22: 21 | U22: 27000 | V22: - | X22: 27000 | AA22: - | AB22: 162000 | AC22: 162000 | AF22: 340000 | AH22: 340000
C23: 18 | D23: 0 | L23: 22 | V23: - | W23: 38000 | X23: 38000 | AA23: - | AB23: 200000 | AC23: 200000 | AE23: 260000 | AH23: 260000
C24: 19 | D24: 0 | L24: 23 | U24: 83000 | V24: - | X24: 83000 | AA24: - | AB24: 520000 | AC24: 520000
C25: 20 | D25: 0 | L25: 24 | U25: 90000 | V25: - | X25: 90000 | AA25: - | AB25: 40000 | AC25: 40000
C26: 21 | D26: 0 | L26: 25 | U26: 70000 | V26: - | X26: 70000 | Z26: 35600 | AA26: - | AC26: 35600
C27: 22 | D27: 0 | L27: 26 | V27: - | W27: 125000 | X27: 125000 | Z27: 30000 | AA27: - | AC27: 30000
C28: 23 | D28: 0 | L28: 27 | V28: - | W28: 80000 | X28: 80000 | AA28: - | AB28: 12500 | AC28: 12500
C29: 24 | D29: 0 | L29: 31 | U29: 133000 | V29: - | X29: 133000 | Z29: 12000 | AA29: - | AC29: 12000
C30: 25 | D30: 0 | L30: 32 | V30: 180000 | X30: 180000 | Z30: 50000 | AA30: - | AC30: 50000
C31: 26 | D31: 0 | L31: 33 | V31: 1100000 | X31: 1100000 | Z31: 43000 | AA31: - | AC31: 43000
C32: 27 | D32: 0 | L32: 34 | V32: - | W32: 250000 | X32: 250000 | Z32: 95000 | AA32: - | AC32: 95000
C33: 28 | D33: 0 | L33: 37 | U33: 270000 | V33: - | X33: 270000 | AA33: - | AB33: 81000 | AC33: 81000
C34: 29 | D34: 0 | L34: 38 | V34: - | W34: 190000 | X34: 190000 | Z34: 190000 | AA34: - | AC34: 190000
C35: 30 | D35: 0 | L35: 39 | U35: 20000 | V35: - | X35: 20000 | AA35: - | AB35: 100000 | AC35: 100000
C36: 31 | D36: 0 | L36: 40 | V36: - | W36: 250000 | X36: 250000 | AA36: - | AB36: 45000 | AC36: 45000
C37: 32 | D37: 0 | L37: 41 | V37: 240000 | X37: 240000 | Z37: 85000 | AA37: - | AC37: 85000
C38: 33 | D38: 0 | L38: 42 | V38: 220000 | X38: 220000 | Z38: 45000 | AA38: - | AC38: 45000
C39: 34 | D39: 0 | L39: 43 | U39: 50000 | V39: - | X39: 50000 | Z39: 70000 | AA39: - | AC39: 70000
C40: 35 | D40: 0 | L40: 44 | Z40: 100000 | AA40: - | AC40: 100000
C41: 36 | D41: 0 | L41: 45 | AA41: - | AB41: 90000 | AC41: 90000
C42: 37 | D42: 0 | L42: 47 | Z42: 66000 | AA42: - | AC42: 66000
C43: 38 | D43: 0 | L43: 48 | Z43: 120000 | AA43: - | AC43: 120000
C44: 39 | D44: 0 | L44: 49 | Z44: 100000 | AA44: - | AC44: 100000
C45: 40 | D45: 0 | L45: 51 | Z45: 500000 | AA45: - | AC45: 500000
C46: 41 | D46: 0 | L46: 52 | Z46: 250000 | AA46: - | AC46: 250000
C47: 42 | D47: 0 | L47: 54 | AA47: - | AB47: 66000 | AC47: 66000
C48: 43 | D48: 0 | L48: 55 | Z48: 75000 | AA48: - | AC48: 75000
C49: 44 | D49: 0 | L49: 56 | Z49: 14000 | AA49: - | AC49: 14000
C50: 45 | D50: 0 | L50: 57 | Z50: 45000 | AA50: - | AC50: 45000
C51: 46 | D51: 0 | L51: 58 | AA51: - | AB51: 160000 | AC51: 160000
C52: 47 | D52: 0 | L52: 60 | Z52: 80000 | AA52: - | AC52: 80000
C53: 48 | D53: 0 | L53: 61 | S53: 170000 | AA53: 170000 | AC53: 170000
C54: 49 | D54: 0 | L54: 62 | S54: 60000 | AA54: 60000 | AC54: 60000
C55: 50 | D55: 0 | L55: 63 | AA55: - | AB55: 150000 | AC55: 150000
C56: 51 | D56: 0 | L56: 64 | Z56: 38000 | AA56: - | AC56: 38000
C57: 52 | D57: 0 | L57: 65 | Z57: 450000 | AA57: - | AC57: 450000
C58: 53 | D58: 0 | L58: 66 | S58: 180000 | AA58: 180000 | AC58: 180000
C59: 54 | D59: 0 | L59: 67 | Z59: 30000 | AA59: - | AC59: 30000
C60: 55 | D60: 0 | L60: 68 | R60: 900000 | AA60: 900000 | AC60: 900000
C61: 56 | D61: 0 | L61: 69 | R61: 450000 | AA61: 450000 | AC61: 450000
C62: 57 | D62: 0 | L62: 70 | S62: 200000 | AA62: 200000 | AC62: 200000
C63: 58 | D63: 0 | L63: 71 | S63: 100000 | AA63: 100000 | AC63: 100000
C64: 59 | D64: 0 | L64: 72 | S64: 45000 | AA64: 45000 | AC64: 45000
C65: 60 | D65: 0 | L65: 73 | AA65: -
C66: 61 | D66: 0 | L66: 74 | AA66: -
C67: 62 | D67: 0 | L67: 75 | AA67: -
C68: 63 | D68: 0 | L68: 76 | AA68: -
C69: 64 | D69: 0 | L69: 77 | AA69: -
C70: 65 | D70: 0 | L70: 78 | AA70: -
C71: 66 | D71: 0 | L71: 80 | AA71: -
C72: 67 | D72: 0 | L72: 81 | AA72: -
C73: 68 | D73: 0 | L73: 82 | AA73: -
C74: 69 | D74: 0 | L74: 83 | AA74: -
C75: 70 | D75: 0 | L75: 84 | AA75: -
C76: 71 | D76: 0 | L76: 85 | AA76: -
... C130: 125 | D130: 0 | L130: 147 | AA130: -
C131: 126 | D131: 0 | L131: Total general | M131: =+SUM(M5:M130) -> 1248085 | N131: =+SUM(N5:N130) -> 1750000 | O131: =+SUM(O5:O130) -> 101000 | P131: =+SUM(P5:P130) -> 3099085 | R131: =+SUM(R5:R130) -> 1350000 | S131: =+SUM(S5:S130) -> 755000 | U131: 1245600 | V131: 1740000 | W131: 3110955 | X131: 6096555 | Z131: 4761416 | AA131: 2105000 | AB131: 3706500 | AC131: 10572916
C132: 127 | D132: 0
C133: 128 | D133: 0
C134: 129 | D134: 0
C135: 130 | D135: 224000
C136: 131 | D136: 60000
C137: 132 | D137: 250000
C138: 133 | D138: 150000
C139: 134 | D139: 38000
C140: 135 | D140: 340000
C141: 136 | D141: 240000
C142: 137 | D142: 220000
C143: 138 | D143: 450000
... C152: 147 | D152: 45000
C153: (en blanco)
C154: Total general | D154: 4729085

Sheet Hoja7
A3: Suma de Monto (USD) | B3: Etiquetas de columna
A4: Etiquetas de fila | B4: Adjudicada | C4: No Adjudicada | D4: Total general | G4: Adjudicada | H4: No Adjudicada | I4: Total general
A5: 7 | B5: 4339980 | D5: 4339980 | F5: 1 | G5: 4339980 | I5: 4339980
A6: 19 | C6: 1650000 | D6: 1650000 | F6: 2 | H6: 1650000 | I6: 1650000
A7: 79 | C7: 1500000 | D7: 1500000 | F7: 3 | H7: 1500000 | I7: 1500000
A8: 118 | C8: 1300000 | D8: 1300000 | F8: 4 | H8: 1300000 | I8: 1300000
A9: 26 | C9: 1100000 | D9: 1100000 | F9: 5 | H9: 1100000 | I9: 1100000
A10: 92 | C10: 1000000 | D10: 1000000 | F10: 6 | H10: 1000000 | I10: 1000000
A11: 59 | C11: 1000000 | D11: 1000000 | F11: 7 | H11: 1000000 | I11: 1000000 | K11: =20/30 -> 0.66666667
A12: 10 | B12: 840000 | D12: 840000 | F12: 8 | G12: 840000 | I12: 840000
A13: 16 | C13: 800000 | D13: 800000 | F13: 9 | H13: 800000 | I13: 800000
A14: 18 | C14: 725000 | D14: 725000 | F14: 10 | H14: 725000 | I14: 725000
A15: 93 | C15: 720000 | D15: 720000 | F15: 11 | H15: 720000 | I15: 720000
A16: 47 | C16: 651000 | D16: 651000 | F16: 12 | H16: 651000 | I16: 651000
A17: 15 | B17: 612000 | D17: 612000 | F17: 13 | G17: 612000 | I17: 612000
A18: 29 | C18: 600000 | D18: 600000 | F18: 14 | H18: 600000 | I18: 600000
A19: 41 | C19: 520000 | D19: 520000 | F19: 15 | H19: 520000 | I19: 520000
A20: 107 | B20: 500000 | D20: 500000 | F20: 16 | G20: 500000 | I20: 500000
A21: 98 | C21: 500000 | D21: 500000 | F21: 17 | H21: 500000 | I21: 500000
A22: 113 | C22: 500000 | D22: 500000 | F22: 18 | H22: 500000 | I22: 500000
A23: 32 | C23: 492580 | D23: 492580 | F23: 19 | H23: 492580 | I23: 492580
A24: 103 | B24: 480000 | D24: 480000 | F24: 20 | G24: 480000 | I24: 480000
A25: 138 | B25: 450000 | D25: 450000 | F25: 21 | G25: 450000 | I25: 450000
A26: 35 | C26: 395205 | D26: 395205 | F26: 22 | H26: 395205 | I26: 395205
A27: 36 | C27: 375000 | D27: 375000 | F27: 23 | H27: 375000 | I27: 375000
A28: 67 | C28: 370000 | D28: 370000 | F28: 24 | H28: 370000 | I28: 370000
A29: 115 | B29: 355000 | D29: 355000 | F29: 25 | G29: 355000 | I29: 355000
A30: 30 | C30: 324700 | D30: 324700 | F30: 26 | H30: 324700 | I30: 324700
A31: 20 | C31: 317000 | D31: 317000 | F31: 27 | H31: 317000 | I31: 317000
A32: 49 | C32: 300000 | D32: 300000 | F32: 28 | H32: 300000 | I32: 300000
A33: 22 | B33: 300000 | D33: 300000 | F33: 29 | G33: 300000 | I33: 300000 | K33: =29/50 -> 0.58
A34: 42 | C34: 285000 | D34: 285000 | F34: 30 | H34: 285000 | I34: 285000
A35: 116 | B35: 270000 | D35: 270000 | F35: 31 | G35: 270000 | I35: 270000
A36: 2 | B36: 263238.4 | D36: 263238.4 | F36: 32 | G36: 263238.4 | I36: 263238.4
A37: 140 | B37: 260000 | D37: 260000 | F37: 33 | G37: 260000 | I37: 260000
A38: 17 | C38: 250000 | D38: 250000 | F38: 34 | H38: 250000 | I38: 250000
A39: 108 | B39: 250000 | D39: 250000 | F39: 35 | G39: 250000 | I39: 250000
A40: 111 | C40: 250000 | D40: 250000 | F40: 36 | H40: 250000 | I40: 250000
A41: 132 | C41: 250000 | D41: 250000 | F41: 37 | H41: 250000 | I41: 250000
A42: 112 | C42: 240000 | D42: 240000 | F42: 38 | H42: 240000 | I42: 240000
A43: 9 | B43: 239000 | D43: 239000 | F43: 39 | G43: 239000 | I43: 239000
A44: 34 | C44: 236000 | D44: 236000 | F44: 40 | H44: 236000 | I44: 236000
A45: 4 | B45: 225000 | D45: 225000 | F45: 41 | G45: 225000 | I45: 225000
A46: 130 | B46: 224000 | D46: 224000 | F46: 42 | G46: 224000 | I46: 224000
A47: 128 | B47: 215000 | D47: 215000 | F47: 43 | G47: 215000 | I47: 215000
A48: 28 | C48: 202300 | D48: 202300 | F48: 44 | H48: 202300 | I48: 202300
A49: 5 | B49: 200000 | D49: 200000 | F49: 45 | G49: 200000 | I49: 200000
A50: 57 | C50: 200000 | D50: 200000 | F50: 46 | H50: 200000 | I50: 200000
A51: 3 | B51: 200000 | D51: 200000 | F51: 47 | G51: 200000 | I51: 200000
A52: 38 | C52: 200000 | D52: 200000 | F52: 48 | H52: 200000 | I52: 200000
A53: 40 | C53: 200000 | D53: 200000 | F53: 49 | H53: 200000 | I53: 200000
A54: 48 | C54: 200000 | D54: 200000 | F54: 50 | H54: 200000 | I54: 200000
A55: 50 | C55: 198000 | D55: 198000 | F55: 51 | H55: 198000 | I55: 198000
A56: 68 | C56: 197000 | D56: 197000 | F56: 52 | H56: 197000 | I56: 197000
A57: 14 | B57: 196600 | D57: 196600 | F57: 53 | G57: 196600 | I57: 196600
A58: 74 | B58: 196000 | D58: 196000 | F58: 54 | G58: 196000 | I58: 196000
A59: 117 | C59: 190000 | D59: 190000 | F59: 55 | H59: 190000 | I59: 190000
A60: 85 | B60: 190000 | D60: 190000 | F60: 56 | G60: 190000 | I60: 190000
A61: 31 | C61: 173900 | D61: 173900 | F61: 57 | H61: 173900 | I61: 173900
A62: 33 | C62: 162000 | D62: 162000 | F62: 58 | H62: 162000 | I62: 162000
A63: 123 | C63: 160000 | D63: 160000 | F63: 59 | H63: 160000 | I63: 160000
A64: 53 | B64: 155000 | D64: 155000 | F64: 60 | G64: 155000 | I64: 155000
A65: 133 | C65: 150000 | D65: 150000 | F65: 61 | H65: 150000 | I65: 150000
A66: 105 | C66: 150000 | D66: 150000 | F66: 62 | H66: 150000 | I66: 150000
A67: 46 | C67: 150000 | D67: 150000 | F67: 63 | H67: 150000 | I67: 150000
A68: 44 | C68: 149657 | D68: 149657 | F68: 64 | H68: 149657 | I68: 149657
A69: 23 | C69: 145000 | D69: 145000 | F69: 65 | H69: 145000 | I69: 145000
A70: 89 | B70: 133000 | D70: 133000 | F70: 66 | G70: 133000 | I70: 133000
A71: 12 | C71: 130000 | D71: 130000 | F71: 67 | H71: 130000 | I71: 130000
A72: 87 | C72: 125000 | D72: 125000 | F72: 68 | H72: 125000 | I72: 125000
A73: 100 | B73: 120000 | D73: 120000 | F73: 69 | G73: 120000 | I73: 120000
A74: 51 | B74: 119000 | D74: 119000 | F74: 70 | G74: 119000 | I74: 119000 | K74: =34/50 -> 0.68
A75: 37 | B75: 105000 | D75: 105000 | F75: 71 | G75: 105000 | I75: 105000
A76: 43 | C76: 102545 | D76: 102545 | F76: 72 | H76: 102545 | I76: 102545
A77: 39 | C77: 101000 | D77: 101000 | F77: 73 | H77: 101000 | I77: 101000
A78: 102 | B78: 100000 | D78: 100000 | F78: 74 | G78: 100000 | I78: 100000
A79: 86 | C79: 100000 | D79: 100000 | F79: 75 | H79: 100000 | I79: 100000
A80: 96 | B80: 100000 | D80: 100000 | F80: 76 | G80: 100000 | I80: 100000
A81: 58 | C81: 100000 | D81: 100000 | F81: 77 | H81: 100000 | I81: 100000
A82: 77 | B82: 98000 | D82: 98000 | F82: 78 | G82: 98000 | I82: 98000
A83: 65 | C83: 97000 | D83: 97000 | F83: 79 | H83: 97000 | I83: 97000
A84: 76 | B84: 95000 | D84: 95000 | F84: 80 | G84: 95000 | I84: 95000
A85: 24 | B85: 91650 | D85: 91650 | F85: 81 | G85: 91650 | I85: 91650
A86: 45 | C86: 90120 | D86: 90120 | F86: 82 | H86: 90120 | I86: 90120
A87: 97 | C87: 90000 | D87: 90000 | F87: 83 | H87: 90000 | I87: 90000
A88: 8 | B88: 90000 | D88: 90000 | F88: 84 | G88: 90000 | I88: 90000
A89: 80 | B89: 90000 | D89: 90000 | F89: 85 | G89: 90000 | I89: 90000
A90: 27 | B90: 88166 | D90: 88166 | F90: 86 | G90: 88166 | I90: 88166
A91: 91 | B91: 85000 | D91: 85000 | F91: 87 | G91: 85000 | I91: 85000
A92: 62 | C92: 85000 | D92: 85000 | F92: 88 | H92: 85000 | I92: 85000
A93: 75 | B93: 83000 | D93: 83000 | F93: 89 | G93: 83000 | I93: 83000
A94: 82 | C94: 81000 | D94: 81000 | F94: 90 | H94: 81000 | I94: 81000
A95: 124 | B95: 80000 | D95: 80000 | F95: 91 | G95: 80000 | I95: 80000
A96: 88 | C96: 80000 | D96: 80000 | F96: 92 | H96: 80000 | I96: 80000
A97: 1 | B97: 78846.6 | D97: 78846.6 | F97: 93 | G97: 78846.6 | I97: 78846.6
A98: 25 | C98: 78000 | D98: 78000 | F98: 94 | H98: 78000 | I98: 78000
A99: 110 | B99: 75000 | D99: 75000 | F99: 95 | G99: 75000 | I99: 75000
A100: 52 | B100: 74000 | D100: 74000 | F100: 96 | G100: 74000 | I100: 74000
A101: 81 | B101: 70000 | D101: 70000 | F101: 97 | G101: 70000 | I101: 70000
A102: 84 | B102: 70000 | D102: 70000 | F102: 98 | G102: 70000 | I102: 70000
...

Sheet Hoja8
A1: 2500
A2: 4666.6667
A3: 6000
A4: 6250
A5: 7500
A6: 8000
A7: 10000
A8: 10000
A9: 10000
A10: 12666.667
A11: 13333.333
A12: 13500
... A145: 309998.57

Sheet Hoja4
A1: Estado Propuesta | B1: Adjudicada
A3: Etiquetas de fila | B3: Promedio de Monto (USD)
A4: ene | B4: 279423.3
A5: feb | B5: 139500
A6: mar | B6: 118308.33
A7: abr | B7: 177333.33
A8: may | B8: 585931.6
A9: jun | B9: 88142.857
A10: jul | B10: 389666.67
A11: ago | B11: 94777.778
A12: sept | B12: 63000
A13: oct | B13: 217500
A14: nov | B14: 75000
A15: dic | B15: 312500
A16: Total general | B16: 230567.57

Sheet Base de Datos 2024
A1: ID | B1: Área | C1: Gestor Comercial (Responsable) | D1: Desarrollador | E1: Estado Propuesta | F1: País (Oficina REDCO) | G1: Empresa | H1: Mina | I1: Descripcion Oportunidad | J1: Tipo de Mineria | K1: Monto (USD) | L1: Tipo de Contrato | M1: Duracion (meses) | N1: Fecha potencial inicio | O1: Core del negocio | P1: Motivo no Adjudicación
A2: 103 | B2: ING | C2: PV | D2: PA | E2: Adjudicada | F2: EEUU | G2: Twin Metals | H2: Birch Lake - Maturi | I2: Prefactibilidad para el conjunto Birch Lake - Maturi | J2: UG | K2: 480000 | L2: Solicitud Directa | M2: 6 | N2: 45658 | O2: Si | Q2: =+K2/M2 -> 80000
A3: 118 | B3: ING | C3: PV | E3: No Adjudicada | F3: EEUU | G3: Highland Copper | H3: Copperword | I3: FS STUDY | J3: UG | K3: 1300000 | L3: Licitación | M3: 12 | N3: 45627 | O3: No | Q3: =+K3/M3 -> 108333.33
A4: 113 | B4: ING | C4: OD | D4: FR | E4: No Adjudicada | F4: Rusia | G4: Highland Gold | H4: Valunisty mine | I4: PFS OP | J4: OP | K4: 500000 | L4: Solicitud Directa | M4: 6 | N4: 45627 | O4: Si | Q4: =+K4/M4 -> 83333.333
A5: 115 | B5: ING | C5: AS | D5: FR | E5: Adjudicada | F5: Brasil | G5: Mosaic | H5: CTV | I5: Proyecto integral CTV Fase 2 | J5: UG | K5: 355000 | L5: Solicitud Directa | M5: 6 | N5: 45627 | O5: Si | Q5: =+K5/M5 -> 59166.667
A6: 116 | B6: ING | C6: FR | D6: PA | E6: Adjudicada | F6: Perú | G6: Minera Hampton | H6: Los Calatos | I6: Los Calatos Pre-FP Study (V3) | J6: UG | K6: 270000 | L6: Solicitud Directa | M6: 6 | N6: 45627 | O6: Si | Q6: =+K6/M6 -> 45000
A7: 112 | B7: ING | C7: OD | D7: FR | E7: No Adjudicada | F7: Rusia | G7: Highland Gold | H7: Taleveem mine | I7: Scoping Study | J7: OP | K7: 240000 | L7: Solicitud Directa | M7: 3 | N7: 45627 | O7: Si | Q7: =+K7/M7 -> 80000
A8: 117 | B8: ING | C8: AZ | D8: AS | E8: No Adjudicada | F8: Perú | G8: Hudbay Perú S.A.C | H8: Constancia | I8: Estudio de Factibilidad del WRF y Tajo Constancia para la 4ta MEIA | J8: OP | K8: 190000 | L8: Licitación | M8: 3 | N8: 45627 | O8: Si | Q8: =+K8/M8 -> 63333.333
A9: 114 | B9: ING | C9: AS | D9: FR | E9: Enviada / Seguimiento | F9: Brasil | G9: Vale | H9: Gongo Soco | I9: Estudio Conceptual | J9: OP | K9: 150000 | L9: Solicitud Directa | M9: 3 | N9: 45627 | O9: Si | Q9: =+K9/M9 -> 50000
A10: 97 | B10: ING | C10: MM | D10: PA | E10: No Adjudicada | F10: Chile | G10: Codelco | H10: DET | I10: ESTUDIO SISTEMA DE GESTIÓN PREMIN DET | J10: UG | K10: 90000 | L10: Licitación | M10: 6 | N10: 45627 | O10: Si | Q10: =+K10/M10 -> 15000
A11: 110 | B11: ING | C11: MM | D11: PA | E11: Adjudicada | F11: Chile | G11: Codelco | H11: DMH | I11: INGENIERÍA EXPLORATORIA DEL PROYECTO DMH NORTE | J11: UG | K11: 75000 | L11: Licitación | M11: 3 | N11: 45597 | O11: Si | Q11: =+K11/M11 -> 25000
A12: 106 | B12: ING | C12: AZ | D12: PA | E12: Enviada / Seguimiento | F12: Perú | G12: Las Bambas | H12: Ferrobamba | I12: PFS Ferrobamba Deep | J12: UG | K12: 1100000 | L12: Licitación | M12: 13 | N12: 45566 | O12: Si | Q12: =+K12/M12 -> 84615.385
A13: 107 | B13: ING | C13: ER | D13: PA | E13: Adjudicada | F13: Chile | G13: AMSA | H13: Centinela | I13: Trade Off Tecnologias de manejo de materiales | J13: q | K13: 500000 | L13: Licitación | M13: 24 | N13: 45566 | O13: Si | Q13: =+K13/M13 -> 20833.333
A14: 108 | B14: ING | C14: ER | D14: PA | E14: Adjudicada | F14: Chile | G14: Capstone Copper | H14: =AVERAGE(M13:M75) -> 4.8730159 | I14: Ing Conceptual: Estudio Extensión Sierra Norte | J14: OP | K14: 250000 | L14: Solicitud Directa | M14: 5 | N14: 45566 | O14: Si | Q14: =+K14/M14 -> 50000
A15: 111 | B15: ING | C15: CH | D15: PA | E15: No Adjudicada | F15: Perú | G15: Sierra Metals | H15: Yauricocha | I15: ESTUDIO DE VENTILACIÓN UNIDAD MINERA YAURICOCHA | J15: UG | K15: 250000 | L15: Licitación | M15: 6 | N15: 45566 | O15: No | Q15: =+K15/M15 -> 41666.667
A16: 101 | B16: ING | C16: AZ | D16: PA | E16: Enviada / Seguimiento | F16: Perú | G16: OCP | H16: Cobriza | I16: Diagnostico operaciónal y construcción de planes alternativos (Blue Sky y potencial) | J16: UG | K16: 180000 | L16: Licitación | M16: 3 | N16: 45566 | O16: Si | Q16: =+K16/M16 -> 60000
A17: 105 | B17: ING | C17: OD | D17: PA | E17: No Adjudicada | F17: Rusia | G17: Seligdar | H17: Seligdar | I17: Construccion de wireframes de cuerpo mineral y modelos de bloque de 2 yacimientos: Nerundinskoye y Mukodek | J17: UG | K17: 150000 | L17: Solicitud Directa | M17: 3 | N17: 45566 | O17: Si | Q17: =+K17/M17 -> 50000
A18: 102 | B18: ING | C18: FR | D18: PA | E18: Adjudicada | F18: Chile | G18: CMP | H18: CNN | I18: Mejoras Operacionales CNN FEL3 (upgrade de la evaluación del proyecto de ampliación) | J18: OP | K18: 100000 | L18: Licitación | M18: 3 | N18: 45566 | O18: Si | Q18: =+K18/M18 -> 33333.333
A19: 109 | B19: ING | C19: PA | D19: PA | E19: No Adjudicada | F19: Chile | G19: Carola | H19: Carola | I19: Apoyo en la planificación de Corto Plazo (SIMPREP) | J19: UG | K19: 66000 | L19: Solicitud Directa | M19: 4 | N19: 45566 | O19: Si | Q19: =+K19/M19 -> 16500
A20: 119 | B20: ING | C20: FR | E20: Adjudicada | F20: Perú | G20: Buenaventura | H20: Tantahuatay | I20: servicio de capacitación en DBS y SIMPLAN | J20: OP | K20: 20000 | L20: Solicitud Directa | M20: 2 | N20: 45566 | O20: Si | Q20: =+K20/M20 -> 10000
A21: 59 | B21: ING | C21: OD | D21: RM | E21: No Adjudicada | F21: Rusia | G21: ERG | H21: - | I21: Desarrollo plan LOM y plan de cierre | J21: OP | K21: 1000000 | L21: Licitación | M21: 12 | N21: 45536 | O21: Si | P21: Anulación de licitación | Q21: =+K21/M21 -> 83333.333
A22: 92 | B22: ING | C22: OD | D22: RM | E22: No Adjudicada | F22: Rusia | G22: Atlas Mining | I22: Ing PFS Mina | J22: OP | K22: 1000000 | L22: Licitación | M22: 6 | N22: 45536 | O22: Si | Q22: =+K22/M22 -> 166666.67
A23: 93 | B23: GEOT | C23: OD | D23: RM | E23: No Adjudicada | F23: Rusia | G23: Kuzbass | H23: Ugol | I23: Modelo 3d geologica de 2 yacimientos | J23: OP | K23: 720000 | L23: Licitación | M23: 12 | N23: 45536 | O23: Si | Q23: =+K23/M23 -> 60000
A24: 38 | B24: ING | C24: AZ | E24: No Adjudicada | F24: Perú | G24: Minera Chinalco Perú S.A | H24: Chinalco | I24: Estimación de Reservas Minerales y Plan de Vida de Mina | J24: OP | K24: 200000 | L24: Licitación | M24: 4 | N24: 45536 | O24: Si | P24: Anulación de licitación | Q24: =+K24/M24 -> 50000
A25: 99 | B25: ING | C25: FR | D25: PA | E25: Adjudicada | F25: Chile | G25: Lundin | H25: Candelaria | I25: Diagnóstico de gaps de planificación y operaciones (Foco en riesgos geomecánicos) | J25: UG | K25: 66000 | L25: Solicitud Directa | M25: 2 | N25: 45536 | O25: Si | Q25: =+K25/M25 -> 33000
A26: 83 | B26: ING | C26: AS | D26: PA | E26: Adjudicada | F26: Brasil | G26: Mosaic | H26: Cajati | I26: Metodologia para evaluar cumplimiento del plan con KPIs reales | J26: UG | K26: 60000 | L26: Solicitud Directa | M26: 2 | N26: 45536 | O26: Si | Q26: =+K26/M26 -> 30000
A27: 11 | B27: ING | C27: MM | E27: No Adjudicada | F27: Chile | G27: Lundin | H27: Candelaria | I27: Mejoras operacionales (Simprep y optimización P&T subterranea) | J27: UG | K27: - | L27: Solicitud Directa | M27: 3 | N27: 45505 | O27: Si
A28: 79 | B28: ING | C28: OD | D28: RM | E28: No Adjudicada | F28: Rusia | G28: EVRAZ | I28: Propuesta sistema de simulación | J28: UG | K28: 1500000 | L28: Licitación | M28: 14 | N28: 45505 | O28: No | Q28: =+K28/M28 -> 107142.86
A29: 98 | B29: ING | C29: PV | E29: No Adjudicada | F29: EEUU | G29: Cementation | I29: Estimación de reservas, mine plan | J29: OP | K29: 500000 | L29: Solicitud Directa | M29: 6 | N29: 45505 | O29: No | Q29: =+K29/M29 -> 83333.333
A30: 85 | B30: ING | D30: PA | E30: Adjudicada | F30: Chile | G30: BHP | H30: Escondida | I30: Modelo predictivo para Definir ubicación óptima de pozos de drenaje | J30: UG | K30: 190000 | L30: Solicitud Directa | M30: 2 | N30: 45505 | O30: No | Q30: =+K30/M30 -> 95000
A31: 31 | B31: ING | C31: PV | E31: No Adjudicada | F31: EEUU | G31: Rockhaven | H31: - | I31: Mining Trade Off Study | J31: UG | K31: 173900 | L31: Solicitud Directa | M31: 3 | N31: 45505 | O31: Si | Q31: =+K31/M31 -> 57966.667
A32: 89 | B32: ING | C32: AZ | D32: PA | E32: Adjudicada | F32: Perú | G32: Minsur | H32: Mina Justa | I32: Estudio técnico – económico para fase de perfil proyecto achupallas | J32: OP | K32: 133000 | L32: Licitación | M32: 2 | N32: 45505 | O32: Si | Q32: =+K32/M32 -> 66500
A33: 87 | B33: ING | C33: MM | D33: PA | E33: No Adjudicada | F33: Perú | G33: Minsur | H33: - | I33: Estandarización, control y seguimiento de KPIs/resultados de corto/mediano plazo para Minsur | J33: UG | K33: 125000 | L33: Solicitud Directa | M33: 4 | N33: 45505 | O33: Si | Q33: =+K33/M33 -> 31250
A34: 100 | B34: ING | C34: FR | D34: PA | E34: Adjudicada | F34: Chile | G34: Lundin | H34: Caserones | I34: Evaluación opciones de mejora a través de nuevos criterios para definir los destinos óptimos y la estrategia de leyes de corte | J34: UG | K34: 120000 | L34: Solicitud Directa | M34: 3 | N34: 45505 | O34: Si | Q34: =+K34/M34 -> 40000
A35: 86 | B35: ING | C35: MM | D35: PV | E35: No Adjudicada | F35: Chile | G35: Codelco | H35: DRT | I35: Análisis y cuantificación de cobre en riesgo por expansión del OP | J35: OP | K35: 100000 | L35: Solicitud Directa | M35: 2 | N35: 45505 | O35: Si | Q35: =+K35/M35 -> 50000
A36: 96 | B36: ING | C36: FR | D36: CH | E36: Adjudicada | F36: Chile | G36: CMP | H36: Algarrobo | I36: Nuevos alcances: Proyecto Algarrobo Finos | J36: OP | K36: 100000 | L36: Solicitud Directa | M36: 10 | N36: 45505 | O36: Si | Q36: =+K36/M36 -> 10000
A37: 91 | B37: ING | C37: MM | D37: PA | E37: Adjudicada | F37: Chile | G37: Codelco | H37: DMH | I37: Estudio Análisis Opciones de Vaciado Mineral Subterránea Vía Rajo Horizonte Corto-Mediano Plazo | J37: OP | K37: 85000 | L37: Licitación | M37: 3 | N37: 45505 | O37: Si | Q37: =+K37/M37 -> 28333.333
A38: 88 | B38: ING | C38: AZ | D38: PA | E38: No Adjudicada | F38: Perú | G38: Buenaventura | H38: El Brocal | I38: Estudio de ingeniería de factibilidad para la Ampliación del Tajo Norte | J38: OP | K38: 80000 | L38: Licitación | M38: 3 | N38: 45505 | O38: Si | P38: Costos muy altos | Q38: =+K38/M38 -> 26666.667
A39: 81 | B39: ING | C39: MF | D39: PA | E39: Adjudicada | F39: Perú | G39: Minsur | H39: San Rafael | I39: Evaluación de recursos marginales | J39: UG | K39: 70000 | L39: Solicitud Directa | M39: 2 | N39: 45505 | O39: Si | Q39: =+K39/M39 -> 35000
A40: 95 | B40: ING | C40: FR | D40: PA | E40: Adjudicada | F40: Chile | G40: BHP | H40: Spence | I40: Análisis de confiabilidad del plan LoA 2025-26 | J40: OP | K40: 70000 | L40: Solicitud Directa | M40: 2 | N40: 45505 | O40: Si | Q40: =+K40/M40 -> 35000
A41: 90 | B41: ING | C41: FR | D41: PA | E41: No Adjudicada | F41: Chile | G41: Codelco | H41: DRT | I41: REVISIÓN INDEPENDIENTE MODELO DE RECURSOS DRT | J41: OP | K41: 45000 | L41: Licitación | M41: 2 | N41: 45505 | O41: No | P41: Anulación de licitación | Q41: =+K41/M41 -> 22500
A42: 94 | B42: ING | C42: FR | E42: Adjudicada | F42: Chile | G42: CMP | H42: CNN | I42: Upgrade Plan Minero CNN - 4.5 Mt Pellet Fee | J42: OP | K42: 45000 | L42: Solicitud Directa | M42: 3 | N42: 45505 | O42: Si | Q42: =+K42/M42 -> 15000
A43: 104 | B43: ING | C43: AS | D43: PA | E43: Adjudicada | F43: Brasil | G43: Lhg | H43: Autazes | I43: Taller y evaluación de información en contexto de riesgos y oportunidades | J43: UG | K43: 40000 | L43: Solicitud Directa | M43: 2 | N43: 45505 | O43: Si | Q43: =+K43/M43 -> 20000
A44: 73 | B44: ING | C44: AZ | D44: PA | E44: No Adjudicada | F44: Perú | G44: Hudbay Perú S.A.C | H44: Constancia | I44: Análisis de Cumplimiento del Plan y Evaluación de Rutas de Alternativas | J44: OP | K44: 38000 | L44: Solicitud Directa | M44: 2 | N44: 45505 | O44: Si | Q44: =+K44/M44 -> 19000
A45: 10 | B45: ING | C45: FR | E45: Adjudicada | F45: Chile | G45: CMP | H45: Romeral | I45: Acompañamiento y ing para puesta en marcha de mina SLS Romeral | J45: OP | K45: 840000 | L45: Solicitud Directa | M45: 12 | N45: 45474 | O45: Si | Q45: =+K45/M45 -> 70000
A46: 9 | B46: ING | C46: FR | E46: Adjudicada | F46: Chile | G46: MCI | H46: Los Bronces | I46: Los Bronces Mine Plan Review | J46: OP | K46: 239000 | L46: Solicitud Directa | M46: 4 | N46: 45474 | O46: Si | Q46: =+K46/M46 -> 59750
A47: 8 | B47: GEOT | C47: CH | E47: Adjudicada | F47: Brasil | G47: Mosaic | H47: Cajati | I47: Actualizacion analisis de Estabilidad OP | J47: OP | K47: 90000 | L47: Marco | M47: 3 | N47: 45474 | O47: Si | Q47: =+K47/M47 -> 30000
A48: 82 | B48: ING | D48: PA | E48: No Adjudicada | F48: Chile | G48: Minera Tres valles | I48: Modelo de flujo gravitacional | J48: UG | K48: 81000 | L48: Solicitud Directa | M48: 2 | N48: 45474 | O48: Si | Q48: =+K48/M48 -> 40500
A49: 13 | B49: ING | C49: OD | E49: No Adjudicada | F49: Rusia | G49: KMARUDA | H49: Planta N°3 | I49: Elaboración de PFS Y ING de detalle para la planta de procesamiento N°3 | J49: OP | K49: - | L49: Solicitud Directa | M49: 12 | N49: 45444 | O49: No | P49: Sin Información
A50: 16 | B50: ING | C50: PV | E50: No Adjudicada | F50: EEUU | G50: Ivanhoe Electric | H50: Santa Cruz | I50: Estudio PFS | J50: UG | K50: 800000 | L50: Solicitud Directa | M50: 12 | N50: 45444 | O50: Si | P50: Estrategia no Adecuada | Q50: =+K50/M50 -> 66666.667
A51: 18 | B51: ING | C51: OD | E51: No Adjudicada | F51: Rusia | G51: Evraz | H51: - | I51: Selección de equipos mineros | J51: UG | K51: 725000 | L51: Solicitud Directa | M51: 3 | N51: 45444 | O51: Si | P51: Sin Información | Q51: =+K51/M51 -> 241666.67
A52: 29 | B52: ING | C52: OD | E52: No Adjudicada | F52: Rusia | G52: EMCO | H52: Solnechny | I52: Optimization of Current Operation and Long-Term Strategy and Trade Off analysis of Transportation System. | J52: UG | K52: 600000 | L52: Licitación | M52: 10 | N52: 45444 | O52: Si | P52: Sin Información | Q52: =+K52/M52 -> 60000
A53: 35 | B53: GEOT | C53: OD | E53: No Adjudicada | F53: Rusia | G53: Alrosa | H53: Yubileynaya | I53: Assestment geomecanico para los parametros del Block Caving | J53: UG | K53: 395205 | L53: Solicitud Directa | M53: 7 | N53: 45444 | O53: Si | P53: Costos muy altos | Q53: =+K53/M53 -> 56457.857
A54: 36 | B54: GEOT | C54: OD | E54: No Adjudicada | F54: Rusia | G54: Eurochem | H54: Zhelezniy | I54: Determinar la estabilidad de los taludes del Rajo y de los emplazamientos y bancos locales del Rajo abierto de Zhelezniy | J54: OP | K54: 375000 | L54: Solicitud Directa | M54: 7 | N54: 45444 | O54: Si | P54: Costos muy altos | Q54: =+K54/M54 -> 53571.429
A55: 30 | B55: ING | C55: OD | E55: No Adjudicada | F55: Rusia | G55: Alrosa | H55: - | I55: Propuesta Tecnologica para MIR | J55: UG | K55: 324700 | L55: Solicitud Directa | M55: 6 | N55: 45444 | O55: No | P55: Sin Información | Q55: =+K55/M55 -> 54116.667
A56: 17 | B56: GEOT | C56: CH | E56: No Adjudicada | F56: Chile | G56: Lundin | H56: Candelaria | I56: Actualización Modelo Geomecánico LOM/Corto Plazo | J56: UG | K56: 250000 | L56: Solicitud Directa | M56: 6 | N56: 45444 | O56: Si | P56: Sin Información | Q56: =+K56/M56 -> 41666.667
A57: 28 | B57: ING | C57: OD | E57: No Adjudicada | F57: Rusia | G57: Polyus | H57: - | I57: Sistema de ore-control para la planificación de corto plazo | J57: UG | K57: 202300 | L57: Solicitud Directa | M57: 6 | N57: 45444 | O57: No | P57: Sin Información | Q57: =+K57/M57 -> 33716.667
A58: 57 | B58: ING | C58: CH | D58: PA | E58: No Adjudicada | F58: Perú | G58: Volcan | H58: Romina | I58: ING Detalle Sistema Ventilación | J58: UG | K58: 200000 | L58: Licitación | M58: 2 | N58: 45444 | O58: No | P58: Selección empresa local | Q58: =+K58/M58 -> 100000
A59: 50 | B59: GEOT | C59: OD | E59: No Adjudicada | F59: Rusia | G59: Polyus | H59: Sukhoy Log | I59: 3D Numerical Analysis of Trial open pit stability | J59: OP | K59: 198000 | L59: Solicitud Directa | M59: 3 | N59: 45444 | O59: Si | P59: Costos muy altos | Q59: =+K59/M59 -> 66000
A60: 68 | B60: ING | C60: ER | D60: MF | E60: No Adjudicada | F60: Perú | G60: Minsur | H60: Raura | I60: Apoyo y mejoramiento de planeamiento de corto plazo | J60: UG | K60: 197000 | L60: Solicitud Directa | M60: 4 | N60: 45444 | O60: Si | Q60: =+K60/M60 -> 49250
A61: 74 | B61: ING | C61: PV | E61: Adjudicada | F61: EEUU | G61: Ivanhoe Electric | H61: Santa Cruz | I61: Mine planning support for PFS | J61: UG | K61: 196000 | L61: Solicitud Directa | M61: 3 | N61: 45444 | O61: Si | Q61: =+K61/M61 -> 65333.333
A62: 12 | B62: ING | C62: RM | D62: PA | E62: No Adjudicada | F62: Chile | G62: Zublin - Strabag | H62: Teniente | I62: Aplicación Simprep en proyecto diamante | J62: UG | K62: 130000 | L62: Solicitud Directa | M62: 4 | N62: 45444 | O62: Si | Q62: =+K62/M62 -> 32500
A63: 77 | B63: ING | C63: PV | E63: Adjudicada | F63: EEUU | G63: EMX Royalty | H63: Chapi | I63: Due Diligence de Chapi (Quilla Resources) | J63: OP | K63: 98000 | L63: Solicitud Directa | M63: 2 | N63: 45444 | O63: Si | Q63: =+K63/M63 -> 49000
A64: 65 | B64: ING | C64: PV | D64: PA | E64: No Adjudicada | F64: EEUU | G64: EMX Royalty | H64: Bunker Hill | I64: Technical Review and Independent Value Assessment (Value@Risk) of Bunker Hill Operation | J64: UG | K64: 97000 | L64: Solicitud Directa | M64: 2 | N64: 45444 | O64: Si | P64: Anulación de licitación | Q64: =+K64/M64 -> 48500
A65: 80 | B65: ING | C65: MF | D65: PA | E65: Adjudicada | F65: Perú | G65: Minsur | H65: San Rafael | I65: Proceso de actualización del LoM | J65: UG | K65: 90000 | L65: Solicitud Directa | M65: 2 | N65: 45444 | O65: Si | Q65: =+K65/M65 -> 45000
A66: 75 | B66: ING | C66: AZ | D66: PA | E66: Adjudicada | F66: Perú | G66: Sierra Metals | H66: Yauricocha | I66: Actualizar los diseños de labores y envolvente del Nivel 1320 al Nivel 1620 | J66: UG | K66: 83000 | L66: Solicitud Directa | M66: 2 | N66: 45444 | O66: Si | Q66: =+K66/M66 -> 41500
A67: 25 | B67: ING | C67: MM | E67: No Adjudicada | F67: Chile | G67: Codelco | H67: DCH | I67: SERVICIO DE ESTUDIO EVALUACION CRECIMIENTO MB NORTE 4 CHUQUICAMATA SUBTERRÁNEA | J67: UG | K67: 78000 | L67: Licitación | M67: 3 | N67: 45444 | O67: Si | Q67: =+K67/M67 -> 26000
A68: 78 | B68: ING | C68: PV | E68: No Adjudicada | F68: EEUU | G68: EMX Royalty | H68: Anaconda Mining | I68: Due Diligence de Goldboro Gold Project (Anaconda Mining) | J68: UG | K68: 70000 | L68: Solicitud Directa | M68: 2 | N68: 45444 | O68: Si | P68: Anulación de licitación | Q68: =+K68/M68 -> 35000
A69: 84 | B69: ING | C69: AS | D69: PA | E69: Adjudicada | F69: Brasil | G69: J&F | I69: Due Diligence study for greenfield project in Brazil (Autazes Potash Project) | J69: UG | K69: 70000 | L69: Solicitud Directa | M69: 2 | N69: 45444 | O69: Si | Q69: =+K69/M69 -> 35000
A70: 69 | B70: ING | C70: FR | D70: PA | E70: Adjudicada | F70: Chile | G70: CMP | H70: Tofo Norte | I70: Revisión de estrategia Tofo Norte, modularizado | J70: UG | K70: 50000 | L70: Solicitud Directa | M70: 2 | N70: 45444 | O70: Si | Q70: =+K70/M70 -> 25000
A71: 54 | B71: ING | C71: RM | E71: No Adjudicada | F71: Chile | G71: Mineria Activa | H71: Pampa Camarones | I71: Análisis 360 de la operación | J71: UG | K71: 40000 | L71: Solicitud Directa | M71: 3 | N71: 45444 | O71: Si | P71: Costos muy altos | Q71: =+K71/M71 -> 13333.333
A72: 56 | B72: ING | C72: CH | D72: CH | E72: Adjudicada | F72: Chile | G72: CEOM/Hoshschield | H72: Inmaculada | I72: Fase 2: mejoras de Corto Plazo | J72: UG | K72: 30000 | L72: Solicitud Directa | M72: 3 | N72: 45444 | O72: Si | Q72: =+K72/M72 -> 10000
A73: 7 | B73: ING | C73: OD | E73: Adjudicada | F73: Rusia | G73: Seligdar | H73: Kyuchus | I73: Execution of the Pre-Feasibility Study for the Kyuchus Mining Project | J73: UG | K73: 4339980 | L73: Licitación | M73: 14 | N73: 45413 | O73: No | Q73: =+K73/M73 -> 309998.57
A74: 67 | B74: ING | C74: ER | D74: PA | E74: No Adjudicada | F74: EEUU | G74: Anglo Gold Ashanti | H74: Merlin | I74: Technical Expert Support Merlin Conceptual Study | J74: UG | K74: 370000 | L74: Solicitud Directa | M74: 4 | N74: 45413 | O74: Si | P74: Selección empresa local | Q74: =+K74/M74 -> 92500
A75: 22 | B75: ING | C75: ER | D75: PA | E75: Adjudicada | F75: Chile | G75: Capstone Copper | H75: 4 operaciones | I75: Methodology for Estimating Mine Plan Reliability (Px) - Phase (1 & 2) (Cozamin, Pinto valley, mantoverde, mantos blancos) | J75: OP | K75: 300000 | L75: Solicitud Directa | M75: 4 | N75: 45413 | O75: Si | Q75: =+K75/M75 -> 75000
A76: 2 | B76: ING | C76: AS | E76: Adjudicada | F76: Brasil | G76: J&F | H76: Mina Urucum | I76: Recuperación de Pilares Mina Urucum | J76: UG | K76: 263238.4 | L76: Solicitud Directa | M76: 8 | N76: 45413 | O76: Si | Q76: =+K76/M76 -> 32904.8
A77: 23 | B77: ING | C77: RM | E77: No Adjudicada | F77: Chile | G77: Anglo American | H77: Chagres | I77: Estudio de Prefactibilidad de Proyecto de Minería Urbana | J77: - | K77: 145000 | L77: Solicitud Directa | M77: 10 | N77: 45413 | O77: No | P77: Sin Información | Q77: =+K77/M77 -> 14500
A78: 37 | B78: ING | C78: AZ | E78: Adjudicada | F78: Perú | G78: Coripuno | H78: Torremani | I78: ALTERNATIVAS DEL METODO DE MINADO EN EL PROYECTO MINERO TORREMANI | J78: UG | K78: 105000 | L78: Licitación | M78: 3 | N78: 45413 | O78: Si | Q78: =+K78/M78 -> 35000
A79: 76 | B79: ING | C79: FR | D79: PA | E79: Adjudicada | F79: Chile | G79: CMP | H79: CNN, MLC | I79: Apoyo LOM 2024 Faenas MLC y CNN | J79: OP | K79: 95000 | L79: Solicitud Directa | M79: 2 | N79: 45413 | O79: Si | Q79: =+K79/M79 -> 47500
A80: 27 | B80: ING | C80: ER | D80: PA | E80: Adjudicada | F80: Chile | G80: Santander | H80: Yauricocha / Bolivar | I80: Revisión en terreno de dos operacones para evaluar fatal flaws. | J80: UG | K80: 88166 | L80: Solicitud Directa | M80: 1 | N80: 45413 | O80: Si | Q80: =+K80/M80 -> 88166
A81: 62 | B81: GEOT | C81: CH | D81: CH | E81: No Adjudicada | F81: Perú | G81: Hoshschield | H81: Inmaculada | I81: Servicio de logeo geomecanico | J81: UG | K81: 85000 | L81: Solicitud Directa | M81: 6 | N81: 45413 | O81: No | P81: Selección empresa local | Q81: =+K81/M81 -> 14166.667
A82: 71 | B82: ING | C82: FR | D82: PA | E82: Adjudicada | F82: Chile | G82: CMP | H82: Los Colorados | I82: “Plan Minero Base Escenario Brownfield MLC | J82: OP | K82: 43000 | L82: Solicitud Directa | M82: 2 | N82: 45413 | O82: Si | Q82: =+K82/M82 -> 21500
A83: 61 | B83: GEOT | C83: CH | D83: PA | E83: No Adjudicada | F83: Perú | G83: Hoshschield | H83: Inmaculada | I83: Revisión Geotecnica de Juicio experto | J83: UG | K83: 40053 | L83: Solicitud Directa | M83: 2 | N83: 45413 | O83: No | P83: Selección empresa local | Q83: =+K83/M83 -> 20026.5
A84: 72 | B84: GEOT | C84: CH | E84: Adjudicada | F84: Perú | G84: Minsur | H84: San Rafael | I84: Geomechanical Analyses of Mine Plan-Mejoramiento de Datos Geotécnicos de Entrada y Refinamiento Geométrico de Sólidos 3D | J84: UG | K84: 27000 | L84: Solicitud Directa | M84: 2 | N84: 45413 | O84: Si | Q84: =+K84/M84 -> 13500
A85: 60 | B85: ING | C85: FR | D85: FR | E85: No Adjudicada | F85: Chile | G85: BCG | H85: - | I85: Apoyo consultivo procesos de planificación minera | J85: OP | K85: 12500 | L85: Solicitud Directa | M85: 2 | N85: 45413 | O85: Si | P85: Sin Información | Q85: =+K85/M85 -> 6250
A86: 64 | B86: ING | C86: ER | D86: PA | E86: Adjudicada | F86: Chile | G86: Glencore | H86: Lomas Bayas | I86: Actualización y capacitación de los modelos MineHaul y MinePlan | J86: OP | K86: 12000 | L86: Solicitud Directa | M86: 2 | N86: 45413 | O86: Si | Q86: =+K86/M86 -> 6000
A87: 19 | B87: ING | C87: PV | E87: No Adjudicada | F87: EEUU | G87: Ivanhoe Electric | H87: Alacran | I87: Asistencia de revisiones y supervisión de Ing. De Detalle de la planta del proyecto Alacran de Cordoba Mining | J87: UG | K87: 1650000 | L87: Solicitud Directa | M87: 12 | N87: 45383 | O87: Si | P87: Sin Información | Q87: =+K87/M87 -> 137500
A88: 15 | B88: ING | C88: PV | E88: Adjudicada | F88: EEUU | G88: McCarthy Abogados | H88: - | I88: Servicio de apoyo experto para defensa de Rio Tinto en Litigio en su contra | J88: UG | K88: 612000 | L88: Solicitud Directa | M88: 5 | N88: 45383 | O88: Si | Q88: =+K88/M88 -> 122400
A89: 34 | B89: ING | C89: AZ | E89: No Adjudicada | F89: Perú | G89: Glencore | H89: Pachon | I89: Estudio de diseños de alternativas de chancado | J89: OP | K89: 236000 | L89: Licitación | M89: 4 | N89: 45383 | O89: Si | P89: Estrategia no Adecuada | Q89: =+K89/M89 -> 59000
A90: 5 | B90: ING | C90: PV | E90: Adjudicada | F90: Chile | G90: BHP | H90: MEL | I90: ESTUDIO FEL -1 DE OPCIONES DE ACCESO EXPLORATORIO - ESCONDIDA EAST DEEP | J90: OP | K90: 200000 | L90: Solicitud Directa | M90: 4 | N90: 45383 | O90: Si | Q90: =+K90/M90 -> 50000
A91: 53 | B91: ING | C91: OD | E91: Adjudicada | F91: Rusia | G91: EUROCHEM | H91: Himmelfarb | I91: auditoría para un " Scoping Study" para reducir Opex y Capex | J91: UG | K91: 155000 | L91: Solicitud Directa | M91: 2 | N91: 45383 | O91: Si | Q91: =+K91/M91 -> 77500
A92: 58 | B92: ING | C92: CH | D92: PA | E92: No Adjudicada | F92: Perú | G92: Volcan | H92: Romina | I92: ING Detalle Sistema Bombeo | J92: UG | K92: 100000 | L92: Licitación | M92: 3 | N92: 45383 | O92: No | P92: Selección empresa local | Q92: =+K92/M92 -> 33333.333
A93: 52 | B93: ING | C93: MF | D93: PA | E93: Adjudicada | F93: Perú | G93: Minsur | H93: San Rafael | I93: Apoyo a la planificación: Integración de Información Planeamiento-Geomecánica // Estudio Conceptual de Justificación Rampa de Acceso Sector San German | J93: UG | K93: 74000 | L93: Solicitud Directa | M93: 3 | N93: 45383 | O93: Si | Q93: =+K93/M93 -> 24666.667
A94: 21 | B94: ING | C94: RM | E94: No Adjudicada | F94: Chile | G94: Las Cenizas | H94: El Sauce | I94: Optimización del desarrollo (Simprep) | J94: UG | K94: 60000 | L94: Solicitud Directa | M94: 3 | N94: 45383 | O94: Si | P94: Costos muy altos | Q94: =+K94/M94 -> 20000
A95: 70 | B95: ING | C95: PV | E95: Adjudicada | F95: EEUU | G95: EMX Royalty | H95: Quilla Project | I95: Metallurgical expert to perform a desktop review | J95: UG | K95: 15000 | L95: Solicitud Directa | M95: 2 | N95: 45383 | O95: Si | Q95: =+K95/M95 -> 7500
A96: 63 | B96: ING | C96: MF | D96: PA | E96: Adjudicada | F96: Perú | G96: Minsur | H96: Raura | I96: Apoyo MEIA Raura | J96: UG | K96: 8000 | L96: Solicitud Directa | M96: 1 | N96: 45383 | O96: Si | Q96: =+K96/M96 -> 8000
A97: 26 | B97: ING | C97: ER | D97: PA | E97: No Adjudicada | F97: Chile | G97: Matrix | H97: - | I97: Revisión de PFS y operaciones (4) | J97: OP | K97: 1100000 | L97: Solicitud Directa | M97: 4 | N97: 45352 | O97: Si | P97: Alcance ineficiente | Q97: =+K97/M97 -> 275000
A98: 32 | B98: ING | C98: MF | E98: No Adjudicada | F98: Perú | G98: Minsur | H98: San Rafael | I98: Definición de KPIs de gestion para Minsur y continuidad proceso SGOP de San Rafael | J98: UG | K98: 492580 | L98: Solicitud Directa | M98: 11 | N98: 45352 | O98: Si | P98: Costos muy altos | Q98: =+K98/M98 -> 44780
A99: 20 | B99: ING | C99: FR | D99: FR | E99: No Adjudicada | F99: Chile | G99: Norte Abierto SpA | H99: Cerro Casale | I99: Optimización de Pit y Diseño de Fase | J99: OP | K99: 317000 | L99: Licitación | M99: 4 | N99: 45352 | O99: Si | P99: Costos muy altos | Q99: =+K99/M99 -> 79250
A100: 3 | B100: ING | C100: RM | E100: Adjudicada | F100: Chile | G100: Lundin | H100: Candelaria | I100: Ingeniería de valor para Robustecer el Proyecto CUGEP | J100: UG | K100: 200000 | L100: Solicitud Directa | M100: 3 | N100: 45352 | O100: Si | Q100: =+K100/M100 -> 66666.667
...

Sheet Hoja5
M13: 480000 | N13: =AVERAGE(M13:M75) -> 216287
M14: 355000
M15: 270000
M16: 75000
M17: 500000
M18: 250000
M19: 100000
M20: 20000
M21: 66000
M22: 60000
M23: 190000
M24: 133000
M25: 120000
... M75: 14000

Sheet POM_Agosto
J1: =+SUM(F2:J2) -> 45 | O1: =+SUM(K2:O2) -> 60.5 | T1: =+SUM(P2:T2) -> 46.8 | Y1: =+SUM(U2:Y2) -> 9 | AD1: =+SUM(Z2:AD2) -> 13 | AI1: =+SUM(AE2:AI2) -> 9 | AN1: =+SUM(AJ2:AN2) -> 9 | AS1: =+SUM(AO2:AS2) -> 9
F2: =+F14+F20+F27+F33+F41+F51+F59+F64+F74+F79+F84+F89+F94+F106+F113+F118+F124+F137+F5+F142+F99+F147 -> 5 | G2: =+G14+G20+G27+G33+G41+G51+G59+G64+G74+G79+G84+G89+G94+G106+G113+G118+G124+G137+G5+G142+G99+G147 -> 7 | H2: =+H14+H20+H27+H33+H41+H51+H59+H64+H74+H79+H84+H89+H94+H106+H113+H118+H124+H137+H5+H142+H99+H147 -> 10.5 | I2: =+I14+I20+I27+I33+I41+I51+I59+I64+I74+I79+I84+I89+I94+I106+I113+I118+I124+I137+I5+I142+I99+I147 -> 14.5 | J2: =+J14+J20+J27+J33+J41+J51+J59+J64+J74+J79+J84+J89+J94+J106+J113+J118+J124+J137+J5+J142+J99+J147 -> 8 | K2: =+K14+K20+K27+K33+K41+K51+K59+K64+K74+K79+K84+K89+K94+K106+K113+K118+K124+K137+K5+K142+K99+K147 -> 7 | L2: =+L14+L20+L27+L33+L41+L51+L59+L64+L74+L79+L84+L89+L94+L106+L113+L118+L124+L137+L5+L142+L99+L147 -> 30 | M2: =+M14+M20+M27+M33+M41+M51+M59+M64+M74+M79+M84+M89+M94+M106+M113+M118+M124+M137+M5+M142+M99+M147 -> 9.5 | ... AS2: =+AS14+AS20+AS27+AS33+AS41+AS51+AS59+AS64+AS74+AS79+AS84+AS89+AS94+AS106+AS113+AS118+AS124+AS137+AS5+AS142+AS99+AS147 -> 0
F3: Semana 05/08 | K3: Semana 12/08 | P3: Semana 19/08 | U3: Semana 26/08 | Z3: Semana 02/09 | AE3: Semana 09/09 | AJ3: Semana 16/09 | AO3: Semana 23/09
A4: ID | B4: País | C4: Tema | D4: Objetivo | E4: Requerimiento | F4: Lunes | G4: Martes | H4: Miércoles | I4: Jueves | J4: Viernes | K4: Lunes | L4: Martes | M4: Miércoles | N4: Jueves | O4: Viernes | P4: Lunes | Q4: Martes | R4: Miércoles | S4: Jueves | T4: Viernes | U4: Lunes | V4: Martes | W4: Miércoles | X4: Jueves | Y4: Viernes | Z4: Lunes | AA4: Martes | AB4: Miércoles | AC4: Jueves | AD4: Viernes | AE4: Lunes | AF4: Martes | AG4: Miércoles | AH4: Jueves | AI4: Viernes | AJ4: Lunes | AK4: Martes | AL4: Miércoles | AM4: Jueves | AN4: Viernes | AO4: Lunes | AP4: Martes | AQ4: Miércoles | AR4: Jueves | AS4: Viernes
A5: 0 | B5: Chile | C5: Reuniones | D5: Reuniones administrativas | F5: =+SUM(F6:F13) -> 2 | G5: =+SUM(G6:G13) -> 0 | H5: =+SUM(H6:H13) -> 2 | I5: =+SUM(I6:I13) -> 2 | J5: =+SUM(J6:J13) -> 0 | K5: =+SUM(K6:K13) -> 2 | L5: =+SUM(L6:L13) -> 4 | M5: =+SUM(M6:M13) -> 2 | ... AS5: =+SUM(AS6:AS13) -> 0
C6: A1 | D6: Reunión ejectuviva (12:00) | F6: 1 | K6: 1 | P6: 1 | U6: 1 | Z6: 1 | AE6: 1 | AJ6: 1 | AO6: 1
C7: A2 | D7: Reunión ejecutiva (13:00) | F7: 1 | K7: 1 | P7: 1 | U7: 1 | Z7: 1 | AE7: 1 | AJ7: 1 | AO7: 1
C8: A3 | D8: Reunión comercial (9:30) | H8: 1 | M8: 1 | R8: 1 | W8: 1 | AB8: 1 | AG8: 1 | AL8: 1 | AQ8: 1
C9: A4 | D9: Reunión de gestión de cobranza (12:30) | H9: 1 | M9: 1 | R9: 1 | W9: 1 | AB9: 1 | AG9: 1 | AL9: 1 | AQ9: 1
C10: A5
C11: A6
C12: A7 | D12: Preparación reunión de gestión | I12: 2 | L12: 4 | AA12: 4
C13: A8 | D13: Reunión de gestión
A14: 1 | B14: USA | C14: KSM | D14: Preparar Statement of Qualifications (SOQ) (20 agosto) | F14: =+SUM(F15:F19) -> 1 | G14: =+SUM(G15:G19) -> 0 | H14: =+SUM(H15:H19) -> 1 | I14: =+SUM(I15:I19) -> 0 | J14: =+SUM(J15:J19) -> 0 | K14: =+SUM(K15:K19) -> 3 | L14: =+SUM(L15:L19) -> 1 | M14: =+SUM(M15:M19) -> 0 | ... AS14: =+SUM(AS15:AS19) -> 0
C15: A1 | D15: Hacer ppta con entendimiento. | F15: 1
C16: A2 | D16: Coordinar con equipo que material vamos a presentar (que y como) | E16: Reunión con ER | H16: 0.5
C17: A3 | D17: Preparar material | H17: 0.5 | I17: 0 | K17: 3
C18: A4 | D18: Validación con PV y equipo de Ing | I18: 0 | L18: 0.5 | P18: 3
C19: A5 | D19: Envio de documento (material) | J19: 0 | K19: 0 | L19: 0.5
A20: 2 | B20: USA | C20: Twin Metals | D20: Prepararación de propuestas Birch Lake - Maturi (05/09) | F20: =+SUM(F21:F25) -> 0 | G20: =+SUM(G21:G25) -> 0 | H20: =+SUM(H21:H25) -> 0 | I20: =+SUM(I21:I25) -> 0 | J20: =+SUM(J21:J25) -> 0 | K20: =+SUM(K21:K25) -> 0 | L20: =+SUM(L21:L25) -> 3 | M20: =+SUM(M21:M25) -> 0.5 | ... AS20: =+SUM(AS21:AS25) -> 0
C21: A1 | D21: Preparación de lamina de entendimiento, alcances y temas principales | G21: 0
C22: A2 | D22: Construcción de excel (HH, gantt, equipo, tareas) y PPT propuesta | K22: 0 | L22: 3
C23: A3 | D23: Validación con PV y equipo de Ing | M23: 0.5
C24: A4 | D24: Construcción documento (word) | N24: 0 | O24: 6 | P24: 6
C25: A5 | D25: Validación con PV y equipo de Ing | Q25: 0.5
C26: A6 | D26: Envio de propuesta | R26: 0.5
A27: 3 | B27: Chile | C27: MassMin | D27: Coordinación participación MassMin | F27: =+SUM(F28:F32) -> 0 | G27: =+SUM(G28:G32) -> 0 | H27: =+SUM(H28:H32) -> 0 | I27: =+SUM(I28:I32) -> 0 | J27: =+SUM(J28:J32) -> 3 | K27: =+SUM(K28:K32) -> 1 | L27: =+SUM(L28:L32) -> 3 | M27: =+SUM(M28:M32) -> 0 | N27: =+SUM(N28:N32) -> 3 | O27: =+SUM(O29:O32) -> 1 | P27: =+SUM(P28:P32) -> 0 | Q27: =+SUM(Q28:Q32) -> 0 | R27: =+SUM(R28:R32) -> 0 | S27: =+SUM(S28:S32) -> 0 | T27: =+SUM(T29:T32) -> 0 | U27: =+SUM(U28:U32) -> 0 | V27: =+SUM(V28:V32) -> 0 | W27: =+SUM(W28:W32) -> 0 | X27: =+SUM(X28:X32) -> 0 | Y27: =+SUM(Y29:Y32) -> 0 | Z27: =+SUM(Z28:Z32) -> 0 | AA27: =+SUM(AA28:AA32) -> 0 | AB27: =+SUM(AB28:AB32) -> 0 | AC27: =+SUM(AC28:AC32) -> 0 | AD27: =+SUM(AD29:AD32) -> 0 | AE27: =+SUM(AE28:AE32) -> 0 | AF27: =+SUM(AF28:AF32) -> 0 | AG27: =+SUM(AG28:AG32) -> 0 | AH27: =+SUM(AH28:AH32) -> 0 | AI27: =+SUM(AI29:AI32) -> 0 | AJ27: =+SUM(AJ28:AJ32) -> 0 | AK27: =+SUM(AK28:AK32) -> 0 | AL27: =+SUM(AL28:AL32) -> 0 | AM27: =+SUM(AM28:AM32) -> 0 | AN27: =+SUM(AN29:AN32) -> 0 | AO27: =+SUM(AO28:AO32) -> 0 | AP27: =+SUM(AP28:AP32) -> 0 | AQ27: =+SUM(AQ28:AQ32) -> 0 | AR27: =+SUM(AR28:AR32) -> 0 | AS27: =+SUM(AS29:AS32) -> 0
C28: A1 | D28: Reunión de coordinación sobre fechas, temas a presentar, etc | E28: Reunión con PV, MF, ER | K28: 1
C29: A2 | D29: Preparar diseño stand | E29: Validación ER | J29: 3
C30: A3 | D30: Preparar presentaciones (ppt) | K30: 0 | L30: 2
C31: A4 | D31: Presentar presentaciones | N31: 3
C32: A5 | D32: Revisión de presentaciones | L32: 1 | O32: 1
A33: 4 | B33: Rusia | C33: Viaje Rusia | D33: Coordinación viaje a Rusia | F33: =+SUM(F34:F35) -> 1 | G33: =+SUM(G34:G35) -> 0 | H33: =+SUM(H34:H35) -> 0 | I33: =+SUM(I34:I35) -> 4 | J33: =+SUM(J34:J35) -> 0 | K33: =+SUM(K34:K35) -> 0 | L33: =+SUM(L34:L35) -> 0 | M33: =+SUM(M34:M35) -> 0 | ... AS33: =+SUM(AS34:AS35) -> 0
C34: A1 | D34: Reunión de coordinación sobre fechas, material para presentar, etc | E34: Reunión con OD y FR | F34: 1
C35: A2 | D35: Preparar presentación actualizada con casos de éxito UG | I35: 4
C36: A3 | D36: Revisión de plan de visita a empresas | K36: 1
C37: A4 | D37: Asiganación de recursos a las solicitudes | O37: 1 | P37: 1 | Q37: 1 | R37: 1
C38: A5
C39: A6
C40: A7
A41: 5 | B41: Perú | C41: Cobriza | D41: Preparar Propuesta Cobriza (Envio propuesta 22/08) | F41: =+SUM(F42:F50) -> 0 | G41: =+SUM(G42:G50) -> 0 | H41: =+SUM(H42:H50) -> 1 | I41: =+SUM(I42:I50) -> 0 | J41: =+SUM(J42:J50) -> 0 | K41: =+SUM(K42:K50) -> 0 | L41: =+SUM(L42:L50) -> 0 | M41: =+SUM(M42:M50) -> 0 | ... AS41: =+SUM(AS42:AS50) -> 0
C42: A1 | H42: 1
C43: A2 | Q43: 1
C44: A3 | R44: 2
C45: A4 | S45: 0.5
C46: A5 | S46: 5
C49: A6 | T49: 0.5
C50: A7 | T50: 0.1
A51: 6 | B51: Perú | D51: Continuidad de trabajo Coroccohuayco y Antapacay | F51: =+SUM(F52:F58) -> 0 | G51: =+SUM(G52:G58) -> 1 | H51: =+SUM(H52:H58) -> 1 | I51: =+SUM(I52:I58) -> 0 | J51: =+SUM(J52:J58) -> 0 | K51: =+SUM(K52:K58) -> 0 | L51: =+SUM(L52:L58) -> 0 | M51: =+SUM(M52:M58) -> 0 | ... AS51: =+SUM(AS52:AS58) -> 0
C52: A1 | D52: Reunión aclaratoria | G52: 1 | H52: 1
C53: A2 | D53: Preparación de lamina de entendimiento, alcances y temas principales | Q53: 1
C54: A3 | D54: Construcción de excel (HH, gantt, equipo, tareas) y PPT propuesta | R54: 2
C55: A4 | D55: Validación con CM y equipo de Ing | S55: 0.5
C56: A5 | D56: Construcción documento (word) | S56: 5
C57: A6 | D57: Validación con CM y equipo de Ing | T57: 0.5
C58: A7 | D58: Envio de propuesta | T58: 0.1
A59: 7 | B59: Perú | D59: Reunión con El Brocal | F59: =+SUM(F60:F63) -> 0 | G59: =+SUM(G60:G63) -> 0 | H59: =+SUM(H60:H63) -> 0.5 | I59: =+SUM(I60:I63) -> 0 | J59: =+SUM(J60:J63) -> 0 | K59: =+SUM(K60:K63) -> 0 | L59: =+SUM(L60:L63) -> 0 | M59: =+SUM(M60:M63) -> 0 | ... AS59: =+SUM(AS60:AS63) -> 0
C60: A1 | D60: Coordinar con AZ temas a preentar | E60: Renuión con AZ,FR | H60: 0.5
C61: A2 | D61: Preparar Presentación OP/UG
C62: A3
C63: A4
A64: 8 | B64: Perú | D64: Miskimayo | F64: =+SUM(F65:F73) -> 0 | G64: =+SUM(G65:G73) -> 0 | H64: =+SUM(H65:H73) -> 0 | I64: =+SUM(I65:I73) -> 0 | J64: =+SUM(J65:J73) -> 1 | K64: =+SUM(K65:K73) -> 0 | L64: =+SUM(L65:L73) -> 4.5 | M64: =+SUM(M65:M73) -> 0 | ... AS64: =+SUM(AS65:AS73) -> 0
C65: A1 | D65: Reunión de coordinación con CM | J65: 1 | L65: 0
C66: A2 | D66: Preparar presentación visión estratégica | L66: 4
C67: A3 | D67: Determinar QP para actualizar Recursos y Reservas | L67: 0.5
C68: A4 | D68: Preparación de lamina de entendimiento, alcances y temas principales | Q68: 1
C69: A5 | D69: Construcción de excel (HH, gantt, equipo, tareas) y PPT propuesta | R69: 2
C70: A6 | D70: Validación con CM y equipo de Ing | S70: 0.5
C71: A7 | D71: Construcción documento (word) | S71: 5
C72: A8 | D72: Validación con CM y equipo de Ing | T72: 0.5
C73: A9 | D73: Envio de propuesta | T73: 0.1
A74: 9 | B74: Perú | D74: Nemont: Yanacocha | F74: =+SUM(F75:F78) -> 0 | G74: =+SUM(G75:G78) -> 0 | H74: =+SUM(H75:H78) -> 0 | I74: =+SUM(I75:I78) -> 0 | J74: =+SUM(J75:J78) -> 0 | K74: =+SUM(K75:K78) -> 0 | L74: =+SUM(L75:L78) -> 0 | M74: =+SUM(M75:M78) -> 2 | ... AS74: =+SUM(AS75:AS78) -> 0
C75: A1 | D75: Reunión de coordinación con CM | M75: 1
C76: A2 | D76: Reunión con Cliente | M76: 1
C77: A3
C78: A4
A79: 10 | B79: Chile | D79: Propuesta CNN | F79: =+SUM(F80:F83) -> 0 | G79: =+SUM(G80:G83) -> 0 | H79: =+SUM(H80:H83) -> 3.5 | I79: =+SUM(I80:I83) -> 0 | J79: =+SUM(J80:J83) -> 0 | K79: =+SUM(K80:K83) -> 0 | L79: =+SUM(L80:L83) -> 0 | M79: =+SUM(M80:M83) -> 0 | ... AS79: =+SUM(AS80:AS83) -> 0
C80: A1 | D80: Construcción de propuesta | G80: 0 | H80: 3
C81: A2 | D81: Envio propuesta | H81: 0.5
C82: A3
C83: A4
A84: 11 | B84: Chile | D84: BHP - Modelo predictivo | F84: =+SUM(F85:F88) -> 0 | G84: =+SUM(G85:G88) -> 0 | H84: =+SUM(H85:H88) -> 1.5 | I84: =+SUM(I85:I88) -> 0 | J84: =+SUM(J85:J88) -> 0 | K84: =+SUM(K85:K88) -> 0 | L84: =+SUM(L85:L88) -> 2.5 | M84: =+SUM(M85:M88) -> 4 | ... AS84: =+SUM(AS85:AS88) -> 0
C85: A1 | D85: Preparar y tener KOM Interno con Cati | H85: 1.5
C86: A2 | D86: Preparar contrato Carlos Morante | H86: 0 | I86: 0 | L86: 0.5
C87: A3 | D87: Revisar y modificar contrato con MCD | E87: Feedback de FR para ver que temas claves incorporar | H87: 0 | I87: 0 | L87: 2
C88: A4 | D88: Ejecución del proyecto | M88: 4 | R88: 4 | W88: 4 | AB88: 4 | AG88: 4 | AL88: 4 | AQ88: 4
A89: 12 | B89: Perú | D89: Propuesta Chinalco | F89: =+SUM(F90:F93) -> 0 | G89: =+SUM(G90:G93) -> 0 | H89: =+SUM(H90:H93) -> 0 | I89: =+SUM(I90:I93) -> 0 | J89: =+SUM(J90:J93) -> 0 | K89: =+SUM(K90:K93) -> 0 | L89: =+SUM(L90:L93) -> 3 | M89: =+SUM(M90:M93) -> 0 | ... AS89: =+SUM(AS90:AS93) -> 0
C90: A1 | D90: Actualización de propuesta | E90: Espera de inf del cliente | L90: 3
C91: A2
C92: A3
C93: A4
A94: 13 | B94: Perú | D94: Propuestas San Rafael - Recursos potenciales | F94: =+SUM(F95:F98) -> 0 | G94: =+SUM(G95:G98) -> 0 | H94: =+SUM(H95:H98) -> 0 | I94: =+SUM(I95:I98) -> 0 | J94: =+SUM(J95:J98) -> 0 | K94: =+SUM(K95:K98) -> 0 | L94: =+SUM(L95:L98) -> 0 | M94: =+SUM(M95:M98) -> 0 | ... AS94: =+SUM(AS95:AS98) -> 0
C95: A1 | D95: Construicción propuesta recursos potenciales | E95: Solicitud de AZ para solicitar alcances | F95: 0
C96: A2 | I96: 0
C97: A3
C98: A4
A99: 15 | B99: Brasil | D99: Mosaic | F99: =+SUM(F100:F105) -> 0 | G99: =+SUM(G100:G105) -> 0 | H99: =+SUM(H100:H105) -> 0 | I99: =+SUM(I100:I105) -> 0 | J99: =+SUM(J100:J105) -> 0 | K99: =+SUM(K100:K105) -> 0 | L99: =+SUM(L100:L105) -> 0 | M99: =+SUM(M100:M105) -> 0 | ... AS99: =+SUM(AS100:AS105) -> 0
C100: A1 | D100: P2 CAJ | E100: Reunión de coordinación con AS, FR, AF | O100: 1
C101: A2 | D101: CTV fase 2 (Optimización) | E101: Reunión de coordinación con AS, FR, AF | O101: 1
C102: A3
...

Sheet Lista de proyectos
A1: Área | B1: Gestor Comercial (Responsable) | C1: Desarrollador | D1: País (Oficina REDCO) | E1: Empresa | F1: Mina | G1: Descripcion Oportunidad | H1: Prioridad | I1: Plan de acción | J1: Fecha entrega | K1: Monto (USD) | L1: Semana 19/08 | M1: Semana 26/08 | N1: Semana 02/09
A2: ING | B2: FR | C2: PA | D2: Chile | E2: Lundin | F2: Caserones | G2: Limpieza de presentación y envio de puntos entendido por REDCO | H2: 1 | I2: A la espera de Felipe | J2: 45413
A3: ING | B3: MM | C3: PA | D3: Perú | E3: Minsur | F3: - | G3: Estandarización, control y seguimiento de KPIs/resultados de corto/mediano plazo para Minsur | H3: 1 | J3: 45413 | K3: 166000
A4: GEOT | B4: CH | C4: CH | D4: Perú | E4: Hudbay Perú S.A.C | F4: Constancia | G4: Análisis de estabilidad OP | H4: 1 | I4: Cladio + Eduardo | J4: 45474 | K4: 81000
A5: ING | B5: FR | E5: CMP | F5: CNN | G5: Reevaluacuión caso sin proyecto vs caso sin proyecto a 6MT | H5: 1 | I5: Felipe Rojas | J5: 45474
A6: ING | B6: FR | C6: PA | D6: Chile | E6: BHP | F6: Spence | G6: Analisis de cumplimiento del plan y evaluación de iniciativas LoA 25 (mediante herramienta SIMPLAN) | H6: 1 | J6: 45476 | K6: 45000
A7: GEOT | B7: AZ | C7: PA | D7: Perú | E7: Buenaventura | F7: El Brocal | G7: Análisis de estabilidad OP | H7: 1 | I7: Revisión final de Claudio | J7: 45477 | K7: 82000
A8: ING | B8: PA | C8: PA | D8: Chile | E8: Codelco | F8: DRT | G8: REVISIÓN INDEPENDIENTE MODELO DE RECURSOS DRT | H8: 1 | I8: Armar pedro aguiluz, buscar ejemplos: Ecuador, hablar mati, ivanhoe | J8: 45478
A9: ING | B9: PA | C9: PA | D9: Chile | E9: Codelco | F9: DCH | G9: Estudio Análisis Opciones de Vaciado Mineral Subterránea Vía Rajo Horizonte Corto-Mediano Plazo | H9: 1 | I9: Responsable Mauro Melendez | J9: 45483
A10: ING | D10: Chile | E10: BHP | F10: Escondida | G10: Modelo predictivo para Definir ubicación óptima de pozos de drenaje | H10: 1 | I10: Enviar propuesta final | J10: 45485 | K10: 200000
A11: ING | B11: FR | C11: PA | D11: Chile | E11: CMP | F11: - | G11: Contrato Marco de Ingeniería – Gerencia de Planificación & Desarrollo CMP | H11: 1 | J11: 45485 | K11: -
A12: ING | B12: MM | C12: PA | D12: Chile | E12: Minera Tres valles | G12: Construcción propuesta simple | H12: 1 | I12: Alejandro espinoza, construir ppt | J12: 45488 | K12: 60000
A13: ING | B13: FR | C13: PA | D13: Chile | E13: Lundin | F13: Corporativo | G13: Revisión gaps de planificación y operaciones | J13: 45490
A14: ING | B14: Codelco | C14: PA | D14: Chile | E14: Codelco | F14: Andina | G14: RFP Servicios de estudios de ingeniería para proyectos | H14: 1 | I14: Envio de no participación | J14: 45491 | K14: -
A15: ING | B15: AZ | C15: PA | D15: Perú | E15: Minsur | F15: Mina Justa | G15: Estudio técnico – económico para fase de perfil proyecto achupallas | H15: 2 | I15: connstruir propuesta | J15: 45491 | K15: 150000
A16: ING | B16: PA | C16: PA | D16: Chile | E16: EY/Codelco | F16: - | G16: “SERVICIO DE INGENIERÍA DE APOYO A PROYECTOS PARA LA DESCARBONIZACIÓN DE PROCESOS” | H16: 1 | I16: Enviado primer paquete | J16: 45496 | K16: -
A17: ING | B17: PV | C17: PA | D17: USA | E17: Cementation | G17: Estimación de reservas, mine plan | J17: 45497
A18: ING | B18: PA | C18: PA | D18: Chile | E18: Codelco | F18: GERENCIA Planificación DISTRITO NORTE | G18: CONTRATO MARCO DE SERVICIOS POR ESPECIALIDAD PARA DIRECCIÓN PLANIFICACIÓN Y DESARROLLO MINERO | H18: 1 | J18: 45497 | K18: -
A19: ING | B19: MM | C19: MM | D19: Chile | E19: Codelco | F19: Teniente | G19: ESTUDIO SISTEMA DE GESTIÓN PREMIN DET | H19: 2 | J19: 45505 | K19: 120000 | L19: 2 | M19: 0 | N19: 0
A20: ING | B20: FR | C20: PA | D20: Chile | E20: CMP | F20: CNN | G20: CNN FEL 3 | J20: 45509 | K20: 180000
A21: ING | B21: OD | D21: Rusia | G21: Envio material de Oro | H21: 3 | J21: 45523
A22: ING | B22: PV | C22: FR | D22: USA | E22: Seabridge Gold | F22: KSM | G22: SOQ KSM | H22: 1 | I22: Completar información requerida y ver CVs | J22: 45524 | L22: 2 | M22: 0 | N22: 0
A23: ING | B23: AS | C23: PA | D23: Brasil | E23: Lhg Mining | F23: Urucum | G23: LOM con nueva configuración de pilares | H23: 1 | I23: Reunión con Alex para revisar propuesta | J23: 45524 | L23: 2 | M23: 0 | N23: 0
A24: ING | B24: AZ | C24: FR | D24: Perú | E24: Glencore | F24: Antapaccay | G24: Presentación DRX | J24: 45527 | L24: 2 | M24: 0
A25: ING | B25: AZ | C25: PA | D25: Perú | E25: Minera Chinalco Perú S.A | F25: Chinalco | G25: Estimación de Reservas Minerales y Plan de Vida de Mina | H25: 1 | J25: 45529 | K25: 198283 | L25: 3 | M25: 0 | N25: 0
A26: ING | B26: FR | C26: PA | D26: Chile | E26: Lundin | F26: Candeleria | G26: Estrategia de estabilización y crecimiento UG | H26: 1 | I26: Enviar propuesta tecnica a cliente (Octavio Cardenas) | J26: 45534 | L26: 9 | M26: 0 | N26: 0
A27: ING | B27: PA | C27: PA | D27: Chile | F27: Escondida | G27: Enviar contrato | J27: 45538
A28: ING | B28: PV | C28: FR | D28: USA | E28: Twin metals | F28: Birch Lake | G28: Pre-PFS: revisión al caso minero de Birch Lake + Maturi | H28: 1 | I28: Actualizar valorización | J28: 45532 | L28: 5 | M28: 5 | N28: 0
D29: Perú | F29: Yauricocha | G29: Auditoria de ventilación | I29: Leer BT y tener reunión el luns para definir partes y piezas | J29: 45539
D30: Perú | F30: Mina de Sal | G30: Pre-Calificación estudio de ingenieria | I30: Verificar con Lama si es necesario postular | J30: 45539
A31: ING | B31: AZ | C31: FR | D31: Perú | E31: Trafigura | G31: Armar presentación | J31: 45532 | L31: 0 | M31: 12 | N31: 0
A32: ING | B32: PA | C32: PA | D32: Chile | G32: Capacitación y implementación de Simprep | I32: Preparar propuesta en base a propusta de Candelaria | J32: 45540 | L32: 5 | M32: 5 | N32: 0
A33: ING | B33: FR | C33: PA | D33: Chile | E33: AMSA | G33: Licitación | H33: 2 | I33: Prepración de taller estrategico + Propuesta | J33: 45541 | L33: 0 | M33: 5 | N33: 0
A34: ING | B34: AZ | D34: Perú | E34: Ferrobamba | F34: Ferrobamba | G34: PFS Ferromamba UG | H34: 1 | I34: Envio interna propuesta formal (lunes) y reunión de cierre el miercoles | J34: 45544 | L34: 0 | M34: 0 | N34: 12
A35: ING | B35: FR | C35: PA | D35: Chile | E35: Lundin | F35: Candeleria | G35: Diagnóstico brechas que impactan riesgos geotécnicos | H35: 1 | I35: Actualizar ppt | J35: 45529 | L35: 1 | M35: 12 | N35: 30
A36: ING | B36: AS | C36: PA | D36: Brasil | E36: Mosaic | F36: Cajati | G36: Proyecto integral Cajati | H36: 1 | I36: A la espera de aprovación del cliente | J36: TBD | L36: 12 | M36: 30 | N36: 0
A37: ING | B37: AS | C37: PA | D37: Brasil | E37: Mosaic | F37: CTV; Fase 2 | G37: Proyecto integral CTV2 | H37: 1 | I37: A la espera de aprovación del cliente | J37: TBD | L37: 2 | M37: 0 | N37: 0
A38: ING | B38: AZ | C38: PA | D38: Perú | E38: Cobriza | F38: Cobriza | G38: Ing FS Cobriza | H38: 2 | I38: Alinear con AZ como mantenernos en proceso | J38: TBD | L38: 0 | M38: 5 | N38: 0
A39: ING | B39: AZ | C39: PA | D39: Perú | E39: Minsur | F39: San Rafael | G39: Ing factibilidad recursos potenciales SR | H39: 2 | I39: Alinear con AZ como mantenernos en proceso | J39: TBD | L39: 0 | M39: 0 | N39: 5
A40: ING | B40: AS | C40: PA | D40: Brasil | E40: Lhg Mining | F40: Urucum | G40: Due Diligence fase 2 | H40: 1 | I40: Coordinación con Antonio para ver material a enviar | J40: TBD
A41: ING | B41: AZ | C41: FR | D41: Perú | E41: Los Calatos | F41: Los Calatos | G41: Fase 2 Los Calatos (estudio PFS) | H41: 1 | I41: Entendimiento con Alex de situación del estudio y coordinación de taller interno | J41: TBD
A42: ING | B42: FR | C42: PA | D42: Chile | E42: Anglo A | F42: Los Bronces | G42: Optimización de capacidad de relaves | H42: 3 | I42: Presentación | J42: TBD
A43: ING | B43: FR | C43: PA | D43: USA | G43: responder a pato por propuesta rajo | H43: 3 | I43: Construir material | J43: TBD
A44: ING | B44: PV | D44: Chile | E44: Codelco | G44: Actualización normativa de reportabilidad de recursos y reservas | H44: 1 | I44: Reunión jueves para definir alcances | J44: 45540
A45: ING | B45: CH | C45: PA | D45: Chile | E45: Lundin Gold | F45: Frutos del norte | G45: SOW Auditoria geotecnica | I45: Coordinar con Claudio para conseguir contacto dentro de la empesa
A46: ING | B46: OD | D46: Rusia | E46: x | F46: x | G46: x | I46: A la espera de entendimiento de propuesta por parte de Ricardo Miranda

Sheet POM_Septiembre
J1: =+SUM(F2:J2) -> 55 | O1: =+SUM(K2:O2) -> 30.5 | T1: =+SUM(P2:T2) -> 4 | Y1: =+SUM(U2:Y2) -> 5
F2: =+F14+F27+F34+F40+F49+F58+F63+F69+F5+F45+F20 -> 8 | G2: =+G14+G27+G34+G40+G49+G58+G63+G69+G5+G45+G20 -> 18 | H2: =+H14+H27+H34+H40+H49+H58+H63+H69+H5+H45+H20 -> 11 | I2: =+I14+I27+I34+I40+I49+I58+I63+I69+I5+I45+I20 -> 15 | J2: =+J14+J27+J34+J40+J49+J58+J63+J69+J5+J45+J20 -> 3 | K2: =+K14+K27+K34+K40+K49+K58+K63+K69+K5+K45+K20 -> 4.5 | L2: =+L14+L27+L34+L40+L49+L58+L63+L69+L5+L45+L20 -> 11 | M2: =+M14+M27+M34+M40+M49+M58+M63+M69+M5+M45+M20 -> 5 | ... Y2: =+Y14+Y27+Y34+Y40+Y49+Y58+Y63+Y69+Y5+Y45+Y20 -> 0
F3: Semana 02/09 | K3: Semana 09/09 | P3: Semana 16/09 | U3: Semana 23/09
A4: ID | B4: País | C4: Tema | D4: Objetivo | E4: Requerimiento | F4: Lunes | G4: Martes | H4: Miércoles | I4: Jueves | J4: Viernes | K4: Lunes | L4: Martes | M4: Miércoles | N4: Jueves | O4: Viernes | P4: Lunes | Q4: Martes | R4: Miércoles | S4: Jueves | T4: Viernes | U4: Lunes | V4: Martes | W4: Miércoles | X4: Jueves | Y4: Viernes
A5: 0 | B5: Chile | C5: Reuniones | D5: Reuniones administrativas | F5: =+SUM(F6:F13) -> 2 | G5: =+SUM(G6:G13) -> 0 | H5: =+SUM(H6:H13) -> 2 | I5: =+SUM(I6:I13) -> 2 | J5: =+SUM(J6:J13) -> 0 | K5: =+SUM(K6:K13) -> 2 | L5: =+SUM(L6:L13) -> 4 | M5: =+SUM(M6:M13) -> 2 | ... Y5: =+SUM(Y6:Y13) -> 0
C6: A1 | D6: Reunión ejectuviva (12:00) | F6: 1 | K6: 1 | P6: 1 | U6: 1
C7: A2 | D7: Reunión ejecutiva (13:00) | F7: 1 | K7: 1 | P7: 1 | U7: 1
C8: A3 | D8: Reunión comercial (9:30) | H8: 1 | M8: 1 | R8: 1 | W8: 1
C9: A4 | D9: Reunión de gestión de cobranza (12:30) | H9: 1 | M9: 1 | R9: 1 | W9: 1
C10: A5
C11: A6
C12: A7 | D12: Preparación reunión de gestión | I12: 2 | L12: 4
C13: A8 | D13: Reunión de gestión
A14: 1 | B14: Perú | C14: Las Bambas | D14: PFS Ferromamba UG | F14: =+SUM(F15:F19) -> 1 | G14: =+SUM(G15:G19) -> 2 | H14: =+SUM(H15:H19) -> 1 | I14: =+SUM(I15:I19) -> 2 | J14: =+SUM(J15:J19) -> 0 | K14: =+SUM(K15:K19) -> 0 | L14: =+SUM(L15:L19) -> 0 | M14: =+SUM(M15:M19) -> 0 | ... Y14: =+SUM(Y15:Y19) -> 0
C15: A1 | D15: Revisión y ajuste | F15: 1 | G15: 2
C16: A2 | D16: Reunión de cierre | H16: 1
C17: A3 | D17: Ajustes post taller | I17: 2
C18: A4
C19: A5
A20: 2 | B20: Chile | C20: AMSA | D20: Servicio Trade -Off Tecnológico Nueva Generación de Distrito | F20: =+SUM(F21:F26) -> 3 | G20: =+SUM(G21:G26) -> 5 | H20: =+SUM(H21:H26) -> 0 | I20: =+SUM(I21:I26) -> 0 | J20: =+SUM(J21:J26) -> 0 | K20: =+SUM(K21:K26) -> 0 | L20: =+SUM(L21:L26) -> 0 | M20: =+SUM(M21:M26) -> 0 | ... Y20: =+SUM(Y21:Y26) -> 0
C21: A1 | D21: Preparación de taller de entendimiento | F21: 2
C22: A2 | D22: Taller estrategico de propuesta | F22: 1
C23: A3 | G23: 5
C24: A4
C25: A5
C26: A6
A27: 3 | B27: Perú | C27: Sierra Metals | D27: Auditoria de ventilación - Yauricocha | F27: =+SUM(F28:F33) -> 1 | G27: =+SUM(G28:G33) -> 4 | H27: =+SUM(H28:H33) -> 0 | I27: =+SUM(I28:I33) -> 0 | J27: =+SUM(J28:J33) -> 0 | K27: =+SUM(K28:K33) -> 0 | L27: =+SUM(L28:L33) -> 0 | M27: =+SUM(M28:M33) -> 0 | ... Y27: =+SUM(Y28:Y33) -> 0
C28: A1 | D28: Taller de coordinación | F28: 1
C29: A2 | D29: Construcción de propuesta | G29: 4
C30: A3
C31: A4
C32: A5
C33: A6
A34: 4 | B34: Chile | C34: MassMin | D34: Coordinación participación MassMin | F34: =+SUM(F35:F39) -> 0 | G34: =+SUM(G35:G39) -> 1 | H34: =+SUM(H35:H39) -> 0 | I34: =+SUM(I35:I39) -> 3 | J34: =+SUM(J35:J39) -> 3 | K34: =+SUM(K35:K39) -> 0 | L34: =+SUM(L35:L39) -> 0 | M34: =+SUM(M35:M39) -> 0 | ... Y34: =+SUM(Y35:Y39) -> 0
C35: A1 | D35: Revisión de presentación y actualización | I35: 0 | J35: 3
C36: A2 | D36: Coordinación viaje CH | G36: 1
C37: A3 | D37: Preparar material brochures | I37: 3
C38: A4
C39: A5
A40: 5 | B40: Perú | C40: Miski Mayo | D40: Mina de Sal - Pre-Calificación estudio de ingenieria | F40: =+SUM(F41:F44) -> 0 | G40: =+SUM(G41:G44) -> 3 | H40: =+SUM(H41:H44) -> 0 | I40: =+SUM(I41:I44) -> 0 | J40: =+SUM(J41:J44) -> 0 | K40: =+SUM(K41:K44) -> 0 | L40: =+SUM(L41:L44) -> 0 | M40: =+SUM(M41:M44) -> 0 | ... Y40: =+SUM(Y41:Y44) -> 0
C41: A1 | D41: Validar si REDCO tiene que enviar información
C42: A2 | D42: Preparación de material | G42: 3
C43: A3
C44: A4
A45: 6 | B45: Brasil | C45: Mosaic | D45: Proyecto integral Cajati | F45: =+SUM(F46:F48) -> 0 | G45: =+SUM(G46:G48) -> 0 | H45: =+SUM(H46:H48) -> 0 | I45: =+SUM(I46:I48) -> 0 | J45: =+SUM(J46:J48) -> 0 | K45: =+SUM(K46:K48) -> 0 | L45: =+SUM(L46:L48) -> 0 | M45: =+SUM(M46:M48) -> 0 | ... Y45: =+SUM(Y46:Y48) -> 0
C46: A1 | D46: A la espera de mas detalles
C47: A2
C48: A3
A49: 7 | B49: Brasil | C49: Mosaic | D49: Proyecto integral CTV Fase 2 | F49: =+SUM(F50:F52) -> 0 | G49: =+SUM(G50:G52) -> 0 | H49: =+SUM(H50:H52) -> 0 | I49: =+SUM(I50:I52) -> 0 | J49: =+SUM(J50:J52) -> 0 | K49: =+SUM(K50:K52) -> 0 | L49: =+SUM(L50:L52) -> 0 | M49: =+SUM(M50:M52) -> 0 | ... Y49: =+SUM(Y50:Y52) -> 0
C50: A1 | D50: A la espera de mas detalles
C51: A2
C52: A3
A53: 8 | B53: Brasil | C53: Vale | D53: Congo Soco | F53: =+SUM(F54:F57) -> 0 | G53: =+SUM(G54:G57) -> 0 | H53: =+SUM(H54:H57) -> 0 | I53: =+SUM(I54:I57) -> 0 | J53: =+SUM(J54:J57) -> 0 | K53: =+SUM(K54:K57) -> 0 | L53: =+SUM(L54:L57) -> 0 | M53: =+SUM(M54:M57) -> 0 | ... Y53: =+SUM(Y54:Y57) -> 0
C54: A1 | D54: A la espera de alcances
C55: A2
C56: A3
C57: A4
A58: 9 | B58: Perú | C58: Calatos | D58: Los Calatos PFS 2 | F58: =+SUM(F59:F62) -> 0 | G58: =+SUM(G59:G62) -> 2 | H58: =+SUM(H59:H62) -> 0 | I58: =+SUM(I59:I62) -> 0 | J58: =+SUM(J59:J62) -> 0 | K58: =+SUM(K59:K62) -> 2.5 | L58: =+SUM(L59:L62) -> 7 | M58: =+SUM(M59:M62) -> 3 | ... Y58: =+SUM(Y59:Y62) -> 0
C59: A1 | D59: Reunión con Alex para prosimos pasos | G59: 1
C60: A2 | D60: Construir SDC 4 | G60: 1
C61: A3 | D61: Construir PFS 2 | K61: 2.5 | L61: 7 | M61: 3 | N61: 8 | O61: 2
C62: A4
A63: 10 | B63: Chile | D63: REDTEC | F63: =+SUM(F64:F68) -> 1 | G63: =+SUM(G64:G68) -> 0 | H63: =+SUM(H64:H68) -> 2 | I63: =+SUM(I64:I68) -> 4 | J63: =+SUM(J64:J68) -> 0 | K63: =+SUM(K64:K68) -> 0 | L63: =+SUM(L64:L68) -> 0 | M63: =+SUM(M64:M68) -> 0 | ... Y63: =+SUM(Y64:Y68) -> 0
C64: A1 | D64: Actualizar PPT REDTEC | I64: 3
C65: A2 | D65: Reunión de coordinación para preparar ppt | F65: 1
C66: A3 | D66: Construcción PPT | H66: 2
D67: Reunión de avance con ER | I67: 1
C68: A4 | W68: 1
A69: 11 | B69: Chile | D69: Otros temas comerciales | F69: =+SUM(F70:F81) -> 0 | G69: =+SUM(G70:G81) -> 1 | H69: =+SUM(H70:H81) -> 6 | I69: =+SUM(I70:I81) -> 4 | J69: =+SUM(J70:J81) -> 0 | K69: =+SUM(K70:K81) -> 0 | L69: =+SUM(L70:L81) -> 0 | M69: =+SUM(M70:M81) -> 0 | ... Y69: =+SUM(Y70:Y81) -> 0
C70: A1 | D70: Tabla de precios productos REDCO | I70: 3
C71: A2 | D71: Volcan: Armar presentación con temas solicitados por el cliente, coordinar reunión | I71: 1
C72: A3 | D72: BHP - Modelo predictivo
C73: A4 | D73: Ing FS Cobriza: Alinear con AZ como mantenernos en proceso | G73: 0.5
C74: A5 | D74: Ing factibilidad recursos potenciales SR: Alinear con AZ como mantenernos en proceso | G74: 0.5
C75: A6 | D75: Anglo: Armar PPT Optimización de capacidad de relaves | H75: 3
C76: A7 | D76: Presentación de capacidads rajo Fe | H76: 3
C77: A8
C78: A9
C79: A10
C80: A11
C81: A12
B82: Rusia | C82: FS Rajo
B83: Chile | C83: DMH | D83: Estudio conceptual transicion OP/UG
D84: armar lamina de budget
C85: Capstone | D85: Ingenieria Conceptual Extensión Proyecto Sierra Norte | F85: 250
C86: AMSA | D86: Trade Off tecnologicos distrito Centinela | F86: 1200

Sheet Hoja3
F7: Lunes | G7: Martes | H7: Miércoles | I7: Jueves | J7: Viernes
F8: =+SUM(F9:F24) -> 2.5 | G8: =+SUM(G9:G24) -> 7 | H8: =+SUM(H9:H24) -> 3 | I8: =+SUM(I9:I24) -> 8 | J8: =+SUM(J9:J24) -> 2
E9: Reunión aclaratoria (CM, CP a GN,DN) | F9: 1
E10: Evaluación de propuesta | F10: 0.5
E11: Diseño y Dimensionamiento de Propuesta PPT (Excel, HH, gantt, equipo, tareas) | G11: 5
E12: Validación con CM y equipo de Ing | H12: 1
E13: Preparación propuesta formal (Word) | I13: 8
E14: Validación con CM y equipo de Ing | J14: 0.5
E15: Acualización de propuesta | J15: 1
E16: Envio de propuesta y creacón de Ficha | J16: 0.5
E18: Preparación de lamina de entendimiento, alcances y temas principales | F18: 1
E19: Construcción de excel (HH, gantt, equipo, tareas) y PPT propuesta | H19: 1
E20: Validación con CM y equipo de Ing | H20: 1
E21: Construcción documento (word)
E22: Validación con CM y equipo de Ing
E23: Envio de propuesta | G23: 2

Sheet 2023
A1: Código Total | B1: Proyecto Contrato Original | C1: Pais | D1: Proyecto | E1: Cliente | F1: Estado | G1: Probabilidad | H1: Monto Total (US$) | I1: Inicio real | J1: Inicio de ingreso | K1: Fin real | L1: Meses Reales | M1: monto mes | N1: Monto 2024 | P1: Monto 2023 | Q1: 45292 | R1: 45323 | S1: 45352 | T1: 45383 | U1: 45413 | V1: 45444 | W1: 45474 | X1: 45505 | Y1: 45536 | Z1: 45566 | AA1: 45597 | AB1: 45627
A2: PE-MMG-OU-FEL00-022-A | B2: LasBambas_Ferrobamba_OP_UG | C2: Perú | D2: Transición OP/UG de Ferrobamba | E2: MMG Las Bambas | F2: En Ejecución | G2: 1 | H2: 160000 | I2: 45229 | J2: =+I2+2 -> 45231 | K2: 45439 | L2: 7 | M2: =+H2/L2 -> 22857.143 | N2: =+H2-P2 -> 160000 | O2: =+H2-(P2+SUM(Q2:W2)) -> 0 | P2: 0 | Q2: =+_xlfn.XLOOKUP($A2,Hoja1!$A:$A,Hoja1!Z:Z) -> 0 | R2: =+_xlfn.XLOOKUP($A2,Hoja1!$A:$A,Hoja1!AA:AA) -> 72174 | S2: =+_xlfn.XLOOKUP($A2,Hoja1!$A:$A,Hoja1!AB:AB) -> 29275.333 | T2: =+_xlfn.XLOOKUP($A2,Hoja1!$A:$A,Hoja1!AC:AC) -> 29275.333 | U2: =+_xlfn.XLOOKUP($A2,Hoja1!$A:$A,Hoja1!AD:AD) -> 29275.333 | V2: =+_xlfn.XLOOKUP($A2,Hoja1!$A:$A,Hoja1!AE:AE) -> 0 | W2: =+_xlfn.XLOOKUP($A2,Hoja1!$A:$A,Hoja1!AF:AF) -> 0 | X2: =+_xlfn.XLOOKUP($A2,Hoja1!$A:$A,Hoja1!AG:AG) -> 0 | Y2: =+_xlfn.XLOOKUP($A2,Hoja1!$A:$A,Hoja1!AH:AH) -> 0 | Z2: =+_xlfn.XLOOKUP($A2,Hoja1!$A:$A,Hoja1!AI:AI) -> 0 | AA2: =+_xlfn.XLOOKUP($A2,Hoja1!$A:$A,Hoja1!AJ:AJ) -> 0 | AB2: =+_xlfn.XLOOKUP($A2,Hoja1!$A:$A,Hoja1!AK:AK) -> 0
A3: PE-CSC-UG-FEL2A-023-A | B3: PFS Los Calatos | C3: Perú | D3: PFS Los Calatos | E3: CD Capital | F3: En Ejecución | G3: 1 | H3: 917313 | I3: 45201 | J3: =+I3+2 -> 45203 | K3: 45488 | L3: 9.5666667 | M3: =+H3/L3 -> 95886.376 | N3: =+H3-P3 -> 825582 | O3: =+H3-(P3+SUM(Q3:W3)) -> 0 | P3: 91731 | Q3: =+_xlfn.XLOOKUP($A3,Hoja1!$A:$A,Hoja1!Z:Z) -> 100441 | R3: =+_xlfn.XLOOKUP($A3,Hoja1!$A:$A,Hoja1!AA:AA) -> 29776 | S3: =+_xlfn.XLOOKUP($A3,Hoja1!$A:$A,Hoja1!AB:AB) -> 70005 | T3: =+_xlfn.XLOOKUP($A3,Hoja1!$A:$A,Hoja1!AC:AC) -> 201211.33 | U3: =+_xlfn.XLOOKUP($A3,Hoja1!$A:$A,Hoja1!AD:AD) -> 201211.33 | V3: =+H3-(SUM(P3:U3)) -> 222937.33 | W3: =+_xlfn.XLOOKUP($A3,Hoja1!$A:$A,Hoja1!AF:AF) -> 0 | X3: =+_xlfn.XLOOKUP($A3,Hoja1!$A:$A,Hoja1!AG:AG) -> 0 | Y3: =+_xlfn.XLOOKUP($A3,Hoja1!$A:$A,Hoja1!AH:AH) -> 0 | Z3: =+_xlfn.XLOOKUP($A3,Hoja1!$A:$A,Hoja1!AI:AI) -> 0 | AA3: =+_xlfn.XLOOKUP($A3,Hoja1!$A:$A,Hoja1!AJ:AJ) -> 0 | AB3: =+_xlfn.XLOOKUP($A3,Hoja1!$A:$A,Hoja1!AK:AK) -> 0
A4: BR-MOS-OU-FEL03-026-A | B4: Mosaic_Cajati | C4: Brasil | D4: Cajati | E4: Mosaic | F4: En Ejecución | G4: 1 | H4: 555021 | I4: 44984 | J4: =+I4+2 -> 44986 | K4: 45383 | L4: 13.3 | M4: =+H4/L4 -> 41730.902 | N4: =+H4-P4 -> 362437 | O4: =+H4-(P4+SUM(Q4:W4)) -> 0 | P4: 192584 | Q4: =+_xlfn.XLOOKUP($A4,Hoja1!$A:$A,Hoja1!Z:Z) -> 155916 | R4: =+_xlfn.XLOOKUP($A4,Hoja1!$A:$A,Hoja1!AA:AA) -> 11081 | S4: =+_xlfn.XLOOKUP($A4,Hoja1!$A:$A,Hoja1!AB:AB) -> 65146.667 | T4: =+_xlfn.XLOOKUP($A4,Hoja1!$A:$A,Hoja1!AC:AC) -> 65146.667 | U4: =+_xlfn.XLOOKUP($A4,Hoja1!$A:$A,Hoja1!AD:AD) -> 65146.667 | V4: =+_xlfn.XLOOKUP($A4,Hoja1!$A:$A,Hoja1!AE:AE) -> 0 | W4: =+_xlfn.XLOOKUP($A4,Hoja1!$A:$A,Hoja1!AF:AF) -> 0 | X4: =+_xlfn.XLOOKUP($A4,Hoja1!$A:$A,Hoja1!AG:AG) -> 0 | Y4: =+_xlfn.XLOOKUP($A4,Hoja1!$A:$A,Hoja1!AH:AH) -> 0 | Z4: =+_xlfn.XLOOKUP($A4,Hoja1!$A:$A,Hoja1!AI:AI) -> 0 | AA4: =+_xlfn.XLOOKUP($A4,Hoja1!$A:$A,Hoja1!AJ:AJ) -> 0 | AB4: =+_xlfn.XLOOKUP($A4,Hoja1!$A:$A,Hoja1!AK:AK) -> 0
A5: BR-NEX-UG-FEL2A-027-A | B5: NEXA_FEL2 Aripuana | C5: Brasil | D5: FEL2 Aripuana | E5: Nexa | F5: En Ejecución | G5: 1 | H5: 203609 | I5: 45159 | J5: =+I5+2 -> 45161 | K5: 45292 | L5: 4.4333333 | M5: =+H5/L5 -> 45926.842 | N5: =+H5-P5 -> 192685 | O5: =+H5-(P5+SUM(Q5:W5)) -> 0 | P5: 10924 | Q5: =+_xlfn.XLOOKUP($A5,Hoja1!$A:$A,Hoja1!Z:Z) -> 15096 | R5: =+_xlfn.XLOOKUP($A5,Hoja1!$A:$A,Hoja1!AA:AA) -> 27426 | S5: =+_xlfn.XLOOKUP($A5,Hoja1!$A:$A,Hoja1!AB:AB) -> 75081.5 | T5: =+_xlfn.XLOOKUP($A5,Hoja1!$A:$A,Hoja1!AC:AC) -> 75081.5 | U5: =+_xlfn.XLOOKUP($A5,Hoja1!$A:$A,Hoja1!AD:AD) -> 0 | V5: =+_xlfn.XLOOKUP($A5,Hoja1!$A:$A,Hoja1!AE:AE) -> 0 | W5: =+_xlfn.XLOOKUP($A5,Hoja1!$A:$A,Hoja1!AF:AF) -> 0 | X5: =+_xlfn.XLOOKUP($A5,Hoja1!$A:$A,Hoja1!AG:AG) -> 0 | Y5: =+_xlfn.XLOOKUP($A5,Hoja1!$A:$A,Hoja1!AH:AH) -> 0 | Z5: =+_xlfn.XLOOKUP($A5,Hoja1!$A:$A,Hoja1!AI:AI) -> 0 | AA5: =+_xlfn.XLOOKUP($A5,Hoja1!$A:$A,Hoja1!AJ:AJ) -> 0 | AB5: =+_xlfn.XLOOKUP($A5,Hoja1!$A:$A,Hoja1!AK:AK) -> 0
A6: BR-MOS-UG-FEL01-028-A | B6: Mosaic_Taquari Vassouras | C6: Brasil | D6: Taquari Vassouras | E6: Mosaic | F6: En Ejecución | G6: 1 | H6: 284633 | I6: 45138 | J6: =+I6+2 -> 45140 | K6: 45312 | L6: 5.8 | M6: =+H6/L6 -> 49074.655 | N6: =+H6-P6 -> 284633 | O6: =+H6-(P6+SUM(Q6:W6)) -> 2846 | P6: 0 | Q6: =+_xlfn.XLOOKUP($A6,Hoja1!$A:$A,Hoja1!Z:Z) -> 68185 | R6: =+_xlfn.XLOOKUP($A6,Hoja1!$A:$A,Hoja1!AA:AA) -> 145213 | S6: =+_xlfn.XLOOKUP($A6,Hoja1!$A:$A,Hoja1!AB:AB) -> 68389 | T6: =+_xlfn.XLOOKUP($A6,Hoja1!$A:$A,Hoja1!AC:AC) -> 0 | U6: =+_xlfn.XLOOKUP($A6,Hoja1!$A:$A,Hoja1!AD:AD) -> 0 | V6: =+_xlfn.XLOOKUP($A6,Hoja1!$A:$A,Hoja1!AE:AE) -> 0 | W6: =+_xlfn.XLOOKUP($A6,Hoja1!$A:$A,Hoja1!AF:AF) -> 0 | X6: =+_xlfn.XLOOKUP($A6,Hoja1!$A:$A,Hoja1!AG:AG) -> 0 | Y6: =+_xlfn.XLOOKUP($A6,Hoja1!$A:$A,Hoja1!AH:AH) -> 0 | Z6: =+_xlfn.XLOOKUP($A6,Hoja1!$A:$A,Hoja1!AI:AI) -> 0 | AA6: =+_xlfn.XLOOKUP($A6,Hoja1!$A:$A,Hoja1!AJ:AJ) -> 0 | AB6: =+_xlfn.XLOOKUP($A6,Hoja1!$A:$A,Hoja1!AK:AK) -> 0
A7: CH-AMS-CS-OTR00-029-A | B7: AMSA_Planificacion | C7: Chile | D7: Apoyo planificación minas AMSA | E7: AMSA | F7: En Ejecución | G7: 1 | H7: 427230 | I7: 45228 | J7: =+I7+2 -> 45230 | K7: 45292 | L7: 2.1333333 | M7: =+H7/L7 -> 200264.06 | N7: =+H7-P7 -> 231483 | O7: =+H7-(P7+SUM(Q7:W7)) -> 0 | P7: 195747 | Q7: =+_xlfn.XLOOKUP($A7,Hoja1!$A:$A,Hoja1!Z:Z) -> 231483 | R7: =+_xlfn.XLOOKUP($A7,Hoja1!$A:$A,Hoja1!AA:AA) -> 0 | S7: =+_xlfn.XLOOKUP($A7,Hoja1!$A:$A,Hoja1!AB:AB) -> 0 | T7: =+_xlfn.XLOOKUP($A7,Hoja1!$A:$A,Hoja1!AC:AC) -> 0 | U7: =+_xlfn.XLOOKUP($A7,Hoja1!$A:$A,Hoja1!AD:AD) -> 0 | V7: =+_xlfn.XLOOKUP($A7,Hoja1!$A:$A,Hoja1!AE:AE) -> 0 | W7: =+_xlfn.XLOOKUP($A7,Hoja1!$A:$A,Hoja1!AF:AF) -> 0 | X7: =+_xlfn.XLOOKUP($A7,Hoja1!$A:$A,Hoja1!AG:AG) -> 0 | Y7: =+_xlfn.XLOOKUP($A7,Hoja1!$A:$A,Hoja1!AH:AH) -> 0 | Z7: =+_xlfn.XLOOKUP($A7,Hoja1!$A:$A,Hoja1!AI:AI) -> 0 | AA7: =+_xlfn.XLOOKUP($A7,Hoja1!$A:$A,Hoja1!AJ:AJ) -> 0 | AB7: =+_xlfn.XLOOKUP($A7,Hoja1!$A:$A,Hoja1!AK:AK) -> 0
A8: CH-COD-OT-OTR00-030-A | B8: Codelco_Capacitacion Deswik DET | C8: Chile | D8: Capacitación Deswik | E8: Codelco | F8: En Ejecución | G8: 1 | H8: 75000 | I8: 45215 | J8: =+I8+2 -> 45217 | K8: 45341 | L8: 4.2 | M8: =+H8/L8 -> 17857.143 | N8: =+H8-P8 -> 75000 | O8: =+H8-(P8+SUM(Q8:W8)) -> 0 | P8: 0 | Q8: =+_xlfn.XLOOKUP($A8,Hoja1!$A:$A,Hoja1!Z:Z) -> 0 | R8: =+_xlfn.XLOOKUP($A8,Hoja1!$A:$A,Hoja1!AA:AA) -> 29752 | S8: =+_xlfn.XLOOKUP($A8,Hoja1!$A:$A,Hoja1!AB:AB) -> 45248 | T8: =+_xlfn.XLOOKUP($A8,Hoja1!$A:$A,Hoja1!AC:AC) -> 0 | U8: =+_xlfn.XLOOKUP($A8,Hoja1!$A:$A,Hoja1!AD:AD) -> 0 | V8: =+_xlfn.XLOOKUP($A8,Hoja1!$A:$A,Hoja1!AE:AE) -> 0 | W8: =+_xlfn.XLOOKUP($A8,Hoja1!$A:$A,Hoja1!AF:AF) -> 0 | X8: =+_xlfn.XLOOKUP($A8,Hoja1!$A:$A,Hoja1!AG:AG) -> 0 | Y8: =+_xlfn.XLOOKUP($A8,Hoja1!$A:$A,Hoja1!AH:AH) -> 0 | Z8: =+_xlfn.XLOOKUP($A8,Hoja1!$A:$A,Hoja1!AI:AI) -> 0 | AA8: =+_xlfn.XLOOKUP($A8,Hoja1!$A:$A,Hoja1!AJ:AJ) -> 0 | AB8: =+_xlfn.XLOOKUP($A8,Hoja1!$A:$A,Hoja1!AK:AK) -> 0
A9: CH-CSH-OP-FEL00-034-A | B9: CSH_LOM Mina Guarello | C9: Chile | D9: Mina Guarello | E9: CSH | F9: En Ejecución | G9: 1 | H9: 114390 | I9: 45264 | J9: =+I9+2 -> 45266 | K9: 45362 | L9: 3.2666667 | M9: =+H9/L9 -> 35017.347 | N9: =+H9-P9 -> 114390 | O9: =+H9-(P9+SUM(Q9:W9)) -> 0 | P9: 0 | Q9: =+_xlfn.XLOOKUP($A9,Hoja1!$A:$A,Hoja1!Z:Z) -> 0 | R9: =+_xlfn.XLOOKUP($A9,Hoja1!$A:$A,Hoja1!AA:AA) -> 19065 | S9: =+_xlfn.XLOOKUP($A9,Hoja1!$A:$A,Hoja1!AB:AB) -> 19065 | T9: =+_xlfn.XLOOKUP($A9,Hoja1!$A:$A,Hoja1!AC:AC) -> 19065 | U9: =+_xlfn.XLOOKUP($A9,Hoja1!$A:$A,Hoja1!AD:AD) -> 19065 | V9: =+_xlfn.XLOOKUP($A9,Hoja1!$A:$A,Hoja1!AE:AE) -> 19065 | W9: =+_xlfn.XLOOKUP($A9,Hoja1!$A:$A,Hoja1!AF:AF) -> 19065 | X9: =+_xlfn.XLOOKUP($A9,Hoja1!$A:$A,Hoja1!AG:AG) -> 0 | Y9: =+_xlfn.XLOOKUP($A9,Hoja1!$A:$A,Hoja1!AH:AH) -> 0 | Z9: =+_xlfn.XLOOKUP($A9,Hoja1!$A:$A,Hoja1!AI:AI) -> 0 | AA9: =+_xlfn.XLOOKUP($A9,Hoja1!$A:$A,Hoja1!AJ:AJ) -> 0 | AB9: =+_xlfn.XLOOKUP($A9,Hoja1!$A:$A,Hoja1!AK:AK) -> 0
A10: PE-COR-UG-FEL2A-035-A | B10: MEIA Coripuno | C10: Perú | D10: Coripuno MEIA | E10: Coripuno | F10: En Ejecución | G10: 1 | H10: 47960 | I10: 45201 | J10: =+I10+2 -> 45203 | K10: 45313 | L10: 3.7333333 | M10: =+H10/L10 -> 12846.429 | N10: =+H10-P10 -> 47960 | O10: =+H10-(P10+SUM(Q10:W10)) -> 47960 | P10: 0 | Q10: =+_xlfn.XLOOKUP($A10,Hoja1!$A:$A,Hoja1!Z:Z) -> 0 | R10: =+_xlfn.XLOOKUP($A10,Hoja1!$A:$A,Hoja1!AA:AA) -> 0 | S10: =+_xlfn.XLOOKUP($A10,Hoja1!$A:$A,Hoja1!AB:AB) -> 0 | T10: =+_xlfn.XLOOKUP($A10,Hoja1!$A:$A,Hoja1!AC:AC) -> 0 | U10: =+_xlfn.XLOOKUP($A10,Hoja1!$A:$A,Hoja1!AD:AD) -> 0 | V10: =+_xlfn.XLOOKUP($A10,Hoja1!$A:$A,Hoja1!AE:AE) -> 0 | W10: =+_xlfn.XLOOKUP($A10,Hoja1!$A:$A,Hoja1!AF:AF) -> 0 | X10: =+_xlfn.XLOOKUP($A10,Hoja1!$A:$A,Hoja1!AG:AG) -> 0 | Y10: =+_xlfn.XLOOKUP($A10,Hoja1!$A:$A,Hoja1!AH:AH) -> 0 | Z10: =+_xlfn.XLOOKUP($A10,Hoja1!$A:$A,Hoja1!AI:AI) -> 0 | AA10: =+_xlfn.XLOOKUP($A10,Hoja1!$A:$A,Hoja1!AJ:AJ) -> 0 | AB10: =+_xlfn.XLOOKUP($A10,Hoja1!$A:$A,Hoja1!AK:AK) -> 0
A11: CH-COD-UG-FEL00-037-A | B11: Codelco_Cluster Toki | C11: Chile | D11: Proyecto Cluster Toqui Subterraneo | E11: Codelco | F11: En Ejecución | G11: 1 | H11: 82787 | I11: 45236 | J11: =+I11+2 -> 45238 | K11: 45320 | L11: 2.8 | M11: =+H11/L11 -> 29566.786 | N11: =+H11-P11 -> 82787 | O11: =+H11-(P11+SUM(Q11:W11)) -> -1262.4737 | P11: 0 | Q11: =+_xlfn.XLOOKUP($A11,Hoja1!$A:$A,Hoja1!Z:Z) -> 0 | R11: =+_xlfn.XLOOKUP($A11,Hoja1!$A:$A,Hoja1!AA:AA) -> 41755 | S11: =+_xlfn.XLOOKUP($A11,Hoja1!$A:$A,Hoja1!AB:AB) -> 38092 | T11: =+_xlfn.XLOOKUP($A11,Hoja1!$A:$A,Hoja1!AC:AC) -> 4202.4737 | U11: =+_xlfn.XLOOKUP($A11,Hoja1!$A:$A,Hoja1!AD:AD) -> 0 | V11: =+_xlfn.XLOOKUP($A11,Hoja1!$A:$A,Hoja1!AE:AE) -> 0 | W11: =+_xlfn.XLOOKUP($A11,Hoja1!$A:$A,Hoja1!AF:AF) -> 0 | X11: =+_xlfn.XLOOKUP($A11,Hoja1!$A:$A,Hoja1!AG:AG) -> 0 | Y11: =+_xlfn.XLOOKUP($A11,Hoja1!$A:$A,Hoja1!AH:AH) -> 0 | Z11: =+_xlfn.XLOOKUP($A11,Hoja1!$A:$A,Hoja1!AI:AI) -> 0 | AA11: =+_xlfn.XLOOKUP($A11,Hoja1!$A:$A,Hoja1!AJ:AJ) -> 0 | AB11: =+_xlfn.XLOOKUP($A11,Hoja1!$A:$A,Hoja1!AK:AK) -> 0
A12: CH-CMP-CS-FEL00-038-A | B12: CMP_Los Colorados Adelantamiento Planta | C12: Chile | D12: Impacto adelantamiento nueva planta MLC | E12: CMP | F12: En Ejecución | G12: 1 | H12: 250000 | I12: 45271 | J12: =+I12+2 -> 45273 | K12: 45327 | L12: 1.8666667 | M12: =+H12/L12 -> 133928.57 | N12: =+H12-P12 -> 250000 | O12: =+H12-(P12+SUM(Q12:W12)) -> 0 | P12: 0 | Q12: =+_xlfn.XLOOKUP($A12,Hoja1!$A:$A,Hoja1!Z:Z) -> 31977.95 | R12: =+_xlfn.XLOOKUP($A12,Hoja1!$A:$A,Hoja1!AA:AA) -> 16146 | S12: =+_xlfn.XLOOKUP($A12,Hoja1!$A:$A,Hoja1!AB:AB) -> 67292.017 | T12: =+_xlfn.XLOOKUP($A12,Hoja1!$A:$A,Hoja1!AC:AC) -> 67292.017 | U12: =+_xlfn.XLOOKUP($A12,Hoja1!$A:$A,Hoja1!AD:AD) -> 67292.017 | V12: =+_xlfn.XLOOKUP($A12,Hoja1!$A:$A,Hoja1!AE:AE) -> 0 | W12: =+_xlfn.XLOOKUP($A12,Hoja1!$A:$A,Hoja1!AF:AF) -> 0 | X12: =+_xlfn.XLOOKUP($A12,Hoja1!$A:$A,Hoja1!AG:AG) -> 0 | Y12: =+_xlfn.XLOOKUP($A12,Hoja1!$A:$A,Hoja1!AH:AH) -> 0 | Z12: =+_xlfn.XLOOKUP($A12,Hoja1!$A:$A,Hoja1!AI:AI) -> 0 | AA12: =+_xlfn.XLOOKUP($A12,Hoja1!$A:$A,Hoja1!AJ:AJ) -> 0 | AB12: =+_xlfn.XLOOKUP($A12,Hoja1!$A:$A,Hoja1!AK:AK) -> 0
A13: CH-COD-UG-FEL01-039-A | B13: Codelco_Drenaje QT | C13: Chile | D13: Drenaje QT Recursos Norte | E13: Codelco | F13: En Ejecución | G13: 1 | H13: 147000 | I13: 45236 | J13: =+I13+2 -> 45238 | K13: 45362 | L13: 4.2 | M13: =+H13/L13 -> 35000 | N13: =+H13-P13 -> 147000 | O13: =+H13-(P13+SUM(Q13:W13)) -> 0 | P13: 0 | Q13: =+_xlfn.XLOOKUP($A13,Hoja1!$A:$A,Hoja1!Z:Z) -> 0 | R13: =+_xlfn.XLOOKUP($A13,Hoja1!$A:$A,Hoja1!AA:AA) -> 14688 | S13: =+_xlfn.XLOOKUP($A13,Hoja1!$A:$A,Hoja1!AB:AB) -> 29292 | T13: =+_xlfn.XLOOKUP($A13,Hoja1!$A:$A,Hoja1!AC:AC) -> 51510 | U13: =+_xlfn.XLOOKUP($A13,Hoja1!$A:$A,Hoja1!AD:AD) -> 51510 | V13: =+_xlfn.XLOOKUP($A13,Hoja1!$A:$A,Hoja1!AE:AE) -> 0 | W13: =+_xlfn.XLOOKUP($A13,Hoja1!$A:$A,Hoja1!AF:AF) -> 0 | X13: =+_xlfn.XLOOKUP($A13,Hoja1!$A:$A,Hoja1!AG:AG) -> 0 | Y13: =+_xlfn.XLOOKUP($A13,Hoja1!$A:$A,Hoja1!AH:AH) -> 0 | Z13: =+_xlfn.XLOOKUP($A13,Hoja1!$A:$A,Hoja1!AI:AI) -> 0 | AA13: =+_xlfn.XLOOKUP($A13,Hoja1!$A:$A,Hoja1!AJ:AJ) -> 0 | AB13: =+_xlfn.XLOOKUP($A13,Hoja1!$A:$A,Hoja1!AK:AK) -> 0
A14: CH-CMP-OU-FEL2A-041-A | B14: CMP_Romeral Estabilización + UG PFS | C14: Chile | D14: Plan Estabilizado, PFS UG, Sistema Gestión Corto plazo Romeral | E14: CMP | F14: En Ejecución | G14: 1 | H14: 370245 | I14: 45261 | J14: =+I14+2 -> 45263 | K14: 45444 | L14: 7 | M14: =+H14/L14 -> 52892.143 | N14: =+H14-P14 -> 370245 | O14: =+H14-(P14+SUM(Q14:W14)) -> 0 | P14: 0 | Q14: =+_xlfn.XLOOKUP($A14,Hoja1!$A:$A,Hoja1!Z:Z) -> 0 | R14: =+_xlfn.XLOOKUP($A14,Hoja1!$A:$A,Hoja1!AA:AA) -> 0 | S14: =+_xlfn.XLOOKUP($A14,Hoja1!$A:$A,Hoja1!AB:AB) -> 74049 | T14: =+_xlfn.XLOOKUP($A14,Hoja1!$A:$A,Hoja1!AC:AC) -> 74049 | U14: =+_xlfn.XLOOKUP($A14,Hoja1!$A:$A,Hoja1!AD:AD) -> 74049 | V14: =+_xlfn.XLOOKUP($A14,Hoja1!$A:$A,Hoja1!AE:AE) -> 74049 | W14: =+_xlfn.XLOOKUP($A14,Hoja1!$A:$A,Hoja1!AF:AF) -> 74049 | X14: =+_xlfn.XLOOKUP($A14,Hoja1!$A:$A,Hoja1!AG:AG) -> 0 | Y14: =+_xlfn.XLOOKUP($A14,Hoja1!$A:$A,Hoja1!AH:AH) -> 0 | Z14: =+_xlfn.XLOOKUP($A14,Hoja1!$A:$A,Hoja1!AI:AI) -> 0 | AA14: =+_xlfn.XLOOKUP($A14,Hoja1!$A:$A,Hoja1!AJ:AJ) -> 0 | AB14: =+_xlfn.XLOOKUP($A14,Hoja1!$A:$A,Hoja1!AK:AK) -> 0
A15: PE-MMA-OP-FEL00-047-A | B15: MiskiMayo_LOM | C15: Perú | D15: Evaluacion de operaciones y plan de minado LOM | E15: Miski Mayo | F15: En Ejecución | G15: 1 | H15: 115136 | I15: 45235 | J15: =+I15+2 -> 45237 | K15: 45354 | L15: 3.9666667 | M15: =+H15/L15 -> 29025.882 | N15: =+H15-P15 -> 91477 | O15: =+H15-(P15+SUM(Q15:W15)) -> 0 | P15: 23659 | Q15: =+_xlfn.XLOOKUP($A15,Hoja1!$A:$A,Hoja1!Z:Z) -> 0 | R15: =+_xlfn.XLOOKUP($A15,Hoja1!$A:$A,Hoja1!AA:AA) -> 26813 | S15: =+_xlfn.XLOOKUP($A15,Hoja1!$A:$A,Hoja1!AB:AB) -> 11222 | T15: =+_xlfn.XLOOKUP($A15,Hoja1!$A:$A,Hoja1!AC:AC) -> 53442 | U15: =+_xlfn.XLOOKUP($A15,Hoja1!$A:$A,Hoja1!AD:AD) -> 0 | V15: =+_xlfn.XLOOKUP($A15,Hoja1!$A:$A,Hoja1!AE:AE) -> 0 | W15: =+_xlfn.XLOOKUP($A15,Hoja1!$A:$A,Hoja1!AF:AF) -> 0 | X15: =+_xlfn.XLOOKUP($A15,Hoja1!$A:$A,Hoja1!AG:AG) -> 0 | Y15: =+_xlfn.XLOOKUP($A15,Hoja1!$A:$A,Hoja1!AH:AH) -> 0 | Z15: =+_xlfn.XLOOKUP($A15,Hoja1!$A:$A,Hoja1!AI:AI) -> 0 | AA15: =+_xlfn.XLOOKUP($A15,Hoja1!$A:$A,Hoja1!AJ:AJ) -> 0 | AB15: =+_xlfn.XLOOKUP($A15,Hoja1!$A:$A,Hoja1!AK:AK) -> 0
A16: PE-MSR-UG-FEL00-071-A | B16: Minsur_Update LOM San Rafael | C16: Perú | D16: Minsur_Update LOM San Rafael | E16: Minsur | F16: En Ejecución | G16: 1 | H16: 25600 | I16: 45273 | J16: =+I16+2 -> 45275 | K16: 45328 | L16: 1.8333333 | M16: =+H16/L16 -> 13963.636 | N16: =+H16-P16 -> 25600 | O16: =+H16-(P16+SUM(Q16:W16)) -> 0 | P16: 0 | Q16: =+_xlfn.XLOOKUP($A16,Hoja1!$A:$A,Hoja1!Z:Z) -> 0 | R16: =+_xlfn.XLOOKUP($A16,Hoja1!$A:$A,Hoja1!AA:AA) -> 0 | S16: =+_xlfn.XLOOKUP($A16,Hoja1!$A:$A,Hoja1!AB:AB) -> 25600 | T16: =+_xlfn.XLOOKUP($A16,Hoja1!$A:$A,Hoja1!AC:AC) -> 0 | U16: =+_xlfn.XLOOKUP($A16,Hoja1!$A:$A,Hoja1!AD:AD) -> 0 | V16: =+_xlfn.XLOOKUP($A16,Hoja1!$A:$A,Hoja1!AE:AE) -> 0 | W16: =+_xlfn.XLOOKUP($A16,Hoja1!$A:$A,Hoja1!AF:AF) -> 0 | X16: =+_xlfn.XLOOKUP($A16,Hoja1!$A:$A,Hoja1!AG:AG) -> 0 | Y16: =+_xlfn.XLOOKUP($A16,Hoja1!$A:$A,Hoja1!AH:AH) -> 0 | Z16: =+_xlfn.XLOOKUP($A16,Hoja1!$A:$A,Hoja1!AI:AI) -> 0 | AA16: =+_xlfn.XLOOKUP($A16,Hoja1!$A:$A,Hoja1!AJ:AJ) -> 0 | AB16: =+_xlfn.XLOOKUP($A16,Hoja1!$A:$A,Hoja1!AK:AK) -> 0
K19: 45291 | Q19: 26 | R19: 27
A222: ----277-!
A223: ----278-!
A224: ----279-!
A225: ----280-!
A226: ----281-!
A227: ----282-!
A228: ----283-!
A229: ----284-!
A230: ----285-!
A231: ----286-!
A232: ----287-!
A233: ----288-!
A234: ----289-!

Sheet Hoja1
A1: Código | B1: Proyecto Contrato Original | C1: Pais | D1: Proyecto | E1: Cliente | F1: Estado | G1: Solicitud de Cambio / Comentario | H1: Probabilidad | I1: Monto Total (US$) | J1: Monto 2023 (US$) | K1: Facturado a la fecha (US$) | L1: % Avance Financiero | M1: Diferencia USD a la Fecha | N1: 44927 | O1: 44958 | P1: 44986 | Q1: 45017 | R1: 45047 | S1: 45078 | T1: 45108 | U1: 45139 | V1: 45170 | W1: 45200 | X1: 45231 | Y1: 45261 | Z1: 45292 | AA1: 45323 | AB1: 45352 | AC1: 45383 | AD1: 45413 | AE1: 45444 | AF1: 45474 | AG1: 45505 | AH1: 45536 | AI1: 45566 | AJ1: 45597 | AK1: 45627
A2: CH-CMP-OU-FEL00-001-A | B2: Adrianita -Raúl | C2: Chile | D2: AARR | E2: CMP | F2: Finalizado | H2: 1 | I2: 179433 | J2: 202930 | K2: 202930 | L2: 1.1309514 | M2: -23497 | N2: 46514 | O2: 0 | P2: 36425 | Q2: 19249 | R2: 0 | S2: 67380 | T2: 23028 | U2: 0 | V2: 10060 | W2: 0 | X2: 274 | Y2: 0 | Z2: 0 | AA2: 0 | AB2: 0 | AC2: 0 | AD2: 0 | AE2: 0 | AF2: 0 | AG2: 0 | AH2: 0 | AI2: 0 | AJ2: 0 | AK2: 0
A3: CH-CMP-OT-FEL00-001-B | B3: Adrianita -Raúl | C3: Chile | D3: AARR -Informe Vida Util | E3: CMP | F3: Finalizado | H3: 1 | I3: 52447 | J3: 51143 | K3: 51143 | L3: 0.9751368 | M3: 1304 | N3: 0 | O3: 0 | P3: 0 | Q3: 0 | R3: 0 | S3: 0 | T3: 0 | U3: 0 | V3: 0 | W3: 0 | X3: 51143 | Y3: 0 | Z3: 0 | AA3: 0 | AB3: 0 | AC3: 0 | AD3: 0 | AE3: 0 | AF3: 0 | AG3: 0 | AH3: 0 | AI3: 0 | AJ3: 0 | AK3: 0
A4: CH-BHP-CD-OTR00-003-A | B4: NO_ESPECIFICADO | C4: Chile | D4: Cuellos de botella del Plan 2YB - Spence | E4: BHP | F4: Finalizado | H4: 1 | I4: 50688 | J4: 50688 | K4: 50688 | L4: 1 | M4: 0 | N4: 0 | O4: 0 | P4: 50688 | Q4: 0 | R4: 0 | S4: 0 | T4: 0 | U4: 0 | V4: 0 | W4: 0 | X4: 0 | Y4: 0 | Z4: 0 | AA4: 0 | AB4: 0 | AC4: 0 | AD4: 0 | AE4: 0 | AF4: 0 | AG4: 0 | AH4: 0 | AI4: 0 | AJ4: 0 | AK4: 0
A5: CH-LUN-CS-OTR00-004-A | B5: Candelaria (Estandar y Planificacion) | C5: Chile | D5: Candelaria (Estandar y Planificacion) | E5: Lundin | F5: Finalizado | H5: 1 | I5: 260550 | J5: 140949 | K5: 140949 | L5: 0.54096718 | M5: 119601 | N5: 0 | O5: 0 | P5: 0 | Q5: 0 | R5: 0 | S5: 90837 | T5: 36666 | U5: 0 | V5: 0 | W5: 13446 | X5: 0 | Y5: 0 | Z5: 0 | AA5: 0 | AB5: 0 | AC5: 0 | AD5: 0 | AE5: 0 | AF5: 0 | AG5: 0 | AH5: 0 | AI5: 0 | AJ5: 0 | AK5: 0
A6: CH-LUN-GM-OTR00-005-A | B6: Pilares Mineros - Candelaria | C6: Chile | D6: Candelaria Pilares | E6: Lundin | F6: Finalizado | H6: 1 | I6: 74080 | J6: 73107 | K6: 73107 | L6: 0.98686555 | M6: 973 | N6: 0 | O6: 0 | P6: 0 | Q6: 0 | R6: 0 | S6: 0 | T6: 0 | U6: 0 | V6: 71362 | W6: 1745 | X6: 0 | Y6: 0 | Z6: 0 | AA6: 973 | AB6: 0 | AC6: 0 | AD6: 0 | AE6: 0 | AF6: 0 | AG6: 0 | AH6: 0 | AI6: 0 | AJ6: 0 | AK6: 0
A7: CH-CMP-CS-OTR00-006-A | B7: CMP Estandar Planificación | C7: Chile | D7: CMP Estandar | E7: CMP | F7: Finalizado | H7: 1 | I7: 296990 | J7: 153748.16 | K7: 153748.16 | L7: 0.517688 | M7: 143241.84 | N7: 32039 | O7: 0 | P7: 59914 | Q7: 25685.41 | R7: 0 | S7: 24609.75 | T7: 0 | U7: 11500 | V7: 0 | W7: 0 | X7: 0 | Y7: 0 | Z7: 0 | AA7: 0 | AB7: 0 | AC7: 0 | AD7: 0 | AE7: 0 | AF7: 0 | AG7: 0 | AH7: 0 | AI7: 0 | AJ7: 0 | AK7: 0
A8: CH-LUN-CS-OTR00-007-A | B8: Diagnóstico Operacional Candelaria | C8: Chile | D8: Diagnóstico Operacional Candelaria | E8: Lundin | F8: Finalizado | H8: 1 | I8: 183024 | J8: 180812 | K8: 180812 | L8: 0.98791415 | M8: 2212 | N8: 0 | O8: 0 | P8: 0 | Q8: 0 | R8: 0 | S8: 96154 | T8: 0 | U8: 0 | V8: 0 | W8: 84658 | X8: 0 | Y8: 0 | Z8: 0 | AA8: 0 | AB8: 0 | AC8: 0 | AD8: 0 | AE8: 0 | AF8: 0 | AG8: 0 | AH8: 0 | AI8: 0 | AJ8: 0 | AK8: 0
A9: PE-MSR-UG-FEL03-008-A | B9: Actualización Lom Raura | C9: Perú | D9: Actualización LOM Raura | E9: Minsur | F9: Finalizado | H9: 1 | I9: 165237 | J9: 165237 | K9: 165237 | L9: 1 | M9: 0 | N9: 0 | O9: 0 | P9: 0 | Q9: 0 | R9: 0 | S9: 0 | T9: 0 | U9: 0 | V9: 0 | W9: 0 | X9: 165237 | Y9: 0 | Z9: 0 | AA9: 0 | AB9: 0 | AC9: 0 | AD9: 0 | AE9: 0 | AF9: 0 | AG9: 0 | AH9: 0 | AI9: 0 | AJ9: 0 | AK9: 0
A10: PE-MSR-OT-OTR00-009-A | B10: AESA Rendimientos | C10: Perú | D10: AESA Rendimientos | E10: Minsur | F10: Finalizado | H10: 1 | I10: 27907 | J10: 27907 | K10: 45815.49 | L10: 1.6417204 | M10: -17908.49 | N10: 0 | O10: 0 | P10: 19250.8 | Q10: 0 | R10: 0 | S10: 0 | T10: 0 | U10: 8656.69 | V10: 0 | W10: 0 | X10: 17908 | Y10: 0 | Z10: 0 | AA10: 0 | AB10: 0 | AC10: 0 | AD10: 0 | AE10: 0 | AF10: 0 | AG10: 0 | AH10: 0 | AI10: 0 | AJ10: 0 | AK10: 0
A11: CH-CMP-OP-FEL03-010-A | B11: LOM CNN 2023 | C11: Chile | D11: LOM CNN | E11: CMP | F11: Finalizado | H11: 1 | I11: 40859.57 | J11: 38221.35 | K11: 38221.35 | L11: 0.93543202 | M11: 2638.22 | N11: 0 | O11: 0 | P11: 0 | Q11: 0 | R11: 0 | S11: 0 | T11: 0 | U11: 0 | V11: 0 | W11: 38221.35 | X11: 0 | Y11: 0 | Z11: 0 | AA11: 0 | AB11: 0 | AC11: 0 | AD11: 0 | AE11: 0 | AF11: 0 | AG11: 0 | AH11: 0 | AI11: 0 | AJ11: 0 | AK11: 0
A12: CH-CMP-OP-FEL03-011-A | B12: LOM MLC 2023 | C12: Chile | D12: LOM MLC | E12: CMP | F12: Finalizado | H12: 1 | I12: 27860.87 | J12: 26093.65 | K12: 26093.65 | L12: 0.93656982 | M12: 1767.22 | N12: 0 | O12: 0 | P12: 0 | Q12: 0 | R12: 0 | S12: 0 | T12: 0 | U12: 0 | V12: 0 | W12: 26093.65 | X12: 0 | Y12: 0 | Z12: 0 | AA12: 0 | AB12: 0 | AC12: 0 | AD12: 0 | AE12: 0 | AF12: 0 | AG12: 0 | AH12: 0 | AI12: 0 | AJ12: 0 | AK12: 0
A13: CH-GLE-OP-FEL01-012-A | B13: Lomas Bayas - LoA24 | C13: Chile | D13: Lomas Bayas | E13: Glencore | F13: Finalizado | H13: 1 | I13: 294845.56 | J13: 254964 | K13: 254964 | L13: 0.86473746 | M13: 39881.56 | N13: 0 | O13: 0 | P13: 0 | Q13: 0 | R13: 0 | S13: 0 | T13: 62800 | U13: 104003 | V13: 0 | W13: 88161 | X13: 0 | Y13: 0 | Z13: 0 | AA13: 3481 | AB13: 0 | AC13: 0 | AD13: 0 | AE13: 0 | AF13: 0 | AG13: 0 | AH13: 0 | AI13: 0 | AJ13: 0 | AK13: 0
... A18: RU-OTR-GM-FEL01-017-A | B18: OKT-NFM-FS | C18: Rusia | D18: Oktyabrsky | E18: Otro | F18: Finalizado | H18: 1 | I18: 123973 | J18: 123973 | K18: 123973 | L18: 1 | M18: 0 | N18: 0 | O18: 0 | P18: 0 | Q18: 0 | R18: 0 | S18: 0 | T18: 66887 | U18: 57086 | V18: 0 | W18: 0 | X18: 0 | Y18: 0 | Z18: 0 | AA18: 0 | AB18: 0 | AC18: 0 | AD18: 0 | AE18: 0 | AF18: 0 | AG18: 0 | AH18: 0 | AI18: 0 | AJ18: 0 | AK18: 0
A19: CH-COD-UG-OTR00-003-B | B19: NO_ESPECIFICADO | C19: Chile | D19: Planificación Minera Subterránea | E19: Codelco | F19: Finalizado | H19: 1 | I19: 92002.26 | J19: 92002.26 | K19: 92002.26 | L19: 1 | M19: 0 | N19: 48365.26 | O19: 43637 | Q19: 0 | R19: 0 | S19: 0 | T19: 0 | U19: 0 | V19: 0 | W19: 0 | X19: 0 | Y19: 0 | Z19: 0 | AA19: 0 | AB19: 0 | AC19: 0 | AD19: 0 | AE19: 0 | AF19: 0 | AG19: 0 | AH19: 0 | AI19: 0 | AJ19: 0 | AK19: 0
A20: PE-MSR-OT-OTR00-019-A | B20: Compilación de R&R | C20: Perú | D20: Compilación de R&R | E20: Minsur | F20: Finalizado | H20: 1 | I20: 130565.64 | J20: 130565.64 | K20: 130565.64 | L20: 1 | M20: 0 | N20: 0 | O20: 0 | P20: 0 | Q20: 33038.61 | R20: 7732.4 | S20: 41477.25 | T20: 6840.375 | U20: 41477 | V20: 0 | W20: 0 | X20: 0 | Y20: 0 | Z20: 0 | AA20: 0 | AB20: 0 | AC20: 0 | AD20: 0 | AE20: 0 | AF20: 0 | AG20: 0 | AH20: 0 | AI20: 0 | AJ20: 0 | AK20: 0
A21: CH-BHP-CD-OTR00-020-A | B21: MEL | C21: Chile | D21: Simulación Dinámica - Enoteca | E21: MEL | F21: Finalizado | H21: 1 | I21: 79918 | J21: 190559 | K21: 190559 | L21: 2.3844315 | M21: -110641 | N21: 39901 | O21: 0 | P21: 109884 | Q21: 0 | R21: 0 | S21: 40774 | T21: 0 | U21: 0 | V21: 0 | W21: 0 | X21: 0 | Y21: 0 | Z21: 0 | AA21: 0 | AB21: 0 | AC21: 0 | AD21: 0 | AE21: 0 | AF21: 0 | AG21: 0 | AH21: 0 | AI21: 0 | AJ21: 0 | AK21: 0
A22: PE-SME-UG-OTR00-021-A | B22: ITS Yauricocha | C22: Perú | D22: ITS Yauricocha | E22: Sierra metals | F22: Finalizado | H22: 1 | I22: 18991 | J22: 18991 | K22: 22336 | L22: 1.1761361 | M22: -3345 | N22: 0 | O22: 0 | P22: 18991 | Q22: 0 | R22: 0 | S22: 0 | T22: 0 | U22: 0 | V22: 0 | W22: 0 | X22: 0 | Y22: 3345 | Z22: 0 | AA22: 0 | AB22: 0 | AC22: 0 | AD22: 0 | AE22: 0 | AF22: 0 | AG22: 0 | AH22: 0 | AI22: 0 | AJ22: 0 | AK22: 0
A23: PE-MMG-OU-FEL00-022-A | B23: LasBambas_Ferrobamba_OP_UG | C23: Perú | D23: Transición OP/UG de Ferrobamba | E23: MMG Las Bambas | F23: En Ejecución | H23: 1 | I23: 160000 | J23: 0 | K23: 0 | L23: 0 | M23: 160000 | N23: 0 | O23: 0 | P23: 0 | Q23: 0 | R23: 0 | S23: 0 | T23: 0 | U23: 0 | V23: 0 | W23: 0 | X23: 0 | Y23: 0 | Z23: 0 | AA23: 72174 | AB23: 29275.333 | AC23: 29275.333 | AD23: 29275.333 | AE23: 0 | AF23: 0 | AG23: 0 | AH23: 0 | AI23: 0 | AJ23: 0 | AK23: 0
A24: PE-CSC-UG-FEL2A-023-A | B24: PFS Los Calatos | C24: Perú | D24: PFS Los Calatos | E24: CD Capital | F24: En Ejecución | H24: 1 | I24: 917313 | J24: 91731 | K24: 91731 | L24: 0.099999673 | M24: 825582 | N24: 0 | O24: 0 | P24: 0 | Q24: 0 | R24: 0 | S24: 0 | T24: 0 | U24: 0 | V24: 0 | W24: 0 | X24: 0 | Y24: 91731 | Z24: 100441 | AA24: 29776 | AB24: 70005 | AC24: 201211.33 | AD24: 201211.33 | AE24: 201211.33 | AF24: 0 | AG24: 0 | AH24: 0 | AI24: 0 | AJ24: 0 | AK24: 0
A25: PE-MSR-OP-OTR00-024-A | B25: Marcobre - Minajusta | C25: Perú | D25: Marcobre | E25: Minsur | F25: Finalizado | H25: 1 | I25: 137832 | J25: 137832 | K25: 137832 | L25: 1 | M25: 0 | N25: 0 | O25: 0 | P25: 0 | Q25: 0 | R25: 0 | S25: 97467 | T25: 0 | U25: 29431 | V25: 0 | W25: 10934 | X25: 0 | Y25: 0 | Z25: 0 | AA25: 0 | AB25: 0 | AC25: 0 | AD25: 0 | AE25: 0 | AF25: 0 | AG25: 0 | AH25: 0 | AI25: 0 | AJ25: 0 | AK25: 0
A26: CH-CMP-OT-OTR00-025-A | B26: RDP | C26: Chile | D26: Optimizar procesos RDP | E26: CMP | F26: Finalizado | H26: 1 | I26: 34790 | J26: 44990 | K26: 44990 | L26: 1.2931877 | M26: -10200 | N26: 0 | O26: 0 | P26: 0 | Q26: 0 | R26: 0 | S26: 0 | T26: 0 | U26: 0 | V26: 0 | W26: 0 | X26: 44990 | Y26: 0 | Z26: 0 | AA26: 0 | AB26: 0 | AC26: 0 | AD26: 0 | AE26: 0 | AF26: 0 | AG26: 0 | AH26: 0 | AI26: 0 | AJ26: 0 | AK26: 0
A27: BR-MOS-OU-FEL03-026-A | B27: Mosaic_Cajati | C27: Brasil | D27: Cajati | E27: Mosaic | F27: En Ejecución | H27: 1 | I27: 555021 | J27: 192584 | K27: 192584 | L27: 0.34698507 | M27: 362437 | N27: 0 | O27: 0 | P27: 0 | Q27: 0 | R27: 0 | S27: 0 | T27: 70821 | U27: 14596 | V27: 40919 | W27: 39419 | X27: 0 | Y27: 26829 | Z27: 155916 | AA27: 11081 | AB27: 65146.667 | AC27: 65146.667 | AD27: 65146.667 | AJ27: 0 | AK27: 0
A28: BR-NEX-UG-FEL2A-027-A | B28: NEXA_FEL2 Aripuana | C28: Brasil | D28: FEL2 Aripuana | E28: Nexa | F28: En Ejecución | H28: 1 | I28: 203609 | J28: 10924 | K28: 10924 | L28: 0.053651852 | M28: 192685 | N28: 0 | O28: 0 | P28: 0 | Q28: 0 | R28: 0 | S28: 0 | T28: 0 | U28: 0 | V28: 0 | W28: 0 | X28: 0 | Y28: 10924 | Z28: 15096 | AA28: 27426 | AB28: 75081.5 | AC28: 75081.5 | AD28: 0 | AE28: 0 | AF28: 0 | AG28: 0 | AH28: 0 | AI28: 0 | AJ28: 0 | AK28: 0
A29: BR-MOS-UG-FEL01-028-A | B29: Mosaic_Taquari Vassouras | C29: Brasil | D29: Taquari Vassouras | E29: Mosaic | F29: En Ejecución | H29: 1 | I29: 284633 | J29: 68185 | K29: 0 | L29: 0 | M29: 284633 | N29: 0 | O29: 0 | P29: 0 | Q29: 0 | R29: 0 | S29: 0 | T29: 0 | U29: 0 | V29: 0 | W29: 0 | X29: 0 | Y29: 0 | Z29: 68185 | AA29: 145213 | AB29: 68389 | AC29: 0 | AD29: 0 | AE29: 0 | AF29: 0 | AG29: 0 | AH29: 0 | AI29: 0 | AJ29: 0 | AK29: 0
A30: CH-AMS-CS-OTR00-029-A | B30: AMSA_Planificacion | C30: Chile | D30: Apoyo planificación minas AMSA | E30: AMSA | F30: En Ejecución | H30: 1 | I30: 427230 | J30: 195747 | K30: 195747 | L30: 0.45817709 | M30: 231483 | N30: 0 | O30: 0 | P30: 0 | Q30: 0 | R30: 0 | S30: 0 | T30: 0 | U30: 0 | V30: 0 | W30: 30338 | X30: 105098 | Y30: 60311 | Z30: 231483 | AA30: 0 | AB30: 0 | AC30: 0 | AD30: 0 | AE30: 0 | AF30: 0 | AG30: 0 | AH30: 0 | AI30: 0 | AJ30: 0 | AK30: 0
A31: CH-COD-OT-OTR00-030-A | B31: Codelco_Capacitacion Deswik DET | C31: Chile | D31: Capacitación Deswik | E31: Codelco | F31: En Ejecución | H31: 1 | I31: 75000 | J31: 0 | K31: 0 | L31: 0 | M31: 75000 | N31: 0 | O31: 0 | P31: 0 | Q31: 0 | R31: 0 | S31: 0 | T31: 0 | U31: 0 | V31: 0 | W31: 0 | X31: 0 | Y31: 0 | Z31: 0 | AA31: 29752 | AB31: 45248 | AC31: 0 | AD31: 0 | AE31: 0 | AF31: 0 | AG31: 0 | AH31: 0 | AI31: 0 | AJ31: 0 | AK31: 0
A32: CH-COD-UG-FEL01-031-A | B32: Codelco_Falla Oeste | C32: Chile | D32: Chuquicamata Falla Oeste | E32: Codelco | F32: Finalizado | H32: 1 | I32: 93503 | J32: 0 | K32: 0 | L32: 0 | M32: 93503 | N32: 0 | O32: 0 | P32: 0 | Q32: 0 | R32: 0 | S32: 0 | T32: 0 | U32: 0 | V32: 0 | W32: 0 | X32: 0 | Y32: 0 | Z32: 0 | AA32: 93503 | AB32: 0 | AC32: 0 | AD32: 0 | AE32: 0 | AF32: 0 | AG32: 0 | AH32: 0 | AI32: 0 | AJ32: 0 | AK32: 0
A33: CH-COD-UG-FEL01-032-A | B33: Codelco_Panel Central | C33: Chile | D33: Chuquicamata Panel Central | E33: Codelco | F33: Finalizado | H33: 1 | I33: 87154 | J33: 0 | K33: 0 | L33: 0 | M33: 87154 | N33: 0 | O33: 0 | P33: 0 | Q33: 0 | R33: 0 | S33: 0 | T33: 0 | U33: 0 | V33: 0 | W33: 0 | X33: 0 | Y33: 0 | Z33: 0 | AA33: 87154 | AB33: 0 | AC33: 0 | AD33: 0 | AE33: 0 | AF33: 0 | AG33: 0 | AH33: 0 | AI33: 0 | AJ33: 0 | AK33: 0
A34: CH-CMP-OU-FEL2A-033-A | B34: CMP - FEL 2A | C34: Chile | D34: CMP - FEL 2A | E34: CMP | F34: En Ejecución | H34: 1 | I34: 545327 | J34: 568482 | K34: 568482 | L34: 1.0424608 | M34: -23155 | N34: 0 | O34: 85502 | P34: 91931 | Q34: 74275 | R34: 56675 | S34: 90591 | T34: 23442 | U34: 0 | V34: 42004 | W34: 39414 | X34: 34741 | Y34: 29907 | Z34: 14672.75 | AA34: 0 | AB34: 0 | AC34: 0 | AD34: 0 | AE34: 0 | AF34: 0 | AG34: 0 | AH34: 0 | AI34: 0 | AJ34: 0 | AK34: 0
A35: CH-CMP-OU-FEL2A-033-B | B35: CMP - FEL 2A | C35: Chile | D35: CMP -FEL-2A (Extensión Modelos) | E35: CMP | F35: En Ejecución | H35: 1 | I35: 0 | J35: 0 | K35: 0 | L35: 0 | M35: 0 | N35: 0 | O35: 0 | P35: 0 | Q35: 0 | R35: 0 | S35: 0 | T35: 0 | U35: 0 | V35: 0 | W35: 0 | X35: 0 | Y35: 0 | Z35: 0 | AA35: 0 | AB35: 0 | AC35: 0 | AD35: 0 | AE35: 0 | AF35: 0 | AG35: 0 | AH35: 0 | AI35: 0 | AJ35: 0 | AK35: 0
A36: CH-CSH-OP-FEL00-034-A | B36: CSH_LOM Mina Guarello | C36: Chile | D36: Mina Guarello | E36: CSH | F36: En Ejecución | H36: 1 | I36: 114390 | J36: 0 | K36: 0 | L36: 0 | M36: 114390 | N36: 0 | O36: 0 | P36: 0 | Q36: 0 | R36: 0 | S36: 0 | T36: 0 | U36: 0 | V36: 0 | W36: 0 | X36: 0 | Y36: 0 | Z36: 0 | AA36: 19065 | AB36: 19065 | AC36: 19065 | AD36: 19065 | AE36: 19065 | AF36: 19065 | AG36: 0 | AH36: 0 | AI36: 0 | AJ36: 0 | AK36: 0
A37: PE-COR-UG-FEL2A-035-A | B37: MEIA Coripuno | C37: Perú | D37: Coripuno MEIA | E37: Coripuno | F37: En Ejecución | H37: 1 | I37: 47960 | J37: 0 | K37: 0 | L37: 0 | M37: 47960 | N37: 0 | O37: 0 | P37: 0 | Q37: 0 | R37: 0 | S37: 0 | T37: 0 | U37: 0 | V37: 0 | W37: 0 | X37: 0 | Y37: 0 | Z37: 0 | AA37: 0 | AB37: 0 | AC37: 0 | AD37: 0 | AE37: 0 | AF37: 0 | AG37: 0 | AH37: 0 | AI37: 0 | AJ37: 0 | AK37: 0
A38: PE-MSR-UG-FEL03-036-A | B38: Minsur_Forecast_Budget24 | C38: Perú | D38: Forecast_Budget24 SR | E38: Minsur | F38: Finalizado | H38: 1 | I38: 65088 | J38: 0 | K38: 0 | L38: 0 | M38: 65088 | N38: 0 | O38: 0 | P38: 0 | Q38: 0 | R38: 0 | S38: 0 | T38: 0 | U38: 0 | V38: 0 | W38: 0 | X38: 0 | Y38: 0 | Z38: 65088 | AA38: 0 | AB38: 0 | AC38: 0 | AD38: 0 | AE38: 0 | AF38: 0 | AG38: 0 | AH38: 0 | AI38: 0 | AJ38: 0 | AK38: 0
A39: PE-MSR-UG-OTR00-003-C | B39: NO_ESPECIFICADO | C39: Perú | D39: Desarrollo casos LOM UM Raura | E39: Minsur | F39: Finalizado | H39: 1 | I39: 14112 | J39: 14112 | K39: 14112 | L39: 1 | M39: 0 | N39: 0 | O39: 14112 | P39: 0 | Q39: 0 | R39: 0 | S39: 0 | T39: 0 | U39: 0 | V39: 0 | W39: 0 | X39: 0 | Y39: 0 | Z39: 0 | AA39: 0 | AB39: 0 | AC39: 0 | AD39: 0 | AE39: 0 | AF39: 0 | AG39: 0 | AH39: 0 | AI39: 0 | AJ39: 0 | AK39: 0
... A55: PE-MSR-CS-OTR00-062-A | B55: Minsur_Ore Sorting Raura | C55: Perú | D55: Minsur_Ore Sorting Raura | E55: Minsur | F55: Finalizado | H55: 1 | I55: 15000 | J55: 15000 | K55: 15000 | L55: 1 | M55: 0 | N55: 0 | O55: 0 | P55: 0 | Q55: 0 | R55: 0 | S55: 0 | T55: 0 | U55: 0 | V55: 0 | W55: 0 | X55: 0 | Y55: 15000 | Z55: 0 | AA55: 0 | AB55: 0 | AC55: 0 | AD55: 0 | AE55: 0 | AF55: 0 | AG55: 0 | AH55: 0 | AI55: 0 | AJ55: 0 | AK55: 0
A56: PE-MSR-UG-FEL00-071-A | B56: Minsur_Update LOM San Rafael | C56: Perú | D56: Minsur_Update LOM San Rafael | E56: Minsur | F56: En Ejecución | H56: 1 | I56: 25600 | J56: 0 | K56: 0 | L56: 0 | M56: 25600 | Y56: 0 | AB56: 25600

Sheet Hoja2
AB1: País | AC1: Empresa-Mina | AD1: Descripción | AE1: Monto (KUSD) | AF1: Ponderado al 80% | AG1: Ponderado al 40% | AJ1: País | AK1: Empresa-Mina | AL1: Descripción | AM1: Monto (KUSD) | AN1: Ponderado al 80% | AO1: Ponderado al 40%
B2: 40 | C2: =+B2*4 -> 160 | AB2: Brasil | AC2: Mosaic - Cajati | AD2: Asesoría para el control de riesgos geotécnicos operacionales | AE2: 60 | AG2: =+AE2*0.4 -> 24 | AH2: =+AG2*1000 -> 24000 | AJ2: EEUU | AK2: Twin Metals - Birch Lake - Maturi | AL2: Prefactibilidad para el conjunto Birch Lake – Maturi | AM2: 480 | AN2: =+AM2*0.8 -> 384 | AO2: =+AN2*1000 -> 384000 | AQ2: Brasil | AR2: =+AO3 -> 125600
B3: =6*4 -> 24 | AB3: Chile | AC3: Lundin Candelaria | AD3: Mejoras operacionales (Simprep y optimización P&T subterránea) | AE3: 101 | AG3: =+AE3*0.4 -> 40.4 | AH3: =+AG3*1000 -> 40400 | AJ3: Brasil | AK3: Lhg - CTV | AL3: Planificación minera LOM (Nuevo tamaño de pilar) | AM3: 157 | AN3: =+AM3*0.8 -> 125.6 | AO3: =+AN3*1000 -> 125600 | AQ3: Chile | AR3: =+AO5+AO6 -> 92000
B4: 2 personas | C4: full | AB4: Chile | AC4: Codelco - DMH | AD4: INGENIERÍA EXPLORATORIA DEL PROYECTO DMH NORTE | AE4: 98 | AG4: =+AE4*0.4 -> 39.2 | AH4: =+AG4*1000 -> 39200 | AJ4: Perú | AK4: Minera Hampton – Los Calatos | AL4: Los Calatos Pre-FP Study (V3) | AM4: 250 | AN4: =+AM4*0.8 -> 200 | AO4: =+AN4*1000 -> 200000 | AQ4: EEUU | AR4: =+AO2+AO7 -> 704000
AB5: Chile | AC5: Mina Carola | AD5: Apoyo en la planificación de Corto Plazo (SIMPREP) | AE5: 77 | AG5: =+AE5*0.4 -> 30.8 | AH5: =+AG5*1000 -> 30800 | AJ5: Chile | AK5: CMP – Tofo Norte | AL5: Actualización tamaño negocio Tofo Norte | AM5: 45 | AN5: =+AM5*0.8 -> 36 | AO5: =+AN5*1000 -> 36000 | AQ5: Perú | AR5: =+AO4 -> 200000
B6: =42*4 -> 168 | C6: 0.3 | D6: alejandro | K6: 250 | AB6: Chile | AC6: Seprocal | AD6: Ingeniería de detalle de fortificación de piques | AE6: 165 | AG6: =+AE6*0.4 -> 66 | AH6: =+AG6*1000 -> 66000 | AJ6: Chile | AK6: CMP - Algarrobo | AL6: Evaluación caso de negocio explotación SLS | AM6: 70 | AN6: =+AM6*0.8 -> 56 | AO6: =+AN6*1000 -> 56000 | AQ6: Rusia | AR6: 0
B7: claudio 20% | K7: 180 | AB7: EEUU | AC7: Highland Copper – Copperwoord | AD7: FS Study Room and Pillar mine | AE7: 1.3 | AG7: 520000 | AH7: 520000 | AJ7: EEUU | AK7: Rio Tinto – Oyu Tolgoi | AL7: Soporte caso de litigio Rio Tinto vs Gobierno Mongolia | AM7: 400 | AN7: =+AM7*0.8 -> 320 | AO7: =+AN7*1000 -> 320000
K8: 250 | AB8: Perú | AC8: Ferrobamba – Las Bambas | AD8: PFS Ferromamba Deep | AE8: 1.24 | AG8: =+AE8*0.4 -> 0.496 | AH8: 500000
K9: 50 | P9: 250 | Q9: =+P9*0.8 -> 200 | AB9: Perú | AC9: Sierra Metals – Yauricohca | AD9: Estudio de ventilación unidad minera Yauricocha | AE9: 250 | AG9: =+AE9*0.4 -> 100 | AH9: =+AG9*1000 -> 100000
K10: 70 | P10: 90 | Q10: =+P10*0.8 -> 72 | AB10: Rusia | AC10: Highland Gold – Valunisty | AD10: Pre factibilidad OP | AE10: 500 | AG10: =+AE10*0.1 -> 50 | AH10: =+AG10*1000 -> 50000
K11: 400 | P11: 480 | Q11: =+P11*0.8 -> 384 | AB11: Rusia | AC11: EMCO | AD11: Optimización de rutas de transporte, Simulación, Modelos geotécnico y monitoreo | AE11: 425 | AG11: =+AE11*0.1 -> 42.5 | AH11: =+AG11*1000 -> 42500
K12: 1600 | P12: 157 | Q12: =+P12*0.8 -> 125.6 | AB12: Rusia | AC12: NRK – Kedrovoye | AD12: Ingeniería de Factibilidad y Detalle (Mina-Planta-Infraestructura) | AE12: -
P13: =+SUM(P9:P12) -> 977 | Q13: =+P13*0.8 -> 781.6
AE14: Brasil | AF14: =+AH2 -> 24000
AE15: Chile | AF15: =+SUM(AH3:AH6) -> 176400
AE16: EEUU | AF16: =+AH7 -> 520000
AE17: Perú | AF17: =+SUM(AH8:AH9) -> 600000
AE18: Rusia | AF18: =+SUM(AH10:AH11) -> 92500
K21: -
M23: original | N23: 9644
N24: 9250

Sheet Codigos
B1: Estado | D1: Gestores Comerciales | E1: Desarrollador Propuesta | F1: Nombre | H1: Tipo | J1: País (Oficina REDCO) | L1: Tipo de Contrato | N1: Tipo de Trabajo | O1: Margen | Q1: Motivo no Adjudicación
B2: Hallazgo Inicial | D2: AS | E2: AS | F2: Antonio Schettino | H2: Propuesta | J2: Brasil | L2: Marco | N2: Consultoria | O2: 0.2 | Q2: Estrategia no Adecuada
B3: En Construcción | D3: RM | E3: RM | F3: Ricardo Miranda | H3: Iniciativa | J3: Chile | L3: Solicitud Directa | N3: Estudios | O3: 0.5 | Q3: Alcance ineficiente
B4: Enviada / Seguimiento | D4: MM | E4: MM | F4: Mauricio Melendez | J4: Perú | L4: Licitación | N4: Proyectos | O4: 0.2 | Q4: Costos muy altos
B5: Adjudicada | D5: FR | E5: FR | F5: Felipe Rojas | J5: Rusia | Q5: Selección empresa local
B6: No Adjudicada | D6: AZ | E6: AZ | F6: Americo Zuzunaga | J6: EEUU | Q6: Sin Información
D7: CH | E7: CH | F7: Claudio Hernandez | Q7: Anulación de licitación
D8: PV | E8: PV | F8: Patricio Vergara | Q8: Otros
D9: ER | E9: ER | F9: Enrique Rubio
D10: OD | E10: OD | F10: Olesya D
D11: MF | E11: MF | F11: Matias Fuentes
D12: PA | E12: PA | F12: Pedro Aguiluz
O13: =4500000*13 -> 58500000
G30: Posible Adjudicación
G35: Pago post Inicio Proyecto [días]
G36: 60

Sheet Nombres
A1: Gestores Comerciales | B1: Desarrollador Propuesta | C1: Nombre
A2: AS | B2: AS | C2: Antonio Schettino
A3: RM | B3: RM | C3: Ricardo Miranda
A4: MM | B4: MM | C4: Mauricio Melendez
A5: FR | B5: FR | C5: Felipe Rojas
A6: AZ | B6: AZ | C6: Americo Zuzunaga
A7: CH | B7: CH | C7: Claudio Hernandez
A8: PV | B8: PV | C8: Patricio Vergara
A9: ER | B9: ER | C9: Enrique Rubio
A10: OD | B10: OD | C10: Olesya D
A11: MF | B11: MF | C11: Matias Fuentes
A12: PA | B12: PA | C12: Pedro Aguiluz

Sheet Apuntes
B2: Propuestas en construcción (word+ppt con lucas) | G2: Iniciativas Concretas (con alguna acción comercial durante la semana)
B3: ID | C3: Consultor | D3: Nombre | E3: Empresa/mina | G3: ID | H3: Consultor | I3: Nombre | J3: Empresa/mina
B4: 1 | G4: 1
B5: 2 | G5: aa
B6: 3 | G6: 3
B7: 4 | G7: 4
B8: 5 | G8: 5
B9: 6 | G9: 6
B10: 7 | G10: 7
B11: 8 | G11: 8
B12: 9 | G12: 9
B13: 10 | G13: 10
B14: 11 | G14: 11
B15: 12 | G15: 12
B16: 13 | G16: 13
B17: 14 | G17: 14
... B25: 22 | G25: 22

Sheet Charts New
A1: Pais (Oficina REDCO) | B1: (Todas)
A2: Tipo | B2: Propuesta
A3: Probabilidad | B3: (Varios elementos)
A4: Gestor Comercial (Responsable) | B4: (Todas)
A6: Etiquetas de fila | B6: Proyeccion Ingreso 2024
A7: En Construccion (Word) | B7: 501283
A8: Enviada / Seguimiento | B8: 4801193
A9: Total general | B9: 5302476
A42: Pais (Oficina REDCO) | B42: (Todas)
A43: Probabilidad | B43: (Varios elementos)
A44: Gestor Comercial (Responsable) | B44: (Todas)
A46: Etiquetas de fila | B46: Proyección 2024 | C46: Nro de Oportunidades
A47: Iniciativa | B47: 8548297.6 | C47: 67
A48: Propuesta | B48: 5302476 | C48: 18
A49: Total general | B49: 13850774 | C49: 85
A61: Pais (Oficina REDCO) | B61: Brasil
A62: Probabilidad | B62: (Varios elementos)
A63: Gestor Comercial (Responsable) | B63: (Todas)
A65: Etiquetas de fila | B65: Proyeccion Ingreso 2024 | C65: Nro de Oportunidades | D65: Fraccion (%)
A66: Iniciativa | B66: 573333.33 | C66: 6 | D66: =+GETPIVOTDATA("Proyeccion Ingreso 2024",$A$65,"Tipo","Iniciativa")/GETPIVOTDATA("Proyeccion Ingreso 2024",$A$65) -> 0.40587909
A67: Propuesta | B67: 839238.4 | C67: 3 | D67: =+GETPIVOTDATA("Proyeccion Ingreso 2024",$A$65,"Tipo","Propuesta")/GETPIVOTDATA("Proyeccion Ingreso 2024",$A$65) -> 0.59412091
A68: Total general | B68: 1412571.7 | C68: 9
A79: Pais (Oficina REDCO) | B79: Chile
A80: Probabilidad | B80: (Varios elementos)
A81: Gestor Comercial (Responsable) | B81: (Todas)
A83: Etiquetas de fila | B83: Proyeccion Ingreso 2024 | C83: Nro de Oportunidades | D83: Fraccion (%)
A84: Iniciativa | B84: 4519250 | C84: 39 | D84: =+GETPIVOTDATA("Proyeccion Ingreso 2024",$A$83,"Tipo","Iniciativa")/GETPIVOTDATA("Proyeccion Ingreso 2024",$A$83) -> 0.75538068
A85: Propuesta | B85: 1463495 | C85: 8 | D85: =+GETPIVOTDATA("Proyeccion Ingreso 2024",$A$83,"Tipo","Propuesta")/GETPIVOTDATA("Proyeccion Ingreso 2024",$A$83) -> 0.24461932
A86: Total general | B86: 5982745 | C86: 47
A96: Pais (Oficina REDCO) | B96: EEUU
A97: Probabilidad | B97: (Varios elementos)
A98: Gestor Comercial (Responsable) | B98: (Todas)
A100: Etiquetas de fila | B100: Proyeccion Ingreso 2024 | C100: Nro de Oportunidades | D100: Fraccion (%)
A101: Iniciativa | B101: 825000 | C101: 5 | D101: =+GETPIVOTDATA("Proyeccion Ingreso 2024",$A$100,"Tipo","Iniciativa")/GETPIVOTDATA("Proyeccion Ingreso 2024",$A$100) -> 0.81471826
A102: Propuesta | B102: 187620 | C102: 1 | D102: =+GETPIVOTDATA("Proyeccion Ingreso 2024",$A$100,"Tipo","Propuesta")/GETPIVOTDATA("Proyeccion Ingreso 2024",$A$100) -> 0.18528174
A103: Total general | B103: 1012620 | C103: 6
A115: Pais (Oficina REDCO) | B115: Perú
A116: Probabilidad | B116: (Varios elementos)
A117: Gestor Comercial (Responsable) | B117: (Todas)
A119: Etiquetas de fila | B119: Proyeccion Ingreso 2024 | C119: Nro de Oportunidades | D119: Fraccion (%)
A120: Iniciativa | B120: 2630714.3 | C120: 17 | D120: =+GETPIVOTDATA("Proyeccion Ingreso 2024",$A$119,"Tipo","Iniciativa")/GETPIVOTDATA("Proyeccion Ingreso 2024",$A$119) -> 0.78693282
A121: Propuesta | B121: 712283 | C121: 3 | D121: =+GETPIVOTDATA("Proyeccion Ingreso 2024",$A$119,"Tipo","Propuesta")/GETPIVOTDATA("Proyeccion Ingreso 2024",$A$119) -> 0.21306718
A122: Total general | B122: 3342997.3 | C122: 20
A134: Pais (Oficina REDCO) | B134: Rusia
A135: Probabilidad | B135: (Varios elementos)
A136: Gestor Comercial (Responsable) | B136: (Todas)
A138: Etiquetas de fila | B138: Proyeccion Ingreso 2024 | C138: Nro de Oportunidades | D138: Fraccion (%)
A139: Propuesta | B139: 1838125 | C139: 2 | D139: =+GETPIVOTDATA("Proyeccion Ingreso 2024",$A$138,"Tipo","Propuesta")/GETPIVOTDATA("Proyeccion Ingreso 2024",$A$138) -> 1
A140: Total general | B140: 1838125 | C140: 2
A149: Probabilidad | B149: (Varios elementos)
A150: Gestor Comercial (Responsable) | B150: (Todas)
A152: Proyeccion Ingresos 2024 | B152: Etiquetas de columna
A153: Etiquetas de fila | B153: Iniciativa | C153: Propuesta | D153: Total general
A154: Brasil | B154: 573333.33 | C154: 839238.4 | D154: 1412571.7
A155: Chile | B155: 4519250 | C155: 1725209.6 | D155: 6244459.6
A156: EEUU | B156: 825000 | C156: 187620 | D156: 1012620
A157: Perú | B157: 2630714.3 | C157: 712283 | D157: 3342997.3
A158: Rusia | C158: 1838125 | D158: 1838125
A159: Total general | B159: 8548297.6 | C159: 5302476 | D159: 13850774
A165: Probabilidad | B165: (Varios elementos)
A166: Tipo | B166: Propuesta
A167: Gestor Comercial (Responsable) | B167: (Todas)
A169: Etiquetas de fila | B169: Proyeccion Ingresos 2024
A170: Execution of the Pre-Feasibility Study for the Kyuchus Mining Project | B170: 1518125
A171: Ingeniería de valor para Robustecer el Proyecto CUGEP | B171: 230000
A172: Mejoramiento Plan 2024 y de Performance de Cumplimiento para Minera Centinela | B172: 225000
A173: Recuperación de Pilares Mina Urucum | B173: 263238.4
A174: Taquari Vassouras - Fase II | B174: 475000
A175: Total general | B175: 2711363.4
A179: Top Oportunidades | B179: Proyeccion Ingresos 2024
A180: Execution of the Pre-Feasibility Study for the Kyuchus Mining Project | B180: 1518125
A181: Ingeniería de valor para Robustecer el Proyecto CUGEP | B181: 230000
A182: Mejoramiento Plan 2024 y de Performance de Cumplimiento para Minera Centinela | B182: 225000
A183: Recuperación de Pilares Mina Urucum | B183: 263238.4
A184: Taquari Vassouras - Fase II | B184: 475000
A185: Total general | B185: =SUM(B180:B184) -> 2711363.4
A189: Probabilidad | B189: (Varios elementos)
A190: Tipo | B190: Propuesta
A191: Gestor Comercial (Responsable) | B191: (Todas)
B193: Etiquetas de columna
B194: feb | D194: mar | F194: Total Proyeccion Ingresos 2024 | G194: Total Suma de Duracion (meses)
A197: Etiquetas de fila | B197: Proyeccion Ingresos 2024 | C197: Suma de Duracion (meses) | D197: Proyeccion Ingresos 2024 | E197: Suma de Duracion (meses)
A198: Execution of the Pre-Feasibility Study for the Kyuchus Mining Project | D198: 1518125 | E198: 16 | F198: 1518125 | G198: 16
A199: Ingeniería de valor para Robustecer el Proyecto CUGEP | D199: 230000 | E199: 3 | F199: 230000 | G199: 3
A200: Mejoramiento Plan 2024 y de Performance de Cumplimiento para Minera Centinela | B200: 225000 | C200: 4 | F200: 225000 | G200: 4
A201: Recuperación de Pilares Mina Urucum | D201: 263238.4 | E201: 8 | F201: 263238.4 | G201: 8
A202: Taquari Vassouras - Fase II | B202: 475000 | C202: 3 | F202: 475000 | G202: 3
A203: Total general | B203: 700000 | C203: 7 | D203: 2011363.4 | E203: 27 | F203: 2711363.4 | G203: 34
B206: Febrero | D206: Marzo
A207: Oportunidad | B207: Proy. 2024 (US$) | C207: Duracion (meses) | D207: Proy. 2024 (US$) | E207: Duracion (meses)
A208: Execution of the Pre-Feasibility Study for the Kyuchus Mining Project | D208: 1518125 | E208: 16
A209: Ingeniería de valor para Robustecer el Proyecto CUGEP | D209: 225000 | E209: 3
A210: Mejoramiento Plan 2024 y de Performance de Cumplimiento para Minera Centinela | B210: 225000 | C210: 4
A211: Recuperación de Pilares Mina Urucum | D211: 263238.4 | E211: 8
A212: Taquari Vassouras - Fase II | B212: 475000 | C212: 3
A213: Total general | B213: =SUM(B208:B212) -> 700000 | D213: =SUM(D208:D212) -> 2006363.4
A217: Probabilidad | B217: (Varios elementos)
A218: Etapa | B218: No Adjudicada
A219: Tipo | B219: Propuesta
A221: Etiquetas de fila | B221: Proyeccion Ingresos 2024
...

Sheet PBI_Flujo Caja (+Pipeline) 2023
F2: Ingresos Proyectados REDCO
F3: Año: 2023
F6: Filtro | G6: =+BF8 -> Todos
F7: Probabilidad Pipeline | G7: =+BF9 -> 1 | AY7: Análisis de Información (Todos)
BE8: Filtro | BF8: Todos | BO8: Cliente | BP8: Total 2023 | BQ8: Enero | BR8: Febrero | BS8: Marzo | BT8: Abril | BU8: Mayo | BV8: Junio | BW8: Julio | BX8: Agosto | BY8: Septiembre | BZ8: Octubre | CA8: Noviembre | CB8: Diciembre
BE9: Probabilidad Pipeline | BF9: 1 | BO9: CMP | BP9: =+SUM(BQ9:CB9) -> 1965776.7 | BQ9: =+IF($G$6="En Ejecución",1*SUMIFS(P$28:P$1048576,$J$28:$J$1048576,">="&$G$7,$G$28:$G$1048576,$BO9,$H$28:$H$1048576,$G$6),0)+IF($G$6="Pipeline",1*SUMIFS(P$28:P$1048576,$J$28:$J$1048576,">="&$G$7,$G$28:$G$1048576,$BO9,$H$28:$H$1048576,$G$6),0)+IF($G$6="Todos",1*SUMIFS(P$28:P$1048576,$J$28:$J$1048576,">="&$G$7,$G$28:$G$1048576,$BO9),0)+IF($G$6="Finalizado",1*SUMIFS(P$28:P$1048576,$J$28:$J$1048576,">="&$G$7,$G$28:$G$1048576,$BO9,$H$28:$H$1048576,$G$6),0) -> 78553 | BR9: =+IF($G$6="En Ejecución",1*SUMIFS(Q$28:Q$1048576,$J$28:$J$1048576,">="&$G$7,$G$28:$G$1048576,$BO9,$H$28:$H$1048576,$G$6),0)+IF($G$6="Pipeline",1*SUMIFS(Q$28:Q$1048576,$J$28:$J$1048576,">="&$G$7,$G$28:$G$1048576,$BO9,$H$28:$H$1048576,$G$6),0)+IF($G$6="Todos",1*SUMIFS(Q$28:Q$1048576,$J$28:$J$1048576,">="&$G$7,$G$28:$G$1048576,$BO9),0)+IF($G$6="Finalizado",1*SUMIFS(Q$28:Q$1048576,$J$28:$J$1048576,">="&$G$7,$G$28:$G$1048576,$BO9,$H$28:$H$1048576,$G$6),0) -> 239406 | BS9: =+IF($G$6="En Ejecución",1*SUMIFS(R$28:R$1048576,$J$28:$J$1048576,">="&$G$7,$G$28:$G$1048576,$BO9,$H$28:$H$1048576,$G$6),0)+IF($G$6="Pipeline",1*SUMIFS(R$28:R$1048576,$J$28:$J$1048576,">="&$G$7,$G$28:$G$1048576,$BO9,$H$28:$H$1048576,$G$6),0)+IF($G$6="Todos",1*SUMIFS(R$28:R$1048576,$J$28:$J$1048576,">="&$G$7,$G$28:$G$1048576,$BO9),0)+IF($G$6="Finalizado",1*SUMIFS(R$28:R$1048576,$J$28:$J$1048576,">="&$G$7,$G$28:$G$1048576,$BO9,$H$28:$H$1048576,$G$6),0) -> 262811 | BT9: =+IF($G$6="En Ejecución",1*SUMIFS(S$28:S$1048576,$J$28:$J$1048576,">="&$G$7,$G$28:$G$1048576,$BO9,$H$28:$H$1048576,$G$6),0)+IF($G$6="Pipeline",1*SUMIFS(S$28:S$1048576,$J$28:$J$1048576,">="&$G$7,$G$28:$G$1048576,$BO9,$H$28:$H$1048576,$G$6),0)+IF($G$6="Todos",1*SUMIFS(S$28:S$1048576,$J$28:$J$1048576,">="&$G$7,$G$28:$G$1048576,$BO9),0)+IF($G$6="Finalizado",1*SUMIFS(S$28:S$1048576,$J$28:$J$1048576,">="&$G$7,$G$28:$G$1048576,$BO9,$H$28:$H$1048576,$G$6),0) -> 338397.41 | BU9: =+IF($G$6="En Ejecución",1*SUMIFS(T$28:T$1048576,$J$28:$J$1048576,">="&$G$7,$G$28:$G$1048576,$BO9,$H$28:$H$1048576,$G$6),0)+IF($G$6="Pipeline",1*SUMIFS(T$28:T$1048576,$J$28:$J$1048576,">="&$G$7,$G$28:$G$1048576,$BO9,$H$28:$H$1048576,$G$6),0)+IF($G$6="Todos",1*SUMIFS(T$28:T$1048576,$J$28:$J$1048576,">="&$G$7,$G$28:$G$1048576,$BO9),0)+IF($G$6="Finalizado",1*SUMIFS(T$28:T$1048576,$J$28:$J$1048576,">="&$G$7,$G$28:$G$1048576,$BO9,$H$28:$H$1048576,$G$6),0) -> 190895 | BV9: =+IF($G$6="En Ejecución",1*SUMIFS(U$28:U$1048576,$J$28:$J$1048576,">="&$G$7,$G$28:$G$1048576,$BO9,$H$28:$H$1048576,$G$6),0)+IF($G$6="Pipeline",1*SUMIFS(U$28:U$1048576,$J$28:$J$1048576,">="&$G$7,$G$28:$G$1048576,$BO9,$H$28:$H$1048576,$G$6),0)+IF($G$6="Todos",1*SUMIFS(U$28:U$1048576,$J$28:$J$1048576,">="&$G$7,$G$28:$G$1048576,$BO9),0)+IF($G$6="Finalizado",1*SUMIFS(U$28:U$1048576,$J$28:$J$1048576,">="&$G$7,$G$28:$G$1048576,$BO9,$H$28:$H$1048576,$G$6),0) -> 253687.75 | BW9: =+IF($G$6="En Ejecución",1*SUMIFS(V$28:V$1048576,$J$28:$J$1048576,">="&$G$7,$G$28:$G$1048576,$BO9,$H$28:$H$1048576,$G$6),0)+IF($G$6="Pipeline",1*SUMIFS(V$28:V$1048576,$J$28:$J$1048576,">="&$G$7,$G$28:$G$1048576,$BO9,$H$28:$H$1048576,$G$6),0)+IF($G$6="Todos",1*SUMIFS(V$28:V$1048576,$J$28:$J$1048576,">="&$G$7,$G$28:$G$1048576,$BO9),0)+IF($G$6="Finalizado",1*SUMIFS(V$28:V$1048576,$J$28:$J$1048576,">="&$G$7,$G$28:$G$1048576,$BO9,$H$28:$H$1048576,$G$6),0) -> 117431 | BX9: =+IF($G$6="En Ejecución",1*SUMIFS(W$28:W$1048576,$J$28:$J$1048576,">="&$G$7,$G$28:$G$1048576,$BO9,$H$28:$H$1048576,$G$6),0)+IF($G$6="Pipeline",1*SUMIFS(W$28:W$1048576,$J$28:$J$1048576,">="&$G$7,$G$28:$G$1048576,$BO9,$H$28:$H$1048576,$G$6),0)+IF($G$6="Todos",1*SUMIFS(W$28:W$1048576,$J$28:$J$1048576,">="&$G$7,$G$28:$G$1048576,$BO9),0)+IF($G$6="Finalizado",1*SUMIFS(W$28:W$1048576,$J$28:$J$1048576,">="&$G$7,$G$28:$G$1048576,$BO9,$H$28:$H$1048576,$G$6),0) -> 11500 | ... CB9: =+IF($G$6="En Ejecución",1*SUMIFS(AA$28:AA$1048576,$J$28:$J$1048576,">="&$G$7,$G$28:$G$1048576,$BO9,$H$28:$H$1048576,$G$6),0)+IF($G$6="Pipeline",1*SUMIFS(AA$28:AA$1048576,$J$28:$J$1048576,">="&$G$7,$G$28:$G$1048576,$BO9,$H$28:$H$1048576,$G$6),0)+IF($G$6="Todos",1*SUMIFS(AA$28:AA$1048576,$J$28:$J$1048576,">="&$G$7,$G$28:$G$1048576,$BO9),0)+IF($G$6="Finalizado",1*SUMIFS(AA$28:AA$1048576,$J$28:$J$1048576,">="&$G$7,$G$28:$G$1048576,$BO9,$H$28:$H$1048576,$G$6),0) -> 0
D10: Pais | E10: Pais | F10: Proyecto | G10: Cliente | H10: Estado | I10: Solicitud de Cambio / Orden de Cambio | J10: Probabilidad | K10: Monto Total (US$) | L10: Monto 2023 (US$) | M10: Facturado a la fecha (US$) | N10: % Avance Financiero | O10: Diferencia USD a la Fecha | P10: 44927 | Q10: 44958 | R10: 44986 | S10: 45017 | T10: 45047 | U10: 45078 | V10: 45108 | W10: 45139 | X10: 45170 | Y10: 45200 | Z10: 45231 | AA10: 45261 | AB10: 45292 | AC10: 45323 | AD10: 45352 | AE10: 45383 | AF10: 45413 | AG10: 45444 | AH10: 45474 | AI10: 45505 | AJ10: 45536 | AK10: 45566 | AL10: 45597 | AM10: 45627 | BO10: Lundin | BP10: =+SUM(BQ10:CB10) -> 395841 | BQ10: =+IF($G$6="En Ejecución",1*SUMIFS(P$28:P$1048576,$J$28:$J$1048576,">="&$G$7,$G$28:$G$1048576,$BO10,$H$28:$H$1048576,$G$6),0)+IF($G$6="Pipeline",1*SUMIFS(P$28:P$1048576,$J$28:$J$1048576,">="&$G$7,$G$28:$G$1048576,$BO10,$H$28:$H$1048576,$G$6),0)+IF($G$6="Todos",1*SUMIFS(P$28:P$1048576,$J$28:$J$1048576,">="&$G$7,$G$28:$G$1048576,$BO10),0)+IF($G$6="Finalizado",1*SUMIFS(P$28:P$1048576,$J$28:$J$1048576,">="&$G$7,$G$28:$G$1048576,$BO10,$H$28:$H$1048576,$G$6),0) -> 0 | BR10: =+IF($G$6="En Ejecución",1*SUMIFS(Q$28:Q$1048576,$J$28:$J$1048576,">="&$G$7,$G$28:$G$1048576,$BO10,$H$28:$H$1048576,$G$6),0)+IF($G$6="Pipeline",1*SUMIFS(Q$28:Q$1048576,$J$28:$J$1048576,">="&$G$7,$G$28:$G$1048576,$BO10,$H$28:$H$1048576,$G$6),0)+IF($G$6="Todos",1*SUMIFS(Q$28:Q$1048576,$J$28:$J$1048576,">="&$G$7,$G$28:$G$1048576,$BO10),0)+IF($G$6="Finalizado",1*SUMIFS(Q$28:Q$1048576,$J$28:$J$1048576,">="&$G$7,$G$28:$G$1048576,$BO10,$H$28:$H$1048576,$G$6),0) -> 0 | BS10: =+IF($G$6="En Ejecución",1*SUMIFS(R$28:R$1048576,$J$28:$J$1048576,">="&$G$7,$G$28:$G$1048576,$BO10,$H$28:$H$1048576,$G$6),0)+IF($G$6="Pipeline",1*SUMIFS(R$28:R$1048576,$J$28:$J$1048576,">="&$G$7,$G$28:$G$1048576,$BO10,$H$28:$H$1048576,$G$6),0)+IF($G$6="Todos",1*SUMIFS(R$28:R$1048576,$J$28:$J$1048576,">="&$G$7,$G$28:$G$1048576,$BO10),0)+IF($G$6="Finalizado",1*SUMIFS(R$28:R$1048576,$J$28:$J$1048576,">="&$G$7,$G$28:$G$1048576,$BO10,$H$28:$H$1048576,$G$6),0) -> 0 | BT10: =+IF($G$6="En Ejecución",1*SUMIFS(S$28:S$1048576,$J$28:$J$1048576,">="&$G$7,$G$28:$G$1048576,$BO10,$H$28:$H$1048576,$G$6),0)+IF($G$6="Pipeline",1*SUMIFS(S$28:S$1048576,$J$28:$J$1048576,">="&$G$7,$G$28:$G$1048576,$BO10,$H$28:$H$1048576,$G$6),0)+IF($G$6="Todos",1*SUMIFS(S$28:S$1048576,$J$28:$J$1048576,">="&$G$7,$G$28:$G$1048576,$BO10),0)+IF($G$6="Finalizado",1*SUMIFS(S$28:S$1048576,$J$28:$J$1048576,">="&$G$7,$G$28:$G$1048576,$BO10,$H$28:$H$1048576,$G$6),0) -> 0 | BU10: =+IF($G$6="En Ejecución",1*SUMIFS(T$28:T$1048576,$J$28:$J$1048576,">="&$G$7,$G$28:$G$1048576,$BO10,$H$28:$H$1048576,$G$6),0)+IF($G$6="Pipeline",1*SUMIFS(T$28:T$1048576,$J$28:$J$1048576,">="&$G$7,$G$28:$G$1048576,$BO10,$H$28:$H$1048576,$G$6),0)+IF($G$6="Todos",1*SUMIFS(T$28:T$1048576,$J$28:$J$1048576,">="&$G$7,$G$28:$G$1048576,$BO10),0)+IF($G$6="Finalizado",1*SUMIFS(T$28:T$1048576,$J$28:$J$1048576,">="&$G$7,$G$28:$G$1048576,$BO10,$H$28:$H$1048576,$G$6),0) -> 0 | BV10: =+IF($G$6="En Ejecución",1*SUMIFS(U$28:U$1048576,$J$28:$J$1048576,">="&$G$7,$G$28:$G$1048576,$BO10,$H$28:$H$1048576,$G$6),0)+IF($G$6="Pipeline",1*SUMIFS(U$28:U$1048576,$J$28:$J$1048576,">="&$G$7,$G$28:$G$1048576,$BO10,$H$28:$H$1048576,$G$6),0)+IF($G$6="Todos",1*SUMIFS(U$28:U$1048576,$J$28:$J$1048576,">="&$G$7,$G$28:$G$1048576,$BO10),0)+IF($G$6="Finalizado",1*SUMIFS(U$28:U$1048576,$J$28:$J$1048576,">="&$G$7,$G$28:$G$1048576,$BO10,$H$28:$H$1048576,$G$6),0) -> 186991 | BW10: =+IF($G$6="En Ejecución",1*SUMIFS(V$28:V$1048576,$J$28:$J$1048576,">="&$G$7,$G$28:$G$1048576,$BO10,$H$28:$H$1048576,$G$6),0)+IF($G$6="Pipeline",1*SUMIFS(V$28:V$1048576,$J$28:$J$1048576,">="&$G$7,$G$28:$G$1048576,$BO10,$H$28:$H$1048576,$G$6),0)+IF($G$6="Todos",1*SUMIFS(V$28:V$1048576,$J$28:$J$1048576,">="&$G$7,$G$28:$G$1048576,$BO10),0)+IF($G$6="Finalizado",1*SUMIFS(V$28:V$1048576,$J$28:$J$1048576,">="&$G$7,$G$28:$G$1048576,$BO10,$H$28:$H$1048576,$G$6),0) -> 36666 | BX10: =+IF($G$6="En Ejecución",1*SUMIFS(W$28:W$1048576,$J$28:$J$1048576,">="&$G$7,$G$28:$G$1048576,$BO10,$H$28:$H$1048576,$G$6),0)+IF($G$6="Pipeline",1*SUMIFS(W$28:W$1048576,$J$28:$J$1048576,">="&$G$7,$G$28:$G$1048576,$BO10,$H$28:$H$1048576,$G$6),0)+IF($G$6="Todos",1*SUMIFS(W$28:W$1048576,$J$28:$J$1048576,">="&$G$7,$G$28:$G$1048576,$BO10),0)+IF($G$6="Finalizado",1*SUMIFS(W$28:W$1048576,$J$28:$J$1048576,">="&$G$7,$G$28:$G$1048576,$BO10,$H$28:$H$1048576,$G$6),0) -> 0 | ... CB10: =+IF($G$6="En Ejecución",1*SUMIFS(AA$28:AA$1048576,$J$28:$J$1048576,">="&$G$7,$G$28:$G$1048576,$BO10,$H$28:$H$1048576,$G$6),0)+IF($G$6="Pipeline",1*SUMIFS(AA$28:AA$1048576,$J$28:$J$1048576,">="&$G$7,$G$28:$G$1048576,$BO10,$H$28:$H$1048576,$G$6),0)+IF($G$6="Todos",1*SUMIFS(AA$28:AA$1048576,$J$28:$J$1048576,">="&$G$7,$G$28:$G$1048576,$BO10),0)+IF($G$6="Finalizado",1*SUMIFS(AA$28:AA$1048576,$J$28:$J$1048576,">="&$G$7,$G$28:$G$1048576,$BO10,$H$28:$H$1048576,$G$6),0) -> 973
D11: Gran Total | E11: Gran Total | F11: =+$G$6 -> Todos | G11: Todos | H11: =+$G$6 -> Todos | I11: =+H11 -> Todos | J11: =+$G$7 -> 1 | K11: =+SUM(K15:K19) -> 9717950.8 | L11: =+SUM(L15:L19) -> 5657429.3 | M11: =+SUM(M15:M19) -> 5056239.8 | N11: =+IFERROR(O11/K11,0) -> 0.47970103 | O11: =+SUM(O15:O19) -> 4661711 | P11: =+SUM(P15:P19) -> 318273.26 | Q11: =+SUM(Q15:Q19) -> 368548 | R11: =+SUM(R15:R19) -> 505870.8 | S11: =+SUM(S15:S19) -> 558554.48 | T11: =+SUM(T15:T19) -> 442765.4 | U11: =+SUM(U15:U19) -> 759035.7 | V11: =+SUM(V15:V19) -> 501758.92 | ... AM11: =+SUM(AM15:AM19) -> 0 | BO11: Glencore | BP11: =+SUM(BQ11:CB11) -> 258445 | BQ11: =+IF($G$6="En Ejecución",1*SUMIFS(P$28:P$1048576,$J$28:$J$1048576,">="&$G$7,$G$28:$G$1048576,$BO11,$H$28:$H$1048576,$G$6),0)+IF($G$6="Pipeline",1*SUMIFS(P$28:P$1048576,$J$28:$J$1048576,">="&$G$7,$G$28:$G$1048576,$BO11,$H$28:$H$1048576,$G$6),0)+IF($G$6="Todos",1*SUMIFS(P$28:P$1048576,$J$28:$J$1048576,">="&$G$7,$G$28:$G$1048576,$BO11),0)+IF($G$6="Finalizado",1*SUMIFS(P$28:P$1048576,$J$28:$J$1048576,">="&$G$7,$G$28:$G$1048576,$BO11,$H$28:$H$1048576,$G$6),0) -> 0 | BR11: =+IF($G$6="En Ejecución",1*SUMIFS(Q$28:Q$1048576,$J$28:$J$1048576,">="&$G$7,$G$28:$G$1048576,$BO11,$H$28:$H$1048576,$G$6),0)+IF($G$6="Pipeline",1*SUMIFS(Q$28:Q$1048576,$J$28:$J$1048576,">="&$G$7,$G$28:$G$1048576,$BO11,$H$28:$H$1048576,$G$6),0)+IF($G$6="Todos",1*SUMIFS(Q$28:Q$1048576,$J$28:$J$1048576,">="&$G$7,$G$28:$G$1048576,$BO11),0)+IF($G$6="Finalizado",1*SUMIFS(Q$28:Q$1048576,$J$28:$J$1048576,">="&$G$7,$G$28:$G$1048576,$BO11,$H$28:$H$1048576,$G$6),0) -> 0 | BS11: =+IF($G$6="En Ejecución",1*SUMIFS(R$28:R$1048576,$J$28:$J$1048576,">="&$G$7,$G$28:$G$1048576,$BO11,$H$28:$H$1048576,$G$6),0)+IF($G$6="Pipeline",1*SUMIFS(R$28:R$1048576,$J$28:$J$1048576,">="&$G$7,$G$28:$G$1048576,$BO11,$H$28:$H$1048576,$G$6),0)+IF($G$6="Todos",1*SUMIFS(R$28:R$1048576,$J$28:$J$1048576,">="&$G$7,$G$28:$G$1048576,$BO11),0)+IF($G$6="Finalizado",1*SUMIFS(R$28:R$1048576,$J$28:$J$1048576,">="&$G$7,$G$28:$G$1048576,$BO11,$H$28:$H$1048576,$G$6),0) -> 0 | BT11: =+IF($G$6="En Ejecución",1*SUMIFS(S$28:S$1048576,$J$28:$J$1048576,">="&$G$7,$G$28:$G$1048576,$BO11,$H$28:$H$1048576,$G$6),0)+IF($G$6="Pipeline",1*SUMIFS(S$28:S$1048576,$J$28:$J$1048576,">="&$G$7,$G$28:$G$1048576,$BO11,$H$28:$H$1048576,$G$6),0)+IF($G$6="Todos",1*SUMIFS(S$28:S$1048576,$J$28:$J$1048576,">="&$G$7,$G$28:$G$1048576,$BO11),0)+IF($G$6="Finalizado",1*SUMIFS(S$28:S$1048576,$J$28:$J$1048576,">="&$G$7,$G$28:$G$1048576,$BO11,$H$28:$H$1048576,$G$6),0) -> 0 | BU11: =+IF($G$6="En Ejecución",1*SUMIFS(T$28:T$1048576,$J$28:$J$1048576,">="&$G$7,$G$28:$G$1048576,$BO11,$H$28:$H$1048576,$G$6),0)+IF($G$6="Pipeline",1*SUMIFS(T$28:T$1048576,$J$28:$J$1048576,">="&$G$7,$G$28:$G$1048576,$BO11,$H$28:$H$1048576,$G$6),0)+IF($G$6="Todos",1*SUMIFS(T$28:T$1048576,$J$28:$J$1048576,">="&$G$7,$G$28:$G$1048576,$BO11),0)+IF($G$6="Finalizado",1*SUMIFS(T$28:T$1048576,$J$28:$J$1048576,">="&$G$7,$G$28:$G$1048576,$BO11,$H$28:$H$1048576,$G$6),0) -> 0 | BV11: =+IF($G$6="En Ejecución",1*SUMIFS(U$28:U$1048576,$J$28:$J$1048576,">="&$G$7,$G$28:$G$1048576,$BO11,$H$28:$H$1048576,$G$6),0)+IF($G$6="Pipeline",1*SUMIFS(U$28:U$1048576,$J$28:$J$1048576,">="&$G$7,$G$28:$G$1048576,$BO11,$H$28:$H$1048576,$G$6),0)+IF($G$6="Todos",1*SUMIFS(U$28:U$1048576,$J$28:$J$1048576,">="&$G$7,$G$28:$G$1048576,$BO11),0)+IF($G$6="Finalizado",1*SUMIFS(U$28:U$1048576,$J$28:$J$1048576,">="&$G$7,$G$28:$G$1048576,$BO11,$H$28:$H$1048576,$G$6),0) -> 0 | BW11: =+IF($G$6="En Ejecución",1*SUMIFS(V$28:V$1048576,$J$28:$J$1048576,">="&$G$7,$G$28:$G$1048576,$BO11,$H$28:$H$1048576,$G$6),0)+IF($G$6="Pipeline",1*SUMIFS(V$28:V$1048576,$J$28:$J$1048576,">="&$G$7,$G$28:$G$1048576,$BO11,$H$28:$H$1048576,$G$6),0)+IF($G$6="Todos",1*SUMIFS(V$28:V$1048576,$J$28:$J$1048576,">="&$G$7,$G$28:$G$1048576,$BO11),0)+IF($G$6="Finalizado",1*SUMIFS(V$28:V$1048576,$J$28:$J$1048576,">="&$G$7,$G$28:$G$1048576,$BO11,$H$28:$H$1048576,$G$6),0) -> 62800 | BX11: =+IF($G$6="En Ejecución",1*SUMIFS(W$28:W$1048576,$J$28:$J$1048576,">="&$G$7,$G$28:$G$1048576,$BO11,$H$28:$H$1048576,$G$6),0)+IF($G$6="Pipeline",1*SUMIFS(W$28:W$1048576,$J$28:$J$1048576,">="&$G$7,$G$28:$G$1048576,$BO11,$H$28:$H$1048576,$G$6),0)+IF($G$6="Todos",1*SUMIFS(W$28:W$1048576,$J$28:$J$1048576,">="&$G$7,$G$28:$G$1048576,$BO11),0)+IF($G$6="Finalizado",1*SUMIFS(W$28:W$1048576,$J$28:$J$1048576,">="&$G$7,$G$28:$G$1048576,$BO11,$H$28:$H$1048576,$G$6),0) -> 104003 | ... CB11: =+IF($G$6="En Ejecución",1*SUMIFS(AA$28:AA$1048576,$J$28:$J$1048576,">="&$G$7,$G$28:$G$1048576,$BO11,$H$28:$H$1048576,$G$6),0)+IF($G$6="Pipeline",1*SUMIFS(AA$28:AA$1048576,$J$28:$J$1048576,">="&$G$7,$G$28:$G$1048576,$BO11,$H$28:$H$1048576,$G$6),0)+IF($G$6="Todos",1*SUMIFS(AA$28:AA$1048576,$J$28:$J$1048576,">="&$G$7,$G$28:$G$1048576,$BO11),0)+IF($G$6="Finalizado",1*SUMIFS(AA$28:AA$1048576,$J$28:$J$1048576,">="&$G$7,$G$28:$G$1048576,$BO11,$H$28:$H$1048576,$G$6),0) -> 3481
D12: Total Finalizado | E12: Total Finalizado | F12: Finalizado | G12: =+F12 -> Finalizado | H12: Finalizado | I12: Finalizado | J12: 1 | K12: =+IF($G$6="Finalizado",1*SUMIFS(K$28:K$1048576,$J$28:$J$1048576,">="&$G$7,$H$28:$H$1048576,"Finalizado"))+IF($G$6="Todos",1*SUMIFS(K$28:K$1048576,$J$28:$J$1048576,">="&$G$7,$H$28:$H$1048576,"Finalizado"),0) -> 4876908.8 | L12: =+IF($G$6="Finalizado",1*SUMIFS(L$28:L$1048576,$J$28:$J$1048576,">="&$G$7,$H$28:$H$1048576,"Finalizado"))+IF($G$6="Todos",1*SUMIFS(L$28:L$1048576,$J$28:$J$1048576,">="&$G$7,$H$28:$H$1048576,"Finalizado"),0) -> 4231873.3 | M12: =+IF($G$6="Finalizado",1*SUMIFS(M$28:M$1048576,$J$28:$J$1048576,">="&$G$7,$H$28:$H$1048576,"Finalizado"))+IF($G$6="Todos",1*SUMIFS(M$28:M$1048576,$J$28:$J$1048576,">="&$G$7,$H$28:$H$1048576,"Finalizado"),0) -> 4215473.8 | N12: =+IFERROR(O12/K12,0) -> 0.13562587 | O12: =+IF($G$6="Finalizado",1*SUMIFS(O$28:O$1048576,$J$28:$J$1048576,">="&$G$7,$H$28:$H$1048576,"Finalizado"))+IF($G$6="Todos",1*SUMIFS(O$28:O$1048576,$J$28:$J$1048576,">="&$G$7,$H$28:$H$1048576,"Finalizado"),0) -> 661435.02 | P12: =+IF($G$6="Finalizado",1*SUMIFS(P$28:P$1048576,$J$28:$J$1048576,">="&$G$7,$H$28:$H$1048576,"Finalizado"))+IF($G$6="Todos",1*SUMIFS(P$28:P$1048576,$J$28:$J$1048576,">="&$G$7,$H$28:$H$1048576,"Finalizado"),0) -> 318273.26 | Q12: =+IF($G$6="Finalizado",1*SUMIFS(Q$28:Q$1048576,$J$28:$J$1048576,">="&$G$7,$H$28:$H$1048576,"Finalizado"))+IF($G$6="Todos",1*SUMIFS(Q$28:Q$1048576,$J$28:$J$1048576,">="&$G$7,$H$28:$H$1048576,"Finalizado"),0) -> 283046 | R12: =+IF($G$6="Finalizado",1*SUMIFS(R$28:R$1048576,$J$28:$J$1048576,">="&$G$7,$H$28:$H$1048576,"Finalizado"))+IF($G$6="Todos",1*SUMIFS(R$28:R$1048576,$J$28:$J$1048576,">="&$G$7,$H$28:$H$1048576,"Finalizado"),0) -> 413939.8 | S12: =+IF($G$6="Finalizado",1*SUMIFS(S$28:S$1048576,$J$28:$J$1048576,">="&$G$7,$H$28:$H$1048576,"Finalizado"))+IF($G$6="Todos",1*SUMIFS(S$28:S$1048576,$J$28:$J$1048576,">="&$G$7,$H$28:$H$1048576,"Finalizado"),0) -> 484279.48 | T12: =+IF($G$6="Finalizado",1*SUMIFS(T$28:T$1048576,$J$28:$J$1048576,">="&$G$7,$H$28:$H$1048576,"Finalizado"))+IF($G$6="Todos",1*SUMIFS(T$28:T$1048576,$J$28:$J$1048576,">="&$G$7,$H$28:$H$1048576,"Finalizado"),0) -> 386090.4 | U12: =+IF($G$6="Finalizado",1*SUMIFS(U$28:U$1048576,$J$28:$J$1048576,">="&$G$7,$H$28:$H$1048576,"Finalizado"))+IF($G$6="Todos",1*SUMIFS(U$28:U$1048576,$J$28:$J$1048576,">="&$G$7,$H$28:$H$1048576,"Finalizado"),0) -> 668444.7 | V12: =+IF($G$6="Finalizado",1*SUMIFS(V$28:V$1048576,$J$28:$J$1048576,">="&$G$7,$H$28:$H$1048576,"Finalizado"))+IF($G$6="Todos",1*SUMIFS(V$28:V$1048576,$J$28:$J$1048576,">="&$G$7,$H$28:$H$1048576,"Finalizado"),0) -> 407495.92 | ... AM12: =+IF($G$6="Finalizado",1*SUMIFS(AM$28:AM$1048576,$J$28:$J$1048576,">="&$G$7,$H$28:$H$1048576,"Finalizado"))+IF($G$6="Todos",1*SUMIFS(AM$28:AM$1048576,$J$28:$J$1048576,">="&$G$7,$H$28:$H$1048576,"Finalizado"),0) -> 0 | BO12: AMSA | BP12: =+SUM(BQ12:CB12) -> 534055 | BQ12: =+IF($G$6="En Ejecución",1*SUMIFS(P$28:P$1048576,$J$28:$J$1048576,">="&$G$7,$G$28:$G$1048576,$BO12,$H$28:$H$1048576,$G$6),0)+IF($G$6="Pipeline",1*SUMIFS(P$28:P$1048576,$J$28:$J$1048576,">="&$G$7,$G$28:$G$1048576,$BO12,$H$28:$H$1048576,$G$6),0)+IF($G$6="Todos",1*SUMIFS(P$28:P$1048576,$J$28:$J$1048576,">="&$G$7,$G$28:$G$1048576,$BO12),0)+IF($G$6="Finalizado",1*SUMIFS(P$28:P$1048576,$J$28:$J$1048576,">="&$G$7,$G$28:$G$1048576,$BO12,$H$28:$H$1048576,$G$6),0) -> 101539 | BR12: =+IF($G$6="En Ejecución",1*SUMIFS(Q$28:Q$1048576,$J$28:$J$1048576,">="&$G$7,$G$28:$G$1048576,$BO12,$H$28:$H$1048576,$G$6),0)+IF($G$6="Pipeline",1*SUMIFS(Q$28:Q$1048576,$J$28:$J$1048576,">="&$G$7,$G$28:$G$1048576,$BO12,$H$28:$H$1048576,$G$6),0)+IF($G$6="Todos",1*SUMIFS(Q$28:Q$1048576,$J$28:$J$1048576,">="&$G$7,$G$28:$G$1048576,$BO12),0)+IF($G$6="Finalizado",1*SUMIFS(Q$28:Q$1048576,$J$28:$J$1048576,">="&$G$7,$G$28:$G$1048576,$BO12,$H$28:$H$1048576,$G$6),0) -> 0 | BS12: =+IF($G$6="En Ejecución",1*SUMIFS(R$28:R$1048576,$J$28:$J$1048576,">="&$G$7,$G$28:$G$1048576,$BO12,$H$28:$H$1048576,$G$6),0)+IF($G$6="Pipeline",1*SUMIFS(R$28:R$1048576,$J$28:$J$1048576,">="&$G$7,$G$28:$G$1048576,$BO12,$H$28:$H$1048576,$G$6),0)+IF($G$6="Todos",1*SUMIFS(R$28:R$1048576,$J$28:$J$1048576,">="&$G$7,$G$28:$G$1048576,$BO12),0)+IF($G$6="Finalizado",1*SUMIFS(R$28:R$1048576,$J$28:$J$1048576,">="&$G$7,$G$28:$G$1048576,$BO12,$H$28:$H$1048576,$G$6),0) -> 44246 | BT12: =+IF($G$6="En Ejecución",1*SUMIFS(S$28:S$1048576,$J$28:$J$1048576,">="&$G$7,$G$28:$G$1048576,$BO12,$H$28:$H$1048576,$G$6),0)+IF($G$6="Pipeline",1*SUMIFS(S$28:S$1048576,$J$28:$J$1048576,">="&$G$7,$G$28:$G$1048576,$BO12,$H$28:$H$1048576,$G$6),0)+IF($G$6="Todos",1*SUMIFS(S$28:S$1048576,$J$28:$J$1048576,">="&$G$7,$G$28:$G$1048576,$BO12),0)+IF($G$6="Finalizado",1*SUMIFS(S$28:S$1048576,$J$28:$J$1048576,">="&$G$7,$G$28:$G$1048576,$BO12,$H$28:$H$1048576,$G$6),0) -> 81731 | BU12: =+IF($G$6="En Ejecución",1*SUMIFS(T$28:T$1048576,$J$28:$J$1048576,">="&$G$7,$G$28:$G$1048576,$BO12,$H$28:$H$1048576,$G$6),0)+IF($G$6="Pipeline",1*SUMIFS(T$28:T$1048576,$J$28:$J$1048576,">="&$G$7,$G$28:$G$1048576,$BO12,$H$28:$H$1048576,$G$6),0)+IF($G$6="Todos",1*SUMIFS(T$28:T$1048576,$J$28:$J$1048576,">="&$G$7,$G$28:$G$1048576,$BO12),0)+IF($G$6="Finalizado",1*SUMIFS(T$28:T$1048576,$J$28:$J$1048576,">="&$G$7,$G$28:$G$1048576,$BO12,$H$28:$H$1048576,$G$6),0) -> 0 | BV12: =+IF($G$6="En Ejecución",1*SUMIFS(U$28:U$1048576,$J$28:$J$1048576,">="&$G$7,$G$28:$G$1048576,$BO12,$H$28:$H$1048576,$G$6),0)+IF($G$6="Pipeline",1*SUMIFS(U$28:U$1048576,$J$28:$J$1048576,">="&$G$7,$G$28:$G$1048576,$BO12,$H$28:$H$1048576,$G$6),0)+IF($G$6="Todos",1*SUMIFS(U$28:U$1048576,$J$28:$J$1048576,">="&$G$7,$G$28:$G$1048576,$BO12),0)+IF($G$6="Finalizado",1*SUMIFS(U$28:U$1048576,$J$28:$J$1048576,">="&$G$7,$G$28:$G$1048576,$BO12,$H$28:$H$1048576,$G$6),0) -> 55498 | BW12: =+IF($G$6="En Ejecución",1*SUMIFS(V$28:V$1048576,$J$28:$J$1048576,">="&$G$7,$G$28:$G$1048576,$BO12,$H$28:$H$1048576,$G$6),0)+IF($G$6="Pipeline",1*SUMIFS(V$28:V$1048576,$J$28:$J$1048576,">="&$G$7,$G$28:$G$1048576,$BO12,$H$28:$H$1048576,$G$6),0)+IF($G$6="Todos",1*SUMIFS(V$28:V$1048576,$J$28:$J$1048576,">="&$G$7,$G$28:$G$1048576,$BO12),0)+IF($G$6="Finalizado",1*SUMIFS(V$28:V$1048576,$J$28:$J$1048576,">="&$G$7,$G$28:$G$1048576,$BO12,$H$28:$H$1048576,$G$6),0) -> 44745 | BX12: =+IF($G$6="En Ejecución",1*SUMIFS(W$28:W$1048576,$J$28:$J$1048576,">="&$G$7,$G$28:$G$1048576,$BO12,$H$28:$H$1048576,$G$6),0)+IF($G$6="Pipeline",1*SUMIFS(W$28:W$1048576,$J$28:$J$1048576,">="&$G$7,$G$28:$G$1048576,$BO12,$H$28:$H$1048576,$G$6),0)+IF($G$6="Todos",1*SUMIFS(W$28:W$1048576,$J$28:$J$1048576,">="&$G$7,$G$28:$G$1048576,$BO12),0)+IF($G$6="Finalizado",1*SUMIFS(W$28:W$1048576,$J$28:$J$1048576,">="&$G$7,$G$28:$G$1048576,$BO12,$H$28:$H$1048576,$G$6),0) -> 10549 | ... CB12: =+IF($G$6="En Ejecución",1*SUMIFS(AA$28:AA$1048576,$J$28:$J$1048576,">="&$G$7,$G$28:$G$1048576,$BO12,$H$28:$H$1048576,$G$6),0)+IF($G$6="Pipeline",1*SUMIFS(AA$28:AA$1048576,$J$28:$J$1048576,">="&$G$7,$G$28:$G$1048576,$BO12,$H$28:$H$1048576,$G$6),0)+IF($G$6="Todos",1*SUMIFS(AA$28:AA$1048576,$J$28:$J$1048576,">="&$G$7,$G$28:$G$1048576,$BO12),0)+IF($G$6="Finalizado",1*SUMIFS(AA$28:AA$1048576,$J$28:$J$1048576,">="&$G$7,$G$28:$G$1048576,$BO12,$H$28:$H$1048576,$G$6),0) -> 60311
D13: Total En Ejecución | E13: Total En Ejecución | F13: En Ejecución | G13: =+F13 -> En Ejecución | H13: En Ejecución | I13: En Ejecución | J13: 1 | K13: =+K11-K14-K12 -> 4841042 | L13: =+L11-L14-L12 -> 1425556 | M13: =+M11-M14-M12 -> 840766 | N13: =+IFERROR(O13/K13,0) -> 0.82632541 | O13: =+O11-O14-O12 -> 4000276 | P13: =+P11-P14-P12 -> 0 | Q13: =+Q11-Q14-Q12 -> 85502 | R13: =+R11-R14-R12 -> 91931 | S13: =+S11-S14-S12 -> 74275 | T13: =+T11-T14-T12 -> 56675 | U13: =+U11-U14-U12 -> 90591 | V13: =+V11-V14-V12 -> 94263 | ... AM13: =+AM11-AM14-AM12 -> 0 | BO13: Minsur | BP13: =+SUM(BQ13:CB13) -> 1079366.4 | BQ13: =+IF($G$6="En Ejecución",1*SUMIFS(P$28:P$1048576,$J$28:$J$1048576,">="&$G$7,$G$28:$G$1048576,$BO13,$H$28:$H$1048576,$G$6),0)+IF($G$6="Pipeline",1*SUMIFS(P$28:P$1048576,$J$28:$J$1048576,">="&$G$7,$G$28:$G$1048576,$BO13,$H$28:$H$1048576,$G$6),0)+IF($G$6="Todos",1*SUMIFS(P$28:P$1048576,$J$28:$J$1048576,">="&$G$7,$G$28:$G$1048576,$BO13),0)+IF($G$6="Finalizado",1*SUMIFS(P$28:P$1048576,$J$28:$J$1048576,">="&$G$7,$G$28:$G$1048576,$BO13,$H$28:$H$1048576,$G$6),0) -> 49915 | BR13: =+IF($G$6="En Ejecución",1*SUMIFS(Q$28:Q$1048576,$J$28:$J$1048576,">="&$G$7,$G$28:$G$1048576,$BO13,$H$28:$H$1048576,$G$6),0)+IF($G$6="Pipeline",1*SUMIFS(Q$28:Q$1048576,$J$28:$J$1048576,">="&$G$7,$G$28:$G$1048576,$BO13,$H$28:$H$1048576,$G$6),0)+IF($G$6="Todos",1*SUMIFS(Q$28:Q$1048576,$J$28:$J$1048576,">="&$G$7,$G$28:$G$1048576,$BO13),0)+IF($G$6="Finalizado",1*SUMIFS(Q$28:Q$1048576,$J$28:$J$1048576,">="&$G$7,$G$28:$G$1048576,$BO13,$H$28:$H$1048576,$G$6),0) -> 70329 | BS13: =+IF($G$6="En Ejecución",1*SUMIFS(R$28:R$1048576,$J$28:$J$1048576,">="&$G$7,$G$28:$G$1048576,$BO13,$H$28:$H$1048576,$G$6),0)+IF($G$6="Pipeline",1*SUMIFS(R$28:R$1048576,$J$28:$J$1048576,">="&$G$7,$G$28:$G$1048576,$BO13,$H$28:$H$1048576,$G$6),0)+IF($G$6="Todos",1*SUMIFS(R$28:R$1048576,$J$28:$J$1048576,">="&$G$7,$G$28:$G$1048576,$BO13),0)+IF($G$6="Finalizado",1*SUMIFS(R$28:R$1048576,$J$28:$J$1048576,">="&$G$7,$G$28:$G$1048576,$BO13,$H$28:$H$1048576,$G$6),0) -> 19250.8 | BT13: =+IF($G$6="En Ejecución",1*SUMIFS(S$28:S$1048576,$J$28:$J$1048576,">="&$G$7,$G$28:$G$1048576,$BO13,$H$28:$H$1048576,$G$6),0)+IF($G$6="Pipeline",1*SUMIFS(S$28:S$1048576,$J$28:$J$1048576,">="&$G$7,$G$28:$G$1048576,$BO13,$H$28:$H$1048576,$G$6),0)+IF($G$6="Todos",1*SUMIFS(S$28:S$1048576,$J$28:$J$1048576,">="&$G$7,$G$28:$G$1048576,$BO13),0)+IF($G$6="Finalizado",1*SUMIFS(S$28:S$1048576,$J$28:$J$1048576,">="&$G$7,$G$28:$G$1048576,$BO13,$H$28:$H$1048576,$G$6),0) -> 138426.07 | BU13: =+IF($G$6="En Ejecución",1*SUMIFS(T$28:T$1048576,$J$28:$J$1048576,">="&$G$7,$G$28:$G$1048576,$BO13,$H$28:$H$1048576,$G$6),0)+IF($G$6="Pipeline",1*SUMIFS(T$28:T$1048576,$J$28:$J$1048576,">="&$G$7,$G$28:$G$1048576,$BO13,$H$28:$H$1048576,$G$6),0)+IF($G$6="Todos",1*SUMIFS(T$28:T$1048576,$J$28:$J$1048576,">="&$G$7,$G$28:$G$1048576,$BO13),0)+IF($G$6="Finalizado",1*SUMIFS(T$28:T$1048576,$J$28:$J$1048576,">="&$G$7,$G$28:$G$1048576,$BO13,$H$28:$H$1048576,$G$6),0) -> 228228.4 | BV13: =+IF($G$6="En Ejecución",1*SUMIFS(U$28:U$1048576,$J$28:$J$1048576,">="&$G$7,$G$28:$G$1048576,$BO13,$H$28:$H$1048576,$G$6),0)+IF($G$6="Pipeline",1*SUMIFS(U$28:U$1048576,$J$28:$J$1048576,">="&$G$7,$G$28:$G$1048576,$BO13,$H$28:$H$1048576,$G$6),0)+IF($G$6="Todos",1*SUMIFS(U$28:U$1048576,$J$28:$J$1048576,">="&$G$7,$G$28:$G$1048576,$BO13),0)+IF($G$6="Finalizado",1*SUMIFS(U$28:U$1048576,$J$28:$J$1048576,">="&$G$7,$G$28:$G$1048576,$BO13,$H$28:$H$1048576,$G$6),0) -> 138944.25 | BW13: =+IF($G$6="En Ejecución",1*SUMIFS(V$28:V$1048576,$J$28:$J$1048576,">="&$G$7,$G$28:$G$1048576,$BO13,$H$28:$H$1048576,$G$6),0)+IF($G$6="Pipeline",1*SUMIFS(V$28:V$1048576,$J$28:$J$1048576,">="&$G$7,$G$28:$G$1048576,$BO13,$H$28:$H$1048576,$G$6),0)+IF($G$6="Todos",1*SUMIFS(V$28:V$1048576,$J$28:$J$1048576,">="&$G$7,$G$28:$G$1048576,$BO13),0)+IF($G$6="Finalizado",1*SUMIFS(V$28:V$1048576,$J$28:$J$1048576,">="&$G$7,$G$28:$G$1048576,$BO13,$H$28:$H$1048576,$G$6),0) -> 67365.175 | BX13: =+IF($G$6="En Ejecución",1*SUMIFS(W$28:W$1048576,$J$28:$J$1048576,">="&$G$7,$G$28:$G$1048576,$BO13,$H$28:$H$1048576,$G$6),0)+IF($G$6="Pipeline",1*SUMIFS(W$28:W$1048576,$J$28:$J$1048576,">="&$G$7,$G$28:$G$1048576,$BO13,$H$28:$H$1048576,$G$6),0)+IF($G$6="Todos",1*SUMIFS(W$28:W$1048576,$J$28:$J$1048576,">="&$G$7,$G$28:$G$1048576,$BO13),0)+IF($G$6="Finalizado",1*SUMIFS(W$28:W$1048576,$J$28:$J$1048576,">="&$G$7,$G$28:$G$1048576,$BO13,$H$28:$H$1048576,$G$6),0) -> 79564.69 | ... CB13: =+IF($G$6="En Ejecución",1*SUMIFS(AA$28:AA$1048576,$J$28:$J$1048576,">="&$G$7,$G$28:$G$1048576,$BO13,$H$28:$H$1048576,$G$6),0)+IF($G$6="Pipeline",1*SUMIFS(AA$28:AA$1048576,$J$28:$J$1048576,">="&$G$7,$G$28:$G$1048576,$BO13,$H$28:$H$1048576,$G$6),0)+IF($G$6="Todos",1*SUMIFS(AA$28:AA$1048576,$J$28:$J$1048576,">="&$G$7,$G$28:$G$1048576,$BO13),0)+IF($G$6="Finalizado",1*SUMIFS(AA$28:AA$1048576,$J$28:$J$1048576,">="&$G$7,$G$28:$G$1048576,$BO13,$H$28:$H$1048576,$G$6),0) -> 32480
D14: Total Pipeline | E14: Total Pipeline | F14: Pipeline | G14: =+F14 -> Pipeline | H14: Pipeline | I14: Pipeline | J14: =+G7 -> 1 | K14: =+IF($G$6="Pipeline",1*SUMIFS(K$28:K$1048576,$J$28:$J$1048576,">="&$G$7,$H$28:$H$1048576,$G$6),0)+IF($G$6="Todos",1*SUMIFS(K$28:K$1048576,$J$28:$J$1048576,">="&$G$7,$H$28:$H$1048576,"Pipeline")) -> 0 | L14: =+IF($G$6="Pipeline",1*SUMIFS(L$28:L$1048576,$J$28:$J$1048576,">="&$G$7,$H$28:$H$1048576,$G$6),0)+IF($G$6="Todos",1*SUMIFS(L$28:L$1048576,$J$28:$J$1048576,">="&$G$7,$H$28:$H$1048576,"Pipeline")) -> 0 | M14: =+IF($G$6="Pipeline",1*SUMIFS(M$28:M$1048576,$J$28:$J$1048576,">="&$G$7,$H$28:$H$1048576,$G$6),0)+IF($G$6="Todos",1*SUMIFS(M$28:M$1048576,$J$28:$J$1048576,">="&$G$7,$H$28:$H$1048576,"Pipeline")) -> 0 | N14: =+IFERROR(O14/K14,0) -> 0 | O14: =+IF($G$6="Pipeline",1*SUMIFS(O$28:O$1048576,$J$28:$J$1048576,">="&$G$7,$H$28:$H$1048576,$G$6),0)+IF($G$6="Todos",1*SUMIFS(O$28:O$1048576,$J$28:$J$1048576,">="&$G$7,$H$28:$H$1048576,"Pipeline")) -> 0 | P14: =+IF($G$6="Pipeline",1*SUMIFS(P$28:P$1048576,$J$28:$J$1048576,">="&$G$7,$H$28:$H$1048576,$G$6),0)+IF($G$6="Todos",1*SUMIFS(P$28:P$1048576,$J$28:$J$1048576,">="&$G$7,$H$28:$H$1048576,"Pipeline")) -> 0 | Q14: =+IF($G$6="Pipeline",1*SUMIFS(Q$28:Q$1048576,$J$28:$J$1048576,">="&$G$7,$H$28:$H$1048576,$G$6),0)+IF($G$6="Todos",1*SUMIFS(Q$28:Q$1048576,$J$28:$J$1048576,">="&$G$7,$H$28:$H$1048576,"Pipeline")) -> 0 | R14: =+IF($G$6="Pipeline",1*SUMIFS(R$28:R$1048576,$J$28:$J$1048576,">="&$G$7,$H$28:$H$1048576,$G$6),0)+IF($G$6="Todos",1*SUMIFS(R$28:R$1048576,$J$28:$J$1048576,">="&$G$7,$H$28:$H$1048576,"Pipeline")) -> 0 | S14: =+IF($G$6="Pipeline",1*SUMIFS(S$28:S$1048576,$J$28:$J$1048576,">="&$G$7,$H$28:$H$1048576,$G$6),0)+IF($G$6="Todos",1*SUMIFS(S$28:S$1048576,$J$28:$J$1048576,">="&$G$7,$H$28:$H$1048576,"Pipeline")) -> 0 | T14: =+IF($G$6="Pipeline",1*SUMIFS(T$28:T$1048576,$J$28:$J$1048576,">="&$G$7,$H$28:$H$1048576,$G$6),0)+IF($G$6="Todos",1*SUMIFS(T$28:T$1048576,$J$28:$J$1048576,">="&$G$7,$H$28:$H$1048576,"Pipeline")) -> 0 | U14: =+IF($G$6="Pipeline",1*SUMIFS(U$28:U$1048576,$J$28:$J$1048576,">="&$G$7,$H$28:$H$1048576,$G$6),0)+IF($G$6="Todos",1*SUMIFS(U$28:U$1048576,$J$28:$J$1048576,">="&$G$7,$H$28:$H$1048576,"Pipeline")) -> 0 | V14: =+IF($G$6="Pipeline",1*SUMIFS(V$28:V$1048576,$J$28:$J$1048576,">="&$G$7,$H$28:$H$1048576,$G$6),0)+IF($G$6="Todos",1*SUMIFS(V$28:V$1048576,$J$28:$J$1048576,">="&$G$7,$H$28:$H$1048576,"Pipeline")) -> 0 | ... AM14: =+IF($G$6="Pipeline",1*SUMIFS(AM$28:AM$1048576,$J$28:$J$1048576,">="&$G$7,$H$28:$H$1048576,$G$6),0)+IF($G$6="Todos",1*SUMIFS(AM$28:AM$1048576,$J$28:$J$1048576,">="&$G$7,$H$28:$H$1048576,"Pipeline")) -> 0 | BO14: Mosaic | BP14: =+SUM(BQ14:CB14) -> 230128 | BQ14: =+IF($G$6="En Ejecución",1*SUMIFS(P$28:P$1048576,$J$28:$J$1048576,">="&$G$7,$G$28:$G$1048576,$BO14,$H$28:$H$1048576,$G$6),0)+IF($G$6="Pipeline",1*SUMIFS(P$28:P$1048576,$J$28:$J$1048576,">="&$G$7,$G$28:$G$1048576,$BO14,$H$28:$H$1048576,$G$6),0)+IF($G$6="Todos",1*SUMIFS(P$28:P$1048576,$J$28:$J$1048576,">="&$G$7,$G$28:$G$1048576,$BO14),0)+IF($G$6="Finalizado",1*SUMIFS(P$28:P$1048576,$J$28:$J$1048576,">="&$G$7,$G$28:$G$1048576,$BO14,$H$28:$H$1048576,$G$6),0) -> 0 | BR14: =+IF($G$6="En Ejecución",1*SUMIFS(Q$28:Q$1048576,$J$28:$J$1048576,">="&$G$7,$G$28:$G$1048576,$BO14,$H$28:$H$1048576,$G$6),0)+IF($G$6="Pipeline",1*SUMIFS(Q$28:Q$1048576,$J$28:$J$1048576,">="&$G$7,$G$28:$G$1048576,$BO14,$H$28:$H$1048576,$G$6),0)+IF($G$6="Todos",1*SUMIFS(Q$28:Q$1048576,$J$28:$J$1048576,">="&$G$7,$G$28:$G$1048576,$BO14),0)+IF($G$6="Finalizado",1*SUMIFS(Q$28:Q$1048576,$J$28:$J$1048576,">="&$G$7,$G$28:$G$1048576,$BO14,$H$28:$H$1048576,$G$6),0) -> 0 | BS14: =+IF($G$6="En Ejecución",1*SUMIFS(R$28:R$1048576,$J$28:$J$1048576,">="&$G$7,$G$28:$G$1048576,$BO14,$H$28:$H$1048576,$G$6),0)+IF($G$6="Pipeline",1*SUMIFS(R$28:R$1048576,$J$28:$J$1048576,">="&$G$7,$G$28:$G$1048576,$BO14,$H$28:$H$1048576,$G$6),0)+IF($G$6="Todos",1*SUMIFS(R$28:R$1048576,$J$28:$J$1048576,">="&$G$7,$G$28:$G$1048576,$BO14),0)+IF($G$6="Finalizado",1*SUMIFS(R$28:R$1048576,$J$28:$J$1048576,">="&$G$7,$G$28:$G$1048576,$BO14,$H$28:$H$1048576,$G$6),0) -> 0 | BT14: =+IF($G$6="En Ejecución",1*SUMIFS(S$28:S$1048576,$J$28:$J$1048576,">="&$G$7,$G$28:$G$1048576,$BO14,$H$28:$H$1048576,$G$6),0)+IF($G$6="Pipeline",1*SUMIFS(S$28:S$1048576,$J$28:$J$1048576,">="&$G$7,$G$28:$G$1048576,$BO14,$H$28:$H$1048576,$G$6),0)+IF($G$6="Todos",1*SUMIFS(S$28:S$1048576,$J$28:$J$1048576,">="&$G$7,$G$28:$G$1048576,$BO14),0)+IF($G$6="Finalizado",1*SUMIFS(S$28:S$1048576,$J$28:$J$1048576,">="&$G$7,$G$28:$G$1048576,$BO14,$H$28:$H$1048576,$G$6),0) -> 0 | BU14: =+IF($G$6="En Ejecución",1*SUMIFS(T$28:T$1048576,$J$28:$J$1048576,">="&$G$7,$G$28:$G$1048576,$BO14,$H$28:$H$1048576,$G$6),0)+IF($G$6="Pipeline",1*SUMIFS(T$28:T$1048576,$J$28:$J$1048576,">="&$G$7,$G$28:$G$1048576,$BO14,$H$28:$H$1048576,$G$6),0)+IF($G$6="Todos",1*SUMIFS(T$28:T$1048576,$J$28:$J$1048576,">="&$G$7,$G$28:$G$1048576,$BO14),0)+IF($G$6="Finalizado",1*SUMIFS(T$28:T$1048576,$J$28:$J$1048576,">="&$G$7,$G$28:$G$1048576,$BO14,$H$28:$H$1048576,$G$6),0) -> 0 | BV14: =+IF($G$6="En Ejecución",1*SUMIFS(U$28:U$1048576,$J$28:$J$1048576,">="&$G$7,$G$28:$G$1048576,$BO14,$H$28:$H$1048576,$G$6),0)+IF($G$6="Pipeline",1*SUMIFS(U$28:U$1048576,$J$28:$J$1048576,">="&$G$7,$G$28:$G$1048576,$BO14,$H$28:$H$1048576,$G$6),0)+IF($G$6="Todos",1*SUMIFS(U$28:U$1048576,$J$28:$J$1048576,">="&$G$7,$G$28:$G$1048576,$BO14),0)+IF($G$6="Finalizado",1*SUMIFS(U$28:U$1048576,$J$28:$J$1048576,">="&$G$7,$G$28:$G$1048576,$BO14,$H$28:$H$1048576,$G$6),0) -> 0 | BW14: =+IF($G$6="En Ejecución",1*SUMIFS(V$28:V$1048576,$J$28:$J$1048576,">="&$G$7,$G$28:$G$1048576,$BO14,$H$28:$H$1048576,$G$6),0)+IF($G$6="Pipeline",1*SUMIFS(V$28:V$1048576,$J$28:$J$1048576,">="&$G$7,$G$28:$G$1048576,$BO14,$H$28:$H$1048576,$G$6),0)+IF($G$6="Todos",1*SUMIFS(V$28:V$1048576,$J$28:$J$1048576,">="&$G$7,$G$28:$G$1048576,$BO14),0)+IF($G$6="Finalizado",1*SUMIFS(V$28:V$1048576,$J$28:$J$1048576,">="&$G$7,$G$28:$G$1048576,$BO14,$H$28:$H$1048576,$G$6),0) -> 70821 | BX14: =+IF($G$6="En Ejecución",1*SUMIFS(W$28:W$1048576,$J$28:$J$1048576,">="&$G$7,$G$28:$G$1048576,$BO14,$H$28:$H$1048576,$G$6),0)+IF($G$6="Pipeline",1*SUMIFS(W$28:W$1048576,$J$28:$J$1048576,">="&$G$7,$G$28:$G$1048576,$BO14,$H$28:$H$1048576,$G$6),0)+IF($G$6="Todos",1*SUMIFS(W$28:W$1048576,$J$28:$J$1048576,">="&$G$7,$G$28:$G$1048576,$BO14),0)+IF($G$6="Finalizado",1*SUMIFS(W$28:W$1048576,$J$28:$J$1048576,">="&$G$7,$G$28:$G$1048576,$BO14,$H$28:$H$1048576,$G$6),0) -> 15596 | ... CB14: =+IF($G$6="En Ejecución",1*SUMIFS(AA$28:AA$1048576,$J$28:$J$1048576,">="&$G$7,$G$28:$G$1048576,$BO14,$H$28:$H$1048576,$G$6),0)+IF($G$6="Pipeline",1*SUMIFS(AA$28:AA$1048576,$J$28:$J$1048576,">="&$G$7,$G$28:$G$1048576,$BO14,$H$28:$H$1048576,$G$6),0)+IF($G$6="Todos",1*SUMIFS(AA$28:AA$1048576,$J$28:$J$1048576,">="&$G$7,$G$28:$G$1048576,$BO14),0)+IF($G$6="Finalizado",1*SUMIFS(AA$28:AA$1048576,$J$28:$J$1048576,">="&$G$7,$G$28:$G$1048576,$BO14,$H$28:$H$1048576,$G$6),0) -> 63373
D15: Chile | E15: Chile | F15: =+$G$6 -> Todos | G15: =+F15 -> Todos | H15: =+$G$6 -> Todos | I15: =+H15 -> Todos | J15: =+$G$7 -> 1 | K15: =+IF($G$6="En Ejecución",1*SUMIFS(K$28:K$1048576,$J$28:$J$1048576,">="&$G$7,$D$28:$D$1048576,$D15,$H$28:$H$1048576,$G$6),0)+IF($G$6="Pipeline",1*SUMIFS(K$28:K$1048576,$J$28:$J$1048576,">="&$G$7,$D$28:$D$1048576,$D15,$H$28:$H$1048576,$G$6),0)+IF($G$6="Todos",1*SUMIFS(K$28:K$1048576,$J$28:$J$1048576,">="&$G$7,$D$28:$D$1048576,$D15),0)+IF($G$6="Finalizado",1*SUMIFS(K$28:K$1048576,$J$28:$J$1048576,">="&$G$7,$D$28:$D$1048576,$D15,$H$28:$H$1048576,$G$6),0) -> 5621730.7 | L15: =+IF($G$6="En Ejecución",1*SUMIFS(L$28:L$1048576,$J$28:$J$1048576,">="&$G$7,$D$28:$D$1048576,$D15,$H$28:$H$1048576,$G$6),0)+IF($G$6="Pipeline",1*SUMIFS(L$28:L$1048576,$J$28:$J$1048576,">="&$G$7,$D$28:$D$1048576,$D15,$H$28:$H$1048576,$G$6),0)+IF($G$6="Todos",1*SUMIFS(L$28:L$1048576,$J$28:$J$1048576,">="&$G$7,$D$28:$D$1048576,$D15),0)+IF($G$6="Finalizado",1*SUMIFS(L$28:L$1048576,$J$28:$J$1048576,">="&$G$7,$D$28:$D$1048576,$D15,$H$28:$H$1048576,$G$6),0) -> 3751213 | M15: =+IF($G$6="En Ejecución",1*SUMIFS(M$28:M$1048576,$J$28:$J$1048576,">="&$G$7,$D$28:$D$1048576,$D15,$H$28:$H$1048576,$G$6),0)+IF($G$6="Pipeline",1*SUMIFS(M$28:M$1048576,$J$28:$J$1048576,">="&$G$7,$D$28:$D$1048576,$D15,$H$28:$H$1048576,$G$6),0)+IF($G$6="Todos",1*SUMIFS(M$28:M$1048576,$J$28:$J$1048576,">="&$G$7,$D$28:$D$1048576,$D15),0)+IF($G$6="Finalizado",1*SUMIFS(M$28:M$1048576,$J$28:$J$1048576,">="&$G$7,$D$28:$D$1048576,$D15,$H$28:$H$1048576,$G$6),0) -> 3446244 | N15: =+IFERROR(O15/K15,0) -> 0.38697812 | O15: =+IF($G$6="En Ejecución",1*SUMIFS(O$28:O$1048576,$J$28:$J$1048576,">="&$G$7,$D$28:$D$1048576,$D15,$H$28:$H$1048576,$G$6),0)+IF($G$6="Pipeline",1*SUMIFS(O$28:O$1048576,$J$28:$J$1048576,">="&$G$7,$D$28:$D$1048576,$D15,$H$28:$H$1048576,$G$6),0)+IF($G$6="Todos",1*SUMIFS(O$28:O$1048576,$J$28:$J$1048576,">="&$G$7,$D$28:$D$1048576,$D15),0)+IF($G$6="Finalizado",1*SUMIFS(O$28:O$1048576,$J$28:$J$1048576,">="&$G$7,$D$28:$D$1048576,$D15,$H$28:$H$1048576,$G$6),0) -> 2175486.8 | P15: =+IF($G$6="En Ejecución",1*SUMIFS(P$28:P$1048576,$J$28:$J$1048576,">="&$G$7,$D$28:$D$1048576,$D15,$H$28:$H$1048576,$G$6),0)+IF($G$6="Pipeline",1*SUMIFS(P$28:P$1048576,$J$28:$J$1048576,">="&$G$7,$D$28:$D$1048576,$D15,$H$28:$H$1048576,$G$6),0)+IF($G$6="Todos",1*SUMIFS(P$28:P$1048576,$J$28:$J$1048576,">="&$G$7,$D$28:$D$1048576,$D15),0)+IF($G$6="Finalizado",1*SUMIFS(P$28:P$1048576,$J$28:$J$1048576,">="&$G$7,$D$28:$D$1048576,$D15,$H$28:$H$1048576,$G$6),0) -> 268358.26 | Q15: =+IF($G$6="En Ejecución",1*SUMIFS(Q$28:Q$1048576,$J$28:$J$1048576,">="&$G$7,$D$28:$D$1048576,$D15,$H$28:$H$1048576,$G$6),0)+IF($G$6="Pipeline",1*SUMIFS(Q$28:Q$1048576,$J$28:$J$1048576,">="&$G$7,$D$28:$D$1048576,$D15,$H$28:$H$1048576,$G$6),0)+IF($G$6="Todos",1*SUMIFS(Q$28:Q$1048576,$J$28:$J$1048576,">="&$G$7,$D$28:$D$1048576,$D15),0)+IF($G$6="Finalizado",1*SUMIFS(Q$28:Q$1048576,$J$28:$J$1048576,">="&$G$7,$D$28:$D$1048576,$D15,$H$28:$H$1048576,$G$6),0) -> 283043 | R15: =+IF($G$6="En Ejecución",1*SUMIFS(R$28:R$1048576,$J$28:$J$1048576,">="&$G$7,$D$28:$D$1048576,$D15,$H$28:$H$1048576,$G$6),0)+IF($G$6="Pipeline",1*SUMIFS(R$28:R$1048576,$J$28:$J$1048576,">="&$G$7,$D$28:$D$1048576,$D15,$H$28:$H$1048576,$G$6),0)+IF($G$6="Todos",1*SUMIFS(R$28:R$1048576,$J$28:$J$1048576,">="&$G$7,$D$28:$D$1048576,$D15),0)+IF($G$6="Finalizado",1*SUMIFS(R$28:R$1048576,$J$28:$J$1048576,">="&$G$7,$D$28:$D$1048576,$D15,$H$28:$H$1048576,$G$6),0) -> 467629 | S15: =+IF($G$6="En Ejecución",1*SUMIFS(S$28:S$1048576,$J$28:$J$1048576,">="&$G$7,$D$28:$D$1048576,$D15,$H$28:$H$1048576,$G$6),0)+IF($G$6="Pipeline",1*SUMIFS(S$28:S$1048576,$J$28:$J$1048576,">="&$G$7,$D$28:$D$1048576,$D15,$H$28:$H$1048576,$G$6),0)+IF($G$6="Todos",1*SUMIFS(S$28:S$1048576,$J$28:$J$1048576,">="&$G$7,$D$28:$D$1048576,$D15),0)+IF($G$6="Finalizado",1*SUMIFS(S$28:S$1048576,$J$28:$J$1048576,">="&$G$7,$D$28:$D$1048576,$D15,$H$28:$H$1048576,$G$6),0) -> 420128.41 | T15: =+IF($G$6="En Ejecución",1*SUMIFS(T$28:T$1048576,$J$28:$J$1048576,">="&$G$7,$D$28:$D$1048576,$D15,$H$28:$H$1048576,$G$6),0)+IF($G$6="Pipeline",1*SUMIFS(T$28:T$1048576,$J$28:$J$1048576,">="&$G$7,$D$28:$D$1048576,$D15,$H$28:$H$1048576,$G$6),0)+IF($G$6="Todos",1*SUMIFS(T$28:T$1048576,$J$28:$J$1048576,">="&$G$7,$D$28:$D$1048576,$D15),0)+IF($G$6="Finalizado",1*SUMIFS(T$28:T$1048576,$J$28:$J$1048576,">="&$G$7,$D$28:$D$1048576,$D15,$H$28:$H$1048576,$G$6),0) -> 214537 | U15: =+IF($G$6="En Ejecución",1*SUMIFS(U$28:U$1048576,$J$28:$J$1048576,">="&$G$7,$D$28:$D$1048576,$D15,$H$28:$H$1048576,$G$6),0)+IF($G$6="Pipeline",1*SUMIFS(U$28:U$1048576,$J$28:$J$1048576,">="&$G$7,$D$28:$D$1048576,$D15,$H$28:$H$1048576,$G$6),0)+IF($G$6="Todos",1*SUMIFS(U$28:U$1048576,$J$28:$J$1048576,">="&$G$7,$D$28:$D$1048576,$D15),0)+IF($G$6="Finalizado",1*SUMIFS(U$28:U$1048576,$J$28:$J$1048576,">="&$G$7,$D$28:$D$1048576,$D15,$H$28:$H$1048576,$G$6),0) -> 536950.75 | V15: =+IF($G$6="En Ejecución",1*SUMIFS(V$28:V$1048576,$J$28:$J$1048576,">="&$G$7,$D$28:$D$1048576,$D15,$H$28:$H$1048576,$G$6),0)+IF($G$6="Pipeline",1*SUMIFS(V$28:V$1048576,$J$28:$J$1048576,">="&$G$7,$D$28:$D$1048576,$D15,$H$28:$H$1048576,$G$6),0)+IF($G$6="Todos",1*SUMIFS(V$28:V$1048576,$J$28:$J$1048576,">="&$G$7,$D$28:$D$1048576,$D15),0)+IF($G$6="Finalizado",1*SUMIFS(V$28:V$1048576,$J$28:$J$1048576,">="&$G$7,$D$28:$D$1048576,$D15,$H$28:$H$1048576,$G$6),0) -> 261642 | ... AM15: =+IF($G$6="En Ejecución",1*SUMIFS(AM$28:AM$1048576,$J$28:$J$1048576,">="&$G$7,$D$28:$D$1048576,$D15,$H$28:$H$1048576,$G$6),0)+IF($G$6="Pipeline",1*SUMIFS(AM$28:AM$1048576,$J$28:$J$1048576,">="&$G$7,$D$28:$D$1048576,$D15,$H$28:$H$1048576,$G$6),0)+IF($G$6="Todos",1*SUMIFS(AM$28:AM$1048576,$J$28:$J$1048576,">="&$G$7,$D$28:$D$1048576,$D15),0)+IF($G$6="Finalizado",1*SUMIFS(AM$28:AM$1048576,$J$28:$J$1048576,">="&$G$7,$D$28:$D$1048576,$D15,$H$28:$H$1048576,$G$6),0) -> 0 | BO15: CSH | BP15: =+SUM(BQ15:CB15) -> 0 | BQ15: =+IF($G$6="En Ejecución",1*SUMIFS(P$28:P$1048576,$J$28:$J$1048576,">="&$G$7,$G$28:$G$1048576,$BO15,$H$28:$H$1048576,$G$6),0)+IF($G$6="Pipeline",1*SUMIFS(P$28:P$1048576,$J$28:$J$1048576,">="&$G$7,$G$28:$G$1048576,$BO15,$H$28:$H$1048576,$G$6),0)+IF($G$6="Todos",1*SUMIFS(P$28:P$1048576,$J$28:$J$1048576,">="&$G$7,$G$28:$G$1048576,$BO15),0)+IF($G$6="Finalizado",1*SUMIFS(P$28:P$1048576,$J$28:$J$1048576,">="&$G$7,$G$28:$G$1048576,$BO15,$H$28:$H$1048576,$G$6),0) -> 0 | BR15: =+IF($G$6="En Ejecución",1*SUMIFS(Q$28:Q$1048576,$J$28:$J$1048576,">="&$G$7,$G$28:$G$1048576,$BO15,$H$28:$H$1048576,$G$6),0)+IF($G$6="Pipeline",1*SUMIFS(Q$28:Q$1048576,$J$28:$J$1048576,">="&$G$7,$G$28:$G$1048576,$BO15,$H$28:$H$1048576,$G$6),0)+IF($G$6="Todos",1*SUMIFS(Q$28:Q$1048576,$J$28:$J$1048576,">="&$G$7,$G$28:$G$1048576,$BO15),0)+IF($G$6="Finalizado",1*SUMIFS(Q$28:Q$1048576,$J$28:$J$1048576,">="&$G$7,$G$28:$G$1048576,$BO15,$H$28:$H$1048576,$G$6),0) -> 0 | BS15: =+IF($G$6="En Ejecución",1*SUMIFS(R$28:R$1048576,$J$28:$J$1048576,">="&$G$7,$G$28:$G$1048576,$BO15,$H$28:$H$1048576,$G$6),0)+IF($G$6="Pipeline",1*SUMIFS(R$28:R$1048576,$J$28:$J$1048576,">="&$G$7,$G$28:$G$1048576,$BO15,$H$28:$H$1048576,$G$6),0)+IF($G$6="Todos",1*SUMIFS(R$28:R$1048576,$J$28:$J$1048576,">="&$G$7,$G$28:$G$1048576,$BO15),0)+IF($G$6="Finalizado",1*SUMIFS(R$28:R$1048576,$J$28:$J$1048576,">="&$G$7,$G$28:$G$1048576,$BO15,$H$28:$H$1048576,$G$6),0) -> 0 | BT15: =+IF($G$6="En Ejecución",1*SUMIFS(S$28:S$1048576,$J$28:$J$1048576,">="&$G$7,$G$28:$G$1048576,$BO15,$H$28:$H$1048576,$G$6),0)+IF($G$6="Pipeline",1*SUMIFS(S$28:S$1048576,$J$28:$J$1048576,">="&$G$7,$G$28:$G$1048576,$BO15,$H$28:$H$1048576,$G$6),0)+IF($G$6="Todos",1*SUMIFS(S$28:S$1048576,$J$28:$J$1048576,">="&$G$7,$G$28:$G$1048576,$BO15),0)+IF($G$6="Finalizado",1*SUMIFS(S$28:S$1048576,$J$28:$J$1048576,">="&$G$7,$G$28:$G$1048576,$BO15,$H$28:$H$1048576,$G$6),0) -> 0 | BU15: =+IF($G$6="En Ejecución",1*SUMIFS(T$28:T$1048576,$J$28:$J$1048576,">="&$G$7,$G$28:$G$1048576,$BO15,$H$28:$H$1048576,$G$6),0)+IF($G$6="Pipeline",1*SUMIFS(T$28:T$1048576,$J$28:$J$1048576,">="&$G$7,$G$28:$G$1048576,$BO15,$H$28:$H$1048576,$G$6),0)+IF($G$6="Todos",1*SUMIFS(T$28:T$1048576,$J$28:$J$1048576,">="&$G$7,$G$28:$G$1048576,$BO15),0)+IF($G$6="Finalizado",1*SUMIFS(T$28:T$1048576,$J$28:$J$1048576,">="&$G$7,$G$28:$G$1048576,$BO15,$H$28:$H$1048576,$G$6),0) -> 0 | BV15: =+IF($G$6="En Ejecución",1*SUMIFS(U$28:U$1048576,$J$28:$J$1048576,">="&$G$7,$G$28:$G$1048576,$BO15,$H$28:$H$1048576,$G$6),0)+IF($G$6="Pipeline",1*SUMIFS(U$28:U$1048576,$J$28:$J$1048576,">="&$G$7,$G$28:$G$1048576,$BO15,$H$28:$H$1048576,$G$6),0)+IF($G$6="Todos",1*SUMIFS(U$28:U$1048576,$J$28:$J$1048576,">="&$G$7,$G$28:$G$1048576,$BO15),0)+IF($G$6="Finalizado",1*SUMIFS(U$28:U$1048576,$J$28:$J$1048576,">="&$G$7,$G$28:$G$1048576,$BO15,$H$28:$H$1048576,$G$6),0) -> 0 | BW15: =+IF($G$6="En Ejecución",1*SUMIFS(V$28:V$1048576,$J$28:$J$1048576,">="&$G$7,$G$28:$G$1048576,$BO15,$H$28:$H$1048576,$G$6),0)+IF($G$6="Pipeline",1*SUMIFS(V$28:V$1048576,$J$28:$J$1048576,">="&$G$7,$G$28:$G$1048576,$BO15,$H$28:$H$1048576,$G$6),0)+IF($G$6="Todos",1*SUMIFS(V$28:V$1048576,$J$28:$J$1048576,">="&$G$7,$G$28:$G$1048576,$BO15),0)+IF($G$6="Finalizado",1*SUMIFS(V$28:V$1048576,$J$28:$J$1048576,">="&$G$7,$G$28:$G$1048576,$BO15,$H$28:$H$1048576,$G$6),0) -> 0 | BX15: =+IF($G$6="En Ejecución",1*SUMIFS(W$28:W$1048576,$J$28:$J$1048576,">="&$G$7,$G$28:$G$1048576,$BO15,$H$28:$H$1048576,$G$6),0)+IF($G$6="Pipeline",1*SUMIFS(W$28:W$1048576,$J$28:$J$1048576,">="&$G$7,$G$28:$G$1048576,$BO15,$H$28:$H$1048576,$G$6),0)+IF($G$6="Todos",1*SUMIFS(W$28:W$1048576,$J$28:$J$1048576,">="&$G$7,$G$28:$G$1048576,$BO15),0)+IF($G$6="Finalizado",1*SUMIFS(W$28:W$1048576,$J$28:$J$1048576,">="&$G$7,$G$28:$G$1048576,$BO15,$H$28:$H$1048576,$G$6),0) -> 0 | ... CB15: =+IF($G$6="En Ejecución",1*SUMIFS(AA$28:AA$1048576,$J$28:$J$1048576,">="&$G$7,$G$28:$G$1048576,$BO15,$H$28:$H$1048576,$G$6),0)+IF($G$6="Pipeline",1*SUMIFS(AA$28:AA$1048576,$J$28:$J$1048576,">="&$G$7,$G$28:$G$1048576,$BO15,$H$28:$H$1048576,$G$6),0)+IF($G$6="Todos",1*SUMIFS(AA$28:AA$1048576,$J$28:$J$1048576,">="&$G$7,$G$28:$G$1048576,$BO15),0)+IF($G$6="Finalizado",1*SUMIFS(AA$28:AA$1048576,$J$28:$J$1048576,">="&$G$7,$G$28:$G$1048576,$BO15,$H$28:$H$1048576,$G$6),0) -> 0
