Workbook

Sheet CRM
A1: ID | B1: País | C1: Descripcion Oportunidad | D1: Empresa | E1: Mina | F1: Tipo de Estudio | G1: Gestor Comercial | H1: Monto (USD) | I1: Modulos | J1: Duracion (meses) | K1: USD/mes | L1: Tipo Cliente | M1: Tipo de Minería | N1: Forma de Venta | O1: Etapa | P1: Fecha de Envío | Q1: Semana de Adjudicación | R1: Motivo de No Adjudicación | S1: Comentarios | T1: Contacto Clave | U1: Ultima Acción Comprometida | V1: Status
A2: 1 | B2: Perú | C2: Diagnostico operaciónal y construcción de planes alternativos (Blue Sky y potencial) | D2: OCP | E2: Cobriza | F2: Planificación estratégica | G2: PA | H2: 180000 | J2: 3 | K2: =IFERROR(H2/J2,0) -> 60000 | L2: Regular | M2: UG | N2: Solicitud Directa | O2: ODS | P2: 45653 | Q2: Enero
A3: 2 | B3: Chile | C3: . | H3: 0 | O3: Presentación Ad-Hoc
A4: 3 | B4: Perú | C4: PFS Ferrobamba Deep | D4: Las Bambas | E4: Ferrobamba | F4: Ing. de minas | G4: MF | H4: 1035000 | J4: 13 | K4: =IFERROR(H4/J4,0) -> 79615.385 | L4: Premium | M4: UG | N4: Reventa | O4: ODS | Q4: Febrero | T4: Maximiliano Adrove | U4: En espera de resultados de REDCO, que se presentara el 31 de marzo para ver continuidad
A5: 4 | B5: Chile | C5: Evaluación caso de negocio explotación SLS | D5: CMP | E5: Algarrobo | F5: Planificación estratégica | G5: FR | H5: 170000 | J5: 3 | K5: =IFERROR(H5/J5,0) -> 56666.667 | L5: Premium | M5: UG | N5: Solicitud Directa | O5: Seguimiento
A6: 5 | B6: EEUU | C6: Soporte caso de litigio Rio Tinto vs Gobierno Mongolia | D6: McCarthy Abogados | E6: Oyu Tolgoi | F6: Consultoría minera | G6: PV | H6: 566000 | J6: 3 | K6: =IFERROR(H6/J6,0) -> 188666.67 | L6: Target | M6: UG | N6: Solicitud Directa | O6: Seguimiento | S6: Deberiamos recibir respuesta de abril a mayo
A7: 6 | B7: Brasil | C7: Servicio IQS para nueve assets | D7: Vale | F7: Mecánica de rocas | G7: AS | H7: 450000 | J7: 12 | K7: =IFERROR(H7/J7,0) -> 37500 | L7: Target | M7: OP/UG | N7: Busqueda Activa | O7: No Adjudicada
A8: 7 | B8: Chile | C8: Estudio integral de LOM Mina Guarelo | D8: CAP | E8: Guarelo | F8: Planificación estratégica | G8: MF | H8: 60000 | J8: 2 | K8: =IFERROR(H8/J8,0) -> 30000 | L8: Regular | M8: OP | N8: Reventa | O8: Seguimiento | T8: Fernando Galez / Jaime Sepulveda | U8: PA Contactara a Jaime Sepulveda a cargo de Guarelo para ver status de la mina y oportunidades de negocio
A9: 8 | B9: EEUU | C9: Technical Expert Support of the plaintiff’s allegation to Alio Gold Inc | D9: McCarthy Abogados | E9: Alio Gold | F9: Consultoría minera | G9: PV | H9: 340000 | J9: 3 | K9: =IFERROR(H9/J9,0) -> 113333.33 | L9: Regular | M9: OP | N9: Reventa | O9: No Adjudicada
A10: 9 | B10: Perú | C10: Preparación IV MEIA San German | D10: Minsur | E10: San Rafael | F10: Ing. de minas | G10: MF | H10: 240000 | J10: 3 | K10: =IFERROR(H10/J10,0) -> 80000 | L10: Premium | M10: UG | N10: Solicitud Directa | O10: Cierre y Negociacón | P10: 45992 | Q10: Enero | S10: Se envio SOW para validar propuesta | U10: Matias contactara Alex para cierre del estudio, sin embargo por conflico con jefe directo estamos menos agresivo
A11: 10 | B11: Perú | C11: Revisión de validación reportes R&R (15 assets) | D11: Volcan | F11: Consultoría minera | G11: EL | H11: 220000 | J11: 3 | K11: =IFERROR(H11/J11,0) -> 73333.333 | L11: Regular | M11: OP/UG | N11: Licitación | O11: No Adjudicada | P11: 45681 | T11: Freddy Gomez | U11: Feedback de evaluación de parte tecnica, jueves 23
A12: 11 | B12: Chile | C12: Ing. Pre factibilidad perforación HHD | D12: Anglo American | E12: Los Bronces | F12: Ing. de minas | G12: RM | H12: 180000 | J12: 5 | K12: =IFERROR(H12/J12,0) -> 36000 | L12: Target | M12: OP | N12: Busqueda Activa | O12: ODS | P12: 46015 | Q12: Enero
A13: 12 | B13: Chile | C13: LOM estrategico | D13: First Quantum | E13: Cobre Panama | F13: Planificación estratégica | G13: PA | H13: 200000 | J13: 3 | K13: =IFERROR(H13/J13,0) -> 66666.667 | L13: Regular | M13: OP | N13: Solicitud Directa | O13: ODS | P13: 46016 | Q13: Enero
A14: 13 | B14: Chile | C14: Estudio de productividad | D14: Anglo American | E14: Los Bronces | F14: Consultoría minera | G14: FR | H14: 56000 | J14: 2 | K14: =IFERROR(H14/J14,0) -> 28000 | L14: Target | M14: OP | N14: Solicitud Directa | O14: Cierre y Negociacón | P14: 45646 | Q14: Febrero
A15: 14 | B15: Chile | C15: Análisis de confiabilidad y detección de cuellos de botella del LoA 25 – Proyecto SCUT | D15: BHP | E15: Spence | F15: Simulación de sistemas mineros | G15: PA | H15: 35000 | J15: 1 | K15: =IFERROR(H15/J15,0) -> 35000 | L15: Target | M15: OP | N15: Reventa | O15: ODS | P15: 45667 | Q15: Enero
A16: 15 | B16: Brasil | C16: Estudio Conceptual | D16: Vale | E16: Gongo Soco | F16: Mecánica de rocas | G16: AS | H16: 150000 | J16: 3 | K16: =IFERROR(H16/J16,0) -> 50000 | L16: Target | M16: OP | N16: Busqueda Activa | O16: Iniciativa | U16: Retomar contacto con cliente para conseguir una solicitud de propuesta
A17: 16 | B17: Chile | C17: Sistema Integrado de Gestión de Riesgos Geotécnicos | D17: Capstone Copper | E17: Todas | F17: Mecánica de rocas | G17: ER | H17: 900000 | J17: 12 | K17: =IFERROR(H17/J17,0) -> 75000 | L17: Premium | M17: OP | N17: Busqueda Activa | O17: Construcción Propuesta
A18: 17 | B18: Chile | C18: Ing Basica MHD UG | D18: Lundin | E18: Candelaria | F18: Ing. de minas | G18: RM | H18: 1380000 | J18: 5 | K18: =IFERROR(H18/J18,0) -> 276000 | L18: Premium | M18: UG | N18: Licitación | O18: Seguimiento | P18: 45674
A19: 18 | B19: Brasil | C19: PLANO AMBIENTAL DE FECHAMENTO CGM | D19: Alcoa | F19: Ing. de minas | G19: AS | H19: 207000 | J19: 6 | K19: =IFERROR(H19/J19,0) -> 34500 | L19: Regular | M19: OP | N19: Licitación | O19: No Adjudicada | P19: 45665
A20: 19 | B20: Chile | C20: Planificación Corto Plazo para Captura de Valor OP | D20: AMSA | E20: Centinela | F20: Planificación estratégica | G20: ER | H20: 150000 | J20: 3 | K20: =IFERROR(H20/J20,0) -> 50000 | L20: Premium | M20: OP | N20: Busqueda Activa | O20: Iniciativa | S20: A la espera de incorporación de cliente clave
A21: 20 | B21: EEUU | C21: Pre-Prefactibilidad Birch Lake + Tunnel acceso a Maturi | D21: Twin Metals Minnesota | E21: Birch Lake - Maturi | F21: Planificación estratégica | G21: PV | H21: 300000 | J21: 3 | K21: =IFERROR(H21/J21,0) -> 100000 | L21: Premium | M21: UG | N21: Busqueda Activa | O21: Iniciativa
A22: 21 | B22: EEUU | C22: Prefactibilidad para el conjunto Birch Lake - Maturi | D22: Twin Metals Minnesota | E22: Birch Lake - Maturi | F22: Ing. de minas | G22: PV | H22: 800000 | J22: 5 | K22: =IFERROR(H22/J22,0) -> 160000 | L22: Premium | M22: UG | N22: Busqueda Activa | O22: Iniciativa
A23: 22 | B23: EEUU | C23: Technical support for royalty acquisition | D23: EMX Royalty | F23: Consultoría minera | G23: PV | H23: 300000 | J23: 3 | K23: =IFERROR(H23/J23,0) -> 100000 | L23: Regular | M23: OP/UG | N23: Solicitud Directa | O23: Iniciativa
A24: 23 | B24: EEUU | C24: FS Santa Cruz Project UG - Revision Técnica | D24: Ivanhoe Electric | E24: Santa Cruz | F24: Planificación estratégica | G24: PV | H24: 100000 | J24: 3 | K24: =IFERROR(H24/J24,0) -> 33333.333 | L24: Target | M24: UG | N24: Busqueda Activa | O24: Iniciativa
A25: 24 | B25: EEUU | C25: Caso Base Resolution: diseño , planes, evalaucion | D25: BHP | E25: Resolution | F25: Planificación estratégica | G25: PV | H25: 200000 | J25: 3 | K25: =IFERROR(H25/J25,0) -> 66666.667 | L25: Target | M25: UG | N25: Busqueda Activa | O25: Iniciativa
A26: 25 | B26: EEUU | C26: Estudios - Diseños - Planes | D26: BHP | E26: Resolution | F26: Planificación estratégica | G26: PV | H26: 300000 | J26: 3 | K26: =IFERROR(H26/J26,0) -> 100000 | L26: Target | M26: UG | N26: Busqueda Activa | O26: Iniciativa
A27: 26 | B27: EEUU | C27: Estudios - Diseños - Planes | D27: BHP | E27: Antamina | F27: Planificación estratégica | G27: PV | H27: 150000 | J27: 3 | K27: =IFERROR(H27/J27,0) -> 50000 | L27: Target | M27: OP | N27: Busqueda Activa | O27: Iniciativa
A28: 27 | B28: EEUU | C28: Estudios - Diseños - Planes | D28: BHP | E28: CU South Australia | F28: Planificación estratégica | G28: PV | H28: 200000 | J28: 3 | K28: =IFERROR(H28/J28,0) -> 66666.667 | L28: Target | M28: OP/UG | N28: Busqueda Activa | O28: Iniciativa
A29: 28 | B29: EEUU | C29: SIMPREP | D29: Freeport-McMoRan Inc. | E29: PTFI | F29: Simulación de sistemas mineros | G29: PV | H29: 150000 | J29: 3 | K29: =IFERROR(H29/J29,0) -> 50000 | L29: Target | M29: UG | N29: Busqueda Activa | O29: Iniciativa
A30: 29 | B30: EEUU | C30: Planificación - Diseño | D30: Freeport-McMoRan Inc. | E30: PTFI | F30: Planificación estratégica | G30: PV | H30: 200000 | J30: 3 | K30: =IFERROR(H30/J30,0) -> 66666.667 | L30: Target | M30: UG | N30: Busqueda Activa | O30: Iniciativa
A31: 30 | B31: EEUU | C31: Planificación - Diseño | D31: Newmont Mining | F31: Planificación estratégica | G31: PV | H31: 200000 | J31: 3 | K31: =IFERROR(H31/J31,0) -> 66666.667 | L31: Target | M31: OP | N31: Busqueda Activa | O31: Iniciativa
A32: 31 | B32: EEUU | C32: Planificación - Diseño | D32: Anglo Gold Ashanti | F32: Planificación estratégica | G32: PV | H32: 200000 | J32: 3 | K32: =IFERROR(H32/J32,0) -> 66666.667 | L32: Target | M32: UG | N32: Busqueda Activa | O32: Iniciativa
A33: 32 | B33: EEUU | C33: Planificación - Diseño | D33: Vale | F33: Planificación estratégica | G33: PV | H33: 150000 | J33: 3 | K33: =IFERROR(H33/J33,0) -> 50000 | L33: Leads | M33: OP/UG | N33: Busqueda Activa | O33: Iniciativa
A34: 33 | B34: EEUU | C34: Planificación - Diseño | D34: South 32 | F34: Planificación estratégica | G34: PV | H34: 100000 | J34: 3 | K34: =IFERROR(H34/J34,0) -> 33333.333 | L34: Leads | M34: UG | N34: Busqueda Activa | O34: Iniciativa
A35: 34 | B35: EEUU | C35: Planificación - Diseño | D35: Barrick | F35: Planificación estratégica | G35: PV | H35: 100000 | J35: 3 | K35: =IFERROR(H35/J35,0) -> 33333.333 | L35: Leads | M35: OP | N35: Busqueda Activa | O35: Iniciativa
A36: 35 | B36: EEUU | C36: Planificación - Diseño | D36: Lundin | E36: Eagle | F36: Planificación estratégica | G36: PV | H36: 100000 | J36: 3 | K36: =IFERROR(H36/J36,0) -> 33333.333 | L36: Leads | M36: UG | N36: Busqueda Activa | O36: Iniciativa
A37: 36 | B37: EEUU | C37: Planificación - Diseño | D37: Kinross | F37: Planificación estratégica | G37: PV | H37: 200000 | J37: 3 | K37: =IFERROR(H37/J37,0) -> 66666.667 | L37: Leads | M37: OP | N37: Busqueda Activa | O37: Iniciativa
A38: 37 | B38: Brasil | C38: Cajati P1: ingeniería de enlace operacional | D38: Mosaic | E38: Cajati | F38: Ing. de minas | G38: AS | H38: 140000 | J38: 7 | K38: =IFERROR(H38/J38,0) -> 20000 | L38: Premium | M38: UG | N38: Busqueda Activa | O38: Cierre y Negociacón | P38: 45727 | Q38: 45731
A39: 38 | B39: Brasil | C39: Mosaic CTV 5Y Plan + Fase II | D39: Mosaic | E39: Cajati | F39: Planificación estratégica | G39: AS | H39: 358000 | J39: 5 | K39: =IFERROR(H39/J39,0) -> 71600 | L39: Premium | M39: UG | N39: Busqueda Activa | O39: Iniciativa
A40: 39 | B40: Brasil | C40: Ing PFS mina UG | D40: Aura Minerals | E40: Mina Paiol | F40: Planificación estratégica | G40: AS | H40: 288000 | J40: 3 | K40: =IFERROR(H40/J40,0) -> 96000 | L40: Target | M40: UG | N40: Reventa | O40: Construcción Propuesta
A41: 40 | B41: Brasil | C41: LOM ( Remoción Pilares y Secuecia Operativa) | D41: Lhg | E41: Mina Urucum | F41: Planificación estratégica | G41: AS | H41: 299000 | J41: 3 | K41: =IFERROR(H41/J41,0) -> 99666.667 | L41: Target | M41: UG | N41: Busqueda Activa | O41: Iniciativa
A42: 41 | B42: Brasil | C42: Proyectos Subeterraneaos | D42: Vale | F42: Planificación estratégica | G42: AS | H42: 220000 | J42: 3 | K42: =IFERROR(H42/J42,0) -> 73333.333 | L42: Target | M42: UG | N42: Busqueda Activa | O42: Iniciativa
A43: 42 | B43: Brasil | C43: Planificación - Diseño | D43: EuroChen | F43: Planificación estratégica | G43: AS | H43: 130000 | J43: 3 | K43: =IFERROR(H43/J43,0) -> 43333.333 | L43: Target | M43: OP/UG | N43: Busqueda Activa | O43: Iniciativa
A44: 43 | B44: Brasil | C44: Planificación - Diseño | D44: AngloGold Ashanti | F44: Planificación estratégica | G44: AS | H44: 150000 | J44: 3 | K44: =IFERROR(H44/J44,0) -> 50000 | L44: Target | M44: UG | N44: Busqueda Activa | O44: Iniciativa
A45: 44 | B45: Brasil | C45: Geotecnica y planeamiento | D45: Samarco | F45: Mecánica de rocas | G45: AS | H45: 150000 | J45: 4 | K45: =IFERROR(H45/J45,0) -> 37500 | L45: Target | M45: UG | N45: Busqueda Activa | O45: Iniciativa
A46: 45 | B46: Brasil | C46: Planificación - Diseño | D46: Anglo American | F46: Planificación estratégica | G46: AS | H46: 200000 | J46: 6 | K46: =IFERROR(H46/J46,0) -> 33333.333 | L46: Target | M46: OP | N46: Busqueda Activa | O46: Iniciativa
A47: 46 | B47: Brasil | C47: Planificación - Diseño | D47: Nexa | E47: Aripuna | F47: Planificación estratégica | G47: AS | H47: 150000 | J47: 3 | K47: =IFERROR(H47/J47,0) -> 50000 | L47: Regular | M47: UG | N47: Busqueda Activa | O47: Iniciativa
A48: 47 | B48: Perú | C48: Apoyo transversal a la planificación: Forecast, Budget, LOM | D48: Minsur | E48: San Rafael | F48: Ing. de minas | G48: MF | H48: 200000 | J48: 4 | K48: =IFERROR(H48/J48,0) -> 50000 | L48: Premium | M48: UG | N48: Busqueda Activa | O48: Contacto Inicial (Enganche) | S48: A la espera de inicio de ciclos de planificación | U48: Contactar inicios de febrero
A49: 48 | B49: Perú | C49: Planificación de largo plazo (LOM) integrada con iniciativas + Potenciales | D49: Minsur | E49: San Rafael | F49: Planificación estratégica | G49: MF | H49: 110000 | J49: 3 | K49: =IFERROR(H49/J49,0) -> 36666.667 | L49: Premium | M49: UG | N49: Reventa | O49: Construcción Propuesta | P49: 45672 | S49: Posible adjudicación abril-mayo | T49: Alan Angles | U49: A enviar esta semana
A50: 49 | B50: Perú | C50: Estandarización de procesos de control, cumplimiento y reconciliación | D50: Minsur | E50: San Rafael | F50: Planificación estratégica | G50: MF | H50: 150000 | J50: 3 | K50: =IFERROR(H50/J50,0) -> 50000 | L50: Premium | M50: UG | N50: Busqueda Activa | O50: Iniciativa | S50: Iniciar iniciativa segundo semestre | U50: Contactar inicios de segundo trimestre
A51: 50 | B51: Perú | C51: Apoyo transversal a la planificación: Forecast, Budget, LOM | D51: Raura | E51: Raura | F51: Planificación estratégica | G51: MF | H51: 200000 | J51: 3 | K51: =IFERROR(H51/J51,0) -> 66666.667 | L51: Premium | M51: UG | N51: Busqueda Activa | O51: Iniciativa | S51: Este proyecto pudiera decantar según el trabajo a realizar en SR | T51: Javier Latorre | U51: Contactar inicios de segundo trimestre
A52: 51 | B52: Perú | C52: Compilación R&R | D52: Minsur | F52: Consultoría minera | G52: PA | H52: 100000 | J52: 4 | K52: =IFERROR(H52/J52,0) -> 25000 | L52: Regular | M52: UG | N52: Busqueda Activa | O52: Iniciativa | S52: Cliente indica que no requiere nada por ahora | T52: Pedro Statuet
A53: 52 | B53: Perú | C53: Estudio geomecánico y trade off de métodos de explotación | D53: Hochschild Mining | E53: Inmaculada | F53: Mecánica de rocas | G53: CH | H53: 50000 | J53: 3 | K53: =IFERROR(H53/J53,0) -> 16666.667 | L53: Regular | M53: UG | N53: Busqueda Activa | O53: Iniciativa
A54: 53 | B54: Perú | C54: Implementación de un sistema de mapeo estructural automatizado | D54: Gold Fields | E54: Cerro Corona | F54: Mecánica de rocas | G54: CH | H54: 100000 | J54: 3 | K54: =IFERROR(H54/J54,0) -> 33333.333 | L54: Target | M54: UG | N54: Busqueda Activa | O54: Contacto Inicial (Enganche) | T54: Richard Ordoñez | U54: Contactar a Geomecanico principal para ofrecer servicios geomecanicos con apoyo de EL y gerente mina
A55: 54 | B55: Perú | C55: Asesoría Técnica para la Identificación de Oportunidades de Mejora para Incremento de Producción Mina | D55: Hochschild Mining | E55: Inmaculada | F55: Consultoría minera | G55: CH | H55: 100000 | J55: 3 | K55: =IFERROR(H55/J55,0) -> 33333.333 | L55: Regular | M55: UG | N55: Busqueda Activa | O55: No Adjudicada | P55: 45695 | Q55: Febrero | R55: Costos muy altos
A56: 55 | B56: Perú | C56: Actualización de métodos de minado Torremani (Etapa II) | D56: Coripuno | E56: Torremani | F56: Ing. de minas | G56: CH | H56: 100000 | J56: 3 | K56: =IFERROR(H56/J56,0) -> 33333.333 | L56: Regular | M56: OP | N56: Busqueda Activa | O56: Contacto Inicial (Enganche) | T56: Frank Mauricio | U56: Solicitar una reunión con cliente para conversar sobre el estudio (semana 13-01)
A57: 56 | B57: Perú | C57: Estudios de planificación u otros | D57: Sierra Metals | E57: Yauricocha | F57: Planificación estratégica | G57: EL | H57: 150000 | J57: 3 | K57: =IFERROR(H57/J57,0) -> 50000 | L57: Target | M57: UG | N57: Busqueda Activa | O57: Iniciativa | U57: Verificar porque no paga el cliente
A58: 57 | B58: Perú | C58: Servicio de apoyo para presentación a la autoridad de ROMINA actualizado | D58: Volcan | E58: Romina | F58: Consultoría minera | G58: CH | H58: 80000 | J58: 3 | K58: =IFERROR(H58/J58,0) -> 26666.667 | L58: Target | M58: UG | N58: Busqueda Activa | O58: Iniciativa | T58: Edgardo Zamora | U58: Llamar a cliente para activar iniciativa (semana 13-01)
A59: 58 | B59: Perú | C59: Estudio Crown pillars y metodos de explotación | D59: Volcan | E59: Chungar | F59: Mecánica de rocas | G59: CH | H59: 100000 | J59: 3 | K59: =IFERROR(H59/J59,0) -> 33333.333 | L59: Target | M59: UG | N59: Busqueda Activa | O59: Contacto Inicial (Enganche) | T59: Orlando Chumpitaz | U59: Coordinar reunión presencial en lima a fin de mes (semana 27) - Llamar semana del (13-01)
A60: 59 | B60: Perú | C60: Apoyo transversal a la planificación: Forecast, Budget, LOM | D60: Miski Mayo | F60: Planificación estratégica | G60: EL | H60: 150000 | J60: 3 | K60: =IFERROR(H60/J60,0) -> 50000 | L60: Target | M60: UG | N60: Busqueda Activa | O60: Contacto Inicial (Enganche) | T60: Marilsa | U60: 1.Cliente indica que saldra a licitación estudio de calculo de flota. 2.AS llame a Marilsa con el apoyo de RUI
A61: 60 | B61: Brasil | C61: Ingenieria para construcción tunel de exploración | D61: Aura Minerals | E61: Mina Paiol | F61: Ing. de minas | G61: AF | H61: 120000 | J61: 3 | K61: =IFERROR(H61/J61,0) -> 40000 | L61: Target | M61: UG | N61: Reventa | O61: Seguimiento | P61: 45713 | U61: Reunión lunes con Alex y Antonio para definir monto de estudio
A62: 61 | B62: Chile | C62: Análisis de Cuellos de Botella 2YB26 | D62: BHP | E62: Spence | F62: Simulación de sistemas mineros | G62: PA | H62: 35000 | J62: 1 | K62: =IFERROR(H62/J62,0) -> 35000 | L62: Target | M62: OP | N62: Reventa | O62: ODS | P62: 45674 | Q62: Enero
A63: 62 | B63: Chile | C63: Auditorias generales Centinela | D63: AMSA | E63: Centinela | F63: Consultoría minera | G63: GD | H63: 100000 | J63: 2 | K63: =IFERROR(H63/J63,0) -> 50000 | L63: Premium | M63: OP | N63: Busqueda Activa | O63: Iniciativa | U63: Coordinar con Caviedes una visita a su oficina. Fines de febrero
A64: 63 | B64: Brasil | C64: Optimización LOM de Cajati OP | D64: Mosaic | E64: Cajati | F64: Planificación estratégica | G64: AF | H64: 120000 | J64: 3 | K64: =IFERROR(H64/J64,0) -> 40000 | L64: Premium | M64: OP | N64: Reventa | O64: Contacto Inicial (Enganche) | U64: Contactar en Febrero al cliente, para proponer servicio previo al cierre de estudio
A65: 64 | B65: Chile | C65: Opportunity Assessment para optimizar el proyecto Cerro Colorado (LOM estrategico) | D65: BHP | E65: Cerro Colorado | F65: Planificación estratégica | G65: ER | H65: 240000 | J65: 5 | K65: =IFERROR(H65/J65,0) -> 48000 | L65: Target | M65: OP | N65: Reventa | O65: No Adjudicada | P65: 45723 | U65: Coordinar con RM proximos pasos y seguir conversaciones con cliente
A66: 65 | B66: Chile | C66: Actualización estudio Conceptual Sierra norte + construcción de nuevo modelo | D66: Capstone Copper | E66: Sierra Norte | F66: Ing. de minas | G66: GD | H66: 300000 | J66: 5 | K66: =IFERROR(H66/J66,0) -> 60000 | L66: Premium | M66: OP | N66: Reventa | O66: Contacto Inicial (Enganche) | U66: Conversar con ER
A67: 66 | B67: Chile | C67: Planificación LOM Blue Sky | D67: Lundin | E67: Caserones | F67: Planificación estratégica | G67: ER | H67: 200000 | J67: 3 | K67: =IFERROR(H67/J67,0) -> 66666.667 | L67: Target | M67: OP | N67: Reventa | O67: Construcción Propuesta | U67: Preparar material y construir ppt ad-hoc
A68: 67 | B68: Chile | C68: Analisis de confiafilidad de plan Forescast + Entrenamiento de usuario | D68: Capstone Copper | F68: Simulación de sistemas mineros | G68: GD | H68: 100000 | J68: 3 | K68: =IFERROR(H68/J68,0) -> 33333.333 | L68: Premium | M68: OP | N68: Reventa | O68: Contacto Inicial (Enganche) | U68: Proxima semana llamar a Max, post cierre PV.
A69: 68 | B69: Perú | C69: Evaluación de cumplimiento de planes de corto plazo | D69: Antamina | E69: Antamina | F69: Simulación de sistemas mineros | G69: EL | H69: 108000 | J69: 3 | K69: =IFERROR(H69/J69,0) -> 36000 | L69: Target | M69: OP | N69: Busqueda Activa | O69: Seguimiento
A70: 69 | B70: Perú | C70: Optimización plan de cierre mina recursos remanentes + stocks | D70: Gold Fields | E70: Cerro Corona | F70: Planificación estratégica | G70: EL | H70: 100000 | J70: 3 | K70: =IFERROR(H70/J70,0) -> 33333.333 | L70: Regular | M70: OP | N70: Busqueda Activa | O70: Iniciativa | U70: Preparar casos de éxito de optimización de stocks+ Raura
A71: 70 | B71: Chile | C71: Analisis estrategico de opciones | D71: BHP | E71: Spence | F71: Planificación estratégica | G71: ER | H71: 150000 | J71: 3 | K71: =IFERROR(H71/J71,0) -> 50000 | L71: Target | M71: OP | N71: Busqueda Activa | O71: Iniciativa | U71: Contactar Pedro Gonzales para ofrecer el servicio post modelo de simulación
A72: 71 | B72: Chile | C72: Analisis oportunidades de recuperación de reservas colapsadas | D72: Codelco | E72: DCH | F72: Mecánica de rocas | G72: CC | H72: 100000 | J72: 2 | K72: =IFERROR(H72/J72,0) -> 50000 | L72: Target | O72: Iniciativa | T72: Rodrigo Quiroz | U72: Esta semana se toma contacto con Rodrigo Quiroz post reunión final de estudio
A73: 72 | B73: Chile | C73: Metodologia para establecer escenarios productivos de corto plazo (Incoporar SIMPLAN en proceso de planificación o Simprep OP) | D73: Codelco | E73: DRT | F73: Simulación de sistemas mineros | G73: CC | H73: 120000 | J73: 3 | K73: =IFERROR(H73/J73,0) -> 40000 | L73: Target | O73: Iniciativa | T73: Sebastian Pizarro | U73: A la espera de post vacaciones, se reactiva en marzo
A74: 73 | B74: Chile | C74: Implementación de SIMPREP | D74: Codelco | E74: DET | F74: Simulación de sistemas mineros | G74: CC | H74: 100000 | J74: 4 | K74: =IFERROR(H74/J74,0) -> 25000 | L74: Target | O74: Iniciativa | S74: Enrique tomo contacto con gerente Felipe Hidalgo | T74: Patricio Miranda | U74: CC se contacto con Felipe Hidalgo y se reunira con el la proxima semana
A75: 74 | B75: Chile | C75: Actualización de estandares y procedimientos de planificación, balances, muestreo, etc (replicar estudios realizados para otras operaciones) | D75: Codelco | E75: DRT | F75: Consultoría minera | G75: CC | H75: 120000 | J75: 3 | K75: =IFERROR(H75/J75,0) -> 40000 | L75: Target | O75: Iniciativa | T75: Sebastian Pizarro | U75: A la espera de post vacaciones, se reactiva en marzo
A76: 75 | B76: Chile | C76: Revisiones independientes | D76: Codelco | E76: GRM | F76: Consultoría minera | G76: CC | H76: 150000 | J76: 3 | K76: =IFERROR(H76/J76,0) -> 50000 | L76: Target | O76: Iniciativa | S76: A la espera de licitación en la cual nos tienen contemplados | T76: Ximena Policroni Galvez | U76: A la espera de licitación en la cual nos tienen contemplados
A77: 76 | B77: Chile | C77: Profundicación de actualización de NCC31 (con apoyo consultor) | D77: Codelco | E77: GRM | F77: Consultoría minera | G77: CC | H77: 100000 | J77: 3 | K77: =IFERROR(H77/J77,0) -> 33333.333 | L77: Target | O77: Iniciativa | S77: A la espera de cerrar el estudio actual para avanzar con la etapa 2 (profundización) | T77: Fernando Marambio | U77: A la espera de cerrar el estudio actual para avanzar con la etapa 2 (profundización)
A78: 77 | B78: Chile | C78: Estudios de oportunidad en planes OP (alargar vida del rajo, recuepeación de stocks y los botaderos, zonas de contacto entre ambos rajos) | D78: Codelco | E78: DCH | F78: Planificación estratégica | G78: CC | H78: 200000 | J78: 3 | K78: =IFERROR(H78/J78,0) -> 66666.667 | L78: Target | O78: Iniciativa | T78: Juan Cristobal Videla | U78: A la espera de respuesta con cliente para coordinar reunión
A79: 78 | B79: Chile | C79: Analisis de oportunidades del plan minero, generar coberturas debido a atrasos en proyectos | D79: Codelco | E79: DET | F79: Planificación estratégica | G79: CC | H79: 150000 | J79: 3 | K79: =IFERROR(H79/J79,0) -> 50000 | L79: Target | O79: Iniciativa | T79: Felipe Hidalgo | U79: =+U74 -> CC se contacto con Felipe Hidalgo y se reunira con el la proxima semana
A80: 79 | B80: Chile | C80: Implementación de SIMPREP | D80: Codelco | E80: DCH | F80: Simulación de sistemas mineros | G80: CC | H80: 100000 | J80: 4 | K80: =IFERROR(H80/J80,0) -> 25000 | L80: Target | O80: Iniciativa | S80: Evaluar la mejor estrategia de implementar esto (tanto para DCH y DET) | T80: Rodrigo Quiroz | U80: A la espera de post vacaciones, se reactiva en marzo
A81: 80 | B81: Chile | C81: Evaluación de oportunidades de optimización integrada Distrito Norte | D81: Codelco | E81: Distrito Norte | F81: Planificación estratégica | G81: CC | H81: 200000 | J81: 4 | K81: =IFERROR(H81/J81,0) -> 50000 | L81: Target | O81: Iniciativa | T81: J San Martin | U81: A la espera de avanzar el estudio con DMH para ver otros estudios, CC llamara para empujar inicio estudio DMH
A82: 81 | B82: Chile | C82: Implementación modelo de riesgo para casos LOM (2 operaciones) | D82: Capstone Copper | F82: Simulación de sistemas mineros | G82: GD | H82: 100000 | J82: 3 | K82: =IFERROR(H82/J82,0) -> 33333.333 | L82: Premium | M82: OP | N82: Reventa | O82: Iniciativa
A83: 82 | B83: Perú | C83: Actualización del Estudio Geomecánico | D83: Nexa | E83: Porvenir | F83: Mecánica de rocas | G83: CH | H83: 89700 | J83: 3 | K83: =IFERROR(H83/J83,0) -> 29900 | L83: Regular | O83: Seguimiento | P83: 45721 | T83: Walter Ramos | U83: Llamar para que cliente envie propuesta formal (fue solicitada verbalmente) (semana 13-01)
A84: 83 | B84: Chile | C84: Auditoría de las bases de datos geomecánicas y actualización de modelo geomecánico | D84: Lundin | E84: Candelaria | F84: Mecánica de rocas | G84: CH | H84: =240000+150000 -> 390000 | J84: 3 | K84: =IFERROR(H84/J84,0) -> 130000 | L84: Premium | O84: Seguimiento | P84: 45679 | T84: Roberto Alfaro / Mario Guerrero
A85: 84 | B85: Chile | C85: Definición de criterios de diseño de caserones SLOS | D85: Lundin | E85: Candelaria | F85: Mecánica de rocas | G85: CH | H85: 200000 | J85: 3 | K85: =IFERROR(H85/J85,0) -> 66666.667 | L85: Premium | O85: Contacto Inicial (Enganche) | T85: Roberto Alfaro / Mario Guerrero | U85: Llamar al contacto para proponer un plan de trabajo integrado, para conseguir una presentación del plan (semana 13-01)
A86: 85 | B86: Chile | C86: Estudio conceptual LOM con Rellenos | D86: Lundin | E86: Candelaria | F86: Ing. de minas | G86: CH | H86: 100000 | J86: 3 | K86: =IFERROR(H86/J86,0) -> 33333.333 | L86: Premium | O86: Contacto Inicial (Enganche) | T86: Roberto Alfaro / Mario Guerrero | U86: Llamar al contacto para proponer un plan de trabajo integrado, para conseguir una presentación del plan (semana 13-01)
A87: 86 | B87: Brasil | C87: Diseño de sistema de monitoreo geotecnico online | D87: Mosaic | E87: CTV | F87: Mecánica de rocas | G87: CH | H87: 60000 | J87: 3 | K87: =IFERROR(H87/J87,0) -> 20000 | L87: Premium | N87: Reventa | O87: Iniciativa
A88: 87 | B88: Chile | C88: Soporte Romeral, construcción túnel exploratorio | D88: CMP | E88: Romeral | F88: Consultoría minera | G88: FR | H88: 646000 | J88: 18 | K88: =IFERROR(H88/J88,0) -> 35888.889 | L88: Premium | O88: Construcción Propuesta
A89: 88 | B89: Chile | C89: Apoyo proceso licitación y contratación empresa explotación SLS | D89: CMP | E89: Romeral | F89: Consultoría minera | G89: FR | H89: 100000 | J89: 3 | K89: =IFERROR(H89/J89,0) -> 33333.333 | L89: Premium | O89: Iniciativa
A90: 89 | B90: Chile | C90: Implementación Simprep | D90: Lundin | E90: Candelaria | F90: Simulación de sistemas mineros | G90: CC | H90: 120000 | J90: 3 | K90: =IFERROR(H90/J90,0) -> 40000 | L90: Premium | O90: Cierre y Negociacón | Q90: 45698 | T90: Octavio Cardenaz | U90: MM converso con cliente y el esta en proceso de digerir la auditoria realizada por REDCO, se contactara el viernes
A91: 90 | B91: Chile | C91: Plan de Estabilización Operacional y Definición de habilitadores para el Crecimiento de Candelaria UG | D91: Lundin | E91: Candelaria | F91: Planificación estratégica | G91: CC | H91: 250000 | J91: 4 | K91: =IFERROR(H91/J91,0) -> 62500 | L91: Premium | O91: Contacto Inicial (Enganche) | T91: Octavio Cardenaz | U91: MM converso con cliente y el esta en proceso de digerir la auditoria realizada por REDCO, se contactara el viernes
A92: 91 | B92: Chile | C92: RDP: Mejoramiento del proceso y Upgrade con FEL 2A (con opciones + Thiele) | D92: CMP | E92: Coporativo | G92: FR | H92: 120000 | J92: 3 | K92: =IFERROR(H92/J92,0) -> 40000 | L92: Premium | O92: Iniciativa
A93: 92 | B93: Chile | C93: Estudio FEL 2B | D93: CMP | E93: CNN | G93: FR | H93: 100000 | J93: 3 | K93: =IFERROR(H93/J93,0) -> 33333.333 | L93: Premium | O93: Iniciativa
A94: 93 | B94: Chile | C94: Apoyo permisos | D94: CMP | E94: CNN | G94: FR | H94: 30000 | J94: 2 | K94: =IFERROR(H94/J94,0) -> 15000 | L94: Premium | O94: Iniciativa
A95: 94 | B95: Chile | C95: FEL 1 o FEL 2A formal | D95: CMP | E95: Romeral | G95: FR | H95: 50000 | J95: 3 | K95: =IFERROR(H95/J95,0) -> 16666.667 | L95: Premium | O95: Iniciativa
A96: 95 | B96: Chile | C96: Asistencia técnica Implementación Proyecto (ingeniería, permisos sectoriales) | D96: CMP | E96: Algarrobo | G96: FR | H96: 50000 | J96: 3 | K96: =IFERROR(H96/J96,0) -> 16666.667 | L96: Premium | O96: Iniciativa
A97: 96 | B97: Chile | C97: Implementación del estándar de planificación | D97: CMP | E97: Corporativo | G97: FR | H97: 50000 | J97: 3 | K97: =IFERROR(H97/J97,0) -> 16666.667 | L97: Premium | O97: Iniciativa
A98: 97 | B98: Perú | C98: Construcción escenarios ing conceptual | D98: Las Bambas | E98: Ferrobamba | F98: Ing. de minas | G98: MF | H98: 70000 | J98: 2 | K98: =IFERROR(H98/J98,0) -> 35000 | L98: Premium | O98: ODS | P98: 46011 | Q98: Enero
A99: 98 | B99: EEUU | C99: BL/Northmet Integration mine planning | D99: Twin Metals Minnesota | E99: birch Lake - Northmet | F99: Ing. de minas | G99: PV | H99: 116000 | J99: 3 | K99: =IFERROR(H99/J99,0) -> 38666.667 | L99: Premium | O99: ODS | P99: 45674 | Q99: Enero
A100: 99 | B100: Perú | C100: PFS tajo Esperanza | D100: Volcan | E100: Chungar | F100: Ing. de minas | G100: EL | H100: 150000 | J100: 4 | K100: =IFERROR(H100/J100,0) -> 37500 | L100: Regular | M100: OP | N100: Busqueda Activa | O100: Contacto Inicial (Enganche) | T100: Orlando Chumpitaz | U100: Contactar a cliente para ser incluido en la licitación
...

Sheet Hoja1
A1: ID | B1: País | C1: Descripcion Oportunidad | D1: Empresa | E1: Mina | F1: Tipo de Estudio | G1: Gestor Comercial | H1: Monto (USD) | I1: Duracion (meses) | J1: USD/mes
A2: 1 | B2: Chile | C2: Ing Basica MHD UG | D2: Lundin | E2: Candelaria | F2: Ing. de minas | G2: RM | H2: 1380000 | I2: 5 | J2: 276000
A3: 2 | B3: Chile | C3: Auditoría de las bases de datos geomecánicas y actualización de modelo geomecánico | D3: Lundin | E3: Candelaria | F3: Mecánica de rocas | G3: CH | H3: 390000 | I3: 3 | J3: 130000
A4: 3 | B4: Chile | C4: Análisis de Diseños de Ingeniería Túneles para suministro hidrico | D4: Worley | E4: Cerro Colorado | F4: Ing. de minas | G4: RM | H4: 381000 | I4: 3 | J4: 127000
A5: 4 | B5: Chile | C5: Estudios de Precisión Diseño Correas y Estudio de Flujo de Mineral | D5: Wood | E5: DCH | F5: Ing. de minas | G5: RM | H5: 638000 | I5: 4.5 | J5: 141777.78

Sheet Ventas
A3: Suma de Monto (USD) | B3: Etiquetas de columna
A4: Etiquetas de fila | B4: Cierre y Negociacón | C4: Construcción Propuesta | D4: Contacto Inicial (Enganche) | E4: Iniciativa | F4: No Adjudicada | G4: ODS | H4: Seguimiento | I4: Total general
A5: Brasil | B5: 140000 | C5: 1348000 | D5: 120000 | E5: 1867000 | F5: 657000 | H5: 1272000 | I5: 5404000
A6: Chile | B6: 221000 | C6: 1826000 | D6: 1150000 | E6: 2340000 | F6: 460000 | G6: 670000 | H6: 3249000 | I6: 9916000
A7: EEUU | E7: 3750000 | G7: 116000 | H7: 906000 | I7: 4772000
A8: Perú | B8: 260000 | C8: 160000 | D8: 800000 | E8: 830000 | F8: 558000 | G8: 1285000 | H8: 375700 | I8: 4268700
A9: Total general | B9: 621000 | C9: 3334000 | D9: 2070000 | E9: 8787000 | F9: 1675000 | G9: 2071000 | H9: 5802700 | I9: 24360700
A13: País | B13: Iniciativa | C13: Contacto Inicial (Enganche) | D13: Construcción Propuesta | E13: Seguimiento | F13: Cierre y Negociacón | G13: ODS | H13: Total general
A14: Brasil | B14: =GETPIVOTDATA("Monto (USD)",$A$3,"País","Brasil","Etapa","Iniciativa ")/1000000 -> 1.867 | C14: =GETPIVOTDATA("Monto (USD)",$A$3,"País","Brasil","Etapa","Contacto Inicial (Enganche)")/1000000 -> 0.12 | D14: =GETPIVOTDATA("Monto (USD)",$A$3,"País","Brasil","Etapa","Construcción Propuesta")/1000000 -> 1.348 | E14: =GETPIVOTDATA("Monto (USD)",$A$3,"País","Brasil","Etapa","Seguimiento")/1000000 -> 1.272 | F14: =GETPIVOTDATA("Monto (USD)",$A$3,"País","Brasil","Etapa","Cierre y Negociacón")/1000000 -> 0.14 | G14: =GETPIVOTDATA("Monto (USD)",$A$3,"País","Brasil","Etapa","ODS")/1000000 -> 0 | H14: =+SUM(B14:F14) -> 4.747
A15: Chile | B15: =GETPIVOTDATA("Monto (USD)",$A$3,"País","Chile","Etapa","Iniciativa ")/1000000 -> 2.34 | C15: =GETPIVOTDATA("Monto (USD)",$A$3,"País","Chile","Etapa","Contacto Inicial (Enganche)")/1000000 -> 1.15 | D15: =GETPIVOTDATA("Monto (USD)",$A$3,"País","Chile","Etapa","Construcción Propuesta")/1000000 -> 1.826 | E15: =GETPIVOTDATA("Monto (USD)",$A$3,"País","Chile","Etapa","Seguimiento")/1000000 -> 3.249 | F15: =GETPIVOTDATA("Monto (USD)",$A$3,"País","Chile","Etapa","Cierre y Negociacón")/1000000 -> 0.221 | G15: =GETPIVOTDATA("Monto (USD)",$A$3,"País","Chile","Etapa","ODS")/1000000 -> 0.67 | H15: =+SUM(B15:F15) -> 8.786
A16: EEUU | B16: =GETPIVOTDATA("Monto (USD)",$A$3,"País","EEUU","Etapa","Iniciativa ")/1000000 -> 3.75 | C16: =GETPIVOTDATA("Monto (USD)",$A$3,"País","EEUU","Etapa","Contacto Inicial (Enganche)")/1000000 -> 0 | D16: =GETPIVOTDATA("Monto (USD)",$A$3,"País","EEUU","Etapa","Construcción Propuesta")/1000000 -> 0 | E16: =GETPIVOTDATA("Monto (USD)",$A$3,"País","EEUU","Etapa","Seguimiento")/1000000 -> 0.906 | F16: =GETPIVOTDATA("Monto (USD)",$A$3,"País","EEUU","Etapa","Cierre y Negociacón")/1000000 -> 0 | G16: =GETPIVOTDATA("Monto (USD)",$A$3,"País","EEUU","Etapa","ODS")/1000000 -> 0.116 | H16: =+SUM(B16:F16) -> 4.656
A17: Perú | B17: =GETPIVOTDATA("Monto (USD)",$A$3,"País","Perú","Etapa","Iniciativa ")/1000000 -> 0.83 | C17: =GETPIVOTDATA("Monto (USD)",$A$3,"País","Perú","Etapa","Contacto Inicial (Enganche)")/1000000 -> 0.8 | D17: =GETPIVOTDATA("Monto (USD)",$A$3,"País","Perú","Etapa","Construcción Propuesta")/1000000 -> 0.16 | E17: =GETPIVOTDATA("Monto (USD)",$A$3,"País","Perú","Etapa","Seguimiento")/1000000 -> 0.3757 | F17: =GETPIVOTDATA("Monto (USD)",$A$3,"País","Perú","Etapa","Cierre y Negociacón")/1000000 -> 0.26 | G17: =GETPIVOTDATA("Monto (USD)",$A$3,"País","Perú","Etapa","ODS")/1000000 -> 1.285 | H17: =+SUM(B17:F17) -> 2.4257
A18: Total general | B18: =+SUM(B14:B17) -> 8.787 | C18: =+SUM(C14:C17) -> 2.07 | D18: =+SUM(D14:D17) -> 3.334 | E18: =+SUM(E14:E17) -> 5.8027 | F18: =+SUM(F14:F17) -> 0.621 | G18: =+SUM(G14:G17) -> 2.071 | H18: =+SUM(B18:F18) -> 20.6147
K23: 10000000
K24: 13000000
K25: 7000000
K26: =SUM(K22:K25) -> 30000000

Sheet Do vs At
M1: 0.25 | P1: 0.2 | Q1: 0.15 | R1: 0.2 | S1: 0.1 | T1: 0.1 | AA1: 0.2 | AB1: 0.35 | AC1: 0.15 | AD1: 0.15 | AE1: 0.15
E2: Atractividad | M2: Factor Atractividad | U2: Ejecutabilidad | AA2: Factor Ejecutabilidad | AI2: linea horizontal | AJ2: x | AK2: y | AX2: Variable | AY2: Porcentaje | AZ2: ATRACTIVIDAD | BG2: Variable | BH2: Porcentaje | BI2: ATRACTIVIDAD
B3: Id | C3: Cliente | D3: Nombre estudio | E3: Monto de venta | F3: Facturado | G3: Costo | H3: ROI | I3: Cercania con cliente | J3: Exposición al mercado frente a riesgos | K3: Riesgo | L3: Escalabilidad | M3: Monto de venta | N3: Facturado | O3: Costo | P3: ROI | Q3: Cercania con cliente | R3: Exposición al mercado frente a riesgos | S3: Riesgo | T3: Escalabilidad | U3: Tiempo de ejecución (meses) | V3: % de Conocimiento en REDCO | W3: % de experiencia en ejecució similar | X3: Cercania con el Core | Y3: Volumen de HHs y gestión | Z3: N° Personas | AA3: Tiempo de ejecución (meses) | AB3: % de Conocimiento en REDCO | AC3: % de experiencia en ejecució similar | AD3: Cercania con el Core | AE3: Volumen de HHs y gestión | AI3: 1 | AJ3: 1 | AK3: 3 | AZ3: 1 | BA3: 2 | BB3: 3 | BC3: 4 | BD3: 5 | BI3: 1 | BJ3: 2 | BK3: 3 | BL3: 4 | BM3: 5
B4: 1 | C4: =+_xlfn.XLOOKUP(D4,'[1]#¡REF'!C:C,'[1]#¡REF'!E:E,"!",0,1) -> ! | D4: Algarrobo Finos | E4: 847330 | F4: =+_xlfn.XLOOKUP(D4,#REF!,#REF!,"!",0,1)+223557 -> #REF! | G4: =+_xlfn.XLOOKUP(D4,#REF!,#REF!,"!",0,1) -> #REF! | H4: =+IFERROR((F4-G4)/F4,0) -> 0 | M4: 4 | P4: 5 | Q4: 5 | R4: 3 | S4: 4 | T4: 1 | U4: 16 | Y4: 3066 | Z4: 12 | AA4: 1 | AD4: 2 | AE4: 4 | AI4: 2 | AJ4: 5 | AK4: 3 | AX4: Monto de Vena | AY4: 0.25 | AZ4: < 120 KUS$ | BA4: 120 - 250 KUS$ | BB4: 250-500 KUS$ | BC4: 500-1000 KUS$ | BD4: >1M$ | BG4: Tiempo de ejecución | BH4: 0.2 | BI4: >2 años | BJ4: 12-24 meses | BK4: 8-12 meses | BL4: 4-8 meses | BM4: < 4 meses
B5: 2 | C5: =+_xlfn.XLOOKUP(D5,#REF!,#REF!,"!",0,1) -> #REF! | D5: AMSA_Asesoria Centinela | E5: =+_xlfn.XLOOKUP(D5,#REF!,#REF!,"!",0,1) -> #REF! | F5: =+_xlfn.XLOOKUP(D5,#REF!,#REF!,"!",0,1) -> #REF! | G5: =+_xlfn.XLOOKUP(D5,#REF!,#REF!,"!",0,1) -> #REF! | H5: =+IFERROR((F5-G5)/F5,0) -> 0 | M5: 2 | P5: 5 | Q5: 4 | R5: 4 | S5: 5 | T5: 3 | U5: 6 | Y5: 1112 | Z5: 8 | AA5: 4 | AD5: 4 | AE5: 5 | AX5: ROI | AY5: 0.2 | AZ5: <20% | BA5: 20%-25% | BB5: 25%-35% | BC5: 35%-45% | BD5: >45% | BG5: % de conocimiento en REDCO | BH5: 0.35 | BI5: <20% | BJ5: 20%-25% | BK5: 25%-35% | BL5: 35%-45% | BM5: >45%
B6: 3 | C6: =+_xlfn.XLOOKUP(D6,#REF!,#REF!,"!",0,1) -> #REF! | D6: Banco Santander_Yauricocha y Bolivar | E6: =+_xlfn.XLOOKUP(D6,#REF!,#REF!,"!",0,1) -> #REF! | F6: =+_xlfn.XLOOKUP(D6,#REF!,#REF!,"!",0,1) -> #REF! | G6: =+E6*45% -> #REF! | H6: =+IFERROR((F6-G6)/F6,0) -> 0 | M6: 1 | P6: 5 | Q6: 4 | R6: 3 | S6: 3 | T6: 2 | U6: 2 | Y6: 3.75 | Z6: 1 | AA6: 5 | AD6: 3 | AE6: 5 | AI6: linea vertical | AJ6: x | AK6: y | AX6: Cercania con cliente | AY6: 0.15 | AZ6: Sin historia | BA6: Referido de un cliente actual | BB6: Actual, pero solo ejecutado 1 proy. | BC6: actul y con 1 a 3 años historia | BD6: actual con más de 3 años de historia | BG6: % de experiencia en ejecución similar | BH6: 0.15 | BI6: <20% | BJ6: 20%-25% | BK6: 25%-35% | BL6: 35%-45% | BM6: >45%
B7: 4 | C7: =+_xlfn.XLOOKUP(D7,#REF!,#REF!,"!",0,1) -> #REF! | D7: Capstone Copper_Estimacion confiabilidad de planes | E7: =+_xlfn.XLOOKUP(D7,#REF!,#REF!,"!",0,1) -> #REF! | F7: =+_xlfn.XLOOKUP(D7,#REF!,#REF!,"!",0,1) -> #REF! | G7: =26074*1.35*1.35*1.4 -> 66527.811 | H7: =+IFERROR((F7-G7)/F7,0) -> 0 | M7: 2 | P7: 5 | Q7: 2 | R7: 4 | S7: 3 | T7: 4 | U7: =+(4*E7)/F7 -> #REF! | Y7: 0 | Z7: 6 | AA7: 4 | AD7: 4 | AE7: 5 | AI7: 1 | AJ7: 3 | AK7: 1 | AX7: Exposición al mercado frente a riesgo | AY7: 0.2 | AZ7: Exposición muy alta, juicio y responsabilidad penal | BA7: Exposición alta, se despliega a la industria | BB7: exposicion media, se pierde la relación con la empresa | BC7: Exposición baja, solo se pierde el proyecto | BD7: Sin exposición | BG7: cercania con el core | BH7: 0.15 | BI7: No es core de REDCO | BJ7: <30% es del core de REDCO | BK7: 30%-60% del core de REDCO | BL7: 60%-80% del core de REDCO | BM7: Full core de REDCO
B8: 5 | C8: =+_xlfn.XLOOKUP(D8,#REF!,#REF!,"!",0,1) -> #REF! | D8: CMP - FEL 2A | E8: =+_xlfn.XLOOKUP(D8,#REF!,#REF!,"!",0,1) -> #REF! | F8: =+_xlfn.XLOOKUP(D8,#REF!,#REF!,"!",0,1) -> #REF! | G8: =+_xlfn.XLOOKUP(D8,#REF!,#REF!,"!",0,1) -> #REF! | H8: =+IFERROR((F8-G8)/F8,0) -> 0 | M8: 4 | P8: 5 | Q8: 5 | R8: 3 | S8: 4 | T8: 3 | U8: 20 | Y8: 12596 | Z8: 27 | AA8: 2 | AD8: 4 | AE8: 3 | AI8: 2 | AJ8: 3 | AK8: 5 | AX8: Riesgo | AY8: 0.1 | AZ8: >40% valor de venta | BA8: 40%-30% del valor de venta | BB8: 30%-20% del valor de venta | BC8: 20%-10% del valor de venta | BD8: <10% del valor de venta | BG8: Volumen de HHs y gestión | BH8: 0.15 | BI8: >30.000 HHs | BJ8: 30.000-20.000 HHs | BK8: 20.000-10.000 | BL8: 10.000-3.000 | BM8: <3.000
B9: 6 | C9: =+_xlfn.XLOOKUP(D9,#REF!,#REF!,"!",0,1) -> #REF! | D9: Codelco_Falla Oeste | E9: =+_xlfn.XLOOKUP(D9,#REF!,#REF!,"!",0,1) -> #REF! | F9: =+_xlfn.XLOOKUP(D9,#REF!,#REF!,"!",0,1) -> #REF! | G9: =+_xlfn.XLOOKUP(D9,#REF!,#REF!,"!",0,1) -> #REF! | H9: =+IFERROR((F9-G9)/F9,0) -> 0 | M9: 1 | P9: 5 | Q9: 4 | R9: 3 | S9: 5 | T9: 3 | U9: 4 | Y9: 2352 | Z9: 10 | AA9: 4 | AD9: 4 | AE9: 5 | AX9: Escalabilidad | AY9: 0.15 | AZ9: No es escalable | BA9: Se puede escalar 30% de la solución | BB9: Se puede escalar entre un 30%-60% de la solución | BC9: 60%-80% es escalable | BD9: Todo es escalable
B10: 7 | C10: =+_xlfn.XLOOKUP(D10,#REF!,#REF!,"!",0,1) -> #REF! | D10: CSH_LOM Mina Guarello | E10: =+_xlfn.XLOOKUP(D10,#REF!,#REF!,"!",0,1) -> #REF! | F10: =+_xlfn.XLOOKUP(D10,#REF!,#REF!,"!",0,1) -> #REF! | G10: =+_xlfn.XLOOKUP(D10,#REF!,#REF!,"!",0,1) -> #REF! | H10: =+IFERROR((F10-G10)/F10,0) -> 0 | M10: 1 | P10: 2 | Q10: 1 | R10: 4 | S10: 5 | T10: 2 | U10: 8 | Y10: 822 | Z10: 5 | AA10: 3 | AD10: 4 | AE10: 5
B11: 8 | C11: =+_xlfn.XLOOKUP(D11,#REF!,#REF!,"!",0,1) -> #REF! | D11: Glencore_Coroccohuayco_OptimizacionLOM | E11: =+_xlfn.XLOOKUP(D11,#REF!,#REF!,"!",0,1) -> #REF! | F11: =+_xlfn.XLOOKUP(D11,#REF!,#REF!,"!",0,1) -> #REF! | G11: =+_xlfn.XLOOKUP(D11,#REF!,#REF!,"!",0,1) -> #REF! | H11: =+IFERROR((F11-G11)/F11,0) -> 0 | M11: 2 | P11: 5 | Q11: 3 | R11: 3 | S11: 4 | T11: 2 | U11: 5 | Y11: 2310.75 | Z11: 12 | AA11: 4 | AD11: 5 | AE11: 5
B12: 9 | C12: =+_xlfn.XLOOKUP(D12,#REF!,#REF!,"!",0,1) -> #REF! | D12: IvanhoeElectric_Santa-Cruz_PrePFS | E12: =+_xlfn.XLOOKUP(D12,#REF!,#REF!,"!",0,1) -> #REF! | F12: =+_xlfn.XLOOKUP(D12,#REF!,#REF!,"!",0,1) -> #REF! | G12: =+_xlfn.XLOOKUP(D12,#REF!,#REF!,"!",0,1) -> #REF! | H12: =+IFERROR((F12-G12)/F12,0) -> 0 | M12: 4 | P12: 4 | Q12: 2 | R12: 2 | S12: 3 | T12: 3 | U12: 7 | Y12: 7244 | Z12: 18 | AA12: 4 | AD12: 5 | AE12: 4
B13: 10 | C13: =+_xlfn.XLOOKUP(D13,#REF!,#REF!,"!",0,1) -> #REF! | D13: McCarthy_Litigio Rio Tinto | E13: =+_xlfn.XLOOKUP(D13,#REF!,#REF!,"!",0,1) -> #REF! | F13: =+_xlfn.XLOOKUP(D13,#REF!,#REF!,"!",0,1) -> #REF! | G13: =5118*1.35*1.35*1.4 -> 13058.577 | H13: =+IFERROR((F13-G13)/F13,0) -> 0 | M13: 4 | P13: 5 | Q13: 1 | R13: 3 | S13: 2 | T13: 2 | U13: =+(6*E13)/F13 -> #REF! | Y13: 149 | Z13: 4 | AA13: 4 | AD13: 2 | AE13: 5
B14: 11 | C14: =+_xlfn.XLOOKUP(D14,#REF!,#REF!,"!",0,1) -> #REF! | D14: Minsur_Apoyo Planificacion San Rafael | E14: =+_xlfn.XLOOKUP(D14,#REF!,#REF!,"!",0,1) -> #REF! | F14: =+_xlfn.XLOOKUP(D14,#REF!,#REF!,"!",0,1) -> #REF! | G14: =4299*1.35*1.35*1.4 -> 10968.899 | H14: =+IFERROR((F14-G14)/F14,0) -> 0 | M14: 1 | P14: 5 | Q14: 5 | R14: 4 | S14: 5 | T14: 3 | U14: =+(5*E14)/F14 -> #REF! | Y14: 270 | Z14: 3 | AA14: 4 | AD14: 4 | AE14: 5
B15: 12 | C15: =+_xlfn.XLOOKUP(D15,#REF!,#REF!,"!",0,1) -> #REF! | D15: NEXA_FEL2 Aripuana | E15: =+_xlfn.XLOOKUP(D15,#REF!,#REF!,"!",0,1) -> #REF! | F15: =+_xlfn.XLOOKUP(D15,#REF!,#REF!,"!",0,1) -> #REF! | G15: =+_xlfn.XLOOKUP(D15,#REF!,#REF!,"!",0,1) -> #REF! | H15: =+IFERROR((F15-G15)/F15,0) -> 0 | M15: 2 | P15: 0 | Q15: 1 | R15: 3 | S15: 3 | T15: 1 | U15: 12 | Y15: 6266.75 | Z15: 17 | AA15: 2 | AD15: 2 | AE15: 4
B16: 13 | C16: =+_xlfn.XLOOKUP(D16,#REF!,#REF!,"!",0,1) -> #REF! | D16: PFS Los Calatos | E16: =+_xlfn.XLOOKUP(D16,#REF!,#REF!,"!",0,1) -> #REF! | F16: =+_xlfn.XLOOKUP(D16,#REF!,#REF!,"!",0,1) -> #REF! | G16: =+_xlfn.XLOOKUP(D16,#REF!,#REF!,"!",0,1) -> #REF! | H16: =+IFERROR((F16-G16)/F16,0) -> 0 | M16: 4 | P16: 1 | Q16: 2 | R16: 3 | S16: 4 | T16: 3 | U16: =+(12*E16)/F16 -> #REF! | Y16: 8698 | Z16: 36 | AA16: 2 | AD16: 4 | AE16: 4
B17: 14 | C17: Seligdar | D17: Seligdar_Kyuchus | E17: 2400000 | F17: 598000 | G17: =+_xlfn.XLOOKUP(D17,#REF!,#REF!,"!",0,1) -> #REF! | H17: =+IFERROR((F17-G17)/F17,0) -> 0 | M17: 5 | P17: 5 | Q17: 1 | R17: 2 | S17: 1 | T17: 3 | U17: 8 | Y17: 3264 | Z17: 11 | AA17: 4 | AD17: 3 | AE17: 4
D18: VALE
B19: 15 | C19: =+_xlfn.XLOOKUP(D19,#REF!,#REF!,"!",0,1) -> #REF! | D19: Spence_Confiabilidad Plan 2YB 2025 | E19: =+_xlfn.XLOOKUP(D19,#REF!,#REF!,"!",0,1) -> #REF! | F19: =+_xlfn.XLOOKUP(D19,#REF!,#REF!,"!",0,1) -> #REF! | G19: =+E19*45% -> #REF! | H19: =+IFERROR((F19-G19)/F19,0) -> 0 | M19: 1 | P19: 5 | Q19: 4 | R19: 3 | S19: 5 | T19: 3 | U19: 1 | Y19: 0 | Z19: 7 | AA19: 5 | AC19: 4 | AD19: 3 | AE19: 5
M23: ATRACTIVIDAD | AA23: EJECUTABILIDAD
B24: Id | C24: Cliente | D24: Nombre estudio | M24: Monto de venta | N24: Facturado | O24: Costo | P24: ROI | Q24: Cercania con cliente | R24: Exposición al mercado frente a riesgos | S24: Riesgo | T24: Escalabilidad | AA24: Tiempo de ejecución (meses) | AB24: % de Conocimiento en REDCO | AC24: % de experiencia en ejecució similar | AD24: Cercania con el Core | AE24: Volumen de HHs y gestión
B25: 1 | C25: =+_xlfn.XLOOKUP(D26,#REF!,#REF!,"!",0,1) -> #REF! | D25: Algarrobo Finos | M25: =+M4*M$1 -> 1 | N25: =+N4*N$1 -> 0 | O25: =+O4*O$1 -> 0 | P25: =+P4*P$1 -> 1 | Q25: =+Q4*Q$1 -> 0.75 | R25: =+R4*R$1 -> 0.6 | S25: =+S4*S$1 -> 0.4 | T25: =+T4*T$1 -> 0.1 | AA25: =+AA4*AA$1 -> 0.2 | AB25: =+AB4*AB$1 -> 0 | AC25: =+AC4*AC$1 -> 0 | AD25: =+AD4*AD$1 -> 0.3 | AE25: =+AE4*AE$1 -> 0.6 | AF25: =+AF4*AF$1 -> 0
B26: 2 | C26: =+_xlfn.XLOOKUP(D27,#REF!,#REF!,"!",0,1) -> #REF! | D26: AMSA_Asesoria Centinela | J26: 120 | M26: =+M5*M$1 -> 0.5 | N26: =+N5*N$1 -> 0 | O26: =+O5*O$1 -> 0 | P26: =+P5*P$1 -> 1 | Q26: =+Q5*Q$1 -> 0.6 | R26: =+R5*R$1 -> 0.8 | S26: =+S5*S$1 -> 0.5 | T26: =+T5*T$1 -> 0.3 | AA26: =+AA5*AA$1 -> 0.8 | AB26: =+AB5*AB$1 -> 0 | AC26: =+AC5*AC$1 -> 0 | AD26: =+AD5*AD$1 -> 0.6 | AE26: =+AE5*AE$1 -> 0.75 | AF26: =+AF5*AF$1 -> 0
B27: 3 | C27: =+_xlfn.XLOOKUP(D28,#REF!,#REF!,"!",0,1) -> #REF! | D27: Banco Santander_Yauricocha y Bolivar | J27: =+J26*1000 -> 120000 | M27: =+M6*M$1 -> 0.25 | N27: =+N6*N$1 -> 0 | O27: =+O6*O$1 -> 0 | P27: =+P6*P$1 -> 1 | Q27: =+Q6*Q$1 -> 0.6 | R27: =+R6*R$1 -> 0.6 | S27: =+S6*S$1 -> 0.3 | T27: =+T6*T$1 -> 0.2 | AA27: =+AA6*AA$1 -> 1 | AB27: =+AB6*AB$1 -> 0 | AC27: =+AC6*AC$1 -> 0 | AD27: =+AD6*AD$1 -> 0.45 | AE27: =+AE6*AE$1 -> 0.75 | AF27: =+AF6*AF$1 -> 0
B28: 4 | C28: =+_xlfn.XLOOKUP(D29,#REF!,#REF!,"!",0,1) -> #REF! | D28: Capstone Copper_Estimacion confiabilidad de planes | J28: =250*1000 -> 250000 | M28: =+M7*M$1 -> 0.5 | N28: =+N7*N$1 -> 0 | O28: =+O7*O$1 -> 0 | P28: =+P7*P$1 -> 1 | Q28: =+Q7*Q$1 -> 0.3 | R28: =+R7*R$1 -> 0.8 | S28: =+S7*S$1 -> 0.3 | T28: =+T7*T$1 -> 0.4 | AA28: =+AA7*AA$1 -> 0.8 | AB28: =+AB7*AB$1 -> 0 | AC28: =+AC7*AC$1 -> 0 | AD28: =+AD7*AD$1 -> 0.6 | AE28: =+AE7*AE$1 -> 0.75 | AF28: =+AF7*AF$1 -> 0
B29: 5 | C29: =+_xlfn.XLOOKUP(D30,#REF!,#REF!,"!",0,1) -> #REF! | D29: CMP - FEL 2A | J29: =500*1000 -> 500000 | M29: =+M8*M$1 -> 1 | N29: =+N8*N$1 -> 0 | O29: =+O8*O$1 -> 0 | P29: =+P8*P$1 -> 1 | Q29: =+Q8*Q$1 -> 0.75 | R29: =+R8*R$1 -> 0.6 | S29: =+S8*S$1 -> 0.4 | T29: =+T8*T$1 -> 0.3 | AA29: =+AA8*AA$1 -> 0.4 | AB29: =+AB8*AB$1 -> 0 | AC29: =+AC8*AC$1 -> 0 | AD29: =+AD8*AD$1 -> 0.6 | AE29: =+AE8*AE$1 -> 0.45 | AF29: =+AF8*AF$1 -> 0
B30: 6 | C30: =+_xlfn.XLOOKUP(D31,#REF!,#REF!,"!",0,1) -> #REF! | D30: Codelco_Falla Oeste | J30: =1000*1000 -> 1000000 | M30: =+M9*M$1 -> 0.25 | N30: =+N9*N$1 -> 0 | O30: =+O9*O$1 -> 0 | P30: =+P9*P$1 -> 1 | Q30: =+Q9*Q$1 -> 0.6 | R30: =+R9*R$1 -> 0.6 | S30: =+S9*S$1 -> 0.5 | T30: =+T9*T$1 -> 0.3 | AA30: =+AA9*AA$1 -> 0.8 | AB30: =+AB9*AB$1 -> 0 | AC30: =+AC9*AC$1 -> 0 | AD30: =+AD9*AD$1 -> 0.6 | AE30: =+AE9*AE$1 -> 0.75 | AF30: =+AF9*AF$1 -> 0
B31: 7 | C31: =+_xlfn.XLOOKUP(D32,#REF!,#REF!,"!",0,1) -> #REF! | D31: CSH_LOM Mina Guarello | M31: =+M10*M$1 -> 0.25 | N31: =+N10*N$1 -> 0 | O31: =+O10*O$1 -> 0 | P31: =+P10*P$1 -> 0.4 | Q31: =+Q10*Q$1 -> 0.15 | R31: =+R10*R$1 -> 0.8 | S31: =+S10*S$1 -> 0.5 | T31: =+T10*T$1 -> 0.2 | AA31: =+AA10*AA$1 -> 0.6 | AB31: =+AB10*AB$1 -> 0 | AC31: =+AC10*AC$1 -> 0 | AD31: =+AD10*AD$1 -> 0.6 | AE31: =+AE10*AE$1 -> 0.75 | AF31: =+AF10*AF$1 -> 0
B32: 8 | C32: =+_xlfn.XLOOKUP(D33,#REF!,#REF!,"!",0,1) -> #REF! | D32: Glencore_Coroccohuayco_OptimizacionLOM | M32: =+M11*M$1 -> 0.5 | N32: =+N11*N$1 -> 0 | O32: =+O11*O$1 -> 0 | P32: =+P11*P$1 -> 1 | Q32: =+Q11*Q$1 -> 0.45 | R32: =+R11*R$1 -> 0.6 | S32: =+S11*S$1 -> 0.4 | T32: =+T11*T$1 -> 0.2 | AA32: =+AA11*AA$1 -> 0.8 | AB32: =+AB11*AB$1 -> 0 | AC32: =+AC11*AC$1 -> 0 | AD32: =+AD11*AD$1 -> 0.75 | AE32: =+AE11*AE$1 -> 0.75 | AF32: =+AF11*AF$1 -> 0
B33: 9 | C33: =+_xlfn.XLOOKUP(D34,#REF!,#REF!,"!",0,1) -> #REF! | D33: IvanhoeElectric_Santa-Cruz_PrePFS | M33: =+M12*M$1 -> 1 | N33: =+N12*N$1 -> 0 | O33: =+O12*O$1 -> 0 | P33: =+P12*P$1 -> 0.8 | Q33: =+Q12*Q$1 -> 0.3 | R33: =+R12*R$1 -> 0.4 | S33: =+S12*S$1 -> 0.3 | T33: =+T12*T$1 -> 0.3 | AA33: =+AA12*AA$1 -> 0.8 | AB33: =+AB12*AB$1 -> 0 | AC33: =+AC12*AC$1 -> 0 | AD33: =+AD12*AD$1 -> 0.75 | AE33: =+AE12*AE$1 -> 0.6 | AF33: =+AF12*AF$1 -> 0
B34: 10 | C34: =+_xlfn.XLOOKUP(D35,#REF!,#REF!,"!",0,1) -> #REF! | D34: McCarthy_Litigio Rio Tinto | M34: =+M13*M$1 -> 1 | N34: =+N13*N$1 -> 0 | O34: =+O13*O$1 -> 0 | P34: =+P13*P$1 -> 1 | Q34: =+Q13*Q$1 -> 0.15 | R34: =+R13*R$1 -> 0.6 | S34: =+S13*S$1 -> 0.2 | T34: =+T13*T$1 -> 0.2 | AA34: =+AA13*AA$1 -> 0.8 | AB34: =+AB13*AB$1 -> 0 | AC34: =+AC13*AC$1 -> 0 | AD34: =+AD13*AD$1 -> 0.3 | AE34: =+AE13*AE$1 -> 0.75 | AF34: =+AF13*AF$1 -> 0
B35: 11 | C35: =+_xlfn.XLOOKUP(D36,#REF!,#REF!,"!",0,1) -> #REF! | D35: Minsur_Apoyo Planificacion San Rafael | M35: =+M14*M$1 -> 0.25 | N35: =+N14*N$1 -> 0 | O35: =+O14*O$1 -> 0 | P35: =+P14*P$1 -> 1 | Q35: =+Q14*Q$1 -> 0.75 | R35: =+R14*R$1 -> 0.8 | S35: =+S14*S$1 -> 0.5 | T35: =+T14*T$1 -> 0.3 | AA35: =+AA14*AA$1 -> 0.8 | AB35: =+AB14*AB$1 -> 0 | AC35: =+AC14*AC$1 -> 0 | AD35: =+AD14*AD$1 -> 0.6 | AE35: =+AE14*AE$1 -> 0.75 | AF35: =+AF14*AF$1 -> 0
B36: 12 | C36: =+_xlfn.XLOOKUP(D37,#REF!,#REF!,"!",0,1) -> #REF! | D36: NEXA_FEL2 Aripuana | M36: =+M15*M$1 -> 0.5 | N36: =+N15*N$1 -> 0 | O36: =+O15*O$1 -> 0 | P36: =+P15*P$1 -> 0 | Q36: =+Q15*Q$1 -> 0.15 | R36: =+R15*R$1 -> 0.6 | S36: =+S15*S$1 -> 0.3 | T36: =+T15*T$1 -> 0.1 | AA36: =+AA15*AA$1 -> 0.4 | AB36: =+AB15*AB$1 -> 0 | AC36: =+AC15*AC$1 -> 0 | AD36: =+AD15*AD$1 -> 0.3 | AE36: =+AE15*AE$1 -> 0.6 | AF36: =+AF15*AF$1 -> 0
B37: 13 | C37: =+_xlfn.XLOOKUP(D38,#REF!,#REF!,"!",0,1) -> #REF! | D37: PFS Los Calatos | M37: =+M16*M$1 -> 1 | N37: =+N16*N$1 -> 0 | O37: =+O16*O$1 -> 0 | P37: =+P16*P$1 -> 0.2 | Q37: =+Q16*Q$1 -> 0.3 | R37: =+R16*R$1 -> 0.6 | S37: =+S16*S$1 -> 0.4 | T37: =+T16*T$1 -> 0.3 | AA37: =+AA16*AA$1 -> 0.4 | AB37: =+AB16*AB$1 -> 0 | AC37: =+AC16*AC$1 -> 0 | AD37: =+AD16*AD$1 -> 0.6 | AE37: =+AE16*AE$1 -> 0.6 | AF37: =+AF16*AF$1 -> 0
B38: 14 | C38: Seligdar | D38: Seligdar_Kyuchus | M38: =+M17*M$1 -> 1.25 | N38: =+N17*N$1 -> 0 | O38: =+O17*O$1 -> 0 | P38: =+P17*P$1 -> 1 | Q38: =+Q17*Q$1 -> 0.15 | R38: =+R17*R$1 -> 0.4 | S38: =+S17*S$1 -> 0.1 | T38: =+T17*T$1 -> 0.3 | AA38: =+AA17*AA$1 -> 0.8 | AB38: =+AB17*AB$1 -> 0 | AC38: =+AC17*AC$1 -> 0 | AD38: =+AD17*AD$1 -> 0.45 | AE38: =+AE17*AE$1 -> 0.6 | AF38: =+AF17*AF$1 -> 0
D39: VALE | M39: =+M18*M$1 -> 0 | N39: =+N18*N$1 -> 0 | O39: =+O18*O$1 -> 0 | P39: =+P18*P$1 -> 0 | Q39: =+Q18*Q$1 -> 0 | S39: =+S18*S$1 -> 0 | T39: =+T18*T$1 -> 0 | AA39: =+AA18*AA$1 -> 0 | AB39: =+AB18*AB$1 -> 0 | AC39: =+AC18*AC$1 -> 0 | AD39: =+AD18*AD$1 -> 0 | AE39: =+AE18*AE$1 -> 0 | AF39: =+AF19*AF$1 -> 0
B40: 15 | C40: =+_xlfn.XLOOKUP(D45,#REF!,#REF!,"!",0,1) -> #REF! | D40: Spence_Confiabilidad Plan 2YB 2025 | M40: =+M19*M$1 -> 0.25 | N40: =+N19*N$1 -> 0 | O40: =+O19*O$1 -> 0 | P40: =+P19*P$1 -> 1 | Q40: =+Q19*Q$1 -> 0.6 | R40: =+R19*R$1 -> 0.6 | S40: =+S19*S$1 -> 0.5 | T40: =+T19*T$1 -> 0.3 | AA40: =+AA19*AA$1 -> 1 | AB40: =+AB19*AB$1 -> 0 | AC40: =+AC19*AC$1 -> 0.6 | AD40: =+AD19*AD$1 -> 0.45 | AE40: =+AE19*AE$1 -> 0.75
B46: Id | C46: Cliente | D46: Nombre estudio | M46: Ejecutabilidad | P46: Atractividad
B47: 1 | C47: =+_xlfn.XLOOKUP(D48,#REF!,#REF!,"!",0,1) -> #REF! | D47: Algarrobo Finos | M47: =+SUM(AA25:AE25) -> 1.1 | P47: =+SUM(M25:T25) -> 3.85
B48: 2 | C48: =+_xlfn.XLOOKUP(D49,#REF!,#REF!,"!",0,1) -> #REF! | D48: AMSA_Asesoria Centinela | M48: =+SUM(AA26:AE26) -> 2.15 | P48: =+SUM(M26:T26) -> 3.7
B49: 3 | C49: =+_xlfn.XLOOKUP(D50,#REF!,#REF!,"!",0,1) -> #REF! | D49: Banco Santander_Yauricocha y Bolivar | M49: =+SUM(AA27:AE27) -> 2.2 | P49: =+SUM(M27:T27) -> 2.95
B50: 4 | C50: =+_xlfn.XLOOKUP(D51,#REF!,#REF!,"!",0,1) -> #REF! | D50: Capstone Copper_Estimacion confiabilidad de planes | M50: =+SUM(AA28:AE28) -> 2.15 | P50: =+SUM(M28:T28) -> 3.3
B51: 5 | C51: =+_xlfn.XLOOKUP(D52,#REF!,#REF!,"!",0,1) -> #REF! | D51: CMP - FEL 2A | M51: =+SUM(AA29:AE29) -> 1.45 | P51: =+SUM(M29:T29) -> 4.05
B52: 6 | C52: =+_xlfn.XLOOKUP(D53,#REF!,#REF!,"!",0,1) -> #REF! | D52: Codelco_Falla Oeste | M52: =+SUM(AA30:AE30) -> 2.15 | P52: =+SUM(M30:T30) -> 3.25
B53: 7 | C53: =+_xlfn.XLOOKUP(D54,#REF!,#REF!,"!",0,1) -> #REF! | D53: CSH_LOM Mina Guarello | M53: =+SUM(AA31:AE31) -> 1.95 | P53: =+SUM(M31:T31) -> 2.3
B54: 8 | C54: =+_xlfn.XLOOKUP(D55,#REF!,#REF!,"!",0,1) -> #REF! | D54: Glencore_Coroccohuayco_OptimizacionLOM | M54: =+SUM(AA32:AE32) -> 2.3 | P54: =+SUM(M32:T32) -> 3.15
B55: 9 | C55: =+_xlfn.XLOOKUP(D56,#REF!,#REF!,"!",0,1) -> #REF! | D55: IvanhoeElectric_Santa-Cruz_PrePFS | M55: =+SUM(AA33:AE33) -> 2.15 | P55: =+SUM(M33:T33) -> 3.1
B56: 10 | C56: =+_xlfn.XLOOKUP(D57,#REF!,#REF!,"!",0,1) -> #REF! | D56: McCarthy_Litigio Rio Tinto | M56: =+SUM(AA34:AE34) -> 1.85 | P56: =+SUM(M34:T34) -> 3.15
B57: 11 | C57: =+_xlfn.XLOOKUP(D58,#REF!,#REF!,"!",0,1) -> #REF! | D57: Minsur_Apoyo Planificacion San Rafael | M57: =+SUM(AA35:AE35) -> 2.15 | P57: =+SUM(M35:T35) -> 3.6
B58: 12 | C58: =+_xlfn.XLOOKUP(D59,#REF!,#REF!,"!",0,1) -> #REF! | D58: NEXA_FEL2 Aripuana | M58: =+SUM(AA36:AE36) -> 1.3 | P58: =+SUM(M36:T36) -> 1.65
B59: 13 | C59: =+_xlfn.XLOOKUP(D60,#REF!,#REF!,"!",0,1) -> #REF! | D59: PFS Los Calatos | M59: =+SUM(AA37:AE37) -> 1.6 | P59: =+SUM(M37:T37) -> 2.8
B60: 14 | C60: Seligdar | D60: Seligdar_Kyuchus | M60: =+SUM(AA38:AE38) -> 1.85 | P60: =+SUM(M38:T38) -> 3.2
B61: 15 | D61: VALE | M61: =+SUM(AA39:AE39) -> 0 | P61: =+SUM(M39:T39) -> 0
B62: 16 | C62: =+_xlfn.XLOOKUP(D65,#REF!,#REF!,"!",0,1) -> #REF! | D62: Spence_Confiabilidad Plan 2YB 2025 | M62: =+SUM(AA40:AE40) -> 2.8 | P62: =+SUM(M40:T40) -> 3.25

Sheet Perú
A1: ID | B1: Tipo Ciente | C1: Empresa | D1: Mina | E1: Descripcion Oportunidad | F1: Monto (USD)
A2: 1 | B2: Premium | C2: Minsur S.A. | D2: San Rafael | E2: Apoyo transversal a la planificación: Forecast, Budget, LOM | F2: 200 | G2: =+F2*1000 -> 200000
A3: 2 | B3: Premium | C3: Minsur S.A. | D3: San Rafael | E3: Proyectización e integración de zonas potenciales | F3: 120 | G3: =+F3*1000 -> 120000
A4: 3 | B4: Premium | C4: Minsur S.A. | D4: San Rafael | E4: Estandarización de procesos de control, cumplimiento y reconciliación | F4: 150 | G4: =+F4*1000 -> 150000
A5: 4 | B5: Premium | C5: Compañía Minera Raura S.A. | D5: Raura | E5: Oportunidades Budget 2025 | F5: 70 | G5: =+F5*1000 -> 70000
A6: 5 | B6: Premium | C6: Compañía Minera Raura S.A. | D6: Raura | E6: Apoyo transversal a la planificación: Forecast, Budget, LOM | F6: 200 | G6: =+F6*1000 -> 200000
A7: 6 | B7: Premium | C7: Minsur S.A. | E7: Compilación R&R | F7: 200 | G7: =+F7*1000 -> 200000
A8: 7 | B8: Regular | C8: Hochschild Mining (Peru) S.A. | D8: Inmaculada | E8: Estudio geomecánico y trade off de métodos de explotación | F8: 50 | G8: =+F8*1000 -> 50000
A9: 8 | B9: Target | C9: Compañía de Minas Buenaventura | D9: - | E9: Análisis de confiabilidad de planes | F9: 150 | G9: =+F9*1000 -> 150000
A10: 9 | B10: Target | C10: Gold Fields | D10: Cerro Corona | E10: Implementación de un sistema de mapeo estructural automatizado | F10: 100 | G10: =+F10*1000 -> 100000
A11: 10 | B11: Regular | C11: Hochschild Mining (Peru) S.A. | D11: Inmaculada | E11: Asesoría Técnica para la Identificación de Oportunidades de Mejora para Incremento de Producción Mina | F11: 150 | G11: =+F11*1000 -> 150000
A12: 11 | B12: Regular | C12: Coripuno | D12: Torremani | E12: Actualización de métodos de minado Torremani (Etapa II) | F12: 100 | G12: =+F12*1000 -> 100000
A13: 12 | B13: Target | C13: Glencore | D13: Coroccohuayco | E13: Estudios Mineros para la PFS | F13: 150 | G13: =+F13*1000 -> 150000
A14: 13 | B14: Target | C14: Hudbay Perú S.A.C | D14: Constancia | E14: Estudio de Factibilidad del WRF y Tajo Constancia para la 4ta MEIA | F14: 150 | G14: =+F14*1000 -> 150000
A15: 14 | B15: Target | C15: Las Bambas | D15: Ferrobamba | E15: Ferrobamba UG (PFS) | F15: 1200 | G15: =+F15*1000 -> 1200000
A16: 15 | B16: Target | C16: Sierra metals | D16: Yauricocha | E16: Desarrollo de Reservas | F16: 150 | G16: =+F16*1000 -> 150000
A17: 16 | B17: Target | C17: Sierra metals | D17: Bolivar | E17: Desarrollo de Reservas | F17: 150 | G17: =+F17*1000 -> 150000
A18: 17 | B18: Target | C18: Volcan Compañía Minera S.A.A. | D18: Todas | E18: Estudio de Validación de R&R | F18: 80 | G18: =+F18*1000 -> 80000
A19: 18 | B19: Target | C19: Volcan Compañía Minera S.A.A. | D19: Romina | E19: Servicio de apoyo para presentación a la autoridad de ROMINA actualizado | F19: 80 | G19: =+F19*1000 -> 80000
... A21: 20 | B21: Target | C21: Volcan Compañía Minera S.A.A. | D21: Chungar | E21: Estudio Conceptual/PFS Proyecto Esperanza | F21: 150 | G21: =+F21*1000 -> 150000
A22: 21 | B22: Target | C22: Miski Mayo | E22: Apoyo transversal a la planificación: Forecast, Budget, LOM | F22: 150 | G22: =+F22*1000 -> 150000
A27: 22 | B27: Leads | C27: Tantahuatay
A28: 23 | B28: Leads | C28: Compañía Minera Condestable S.A
A29: 24 | B29: Leads | C29: Pan American Dolores
A30: 25 | B30: Leads | C30: Hochschild Mining plc
A31: 26 | B31: Leads | C31: Alpayana
A32: 27 | B32: Leads | C32: Pan American Silver Corp.
A33: 28 | B33: Leads | C33: Vulco Perú S.A.
A34: 29 | B34: Leads | C34: Minera Yanacocha S.R.L.
A35: 30 | B35: Leads | C35: Southern Peru Copper
A36: 31 | B36: Leads | C36: Anglo American Quellaveco S.A.
A37: 32 | B37: Leads | C37: Barrick Latam
A38: 33 | B38: Leads | C38: Compañía Minera Zafranal S.A.C.
... A50: 45 | B50: Leads | C50: Minera Boroo Misquichilca

Sheet Chile
A1: ID | B1: Tipo Ciente | C1: Empresa | D1: Mina | E1: Descripcion Oportunidad | F1: Monto (USD) | G1: Fecha de contacto | H1: Fecha de Inicio | I1: Duración | J1: Gestor Comercial | K1: Contacto clave | L1: Comentarios
A3: 14 | B3: Premium | C3: CMP
A4: 15 | B4: Premium | C4: CMP | D4: CNN | E4: Estudio FEL 2B | F4: 100
A5: 16 | B5: Premium | C5: CMP | D5: CNN | E5: Apoyo permisos | F5: 30
A6: 17 | B6: Premium | C6: CMP | D6: CNN | E6: Estudio FEL 3 | F6: 150
A7: 18 | B7: Premium | C7: CMP | D7: Romeral | E7: FEL 1 o FEL 2A formal | F7: 50
A8: 19 | B8: Premium | C8: CMP | D8: Algarrobo | E8: Estudio conceptual UG - SLS + túnel + opc. OP | F8: 150
A9: 20 | B9: Premium | C9: CMP | D9: Algarrobo | E9: Asistencia técnica Implementación Proyecto (ingeniería, permisos sectoriales) | F9: 50
A10: 21 | B10: Premium | C10: CMP | D10: Algarrobo | E10: FEL 2A UG - SLS | F10: 80
A11: 22 | B11: Premium | C11: CMP | D11: MLC | E11: Estudio FEL 2 B | F11: 150
A12: 23 | B12: Premium | C12: CMP | D12: Corporativo | E12: Implementación del estándar de planificación | F12: 150
A13: 24 | B13: Premium | C13: AMSA | D13: Centinela | E13: Planificación - Diseño | F13: 350
A14: 25 | B14: Premium | C14: AMSA
A15: 26 | B15: Premium | C15: AMSA
A16: 27 | B16: Premium | C16: AMSA | D16: Pelambres | E16: Planificación - Diseño | F16: 350
A20: 6 | B20: Premium | C20: Codelco | D20: DCH | E20: Analisis oportunidades de recuperación de reservas colapsadas | F20: 100 | G20: 45658 | H20: 45717 | I20: 2 | J20: MM | K20: Rodrigo Quiroz
A21: 7 | B21: Premium | C21: Codelco | D21: DRT | E21: Metodologia para establecer escenarios productivos de corto plazo (Incoporar SIMPLAN en proceso de planificación o Simprep OP) | F21: 120 | G21: =+G20 -> 45658 | H21: =+H20 -> 45717 | I21: 3 | J21: MM | K21: Sebastian Pizarro
A22: 8 | B22: Premium | C22: Codelco | D22: DET | E22: Implementación de SIMPREP | F22: 100 | G22: =+G21 -> 45658 | H22: =+H21 -> 45717 | I22: 4 | J22: MM | K22: Patricio Miranda | L22: Enrique tomo contacto con gerente Felipe Hidalgo
A23: 9 | B23: Premium | C23: Codelco | D23: DRT | E23: Actualización de estandares y procedimientos de planificación, balances, muestreo, etc (replicar estudios realizados para otras operaciones) | F23: 120 | G23: =+G22 -> 45658 | H23: =+H22 -> 45717 | I23: 3 | J23: MM | K23: Sebastian Pizarro
A24: 10 | B24: Premium | C24: Codelco | D24: GRM | E24: Revisiones independientes | F24: 150 | G24: 45717 | H24: 45839 | I24: 3 | J24: MM | K24: Ximena Policroni Galvez | L24: A la espera de licitación en la cual nos tienen contemplados
A25: 11 | B25: Premium | C25: Codelco | D25: GRM | E25: Profundicación de actualización de NCC31 (con apoyo consultor) | F25: 100 | G25: 45689 | H25: =+H23 -> 45717 | I25: 3 | J25: MM | K25: Fernando Marambio | L25: A la espera de cerrar el estudio actual para avanzar con la etapa 2 (profundización)
A26: 12 | B26: Target | C26: Codelco | D26: DCH | E26: Estudios de oportunidad en planes OP (alargar vida del rajo, recuepeación de stocks y los botaderos, zonas de contacto entre ambos rajos) | F26: 200 | G26: 45658 | H26: 45748 | I26: 3 | J26: CC | K26: Juan Cristobal Videla
A27: 13 | B27: Target | C27: Codelco | D27: DET | E27: Analisis de oportunidades del plan minero, generar coberturas debido a atrasos en proyectos | F27: 150 | G27: 45658 | H27: 45748 | I27: 3 | J27: CC | K27: Felipe Hidalgo
A28: 14 | B28: Target | C28: Codelco | D28: DCH | E28: Implementación de SIMPREP | F28: 100 | G28: =+G27 -> 45658 | H28: =+H27 -> 45748 | I28: 4 | J28: MM | K28: Rodrigo Quiroz | L28: Evaluar la mejor estrategia de implementar esto (tanto para DCH y DET)
A29: 15 | B29: Target | C29: Codelco | D29: Distrito Norte | E29: Evaluación de oportunidades de optimización integrada Distrito Norte | F29: 200 | G29: 45658 | J29: CC | K29: Juan San Martin
B30: Target | C30: Codelco | D30: DMH | E30: XXXXXX | G30: =+G29 -> 45658 | J30: CC, MM | K30: Jose Miguel Castro
A34: 29
A35: 30
A36: 31
A37: 32
A38: 33
A39: 34 | B39: Target | C39: Glencore | D39: Lomas Bayas | E39: Planificación - Diseño | F39: 300
A40: 35 | B40: Target | C40: MCI | D40: Los Bronces | E40: Los Bronces Mine Plan Review | F40: 300
A41: 36 | B41: Target | C41: Collahuasi | E41: Planificación - Diseño | F41: 300
A42: 37 | B42: Target | C42: BHP | D42: Escondida | E42: Planificación - Diseño | F42: 500
A43: 38 | B43: Target | C43: BHP | D43: Spence | E43: Planificación - Diseño | F43: 500
A44: 39 | B44: Target | C44: MARA | E44: Planificación - Diseño | F44: 150
A45: 40 | B45: Target | C45: Anglo American | D45: Los Bronces | E45: Planificación - Diseño | F45: 300
A46: 41 | B46: Regular
A47: 42 | B47: Regular | C47: CEMIN | E47: Planificación - Diseño | F47: 90
A48: 43 | B48: Leads | C48: PuCobre | D48: Punta del Cobre | E48: Planificación - Diseño | F48: 150
A49: 44 | B49: Leads | C49: PuCobre | D49: El Espino | E49: Planificación - Diseño | F49: 150
A50: 45 | B50: Leads | C50: Pan American Silver | D50: Florida
A51: 46 | B51: Leads | C51: Pan American Silver | D51: EL Peñon
A52: 47 | B52: Leads | C52: Tesoro Resources Limited
A53: 48 | B53: Leads | C53: PuCobre | D53: Tovaku
A54: 49 | B54: Leads | C54: Fuerte Metals | D54: Placeton
A55: 50 | B55: Leads | C55: Fuerte Metals | D55: El Cofre
A56: 51 | B56: Leads | C56: Freeport-McMoRan Inc. | D56: El Abra
A57: 52 | B57: Leads | C57: Sierra Gorda
A58: 53 | B58: Leads | C58: San geronimo
A59: 54 | B59: Leads | C59: Norte Abierto SpA
A60: 55 | B60: Leads | C60: Pampa Camarones SpA
A61: 56 | B61: Leads | C61: Teck | D61: Quebrada Blanca
A62: 57 | B62: Leads | C62: Santiago Metals Limitada | D62: Delirio
A63: 58 | B63: Leads | C63: Santiago Metals Limitada | D63: PUQUIOS

Sheet Brasil
A1: ID | B1: Tipo Ciente | C1: Empresa | D1: Mina | E1: Descripcion Oportunidad | F1: Monto (USD)
A2: 1 | B2: Premium | C2: Mosaic | D2: Cajati | E2: Cajati P2 | F2: 400 | G2: =+F2*1000 -> 400000
A3: 2 | B3: Premium | C3: Mosaic | D3: Cajati | E3: Mosaic CTV 5Y Plan + Fase II | F3: 350 | G3: =+F3*1000 -> 350000
A4: 3 | B4: Premium | C4: Aura Minerals | E4: Fase 1 | F4: 230 | G4: =+F4*1000 -> 230000
A5: 4 | B5: Premium | C5: Aura Minerals | E5: Fase 2 | F5: 220 | G5: =+F5*1000 -> 220000
A6: 5 | B6: Premium | C6: Lhg | D6: Mina Urucum | E6: Remoción Pilares y Secuecia Operativa | F6: 150 | G6: =+F6*1000 -> 150000
A7: 6 | B7: Target | C7: Vale | E7: Proyectos Subeterraneaos | F7: 220 | G7: =+F7*1000 -> 220000
A8: 7 | B8: Target | C8: Vale | E8: IQS | F8: 450 | G8: =+F8*1000 -> 450000
A9: 8 | B9: Target | C9: EuroChen | E9: Planificación - Diseño | F9: 130 | G9: =+F9*1000 -> 130000
A10: 9 | B10: Target | C10: Alcoa | E10: Planificación - Diseño | F10: 150 | G10: =+F10*1000 -> 150000
A11: 10 | B11: Target | C11: AngloGold Ashanti | E11: Planificación - Diseño | F11: 150 | G11: =+F11*1000 -> 150000 | I11: gerente sumintro y planeamienot mina
A12: 11 | B12: Target | C12: Samarco | E12: Geotecnica y planeamiento | F12: 150 | G12: =+F12*1000 -> 150000 | I12: gerente de geotecnica
A13: 12 | B13: Target | C13: Anglo American | E13: Planificación - Diseño | F13: 300 | G13: =+F13*1000 -> 300000
A14: 13 | B14: Regular | C14: Nexa | D14: Aripuna | E14: Planificación - Diseño | F14: 150 | G14: =+F14*1000 -> 150000
A15: 14 | B15: Leads | C15: Hochschild Mining plc Mara Rosa
A16: 15 | B16: Leads | C16: CBMM
A17: 16 | B17: Leads | C17: CSN
A18: 17 | B18: Leads | C18: Eurochem
A19: 18 | B19: Leads | C19: Erro Copper
A20: 19 | B20: Leads | C20: Gerdau
A21: 20 | B21: Leads | C21: BHP/OZ
A22: 21 | B22: Leads | C22: Vale
A23: 22 | B23: Leads | C23: Arcelor-Mittal
A24: 23 | B24: Leads | C24: Atlantic Nickel
A25: 24 | B25: Leads | C25: Rio Tinto
A26: 25 | B26: Leads | C26: Equinox Gold
... A78: 77 | B78: Leads | C78: Kinrross

Sheet EEUU
A1: ID | B1: Tipo Ciente | C1: Empresa | D1: Mina | E1: Descripcion Oportunidad | F1: Monto 2025 USD | G1: Contrato | H1: Propuesta | I1: Cant Pptas Nuevas
A2: 1 | B2: Premium | C2: Twin Metals Minnesota | D2: Birch Lake - Maturi | E2: Pre-Prefactibilidad Birch Lake + Tunnel acceso a Maturi | F2: 300 | G2: Vigente | H2: NA
A3: 2 | B3: Premium | C3: Twin Metals Minnesota | E3: Prefactibilidad para el conjunto Birch Lake - Maturi | F3: 800 | G3: Nuevo | H3: Nueva | I3: 2
A4: 3 | B4: Regular | C4: EMX Royalty | E4: Technical support for royalty acquisition | F4: 300 | G4: Nuevo | H4: Nueva | I4: 3
A5: 4 | B5: Target | C5: Ivanhoe Electric | D5: Santa Cruz | E5: FS Santa Cruz Project UG - Revision Técnica | F5: 100 | G5: Nuevo | H5: Nueva | I5: 1
A6: 5 | B6: Target | C6: Highland Copper | D6: Copperwood | E6: FS + Detail Engineering | F6: 600 | G6: Nuevo | H6: Vigente
A7: 6 | B7: Target | C7: BHP | D7: Resolution | E7: Caso Base Resolution: diseño , planes, evalaucion | F7: 200 | G7: Vigente | H7: Vigente
A8: 7 | B8: Target | C8: BHP | D8: Resolution | E8: Estudios - Diseños - Planes | F8: 300 | G8: Nuevo | H8: Nueva | I8: 2
A9: 8 | B9: Target | C9: BHP | D9: Antamina | E9: Estudios - Diseños - Planes | F9: 150 | G9: Nuevo | H9: Nueva | I9: 1
A10: 9 | B10: Target | C10: BHP | D10: CU South Australia | E10: Estudios - Diseños - Planes | F10: 200 | G10: Nuevo | H10: Nueva | I10: 2
A11: 10 | B11: Target | C11: Freeport-McMoRan Inc. | D11: PTFI | E11: SIMPREP | F11: 150 | G11: Nuevo | H11: Nueva | I11: 1
A12: 11 | B12: Target | C12: Freeport-McMoRan Inc. | D12: PTFI | E12: Planificación - Diseño | F12: 200 | G12: Nuevo | H12: Nueva | I12: 1
A13: 12 | B13: Target | C13: Newmont Mining | E13: Planificación - Diseño | F13: 200 | G13: Nuevo | H13: Nueva | I13: 2
A14: 13 | B14: Target | C14: Anglo Gold Ashanti | E14: Planificación - Diseño | F14: 200 | G14: Nuevo | H14: Nueva | I14: 2
A15: 14 | B15: Leads | C15: Vale | E15: Planificación - Diseño | F15: 150 | G15: Nuevo | H15: Nueva | I15: 2
A16: 15 | B16: Leads | C16: South 32 | E16: Planificación - Diseño | F16: 100 | G16: Nuevo | H16: Nueva | I16: 1
A17: 16 | B17: Leads | C17: Barrick | E17: Planificación - Diseño | F17: 100 | G17: Nuevo | H17: Nueva | I17: 1
A18: 17 | B18: Leads | C18: Lundin | D18: Eagle | E18: Planificación - Diseño | F18: 100 | G18: Nuevo | H18: Nueva | I18: 1
A19: 18 | B19: Leads | C19: Kinross | E19: Planificación - Diseño | F19: 200 | G19: Nuevo | H19: Nueva | I19: 2
A20: 19 | B20: Leads | C20: Cleveland-Cliffs
A21: 20 | B21: Leads | C21: Pan American Silver Corp.
A22: 21 | B22: Leads | C22: Endeavour Silver Corp.
A23: 22 | B23: Leads | C23: Calibre Mining Corp.
A24: 23 | B24: Leads | C24: FMC Corporation
A25: 24 | B25: Leads | C25: Peabody Energy
A26: 25 | B26: Leads | C26: Southern Copper
A27: 26 | B27: Leads | C27: Midas Gold Corp.
A28: 27 | B28: Leads | C28: Hecla Mining Company
A29: 28 | B29: Leads | C29: Royal Gold
A30: 29 | B30: Leads | C30: Albemarle
A31: 30 | B31: Leads | C31: Mosaic
... A37: 36 | B37: Leads | C37: Hecla mining

Sheet CRM (v1)
B1: Información Iniciativas | N1: Evaluación de Riesgo | T1: Status de las Iniciativas | AK1: Comentarios Seguimiento
A2: País | B2: ID | C2: Tipo | D2: Descripcion Oportunidad | E2: Empresa | F2: Mina | G2: Gestor Comercial | H2: Monto (USD) | I2: Duracion (meses) | J2: Tipo Cliente | K2: Tipo de Mineria | L2: Tipo de Contrato | N2: USD/mes | O2: Riesgo | R2: Valor Final | T2: Contacto Inicial / Enganche | U2: Café/Llamada | V2: Presentación REDCO | W2: Presentación Ad-hoc | X2: Solicitud Propuesta | Y2: Construcción PPT | Z2: Construcción Word | AA2: Presentación Presencial | AB2: Propuesta Enviada | AC2: Seguimiento | AD2: Cierre y Negociación | AE2: ODS | AH2: Estado | AI2: Motivo | AK2: Semana 1 | AL2: Semana 2 | AM2: Semana 3 | AN2: Abril | AO2: Mayo | AP2: Junio | AQ2: Julio | AR2: Agosto | AS2: Septiembre | AT2: Octubre | AU2: Noviembre | AV2: Diciembre
A3: Chile | B3: 1 | C3: Estudios de ing. de minas | D3: Ing de factibilidad: Diseño de botaderos | E3: BPH | F3: Cerro Colorado | G3: PA | H3: 450000 | I3: 6 | J3: Target | K3: OP | L3: Licitación | N3: =+H3/I3 -> 75000 | T3: FALSE | U3: FALSE | V3: TRUE | W3: TRUE | X3: TRUE | Y3: TRUE | Z3: TRUE | AA3: TRUE | AB3: TRUE | AC3: TRUE | AD3: FALSE | AH3: Seguimiento | AI3: N/A | AK3: Coordinar reunión con cliente
A4: Chile | B4: 2 | C4: Estudios de ing. de minas | D4: Ing. Pre factibilidad perforación DHH | E4: Anglo American | F4: Los Bronces | G4: RM | H4: 180000 | I4: 3 | J4: Target | K4: OP | L4: Solicitud Directa | N4: =+H4/I4 -> 60000 | T4: TRUE | U4: TRUE | V4: TRUE | W4: TRUE | X4: TRUE | Y4: TRUE | Z4: FALSE | AA4: TRUE | AB4: TRUE | AC4: TRUE | AD4: FALSE | AH4: Seguimiento | AI4: N/A
A5: Perú | B5: 3 | C5: Estudios de ing. de minas | D5: PFS Ferrobamba Deep | E5: Las Bambas | F5: Ferrobamba | G5: EL | H5: 1100000 | I5: 12 | J5: Target | K5: UG | L5: Licitación | N5: =+H5/I5 -> 91666.667 | T5: FALSE | U5: FALSE | V5: FALSE | W5: FALSE | X5: TRUE | Y5: TRUE | Z5: TRUE | AA5: TRUE | AB5: TRUE | AC5: TRUE | AD5: TRUE | AH5: Seguimiento | AI5: N/A
A6: Chile | B6: 4 | C6: Planificación estratégica | D6: Evaluación caso de negocio explotación SLS | E6: CMP | F6: Algarrobo | G6: FR | H6: 170000 | I6: 3 | J6: Premium | K6: UG | L6: Licitación | N6: =+H6/I6 -> 56666.667 | T6: FALSE | U6: TRUE | V6: FALSE | W6: TRUE | X6: TRUE | Y6: TRUE | Z6: TRUE | AA6: TRUE | AB6: TRUE | AC6: TRUE | AD6: FALSE | AH6: No Adjudicada | AI6: Anulación de licitación
A7: EEUU | B7: 5 | C7: Consultoría minera | D7: Soporte caso de litigio Rio Tinto vs Gobierno Mongolia | E7: Rio Tinto | F7: Oyu Tolgoi | G7: PV | H7: 566000 | I7: 4 | J7: Target | K7: UG | L7: Solicitud Directa | N7: =+H7/I7 -> 141500 | T7: TRUE | U7: TRUE | V7: FALSE | W7: TRUE | X7: TRUE | Y7: TRUE | Z7: FALSE | AA7: TRUE | AB7: TRUE | AC7: TRUE | AD7: TRUE | AH7: Seguimiento | AI7: N/A
T8: FALSE | U8: FALSE | V8: TRUE | W8: FALSE | X8: FALSE | Y8: FALSE | Z8: FALSE | AA8: FALSE | AB8: FALSE | AC8: FALSE | AD8: FALSE
T9: FALSE | U9: FALSE | V9: TRUE | W9: FALSE | X9: FALSE | Y9: FALSE | Z9: FALSE | AA9: TRUE | AB9: FALSE | AC9: FALSE | AD9: FALSE
T10: FALSE | U10: FALSE | V10: FALSE | W10: FALSE | X10: FALSE | Y10: FALSE | Z10: FALSE | AA10: FALSE | AB10: FALSE | AC10: FALSE | AD10: FALSE
T11: FALSE | U11: FALSE | V11: FALSE | W11: FALSE | X11: FALSE | Y11: FALSE | Z11: FALSE | AA11: FALSE | AB11: FALSE | AC11: FALSE | AD11: FALSE
T12: FALSE | U12: FALSE | V12: FALSE | W12: FALSE | X12: FALSE | Y12: FALSE | Z12: FALSE | AA12: FALSE | AB12: FALSE | AC12: FALSE | AD12: FALSE
T13: FALSE | U13: FALSE | V13: FALSE | W13: FALSE | X13: FALSE | Y13: FALSE | Z13: FALSE | AA13: FALSE | AB13: FALSE | AC13: FALSE | AD13: FALSE
T14: FALSE | U14: FALSE | V14: FALSE | W14: FALSE | X14: FALSE | Y14: FALSE | Z14: FALSE | AA14: FALSE | AB14: FALSE | AC14: FALSE | AD14: FALSE
T15: FALSE | U15: FALSE | V15: FALSE | W15: FALSE | X15: FALSE | Y15: FALSE | Z15: FALSE | AA15: FALSE | AB15: FALSE | AC15: FALSE | AD15: FALSE
T16: FALSE | U16: FALSE | V16: FALSE | W16: FALSE | X16: FALSE | Y16: FALSE | Z16: FALSE | AA16: FALSE | AB16: FALSE | AC16: FALSE | AD16: FALSE
T17: FALSE | U17: FALSE | V17: FALSE | W17: FALSE | X17: FALSE | Y17: FALSE | Z17: FALSE | AA17: FALSE | AB17: FALSE | AC17: FALSE | AD17: FALSE
T18: FALSE | U18: FALSE | V18: FALSE | W18: FALSE | X18: FALSE | Y18: FALSE | Z18: FALSE | AA18: FALSE | AB18: FALSE | AC18: FALSE | AD18: FALSE

Sheet Resumen cantidades
A3: Cuenta de Monto (USD) | B3: Etiquetas de columna
A4: Etiquetas de fila | B4: Cierre y Negociacón | C4: Construcción Propuesta | D4: Contacto Inicial (Enganche) | E4: Iniciativa | F4: No Adjudicada | G4: ODS | H4: Presentación Ad-Hoc | I4: Seguimiento | J4: Total general
A5: Brasil | B5: 1 | C5: 4 | D5: 1 | E5: 10 | F5: 2 | I5: 4 | J5: 22
A6: Chile | B6: 4 | C6: 4 | D6: 6 | E6: 21 | F6: 2 | G6: 6 | H6: 1 | I6: 8 | J6: 52
A7: EEUU | E7: 17 | G7: 1 | I7: 2 | J7: 20
A8: Perú | B8: 2 | C8: 1 | D8: 6 | E8: 7 | F8: 3 | G8: 3 | I8: 4 | J8: 26
A9: Total general | B9: 7 | C9: 9 | D9: 13 | E9: 55 | F9: 7 | G9: 10 | H9: 1 | I9: 18 | J9: 120
B13: País | C13: Iniciativa | D13: Contacto Inicial (Enganche) | E13: Construcción Propuesta | F13: Seguimiento | G13: Cierre y Negociación | H13: ODS | I13: Total General
B14: Cantidad | C14: =+GETPIVOTDATA("Monto (USD)",$A$3,"Etapa","Iniciativa ") -> 55 | D14: =+GETPIVOTDATA("Monto (USD)",$A$3,"Etapa","Contacto Inicial (Enganche)") -> 13 | E14: =+GETPIVOTDATA("Monto (USD)",$A$3,"Etapa","Construcción Propuesta") -> 9 | F14: =+GETPIVOTDATA("Monto (USD)",$A$3,"Etapa","Seguimiento") -> 18 | G14: =+GETPIVOTDATA("Monto (USD)",$A$3,"Etapa","Cierre y Negociacón") -> 7 | H14: =+GETPIVOTDATA("Monto (USD)",$A$3,"Etapa","ODS") -> 10 | I14: =+SUM(C14:G14) -> 102
B15: Dif | C15: -2 | D15: 1 | E15: -2 | F15: -5 | H15: 3 | I15: 1

Sheet Gestión
B1: Etapa | C1: (Varios elementos)
B3: Etiquetas de fila | C3: Suma de Monto (USD)
B4: Premium | C4: 1756000 | S4: Marzo | U4: Abril
B5: Regular | C5: 380000 | M5: País | N5: Ventas Enero | O5: Ventas Febrero | P5: Proyección Marzo | Q5: Proyección Abril | R5: Proyección (vendido) | S5: Proyección (posibles)
B6: Target | C6: 556000 | M6: Brasil | N6: 0 | O6: 0 | P6: =+SUM(R6:S6) -> 474400 | Q6: 630000 | R6: 380000 | S6: 94400
B7: Total general | C7: 2692000 | M7: Chile | N7: 450000 | O7: 211000 | P7: =+SUM(R7:S7) -> 310000 | Q7: 1560000 | R7: 30000 | S7: 280000
J8: 9,5 seguimiento y construcción | M8: EEUU | N8: 116000 | O8: 0 | P8: =+SUM(R8:S8) -> 0 | Q8: 0 | R8: 0 | S8: 0
M9: Perú | N9: 490000 | O9: 1035000 | P9: =+SUM(R9:S9) -> 108000 | Q9: 0 | R9: 20000 | S9: 88000
M10: Total | N10: =+SUM(N6:N9) -> 1056000 | O10: =+SUM(O6:O9) -> 1246000 | P10: =+SUM(P6:P9) -> 892400 | Q10: =+SUM(Q6:Q9) -> 2190000 | R10: =+SUM(R6:R9) -> 430000 | S10: =+SUM(S6:S9) -> 462400
M12: Propuestas
L14: Ítem | M14: Unidad | N14: 45658 | O14: 45689 | R14: S1 Mar-25 | S14: Media Acu
L15: Propuestas emitidas | M15: # | N15: 8 | O15: 10 | R15: 5 | S15: 0.35
M16: MUS$ | N16: 2.2 | O16: 2.6 | R16: 0.57
L17: Propuestas adjudicadas | M17: # | N17: 8 | O17: 7 | R17: 0 | S17: 0.18
F18: Etiquetas de fila | G18: Suma de Monto (USD) | H18: % | M18: kUS$ | N18: 1.1 | O18: 1.3 | R18: 0.4
F19: Las Bambas | G19: 1125000 | H19: =+G19/$G$29 -> 0.41178624
F20: Mosaic | G20: 380000 | H20: =+G20/$G$29 -> 0.13909224
F21: Minsur | G21: 240000 | H21: =+G21/$G$29 -> 0.087847731 | N21: Chile | O21: =0.66/2.4 -> 0.275
F22: Anglo American | G22: 236000 | H22: =+G22/$G$29 -> 0.086383602 | N22: Peru | O22: =1.5/2.4 -> 0.625
F23: First Quantum | G23: 200000 | H23: =+G23/$G$29 -> 0.073206442
F24: OCP | G24: 180000 | H24: =+G24/$G$29 -> 0.065885798
F25: Lundin | G25: 120000 | H25: =+G25/$G$29 -> 0.043923865
F26: BHP | G26: 120000 | H26: =+G26/$G$29 -> 0.043923865
F27: Twin Metals Minnesota | G27: 116000 | H27: =+G27/$G$29 -> 0.042459736
F28: CMP | G28: 15000 | H28: =+G28/$G$29 -> 0.0054904832
F29: Total general | G29: 2732000 | H29: =+G29/$G$29 -> 1
L45: Etiquetas de fila | M45: Suma de Monto (USD)
L46: Consultoría minera | M46: 56000 | N46: =+M46/$M$50 -> 0.020497804
L47: Ing. de minas | M47: 2071000 | N47: =+M47/$M$50 -> 0.75805271
L48: Planificación estratégica | M48: 395000 | N48: =+M48/$M$50 -> 0.14458272
L49: Simulación de sistemas mineros | M49: 210000 | N49: =+M49/$M$50 -> 0.076866764
M50: =+SUM(M46:M49) -> 2732000
L55: Premium | M55: 921000 | N55: =+M55/$M$58 -> 0.33711567
L56: Regular | M56: 380000 | N56: =+M56/$M$58 -> 0.13909224
L57: Target | M57: 1431000 | N57: =+M57/$M$58 -> 0.52379209
M58: =+SUM(M55:M57) -> 2732000

Sheet Posbiles
A1: ID | B1: País | C1: Descripcion Oportunidad | D1: Empresa | E1: Mina | F1: Gestor Comercial | G1: Monto (USD) | H1: Tasa de ajuste | I1: Monto (USD) | L1: Duracion (meses) | M1: USD/mes | N1: Tipo Cliente | O1: Forma de Venta
A2: 1 | B2: Perú | C2: Planificación de largo plazo (LOM) integrada con iniciativas + Potenciales | D2: Minsur | E2: San Rafael | F2: MF | G2: 110000 | H2: 0.8 | I2: =+H2*G2 -> 88000 | L2: 3 | M2: 53333.333 | N2: Premium | O2: Reventa
A3: 2 | B3: Brasil | C3: Evaluación estocástica de escenarios con herramienta SIMPLAN | D3: CBMM | F3: AS | G3: 118000 | H3: 0.8 | I3: =+H3*G3 -> 94400 | L3: 3 | M3: 39333.333 | N3: Target | O3: Busqueda Activa
A4: 3 | B4: Chile | C4: Tunel exploración | D4: BHP | E4: Escondida | F4: PV | G4: 200000 | H4: 0.8 | I4: =+H4*G4 -> 160000 | L4: 3 | M4: 66666.667 | N4: Target | O4: Busqueda Activa
A5: 4 | B5: Chile | C5: Opportunity Assessment para optimizar el proyecto Cerro Colorado (LOM estrategico) | D5: BHP | E5: Cerro Colorado | F5: ER | G5: 240000 | H5: 0.5 | I5: =+H5*G5 -> 120000 | L5: 5 | M5: 48000 | N5: Target | O5: Reventa
A7: Marzo | G7: =+SUM(G2:G5) -> 668000 | H7: Tasa de ajuste | I7: =+SUM(I2:I5) -> 462400
A8: 4 | B8: Chile | C8: Evaluación caso de negocio explotación SLS | D8: CMP | E8: Algarrobo | F8: FR | G8: 170000 | H8: 0.8 | I8: =+H8*G8 -> 136000 | L8: 3 | M8: 56666.667 | N8: Premium | O8: Solicitud Directa
A9: 17 | B9: Chile | C9: Ing Basica MHD UG | D9: Lundin | E9: Candelaria | F9: RM | G9: 1380000 | H9: 0.5 | I9: =+H9*G9 -> 690000 | L9: 5 | M9: 276000 | N9: Premium | O9: Licitación
A10: 66 | B10: Chile | C10: Planificación LOM Blue Sky | D10: Lundin | E10: Caserones | F10: ER | G10: 200000 | H10: 0.5 | I10: =+H10*G10 -> 100000 | L10: 3 | M10: 66666.667 | N10: Target | O10: Reventa
A11: 83 | B11: Chile | C11: Auditoría de las bases de datos geomecánicas y actualización de modelo geomecánico | D11: Lundin | E11: Candelaria | F11: CH | G11: 390000 | H11: 0.8 | I11: =+H11*G11 -> 312000 | L11: 3 | M11: 130000 | N11: Premium
A12: 87 | B12: Chile | C12: Soporte Romeral, construcción túnel exploratorio | D12: CMP | E12: Romeral | F12: FR | G12: 646000 | H12: 0.5 | I12: =+H12*G12 -> 323000 | L12: 18 | M12: 35888.889 | N12: Premium
A13: 39 | B13: Brasil | C13: Ing PFS mina UG | D13: Aura Minerals | E13: Mina Paiol | F13: AS | G13: 288000 | H13: 0.8 | I13: =+H13*G13 -> 230400 | L13: 3 | M13: 96000 | N13: Target | O13: Reventa
A14: 60 | B14: Brasil | C14: Ingenieria para construcción tunel de exploración | D14: Aura Minerals | E14: Mina Paiol | F14: AF | G14: 72000 | H14: 0.8 | I14: =+H14*G14 -> 57600 | L14: 3 | M14: 24000 | N14: Target | O14: Reventa
A15: 112 | B15: Brasil | C15: Acompañamiento LOM y capacitación Simplan para Cajati | D15: Mosaic | E15: Cajati | F15: AS | G15: 84000 | H15: 0.8 | I15: =+H15*G15 -> 67200 | L15: 3 | M15: 28000 | N15: Premium | O15: Reventa
A16: 116 | B16: Brasil | C16: PEA Projecto Furnas | D16: Ero Copper | E16: Furnas | F16: AS | G16: 550000 | H16: 0.5 | I16: =+H16*G16 -> 275000 | L16: 6 | M16: 91666.667 | N16: Target | O16: Busqueda Activa
A17: Abril | G17: =+SUM(G8:G16) -> 3780000 | I17: =+SUM(I8:I16) -> 2191200

Sheet Tabla Budget
C2: Proyección EDP | R2: Proyección Venta
C3: Tipo | D3: 45658 | E3: 45689 | F3: 45717 | G3: 45748 | H3: 45778 | I3: 45809 | J3: 45839 | K3: 45870 | L3: 45901 | M3: 45931 | N3: 45962 | O3: 45992 | P3: Total | R3: Tipo | S3: 45658 | T3: 45689 | U3: 45717 | V3: 45748 | W3: 45778 | X3: 45809 | Y3: 45839 | Z3: 45870 | AA3: 45901 | AB3: 45931 | AC3: 45962 | AD3: 45992 | AE3: Total
C4: Remanente | D4: 753937 | E4: 565714 | F4: 326816 | G4: 326816 | H4: 191513 | I4: 191513 | J4: 161442 | K4: 19435 | L4: 19435 | M4: 19435 | N4: 19435 | O4: 19435 | P4: =+SUM(D4:O4) -> 2614926 | R4: Remanente | S4: 0 | T4: 0 | U4: 0 | V4: 0 | W4: 0 | X4: 0 | Y4: 0 | Z4: 0 | AA4: 0 | AB4: 0 | AC4: 0 | AD4: 0 | AE4: =+SUM(S4:AD4) -> 0
C5: Vendido | E5: =+J21 -> 277666.67 | F5: =+K21 -> 327666.67 | G5: =+L21 -> 252666.67 | H5: =+M21 -> 36000 | I5: =+N21 -> 36000 | J5: =+O21 -> 0 | K5: =+P21 -> 0 | L5: =+Q21 -> 0 | ... O5: =+T21 -> 0 | P5: =+SUM(D5:O5) -> 930000 | R5: Vendido | S5: 930000 | T5: 0 | U5: 0 | V5: 0 | W5: 0 | X5: 0 | Y5: 0 | Z5: 0 | AA5: 0 | AB5: 0 | AC5: 0 | AD5: 0 | AE5: =+SUM(S5:AD5) -> 930000
C6: Proyección | D6: =+J43 -> 0 | E6: =+K43 -> 0 | F6: =+L43 -> 244561.67 | G6: =+M43 -> 460753.33 | H6: =+N43 -> 631753.33 | I6: =+O43 -> 496866.67 | J6: =+P43 -> 427960 | K6: =+Q43 -> 342626.67 | ... O6: =+U43 -> 134875 | P6: =+SUM(D6:O6) -> 3527440 | R6: Proyección | T6: 1008000 | U6: 1590000 | V6: 1406000 | W6: 0 | X6: 0 | Y6: 0 | Z6: 0 | AA6: 0 | AB6: 0 | AC6: 0 | AD6: 0 | AE6: =+SUM(S6:AD6) -> 4004000
C7: Pipeline | J7: =845000-SUM(J4:J6) -> 255598 | K7: =845000-SUM(K4:K6) -> 482938.33 | L7: =845000-SUM(L4:L6) -> 482938.33 | M7: =845000-SUM(M4:M6) -> 515023.33 | N7: =845000-SUM(N4:N6) -> 690690 | O7: =+G100-SUM(J7:N7) -> 502212 | P7: =+SUM(D7:O7) -> 2929400 | R7: Pipeline | S7: 0 | T7: 0 | U7: 0 | V7: 0 | W7: =+G100/4 -> 732350 | X7: =+W7 -> 732350 | Y7: =+X7 -> 732350 | Z7: =+Y7 -> 732350 | AB7: 0 | AC7: 0 | AD7: 0 | AE7: =+SUM(S7:AD7) -> 2929400 | AF7: =+AE7-G100 -> 0 | AG7: =+AF7/3 -> 0 | AJ7: País | AK7: Monto
C8: Total | D8: =+SUM(D4:D7) -> 753937 | E8: =+SUM(E4:E7) -> 843380.67 | F8: =+SUM(F4:F7) -> 899044.33 | G8: =+SUM(G4:G7) -> 1040236 | H8: =+SUM(H4:H7) -> 859266.33 | I8: =+SUM(I4:I7) -> 724379.67 | J8: =+SUM(J4:J7) -> 845000 | K8: =+SUM(K4:K7) -> 845000 | ... P8: =+SUM(P4:P7) -> 10001766 | R8: Por Identificar | S8: 0 | T8: 0 | U8: 0 | V8: 0 | W8: 0 | X8: 0 | Y8: 0 | AA8: 800000 | AB8: 800000 | AC8: 800000 | AD8: =+AE12-10263400 -> 536600 | AE8: =+SUM(S8:AD8) -> 2936600 | AJ8: Perú | AK8: =+(A29+SUM(A32:A34)+SUM(A75:A86))/1000000 -> 1.00262 | AL8: =+AK8/$AK$14 -> 0.13825256 | AN8: =+AL8*$AN$13 -> 1.4931276
R9: Total Pipeline | S9: =+SUM(S4:S7) -> 930000 | T9: =+SUM(T4:T7) -> 1008000 | U9: =+SUM(U4:U7) -> 1590000 | V9: =+SUM(V4:V7) -> 1406000 | W9: =+SUM(W4:W7) -> 732350 | X9: =+SUM(X4:X7) -> 732350 | Y9: =+SUM(Y4:Y7) -> 732350 | Z9: =+SUM(Z4:Z7) -> 732350 | ... AE9: =+SUM(AE4:AE7) -> 7863400 | AJ9: Chile | AK9: =(SUM(G17:G19)+SUM(A26:A28)+A30+SUM(A37:A39)+SUM(A87:A99))/1000000 -> 3.4526 | AL9: =+AK9/$AK$14 -> 0.47608345 | AN9: =+AL9*$AN$13 -> 5.1417012
R10: Total | S10: =+SUM(S4:S8) -> 930000 | T10: =+SUM(T4:T8) -> 1008000 | U10: =+SUM(U4:U8) -> 1590000 | V10: =+SUM(V4:V8) -> 1406000 | W10: =+SUM(W4:W8) -> 732350 | X10: =+SUM(X4:X8) -> 732350 | Y10: =+SUM(Y4:Y8) -> 732350 | Z10: =+SUM(Z4:Z8) -> 732350 | ... AD10: =+SUM(AD4:AD8) -> 536600 | AE10: =+SUM(AE5:AE8) -> 10800000 | AJ10: Brasil | AK10: =(SUM(A40:A42)+SUM(A65:A74))/1000000 -> 2.17511 | AL10: =+AK10/$AK$14 -> 0.29992871 | AN10: =+AL10*$AN$13 -> 3.2392301
AJ11: EEUU | AK11: =(SUM(A35:A36)+A31+SUM(A49:A63))/1000000 -> 0.62176 | AL11: =+AK11/$AK$14 -> 0.085735285 | AN11: =+AL11*$AN$13 -> 0.92594107
R12: Meta | S12: =10800000/12 -> 900000 | T12: =10800000/12 -> 900000 | U12: =10800000/12 -> 900000 | V12: =10800000/12 -> 900000 | W12: =10800000/12 -> 900000 | X12: =10800000/12 -> 900000 | Y12: =10800000/12 -> 900000 | Z12: =10800000/12 -> 900000 | ... AD12: =10800000/12 -> 900000 | AE12: =+SUM(S12:AD12) -> 10800000 | AJ12: Otros | AK12: =(AE12/1000000-SUM(AK8:AK11)) -> 3.54791
C13: Vendido | J13: Febrero | K13: Marzo | L13: Abril | M13: Mayo | N13: Junio | AN13: 10.8
C14: País | D14: Descripcion Oportunidad | E14: Empresa | F14: Mina | G14: Monto (USD) | H14: Duración | I14: Tasa de ajuste | J14: EDP 1 | K14: EDP 2 | L14: EDP 3 | M14: EDP 4 | N14: EDP 5 | O14: EDP 6 | P14: EDP 7 | Q14: EDP 8 | R14: EDP 9 | S14: EDP 10 | T14: EDP 11 | U14: EDP 12 | V14: Error | AJ14: total | AK14: =+AK8+AK9+AK10+AK11 -> 7.25209
C15: Perú | D15: Diagnostico operaciónal y construcción de planes alternativos (Blue Sky y potencial) | E15: OCP | F15: Cobriza | G15: 180000 | H15: 3 | I15: 0 | J15: =+G15/H15 -> 60000 | K15: 80000 | L15: 40000 | V15: =+G15-SUM(J15:U15) -> 0
C16: Perú | D16: Preparación IV MEIA San German | E16: Minsur | F16: San Rafael | G16: 240000 | H16: 3 | I16: 0 | J16: =+G16/H16 -> 80000 | K16: =+J16 -> 80000 | L16: =+K16 -> 80000 | V16: =+G16-SUM(J16:U16) -> 0
C17: Chile | D17: Ing. Pre factibilidad perforación HHD | E17: Anglo American | F17: Los Bronces | G17: 180000 | H17: 5 | I17: 0 | J17: =+G17/H17 -> 36000 | K17: =+J17 -> 36000 | L17: 36000 | M17: 36000 | N17: =+G17-SUM(J17:M17) -> 36000 | V17: =+G17-SUM(J17:U17) -> 0
C18: Chile | D18: LOM estrategico | E18: First Quantum | F18: Cobre Panama | G18: 200000 | H18: 3 | I18: 0 | J18: =+G18/H18 -> 66666.667 | K18: =+J18 -> 66666.667 | L18: =+K18 -> 66666.667 | V18: =+G18-SUM(J18:U18) -> 0
C19: Chile | D19: Análisis de Cuellos de Botella 2YB26 | E19: BHP | F19: Spence | G19: 60000 | H19: 2 | I19: 0 | K19: =+G19/H19 -> 30000 | L19: =+K19 -> 30000 | V19: =+G19-SUM(J19:U19) -> 0
C20: Perú | D20: Construcción escenarios ing conceptual | E20: Las Bambas | F20: Ferrobamba | G20: 70000 | H20: 2 | I20: 0 | J20: =+G20/H20 -> 35000 | K20: 35000 | V20: =+G20-SUM(J20:U20) -> 0
F21: Total | G21: =+SUM(G15:G20) -> 930000 | J21: =+SUM(J15:J20) -> 277666.67 | K21: =+SUM(K15:K20) -> 327666.67 | L21: =+SUM(L15:L20) -> 252666.67 | M21: =+SUM(M15:M20) -> 36000 | N21: =+SUM(N15:N20) -> 36000 | O21: =+SUM(O15:O20) -> 0 | P21: =+SUM(P15:P20) -> 0 | Q21: =+SUM(Q15:Q20) -> 0 | ... V21: =+SUM(V15:V20) -> 0
B24: Proyección | J24: Enero | K24: Febrero | L24: Marzo | M24: Abril | N24: Mayo | O24: Junio | P24: Julio | Q24: Agosto | R24: Septiembre | S24: Octubre | T24: Noviembre | U24: Diciembre
B25: Tipo Cliente | C25: País | D25: Descripcion Oportunidad | E25: Empresa | F25: Mina | G25: Monto (USD) | H25: Duración | I25: Tasa de ajuste | J25: EDP 1 | K25: EDP 2 | L25: EDP 3 | M25: EDP 4 | N25: EDP 5 | O25: EDP 6 | P25: EDP 7 | Q25: EDP 8 | R25: EDP 9 | S25: EDP 10 | T25: EDP 11 | U25: EDP 12 | V25: Error
A26: =+G26*I26 -> 136000 | B26: Premium | C26: Chile | D26: Evaluación caso de negocio explotación SLS | E26: CMP | F26: Algarrobo | G26: 170000 | H26: 3 | I26: 0.8 | N26: 45333.333 | O26: 45333.333 | P26: 45333.333 | V26: =0.8*G26-SUM(J26:U26) -> 0 | W26: =+G26*I26 -> 136000
A27: =+G27*I27 -> 720000 | B27: Premium | C27: Chile | D27: Sistema Integrado de Gestión de Riesgos Geotécnicos | E27: Capstone Copper | F27: Todas | G27: 900000 | H27: 12 | I27: 0.8 | O27: 60000 | P27: 60000 | Q27: 60000 | R27: 60000 | S27: 60000 | T27: 60000 | U27: 60000 | V27: =0.8*G27-SUM(J27:U27) -> 300000 | W27: =+G27*I27 -> 720000 | AA27: =15*12*150000*0.4 -> 10800000
A28: =+G28*I28 -> 1104000 | B28: Premium | C28: Chile | D28: Ing Basica MHD UG | E28: Lundin | F28: Candelaria | G28: 1380000 | H28: 5 | I28: 0.8 | M28: 50000 | N28: =+((G28*I28)-50000)/6 -> 175666.67 | O28: =+N28 -> 175666.67 | P28: =+O28 -> 175666.67 | Q28: =+O28 -> 175666.67 | R28: =+Q28 -> 175666.67 | S28: =+R28 -> 175666.67 | V28: =0.8*G28-SUM(J28:U28) -> 0 | W28: =+G28*I28 -> 1104000
A29: =+G29*I29 -> 120000 | B29: Premium | C29: Perú | D29: Planificación de largo plazo (LOM) integrada con iniciativas | E29: Minsur | F29: San Rafael | G29: 150000 | H29: 3 | I29: 0.8 | L29: =+(G29/H29)*0.8 -> 40000 | M29: 40000 | N29: 40000 | V29: =0.8*G29-SUM(J29:U29) -> 0 | W29: =+G29*I29 -> 120000 | AA29: 7.9
A30: =+G30*I30 -> 120000 | B30: Premium | C30: Chile | D30: Auditoría de las bases de datos geomecánicas y actualización de modelo geomecánico | E30: Lundin | F30: Candelaria | G30: 150000 | H30: 3 | I30: 0.8 | L30: =+(G30/H30)*0.8 -> 40000 | M30: 40000 | N30: 40000 | V30: =0.8*G30-SUM(J30:U30) -> 0 | W30: =+G30*I30 -> 120000 | AA30: =2.9+AA29 -> 10.8
A31: =+G31*I31 -> 140000 | B31: Premium | C31: EEUU | D31: BL/Northmet Integration mine planning | E31: Twin Metals Minnesota | F31: birch Lake - Northmet | G31: 175000 | H31: 3 | I31: 0.8 | L31: =+(G31/H31)*0.8 -> 46666.667 | M31: 46666.667 | N31: 46666.667 | V31: =0.8*G31-SUM(J31:U31) -> 0 | W31: =+G31*I31 -> 140000
A32: =+G32*I32 -> 550000 | B32: Otros | C32: Perú | D32: PFS Ferrobamba Deep | E32: Las Bambas | F32: Ferrobamba | G32: 1100000 | H32: 13 | I32: 0.5 | M32: 40000 | N32: =+M32 -> 40000 | O32: 80000 | P32: 80000 | Q32: 40000 | R32: =+Q32 -> 40000 | S32: =+R32 -> 40000 | T32: =+S32 -> 40000 | U32: =+T32 -> 40000 | V32: =I32*G32-SUM(J32:U32) -> 110000 | W32: =+G32*I32 -> 550000
A33: =+G33*I33 -> 63800 | B33: Otros | C33: Perú | D33: Revisión de validación reportes R&R (15 assets) | E33: Volcan | G33: 220000 | H33: 3 | I33: 0.29 | M33: 21266.667 | N33: 21266.667 | O33: =+N33 -> 21266.667 | V33: =I33*G33-SUM(J33:U33) -> 0 | W33: =+G33*I33 -> 63800
A34: =+G34*I34 -> 31320 | B34: Otros | C34: Perú | D34: Evaluación de cumplimiento de planes de corto plazo | E34: Antamina | F34: Antamina | G34: 108000 | H34: 3 | I34: 0.29 | M34: 10440 | N34: 10440 | O34: 10440 | V34: =I34*G34-SUM(J34:U34) -> 0 | W34: =+G34*I34 -> 31320
A35: =+G35*I35 -> 118860 | B35: Otros | C35: EEUU | D35: Soporte caso de litigio Rio Tinto vs Gobierno Mongolia | E35: Rio Tinto | F35: Oyu Tolgoi | G35: 566000 | H35: 3 | I35: 0.21 | L35: =+I35*G35/H35 -> 39620 | M35: =+L35 -> 39620 | N35: =+M35 -> 39620 | V35: =I35*G35-SUM(J35:U35) -> 0 | W35: =+G35*I35 -> 118860
A36: =+G36*I36 -> 71400 | B36: Otros | C36: EEUU | D36: Technical Expert Support of the plaintiff’s allegation to Alio Gold Inc | E36: McCarthy Abogados | F36: Alio Gold | G36: 340000 | H36: 3 | I36: 0.21 | L36: =+I36*G36/H36 -> 23800 | M36: =+L36 -> 23800 | N36: =+M36 -> 23800 | V36: =I36*G36-SUM(J36:U36) -> 0 | W36: =+G36*I36 -> 71400
A37: =+G37*I37 -> 33600 | B37: Otros | C37: Chile | D37: Estudio integral de LOM Mina Guarelo | E37: CAP | F37: Guarelo | G37: 60000 | H37: 2 | I37: 0.56 | M37: =+G37*I37/H37 -> 16800 | N37: =+M37 -> 16800 | V37: =I37*G37-SUM(J37:U37) -> 0 | W37: =+G37*I37 -> 33600
A38: =+G38*I38 -> 56000 | B38: Otros | C38: Chile | D38: Estudio de productividad | E38: Anglo American | F38: Los Bronces | G38: 100000 | H38: 2 | I38: 0.56 | M38: 28000 | N38: 28000 | V38: =I38*G38-SUM(J38:U38) -> 0 | W38: =+G38*I38 -> 56000
A39: =+G39*I39 -> 19600 | B39: Otros | C39: Chile | D39: Análisis de confiabilidad y detección de cuellos de botella del LoA 25 – Proyecto SCUT | E39: BHP | F39: Spence | G39: 35000 | H39: 1 | I39: 0.56 | L39: =+G39*I39 -> 19600 | V39: =I39*G39-SUM(J39:U39) -> 0 | W39: =+G39*I39 -> 19600
A40: =+G40*I40 -> 418500 | B40: Otros | C40: Brasil | D40: Servicio IQS para nueve assets | E40: Vale | G40: 450000 | H40: 12 | I40: 0.93 | L40: =+G40*I40/H40 -> 34875 | M40: =+L40 -> 34875 | N40: =+M40 -> 34875 | O40: =+N40 -> 34875 | P40: =+O40 -> 34875 | Q40: =+P40 -> 34875 | R40: =+Q40 -> 34875 | S40: =+R40 -> 34875 | T40: =+S40 -> 34875 | U40: =+T40 -> 34875 | V40: =I40*G40-SUM(J40:U40) -> 69750 | W40: =+G40*I40 -> 418500
A41: =+G41*I41 -> 192510 | B41: Otros | C41: Brasil | D41: PLANO AMBIENTAL DE FECHAMENTO CGM | E41: Alcoa | G41: 207000 | H41: 6 | I41: 0.93 | M41: =+G41*I41/H41 -> 32085 | N41: =+M41 -> 32085 | O41: =+N41 -> 32085 | P41: =+O41 -> 32085 | Q41: =+P41 -> 32085 | R41: =+Q41 -> 32085 | V41: =I41*G41-SUM(J41:U41) -> 0 | W41: =+G41*I41 -> 192510
A42: =+G42*I42 -> 111600 | B42: Otros | C42: Brasil | D42: Ingenieria Conceptual avanzada de tunel de exploración | E42: Aura Minerals | F42: Mina Paiol | G42: 120000 | H42: 3 | I42: 0.93 | M42: =+G42*I42/H42 -> 37200 | N42: =+M42 -> 37200 | O42: =+N42 -> 37200 | V42: =I42*G42-SUM(J42:U42) -> 0 | W42: =+G42*I42 -> 111600
F43: Total | G43: =+SUMPRODUCT(G26:G42,I26:I42) -> 4007190 | J43: =+SUM(J26:J42) -> 0 | K43: =+SUM(K26:K42) -> 0 | L43: =+SUM(L26:L42) -> 244561.67 | M43: =+SUM(M26:M42) -> 460753.33 | N43: =+SUM(N26:N42) -> 631753.33 | O43: =+SUM(O26:O42) -> 496866.67 | P43: =+SUM(P26:P42) -> 427960 | Q43: =+SUM(Q26:Q42) -> 342626.67 | ... W43: =+SUM(W26:W42) -> 4007190
X44: Enero | Y44: Febrero | Z44: Marzo | AA44: Abril | AB44: Mayo | AC44: Junio | AD44: Julio | AE44: Agosto | AF44: Septiembre | AG44: Octubre | AH44: Noviembre | AI44: Diciembre
X45: 845000 | Y45: 845000 | Z45: 845000 | AA45: 845000 | AB45: 845000 | AC45: 845000 | AD45: 845000 | AE45: 845000 | AF45: 845000 | AG45: 845000 | AH45: 845000 | AI45: 845000
B47: Pipeline | J47: Enero | K47: Febrero | L47: Marzo | M47: Abril | N47: Mayo | O47: Junio | P47: Julio | Q47: Agosto | R47: Septiembre | S47: Octubre | T47: Noviembre | U47: Diciembre
B48: Tipo Cliente | C48: País | D48: Descripcion Oportunidad | E48: Empresa | F48: Mina | G48: Monto (USD) | H48: Duración | I48: Tasa de ajuste | J48: EDP 1 | K48: EDP 2 | L48: EDP 3 | M48: EDP 4 | N48: EDP 5 | O48: EDP 6 | P48: EDP 7 | Q48: EDP 8 | R48: EDP 9 | S48: EDP 10 | T48: EDP 11 | U48: EDP 12 | V48: Error
A49: =+G49*I49 -> 33000 | B49: Otros | C49: EEUU | D49: Technical support for royalty acquisition | E49: EMX Royalty | G49: 300000 | H49: 3 | I49: 0.11 | O49: =+I49*G49/H49 -> 11000 | P49: =+O49 -> 11000 | Q49: =+P49 -> 11000 | X49: EEUU | Y49: 0.21
A50: =+G50*I50 -> 11000 | B50: Otros | C50: EEUU | D50: FS Santa Cruz Project UG - Revision Técnica | E50: Ivanhoe Electric | F50: Santa Cruz | G50: 100000 | H50: 3 | I50: 0.11 | O50: =+I50*G50/H50 -> 3666.6667 | P50: =+O50 -> 3666.6667 | Q50: =+P50 -> 3666.6667 | X50: Chile | Y50: 0.05
A51: =+G51*I51 -> 22000 | B51: Otros | C51: EEUU | D51: Caso Base Resolution: diseño , planes, evalaucion | E51: BHP | F51: Resolution | G51: 200000 | H51: 3 | I51: 0.11 | O51: =+I51*G51/H51 -> 7333.3333 | P51: =+O51 -> 7333.3333 | Q51: =+P51 -> 7333.3333 | X51: Perú | Y51: 0.29
A52: =+G52*I52 -> 33000 | B52: Otros | C52: EEUU | D52: Estudios - Diseños - Planes | E52: BHP | F52: Resolution | G52: 300000 | H52: 3 | I52: 0.11 | O52: =+I52*G52/H52 -> 11000 | P52: =+O52 -> 11000 | Q52: =+P52 -> 11000
A53: =+G53*I53 -> 16500 | B53: Otros | C53: EEUU | D53: Estudios - Diseños - Planes | E53: BHP | F53: Antamina | G53: 150000 | H53: 3 | I53: 0.11 | O53: =+I53*G53/H53 -> 5500 | P53: =+O53 -> 5500 | Q53: =+P53 -> 5500
A54: =+G54*I54 -> 22000 | B54: Otros | C54: EEUU | D54: Estudios - Diseños - Planes | E54: BHP | F54: CU South Australia | G54: 200000 | H54: 3 | I54: 0.11 | O54: =+I54*G54/H54 -> 7333.3333 | P54: =+O54 -> 7333.3333 | Q54: =+P54 -> 7333.3333
A55: =+G55*I55 -> 16500 | B55: Otros | C55: EEUU | D55: SIMPREP | E55: Freeport-McMoRan Inc. | F55: PTFI | G55: 150000 | H55: 3 | I55: 0.11 | O55: =+I55*G55/H55 -> 5500 | P55: =+O55 -> 5500 | Q55: =+P55 -> 5500
A56: =+G56*I56 -> 22000 | B56: Otros | C56: EEUU | D56: Planificación - Diseño | E56: Freeport-McMoRan Inc. | F56: PTFI | G56: 200000 | H56: 3 | I56: 0.11 | O56: =+I56*G56/H56 -> 7333.3333 | P56: =+O56 -> 7333.3333 | Q56: =+P56 -> 7333.3333
A57: =+G57*I57 -> 22000 | B57: Otros | C57: EEUU | D57: Planificación - Diseño | E57: Newmont Mining | G57: 200000 | H57: 3 | I57: 0.11 | O57: =+I57*G57/H57 -> 7333.3333 | P57: =+O57 -> 7333.3333 | Q57: =+P57 -> 7333.3333
A58: =+G58*I58 -> 22000 | B58: Otros | C58: EEUU | D58: Planificación - Diseño | E58: Anglo Gold Ashanti | G58: 200000 | H58: 3 | I58: 0.11 | O58: =+I58*G58/H58 -> 7333.3333 | P58: =+O58 -> 7333.3333 | Q58: =+P58 -> 7333.3333
A59: =+G59*I59 -> 16500 | B59: Otros | C59: EEUU | D59: Planificación - Diseño | E59: Vale | G59: 150000 | H59: 3 | I59: 0.11 | O59: =+I59*G59/H59 -> 5500 | P59: =+O59 -> 5500 | Q59: =+P59 -> 5500
A60: =+G60*I60 -> 11000 | B60: Otros | C60: EEUU | D60: Planificación - Diseño | E60: South 32 | G60: 100000 | H60: 3 | I60: 0.11 | O60: =+I60*G60/H60 -> 3666.6667 | P60: =+O60 -> 3666.6667 | Q60: =+P60 -> 3666.6667
A61: =+G61*I61 -> 11000 | B61: Otros | C61: EEUU | D61: Planificación - Diseño | E61: Barrick | G61: 100000 | H61: 3 | I61: 0.11 | O61: =+I61*G61/H61 -> 3666.6667 | P61: =+O61 -> 3666.6667 | Q61: =+P61 -> 3666.6667
A62: =+G62*I62 -> 11000 | B62: Otros | C62: EEUU | D62: Planificación - Diseño | E62: Lundin | F62: Eagle | G62: 100000 | H62: 3 | I62: 0.11 | O62: =+I62*G62/H62 -> 3666.6667 | P62: =+O62 -> 3666.6667 | Q62: =+P62 -> 3666.6667
A63: =+G63*I63 -> 22000 | B63: Otros | C63: EEUU | D63: Planificación - Diseño | E63: Kinross | G63: 200000 | H63: 3 | I63: 0.11 | O63: =+I63*G63/H63 -> 7333.3333 | P63: =+O63 -> 7333.3333 | Q63: =+P63 -> 7333.3333
A64: =+G64*I64 -> 124500 | B64: Otros | C64: Brasil | D64: Estudio Conceptual | E64: Vale | F64: Gongo Soco | G64: 150000 | H64: 3 | I64: 0.83 | O64: =+I64*G64/H64 -> 41500 | P64: =+O64 -> 41500 | Q64: =+P64 -> 41500
A65: =+G65*I65 -> 190900 | B65: Otros | C65: Brasil | D65: Fase 1 | E65: Aura Minerals | G65: 230000 | H65: 3 | I65: 0.83 | O65: =+I65*G65/H65 -> 63633.333 | P65: =+O65 -> 63633.333 | Q65: =+P65 -> 63633.333
A66: =+G66*I66 -> 182600 | B66: Otros | C66: Brasil | D66: Fase 2 | E66: Aura Minerals | G66: 220000 | H66: 3 | I66: 0.83 | O66: =+I66*G66/H66 -> 60866.667 | P66: =+O66 -> 60866.667 | Q66: =+P66 -> 60866.667
A67: =+G67*I67 -> 124500 | B67: Otros | C67: Brasil | D67: Remoción Pilares y Secuecia Operativa | E67: Lhg | F67: Mina Urucum | G67: 150000 | H67: 3 | I67: 0.83 | O67: =+I67*G67/H67 -> 41500 | P67: =+O67 -> 41500 | Q67: =+P67 -> 41500
A68: =+G68*I68 -> 182600 | B68: Otros | C68: Brasil | D68: Proyectos Subeterraneaos | E68: Vale | G68: 220000 | H68: 3 | I68: 0.83 | O68: =+I68*G68/H68 -> 60866.667 | P68: =+O68 -> 60866.667 | Q68: =+P68 -> 60866.667
A69: =+G69*I69 -> 107900 | B69: Otros | C69: Brasil | D69: Planificación - Diseño | E69: EuroChen | G69: 130000 | H69: 3 | I69: 0.83 | O69: =+I69*G69/H69 -> 35966.667 | P69: =+O69 -> 35966.667 | Q69: =+P69 -> 35966.667
A70: =+G70*I70 -> 124500 | B70: Otros | C70: Brasil | D70: Planificación - Diseño | E70: Alcoa | G70: 150000 | H70: 3 | I70: 0.83 | O70: =+I70*G70/H70 -> 41500 | P70: =+O70 -> 41500 | Q70: =+P70 -> 41500
A71: =+G71*I71 -> 124500 | B71: Otros | C71: Brasil | D71: Planificación - Diseño | E71: AngloGold Ashanti | G71: 150000 | H71: 3 | I71: 0.83 | O71: =+I71*G71/H71 -> 41500 | P71: =+O71 -> 41500 | Q71: =+P71 -> 41500
A72: =+G72*I72 -> 124500 | B72: Otros | C72: Brasil | D72: Geotecnica y planeamiento | E72: Samarco | G72: 150000 | H72: 4 | I72: 0.83 | O72: =+I72*G72/H72 -> 31125 | P72: =+O72 -> 31125 | Q72: =+P72 -> 31125 | R72: =+Q72 -> 31125
A73: =+G73*I73 -> 166000 | B73: Otros | C73: Brasil | D73: Planificación - Diseño | E73: Anglo American | G73: 200000 | H73: 6 | I73: 0.83 | O73: =+I73*G73/H73 -> 27666.667 | P73: =+O73 -> 27666.667 | Q73: =+P73 -> 27666.667 | R73: =+Q73 -> 27666.667 | S73: =+R73 -> 27666.667 | T73: =+S73 -> 27666.667
A74: =+G74*I74 -> 124500 | B74: Otros | C74: Brasil | D74: Planificación - Diseño | E74: Nexa | F74: Aripuna | G74: 150000 | H74: 3 | I74: 0.83 | O74: =+I74*G74/H74 -> 41500 | P74: =+O74 -> 41500 | Q74: =+P74 -> 41500
A75: =+G75*I75 -> 19000 | B75: Otros | C75: Perú | D75: Compilación R&R | E75: Minsur | G75: 100000 | H75: 4 | I75: 0.19 | O75: =+I75*G75/H75 -> 4750 | P75: =+O75 -> 4750 | Q75: =+P75 -> 4750 | R75: =+Q75 -> 4750
A76: =+G76*I76 -> 9500 | B76: Otros | C76: Perú | D76: Estudio geomecánico y trade off de métodos de explotación | E76: Hochschild Mining | F76: Inmaculada | G76: 50000 | H76: 3 | I76: 0.19 | O76: =+I76*G76/H76 -> 3166.6667 | P76: =+O76 -> 3166.6667 | Q76: =+P76 -> 3166.6667
A77: =+G77*I77 -> 19000 | B77: Otros | C77: Perú | D77: Implementación de un sistema de mapeo estructural automatizado | E77: Gold Fields | F77: Cerro Corona | G77: 100000 | H77: 3 | I77: 0.19 | O77: =+I77*G77/H77 -> 6333.3333 | P77: =+O77 -> 6333.3333 | Q77: =+P77 -> 6333.3333
A78: =+G78*I78 -> 19000 | B78: Otros | C78: Perú | D78: Asesoría Técnica para la Identificación de Oportunidades de Mejora para Incremento de Producción Mina | E78: Hochschild Mining | F78: Inmaculada | G78: 100000 | H78: 3 | I78: 0.19 | O78: =+I78*G78/H78 -> 6333.3333 | P78: =+O78 -> 6333.3333 | Q78: =+P78 -> 6333.3333
A79: =+G79*I79 -> 19000 | B79: Otros | C79: Perú | D79: Actualización de métodos de minado Torremani (Etapa II) | E79: Coripuno | F79: Torremani | G79: 100000 | H79: 3 | I79: 0.19 | O79: =+I79*G79/H79 -> 6333.3333 | P79: =+O79 -> 6333.3333 | Q79: =+P79 -> 6333.3333
A80: =+G80*I80 -> 28500 | B80: Otros | C80: Perú | D80: Estudios de planificación u otros | E80: Sierra Metals | F80: Yauricocha | G80: 150000 | H80: 3 | I80: 0.19 | O80: =+I80*G80/H80 -> 9500 | P80: =+O80 -> 9500 | Q80: =+P80 -> 9500
A81: =+G81*I81 -> 15200 | B81: Otros | C81: Perú | D81: Servicio de apoyo para presentación a la autoridad de ROMINA actualizado | E81: Volcan | F81: Romina | G81: 80000 | H81: 3 | I81: 0.19 | O81: =+I81*G81/H81 -> 5066.6667 | P81: =+O81 -> 5066.6667 | Q81: =+P81 -> 5066.6667
A82: =+G82*I82 -> 19000 | B82: Otros | C82: Perú | D82: Estudio Crown pillars y metodos de explotación | E82: Volcan | F82: Chungar | G82: 100000 | H82: 3 | I82: 0.19 | O82: =+I82*G82/H82 -> 6333.3333 | P82: =+O82 -> 6333.3333 | Q82: =+P82 -> 6333.3333
A83: =+G83*I83 -> 28500 | B83: Otros | C83: Perú | D83: Apoyo transversal a la planificación: Forecast, Budget, LOM | E83: Miski Mayo | G83: 150000 | H83: 3 | I83: 0.19 | O83: =+I83*G83/H83 -> 9500 | P83: =+O83 -> 9500 | Q83: =+P83 -> 9500
A84: =+G84*I84 -> 13300 | B84: Otros | C84: Perú | D84: Diseño de sistema de monitoreo | E84: Nexa | F84: Cerro Lindo | G84: 70000 | H84: 3 | I84: 0.19 | O84: =+I84*G84/H84 -> 4433.3333 | P84: =+O84 -> 4433.3333 | Q84: =+P84 -> 4433.3333
A85: =+G85*I85 -> 28500 | B85: Otros | C85: Perú | D85: PFS tajo Esperanza | E85: Volcan | F85: Chungar | G85: 150000 | H85: 4 | I85: 0.19 | O85: =+I85*G85/H85 -> 7125 | P85: =+O85 -> 7125 | Q85: =+P85 -> 7125 | R85: =+Q85 -> 7125
A86: =+G86*I86 -> 19000 | B86: Otros | C86: Perú | D86: Optimización plan de cierre mina recursos remanentes + stocks | E86: Gold Fields | F86: Cerro Corona | G86: 100000 | H86: 3 | I86: 0.19 | O86: =+I86*G86/H86 -> 6333.3333 | P86: =+O86 -> 6333.3333 | Q86: =+P86 -> 6333.3333
A87: =+G87*I87 -> 69000 | B87: Otros | C87: Chile | D87: Proyecto integral: Diseño y planficación del OP | E87: BHP | F87: Cerro Colorado | G87: 150000 | H87: 3 | I87: 0.46 | O87: =+I87*G87/H87 -> 23000 | P87: =+O87 -> 23000 | Q87: =+P87 -> 23000
A88: =+G88*I88 -> 69000 | B88: Otros | C88: Chile | D88: Planificación Corto Plazo para Captura de Valor OP | E88: Lundin | F88: Caserones | G88: 150000 | H88: 3 | I88: 0.46 | O88: =+I88*G88/H88 -> 23000 | P88: =+O88 -> 23000 | Q88: =+P88 -> 23000
A89: =+G89*I89 -> 69000 | B89: Otros | C89: Chile | D89: Analisis estrategico de opciones | E89: BHP | F89: Spence | G89: 150000 | H89: 3 | I89: 0.46 | O89: =+I89*G89/H89 -> 23000 | P89: =+O89 -> 23000 | Q89: =+P89 -> 23000
A90: =+G90*I90 -> 46000 | B90: Otros | C90: Chile | D90: Analisis oportunidades de recuperación de reservas colapsadas | E90: Codelco | F90: DCH | G90: 100000 | H90: 2 | I90: 0.46 | O90: =+I90*G90/H90 -> 23000 | P90: =+O90 -> 23000
A91: =+G91*I91 -> 55200 | B91: Otros | C91: Chile | D91: Metodologia para establecer escenarios productivos de corto plazo (Incoporar SIMPLAN en proceso de planificación o Simprep OP) | E91: Codelco | F91: DRT | G91: 120000 | H91: 3 | I91: 0.46 | O91: =+I91*G91/H91 -> 18400 | P91: =+O91 -> 18400 | Q91: =+P91 -> 18400
A92: =+G92*I92 -> 46000 | B92: Otros | C92: Chile | D92: Implementación de SIMPREP | E92: Codelco | F92: DET | G92: 100000 | H92: 4 | I92: 0.46 | O92: =+I92*G92/H92 -> 11500 | P92: =+O92 -> 11500 | Q92: =+P92 -> 11500 | R92: =+Q92 -> 11500
A93: =+G93*I93 -> 55200 | B93: Otros | C93: Chile | D93: Actualización de estandares y procedimientos de planificación, balances, muestreo, etc (replicar estudios realizados para otras operaciones) | E93: Codelco | F93: DRT | G93: 120000 | H93: 3 | I93: 0.46 | O93: =+I93*G93/H93 -> 18400 | P93: =+O93 -> 18400 | Q93: =+P93 -> 18400
A94: =+G94*I94 -> 69000 | B94: Otros | C94: Chile | D94: Revisiones independientes | E94: Codelco | F94: GRM | G94: 150000 | H94: 3 | I94: 0.46 | O94: =+I94*G94/H94 -> 23000 | P94: =+O94 -> 23000 | Q94: =+P94 -> 23000
A95: =+G95*I95 -> 46000 | B95: Otros | C95: Chile | D95: Profundicación de actualización de NCC31 (con apoyo consultor) | E95: Codelco | F95: GRM | G95: 100000 | H95: 3 | I95: 0.46 | O95: =+I95*G95/H95 -> 15333.333 | P95: =+O95 -> 15333.333 | Q95: =+P95 -> 15333.333
A96: =+G96*I96 -> 92000 | B96: Otros | C96: Chile | D96: Estudios de oportunidad en planes OP (alargar vida del rajo, recuepeación de stocks y los botaderos, zonas de contacto entre ambos rajos) | E96: Codelco | F96: DCH | G96: 200000 | H96: 3 | I96: 0.46 | O96: =+I96*G96/H96 -> 30666.667 | P96: =+O96 -> 30666.667 | Q96: =+P96 -> 30666.667
A97: =+G97*I97 -> 69000 | B97: Otros | C97: Chile | D97: Analisis de oportunidades del plan minero, generar coberturas debido a atrasos en proyectos | E97: Codelco | F97: DET | G97: 150000 | H97: 3 | I97: 0.46 | O97: =+I97*G97/H97 -> 23000 | P97: =+O97 -> 23000 | Q97: =+P97 -> 23000
A98: =+G98*I98 -> 46000 | B98: Otros | C98: Chile | D98: Implementación de SIMPREP | E98: Codelco | F98: DCH | G98: 100000 | H98: 4 | I98: 0.46 | O98: =+I98*G98/H98 -> 11500 | P98: =+O98 -> 11500 | Q98: =+P98 -> 11500 | R98: =+Q98 -> 11500
A99: =+G99*I99 -> 92000 | B99: Otros | C99: Chile | D99: Evaluación de oportunidades de optimización integrada Distrito Norte | E99: Codelco | F99: Distrito Norte | G99: 200000 | H99: 4 | I99: 0.46 | O99: =+I99*G99/H99 -> 23000 | P99: =+O99 -> 23000 | Q99: =+P99 -> 23000 | R99: =+Q99 -> 23000
F100: Total | G100: =+SUMPRODUCT(G49:G99,I49:I99) -> 2929400 | J100: =+SUM(J49:J99) -> 0 | K100: =+SUM(K49:K99) -> 0 | L100: =+SUM(L49:L99) -> 0 | M100: =+SUM(M49:M99) -> 0 | N100: =+SUM(N49:N99) -> 0 | O100: =+SUM(O49:O99) -> 926800 | P100: =+SUM(P49:P99) -> 926800 | Q100: =+SUM(Q49:Q99) -> 903800 | ... V100: =+SUM(V49:V99) -> 0
G104: =+G100/3 -> 976466.67 | Q104: 845000 | R104: 845000 | S104: 845000 | T104: 845000 | U104: 845000 | V104: 845000

Sheet Modelo Recursos
A1: Peru
A2: Descripción | B2: Input | C2: Unidad
A3: Venta Esperada | B3: 11.5 | C3: M$ | E3: Vacaciones | F3: 15
A4: Valor de venta medio | B4: 0.15 | C4: M$ | E4: Feriados | F4: 10
A5: Venta Spot | B5: 0.2 | C5: % | E5: Días hábiles | F5: =12*20 -> 240
A6: Reventa | B6: 0.15 | C6: % | E6: Días efectivos | F6: =+F5-SUM(F3:F4) -> 215
A7: Búsqueda de Nuevas oportunidades | B7: =1-SUM(B5:B6) -> 0.65 | C7: %
A8: Iniciativas-Solicitud de ppta | B8: 2 | C8: Cantidad
A9: Presentación formal de REDCO o idea | B9: 1.5 | C9: Cantidad
A10: Contacto inicial | B10: 3 | C10: Cantidad
A12: Indicadores de seguimiento | E12: Tiempo requerido (horas)
A13: Búsqueda de Nuevas oportunidades | B13: =+B3-(B3*(SUM(B5:B6))) -> 7.475 | C13: M$ | E13: Búsqueda de Nuevas oportunidades | F13: Total HH | G13: GC | H13: C/GI | I13: DD
A14: Propuestas Adjudicadas (%) | B14: 0.4 | C14: % | E14: Propuesta Construidas | F14: =+B16*SUM(G14:I14) -> 872.08333 | G14: 1 | I14: 6
A15: Propuesta Construidas | B15: =+B13/B14 -> 18.6875 | C15: M$ | E15: Iniciativas-Solicitud de ppta | F15: =+B17*SUM(G15:I15) -> 498.33333 | G15: 1 | I15: 1
A16: Propuesta Construidas | B16: =+B15/B4 -> 124.58333 | C16: Cantidad | E16: Presentación formal de REDCO o idea | F16: =+B18*SUM(G16:I16) -> 1681.875 | G16: 1 | H16: 0.5 | I16: 3
A17: Iniciativas-Solicitud de ppta | B17: =+B16*B8 -> 249.16667 | C17: Cantidad | E17: Contacto inicial (café/llamada) | F17: =+B19*SUM(G17:I17) -> 2803.125 | G17: 2.5 | H17: 0 | I17: 0
A18: Presentación formal de REDCO o idea | B18: =+B17*B9 -> 373.75 | C18: Cantidad | F18: =+SUM(F14:F17) -> 5855.4167 | G18: =+SUMPRODUCT(G14:G17,$B$16:$B$19) -> 3550.625 | H18: =+SUMPRODUCT(H14:H17,$B$16:$B$19) -> 186.875 | I18: =+SUMPRODUCT(I14:I17,$B$16:$B$19) -> 2117.9167
A19: Contacto inicial (café/llamada) | B19: =+B18*B10 -> 1121.25 | C19: Cantidad
A20: Venta Spot | B20: =+B3*B5 -> 2.3 | C20: M$ | E20: Venta Spot | F20: Total HH | G20: GC | H20: C/GI | I20: DD
A21: Propuestas Adjudicadas (%) | B21: 0.4 | C21: % | E21: Construcción propuesta + Ajuste | F21: =+B23*SUM(G21:I21) -> 575 | G21: 1 | H21: 2 | I21: 12
A22: Propuesta Construidas | B22: =+B20/B21 -> 5.75 | C22: M$ | E22: Presentación formal de propuesta | F22: =+B24*SUM(G22:I22) -> 249.16667 | G22: 2 | H22: 1.5 | I22: 3
A23: Propuesta Construidas | B23: =+B22/B4 -> 38.333333 | C23: Cantidad | F23: =+SUM(F21:F22) -> 824.16667 | G23: =+SUMPRODUCT(G21:G22,$B$23:$B$24) -> 115 | H23: =+SUMPRODUCT(H21:H22,$B$23:$B$24) -> 134.16667 | I23: =+SUMPRODUCT(I21:I22,$B$23:$B$24) -> 575
A24: Presentación formal de propuesta | B24: =+B23 -> 38.333333 | C24: Cantidad
A25: Reventa | B25: =+B6*B3 -> 1.725 | C25: M$ | E25: Reventa | F25: Total HH | G25: GC | H25: C/GI | I25: DD
A26: Propuestas Adjudicadas (%) | B26: 0.8 | C26: % | E26: Construcción propuesta | F26: =+B28*SUM(G26:I26) -> 186.875 | G26: 1 | H26: 4 | I26: 8
A27: Propuesta Construidas | B27: =+B25/B26 -> 2.15625 | C27: M$ | E27: Presentación formal de idea | F27: =+B29*SUM(G27:I27) -> 86.25 | G27: 2 | H27: 2 | I27: 2
A28: Propuesta Construidas | B28: =+B27/B4 -> 14.375 | C28: Cantidad | E28: Ajuste propuesta | F28: =+B30*SUM(G28:I28) -> 64.6875 | G28: 0.5 | H28: 2 | I28: 2
A29: Presentación formal de idea | B29: =+B28 -> 14.375 | C29: Cantidad | F29: =+SUM(F26:F28) -> 337.8125 | G29: =+SUMPRODUCT(G26:G28,$B$28:$B$30) -> 50.3125 | H29: =+SUMPRODUCT(H26:H28,$B$28:$B$30) -> 115 | I29: =+SUMPRODUCT(I26:I28,$B$28:$B$30) -> 172.5
A30: Ajuste propuesta | B30: =+B29 -> 14.375 | C30: Cantidad
F32: Total Tiempo | G32: GC/CM | H32: C/GI | I32: DD
A33: Total | B33: Cantidad | F33: Horas | G33: =+G29+G23+G18 -> 3715.9375 | H33: =+H29+H23+H18 -> 436.04167 | I33: =+I29+I23+I18 -> 2865.4167
A34: Propuesta Construidas | B34: =+B28+B23+B16 -> 177.29167 | F34: Días | G34: =+G33/9 -> 412.88194 | H34: =+H33/9 -> 48.449074 | I34: =+I33/9 -> 318.37963
F35: % Ocupación | G35: =+G34/$F$6 -> 1.9203811 | H35: =+H34/$F$6 -> 0.22534453 | I35: =+I34/$F$6 -> 1.4808355

Sheet Contactos
A1: Contacto clave | B1: Cargo | C1: Correo | D1: Telefono | E1: Empresa | F1: Mina
A2: Rodrigo Quiroz | E2: Codelco
A3: Patricio Miranda | E3: Codelco
A4: Sebastian Pizarro | E4: Codelco
A5: Ximena Policroni Galvez | E5: Codelco
A6: Fernando Marambio | E6: Codelco
A7: Juan Cristobal Videla | E7: Codelco
A8: Felipe Hidalgo | E8: Codelco
A9: Juan San Martin | E9: Codelco
A10: Jose Miguel Castro | E10: Codelco
A11: Jaime Rivera | B11: Gerente General Mantos Blancos | E11: Capstone Cooper | F11: Mantos Blancos
A15: Eduardo Viera | E15: Lundin | F15: Candelaria
A16: Octavio Cardenas | E16: Lundin | F16: Candelaria

Sheet Resumen
B2: Pipeline 2025
B3: País | C3: Tipo cliente | D3: Monto | E3: Tasa de adjudicación (%) | F3: Monto esperado | I3: País | J3: Venta 2023 [US$] | K3: Venta 2024 [US$] | L3: Promedio Venta 2023 [US$] | M3: Promedio Venta 2024 [US$] | N3: % Adjudicación (2024)
B4: Chile | C4: Premium | D4: =+SUMIFS(Chile!F:F,Chile!B:B,Resumen!C4) -> 2300 | E4: 0.9 | F4: =+E4*D4 -> 2070 | G4: =+D4/$D$8 -> 0.40421793 | I4: Brasil | J4: 1121263 | K4: 1024085 | L4: 280316 | M4: 128011 | N4: 0.91
C5: Regular | D5: =+SUMIFS(Chile!F:F,Chile!B:B,Resumen!C5) -> 90 | E5: 0.5 | F5: =+E5*D5 -> 45 | G5: =+D5/$D$8 -> 0.015817223 | I5: Chile | J5: 3902850 | K5: 4088416 | L5: 121964 | M5: 151423 | N5: 0.54
C6: Target | D6: =+SUMIFS(Chile!F:F,Chile!B:B,Resumen!C6) -> 3000 | E6: 0.4 | F6: =+E6*D6 -> 1200 | G6: =+D6/$D$8 -> 0.52724077 | I6: EEUU | J6: 536410 | K6: 1401000 | L6: 536410 | M6: 275167 | N6: 0.26
C7: Leads | D7: =+SUMIFS(Chile!F:F,Chile!B:B,Resumen!C7) -> 300 | E7: 0.4 | F7: =+E7*D7 -> 120 | G7: =+D7/$D$8 -> 0.052724077 | I7: Perú | J7: 2098958 | K7: 1365600 | L7: 123468 | M7: 105046 | N7: 0.36
C8: Total | D8: =+SUM(D4:D7) -> 5690 | E8: - | F8: =+SUM(F4:F7) -> 3435 | I8: Total general | J8: 7659480 | K8: 8034101 | L8: 141842 | M8: 150539 | N8: 0.43
B9: Perú | C9: Premium | D9: =+SUMIFS(Perú!F:F,Perú!B:B,Resumen!C9) -> 940 | E9: 0.9 | F9: =+E9*D9 -> 846 | G9: =+D9/$D$13 -> 0.24671916
C10: Regular | D10: =+SUMIFS(Perú!F:F,Perú!B:B,Resumen!C10) -> 300 | E10: 0.5 | F10: =+E10*D10 -> 150 | G10: =+D10/$D$13 -> 0.078740157
C11: Target | D11: =+SUMIFS(Perú!F:F,Perú!B:B,Resumen!C11) -> 2570 | E11: 0.4 | F11: =+E11*D11 -> 1028 | G11: =+D11/$D$13 -> 0.67454068
C12: Leads | D12: =+SUMIFS(Perú!F:F,Perú!B:B,Resumen!C12) -> 0 | E12: 0.4 | F12: =+E12*D12 -> 0 | G12: =+D12/$D$13 -> 0
C13: Total | D13: =+SUM(D9:D12) -> 3810 | E13: - | F13: =+SUM(F9:F12) -> 2024
B14: Brasil | C14: Premium | D14: =+SUMIFS(Brasil!F:F,Brasil!B:B,Resumen!C14) -> 1350 | E14: 0.95 | F14: =+E14*D14 -> 1282.5 | G14: =+D14/$D$18 -> 0.44262295
C15: Regular | D15: =+SUMIFS(Brasil!F:F,Brasil!B:B,Resumen!C15) -> 150 | E15: 0.5 | F15: =+E15*D15 -> 75 | G15: =+D15/$D$18 -> 0.049180328
C16: Target | D16: =+SUMIFS(Brasil!F:F,Brasil!B:B,Resumen!C16) -> 1550 | E16: 0.5 | F16: =+E16*D16 -> 775 | G16: =+D16/$D$18 -> 0.50819672
C17: Leads | D17: =+SUMIFS(Brasil!F:F,Brasil!B:B,Resumen!C17) -> 0 | E17: 0.4 | F17: =+E17*D17 -> 0 | G17: =+D17/$D$18 -> 0
C18: Total | D18: =+SUM(D14:D17) -> 3050 | E18: - | F18: =+SUM(F14:F17) -> 2132.5
B19: EEUU | C19: Premium | D19: =+SUMIFS(EEUU!F:F,EEUU!B:B,Resumen!C19) -> 1100 | E19: 0.8 | F19: =+E19*D19 -> 880 | G19: =+D19/$D$23 -> 0.25287356
C20: Regular | D20: =+SUMIFS(EEUU!F:F,EEUU!B:B,Resumen!C20) -> 300 | E20: 0.4 | F20: =+E20*D20 -> 120 | G20: =+D20/$D$23 -> 0.068965517
C21: Target | D21: =+SUMIFS(EEUU!F:F,EEUU!B:B,Resumen!C21) -> 2300 | E21: 0.5 | F21: =+E21*D21 -> 1150 | G21: =+D21/$D$23 -> 0.52873563
C22: Leads | D22: =+SUMIFS(EEUU!F:F,EEUU!B:B,Resumen!C22) -> 650 | E22: 0.5 | F22: =+E22*D22 -> 325 | G22: =+D22/$D$23 -> 0.14942529
C23: Total | D23: =+SUM(D19:D22) -> 4350 | E23: - | F23: =+SUM(F19:F22) -> 2475
B24: Total | D24: =+D23+D18+D13+D8 -> 16900 | F24: =+F23+F18+F13+F8 -> 10066.5
G27: Pipeline | H27: V. Esperada
F28: Chile | G28: =+D8/$G$32 -> 0.33668639 | H28: =+F8/$H$32 -> 0.34123082
F29: Perú | G29: =+D13/$G$32 -> 0.22544379 | H29: =+F13/$H$32 -> 0.20106293
F30: Brasil | G30: =+D18/$G$32 -> 0.18047337 | H30: =+F18/$H$32 -> 0.21184126
F31: EEUU | G31: =+D23/$G$32 -> 0.25739645 | H31: =+F23/$H$32 -> 0.245865
F32: Total | G32: =+D24 -> 16900 | H32: =+F24 -> 10066.5

Sheet Categorias
B1: ID | C1: País
B2: 1 | C2: Chile
B3: 2 | C3: Perú
B4: 3 | C4: Brasil
B5: 4 | C5: EEUU
B7: ID | C7: Tipo de Estudio
B8: 1 | C8: Ing. de minas
B9: 2 | C9: Planificación estratégica
B10: 3 | C10: Simulación de sistemas mineros
B11: 4 | C11: Mecánica de rocas
B12: 5 | C12: Consultoría minera
B14: ID | C14: Gestor Comercial | D14: Nombre
B15: 1 | C15: AF | D15: Alex Figueroa
B16: 2 | C16: CH | D16: Claudio Hernández
B17: 3 | C17: GD | D17: Gonzalo Diaz
B18: 4 | C18: RM | D18: Renzo Misari
B19: 5 | C19: CA | D19: Carolina Arcos
B20: 6 | C20: MF | D20: Matías Fuentes
B21: 7 | C21: RM | D21: Ricardo Miranda
B22: 8 | C22: FR | D22: Felipe Rojas
B23: 9 | C23: CC | D23: Christian Caviedes
B24: 10 | C24: PV | D24: Patricio Vergara
B25: 11 | C25: AA | D25: Isabela Alves Camisassa
B26: 12 | C26: EL | D26: Eduardo Lama
... B29: 15 | C29: AS | D29: Antonio Schettino
B31: ID | C31: Tipo de cliente | D31: Descripción
B32: 1 | C32: Premium | D32: Cliente cercano,de confianza responsable de mayor % de venta del país
B33: 2 | C33: Regular | D33: Cliente con historial de trabajo previo, con baja relevancia para la estrategia de REDCO
B34: 3 | C34: Target | D34: Clientes con/sin registros a los cuales REDCO le gustaria posicionarse como cliente Premium
B35: 4 | C35: Leads | D35: Nuevos clientes/oportunidades
B37: ID | C37: Tipo de Mineria
B38: 1 | C38: OP
B39: 2 | C39: UG
B40: 3 | C40: OP/UG
B42: ID | C42: Forma de Venta
B43: 1 | C43: Licitación
B44: 2 | C44: Solicitud Directa
B45: 3 | C45: Busqueda Activa
B46: 4 | C46: Reventa
B49: ID | C49: Etapa
B50: 1 | C50: Iniciativa
B51: 2 | C51: Contacto Inicial (Enganche)
B52: 3 | C52: Presentación Ad-Hoc
B53: 4 | C53: Construcción Propuesta
B54: 5 | C54: Seguimiento
B55: 6 | C55: Cierre y Negociacón
B56: 7 | C56: No Adjudicada
B57: 8 | C57: ODS
B59: ID | C59: Motivo de No Adjudicación
B60: 1 | C60: Estrategia no Adecuada
B61: 2 | C61: Alcance ineficiente
B62: 3 | C62: Costos muy altos
B63: 4 | C63: Anulación de licitación
B64: 5 | C64: Otros
