Workbook

Sheet 00_Portada_Metodologia
B1: REDCO · Rentabilidad, Ventas y Flujo de Caja — Análisis histórico
B2: Libro único de trazabilidad. Fecha de generación: 2026-07-05. Todos los montos en USD.
B4: Qué es este archivo
B5: Cuatro análisis históricos de REDCO, cada uno en su hoja (01-04), más el puente de identidad (91), las hojas de datos de origen (90_*) y las fuentes (99).
B6: Las hojas 01-04 NO contienen valores pegados: se calculan con fórmulas (SUMIFS/VLOOKUP) que leen de las hojas 90_* y 91. La trazabilidad es recalculable dentro del mismo libro (Datos → Actualizar / recalcular).
B7: Regla de color: texto VERDE = fórmula que enlaza a otra hoja del libro (staging); texto NEGRO = cálculo dentro de la hoja.
B9: Definición de 'VENTA' usada (Entregable 2)
B10: VENTA = 'Emitido USD' del ledger CicloEdP_2023_v1 (devengo real del servicio ejecutado / EDP emitido).
B11: Motivo: el campo 'Proyectado USD' está en 0 para todo 2025 en el ledger (la proyección de ese año se llevó en el POM, no en el ledger), por lo que NO sirve como proxy de venta comparable entre años.
B12: 'Proyectado USD', 'Facturado USD' e 'Ingresado USD' se muestran como columnas de contraste (hoja 02, bloque C).
B14: Definición de 'TIPO DE PRODUCTO' (derivado — no es campo nativo)
B15: No existe columna de tipo de producto/línea de servicio en ninguna fuente. Se deriva del segmento FASE del campo 'Código' del ledger (formato PAÍS-CLIENTE-UNIDAD-FASE-corr-rev, p.ej. CH-CMP-OU-FEL00-001-A).
... B46: 00_Portada_Metodologia · 01_Rentabilidad_2024_2025 · 02_Ventas_2023_2025 · 03_FlujoCaja_2024_2025 · 04_Rentab_Dotacion_Dic2025 (FOTO dic-2025) · 91_Puente_Identidad · 90_Origen_* (datos de origen) · 99_Fuentes.

Sheet 01_Rentabilidad_2024_2025
A1: ENTREGABLE 1 · Rentabilidad histórica por país y tipo de producto
A2: 2025: País×Mes (resultado operacional real). 2024: solo ingreso devengado (EDP emitido) — el costo/margen 2024 por país NO existe en las fuentes.
A4: A) 2025 — Resultado operacional por País × Mes (USD) · fuente: Tabla datos unidades_Dic
A5: País | B5: Mes | C5: Ingreso Op. USD | D5: Gasto Op. USD (incl. adm.) | E5: Beneficio USD | F5: Margen %
A6: Chile | B6: ene | C6: =SUMIFS('90_Origen_Rentab_2025'!$F$3:$F$122,'90_Origen_Rentab_2025'!$A$3:$A$122,$A6,'90_Origen_Rentab_2025'!$C$3:$C$122,1,'90_Origen_Rentab_2025'!$E$3:$E$122,"INGRESOS OP") -> 362362.73 | D6: =SUMIFS('90_Origen_Rentab_2025'!$F$3:$F$122,'90_Origen_Rentab_2025'!$A$3:$A$122,$A6,'90_Origen_Rentab_2025'!$C$3:$C$122,1,'90_Origen_Rentab_2025'!$E$3:$E$122,"COSTOS OP") -> 397276.65 | E6: =C6-D6 -> -34913.92 | F6: =IF(C6=0,"-",E6/C6) -> -0.096350748
A7: Chile | B7: feb | C7: =SUMIFS('90_Origen_Rentab_2025'!$F$3:$F$122,'90_Origen_Rentab_2025'!$A$3:$A$122,$A7,'90_Origen_Rentab_2025'!$C$3:$C$122,2,'90_Origen_Rentab_2025'!$E$3:$E$122,"INGRESOS OP") -> 547310.62 | D7: =SUMIFS('90_Origen_Rentab_2025'!$F$3:$F$122,'90_Origen_Rentab_2025'!$A$3:$A$122,$A7,'90_Origen_Rentab_2025'!$C$3:$C$122,2,'90_Origen_Rentab_2025'!$E$3:$E$122,"COSTOS OP") -> 422126.64 | E7: =C7-D7 -> 125183.98 | F7: =IF(C7=0,"-",E7/C7) -> 0.22872565
A8: Chile | B8: mar | C8: =SUMIFS('90_Origen_Rentab_2025'!$F$3:$F$122,'90_Origen_Rentab_2025'!$A$3:$A$122,$A8,'90_Origen_Rentab_2025'!$C$3:$C$122,3,'90_Origen_Rentab_2025'!$E$3:$E$122,"INGRESOS OP") -> 389727.46 | D8: =SUMIFS('90_Origen_Rentab_2025'!$F$3:$F$122,'90_Origen_Rentab_2025'!$A$3:$A$122,$A8,'90_Origen_Rentab_2025'!$C$3:$C$122,3,'90_Origen_Rentab_2025'!$E$3:$E$122,"COSTOS OP") -> 439899.18 | E8: =C8-D8 -> -50171.72 | F8: =IF(C8=0,"-",E8/C8) -> -0.1287354
A9: Chile | B9: abr | C9: =SUMIFS('90_Origen_Rentab_2025'!$F$3:$F$122,'90_Origen_Rentab_2025'!$A$3:$A$122,$A9,'90_Origen_Rentab_2025'!$C$3:$C$122,4,'90_Origen_Rentab_2025'!$E$3:$E$122,"INGRESOS OP") -> 237434.48 | D9: =SUMIFS('90_Origen_Rentab_2025'!$F$3:$F$122,'90_Origen_Rentab_2025'!$A$3:$A$122,$A9,'90_Origen_Rentab_2025'!$C$3:$C$122,4,'90_Origen_Rentab_2025'!$E$3:$E$122,"COSTOS OP") -> 341507.35 | E9: =C9-D9 -> -104072.87 | F9: =IF(C9=0,"-",E9/C9) -> -0.43832248
A10: Chile | B10: may | C10: =SUMIFS('90_Origen_Rentab_2025'!$F$3:$F$122,'90_Origen_Rentab_2025'!$A$3:$A$122,$A10,'90_Origen_Rentab_2025'!$C$3:$C$122,5,'90_Origen_Rentab_2025'!$E$3:$E$122,"INGRESOS OP") -> 272631.08 | D10: =SUMIFS('90_Origen_Rentab_2025'!$F$3:$F$122,'90_Origen_Rentab_2025'!$A$3:$A$122,$A10,'90_Origen_Rentab_2025'!$C$3:$C$122,5,'90_Origen_Rentab_2025'!$E$3:$E$122,"COSTOS OP") -> 340134.8 | E10: =C10-D10 -> -67503.72 | F10: =IF(C10=0,"-",E10/C10) -> -0.24760097
A11: Chile | B11: jun | C11: =SUMIFS('90_Origen_Rentab_2025'!$F$3:$F$122,'90_Origen_Rentab_2025'!$A$3:$A$122,$A11,'90_Origen_Rentab_2025'!$C$3:$C$122,6,'90_Origen_Rentab_2025'!$E$3:$E$122,"INGRESOS OP") -> 277419.07 | D11: =SUMIFS('90_Origen_Rentab_2025'!$F$3:$F$122,'90_Origen_Rentab_2025'!$A$3:$A$122,$A11,'90_Origen_Rentab_2025'!$C$3:$C$122,6,'90_Origen_Rentab_2025'!$E$3:$E$122,"COSTOS OP") -> 380566.17 | E11: =C11-D11 -> -103147.1 | F11: =IF(C11=0,"-",E11/C11) -> -0.3718097
A12: Chile | B12: jul | C12: =SUMIFS('90_Origen_Rentab_2025'!$F$3:$F$122,'90_Origen_Rentab_2025'!$A$3:$A$122,$A12,'90_Origen_Rentab_2025'!$C$3:$C$122,7,'90_Origen_Rentab_2025'!$E$3:$E$122,"INGRESOS OP") -> 475570.75 | D12: =SUMIFS('90_Origen_Rentab_2025'!$F$3:$F$122,'90_Origen_Rentab_2025'!$A$3:$A$122,$A12,'90_Origen_Rentab_2025'!$C$3:$C$122,7,'90_Origen_Rentab_2025'!$E$3:$E$122,"COSTOS OP") -> 395727.19 | E12: =C12-D12 -> 79843.56 | F12: =IF(C12=0,"-",E12/C12) -> 0.16788997
A13: Chile | B13: ago | C13: =SUMIFS('90_Origen_Rentab_2025'!$F$3:$F$122,'90_Origen_Rentab_2025'!$A$3:$A$122,$A13,'90_Origen_Rentab_2025'!$C$3:$C$122,8,'90_Origen_Rentab_2025'!$E$3:$E$122,"INGRESOS OP") -> 151482.74 | D13: =SUMIFS('90_Origen_Rentab_2025'!$F$3:$F$122,'90_Origen_Rentab_2025'!$A$3:$A$122,$A13,'90_Origen_Rentab_2025'!$C$3:$C$122,8,'90_Origen_Rentab_2025'!$E$3:$E$122,"COSTOS OP") -> 425248.91 | E13: =C13-D13 -> -273766.17 | F13: =IF(C13=0,"-",E13/C13) -> -1.8072433
A14: Chile | B14: sep | C14: =SUMIFS('90_Origen_Rentab_2025'!$F$3:$F$122,'90_Origen_Rentab_2025'!$A$3:$A$122,$A14,'90_Origen_Rentab_2025'!$C$3:$C$122,9,'90_Origen_Rentab_2025'!$E$3:$E$122,"INGRESOS OP") -> 297925.05 | D14: =SUMIFS('90_Origen_Rentab_2025'!$F$3:$F$122,'90_Origen_Rentab_2025'!$A$3:$A$122,$A14,'90_Origen_Rentab_2025'!$C$3:$C$122,9,'90_Origen_Rentab_2025'!$E$3:$E$122,"COSTOS OP") -> 455871.33 | E14: =C14-D14 -> -157946.28 | F14: =IF(C14=0,"-",E14/C14) -> -0.53015441
A15: Chile | B15: oct | C15: =SUMIFS('90_Origen_Rentab_2025'!$F$3:$F$122,'90_Origen_Rentab_2025'!$A$3:$A$122,$A15,'90_Origen_Rentab_2025'!$C$3:$C$122,10,'90_Origen_Rentab_2025'!$E$3:$E$122,"INGRESOS OP") -> 158266.46 | D15: =SUMIFS('90_Origen_Rentab_2025'!$F$3:$F$122,'90_Origen_Rentab_2025'!$A$3:$A$122,$A15,'90_Origen_Rentab_2025'!$C$3:$C$122,10,'90_Origen_Rentab_2025'!$E$3:$E$122,"COSTOS OP") -> 513185.66 | E15: =C15-D15 -> -354919.2 | F15: =IF(C15=0,"-",E15/C15) -> -2.2425421
A16: Chile | B16: nov | C16: =SUMIFS('90_Origen_Rentab_2025'!$F$3:$F$122,'90_Origen_Rentab_2025'!$A$3:$A$122,$A16,'90_Origen_Rentab_2025'!$C$3:$C$122,11,'90_Origen_Rentab_2025'!$E$3:$E$122,"INGRESOS OP") -> 248788.93 | D16: =SUMIFS('90_Origen_Rentab_2025'!$F$3:$F$122,'90_Origen_Rentab_2025'!$A$3:$A$122,$A16,'90_Origen_Rentab_2025'!$C$3:$C$122,11,'90_Origen_Rentab_2025'!$E$3:$E$122,"COSTOS OP") -> 392218.11 | E16: =C16-D16 -> -143429.18 | F16: =IF(C16=0,"-",E16/C16) -> -0.57650949
A17: Chile | B17: dic | C17: =SUMIFS('90_Origen_Rentab_2025'!$F$3:$F$122,'90_Origen_Rentab_2025'!$A$3:$A$122,$A17,'90_Origen_Rentab_2025'!$C$3:$C$122,12,'90_Origen_Rentab_2025'!$E$3:$E$122,"INGRESOS OP") -> 173207.55 | D17: =SUMIFS('90_Origen_Rentab_2025'!$F$3:$F$122,'90_Origen_Rentab_2025'!$A$3:$A$122,$A17,'90_Origen_Rentab_2025'!$C$3:$C$122,12,'90_Origen_Rentab_2025'!$E$3:$E$122,"COSTOS OP") -> 495505.54 | E17: =C17-D17 -> -322297.99 | F17: =IF(C17=0,"-",E17/C17) -> -1.8607618
A18: Perú | B18: ene | C18: =SUMIFS('90_Origen_Rentab_2025'!$F$3:$F$122,'90_Origen_Rentab_2025'!$A$3:$A$122,$A18,'90_Origen_Rentab_2025'!$C$3:$C$122,1,'90_Origen_Rentab_2025'!$E$3:$E$122,"INGRESOS OP") -> 123848 | D18: =SUMIFS('90_Origen_Rentab_2025'!$F$3:$F$122,'90_Origen_Rentab_2025'!$A$3:$A$122,$A18,'90_Origen_Rentab_2025'!$C$3:$C$122,1,'90_Origen_Rentab_2025'!$E$3:$E$122,"COSTOS OP") -> 89462.85 | E18: =C18-D18 -> 34385.15 | F18: =IF(C18=0,"-",E18/C18) -> 0.27763993
A19: Perú | B19: feb | C19: =SUMIFS('90_Origen_Rentab_2025'!$F$3:$F$122,'90_Origen_Rentab_2025'!$A$3:$A$122,$A19,'90_Origen_Rentab_2025'!$C$3:$C$122,2,'90_Origen_Rentab_2025'!$E$3:$E$122,"INGRESOS OP") -> 62454 | D19: =SUMIFS('90_Origen_Rentab_2025'!$F$3:$F$122,'90_Origen_Rentab_2025'!$A$3:$A$122,$A19,'90_Origen_Rentab_2025'!$C$3:$C$122,2,'90_Origen_Rentab_2025'!$E$3:$E$122,"COSTOS OP") -> 81597 | E19: =C19-D19 -> -19143 | F19: =IF(C19=0,"-",E19/C19) -> -0.30651359
A20: Perú | B20: mar | C20: =SUMIFS('90_Origen_Rentab_2025'!$F$3:$F$122,'90_Origen_Rentab_2025'!$A$3:$A$122,$A20,'90_Origen_Rentab_2025'!$C$3:$C$122,3,'90_Origen_Rentab_2025'!$E$3:$E$122,"INGRESOS OP") -> 105377 | D20: =SUMIFS('90_Origen_Rentab_2025'!$F$3:$F$122,'90_Origen_Rentab_2025'!$A$3:$A$122,$A20,'90_Origen_Rentab_2025'!$C$3:$C$122,3,'90_Origen_Rentab_2025'!$E$3:$E$122,"COSTOS OP") -> 92755 | E20: =C20-D20 -> 12622 | F20: =IF(C20=0,"-",E20/C20) -> 0.11977946
A21: Perú | B21: abr | C21: =SUMIFS('90_Origen_Rentab_2025'!$F$3:$F$122,'90_Origen_Rentab_2025'!$A$3:$A$122,$A21,'90_Origen_Rentab_2025'!$C$3:$C$122,4,'90_Origen_Rentab_2025'!$E$3:$E$122,"INGRESOS OP") -> 110077 | D21: =SUMIFS('90_Origen_Rentab_2025'!$F$3:$F$122,'90_Origen_Rentab_2025'!$A$3:$A$122,$A21,'90_Origen_Rentab_2025'!$C$3:$C$122,4,'90_Origen_Rentab_2025'!$E$3:$E$122,"COSTOS OP") -> 137672.3 | E21: =C21-D21 -> -27595.3 | F21: =IF(C21=0,"-",E21/C21) -> -0.25069088
A22: Perú | B22: may | C22: =SUMIFS('90_Origen_Rentab_2025'!$F$3:$F$122,'90_Origen_Rentab_2025'!$A$3:$A$122,$A22,'90_Origen_Rentab_2025'!$C$3:$C$122,5,'90_Origen_Rentab_2025'!$E$3:$E$122,"INGRESOS OP") -> 142610 | D22: =SUMIFS('90_Origen_Rentab_2025'!$F$3:$F$122,'90_Origen_Rentab_2025'!$A$3:$A$122,$A22,'90_Origen_Rentab_2025'!$C$3:$C$122,5,'90_Origen_Rentab_2025'!$E$3:$E$122,"COSTOS OP") -> 128924 | E22: =C22-D22 -> 13686 | F22: =IF(C22=0,"-",E22/C22) -> 0.095968025
A23: Perú | B23: jun | C23: =SUMIFS('90_Origen_Rentab_2025'!$F$3:$F$122,'90_Origen_Rentab_2025'!$A$3:$A$122,$A23,'90_Origen_Rentab_2025'!$C$3:$C$122,6,'90_Origen_Rentab_2025'!$E$3:$E$122,"INGRESOS OP") -> 229588 | D23: =SUMIFS('90_Origen_Rentab_2025'!$F$3:$F$122,'90_Origen_Rentab_2025'!$A$3:$A$122,$A23,'90_Origen_Rentab_2025'!$C$3:$C$122,6,'90_Origen_Rentab_2025'!$E$3:$E$122,"COSTOS OP") -> 167995 | E23: =C23-D23 -> 61593 | F23: =IF(C23=0,"-",E23/C23) -> 0.26827622
A24: Perú | B24: jul | C24: =SUMIFS('90_Origen_Rentab_2025'!$F$3:$F$122,'90_Origen_Rentab_2025'!$A$3:$A$122,$A24,'90_Origen_Rentab_2025'!$C$3:$C$122,7,'90_Origen_Rentab_2025'!$E$3:$E$122,"INGRESOS OP") -> 251702 | D24: =SUMIFS('90_Origen_Rentab_2025'!$F$3:$F$122,'90_Origen_Rentab_2025'!$A$3:$A$122,$A24,'90_Origen_Rentab_2025'!$C$3:$C$122,7,'90_Origen_Rentab_2025'!$E$3:$E$122,"COSTOS OP") -> 199355 | E24: =C24-D24 -> 52347 | F24: =IF(C24=0,"-",E24/C24) -> 0.20797213
A25: Perú | B25: ago | C25: =SUMIFS('90_Origen_Rentab_2025'!$F$3:$F$122,'90_Origen_Rentab_2025'!$A$3:$A$122,$A25,'90_Origen_Rentab_2025'!$C$3:$C$122,8,'90_Origen_Rentab_2025'!$E$3:$E$122,"INGRESOS OP") -> 641573 | D25: =SUMIFS('90_Origen_Rentab_2025'!$F$3:$F$122,'90_Origen_Rentab_2025'!$A$3:$A$122,$A25,'90_Origen_Rentab_2025'!$C$3:$C$122,8,'90_Origen_Rentab_2025'!$E$3:$E$122,"COSTOS OP") -> 225572 | E25: =C25-D25 -> 416001 | F25: =IF(C25=0,"-",E25/C25) -> 0.6484079
A26: Perú | B26: sep | C26: =SUMIFS('90_Origen_Rentab_2025'!$F$3:$F$122,'90_Origen_Rentab_2025'!$A$3:$A$122,$A26,'90_Origen_Rentab_2025'!$C$3:$C$122,9,'90_Origen_Rentab_2025'!$E$3:$E$122,"INGRESOS OP") -> 119133 | D26: =SUMIFS('90_Origen_Rentab_2025'!$F$3:$F$122,'90_Origen_Rentab_2025'!$A$3:$A$122,$A26,'90_Origen_Rentab_2025'!$C$3:$C$122,9,'90_Origen_Rentab_2025'!$E$3:$E$122,"COSTOS OP") -> 127097 | E26: =C26-D26 -> -7964 | F26: =IF(C26=0,"-",E26/C26) -> -0.066849655
A27: Perú | B27: oct | C27: =SUMIFS('90_Origen_Rentab_2025'!$F$3:$F$122,'90_Origen_Rentab_2025'!$A$3:$A$122,$A27,'90_Origen_Rentab_2025'!$C$3:$C$122,10,'90_Origen_Rentab_2025'!$E$3:$E$122,"INGRESOS OP") -> 265449 | D27: =SUMIFS('90_Origen_Rentab_2025'!$F$3:$F$122,'90_Origen_Rentab_2025'!$A$3:$A$122,$A27,'90_Origen_Rentab_2025'!$C$3:$C$122,10,'90_Origen_Rentab_2025'!$E$3:$E$122,"COSTOS OP") -> 108174 | E27: =C27-D27 -> 157275 | F27: =IF(C27=0,"-",E27/C27) -> 0.59248669
A28: Perú | B28: nov | C28: =SUMIFS('90_Origen_Rentab_2025'!$F$3:$F$122,'90_Origen_Rentab_2025'!$A$3:$A$122,$A28,'90_Origen_Rentab_2025'!$C$3:$C$122,11,'90_Origen_Rentab_2025'!$E$3:$E$122,"INGRESOS OP") -> 96110 | D28: =SUMIFS('90_Origen_Rentab_2025'!$F$3:$F$122,'90_Origen_Rentab_2025'!$A$3:$A$122,$A28,'90_Origen_Rentab_2025'!$C$3:$C$122,11,'90_Origen_Rentab_2025'!$E$3:$E$122,"COSTOS OP") -> 139137.64 | E28: =C28-D28 -> -43027.64 | F28: =IF(C28=0,"-",E28/C28) -> -0.4476916
A29: Perú | B29: dic | C29: =SUMIFS('90_Origen_Rentab_2025'!$F$3:$F$122,'90_Origen_Rentab_2025'!$A$3:$A$122,$A29,'90_Origen_Rentab_2025'!$C$3:$C$122,12,'90_Origen_Rentab_2025'!$E$3:$E$122,"INGRESOS OP") -> 269432 | D29: =SUMIFS('90_Origen_Rentab_2025'!$F$3:$F$122,'90_Origen_Rentab_2025'!$A$3:$A$122,$A29,'90_Origen_Rentab_2025'!$C$3:$C$122,12,'90_Origen_Rentab_2025'!$E$3:$E$122,"COSTOS OP") -> 234121 | E29: =C29-D29 -> 35311 | F29: =IF(C29=0,"-",E29/C29) -> 0.13105719
A30: Brasil | B30: ene | C30: =SUMIFS('90_Origen_Rentab_2025'!$F$3:$F$122,'90_Origen_Rentab_2025'!$A$3:$A$122,$A30,'90_Origen_Rentab_2025'!$C$3:$C$122,1,'90_Origen_Rentab_2025'!$E$3:$E$122,"INGRESOS OP") -> 80502 | D30: =SUMIFS('90_Origen_Rentab_2025'!$F$3:$F$122,'90_Origen_Rentab_2025'!$A$3:$A$122,$A30,'90_Origen_Rentab_2025'!$C$3:$C$122,1,'90_Origen_Rentab_2025'!$E$3:$E$122,"COSTOS OP") -> 21023 | E30: =C30-D30 -> 59479 | F30: =IF(C30=0,"-",E30/C30) -> 0.73885121
A31: Brasil | B31: feb | C31: =SUMIFS('90_Origen_Rentab_2025'!$F$3:$F$122,'90_Origen_Rentab_2025'!$A$3:$A$122,$A31,'90_Origen_Rentab_2025'!$C$3:$C$122,2,'90_Origen_Rentab_2025'!$E$3:$E$122,"INGRESOS OP") -> 59683 | D31: =SUMIFS('90_Origen_Rentab_2025'!$F$3:$F$122,'90_Origen_Rentab_2025'!$A$3:$A$122,$A31,'90_Origen_Rentab_2025'!$C$3:$C$122,2,'90_Origen_Rentab_2025'!$E$3:$E$122,"COSTOS OP") -> 27812 | E31: =C31-D31 -> 31871 | F31: =IF(C31=0,"-",E31/C31) -> 0.53400466
A32: Brasil | B32: mar | C32: =SUMIFS('90_Origen_Rentab_2025'!$F$3:$F$122,'90_Origen_Rentab_2025'!$A$3:$A$122,$A32,'90_Origen_Rentab_2025'!$C$3:$C$122,3,'90_Origen_Rentab_2025'!$E$3:$E$122,"INGRESOS OP") -> 96322 | D32: =SUMIFS('90_Origen_Rentab_2025'!$F$3:$F$122,'90_Origen_Rentab_2025'!$A$3:$A$122,$A32,'90_Origen_Rentab_2025'!$C$3:$C$122,3,'90_Origen_Rentab_2025'!$E$3:$E$122,"COSTOS OP") -> 26425 | E32: =C32-D32 -> 69897 | F32: =IF(C32=0,"-",E32/C32) -> 0.72565977
A33: Brasil | B33: abr | C33: =SUMIFS('90_Origen_Rentab_2025'!$F$3:$F$122,'90_Origen_Rentab_2025'!$A$3:$A$122,$A33,'90_Origen_Rentab_2025'!$C$3:$C$122,4,'90_Origen_Rentab_2025'!$E$3:$E$122,"INGRESOS OP") -> 97209.7 | D33: =SUMIFS('90_Origen_Rentab_2025'!$F$3:$F$122,'90_Origen_Rentab_2025'!$A$3:$A$122,$A33,'90_Origen_Rentab_2025'!$C$3:$C$122,4,'90_Origen_Rentab_2025'!$E$3:$E$122,"COSTOS OP") -> 52004.4 | E33: =C33-D33 -> 45205.3 | F33: =IF(C33=0,"-",E33/C33) -> 0.4650287
A34: Brasil | B34: may | C34: =SUMIFS('90_Origen_Rentab_2025'!$F$3:$F$122,'90_Origen_Rentab_2025'!$A$3:$A$122,$A34,'90_Origen_Rentab_2025'!$C$3:$C$122,5,'90_Origen_Rentab_2025'!$E$3:$E$122,"INGRESOS OP") -> 37074 | D34: =SUMIFS('90_Origen_Rentab_2025'!$F$3:$F$122,'90_Origen_Rentab_2025'!$A$3:$A$122,$A34,'90_Origen_Rentab_2025'!$C$3:$C$122,5,'90_Origen_Rentab_2025'!$E$3:$E$122,"COSTOS OP") -> 33329 | E34: =C34-D34 -> 3745 | F34: =IF(C34=0,"-",E34/C34) -> 0.10101419
A35: Brasil | B35: jun | C35: =SUMIFS('90_Origen_Rentab_2025'!$F$3:$F$122,'90_Origen_Rentab_2025'!$A$3:$A$122,$A35,'90_Origen_Rentab_2025'!$C$3:$C$122,6,'90_Origen_Rentab_2025'!$E$3:$E$122,"INGRESOS OP") -> 66563 | D35: =SUMIFS('90_Origen_Rentab_2025'!$F$3:$F$122,'90_Origen_Rentab_2025'!$A$3:$A$122,$A35,'90_Origen_Rentab_2025'!$C$3:$C$122,6,'90_Origen_Rentab_2025'!$E$3:$E$122,"COSTOS OP") -> 76286 | E35: =C35-D35 -> -9723 | F35: =IF(C35=0,"-",E35/C35) -> -0.14607214
A36: Brasil | B36: jul | C36: =SUMIFS('90_Origen_Rentab_2025'!$F$3:$F$122,'90_Origen_Rentab_2025'!$A$3:$A$122,$A36,'90_Origen_Rentab_2025'!$C$3:$C$122,7,'90_Origen_Rentab_2025'!$E$3:$E$122,"INGRESOS OP") -> 47717 | D36: =SUMIFS('90_Origen_Rentab_2025'!$F$3:$F$122,'90_Origen_Rentab_2025'!$A$3:$A$122,$A36,'90_Origen_Rentab_2025'!$C$3:$C$122,7,'90_Origen_Rentab_2025'!$E$3:$E$122,"COSTOS OP") -> 31019 | E36: =C36-D36 -> 16698 | F36: =IF(C36=0,"-",E36/C36) -> 0.34993818
A37: Brasil | B37: ago | C37: =SUMIFS('90_Origen_Rentab_2025'!$F$3:$F$122,'90_Origen_Rentab_2025'!$A$3:$A$122,$A37,'90_Origen_Rentab_2025'!$C$3:$C$122,8,'90_Origen_Rentab_2025'!$E$3:$E$122,"INGRESOS OP") -> 119652 | D37: =SUMIFS('90_Origen_Rentab_2025'!$F$3:$F$122,'90_Origen_Rentab_2025'!$A$3:$A$122,$A37,'90_Origen_Rentab_2025'!$C$3:$C$122,8,'90_Origen_Rentab_2025'!$E$3:$E$122,"COSTOS OP") -> 21475 | E37: =C37-D37 -> 98177 | F37: =IF(C37=0,"-",E37/C37) -> 0.82052118
A38: Brasil | B38: sep | C38: =SUMIFS('90_Origen_Rentab_2025'!$F$3:$F$122,'90_Origen_Rentab_2025'!$A$3:$A$122,$A38,'90_Origen_Rentab_2025'!$C$3:$C$122,9,'90_Origen_Rentab_2025'!$E$3:$E$122,"INGRESOS OP") -> 203588 | D38: =SUMIFS('90_Origen_Rentab_2025'!$F$3:$F$122,'90_Origen_Rentab_2025'!$A$3:$A$122,$A38,'90_Origen_Rentab_2025'!$C$3:$C$122,9,'90_Origen_Rentab_2025'!$E$3:$E$122,"COSTOS OP") -> 77323 | E38: =C38-D38 -> 126265 | F38: =IF(C38=0,"-",E38/C38) -> 0.62019864
A39: Brasil | B39: oct | C39: =SUMIFS('90_Origen_Rentab_2025'!$F$3:$F$122,'90_Origen_Rentab_2025'!$A$3:$A$122,$A39,'90_Origen_Rentab_2025'!$C$3:$C$122,10,'90_Origen_Rentab_2025'!$E$3:$E$122,"INGRESOS OP") -> 325062 | D39: =SUMIFS('90_Origen_Rentab_2025'!$F$3:$F$122,'90_Origen_Rentab_2025'!$A$3:$A$122,$A39,'90_Origen_Rentab_2025'!$C$3:$C$122,10,'90_Origen_Rentab_2025'!$E$3:$E$122,"COSTOS OP") -> 14049 | E39: =C39-D39 -> 311013 | F39: =IF(C39=0,"-",E39/C39) -> 0.95678055
A40: Brasil | B40: nov | C40: =SUMIFS('90_Origen_Rentab_2025'!$F$3:$F$122,'90_Origen_Rentab_2025'!$A$3:$A$122,$A40,'90_Origen_Rentab_2025'!$C$3:$C$122,11,'90_Origen_Rentab_2025'!$E$3:$E$122,"INGRESOS OP") -> 239603 | D40: =SUMIFS('90_Origen_Rentab_2025'!$F$3:$F$122,'90_Origen_Rentab_2025'!$A$3:$A$122,$A40,'90_Origen_Rentab_2025'!$C$3:$C$122,11,'90_Origen_Rentab_2025'!$E$3:$E$122,"COSTOS OP") -> 47971 | E40: =C40-D40 -> 191632 | F40: =IF(C40=0,"-",E40/C40) -> 0.79978965
A41: Brasil | B41: dic | C41: =SUMIFS('90_Origen_Rentab_2025'!$F$3:$F$122,'90_Origen_Rentab_2025'!$A$3:$A$122,$A41,'90_Origen_Rentab_2025'!$C$3:$C$122,12,'90_Origen_Rentab_2025'!$E$3:$E$122,"INGRESOS OP") -> 224116.51 | D41: =SUMIFS('90_Origen_Rentab_2025'!$F$3:$F$122,'90_Origen_Rentab_2025'!$A$3:$A$122,$A41,'90_Origen_Rentab_2025'!$C$3:$C$122,12,'90_Origen_Rentab_2025'!$E$3:$E$122,"COSTOS OP") -> 23001 | E41: =C41-D41 -> 201115.51 | F41: =IF(C41=0,"-",E41/C41) -> 0.89737035
A42: USA | B42: ene | C42: =SUMIFS('90_Origen_Rentab_2025'!$F$3:$F$122,'90_Origen_Rentab_2025'!$A$3:$A$122,$A42,'90_Origen_Rentab_2025'!$C$3:$C$122,1,'90_Origen_Rentab_2025'!$E$3:$E$122,"INGRESOS OP") -> 150453 | D42: =SUMIFS('90_Origen_Rentab_2025'!$F$3:$F$122,'90_Origen_Rentab_2025'!$A$3:$A$122,$A42,'90_Origen_Rentab_2025'!$C$3:$C$122,1,'90_Origen_Rentab_2025'!$E$3:$E$122,"COSTOS OP") -> 15 | E42: =C42-D42 -> 150438 | F42: =IF(C42=0,"-",E42/C42) -> 0.9999003
A43: USA | B43: feb | C43: =SUMIFS('90_Origen_Rentab_2025'!$F$3:$F$122,'90_Origen_Rentab_2025'!$A$3:$A$122,$A43,'90_Origen_Rentab_2025'!$C$3:$C$122,2,'90_Origen_Rentab_2025'!$E$3:$E$122,"INGRESOS OP") -> 243465.21 | D43: =SUMIFS('90_Origen_Rentab_2025'!$F$3:$F$122,'90_Origen_Rentab_2025'!$A$3:$A$122,$A43,'90_Origen_Rentab_2025'!$C$3:$C$122,2,'90_Origen_Rentab_2025'!$E$3:$E$122,"COSTOS OP") -> 2025 | E43: =C43-D43 -> 241440.21 | F43: =IF(C43=0,"-",E43/C43) -> 0.99168259
A44: USA | B44: mar | C44: =SUMIFS('90_Origen_Rentab_2025'!$F$3:$F$122,'90_Origen_Rentab_2025'!$A$3:$A$122,$A44,'90_Origen_Rentab_2025'!$C$3:$C$122,3,'90_Origen_Rentab_2025'!$E$3:$E$122,"INGRESOS OP") -> 141526 | D44: =SUMIFS('90_Origen_Rentab_2025'!$F$3:$F$122,'90_Origen_Rentab_2025'!$A$3:$A$122,$A44,'90_Origen_Rentab_2025'!$C$3:$C$122,3,'90_Origen_Rentab_2025'!$E$3:$E$122,"COSTOS OP") -> 58728 | E44: =C44-D44 -> 82798 | F44: =IF(C44=0,"-",E44/C44) -> 0.58503738
A45: USA | B45: abr | C45: =SUMIFS('90_Origen_Rentab_2025'!$F$3:$F$122,'90_Origen_Rentab_2025'!$A$3:$A$122,$A45,'90_Origen_Rentab_2025'!$C$3:$C$122,4,'90_Origen_Rentab_2025'!$E$3:$E$122,"INGRESOS OP") -> 169200 | D45: =SUMIFS('90_Origen_Rentab_2025'!$F$3:$F$122,'90_Origen_Rentab_2025'!$A$3:$A$122,$A45,'90_Origen_Rentab_2025'!$C$3:$C$122,4,'90_Origen_Rentab_2025'!$E$3:$E$122,"COSTOS OP") -> 9898 | E45: =C45-D45 -> 159302 | F45: =IF(C45=0,"-",E45/C45) -> 0.94150118
A46: USA | B46: may | C46: =SUMIFS('90_Origen_Rentab_2025'!$F$3:$F$122,'90_Origen_Rentab_2025'!$A$3:$A$122,$A46,'90_Origen_Rentab_2025'!$C$3:$C$122,5,'90_Origen_Rentab_2025'!$E$3:$E$122,"INGRESOS OP") -> 195090 | D46: =SUMIFS('90_Origen_Rentab_2025'!$F$3:$F$122,'90_Origen_Rentab_2025'!$A$3:$A$122,$A46,'90_Origen_Rentab_2025'!$C$3:$C$122,5,'90_Origen_Rentab_2025'!$E$3:$E$122,"COSTOS OP") -> 47666 | E46: =C46-D46 -> 147424 | F46: =IF(C46=0,"-",E46/C46) -> 0.75567174
A47: USA | B47: jun | C47: =SUMIFS('90_Origen_Rentab_2025'!$F$3:$F$122,'90_Origen_Rentab_2025'!$A$3:$A$122,$A47,'90_Origen_Rentab_2025'!$C$3:$C$122,6,'90_Origen_Rentab_2025'!$E$3:$E$122,"INGRESOS OP") -> 61796 | D47: =SUMIFS('90_Origen_Rentab_2025'!$F$3:$F$122,'90_Origen_Rentab_2025'!$A$3:$A$122,$A47,'90_Origen_Rentab_2025'!$C$3:$C$122,6,'90_Origen_Rentab_2025'!$E$3:$E$122,"COSTOS OP") -> 4178 | E47: =C47-D47 -> 57618 | F47: =IF(C47=0,"-",E47/C47) -> 0.93239045
A48: USA | B48: jul | C48: =SUMIFS('90_Origen_Rentab_2025'!$F$3:$F$122,'90_Origen_Rentab_2025'!$A$3:$A$122,$A48,'90_Origen_Rentab_2025'!$C$3:$C$122,7,'90_Origen_Rentab_2025'!$E$3:$E$122,"INGRESOS OP") -> 0 | D48: =SUMIFS('90_Origen_Rentab_2025'!$F$3:$F$122,'90_Origen_Rentab_2025'!$A$3:$A$122,$A48,'90_Origen_Rentab_2025'!$C$3:$C$122,7,'90_Origen_Rentab_2025'!$E$3:$E$122,"COSTOS OP") -> 10017 | E48: =C48-D48 -> -10017 | F48: =IF(C48=0,"-",E48/C48) -> -
A49: USA | B49: ago | C49: =SUMIFS('90_Origen_Rentab_2025'!$F$3:$F$122,'90_Origen_Rentab_2025'!$A$3:$A$122,$A49,'90_Origen_Rentab_2025'!$C$3:$C$122,8,'90_Origen_Rentab_2025'!$E$3:$E$122,"INGRESOS OP") -> 20000 | D49: =SUMIFS('90_Origen_Rentab_2025'!$F$3:$F$122,'90_Origen_Rentab_2025'!$A$3:$A$122,$A49,'90_Origen_Rentab_2025'!$C$3:$C$122,8,'90_Origen_Rentab_2025'!$E$3:$E$122,"COSTOS OP") -> 1015 | E49: =C49-D49 -> 18985 | F49: =IF(C49=0,"-",E49/C49) -> 0.94925
A50: USA | B50: sep | C50: =SUMIFS('90_Origen_Rentab_2025'!$F$3:$F$122,'90_Origen_Rentab_2025'!$A$3:$A$122,$A50,'90_Origen_Rentab_2025'!$C$3:$C$122,9,'90_Origen_Rentab_2025'!$E$3:$E$122,"INGRESOS OP") -> 0 | D50: =SUMIFS('90_Origen_Rentab_2025'!$F$3:$F$122,'90_Origen_Rentab_2025'!$A$3:$A$122,$A50,'90_Origen_Rentab_2025'!$C$3:$C$122,9,'90_Origen_Rentab_2025'!$E$3:$E$122,"COSTOS OP") -> 1000 | E50: =C50-D50 -> -1000 | F50: =IF(C50=0,"-",E50/C50) -> -
A51: USA | B51: oct | C51: =SUMIFS('90_Origen_Rentab_2025'!$F$3:$F$122,'90_Origen_Rentab_2025'!$A$3:$A$122,$A51,'90_Origen_Rentab_2025'!$C$3:$C$122,10,'90_Origen_Rentab_2025'!$E$3:$E$122,"INGRESOS OP") -> 45000 | D51: =SUMIFS('90_Origen_Rentab_2025'!$F$3:$F$122,'90_Origen_Rentab_2025'!$A$3:$A$122,$A51,'90_Origen_Rentab_2025'!$C$3:$C$122,10,'90_Origen_Rentab_2025'!$E$3:$E$122,"COSTOS OP") -> 88411 | E51: =C51-D51 -> -43411 | F51: =IF(C51=0,"-",E51/C51) -> -0.96468889
A52: USA | B52: nov | C52: =SUMIFS('90_Origen_Rentab_2025'!$F$3:$F$122,'90_Origen_Rentab_2025'!$A$3:$A$122,$A52,'90_Origen_Rentab_2025'!$C$3:$C$122,11,'90_Origen_Rentab_2025'!$E$3:$E$122,"INGRESOS OP") -> 0 | D52: =SUMIFS('90_Origen_Rentab_2025'!$F$3:$F$122,'90_Origen_Rentab_2025'!$A$3:$A$122,$A52,'90_Origen_Rentab_2025'!$C$3:$C$122,11,'90_Origen_Rentab_2025'!$E$3:$E$122,"COSTOS OP") -> 1000 | E52: =C52-D52 -> -1000 | F52: =IF(C52=0,"-",E52/C52) -> -
A53: USA | B53: dic | C53: =SUMIFS('90_Origen_Rentab_2025'!$F$3:$F$122,'90_Origen_Rentab_2025'!$A$3:$A$122,$A53,'90_Origen_Rentab_2025'!$C$3:$C$122,12,'90_Origen_Rentab_2025'!$E$3:$E$122,"INGRESOS OP") -> 178785 | D53: =SUMIFS('90_Origen_Rentab_2025'!$F$3:$F$122,'90_Origen_Rentab_2025'!$A$3:$A$122,$A53,'90_Origen_Rentab_2025'!$C$3:$C$122,12,'90_Origen_Rentab_2025'!$E$3:$E$122,"COSTOS OP") -> 218410 | E53: =C53-D53 -> -39625 | F53: =IF(C53=0,"-",E53/C53) -> -0.22163492
A54: Otros | B54: ene | C54: =SUMIFS('90_Origen_Rentab_2025'!$F$3:$F$122,'90_Origen_Rentab_2025'!$A$3:$A$122,$A54,'90_Origen_Rentab_2025'!$C$3:$C$122,1,'90_Origen_Rentab_2025'!$E$3:$E$122,"INGRESOS OP") -> 0 | D54: =SUMIFS('90_Origen_Rentab_2025'!$F$3:$F$122,'90_Origen_Rentab_2025'!$A$3:$A$122,$A54,'90_Origen_Rentab_2025'!$C$3:$C$122,1,'90_Origen_Rentab_2025'!$E$3:$E$122,"COSTOS OP") -> 14044 | E54: =C54-D54 -> -14044 | F54: =IF(C54=0,"-",E54/C54) -> -
A55: Otros | B55: feb | C55: =SUMIFS('90_Origen_Rentab_2025'!$F$3:$F$122,'90_Origen_Rentab_2025'!$A$3:$A$122,$A55,'90_Origen_Rentab_2025'!$C$3:$C$122,2,'90_Origen_Rentab_2025'!$E$3:$E$122,"INGRESOS OP") -> 21682 | D55: =SUMIFS('90_Origen_Rentab_2025'!$F$3:$F$122,'90_Origen_Rentab_2025'!$A$3:$A$122,$A55,'90_Origen_Rentab_2025'!$C$3:$C$122,2,'90_Origen_Rentab_2025'!$E$3:$E$122,"COSTOS OP") -> 0 | E55: =C55-D55 -> 21682 | F55: =IF(C55=0,"-",E55/C55) -> 1
A56: Otros | B56: mar | C56: =SUMIFS('90_Origen_Rentab_2025'!$F$3:$F$122,'90_Origen_Rentab_2025'!$A$3:$A$122,$A56,'90_Origen_Rentab_2025'!$C$3:$C$122,3,'90_Origen_Rentab_2025'!$E$3:$E$122,"INGRESOS OP") -> 45478 | D56: =SUMIFS('90_Origen_Rentab_2025'!$F$3:$F$122,'90_Origen_Rentab_2025'!$A$3:$A$122,$A56,'90_Origen_Rentab_2025'!$C$3:$C$122,3,'90_Origen_Rentab_2025'!$E$3:$E$122,"COSTOS OP") -> 0 | E56: =C56-D56 -> 45478 | F56: =IF(C56=0,"-",E56/C56) -> 1
A57: Otros | B57: abr | C57: =SUMIFS('90_Origen_Rentab_2025'!$F$3:$F$122,'90_Origen_Rentab_2025'!$A$3:$A$122,$A57,'90_Origen_Rentab_2025'!$C$3:$C$122,4,'90_Origen_Rentab_2025'!$E$3:$E$122,"INGRESOS OP") -> 0 | D57: =SUMIFS('90_Origen_Rentab_2025'!$F$3:$F$122,'90_Origen_Rentab_2025'!$A$3:$A$122,$A57,'90_Origen_Rentab_2025'!$C$3:$C$122,4,'90_Origen_Rentab_2025'!$E$3:$E$122,"COSTOS OP") -> 14380 | E57: =C57-D57 -> -14380 | F57: =IF(C57=0,"-",E57/C57) -> -
A58: Otros | B58: may | C58: =SUMIFS('90_Origen_Rentab_2025'!$F$3:$F$122,'90_Origen_Rentab_2025'!$A$3:$A$122,$A58,'90_Origen_Rentab_2025'!$C$3:$C$122,5,'90_Origen_Rentab_2025'!$E$3:$E$122,"INGRESOS OP") -> 0 | D58: =SUMIFS('90_Origen_Rentab_2025'!$F$3:$F$122,'90_Origen_Rentab_2025'!$A$3:$A$122,$A58,'90_Origen_Rentab_2025'!$C$3:$C$122,5,'90_Origen_Rentab_2025'!$E$3:$E$122,"COSTOS OP") -> 16000 | E58: =C58-D58 -> -16000 | F58: =IF(C58=0,"-",E58/C58) -> -
A59: Otros | B59: jun | C59: =SUMIFS('90_Origen_Rentab_2025'!$F$3:$F$122,'90_Origen_Rentab_2025'!$A$3:$A$122,$A59,'90_Origen_Rentab_2025'!$C$3:$C$122,6,'90_Origen_Rentab_2025'!$E$3:$E$122,"INGRESOS OP") -> 172045 | D59: =SUMIFS('90_Origen_Rentab_2025'!$F$3:$F$122,'90_Origen_Rentab_2025'!$A$3:$A$122,$A59,'90_Origen_Rentab_2025'!$C$3:$C$122,6,'90_Origen_Rentab_2025'!$E$3:$E$122,"COSTOS OP") -> 15094 | E59: =C59-D59 -> 156951 | F59: =IF(C59=0,"-",E59/C59) -> 0.91226714
A60: Otros | B60: jul | C60: =SUMIFS('90_Origen_Rentab_2025'!$F$3:$F$122,'90_Origen_Rentab_2025'!$A$3:$A$122,$A60,'90_Origen_Rentab_2025'!$C$3:$C$122,7,'90_Origen_Rentab_2025'!$E$3:$E$122,"INGRESOS OP") -> 0 | D60: =SUMIFS('90_Origen_Rentab_2025'!$F$3:$F$122,'90_Origen_Rentab_2025'!$A$3:$A$122,$A60,'90_Origen_Rentab_2025'!$C$3:$C$122,7,'90_Origen_Rentab_2025'!$E$3:$E$122,"COSTOS OP") -> 5684.8 | E60: =C60-D60 -> -5684.8 | F60: =IF(C60=0,"-",E60/C60) -> -
A61: Otros | B61: ago | C61: =SUMIFS('90_Origen_Rentab_2025'!$F$3:$F$122,'90_Origen_Rentab_2025'!$A$3:$A$122,$A61,'90_Origen_Rentab_2025'!$C$3:$C$122,8,'90_Origen_Rentab_2025'!$E$3:$E$122,"INGRESOS OP") -> 99524 | D61: =SUMIFS('90_Origen_Rentab_2025'!$F$3:$F$122,'90_Origen_Rentab_2025'!$A$3:$A$122,$A61,'90_Origen_Rentab_2025'!$C$3:$C$122,8,'90_Origen_Rentab_2025'!$E$3:$E$122,"COSTOS OP") -> 5684.8 | E61: =C61-D61 -> 93839.2 | F61: =IF(C61=0,"-",E61/C61) -> 0.94288011
A62: Otros | B62: sep | C62: =SUMIFS('90_Origen_Rentab_2025'!$F$3:$F$122,'90_Origen_Rentab_2025'!$A$3:$A$122,$A62,'90_Origen_Rentab_2025'!$C$3:$C$122,9,'90_Origen_Rentab_2025'!$E$3:$E$122,"INGRESOS OP") -> 0 | D62: =SUMIFS('90_Origen_Rentab_2025'!$F$3:$F$122,'90_Origen_Rentab_2025'!$A$3:$A$122,$A62,'90_Origen_Rentab_2025'!$C$3:$C$122,9,'90_Origen_Rentab_2025'!$E$3:$E$122,"COSTOS OP") -> 5684.8 | E62: =C62-D62 -> -5684.8 | F62: =IF(C62=0,"-",E62/C62) -> -
A63: Otros | B63: oct | C63: =SUMIFS('90_Origen_Rentab_2025'!$F$3:$F$122,'90_Origen_Rentab_2025'!$A$3:$A$122,$A63,'90_Origen_Rentab_2025'!$C$3:$C$122,10,'90_Origen_Rentab_2025'!$E$3:$E$122,"INGRESOS OP") -> 0 | D63: =SUMIFS('90_Origen_Rentab_2025'!$F$3:$F$122,'90_Origen_Rentab_2025'!$A$3:$A$122,$A63,'90_Origen_Rentab_2025'!$C$3:$C$122,10,'90_Origen_Rentab_2025'!$E$3:$E$122,"COSTOS OP") -> 5684.8 | E63: =C63-D63 -> -5684.8 | F63: =IF(C63=0,"-",E63/C63) -> -
A64: Otros | B64: nov | C64: =SUMIFS('90_Origen_Rentab_2025'!$F$3:$F$122,'90_Origen_Rentab_2025'!$A$3:$A$122,$A64,'90_Origen_Rentab_2025'!$C$3:$C$122,11,'90_Origen_Rentab_2025'!$E$3:$E$122,"INGRESOS OP") -> 0 | D64: =SUMIFS('90_Origen_Rentab_2025'!$F$3:$F$122,'90_Origen_Rentab_2025'!$A$3:$A$122,$A64,'90_Origen_Rentab_2025'!$C$3:$C$122,11,'90_Origen_Rentab_2025'!$E$3:$E$122,"COSTOS OP") -> 5684.8 | E64: =C64-D64 -> -5684.8 | F64: =IF(C64=0,"-",E64/C64) -> -
A65: Otros | B65: dic | C65: =SUMIFS('90_Origen_Rentab_2025'!$F$3:$F$122,'90_Origen_Rentab_2025'!$A$3:$A$122,$A65,'90_Origen_Rentab_2025'!$C$3:$C$122,12,'90_Origen_Rentab_2025'!$E$3:$E$122,"INGRESOS OP") -> 0 | D65: =SUMIFS('90_Origen_Rentab_2025'!$F$3:$F$122,'90_Origen_Rentab_2025'!$A$3:$A$122,$A65,'90_Origen_Rentab_2025'!$C$3:$C$122,12,'90_Origen_Rentab_2025'!$E$3:$E$122,"COSTOS OP") -> 5684.8 | E65: =C65-D65 -> -5684.8 | F65: =IF(C65=0,"-",E65/C65) -> -
A66: Subtotal anual 2025 por país
A67: País | C67: Ingreso Op. USD | D67: Gasto Op. USD | E67: Beneficio USD | F67: Margen %
A68: Chile | C68: =SUMIFS('90_Origen_Rentab_2025'!$F$3:$F$122,'90_Origen_Rentab_2025'!$A$3:$A$122,$A68,'90_Origen_Rentab_2025'!$E$3:$E$122,"INGRESOS OP") -> 3592126.9 | D68: =SUMIFS('90_Origen_Rentab_2025'!$F$3:$F$122,'90_Origen_Rentab_2025'!$A$3:$A$122,$A68,'90_Origen_Rentab_2025'!$E$3:$E$122,"COSTOS OP") -> 4999267.5 | E68: =C68-D68 -> -1407140.6 | F68: =IF(C68=0,"-",E68/C68) -> -0.39172909
A69: Perú | C69: =SUMIFS('90_Origen_Rentab_2025'!$F$3:$F$122,'90_Origen_Rentab_2025'!$A$3:$A$122,$A69,'90_Origen_Rentab_2025'!$E$3:$E$122,"INGRESOS OP") -> 2417353 | D69: =SUMIFS('90_Origen_Rentab_2025'!$F$3:$F$122,'90_Origen_Rentab_2025'!$A$3:$A$122,$A69,'90_Origen_Rentab_2025'!$E$3:$E$122,"COSTOS OP") -> 1731862.8 | E69: =C69-D69 -> 685490.21 | F69: =IF(C69=0,"-",E69/C69) -> 0.28357059
A70: Brasil | C70: =SUMIFS('90_Origen_Rentab_2025'!$F$3:$F$122,'90_Origen_Rentab_2025'!$A$3:$A$122,$A70,'90_Origen_Rentab_2025'!$E$3:$E$122,"INGRESOS OP") -> 1597092.2 | D70: =SUMIFS('90_Origen_Rentab_2025'!$F$3:$F$122,'90_Origen_Rentab_2025'!$A$3:$A$122,$A70,'90_Origen_Rentab_2025'!$E$3:$E$122,"COSTOS OP") -> 451717.4 | E70: =C70-D70 -> 1145374.8 | F70: =IF(C70=0,"-",E70/C70) -> 0.71716261
A71: USA | C71: =SUMIFS('90_Origen_Rentab_2025'!$F$3:$F$122,'90_Origen_Rentab_2025'!$A$3:$A$122,$A71,'90_Origen_Rentab_2025'!$E$3:$E$122,"INGRESOS OP") -> 1205315.2 | D71: =SUMIFS('90_Origen_Rentab_2025'!$F$3:$F$122,'90_Origen_Rentab_2025'!$A$3:$A$122,$A71,'90_Origen_Rentab_2025'!$E$3:$E$122,"COSTOS OP") -> 442363 | E71: =C71-D71 -> 762952.21 | F71: =IF(C71=0,"-",E71/C71) -> 0.63298978
A72: Otros | C72: =SUMIFS('90_Origen_Rentab_2025'!$F$3:$F$122,'90_Origen_Rentab_2025'!$A$3:$A$122,$A72,'90_Origen_Rentab_2025'!$E$3:$E$122,"INGRESOS OP") -> 338729 | D72: =SUMIFS('90_Origen_Rentab_2025'!$F$3:$F$122,'90_Origen_Rentab_2025'!$A$3:$A$122,$A72,'90_Origen_Rentab_2025'!$E$3:$E$122,"COSTOS OP") -> 93626.8 | E72: =C72-D72 -> 245102.2 | F72: =IF(C72=0,"-",E72/C72) -> 0.72359379
A73: TOTAL 2025 | C73: =SUM(C68:C72) -> 9150616.3 | D73: =SUM(D68:D72) -> 7718837.5 | E73: =SUM(E68:E72) -> 1431778.8 | F73: =IF(C73=0,"-",E73/C73) -> 0.15646802
A76: B) 2024 — Resultado operacional de gestión CONSOLIDADO por mes (USD). fuente: 'Gastos a Diciembre 2024_v0.xlsx' hoja 'Beneficio'. Margen por país 2024 no disponible (solo consolidado).
A77: Mes 2024 | B77: Ingresos USD | C77: Gastos USD | D77: Beneficio USD | E77: Margen %
A78: ene | B78: =SUMIFS('90_Origen_PL2024'!$E$3:$E$38,'90_Origen_PL2024'!$D$3:$D$38,"Ingresos",'90_Origen_PL2024'!$B$3:$B$38,1) -> 782472.65 | C78: =SUMIFS('90_Origen_PL2024'!$E$3:$E$38,'90_Origen_PL2024'!$D$3:$D$38,"Gastos",'90_Origen_PL2024'!$B$3:$B$38,1) -> 688030.16 | D78: =B78-C78 -> 94442.49 | E78: =IF(B78=0,"-",D78/B78) -> 0.1206975
A79: feb | B79: =SUMIFS('90_Origen_PL2024'!$E$3:$E$38,'90_Origen_PL2024'!$D$3:$D$38,"Ingresos",'90_Origen_PL2024'!$B$3:$B$38,2) -> 579083.73 | C79: =SUMIFS('90_Origen_PL2024'!$E$3:$E$38,'90_Origen_PL2024'!$D$3:$D$38,"Gastos",'90_Origen_PL2024'!$B$3:$B$38,2) -> 472255.04 | D79: =B79-C79 -> 106828.69 | E79: =IF(B79=0,"-",D79/B79) -> 0.18447883
A80: mar | B80: =SUMIFS('90_Origen_PL2024'!$E$3:$E$38,'90_Origen_PL2024'!$D$3:$D$38,"Ingresos",'90_Origen_PL2024'!$B$3:$B$38,3) -> 663711.77 | C80: =SUMIFS('90_Origen_PL2024'!$E$3:$E$38,'90_Origen_PL2024'!$D$3:$D$38,"Gastos",'90_Origen_PL2024'!$B$3:$B$38,3) -> 437957.9 | D80: =B80-C80 -> 225753.87 | E80: =IF(B80=0,"-",D80/B80) -> 0.34013842
A81: abr | B81: =SUMIFS('90_Origen_PL2024'!$E$3:$E$38,'90_Origen_PL2024'!$D$3:$D$38,"Ingresos",'90_Origen_PL2024'!$B$3:$B$38,4) -> 492664.2 | C81: =SUMIFS('90_Origen_PL2024'!$E$3:$E$38,'90_Origen_PL2024'!$D$3:$D$38,"Gastos",'90_Origen_PL2024'!$B$3:$B$38,4) -> 351009.4 | D81: =B81-C81 -> 141654.8 | E81: =IF(B81=0,"-",D81/B81) -> 0.2875281
A82: may | B82: =SUMIFS('90_Origen_PL2024'!$E$3:$E$38,'90_Origen_PL2024'!$D$3:$D$38,"Ingresos",'90_Origen_PL2024'!$B$3:$B$38,5) -> 817072 | C82: =SUMIFS('90_Origen_PL2024'!$E$3:$E$38,'90_Origen_PL2024'!$D$3:$D$38,"Gastos",'90_Origen_PL2024'!$B$3:$B$38,5) -> 522763.43 | D82: =B82-C82 -> 294308.57 | E82: =IF(B82=0,"-",D82/B82) -> 0.36019906
A83: jun | B83: =SUMIFS('90_Origen_PL2024'!$E$3:$E$38,'90_Origen_PL2024'!$D$3:$D$38,"Ingresos",'90_Origen_PL2024'!$B$3:$B$38,6) -> 398011 | C83: =SUMIFS('90_Origen_PL2024'!$E$3:$E$38,'90_Origen_PL2024'!$D$3:$D$38,"Gastos",'90_Origen_PL2024'!$B$3:$B$38,6) -> 394836.49 | D83: =B83-C83 -> 3174.51 | E83: =IF(B83=0,"-",D83/B83) -> 0.0079759353
A84: jul | B84: =SUMIFS('90_Origen_PL2024'!$E$3:$E$38,'90_Origen_PL2024'!$D$3:$D$38,"Ingresos",'90_Origen_PL2024'!$B$3:$B$38,7) -> 464298.77 | C84: =SUMIFS('90_Origen_PL2024'!$E$3:$E$38,'90_Origen_PL2024'!$D$3:$D$38,"Gastos",'90_Origen_PL2024'!$B$3:$B$38,7) -> 526620.49 | D84: =B84-C84 -> -62321.72 | E84: =IF(B84=0,"-",D84/B84) -> -0.13422762
A85: ago | B85: =SUMIFS('90_Origen_PL2024'!$E$3:$E$38,'90_Origen_PL2024'!$D$3:$D$38,"Ingresos",'90_Origen_PL2024'!$B$3:$B$38,8) -> 672285.96 | C85: =SUMIFS('90_Origen_PL2024'!$E$3:$E$38,'90_Origen_PL2024'!$D$3:$D$38,"Gastos",'90_Origen_PL2024'!$B$3:$B$38,8) -> 538310.08 | D85: =B85-C85 -> 133975.88 | E85: =IF(B85=0,"-",D85/B85) -> 0.19928407
A86: sep | B86: =SUMIFS('90_Origen_PL2024'!$E$3:$E$38,'90_Origen_PL2024'!$D$3:$D$38,"Ingresos",'90_Origen_PL2024'!$B$3:$B$38,9) -> 1311681 | C86: =SUMIFS('90_Origen_PL2024'!$E$3:$E$38,'90_Origen_PL2024'!$D$3:$D$38,"Gastos",'90_Origen_PL2024'!$B$3:$B$38,9) -> 383777.24 | D86: =B86-C86 -> 927903.76 | E86: =IF(B86=0,"-",D86/B86) -> 0.70741572
A87: oct | B87: =SUMIFS('90_Origen_PL2024'!$E$3:$E$38,'90_Origen_PL2024'!$D$3:$D$38,"Ingresos",'90_Origen_PL2024'!$B$3:$B$38,10) -> 1003565.1 | C87: =SUMIFS('90_Origen_PL2024'!$E$3:$E$38,'90_Origen_PL2024'!$D$3:$D$38,"Gastos",'90_Origen_PL2024'!$B$3:$B$38,10) -> 519012.89 | D87: =B87-C87 -> 484552.2 | E87: =IF(B87=0,"-",D87/B87) -> 0.48283086
A88: nov | B88: =SUMIFS('90_Origen_PL2024'!$E$3:$E$38,'90_Origen_PL2024'!$D$3:$D$38,"Ingresos",'90_Origen_PL2024'!$B$3:$B$38,11) -> 614740 | C88: =SUMIFS('90_Origen_PL2024'!$E$3:$E$38,'90_Origen_PL2024'!$D$3:$D$38,"Gastos",'90_Origen_PL2024'!$B$3:$B$38,11) -> 452203.54 | D88: =B88-C88 -> 162536.46 | E88: =IF(B88=0,"-",D88/B88) -> 0.26439871
A89: dic | B89: =SUMIFS('90_Origen_PL2024'!$E$3:$E$38,'90_Origen_PL2024'!$D$3:$D$38,"Ingresos",'90_Origen_PL2024'!$B$3:$B$38,12) -> 475262 | C89: =SUMIFS('90_Origen_PL2024'!$E$3:$E$38,'90_Origen_PL2024'!$D$3:$D$38,"Gastos",'90_Origen_PL2024'!$B$3:$B$38,12) -> 681066.38 | D89: =B89-C89 -> -205804.38 | E89: =IF(B89=0,"-",D89/B89) -> -0.43303353
A90: TOTAL 2024 | B90: =SUM(B78:B89) -> 8274848.2 | C90: =SUM(C78:C89) -> 5967843 | D90: =SUM(D78:D89) -> 2307005.1 | E90: =IF(B90=0,"-",D90/B90) -> 0.27879728
A92: B2) 2024 — Ingreso por País (anual, USD). Fuente: 'Ingresos para PPT_Dic'. Contraste: Emitido USD del ledger.
A93: País | B93: Ingreso 2024 USD (gestión) | C93: Contraste: Emitido USD (ledger)
A94: Chile | B94: =SUMIFS('90_Origen_Ing2024_Pais'!$E$3:$E$62,'90_Origen_Ing2024_Pais'!$A$3:$A$62,$A94) -> 3370428.5 | C94: =SUMIFS('90_Origen_Ledger_EdP'!$K$3:$K$702,'90_Origen_Ledger_EdP'!$F$3:$F$702,$A94,'90_Origen_Ledger_EdP'!$I$3:$I$702,2024) -> 3522359.5
A95: Perú | B95: =SUMIFS('90_Origen_Ing2024_Pais'!$E$3:$E$62,'90_Origen_Ing2024_Pais'!$A$3:$A$62,$A95) -> 2077901.3 | C95: =SUMIFS('90_Origen_Ledger_EdP'!$K$3:$K$702,'90_Origen_Ledger_EdP'!$F$3:$F$702,$A95,'90_Origen_Ledger_EdP'!$I$3:$I$702,2024) -> 2105737.1
A96: Brasil | B96: =SUMIFS('90_Origen_Ing2024_Pais'!$E$3:$E$62,'90_Origen_Ing2024_Pais'!$A$3:$A$62,$A96) -> 1210944.4 | C96: =SUMIFS('90_Origen_Ledger_EdP'!$K$3:$K$702,'90_Origen_Ledger_EdP'!$F$3:$F$702,$A96,'90_Origen_Ledger_EdP'!$I$3:$I$702,2024) -> 1007708
A97: USA | B97: =SUMIFS('90_Origen_Ing2024_Pais'!$E$3:$E$62,'90_Origen_Ing2024_Pais'!$A$3:$A$62,$A97) -> 1463474 | C97: =SUMIFS('90_Origen_Ledger_EdP'!$K$3:$K$702,'90_Origen_Ledger_EdP'!$F$3:$F$702,$A97,'90_Origen_Ledger_EdP'!$I$3:$I$702,2024) -> 1563780
A98: Rusia | B98: =SUMIFS('90_Origen_Ing2024_Pais'!$E$3:$E$62,'90_Origen_Ing2024_Pais'!$A$3:$A$62,$A98) -> 152100 | C98: =SUMIFS('90_Origen_Ledger_EdP'!$K$3:$K$702,'90_Origen_Ledger_EdP'!$F$3:$F$702,$A98,'90_Origen_Ledger_EdP'!$I$3:$I$702,2024) -> 152100
A99: TOTAL 2024 | B99: =SUM(B94:B98) -> 8274848.2 | C99: =SUM(C94:C98) -> 8351684.5
A102: C) Tipo de producto (derivado del código FEL) — Ingreso devengado (EDP Emitido USD). El costo NO es divisible por tipo de producto.
A103: Tipo de producto (FEL) | B103: Emitido 2024 USD | C103: Emitido 2025 USD | D103: Total 24-25 USD | E103: % del total
A104: Core (Estudios FEL 0-1-2A-2B) | B104: =SUMIFS('90_Origen_Ledger_EdP'!$K$3:$K$702,'90_Origen_Ledger_EdP'!$S$3:$S$702,$A104,'90_Origen_Ledger_EdP'!$I$3:$I$702,2024) -> 4290363.2 | C104: =SUMIFS('90_Origen_Ledger_EdP'!$K$3:$K$702,'90_Origen_Ledger_EdP'!$S$3:$S$702,$A104,'90_Origen_Ledger_EdP'!$I$3:$I$702,2025) -> 4937055.1 | D104: =B104+C104 -> 9227418.3 | E104: =IF(SUM($D$104:$D$107)=0,0,D104/SUM($D$104:$D$107)) -> 0.51638113
A105: Adyacencia (Ingeniería FEL 3-4) | B105: =SUMIFS('90_Origen_Ledger_EdP'!$K$3:$K$702,'90_Origen_Ledger_EdP'!$S$3:$S$702,$A105,'90_Origen_Ledger_EdP'!$I$3:$I$702,2024) -> 1192308.4 | C105: =SUMIFS('90_Origen_Ledger_EdP'!$K$3:$K$702,'90_Origen_Ledger_EdP'!$S$3:$S$702,$A105,'90_Origen_Ledger_EdP'!$I$3:$I$702,2025) -> 885028.33 | D105: =B105+C105 -> 2077336.7 | E105: =IF(SUM($D$104:$D$107)=0,0,D105/SUM($D$104:$D$107)) -> 0.11625109
A106: Otro / Sin fase (OTR) | B106: =SUMIFS('90_Origen_Ledger_EdP'!$K$3:$K$702,'90_Origen_Ledger_EdP'!$S$3:$S$702,$A106,'90_Origen_Ledger_EdP'!$I$3:$I$702,2024) -> 2609891 | C106: =SUMIFS('90_Origen_Ledger_EdP'!$K$3:$K$702,'90_Origen_Ledger_EdP'!$S$3:$S$702,$A106,'90_Origen_Ledger_EdP'!$I$3:$I$702,2025) -> 3281696.7 | D106: =B106+C106 -> 5891587.7 | E106: =IF(SUM($D$104:$D$107)=0,0,D106/SUM($D$104:$D$107)) -> 0.3297027
...

Sheet 02_Ventas_2023_2025
A1: ENTREGABLE 2 · Ventas por país y cliente (2023→2026 parcial)
A2: Definición de VENTA = 'Emitido USD' (devengo real del EDP). 'Proyectado USD' se descarta como principal (=0 en 2025). Contraste: Proyectado / Ingresado.
A4: A) Venta (Emitido USD) por País × Cliente × Año — top 10 clientes por país + resto
A5: País | B5: Cliente | C5: 2023 | D5: 2024 | E5: 2025 | F5: 2026 (parc.) | G5: Total 23-26 | H5: % país
A6: Chile | B6: CMP | C6: =SUMIFS('90_Origen_Ledger_EdP'!$K$3:$K$702,'90_Origen_Ledger_EdP'!$F$3:$F$702,$A6,'90_Origen_Ledger_EdP'!$E$3:$E$702,$B6,'90_Origen_Ledger_EdP'!$G$3:$G$702,2023) -> 2283982.6 | D6: =SUMIFS('90_Origen_Ledger_EdP'!$K$3:$K$702,'90_Origen_Ledger_EdP'!$F$3:$F$702,$A6,'90_Origen_Ledger_EdP'!$E$3:$E$702,$B6,'90_Origen_Ledger_EdP'!$G$3:$G$702,2024) -> 1652260.5 | E6: =SUMIFS('90_Origen_Ledger_EdP'!$K$3:$K$702,'90_Origen_Ledger_EdP'!$F$3:$F$702,$A6,'90_Origen_Ledger_EdP'!$E$3:$E$702,$B6,'90_Origen_Ledger_EdP'!$G$3:$G$702,2025) -> 423425 | F6: =SUMIFS('90_Origen_Ledger_EdP'!$K$3:$K$702,'90_Origen_Ledger_EdP'!$F$3:$F$702,$A6,'90_Origen_Ledger_EdP'!$E$3:$E$702,$B6,'90_Origen_Ledger_EdP'!$G$3:$G$702,2026) -> 0 | G6: =SUM(C6:F6) -> 4359668.1 | H6: =IF($G$17=0,"-",G6/$G$17) -> 0.36297503
A7: Chile | B7: AMSA | C7: =SUMIFS('90_Origen_Ledger_EdP'!$K$3:$K$702,'90_Origen_Ledger_EdP'!$F$3:$F$702,$A7,'90_Origen_Ledger_EdP'!$E$3:$E$702,$B7,'90_Origen_Ledger_EdP'!$G$3:$G$702,2023) -> 765922.76 | D7: =SUMIFS('90_Origen_Ledger_EdP'!$K$3:$K$702,'90_Origen_Ledger_EdP'!$F$3:$F$702,$A7,'90_Origen_Ledger_EdP'!$E$3:$E$702,$B7,'90_Origen_Ledger_EdP'!$G$3:$G$702,2024) -> 390618 | E7: =SUMIFS('90_Origen_Ledger_EdP'!$K$3:$K$702,'90_Origen_Ledger_EdP'!$F$3:$F$702,$A7,'90_Origen_Ledger_EdP'!$E$3:$E$702,$B7,'90_Origen_Ledger_EdP'!$G$3:$G$702,2025) -> 375534.67 | F7: =SUMIFS('90_Origen_Ledger_EdP'!$K$3:$K$702,'90_Origen_Ledger_EdP'!$F$3:$F$702,$A7,'90_Origen_Ledger_EdP'!$E$3:$E$702,$B7,'90_Origen_Ledger_EdP'!$G$3:$G$702,2026) -> 23913 | G7: =SUM(C7:F7) -> 1555988.4 | H7: =IF($G$17=0,"-",G7/$G$17) -> 0.12954769
A8: Chile | B8: BHP | C8: =SUMIFS('90_Origen_Ledger_EdP'!$K$3:$K$702,'90_Origen_Ledger_EdP'!$F$3:$F$702,$A8,'90_Origen_Ledger_EdP'!$E$3:$E$702,$B8,'90_Origen_Ledger_EdP'!$G$3:$G$702,2023) -> 50688.323 | D8: =SUMIFS('90_Origen_Ledger_EdP'!$K$3:$K$702,'90_Origen_Ledger_EdP'!$F$3:$F$702,$A8,'90_Origen_Ledger_EdP'!$E$3:$E$702,$B8,'90_Origen_Ledger_EdP'!$G$3:$G$702,2024) -> 116314 | E8: =SUMIFS('90_Origen_Ledger_EdP'!$K$3:$K$702,'90_Origen_Ledger_EdP'!$F$3:$F$702,$A8,'90_Origen_Ledger_EdP'!$E$3:$E$702,$B8,'90_Origen_Ledger_EdP'!$G$3:$G$702,2025) -> 1153726.4 | F8: =SUMIFS('90_Origen_Ledger_EdP'!$K$3:$K$702,'90_Origen_Ledger_EdP'!$F$3:$F$702,$A8,'90_Origen_Ledger_EdP'!$E$3:$E$702,$B8,'90_Origen_Ledger_EdP'!$G$3:$G$702,2026) -> 0 | G8: =SUM(C8:F8) -> 1320728.8 | H8: =IF($G$17=0,"-",G8/$G$17) -> 0.10996056
A9: Chile | B9: Codelco | C9: =SUMIFS('90_Origen_Ledger_EdP'!$K$3:$K$702,'90_Origen_Ledger_EdP'!$F$3:$F$702,$A9,'90_Origen_Ledger_EdP'!$E$3:$E$702,$B9,'90_Origen_Ledger_EdP'!$G$3:$G$702,2023) -> 349598 | D9: =SUMIFS('90_Origen_Ledger_EdP'!$K$3:$K$702,'90_Origen_Ledger_EdP'!$F$3:$F$702,$A9,'90_Origen_Ledger_EdP'!$E$3:$E$702,$B9,'90_Origen_Ledger_EdP'!$G$3:$G$702,2024) -> 289901 | E9: =SUMIFS('90_Origen_Ledger_EdP'!$K$3:$K$702,'90_Origen_Ledger_EdP'!$F$3:$F$702,$A9,'90_Origen_Ledger_EdP'!$E$3:$E$702,$B9,'90_Origen_Ledger_EdP'!$G$3:$G$702,2025) -> 125926.75 | F9: =SUMIFS('90_Origen_Ledger_EdP'!$K$3:$K$702,'90_Origen_Ledger_EdP'!$F$3:$F$702,$A9,'90_Origen_Ledger_EdP'!$E$3:$E$702,$B9,'90_Origen_Ledger_EdP'!$G$3:$G$702,2026) -> 292487 | G9: =SUM(C9:F9) -> 1057912.8 | H9: =IF($G$17=0,"-",G9/$G$17) -> 0.088079162
A10: Chile | B10: Lundin | C10: =SUMIFS('90_Origen_Ledger_EdP'!$K$3:$K$702,'90_Origen_Ledger_EdP'!$F$3:$F$702,$A10,'90_Origen_Ledger_EdP'!$E$3:$E$702,$B10,'90_Origen_Ledger_EdP'!$G$3:$G$702,2023) -> 390540.16 | D10: =SUMIFS('90_Origen_Ledger_EdP'!$K$3:$K$702,'90_Origen_Ledger_EdP'!$F$3:$F$702,$A10,'90_Origen_Ledger_EdP'!$E$3:$E$702,$B10,'90_Origen_Ledger_EdP'!$G$3:$G$702,2024) -> 313105.94 | E10: =SUMIFS('90_Origen_Ledger_EdP'!$K$3:$K$702,'90_Origen_Ledger_EdP'!$F$3:$F$702,$A10,'90_Origen_Ledger_EdP'!$E$3:$E$702,$B10,'90_Origen_Ledger_EdP'!$G$3:$G$702,2025) -> 299270 | F10: =SUMIFS('90_Origen_Ledger_EdP'!$K$3:$K$702,'90_Origen_Ledger_EdP'!$F$3:$F$702,$A10,'90_Origen_Ledger_EdP'!$E$3:$E$702,$B10,'90_Origen_Ledger_EdP'!$G$3:$G$702,2026) -> 0 | G10: =SUM(C10:F10) -> 1002916.1 | H10: =IF($G$17=0,"-",G10/$G$17) -> 0.083500278
A11: Chile | B11: Glencore | C11: =SUMIFS('90_Origen_Ledger_EdP'!$K$3:$K$702,'90_Origen_Ledger_EdP'!$F$3:$F$702,$A11,'90_Origen_Ledger_EdP'!$E$3:$E$702,$B11,'90_Origen_Ledger_EdP'!$G$3:$G$702,2023) -> 258540.53 | D11: =SUMIFS('90_Origen_Ledger_EdP'!$K$3:$K$702,'90_Origen_Ledger_EdP'!$F$3:$F$702,$A11,'90_Origen_Ledger_EdP'!$E$3:$E$702,$B11,'90_Origen_Ledger_EdP'!$G$3:$G$702,2024) -> 0 | E11: =SUMIFS('90_Origen_Ledger_EdP'!$K$3:$K$702,'90_Origen_Ledger_EdP'!$F$3:$F$702,$A11,'90_Origen_Ledger_EdP'!$E$3:$E$702,$B11,'90_Origen_Ledger_EdP'!$G$3:$G$702,2025) -> 198640 | F11: =SUMIFS('90_Origen_Ledger_EdP'!$K$3:$K$702,'90_Origen_Ledger_EdP'!$F$3:$F$702,$A11,'90_Origen_Ledger_EdP'!$E$3:$E$702,$B11,'90_Origen_Ledger_EdP'!$G$3:$G$702,2026) -> 186828 | G11: =SUM(C11:F11) -> 644008.53 | H11: =IF($G$17=0,"-",G11/$G$17) -> 0.053618535
A12: Chile | B12: Capstone Copper | C12: =SUMIFS('90_Origen_Ledger_EdP'!$K$3:$K$702,'90_Origen_Ledger_EdP'!$F$3:$F$702,$A12,'90_Origen_Ledger_EdP'!$E$3:$E$702,$B12,'90_Origen_Ledger_EdP'!$G$3:$G$702,2023) -> 0 | D12: =SUMIFS('90_Origen_Ledger_EdP'!$K$3:$K$702,'90_Origen_Ledger_EdP'!$F$3:$F$702,$A12,'90_Origen_Ledger_EdP'!$E$3:$E$702,$B12,'90_Origen_Ledger_EdP'!$G$3:$G$702,2024) -> 354849 | E12: =SUMIFS('90_Origen_Ledger_EdP'!$K$3:$K$702,'90_Origen_Ledger_EdP'!$F$3:$F$702,$A12,'90_Origen_Ledger_EdP'!$E$3:$E$702,$B12,'90_Origen_Ledger_EdP'!$G$3:$G$702,2025) -> 184058 | F12: =SUMIFS('90_Origen_Ledger_EdP'!$K$3:$K$702,'90_Origen_Ledger_EdP'!$F$3:$F$702,$A12,'90_Origen_Ledger_EdP'!$E$3:$E$702,$B12,'90_Origen_Ledger_EdP'!$G$3:$G$702,2026) -> 0 | G12: =SUM(C12:F12) -> 538907 | H12: =IF($G$17=0,"-",G12/$G$17) -> 0.044868045
A13: Chile | B13: AngloAmerican | C13: =SUMIFS('90_Origen_Ledger_EdP'!$K$3:$K$702,'90_Origen_Ledger_EdP'!$F$3:$F$702,$A13,'90_Origen_Ledger_EdP'!$E$3:$E$702,$B13,'90_Origen_Ledger_EdP'!$G$3:$G$702,2023) -> 0 | D13: =SUMIFS('90_Origen_Ledger_EdP'!$K$3:$K$702,'90_Origen_Ledger_EdP'!$F$3:$F$702,$A13,'90_Origen_Ledger_EdP'!$E$3:$E$702,$B13,'90_Origen_Ledger_EdP'!$G$3:$G$702,2024) -> 0 | E13: =SUMIFS('90_Origen_Ledger_EdP'!$K$3:$K$702,'90_Origen_Ledger_EdP'!$F$3:$F$702,$A13,'90_Origen_Ledger_EdP'!$E$3:$E$702,$B13,'90_Origen_Ledger_EdP'!$G$3:$G$702,2025) -> 340671.33 | F13: =SUMIFS('90_Origen_Ledger_EdP'!$K$3:$K$702,'90_Origen_Ledger_EdP'!$F$3:$F$702,$A13,'90_Origen_Ledger_EdP'!$E$3:$E$702,$B13,'90_Origen_Ledger_EdP'!$G$3:$G$702,2026) -> 0 | G13: =SUM(C13:F13) -> 340671.33 | H13: =IF($G$17=0,"-",G13/$G$17) -> 0.02836344
A14: Chile | B14: Mitsubichi | C14: =SUMIFS('90_Origen_Ledger_EdP'!$K$3:$K$702,'90_Origen_Ledger_EdP'!$F$3:$F$702,$A14,'90_Origen_Ledger_EdP'!$E$3:$E$702,$B14,'90_Origen_Ledger_EdP'!$G$3:$G$702,2023) -> 0 | D14: =SUMIFS('90_Origen_Ledger_EdP'!$K$3:$K$702,'90_Origen_Ledger_EdP'!$F$3:$F$702,$A14,'90_Origen_Ledger_EdP'!$E$3:$E$702,$B14,'90_Origen_Ledger_EdP'!$G$3:$G$702,2024) -> 215280 | E14: =SUMIFS('90_Origen_Ledger_EdP'!$K$3:$K$702,'90_Origen_Ledger_EdP'!$F$3:$F$702,$A14,'90_Origen_Ledger_EdP'!$E$3:$E$702,$B14,'90_Origen_Ledger_EdP'!$G$3:$G$702,2025) -> 23720 | F14: =SUMIFS('90_Origen_Ledger_EdP'!$K$3:$K$702,'90_Origen_Ledger_EdP'!$F$3:$F$702,$A14,'90_Origen_Ledger_EdP'!$E$3:$E$702,$B14,'90_Origen_Ledger_EdP'!$G$3:$G$702,2026) -> 0 | G14: =SUM(C14:F14) -> 239000 | H14: =IF($G$17=0,"-",G14/$G$17) -> 0.01989854
A15: Chile | B15: MEL | C15: =SUMIFS('90_Origen_Ledger_EdP'!$K$3:$K$702,'90_Origen_Ledger_EdP'!$F$3:$F$702,$A15,'90_Origen_Ledger_EdP'!$E$3:$E$702,$B15,'90_Origen_Ledger_EdP'!$G$3:$G$702,2023) -> 150618.18 | D15: =SUMIFS('90_Origen_Ledger_EdP'!$K$3:$K$702,'90_Origen_Ledger_EdP'!$F$3:$F$702,$A15,'90_Origen_Ledger_EdP'!$E$3:$E$702,$B15,'90_Origen_Ledger_EdP'!$G$3:$G$702,2024) -> 0 | E15: =SUMIFS('90_Origen_Ledger_EdP'!$K$3:$K$702,'90_Origen_Ledger_EdP'!$F$3:$F$702,$A15,'90_Origen_Ledger_EdP'!$E$3:$E$702,$B15,'90_Origen_Ledger_EdP'!$G$3:$G$702,2025) -> 0 | F15: =SUMIFS('90_Origen_Ledger_EdP'!$K$3:$K$702,'90_Origen_Ledger_EdP'!$F$3:$F$702,$A15,'90_Origen_Ledger_EdP'!$E$3:$E$702,$B15,'90_Origen_Ledger_EdP'!$G$3:$G$702,2026) -> 0 | G15: =SUM(C15:F15) -> 150618.18 | H15: =IF($G$17=0,"-",G15/$G$17) -> 0.012540092
A16: Chile | B16: Otros clientes (resto) | C16: =SUMIFS('90_Origen_Ledger_EdP'!$K$3:$K$702,'90_Origen_Ledger_EdP'!$F$3:$F$702,$A16,'90_Origen_Ledger_EdP'!$G$3:$G$702,2023)-SUM(C6:C15) -> 42285 | D16: =SUMIFS('90_Origen_Ledger_EdP'!$K$3:$K$702,'90_Origen_Ledger_EdP'!$F$3:$F$702,$A16,'90_Origen_Ledger_EdP'!$G$3:$G$702,2024)-SUM(D6:D15) -> 190031 | E16: =SUMIFS('90_Origen_Ledger_EdP'!$K$3:$K$702,'90_Origen_Ledger_EdP'!$F$3:$F$702,$A16,'90_Origen_Ledger_EdP'!$G$3:$G$702,2025)-SUM(E6:E15) -> 128461 | F16: =SUMIFS('90_Origen_Ledger_EdP'!$K$3:$K$702,'90_Origen_Ledger_EdP'!$F$3:$F$702,$A16,'90_Origen_Ledger_EdP'!$G$3:$G$702,2026)-SUM(F6:F15) -> 439735 | G16: =SUM(C16:F16) -> 800512 | H16: =IF($G$17=0,"-",G16/$G$17) -> 0.066648621
A17: Chile | B17: TOTAL Chile | C17: =SUM(C6:C16) -> 4292175.5 | D17: =SUM(D6:D16) -> 3522359.5 | E17: =SUM(E6:E16) -> 3253433.2 | F17: =SUM(F6:F16) -> 942963 | G17: =SUM(C17:F17) -> 12010931 | H17: 1
A18: Perú | B18: Minsur | C18: =SUMIFS('90_Origen_Ledger_EdP'!$K$3:$K$702,'90_Origen_Ledger_EdP'!$F$3:$F$702,$A18,'90_Origen_Ledger_EdP'!$E$3:$E$702,$B18,'90_Origen_Ledger_EdP'!$G$3:$G$702,2023) -> 933597.6 | D18: =SUMIFS('90_Origen_Ledger_EdP'!$K$3:$K$702,'90_Origen_Ledger_EdP'!$F$3:$F$702,$A18,'90_Origen_Ledger_EdP'!$E$3:$E$702,$B18,'90_Origen_Ledger_EdP'!$G$3:$G$702,2024) -> 405659.87 | E18: =SUMIFS('90_Origen_Ledger_EdP'!$K$3:$K$702,'90_Origen_Ledger_EdP'!$F$3:$F$702,$A18,'90_Origen_Ledger_EdP'!$E$3:$E$702,$B18,'90_Origen_Ledger_EdP'!$G$3:$G$702,2025) -> 356402 | F18: =SUMIFS('90_Origen_Ledger_EdP'!$K$3:$K$702,'90_Origen_Ledger_EdP'!$F$3:$F$702,$A18,'90_Origen_Ledger_EdP'!$E$3:$E$702,$B18,'90_Origen_Ledger_EdP'!$G$3:$G$702,2026) -> 50798 | G18: =SUM(C18:F18) -> 1746457.5 | H18: =IF($G$29=0,"-",G18/$G$29) -> 0.24832541
A19: Perú | B19: CD Capitals | C19: =SUMIFS('90_Origen_Ledger_EdP'!$K$3:$K$702,'90_Origen_Ledger_EdP'!$F$3:$F$702,$A19,'90_Origen_Ledger_EdP'!$E$3:$E$702,$B19,'90_Origen_Ledger_EdP'!$G$3:$G$702,2023) -> 221948.28 | D19: =SUMIFS('90_Origen_Ledger_EdP'!$K$3:$K$702,'90_Origen_Ledger_EdP'!$F$3:$F$702,$A19,'90_Origen_Ledger_EdP'!$E$3:$E$702,$B19,'90_Origen_Ledger_EdP'!$G$3:$G$702,2024) -> 817713 | E19: =SUMIFS('90_Origen_Ledger_EdP'!$K$3:$K$702,'90_Origen_Ledger_EdP'!$F$3:$F$702,$A19,'90_Origen_Ledger_EdP'!$E$3:$E$702,$B19,'90_Origen_Ledger_EdP'!$G$3:$G$702,2025) -> 336554 | F19: =SUMIFS('90_Origen_Ledger_EdP'!$K$3:$K$702,'90_Origen_Ledger_EdP'!$F$3:$F$702,$A19,'90_Origen_Ledger_EdP'!$E$3:$E$702,$B19,'90_Origen_Ledger_EdP'!$G$3:$G$702,2026) -> 86140 | G19: =SUM(C19:F19) -> 1462355.3 | H19: =IF($G$29=0,"-",G19/$G$29) -> 0.20792947
A20: Perú | B20: Las Bambas | C20: =SUMIFS('90_Origen_Ledger_EdP'!$K$3:$K$702,'90_Origen_Ledger_EdP'!$F$3:$F$702,$A20,'90_Origen_Ledger_EdP'!$E$3:$E$702,$B20,'90_Origen_Ledger_EdP'!$G$3:$G$702,2023) -> 40394 | D20: =SUMIFS('90_Origen_Ledger_EdP'!$K$3:$K$702,'90_Origen_Ledger_EdP'!$F$3:$F$702,$A20,'90_Origen_Ledger_EdP'!$E$3:$E$702,$B20,'90_Origen_Ledger_EdP'!$G$3:$G$702,2024) -> 189557 | E20: =SUMIFS('90_Origen_Ledger_EdP'!$K$3:$K$702,'90_Origen_Ledger_EdP'!$F$3:$F$702,$A20,'90_Origen_Ledger_EdP'!$E$3:$E$702,$B20,'90_Origen_Ledger_EdP'!$G$3:$G$702,2025) -> 1085729.6 | F20: =SUMIFS('90_Origen_Ledger_EdP'!$K$3:$K$702,'90_Origen_Ledger_EdP'!$F$3:$F$702,$A20,'90_Origen_Ledger_EdP'!$E$3:$E$702,$B20,'90_Origen_Ledger_EdP'!$G$3:$G$702,2026) -> 0 | G20: =SUM(C20:F20) -> 1315680.6 | H20: =IF($G$29=0,"-",G20/$G$29) -> 0.18707408
A21: Perú | B21: Marcobre | C21: =SUMIFS('90_Origen_Ledger_EdP'!$K$3:$K$702,'90_Origen_Ledger_EdP'!$F$3:$F$702,$A21,'90_Origen_Ledger_EdP'!$E$3:$E$702,$B21,'90_Origen_Ledger_EdP'!$G$3:$G$702,2023) -> 137832 | D21: =SUMIFS('90_Origen_Ledger_EdP'!$K$3:$K$702,'90_Origen_Ledger_EdP'!$F$3:$F$702,$A21,'90_Origen_Ledger_EdP'!$E$3:$E$702,$B21,'90_Origen_Ledger_EdP'!$G$3:$G$702,2024) -> 73833 | E21: =SUMIFS('90_Origen_Ledger_EdP'!$K$3:$K$702,'90_Origen_Ledger_EdP'!$F$3:$F$702,$A21,'90_Origen_Ledger_EdP'!$E$3:$E$702,$B21,'90_Origen_Ledger_EdP'!$G$3:$G$702,2025) -> 87945 | F21: =SUMIFS('90_Origen_Ledger_EdP'!$K$3:$K$702,'90_Origen_Ledger_EdP'!$F$3:$F$702,$A21,'90_Origen_Ledger_EdP'!$E$3:$E$702,$B21,'90_Origen_Ledger_EdP'!$G$3:$G$702,2026) -> 0 | G21: =SUM(C21:F21) -> 299610 | H21: =IF($G$29=0,"-",G21/$G$29) -> 0.042600967
A22: Perú | B22: Sierra metals | C22: =SUMIFS('90_Origen_Ledger_EdP'!$K$3:$K$702,'90_Origen_Ledger_EdP'!$F$3:$F$702,$A22,'90_Origen_Ledger_EdP'!$E$3:$E$702,$B22,'90_Origen_Ledger_EdP'!$G$3:$G$702,2023) -> 95353.875 | D22: =SUMIFS('90_Origen_Ledger_EdP'!$K$3:$K$702,'90_Origen_Ledger_EdP'!$F$3:$F$702,$A22,'90_Origen_Ledger_EdP'!$E$3:$E$702,$B22,'90_Origen_Ledger_EdP'!$G$3:$G$702,2024) -> 186049 | E22: =SUMIFS('90_Origen_Ledger_EdP'!$K$3:$K$702,'90_Origen_Ledger_EdP'!$F$3:$F$702,$A22,'90_Origen_Ledger_EdP'!$E$3:$E$702,$B22,'90_Origen_Ledger_EdP'!$G$3:$G$702,2025) -> 0 | F22: =SUMIFS('90_Origen_Ledger_EdP'!$K$3:$K$702,'90_Origen_Ledger_EdP'!$F$3:$F$702,$A22,'90_Origen_Ledger_EdP'!$E$3:$E$702,$B22,'90_Origen_Ledger_EdP'!$G$3:$G$702,2026) -> 0 | G22: =SUM(C22:F22) -> 281402.88 | H22: =IF($G$29=0,"-",G22/$G$29) -> 0.040012131
A23: Perú | B23: MiskiMayo | C23: =SUMIFS('90_Origen_Ledger_EdP'!$K$3:$K$702,'90_Origen_Ledger_EdP'!$F$3:$F$702,$A23,'90_Origen_Ledger_EdP'!$E$3:$E$702,$B23,'90_Origen_Ledger_EdP'!$G$3:$G$702,2023) -> 50472.9 | D23: =SUMIFS('90_Origen_Ledger_EdP'!$K$3:$K$702,'90_Origen_Ledger_EdP'!$F$3:$F$702,$A23,'90_Origen_Ledger_EdP'!$E$3:$E$702,$B23,'90_Origen_Ledger_EdP'!$G$3:$G$702,2024) -> 64663.2 | E23: =SUMIFS('90_Origen_Ledger_EdP'!$K$3:$K$702,'90_Origen_Ledger_EdP'!$F$3:$F$702,$A23,'90_Origen_Ledger_EdP'!$E$3:$E$702,$B23,'90_Origen_Ledger_EdP'!$G$3:$G$702,2025) -> 44033 | F23: =SUMIFS('90_Origen_Ledger_EdP'!$K$3:$K$702,'90_Origen_Ledger_EdP'!$F$3:$F$702,$A23,'90_Origen_Ledger_EdP'!$E$3:$E$702,$B23,'90_Origen_Ledger_EdP'!$G$3:$G$702,2026) -> 126618 | G23: =SUM(C23:F23) -> 285787.1 | H23: =IF($G$29=0,"-",G23/$G$29) -> 0.040635515
A24: Perú | B24: Glencore | C24: =SUMIFS('90_Origen_Ledger_EdP'!$K$3:$K$702,'90_Origen_Ledger_EdP'!$F$3:$F$702,$A24,'90_Origen_Ledger_EdP'!$E$3:$E$702,$B24,'90_Origen_Ledger_EdP'!$G$3:$G$702,2023) -> 0 | D24: =SUMIFS('90_Origen_Ledger_EdP'!$K$3:$K$702,'90_Origen_Ledger_EdP'!$F$3:$F$702,$A24,'90_Origen_Ledger_EdP'!$E$3:$E$702,$B24,'90_Origen_Ledger_EdP'!$G$3:$G$702,2024) -> 198000 | E24: =SUMIFS('90_Origen_Ledger_EdP'!$K$3:$K$702,'90_Origen_Ledger_EdP'!$F$3:$F$702,$A24,'90_Origen_Ledger_EdP'!$E$3:$E$702,$B24,'90_Origen_Ledger_EdP'!$G$3:$G$702,2025) -> 0 | F24: =SUMIFS('90_Origen_Ledger_EdP'!$K$3:$K$702,'90_Origen_Ledger_EdP'!$F$3:$F$702,$A24,'90_Origen_Ledger_EdP'!$E$3:$E$702,$B24,'90_Origen_Ledger_EdP'!$G$3:$G$702,2026) -> 0 | G24: =SUM(C24:F24) -> 198000 | H24: =IF($G$29=0,"-",G24/$G$29) -> 0.028153237
A25: Perú | B25: Alpayana | C25: =SUMIFS('90_Origen_Ledger_EdP'!$K$3:$K$702,'90_Origen_Ledger_EdP'!$F$3:$F$702,$A25,'90_Origen_Ledger_EdP'!$E$3:$E$702,$B25,'90_Origen_Ledger_EdP'!$G$3:$G$702,2023) -> 0 | D25: =SUMIFS('90_Origen_Ledger_EdP'!$K$3:$K$702,'90_Origen_Ledger_EdP'!$F$3:$F$702,$A25,'90_Origen_Ledger_EdP'!$E$3:$E$702,$B25,'90_Origen_Ledger_EdP'!$G$3:$G$702,2024) -> 0 | E25: =SUMIFS('90_Origen_Ledger_EdP'!$K$3:$K$702,'90_Origen_Ledger_EdP'!$F$3:$F$702,$A25,'90_Origen_Ledger_EdP'!$E$3:$E$702,$B25,'90_Origen_Ledger_EdP'!$G$3:$G$702,2025) -> 131313 | F25: =SUMIFS('90_Origen_Ledger_EdP'!$K$3:$K$702,'90_Origen_Ledger_EdP'!$F$3:$F$702,$A25,'90_Origen_Ledger_EdP'!$E$3:$E$702,$B25,'90_Origen_Ledger_EdP'!$G$3:$G$702,2026) -> 56306 | G25: =SUM(C25:F25) -> 187619 | H25: =IF($G$29=0,"-",G25/$G$29) -> 0.026677183
A26: Perú | B26: Emincar | C26: =SUMIFS('90_Origen_Ledger_EdP'!$K$3:$K$702,'90_Origen_Ledger_EdP'!$F$3:$F$702,$A26,'90_Origen_Ledger_EdP'!$E$3:$E$702,$B26,'90_Origen_Ledger_EdP'!$G$3:$G$702,2023) -> 0 | D26: =SUMIFS('90_Origen_Ledger_EdP'!$K$3:$K$702,'90_Origen_Ledger_EdP'!$F$3:$F$702,$A26,'90_Origen_Ledger_EdP'!$E$3:$E$702,$B26,'90_Origen_Ledger_EdP'!$G$3:$G$702,2024) -> 0 | E26: =SUMIFS('90_Origen_Ledger_EdP'!$K$3:$K$702,'90_Origen_Ledger_EdP'!$F$3:$F$702,$A26,'90_Origen_Ledger_EdP'!$E$3:$E$702,$B26,'90_Origen_Ledger_EdP'!$G$3:$G$702,2025) -> 0 | F26: =SUMIFS('90_Origen_Ledger_EdP'!$K$3:$K$702,'90_Origen_Ledger_EdP'!$F$3:$F$702,$A26,'90_Origen_Ledger_EdP'!$E$3:$E$702,$B26,'90_Origen_Ledger_EdP'!$G$3:$G$702,2026) -> 183496 | G26: =SUM(C26:F26) -> 183496 | H26: =IF($G$29=0,"-",G26/$G$29) -> 0.026090941
A27: Perú | B27: Raura | C27: =SUMIFS('90_Origen_Ledger_EdP'!$K$3:$K$702,'90_Origen_Ledger_EdP'!$F$3:$F$702,$A27,'90_Origen_Ledger_EdP'!$E$3:$E$702,$B27,'90_Origen_Ledger_EdP'!$G$3:$G$702,2023) -> 96638.4 | D27: =SUMIFS('90_Origen_Ledger_EdP'!$K$3:$K$702,'90_Origen_Ledger_EdP'!$F$3:$F$702,$A27,'90_Origen_Ledger_EdP'!$E$3:$E$702,$B27,'90_Origen_Ledger_EdP'!$G$3:$G$702,2024) -> 0 | E27: =SUMIFS('90_Origen_Ledger_EdP'!$K$3:$K$702,'90_Origen_Ledger_EdP'!$F$3:$F$702,$A27,'90_Origen_Ledger_EdP'!$E$3:$E$702,$B27,'90_Origen_Ledger_EdP'!$G$3:$G$702,2025) -> 0 | F27: =SUMIFS('90_Origen_Ledger_EdP'!$K$3:$K$702,'90_Origen_Ledger_EdP'!$F$3:$F$702,$A27,'90_Origen_Ledger_EdP'!$E$3:$E$702,$B27,'90_Origen_Ledger_EdP'!$G$3:$G$702,2026) -> 0 | G27: =SUM(C27:F27) -> 96638.4 | H27: =IF($G$29=0,"-",G27/$G$29) -> 0.013740827
A28: Perú | B28: Otros clientes (resto) | C28: =SUMIFS('90_Origen_Ledger_EdP'!$K$3:$K$702,'90_Origen_Ledger_EdP'!$F$3:$F$702,$A28,'90_Origen_Ledger_EdP'!$G$3:$G$702,2023)-SUM(C18:C27) -> 50760 | D28: =SUMIFS('90_Origen_Ledger_EdP'!$K$3:$K$702,'90_Origen_Ledger_EdP'!$F$3:$F$702,$A28,'90_Origen_Ledger_EdP'!$G$3:$G$702,2024)-SUM(D18:D27) -> 170262 | E28: =SUMIFS('90_Origen_Ledger_EdP'!$K$3:$K$702,'90_Origen_Ledger_EdP'!$F$3:$F$702,$A28,'90_Origen_Ledger_EdP'!$G$3:$G$702,2025)-SUM(E18:E27) -> 423077 | F28: =SUMIFS('90_Origen_Ledger_EdP'!$K$3:$K$702,'90_Origen_Ledger_EdP'!$F$3:$F$702,$A28,'90_Origen_Ledger_EdP'!$G$3:$G$702,2026)-SUM(F18:F27) -> 331793.29 | G28: =SUM(C28:F28) -> 975892.29 | H28: =IF($G$29=0,"-",G28/$G$29) -> 0.13876024
A29: Perú | B29: TOTAL Perú | C29: =SUM(C18:C28) -> 1626997.1 | D29: =SUM(D18:D28) -> 2105737.1 | E29: =SUM(E18:E28) -> 2465053.6 | F29: =SUM(F18:F28) -> 835151.29 | G29: =SUM(C29:F29) -> 7032939 | H29: 1
A30: Brasil | B30: Mosaic | C30: =SUMIFS('90_Origen_Ledger_EdP'!$K$3:$K$702,'90_Origen_Ledger_EdP'!$F$3:$F$702,$A30,'90_Origen_Ledger_EdP'!$E$3:$E$702,$B30,'90_Origen_Ledger_EdP'!$G$3:$G$702,2023) -> 600368.46 | D30: =SUMIFS('90_Origen_Ledger_EdP'!$K$3:$K$702,'90_Origen_Ledger_EdP'!$F$3:$F$702,$A30,'90_Origen_Ledger_EdP'!$E$3:$E$702,$B30,'90_Origen_Ledger_EdP'!$G$3:$G$702,2024) -> 612782 | E30: =SUMIFS('90_Origen_Ledger_EdP'!$K$3:$K$702,'90_Origen_Ledger_EdP'!$F$3:$F$702,$A30,'90_Origen_Ledger_EdP'!$E$3:$E$702,$B30,'90_Origen_Ledger_EdP'!$G$3:$G$702,2025) -> 404204 | F30: =SUMIFS('90_Origen_Ledger_EdP'!$K$3:$K$702,'90_Origen_Ledger_EdP'!$F$3:$F$702,$A30,'90_Origen_Ledger_EdP'!$E$3:$E$702,$B30,'90_Origen_Ledger_EdP'!$G$3:$G$702,2026) -> 101210 | G30: =SUM(C30:F30) -> 1718564.5 | H30: =IF($G$40=0,"-",G30/$G$40) -> 0.42563915
A31: Brasil | B31: EroCopper | C31: =SUMIFS('90_Origen_Ledger_EdP'!$K$3:$K$702,'90_Origen_Ledger_EdP'!$F$3:$F$702,$A31,'90_Origen_Ledger_EdP'!$E$3:$E$702,$B31,'90_Origen_Ledger_EdP'!$G$3:$G$702,2023) -> 0 | D31: =SUMIFS('90_Origen_Ledger_EdP'!$K$3:$K$702,'90_Origen_Ledger_EdP'!$F$3:$F$702,$A31,'90_Origen_Ledger_EdP'!$E$3:$E$702,$B31,'90_Origen_Ledger_EdP'!$G$3:$G$702,2024) -> 0 | E31: =SUMIFS('90_Origen_Ledger_EdP'!$K$3:$K$702,'90_Origen_Ledger_EdP'!$F$3:$F$702,$A31,'90_Origen_Ledger_EdP'!$E$3:$E$702,$B31,'90_Origen_Ledger_EdP'!$G$3:$G$702,2025) -> 406493.6 | F31: =SUMIFS('90_Origen_Ledger_EdP'!$K$3:$K$702,'90_Origen_Ledger_EdP'!$F$3:$F$702,$A31,'90_Origen_Ledger_EdP'!$E$3:$E$702,$B31,'90_Origen_Ledger_EdP'!$G$3:$G$702,2026) -> 151478.5 | G31: =SUM(C31:F31) -> 557972.1 | H31: =IF($G$40=0,"-",G31/$G$40) -> 0.13819369
A32: Brasil | B32: AuraMinerals | C32: =SUMIFS('90_Origen_Ledger_EdP'!$K$3:$K$702,'90_Origen_Ledger_EdP'!$F$3:$F$702,$A32,'90_Origen_Ledger_EdP'!$E$3:$E$702,$B32,'90_Origen_Ledger_EdP'!$G$3:$G$702,2023) -> 0 | D32: =SUMIFS('90_Origen_Ledger_EdP'!$K$3:$K$702,'90_Origen_Ledger_EdP'!$F$3:$F$702,$A32,'90_Origen_Ledger_EdP'!$E$3:$E$702,$B32,'90_Origen_Ledger_EdP'!$G$3:$G$702,2024) -> 0 | E32: =SUMIFS('90_Origen_Ledger_EdP'!$K$3:$K$702,'90_Origen_Ledger_EdP'!$F$3:$F$702,$A32,'90_Origen_Ledger_EdP'!$E$3:$E$702,$B32,'90_Origen_Ledger_EdP'!$G$3:$G$702,2025) -> 342523.62 | F32: =SUMIFS('90_Origen_Ledger_EdP'!$K$3:$K$702,'90_Origen_Ledger_EdP'!$F$3:$F$702,$A32,'90_Origen_Ledger_EdP'!$E$3:$E$702,$B32,'90_Origen_Ledger_EdP'!$G$3:$G$702,2026) -> 159558.2 | G32: =SUM(C32:F32) -> 502081.82 | H32: =IF($G$40=0,"-",G32/$G$40) -> 0.12435127
A33: Brasil | B33: EQUINOX | C33: =SUMIFS('90_Origen_Ledger_EdP'!$K$3:$K$702,'90_Origen_Ledger_EdP'!$F$3:$F$702,$A33,'90_Origen_Ledger_EdP'!$E$3:$E$702,$B33,'90_Origen_Ledger_EdP'!$G$3:$G$702,2023) -> 0 | D33: =SUMIFS('90_Origen_Ledger_EdP'!$K$3:$K$702,'90_Origen_Ledger_EdP'!$F$3:$F$702,$A33,'90_Origen_Ledger_EdP'!$E$3:$E$702,$B33,'90_Origen_Ledger_EdP'!$G$3:$G$702,2024) -> 0 | E33: =SUMIFS('90_Origen_Ledger_EdP'!$K$3:$K$702,'90_Origen_Ledger_EdP'!$F$3:$F$702,$A33,'90_Origen_Ledger_EdP'!$E$3:$E$702,$B33,'90_Origen_Ledger_EdP'!$G$3:$G$702,2025) -> 306848 | F33: =SUMIFS('90_Origen_Ledger_EdP'!$K$3:$K$702,'90_Origen_Ledger_EdP'!$F$3:$F$702,$A33,'90_Origen_Ledger_EdP'!$E$3:$E$702,$B33,'90_Origen_Ledger_EdP'!$G$3:$G$702,2026) -> 47145 | G33: =SUM(C33:F33) -> 353993 | H33: =IF($G$40=0,"-",G33/$G$40) -> 0.087673919
A34: Brasil | B34: J&F | C34: =SUMIFS('90_Origen_Ledger_EdP'!$K$3:$K$702,'90_Origen_Ledger_EdP'!$F$3:$F$702,$A34,'90_Origen_Ledger_EdP'!$E$3:$E$702,$B34,'90_Origen_Ledger_EdP'!$G$3:$G$702,2023) -> 0 | D34: =SUMIFS('90_Origen_Ledger_EdP'!$K$3:$K$702,'90_Origen_Ledger_EdP'!$F$3:$F$702,$A34,'90_Origen_Ledger_EdP'!$E$3:$E$702,$B34,'90_Origen_Ledger_EdP'!$G$3:$G$702,2024) -> 319132 | E34: =SUMIFS('90_Origen_Ledger_EdP'!$K$3:$K$702,'90_Origen_Ledger_EdP'!$F$3:$F$702,$A34,'90_Origen_Ledger_EdP'!$E$3:$E$702,$B34,'90_Origen_Ledger_EdP'!$G$3:$G$702,2025) -> 8092 | F34: =SUMIFS('90_Origen_Ledger_EdP'!$K$3:$K$702,'90_Origen_Ledger_EdP'!$F$3:$F$702,$A34,'90_Origen_Ledger_EdP'!$E$3:$E$702,$B34,'90_Origen_Ledger_EdP'!$G$3:$G$702,2026) -> 0 | G34: =SUM(C34:F34) -> 327224 | H34: =IF($G$40=0,"-",G34/$G$40) -> 0.081044005
A35: Brasil | B35: NEXA | C35: =SUMIFS('90_Origen_Ledger_EdP'!$K$3:$K$702,'90_Origen_Ledger_EdP'!$F$3:$F$702,$A35,'90_Origen_Ledger_EdP'!$E$3:$E$702,$B35,'90_Origen_Ledger_EdP'!$G$3:$G$702,2023) -> 128549.59 | D35: =SUMIFS('90_Origen_Ledger_EdP'!$K$3:$K$702,'90_Origen_Ledger_EdP'!$F$3:$F$702,$A35,'90_Origen_Ledger_EdP'!$E$3:$E$702,$B35,'90_Origen_Ledger_EdP'!$G$3:$G$702,2024) -> 75794 | E35: =SUMIFS('90_Origen_Ledger_EdP'!$K$3:$K$702,'90_Origen_Ledger_EdP'!$F$3:$F$702,$A35,'90_Origen_Ledger_EdP'!$E$3:$E$702,$B35,'90_Origen_Ledger_EdP'!$G$3:$G$702,2025) -> 0 | F35: =SUMIFS('90_Origen_Ledger_EdP'!$K$3:$K$702,'90_Origen_Ledger_EdP'!$F$3:$F$702,$A35,'90_Origen_Ledger_EdP'!$E$3:$E$702,$B35,'90_Origen_Ledger_EdP'!$G$3:$G$702,2026) -> 0 | G35: =SUM(C35:F35) -> 204343.59 | H35: =IF($G$40=0,"-",G35/$G$40) -> 0.05061005
A36: Brasil | B36: Taboca | C36: =SUMIFS('90_Origen_Ledger_EdP'!$K$3:$K$702,'90_Origen_Ledger_EdP'!$F$3:$F$702,$A36,'90_Origen_Ledger_EdP'!$E$3:$E$702,$B36,'90_Origen_Ledger_EdP'!$G$3:$G$702,2023) -> 0 | D36: =SUMIFS('90_Origen_Ledger_EdP'!$K$3:$K$702,'90_Origen_Ledger_EdP'!$F$3:$F$702,$A36,'90_Origen_Ledger_EdP'!$E$3:$E$702,$B36,'90_Origen_Ledger_EdP'!$G$3:$G$702,2024) -> 0 | E36: =SUMIFS('90_Origen_Ledger_EdP'!$K$3:$K$702,'90_Origen_Ledger_EdP'!$F$3:$F$702,$A36,'90_Origen_Ledger_EdP'!$E$3:$E$702,$B36,'90_Origen_Ledger_EdP'!$G$3:$G$702,2025) -> 180000 | F36: =SUMIFS('90_Origen_Ledger_EdP'!$K$3:$K$702,'90_Origen_Ledger_EdP'!$F$3:$F$702,$A36,'90_Origen_Ledger_EdP'!$E$3:$E$702,$B36,'90_Origen_Ledger_EdP'!$G$3:$G$702,2026) -> 0 | G36: =SUM(C36:F36) -> 180000 | H36: =IF($G$40=0,"-",G36/$G$40) -> 0.04458084
A37: Brasil | B37: LHG | C37: =SUMIFS('90_Origen_Ledger_EdP'!$K$3:$K$702,'90_Origen_Ledger_EdP'!$F$3:$F$702,$A37,'90_Origen_Ledger_EdP'!$E$3:$E$702,$B37,'90_Origen_Ledger_EdP'!$G$3:$G$702,2023) -> 0 | D37: =SUMIFS('90_Origen_Ledger_EdP'!$K$3:$K$702,'90_Origen_Ledger_EdP'!$F$3:$F$702,$A37,'90_Origen_Ledger_EdP'!$E$3:$E$702,$B37,'90_Origen_Ledger_EdP'!$G$3:$G$702,2024) -> 0 | E37: =SUMIFS('90_Origen_Ledger_EdP'!$K$3:$K$702,'90_Origen_Ledger_EdP'!$F$3:$F$702,$A37,'90_Origen_Ledger_EdP'!$E$3:$E$702,$B37,'90_Origen_Ledger_EdP'!$G$3:$G$702,2025) -> 113137 | F37: =SUMIFS('90_Origen_Ledger_EdP'!$K$3:$K$702,'90_Origen_Ledger_EdP'!$F$3:$F$702,$A37,'90_Origen_Ledger_EdP'!$E$3:$E$702,$B37,'90_Origen_Ledger_EdP'!$G$3:$G$702,2026) -> 0 | G37: =SUM(C37:F37) -> 113137 | H37: =IF($G$40=0,"-",G37/$G$40) -> 0.028020792
A38: Brasil | B38: CBMM | C38: =SUMIFS('90_Origen_Ledger_EdP'!$K$3:$K$702,'90_Origen_Ledger_EdP'!$F$3:$F$702,$A38,'90_Origen_Ledger_EdP'!$E$3:$E$702,$B38,'90_Origen_Ledger_EdP'!$G$3:$G$702,2023) -> 0 | D38: =SUMIFS('90_Origen_Ledger_EdP'!$K$3:$K$702,'90_Origen_Ledger_EdP'!$F$3:$F$702,$A38,'90_Origen_Ledger_EdP'!$E$3:$E$702,$B38,'90_Origen_Ledger_EdP'!$G$3:$G$702,2024) -> 0 | E38: =SUMIFS('90_Origen_Ledger_EdP'!$K$3:$K$702,'90_Origen_Ledger_EdP'!$F$3:$F$702,$A38,'90_Origen_Ledger_EdP'!$E$3:$E$702,$B38,'90_Origen_Ledger_EdP'!$G$3:$G$702,2025) -> 72515 | F38: =SUMIFS('90_Origen_Ledger_EdP'!$K$3:$K$702,'90_Origen_Ledger_EdP'!$F$3:$F$702,$A38,'90_Origen_Ledger_EdP'!$E$3:$E$702,$B38,'90_Origen_Ledger_EdP'!$G$3:$G$702,2026) -> 7778 | G38: =SUM(C38:F38) -> 80293 | H38: =IF($G$40=0,"-",G38/$G$40) -> 0.019886274
A39: Brasil | B39: Otros clientes (resto) | C39: =SUMIFS('90_Origen_Ledger_EdP'!$K$3:$K$702,'90_Origen_Ledger_EdP'!$F$3:$F$702,$A39,'90_Origen_Ledger_EdP'!$G$3:$G$702,2023)-SUM(C30:C38) -> 0 | D39: =SUMIFS('90_Origen_Ledger_EdP'!$K$3:$K$702,'90_Origen_Ledger_EdP'!$F$3:$F$702,$A39,'90_Origen_Ledger_EdP'!$G$3:$G$702,2024)-SUM(D30:D38) -> 0 | E39: =SUMIFS('90_Origen_Ledger_EdP'!$K$3:$K$702,'90_Origen_Ledger_EdP'!$F$3:$F$702,$A39,'90_Origen_Ledger_EdP'!$G$3:$G$702,2025)-SUM(E30:E38) -> 0 | F39: =SUMIFS('90_Origen_Ledger_EdP'!$K$3:$K$702,'90_Origen_Ledger_EdP'!$F$3:$F$702,$A39,'90_Origen_Ledger_EdP'!$G$3:$G$702,2026)-SUM(F30:F38) -> 0 | G39: =SUM(C39:F39) -> 0 | H39: =IF($G$40=0,"-",G39/$G$40) -> 0
A40: Brasil | B40: TOTAL Brasil | C40: =SUM(C30:C39) -> 728918.05 | D40: =SUM(D30:D39) -> 1007708 | E40: =SUM(E30:E39) -> 1833813.2 | F40: =SUM(F30:F39) -> 467169.7 | G40: =SUM(C40:F40) -> 4037609 | H40: 1
A41: USA | B41: Ivanhoe | C41: =SUMIFS('90_Origen_Ledger_EdP'!$K$3:$K$702,'90_Origen_Ledger_EdP'!$F$3:$F$702,$A41,'90_Origen_Ledger_EdP'!$E$3:$E$702,$B41,'90_Origen_Ledger_EdP'!$G$3:$G$702,2023) -> 102384 | D41: =SUMIFS('90_Origen_Ledger_EdP'!$K$3:$K$702,'90_Origen_Ledger_EdP'!$F$3:$F$702,$A41,'90_Origen_Ledger_EdP'!$E$3:$E$702,$B41,'90_Origen_Ledger_EdP'!$G$3:$G$702,2024) -> 601598 | E41: =SUMIFS('90_Origen_Ledger_EdP'!$K$3:$K$702,'90_Origen_Ledger_EdP'!$F$3:$F$702,$A41,'90_Origen_Ledger_EdP'!$E$3:$E$702,$B41,'90_Origen_Ledger_EdP'!$G$3:$G$702,2025) -> 0 | F41: =SUMIFS('90_Origen_Ledger_EdP'!$K$3:$K$702,'90_Origen_Ledger_EdP'!$F$3:$F$702,$A41,'90_Origen_Ledger_EdP'!$E$3:$E$702,$B41,'90_Origen_Ledger_EdP'!$G$3:$G$702,2026) -> 0 | G41: =SUM(C41:F41) -> 703982 | H41: =IF($G$52=0,"-",G41/$G$52) -> 0.18368753
A42: USA | B42: ThreeCrowns | C42: =SUMIFS('90_Origen_Ledger_EdP'!$K$3:$K$702,'90_Origen_Ledger_EdP'!$F$3:$F$702,$A42,'90_Origen_Ledger_EdP'!$E$3:$E$702,$B42,'90_Origen_Ledger_EdP'!$G$3:$G$702,2023) -> 0 | D42: =SUMIFS('90_Origen_Ledger_EdP'!$K$3:$K$702,'90_Origen_Ledger_EdP'!$F$3:$F$702,$A42,'90_Origen_Ledger_EdP'!$E$3:$E$702,$B42,'90_Origen_Ledger_EdP'!$G$3:$G$702,2024) -> 28545 | E42: =SUMIFS('90_Origen_Ledger_EdP'!$K$3:$K$702,'90_Origen_Ledger_EdP'!$F$3:$F$702,$A42,'90_Origen_Ledger_EdP'!$E$3:$E$702,$B42,'90_Origen_Ledger_EdP'!$G$3:$G$702,2025) -> 645700 | F42: =SUMIFS('90_Origen_Ledger_EdP'!$K$3:$K$702,'90_Origen_Ledger_EdP'!$F$3:$F$702,$A42,'90_Origen_Ledger_EdP'!$E$3:$E$702,$B42,'90_Origen_Ledger_EdP'!$G$3:$G$702,2026) -> 0 | G42: =SUM(C42:F42) -> 674245 | H42: =IF($G$52=0,"-",G42/$G$52) -> 0.17592836
A43: USA | B43: McCarthy | C43: =SUMIFS('90_Origen_Ledger_EdP'!$K$3:$K$702,'90_Origen_Ledger_EdP'!$F$3:$F$702,$A43,'90_Origen_Ledger_EdP'!$E$3:$E$702,$B43,'90_Origen_Ledger_EdP'!$G$3:$G$702,2023) -> 0 | D43: =SUMIFS('90_Origen_Ledger_EdP'!$K$3:$K$702,'90_Origen_Ledger_EdP'!$F$3:$F$702,$A43,'90_Origen_Ledger_EdP'!$E$3:$E$702,$B43,'90_Origen_Ledger_EdP'!$G$3:$G$702,2024) -> 572400 | E43: =SUMIFS('90_Origen_Ledger_EdP'!$K$3:$K$702,'90_Origen_Ledger_EdP'!$F$3:$F$702,$A43,'90_Origen_Ledger_EdP'!$E$3:$E$702,$B43,'90_Origen_Ledger_EdP'!$G$3:$G$702,2025) -> 0 | F43: =SUMIFS('90_Origen_Ledger_EdP'!$K$3:$K$702,'90_Origen_Ledger_EdP'!$F$3:$F$702,$A43,'90_Origen_Ledger_EdP'!$E$3:$E$702,$B43,'90_Origen_Ledger_EdP'!$G$3:$G$702,2026) -> 0 | G43: =SUM(C43:F43) -> 572400 | H43: =IF($G$52=0,"-",G43/$G$52) -> 0.1493543
A44: USA | B44: TwinMetals | C44: =SUMIFS('90_Origen_Ledger_EdP'!$K$3:$K$702,'90_Origen_Ledger_EdP'!$F$3:$F$702,$A44,'90_Origen_Ledger_EdP'!$E$3:$E$702,$B44,'90_Origen_Ledger_EdP'!$G$3:$G$702,2023) -> 0 | D44: =SUMIFS('90_Origen_Ledger_EdP'!$K$3:$K$702,'90_Origen_Ledger_EdP'!$F$3:$F$702,$A44,'90_Origen_Ledger_EdP'!$E$3:$E$702,$B44,'90_Origen_Ledger_EdP'!$G$3:$G$702,2024) -> 112741 | E44: =SUMIFS('90_Origen_Ledger_EdP'!$K$3:$K$702,'90_Origen_Ledger_EdP'!$F$3:$F$702,$A44,'90_Origen_Ledger_EdP'!$E$3:$E$702,$B44,'90_Origen_Ledger_EdP'!$G$3:$G$702,2025) -> 453025.1 | F44: =SUMIFS('90_Origen_Ledger_EdP'!$K$3:$K$702,'90_Origen_Ledger_EdP'!$F$3:$F$702,$A44,'90_Origen_Ledger_EdP'!$E$3:$E$702,$B44,'90_Origen_Ledger_EdP'!$G$3:$G$702,2026) -> 0 | G44: =SUM(C44:F44) -> 565766.1 | H44: =IF($G$52=0,"-",G44/$G$52) -> 0.14762334
A45: USA | B45: VP Mining | C45: =SUMIFS('90_Origen_Ledger_EdP'!$K$3:$K$702,'90_Origen_Ledger_EdP'!$F$3:$F$702,$A45,'90_Origen_Ledger_EdP'!$E$3:$E$702,$B45,'90_Origen_Ledger_EdP'!$G$3:$G$702,2023) -> 0 | D45: =SUMIFS('90_Origen_Ledger_EdP'!$K$3:$K$702,'90_Origen_Ledger_EdP'!$F$3:$F$702,$A45,'90_Origen_Ledger_EdP'!$E$3:$E$702,$B45,'90_Origen_Ledger_EdP'!$G$3:$G$702,2024) -> 0 | E45: =SUMIFS('90_Origen_Ledger_EdP'!$K$3:$K$702,'90_Origen_Ledger_EdP'!$F$3:$F$702,$A45,'90_Origen_Ledger_EdP'!$E$3:$E$702,$B45,'90_Origen_Ledger_EdP'!$G$3:$G$702,2025) -> 301820 | F45: =SUMIFS('90_Origen_Ledger_EdP'!$K$3:$K$702,'90_Origen_Ledger_EdP'!$F$3:$F$702,$A45,'90_Origen_Ledger_EdP'!$E$3:$E$702,$B45,'90_Origen_Ledger_EdP'!$G$3:$G$702,2026) -> 0 | G45: =SUM(C45:F45) -> 301820 | H45: =IF($G$52=0,"-",G45/$G$52) -> 0.078752822
A46: USA | B46: Resolution | C46: =SUMIFS('90_Origen_Ledger_EdP'!$K$3:$K$702,'90_Origen_Ledger_EdP'!$F$3:$F$702,$A46,'90_Origen_Ledger_EdP'!$E$3:$E$702,$B46,'90_Origen_Ledger_EdP'!$G$3:$G$702,2023) -> 0 | D46: =SUMIFS('90_Origen_Ledger_EdP'!$K$3:$K$702,'90_Origen_Ledger_EdP'!$F$3:$F$702,$A46,'90_Origen_Ledger_EdP'!$E$3:$E$702,$B46,'90_Origen_Ledger_EdP'!$G$3:$G$702,2024) -> 0 | E46: =SUMIFS('90_Origen_Ledger_EdP'!$K$3:$K$702,'90_Origen_Ledger_EdP'!$F$3:$F$702,$A46,'90_Origen_Ledger_EdP'!$E$3:$E$702,$B46,'90_Origen_Ledger_EdP'!$G$3:$G$702,2025) -> 154621 | F46: =SUMIFS('90_Origen_Ledger_EdP'!$K$3:$K$702,'90_Origen_Ledger_EdP'!$F$3:$F$702,$A46,'90_Origen_Ledger_EdP'!$E$3:$E$702,$B46,'90_Origen_Ledger_EdP'!$G$3:$G$702,2026) -> 94955 | G46: =SUM(C46:F46) -> 249576 | H46: =IF($G$52=0,"-",G46/$G$52) -> 0.06512098
A47: USA | B47: Freeport | C47: =SUMIFS('90_Origen_Ledger_EdP'!$K$3:$K$702,'90_Origen_Ledger_EdP'!$F$3:$F$702,$A47,'90_Origen_Ledger_EdP'!$E$3:$E$702,$B47,'90_Origen_Ledger_EdP'!$G$3:$G$702,2023) -> 0 | D47: =SUMIFS('90_Origen_Ledger_EdP'!$K$3:$K$702,'90_Origen_Ledger_EdP'!$F$3:$F$702,$A47,'90_Origen_Ledger_EdP'!$E$3:$E$702,$B47,'90_Origen_Ledger_EdP'!$G$3:$G$702,2024) -> 0 | E47: =SUMIFS('90_Origen_Ledger_EdP'!$K$3:$K$702,'90_Origen_Ledger_EdP'!$F$3:$F$702,$A47,'90_Origen_Ledger_EdP'!$E$3:$E$702,$B47,'90_Origen_Ledger_EdP'!$G$3:$G$702,2025) -> 0 | F47: =SUMIFS('90_Origen_Ledger_EdP'!$K$3:$K$702,'90_Origen_Ledger_EdP'!$F$3:$F$702,$A47,'90_Origen_Ledger_EdP'!$E$3:$E$702,$B47,'90_Origen_Ledger_EdP'!$G$3:$G$702,2026) -> 239843.5 | G47: =SUM(C47:F47) -> 239843.5 | H47: =IF($G$52=0,"-",G47/$G$52) -> 0.062581513
A48: USA | B48: EMX | C48: =SUMIFS('90_Origen_Ledger_EdP'!$K$3:$K$702,'90_Origen_Ledger_EdP'!$F$3:$F$702,$A48,'90_Origen_Ledger_EdP'!$E$3:$E$702,$B48,'90_Origen_Ledger_EdP'!$G$3:$G$702,2023) -> 0 | D48: =SUMIFS('90_Origen_Ledger_EdP'!$K$3:$K$702,'90_Origen_Ledger_EdP'!$F$3:$F$702,$A48,'90_Origen_Ledger_EdP'!$E$3:$E$702,$B48,'90_Origen_Ledger_EdP'!$G$3:$G$702,2024) -> 174694 | E48: =SUMIFS('90_Origen_Ledger_EdP'!$K$3:$K$702,'90_Origen_Ledger_EdP'!$F$3:$F$702,$A48,'90_Origen_Ledger_EdP'!$E$3:$E$702,$B48,'90_Origen_Ledger_EdP'!$G$3:$G$702,2025) -> 0 | F48: =SUMIFS('90_Origen_Ledger_EdP'!$K$3:$K$702,'90_Origen_Ledger_EdP'!$F$3:$F$702,$A48,'90_Origen_Ledger_EdP'!$E$3:$E$702,$B48,'90_Origen_Ledger_EdP'!$G$3:$G$702,2026) -> 0 | G48: =SUM(C48:F48) -> 174694 | H48: =IF($G$52=0,"-",G48/$G$52) -> 0.045582286
A49: USA | B49: South32 | C49: =SUMIFS('90_Origen_Ledger_EdP'!$K$3:$K$702,'90_Origen_Ledger_EdP'!$F$3:$F$702,$A49,'90_Origen_Ledger_EdP'!$E$3:$E$702,$B49,'90_Origen_Ledger_EdP'!$G$3:$G$702,2023) -> 0 | D49: =SUMIFS('90_Origen_Ledger_EdP'!$K$3:$K$702,'90_Origen_Ledger_EdP'!$F$3:$F$702,$A49,'90_Origen_Ledger_EdP'!$E$3:$E$702,$B49,'90_Origen_Ledger_EdP'!$G$3:$G$702,2024) -> 0 | E49: =SUMIFS('90_Origen_Ledger_EdP'!$K$3:$K$702,'90_Origen_Ledger_EdP'!$F$3:$F$702,$A49,'90_Origen_Ledger_EdP'!$E$3:$E$702,$B49,'90_Origen_Ledger_EdP'!$G$3:$G$702,2025) -> 44465 | F49: =SUMIFS('90_Origen_Ledger_EdP'!$K$3:$K$702,'90_Origen_Ledger_EdP'!$F$3:$F$702,$A49,'90_Origen_Ledger_EdP'!$E$3:$E$702,$B49,'90_Origen_Ledger_EdP'!$G$3:$G$702,2026) -> 109236 | G49: =SUM(C49:F49) -> 153701 | H49: =IF($G$52=0,"-",G49/$G$52) -> 0.040104657
A50: USA | B50: Lundin | C50: =SUMIFS('90_Origen_Ledger_EdP'!$K$3:$K$702,'90_Origen_Ledger_EdP'!$F$3:$F$702,$A50,'90_Origen_Ledger_EdP'!$E$3:$E$702,$B50,'90_Origen_Ledger_EdP'!$G$3:$G$702,2023) -> 0 | D50: =SUMIFS('90_Origen_Ledger_EdP'!$K$3:$K$702,'90_Origen_Ledger_EdP'!$F$3:$F$702,$A50,'90_Origen_Ledger_EdP'!$E$3:$E$702,$B50,'90_Origen_Ledger_EdP'!$G$3:$G$702,2024) -> 66652 | E50: =SUMIFS('90_Origen_Ledger_EdP'!$K$3:$K$702,'90_Origen_Ledger_EdP'!$F$3:$F$702,$A50,'90_Origen_Ledger_EdP'!$E$3:$E$702,$B50,'90_Origen_Ledger_EdP'!$G$3:$G$702,2025) -> 0 | F50: =SUMIFS('90_Origen_Ledger_EdP'!$K$3:$K$702,'90_Origen_Ledger_EdP'!$F$3:$F$702,$A50,'90_Origen_Ledger_EdP'!$E$3:$E$702,$B50,'90_Origen_Ledger_EdP'!$G$3:$G$702,2026) -> 0 | G50: =SUM(C50:F50) -> 66652 | H50: =IF($G$52=0,"-",G50/$G$52) -> 0.01739127
A51: USA | B51: Otros clientes (resto) | C51: =SUMIFS('90_Origen_Ledger_EdP'!$K$3:$K$702,'90_Origen_Ledger_EdP'!$F$3:$F$702,$A51,'90_Origen_Ledger_EdP'!$G$3:$G$702,2023)-SUM(C41:C50) -> 0 | D51: =SUMIFS('90_Origen_Ledger_EdP'!$K$3:$K$702,'90_Origen_Ledger_EdP'!$F$3:$F$702,$A51,'90_Origen_Ledger_EdP'!$G$3:$G$702,2024)-SUM(D41:D50) -> 7150 | E51: =SUMIFS('90_Origen_Ledger_EdP'!$K$3:$K$702,'90_Origen_Ledger_EdP'!$F$3:$F$702,$A51,'90_Origen_Ledger_EdP'!$G$3:$G$702,2025)-SUM(E41:E50) -> 52075 | F51: =SUMIFS('90_Origen_Ledger_EdP'!$K$3:$K$702,'90_Origen_Ledger_EdP'!$F$3:$F$702,$A51,'90_Origen_Ledger_EdP'!$G$3:$G$702,2026)-SUM(F41:F50) -> 70593 | G51: =SUM(C51:F51) -> 129818 | H51: =IF($G$52=0,"-",G51/$G$52) -> 0.03387295
A52: USA | B52: TOTAL USA | C52: =SUM(C41:C51) -> 102384 | D52: =SUM(D41:D51) -> 1563780 | E52: =SUM(E41:E51) -> 1651706.1 | F52: =SUM(F41:F51) -> 514627.5 | G52: =SUM(C52:F52) -> 3832497.6 | H52: 1
A53: Rusia | B53: Seligdar | C53: =SUMIFS('90_Origen_Ledger_EdP'!$K$3:$K$702,'90_Origen_Ledger_EdP'!$F$3:$F$702,$A53,'90_Origen_Ledger_EdP'!$E$3:$E$702,$B53,'90_Origen_Ledger_EdP'!$G$3:$G$702,2023) -> 0 | D53: =SUMIFS('90_Origen_Ledger_EdP'!$K$3:$K$702,'90_Origen_Ledger_EdP'!$F$3:$F$702,$A53,'90_Origen_Ledger_EdP'!$E$3:$E$702,$B53,'90_Origen_Ledger_EdP'!$G$3:$G$702,2024) -> 0 | E53: =SUMIFS('90_Origen_Ledger_EdP'!$K$3:$K$702,'90_Origen_Ledger_EdP'!$F$3:$F$702,$A53,'90_Origen_Ledger_EdP'!$E$3:$E$702,$B53,'90_Origen_Ledger_EdP'!$G$3:$G$702,2025) -> 0 | F53: =SUMIFS('90_Origen_Ledger_EdP'!$K$3:$K$702,'90_Origen_Ledger_EdP'!$F$3:$F$702,$A53,'90_Origen_Ledger_EdP'!$E$3:$E$702,$B53,'90_Origen_Ledger_EdP'!$G$3:$G$702,2026) -> 400000 | G53: =SUM(C53:F53) -> 400000 | H53: =IF($G$59=0,"-",G53/$G$59) -> 0.32781619
A54: Rusia | B54: Polyus | C54: =SUMIFS('90_Origen_Ledger_EdP'!$K$3:$K$702,'90_Origen_Ledger_EdP'!$F$3:$F$702,$A54,'90_Origen_Ledger_EdP'!$E$3:$E$702,$B54,'90_Origen_Ledger_EdP'!$G$3:$G$702,2023) -> 0 | D54: =SUMIFS('90_Origen_Ledger_EdP'!$K$3:$K$702,'90_Origen_Ledger_EdP'!$F$3:$F$702,$A54,'90_Origen_Ledger_EdP'!$E$3:$E$702,$B54,'90_Origen_Ledger_EdP'!$G$3:$G$702,2024) -> 0 | E54: =SUMIFS('90_Origen_Ledger_EdP'!$K$3:$K$702,'90_Origen_Ledger_EdP'!$F$3:$F$702,$A54,'90_Origen_Ledger_EdP'!$E$3:$E$702,$B54,'90_Origen_Ledger_EdP'!$G$3:$G$702,2025) -> 0 | F54: =SUMIFS('90_Origen_Ledger_EdP'!$K$3:$K$702,'90_Origen_Ledger_EdP'!$F$3:$F$702,$A54,'90_Origen_Ledger_EdP'!$E$3:$E$702,$B54,'90_Origen_Ledger_EdP'!$G$3:$G$702,2026) -> 332434 | G54: =SUM(C54:F54) -> 332434 | H54: =IF($G$59=0,"-",G54/$G$59) -> 0.27244312
A55: Rusia | B55: Otro | C55: =SUMIFS('90_Origen_Ledger_EdP'!$K$3:$K$702,'90_Origen_Ledger_EdP'!$F$3:$F$702,$A55,'90_Origen_Ledger_EdP'!$E$3:$E$702,$B55,'90_Origen_Ledger_EdP'!$G$3:$G$702,2023) -> 320662 | D55: =SUMIFS('90_Origen_Ledger_EdP'!$K$3:$K$702,'90_Origen_Ledger_EdP'!$F$3:$F$702,$A55,'90_Origen_Ledger_EdP'!$E$3:$E$702,$B55,'90_Origen_Ledger_EdP'!$G$3:$G$702,2024) -> 0 | E55: =SUMIFS('90_Origen_Ledger_EdP'!$K$3:$K$702,'90_Origen_Ledger_EdP'!$F$3:$F$702,$A55,'90_Origen_Ledger_EdP'!$E$3:$E$702,$B55,'90_Origen_Ledger_EdP'!$G$3:$G$702,2025) -> 0 | F55: =SUMIFS('90_Origen_Ledger_EdP'!$K$3:$K$702,'90_Origen_Ledger_EdP'!$F$3:$F$702,$A55,'90_Origen_Ledger_EdP'!$E$3:$E$702,$B55,'90_Origen_Ledger_EdP'!$G$3:$G$702,2026) -> 0 | G55: =SUM(C55:F55) -> 320662 | H55: =IF($G$59=0,"-",G55/$G$59) -> 0.26279549
A56: Rusia | B56: Eurochem | C56: =SUMIFS('90_Origen_Ledger_EdP'!$K$3:$K$702,'90_Origen_Ledger_EdP'!$F$3:$F$702,$A56,'90_Origen_Ledger_EdP'!$E$3:$E$702,$B56,'90_Origen_Ledger_EdP'!$G$3:$G$702,2023) -> 0 | D56: =SUMIFS('90_Origen_Ledger_EdP'!$K$3:$K$702,'90_Origen_Ledger_EdP'!$F$3:$F$702,$A56,'90_Origen_Ledger_EdP'!$E$3:$E$702,$B56,'90_Origen_Ledger_EdP'!$G$3:$G$702,2024) -> 152100 | E56: =SUMIFS('90_Origen_Ledger_EdP'!$K$3:$K$702,'90_Origen_Ledger_EdP'!$F$3:$F$702,$A56,'90_Origen_Ledger_EdP'!$E$3:$E$702,$B56,'90_Origen_Ledger_EdP'!$G$3:$G$702,2025) -> 0 | F56: =SUMIFS('90_Origen_Ledger_EdP'!$K$3:$K$702,'90_Origen_Ledger_EdP'!$F$3:$F$702,$A56,'90_Origen_Ledger_EdP'!$E$3:$E$702,$B56,'90_Origen_Ledger_EdP'!$G$3:$G$702,2026) -> 0 | G56: =SUM(C56:F56) -> 152100 | H56: =IF($G$59=0,"-",G56/$G$59) -> 0.12465211
A57: Rusia | B57: AtlasMining | C57: =SUMIFS('90_Origen_Ledger_EdP'!$K$3:$K$702,'90_Origen_Ledger_EdP'!$F$3:$F$702,$A57,'90_Origen_Ledger_EdP'!$E$3:$E$702,$B57,'90_Origen_Ledger_EdP'!$G$3:$G$702,2023) -> 0 | D57: =SUMIFS('90_Origen_Ledger_EdP'!$K$3:$K$702,'90_Origen_Ledger_EdP'!$F$3:$F$702,$A57,'90_Origen_Ledger_EdP'!$E$3:$E$702,$B57,'90_Origen_Ledger_EdP'!$G$3:$G$702,2024) -> 0 | E57: =SUMIFS('90_Origen_Ledger_EdP'!$K$3:$K$702,'90_Origen_Ledger_EdP'!$F$3:$F$702,$A57,'90_Origen_Ledger_EdP'!$E$3:$E$702,$B57,'90_Origen_Ledger_EdP'!$G$3:$G$702,2025) -> 0 | F57: =SUMIFS('90_Origen_Ledger_EdP'!$K$3:$K$702,'90_Origen_Ledger_EdP'!$F$3:$F$702,$A57,'90_Origen_Ledger_EdP'!$E$3:$E$702,$B57,'90_Origen_Ledger_EdP'!$G$3:$G$702,2026) -> 15000 | G57: =SUM(C57:F57) -> 15000 | H57: =IF($G$59=0,"-",G57/$G$59) -> 0.012293107
A58: Rusia | B58: Otros clientes (resto) | C58: =SUMIFS('90_Origen_Ledger_EdP'!$K$3:$K$702,'90_Origen_Ledger_EdP'!$F$3:$F$702,$A58,'90_Origen_Ledger_EdP'!$G$3:$G$702,2023)-SUM(C53:C57) -> 0 | D58: =SUMIFS('90_Origen_Ledger_EdP'!$K$3:$K$702,'90_Origen_Ledger_EdP'!$F$3:$F$702,$A58,'90_Origen_Ledger_EdP'!$G$3:$G$702,2024)-SUM(D53:D57) -> 0 | E58: =SUMIFS('90_Origen_Ledger_EdP'!$K$3:$K$702,'90_Origen_Ledger_EdP'!$F$3:$F$702,$A58,'90_Origen_Ledger_EdP'!$G$3:$G$702,2025)-SUM(E53:E57) -> 0 | F58: =SUMIFS('90_Origen_Ledger_EdP'!$K$3:$K$702,'90_Origen_Ledger_EdP'!$F$3:$F$702,$A58,'90_Origen_Ledger_EdP'!$G$3:$G$702,2026)-SUM(F53:F57) -> 0 | G58: =SUM(C58:F58) -> 0 | H58: =IF($G$59=0,"-",G58/$G$59) -> 0
A59: Rusia | B59: TOTAL Rusia | C59: =SUM(C53:C58) -> 320662 | D59: =SUM(D53:D58) -> 152100 | E59: =SUM(E53:E58) -> 0 | F59: =SUM(F53:F58) -> 747434 | G59: =SUM(C59:F59) -> 1220196 | H59: 1
A60: BVI | B60: Debevoise&Plimpton | C60: =SUMIFS('90_Origen_Ledger_EdP'!$K$3:$K$702,'90_Origen_Ledger_EdP'!$F$3:$F$702,$A60,'90_Origen_Ledger_EdP'!$E$3:$E$702,$B60,'90_Origen_Ledger_EdP'!$G$3:$G$702,2023) -> 0 | D60: =SUMIFS('90_Origen_Ledger_EdP'!$K$3:$K$702,'90_Origen_Ledger_EdP'!$F$3:$F$702,$A60,'90_Origen_Ledger_EdP'!$E$3:$E$702,$B60,'90_Origen_Ledger_EdP'!$G$3:$G$702,2024) -> 0 | E60: =SUMIFS('90_Origen_Ledger_EdP'!$K$3:$K$702,'90_Origen_Ledger_EdP'!$F$3:$F$702,$A60,'90_Origen_Ledger_EdP'!$E$3:$E$702,$B60,'90_Origen_Ledger_EdP'!$G$3:$G$702,2025) -> 272031 | F60: =SUMIFS('90_Origen_Ledger_EdP'!$K$3:$K$702,'90_Origen_Ledger_EdP'!$F$3:$F$702,$A60,'90_Origen_Ledger_EdP'!$E$3:$E$702,$B60,'90_Origen_Ledger_EdP'!$G$3:$G$702,2026) -> 0 | G60: =SUM(C60:F60) -> 272031 | H60: =IF($G$63=0,"-",G60/$G$63) -> 0.80199946
A61: BVI | B61: Capstone Copper | C61: =SUMIFS('90_Origen_Ledger_EdP'!$K$3:$K$702,'90_Origen_Ledger_EdP'!$F$3:$F$702,$A61,'90_Origen_Ledger_EdP'!$E$3:$E$702,$B61,'90_Origen_Ledger_EdP'!$G$3:$G$702,2023) -> 0 | D61: =SUMIFS('90_Origen_Ledger_EdP'!$K$3:$K$702,'90_Origen_Ledger_EdP'!$F$3:$F$702,$A61,'90_Origen_Ledger_EdP'!$E$3:$E$702,$B61,'90_Origen_Ledger_EdP'!$G$3:$G$702,2024) -> 67160 | E61: =SUMIFS('90_Origen_Ledger_EdP'!$K$3:$K$702,'90_Origen_Ledger_EdP'!$F$3:$F$702,$A61,'90_Origen_Ledger_EdP'!$E$3:$E$702,$B61,'90_Origen_Ledger_EdP'!$G$3:$G$702,2025) -> 0 | F61: =SUMIFS('90_Origen_Ledger_EdP'!$K$3:$K$702,'90_Origen_Ledger_EdP'!$F$3:$F$702,$A61,'90_Origen_Ledger_EdP'!$E$3:$E$702,$B61,'90_Origen_Ledger_EdP'!$G$3:$G$702,2026) -> 0 | G61: =SUM(C61:F61) -> 67160 | H61: =IF($G$63=0,"-",G61/$G$63) -> 0.19800054
A62: BVI | B62: Otros clientes (resto) | C62: =SUMIFS('90_Origen_Ledger_EdP'!$K$3:$K$702,'90_Origen_Ledger_EdP'!$F$3:$F$702,$A62,'90_Origen_Ledger_EdP'!$G$3:$G$702,2023)-SUM(C60:C61) -> 0 | D62: =SUMIFS('90_Origen_Ledger_EdP'!$K$3:$K$702,'90_Origen_Ledger_EdP'!$F$3:$F$702,$A62,'90_Origen_Ledger_EdP'!$G$3:$G$702,2024)-SUM(D60:D61) -> 0 | E62: =SUMIFS('90_Origen_Ledger_EdP'!$K$3:$K$702,'90_Origen_Ledger_EdP'!$F$3:$F$702,$A62,'90_Origen_Ledger_EdP'!$G$3:$G$702,2025)-SUM(E60:E61) -> 0 | F62: =SUMIFS('90_Origen_Ledger_EdP'!$K$3:$K$702,'90_Origen_Ledger_EdP'!$F$3:$F$702,$A62,'90_Origen_Ledger_EdP'!$G$3:$G$702,2026)-SUM(F60:F61) -> 0 | G62: =SUM(C62:F62) -> 0 | H62: =IF($G$63=0,"-",G62/$G$63) -> 0
A63: BVI | B63: TOTAL BVI | C63: =SUM(C60:C62) -> 0 | D63: =SUM(D60:D62) -> 67160 | E63: =SUM(E60:E62) -> 272031 | F63: =SUM(F60:F62) -> 0 | G63: =SUM(C63:F63) -> 339191 | H63: 1
A64: Canadá | B64: Seabridge Gold | C64: =SUMIFS('90_Origen_Ledger_EdP'!$K$3:$K$702,'90_Origen_Ledger_EdP'!$F$3:$F$702,$A64,'90_Origen_Ledger_EdP'!$E$3:$E$702,$B64,'90_Origen_Ledger_EdP'!$G$3:$G$702,2023) -> 0 | D64: =SUMIFS('90_Origen_Ledger_EdP'!$K$3:$K$702,'90_Origen_Ledger_EdP'!$F$3:$F$702,$A64,'90_Origen_Ledger_EdP'!$E$3:$E$702,$B64,'90_Origen_Ledger_EdP'!$G$3:$G$702,2024) -> 0 | E64: =SUMIFS('90_Origen_Ledger_EdP'!$K$3:$K$702,'90_Origen_Ledger_EdP'!$F$3:$F$702,$A64,'90_Origen_Ledger_EdP'!$E$3:$E$702,$B64,'90_Origen_Ledger_EdP'!$G$3:$G$702,2025) -> 0 | F64: =SUMIFS('90_Origen_Ledger_EdP'!$K$3:$K$702,'90_Origen_Ledger_EdP'!$F$3:$F$702,$A64,'90_Origen_Ledger_EdP'!$E$3:$E$702,$B64,'90_Origen_Ledger_EdP'!$G$3:$G$702,2026) -> 47121 | G64: =SUM(C64:F64) -> 47121 | H64: =IF($G$66=0,"-",G64/$G$66) -> 1
A65: Canadá | B65: Otros clientes (resto) | C65: =SUMIFS('90_Origen_Ledger_EdP'!$K$3:$K$702,'90_Origen_Ledger_EdP'!$F$3:$F$702,$A65,'90_Origen_Ledger_EdP'!$G$3:$G$702,2023)-SUM(C64) -> 0 | D65: =SUMIFS('90_Origen_Ledger_EdP'!$K$3:$K$702,'90_Origen_Ledger_EdP'!$F$3:$F$702,$A65,'90_Origen_Ledger_EdP'!$G$3:$G$702,2024)-SUM(D64) -> 0 | E65: =SUMIFS('90_Origen_Ledger_EdP'!$K$3:$K$702,'90_Origen_Ledger_EdP'!$F$3:$F$702,$A65,'90_Origen_Ledger_EdP'!$G$3:$G$702,2025)-SUM(E64) -> 0 | F65: =SUMIFS('90_Origen_Ledger_EdP'!$K$3:$K$702,'90_Origen_Ledger_EdP'!$F$3:$F$702,$A65,'90_Origen_Ledger_EdP'!$G$3:$G$702,2026)-SUM(F64) -> 0 | G65: =SUM(C65:F65) -> 0 | H65: =IF($G$66=0,"-",G65/$G$66) -> 0
A66: Canadá | B66: TOTAL Canadá | C66: =SUM(C64:C65) -> 0 | D66: =SUM(D64:D65) -> 0 | E66: =SUM(E64:E65) -> 0 | F66: =SUM(F64:F65) -> 47121 | G66: =SUM(C66:F66) -> 47121 | H66: 1
A68: B) Concentración de cartera por país (sobre venta Emitido total 23-26)
A69: País | B69: Venta total 23-26 USD | C69: N° clientes (top+resto) | D69: % Top-1 cliente | E69: % Top-3 clientes
A70: Chile | B70: ='02_Ventas_2023_2025'!$G$17 -> 12010931 | C70: =COUNT($G$6:$G$15)+1 -> 11 | D70: =IF($G$17=0,"-",MAX($G$6:$G$15)/$G$17) -> 0.36297503 | E70: =IF($G$17=0,"-",(IFERROR(LARGE($G$6:$G$15,1),0)+IFERROR(LARGE($G$6:$G$15,2),0)+IFERROR(LARGE($G$6:$G$15,3),0))/$G$17) -> 0.60248329
A71: Perú | B71: ='02_Ventas_2023_2025'!$G$29 -> 7032939 | C71: =COUNT($G$18:$G$27)+1 -> 11 | D71: =IF($G$29=0,"-",MAX($G$18:$G$27)/$G$29) -> 0.24832541 | E71: =IF($G$29=0,"-",(IFERROR(LARGE($G$18:$G$27,1),0)+IFERROR(LARGE($G$18:$G$27,2),0)+IFERROR(LARGE($G$18:$G$27,3),0))/$G$29) -> 0.64332896
A72: Brasil | B72: ='02_Ventas_2023_2025'!$G$40 -> 4037609 | C72: =COUNT($G$30:$G$38)+1 -> 10 | D72: =IF($G$40=0,"-",MAX($G$30:$G$38)/$G$40) -> 0.42563915 | E72: =IF($G$40=0,"-",(IFERROR(LARGE($G$30:$G$38,1),0)+IFERROR(LARGE($G$30:$G$38,2),0)+IFERROR(LARGE($G$30:$G$38,3),0))/$G$40) -> 0.68818412
A73: USA | B73: ='02_Ventas_2023_2025'!$G$52 -> 3832497.6 | C73: =COUNT($G$41:$G$50)+1 -> 11 | D73: =IF($G$52=0,"-",MAX($G$41:$G$50)/$G$52) -> 0.18368753 | E73: =IF($G$52=0,"-",(IFERROR(LARGE($G$41:$G$50,1),0)+IFERROR(LARGE($G$41:$G$50,2),0)+IFERROR(LARGE($G$41:$G$50,3),0))/$G$52) -> 0.50897018
A74: Rusia | B74: ='02_Ventas_2023_2025'!$G$59 -> 1220196 | C74: =COUNT($G$53:$G$57)+1 -> 6 | D74: =IF($G$59=0,"-",MAX($G$53:$G$57)/$G$59) -> 0.32781619 | E74: =IF($G$59=0,"-",(IFERROR(LARGE($G$53:$G$57,1),0)+IFERROR(LARGE($G$53:$G$57,2),0)+IFERROR(LARGE($G$53:$G$57,3),0))/$G$59) -> 0.86305479
A75: BVI | B75: ='02_Ventas_2023_2025'!$G$63 -> 339191 | C75: =COUNT($G$60:$G$61)+1 -> 3 | D75: =IF($G$63=0,"-",MAX($G$60:$G$61)/$G$63) -> 0.80199946 | E75: =IF($G$63=0,"-",(IFERROR(LARGE($G$60:$G$61,1),0)+IFERROR(LARGE($G$60:$G$61,2),0)+IFERROR(LARGE($G$60:$G$61,3),0))/$G$63) -> 1
A76: Canadá | B76: ='02_Ventas_2023_2025'!$G$66 -> 47121 | C76: =COUNT($G$64)+1 -> 2 | D76: =IF($G$66=0,"-",MAX($G$64)/$G$66) -> 1 | E76: =IF($G$66=0,"-",(IFERROR(LARGE($G$64,1),0)+IFERROR(LARGE($G$64,2),0)+IFERROR(LARGE($G$64,3),0))/$G$66) -> 1
A78: C) Contraste de definición de 'venta' — consolidado por año (USD)
A79: Año | B79: Proyectado USD (intención) | C79: Emitido USD (VENTA usada) | D79: Facturado USD | E79: Ingresado USD (caja)
A80: 2023 | B80: =SUMIFS('90_Origen_Ledger_EdP'!$H$3:$H$702,'90_Origen_Ledger_EdP'!$G$3:$G$702,2023) -> 3410142.9 | C80: =SUMIFS('90_Origen_Ledger_EdP'!$K$3:$K$702,'90_Origen_Ledger_EdP'!$G$3:$G$702,2023) -> 7071136.6 | D80: =SUMIFS('90_Origen_Ledger_EdP'!$N$3:$N$702,'90_Origen_Ledger_EdP'!$G$3:$G$702,2023) -> 7066623.3 | E80: =SUMIFS('90_Origen_Ledger_EdP'!$Q$3:$Q$702,'90_Origen_Ledger_EdP'!$G$3:$G$702,2023) -> 6928320
A81: 2024 | B81: =SUMIFS('90_Origen_Ledger_EdP'!$H$3:$H$702,'90_Origen_Ledger_EdP'!$G$3:$G$702,2024) -> 3166713.1 | C81: =SUMIFS('90_Origen_Ledger_EdP'!$K$3:$K$702,'90_Origen_Ledger_EdP'!$G$3:$G$702,2024) -> 8418844.5 | D81: =SUMIFS('90_Origen_Ledger_EdP'!$N$3:$N$702,'90_Origen_Ledger_EdP'!$G$3:$G$702,2024) -> 8323592.3 | E81: =SUMIFS('90_Origen_Ledger_EdP'!$Q$3:$Q$702,'90_Origen_Ledger_EdP'!$G$3:$G$702,2024) -> 8323276.2
A82: 2025 | B82: =SUMIFS('90_Origen_Ledger_EdP'!$H$3:$H$702,'90_Origen_Ledger_EdP'!$G$3:$G$702,2025) -> 0 | C82: =SUMIFS('90_Origen_Ledger_EdP'!$K$3:$K$702,'90_Origen_Ledger_EdP'!$G$3:$G$702,2025) -> 9476037.1 | D82: =SUMIFS('90_Origen_Ledger_EdP'!$N$3:$N$702,'90_Origen_Ledger_EdP'!$G$3:$G$702,2025) -> 9596451.6 | E82: =SUMIFS('90_Origen_Ledger_EdP'!$Q$3:$Q$702,'90_Origen_Ledger_EdP'!$G$3:$G$702,2025) -> 9437343.9
A83: 2026 | B83: =SUMIFS('90_Origen_Ledger_EdP'!$H$3:$H$702,'90_Origen_Ledger_EdP'!$G$3:$G$702,2026) -> 2545429.4 | C83: =SUMIFS('90_Origen_Ledger_EdP'!$K$3:$K$702,'90_Origen_Ledger_EdP'!$G$3:$G$702,2026) -> 3554466.5 | D83: =SUMIFS('90_Origen_Ledger_EdP'!$N$3:$N$702,'90_Origen_Ledger_EdP'!$G$3:$G$702,2026) -> 2744008.6 | E83: =SUMIFS('90_Origen_Ledger_EdP'!$Q$3:$Q$702,'90_Origen_Ledger_EdP'!$G$3:$G$702,2026) -> 1191382.6
A85: D) TURNOVER del ciclo EdP por País — días promedio entre los 3 momentos (Emisión→Facturación→Ingreso). Rotación anual = 365 / días del ciclo total. Fuente: CicloEdP_2023_v1.
A86: País | B86: N° EDP (ciclo) | C86: Días Emisión→Factura | D86: Días Factura→Ingreso | E86: Días Emisión→Ingreso (ciclo) | F86: Rotación anual (veces)
A87: Chile | B87: =COUNTIFS('90_Origen_Ledger_EdP'!$F$3:$F$702,$A87,'90_Origen_Ledger_EdP'!$X$3:$X$702,">=0") -> 300 | C87: =IFERROR(AVERAGEIFS('90_Origen_Ledger_EdP'!$V$3:$V$702,'90_Origen_Ledger_EdP'!$F$3:$F$702,$A87),"-") -> 34.851351 | D87: =IFERROR(AVERAGEIFS('90_Origen_Ledger_EdP'!$W$3:$W$702,'90_Origen_Ledger_EdP'!$F$3:$F$702,$A87),"-") -> 21.096346 | E87: =IFERROR(AVERAGEIFS('90_Origen_Ledger_EdP'!$X$3:$X$702,'90_Origen_Ledger_EdP'!$F$3:$F$702,$A87),"-") -> 54.11 | F87: =IFERROR(365/E87,"-") -> 6.7455184
A88: Perú | B88: =COUNTIFS('90_Origen_Ledger_EdP'!$F$3:$F$702,$A88,'90_Origen_Ledger_EdP'!$X$3:$X$702,">=0") -> 172 | C88: =IFERROR(AVERAGEIFS('90_Origen_Ledger_EdP'!$V$3:$V$702,'90_Origen_Ledger_EdP'!$F$3:$F$702,$A88),"-") -> 32.279762 | D88: =IFERROR(AVERAGEIFS('90_Origen_Ledger_EdP'!$W$3:$W$702,'90_Origen_Ledger_EdP'!$F$3:$F$702,$A88),"-") -> 29.394286 | E88: =IFERROR(AVERAGEIFS('90_Origen_Ledger_EdP'!$X$3:$X$702,'90_Origen_Ledger_EdP'!$F$3:$F$702,$A88),"-") -> 60.47093 | F88: =IFERROR(365/E88,"-") -> 6.0359581
A89: Brasil | B89: =COUNTIFS('90_Origen_Ledger_EdP'!$F$3:$F$702,$A89,'90_Origen_Ledger_EdP'!$X$3:$X$702,">=0") -> 115 | C89: =IFERROR(AVERAGEIFS('90_Origen_Ledger_EdP'!$V$3:$V$702,'90_Origen_Ledger_EdP'!$F$3:$F$702,$A89),"-") -> 17.37037 | D89: =IFERROR(AVERAGEIFS('90_Origen_Ledger_EdP'!$W$3:$W$702,'90_Origen_Ledger_EdP'!$F$3:$F$702,$A89),"-") -> 60.113043 | E89: =IFERROR(AVERAGEIFS('90_Origen_Ledger_EdP'!$X$3:$X$702,'90_Origen_Ledger_EdP'!$F$3:$F$702,$A89),"-") -> 76.191304 | F89: =IFERROR(365/E89,"-") -> 4.7905729
A90: USA | B90: =COUNTIFS('90_Origen_Ledger_EdP'!$F$3:$F$702,$A90,'90_Origen_Ledger_EdP'!$X$3:$X$702,">=0") -> 54 | C90: =IFERROR(AVERAGEIFS('90_Origen_Ledger_EdP'!$V$3:$V$702,'90_Origen_Ledger_EdP'!$F$3:$F$702,$A90),"-") -> 10.169811 | D90: =IFERROR(AVERAGEIFS('90_Origen_Ledger_EdP'!$W$3:$W$702,'90_Origen_Ledger_EdP'!$F$3:$F$702,$A90),"-") -> 43.946429 | E90: =IFERROR(AVERAGEIFS('90_Origen_Ledger_EdP'!$X$3:$X$702,'90_Origen_Ledger_EdP'!$F$3:$F$702,$A90),"-") -> 52.222222 | F90: =IFERROR(365/E90,"-") -> 6.9893617
A91: Rusia | B91: =COUNTIFS('90_Origen_Ledger_EdP'!$F$3:$F$702,$A91,'90_Origen_Ledger_EdP'!$X$3:$X$702,">=0") -> 16 | C91: =IFERROR(AVERAGEIFS('90_Origen_Ledger_EdP'!$V$3:$V$702,'90_Origen_Ledger_EdP'!$F$3:$F$702,$A91),"-") -> 29.75 | D91: =IFERROR(AVERAGEIFS('90_Origen_Ledger_EdP'!$W$3:$W$702,'90_Origen_Ledger_EdP'!$F$3:$F$702,$A91),"-") -> 50.1875 | E91: =IFERROR(AVERAGEIFS('90_Origen_Ledger_EdP'!$X$3:$X$702,'90_Origen_Ledger_EdP'!$F$3:$F$702,$A91),"-") -> 79.9375 | F91: =IFERROR(365/E91,"-") -> 4.5660672
A92: BVI | B92: =COUNTIFS('90_Origen_Ledger_EdP'!$F$3:$F$702,$A92,'90_Origen_Ledger_EdP'!$X$3:$X$702,">=0") -> 5 | C92: =IFERROR(AVERAGEIFS('90_Origen_Ledger_EdP'!$V$3:$V$702,'90_Origen_Ledger_EdP'!$F$3:$F$702,$A92),"-") -> 42.2 | D92: =IFERROR(AVERAGEIFS('90_Origen_Ledger_EdP'!$W$3:$W$702,'90_Origen_Ledger_EdP'!$F$3:$F$702,$A92),"-") -> 28.2 | E92: =IFERROR(AVERAGEIFS('90_Origen_Ledger_EdP'!$X$3:$X$702,'90_Origen_Ledger_EdP'!$F$3:$F$702,$A92),"-") -> 70.4 | F92: =IFERROR(365/E92,"-") -> 5.1846591
A93: TOTAL / promedio | B93: =COUNT('90_Origen_Ledger_EdP'!$X$3:$X$702) -> 662 | C93: =IFERROR(AVERAGE('90_Origen_Ledger_EdP'!$V$3:$V$702),"-") -> 29.165635 | D93: =IFERROR(AVERAGE('90_Origen_Ledger_EdP'!$W$3:$W$702),"-") -> 32.652695 | E93: =IFERROR(AVERAGE('90_Origen_Ledger_EdP'!$X$3:$X$702),"-") -> 60.191843 | F93: =IFERROR(365/E93,"-") -> 6.0639446
A95: E) TURNOVER del ciclo EdP por Cliente (top 15 por venta Emitido). Días promedio por etapa + rotación anual.
A96: Cliente | B96: País | C96: N° EDP | D96: Días Emis→Fact | E96: Días Fact→Ingr | F96: Ciclo Emis→Ingr (días) | G96: Rotación anual
A97: CMP | B97: Chile | C97: =COUNTIFS('90_Origen_Ledger_EdP'!$E$3:$E$702,$A97,'90_Origen_Ledger_EdP'!$X$3:$X$702,">=0") -> 115 | D97: =IFERROR(AVERAGEIFS('90_Origen_Ledger_EdP'!$V$3:$V$702,'90_Origen_Ledger_EdP'!$E$3:$E$702,$A97),"-") -> 25.140351 | E97: =IFERROR(AVERAGEIFS('90_Origen_Ledger_EdP'!$W$3:$W$702,'90_Origen_Ledger_EdP'!$E$3:$E$702,$A97),"-") -> 20.034783 | F97: =IFERROR(AVERAGEIFS('90_Origen_Ledger_EdP'!$X$3:$X$702,'90_Origen_Ledger_EdP'!$E$3:$E$702,$A97),"-") -> 41.913043 | G97: =IFERROR(365/F97,"-") -> 8.7085062
A98: Minsur | B98: Perú | C98: =COUNTIFS('90_Origen_Ledger_EdP'!$E$3:$E$702,$A98,'90_Origen_Ledger_EdP'!$X$3:$X$702,">=0") -> 44 | D98: =IFERROR(AVERAGEIFS('90_Origen_Ledger_EdP'!$V$3:$V$702,'90_Origen_Ledger_EdP'!$E$3:$E$702,$A98),"-") -> 40.571429 | E98: =IFERROR(AVERAGEIFS('90_Origen_Ledger_EdP'!$W$3:$W$702,'90_Origen_Ledger_EdP'!$E$3:$E$702,$A98),"-") -> 18.454545 | F98: =IFERROR(AVERAGEIFS('90_Origen_Ledger_EdP'!$X$3:$X$702,'90_Origen_Ledger_EdP'!$E$3:$E$702,$A98),"-") -> 55.090909 | G98: =IFERROR(365/F98,"-") -> 6.6254125
A99: Mosaic | B99: Brasil | C99: =COUNTIFS('90_Origen_Ledger_EdP'!$E$3:$E$702,$A99,'90_Origen_Ledger_EdP'!$X$3:$X$702,">=0") -> 59 | D99: =IFERROR(AVERAGEIFS('90_Origen_Ledger_EdP'!$V$3:$V$702,'90_Origen_Ledger_EdP'!$E$3:$E$702,$A99),"-") -> 24.057692 | E99: =IFERROR(AVERAGEIFS('90_Origen_Ledger_EdP'!$W$3:$W$702,'90_Origen_Ledger_EdP'!$E$3:$E$702,$A99),"-") -> 75.508475 | F99: =IFERROR(AVERAGEIFS('90_Origen_Ledger_EdP'!$X$3:$X$702,'90_Origen_Ledger_EdP'!$E$3:$E$702,$A99),"-") -> 96.254237 | G99: =IFERROR(365/F99,"-") -> 3.7920409
A100: AMSA | B100: Chile | C100: =COUNTIFS('90_Origen_Ledger_EdP'!$E$3:$E$702,$A100,'90_Origen_Ledger_EdP'!$X$3:$X$702,">=0") -> 38 | D100: =IFERROR(AVERAGEIFS('90_Origen_Ledger_EdP'!$V$3:$V$702,'90_Origen_Ledger_EdP'!$E$3:$E$702,$A100),"-") -> 24.864865 | E100: =IFERROR(AVERAGEIFS('90_Origen_Ledger_EdP'!$W$3:$W$702,'90_Origen_Ledger_EdP'!$E$3:$E$702,$A100),"-") -> 10.263158 | F100: =IFERROR(AVERAGEIFS('90_Origen_Ledger_EdP'!$X$3:$X$702,'90_Origen_Ledger_EdP'!$E$3:$E$702,$A100),"-") -> 34.421053 | G100: =IFERROR(365/F100,"-") -> 10.603976
A101: CD Capitals | B101: Perú | C101: =COUNTIFS('90_Origen_Ledger_EdP'!$E$3:$E$702,$A101,'90_Origen_Ledger_EdP'!$X$3:$X$702,">=0") -> 26 | D101: =IFERROR(AVERAGEIFS('90_Origen_Ledger_EdP'!$V$3:$V$702,'90_Origen_Ledger_EdP'!$E$3:$E$702,$A101),"-") -> 18.538462 | E101: =IFERROR(AVERAGEIFS('90_Origen_Ledger_EdP'!$W$3:$W$702,'90_Origen_Ledger_EdP'!$E$3:$E$702,$A101),"-") -> 19.115385 | F101: =IFERROR(AVERAGEIFS('90_Origen_Ledger_EdP'!$X$3:$X$702,'90_Origen_Ledger_EdP'!$E$3:$E$702,$A101),"-") -> 37.653846 | G101: =IFERROR(365/F101,"-") -> 9.6935649
A102: BHP | B102: Chile | C102: =COUNTIFS('90_Origen_Ledger_EdP'!$E$3:$E$702,$A102,'90_Origen_Ledger_EdP'!$X$3:$X$702,">=0") -> 24 | D102: =IFERROR(AVERAGEIFS('90_Origen_Ledger_EdP'!$V$3:$V$702,'90_Origen_Ledger_EdP'!$E$3:$E$702,$A102),"-") -> 38.583333 | E102: =IFERROR(AVERAGEIFS('90_Origen_Ledger_EdP'!$W$3:$W$702,'90_Origen_Ledger_EdP'!$E$3:$E$702,$A102),"-") -> 8.2916667 | F102: =IFERROR(AVERAGEIFS('90_Origen_Ledger_EdP'!$X$3:$X$702,'90_Origen_Ledger_EdP'!$E$3:$E$702,$A102),"-") -> 46.875 | G102: =IFERROR(365/F102,"-") -> 7.7866667
A103: Las Bambas | B103: Perú | C103: =COUNTIFS('90_Origen_Ledger_EdP'!$E$3:$E$702,$A103,'90_Origen_Ledger_EdP'!$X$3:$X$702,">=0") -> 26 | D103: =IFERROR(AVERAGEIFS('90_Origen_Ledger_EdP'!$V$3:$V$702,'90_Origen_Ledger_EdP'!$E$3:$E$702,$A103),"-") -> 31.230769 | E103: =IFERROR(AVERAGEIFS('90_Origen_Ledger_EdP'!$W$3:$W$702,'90_Origen_Ledger_EdP'!$E$3:$E$702,$A103),"-") -> 35.076923 | F103: =IFERROR(AVERAGEIFS('90_Origen_Ledger_EdP'!$X$3:$X$702,'90_Origen_Ledger_EdP'!$E$3:$E$702,$A103),"-") -> 66.307692 | G103: =IFERROR(365/F103,"-") -> 5.5046404
A104: Codelco | B104: Chile | C104: =COUNTIFS('90_Origen_Ledger_EdP'!$E$3:$E$702,$A104,'90_Origen_Ledger_EdP'!$X$3:$X$702,">=0") -> 32 | D104: =IFERROR(AVERAGEIFS('90_Origen_Ledger_EdP'!$V$3:$V$702,'90_Origen_Ledger_EdP'!$E$3:$E$702,$A104),"-") -> 80.03125 | E104: =IFERROR(AVERAGEIFS('90_Origen_Ledger_EdP'!$W$3:$W$702,'90_Origen_Ledger_EdP'!$E$3:$E$702,$A104),"-") -> 26.21875 | F104: =IFERROR(AVERAGEIFS('90_Origen_Ledger_EdP'!$X$3:$X$702,'90_Origen_Ledger_EdP'!$E$3:$E$702,$A104),"-") -> 106.25 | G104: =IFERROR(365/F104,"-") -> 3.4352941
A105: Lundin | B105: Chile | C105: =COUNTIFS('90_Origen_Ledger_EdP'!$E$3:$E$702,$A105,'90_Origen_Ledger_EdP'!$X$3:$X$702,">=0") -> 28 | D105: =IFERROR(AVERAGEIFS('90_Origen_Ledger_EdP'!$V$3:$V$702,'90_Origen_Ledger_EdP'!$E$3:$E$702,$A105),"-") -> 47.464286 | E105: =IFERROR(AVERAGEIFS('90_Origen_Ledger_EdP'!$W$3:$W$702,'90_Origen_Ledger_EdP'!$E$3:$E$702,$A105),"-") -> 25.785714 | F105: =IFERROR(AVERAGEIFS('90_Origen_Ledger_EdP'!$X$3:$X$702,'90_Origen_Ledger_EdP'!$E$3:$E$702,$A105),"-") -> 73.25 | G105: =IFERROR(365/F105,"-") -> 4.9829352
...

Sheet 03_FlujoCaja_2024_2025
A1: ENTREGABLE 3 · Flujo de caja histórico mensual
A2: Se separa DEVENGO (gestión: EDP/Factura/Ingreso) de CAJA REAL (movimientos). 2025 completo por entidad; 2024 solo cobros a caja (egresos/saldos 2024 no disponibles mensualmente).
A4: A) CAJA REAL 2025 — por entidad × mes (USD). Caja Inicial · Ingresos · Egresos · Caja Final. Fuente: 'Flujo Redco <país>'.
A5: Entidad | B5: Mes | C5: Caja Inicial | D5: Ingresos (op+otros) | E5: Egresos (costos+admin+no op+cta cte) | F5: Caja Final | G5: Flujo Neto Mes
A6: Chile | B6: ene | C6: =SUMIFS('90_Origen_Caja_2025'!$F$3:$F$542,'90_Origen_Caja_2025'!$A$3:$A$542,"Chile",'90_Origen_Caja_2025'!$C$3:$C$542,1,'90_Origen_Caja_2025'!$E$3:$E$542,"Caja Inicial") -> 52257.14 | D6: =SUMIFS('90_Origen_Caja_2025'!$F$3:$F$542,'90_Origen_Caja_2025'!$A$3:$A$542,"Chile",'90_Origen_Caja_2025'!$C$3:$C$542,1,'90_Origen_Caja_2025'!$E$3:$E$542,"Ingresos Op.")+SUMIFS('90_Origen_Caja_2025'!$F$3:$F$542,'90_Origen_Caja_2025'!$A$3:$A$542,"Chile",'90_Origen_Caja_2025'!$C$3:$C$542,1,'90_Origen_Caja_2025'!$E$3:$E$542,"Otros Ingresos") -> 623639.54 | E6: =SUMIFS('90_Origen_Caja_2025'!$F$3:$F$542,'90_Origen_Caja_2025'!$A$3:$A$542,"Chile",'90_Origen_Caja_2025'!$C$3:$C$542,1,'90_Origen_Caja_2025'!$E$3:$E$542,"Costos Op.")+SUMIFS('90_Origen_Caja_2025'!$F$3:$F$542,'90_Origen_Caja_2025'!$A$3:$A$542,"Chile",'90_Origen_Caja_2025'!$C$3:$C$542,1,'90_Origen_Caja_2025'!$E$3:$E$542,"Costos Admin.")+SUMIFS('90_Origen_Caja_2025'!$F$3:$F$542,'90_Origen_Caja_2025'!$A$3:$A$542,"Chile",'90_Origen_Caja_2025'!$C$3:$C$542,1,'90_Origen_Caja_2025'!$E$3:$E$542,"Activo")+SUMIFS('90_Origen_Caja_2025'!$F$3:$F$542,'90_Origen_Caja_2025'!$A$3:$A$542,"Chile",'90_Origen_Caja_2025'!$C$3:$C$542,1,'90_Origen_Caja_2025'!$E$3:$E$542,"Egresos No Op.")+SUMIFS('90_Origen_Caja_2025'!$F$3:$F$542,'90_Origen_Caja_2025'!$A$3:$A$542,"Chile",'90_Origen_Caja_2025'!$C$3:$C$542,1,'90_Origen_Caja_2025'!$E$3:$E$542,"Pagos Cta.Cte.") -> 505243.99 | F6: =C6+D6-E6 -> 170652.69 | G6: =D6-E6 -> 118395.55
A7: Chile | B7: feb | C7: =SUMIFS('90_Origen_Caja_2025'!$F$3:$F$542,'90_Origen_Caja_2025'!$A$3:$A$542,"Chile",'90_Origen_Caja_2025'!$C$3:$C$542,2,'90_Origen_Caja_2025'!$E$3:$E$542,"Caja Inicial") -> 170652.7 | D7: =SUMIFS('90_Origen_Caja_2025'!$F$3:$F$542,'90_Origen_Caja_2025'!$A$3:$A$542,"Chile",'90_Origen_Caja_2025'!$C$3:$C$542,2,'90_Origen_Caja_2025'!$E$3:$E$542,"Ingresos Op.")+SUMIFS('90_Origen_Caja_2025'!$F$3:$F$542,'90_Origen_Caja_2025'!$A$3:$A$542,"Chile",'90_Origen_Caja_2025'!$C$3:$C$542,2,'90_Origen_Caja_2025'!$E$3:$E$542,"Otros Ingresos") -> 776046.03 | E7: =SUMIFS('90_Origen_Caja_2025'!$F$3:$F$542,'90_Origen_Caja_2025'!$A$3:$A$542,"Chile",'90_Origen_Caja_2025'!$C$3:$C$542,2,'90_Origen_Caja_2025'!$E$3:$E$542,"Costos Op.")+SUMIFS('90_Origen_Caja_2025'!$F$3:$F$542,'90_Origen_Caja_2025'!$A$3:$A$542,"Chile",'90_Origen_Caja_2025'!$C$3:$C$542,2,'90_Origen_Caja_2025'!$E$3:$E$542,"Costos Admin.")+SUMIFS('90_Origen_Caja_2025'!$F$3:$F$542,'90_Origen_Caja_2025'!$A$3:$A$542,"Chile",'90_Origen_Caja_2025'!$C$3:$C$542,2,'90_Origen_Caja_2025'!$E$3:$E$542,"Activo")+SUMIFS('90_Origen_Caja_2025'!$F$3:$F$542,'90_Origen_Caja_2025'!$A$3:$A$542,"Chile",'90_Origen_Caja_2025'!$C$3:$C$542,2,'90_Origen_Caja_2025'!$E$3:$E$542,"Egresos No Op.")+SUMIFS('90_Origen_Caja_2025'!$F$3:$F$542,'90_Origen_Caja_2025'!$A$3:$A$542,"Chile",'90_Origen_Caja_2025'!$C$3:$C$542,2,'90_Origen_Caja_2025'!$E$3:$E$542,"Pagos Cta.Cte.") -> 642883.86 | F7: =C7+D7-E7 -> 303814.87 | G7: =D7-E7 -> 133162.17
A8: Chile | B8: mar | C8: =SUMIFS('90_Origen_Caja_2025'!$F$3:$F$542,'90_Origen_Caja_2025'!$A$3:$A$542,"Chile",'90_Origen_Caja_2025'!$C$3:$C$542,3,'90_Origen_Caja_2025'!$E$3:$E$542,"Caja Inicial") -> 303814.87 | D8: =SUMIFS('90_Origen_Caja_2025'!$F$3:$F$542,'90_Origen_Caja_2025'!$A$3:$A$542,"Chile",'90_Origen_Caja_2025'!$C$3:$C$542,3,'90_Origen_Caja_2025'!$E$3:$E$542,"Ingresos Op.")+SUMIFS('90_Origen_Caja_2025'!$F$3:$F$542,'90_Origen_Caja_2025'!$A$3:$A$542,"Chile",'90_Origen_Caja_2025'!$C$3:$C$542,3,'90_Origen_Caja_2025'!$E$3:$E$542,"Otros Ingresos") -> 490017.58 | E8: =SUMIFS('90_Origen_Caja_2025'!$F$3:$F$542,'90_Origen_Caja_2025'!$A$3:$A$542,"Chile",'90_Origen_Caja_2025'!$C$3:$C$542,3,'90_Origen_Caja_2025'!$E$3:$E$542,"Costos Op.")+SUMIFS('90_Origen_Caja_2025'!$F$3:$F$542,'90_Origen_Caja_2025'!$A$3:$A$542,"Chile",'90_Origen_Caja_2025'!$C$3:$C$542,3,'90_Origen_Caja_2025'!$E$3:$E$542,"Costos Admin.")+SUMIFS('90_Origen_Caja_2025'!$F$3:$F$542,'90_Origen_Caja_2025'!$A$3:$A$542,"Chile",'90_Origen_Caja_2025'!$C$3:$C$542,3,'90_Origen_Caja_2025'!$E$3:$E$542,"Activo")+SUMIFS('90_Origen_Caja_2025'!$F$3:$F$542,'90_Origen_Caja_2025'!$A$3:$A$542,"Chile",'90_Origen_Caja_2025'!$C$3:$C$542,3,'90_Origen_Caja_2025'!$E$3:$E$542,"Egresos No Op.")+SUMIFS('90_Origen_Caja_2025'!$F$3:$F$542,'90_Origen_Caja_2025'!$A$3:$A$542,"Chile",'90_Origen_Caja_2025'!$C$3:$C$542,3,'90_Origen_Caja_2025'!$E$3:$E$542,"Pagos Cta.Cte.") -> 559907.99 | F8: =C8+D8-E8 -> 233924.46 | G8: =D8-E8 -> -69890.41
A9: Chile | B9: abr | C9: =SUMIFS('90_Origen_Caja_2025'!$F$3:$F$542,'90_Origen_Caja_2025'!$A$3:$A$542,"Chile",'90_Origen_Caja_2025'!$C$3:$C$542,4,'90_Origen_Caja_2025'!$E$3:$E$542,"Caja Inicial") -> 233924.45 | D9: =SUMIFS('90_Origen_Caja_2025'!$F$3:$F$542,'90_Origen_Caja_2025'!$A$3:$A$542,"Chile",'90_Origen_Caja_2025'!$C$3:$C$542,4,'90_Origen_Caja_2025'!$E$3:$E$542,"Ingresos Op.")+SUMIFS('90_Origen_Caja_2025'!$F$3:$F$542,'90_Origen_Caja_2025'!$A$3:$A$542,"Chile",'90_Origen_Caja_2025'!$C$3:$C$542,4,'90_Origen_Caja_2025'!$E$3:$E$542,"Otros Ingresos") -> 501115.29 | E9: =SUMIFS('90_Origen_Caja_2025'!$F$3:$F$542,'90_Origen_Caja_2025'!$A$3:$A$542,"Chile",'90_Origen_Caja_2025'!$C$3:$C$542,4,'90_Origen_Caja_2025'!$E$3:$E$542,"Costos Op.")+SUMIFS('90_Origen_Caja_2025'!$F$3:$F$542,'90_Origen_Caja_2025'!$A$3:$A$542,"Chile",'90_Origen_Caja_2025'!$C$3:$C$542,4,'90_Origen_Caja_2025'!$E$3:$E$542,"Costos Admin.")+SUMIFS('90_Origen_Caja_2025'!$F$3:$F$542,'90_Origen_Caja_2025'!$A$3:$A$542,"Chile",'90_Origen_Caja_2025'!$C$3:$C$542,4,'90_Origen_Caja_2025'!$E$3:$E$542,"Activo")+SUMIFS('90_Origen_Caja_2025'!$F$3:$F$542,'90_Origen_Caja_2025'!$A$3:$A$542,"Chile",'90_Origen_Caja_2025'!$C$3:$C$542,4,'90_Origen_Caja_2025'!$E$3:$E$542,"Egresos No Op.")+SUMIFS('90_Origen_Caja_2025'!$F$3:$F$542,'90_Origen_Caja_2025'!$A$3:$A$542,"Chile",'90_Origen_Caja_2025'!$C$3:$C$542,4,'90_Origen_Caja_2025'!$E$3:$E$542,"Pagos Cta.Cte.") -> 614316.02 | F9: =C9+D9-E9 -> 120723.72 | G9: =D9-E9 -> -113200.73
A10: Chile | B10: may | C10: =SUMIFS('90_Origen_Caja_2025'!$F$3:$F$542,'90_Origen_Caja_2025'!$A$3:$A$542,"Chile",'90_Origen_Caja_2025'!$C$3:$C$542,5,'90_Origen_Caja_2025'!$E$3:$E$542,"Caja Inicial") -> 120723.72 | D10: =SUMIFS('90_Origen_Caja_2025'!$F$3:$F$542,'90_Origen_Caja_2025'!$A$3:$A$542,"Chile",'90_Origen_Caja_2025'!$C$3:$C$542,5,'90_Origen_Caja_2025'!$E$3:$E$542,"Ingresos Op.")+SUMIFS('90_Origen_Caja_2025'!$F$3:$F$542,'90_Origen_Caja_2025'!$A$3:$A$542,"Chile",'90_Origen_Caja_2025'!$C$3:$C$542,5,'90_Origen_Caja_2025'!$E$3:$E$542,"Otros Ingresos") -> 432617.57 | E10: =SUMIFS('90_Origen_Caja_2025'!$F$3:$F$542,'90_Origen_Caja_2025'!$A$3:$A$542,"Chile",'90_Origen_Caja_2025'!$C$3:$C$542,5,'90_Origen_Caja_2025'!$E$3:$E$542,"Costos Op.")+SUMIFS('90_Origen_Caja_2025'!$F$3:$F$542,'90_Origen_Caja_2025'!$A$3:$A$542,"Chile",'90_Origen_Caja_2025'!$C$3:$C$542,5,'90_Origen_Caja_2025'!$E$3:$E$542,"Costos Admin.")+SUMIFS('90_Origen_Caja_2025'!$F$3:$F$542,'90_Origen_Caja_2025'!$A$3:$A$542,"Chile",'90_Origen_Caja_2025'!$C$3:$C$542,5,'90_Origen_Caja_2025'!$E$3:$E$542,"Activo")+SUMIFS('90_Origen_Caja_2025'!$F$3:$F$542,'90_Origen_Caja_2025'!$A$3:$A$542,"Chile",'90_Origen_Caja_2025'!$C$3:$C$542,5,'90_Origen_Caja_2025'!$E$3:$E$542,"Egresos No Op.")+SUMIFS('90_Origen_Caja_2025'!$F$3:$F$542,'90_Origen_Caja_2025'!$A$3:$A$542,"Chile",'90_Origen_Caja_2025'!$C$3:$C$542,5,'90_Origen_Caja_2025'!$E$3:$E$542,"Pagos Cta.Cte.") -> 473383.13 | F10: =C10+D10-E10 -> 79958.16 | G10: =D10-E10 -> -40765.56
A11: Chile | B11: jun | C11: =SUMIFS('90_Origen_Caja_2025'!$F$3:$F$542,'90_Origen_Caja_2025'!$A$3:$A$542,"Chile",'90_Origen_Caja_2025'!$C$3:$C$542,6,'90_Origen_Caja_2025'!$E$3:$E$542,"Caja Inicial") -> 79958.16 | D11: =SUMIFS('90_Origen_Caja_2025'!$F$3:$F$542,'90_Origen_Caja_2025'!$A$3:$A$542,"Chile",'90_Origen_Caja_2025'!$C$3:$C$542,6,'90_Origen_Caja_2025'!$E$3:$E$542,"Ingresos Op.")+SUMIFS('90_Origen_Caja_2025'!$F$3:$F$542,'90_Origen_Caja_2025'!$A$3:$A$542,"Chile",'90_Origen_Caja_2025'!$C$3:$C$542,6,'90_Origen_Caja_2025'!$E$3:$E$542,"Otros Ingresos") -> 420992.32 | E11: =SUMIFS('90_Origen_Caja_2025'!$F$3:$F$542,'90_Origen_Caja_2025'!$A$3:$A$542,"Chile",'90_Origen_Caja_2025'!$C$3:$C$542,6,'90_Origen_Caja_2025'!$E$3:$E$542,"Costos Op.")+SUMIFS('90_Origen_Caja_2025'!$F$3:$F$542,'90_Origen_Caja_2025'!$A$3:$A$542,"Chile",'90_Origen_Caja_2025'!$C$3:$C$542,6,'90_Origen_Caja_2025'!$E$3:$E$542,"Costos Admin.")+SUMIFS('90_Origen_Caja_2025'!$F$3:$F$542,'90_Origen_Caja_2025'!$A$3:$A$542,"Chile",'90_Origen_Caja_2025'!$C$3:$C$542,6,'90_Origen_Caja_2025'!$E$3:$E$542,"Activo")+SUMIFS('90_Origen_Caja_2025'!$F$3:$F$542,'90_Origen_Caja_2025'!$A$3:$A$542,"Chile",'90_Origen_Caja_2025'!$C$3:$C$542,6,'90_Origen_Caja_2025'!$E$3:$E$542,"Egresos No Op.")+SUMIFS('90_Origen_Caja_2025'!$F$3:$F$542,'90_Origen_Caja_2025'!$A$3:$A$542,"Chile",'90_Origen_Caja_2025'!$C$3:$C$542,6,'90_Origen_Caja_2025'!$E$3:$E$542,"Pagos Cta.Cte.") -> 469053.99 | F11: =C11+D11-E11 -> 31896.49 | G11: =D11-E11 -> -48061.67
A12: Chile | B12: jul | C12: =SUMIFS('90_Origen_Caja_2025'!$F$3:$F$542,'90_Origen_Caja_2025'!$A$3:$A$542,"Chile",'90_Origen_Caja_2025'!$C$3:$C$542,7,'90_Origen_Caja_2025'!$E$3:$E$542,"Caja Inicial") -> 31896.49 | D12: =SUMIFS('90_Origen_Caja_2025'!$F$3:$F$542,'90_Origen_Caja_2025'!$A$3:$A$542,"Chile",'90_Origen_Caja_2025'!$C$3:$C$542,7,'90_Origen_Caja_2025'!$E$3:$E$542,"Ingresos Op.")+SUMIFS('90_Origen_Caja_2025'!$F$3:$F$542,'90_Origen_Caja_2025'!$A$3:$A$542,"Chile",'90_Origen_Caja_2025'!$C$3:$C$542,7,'90_Origen_Caja_2025'!$E$3:$E$542,"Otros Ingresos") -> 694589.56 | E12: =SUMIFS('90_Origen_Caja_2025'!$F$3:$F$542,'90_Origen_Caja_2025'!$A$3:$A$542,"Chile",'90_Origen_Caja_2025'!$C$3:$C$542,7,'90_Origen_Caja_2025'!$E$3:$E$542,"Costos Op.")+SUMIFS('90_Origen_Caja_2025'!$F$3:$F$542,'90_Origen_Caja_2025'!$A$3:$A$542,"Chile",'90_Origen_Caja_2025'!$C$3:$C$542,7,'90_Origen_Caja_2025'!$E$3:$E$542,"Costos Admin.")+SUMIFS('90_Origen_Caja_2025'!$F$3:$F$542,'90_Origen_Caja_2025'!$A$3:$A$542,"Chile",'90_Origen_Caja_2025'!$C$3:$C$542,7,'90_Origen_Caja_2025'!$E$3:$E$542,"Activo")+SUMIFS('90_Origen_Caja_2025'!$F$3:$F$542,'90_Origen_Caja_2025'!$A$3:$A$542,"Chile",'90_Origen_Caja_2025'!$C$3:$C$542,7,'90_Origen_Caja_2025'!$E$3:$E$542,"Egresos No Op.")+SUMIFS('90_Origen_Caja_2025'!$F$3:$F$542,'90_Origen_Caja_2025'!$A$3:$A$542,"Chile",'90_Origen_Caja_2025'!$C$3:$C$542,7,'90_Origen_Caja_2025'!$E$3:$E$542,"Pagos Cta.Cte.") -> 502823.19 | F12: =C12+D12-E12 -> 223662.86 | G12: =D12-E12 -> 191766.37
A13: Chile | B13: ago | C13: =SUMIFS('90_Origen_Caja_2025'!$F$3:$F$542,'90_Origen_Caja_2025'!$A$3:$A$542,"Chile",'90_Origen_Caja_2025'!$C$3:$C$542,8,'90_Origen_Caja_2025'!$E$3:$E$542,"Caja Inicial") -> 223662.84 | D13: =SUMIFS('90_Origen_Caja_2025'!$F$3:$F$542,'90_Origen_Caja_2025'!$A$3:$A$542,"Chile",'90_Origen_Caja_2025'!$C$3:$C$542,8,'90_Origen_Caja_2025'!$E$3:$E$542,"Ingresos Op.")+SUMIFS('90_Origen_Caja_2025'!$F$3:$F$542,'90_Origen_Caja_2025'!$A$3:$A$542,"Chile",'90_Origen_Caja_2025'!$C$3:$C$542,8,'90_Origen_Caja_2025'!$E$3:$E$542,"Otros Ingresos") -> 684254.25 | E13: =SUMIFS('90_Origen_Caja_2025'!$F$3:$F$542,'90_Origen_Caja_2025'!$A$3:$A$542,"Chile",'90_Origen_Caja_2025'!$C$3:$C$542,8,'90_Origen_Caja_2025'!$E$3:$E$542,"Costos Op.")+SUMIFS('90_Origen_Caja_2025'!$F$3:$F$542,'90_Origen_Caja_2025'!$A$3:$A$542,"Chile",'90_Origen_Caja_2025'!$C$3:$C$542,8,'90_Origen_Caja_2025'!$E$3:$E$542,"Costos Admin.")+SUMIFS('90_Origen_Caja_2025'!$F$3:$F$542,'90_Origen_Caja_2025'!$A$3:$A$542,"Chile",'90_Origen_Caja_2025'!$C$3:$C$542,8,'90_Origen_Caja_2025'!$E$3:$E$542,"Activo")+SUMIFS('90_Origen_Caja_2025'!$F$3:$F$542,'90_Origen_Caja_2025'!$A$3:$A$542,"Chile",'90_Origen_Caja_2025'!$C$3:$C$542,8,'90_Origen_Caja_2025'!$E$3:$E$542,"Egresos No Op.")+SUMIFS('90_Origen_Caja_2025'!$F$3:$F$542,'90_Origen_Caja_2025'!$A$3:$A$542,"Chile",'90_Origen_Caja_2025'!$C$3:$C$542,8,'90_Origen_Caja_2025'!$E$3:$E$542,"Pagos Cta.Cte.") -> 549999.74 | F13: =C13+D13-E13 -> 357917.35 | G13: =D13-E13 -> 134254.51
A14: Chile | B14: sep | C14: =SUMIFS('90_Origen_Caja_2025'!$F$3:$F$542,'90_Origen_Caja_2025'!$A$3:$A$542,"Chile",'90_Origen_Caja_2025'!$C$3:$C$542,9,'90_Origen_Caja_2025'!$E$3:$E$542,"Caja Inicial") -> 357917.35 | D14: =SUMIFS('90_Origen_Caja_2025'!$F$3:$F$542,'90_Origen_Caja_2025'!$A$3:$A$542,"Chile",'90_Origen_Caja_2025'!$C$3:$C$542,9,'90_Origen_Caja_2025'!$E$3:$E$542,"Ingresos Op.")+SUMIFS('90_Origen_Caja_2025'!$F$3:$F$542,'90_Origen_Caja_2025'!$A$3:$A$542,"Chile",'90_Origen_Caja_2025'!$C$3:$C$542,9,'90_Origen_Caja_2025'!$E$3:$E$542,"Otros Ingresos") -> 386490.19 | E14: =SUMIFS('90_Origen_Caja_2025'!$F$3:$F$542,'90_Origen_Caja_2025'!$A$3:$A$542,"Chile",'90_Origen_Caja_2025'!$C$3:$C$542,9,'90_Origen_Caja_2025'!$E$3:$E$542,"Costos Op.")+SUMIFS('90_Origen_Caja_2025'!$F$3:$F$542,'90_Origen_Caja_2025'!$A$3:$A$542,"Chile",'90_Origen_Caja_2025'!$C$3:$C$542,9,'90_Origen_Caja_2025'!$E$3:$E$542,"Costos Admin.")+SUMIFS('90_Origen_Caja_2025'!$F$3:$F$542,'90_Origen_Caja_2025'!$A$3:$A$542,"Chile",'90_Origen_Caja_2025'!$C$3:$C$542,9,'90_Origen_Caja_2025'!$E$3:$E$542,"Activo")+SUMIFS('90_Origen_Caja_2025'!$F$3:$F$542,'90_Origen_Caja_2025'!$A$3:$A$542,"Chile",'90_Origen_Caja_2025'!$C$3:$C$542,9,'90_Origen_Caja_2025'!$E$3:$E$542,"Egresos No Op.")+SUMIFS('90_Origen_Caja_2025'!$F$3:$F$542,'90_Origen_Caja_2025'!$A$3:$A$542,"Chile",'90_Origen_Caja_2025'!$C$3:$C$542,9,'90_Origen_Caja_2025'!$E$3:$E$542,"Pagos Cta.Cte.") -> 543016.09 | F14: =C14+D14-E14 -> 201391.45 | G14: =D14-E14 -> -156525.9
A15: Chile | B15: oct | C15: =SUMIFS('90_Origen_Caja_2025'!$F$3:$F$542,'90_Origen_Caja_2025'!$A$3:$A$542,"Chile",'90_Origen_Caja_2025'!$C$3:$C$542,10,'90_Origen_Caja_2025'!$E$3:$E$542,"Caja Inicial") -> 201391.46 | D15: =SUMIFS('90_Origen_Caja_2025'!$F$3:$F$542,'90_Origen_Caja_2025'!$A$3:$A$542,"Chile",'90_Origen_Caja_2025'!$C$3:$C$542,10,'90_Origen_Caja_2025'!$E$3:$E$542,"Ingresos Op.")+SUMIFS('90_Origen_Caja_2025'!$F$3:$F$542,'90_Origen_Caja_2025'!$A$3:$A$542,"Chile",'90_Origen_Caja_2025'!$C$3:$C$542,10,'90_Origen_Caja_2025'!$E$3:$E$542,"Otros Ingresos") -> 449664.61 | E15: =SUMIFS('90_Origen_Caja_2025'!$F$3:$F$542,'90_Origen_Caja_2025'!$A$3:$A$542,"Chile",'90_Origen_Caja_2025'!$C$3:$C$542,10,'90_Origen_Caja_2025'!$E$3:$E$542,"Costos Op.")+SUMIFS('90_Origen_Caja_2025'!$F$3:$F$542,'90_Origen_Caja_2025'!$A$3:$A$542,"Chile",'90_Origen_Caja_2025'!$C$3:$C$542,10,'90_Origen_Caja_2025'!$E$3:$E$542,"Costos Admin.")+SUMIFS('90_Origen_Caja_2025'!$F$3:$F$542,'90_Origen_Caja_2025'!$A$3:$A$542,"Chile",'90_Origen_Caja_2025'!$C$3:$C$542,10,'90_Origen_Caja_2025'!$E$3:$E$542,"Activo")+SUMIFS('90_Origen_Caja_2025'!$F$3:$F$542,'90_Origen_Caja_2025'!$A$3:$A$542,"Chile",'90_Origen_Caja_2025'!$C$3:$C$542,10,'90_Origen_Caja_2025'!$E$3:$E$542,"Egresos No Op.")+SUMIFS('90_Origen_Caja_2025'!$F$3:$F$542,'90_Origen_Caja_2025'!$A$3:$A$542,"Chile",'90_Origen_Caja_2025'!$C$3:$C$542,10,'90_Origen_Caja_2025'!$E$3:$E$542,"Pagos Cta.Cte.") -> 595355.26 | F15: =C15+D15-E15 -> 55700.81 | G15: =D15-E15 -> -145690.65
A16: Chile | B16: nov | C16: =SUMIFS('90_Origen_Caja_2025'!$F$3:$F$542,'90_Origen_Caja_2025'!$A$3:$A$542,"Chile",'90_Origen_Caja_2025'!$C$3:$C$542,11,'90_Origen_Caja_2025'!$E$3:$E$542,"Caja Inicial") -> 55700.81 | D16: =SUMIFS('90_Origen_Caja_2025'!$F$3:$F$542,'90_Origen_Caja_2025'!$A$3:$A$542,"Chile",'90_Origen_Caja_2025'!$C$3:$C$542,11,'90_Origen_Caja_2025'!$E$3:$E$542,"Ingresos Op.")+SUMIFS('90_Origen_Caja_2025'!$F$3:$F$542,'90_Origen_Caja_2025'!$A$3:$A$542,"Chile",'90_Origen_Caja_2025'!$C$3:$C$542,11,'90_Origen_Caja_2025'!$E$3:$E$542,"Otros Ingresos") -> 434071.77 | E16: =SUMIFS('90_Origen_Caja_2025'!$F$3:$F$542,'90_Origen_Caja_2025'!$A$3:$A$542,"Chile",'90_Origen_Caja_2025'!$C$3:$C$542,11,'90_Origen_Caja_2025'!$E$3:$E$542,"Costos Op.")+SUMIFS('90_Origen_Caja_2025'!$F$3:$F$542,'90_Origen_Caja_2025'!$A$3:$A$542,"Chile",'90_Origen_Caja_2025'!$C$3:$C$542,11,'90_Origen_Caja_2025'!$E$3:$E$542,"Costos Admin.")+SUMIFS('90_Origen_Caja_2025'!$F$3:$F$542,'90_Origen_Caja_2025'!$A$3:$A$542,"Chile",'90_Origen_Caja_2025'!$C$3:$C$542,11,'90_Origen_Caja_2025'!$E$3:$E$542,"Activo")+SUMIFS('90_Origen_Caja_2025'!$F$3:$F$542,'90_Origen_Caja_2025'!$A$3:$A$542,"Chile",'90_Origen_Caja_2025'!$C$3:$C$542,11,'90_Origen_Caja_2025'!$E$3:$E$542,"Egresos No Op.")+SUMIFS('90_Origen_Caja_2025'!$F$3:$F$542,'90_Origen_Caja_2025'!$A$3:$A$542,"Chile",'90_Origen_Caja_2025'!$C$3:$C$542,11,'90_Origen_Caja_2025'!$E$3:$E$542,"Pagos Cta.Cte.") -> 469718.2 | F16: =C16+D16-E16 -> 20054.38 | G16: =D16-E16 -> -35646.43
A17: Chile | B17: dic | C17: =SUMIFS('90_Origen_Caja_2025'!$F$3:$F$542,'90_Origen_Caja_2025'!$A$3:$A$542,"Chile",'90_Origen_Caja_2025'!$C$3:$C$542,12,'90_Origen_Caja_2025'!$E$3:$E$542,"Caja Inicial") -> 20054.38 | D17: =SUMIFS('90_Origen_Caja_2025'!$F$3:$F$542,'90_Origen_Caja_2025'!$A$3:$A$542,"Chile",'90_Origen_Caja_2025'!$C$3:$C$542,12,'90_Origen_Caja_2025'!$E$3:$E$542,"Ingresos Op.")+SUMIFS('90_Origen_Caja_2025'!$F$3:$F$542,'90_Origen_Caja_2025'!$A$3:$A$542,"Chile",'90_Origen_Caja_2025'!$C$3:$C$542,12,'90_Origen_Caja_2025'!$E$3:$E$542,"Otros Ingresos") -> 602066.43 | E17: =SUMIFS('90_Origen_Caja_2025'!$F$3:$F$542,'90_Origen_Caja_2025'!$A$3:$A$542,"Chile",'90_Origen_Caja_2025'!$C$3:$C$542,12,'90_Origen_Caja_2025'!$E$3:$E$542,"Costos Op.")+SUMIFS('90_Origen_Caja_2025'!$F$3:$F$542,'90_Origen_Caja_2025'!$A$3:$A$542,"Chile",'90_Origen_Caja_2025'!$C$3:$C$542,12,'90_Origen_Caja_2025'!$E$3:$E$542,"Costos Admin.")+SUMIFS('90_Origen_Caja_2025'!$F$3:$F$542,'90_Origen_Caja_2025'!$A$3:$A$542,"Chile",'90_Origen_Caja_2025'!$C$3:$C$542,12,'90_Origen_Caja_2025'!$E$3:$E$542,"Activo")+SUMIFS('90_Origen_Caja_2025'!$F$3:$F$542,'90_Origen_Caja_2025'!$A$3:$A$542,"Chile",'90_Origen_Caja_2025'!$C$3:$C$542,12,'90_Origen_Caja_2025'!$E$3:$E$542,"Egresos No Op.")+SUMIFS('90_Origen_Caja_2025'!$F$3:$F$542,'90_Origen_Caja_2025'!$A$3:$A$542,"Chile",'90_Origen_Caja_2025'!$C$3:$C$542,12,'90_Origen_Caja_2025'!$E$3:$E$542,"Pagos Cta.Cte.") -> 598836.75 | F17: =C17+D17-E17 -> 23284.06 | G17: =D17-E17 -> 3229.68
A18: Perú | B18: ene | C18: =SUMIFS('90_Origen_Caja_2025'!$F$3:$F$542,'90_Origen_Caja_2025'!$A$3:$A$542,"Perú",'90_Origen_Caja_2025'!$C$3:$C$542,1,'90_Origen_Caja_2025'!$E$3:$E$542,"Caja Inicial") -> 136767.69 | D18: =SUMIFS('90_Origen_Caja_2025'!$F$3:$F$542,'90_Origen_Caja_2025'!$A$3:$A$542,"Perú",'90_Origen_Caja_2025'!$C$3:$C$542,1,'90_Origen_Caja_2025'!$E$3:$E$542,"Ingresos Op.")+SUMIFS('90_Origen_Caja_2025'!$F$3:$F$542,'90_Origen_Caja_2025'!$A$3:$A$542,"Perú",'90_Origen_Caja_2025'!$C$3:$C$542,1,'90_Origen_Caja_2025'!$E$3:$E$542,"Otros Ingresos") -> 135755 | E18: =SUMIFS('90_Origen_Caja_2025'!$F$3:$F$542,'90_Origen_Caja_2025'!$A$3:$A$542,"Perú",'90_Origen_Caja_2025'!$C$3:$C$542,1,'90_Origen_Caja_2025'!$E$3:$E$542,"Costos Op.")+SUMIFS('90_Origen_Caja_2025'!$F$3:$F$542,'90_Origen_Caja_2025'!$A$3:$A$542,"Perú",'90_Origen_Caja_2025'!$C$3:$C$542,1,'90_Origen_Caja_2025'!$E$3:$E$542,"Costos Admin.")+SUMIFS('90_Origen_Caja_2025'!$F$3:$F$542,'90_Origen_Caja_2025'!$A$3:$A$542,"Perú",'90_Origen_Caja_2025'!$C$3:$C$542,1,'90_Origen_Caja_2025'!$E$3:$E$542,"Activo")+SUMIFS('90_Origen_Caja_2025'!$F$3:$F$542,'90_Origen_Caja_2025'!$A$3:$A$542,"Perú",'90_Origen_Caja_2025'!$C$3:$C$542,1,'90_Origen_Caja_2025'!$E$3:$E$542,"Egresos No Op.")+SUMIFS('90_Origen_Caja_2025'!$F$3:$F$542,'90_Origen_Caja_2025'!$A$3:$A$542,"Perú",'90_Origen_Caja_2025'!$C$3:$C$542,1,'90_Origen_Caja_2025'!$E$3:$E$542,"Pagos Cta.Cte.") -> 131956.85 | F18: =C18+D18-E18 -> 140565.84 | G18: =D18-E18 -> 3798.15
A19: Perú | B19: feb | C19: =SUMIFS('90_Origen_Caja_2025'!$F$3:$F$542,'90_Origen_Caja_2025'!$A$3:$A$542,"Perú",'90_Origen_Caja_2025'!$C$3:$C$542,2,'90_Origen_Caja_2025'!$E$3:$E$542,"Caja Inicial") -> 140565.84 | D19: =SUMIFS('90_Origen_Caja_2025'!$F$3:$F$542,'90_Origen_Caja_2025'!$A$3:$A$542,"Perú",'90_Origen_Caja_2025'!$C$3:$C$542,2,'90_Origen_Caja_2025'!$E$3:$E$542,"Ingresos Op.")+SUMIFS('90_Origen_Caja_2025'!$F$3:$F$542,'90_Origen_Caja_2025'!$A$3:$A$542,"Perú",'90_Origen_Caja_2025'!$C$3:$C$542,2,'90_Origen_Caja_2025'!$E$3:$E$542,"Otros Ingresos") -> 78954 | E19: =SUMIFS('90_Origen_Caja_2025'!$F$3:$F$542,'90_Origen_Caja_2025'!$A$3:$A$542,"Perú",'90_Origen_Caja_2025'!$C$3:$C$542,2,'90_Origen_Caja_2025'!$E$3:$E$542,"Costos Op.")+SUMIFS('90_Origen_Caja_2025'!$F$3:$F$542,'90_Origen_Caja_2025'!$A$3:$A$542,"Perú",'90_Origen_Caja_2025'!$C$3:$C$542,2,'90_Origen_Caja_2025'!$E$3:$E$542,"Costos Admin.")+SUMIFS('90_Origen_Caja_2025'!$F$3:$F$542,'90_Origen_Caja_2025'!$A$3:$A$542,"Perú",'90_Origen_Caja_2025'!$C$3:$C$542,2,'90_Origen_Caja_2025'!$E$3:$E$542,"Activo")+SUMIFS('90_Origen_Caja_2025'!$F$3:$F$542,'90_Origen_Caja_2025'!$A$3:$A$542,"Perú",'90_Origen_Caja_2025'!$C$3:$C$542,2,'90_Origen_Caja_2025'!$E$3:$E$542,"Egresos No Op.")+SUMIFS('90_Origen_Caja_2025'!$F$3:$F$542,'90_Origen_Caja_2025'!$A$3:$A$542,"Perú",'90_Origen_Caja_2025'!$C$3:$C$542,2,'90_Origen_Caja_2025'!$E$3:$E$542,"Pagos Cta.Cte.") -> 81597 | F19: =C19+D19-E19 -> 137922.84 | G19: =D19-E19 -> -2643
A20: Perú | B20: mar | C20: =SUMIFS('90_Origen_Caja_2025'!$F$3:$F$542,'90_Origen_Caja_2025'!$A$3:$A$542,"Perú",'90_Origen_Caja_2025'!$C$3:$C$542,3,'90_Origen_Caja_2025'!$E$3:$E$542,"Caja Inicial") -> 137922.84 | D20: =SUMIFS('90_Origen_Caja_2025'!$F$3:$F$542,'90_Origen_Caja_2025'!$A$3:$A$542,"Perú",'90_Origen_Caja_2025'!$C$3:$C$542,3,'90_Origen_Caja_2025'!$E$3:$E$542,"Ingresos Op.")+SUMIFS('90_Origen_Caja_2025'!$F$3:$F$542,'90_Origen_Caja_2025'!$A$3:$A$542,"Perú",'90_Origen_Caja_2025'!$C$3:$C$542,3,'90_Origen_Caja_2025'!$E$3:$E$542,"Otros Ingresos") -> 177338 | E20: =SUMIFS('90_Origen_Caja_2025'!$F$3:$F$542,'90_Origen_Caja_2025'!$A$3:$A$542,"Perú",'90_Origen_Caja_2025'!$C$3:$C$542,3,'90_Origen_Caja_2025'!$E$3:$E$542,"Costos Op.")+SUMIFS('90_Origen_Caja_2025'!$F$3:$F$542,'90_Origen_Caja_2025'!$A$3:$A$542,"Perú",'90_Origen_Caja_2025'!$C$3:$C$542,3,'90_Origen_Caja_2025'!$E$3:$E$542,"Costos Admin.")+SUMIFS('90_Origen_Caja_2025'!$F$3:$F$542,'90_Origen_Caja_2025'!$A$3:$A$542,"Perú",'90_Origen_Caja_2025'!$C$3:$C$542,3,'90_Origen_Caja_2025'!$E$3:$E$542,"Activo")+SUMIFS('90_Origen_Caja_2025'!$F$3:$F$542,'90_Origen_Caja_2025'!$A$3:$A$542,"Perú",'90_Origen_Caja_2025'!$C$3:$C$542,3,'90_Origen_Caja_2025'!$E$3:$E$542,"Egresos No Op.")+SUMIFS('90_Origen_Caja_2025'!$F$3:$F$542,'90_Origen_Caja_2025'!$A$3:$A$542,"Perú",'90_Origen_Caja_2025'!$C$3:$C$542,3,'90_Origen_Caja_2025'!$E$3:$E$542,"Pagos Cta.Cte.") -> 112203 | F20: =C20+D20-E20 -> 203057.84 | G20: =D20-E20 -> 65135
A21: Perú | B21: abr | C21: =SUMIFS('90_Origen_Caja_2025'!$F$3:$F$542,'90_Origen_Caja_2025'!$A$3:$A$542,"Perú",'90_Origen_Caja_2025'!$C$3:$C$542,4,'90_Origen_Caja_2025'!$E$3:$E$542,"Caja Inicial") -> 203057.84 | D21: =SUMIFS('90_Origen_Caja_2025'!$F$3:$F$542,'90_Origen_Caja_2025'!$A$3:$A$542,"Perú",'90_Origen_Caja_2025'!$C$3:$C$542,4,'90_Origen_Caja_2025'!$E$3:$E$542,"Ingresos Op.")+SUMIFS('90_Origen_Caja_2025'!$F$3:$F$542,'90_Origen_Caja_2025'!$A$3:$A$542,"Perú",'90_Origen_Caja_2025'!$C$3:$C$542,4,'90_Origen_Caja_2025'!$E$3:$E$542,"Otros Ingresos") -> 138606 | E21: =SUMIFS('90_Origen_Caja_2025'!$F$3:$F$542,'90_Origen_Caja_2025'!$A$3:$A$542,"Perú",'90_Origen_Caja_2025'!$C$3:$C$542,4,'90_Origen_Caja_2025'!$E$3:$E$542,"Costos Op.")+SUMIFS('90_Origen_Caja_2025'!$F$3:$F$542,'90_Origen_Caja_2025'!$A$3:$A$542,"Perú",'90_Origen_Caja_2025'!$C$3:$C$542,4,'90_Origen_Caja_2025'!$E$3:$E$542,"Costos Admin.")+SUMIFS('90_Origen_Caja_2025'!$F$3:$F$542,'90_Origen_Caja_2025'!$A$3:$A$542,"Perú",'90_Origen_Caja_2025'!$C$3:$C$542,4,'90_Origen_Caja_2025'!$E$3:$E$542,"Activo")+SUMIFS('90_Origen_Caja_2025'!$F$3:$F$542,'90_Origen_Caja_2025'!$A$3:$A$542,"Perú",'90_Origen_Caja_2025'!$C$3:$C$542,4,'90_Origen_Caja_2025'!$E$3:$E$542,"Egresos No Op.")+SUMIFS('90_Origen_Caja_2025'!$F$3:$F$542,'90_Origen_Caja_2025'!$A$3:$A$542,"Perú",'90_Origen_Caja_2025'!$C$3:$C$542,4,'90_Origen_Caja_2025'!$E$3:$E$542,"Pagos Cta.Cte.") -> 139670.3 | F21: =C21+D21-E21 -> 201993.54 | G21: =D21-E21 -> -1064.3
A22: Perú | B22: may | C22: =SUMIFS('90_Origen_Caja_2025'!$F$3:$F$542,'90_Origen_Caja_2025'!$A$3:$A$542,"Perú",'90_Origen_Caja_2025'!$C$3:$C$542,5,'90_Origen_Caja_2025'!$E$3:$E$542,"Caja Inicial") -> 201993.54 | D22: =SUMIFS('90_Origen_Caja_2025'!$F$3:$F$542,'90_Origen_Caja_2025'!$A$3:$A$542,"Perú",'90_Origen_Caja_2025'!$C$3:$C$542,5,'90_Origen_Caja_2025'!$E$3:$E$542,"Ingresos Op.")+SUMIFS('90_Origen_Caja_2025'!$F$3:$F$542,'90_Origen_Caja_2025'!$A$3:$A$542,"Perú",'90_Origen_Caja_2025'!$C$3:$C$542,5,'90_Origen_Caja_2025'!$E$3:$E$542,"Otros Ingresos") -> 173914 | E22: =SUMIFS('90_Origen_Caja_2025'!$F$3:$F$542,'90_Origen_Caja_2025'!$A$3:$A$542,"Perú",'90_Origen_Caja_2025'!$C$3:$C$542,5,'90_Origen_Caja_2025'!$E$3:$E$542,"Costos Op.")+SUMIFS('90_Origen_Caja_2025'!$F$3:$F$542,'90_Origen_Caja_2025'!$A$3:$A$542,"Perú",'90_Origen_Caja_2025'!$C$3:$C$542,5,'90_Origen_Caja_2025'!$E$3:$E$542,"Costos Admin.")+SUMIFS('90_Origen_Caja_2025'!$F$3:$F$542,'90_Origen_Caja_2025'!$A$3:$A$542,"Perú",'90_Origen_Caja_2025'!$C$3:$C$542,5,'90_Origen_Caja_2025'!$E$3:$E$542,"Activo")+SUMIFS('90_Origen_Caja_2025'!$F$3:$F$542,'90_Origen_Caja_2025'!$A$3:$A$542,"Perú",'90_Origen_Caja_2025'!$C$3:$C$542,5,'90_Origen_Caja_2025'!$E$3:$E$542,"Egresos No Op.")+SUMIFS('90_Origen_Caja_2025'!$F$3:$F$542,'90_Origen_Caja_2025'!$A$3:$A$542,"Perú",'90_Origen_Caja_2025'!$C$3:$C$542,5,'90_Origen_Caja_2025'!$E$3:$E$542,"Pagos Cta.Cte.") -> 178913 | F22: =C22+D22-E22 -> 196994.54 | G22: =D22-E22 -> -4999
A23: Perú | B23: jun | C23: =SUMIFS('90_Origen_Caja_2025'!$F$3:$F$542,'90_Origen_Caja_2025'!$A$3:$A$542,"Perú",'90_Origen_Caja_2025'!$C$3:$C$542,6,'90_Origen_Caja_2025'!$E$3:$E$542,"Caja Inicial") -> 196994.54 | D23: =SUMIFS('90_Origen_Caja_2025'!$F$3:$F$542,'90_Origen_Caja_2025'!$A$3:$A$542,"Perú",'90_Origen_Caja_2025'!$C$3:$C$542,6,'90_Origen_Caja_2025'!$E$3:$E$542,"Ingresos Op.")+SUMIFS('90_Origen_Caja_2025'!$F$3:$F$542,'90_Origen_Caja_2025'!$A$3:$A$542,"Perú",'90_Origen_Caja_2025'!$C$3:$C$542,6,'90_Origen_Caja_2025'!$E$3:$E$542,"Otros Ingresos") -> 265715 | E23: =SUMIFS('90_Origen_Caja_2025'!$F$3:$F$542,'90_Origen_Caja_2025'!$A$3:$A$542,"Perú",'90_Origen_Caja_2025'!$C$3:$C$542,6,'90_Origen_Caja_2025'!$E$3:$E$542,"Costos Op.")+SUMIFS('90_Origen_Caja_2025'!$F$3:$F$542,'90_Origen_Caja_2025'!$A$3:$A$542,"Perú",'90_Origen_Caja_2025'!$C$3:$C$542,6,'90_Origen_Caja_2025'!$E$3:$E$542,"Costos Admin.")+SUMIFS('90_Origen_Caja_2025'!$F$3:$F$542,'90_Origen_Caja_2025'!$A$3:$A$542,"Perú",'90_Origen_Caja_2025'!$C$3:$C$542,6,'90_Origen_Caja_2025'!$E$3:$E$542,"Activo")+SUMIFS('90_Origen_Caja_2025'!$F$3:$F$542,'90_Origen_Caja_2025'!$A$3:$A$542,"Perú",'90_Origen_Caja_2025'!$C$3:$C$542,6,'90_Origen_Caja_2025'!$E$3:$E$542,"Egresos No Op.")+SUMIFS('90_Origen_Caja_2025'!$F$3:$F$542,'90_Origen_Caja_2025'!$A$3:$A$542,"Perú",'90_Origen_Caja_2025'!$C$3:$C$542,6,'90_Origen_Caja_2025'!$E$3:$E$542,"Pagos Cta.Cte.") -> 223620 | F23: =C23+D23-E23 -> 239089.54 | G23: =D23-E23 -> 42095
A24: Perú | B24: jul | C24: =SUMIFS('90_Origen_Caja_2025'!$F$3:$F$542,'90_Origen_Caja_2025'!$A$3:$A$542,"Perú",'90_Origen_Caja_2025'!$C$3:$C$542,7,'90_Origen_Caja_2025'!$E$3:$E$542,"Caja Inicial") -> 239089.54 | D24: =SUMIFS('90_Origen_Caja_2025'!$F$3:$F$542,'90_Origen_Caja_2025'!$A$3:$A$542,"Perú",'90_Origen_Caja_2025'!$C$3:$C$542,7,'90_Origen_Caja_2025'!$E$3:$E$542,"Ingresos Op.")+SUMIFS('90_Origen_Caja_2025'!$F$3:$F$542,'90_Origen_Caja_2025'!$A$3:$A$542,"Perú",'90_Origen_Caja_2025'!$C$3:$C$542,7,'90_Origen_Caja_2025'!$E$3:$E$542,"Otros Ingresos") -> 285885 | E24: =SUMIFS('90_Origen_Caja_2025'!$F$3:$F$542,'90_Origen_Caja_2025'!$A$3:$A$542,"Perú",'90_Origen_Caja_2025'!$C$3:$C$542,7,'90_Origen_Caja_2025'!$E$3:$E$542,"Costos Op.")+SUMIFS('90_Origen_Caja_2025'!$F$3:$F$542,'90_Origen_Caja_2025'!$A$3:$A$542,"Perú",'90_Origen_Caja_2025'!$C$3:$C$542,7,'90_Origen_Caja_2025'!$E$3:$E$542,"Costos Admin.")+SUMIFS('90_Origen_Caja_2025'!$F$3:$F$542,'90_Origen_Caja_2025'!$A$3:$A$542,"Perú",'90_Origen_Caja_2025'!$C$3:$C$542,7,'90_Origen_Caja_2025'!$E$3:$E$542,"Activo")+SUMIFS('90_Origen_Caja_2025'!$F$3:$F$542,'90_Origen_Caja_2025'!$A$3:$A$542,"Perú",'90_Origen_Caja_2025'!$C$3:$C$542,7,'90_Origen_Caja_2025'!$E$3:$E$542,"Egresos No Op.")+SUMIFS('90_Origen_Caja_2025'!$F$3:$F$542,'90_Origen_Caja_2025'!$A$3:$A$542,"Perú",'90_Origen_Caja_2025'!$C$3:$C$542,7,'90_Origen_Caja_2025'!$E$3:$E$542,"Pagos Cta.Cte.") -> 237006 | F24: =C24+D24-E24 -> 287968.54 | G24: =D24-E24 -> 48879
A25: Perú | B25: ago | C25: =SUMIFS('90_Origen_Caja_2025'!$F$3:$F$542,'90_Origen_Caja_2025'!$A$3:$A$542,"Perú",'90_Origen_Caja_2025'!$C$3:$C$542,8,'90_Origen_Caja_2025'!$E$3:$E$542,"Caja Inicial") -> 287968.54 | D25: =SUMIFS('90_Origen_Caja_2025'!$F$3:$F$542,'90_Origen_Caja_2025'!$A$3:$A$542,"Perú",'90_Origen_Caja_2025'!$C$3:$C$542,8,'90_Origen_Caja_2025'!$E$3:$E$542,"Ingresos Op.")+SUMIFS('90_Origen_Caja_2025'!$F$3:$F$542,'90_Origen_Caja_2025'!$A$3:$A$542,"Perú",'90_Origen_Caja_2025'!$C$3:$C$542,8,'90_Origen_Caja_2025'!$E$3:$E$542,"Otros Ingresos") -> 768008 | E25: =SUMIFS('90_Origen_Caja_2025'!$F$3:$F$542,'90_Origen_Caja_2025'!$A$3:$A$542,"Perú",'90_Origen_Caja_2025'!$C$3:$C$542,8,'90_Origen_Caja_2025'!$E$3:$E$542,"Costos Op.")+SUMIFS('90_Origen_Caja_2025'!$F$3:$F$542,'90_Origen_Caja_2025'!$A$3:$A$542,"Perú",'90_Origen_Caja_2025'!$C$3:$C$542,8,'90_Origen_Caja_2025'!$E$3:$E$542,"Costos Admin.")+SUMIFS('90_Origen_Caja_2025'!$F$3:$F$542,'90_Origen_Caja_2025'!$A$3:$A$542,"Perú",'90_Origen_Caja_2025'!$C$3:$C$542,8,'90_Origen_Caja_2025'!$E$3:$E$542,"Activo")+SUMIFS('90_Origen_Caja_2025'!$F$3:$F$542,'90_Origen_Caja_2025'!$A$3:$A$542,"Perú",'90_Origen_Caja_2025'!$C$3:$C$542,8,'90_Origen_Caja_2025'!$E$3:$E$542,"Egresos No Op.")+SUMIFS('90_Origen_Caja_2025'!$F$3:$F$542,'90_Origen_Caja_2025'!$A$3:$A$542,"Perú",'90_Origen_Caja_2025'!$C$3:$C$542,8,'90_Origen_Caja_2025'!$E$3:$E$542,"Pagos Cta.Cte.") -> 800514 | F25: =C25+D25-E25 -> 255462.54 | G25: =D25-E25 -> -32506
A26: Perú | B26: sep | C26: =SUMIFS('90_Origen_Caja_2025'!$F$3:$F$542,'90_Origen_Caja_2025'!$A$3:$A$542,"Perú",'90_Origen_Caja_2025'!$C$3:$C$542,9,'90_Origen_Caja_2025'!$E$3:$E$542,"Caja Inicial") -> 255462.54 | D26: =SUMIFS('90_Origen_Caja_2025'!$F$3:$F$542,'90_Origen_Caja_2025'!$A$3:$A$542,"Perú",'90_Origen_Caja_2025'!$C$3:$C$542,9,'90_Origen_Caja_2025'!$E$3:$E$542,"Ingresos Op.")+SUMIFS('90_Origen_Caja_2025'!$F$3:$F$542,'90_Origen_Caja_2025'!$A$3:$A$542,"Perú",'90_Origen_Caja_2025'!$C$3:$C$542,9,'90_Origen_Caja_2025'!$E$3:$E$542,"Otros Ingresos") -> 135170 | E26: =SUMIFS('90_Origen_Caja_2025'!$F$3:$F$542,'90_Origen_Caja_2025'!$A$3:$A$542,"Perú",'90_Origen_Caja_2025'!$C$3:$C$542,9,'90_Origen_Caja_2025'!$E$3:$E$542,"Costos Op.")+SUMIFS('90_Origen_Caja_2025'!$F$3:$F$542,'90_Origen_Caja_2025'!$A$3:$A$542,"Perú",'90_Origen_Caja_2025'!$C$3:$C$542,9,'90_Origen_Caja_2025'!$E$3:$E$542,"Costos Admin.")+SUMIFS('90_Origen_Caja_2025'!$F$3:$F$542,'90_Origen_Caja_2025'!$A$3:$A$542,"Perú",'90_Origen_Caja_2025'!$C$3:$C$542,9,'90_Origen_Caja_2025'!$E$3:$E$542,"Activo")+SUMIFS('90_Origen_Caja_2025'!$F$3:$F$542,'90_Origen_Caja_2025'!$A$3:$A$542,"Perú",'90_Origen_Caja_2025'!$C$3:$C$542,9,'90_Origen_Caja_2025'!$E$3:$E$542,"Egresos No Op.")+SUMIFS('90_Origen_Caja_2025'!$F$3:$F$542,'90_Origen_Caja_2025'!$A$3:$A$542,"Perú",'90_Origen_Caja_2025'!$C$3:$C$542,9,'90_Origen_Caja_2025'!$E$3:$E$542,"Pagos Cta.Cte.") -> 173873 | F26: =C26+D26-E26 -> 216759.54 | G26: =D26-E26 -> -38703
A27: Perú | B27: oct | C27: =SUMIFS('90_Origen_Caja_2025'!$F$3:$F$542,'90_Origen_Caja_2025'!$A$3:$A$542,"Perú",'90_Origen_Caja_2025'!$C$3:$C$542,10,'90_Origen_Caja_2025'!$E$3:$E$542,"Caja Inicial") -> 216759.54 | D27: =SUMIFS('90_Origen_Caja_2025'!$F$3:$F$542,'90_Origen_Caja_2025'!$A$3:$A$542,"Perú",'90_Origen_Caja_2025'!$C$3:$C$542,10,'90_Origen_Caja_2025'!$E$3:$E$542,"Ingresos Op.")+SUMIFS('90_Origen_Caja_2025'!$F$3:$F$542,'90_Origen_Caja_2025'!$A$3:$A$542,"Perú",'90_Origen_Caja_2025'!$C$3:$C$542,10,'90_Origen_Caja_2025'!$E$3:$E$542,"Otros Ingresos") -> 307566 | E27: =SUMIFS('90_Origen_Caja_2025'!$F$3:$F$542,'90_Origen_Caja_2025'!$A$3:$A$542,"Perú",'90_Origen_Caja_2025'!$C$3:$C$542,10,'90_Origen_Caja_2025'!$E$3:$E$542,"Costos Op.")+SUMIFS('90_Origen_Caja_2025'!$F$3:$F$542,'90_Origen_Caja_2025'!$A$3:$A$542,"Perú",'90_Origen_Caja_2025'!$C$3:$C$542,10,'90_Origen_Caja_2025'!$E$3:$E$542,"Costos Admin.")+SUMIFS('90_Origen_Caja_2025'!$F$3:$F$542,'90_Origen_Caja_2025'!$A$3:$A$542,"Perú",'90_Origen_Caja_2025'!$C$3:$C$542,10,'90_Origen_Caja_2025'!$E$3:$E$542,"Activo")+SUMIFS('90_Origen_Caja_2025'!$F$3:$F$542,'90_Origen_Caja_2025'!$A$3:$A$542,"Perú",'90_Origen_Caja_2025'!$C$3:$C$542,10,'90_Origen_Caja_2025'!$E$3:$E$542,"Egresos No Op.")+SUMIFS('90_Origen_Caja_2025'!$F$3:$F$542,'90_Origen_Caja_2025'!$A$3:$A$542,"Perú",'90_Origen_Caja_2025'!$C$3:$C$542,10,'90_Origen_Caja_2025'!$E$3:$E$542,"Pagos Cta.Cte.") -> 294213 | F27: =C27+D27-E27 -> 230112.54 | G27: =D27-E27 -> 13353
A28: Perú | B28: nov | C28: =SUMIFS('90_Origen_Caja_2025'!$F$3:$F$542,'90_Origen_Caja_2025'!$A$3:$A$542,"Perú",'90_Origen_Caja_2025'!$C$3:$C$542,11,'90_Origen_Caja_2025'!$E$3:$E$542,"Caja Inicial") -> 230112.54 | D28: =SUMIFS('90_Origen_Caja_2025'!$F$3:$F$542,'90_Origen_Caja_2025'!$A$3:$A$542,"Perú",'90_Origen_Caja_2025'!$C$3:$C$542,11,'90_Origen_Caja_2025'!$E$3:$E$542,"Ingresos Op.")+SUMIFS('90_Origen_Caja_2025'!$F$3:$F$542,'90_Origen_Caja_2025'!$A$3:$A$542,"Perú",'90_Origen_Caja_2025'!$C$3:$C$542,11,'90_Origen_Caja_2025'!$E$3:$E$542,"Otros Ingresos") -> 201203 | E28: =SUMIFS('90_Origen_Caja_2025'!$F$3:$F$542,'90_Origen_Caja_2025'!$A$3:$A$542,"Perú",'90_Origen_Caja_2025'!$C$3:$C$542,11,'90_Origen_Caja_2025'!$E$3:$E$542,"Costos Op.")+SUMIFS('90_Origen_Caja_2025'!$F$3:$F$542,'90_Origen_Caja_2025'!$A$3:$A$542,"Perú",'90_Origen_Caja_2025'!$C$3:$C$542,11,'90_Origen_Caja_2025'!$E$3:$E$542,"Costos Admin.")+SUMIFS('90_Origen_Caja_2025'!$F$3:$F$542,'90_Origen_Caja_2025'!$A$3:$A$542,"Perú",'90_Origen_Caja_2025'!$C$3:$C$542,11,'90_Origen_Caja_2025'!$E$3:$E$542,"Activo")+SUMIFS('90_Origen_Caja_2025'!$F$3:$F$542,'90_Origen_Caja_2025'!$A$3:$A$542,"Perú",'90_Origen_Caja_2025'!$C$3:$C$542,11,'90_Origen_Caja_2025'!$E$3:$E$542,"Egresos No Op.")+SUMIFS('90_Origen_Caja_2025'!$F$3:$F$542,'90_Origen_Caja_2025'!$A$3:$A$542,"Perú",'90_Origen_Caja_2025'!$C$3:$C$542,11,'90_Origen_Caja_2025'!$E$3:$E$542,"Pagos Cta.Cte.") -> 325200.64 | F28: =C28+D28-E28 -> 106114.9 | G28: =D28-E28 -> -123997.64
A29: Perú | B29: dic | C29: =SUMIFS('90_Origen_Caja_2025'!$F$3:$F$542,'90_Origen_Caja_2025'!$A$3:$A$542,"Perú",'90_Origen_Caja_2025'!$C$3:$C$542,12,'90_Origen_Caja_2025'!$E$3:$E$542,"Caja Inicial") -> 106114.9 | D29: =SUMIFS('90_Origen_Caja_2025'!$F$3:$F$542,'90_Origen_Caja_2025'!$A$3:$A$542,"Perú",'90_Origen_Caja_2025'!$C$3:$C$542,12,'90_Origen_Caja_2025'!$E$3:$E$542,"Ingresos Op.")+SUMIFS('90_Origen_Caja_2025'!$F$3:$F$542,'90_Origen_Caja_2025'!$A$3:$A$542,"Perú",'90_Origen_Caja_2025'!$C$3:$C$542,12,'90_Origen_Caja_2025'!$E$3:$E$542,"Otros Ingresos") -> 345317 | E29: =SUMIFS('90_Origen_Caja_2025'!$F$3:$F$542,'90_Origen_Caja_2025'!$A$3:$A$542,"Perú",'90_Origen_Caja_2025'!$C$3:$C$542,12,'90_Origen_Caja_2025'!$E$3:$E$542,"Costos Op.")+SUMIFS('90_Origen_Caja_2025'!$F$3:$F$542,'90_Origen_Caja_2025'!$A$3:$A$542,"Perú",'90_Origen_Caja_2025'!$C$3:$C$542,12,'90_Origen_Caja_2025'!$E$3:$E$542,"Costos Admin.")+SUMIFS('90_Origen_Caja_2025'!$F$3:$F$542,'90_Origen_Caja_2025'!$A$3:$A$542,"Perú",'90_Origen_Caja_2025'!$C$3:$C$542,12,'90_Origen_Caja_2025'!$E$3:$E$542,"Activo")+SUMIFS('90_Origen_Caja_2025'!$F$3:$F$542,'90_Origen_Caja_2025'!$A$3:$A$542,"Perú",'90_Origen_Caja_2025'!$C$3:$C$542,12,'90_Origen_Caja_2025'!$E$3:$E$542,"Egresos No Op.")+SUMIFS('90_Origen_Caja_2025'!$F$3:$F$542,'90_Origen_Caja_2025'!$A$3:$A$542,"Perú",'90_Origen_Caja_2025'!$C$3:$C$542,12,'90_Origen_Caja_2025'!$E$3:$E$542,"Pagos Cta.Cte.") -> 370614 | F29: =C29+D29-E29 -> 80817.9 | G29: =D29-E29 -> -25297
A30: Brasil | B30: ene | C30: =SUMIFS('90_Origen_Caja_2025'!$F$3:$F$542,'90_Origen_Caja_2025'!$A$3:$A$542,"Brasil",'90_Origen_Caja_2025'!$C$3:$C$542,1,'90_Origen_Caja_2025'!$E$3:$E$542,"Caja Inicial") -> 9622.33 | D30: =SUMIFS('90_Origen_Caja_2025'!$F$3:$F$542,'90_Origen_Caja_2025'!$A$3:$A$542,"Brasil",'90_Origen_Caja_2025'!$C$3:$C$542,1,'90_Origen_Caja_2025'!$E$3:$E$542,"Ingresos Op.")+SUMIFS('90_Origen_Caja_2025'!$F$3:$F$542,'90_Origen_Caja_2025'!$A$3:$A$542,"Brasil",'90_Origen_Caja_2025'!$C$3:$C$542,1,'90_Origen_Caja_2025'!$E$3:$E$542,"Otros Ingresos") -> 86890 | E30: =SUMIFS('90_Origen_Caja_2025'!$F$3:$F$542,'90_Origen_Caja_2025'!$A$3:$A$542,"Brasil",'90_Origen_Caja_2025'!$C$3:$C$542,1,'90_Origen_Caja_2025'!$E$3:$E$542,"Costos Op.")+SUMIFS('90_Origen_Caja_2025'!$F$3:$F$542,'90_Origen_Caja_2025'!$A$3:$A$542,"Brasil",'90_Origen_Caja_2025'!$C$3:$C$542,1,'90_Origen_Caja_2025'!$E$3:$E$542,"Costos Admin.")+SUMIFS('90_Origen_Caja_2025'!$F$3:$F$542,'90_Origen_Caja_2025'!$A$3:$A$542,"Brasil",'90_Origen_Caja_2025'!$C$3:$C$542,1,'90_Origen_Caja_2025'!$E$3:$E$542,"Activo")+SUMIFS('90_Origen_Caja_2025'!$F$3:$F$542,'90_Origen_Caja_2025'!$A$3:$A$542,"Brasil",'90_Origen_Caja_2025'!$C$3:$C$542,1,'90_Origen_Caja_2025'!$E$3:$E$542,"Egresos No Op.")+SUMIFS('90_Origen_Caja_2025'!$F$3:$F$542,'90_Origen_Caja_2025'!$A$3:$A$542,"Brasil",'90_Origen_Caja_2025'!$C$3:$C$542,1,'90_Origen_Caja_2025'!$E$3:$E$542,"Pagos Cta.Cte.") -> 34980 | F30: =C30+D30-E30 -> 61532.33 | G30: =D30-E30 -> 51910
A31: Brasil | B31: feb | C31: =SUMIFS('90_Origen_Caja_2025'!$F$3:$F$542,'90_Origen_Caja_2025'!$A$3:$A$542,"Brasil",'90_Origen_Caja_2025'!$C$3:$C$542,2,'90_Origen_Caja_2025'!$E$3:$E$542,"Caja Inicial") -> 61532.33 | D31: =SUMIFS('90_Origen_Caja_2025'!$F$3:$F$542,'90_Origen_Caja_2025'!$A$3:$A$542,"Brasil",'90_Origen_Caja_2025'!$C$3:$C$542,2,'90_Origen_Caja_2025'!$E$3:$E$542,"Ingresos Op.")+SUMIFS('90_Origen_Caja_2025'!$F$3:$F$542,'90_Origen_Caja_2025'!$A$3:$A$542,"Brasil",'90_Origen_Caja_2025'!$C$3:$C$542,2,'90_Origen_Caja_2025'!$E$3:$E$542,"Otros Ingresos") -> 60046 | E31: =SUMIFS('90_Origen_Caja_2025'!$F$3:$F$542,'90_Origen_Caja_2025'!$A$3:$A$542,"Brasil",'90_Origen_Caja_2025'!$C$3:$C$542,2,'90_Origen_Caja_2025'!$E$3:$E$542,"Costos Op.")+SUMIFS('90_Origen_Caja_2025'!$F$3:$F$542,'90_Origen_Caja_2025'!$A$3:$A$542,"Brasil",'90_Origen_Caja_2025'!$C$3:$C$542,2,'90_Origen_Caja_2025'!$E$3:$E$542,"Costos Admin.")+SUMIFS('90_Origen_Caja_2025'!$F$3:$F$542,'90_Origen_Caja_2025'!$A$3:$A$542,"Brasil",'90_Origen_Caja_2025'!$C$3:$C$542,2,'90_Origen_Caja_2025'!$E$3:$E$542,"Activo")+SUMIFS('90_Origen_Caja_2025'!$F$3:$F$542,'90_Origen_Caja_2025'!$A$3:$A$542,"Brasil",'90_Origen_Caja_2025'!$C$3:$C$542,2,'90_Origen_Caja_2025'!$E$3:$E$542,"Egresos No Op.")+SUMIFS('90_Origen_Caja_2025'!$F$3:$F$542,'90_Origen_Caja_2025'!$A$3:$A$542,"Brasil",'90_Origen_Caja_2025'!$C$3:$C$542,2,'90_Origen_Caja_2025'!$E$3:$E$542,"Pagos Cta.Cte.") -> 43055 | F31: =C31+D31-E31 -> 78523.33 | G31: =D31-E31 -> 16991
A32: Brasil | B32: mar | C32: =SUMIFS('90_Origen_Caja_2025'!$F$3:$F$542,'90_Origen_Caja_2025'!$A$3:$A$542,"Brasil",'90_Origen_Caja_2025'!$C$3:$C$542,3,'90_Origen_Caja_2025'!$E$3:$E$542,"Caja Inicial") -> 78523.33 | D32: =SUMIFS('90_Origen_Caja_2025'!$F$3:$F$542,'90_Origen_Caja_2025'!$A$3:$A$542,"Brasil",'90_Origen_Caja_2025'!$C$3:$C$542,3,'90_Origen_Caja_2025'!$E$3:$E$542,"Ingresos Op.")+SUMIFS('90_Origen_Caja_2025'!$F$3:$F$542,'90_Origen_Caja_2025'!$A$3:$A$542,"Brasil",'90_Origen_Caja_2025'!$C$3:$C$542,3,'90_Origen_Caja_2025'!$E$3:$E$542,"Otros Ingresos") -> 96322 | E32: =SUMIFS('90_Origen_Caja_2025'!$F$3:$F$542,'90_Origen_Caja_2025'!$A$3:$A$542,"Brasil",'90_Origen_Caja_2025'!$C$3:$C$542,3,'90_Origen_Caja_2025'!$E$3:$E$542,"Costos Op.")+SUMIFS('90_Origen_Caja_2025'!$F$3:$F$542,'90_Origen_Caja_2025'!$A$3:$A$542,"Brasil",'90_Origen_Caja_2025'!$C$3:$C$542,3,'90_Origen_Caja_2025'!$E$3:$E$542,"Costos Admin.")+SUMIFS('90_Origen_Caja_2025'!$F$3:$F$542,'90_Origen_Caja_2025'!$A$3:$A$542,"Brasil",'90_Origen_Caja_2025'!$C$3:$C$542,3,'90_Origen_Caja_2025'!$E$3:$E$542,"Activo")+SUMIFS('90_Origen_Caja_2025'!$F$3:$F$542,'90_Origen_Caja_2025'!$A$3:$A$542,"Brasil",'90_Origen_Caja_2025'!$C$3:$C$542,3,'90_Origen_Caja_2025'!$E$3:$E$542,"Egresos No Op.")+SUMIFS('90_Origen_Caja_2025'!$F$3:$F$542,'90_Origen_Caja_2025'!$A$3:$A$542,"Brasil",'90_Origen_Caja_2025'!$C$3:$C$542,3,'90_Origen_Caja_2025'!$E$3:$E$542,"Pagos Cta.Cte.") -> 34370 | F32: =C32+D32-E32 -> 140475.33 | G32: =D32-E32 -> 61952
A33: Brasil | B33: abr | C33: =SUMIFS('90_Origen_Caja_2025'!$F$3:$F$542,'90_Origen_Caja_2025'!$A$3:$A$542,"Brasil",'90_Origen_Caja_2025'!$C$3:$C$542,4,'90_Origen_Caja_2025'!$E$3:$E$542,"Caja Inicial") -> 140475.33 | D33: =SUMIFS('90_Origen_Caja_2025'!$F$3:$F$542,'90_Origen_Caja_2025'!$A$3:$A$542,"Brasil",'90_Origen_Caja_2025'!$C$3:$C$542,4,'90_Origen_Caja_2025'!$E$3:$E$542,"Ingresos Op.")+SUMIFS('90_Origen_Caja_2025'!$F$3:$F$542,'90_Origen_Caja_2025'!$A$3:$A$542,"Brasil",'90_Origen_Caja_2025'!$C$3:$C$542,4,'90_Origen_Caja_2025'!$E$3:$E$542,"Otros Ingresos") -> 97209.7 | E33: =SUMIFS('90_Origen_Caja_2025'!$F$3:$F$542,'90_Origen_Caja_2025'!$A$3:$A$542,"Brasil",'90_Origen_Caja_2025'!$C$3:$C$542,4,'90_Origen_Caja_2025'!$E$3:$E$542,"Costos Op.")+SUMIFS('90_Origen_Caja_2025'!$F$3:$F$542,'90_Origen_Caja_2025'!$A$3:$A$542,"Brasil",'90_Origen_Caja_2025'!$C$3:$C$542,4,'90_Origen_Caja_2025'!$E$3:$E$542,"Costos Admin.")+SUMIFS('90_Origen_Caja_2025'!$F$3:$F$542,'90_Origen_Caja_2025'!$A$3:$A$542,"Brasil",'90_Origen_Caja_2025'!$C$3:$C$542,4,'90_Origen_Caja_2025'!$E$3:$E$542,"Activo")+SUMIFS('90_Origen_Caja_2025'!$F$3:$F$542,'90_Origen_Caja_2025'!$A$3:$A$542,"Brasil",'90_Origen_Caja_2025'!$C$3:$C$542,4,'90_Origen_Caja_2025'!$E$3:$E$542,"Egresos No Op.")+SUMIFS('90_Origen_Caja_2025'!$F$3:$F$542,'90_Origen_Caja_2025'!$A$3:$A$542,"Brasil",'90_Origen_Caja_2025'!$C$3:$C$542,4,'90_Origen_Caja_2025'!$E$3:$E$542,"Pagos Cta.Cte.") -> 78402.4 | F33: =C33+D33-E33 -> 159282.63 | G33: =D33-E33 -> 18807.3
A34: Brasil | B34: may | C34: =SUMIFS('90_Origen_Caja_2025'!$F$3:$F$542,'90_Origen_Caja_2025'!$A$3:$A$542,"Brasil",'90_Origen_Caja_2025'!$C$3:$C$542,5,'90_Origen_Caja_2025'!$E$3:$E$542,"Caja Inicial") -> 159282.63 | D34: =SUMIFS('90_Origen_Caja_2025'!$F$3:$F$542,'90_Origen_Caja_2025'!$A$3:$A$542,"Brasil",'90_Origen_Caja_2025'!$C$3:$C$542,5,'90_Origen_Caja_2025'!$E$3:$E$542,"Ingresos Op.")+SUMIFS('90_Origen_Caja_2025'!$F$3:$F$542,'90_Origen_Caja_2025'!$A$3:$A$542,"Brasil",'90_Origen_Caja_2025'!$C$3:$C$542,5,'90_Origen_Caja_2025'!$E$3:$E$542,"Otros Ingresos") -> 38600 | E34: =SUMIFS('90_Origen_Caja_2025'!$F$3:$F$542,'90_Origen_Caja_2025'!$A$3:$A$542,"Brasil",'90_Origen_Caja_2025'!$C$3:$C$542,5,'90_Origen_Caja_2025'!$E$3:$E$542,"Costos Op.")+SUMIFS('90_Origen_Caja_2025'!$F$3:$F$542,'90_Origen_Caja_2025'!$A$3:$A$542,"Brasil",'90_Origen_Caja_2025'!$C$3:$C$542,5,'90_Origen_Caja_2025'!$E$3:$E$542,"Costos Admin.")+SUMIFS('90_Origen_Caja_2025'!$F$3:$F$542,'90_Origen_Caja_2025'!$A$3:$A$542,"Brasil",'90_Origen_Caja_2025'!$C$3:$C$542,5,'90_Origen_Caja_2025'!$E$3:$E$542,"Activo")+SUMIFS('90_Origen_Caja_2025'!$F$3:$F$542,'90_Origen_Caja_2025'!$A$3:$A$542,"Brasil",'90_Origen_Caja_2025'!$C$3:$C$542,5,'90_Origen_Caja_2025'!$E$3:$E$542,"Egresos No Op.")+SUMIFS('90_Origen_Caja_2025'!$F$3:$F$542,'90_Origen_Caja_2025'!$A$3:$A$542,"Brasil",'90_Origen_Caja_2025'!$C$3:$C$542,5,'90_Origen_Caja_2025'!$E$3:$E$542,"Pagos Cta.Cte.") -> 176450 | F34: =C34+D34-E34 -> 21432.63 | G34: =D34-E34 -> -137850
A35: Brasil | B35: jun | C35: =SUMIFS('90_Origen_Caja_2025'!$F$3:$F$542,'90_Origen_Caja_2025'!$A$3:$A$542,"Brasil",'90_Origen_Caja_2025'!$C$3:$C$542,6,'90_Origen_Caja_2025'!$E$3:$E$542,"Caja Inicial") -> 21432.63 | D35: =SUMIFS('90_Origen_Caja_2025'!$F$3:$F$542,'90_Origen_Caja_2025'!$A$3:$A$542,"Brasil",'90_Origen_Caja_2025'!$C$3:$C$542,6,'90_Origen_Caja_2025'!$E$3:$E$542,"Ingresos Op.")+SUMIFS('90_Origen_Caja_2025'!$F$3:$F$542,'90_Origen_Caja_2025'!$A$3:$A$542,"Brasil",'90_Origen_Caja_2025'!$C$3:$C$542,6,'90_Origen_Caja_2025'!$E$3:$E$542,"Otros Ingresos") -> 66563 | E35: =SUMIFS('90_Origen_Caja_2025'!$F$3:$F$542,'90_Origen_Caja_2025'!$A$3:$A$542,"Brasil",'90_Origen_Caja_2025'!$C$3:$C$542,6,'90_Origen_Caja_2025'!$E$3:$E$542,"Costos Op.")+SUMIFS('90_Origen_Caja_2025'!$F$3:$F$542,'90_Origen_Caja_2025'!$A$3:$A$542,"Brasil",'90_Origen_Caja_2025'!$C$3:$C$542,6,'90_Origen_Caja_2025'!$E$3:$E$542,"Costos Admin.")+SUMIFS('90_Origen_Caja_2025'!$F$3:$F$542,'90_Origen_Caja_2025'!$A$3:$A$542,"Brasil",'90_Origen_Caja_2025'!$C$3:$C$542,6,'90_Origen_Caja_2025'!$E$3:$E$542,"Activo")+SUMIFS('90_Origen_Caja_2025'!$F$3:$F$542,'90_Origen_Caja_2025'!$A$3:$A$542,"Brasil",'90_Origen_Caja_2025'!$C$3:$C$542,6,'90_Origen_Caja_2025'!$E$3:$E$542,"Egresos No Op.")+SUMIFS('90_Origen_Caja_2025'!$F$3:$F$542,'90_Origen_Caja_2025'!$A$3:$A$542,"Brasil",'90_Origen_Caja_2025'!$C$3:$C$542,6,'90_Origen_Caja_2025'!$E$3:$E$542,"Pagos Cta.Cte.") -> 88740 | F35: =C35+D35-E35 -> -744.37 | G35: =D35-E35 -> -22177
A36: Brasil | B36: jul | C36: =SUMIFS('90_Origen_Caja_2025'!$F$3:$F$542,'90_Origen_Caja_2025'!$A$3:$A$542,"Brasil",'90_Origen_Caja_2025'!$C$3:$C$542,7,'90_Origen_Caja_2025'!$E$3:$E$542,"Caja Inicial") -> -744.37 | D36: =SUMIFS('90_Origen_Caja_2025'!$F$3:$F$542,'90_Origen_Caja_2025'!$A$3:$A$542,"Brasil",'90_Origen_Caja_2025'!$C$3:$C$542,7,'90_Origen_Caja_2025'!$E$3:$E$542,"Ingresos Op.")+SUMIFS('90_Origen_Caja_2025'!$F$3:$F$542,'90_Origen_Caja_2025'!$A$3:$A$542,"Brasil",'90_Origen_Caja_2025'!$C$3:$C$542,7,'90_Origen_Caja_2025'!$E$3:$E$542,"Otros Ingresos") -> 47717 | E36: =SUMIFS('90_Origen_Caja_2025'!$F$3:$F$542,'90_Origen_Caja_2025'!$A$3:$A$542,"Brasil",'90_Origen_Caja_2025'!$C$3:$C$542,7,'90_Origen_Caja_2025'!$E$3:$E$542,"Costos Op.")+SUMIFS('90_Origen_Caja_2025'!$F$3:$F$542,'90_Origen_Caja_2025'!$A$3:$A$542,"Brasil",'90_Origen_Caja_2025'!$C$3:$C$542,7,'90_Origen_Caja_2025'!$E$3:$E$542,"Costos Admin.")+SUMIFS('90_Origen_Caja_2025'!$F$3:$F$542,'90_Origen_Caja_2025'!$A$3:$A$542,"Brasil",'90_Origen_Caja_2025'!$C$3:$C$542,7,'90_Origen_Caja_2025'!$E$3:$E$542,"Activo")+SUMIFS('90_Origen_Caja_2025'!$F$3:$F$542,'90_Origen_Caja_2025'!$A$3:$A$542,"Brasil",'90_Origen_Caja_2025'!$C$3:$C$542,7,'90_Origen_Caja_2025'!$E$3:$E$542,"Egresos No Op.")+SUMIFS('90_Origen_Caja_2025'!$F$3:$F$542,'90_Origen_Caja_2025'!$A$3:$A$542,"Brasil",'90_Origen_Caja_2025'!$C$3:$C$542,7,'90_Origen_Caja_2025'!$E$3:$E$542,"Pagos Cta.Cte.") -> 49549 | F36: =C36+D36-E36 -> -2576.37 | G36: =D36-E36 -> -1832
A37: Brasil | B37: ago | C37: =SUMIFS('90_Origen_Caja_2025'!$F$3:$F$542,'90_Origen_Caja_2025'!$A$3:$A$542,"Brasil",'90_Origen_Caja_2025'!$C$3:$C$542,8,'90_Origen_Caja_2025'!$E$3:$E$542,"Caja Inicial") -> -2576.37 | D37: =SUMIFS('90_Origen_Caja_2025'!$F$3:$F$542,'90_Origen_Caja_2025'!$A$3:$A$542,"Brasil",'90_Origen_Caja_2025'!$C$3:$C$542,8,'90_Origen_Caja_2025'!$E$3:$E$542,"Ingresos Op.")+SUMIFS('90_Origen_Caja_2025'!$F$3:$F$542,'90_Origen_Caja_2025'!$A$3:$A$542,"Brasil",'90_Origen_Caja_2025'!$C$3:$C$542,8,'90_Origen_Caja_2025'!$E$3:$E$542,"Otros Ingresos") -> 119652 | E37: =SUMIFS('90_Origen_Caja_2025'!$F$3:$F$542,'90_Origen_Caja_2025'!$A$3:$A$542,"Brasil",'90_Origen_Caja_2025'!$C$3:$C$542,8,'90_Origen_Caja_2025'!$E$3:$E$542,"Costos Op.")+SUMIFS('90_Origen_Caja_2025'!$F$3:$F$542,'90_Origen_Caja_2025'!$A$3:$A$542,"Brasil",'90_Origen_Caja_2025'!$C$3:$C$542,8,'90_Origen_Caja_2025'!$E$3:$E$542,"Costos Admin.")+SUMIFS('90_Origen_Caja_2025'!$F$3:$F$542,'90_Origen_Caja_2025'!$A$3:$A$542,"Brasil",'90_Origen_Caja_2025'!$C$3:$C$542,8,'90_Origen_Caja_2025'!$E$3:$E$542,"Activo")+SUMIFS('90_Origen_Caja_2025'!$F$3:$F$542,'90_Origen_Caja_2025'!$A$3:$A$542,"Brasil",'90_Origen_Caja_2025'!$C$3:$C$542,8,'90_Origen_Caja_2025'!$E$3:$E$542,"Egresos No Op.")+SUMIFS('90_Origen_Caja_2025'!$F$3:$F$542,'90_Origen_Caja_2025'!$A$3:$A$542,"Brasil",'90_Origen_Caja_2025'!$C$3:$C$542,8,'90_Origen_Caja_2025'!$E$3:$E$542,"Pagos Cta.Cte.") -> 49036 | F37: =C37+D37-E37 -> 68039.63 | G37: =D37-E37 -> 70616
A38: Brasil | B38: sep | C38: =SUMIFS('90_Origen_Caja_2025'!$F$3:$F$542,'90_Origen_Caja_2025'!$A$3:$A$542,"Brasil",'90_Origen_Caja_2025'!$C$3:$C$542,9,'90_Origen_Caja_2025'!$E$3:$E$542,"Caja Inicial") -> 68039.63 | D38: =SUMIFS('90_Origen_Caja_2025'!$F$3:$F$542,'90_Origen_Caja_2025'!$A$3:$A$542,"Brasil",'90_Origen_Caja_2025'!$C$3:$C$542,9,'90_Origen_Caja_2025'!$E$3:$E$542,"Ingresos Op.")+SUMIFS('90_Origen_Caja_2025'!$F$3:$F$542,'90_Origen_Caja_2025'!$A$3:$A$542,"Brasil",'90_Origen_Caja_2025'!$C$3:$C$542,9,'90_Origen_Caja_2025'!$E$3:$E$542,"Otros Ingresos") -> 203588 | E38: =SUMIFS('90_Origen_Caja_2025'!$F$3:$F$542,'90_Origen_Caja_2025'!$A$3:$A$542,"Brasil",'90_Origen_Caja_2025'!$C$3:$C$542,9,'90_Origen_Caja_2025'!$E$3:$E$542,"Costos Op.")+SUMIFS('90_Origen_Caja_2025'!$F$3:$F$542,'90_Origen_Caja_2025'!$A$3:$A$542,"Brasil",'90_Origen_Caja_2025'!$C$3:$C$542,9,'90_Origen_Caja_2025'!$E$3:$E$542,"Costos Admin.")+SUMIFS('90_Origen_Caja_2025'!$F$3:$F$542,'90_Origen_Caja_2025'!$A$3:$A$542,"Brasil",'90_Origen_Caja_2025'!$C$3:$C$542,9,'90_Origen_Caja_2025'!$E$3:$E$542,"Activo")+SUMIFS('90_Origen_Caja_2025'!$F$3:$F$542,'90_Origen_Caja_2025'!$A$3:$A$542,"Brasil",'90_Origen_Caja_2025'!$C$3:$C$542,9,'90_Origen_Caja_2025'!$E$3:$E$542,"Egresos No Op.")+SUMIFS('90_Origen_Caja_2025'!$F$3:$F$542,'90_Origen_Caja_2025'!$A$3:$A$542,"Brasil",'90_Origen_Caja_2025'!$C$3:$C$542,9,'90_Origen_Caja_2025'!$E$3:$E$542,"Pagos Cta.Cte.") -> 99306 | F38: =C38+D38-E38 -> 172321.63 | G38: =D38-E38 -> 104282
A39: Brasil | B39: oct | C39: =SUMIFS('90_Origen_Caja_2025'!$F$3:$F$542,'90_Origen_Caja_2025'!$A$3:$A$542,"Brasil",'90_Origen_Caja_2025'!$C$3:$C$542,10,'90_Origen_Caja_2025'!$E$3:$E$542,"Caja Inicial") -> 179973.63 | D39: =SUMIFS('90_Origen_Caja_2025'!$F$3:$F$542,'90_Origen_Caja_2025'!$A$3:$A$542,"Brasil",'90_Origen_Caja_2025'!$C$3:$C$542,10,'90_Origen_Caja_2025'!$E$3:$E$542,"Ingresos Op.")+SUMIFS('90_Origen_Caja_2025'!$F$3:$F$542,'90_Origen_Caja_2025'!$A$3:$A$542,"Brasil",'90_Origen_Caja_2025'!$C$3:$C$542,10,'90_Origen_Caja_2025'!$E$3:$E$542,"Otros Ingresos") -> 326865 | E39: =SUMIFS('90_Origen_Caja_2025'!$F$3:$F$542,'90_Origen_Caja_2025'!$A$3:$A$542,"Brasil",'90_Origen_Caja_2025'!$C$3:$C$542,10,'90_Origen_Caja_2025'!$E$3:$E$542,"Costos Op.")+SUMIFS('90_Origen_Caja_2025'!$F$3:$F$542,'90_Origen_Caja_2025'!$A$3:$A$542,"Brasil",'90_Origen_Caja_2025'!$C$3:$C$542,10,'90_Origen_Caja_2025'!$E$3:$E$542,"Costos Admin.")+SUMIFS('90_Origen_Caja_2025'!$F$3:$F$542,'90_Origen_Caja_2025'!$A$3:$A$542,"Brasil",'90_Origen_Caja_2025'!$C$3:$C$542,10,'90_Origen_Caja_2025'!$E$3:$E$542,"Activo")+SUMIFS('90_Origen_Caja_2025'!$F$3:$F$542,'90_Origen_Caja_2025'!$A$3:$A$542,"Brasil",'90_Origen_Caja_2025'!$C$3:$C$542,10,'90_Origen_Caja_2025'!$E$3:$E$542,"Egresos No Op.")+SUMIFS('90_Origen_Caja_2025'!$F$3:$F$542,'90_Origen_Caja_2025'!$A$3:$A$542,"Brasil",'90_Origen_Caja_2025'!$C$3:$C$542,10,'90_Origen_Caja_2025'!$E$3:$E$542,"Pagos Cta.Cte.") -> 82009 | F39: =C39+D39-E39 -> 424829.63 | G39: =D39-E39 -> 244856
A40: Brasil | B40: nov | C40: =SUMIFS('90_Origen_Caja_2025'!$F$3:$F$542,'90_Origen_Caja_2025'!$A$3:$A$542,"Brasil",'90_Origen_Caja_2025'!$C$3:$C$542,11,'90_Origen_Caja_2025'!$E$3:$E$542,"Caja Inicial") -> 426650.63 | D40: =SUMIFS('90_Origen_Caja_2025'!$F$3:$F$542,'90_Origen_Caja_2025'!$A$3:$A$542,"Brasil",'90_Origen_Caja_2025'!$C$3:$C$542,11,'90_Origen_Caja_2025'!$E$3:$E$542,"Ingresos Op.")+SUMIFS('90_Origen_Caja_2025'!$F$3:$F$542,'90_Origen_Caja_2025'!$A$3:$A$542,"Brasil",'90_Origen_Caja_2025'!$C$3:$C$542,11,'90_Origen_Caja_2025'!$E$3:$E$542,"Otros Ingresos") -> 241225 | E40: =SUMIFS('90_Origen_Caja_2025'!$F$3:$F$542,'90_Origen_Caja_2025'!$A$3:$A$542,"Brasil",'90_Origen_Caja_2025'!$C$3:$C$542,11,'90_Origen_Caja_2025'!$E$3:$E$542,"Costos Op.")+SUMIFS('90_Origen_Caja_2025'!$F$3:$F$542,'90_Origen_Caja_2025'!$A$3:$A$542,"Brasil",'90_Origen_Caja_2025'!$C$3:$C$542,11,'90_Origen_Caja_2025'!$E$3:$E$542,"Costos Admin.")+SUMIFS('90_Origen_Caja_2025'!$F$3:$F$542,'90_Origen_Caja_2025'!$A$3:$A$542,"Brasil",'90_Origen_Caja_2025'!$C$3:$C$542,11,'90_Origen_Caja_2025'!$E$3:$E$542,"Activo")+SUMIFS('90_Origen_Caja_2025'!$F$3:$F$542,'90_Origen_Caja_2025'!$A$3:$A$542,"Brasil",'90_Origen_Caja_2025'!$C$3:$C$542,11,'90_Origen_Caja_2025'!$E$3:$E$542,"Egresos No Op.")+SUMIFS('90_Origen_Caja_2025'!$F$3:$F$542,'90_Origen_Caja_2025'!$A$3:$A$542,"Brasil",'90_Origen_Caja_2025'!$C$3:$C$542,11,'90_Origen_Caja_2025'!$E$3:$E$542,"Pagos Cta.Cte.") -> 384296 | F40: =C40+D40-E40 -> 283579.63 | G40: =D40-E40 -> -143071
A41: Brasil | B41: dic | C41: =SUMIFS('90_Origen_Caja_2025'!$F$3:$F$542,'90_Origen_Caja_2025'!$A$3:$A$542,"Brasil",'90_Origen_Caja_2025'!$C$3:$C$542,12,'90_Origen_Caja_2025'!$E$3:$E$542,"Caja Inicial") -> 283579.63 | D41: =SUMIFS('90_Origen_Caja_2025'!$F$3:$F$542,'90_Origen_Caja_2025'!$A$3:$A$542,"Brasil",'90_Origen_Caja_2025'!$C$3:$C$542,12,'90_Origen_Caja_2025'!$E$3:$E$542,"Ingresos Op.")+SUMIFS('90_Origen_Caja_2025'!$F$3:$F$542,'90_Origen_Caja_2025'!$A$3:$A$542,"Brasil",'90_Origen_Caja_2025'!$C$3:$C$542,12,'90_Origen_Caja_2025'!$E$3:$E$542,"Otros Ingresos") -> 224116.51 | E41: =SUMIFS('90_Origen_Caja_2025'!$F$3:$F$542,'90_Origen_Caja_2025'!$A$3:$A$542,"Brasil",'90_Origen_Caja_2025'!$C$3:$C$542,12,'90_Origen_Caja_2025'!$E$3:$E$542,"Costos Op.")+SUMIFS('90_Origen_Caja_2025'!$F$3:$F$542,'90_Origen_Caja_2025'!$A$3:$A$542,"Brasil",'90_Origen_Caja_2025'!$C$3:$C$542,12,'90_Origen_Caja_2025'!$E$3:$E$542,"Costos Admin.")+SUMIFS('90_Origen_Caja_2025'!$F$3:$F$542,'90_Origen_Caja_2025'!$A$3:$A$542,"Brasil",'90_Origen_Caja_2025'!$C$3:$C$542,12,'90_Origen_Caja_2025'!$E$3:$E$542,"Activo")+SUMIFS('90_Origen_Caja_2025'!$F$3:$F$542,'90_Origen_Caja_2025'!$A$3:$A$542,"Brasil",'90_Origen_Caja_2025'!$C$3:$C$542,12,'90_Origen_Caja_2025'!$E$3:$E$542,"Egresos No Op.")+SUMIFS('90_Origen_Caja_2025'!$F$3:$F$542,'90_Origen_Caja_2025'!$A$3:$A$542,"Brasil",'90_Origen_Caja_2025'!$C$3:$C$542,12,'90_Origen_Caja_2025'!$E$3:$E$542,"Pagos Cta.Cte.") -> 118608 | F41: =C41+D41-E41 -> 389088.14 | G41: =D41-E41 -> 105508.51
A42: USA | B42: ene | C42: =SUMIFS('90_Origen_Caja_2025'!$F$3:$F$542,'90_Origen_Caja_2025'!$A$3:$A$542,"USA",'90_Origen_Caja_2025'!$C$3:$C$542,1,'90_Origen_Caja_2025'!$E$3:$E$542,"Caja Inicial") -> 55345 | D42: =SUMIFS('90_Origen_Caja_2025'!$F$3:$F$542,'90_Origen_Caja_2025'!$A$3:$A$542,"USA",'90_Origen_Caja_2025'!$C$3:$C$542,1,'90_Origen_Caja_2025'!$E$3:$E$542,"Ingresos Op.")+SUMIFS('90_Origen_Caja_2025'!$F$3:$F$542,'90_Origen_Caja_2025'!$A$3:$A$542,"USA",'90_Origen_Caja_2025'!$C$3:$C$542,1,'90_Origen_Caja_2025'!$E$3:$E$542,"Otros Ingresos") -> 150453 | E42: =SUMIFS('90_Origen_Caja_2025'!$F$3:$F$542,'90_Origen_Caja_2025'!$A$3:$A$542,"USA",'90_Origen_Caja_2025'!$C$3:$C$542,1,'90_Origen_Caja_2025'!$E$3:$E$542,"Costos Op.")+SUMIFS('90_Origen_Caja_2025'!$F$3:$F$542,'90_Origen_Caja_2025'!$A$3:$A$542,"USA",'90_Origen_Caja_2025'!$C$3:$C$542,1,'90_Origen_Caja_2025'!$E$3:$E$542,"Costos Admin.")+SUMIFS('90_Origen_Caja_2025'!$F$3:$F$542,'90_Origen_Caja_2025'!$A$3:$A$542,"USA",'90_Origen_Caja_2025'!$C$3:$C$542,1,'90_Origen_Caja_2025'!$E$3:$E$542,"Activo")+SUMIFS('90_Origen_Caja_2025'!$F$3:$F$542,'90_Origen_Caja_2025'!$A$3:$A$542,"USA",'90_Origen_Caja_2025'!$C$3:$C$542,1,'90_Origen_Caja_2025'!$E$3:$E$542,"Egresos No Op.")+SUMIFS('90_Origen_Caja_2025'!$F$3:$F$542,'90_Origen_Caja_2025'!$A$3:$A$542,"USA",'90_Origen_Caja_2025'!$C$3:$C$542,1,'90_Origen_Caja_2025'!$E$3:$E$542,"Pagos Cta.Cte.") -> 15 | F42: =C42+D42-E42 -> 205783 | G42: =D42-E42 -> 150438
A43: USA | B43: feb | C43: =SUMIFS('90_Origen_Caja_2025'!$F$3:$F$542,'90_Origen_Caja_2025'!$A$3:$A$542,"USA",'90_Origen_Caja_2025'!$C$3:$C$542,2,'90_Origen_Caja_2025'!$E$3:$E$542,"Caja Inicial") -> 205783 | D43: =SUMIFS('90_Origen_Caja_2025'!$F$3:$F$542,'90_Origen_Caja_2025'!$A$3:$A$542,"USA",'90_Origen_Caja_2025'!$C$3:$C$542,2,'90_Origen_Caja_2025'!$E$3:$E$542,"Ingresos Op.")+SUMIFS('90_Origen_Caja_2025'!$F$3:$F$542,'90_Origen_Caja_2025'!$A$3:$A$542,"USA",'90_Origen_Caja_2025'!$C$3:$C$542,2,'90_Origen_Caja_2025'!$E$3:$E$542,"Otros Ingresos") -> 243465.21 | E43: =SUMIFS('90_Origen_Caja_2025'!$F$3:$F$542,'90_Origen_Caja_2025'!$A$3:$A$542,"USA",'90_Origen_Caja_2025'!$C$3:$C$542,2,'90_Origen_Caja_2025'!$E$3:$E$542,"Costos Op.")+SUMIFS('90_Origen_Caja_2025'!$F$3:$F$542,'90_Origen_Caja_2025'!$A$3:$A$542,"USA",'90_Origen_Caja_2025'!$C$3:$C$542,2,'90_Origen_Caja_2025'!$E$3:$E$542,"Costos Admin.")+SUMIFS('90_Origen_Caja_2025'!$F$3:$F$542,'90_Origen_Caja_2025'!$A$3:$A$542,"USA",'90_Origen_Caja_2025'!$C$3:$C$542,2,'90_Origen_Caja_2025'!$E$3:$E$542,"Activo")+SUMIFS('90_Origen_Caja_2025'!$F$3:$F$542,'90_Origen_Caja_2025'!$A$3:$A$542,"USA",'90_Origen_Caja_2025'!$C$3:$C$542,2,'90_Origen_Caja_2025'!$E$3:$E$542,"Egresos No Op.")+SUMIFS('90_Origen_Caja_2025'!$F$3:$F$542,'90_Origen_Caja_2025'!$A$3:$A$542,"USA",'90_Origen_Caja_2025'!$C$3:$C$542,2,'90_Origen_Caja_2025'!$E$3:$E$542,"Pagos Cta.Cte.") -> 2025 | F43: =C43+D43-E43 -> 447223.21 | G43: =D43-E43 -> 241440.21
A44: USA | B44: mar | C44: =SUMIFS('90_Origen_Caja_2025'!$F$3:$F$542,'90_Origen_Caja_2025'!$A$3:$A$542,"USA",'90_Origen_Caja_2025'!$C$3:$C$542,3,'90_Origen_Caja_2025'!$E$3:$E$542,"Caja Inicial") -> 447223.21 | D44: =SUMIFS('90_Origen_Caja_2025'!$F$3:$F$542,'90_Origen_Caja_2025'!$A$3:$A$542,"USA",'90_Origen_Caja_2025'!$C$3:$C$542,3,'90_Origen_Caja_2025'!$E$3:$E$542,"Ingresos Op.")+SUMIFS('90_Origen_Caja_2025'!$F$3:$F$542,'90_Origen_Caja_2025'!$A$3:$A$542,"USA",'90_Origen_Caja_2025'!$C$3:$C$542,3,'90_Origen_Caja_2025'!$E$3:$E$542,"Otros Ingresos") -> 141526 | E44: =SUMIFS('90_Origen_Caja_2025'!$F$3:$F$542,'90_Origen_Caja_2025'!$A$3:$A$542,"USA",'90_Origen_Caja_2025'!$C$3:$C$542,3,'90_Origen_Caja_2025'!$E$3:$E$542,"Costos Op.")+SUMIFS('90_Origen_Caja_2025'!$F$3:$F$542,'90_Origen_Caja_2025'!$A$3:$A$542,"USA",'90_Origen_Caja_2025'!$C$3:$C$542,3,'90_Origen_Caja_2025'!$E$3:$E$542,"Costos Admin.")+SUMIFS('90_Origen_Caja_2025'!$F$3:$F$542,'90_Origen_Caja_2025'!$A$3:$A$542,"USA",'90_Origen_Caja_2025'!$C$3:$C$542,3,'90_Origen_Caja_2025'!$E$3:$E$542,"Activo")+SUMIFS('90_Origen_Caja_2025'!$F$3:$F$542,'90_Origen_Caja_2025'!$A$3:$A$542,"USA",'90_Origen_Caja_2025'!$C$3:$C$542,3,'90_Origen_Caja_2025'!$E$3:$E$542,"Egresos No Op.")+SUMIFS('90_Origen_Caja_2025'!$F$3:$F$542,'90_Origen_Caja_2025'!$A$3:$A$542,"USA",'90_Origen_Caja_2025'!$C$3:$C$542,3,'90_Origen_Caja_2025'!$E$3:$E$542,"Pagos Cta.Cte.") -> 58728 | F44: =C44+D44-E44 -> 530021.21 | G44: =D44-E44 -> 82798
A45: USA | B45: abr | C45: =SUMIFS('90_Origen_Caja_2025'!$F$3:$F$542,'90_Origen_Caja_2025'!$A$3:$A$542,"USA",'90_Origen_Caja_2025'!$C$3:$C$542,4,'90_Origen_Caja_2025'!$E$3:$E$542,"Caja Inicial") -> 530021.21 | D45: =SUMIFS('90_Origen_Caja_2025'!$F$3:$F$542,'90_Origen_Caja_2025'!$A$3:$A$542,"USA",'90_Origen_Caja_2025'!$C$3:$C$542,4,'90_Origen_Caja_2025'!$E$3:$E$542,"Ingresos Op.")+SUMIFS('90_Origen_Caja_2025'!$F$3:$F$542,'90_Origen_Caja_2025'!$A$3:$A$542,"USA",'90_Origen_Caja_2025'!$C$3:$C$542,4,'90_Origen_Caja_2025'!$E$3:$E$542,"Otros Ingresos") -> 169200 | E45: =SUMIFS('90_Origen_Caja_2025'!$F$3:$F$542,'90_Origen_Caja_2025'!$A$3:$A$542,"USA",'90_Origen_Caja_2025'!$C$3:$C$542,4,'90_Origen_Caja_2025'!$E$3:$E$542,"Costos Op.")+SUMIFS('90_Origen_Caja_2025'!$F$3:$F$542,'90_Origen_Caja_2025'!$A$3:$A$542,"USA",'90_Origen_Caja_2025'!$C$3:$C$542,4,'90_Origen_Caja_2025'!$E$3:$E$542,"Costos Admin.")+SUMIFS('90_Origen_Caja_2025'!$F$3:$F$542,'90_Origen_Caja_2025'!$A$3:$A$542,"USA",'90_Origen_Caja_2025'!$C$3:$C$542,4,'90_Origen_Caja_2025'!$E$3:$E$542,"Activo")+SUMIFS('90_Origen_Caja_2025'!$F$3:$F$542,'90_Origen_Caja_2025'!$A$3:$A$542,"USA",'90_Origen_Caja_2025'!$C$3:$C$542,4,'90_Origen_Caja_2025'!$E$3:$E$542,"Egresos No Op.")+SUMIFS('90_Origen_Caja_2025'!$F$3:$F$542,'90_Origen_Caja_2025'!$A$3:$A$542,"USA",'90_Origen_Caja_2025'!$C$3:$C$542,4,'90_Origen_Caja_2025'!$E$3:$E$542,"Pagos Cta.Cte.") -> 9898 | F45: =C45+D45-E45 -> 689323.21 | G45: =D45-E45 -> 159302
A46: USA | B46: may | C46: =SUMIFS('90_Origen_Caja_2025'!$F$3:$F$542,'90_Origen_Caja_2025'!$A$3:$A$542,"USA",'90_Origen_Caja_2025'!$C$3:$C$542,5,'90_Origen_Caja_2025'!$E$3:$E$542,"Caja Inicial") -> 689323.21 | D46: =SUMIFS('90_Origen_Caja_2025'!$F$3:$F$542,'90_Origen_Caja_2025'!$A$3:$A$542,"USA",'90_Origen_Caja_2025'!$C$3:$C$542,5,'90_Origen_Caja_2025'!$E$3:$E$542,"Ingresos Op.")+SUMIFS('90_Origen_Caja_2025'!$F$3:$F$542,'90_Origen_Caja_2025'!$A$3:$A$542,"USA",'90_Origen_Caja_2025'!$C$3:$C$542,5,'90_Origen_Caja_2025'!$E$3:$E$542,"Otros Ingresos") -> 195090 | E46: =SUMIFS('90_Origen_Caja_2025'!$F$3:$F$542,'90_Origen_Caja_2025'!$A$3:$A$542,"USA",'90_Origen_Caja_2025'!$C$3:$C$542,5,'90_Origen_Caja_2025'!$E$3:$E$542,"Costos Op.")+SUMIFS('90_Origen_Caja_2025'!$F$3:$F$542,'90_Origen_Caja_2025'!$A$3:$A$542,"USA",'90_Origen_Caja_2025'!$C$3:$C$542,5,'90_Origen_Caja_2025'!$E$3:$E$542,"Costos Admin.")+SUMIFS('90_Origen_Caja_2025'!$F$3:$F$542,'90_Origen_Caja_2025'!$A$3:$A$542,"USA",'90_Origen_Caja_2025'!$C$3:$C$542,5,'90_Origen_Caja_2025'!$E$3:$E$542,"Activo")+SUMIFS('90_Origen_Caja_2025'!$F$3:$F$542,'90_Origen_Caja_2025'!$A$3:$A$542,"USA",'90_Origen_Caja_2025'!$C$3:$C$542,5,'90_Origen_Caja_2025'!$E$3:$E$542,"Egresos No Op.")+SUMIFS('90_Origen_Caja_2025'!$F$3:$F$542,'90_Origen_Caja_2025'!$A$3:$A$542,"USA",'90_Origen_Caja_2025'!$C$3:$C$542,5,'90_Origen_Caja_2025'!$E$3:$E$542,"Pagos Cta.Cte.") -> 329524 | F46: =C46+D46-E46 -> 554889.21 | G46: =D46-E46 -> -134434
A47: USA | B47: jun | C47: =SUMIFS('90_Origen_Caja_2025'!$F$3:$F$542,'90_Origen_Caja_2025'!$A$3:$A$542,"USA",'90_Origen_Caja_2025'!$C$3:$C$542,6,'90_Origen_Caja_2025'!$E$3:$E$542,"Caja Inicial") -> 554889.21 | D47: =SUMIFS('90_Origen_Caja_2025'!$F$3:$F$542,'90_Origen_Caja_2025'!$A$3:$A$542,"USA",'90_Origen_Caja_2025'!$C$3:$C$542,6,'90_Origen_Caja_2025'!$E$3:$E$542,"Ingresos Op.")+SUMIFS('90_Origen_Caja_2025'!$F$3:$F$542,'90_Origen_Caja_2025'!$A$3:$A$542,"USA",'90_Origen_Caja_2025'!$C$3:$C$542,6,'90_Origen_Caja_2025'!$E$3:$E$542,"Otros Ingresos") -> 61796 | E47: =SUMIFS('90_Origen_Caja_2025'!$F$3:$F$542,'90_Origen_Caja_2025'!$A$3:$A$542,"USA",'90_Origen_Caja_2025'!$C$3:$C$542,6,'90_Origen_Caja_2025'!$E$3:$E$542,"Costos Op.")+SUMIFS('90_Origen_Caja_2025'!$F$3:$F$542,'90_Origen_Caja_2025'!$A$3:$A$542,"USA",'90_Origen_Caja_2025'!$C$3:$C$542,6,'90_Origen_Caja_2025'!$E$3:$E$542,"Costos Admin.")+SUMIFS('90_Origen_Caja_2025'!$F$3:$F$542,'90_Origen_Caja_2025'!$A$3:$A$542,"USA",'90_Origen_Caja_2025'!$C$3:$C$542,6,'90_Origen_Caja_2025'!$E$3:$E$542,"Activo")+SUMIFS('90_Origen_Caja_2025'!$F$3:$F$542,'90_Origen_Caja_2025'!$A$3:$A$542,"USA",'90_Origen_Caja_2025'!$C$3:$C$542,6,'90_Origen_Caja_2025'!$E$3:$E$542,"Egresos No Op.")+SUMIFS('90_Origen_Caja_2025'!$F$3:$F$542,'90_Origen_Caja_2025'!$A$3:$A$542,"USA",'90_Origen_Caja_2025'!$C$3:$C$542,6,'90_Origen_Caja_2025'!$E$3:$E$542,"Pagos Cta.Cte.") -> 4178 | F47: =C47+D47-E47 -> 612507.21 | G47: =D47-E47 -> 57618
A48: USA | B48: jul | C48: =SUMIFS('90_Origen_Caja_2025'!$F$3:$F$542,'90_Origen_Caja_2025'!$A$3:$A$542,"USA",'90_Origen_Caja_2025'!$C$3:$C$542,7,'90_Origen_Caja_2025'!$E$3:$E$542,"Caja Inicial") -> 612507.21 | D48: =SUMIFS('90_Origen_Caja_2025'!$F$3:$F$542,'90_Origen_Caja_2025'!$A$3:$A$542,"USA",'90_Origen_Caja_2025'!$C$3:$C$542,7,'90_Origen_Caja_2025'!$E$3:$E$542,"Ingresos Op.")+SUMIFS('90_Origen_Caja_2025'!$F$3:$F$542,'90_Origen_Caja_2025'!$A$3:$A$542,"USA",'90_Origen_Caja_2025'!$C$3:$C$542,7,'90_Origen_Caja_2025'!$E$3:$E$542,"Otros Ingresos") -> 0 | E48: =SUMIFS('90_Origen_Caja_2025'!$F$3:$F$542,'90_Origen_Caja_2025'!$A$3:$A$542,"USA",'90_Origen_Caja_2025'!$C$3:$C$542,7,'90_Origen_Caja_2025'!$E$3:$E$542,"Costos Op.")+SUMIFS('90_Origen_Caja_2025'!$F$3:$F$542,'90_Origen_Caja_2025'!$A$3:$A$542,"USA",'90_Origen_Caja_2025'!$C$3:$C$542,7,'90_Origen_Caja_2025'!$E$3:$E$542,"Costos Admin.")+SUMIFS('90_Origen_Caja_2025'!$F$3:$F$542,'90_Origen_Caja_2025'!$A$3:$A$542,"USA",'90_Origen_Caja_2025'!$C$3:$C$542,7,'90_Origen_Caja_2025'!$E$3:$E$542,"Activo")+SUMIFS('90_Origen_Caja_2025'!$F$3:$F$542,'90_Origen_Caja_2025'!$A$3:$A$542,"USA",'90_Origen_Caja_2025'!$C$3:$C$542,7,'90_Origen_Caja_2025'!$E$3:$E$542,"Egresos No Op.")+SUMIFS('90_Origen_Caja_2025'!$F$3:$F$542,'90_Origen_Caja_2025'!$A$3:$A$542,"USA",'90_Origen_Caja_2025'!$C$3:$C$542,7,'90_Origen_Caja_2025'!$E$3:$E$542,"Pagos Cta.Cte.") -> 10017 | F48: =C48+D48-E48 -> 602490.21 | G48: =D48-E48 -> -10017
A49: USA | B49: ago | C49: =SUMIFS('90_Origen_Caja_2025'!$F$3:$F$542,'90_Origen_Caja_2025'!$A$3:$A$542,"USA",'90_Origen_Caja_2025'!$C$3:$C$542,8,'90_Origen_Caja_2025'!$E$3:$E$542,"Caja Inicial") -> 602490.21 | D49: =SUMIFS('90_Origen_Caja_2025'!$F$3:$F$542,'90_Origen_Caja_2025'!$A$3:$A$542,"USA",'90_Origen_Caja_2025'!$C$3:$C$542,8,'90_Origen_Caja_2025'!$E$3:$E$542,"Ingresos Op.")+SUMIFS('90_Origen_Caja_2025'!$F$3:$F$542,'90_Origen_Caja_2025'!$A$3:$A$542,"USA",'90_Origen_Caja_2025'!$C$3:$C$542,8,'90_Origen_Caja_2025'!$E$3:$E$542,"Otros Ingresos") -> 20000 | E49: =SUMIFS('90_Origen_Caja_2025'!$F$3:$F$542,'90_Origen_Caja_2025'!$A$3:$A$542,"USA",'90_Origen_Caja_2025'!$C$3:$C$542,8,'90_Origen_Caja_2025'!$E$3:$E$542,"Costos Op.")+SUMIFS('90_Origen_Caja_2025'!$F$3:$F$542,'90_Origen_Caja_2025'!$A$3:$A$542,"USA",'90_Origen_Caja_2025'!$C$3:$C$542,8,'90_Origen_Caja_2025'!$E$3:$E$542,"Costos Admin.")+SUMIFS('90_Origen_Caja_2025'!$F$3:$F$542,'90_Origen_Caja_2025'!$A$3:$A$542,"USA",'90_Origen_Caja_2025'!$C$3:$C$542,8,'90_Origen_Caja_2025'!$E$3:$E$542,"Activo")+SUMIFS('90_Origen_Caja_2025'!$F$3:$F$542,'90_Origen_Caja_2025'!$A$3:$A$542,"USA",'90_Origen_Caja_2025'!$C$3:$C$542,8,'90_Origen_Caja_2025'!$E$3:$E$542,"Egresos No Op.")+SUMIFS('90_Origen_Caja_2025'!$F$3:$F$542,'90_Origen_Caja_2025'!$A$3:$A$542,"USA",'90_Origen_Caja_2025'!$C$3:$C$542,8,'90_Origen_Caja_2025'!$E$3:$E$542,"Pagos Cta.Cte.") -> 1015 | F49: =C49+D49-E49 -> 621475.21 | G49: =D49-E49 -> 18985
A50: USA | B50: sep | C50: =SUMIFS('90_Origen_Caja_2025'!$F$3:$F$542,'90_Origen_Caja_2025'!$A$3:$A$542,"USA",'90_Origen_Caja_2025'!$C$3:$C$542,9,'90_Origen_Caja_2025'!$E$3:$E$542,"Caja Inicial") -> 621475.21 | D50: =SUMIFS('90_Origen_Caja_2025'!$F$3:$F$542,'90_Origen_Caja_2025'!$A$3:$A$542,"USA",'90_Origen_Caja_2025'!$C$3:$C$542,9,'90_Origen_Caja_2025'!$E$3:$E$542,"Ingresos Op.")+SUMIFS('90_Origen_Caja_2025'!$F$3:$F$542,'90_Origen_Caja_2025'!$A$3:$A$542,"USA",'90_Origen_Caja_2025'!$C$3:$C$542,9,'90_Origen_Caja_2025'!$E$3:$E$542,"Otros Ingresos") -> 0 | E50: =SUMIFS('90_Origen_Caja_2025'!$F$3:$F$542,'90_Origen_Caja_2025'!$A$3:$A$542,"USA",'90_Origen_Caja_2025'!$C$3:$C$542,9,'90_Origen_Caja_2025'!$E$3:$E$542,"Costos Op.")+SUMIFS('90_Origen_Caja_2025'!$F$3:$F$542,'90_Origen_Caja_2025'!$A$3:$A$542,"USA",'90_Origen_Caja_2025'!$C$3:$C$542,9,'90_Origen_Caja_2025'!$E$3:$E$542,"Costos Admin.")+SUMIFS('90_Origen_Caja_2025'!$F$3:$F$542,'90_Origen_Caja_2025'!$A$3:$A$542,"USA",'90_Origen_Caja_2025'!$C$3:$C$542,9,'90_Origen_Caja_2025'!$E$3:$E$542,"Activo")+SUMIFS('90_Origen_Caja_2025'!$F$3:$F$542,'90_Origen_Caja_2025'!$A$3:$A$542,"USA",'90_Origen_Caja_2025'!$C$3:$C$542,9,'90_Origen_Caja_2025'!$E$3:$E$542,"Egresos No Op.")+SUMIFS('90_Origen_Caja_2025'!$F$3:$F$542,'90_Origen_Caja_2025'!$A$3:$A$542,"USA",'90_Origen_Caja_2025'!$C$3:$C$542,9,'90_Origen_Caja_2025'!$E$3:$E$542,"Pagos Cta.Cte.") -> 1000 | F50: =C50+D50-E50 -> 620475.21 | G50: =D50-E50 -> -1000
A51: USA | B51: oct | C51: =SUMIFS('90_Origen_Caja_2025'!$F$3:$F$542,'90_Origen_Caja_2025'!$A$3:$A$542,"USA",'90_Origen_Caja_2025'!$C$3:$C$542,10,'90_Origen_Caja_2025'!$E$3:$E$542,"Caja Inicial") -> 620475.21 | D51: =SUMIFS('90_Origen_Caja_2025'!$F$3:$F$542,'90_Origen_Caja_2025'!$A$3:$A$542,"USA",'90_Origen_Caja_2025'!$C$3:$C$542,10,'90_Origen_Caja_2025'!$E$3:$E$542,"Ingresos Op.")+SUMIFS('90_Origen_Caja_2025'!$F$3:$F$542,'90_Origen_Caja_2025'!$A$3:$A$542,"USA",'90_Origen_Caja_2025'!$C$3:$C$542,10,'90_Origen_Caja_2025'!$E$3:$E$542,"Otros Ingresos") -> 45000 | E51: =SUMIFS('90_Origen_Caja_2025'!$F$3:$F$542,'90_Origen_Caja_2025'!$A$3:$A$542,"USA",'90_Origen_Caja_2025'!$C$3:$C$542,10,'90_Origen_Caja_2025'!$E$3:$E$542,"Costos Op.")+SUMIFS('90_Origen_Caja_2025'!$F$3:$F$542,'90_Origen_Caja_2025'!$A$3:$A$542,"USA",'90_Origen_Caja_2025'!$C$3:$C$542,10,'90_Origen_Caja_2025'!$E$3:$E$542,"Costos Admin.")+SUMIFS('90_Origen_Caja_2025'!$F$3:$F$542,'90_Origen_Caja_2025'!$A$3:$A$542,"USA",'90_Origen_Caja_2025'!$C$3:$C$542,10,'90_Origen_Caja_2025'!$E$3:$E$542,"Activo")+SUMIFS('90_Origen_Caja_2025'!$F$3:$F$542,'90_Origen_Caja_2025'!$A$3:$A$542,"USA",'90_Origen_Caja_2025'!$C$3:$C$542,10,'90_Origen_Caja_2025'!$E$3:$E$542,"Egresos No Op.")+SUMIFS('90_Origen_Caja_2025'!$F$3:$F$542,'90_Origen_Caja_2025'!$A$3:$A$542,"USA",'90_Origen_Caja_2025'!$C$3:$C$542,10,'90_Origen_Caja_2025'!$E$3:$E$542,"Pagos Cta.Cte.") -> 199165 | F51: =C51+D51-E51 -> 466310.21 | G51: =D51-E51 -> -154165
A52: USA | B52: nov | C52: =SUMIFS('90_Origen_Caja_2025'!$F$3:$F$542,'90_Origen_Caja_2025'!$A$3:$A$542,"USA",'90_Origen_Caja_2025'!$C$3:$C$542,11,'90_Origen_Caja_2025'!$E$3:$E$542,"Caja Inicial") -> 466310.21 | D52: =SUMIFS('90_Origen_Caja_2025'!$F$3:$F$542,'90_Origen_Caja_2025'!$A$3:$A$542,"USA",'90_Origen_Caja_2025'!$C$3:$C$542,11,'90_Origen_Caja_2025'!$E$3:$E$542,"Ingresos Op.")+SUMIFS('90_Origen_Caja_2025'!$F$3:$F$542,'90_Origen_Caja_2025'!$A$3:$A$542,"USA",'90_Origen_Caja_2025'!$C$3:$C$542,11,'90_Origen_Caja_2025'!$E$3:$E$542,"Otros Ingresos") -> 0 | E52: =SUMIFS('90_Origen_Caja_2025'!$F$3:$F$542,'90_Origen_Caja_2025'!$A$3:$A$542,"USA",'90_Origen_Caja_2025'!$C$3:$C$542,11,'90_Origen_Caja_2025'!$E$3:$E$542,"Costos Op.")+SUMIFS('90_Origen_Caja_2025'!$F$3:$F$542,'90_Origen_Caja_2025'!$A$3:$A$542,"USA",'90_Origen_Caja_2025'!$C$3:$C$542,11,'90_Origen_Caja_2025'!$E$3:$E$542,"Costos Admin.")+SUMIFS('90_Origen_Caja_2025'!$F$3:$F$542,'90_Origen_Caja_2025'!$A$3:$A$542,"USA",'90_Origen_Caja_2025'!$C$3:$C$542,11,'90_Origen_Caja_2025'!$E$3:$E$542,"Activo")+SUMIFS('90_Origen_Caja_2025'!$F$3:$F$542,'90_Origen_Caja_2025'!$A$3:$A$542,"USA",'90_Origen_Caja_2025'!$C$3:$C$542,11,'90_Origen_Caja_2025'!$E$3:$E$542,"Egresos No Op.")+SUMIFS('90_Origen_Caja_2025'!$F$3:$F$542,'90_Origen_Caja_2025'!$A$3:$A$542,"USA",'90_Origen_Caja_2025'!$C$3:$C$542,11,'90_Origen_Caja_2025'!$E$3:$E$542,"Pagos Cta.Cte.") -> 7408 | F52: =C52+D52-E52 -> 458902.21 | G52: =D52-E52 -> -7408
A53: USA | B53: dic | C53: =SUMIFS('90_Origen_Caja_2025'!$F$3:$F$542,'90_Origen_Caja_2025'!$A$3:$A$542,"USA",'90_Origen_Caja_2025'!$C$3:$C$542,12,'90_Origen_Caja_2025'!$E$3:$E$542,"Caja Inicial") -> 458902.21 | D53: =SUMIFS('90_Origen_Caja_2025'!$F$3:$F$542,'90_Origen_Caja_2025'!$A$3:$A$542,"USA",'90_Origen_Caja_2025'!$C$3:$C$542,12,'90_Origen_Caja_2025'!$E$3:$E$542,"Ingresos Op.")+SUMIFS('90_Origen_Caja_2025'!$F$3:$F$542,'90_Origen_Caja_2025'!$A$3:$A$542,"USA",'90_Origen_Caja_2025'!$C$3:$C$542,12,'90_Origen_Caja_2025'!$E$3:$E$542,"Otros Ingresos") -> 178785 | E53: =SUMIFS('90_Origen_Caja_2025'!$F$3:$F$542,'90_Origen_Caja_2025'!$A$3:$A$542,"USA",'90_Origen_Caja_2025'!$C$3:$C$542,12,'90_Origen_Caja_2025'!$E$3:$E$542,"Costos Op.")+SUMIFS('90_Origen_Caja_2025'!$F$3:$F$542,'90_Origen_Caja_2025'!$A$3:$A$542,"USA",'90_Origen_Caja_2025'!$C$3:$C$542,12,'90_Origen_Caja_2025'!$E$3:$E$542,"Costos Admin.")+SUMIFS('90_Origen_Caja_2025'!$F$3:$F$542,'90_Origen_Caja_2025'!$A$3:$A$542,"USA",'90_Origen_Caja_2025'!$C$3:$C$542,12,'90_Origen_Caja_2025'!$E$3:$E$542,"Activo")+SUMIFS('90_Origen_Caja_2025'!$F$3:$F$542,'90_Origen_Caja_2025'!$A$3:$A$542,"USA",'90_Origen_Caja_2025'!$C$3:$C$542,12,'90_Origen_Caja_2025'!$E$3:$E$542,"Egresos No Op.")+SUMIFS('90_Origen_Caja_2025'!$F$3:$F$542,'90_Origen_Caja_2025'!$A$3:$A$542,"USA",'90_Origen_Caja_2025'!$C$3:$C$542,12,'90_Origen_Caja_2025'!$E$3:$E$542,"Pagos Cta.Cte.") -> 567924 | F53: =C53+D53-E53 -> 69763.21 | G53: =D53-E53 -> -389139
A54: BVI | B54: ene | C54: =SUMIFS('90_Origen_Caja_2025'!$F$3:$F$542,'90_Origen_Caja_2025'!$A$3:$A$542,"BVI",'90_Origen_Caja_2025'!$C$3:$C$542,1,'90_Origen_Caja_2025'!$E$3:$E$542,"Caja Inicial") -> 0 | D54: =SUMIFS('90_Origen_Caja_2025'!$F$3:$F$542,'90_Origen_Caja_2025'!$A$3:$A$542,"BVI",'90_Origen_Caja_2025'!$C$3:$C$542,1,'90_Origen_Caja_2025'!$E$3:$E$542,"Ingresos Op.")+SUMIFS('90_Origen_Caja_2025'!$F$3:$F$542,'90_Origen_Caja_2025'!$A$3:$A$542,"BVI",'90_Origen_Caja_2025'!$C$3:$C$542,1,'90_Origen_Caja_2025'!$E$3:$E$542,"Otros Ingresos") -> 0 | E54: =SUMIFS('90_Origen_Caja_2025'!$F$3:$F$542,'90_Origen_Caja_2025'!$A$3:$A$542,"BVI",'90_Origen_Caja_2025'!$C$3:$C$542,1,'90_Origen_Caja_2025'!$E$3:$E$542,"Costos Op.")+SUMIFS('90_Origen_Caja_2025'!$F$3:$F$542,'90_Origen_Caja_2025'!$A$3:$A$542,"BVI",'90_Origen_Caja_2025'!$C$3:$C$542,1,'90_Origen_Caja_2025'!$E$3:$E$542,"Costos Admin.")+SUMIFS('90_Origen_Caja_2025'!$F$3:$F$542,'90_Origen_Caja_2025'!$A$3:$A$542,"BVI",'90_Origen_Caja_2025'!$C$3:$C$542,1,'90_Origen_Caja_2025'!$E$3:$E$542,"Activo")+SUMIFS('90_Origen_Caja_2025'!$F$3:$F$542,'90_Origen_Caja_2025'!$A$3:$A$542,"BVI",'90_Origen_Caja_2025'!$C$3:$C$542,1,'90_Origen_Caja_2025'!$E$3:$E$542,"Egresos No Op.")+SUMIFS('90_Origen_Caja_2025'!$F$3:$F$542,'90_Origen_Caja_2025'!$A$3:$A$542,"BVI",'90_Origen_Caja_2025'!$C$3:$C$542,1,'90_Origen_Caja_2025'!$E$3:$E$542,"Pagos Cta.Cte.") -> 14044 | F54: =C54+D54-E54 -> -14044 | G54: =D54-E54 -> -14044
A55: BVI | B55: feb | C55: =SUMIFS('90_Origen_Caja_2025'!$F$3:$F$542,'90_Origen_Caja_2025'!$A$3:$A$542,"BVI",'90_Origen_Caja_2025'!$C$3:$C$542,2,'90_Origen_Caja_2025'!$E$3:$E$542,"Caja Inicial") -> -14044 | D55: =SUMIFS('90_Origen_Caja_2025'!$F$3:$F$542,'90_Origen_Caja_2025'!$A$3:$A$542,"BVI",'90_Origen_Caja_2025'!$C$3:$C$542,2,'90_Origen_Caja_2025'!$E$3:$E$542,"Ingresos Op.")+SUMIFS('90_Origen_Caja_2025'!$F$3:$F$542,'90_Origen_Caja_2025'!$A$3:$A$542,"BVI",'90_Origen_Caja_2025'!$C$3:$C$542,2,'90_Origen_Caja_2025'!$E$3:$E$542,"Otros Ingresos") -> 21682 | E55: =SUMIFS('90_Origen_Caja_2025'!$F$3:$F$542,'90_Origen_Caja_2025'!$A$3:$A$542,"BVI",'90_Origen_Caja_2025'!$C$3:$C$542,2,'90_Origen_Caja_2025'!$E$3:$E$542,"Costos Op.")+SUMIFS('90_Origen_Caja_2025'!$F$3:$F$542,'90_Origen_Caja_2025'!$A$3:$A$542,"BVI",'90_Origen_Caja_2025'!$C$3:$C$542,2,'90_Origen_Caja_2025'!$E$3:$E$542,"Costos Admin.")+SUMIFS('90_Origen_Caja_2025'!$F$3:$F$542,'90_Origen_Caja_2025'!$A$3:$A$542,"BVI",'90_Origen_Caja_2025'!$C$3:$C$542,2,'90_Origen_Caja_2025'!$E$3:$E$542,"Activo")+SUMIFS('90_Origen_Caja_2025'!$F$3:$F$542,'90_Origen_Caja_2025'!$A$3:$A$542,"BVI",'90_Origen_Caja_2025'!$C$3:$C$542,2,'90_Origen_Caja_2025'!$E$3:$E$542,"Egresos No Op.")+SUMIFS('90_Origen_Caja_2025'!$F$3:$F$542,'90_Origen_Caja_2025'!$A$3:$A$542,"BVI",'90_Origen_Caja_2025'!$C$3:$C$542,2,'90_Origen_Caja_2025'!$E$3:$E$542,"Pagos Cta.Cte.") -> 0 | F55: =C55+D55-E55 -> 7638 | G55: =D55-E55 -> 21682
A56: BVI | B56: mar | C56: =SUMIFS('90_Origen_Caja_2025'!$F$3:$F$542,'90_Origen_Caja_2025'!$A$3:$A$542,"BVI",'90_Origen_Caja_2025'!$C$3:$C$542,3,'90_Origen_Caja_2025'!$E$3:$E$542,"Caja Inicial") -> 7638 | D56: =SUMIFS('90_Origen_Caja_2025'!$F$3:$F$542,'90_Origen_Caja_2025'!$A$3:$A$542,"BVI",'90_Origen_Caja_2025'!$C$3:$C$542,3,'90_Origen_Caja_2025'!$E$3:$E$542,"Ingresos Op.")+SUMIFS('90_Origen_Caja_2025'!$F$3:$F$542,'90_Origen_Caja_2025'!$A$3:$A$542,"BVI",'90_Origen_Caja_2025'!$C$3:$C$542,3,'90_Origen_Caja_2025'!$E$3:$E$542,"Otros Ingresos") -> 45478 | E56: =SUMIFS('90_Origen_Caja_2025'!$F$3:$F$542,'90_Origen_Caja_2025'!$A$3:$A$542,"BVI",'90_Origen_Caja_2025'!$C$3:$C$542,3,'90_Origen_Caja_2025'!$E$3:$E$542,"Costos Op.")+SUMIFS('90_Origen_Caja_2025'!$F$3:$F$542,'90_Origen_Caja_2025'!$A$3:$A$542,"BVI",'90_Origen_Caja_2025'!$C$3:$C$542,3,'90_Origen_Caja_2025'!$E$3:$E$542,"Costos Admin.")+SUMIFS('90_Origen_Caja_2025'!$F$3:$F$542,'90_Origen_Caja_2025'!$A$3:$A$542,"BVI",'90_Origen_Caja_2025'!$C$3:$C$542,3,'90_Origen_Caja_2025'!$E$3:$E$542,"Activo")+SUMIFS('90_Origen_Caja_2025'!$F$3:$F$542,'90_Origen_Caja_2025'!$A$3:$A$542,"BVI",'90_Origen_Caja_2025'!$C$3:$C$542,3,'90_Origen_Caja_2025'!$E$3:$E$542,"Egresos No Op.")+SUMIFS('90_Origen_Caja_2025'!$F$3:$F$542,'90_Origen_Caja_2025'!$A$3:$A$542,"BVI",'90_Origen_Caja_2025'!$C$3:$C$542,3,'90_Origen_Caja_2025'!$E$3:$E$542,"Pagos Cta.Cte.") -> 0 | F56: =C56+D56-E56 -> 53116 | G56: =D56-E56 -> 45478
A57: BVI | B57: abr | C57: =SUMIFS('90_Origen_Caja_2025'!$F$3:$F$542,'90_Origen_Caja_2025'!$A$3:$A$542,"BVI",'90_Origen_Caja_2025'!$C$3:$C$542,4,'90_Origen_Caja_2025'!$E$3:$E$542,"Caja Inicial") -> 53116 | D57: =SUMIFS('90_Origen_Caja_2025'!$F$3:$F$542,'90_Origen_Caja_2025'!$A$3:$A$542,"BVI",'90_Origen_Caja_2025'!$C$3:$C$542,4,'90_Origen_Caja_2025'!$E$3:$E$542,"Ingresos Op.")+SUMIFS('90_Origen_Caja_2025'!$F$3:$F$542,'90_Origen_Caja_2025'!$A$3:$A$542,"BVI",'90_Origen_Caja_2025'!$C$3:$C$542,4,'90_Origen_Caja_2025'!$E$3:$E$542,"Otros Ingresos") -> 0 | E57: =SUMIFS('90_Origen_Caja_2025'!$F$3:$F$542,'90_Origen_Caja_2025'!$A$3:$A$542,"BVI",'90_Origen_Caja_2025'!$C$3:$C$542,4,'90_Origen_Caja_2025'!$E$3:$E$542,"Costos Op.")+SUMIFS('90_Origen_Caja_2025'!$F$3:$F$542,'90_Origen_Caja_2025'!$A$3:$A$542,"BVI",'90_Origen_Caja_2025'!$C$3:$C$542,4,'90_Origen_Caja_2025'!$E$3:$E$542,"Costos Admin.")+SUMIFS('90_Origen_Caja_2025'!$F$3:$F$542,'90_Origen_Caja_2025'!$A$3:$A$542,"BVI",'90_Origen_Caja_2025'!$C$3:$C$542,4,'90_Origen_Caja_2025'!$E$3:$E$542,"Activo")+SUMIFS('90_Origen_Caja_2025'!$F$3:$F$542,'90_Origen_Caja_2025'!$A$3:$A$542,"BVI",'90_Origen_Caja_2025'!$C$3:$C$542,4,'90_Origen_Caja_2025'!$E$3:$E$542,"Egresos No Op.")+SUMIFS('90_Origen_Caja_2025'!$F$3:$F$542,'90_Origen_Caja_2025'!$A$3:$A$542,"BVI",'90_Origen_Caja_2025'!$C$3:$C$542,4,'90_Origen_Caja_2025'!$E$3:$E$542,"Pagos Cta.Cte.") -> 14380 | F57: =C57+D57-E57 -> 38736 | G57: =D57-E57 -> -14380
A58: BVI | B58: may | C58: =SUMIFS('90_Origen_Caja_2025'!$F$3:$F$542,'90_Origen_Caja_2025'!$A$3:$A$542,"BVI",'90_Origen_Caja_2025'!$C$3:$C$542,5,'90_Origen_Caja_2025'!$E$3:$E$542,"Caja Inicial") -> 38736 | D58: =SUMIFS('90_Origen_Caja_2025'!$F$3:$F$542,'90_Origen_Caja_2025'!$A$3:$A$542,"BVI",'90_Origen_Caja_2025'!$C$3:$C$542,5,'90_Origen_Caja_2025'!$E$3:$E$542,"Ingresos Op.")+SUMIFS('90_Origen_Caja_2025'!$F$3:$F$542,'90_Origen_Caja_2025'!$A$3:$A$542,"BVI",'90_Origen_Caja_2025'!$C$3:$C$542,5,'90_Origen_Caja_2025'!$E$3:$E$542,"Otros Ingresos") -> 415568 | E58: =SUMIFS('90_Origen_Caja_2025'!$F$3:$F$542,'90_Origen_Caja_2025'!$A$3:$A$542,"BVI",'90_Origen_Caja_2025'!$C$3:$C$542,5,'90_Origen_Caja_2025'!$E$3:$E$542,"Costos Op.")+SUMIFS('90_Origen_Caja_2025'!$F$3:$F$542,'90_Origen_Caja_2025'!$A$3:$A$542,"BVI",'90_Origen_Caja_2025'!$C$3:$C$542,5,'90_Origen_Caja_2025'!$E$3:$E$542,"Costos Admin.")+SUMIFS('90_Origen_Caja_2025'!$F$3:$F$542,'90_Origen_Caja_2025'!$A$3:$A$542,"BVI",'90_Origen_Caja_2025'!$C$3:$C$542,5,'90_Origen_Caja_2025'!$E$3:$E$542,"Activo")+SUMIFS('90_Origen_Caja_2025'!$F$3:$F$542,'90_Origen_Caja_2025'!$A$3:$A$542,"BVI",'90_Origen_Caja_2025'!$C$3:$C$542,5,'90_Origen_Caja_2025'!$E$3:$E$542,"Egresos No Op.")+SUMIFS('90_Origen_Caja_2025'!$F$3:$F$542,'90_Origen_Caja_2025'!$A$3:$A$542,"BVI",'90_Origen_Caja_2025'!$C$3:$C$542,5,'90_Origen_Caja_2025'!$E$3:$E$542,"Pagos Cta.Cte.") -> 16000 | F58: =C58+D58-E58 -> 438304 | G58: =D58-E58 -> 399568
A59: BVI | B59: jun | C59: =SUMIFS('90_Origen_Caja_2025'!$F$3:$F$542,'90_Origen_Caja_2025'!$A$3:$A$542,"BVI",'90_Origen_Caja_2025'!$C$3:$C$542,6,'90_Origen_Caja_2025'!$E$3:$E$542,"Caja Inicial") -> 438304 | D59: =SUMIFS('90_Origen_Caja_2025'!$F$3:$F$542,'90_Origen_Caja_2025'!$A$3:$A$542,"BVI",'90_Origen_Caja_2025'!$C$3:$C$542,6,'90_Origen_Caja_2025'!$E$3:$E$542,"Ingresos Op.")+SUMIFS('90_Origen_Caja_2025'!$F$3:$F$542,'90_Origen_Caja_2025'!$A$3:$A$542,"BVI",'90_Origen_Caja_2025'!$C$3:$C$542,6,'90_Origen_Caja_2025'!$E$3:$E$542,"Otros Ingresos") -> 172045 | E59: =SUMIFS('90_Origen_Caja_2025'!$F$3:$F$542,'90_Origen_Caja_2025'!$A$3:$A$542,"BVI",'90_Origen_Caja_2025'!$C$3:$C$542,6,'90_Origen_Caja_2025'!$E$3:$E$542,"Costos Op.")+SUMIFS('90_Origen_Caja_2025'!$F$3:$F$542,'90_Origen_Caja_2025'!$A$3:$A$542,"BVI",'90_Origen_Caja_2025'!$C$3:$C$542,6,'90_Origen_Caja_2025'!$E$3:$E$542,"Costos Admin.")+SUMIFS('90_Origen_Caja_2025'!$F$3:$F$542,'90_Origen_Caja_2025'!$A$3:$A$542,"BVI",'90_Origen_Caja_2025'!$C$3:$C$542,6,'90_Origen_Caja_2025'!$E$3:$E$542,"Activo")+SUMIFS('90_Origen_Caja_2025'!$F$3:$F$542,'90_Origen_Caja_2025'!$A$3:$A$542,"BVI",'90_Origen_Caja_2025'!$C$3:$C$542,6,'90_Origen_Caja_2025'!$E$3:$E$542,"Egresos No Op.")+SUMIFS('90_Origen_Caja_2025'!$F$3:$F$542,'90_Origen_Caja_2025'!$A$3:$A$542,"BVI",'90_Origen_Caja_2025'!$C$3:$C$542,6,'90_Origen_Caja_2025'!$E$3:$E$542,"Pagos Cta.Cte.") -> 15094 | F59: =C59+D59-E59 -> 595255 | G59: =D59-E59 -> 156951
A60: BVI | B60: jul | C60: =SUMIFS('90_Origen_Caja_2025'!$F$3:$F$542,'90_Origen_Caja_2025'!$A$3:$A$542,"BVI",'90_Origen_Caja_2025'!$C$3:$C$542,7,'90_Origen_Caja_2025'!$E$3:$E$542,"Caja Inicial") -> 595255 | D60: =SUMIFS('90_Origen_Caja_2025'!$F$3:$F$542,'90_Origen_Caja_2025'!$A$3:$A$542,"BVI",'90_Origen_Caja_2025'!$C$3:$C$542,7,'90_Origen_Caja_2025'!$E$3:$E$542,"Ingresos Op.")+SUMIFS('90_Origen_Caja_2025'!$F$3:$F$542,'90_Origen_Caja_2025'!$A$3:$A$542,"BVI",'90_Origen_Caja_2025'!$C$3:$C$542,7,'90_Origen_Caja_2025'!$E$3:$E$542,"Otros Ingresos") -> 0 | E60: =SUMIFS('90_Origen_Caja_2025'!$F$3:$F$542,'90_Origen_Caja_2025'!$A$3:$A$542,"BVI",'90_Origen_Caja_2025'!$C$3:$C$542,7,'90_Origen_Caja_2025'!$E$3:$E$542,"Costos Op.")+SUMIFS('90_Origen_Caja_2025'!$F$3:$F$542,'90_Origen_Caja_2025'!$A$3:$A$542,"BVI",'90_Origen_Caja_2025'!$C$3:$C$542,7,'90_Origen_Caja_2025'!$E$3:$E$542,"Costos Admin.")+SUMIFS('90_Origen_Caja_2025'!$F$3:$F$542,'90_Origen_Caja_2025'!$A$3:$A$542,"BVI",'90_Origen_Caja_2025'!$C$3:$C$542,7,'90_Origen_Caja_2025'!$E$3:$E$542,"Activo")+SUMIFS('90_Origen_Caja_2025'!$F$3:$F$542,'90_Origen_Caja_2025'!$A$3:$A$542,"BVI",'90_Origen_Caja_2025'!$C$3:$C$542,7,'90_Origen_Caja_2025'!$E$3:$E$542,"Egresos No Op.")+SUMIFS('90_Origen_Caja_2025'!$F$3:$F$542,'90_Origen_Caja_2025'!$A$3:$A$542,"BVI",'90_Origen_Caja_2025'!$C$3:$C$542,7,'90_Origen_Caja_2025'!$E$3:$E$542,"Pagos Cta.Cte.") -> 5684.8 | F60: =C60+D60-E60 -> 589570.2 | G60: =D60-E60 -> -5684.8
A61: BVI | B61: ago | C61: =SUMIFS('90_Origen_Caja_2025'!$F$3:$F$542,'90_Origen_Caja_2025'!$A$3:$A$542,"BVI",'90_Origen_Caja_2025'!$C$3:$C$542,8,'90_Origen_Caja_2025'!$E$3:$E$542,"Caja Inicial") -> 589570.2 | D61: =SUMIFS('90_Origen_Caja_2025'!$F$3:$F$542,'90_Origen_Caja_2025'!$A$3:$A$542,"BVI",'90_Origen_Caja_2025'!$C$3:$C$542,8,'90_Origen_Caja_2025'!$E$3:$E$542,"Ingresos Op.")+SUMIFS('90_Origen_Caja_2025'!$F$3:$F$542,'90_Origen_Caja_2025'!$A$3:$A$542,"BVI",'90_Origen_Caja_2025'!$C$3:$C$542,8,'90_Origen_Caja_2025'!$E$3:$E$542,"Otros Ingresos") -> 99524 | E61: =SUMIFS('90_Origen_Caja_2025'!$F$3:$F$542,'90_Origen_Caja_2025'!$A$3:$A$542,"BVI",'90_Origen_Caja_2025'!$C$3:$C$542,8,'90_Origen_Caja_2025'!$E$3:$E$542,"Costos Op.")+SUMIFS('90_Origen_Caja_2025'!$F$3:$F$542,'90_Origen_Caja_2025'!$A$3:$A$542,"BVI",'90_Origen_Caja_2025'!$C$3:$C$542,8,'90_Origen_Caja_2025'!$E$3:$E$542,"Costos Admin.")+SUMIFS('90_Origen_Caja_2025'!$F$3:$F$542,'90_Origen_Caja_2025'!$A$3:$A$542,"BVI",'90_Origen_Caja_2025'!$C$3:$C$542,8,'90_Origen_Caja_2025'!$E$3:$E$542,"Activo")+SUMIFS('90_Origen_Caja_2025'!$F$3:$F$542,'90_Origen_Caja_2025'!$A$3:$A$542,"BVI",'90_Origen_Caja_2025'!$C$3:$C$542,8,'90_Origen_Caja_2025'!$E$3:$E$542,"Egresos No Op.")+SUMIFS('90_Origen_Caja_2025'!$F$3:$F$542,'90_Origen_Caja_2025'!$A$3:$A$542,"BVI",'90_Origen_Caja_2025'!$C$3:$C$542,8,'90_Origen_Caja_2025'!$E$3:$E$542,"Pagos Cta.Cte.") -> 5684.8 | F61: =C61+D61-E61 -> 683409.4 | G61: =D61-E61 -> 93839.2
A62: BVI | B62: sep | C62: =SUMIFS('90_Origen_Caja_2025'!$F$3:$F$542,'90_Origen_Caja_2025'!$A$3:$A$542,"BVI",'90_Origen_Caja_2025'!$C$3:$C$542,9,'90_Origen_Caja_2025'!$E$3:$E$542,"Caja Inicial") -> 683409.4 | D62: =SUMIFS('90_Origen_Caja_2025'!$F$3:$F$542,'90_Origen_Caja_2025'!$A$3:$A$542,"BVI",'90_Origen_Caja_2025'!$C$3:$C$542,9,'90_Origen_Caja_2025'!$E$3:$E$542,"Ingresos Op.")+SUMIFS('90_Origen_Caja_2025'!$F$3:$F$542,'90_Origen_Caja_2025'!$A$3:$A$542,"BVI",'90_Origen_Caja_2025'!$C$3:$C$542,9,'90_Origen_Caja_2025'!$E$3:$E$542,"Otros Ingresos") -> 0 | E62: =SUMIFS('90_Origen_Caja_2025'!$F$3:$F$542,'90_Origen_Caja_2025'!$A$3:$A$542,"BVI",'90_Origen_Caja_2025'!$C$3:$C$542,9,'90_Origen_Caja_2025'!$E$3:$E$542,"Costos Op.")+SUMIFS('90_Origen_Caja_2025'!$F$3:$F$542,'90_Origen_Caja_2025'!$A$3:$A$542,"BVI",'90_Origen_Caja_2025'!$C$3:$C$542,9,'90_Origen_Caja_2025'!$E$3:$E$542,"Costos Admin.")+SUMIFS('90_Origen_Caja_2025'!$F$3:$F$542,'90_Origen_Caja_2025'!$A$3:$A$542,"BVI",'90_Origen_Caja_2025'!$C$3:$C$542,9,'90_Origen_Caja_2025'!$E$3:$E$542,"Activo")+SUMIFS('90_Origen_Caja_2025'!$F$3:$F$542,'90_Origen_Caja_2025'!$A$3:$A$542,"BVI",'90_Origen_Caja_2025'!$C$3:$C$542,9,'90_Origen_Caja_2025'!$E$3:$E$542,"Egresos No Op.")+SUMIFS('90_Origen_Caja_2025'!$F$3:$F$542,'90_Origen_Caja_2025'!$A$3:$A$542,"BVI",'90_Origen_Caja_2025'!$C$3:$C$542,9,'90_Origen_Caja_2025'!$E$3:$E$542,"Pagos Cta.Cte.") -> 5684.8 | F62: =C62+D62-E62 -> 677724.6 | G62: =D62-E62 -> -5684.8
A63: BVI | B63: oct | C63: =SUMIFS('90_Origen_Caja_2025'!$F$3:$F$542,'90_Origen_Caja_2025'!$A$3:$A$542,"BVI",'90_Origen_Caja_2025'!$C$3:$C$542,10,'90_Origen_Caja_2025'!$E$3:$E$542,"Caja Inicial") -> 677724.6 | D63: =SUMIFS('90_Origen_Caja_2025'!$F$3:$F$542,'90_Origen_Caja_2025'!$A$3:$A$542,"BVI",'90_Origen_Caja_2025'!$C$3:$C$542,10,'90_Origen_Caja_2025'!$E$3:$E$542,"Ingresos Op.")+SUMIFS('90_Origen_Caja_2025'!$F$3:$F$542,'90_Origen_Caja_2025'!$A$3:$A$542,"BVI",'90_Origen_Caja_2025'!$C$3:$C$542,10,'90_Origen_Caja_2025'!$E$3:$E$542,"Otros Ingresos") -> 110754 | E63: =SUMIFS('90_Origen_Caja_2025'!$F$3:$F$542,'90_Origen_Caja_2025'!$A$3:$A$542,"BVI",'90_Origen_Caja_2025'!$C$3:$C$542,10,'90_Origen_Caja_2025'!$E$3:$E$542,"Costos Op.")+SUMIFS('90_Origen_Caja_2025'!$F$3:$F$542,'90_Origen_Caja_2025'!$A$3:$A$542,"BVI",'90_Origen_Caja_2025'!$C$3:$C$542,10,'90_Origen_Caja_2025'!$E$3:$E$542,"Costos Admin.")+SUMIFS('90_Origen_Caja_2025'!$F$3:$F$542,'90_Origen_Caja_2025'!$A$3:$A$542,"BVI",'90_Origen_Caja_2025'!$C$3:$C$542,10,'90_Origen_Caja_2025'!$E$3:$E$542,"Activo")+SUMIFS('90_Origen_Caja_2025'!$F$3:$F$542,'90_Origen_Caja_2025'!$A$3:$A$542,"BVI",'90_Origen_Caja_2025'!$C$3:$C$542,10,'90_Origen_Caja_2025'!$E$3:$E$542,"Egresos No Op.")+SUMIFS('90_Origen_Caja_2025'!$F$3:$F$542,'90_Origen_Caja_2025'!$A$3:$A$542,"BVI",'90_Origen_Caja_2025'!$C$3:$C$542,10,'90_Origen_Caja_2025'!$E$3:$E$542,"Pagos Cta.Cte.") -> 5684.8 | F63: =C63+D63-E63 -> 782793.8 | G63: =D63-E63 -> 105069.2
A64: BVI | B64: nov | C64: =SUMIFS('90_Origen_Caja_2025'!$F$3:$F$542,'90_Origen_Caja_2025'!$A$3:$A$542,"BVI",'90_Origen_Caja_2025'!$C$3:$C$542,11,'90_Origen_Caja_2025'!$E$3:$E$542,"Caja Inicial") -> 782793.8 | D64: =SUMIFS('90_Origen_Caja_2025'!$F$3:$F$542,'90_Origen_Caja_2025'!$A$3:$A$542,"BVI",'90_Origen_Caja_2025'!$C$3:$C$542,11,'90_Origen_Caja_2025'!$E$3:$E$542,"Ingresos Op.")+SUMIFS('90_Origen_Caja_2025'!$F$3:$F$542,'90_Origen_Caja_2025'!$A$3:$A$542,"BVI",'90_Origen_Caja_2025'!$C$3:$C$542,11,'90_Origen_Caja_2025'!$E$3:$E$542,"Otros Ingresos") -> 278213 | E64: =SUMIFS('90_Origen_Caja_2025'!$F$3:$F$542,'90_Origen_Caja_2025'!$A$3:$A$542,"BVI",'90_Origen_Caja_2025'!$C$3:$C$542,11,'90_Origen_Caja_2025'!$E$3:$E$542,"Costos Op.")+SUMIFS('90_Origen_Caja_2025'!$F$3:$F$542,'90_Origen_Caja_2025'!$A$3:$A$542,"BVI",'90_Origen_Caja_2025'!$C$3:$C$542,11,'90_Origen_Caja_2025'!$E$3:$E$542,"Costos Admin.")+SUMIFS('90_Origen_Caja_2025'!$F$3:$F$542,'90_Origen_Caja_2025'!$A$3:$A$542,"BVI",'90_Origen_Caja_2025'!$C$3:$C$542,11,'90_Origen_Caja_2025'!$E$3:$E$542,"Activo")+SUMIFS('90_Origen_Caja_2025'!$F$3:$F$542,'90_Origen_Caja_2025'!$A$3:$A$542,"BVI",'90_Origen_Caja_2025'!$C$3:$C$542,11,'90_Origen_Caja_2025'!$E$3:$E$542,"Egresos No Op.")+SUMIFS('90_Origen_Caja_2025'!$F$3:$F$542,'90_Origen_Caja_2025'!$A$3:$A$542,"BVI",'90_Origen_Caja_2025'!$C$3:$C$542,11,'90_Origen_Caja_2025'!$E$3:$E$542,"Pagos Cta.Cte.") -> 5684.8 | F64: =C64+D64-E64 -> 1055322 | G64: =D64-E64 -> 272528.2
A65: BVI | B65: dic | C65: =SUMIFS('90_Origen_Caja_2025'!$F$3:$F$542,'90_Origen_Caja_2025'!$A$3:$A$542,"BVI",'90_Origen_Caja_2025'!$C$3:$C$542,12,'90_Origen_Caja_2025'!$E$3:$E$542,"Caja Inicial") -> 1055322 | D65: =SUMIFS('90_Origen_Caja_2025'!$F$3:$F$542,'90_Origen_Caja_2025'!$A$3:$A$542,"BVI",'90_Origen_Caja_2025'!$C$3:$C$542,12,'90_Origen_Caja_2025'!$E$3:$E$542,"Ingresos Op.")+SUMIFS('90_Origen_Caja_2025'!$F$3:$F$542,'90_Origen_Caja_2025'!$A$3:$A$542,"BVI",'90_Origen_Caja_2025'!$C$3:$C$542,12,'90_Origen_Caja_2025'!$E$3:$E$542,"Otros Ingresos") -> 349514 | E65: =SUMIFS('90_Origen_Caja_2025'!$F$3:$F$542,'90_Origen_Caja_2025'!$A$3:$A$542,"BVI",'90_Origen_Caja_2025'!$C$3:$C$542,12,'90_Origen_Caja_2025'!$E$3:$E$542,"Costos Op.")+SUMIFS('90_Origen_Caja_2025'!$F$3:$F$542,'90_Origen_Caja_2025'!$A$3:$A$542,"BVI",'90_Origen_Caja_2025'!$C$3:$C$542,12,'90_Origen_Caja_2025'!$E$3:$E$542,"Costos Admin.")+SUMIFS('90_Origen_Caja_2025'!$F$3:$F$542,'90_Origen_Caja_2025'!$A$3:$A$542,"BVI",'90_Origen_Caja_2025'!$C$3:$C$542,12,'90_Origen_Caja_2025'!$E$3:$E$542,"Activo")+SUMIFS('90_Origen_Caja_2025'!$F$3:$F$542,'90_Origen_Caja_2025'!$A$3:$A$542,"BVI",'90_Origen_Caja_2025'!$C$3:$C$542,12,'90_Origen_Caja_2025'!$E$3:$E$542,"Egresos No Op.")+SUMIFS('90_Origen_Caja_2025'!$F$3:$F$542,'90_Origen_Caja_2025'!$A$3:$A$542,"BVI",'90_Origen_Caja_2025'!$C$3:$C$542,12,'90_Origen_Caja_2025'!$E$3:$E$542,"Pagos Cta.Cte.") -> 5684.8 | F65: =C65+D65-E65 -> 1399151.2 | G65: =D65-E65 -> 343829.2
A66: Consolidado 2025 (suma de entidades) por mes
A67: Consolidado | B67: Mes | C67: Caja Inicial | D67: Ingresos | E67: Egresos | F67: Caja Final | G67: Flujo Neto Mes
A68: TOTAL | B68: ene | C68: =SUMIFS('90_Origen_Caja_2025'!$F$3:$F$542,'90_Origen_Caja_2025'!$C$3:$C$542,1,'90_Origen_Caja_2025'!$E$3:$E$542,"Caja Inicial") -> 253992.16 | D68: =SUMIFS('90_Origen_Caja_2025'!$F$3:$F$542,'90_Origen_Caja_2025'!$C$3:$C$542,1,'90_Origen_Caja_2025'!$E$3:$E$542,"Ingresos Op.")+SUMIFS('90_Origen_Caja_2025'!$F$3:$F$542,'90_Origen_Caja_2025'!$C$3:$C$542,1,'90_Origen_Caja_2025'!$E$3:$E$542,"Otros Ingresos") -> 996737.54 | E68: =SUMIFS('90_Origen_Caja_2025'!$F$3:$F$542,'90_Origen_Caja_2025'!$C$3:$C$542,1,'90_Origen_Caja_2025'!$E$3:$E$542,"Costos Op.")+SUMIFS('90_Origen_Caja_2025'!$F$3:$F$542,'90_Origen_Caja_2025'!$C$3:$C$542,1,'90_Origen_Caja_2025'!$E$3:$E$542,"Costos Admin.")+SUMIFS('90_Origen_Caja_2025'!$F$3:$F$542,'90_Origen_Caja_2025'!$C$3:$C$542,1,'90_Origen_Caja_2025'!$E$3:$E$542,"Activo")+SUMIFS('90_Origen_Caja_2025'!$F$3:$F$542,'90_Origen_Caja_2025'!$C$3:$C$542,1,'90_Origen_Caja_2025'!$E$3:$E$542,"Egresos No Op.")+SUMIFS('90_Origen_Caja_2025'!$F$3:$F$542,'90_Origen_Caja_2025'!$C$3:$C$542,1,'90_Origen_Caja_2025'!$E$3:$E$542,"Pagos Cta.Cte.") -> 686239.84 | F68: =C68+D68-E68 -> 564489.86 | G68: =D68-E68 -> 310497.7
A69: TOTAL | B69: feb | C69: =SUMIFS('90_Origen_Caja_2025'!$F$3:$F$542,'90_Origen_Caja_2025'!$C$3:$C$542,2,'90_Origen_Caja_2025'!$E$3:$E$542,"Caja Inicial") -> 564489.87 | D69: =SUMIFS('90_Origen_Caja_2025'!$F$3:$F$542,'90_Origen_Caja_2025'!$C$3:$C$542,2,'90_Origen_Caja_2025'!$E$3:$E$542,"Ingresos Op.")+SUMIFS('90_Origen_Caja_2025'!$F$3:$F$542,'90_Origen_Caja_2025'!$C$3:$C$542,2,'90_Origen_Caja_2025'!$E$3:$E$542,"Otros Ingresos") -> 1180193.2 | E69: =SUMIFS('90_Origen_Caja_2025'!$F$3:$F$542,'90_Origen_Caja_2025'!$C$3:$C$542,2,'90_Origen_Caja_2025'!$E$3:$E$542,"Costos Op.")+SUMIFS('90_Origen_Caja_2025'!$F$3:$F$542,'90_Origen_Caja_2025'!$C$3:$C$542,2,'90_Origen_Caja_2025'!$E$3:$E$542,"Costos Admin.")+SUMIFS('90_Origen_Caja_2025'!$F$3:$F$542,'90_Origen_Caja_2025'!$C$3:$C$542,2,'90_Origen_Caja_2025'!$E$3:$E$542,"Activo")+SUMIFS('90_Origen_Caja_2025'!$F$3:$F$542,'90_Origen_Caja_2025'!$C$3:$C$542,2,'90_Origen_Caja_2025'!$E$3:$E$542,"Egresos No Op.")+SUMIFS('90_Origen_Caja_2025'!$F$3:$F$542,'90_Origen_Caja_2025'!$C$3:$C$542,2,'90_Origen_Caja_2025'!$E$3:$E$542,"Pagos Cta.Cte.") -> 769560.86 | F69: =C69+D69-E69 -> 975122.25 | G69: =D69-E69 -> 410632.38
A70: TOTAL | B70: mar | C70: =SUMIFS('90_Origen_Caja_2025'!$F$3:$F$542,'90_Origen_Caja_2025'!$C$3:$C$542,3,'90_Origen_Caja_2025'!$E$3:$E$542,"Caja Inicial") -> 975122.25 | D70: =SUMIFS('90_Origen_Caja_2025'!$F$3:$F$542,'90_Origen_Caja_2025'!$C$3:$C$542,3,'90_Origen_Caja_2025'!$E$3:$E$542,"Ingresos Op.")+SUMIFS('90_Origen_Caja_2025'!$F$3:$F$542,'90_Origen_Caja_2025'!$C$3:$C$542,3,'90_Origen_Caja_2025'!$E$3:$E$542,"Otros Ingresos") -> 950681.58 | E70: =SUMIFS('90_Origen_Caja_2025'!$F$3:$F$542,'90_Origen_Caja_2025'!$C$3:$C$542,3,'90_Origen_Caja_2025'!$E$3:$E$542,"Costos Op.")+SUMIFS('90_Origen_Caja_2025'!$F$3:$F$542,'90_Origen_Caja_2025'!$C$3:$C$542,3,'90_Origen_Caja_2025'!$E$3:$E$542,"Costos Admin.")+SUMIFS('90_Origen_Caja_2025'!$F$3:$F$542,'90_Origen_Caja_2025'!$C$3:$C$542,3,'90_Origen_Caja_2025'!$E$3:$E$542,"Activo")+SUMIFS('90_Origen_Caja_2025'!$F$3:$F$542,'90_Origen_Caja_2025'!$C$3:$C$542,3,'90_Origen_Caja_2025'!$E$3:$E$542,"Egresos No Op.")+SUMIFS('90_Origen_Caja_2025'!$F$3:$F$542,'90_Origen_Caja_2025'!$C$3:$C$542,3,'90_Origen_Caja_2025'!$E$3:$E$542,"Pagos Cta.Cte.") -> 765208.99 | F70: =C70+D70-E70 -> 1160594.8 | G70: =D70-E70 -> 185472.59
A71: TOTAL | B71: abr | C71: =SUMIFS('90_Origen_Caja_2025'!$F$3:$F$542,'90_Origen_Caja_2025'!$C$3:$C$542,4,'90_Origen_Caja_2025'!$E$3:$E$542,"Caja Inicial") -> 1160594.8 | D71: =SUMIFS('90_Origen_Caja_2025'!$F$3:$F$542,'90_Origen_Caja_2025'!$C$3:$C$542,4,'90_Origen_Caja_2025'!$E$3:$E$542,"Ingresos Op.")+SUMIFS('90_Origen_Caja_2025'!$F$3:$F$542,'90_Origen_Caja_2025'!$C$3:$C$542,4,'90_Origen_Caja_2025'!$E$3:$E$542,"Otros Ingresos") -> 906130.99 | E71: =SUMIFS('90_Origen_Caja_2025'!$F$3:$F$542,'90_Origen_Caja_2025'!$C$3:$C$542,4,'90_Origen_Caja_2025'!$E$3:$E$542,"Costos Op.")+SUMIFS('90_Origen_Caja_2025'!$F$3:$F$542,'90_Origen_Caja_2025'!$C$3:$C$542,4,'90_Origen_Caja_2025'!$E$3:$E$542,"Costos Admin.")+SUMIFS('90_Origen_Caja_2025'!$F$3:$F$542,'90_Origen_Caja_2025'!$C$3:$C$542,4,'90_Origen_Caja_2025'!$E$3:$E$542,"Activo")+SUMIFS('90_Origen_Caja_2025'!$F$3:$F$542,'90_Origen_Caja_2025'!$C$3:$C$542,4,'90_Origen_Caja_2025'!$E$3:$E$542,"Egresos No Op.")+SUMIFS('90_Origen_Caja_2025'!$F$3:$F$542,'90_Origen_Caja_2025'!$C$3:$C$542,4,'90_Origen_Caja_2025'!$E$3:$E$542,"Pagos Cta.Cte.") -> 856666.72 | F71: =C71+D71-E71 -> 1210059.1 | G71: =D71-E71 -> 49464.27
A72: TOTAL | B72: may | C72: =SUMIFS('90_Origen_Caja_2025'!$F$3:$F$542,'90_Origen_Caja_2025'!$C$3:$C$542,5,'90_Origen_Caja_2025'!$E$3:$E$542,"Caja Inicial") -> 1210059.1 | D72: =SUMIFS('90_Origen_Caja_2025'!$F$3:$F$542,'90_Origen_Caja_2025'!$C$3:$C$542,5,'90_Origen_Caja_2025'!$E$3:$E$542,"Ingresos Op.")+SUMIFS('90_Origen_Caja_2025'!$F$3:$F$542,'90_Origen_Caja_2025'!$C$3:$C$542,5,'90_Origen_Caja_2025'!$E$3:$E$542,"Otros Ingresos") -> 1255789.6 | E72: =SUMIFS('90_Origen_Caja_2025'!$F$3:$F$542,'90_Origen_Caja_2025'!$C$3:$C$542,5,'90_Origen_Caja_2025'!$E$3:$E$542,"Costos Op.")+SUMIFS('90_Origen_Caja_2025'!$F$3:$F$542,'90_Origen_Caja_2025'!$C$3:$C$542,5,'90_Origen_Caja_2025'!$E$3:$E$542,"Costos Admin.")+SUMIFS('90_Origen_Caja_2025'!$F$3:$F$542,'90_Origen_Caja_2025'!$C$3:$C$542,5,'90_Origen_Caja_2025'!$E$3:$E$542,"Activo")+SUMIFS('90_Origen_Caja_2025'!$F$3:$F$542,'90_Origen_Caja_2025'!$C$3:$C$542,5,'90_Origen_Caja_2025'!$E$3:$E$542,"Egresos No Op.")+SUMIFS('90_Origen_Caja_2025'!$F$3:$F$542,'90_Origen_Caja_2025'!$C$3:$C$542,5,'90_Origen_Caja_2025'!$E$3:$E$542,"Pagos Cta.Cte.") -> 1174270.1 | F72: =C72+D72-E72 -> 1291578.5 | G72: =D72-E72 -> 81519.44
A73: TOTAL | B73: jun | C73: =SUMIFS('90_Origen_Caja_2025'!$F$3:$F$542,'90_Origen_Caja_2025'!$C$3:$C$542,6,'90_Origen_Caja_2025'!$E$3:$E$542,"Caja Inicial") -> 1291578.5 | D73: =SUMIFS('90_Origen_Caja_2025'!$F$3:$F$542,'90_Origen_Caja_2025'!$C$3:$C$542,6,'90_Origen_Caja_2025'!$E$3:$E$542,"Ingresos Op.")+SUMIFS('90_Origen_Caja_2025'!$F$3:$F$542,'90_Origen_Caja_2025'!$C$3:$C$542,6,'90_Origen_Caja_2025'!$E$3:$E$542,"Otros Ingresos") -> 987111.32 | E73: =SUMIFS('90_Origen_Caja_2025'!$F$3:$F$542,'90_Origen_Caja_2025'!$C$3:$C$542,6,'90_Origen_Caja_2025'!$E$3:$E$542,"Costos Op.")+SUMIFS('90_Origen_Caja_2025'!$F$3:$F$542,'90_Origen_Caja_2025'!$C$3:$C$542,6,'90_Origen_Caja_2025'!$E$3:$E$542,"Costos Admin.")+SUMIFS('90_Origen_Caja_2025'!$F$3:$F$542,'90_Origen_Caja_2025'!$C$3:$C$542,6,'90_Origen_Caja_2025'!$E$3:$E$542,"Activo")+SUMIFS('90_Origen_Caja_2025'!$F$3:$F$542,'90_Origen_Caja_2025'!$C$3:$C$542,6,'90_Origen_Caja_2025'!$E$3:$E$542,"Egresos No Op.")+SUMIFS('90_Origen_Caja_2025'!$F$3:$F$542,'90_Origen_Caja_2025'!$C$3:$C$542,6,'90_Origen_Caja_2025'!$E$3:$E$542,"Pagos Cta.Cte.") -> 800685.99 | F73: =C73+D73-E73 -> 1478003.9 | G73: =D73-E73 -> 186425.33
A74: TOTAL | B74: jul | C74: =SUMIFS('90_Origen_Caja_2025'!$F$3:$F$542,'90_Origen_Caja_2025'!$C$3:$C$542,7,'90_Origen_Caja_2025'!$E$3:$E$542,"Caja Inicial") -> 1478003.9 | D74: =SUMIFS('90_Origen_Caja_2025'!$F$3:$F$542,'90_Origen_Caja_2025'!$C$3:$C$542,7,'90_Origen_Caja_2025'!$E$3:$E$542,"Ingresos Op.")+SUMIFS('90_Origen_Caja_2025'!$F$3:$F$542,'90_Origen_Caja_2025'!$C$3:$C$542,7,'90_Origen_Caja_2025'!$E$3:$E$542,"Otros Ingresos") -> 1028191.6 | E74: =SUMIFS('90_Origen_Caja_2025'!$F$3:$F$542,'90_Origen_Caja_2025'!$C$3:$C$542,7,'90_Origen_Caja_2025'!$E$3:$E$542,"Costos Op.")+SUMIFS('90_Origen_Caja_2025'!$F$3:$F$542,'90_Origen_Caja_2025'!$C$3:$C$542,7,'90_Origen_Caja_2025'!$E$3:$E$542,"Costos Admin.")+SUMIFS('90_Origen_Caja_2025'!$F$3:$F$542,'90_Origen_Caja_2025'!$C$3:$C$542,7,'90_Origen_Caja_2025'!$E$3:$E$542,"Activo")+SUMIFS('90_Origen_Caja_2025'!$F$3:$F$542,'90_Origen_Caja_2025'!$C$3:$C$542,7,'90_Origen_Caja_2025'!$E$3:$E$542,"Egresos No Op.")+SUMIFS('90_Origen_Caja_2025'!$F$3:$F$542,'90_Origen_Caja_2025'!$C$3:$C$542,7,'90_Origen_Caja_2025'!$E$3:$E$542,"Pagos Cta.Cte.") -> 805079.99 | F74: =C74+D74-E74 -> 1701115.4 | G74: =D74-E74 -> 223111.57
A75: TOTAL | B75: ago | C75: =SUMIFS('90_Origen_Caja_2025'!$F$3:$F$542,'90_Origen_Caja_2025'!$C$3:$C$542,8,'90_Origen_Caja_2025'!$E$3:$E$542,"Caja Inicial") -> 1701115.4 | D75: =SUMIFS('90_Origen_Caja_2025'!$F$3:$F$542,'90_Origen_Caja_2025'!$C$3:$C$542,8,'90_Origen_Caja_2025'!$E$3:$E$542,"Ingresos Op.")+SUMIFS('90_Origen_Caja_2025'!$F$3:$F$542,'90_Origen_Caja_2025'!$C$3:$C$542,8,'90_Origen_Caja_2025'!$E$3:$E$542,"Otros Ingresos") -> 1691438.2 | E75: =SUMIFS('90_Origen_Caja_2025'!$F$3:$F$542,'90_Origen_Caja_2025'!$C$3:$C$542,8,'90_Origen_Caja_2025'!$E$3:$E$542,"Costos Op.")+SUMIFS('90_Origen_Caja_2025'!$F$3:$F$542,'90_Origen_Caja_2025'!$C$3:$C$542,8,'90_Origen_Caja_2025'!$E$3:$E$542,"Costos Admin.")+SUMIFS('90_Origen_Caja_2025'!$F$3:$F$542,'90_Origen_Caja_2025'!$C$3:$C$542,8,'90_Origen_Caja_2025'!$E$3:$E$542,"Activo")+SUMIFS('90_Origen_Caja_2025'!$F$3:$F$542,'90_Origen_Caja_2025'!$C$3:$C$542,8,'90_Origen_Caja_2025'!$E$3:$E$542,"Egresos No Op.")+SUMIFS('90_Origen_Caja_2025'!$F$3:$F$542,'90_Origen_Caja_2025'!$C$3:$C$542,8,'90_Origen_Caja_2025'!$E$3:$E$542,"Pagos Cta.Cte.") -> 1406249.5 | F75: =C75+D75-E75 -> 1986304.1 | G75: =D75-E75 -> 285188.71
A76: TOTAL | B76: sep | C76: =SUMIFS('90_Origen_Caja_2025'!$F$3:$F$542,'90_Origen_Caja_2025'!$C$3:$C$542,9,'90_Origen_Caja_2025'!$E$3:$E$542,"Caja Inicial") -> 1986304.1 | D76: =SUMIFS('90_Origen_Caja_2025'!$F$3:$F$542,'90_Origen_Caja_2025'!$C$3:$C$542,9,'90_Origen_Caja_2025'!$E$3:$E$542,"Ingresos Op.")+SUMIFS('90_Origen_Caja_2025'!$F$3:$F$542,'90_Origen_Caja_2025'!$C$3:$C$542,9,'90_Origen_Caja_2025'!$E$3:$E$542,"Otros Ingresos") -> 725248.19 | E76: =SUMIFS('90_Origen_Caja_2025'!$F$3:$F$542,'90_Origen_Caja_2025'!$C$3:$C$542,9,'90_Origen_Caja_2025'!$E$3:$E$542,"Costos Op.")+SUMIFS('90_Origen_Caja_2025'!$F$3:$F$542,'90_Origen_Caja_2025'!$C$3:$C$542,9,'90_Origen_Caja_2025'!$E$3:$E$542,"Costos Admin.")+SUMIFS('90_Origen_Caja_2025'!$F$3:$F$542,'90_Origen_Caja_2025'!$C$3:$C$542,9,'90_Origen_Caja_2025'!$E$3:$E$542,"Activo")+SUMIFS('90_Origen_Caja_2025'!$F$3:$F$542,'90_Origen_Caja_2025'!$C$3:$C$542,9,'90_Origen_Caja_2025'!$E$3:$E$542,"Egresos No Op.")+SUMIFS('90_Origen_Caja_2025'!$F$3:$F$542,'90_Origen_Caja_2025'!$C$3:$C$542,9,'90_Origen_Caja_2025'!$E$3:$E$542,"Pagos Cta.Cte.") -> 822879.89 | F76: =C76+D76-E76 -> 1888672.4 | G76: =D76-E76 -> -97631.7
A77: TOTAL | B77: oct | C77: =SUMIFS('90_Origen_Caja_2025'!$F$3:$F$542,'90_Origen_Caja_2025'!$C$3:$C$542,10,'90_Origen_Caja_2025'!$E$3:$E$542,"Caja Inicial") -> 1896324.4 | D77: =SUMIFS('90_Origen_Caja_2025'!$F$3:$F$542,'90_Origen_Caja_2025'!$C$3:$C$542,10,'90_Origen_Caja_2025'!$E$3:$E$542,"Ingresos Op.")+SUMIFS('90_Origen_Caja_2025'!$F$3:$F$542,'90_Origen_Caja_2025'!$C$3:$C$542,10,'90_Origen_Caja_2025'!$E$3:$E$542,"Otros Ingresos") -> 1239849.6 | E77: =SUMIFS('90_Origen_Caja_2025'!$F$3:$F$542,'90_Origen_Caja_2025'!$C$3:$C$542,10,'90_Origen_Caja_2025'!$E$3:$E$542,"Costos Op.")+SUMIFS('90_Origen_Caja_2025'!$F$3:$F$542,'90_Origen_Caja_2025'!$C$3:$C$542,10,'90_Origen_Caja_2025'!$E$3:$E$542,"Costos Admin.")+SUMIFS('90_Origen_Caja_2025'!$F$3:$F$542,'90_Origen_Caja_2025'!$C$3:$C$542,10,'90_Origen_Caja_2025'!$E$3:$E$542,"Activo")+SUMIFS('90_Origen_Caja_2025'!$F$3:$F$542,'90_Origen_Caja_2025'!$C$3:$C$542,10,'90_Origen_Caja_2025'!$E$3:$E$542,"Egresos No Op.")+SUMIFS('90_Origen_Caja_2025'!$F$3:$F$542,'90_Origen_Caja_2025'!$C$3:$C$542,10,'90_Origen_Caja_2025'!$E$3:$E$542,"Pagos Cta.Cte.") -> 1176427.1 | F77: =C77+D77-E77 -> 1959747 | G77: =D77-E77 -> 63422.55
