Workbook
Name RutaCarpeta: #REF!
Name RutaCarpeta: #REF!
Name RutaCarpeta: #REF!
Name RutaCarpeta: #REF!
Name RutaCarpeta: #REF!
Name RutaCarpeta: #REF!
Name RutaCarpeta: #REF!
Name RutaCarpeta: #REF!
Name RutaCarpeta: #REF!
Name RutaCarpeta: #REF!
Name RutaCarpeta: #REF!
Name RutaCarpeta: #REF!
Name RutaCarpeta: #REF!
Name RutaCarpeta: #REF!
Name RutaCarpeta: #REF!

Sheet Gasto Diciembre (4)
A2: Clasificación 1 | B2: (Todas)
A3: País | B3: Chile
A5: Suma de Valor USD | E5: Meses (Atributo)
A6: Clasificación 0 | B6: Clasificación 2 | C6: Clasificación 3 | D6: Detalle | E6: ene | F6: feb | G6: mar | H6: abr | I6: may | J6: jun | K6: jul | L6: ago | M6: sept | N6: oct | O6: nov | P6: dic
A7: Fijo | B7: Sueldos | E7: 198081.87 | F7: 192564.08 | G7: 201303.57 | H7: 191949.92 | I7: 203926.54 | J7: 158834.49 | K7: 206742.44 | L7: 213676.32 | M7: 209758.6 | N7: 218099.34 | O7: 180235.68 | P7: 210281.54
A8: Fijo | B8: Oficina | C8: Arriendo | D8: Arriendo oficina 1502 + estac-Edif. Kennedy 85 UF | E8: 0 | F8: 0 | G8: 0 | H8: 0 | I8: 0 | J8: 0 | K8: 0 | L8: 0 | M8: 0 | N8: 0 | O8: 0 | P8: 3325.6019
A9: Fijo | B9: Oficina | C9: Caja Chica | E9: 727.30977 | F9: 840.72594 | G9: 0 | H9: 533.34618 | I9: 431.11082 | J9: 399.46981 | K9: 0 | L9: 0 | M9: 0 | N9: 0 | O9: 0 | P9: 0
A10: Fijo | B10: Oficina | C10: Credito | E10: 5434.0037 | F10: 5121.254 | G10: 5097.4926 | H10: 0 | I10: 0 | J10: 0 | K10: 20056.597 | L10: 20219.14 | M10: 20292.392 | N10: 20123.773 | O10: 19323.355 | P10: 19118.322 | Q10: =+SUM(E10:P10) -> 134786.33
A11: Fijo | B11: Oficina | C11: Dividendo | E11: 7385.6937 | F11: 6926.5943 | G11: 6940.7147 | H11: 7041.2961 | I11: 7394.7891 | J11: 7365.1434 | K11: 7257.5718 | L11: 7309.8688 | M11: 7390.6943 | N11: 7351.6261 | O11: 7071.903 | P11: 7068.4154
A12: Fijo | B12: Oficina | C12: Estacionamiento | E12: 563.77934 | F12: 833.38661 | G12: 186.48559 | H12: 231.62247 | I12: 881.57384 | J12: 438.28935 | K12: 336.76885 | L12: 437.55242 | M12: 440.47138 | N12: 437.2624 | O12: 236.03849 | P12: 0
A13: Fijo | B13: Oficina | C13: GGCC | E13: 1631.7195 | F13: 3153.2529 | G13: 1703.742 | H13: 0 | I13: 3464.7961 | J13: 1594.0513 | K13: 1829.9533 | L13: 1829.6451 | M13: 1943.7061 | N13: 1931.123 | O13: 1730.6196 | P13: 1692.5466
A14: Fijo | B14: Oficina | C14: Pago servicio | D14: Prisa S.A. arts. Aseso y cocina | E14: 0 | F14: 0 | G14: 0 | H14: 0 | I14: 0 | J14: 0 | K14: 270.24937 | L14: 354.15959 | M14: 248.09169 | N14: 319.03385 | O14: 283.28016 | P14: 320.23548
A15: Fijo | B15: Oficina | C15: Patente | E15: 234.19751 | F15: 0 | G15: 0 | H15: 0 | I15: 0 | J15: 0 | K15: 444.74274 | L15: 0 | M15: 0 | N15: 0 | O15: 0 | P15: 0
A16: Fijo | B16: Oficina | C16: Registro Proveedores | E16: 786.88532 | F16: 0 | G16: 0 | H16: 1369.4388 | I16: 0 | J16: 141.96506 | K16: 0 | L16: 0 | M16: 0 | N16: 0 | O16: 0 | P16: 186.31142
A17: Fijo | B17: Oficina | C17: Software | E17: 1408.3305 | F17: 0 | G17: 0 | H17: 2485.0699 | I17: 0 | J17: 0 | K17: 1459.0864 | L17: 492.34649 | M17: 496.1499 | N17: 1892.4888 | O17: 475.44463 | P17: 6475.7578
A18: Fijo | B18: Oficina | C18: Tarjeta | E18: 11332.386 | F18: 0 | G18: 0 | H18: 5740.8586 | I18: 10765.363 | J18: 6994.2921 | K18: 4987.7725 | L18: 4749.3128 | M18: 3756.4883 | N18: 10809.471 | O18: 3941.0292 | P18: 13615.383
A19: Fijo | B19: Oficina | C19: Telefonia | E19: 716.93961 | F19: 947.894 | G19: 558.75528 | H19: 0 | I19: 2075.049 | J19: 0 | K19: 1546.173 | L19: 1020.6216 | M19: 333.36824 | N19: 668.79451 | O19: 919.83326 | P19: 1577.9017
A20: Fijo | B20: Oficina | C20: Prestamo | D20: Préstamo Bco. Chile - Redco Perú | E20: 0 | F20: 0 | G20: 0 | H20: 0 | I20: 0 | J20: 5658.2315 | K20: 5585.8718 | L20: 5630.5689 | M20: 5649.6021 | N20: 5601.5838 | O20: 5381.6622 | P20: 0
A21: Fijo | B21: Extras personas | E21: 4574.0405 | F21: 4427.5118 | G21: 5067.7415 | H21: 2404.6587 | I21: 5844.4873 | J21: 3856.6463 | K21: 4005.1474 | L21: 4380.3484 | M21: 4268.1498 | N21: 4189.2387 | O21: 745.20585 | P21: 1865.8346
A22: Fijo | B22: Externo | C22: Pago servicio | D22: Salcedo & Cia. Limitada (Asesoria Tributaria) | E22: 805.48795 | F22: 762.41593 | G22: 761.73587 | H22: 0 | I22: 812.02227 | J22: 808.67636 | K22: 801.5615 | L22: 808.21056 | M22: 815.42955 | N22: 812.03243 | O22: 781.65191 | P22: 779.36527
A23: Fijo | B23: Externo | C23: Pago servicio | D23: Transp. Nueva Apoquindo Ltda. Mayo | E23: 562.26721 | F23: 326.20298 | G23: 606.07689 | H23: 0 | I23: 962.64 | J23: 396.47871 | K23: 581.36119 | L23: 429.1483 | M23: 449.21346 | N23: 872.42694 | O23: 201.39358 | P23: 399.30844
A24: Fijo | B24: Externo | C24: Pago servicio | D24: Transp. Nueva Apoquindo Ltda. Abril | E24: 0 | F24: 607.48983 | G24: 0 | H24: 0 | I24: 549.58164 | J24: 0 | K24: 0 | L24: 0 | M24: 0 | N24: 0 | O24: 0 | P24: 0
A25: Fijo | B25: Externo | C25: Pago servicio | D25: Salcedo & Cia. Limitada (Asesoria Tributaria) marzo y abril | E25: 0 | F25: 763.88047 | G25: 0 | H25: 0 | I25: 1593.8336 | J25: 0 | K25: 0 | L25: 0 | M25: 0 | N25: 0 | O25: 0 | P25: 0
A26: Fijo | B26: Externo | C26: Pago servicio | D26: Par Cuatro aromatizacion oficina mayo | E26: 135.91229 | F26: 129.00751 | G26: 128.10637 | H26: 0 | I26: 138.55188 | J26: 136.38563 | K26: 0 | L26: 0 | M26: 0 | N26: 0 | O26: 0 | P26: 0
A27: Fijo | B27: Externo | C27: Pago servicio | D27: Par Cuatro aromatizacion oficina factura abril | E27: 0 | F27: 129.08432 | G27: 0 | H27: 0 | I27: 134.70824 | J27: 0 | K27: 0 | L27: 0 | M27: 0 | N27: 0 | O27: 0 | P27: 0
A28: Fijo | B28: Externo | C28: Pago servicio | D28: Nespresso Chile S.A. mayo | E28: 566.17364 | F28: 533.58798 | G28: 1120.0087 | H28: 0 | I28: 292.02946 | J28: 292.65614 | K28: 283.99569 | L28: 574.58974 | M28: 291.652 | N28: 289.27833 | O28: 277.10786 | P28: 274.2178
A29: Fijo | B29: Externo | C29: Pago servicio | D29: Nespresso Chile S.A. abril | E29: 0 | F29: 0 | G29: 0 | H29: 0 | I29: 590.54125 | J29: 0 | K29: 0 | L29: 0 | M29: 0 | N29: 0 | O29: 0 | P29: 0
A30: Fijo | B30: Dueño | C30: Credito | E30: 0 | F30: 2174.0077 | G30: 1084.7913 | H30: 1093.5926 | I30: 1140.9585 | J30: 1130.8559 | K30: 2234.0181 | L30: 1126.2103 | M30: 1130.6971 | N30: 0 | O30: 1077.8746 | P30: 1066.6331
A31: Fijo | B31: Dueño | C31: Seguro | E31: 298.83699 | F31: 230.32675 | G31: 171.39669 | H31: 173.79341 | I31: 41.82246 | J31: 41.637871 | K31: 318.70707 | L31: 41.809872 | M31: 325.10662 | N31: 41.84363 | O31: 176.79498 | P31: 40.017722
A32: Fijo | B32: Comercial | C32: Publicidad | E32: 917.41098 | F32: 864.61015 | G32: 1721.1988 | H32: 0 | I32: 1815.0521 | J32: 899.49032 | K32: 888.47647 | L32: 895.79525 | M32: 1130.6291 | N32: 892.04442 | O32: 2363.8329 | P32: 1026.5726
A33: Fijo | B33: Bancarios | E33: 702.15641 | F33: 185.02346 | G33: 224.98218 | H33: 139.82023 | I33: 553.76956 | J33: 343.9746 | K33: 456.20014 | L33: 203.9144 | M33: 420.02786 | N33: 280.12444 | O33: 1209.8837 | P33: 408.12454
A34: Fijo | B34: Compañía | E34: 1186.458 | F34: 2675.0934 | G34: 2662.6843 | H34: 2684.2877 | I34: 2807.8747 | J34: 0 | K34: 2748.9355 | L34: 5543.1595 | M34: 2782.6217 | N34: 5519.9495 | O34: 2652.6266 | P34: 2624.9613
A35: Total Fijo | E35: 238051.86 | F35: 224195.43 | G35: 229339.48 | H35: 215847.71 | I35: 246217.1 | J35: 189332.73 | K35: 262835.63 | L35: 269722.72 | M35: 261923.09 | N35: 280131.44 | O35: 229085.21 | P35: 272147.06
A36: Variable | B36: Impuestos | C36: Impuesto | D36: PPM 6,8% | E36: 0 | F36: 0 | G36: 0 | H36: 0 | I36: 0 | J36: 0 | K36: 0 | L36: 0 | M36: 0 | N36: 0 | O36: 0 | P36: 0
A37: Variable | B37: Impuestos | C37: Impuesto | D37: IVA DEBITO FISCAL | E37: 87861.647 | F37: 75662.112 | G37: 16948.437 | H37: 41207.305 | I37: 18324.099 | J37: 25946.446 | K37: 25109.218 | L37: 0 | M37: 100217.1 | N37: 82725.581 | O37: 69233.677 | P37: 11568.045
A38: Variable | B38: Impuestos | C38: Impuesto | D38: IMPTO.ADICIONAL 20% | E38: 2122.541 | F38: 380.23644 | G38: 718.38769 | H38: 416.78089 | I38: 398.3244 | J38: 438.25587 | K38: 472.24604 | L38: 0 | M38: 447.51082 | N38: 0 | O38: 714.69226 | P38: 140.52697
A39: Variable | B39: Impuestos | C39: Impuesto | D39: IMPTO.TIMBRE Y ESTAMPILLA | E39: 0 | F39: 0 | G39: 0 | H39: 0 | I39: 0 | J39: 126.32494 | K39: 0 | L39: 0 | M39: 0 | N39: 0 | O39: 0 | P39: 0
A40: Variable | B40: Impuestos | C40: REDTEC | E40: 0 | F40: 0 | G40: 0 | H40: 0 | I40: 0 | J40: 0 | K40: 0 | L40: 0 | M40: 0 | N40: 8002.0732 | O40: 0 | P40: 0
A41: Variable | B41: Externo | C41: Pago servicio | D41: Cintamatrix Ltda. | E41: 72.737585 | F41: 168.21598 | G41: 0 | H41: 0 | I41: 58.34096 | J41: 0 | K41: 0 | L41: 0 | M41: 0 | N41: 0 | O41: 71.037464 | P41: 0
A42: Variable | B42: Externo | C42: Pago servicio | D42: CONSTRUCCION SERVI TRES SPA | E42: 0 | F42: 0 | G42: 0 | H42: 0 | I42: 129.64658 | J42: 0 | K42: 0 | L42: 0 | M42: 0 | N42: 0 | O42: 0 | P42: 0
A43: Variable | B43: Externo | C43: Pago servicio | D43: Cynthia Ordoñes - coach Osacar Cáceres | E43: 5504.2298 | F43: 3751.6137 | G43: 3289.5456 | H43: 0 | I43: 0 | J43: 0 | K43: 0 | L43: 0 | M43: 0 | N43: 0 | O43: 0 | P43: 0
A44: Variable | B44: Externo | C44: Pago servicio | D44: Dsignos Spa | E44: 8634.148 | F44: 0 | G44: 172.01657 | H44: 0 | I44: 0 | J44: 0 | K44: 0 | L44: 0 | M44: 0 | N44: 0 | O44: 0 | P44: 0
A45: Variable | B45: Externo | C45: Pago servicio | D45: Edge SpA 3 sillas | E45: 0 | F45: 0 | G45: 363.24941 | H45: 0 | I45: 0 | J45: 0 | K45: 0 | L45: 0 | M45: 0 | N45: 0 | O45: 0 | P45: 0
A46: Variable | B46: Externo | C46: Pago servicio | D46: Factura Sumiprint SPA | E46: 0 | F46: 0 | G46: 0 | H46: 0 | I46: 174.91938 | J46: 0 | K46: 114.13136 | L46: 0 | M46: 115.52996 | N46: 57.29431 | O46: 0 | P46: 0
A47: Variable | B47: Externo | C47: Pago servicio | D47: Marisol Corvalan Notaria | E47: 176.21339 | F47: 0 | G47: 0 | H47: 0 | I47: 0 | J47: 0 | K47: 0 | L47: 0 | M47: 0 | N47: 0 | O47: 0 | P47: 0
A48: Variable | B48: Externo | C48: Pago servicio | D48: Patricio Vegara (EEUU) | E48: 42198.646 | F48: 0 | G48: 13886.803 | H48: 0 | I48: 0 | J48: 22741.378 | K48: 0 | L48: 7569.2946 | M48: 0 | N48: 1156.1931 | O48: 34823.875 | P48: 15173.832
A49: Variable | B49: Externo | C49: Pago servicio | D49: Armando Olavarría | E49: 0 | F49: 0 | G49: 0 | H49: 0 | I49: 1539.4455 | J49: 0 | K49: 0 | L49: 0 | M49: 0 | N49: 342.45337 | O49: 0 | P49: 0
A50: Variable | B50: Externo | C50: Pago servicio | D50: Consultora Hominum SpA Fact. 23-Proceso reclutamiento ingenieros | E50: 0 | F50: 0 | G50: 0 | H50: 0 | I50: 914.87231 | J50: 0 | K50: 0 | L50: 0 | M50: 0 | N50: 0 | O50: 0 | P50: 0
A51: Variable | B51: Externo | C51: Pago servicio | D51: Andes IP Abogados Limitada | E51: 1989.0649 | F51: 0 | G51: 0 | H51: 0 | I51: 81.353772 | J51: 0 | K51: 0 | L51: 0 | M51: 0 | N51: 0 | O51: 0 | P51: 341.58824
A52: Variable | B52: Externo | C52: Pago servicio | D52: Gonzalo Díaz | E52: 0 | F52: 0 | G52: 0 | H52: 0 | I52: 0 | J52: 0 | K52: 0 | L52: 0 | M52: 0 | N52: 0 | O52: 0 | P52: 0
... A56: Variable | B56: Externo | C56: Pago servicio | D56: Holaleon SPA mural jardin infantil | E56: 0 | F56: 0 | G56: 0 | H56: 0 | I56: 0 | J56: 0 | K56: 0 | L56: 0 | M56: 0 | N56: 0 | O56: 2449.5677 | P56: 0
A57: Variable | B57: Externo | C57: REDTEC | E57: 0 | F57: 81.834883 | G57: 0 | H57: 0 | I57: 0 | J57: 323.9461 | K57: 0 | L57: 1075.3844 | M57: 0 | N57: 0 | O57: 0 | P57: 0
A58: Variable | B58: Oficina | C58: Asesoria | E58: 0 | F58: 0 | G58: 135.84143 | H58: 0 | I58: 0 | J58: 0 | K58: 139.97931 | L58: 0 | M58: 0 | N58: 198.5693 | O58: 0 | P58: 0
A59: Variable | B59: Oficina | C59: Caja Chica | E59: 0 | F59: 0 | G59: 0 | H59: 0 | I59: 0 | J59: 215.96406 | K59: 281.00708 | L59: 120.70975 | M59: 124.32386 | N59: 145.84551 | O59: 444.85076 | P59: 113.93913
A60: Variable | B60: Oficina | C60: Contribuciones | E60: 0 | F60: 0 | G60: 0 | H60: 51.355011 | I60: 2309.8542 | J60: 0 | K60: 2278.3598 | L60: 0 | M60: 2344.017 | N60: 0 | O60: 0 | P60: 2211.2075
A61: Variable | B61: Oficina | C61: Pago servicio | D61: Cristián Flores Serv. Flexline | E61: 0 | F61: 0 | G61: 0 | H61: 0 | I61: 0 | J61: 584.56505 | K61: 0 | L61: 0 | M61: 0 | N61: 0 | O61: 0 | P61: 0
A62: Variable | B62: Oficina | C62: Pago servicio | D62: Diego Fuente Mant. Baños of | E62: 0 | F62: 0 | G62: 0 | H62: 0 | I62: 0 | J62: 276.81194 | K62: 266.65067 | L62: 0 | M62: 0 | N62: 0 | O62: 98.428366 | P62: 0
A63: Variable | B63: Oficina | C63: Pago servicio | D63: Gtos. personal Redco- Hamb | E63: 0 | F63: 0 | G63: 0 | H63: 0 | I63: 0 | J63: 0 | K63: 495.37096 | L63: 0 | M63: 0 | N63: 0 | O63: 0 | P63: 1040.5575
A64: Variable | B64: Oficina | C64: Regalo | E64: 0 | F64: 0 | G64: 127.58154 | H64: 0 | I64: 0 | J64: 0 | K64: 0 | L64: 0 | M64: 0 | N64: 0 | O64: 0 | P64: 0
A65: Variable | B65: Oficina | C65: Rendición | E65: 0 | F65: 0 | G65: 35.095513 | H65: 44.04566 | I65: 0 | J65: 0 | K65: 0 | L65: 0 | M65: 0 | N65: 0 | O65: 0 | P65: 0
A66: Variable | B66: Oficina | C66: Software | E66: 1887.7774 | F66: 1871.8073 | G66: 0 | H66: 1928.3417 | I66: 2040.8757 | J66: 2023.0174 | K66: 4142.2629 | L66: 0 | M66: 0 | N66: 4146.668 | O66: 4175.3232 | P66: 4497.576
A67: Variable | B67: Oficina | C67: Varios | E67: 102.90862 | F67: 0 | G67: 62.517951 | H67: 0 | I67: 102.70624 | J67: 0 | K67: 0 | L67: 0 | M67: 0 | N67: 0 | O67: 0 | P67: 0
A68: Variable | B68: Oficina | C68: Otro | E68: 0 | F68: 648.988 | G68: 0 | H68: 0 | I68: 0 | J68: 0 | K68: 0 | L68: 0 | M68: 0 | N68: 0 | O68: 0 | P68: 0
A69: Variable | B69: Oficina | C69: Tintas | E69: 0 | F69: 0 | G69: 0 | H69: 0 | I69: 0 | J69: 0 | K69: 0 | L69: 0 | M69: 0 | N69: 0 | O69: 0 | P69: 0
A70: Variable | B70: Oficina | C70: REDTEC | E70: 0 | F70: 0 | G70: 0 | H70: 0 | I70: 0 | J70: 0 | K70: 0 | L70: 0 | M70: 0 | N70: 1381.4202 | O70: 0 | P70: 0
A71: Variable | B71: Extras personas | E71: 84561.24 | F71: 24650.077 | G71: 12434.175 | H71: 3310.0725 | I71: 12154.319 | J71: 1725.6079 | K71: 623.64593 | L71: 101.83891 | M71: 0 | N71: 25309.82 | O71: 27730.612 | P71: 3460.6351
A72: Variable | B72: Dueño | C72: Impuesto | D72: Pago Impto. Rta. AT2024 E.Rubio | E72: 0 | F72: 0 | G72: 0 | H72: 17895.682 | I72: 0 | J72: 1535.052 | K72: 0 | L72: 3382.0841 | M72: 0 | N72: 0 | O72: 0 | P72: 13.404424
A73: Variable | B73: Dueño | C73: EERR | D73: Cta. Cte Redcross | E73: 0 | F73: 0 | G73: 0 | H73: 0 | I73: 0 | J73: 0 | K73: 0 | L73: 865.67588 | M73: 0 | N73: 0 | O73: 0 | P73: 0
A74: Variable | B74: Dueño | C74: EERR | D74: Cta. Cte Redco Global Perú | E74: 0 | F74: 0 | G74: 0 | H74: 0 | I74: 32677.978 | J74: 0 | K74: 0 | L74: 0 | M74: 0 | N74: 0 | O74: 0 | P74: 0
A75: Variable | B75: Dueño | C75: Donación | E75: 0 | F75: 1037.9474 | G75: 0 | H75: 0 | I75: 435.78681 | J75: 0 | K75: 0 | L75: 19356.92 | M75: 0 | N75: 0 | O75: 0 | P75: 20441.989
A76: Variable | B76: Dueño | C76: TAG | E76: 0 | F76: 0 | G76: 0 | H76: 0 | I76: 59.489258 | J76: 11.287362 | K76: 55.216733 | L76: 106.44908 | M76: 84.949418 | N76: 71.211488 | O76: 10.21408 | P76: 211.80131
A77: Variable | B77: Viajes | C77: Alojamiento | E77: 615.97595 | F77: 352.01985 | G77: 0 | H77: 0 | I77: 0 | J77: 0 | K77: 0 | L77: 0 | M77: 0 | N77: 0 | O77: 0 | P77: 0
A78: Variable | B78: Viajes | C78: Examenes | E78: 0 | F78: 0 | G78: 0 | H78: 80.654904 | I78: 438.26317 | J78: 49.883379 | K78: 245.85093 | L78: 0 | M78: 0 | N78: 12.85058 | O78: 0 | P78: 0
A79: Variable | B79: Viajes | C79: Pasaje | E79: 20476.158 | F79: 5154.7548 | G79: 5079.8859 | H79: 1472.8581 | I79: 0 | J79: 0 | K79: 7784.4351 | L79: 0 | M79: 4966.4763 | N79: 4102.6322 | O79: 0 | P79: 0 | Q79: =+SUM(E79:P79) -> 49037.201 | R79: 411000
A80: Variable | B80: Viajes | C80: Reembolso | E80: 0 | F80: 0 | G80: 0 | H80: 0 | I80: 1601.3531 | J80: 0 | K80: 0 | L80: 90.332294 | M80: 0 | N80: 0 | O80: 0 | P80: 0
A81: Variable | B81: Viajes | C81: Rendición | E81: 1081.3379 | F81: 86.540937 | G81: 171.90293 | H81: 8037.7153 | I81: 1829.2544 | J81: 1344.3385 | K81: 244.17637 | L81: 2950.699 | M81: 39.500761 | N81: 1166.3293 | O81: 140.67312 | P81: 0
A82: Variable | B82: Viajes | C82: Seguro | E82: 0 | F82: 0 | G82: 0 | H82: 225.2359 | I82: 0 | J82: 0 | K82: 0 | L82: 0 | M82: 0 | N82: 0 | O82: 0 | P82: 0
A83: Variable | B83: Viajes | C83: Tarjeta | E83: 12103.167 | F83: 5251.067 | G83: 0 | H83: 0 | I83: 0 | J83: 0 | K83: 0 | L83: 0 | M83: 0 | N83: 0 | O83: 0 | P83: 0
A84: Variable | B84: Viajes | C84: Traslado | E84: 0 | F84: 0 | G84: 29.960844 | H84: 0 | I84: 0 | J84: 0 | K84: 0 | L84: 0 | M84: 0 | N84: 0 | O84: 0 | P84: 0
A85: Variable | B85: Sueldos | E85: 275.33343 | F85: 72.656315 | G85: 118.81024 | H85: 0 | I85: 0 | J85: 314.94795 | K85: 266.6496 | L85: 376.38456 | M85: 465.60715 | N85: 461.81771 | O85: 1024.5723 | P85: 6469.381
A86: Variable | B86: Compañía | E86: 11750.39 | F86: 2604.9655 | G86: 0 | H86: 0 | I86: 4112.9766 | J86: 0 | K86: 2944.5209 | L86: 202.59168 | M86: 0 | N86: 0 | O86: 10693.744 | P86: 9987.7495
A87: Variable | B87: Comercial | C87: Rendición | E87: 228.87697 | F87: 0 | G87: 0 | H87: 0 | I87: 0 | J87: 0 | K87: 0 | L87: 0 | M87: 0 | N87: 0 | O87: 0 | P87: 167.54665
A88: Variable | B88: Comercial | C88: Publicidad | E88: 0 | F88: 0 | G88: 0 | H88: 0 | I88: 559.42498 | J88: 0 | K88: 0 | L88: 0 | M88: 0 | N88: 0 | O88: 0 | P88: 0
A89: Total Variable | E89: 281642.39 | F89: 121774.84 | G89: 53574.211 | H89: 74670.047 | I89: 79943.283 | J89: 57657.827 | K89: 45463.721 | L89: 37064.04 | M89: 108880.6 | N89: 133417.98 | O89: 193894.4 | P89: 76973.938
A90: Adicionales | B90: Externo | C90: Pago servicio | D90: Alejandro Espinosa Factura 35 dic.2023 | E90: 0 | F90: 0 | G90: 0 | H90: 0 | I90: 0 | J90: 0 | K90: 0 | L90: 0 | M90: 0 | N90: 4911.296 | O90: 0 | P90: 0
A91: Adicionales | B91: Externo | C91: Pago servicio | D91: Anna Usoltceva Intrepete Español a Ruso 200 USD | E91: 0 | F91: 0 | G91: 216.20127 | H91: 0 | I91: 497.88921 | J91: 699.0775 | K91: 0 | L91: 404.77513 | M91: 0 | N91: 0 | O91: 788.85398 | P91: 0
A92: Adicionales | B92: Externo | C92: Pago servicio | D92: Darwin Varas Diseño Losas Piscinas Hormigon | E92: 0 | F92: 0 | G92: 1745.82 | H92: 0 | I92: 0 | J92: 0 | K92: 0 | L92: 431.9637 | M92: 0 | N92: 0 | O92: 0 | P92: 0
A93: Adicionales | B93: Externo | C93: Pago servicio | D93: Enrique Molina Factura 1 | E93: 11892.875 | F93: 16400.787 | G93: 0 | H93: 0 | I93: 16135.033 | J93: 0 | K93: 16383.137 | L93: 0 | M93: 0 | N93: 0 | O93: 0 | P93: 0
A94: Adicionales | B94: Externo | C94: Pago servicio | D94: Fernando Mora | E94: 0 | F94: 5071.0392 | G94: 4760.9106 | H94: 0 | I94: 0 | J94: 0 | K94: 0 | L94: 0 | M94: 0 | N94: 0 | O94: 0 | P94: 0
A95: Adicionales | B95: Externo | C95: Pago servicio | D95: Freddy Centeno | E95: 1650.9867 | F95: 1712.9425 | G95: 1631.5404 | H95: 1790.6728 | I95: 1770.0764 | J95: 1891.6248 | K95: 0 | L95: 1543.123 | M95: 0 | N95: 3303.4087 | O95: 0 | P95: 0
A96: Adicionales | B96: Externo | C96: Pago servicio | D96: Juan Rivera | E96: 621.23493 | F96: 28847.599 | G96: 0 | H96: 0 | I96: 0 | J96: 0 | K96: 0 | L96: 0 | M96: 0 | N96: 0 | O96: 0 | P96: 10651.9
A97: Adicionales | B97: Externo | C97: Pago servicio | D97: León Arzola (Electrico) | E97: 0 | F97: 0 | G97: 0 | H97: 0 | I97: 1826.159 | J97: 0 | K97: 0 | L97: 0 | M97: 0 | N97: 0 | O97: 0 | P97: 0
A98: Adicionales | B98: Externo | C98: Pago servicio | D98: León Consulting Chile SpA ( Felipe León) | E98: 0 | F98: 0 | G98: 8620.8893 | H98: 0 | I98: 0 | J98: 0 | K98: 0 | L98: 0 | M98: 0 | N98: 0 | O98: 0 | P98: 0
A99: Adicionales | B99: Externo | C99: Pago servicio | D99: Rodrigo Godoy | E99: 0 | F99: 0 | G99: 0 | H99: 0 | I99: 1367.9966 | J99: 0 | K99: 0 | L99: 0 | M99: 0 | N99: 0 | O99: 0 | P99: 0
A100: Adicionales | B100: Externo | C100: Pago servicio | D100: SGS MINERALS S.A. 50% | E100: 38183.68 | F100: 0 | G100: 0 | H100: 0 | I100: 0 | J100: 0 | K100: 0 | L100: 0 | M100: 0 | N100: 0 | O100: 0 | P100: 0
A101: Adicionales | B101: Externo | C101: Pago servicio | D101: ASMIN Industrial Ltda. Fact. 3330 PFS - Los Calatos EdP01 | E101: 0 | F101: 0 | G101: 0 | H101: 0 | I101: 0 | J101: 18250.566 | K101: 17011.653 | L101: 0 | M101: 0 | N101: 0 | O101: 0 | P101: 0
... A121: Adicionales | B121: Externo | C121: Pago servicio | D121: Carlos Castañeda | E121: 0 | F121: 0 | G121: 0 | H121: 0 | I121: 0 | J121: 0 | K121: 0 | L121: 0 | M121: 0 | N121: 0 | O121: 0 | P121: 6064.3301
A122: Adicionales | B122: Externo | C122: REDTEC | E122: 0 | F122: 0 | G122: 0 | H122: 0 | I122: 0 | J122: 0 | K122: 0 | L122: 0 | M122: 0 | N122: 0 | O122: 111920.12 | P122: 0
A123: Adicionales | B123: Dueño | C123: EERR | D123: R + Ingineering Arriendo of. Dic + gtia. Of. 1502 | E123: 0 | F123: 0 | G123: 0 | H123: 0 | I123: 0 | J123: 0 | K123: 0 | L123: 0 | M123: 0 | N123: 0 | O123: 0 | P123: 6643.4918
A124: Adicionales | B124: Dueño | C124: EERR | D124: R + Ingineering Gtos. Implementación of. 1502 | E124: 0 | F124: 0 | G124: 0 | H124: 0 | I124: 0 | J124: 0 | K124: 0 | L124: 0 | M124: 0 | N124: 0 | O124: 0 | P124: 24258.54
...

Sheet Gasto total_Análisis (2)
C3: Gasto Proyectado REDCO sin EEUU
O4: =+O8-N8 -> 28.076021
C5: Item | D5: ene | E5: feb | F5: mar | G5: abr | H5: may | I5: jun | J5: jul | K5: ago | L5: sept | M5: oct | N5: nov | O5: dic | P5: Total | Q5: Promedio
C6: ='Gasto Septiembre'!A9 -> Sueldos | D6: =('Gasto Diciembre (2)'!B8)/1000 -> 302.50526 | E6: =('Gasto Diciembre (2)'!C8)/1000 -> 278.5006 | F6: =('Gasto Diciembre (2)'!D8)/1000 -> 288.865 | G6: =('Gasto Diciembre (2)'!E8)/1000 -> 271.76518 | H6: =('Gasto Diciembre (2)'!F8)/1000 -> 312.95631 | I6: =('Gasto Diciembre (2)'!G8)/1000 -> 233.21148 | J6: =('Gasto Diciembre (2)'!H8)/1000 -> 335.85132 | K6: =('Gasto Diciembre (2)'!I8)/1000 -> 306.40784 | ... O6: =('Gasto Diciembre (2)'!M8)/1000 -> 316.82887 | P6: =+SUM(D6:O6) -> 3489.543 | Q6: =+AVERAGE(D6:O6) -> 290.79525
C7: ='Gasto Septiembre'!A10 -> Externo | D7: =('Gasto Diciembre (2)'!B9)/1000 -> 123.39341 | E7: =('Gasto Diciembre (2)'!C9)/1000 -> 95.218967 | F7: =('Gasto Diciembre (2)'!D9)/1000 -> 63.271157 | G7: =('Gasto Diciembre (2)'!E9)/1000 -> 9.5349993 | H7: =('Gasto Diciembre (2)'!F9)/1000 -> 90.110012 | I7: =('Gasto Diciembre (2)'!G9)/1000 -> 101.18794 | J7: =('Gasto Diciembre (2)'!H9)/1000 -> 53.135335 | K7: =('Gasto Diciembre (2)'!I9)/1000 -> 107.30165 | ... O7: =('Gasto Diciembre (2)'!M9)/1000 -> 97.664797 | P7: =+SUM(D7:O7) -> 948.81357 | Q7: =+AVERAGE(D7:O7) -> 79.067798
C8: ='Gasto Septiembre'!A11 -> Oficina | D8: =('Gasto Diciembre (2)'!B10)/1000 -> 46.73479 | E8: =('Gasto Diciembre (2)'!C10)/1000 -> 35.698197 | F8: =('Gasto Diciembre (2)'!D10)/1000 -> 25.091045 | G8: =('Gasto Diciembre (2)'!E10)/1000 -> 34.665023 | H8: =('Gasto Diciembre (2)'!F10)/1000 -> 46.509808 | I8: =('Gasto Diciembre (2)'!G10)/1000 -> 36.712331 | J8: =('Gasto Diciembre (2)'!H10)/1000 -> 41.59982 | K8: =('Gasto Diciembre (2)'!I10)/1000 -> 37.109385 | ... O8: =('Gasto Diciembre (2)'!M10)/1000 -> 70.662434 | P8: =+SUM(D8:O8) -> 508.93863 | Q8: =+AVERAGE(D8:O8) -> 42.411552
C9: ='Gasto Septiembre'!A12 -> Extras personas | D9: =('Gasto Diciembre (2)'!B11)/1000 -> 129.39817 | E9: =('Gasto Diciembre (2)'!C11)/1000 -> 40.431764 | F9: =('Gasto Diciembre (2)'!D11)/1000 -> 19.643364 | G9: =('Gasto Diciembre (2)'!E11)/1000 -> 12.341404 | H9: =('Gasto Diciembre (2)'!F11)/1000 -> 18.451806 | I9: =('Gasto Diciembre (2)'!G11)/1000 -> 6.0272542 | J9: =('Gasto Diciembre (2)'!H11)/1000 -> 5.0827933 | K9: =('Gasto Diciembre (2)'!I11)/1000 -> 4.9271873 | ... O9: =('Gasto Diciembre (2)'!M11)/1000 -> 13.829525 | P9: =+SUM(D9:O9) -> 313.73029 | Q9: =+AVERAGE(D9:O9) -> 26.144191
C10: ='Gasto Septiembre'!A13 -> Viajes | D10: =('Gasto Diciembre (2)'!B12)/1000 -> 70.94038 | E10: =('Gasto Diciembre (2)'!C12)/1000 -> 15.541723 | F10: =('Gasto Diciembre (2)'!D12)/1000 -> 6.4251697 | G10: =('Gasto Diciembre (2)'!E12)/1000 -> 19.654064 | H10: =('Gasto Diciembre (2)'!F12)/1000 -> 11.217311 | I10: =('Gasto Diciembre (2)'!G12)/1000 -> 6.643918 | J10: =('Gasto Diciembre (2)'!H12)/1000 -> 10.766462 | K10: =('Gasto Diciembre (2)'!I12)/1000 -> 12.765451 | ... O10: =('Gasto Diciembre (2)'!M12)/1000 -> 16.0338 | P10: =+SUM(D10:O10) -> 192.24619 | Q10: =+AVERAGE(D10:O10) -> 16.020516
C11: ='Gasto Septiembre'!A14 -> Compañía | D11: =('Gasto Diciembre (2)'!B13)/1000 -> 12.901351 | E11: =('Gasto Diciembre (2)'!C13)/1000 -> 5.280059 | F11: =('Gasto Diciembre (2)'!D13)/1000 -> 2.6626843 | G11: =('Gasto Diciembre (2)'!E13)/1000 -> 2.6842877 | H11: =('Gasto Diciembre (2)'!F13)/1000 -> 6.9208513 | I11: =('Gasto Diciembre (2)'!G13)/1000 -> 0 | J11: =('Gasto Diciembre (2)'!H13)/1000 -> 5.6590789 | K11: =('Gasto Diciembre (2)'!I13)/1000 -> 5.7457512 | ... O11: =('Gasto Diciembre (2)'!M13)/1000 -> 12.612711 | P11: =+SUM(D11:O11) -> 76.115717 | Q11: =+AVERAGE(D11:O11) -> 6.3429764
C12: ='Gasto Septiembre'!A15 -> Comercial | D12: =('Gasto Diciembre (2)'!B14)/1000 -> 1.146288 | E12: =('Gasto Diciembre (2)'!C14)/1000 -> 0.86461015 | F12: =('Gasto Diciembre (2)'!D14)/1000 -> 1.7211988 | G12: =('Gasto Diciembre (2)'!E14)/1000 -> 0 | H12: =('Gasto Diciembre (2)'!F14)/1000 -> 2.3744771 | I12: =('Gasto Diciembre (2)'!G14)/1000 -> 0.89949032 | J12: =('Gasto Diciembre (2)'!H14)/1000 -> 0.88847647 | K12: =('Gasto Diciembre (2)'!I14)/1000 -> 0.89579525 | ... O12: =('Gasto Diciembre (2)'!M14)/1000 -> 1.1941192 | P12: =+SUM(D12:O12) -> 14.370962 | Q12: =+AVERAGE(D12:O12) -> 1.1975801
C13: ='Gasto Septiembre'!A16 -> Bancarios | D13: =('Gasto Diciembre (2)'!B15)/1000 -> 1.010502 | E13: =('Gasto Diciembre (2)'!C15)/1000 -> 0.71911981 | F13: =('Gasto Diciembre (2)'!D15)/1000 -> 0.47228157 | G13: =('Gasto Diciembre (2)'!E15)/1000 -> 0.36444023 | H13: =('Gasto Diciembre (2)'!F15)/1000 -> 0.81385956 | I13: =('Gasto Diciembre (2)'!G15)/1000 -> 1.6420746 | J13: =('Gasto Diciembre (2)'!H15)/1000 -> 2.1692001 | K13: =('Gasto Diciembre (2)'!I15)/1000 -> 1.1940144 | ... O13: =('Gasto Diciembre (2)'!M15)/1000 -> 1.5701245 | P13: =+SUM(D13:O13) -> 13.501653 | Q13: =+AVERAGE(D13:O13) -> 1.1251377
C14: Total | D14: =+SUM(D6:D13) -> 688.03016 | E14: =+SUM(E6:E13) -> 472.25504 | F14: =+SUM(F6:F13) -> 408.1519 | G14: =+SUM(G6:G13) -> 351.0094 | H14: =+SUM(H6:H13) -> 489.35443 | I14: =+SUM(I6:I13) -> 386.32449 | J14: =+SUM(J6:J13) -> 455.15249 | K14: =+SUM(K6:K13) -> 476.34708 | ... Q14: =+SUM(Q6:Q13) -> 463.105
C15: Acumulado | D15: =+SUM($D$14:D14) -> 688.03016 | E15: =+SUM($D$14:E14) -> 1160.2852 | F15: =+SUM($D$14:F14) -> 1568.4371 | G15: =+SUM($D$14:G14) -> 1919.4465 | H15: =+SUM($D$14:H14) -> 2408.8009 | I15: =+SUM($D$14:I14) -> 2795.1254 | J15: =+SUM($D$14:J14) -> 3250.2779 | K15: =+SUM($D$14:K14) -> 3726.625 | ... O15: =+SUM($D$14:O14) -> 5557.26
D16: =+D15/$O$15 -> 0.12380744 | E16: =+E15/$O$15 -> 0.20878728 | F16: =+F15/$O$15 -> 0.28223209 | G16: =+G15/$O$15 -> 0.3453944 | H16: =+H15/$O$15 -> 0.43345118 | I16: =+I15/$O$15 -> 0.50296826 | J16: =+J15/$O$15 -> 0.58487058 | K16: =+K15/$O$15 -> 0.67058676 | ... O16: =+O15/$O$15 -> 1
C18: Sueldo/total | D18: =+D6/D14 -> 0.43966861 | E18: =+E6/E14 -> 0.58972499 | F18: =+F6/F14 -> 0.70773896 | G18: =+G6/G14 -> 0.77423904 | H18: =+H6/H14 -> 0.63952892 | I18: =+I6/I14 -> 0.60366736 | J18: =+J6/J14 -> 0.73788748 | K18: =+K6/K14 -> 0.64324494 | ... M18: =+M6/M14 -> 0.60569456
C19: Externo/total | D19: =+D7/D14 -> 0.17934303 | E19: =+E7/E14 -> 0.20162615 | F19: =+F7/F14 -> 0.15501865 | G19: =+G7/G14 -> 0.027164513 | H19: =+H7/H14 -> 0.18414058 | I19: =+I7/I14 -> 0.26192473 | J19: =+J7/J14 -> 0.11674183 | K19: =+K7/K14 -> 0.22525938 | ... M19: =+M7/M14 -> 0.20205971
C20: Oficina/total | D20: =+D8/D14 -> 0.067925497 | E20: =+E8/E14 -> 0.075590928 | F20: =+F8/F14 -> 0.061474772 | G20: =+G8/G14 -> 0.098758104 | H20: =+H8/H14 -> 0.095043192 | I20: =+I8/I14 -> 0.095029779 | J20: =+J8/J14 -> 0.091397546 | K20: =+K8/K14 -> 0.07790409 | ... M20: =+M8/M14 -> 0.097829435
C23: Item | D23: ene | E23: feb | F23: mar | G23: abr | H23: may | I23: jun | J23: jul | K23: ago | L23: sept | M23: oct | N23: nov | O23: dic | P23: Total | Q23: Promedio
C24: ='Gasto Septiembre'!A30 -> Chile | D24: =('Gasto Diciembre (2)'!B28)/1000 -> 476.29051 | E24: =('Gasto Diciembre (2)'!C28)/1000 -> 313.31492 | F24: =('Gasto Diciembre (2)'!D28)/1000 -> 275.86855 | G24: =('Gasto Diciembre (2)'!E28)/1000 -> 231.52127 | H24: =('Gasto Diciembre (2)'!F28)/1000 -> 317.17005 | I24: =('Gasto Diciembre (2)'!G28)/1000 -> 288.14494 | J24: =('Gasto Diciembre (2)'!H28)/1000 -> 292.12749 | K24: =('Gasto Diciembre (2)'!I28)/1000 -> 299.21779 | ... O24: =('Gasto Diciembre (2)'!M28)/1000 -> 334.87696 | P24: =+SUM(D24:O24) -> 3770.4617 | Q24: =+AVERAGE(D24:O24) -> 314.20514
C25: ='Gasto Septiembre'!A31 -> Perú | D25: =('Gasto Diciembre (2)'!B29)/1000 -> 167.14016 | E25: =('Gasto Diciembre (2)'!C29)/1000 -> 109.66978 | F25: =('Gasto Diciembre (2)'!D29)/1000 -> 119.90377 | G25: =('Gasto Diciembre (2)'!E29)/1000 -> 98.13241 | H25: =('Gasto Diciembre (2)'!F29)/1000 -> 125.25863 | I25: =('Gasto Diciembre (2)'!G29)/1000 -> 82.824806 | J25: =('Gasto Diciembre (2)'!H29)/1000 -> 139.674 | K25: =('Gasto Diciembre (2)'!I29)/1000 -> 152.09422 | ... O25: =('Gasto Diciembre (2)'!M29)/1000 -> 159.18262 | P25: =+SUM(D25:O25) -> 1428.4109 | Q25: =+AVERAGE(D25:O25) -> 119.03424
C26: ='Gasto Septiembre'!A32 -> Brasil | D26: =('Gasto Diciembre (2)'!B30)/1000 -> 44.59949 | E26: =('Gasto Diciembre (2)'!C30)/1000 -> 49.27034 | F26: =('Gasto Diciembre (2)'!D30)/1000 -> 12.37958 | G26: =('Gasto Diciembre (2)'!E30)/1000 -> 21.355715 | H26: =('Gasto Diciembre (2)'!F30)/1000 -> 46.92575 | I26: =('Gasto Diciembre (2)'!G30)/1000 -> 15.35474 | J26: =('Gasto Diciembre (2)'!H30)/1000 -> 23.351 | K26: =('Gasto Diciembre (2)'!I30)/1000 -> 25.03507 | ... O26: =('Gasto Diciembre (2)'!M30)/1000 -> 36.3368 | P26: =+SUM(D26:O26) -> 358.38748 | Q26: =+AVERAGE(D26:O26) -> 29.865624
C27: Total | D27: =+SUM(D24:D26) -> 688.03016 | E27: =+SUM(E24:E26) -> 472.25504 | F27: =+SUM(F24:F26) -> 408.1519 | G27: =+SUM(G24:G26) -> 351.0094 | H27: =+SUM(H24:H26) -> 489.35443 | I27: =+SUM(I24:I26) -> 386.32449 | J27: =+SUM(J24:J26) -> 455.15249 | K27: =+SUM(K24:K26) -> 476.34708 | ... Q27: =+SUM(Q24:Q26) -> 463.105
C28: Acumulado | D28: =+SUM($D$27:D27) -> 688.03016 | E28: =+SUM($D$27:E27) -> 1160.2852 | F28: =+SUM($D$27:F27) -> 1568.4371 | G28: =+SUM($D$27:G27) -> 1919.4465 | H28: =+SUM($D$27:H27) -> 2408.8009 | I28: =+SUM($D$27:I27) -> 2795.1254 | J28: =+SUM($D$27:J27) -> 3250.2779 | K28: =+SUM($D$27:K27) -> 3726.625 | ... O28: =+SUM($D$27:O27) -> 5557.26
D29: =+D28/$O$28 -> 0.12380744 | E29: =+E28/$O$28 -> 0.20878728 | F29: =+F28/$O$28 -> 0.28223209 | G29: =+G28/$O$28 -> 0.3453944 | H29: =+H28/$O$28 -> 0.43345118 | I29: =+I28/$O$28 -> 0.50296826 | J29: =+J28/$O$28 -> 0.58487058 | K29: =+K28/$O$28 -> 0.67058676 | ... O29: =+O28/$O$28 -> 1
E31: =+(E27-D27)/D27 -> -0.31361288 | F31: =+(F27-E27)/E27 -> -0.13573839 | G31: =+(G27-F27)/F27 -> -0.14000304 | H31: =+(H27-G27)/G27 -> 0.39413486 | I31: =+(I27-H27)/H27 -> -0.21054258 | J31: =+(J27-I27)/I27 -> 0.17816111 | K31: =+(K27-J27)/J27 -> 0.0465659 | L31: =+(L27-K27)/K27 -> -0.22561245 | ... O31: =+(O27-N27)/N27 -> 0.19269656
C37: Gasto Proyectado REDCO con EEUU
C39: Item | D39: ene | E39: feb | F39: mar | G39: abr | H39: may | I39: jun | J39: jul | K39: ago | L39: sept | M39: oct | N39: nov | O39: dic | P39: Total | Q39: Promedio
C40: Chile | D40: 476.29051 | E40: 313.31492 | F40: 275.86855 | G40: 231.52127 | H40: 317.17005 | I40: 288.14494 | J40: 292.12749 | K40: 299.21779 | L40: 267.60024 | M40: 356.05444 | N40: 318.27454 | O40: 334.87696 | P40: =+SUM(D40:O40) -> 3770.4617 | Q40: =+AVERAGE(D40:O40) -> 314.20514
C41: Perú | D41: 167.14016 | E41: 109.66978 | F41: 119.90377 | G41: 98.13241 | H41: 125.25863 | I41: 82.824806 | J41: 139.674 | K41: 152.09422 | L41: 73.594 | M41: 88.14845 | N41: 112.788 | O41: 159.18262 | P41: =+SUM(D41:O41) -> 1428.4109 | Q41: =+AVERAGE(D41:O41) -> 119.03424
C42: Brasil | D42: 44.59949 | E42: 49.27034 | F42: 12.37958 | G42: 21.355715 | H42: 46.92575 | I42: 15.35474 | J42: 23.351 | K42: 25.03507 | L42: 27.683 | M42: 42.455 | N42: 13.641 | O42: 36.3368 | P42: =+SUM(D42:O42) -> 358.38748 | Q42: =+AVERAGE(D42:O42) -> 29.865624
C43: EEUU | D43: 0 | E43: 0 | F43: 29.806 | G43: 0 | H43: 33.409 | I43: 8.512 | J43: 71.468 | K43: 61.963 | L43: 14.9 | M43: 32.355 | N43: 7.5 | O43: 150.67 | P43: =+SUM(D43:O43) -> 410.583 | Q43: =+AVERAGE(D43:O43) -> 34.21525
C44: Total | D44: =+SUM(D40:D43) -> 688.03016 | E44: =+SUM(E40:E43) -> 472.25504 | F44: =+SUM(F40:F43) -> 437.9579 | G44: =+SUM(G40:G43) -> 351.0094 | H44: =+SUM(H40:H43) -> 522.76343 | I44: =+SUM(I40:I43) -> 394.83649 | J44: =+SUM(J40:J43) -> 526.62049 | K44: =+SUM(K40:K43) -> 538.31008 | ... Q44: =+SUM(Q40:Q43) -> 497.32025
C47: Item | D47: ene | E47: feb | F47: mar | G47: abr | H47: may | I47: jun | J47: jul | K47: ago | L47: sept | M47: oct | N47: nov | O47: dic | P47: Total | Q47: Promedio | R47: P2025
C48: Sueldos | D48: 344.70391 | E48: 313.86733 | F48: 332.5578 | G48: 271.76518 | H48: 381.94289 | I48: 266.57109 | J48: 407.31932 | K48: 375.94014 | L48: 286.92174 | M48: 356.79323 | N48: 318.18725 | O48: 488.7877 | P48: =+SUM(D48:O48) -> 4145.3576 | Q48: =+AVERAGE(D48:O48) -> 345.44647 | R48: =+P48+300+120 -> 4565.3576 | S48: =+(R48-P48)/P48 -> 0.10131816
C49: Oficina | D49: 67.486891 | E49: 43.518066 | F49: 36.558028 | G49: 37.661349 | H49: 56.954104 | I49: 42.344468 | J49: 56.94287 | K49: 42.07897 | L49: 48.093315 | M49: 56.748175 | N49: 51.180095 | O49: 80.809693 | P49: =+SUM(D49:O49) -> 620.37602 | Q49: =+AVERAGE(D49:O49) -> 51.698002 | R49: =+P49 -> 620.37602 | S49: =+(R49-P49)/P49 -> 0
C50: Otros gastos | D50: 215.39669 | E50: 62.837275 | F50: 30.924698 | G50: 35.044196 | H50: 39.778305 | I50: 15.212737 | J50: 24.566011 | K50: 25.528199 | L50: 21.856405 | M50: 45.948439 | N50: 47.631579 | O50: 45.24028 | P50: =+SUM(D50:O50) -> 609.96482 | Q50: =+AVERAGE(D50:O50) -> 50.830401 | R50: =+P50/P48*R48 -> 671.76533 | S50: =+(R50-P50)/P50 -> 0.10131816
C51: Externo | D51: 60.442668 | E51: 52.032368 | F51: 37.917372 | G51: 6.5386728 | H51: 44.088135 | I51: 70.708193 | J51: 37.792285 | K51: 94.762768 | L51: 26.905788 | M51: 59.523048 | N51: 35.204613 | O51: 66.228705 | P51: =+SUM(D51:O51) -> 592.14461 | Q51: =+AVERAGE(D51:O51) -> 49.345384 | R51: =+P51/P48*R48 -> 652.13962 | S51: =+(R51-P51)/P51 -> 0.10131816
C52: Total | D52: =+SUM(D48:D51) -> 688.03016 | E52: =+SUM(E48:E51) -> 472.25504 | F52: =+SUM(F48:F51) -> 437.9579 | G52: =+SUM(G48:G51) -> 351.0094 | H52: =+SUM(H48:H51) -> 522.76343 | I52: =+SUM(I48:I51) -> 394.83649 | J52: =+SUM(J48:J51) -> 526.62049 | K52: =+SUM(K48:K51) -> 538.31008 | ... R52: =+SUM(R48:R51) -> 6509.6386
C53: Acumulado | D53: =+SUM($D$52:D52) -> 688.03016 | E53: =+SUM($D$52:E52) -> 1160.2852 | F53: =+SUM($D$52:F52) -> 1598.2431 | G53: =+SUM($D$52:G52) -> 1949.2525 | H53: =+SUM($D$52:H52) -> 2472.0159 | I53: =+SUM($D$52:I52) -> 2866.8524 | J53: =+SUM($D$52:J52) -> 3393.4729 | K53: =+SUM($D$52:K52) -> 3931.783 | ... O53: =+SUM($D$52:O52) -> 5967.843 | R53: 9660
P55: 8275 | R55: =+R53-R52 -> 3150.3614
P56: =+P55-P52 -> 2307.157 | R56: =+R55/R53 -> 0.32612437
P57: =+P56/P55 -> 0.27881051
C72: kUS$ | D72: =+Q52 -> 497.32025 | E72: Media
C73: kUS$ | D73: =+_xlfn.STDEV.P(D52:O52) -> 101.9718 | E73: Desviación Estandar (Gasto)
C74: % | D74: =+D73/D72 -> 0.20504253 | E74: Coeficiente de variación

Sheet Ingresos para PPT_Dic
B3: Pais | C3: 45292 | D3: 45323 | E3: 45352 | F3: 45383 | G3: 45413 | H3: 45444 | I3: 45474 | J3: 45505 | K3: 45536 | L3: 45566 | M3: 45597 | N3: 45627
B4: Gran Total | C4: 782.47265 | D4: 579.08373 | E4: 663.71177 | F4: 492.6642 | G4: 817.072 | H4: 398.011 | I4: 464.29877 | J4: 672.28596 | K4: 1311.681 | L4: 1003.5651 | M4: 614.74 | N4: 475.262 | O4: =+SUM(C4:N4) -> 8274.8482 | R4: =+AVERAGE(C4:I4) -> 599.6163 | S4: =+MEDIAN(C4:I4) -> 579.08373
B5: Finalizado | C5: 667.3589 | D5: 532.92403 | E5: 468.64003 | F5: 461.52255 | G5: 641.341 | H5: 189.42 | I5: 229.80636 | J5: 456.18696 | K5: 887.187 | L5: 334.20609 | M5: 161.027 | N5: 9.928 | O5: =+SUM(C5:N5) -> 5039.5479 | P5: =+O5/$O$4 -> 0.60901999 | R5: =+(K4-R4)/R4 -> 1.1875339
B6: Ejecución | C6: 115.11375 | D6: 46.1597 | E6: 195.07174 | F6: 31.14165 | G6: 175.731 | H6: 208.591 | I6: 234.49241 | J6: 216.099 | K6: 424.494 | L6: 669.359 | M6: 453.713 | N6: 465.334 | O6: =+SUM(C6:N6) -> 3235.3003 | P6: =+O6/$O$4 -> 0.39098001
B7: Pipeline | C7: 0 | D7: 0 | E7: 0 | F7: 0 | G7: 0 | H7: 0 | I7: 0 | J7: 0 | K7: 0 | L7: 0 | M7: 0 | N7: 0 | O7: =+SUM(C7:N7) -> 0 | P7: =+O7/$O$4 -> 0 | R7: =+AVERAGE(C4:N4) -> 689.57068 | U7: País | V7: kUSD
B8: Chile | C8: 427.78565 | D8: 203.47573 | E8: 294.69749 | F8: 239.0302 | G8: 253.288 | H8: 181.519 | I8: 199.83051 | J8: 191.73696 | K8: 305.343 | L8: 505.285 | M8: 354.326 | N8: 214.111 | O8: =+SUM(C8:N8) -> 3370.4285 | P8: =+O8/$O$4 -> 0.40731002 | R8: =+_xlfn.STDEV.P(C4:N4) -> 249.95506 | U8: Chile | V8: =+_xlfn.XLOOKUP(U8,B:B,O:O,"!",0,1) -> 3370.4285 | W8: =+V8/$V$13 -> 0.40731002
B9: Perú | C9: 165.529 | D9: 97.072 | E9: 127.385 | F9: 76.133 | G9: 107.922 | H9: 172.201 | I9: 189.28926 | J9: 185.957 | K9: 387.972 | L9: 293.429 | M9: 155.905 | N9: 119.107 | O9: =+SUM(C9:N9) -> 2077.9013 | P9: =+O9/$O$4 -> 0.2511105 | R9: =+R8/R7 -> 0.36247925 | U9: Perú | V9: =+_xlfn.XLOOKUP(U9,B:B,O:O,"!",0,1) -> 2077.9013 | W9: =+V9/$V$13 -> 0.2511105
B10: Brasil | C10: 189.158 | D10: 225.732 | E10: 78.64628 | F10: 74.596 | G10: 267.262 | H10: 0 | I10: 23.44 | J10: 144.771 | K10: 0 | L10: 128.80109 | M10: 58.584 | N10: 19.954 | O10: =+SUM(C10:N10) -> 1210.9444 | P10: =+O10/$O$4 -> 0.14634037 | U10: EEUU | V10: =+_xlfn.XLOOKUP(U10,B:B,O:O,"!",0,1) -> 1463.474 | W10: =+V10/$V$13 -> 0.17685811
B11: Rusia | C11: 0 | D11: 0 | E11: 0 | F11: 0 | G11: 0 | H11: 0 | I11: 0 | J11: 0 | K11: 0 | L11: 76.05 | M11: 0 | N11: 76.05 | O11: =+SUM(C11:N11) -> 152.1 | P11: =+O11/$O$4 -> 0.018381002 | U11: Brasil | V11: =+_xlfn.XLOOKUP(U11,B:B,O:O,"!",0,1) -> 1210.9444 | W11: =+V11/$V$13 -> 0.14634037
B12: EEUU | C12: 0 | D12: 52.804 | E12: 162.983 | F12: 102.905 | G12: 188.6 | H12: 44.291 | I12: 51.739 | J12: 149.821 | K12: 618.366 | L12: 0 | M12: 45.925 | N12: 46.04 | O12: =+SUM(C12:N12) -> 1463.474 | P12: =+O12/$O$4 -> 0.17685811 | U12: Rusia | V12: =+_xlfn.XLOOKUP(U12,B:B,O:O,"!",0,1) -> 152.1 | W12: =+V12/$V$13 -> 0.018381002
B13: Nro. de Proyectos | C13: 10 | D13: 14 | E13: 14 | F13: 13 | G13: 14 | H13: 8 | I13: 13 | J13: 14 | K13: 13 | L13: 22 | M13: 15 | N13: 14 | O13: =+AVERAGE(C13:N13) -> 13.666667 | V13: =+SUM(V8:V12) -> 8274.8482
B14: Acumulado | C14: 782.47265 | D14: 1361.5564 | E14: 2025.2682 | F14: 2517.9324 | G14: 3335.0044 | H14: 3733.0154 | I14: 4197.3141 | J14: 4869.6001 | K14: 6181.2811 | L14: 7184.8462 | M14: 7799.5862 | N14: 8274.8482
C15: =+C14/$N$14 -> 0.094560363 | D15: =+D14/$N$14 -> 0.16454155 | E15: =+E14/$N$14 -> 0.24474989 | F15: =+F14/$N$14 -> 0.30428744 | G15: =+G14/$N$14 -> 0.40302907 | H15: =+H14/$N$14 -> 0.45112796 | I15: =+I14/$N$14 -> 0.5072376 | J15: =+J14/$N$14 -> 0.58848211 | ... N15: =+N14/$N$14 -> 1
D16: =+(D14-C14)/C14 -> 0.74006897 | E16: =+(E14-D14)/D14 -> 0.48746551 | F16: =+(F14-E14)/E14 -> 0.24325875 | G16: =+(G14-F14)/F14 -> 0.32450117 | H16: =+(H14-G14)/G14 -> 0.11934347 | I16: =+(I14-H14)/H14 -> 0.12437633 | J16: =+(J14-I14)/I14 -> 0.16017051 | K16: =+(K14-J14)/J14 -> 0.26936113 | ... N16: =+(N14-M14)/M14 -> 0.060934259

Sheet Gasto Noviembre_Pruebas
A2: Clasificación 1 | B2: (Varios elementos)
A3: País | B3: (Todas)
A5: Suma de Valor USD | E5: Meses (Atributo)
A6: Clasificación 0 | B6: Clasificación 2 | C6: Clasificación 3 | D6: Detalle | E6: ene | F6: feb | G6: mar | H6: abr | I6: may | J6: jun | K6: jul | L6: ago | M6: sept | N6: oct | O6: nov | P6: dic
A7: Fijo | B7: Sueldos | E7: 302229.93 | F7: 278427.94 | G7: 288746.19 | H7: 271765.18 | I7: 312956.31 | J7: 232896.54 | K7: 335584.67 | L7: 306031.46 | M7: 271556.13 | N7: 268591.11 | O7: 274838.8 | P7: 312370.57
A8: Fijo | B8: Oficina | E8: 35918.38 | F8: 22497.787 | G8: 23276.092 | H8: 28010.34 | I8: 36031.921 | J8: 31987.272 | K8: 32369.19 | L8: 31539.816 | M8: 29697.572 | N8: 39183.383 | O8: 28484.811 | P8: 31457.659
A9: Fijo | B9: Externo | E9: 4375.7069 | F9: 3900.039 | G9: 7037.4952 | H9: 2996.3265 | I9: 7545.7184 | J9: 4977.1768 | K9: 15134.918 | L9: 4103.9086 | M9: 3849.295 | N9: 4361.7377 | O9: 3517.1534 | P9: 3746.6714
A10: Fijo | B10: Extras personas | E10: 4574.0405 | F10: 4427.5118 | G10: 5067.7415 | H10: 2404.6587 | I10: 5844.4873 | J10: 3856.6463 | K10: 4005.1474 | L10: 4380.3484 | M10: 4268.1498 | N10: 3748.5195 | O10: 1681.9514 | P10: 3497.8842
A11: Fijo | B11: Bancarios | E11: 1010.502 | F11: 719.11981 | G11: 472.28157 | H11: 364.44023 | I11: 813.85956 | J11: 1642.0746 | K11: 2169.2001 | L11: 1194.0144 | M11: 1128.0279 | N11: 864.12444 | O11: 1479.8837 | P11: 779.89359
A12: Fijo | B12: Comercial | E12: 917.41098 | F12: 864.61015 | G12: 1721.1988 | H12: 0 | I12: 1815.0521 | J12: 899.49032 | K12: 888.47647 | L12: 895.79525 | M12: 1130.6291 | N12: 892.04442 | O12: 2363.8329 | P12: 882.53679
A13: Fijo | B13: Compañía | C13: EERR | E13: 1186.458 | F13: 2675.0934 | G13: 2662.6843 | H13: 2684.2877 | I13: 2807.8747 | J13: 0 | K13: 2748.9355 | L13: 5543.1595 | M13: 2782.6217 | N13: 2759.9747 | O13: 2652.6266 | P13: 2730.5582
A14: Total Fijo | E14: 350212.43 | F14: 313512.11 | G14: 328983.69 | H14: 308225.23 | I14: 367815.22 | J14: 276259.2 | K14: 392900.54 | L14: 353688.5 | M14: 314412.42 | N14: 320400.89 | O14: 315019.06 | P14: 355465.77
A15: Variable | B15: Externo | E15: 58575.039 | F15: 39286.56 | G15: 18316.29 | H15: 0 | I15: 38476.159 | J15: 25502.568 | K15: 208.13136 | L15: 8434.9704 | M15: 284.10677 | N15: 34449.165 | O15: 39900.403 | P15: 1442
A16: Variable | B16: Viajes | E16: 70940.38 | F16: 15541.723 | G16: 6425.1697 | H16: 19654.064 | I16: 11217.311 | J16: 6643.918 | K16: 10766.462 | L16: 12765.451 | M16: 12095.977 | N16: 8598.2621 | O16: 1440.6731 | P16: 8082
A17: Variable | B17: Oficina | E17: 10816.411 | F17: 13200.409 | G17: 1814.9526 | H17: 6654.6824 | I17: 10477.886 | J17: 4725.0585 | K17: 9230.6307 | L17: 5569.5698 | M17: 14262.341 | N17: 8426.0828 | O17: 14101.602 | P17: 4858.734
A18: Variable | B18: Extras personas | E18: 124824.13 | F18: 36004.252 | G18: 14575.623 | H18: 9936.7454 | I18: 12607.319 | J18: 2170.6079 | K18: 1077.6459 | L18: 546.83891 | M18: 451 | N18: 25761.82 | O18: 27886.439 | P18: 452
A19: Variable | B19: Sueldos | E19: 275.33343 | F19: 72.656315 | G19: 118.81024 | H19: 0 | I19: 0 | J19: 314.94795 | K19: 266.6496 | L19: 376.38456 | M19: 465.60715 | N19: 461.81771 | O19: 1024.5723 | P19: 456.89555
A20: Variable | B20: Compañía | C20: Boleta | D20: Boletas de garantía CMP Comisión+i | E20: 1040.5875 | F20: 519.3245 | G20: 0 | H20: 0 | I20: 4112.9766 | J20: 0 | K20: 2910.1434 | L20: 202.59168 | M20: 0 | N20: 0 | O20: 10693.744 | P20: 530.09207
A21: Variable | B21: Compañía | C21: Boleta | D21: Boletas de garantía CMP intereses | E21: 10674.306 | F21: 0 | G21: 0 | H21: 0 | I21: 0 | J21: 0 | K21: 0 | L21: 0 | M21: 0 | N21: 0 | O21: 0 | P21: 0
A22: Variable | B22: Compañía | C22: EERR | E22: 0 | F22: 2085.641 | G22: 0 | H22: 0 | I22: 0 | J22: 0 | K22: 0 | L22: 0 | M22: 0 | N22: 0 | O22: 0 | P22: 0
A23: Variable | B23: Comercial | E23: 228.87697 | F23: 0 | G23: 0 | H23: 0 | I23: 559.42498 | J23: 0 | K23: 0 | L23: 0 | M23: 0 | N23: 0 | O23: 0 | P23: 0
A24: Total Variable | E24: 277375.06 | F24: 106710.57 | G24: 41250.845 | H24: 36245.492 | I24: 77451.076 | J24: 39357.101 | K24: 24459.663 | L24: 27895.807 | M24: 27559.032 | N24: 77697.147 | O24: 95047.435 | P24: 15821.722
A25: Adicionales | B25: Externo | E25: 60442.668 | F25: 52032.368 | G25: 37917.372 | H25: 6538.6728 | I25: 44088.135 | J25: 70708.193 | K25: 37792.285 | L25: 94762.768 | M25: 26905.788 | N25: 59523.048 | O25: 35204.613 | P25: 0
A26: Total Adicionales | E26: 60442.668 | F26: 52032.368 | G26: 37917.372 | H26: 6538.6728 | I26: 44088.135 | J26: 70708.193 | K26: 37792.285 | L26: 94762.768 | M26: 26905.788 | N26: 59523.048 | O26: 35204.613 | P26: 0
A27: Total general | E27: 688030.16 | F27: 472255.04 | G27: 408151.9 | H27: 351009.4 | I27: 489354.43 | J27: 386324.49 | K27: 455152.49 | L27: 476347.08 | M27: 368877.24 | N27: 457621.08 | O27: 445271.11 | P27: 371287.49
D29: Costo Directo | E29: 300430.87 | F29: 321466.3 | G29: 291430.23 | H29: 301846.1 | I29: 343761.08 | J29: 307715.81 | K29: 412320.75 | L29: 318179.89 | M29: 274659.87 | N29: 311374.2 | U29: Costo Directo | V29: 150215.44 | W29: 160733.15 | X29: 145715.11 | Y29: 150923.05 | Z29: 171880.54 | AA29: 153857.9 | AB29: 206160.38 | AC29: 159089.95 | AD29: 137329.94 | AE29: 155687.1
D30: Gasto Sueldos | E30: =[1]Sueldos!G107 -> 3345.9327 | F30: =[1]Sueldos!H107 -> 2746.0803 | G30: =[1]Sueldos!I107 -> 2790.9983 | H30: =[1]Sueldos!J107 -> 2849.6109 | I30: =[1]Sueldos!K107 -> 3928.1958 | J30: =[1]Sueldos!L107 -> 2691.4163 | K30: =[1]Sueldos!M107 -> 0 | L30: =[1]Sueldos!N107 -> 0 | ... P30: =[1]Sueldos!R107 -> 0
D31: Delta | E31: =+E30-E29 -> -297084.94 | F31: =+F30-F29 -> -318720.22 | G31: =+G30-G29 -> -288639.23 | H31: =+H30-H29 -> -298996.49 | I31: =+I30-I29 -> -339832.89 | J31: =+J30-J29 -> -305024.39 | K31: =+K30-K29 -> -412320.75 | L31: =+L30-L29 -> -318179.89 | ... N31: =+N30-N29 -> -311374.2
E32: =+E31/E30 -> -88.789875 | F32: =+F31/F30 -> -116.06369 | G32: =+G31/G30 -> -103.41791 | H32: =+H31/H30 -> -104.92537 | I32: =+I31/I30 -> -86.511188 | J32: =+J31/J30 -> -113.3323 | K32: =+K31/K30 -> #DIV/0! | L32: =+L31/L30 -> #DIV/0! | ... N32: =+N31/N30 -> #DIV/0!
T33: 48000
D35: % Sueldo | E35: =+E30/E25 -> 0.055357131 | F35: =+F30/F25 -> 0.052776385 | G35: =+G30/G25 -> 0.073607379 | H35: =+H30/H25 -> 0.43580876 | I35: =+I30/I25 -> 0.089098708 | J35: =+J30/J25 -> 0.038063711 | K35: =+K30/K25 -> 0 | L35: =+L30/L25 -> 0 | ... P35: =+P30/P25 -> #DIV/0!
D38: Gasto Otros | E38: =+E25-E30 -> 57096.735 | F38: =+F25-F30 -> 49286.288 | G38: =+G25-G30 -> 35126.373 | H38: =+H25-H30 -> 3689.0619 | I38: =+I25-I30 -> 40159.939 | J38: =+J25-J30 -> 68016.777 | K38: =+K25-K30 -> 37792.285 | L38: =+L25-L30 -> 94762.768 | ... P38: =+P25-P30 -> 0
E39: =+E38/E25 -> 0.94464287 | F39: =+F38/F25 -> 0.94722361 | G39: =+G38/G25 -> 0.92639262 | H39: =+H38/H25 -> 0.56419124 | I39: =+I38/I25 -> 0.91090129 | J39: =+J38/J25 -> 0.96193629 | K39: =+K38/K25 -> 1 | L39: =+L38/L25 -> 1 | ... P39: =+P38/P25 -> #DIV/0!

Sheet Hoja3
B1: 45292 | C1: 45323 | D1: 45352 | E1: 45383 | F1: 45413 | G1: 45444 | H1: 45474 | I1: 45505 | J1: 45536 | K1: 45566 | L1: 45597 | M1: 45627
A2: Gastos del dueño | B2: 298.83699 | C2: 1268.2741 | D2: 171.39669 | E2: 18069.475 | F2: 537.09853 | G2: 1587.9773 | H2: 373.9238 | I2: 22887.263 | J2: 410.05603 | K2: 113.05512 | L2: 52579.889 | M2: 20707.212
A3: REDTEC | B3: 1060.3246 | C3: 70628.998 | D3: 8560.529 | E3: 6450 | F3: 12531 | G3: 8690.9461 | H3: 10711.144 | I3: 10163.703 | J3: 9855.4696 | K3: 18252.545 | L3: 115687.99 | M3: 6886
A8: Ingresos
A9: Chile | B9: 491038355 | C9: 328098423 | D9: 344330410 | E9: 238698876 | F9: 348792953 | G9: 141091125 | H9: 326660345 | I9: 3.1477254e+08 | J9: 585454974 | K9: 516832647 | L9: 411995131 | M9: 358257483
A10: Perú | B10: 205682.23 | C10: 117395.19 | D10: 147879.94 | E10: 90961 | F10: 120651 | G10: 184899 | H10: 235161 | I10: 222913 | J10: 455729 | K10: 356456 | L10: 202065 | M10: 139885
A11: Brasil
A12: EEUU

Sheet Gasto Diciembre (3)
A2: Clasificación 1 | B2: (Varios elementos)
A3: País | B3: (Todas)
A5: Suma de Valor USD | E5: Meses (Atributo)
A6: Clasificación 0 | B6: Clasificación 2 | C6: Clasificación 3 | D6: Detalle | E6: ene | F6: feb | G6: mar | H6: abr | I6: may | J6: jun | K6: jul | L6: ago | M6: sept | N6: oct | O6: nov | P6: dic
A7: Fijo | B7: Sueldos | C7: Asociado a sueldo | D7: Ricardo Miranda | E7: 0 | F7: 1467.7533 | G7: 0 | H7: 0 | I7: 260.87986 | J7: 0 | K7: 0 | L7: 0 | M7: 0 | N7: 0 | O7: 0 | P7: 0 | R7: =+IF(P7>0,1,0) -> 0
A8: Fijo | B8: Sueldos | C8: Sueldo | D8: Alejandro Espinosa | E8: 8612.8752 | F8: 8256.7911 | G8: 8277.5328 | H8: 8177.8985 | I8: 8346.2575 | J8: 8561.1387 | K8: 8384.322 | L8: 0 | M8: 12470.381 | N8: 0 | O8: 0 | P8: 0 | R8: =+IF(P8>0,1,0) -> 0
A9: Fijo | B9: Sueldos | C9: Sueldo | D9: Alex Figueroa | E9: 8425.1203 | F9: 8065.6523 | G9: 8084.2266 | H9: 9000.5222 | I9: 9188.1821 | J9: 9427.2681 | K9: 9215.5727 | L9: 9646.0851 | M9: 9698.6681 | N9: 8989.0109 | O9: 8785.0906 | P9: 8896.3497 | R9: =+IF(P9>0,1,0) -> 1
A10: Fijo | B10: Sueldos | C10: Sueldo | D10: Alex Pacheco C. | E10: 2947.9802 | F10: 2825.3146 | G10: 2831.856 | H10: 2796.9641 | I10: 2854.5881 | J10: 2927.2905 | K10: 2944.313 | L10: 3029.1555 | M10: 3023.0005 | N10: 2797.3888 | O10: 2733.6622 | P10: 3505.8177 | Q10: =+SUM(E10:P10) -> 35217.331 | R10: =+IF(P10>0,1,0) -> 1
A11: Fijo | B11: Sueldos | C11: Sueldo | D11: Americo Zuzunaga | E11: 15627.149 | F11: 12771.726 | G11: 12720.817 | H11: 13033.347 | I11: 18057.936 | J11: 12583.422 | K11: 24597.319 | L11: 21641.216 | M11: 12712.144 | N11: 0 | O11: 0 | P11: 0 | R11: =+IF(P11>0,1,0) -> 0
A12: Fijo | B12: Sueldos | C12: Sueldo | D12: Andree del Castillo | E12: 3378.5173 | F12: 2772.8232 | G12: 2818.1787 | H12: 2877.3642 | I12: 3966.4574 | J12: 3082.1981 | K12: 13291.234 | L12: 0 | M12: 0 | N12: 0 | O12: 0 | P12: 0 | R12: =+IF(P12>0,1,0) -> 0
A13: Fijo | B13: Sueldos | C13: Sueldo | D13: Andrés Budini M. | E13: 3630.5471 | F13: 3477.3079 | G13: 1991.6571 | H13: 3438.5715 | I13: 3509.267 | J13: 3598.4542 | K13: 3608.7223 | L13: 3694.1883 | M13: 3770.5848 | N13: 6794.0432 | O13: 0 | P13: 0 | R13: =+IF(P13>0,1,0) -> 0
A14: Fijo | B14: Sueldos | C14: Sueldo | D14: Angelo Patri Carbajal | E14: 655.65172 | F14: 658.4 | G14: 671.8624 | H14: 334.76 | I14: 0 | J14: 0 | K14: 0 | L14: 0 | M14: 0 | N14: 0 | O14: 0 | P14: 0 | R14: =+IF(P14>0,1,0) -> 0
A15: Fijo | B15: Sueldos | C15: Sueldo | D15: Arnold Tadeo | E15: 3002.0235 | F15: 1495.2351 | G15: 1519.6929 | H15: 1551.6122 | I15: 2138.8881 | J15: 1465.4653 | K15: 2922.7402 | L15: 2520.336 | M15: 1497.0419 | N15: 2305.4657 | O15: 2706.7812 | P15: 2868.3641 | R15: =+IF(P15>0,1,0) -> 1
A16: Fijo | B16: Sueldos | C16: Sueldo | D16: CARLOS CARMELO HIDALGO | E16: 4101.7571 | F16: 0 | G16: 0 | H16: 0 | I16: 0 | J16: 0 | K16: 0 | L16: 0 | M16: 0 | N16: 0 | O16: 0 | P16: 0 | R16: =+IF(P16>0,1,0) -> 0
A17: Fijo | B17: Sueldos | C17: Sueldo | D17: Carlos Catalán | E17: 3582.3951 | F17: 2930.091 | G17: 2960.0891 | H17: 3022.2491 | I17: 4166.1994 | J17: 2854.4678 | K17: 6129.0731 | L17: 5367.0215 | M17: 2946.2263 | N17: 5676.5791 | O17: 6661.5991 | P17: 7066.0392 | R17: =+IF(P17>0,1,0) -> 1
A18: Fijo | B18: Sueldos | C18: Sueldo | D18: Carlos Morante | E18: 3867.8791 | F18: 3174.4532 | G18: 3226.3782 | H18: 3294.14 | I18: 4540.9759 | J18: 3111.2584 | K18: 0 | L18: 0 | M18: 0 | N18: 0 | O18: 0 | P18: 0 | R18: =+IF(P18>0,1,0) -> 0
A19: Fijo | B19: Sueldos | C19: Sueldo | D19: Claudio Hernandez | E19: 10340.278 | F19: 9912.7777 | G19: 9941.9923 | H19: 9825.5356 | I19: 10030.851 | J19: 10291.81 | K19: 10050.912 | L19: 10530.224 | M19: 10562.402 | N19: 9818.5739 | O19: 9597.5381 | P19: 9600.55 | R19: =+IF(P19>0,1,0) -> 1
A20: Fijo | B20: Sueldos | C20: Sueldo | D20: Clinton Yahuira | E20: 655.65172 | F20: 658.4 | G20: 671.8624 | H20: 669.52 | I20: 666.13 | J20: 654.96 | K20: 668 | L20: 654.96 | M20: 0 | N20: 0 | O20: 0 | P20: 0 | R20: =+IF(P20>0,1,0) -> 0
A21: Fijo | B21: Sueldos | C21: Sueldo | D21: Cristián Alarcón | E21: 2214.8278 | F21: 2123.0161 | G21: 2524.1096 | H21: 2492.4647 | I21: 2543.443 | J21: 2451.1332 | K21: 2490.2273 | L21: 2842.5992 | M21: 2682.7516 | N21: 2497.4535 | O21: 2442.0531 | P21: 2706.5608 | R21: =+IF(P21>0,1,0) -> 1
A22: Fijo | B22: Sueldos | C22: Sueldo | D22: Cristián García | E22: 7950.2818 | F22: 8123.8317 | G22: 0 | H22: 0 | I22: 0 | J22: 0 | K22: 0 | L22: 0 | M22: 0 | N22: 0 | O22: 0 | P22: 0 | R22: =+IF(P22>0,1,0) -> 0
... A70: Fijo | B70: Sueldos | C70: Sueldo | D70: Nelson Rumino | E70: 8571.5704 | F70: 8217.194 | G70: 8208.0735 | H70: 5202.6789 | I70: 9345.9367 | J70: 0 | K70: 0 | L70: 0 | M70: 0 | N70: 0 | O70: 0 | P70: 0 | R70: =+IF(P70>0,1,0) -> 0
A71: Fijo | B71: Sueldos | C71: Sueldo | D71: Nicolás Ayarza D. | E71: 2947.789 | F71: 2825.1313 | G71: 4206.8493 | H71: 4151.3789 | I71: 4233.1904 | J71: 4337.9801 | K71: 4333.4784 | L71: 4449.8019 | M71: 4531.7376 | N71: 4126.6661 | O71: 4030.0378 | P71: 4312.2767
A72: Fijo | B72: Sueldos | C72: Sueldo | D72: Nicolás Sanzana | E72: 1938.2542 | F72: 1857.877 | G72: 2243.653 | H72: 2215.5565 | I72: 2260.8933 | J72: 2318.0773 | K72: 2360.6434 | L72: 2386.5227 | M72: 2388.0888 | N72: 2221.8622 | O72: 2172.5817 | P72: 2448.8362 | R72: =+IF(P72>0,1,0) -> 1
A73: Fijo | B73: Sueldos | C73: Sueldo | D73: Nilcélio José Dos Santos | E73: 2829.304 | F73: 2609.6521 | G73: 3831.9996 | H73: 2879.8682 | I73: 1881.46 | J73: 3098.1 | K73: 4489.222 | L73: 2622.9914 | M73: 2724.3547 | N73: 2292.3891 | O73: 4295.2801 | P73: 3585.5581
A74: Fijo | B74: Sueldos | C74: Sueldo | D74: Olesya Dashavskaya | E74: 3341.2793 | F74: 3225.9169 | G74: 3130.9925 | H74: 3092.3157 | I74: 3155.957 | J74: 3447.4363 | K74: 3341.4649 | L74: 3754.8482 | M74: 3457.0857 | N74: 3177.1164 | O74: 3104.7693 | P74: 3458.5523 | R74: =+IF(P74>0,1,0) -> 1
A75: Fijo | B75: Sueldos | C75: Sueldo | D75: Omar Meléndez Huamán | E75: 1966.9552 | F75: 1975.2 | G75: 2015.5872 | H75: 0 | I75: 0 | J75: 0 | K75: 0 | L75: 0 | M75: 0 | N75: 0 | O75: 0 | P75: 0
A76: Fijo | B76: Sueldos | C76: Sueldo | D76: Oscar Cáceres servicios | E76: 0 | F76: 0 | G76: 6729.0529 | H76: 0 | I76: 0 | J76: 0 | K76: 0 | L76: 0 | M76: 0 | N76: 0 | O76: 0 | P76: 0 | R76: =+IF(P76>0,1,0) -> 0
A77: Fijo | B77: Sueldos | C77: Sueldo | D77: Osvaldo Ulloa | E77: 1462.6464 | F77: 720.92549 | G77: 0 | H77: 561.93443 | I77: 0 | J77: 0 | K77: 0 | L77: 0 | M77: 0 | N77: 0 | O77: 0 | P77: 0 | R77: =+IF(P77>0,1,0) -> 0
A78: Fijo | B78: Sueldos | C78: Sueldo | D78: Pablo Quiero | E78: 6116.6473 | F78: 5859.2992 | G78: 5868.7329 | H78: 5770.9611 | I78: 5886.5524 | J78: 6034.1019 | K78: 5965.323 | L78: 6181.7069 | M78: 6249.5378 | N78: 5733.3651 | O78: 5600.9214 | P78: 5820.3729 | R78: =+IF(P78>0,1,0) -> 1
A79: Fijo | B79: Sueldos | C79: Sueldo | D79: Paolo Tito | E79: 1994.709 | F79: 1637.1014 | G79: 1663.8797 | H79: 1698.8277 | I79: 6991.7565 | J79: 0 | K79: 0 | L79: 0 | M79: 0 | N79: 0 | O79: 274 | P79: 0 | Q79: =+SUM(E79:P79) -> 14260.274 | R79: =+IF(P79>0,1,0) -> 0
A80: Fijo | B80: Sueldos | C80: Sueldo | D80: Pedro Aguiluz P. | E80: 2955.3281 | F80: 2832.3588 | G80: 4206.8493 | H80: 4151.3955 | I80: 4233.2229 | J80: 4338.0264 | K80: 4333.526 | L80: 4449.8699 | M80: 4531.8154 | N80: 4135.1181 | O80: 4038.3857 | P80: 4441.1686
A81: Fijo | B81: Sueldos | C81: Sueldo | D81: Pedro Ccanto | E81: 655.65172 | F81: 658.4 | G81: 671.8624 | H81: 669.52 | I81: 666.13 | J81: 654.96 | K81: 0 | L81: 0 | M81: 0 | N81: 0 | O81: 0 | P81: 0
A82: Fijo | B82: Sueldos | C82: Sueldo | D82: Ricardo Miranda | E82: 9705.5518 | F82: 9689.2921 | G82: 9152.7915 | H82: 9549.1047 | I82: 10598.236 | J82: 0 | K82: 16952.004 | L82: 10605.981 | M82: 9094.1616 | N82: 15822.168 | O82: 13212.968 | P82: 13223.502 | R82: =+IF(P82>0,1,0) -> 1
A83: Fijo | B83: Sueldos | C83: Sueldo | D83: Rodrigo Cori Córdova | E83: 9029.0693 | F83: 6945.5798 | G83: 7059.1897 | H83: 7206.1373 | I83: 9933.6704 | J83: 6806.0767 | K83: 13571.932 | L83: 11704.079 | M83: 6955.7861 | N83: 13704.458 | O83: 13633.857 | P83: 14460.863 | R83: =+IF(P83>0,1,0) -> 1
A84: Fijo | B84: Sueldos | C84: Sueldo | D84: Rodrigo Pinto H. | E84: 0 | F84: 3372.6944 | G84: 0 | H84: 0 | I84: 0 | J84: 0 | K84: 0 | L84: 0 | M84: 0 | N84: 0 | O84: 0 | P84: 0 | R84: =+IF(P84>0,1,0) -> 0
A85: Fijo | B85: Sueldos | C85: Sueldo | D85: Roxana Avilés | E85: 1882.588 | F85: 1803.9649 | G85: 1806.7268 | H85: 1783.4191 | I85: 1819.1622 | J85: 1864.6137 | K85: 1921.339 | L85: 1910.8177 | M85: 1931.1291 | N85: 2260.7647 | O85: 2210.6205 | P85: 2045.9159 | R85: =+IF(P85>0,1,0) -> 1
A86: Fijo | B86: Sueldos | C86: Sueldo | D86: Sebastián González | E86: 1607.8029 | F86: 1541.0876 | G86: 1544.3975 | H86: 513.72151 | I86: 0 | J86: 0 | K86: 0 | L86: 0 | M86: 0 | N86: 0 | O86: 0 | P86: 0 | R86: =+IF(P86>0,1,0) -> 0
A87: Fijo | B87: Sueldos | C87: Sueldo | D87: Thalia Rimac | E87: 675.02842 | F87: 554.01063 | G87: 563.06825 | H87: 574.89325 | I87: 2217.0896 | J87: 0 | K87: 0 | L87: 0 | M87: 0 | N87: 0 | O87: 0 | P87: 0 | R87: =+IF(P87>0,1,0) -> 0
A88: Fijo | B88: Sueldos | C88: Sueldo | D88: Victor Arias | E88: 3478.5661 | F88: 2854.9355 | G88: 2901.6341 | H88: 2962.5717 | I88: 4083.919 | J88: 2798.1089 | K88: 5587.9321 | L88: 4820.2371 | M88: 2863.9713 | N88: 4406.9688 | O88: 5173.1396 | P88: 5490.1396 | R88: =+IF(P88>0,1,0) -> 1
A89: Fijo | B89: Sueldos | C89: Sueldo | D89: Victor Mohana Tapia | E89: 2200.2998 | F89: 1799.0398 | G89: 2524.1096 | H89: 2467.2148 | I89: 2517.6787 | J89: 2581.33 | K89: 2614.7413 | L89: 2655.4243 | M89: 2625.4619 | N89: 2467.1972 | O89: 2410.9698 | P89: 2683.0602 | R89: =+IF(P89>0,1,0) -> 1
A90: Fijo | B90: Sueldos | C90: Sueldo | D90: VILLANUEVA CRISTOBAL PAOLO CESAR | E90: 1192.3895 | F90: 978.6202 | G90: 0 | H90: 0 | I90: 0 | J90: 0 | K90: 0 | L90: 0 | M90: 0 | N90: 0 | O90: 0 | P90: 0 | R90: =+IF(P90>0,1,0) -> 0
A91: Fijo | B91: Sueldos | C91: Sueldo | D91: Walter Lupinta | E91: 1835.82 | F91: 1843.6 | G91: 1881.2147 | H91: 0 | I91: 0 | J91: 0 | K91: 0 | L91: 0 | M91: 0 | N91: 0 | O91: 0 | P91: 0 | R91: =+IF(P91>0,1,0) -> 0
A92: Fijo | B92: Sueldos | C92: Sueldo | D92: Yosep Aviles | E92: 1180.1731 | F92: 1185.1 | G92: 1209.3523 | H92: 0 | I92: 0 | J92: 0 | K92: 0 | L92: 0 | M92: 0 | N92: 0 | O92: 0 | P92: 0 | R92: =+IF(P92>0,1,0) -> 0
A93: Fijo | B93: Sueldos | C93: Sueldo | D93: Cristóbal Ventura | E93: 0 | F93: 0 | G93: 0 | H93: 0 | I93: 2056.2749 | J93: 1580.6023 | K93: 1584.3983 | L93: 1634.3019 | M93: 1652.3532 | N93: 1500.5437 | O93: 2962.9778 | P93: 1726.8078 | R93: =+IF(P93>0,1,0) -> 1
... A97: Fijo | B97: Sueldos | C97: Sueldo | D97: Eduardo Sanchez | E97: 0 | F97: 0 | G97: 0 | H97: 0 | I97: 0 | J97: 0 | K97: 0 | L97: 1199.7126 | M97: 5141.6884 | N97: 7819.3331 | O97: 9071.2287 | P97: 9716.1582 | R97: =+IF(P97>0,1,0) -> 1
A98: Fijo | B98: Sueldos | C98: Sueldo | D98: Max Le Clerc | E98: 2059.2952 | F98: 2047.8241 | G98: 1922.5866 | H98: 2126.3823 | I98: 2250.0888 | J98: 0 | K98: 3847.0988 | L98: 1902.8023 | M98: 2241.0612 | N98: 0 | O98: 0 | P98: 0 | R98: 1
A99: Fijo | B99: Sueldos | C99: Sueldo | D99: Rodrigo Báez | E99: 0 | F99: 0 | G99: 0 | H99: 0 | I99: 0 | J99: 0 | K99: 0 | L99: 0 | M99: 7567.3929 | N99: 6949.0928 | O99: 6791.0936 | P99: 6820.6214 | R99: =+IF(P99>0,1,0) -> 1
A100: Fijo | B100: Sueldos | C100: Sueldo | D100: Maria Célia P. Fonseca | E100: 1531.846 | F100: 1546.9079 | G100: 2115.5404 | H100: 1599.2618 | I100: 1060.36 | J100: 1558.91 | K100: 1362.778 | L100: 1463.2386 | M100: 1558.6453 | N100: 1258.6109 | O100: 2365.7199 | P100: 1980.4419 | R100: =+IF(P100>0,1,0) -> 1
A101: Fijo | B101: Sueldos | C101: Sueldo | D101: Antônio Alberto Fróes Schettino | E101: 2802.86 | F101: 2844.04 | G101: 2846.91 | H101: 2881.39 | I101: 2950.14 | J101: 2720.9 | K101: 2788 | L101: 2956.01 | M101: 2946 | N101: 2695 | O101: 2806 | P101: 3034 | R101: =+IF(P101>0,1,0) -> 1
A102: Fijo | B102: Sueldos | C102: Sueldo | D102: Mateo Villanueva | E102: 0 | F102: 0 | G102: 0 | H102: 0 | I102: 0 | J102: 0 | K102: 0 | L102: 838.3 | M102: 848 | N102: 852 | O102: 848 | P102: 858 | R102: =+IF(P102>0,1,0) -> 1
A103: Fijo | B103: Sueldos | C103: Sueldo | D103: Cristóbal Poblete | E103: 0 | F103: 0 | G103: 0 | H103: 0 | I103: 0 | J103: 0 | K103: 0 | L103: 0 | M103: 0 | N103: 1118.9004 | O103: 1751.7118 | P103: 1805.0929 | R103: =+IF(P103>0,1,0) -> 1
A104: Fijo | B104: Sueldos | C104: Sueldo | D104: Cynthia Ordoñes (RRHH) | E104: 0 | F104: 0 | G104: 0 | H104: 0 | I104: 0 | J104: 0 | K104: 0 | L104: 0 | M104: 0 | N104: 5354.4083 | O104: 2573.0753 | P104: 2800.8637 | R104: =+IF(P104>0,1,0) -> 1
A105: Fijo | B105: Sueldos | C105: Sueldo | D105: Erick Sanhueza Correa | E105: 0 | F105: 0 | G105: 0 | H105: 0 | I105: 0 | J105: 0 | K105: 0 | L105: 0 | M105: 0 | N105: 0 | O105: 2520.9709 | P105: 2541.2047 | R105: =+IF(P105>0,1,0) -> 1
A106: Fijo | B106: Sueldos | C106: Sueldo | D106: Joseph Livia | E106: 0 | F106: 0 | G106: 0 | H106: 0 | I106: 0 | J106: 0 | K106: 0 | L106: 0 | M106: 0 | N106: 0 | O106: 1458 | P106: 1474 | R106: =+IF(P106>0,1,0) -> 1
A107: Fijo | B107: Sueldos | C107: Sueldo | D107: Darwin Varas | E107: 0 | F107: 0 | G107: 0 | H107: 0 | I107: 0 | J107: 0 | K107: 0 | L107: 0 | M107: 0 | N107: 0 | O107: 0 | P107: 1829.5407 | R107: =+IF(P107>0,1,0) -> 1
A108: Fijo | B108: Sueldos | C108: Sueldo | D108: Germán Soto | E108: 0 | F108: 0 | G108: 0 | H108: 0 | I108: 0 | J108: 0 | K108: 0 | L108: 0 | M108: 0 | N108: 0 | O108: 0 | P108: 6571.9777 | R108: =+IF(P108>0,1,0) -> 1
A109: Fijo | B109: Sueldos | C109: Sueldo | D109: Eduardo Morales | E109: 0 | F109: 0 | G109: 0 | H109: 0 | I109: 0 | J109: 0 | K109: 0 | L109: 0 | M109: 0 | N109: 0 | O109: 0 | P109: 7409.5828 | R109: =+IF(P109>0,1,0) -> 1
A110: Fijo | B110: Sueldos | C110: Sueldo | D110: Carolina Arcos | E110: 0 | F110: 0 | G110: 0 | H110: 0 | I110: 0 | J110: 0 | K110: 0 | L110: 0 | M110: 0 | N110: 0 | O110: 0 | P110: 6249.822 | R110: =+IF(P110>0,1,0) -> 1
A111: Fijo | B111: Sueldos | C111: REDTEC | E111: 0 | F111: 0 | G111: 2418.7046 | H111: 0 | I111: 0 | J111: 0 | K111: 2133.7664 | L111: 2201.3184 | M111: 2843.4696 | N111: 4672.125 | O111: 603.87093 | P111: 0 | R111: =+IF(P111>0,1,0) -> 0
A112: Fijo | B112: Sueldos | C112: REDCROSS | D112: Paola Awilhem | E112: 874.87197 | F112: 824.51943 | G112: 820.69468 | H112: 827.3533 | I112: 865.44537 | J112: 0 | K112: 847.27911 | L112: 1708.517 | M112: 857.66187 | N112: 1701.3632 | O112: 817.59469 | P112: 809.06767
A113: Fijo | B113: Sueldos | C113: REDCROSS | D113: Enrique Rubio | E113: 15418.672 | F113: 14531.263 | G113: 14463.856 | H113: 14581.207 | I113: 15252.538 | J113: 0 | K113: 14932.378 | L113: 30110.765 | M113: 15115.363 | N113: 29984.686 | O113: 14409.222 | P113: 14258.942 | R113: =+IF(P113>0,1,0) -> 1
A114: Fijo | B114: Sueldos | C114: REDCROSS | D114: Constanza Hochstetter | E114: 7645.5501 | F114: 7205.5167 | G114: 7172.092 | H114: 7230.282 | I114: 7563.1706 | J114: 0 | K114: 7404.4147 | L114: 14930.816 | M114: 7495.1501 | N114: 14868.299 | O114: 7145.001 | P114: 7070.483
A115: Fijo | B115: Sueldos | C115: REDCROSS | D115: Isabel Marchant | E115: 2505.206 | F115: 2361.0209 | G115: 2350.0687 | H115: 2369.1358 | I115: 2478.2128 | J115: 0 | K115: 2426.1935 | L115: 4892.3583 | M115: 2455.9247 | N115: 4871.8733 | O115: 2341.1918 | P115: 2316.7746 | R115: =+IF(P115>0,1,0) -> 1
A116: Total Fijo | E116: 302229.93 | F116: 278427.94 | G116: 291164.9 | H116: 271765.18 | I116: 312956.31 | J116: 232896.54 | K116: 337718.44 | L116: 308232.78 | M116: 274399.6 | N116: 298976.34 | O116: 275442.68 | P116: 310359.49
A117: Variable | B117: Sueldos | C117: Sueldo | D117: Reemplazo serv aseo of (vacaciones Gladys) | E117: 0 | F117: 72.656315 | G117: 118.81024 | H117: 0 | I117: 0 | J117: 0 | K117: 0 | L117: 0 | M117: 0 | N117: 0 | O117: 0 | P117: 0 | R117: =+IF(P117>0,1,0) -> 0
A118: Variable | B118: Sueldos | C118: Sueldo | D118: Benjamin Morales | E118: 0 | F118: 0 | G118: 0 | H118: 0 | I118: 0 | J118: 0 | K118: 0 | L118: 0 | M118: 0 | N118: 0 | O118: 580.71678 | P118: 0 | R118: =+IF(P118>0,1,0) -> 0
A119: Variable | B119: Sueldos | C119: Sueldo | D119: Cristian Caviedes | E119: 0 | F119: 0 | G119: 0 | H119: 0 | I119: 0 | J119: 0 | K119: 0 | L119: 0 | M119: 0 | N119: 0 | O119: 0 | P119: 5877.3803 | R119: =+IF(P119>0,1,0) -> 1
A120: Variable | B120: Sueldos | C120: Sueldo | D120: Victoria Franz Contabilidad | E120: 275.33343 | F120: 0 | G120: 0 | H120: 0 | I120: 0 | J120: 314.94795 | K120: 266.6496 | L120: 376.38456 | M120: 465.60715 | N120: 461.81771 | O120: 443.8555 | P120: 592.00073 | R120: =+IF(P120>0,1,0) -> 1
A121: Total Variable | E121: 275.33343 | F121: 72.656315 | G121: 118.81024 | H121: 0 | I121: 0 | J121: 314.94795 | K121: 266.6496 | L121: 376.38456 | M121: 465.60715 | N121: 461.81771 | O121: 1024.5723 | P121: 6469.381
A122: Total general | E122: 302505.26 | F122: 278500.6 | G122: 291283.71 | H122: 271765.18 | I122: 312956.31 | J122: 233211.48 | K122: 337985.09 | L122: 308609.16 | M122: 274865.2 | N122: 299438.16 | O122: 276467.25 | P122: 316828.87

Sheet Gasto Diciembre
A2: Clasificación 1 | B2: (Varios elementos)
A3: País | B3: (Todas)
A5: Suma de Valor USD | E5: Meses (Atributo) | U5: REDCO | V5: REDCROSS | W5: R+
A6: Clasificación 0 | B6: Clasificación 2 | C6: Clasificación 3 | D6: Detalle | E6: ene | F6: feb | G6: mar | H6: abr | I6: may | J6: jun | K6: jul | L6: ago | M6: sept | N6: oct | O6: nov | P6: dic
A7: Fijo | B7: Sueldos | C7: Asociado a sueldo | D7: Ricardo Miranda | E7: 0 | F7: 1467.7533 | G7: 0 | H7: 0 | I7: 260.87986 | J7: 0 | K7: 0 | L7: 0 | M7: 0 | N7: 0 | O7: 0 | P7: 0 | Q7: =+SUM(E7:P7) -> 1728.6331 | R7: 1 | S7: =+Q7*R7 -> 1728.6331 | U7: =+IF(P7>0,1,0) -> 0 | W7: =+IF(P7>0,1,0) -> 0
A8: Fijo | B8: Sueldos | C8: Sueldo | D8: Alejandro Espinosa | E8: 8612.8752 | F8: 8256.7911 | G8: 8277.5328 | H8: 8177.8985 | I8: 8346.2575 | J8: 8561.1387 | K8: 8384.322 | L8: 0 | M8: 12470.381 | N8: 0 | O8: 0 | P8: 0 | Q8: =+SUM(E8:P8) -> 71087.197 | R8: 1 | S8: =+Q8*R8 -> 71087.197 | U8: =+IF(P8>0,1,0) -> 0 | W8: =+IF(P8>0,1,0) -> 0
A9: Fijo | B9: Sueldos | C9: Sueldo | D9: Alex Figueroa | E9: 8425.1203 | F9: 8065.6523 | G9: 8084.2266 | H9: 9000.5222 | I9: 9188.1821 | J9: 9427.2681 | K9: 9215.5727 | L9: 9646.0851 | M9: 9698.6681 | N9: 8989.0109 | O9: 8785.0906 | P9: 8896.3497 | Q9: =+SUM(E9:P9) -> 107421.75 | R9: 1 | S9: =+Q9*R9 -> 107421.75 | U9: =+IF(P9>0,1,0) -> 1
A10: Fijo | B10: Sueldos | C10: Sueldo | D10: Alex Pacheco C. | E10: 2947.9802 | F10: 2825.3146 | G10: 2831.856 | H10: 2796.9641 | I10: 2854.5881 | J10: 2927.2905 | K10: 2944.313 | L10: 3029.1555 | M10: 3023.0005 | N10: 2797.3888 | O10: 2733.6622 | P10: 3505.8177 | Q10: =+SUM(E10:P10) -> 35217.331 | R10: 1 | S10: =+Q10*R10 -> 35217.331 | U10: =+IF(P10>0,1,0) -> 1
A11: Fijo | B11: Sueldos | C11: Sueldo | D11: Americo Zuzunaga | E11: 15627.149 | F11: 12771.726 | G11: 12720.817 | H11: 13033.347 | I11: 18057.936 | J11: 12583.422 | K11: 24597.319 | L11: 21641.216 | M11: 12712.144 | N11: 0 | O11: 0 | P11: 0 | Q11: =+SUM(E11:P11) -> 143745.07 | R11: 0 | S11: =+Q11*R11 -> 0 | U11: =+IF(P11>0,1,0) -> 0 | W11: =+IF(P11>0,1,0) -> 0
A12: Fijo | B12: Sueldos | C12: Sueldo | D12: Andree del Castillo | E12: 3378.5173 | F12: 2772.8232 | G12: 2818.1787 | H12: 2877.3642 | I12: 3966.4574 | J12: 3082.1981 | K12: 13291.234 | L12: 0 | M12: 0 | N12: 0 | O12: 0 | P12: 0 | Q12: =+SUM(E12:P12) -> 32186.772 | R12: 1 | S12: =+Q12*R12 -> 32186.772 | U12: =+IF(P12>0,1,0) -> 0 | W12: =+IF(P12>0,1,0) -> 0
A13: Fijo | B13: Sueldos | C13: Sueldo | D13: Andrés Budini M. | E13: 3630.5471 | F13: 3477.3079 | G13: 1991.6571 | H13: 3438.5715 | I13: 3509.267 | J13: 3598.4542 | K13: 3608.7223 | L13: 3694.1883 | M13: 3770.5848 | N13: 6794.0432 | O13: 0 | P13: 0 | Q13: =+SUM(E13:P13) -> 37513.343 | R13: 1 | S13: =+Q13*R13 -> 37513.343 | U13: =+IF(P13>0,1,0) -> 0 | W13: =+IF(P13>0,1,0) -> 0
A14: Fijo | B14: Sueldos | C14: Sueldo | D14: Angelo Patri Carbajal | E14: 655.65172 | F14: 658.4 | G14: 671.8624 | H14: 334.76 | I14: 0 | J14: 0 | K14: 0 | L14: 0 | M14: 0 | N14: 0 | O14: 0 | P14: 0 | Q14: =+SUM(E14:P14) -> 2320.6741 | R14: 1 | S14: =+Q14*R14 -> 2320.6741 | U14: =+IF(P14>0,1,0) -> 0 | W14: =+IF(P14>0,1,0) -> 0
A15: Fijo | B15: Sueldos | C15: Sueldo | D15: Arnold Tadeo | E15: 3002.0235 | F15: 1495.2351 | G15: 1519.6929 | H15: 1551.6122 | I15: 2138.8881 | J15: 1465.4653 | K15: 2922.7402 | L15: 2520.336 | M15: 1497.0419 | N15: 2305.4657 | O15: 2706.7812 | P15: 2868.3641 | Q15: =+SUM(E15:P15) -> 25993.646 | R15: 1 | S15: =+Q15*R15 -> 25993.646 | U15: =+IF(P15>0,1,0) -> 1
A16: Fijo | B16: Sueldos | C16: Sueldo | D16: CARLOS CARMELO HIDALGO | E16: 4101.7571 | F16: 0 | G16: 0 | H16: 0 | I16: 0 | J16: 0 | K16: 0 | L16: 0 | M16: 0 | N16: 0 | O16: 0 | P16: 0 | Q16: =+SUM(E16:P16) -> 4101.7571 | R16: 0 | S16: =+Q16*R16 -> 0 | U16: =+IF(P16>0,1,0) -> 0 | W16: =+IF(P16>0,1,0) -> 0
A17: Fijo | B17: Sueldos | C17: Sueldo | D17: Carlos Catalán | E17: 3582.3951 | F17: 2930.091 | G17: 2960.0891 | H17: 3022.2491 | I17: 4166.1994 | J17: 2854.4678 | K17: 6129.0731 | L17: 5367.0215 | M17: 2946.2263 | N17: 5676.5791 | O17: 6661.5991 | P17: 7066.0392 | Q17: =+SUM(E17:P17) -> 53362.03 | R17: 1 | S17: =+Q17*R17 -> 53362.03 | U17: =+IF(P17>0,1,0) -> 1
A18: Fijo | B18: Sueldos | C18: Sueldo | D18: Carlos Morante | E18: 3867.8791 | F18: 3174.4532 | G18: 3226.3782 | H18: 3294.14 | I18: 4540.9759 | J18: 3111.2584 | K18: 0 | L18: 0 | M18: 0 | N18: 0 | O18: 0 | P18: 0 | Q18: =+SUM(E18:P18) -> 21215.085 | R18: 1 | S18: =+Q18*R18 -> 21215.085 | U18: =+IF(P18>0,1,0) -> 0 | W18: =+IF(P18>0,1,0) -> 0
A19: Fijo | B19: Sueldos | C19: Sueldo | D19: Claudio Hernandez | E19: 10340.278 | F19: 9912.7777 | G19: 9941.9923 | H19: 9825.5356 | I19: 10030.851 | J19: 10291.81 | K19: 10050.912 | L19: 10530.224 | M19: 10562.402 | N19: 9818.5739 | O19: 9597.5381 | P19: 9600.55 | Q19: =+SUM(E19:P19) -> 120503.45 | R19: 1 | S19: =+Q19*R19 -> 120503.45 | U19: =+IF(P19>0,1,0) -> 1
A20: Fijo | B20: Sueldos | C20: Sueldo | D20: Clinton Yahuira | E20: 655.65172 | F20: 658.4 | G20: 671.8624 | H20: 669.52 | I20: 666.13 | J20: 654.96 | K20: 668 | L20: 654.96 | M20: 0 | N20: 0 | O20: 0 | P20: 0 | Q20: =+SUM(E20:P20) -> 5299.4841 | R20: 1 | S20: =+Q20*R20 -> 5299.4841 | U20: =+IF(P20>0,1,0) -> 0 | W20: =+IF(P20>0,1,0) -> 0
A21: Fijo | B21: Sueldos | C21: Sueldo | D21: Cristián Alarcón | E21: 2214.8278 | F21: 2123.0161 | G21: 2524.1096 | H21: 2492.4647 | I21: 2543.443 | J21: 2451.1332 | K21: 2490.2273 | L21: 2842.5992 | M21: 2682.7516 | N21: 2497.4535 | O21: 2442.0531 | P21: 2706.5608 | Q21: =+SUM(E21:P21) -> 30010.64 | R21: 1 | S21: =+Q21*R21 -> 30010.64 | U21: =+IF(P21>0,1,0) -> 1
A22: Fijo | B22: Sueldos | C22: Sueldo | D22: Cristián García | E22: 7950.2818 | F22: 8123.8317 | G22: 0 | H22: 0 | I22: 0 | J22: 0 | K22: 0 | L22: 0 | M22: 0 | N22: 0 | O22: 0 | P22: 0 | Q22: =+SUM(E22:P22) -> 16074.114 | R22: 0 | S22: =+Q22*R22 -> 0 | U22: =+IF(P22>0,1,0) -> 0 | W22: =+IF(P22>0,1,0) -> 0
A23: Fijo | B23: Sueldos | C23: Sueldo | D23: Cristian Quezada | E23: 0 | F23: 0 | G23: 8988.0921 | H23: 9037.1248 | I23: 9562.8774 | J23: 9618.1163 | K23: 9327.9782 | L23: 9841.642 | M23: 9929.0624 | N23: 6512.2778 | O23: 0 | P23: 0 | Q23: =+SUM(E23:P23) -> 72817.171 | R23: 1 | S23: =+Q23*R23 -> 72817.171 | U23: =+IF(P23>0,1,0) -> 0 | W23: =+IF(P23>0,1,0) -> 0
A24: Fijo | B24: Sueldos | C24: Sueldo | D24: Cristóbal García Wallis practicante | E24: 157.80001 | F24: 296.7861 | G24: 204.3325 | H24: 0 | I24: 0 | J24: 0 | K24: 0 | L24: 0 | M24: 0 | N24: 0 | O24: 0 | P24: 0 | Q24: =+SUM(E24:P24) -> 658.9186 | R24: 1 | S24: =+Q24*R24 -> 658.9186 | U24: =+IF(P24>0,1,0) -> 0 | W24: =+IF(P24>0,1,0) -> 0
A25: Fijo | B25: Sueldos | C25: Sueldo | D25: Daniela Oyarzo E. | E25: 1900.1613 | F25: 1821.3576 | G25: 2524.1096 | H25: 2492.4647 | I25: 2543.443 | J25: 2607.743 | K25: 2641.543 | L25: 2682.6035 | M25: 2682.7516 | N25: 2497.4535 | O25: 2442.0531 | P25: 2770.9919 | Q25: =+SUM(E25:P25) -> 29606.676 | R25: 1 | S25: =+Q25*R25 -> 29606.676 | U25: =+IF(P25>0,1,0) -> 1
A26: Fijo | B26: Sueldos | C26: Sueldo | D26: Diego Muñoz | E26: 1940.7741 | F26: 1860.2927 | G26: 1511.9865 | H26: 2215.5565 | I26: 2260.8933 | J26: 2318.0773 | K26: 3719.6206 | L26: 2386.5479 | M26: 2388.6901 | N26: 2221.8856 | O26: 2172.6046 | P26: 2448.8362 | Q26: =+SUM(E26:P26) -> 27445.765 | R26: 1 | S26: =+Q26*R26 -> 27445.765 | U26: =+IF(P26>0,1,0) -> 1
A27: Fijo | B27: Sueldos | C27: Sueldo | D27: Diego Troncoso | E27: 1616.1771 | F27: 1549.1156 | G27: 1552.441 | H27: 1533.0899 | I27: 1564.5228 | J27: 1078.9067 | K27: 0 | L27: 0 | M27: 0 | N27: 0 | O27: 0 | P27: 0 | Q27: =+SUM(E27:P27) -> 8894.2531 | R27: 1 | S27: =+Q27*R27 -> 8894.2531 | U27: =+IF(P27>0,1,0) -> 0 | W27: =+IF(P27>0,1,0) -> 0
A28: Fijo | B28: Sueldos | C28: Sueldo | D28: Eduardo Cuevas | E28: 2585.6758 | F28: 2478.5321 | G28: 3505.7078 | H28: 3458.9533 | I28: 3526.4912 | J28: 3613.3574 | K28: 3633.3522 | L28: 3709.3411 | M28: 3796.5793 | N28: 3453.7916 | O28: 3377.268 | P28: 3667.6687 | Q28: =+SUM(E28:P28) -> 40806.719 | R28: 0 | S28: =+Q28*R28 -> 0 | U28: =+IF(P28>0,1,0) -> 1
A29: Fijo | B29: Sueldos | C29: Sueldo | D29: Eduardo Lama | E29: 2045.6334 | F29: 2054.3 | G29: 2096.2107 | H29: 2088.91 | I29: 2078.34 | J29: 2043.49 | K29: 2084 | L29: 2043.49 | M29: 2518 | N29: 5798.04 | O29: 6807.4736 | P29: 7221.9285 | Q29: =+SUM(E29:P29) -> 38879.816 | R29: 0 | S29: =+Q29*R29 -> 0 | U29: =+IF(P29>0,1,0) -> 1
A30: Fijo | B30: Sueldos | C30: Sueldo | D30: Edward Torres | E30: 1683.1014 | F30: 1381.3582 | G30: 1403.9533 | H30: 1433.4381 | I30: 1976.0055 | J30: 1353.8577 | K30: 2699.9175 | L30: 2328.3911 | M30: 1383.3804 | N30: 2129.0036 | O30: 2498.775 | P30: 2650.119 | Q30: =+SUM(E30:P30) -> 22921.301 | R30: 1 | S30: =+Q30*R30 -> 22921.301 | U30: =+IF(P30>0,1,0) -> 1
A31: Fijo | B31: Sueldos | C31: Sueldo | D31: Emilio Sánchez | E31: 6440.2135 | F31: 6173.9543 | G31: 6184.0531 | H31: 5690.3406 | I31: 6233.7735 | J31: 5411.6844 | K31: 8398.601 | L31: 6548.0607 | M31: 6594.0449 | N31: 6079.7914 | O31: 12675.226 | P31: 6201.5179 | Q31: =+SUM(E31:P31) -> 82631.262 | R31: 1 | S31: =+Q31*R31 -> 82631.262 | U31: 0 | W31: =+IF(P31>0,1,0) -> 1
A32: Fijo | B32: Sueldos | C32: Sueldo | D32: Fabián González Recabarren | E32: 1606.9736 | F32: 1541.8742 | G32: 1545.1856 | H32: 1525.9263 | I32: 1557.2132 | J32: 2542.2702 | K32: 0 | L32: 0 | M32: 0 | N32: 0 | O32: 0 | P32: 0 | Q32: =+SUM(E32:P32) -> 10319.443 | R32: 1 | S32: =+Q32*R32 -> 10319.443 | U32: =+IF(P32>0,1,0) -> 0 | W32: =+IF(P32>0,1,0) -> 0
A33: Fijo | B33: Sueldos | C33: Sueldo | D33: Felipe Espinosa Practica en informática nov.23 | E33: 0 | F33: 0 | G33: 0 | H33: 308.17135 | I33: 0 | J33: 0 | K33: 0 | L33: 0 | M33: 0 | N33: 0 | O33: 0 | P33: 0 | Q33: =+SUM(E33:P33) -> 308.17135 | R33: 1 | S33: =+Q33*R33 -> 308.17135 | U33: =+IF(P33>0,1,0) -> 0 | W33: =+IF(P33>0,1,0) -> 0
A34: Fijo | B34: Sueldos | C34: Sueldo | D34: Felipe Lira A. | E34: 4374.5966 | F34: 4190.4798 | G34: 4627.5343 | H34: 4568.267 | I34: 4659.6313 | J34: 4776.4984 | K34: 4749.4501 | L34: 4897.0997 | M34: 3767.3152 | N34: 3300.8313 | O34: 4584.0874 | P34: 4701.2501 | Q34: =+SUM(E34:P34) -> 53197.041 | R34: 1 | S34: =+Q34*R34 -> 53197.041 | U34: =+IF(P34>0,1,0) -> 1
A35: Fijo | B35: Sueldos | C35: Sueldo | D35: Felipe Matamoros C. | E35: 4537.6827 | F35: 4348.7199 | G35: 4423.2777 | H35: 4366.3829 | I35: 4453.4068 | J35: 4564.9059 | K35: 5700.3997 | L35: 0 | M35: 0 | N35: 0 | O35: 0 | P35: 0 | Q35: =+SUM(E35:P35) -> 32394.776 | R35: 1 | S35: =+Q35*R35 -> 32394.776 | U35: =+IF(P35>0,1,0) -> 0 | W35: =+IF(P35>0,1,0) -> 0
A36: Fijo | B36: Sueldos | C36: Sueldo | D36: Felipe Rojas Z. | E36: 8782.9384 | F36: 8366.8112 | G36: 8373.8724 | H36: 8271.4672 | I36: 8440.0669 | J36: 8656.0283 | K36: 8389.7375 | L36: 8842.8204 | M36: 8926.0301 | N36: 8213.102 | O36: 8022.4436 | P36: 8278.3956 | Q36: =+SUM(E36:P36) -> 101563.71 | R36: 1 | S36: =+Q36*R36 -> 101563.71 | U36: =+IF(P36>0,1,0) -> 1
A37: Fijo | B37: Sueldos | C37: Sueldo | D37: Fernando Caballero | E37: 3560.658 | F37: 1415.3235 | G37: 0 | H37: 0 | I37: 0 | J37: 0 | K37: 0 | L37: 0 | M37: 0 | N37: 0 | O37: 0 | P37: 0 | Q37: =+SUM(E37:P37) -> 4975.9816 | R37: 1 | S37: =+Q37*R37 -> 4975.9816 | U37: =+IF(P37>0,1,0) -> 0 | W37: =+IF(P37>0,1,0) -> 0
A38: Fijo | B38: Sueldos | C38: Sueldo | D38: Francisco Bello Moreno | E38: 2360.8092 | F38: 2262.9608 | G38: 3085.0228 | H38: 3046.9277 | I38: 1593.0391 | J38: 3188.769 | K38: 3198.1772 | L38: 3275.6527 | M38: 6341.147 | N38: 0 | O38: 0 | P38: 0 | Q38: =+SUM(E38:P38) -> 28352.505 | R38: 1 | S38: =+Q38*R38 -> 28352.505 | U38: =+IF(P38>0,1,0) -> 0 | W38: =+IF(P38>0,1,0) -> 0
A39: Fijo | B39: Sueldos | C39: Sueldo | D39: Freddy Díaz | E39: 5083.8147 | F39: 4873.6334 | G39: 4887.8345 | H39: 4825.3029 | I39: 4915.4108 | J39: 6517.6964 | K39: 6426.1494 | L39: 6689.0507 | M39: 6729.9375 | N39: 6206.2222 | O39: 6064.6647 | P39: 6270.6616 | Q39: =+SUM(E39:P39) -> 69490.379 | R39: 1 | S39: =+Q39*R39 -> 69490.379 | U39: =+IF(P39>0,1,0) -> 1
A40: Fijo | B40: Sueldos | C40: Sueldo | D40: Gerson Alfaro | E40: 2947.5685 | F40: 2824.92 | G40: 4206.8493 | H40: 4151.3789 | I40: 4233.1904 | J40: 4337.9801 | K40: 4333.4784 | L40: 4449.8019 | M40: 4531.7376 | N40: 4139.3751 | O40: 4042.5536 | P40: 4312.2767 | Q40: =+SUM(E40:P40) -> 48511.11 | R40: 1 | S40: =+Q40*R40 -> 48511.11 | U40: =+IF(P40>0,1,0) -> 1
A41: Fijo | B41: Sueldos | C41: Sueldo | D41: Gino Espinoza | E41: 2466.5056 | F41: 2024.3153 | G41: 2057.4273 | H41: 2100.6381 | I41: 2895.7281 | J41: 1984.0207 | K41: 3955.8276 | L41: 3411.674 | M41: 2027.9609 | N41: 3121.3164 | O41: 3663.0691 | P41: 4359.2332 | Q41: =+SUM(E41:P41) -> 34067.716 | R41: 1 | S41: =+Q41*R41 -> 34067.716 | U41: =+IF(P41>0,1,0) -> 1
A42: Fijo | B42: Sueldos | C42: Sueldo | D42: Gladys Myriam Muñoz | E42: 799.46255 | F42: 753.45014 | G42: 727.39971 | H42: 733.30139 | I42: 3490.7308 | J42: 807.42053 | K42: 774.24805 | L42: 851.05925 | M42: 1238.6737 | N42: 699.62091 | O42: 747.12227 | P42: 1528.6645 | Q42: =+SUM(E42:P42) -> 13151.154 | R42: 0 | S42: =+Q42*R42 -> 0 | U42: =+IF(P42>0,1,0) -> 1
A43: Fijo | B43: Sueldos | C43: Sueldo | D43: Grace Ramon | E43: 157.80001 | F43: 296.7861 | G43: 1043.2699 | H43: 1384.8318 | I43: 1413.2443 | J43: 1449.086 | K43: 1481.5545 | L43: 1499.0632 | M43: 1500.7383 | N43: 1394.0304 | O43: 1354.2035 | P43: 1114.7698 | Q43: =+SUM(E43:P43) -> 14089.378 | R43: 1 | S43: =+Q43*R43 -> 14089.378 | U43: 0 | W43: 0
A44: Fijo | B44: Sueldos | C44: Sueldo | D44: Guillermo Ricaldi | E44: 472.06924 | F44: 474.1 | G44: 483.74093 | H44: 482.06 | I44: 479.62 | J44: 0 | K44: 0 | L44: 0 | M44: 0 | N44: 0 | O44: 0 | P44: 0 | Q44: =+SUM(E44:P44) -> 2391.5902 | R44: 1 | S44: =+Q44*R44 -> 2391.5902 | U44: =+IF(P44>0,1,0) -> 0 | W44: =+IF(P44>0,1,0) -> 0
A45: Fijo | B45: Sueldos | C45: Sueldo | D45: Ignacio González | E45: 1607.4686 | F45: 1411.7378 | G45: 1544.075 | H45: 474.45315 | I45: 0 | J45: 0 | K45: 0 | L45: 0 | M45: 0 | N45: 0 | O45: 0 | P45: 0 | Q45: =+SUM(E45:P45) -> 5037.7345 | R45: 1 | S45: =+Q45*R45 -> 5037.7345 | U45: =+IF(P45>0,1,0) -> 0 | W45: =+IF(P45>0,1,0) -> 0
A46: Fijo | B46: Sueldos | C46: Sueldo | D46: Isidora Figueroa | E46: 1801.6705 | F46: 1726.4404 | G46: 2243.653 | H46: 1983.776 | I46: 2102.277 | J46: 2154.9123 | K46: 2848.995 | L46: 2297.787 | M46: 2385.6853 | N46: 2215.8947 | O46: 2166.7467 | P46: 2304.156 | Q46: =+SUM(E46:P46) -> 26231.994 | R46: 1 | S46: =+Q46*R46 -> 26231.994 | U46: =+IF(P46>0,1,0) -> 1
A47: Fijo | B47: Sueldos | C47: Sueldo | D47: Ismael Leyton Aliste practicante | E47: 157.80001 | F47: 296.7861 | G47: 204.3325 | H47: 0 | I47: 0 | J47: 0 | K47: 0 | L47: 0 | M47: 0 | N47: 0 | O47: 0 | P47: 0 | Q47: =+SUM(E47:P47) -> 658.9186 | R47: 1 | S47: =+Q47*R47 -> 658.9186 | U47: =+IF(P47>0,1,0) -> 0 | W47: =+IF(P47>0,1,0) -> 0
A48: Fijo | B48: Sueldos | C48: Sueldo | D48: Jarold Orna | E48: 1704.6945 | F48: 1514.2693 | G48: 2605.5226 | H48: 2669.4747 | I48: 3679.8886 | J48: 2521.2884 | K48: 5026.5344 | L48: 4336.1613 | M48: 2576.8264 | N48: 3964.6677 | O48: 4651.7736 | P48: 4818.3982 | Q48: =+SUM(E48:P48) -> 40069.5 | R48: 1 | S48: =+Q48*R48 -> 40069.5 | U48: =+IF(P48>0,1,0) -> 1
A49: Fijo | B49: Sueldos | C49: Sueldo | D49: Jessica Rojas | E49: 3345.9327 | F49: 2746.0803 | G49: 2790.9983 | H49: 2849.6109 | I49: 3928.1958 | J49: 2691.4163 | K49: 0 | L49: 0 | M49: 0 | N49: 0 | O49: 0 | P49: 0 | Q49: =+SUM(E49:P49) -> 18352.234 | R49: 0 | S49: =+Q49*R49 -> 0 | U49: =+IF(P49>0,1,0) -> 0 | W49: =+IF(P49>0,1,0) -> 0
A50: Fijo | B50: Sueldos | C50: Sueldo | D50: Jhonatan Huaynate | E50: 1442.4338 | F50: 1448.5 | G50: 1478.0973 | H50: 1472.95 | I50: 1465.49 | J50: 1440.92 | K50: 1470 | L50: 1440.92 | M50: 1640.6143 | N50: 2523.1787 | O50: 2963.4121 | P50: 3143.2962 | Q50: =+SUM(E50:P50) -> 21929.812 | R50: 1 | S50: =+Q50*R50 -> 21929.812 | U50: =+IF(P50>0,1,0) -> 1
A51: Fijo | B51: Sueldos | C51: Sueldo | D51: Jhonatan Mandujano | E51: 2066.9563 | F51: 1696.3964 | G51: 1724.1446 | H51: 1859.9352 | I51: 2563.9294 | J51: 1756.6901 | K51: 3501.5007 | L51: 3021.1901 | M51: 1794.6556 | N51: 2763.8088 | O51: 3241.6541 | P51: 3440.9032 | Q51: =+SUM(E51:P51) -> 29431.764 | R51: 1 | S51: =+Q51*R51 -> 29431.764 | U51: =+IF(P51>0,1,0) -> 1
A52: Fijo | B52: Sueldos | C52: Sueldo | D52: Joél Pérez | E52: 1608.1299 | F52: 1541.3997 | G52: 1544.7102 | H52: 1525.4569 | I52: 1556.7343 | J52: 1596.1891 | K52: 1653.6324 | L52: 1638.0232 | M52: 1635.0798 | N52: 1525.1589 | O52: 1491.3477 | P52: 1806.5452 | Q52: =+SUM(E52:P52) -> 19122.407 | R52: 1 | S52: =+Q52*R52 -> 19122.407 | U52: =+IF(P52>0,1,0) -> 1
A53: Fijo | B53: Sueldos | C53: Sueldo | D53: Johnny Pacheco | E53: 3413.9611 | F53: 2801.9127 | G53: 2847.744 | H53: 2907.5556 | I53: 4008.0756 | J53: 2746.1319 | K53: 5475.0738 | L53: 4722.8516 | M53: 2807.1405 | N53: 5348.8638 | O53: 6278.0034 | P53: 6723.0826 | Q53: =+SUM(E53:P53) -> 50080.397 | R53: 1 | S53: =+Q53*R53 -> 50080.397 | U53: =+IF(P53>0,1,0) -> 1
A54: Fijo | B54: Sueldos | C54: Sueldo | D54: Jonathan Galvez | E54: 1899.7832 | F54: 1820.9965 | G54: 1824.8457 | H54: 1802.0481 | I54: 1838.9605 | J54: 1885.5217 | K54: 1942.8791 | L54: 1944.6447 | M54: 1941.9936 | N54: 1810.5616 | O54: 1770.4127 | P54: 2063.9747 | Q54: =+SUM(E54:P54) -> 22546.622 | R54: 1 | S54: =+Q54*R54 -> 22546.622 | U54: 0 | W54: 0
A55: Fijo | B55: Sueldos | C55: Sueldo | D55: Jorman Barrera | E55: 6027.8688 | F55: 4765.172 | G55: 4843.1167 | H55: 4943.5177 | I55: 6814.6612 | J55: 4669.0712 | K55: 9309.3617 | L55: 8030.164 | M55: 4772.2884 | N55: 7342.6562 | O55: 8455.3144 | P55: 9106.7725 | Q55: =+SUM(E55:P55) -> 79079.965 | R55: 1 | S55: =+Q55*R55 -> 79079.965 | U55: =+IF(P55>0,1,0) -> 1
A56: Fijo | B56: Sueldos | C56: Sueldo | D56: Jose Mamani | E56: 655.65172 | F56: 658.4 | G56: 1084.1172 | H56: 1080.34 | I56: 1074.87 | J56: 1056.85 | K56: 1078 | L56: 2062.35 | M56: 0 | N56: 0 | O56: 0 | P56: 0 | Q56: =+SUM(E56:P56) -> 8750.5789 | R56: 1 | S56: =+Q56*R56 -> 8750.5789 | U56: =+IF(P56>0,1,0) -> 0 | W56: =+IF(P56>0,1,0) -> 0
A57: Fijo | B57: Sueldos | C57: Sueldo | D57: José Pizarro Aranguiz | E57: 1608.1299 | F57: 1541.3997 | G57: 1822.968 | H57: 1800.1942 | I57: 1837.0688 | J57: 2463.6785 | K57: 2485.6878 | L57: 2517.8079 | M57: 2523.7331 | N57: 2344.0608 | O57: 2292.0673 | P57: 2062.2492 | Q57: =+SUM(E57:P57) -> 25299.045 | R57: 1 | S57: =+Q57*R57 -> 25299.045 | U57: =+IF(P57>0,1,0) -> 1
A58: Fijo | B58: Sueldos | C58: Sueldo | D58: Josue Tello Olivas | E58: 813.01 | F58: 816.4 | G58: 833.10938 | H58: 207.55 | I58: 0 | J58: 0 | K58: 0 | L58: 0 | M58: 0 | N58: 0 | O58: 0 | P58: 0 | Q58: =+SUM(E58:P58) -> 2670.0694 | R58: 1 | S58: =+Q58*R58 -> 2670.0694 | U58: =+IF(P58>0,1,0) -> 0 | W58: =+IF(P58>0,1,0) -> 0
A59: Fijo | B59: Sueldos | C59: Sueldo | D59: Juan Pablo Vera | E59: 1954.0567 | F59: 1308.9424 | G59: 0 | H59: 0 | I59: 0 | J59: 0 | K59: 0 | L59: 0 | M59: 0 | N59: 0 | O59: 0 | P59: 0 | Q59: =+SUM(E59:P59) -> 3262.999 | R59: 1 | S59: =+Q59*R59 -> 3262.999 | U59: =+IF(P59>0,1,0) -> 0 | W59: =+IF(P59>0,1,0) -> 0
A60: Fijo | B60: Sueldos | C60: Sueldo | D60: Julio Herrera | E60: 3224.2443 | F60: 3090.157 | G60: 3097.2087 | H60: 3058.9594 | I60: 3121.9211 | J60: 3148.9039 | K60: 0 | L60: 0 | M60: 0 | N60: 0 | O60: 0 | P60: 0 | Q60: =+SUM(E60:P60) -> 18741.394 | R60: 1 | S60: =+Q60*R60 -> 18741.394 | U60: =+IF(P60>0,1,0) -> 0 | W60: =+IF(P60>0,1,0) -> 0
A61: Fijo | B61: Sueldos | C61: Sueldo | D61: Kevin Rios | E61: 3790.2846 | F61: 4848.606 | G61: 3161.653 | H61: 3228.0533 | I61: 5143.8773 | J61: 3524.35 | K61: 7026.1518 | L61: 6061.2462 | M61: 3601.2756 | N61: 5543.6596 | O61: 6504.9192 | P61: 6901.6468 | Q61: =+SUM(E61:P61) -> 59335.723 | R61: 1 | S61: =+Q61*R61 -> 59335.723 | U61: =+IF(P61>0,1,0) -> 1
A62: Fijo | B62: Sueldos | C62: Sueldo | D62: Lincoln Esteban Perez | E62: 655.65172 | F62: 658.4 | G62: 671.8624 | H62: 167.38 | I62: 0 | J62: 0 | K62: 0 | L62: 0 | M62: 0 | N62: 0 | O62: 0 | P62: 0 | Q62: =+SUM(E62:P62) -> 2153.2941 | R62: 1 | S62: =+Q62*R62 -> 2153.2941 | U62: =+IF(P62>0,1,0) -> 0 | W62: =+IF(P62>0,1,0) -> 0
A63: Fijo | B63: Sueldos | C63: Sueldo | D63: Luis Camasca | E63: 1294.2706 | F63: 1062.2362 | G63: 1079.6114 | H63: 0 | I63: 0 | J63: 0 | K63: 0 | L63: 0 | M63: 0 | N63: 0 | O63: 0 | P63: 0 | Q63: =+SUM(E63:P63) -> 3436.1182 | R63: 1 | S63: =+Q63*R63 -> 3436.1182 | U63: =+IF(P63>0,1,0) -> 0 | W63: =+IF(P63>0,1,0) -> 0
A64: Fijo | B64: Sueldos | C64: Sueldo | D64: Luis Chumpitaz | E64: 367.16496 | F64: 368.7 | G64: 376.24295 | H64: 374.93 | I64: 373.03 | J64: 366.78 | K64: 855 | L64: 838.35 | M64: 848 | N64: 852 | O64: 849 | P64: 1179 | Q64: =+SUM(E64:P64) -> 7648.1979 | R64: 1 | S64: =+Q64*R64 -> 7648.1979 | U64: =+IF(P64>0,1,0) -> 1
A65: Fijo | B65: Sueldos | C65: Sueldo | D65: Marcelo Mendoza | E65: 1900.1613 | F65: 1821.3576 | G65: 1825.2075 | H65: 1802.4053 | I65: 1839.3249 | J65: 1885.8954 | K65: 1944.1036 | L65: 1789.7951 | M65: 1945.5428 | N65: 1781.9181 | O65: 3501.4898 | P65: 2064.3072 | Q65: =+SUM(E65:P65) -> 24101.508 | R65: 1 | S65: =+Q65*R65 -> 24101.508 | U65: 0 | W65: =+IF(P65>0,1,0) -> 1
A66: Fijo | B66: Sueldos | C66: Sueldo | D66: Matías Cid Uslar | E66: 928.23769 | F66: 1486.1762 | G66: 1485.2394 | H66: 1465.9216 | I66: 1495.1102 | J66: 1532.3384 | K66: 1603.47 | L66: 1924.1712 | M66: 1956.9501 | N66: 1775.861 | O66: 1735.0928 | P66: 2061.7969 | Q66: =+SUM(E66:P66) -> 19450.366 | R66: 1 | S66: =+Q66*R66 -> 19450.366 | U66: =+IF(P66>0,1,0) -> 1
A67: Fijo | B67: Sueldos | C67: Sueldo | D67: Matías Fuentes B. | E67: 10427.76 | F67: 9983.5296 | G67: 10086.708 | H67: 9968.5089 | I67: 10176.831 | J67: 10441.538 | K67: 10945.563 | L67: 12068.867 | M67: 11352.381 | N67: 10483.642 | O67: 10174.684 | P67: 9862.5657 | Q67: =+SUM(E67:P67) -> 125972.58 | R67: 0 | S67: =+Q67*R67 -> 0 | U67: =+IF(P67>0,1,0) -> 1
A68: Fijo | B68: Sueldos | C68: Sueldo | D68: Mauricio Melendez | E68: 6756.0611 | F68: 6512.7914 | G68: 8230.7512 | H68: 8132.7126 | I68: 8260.3497 | J68: 8477.7067 | K68: 8303.7475 | L68: 8676.4372 | M68: 8709.3315 | N68: 8066.0706 | O68: 7883.1299 | P68: 19756.918 | Q68: =+SUM(E68:P68) -> 107766.01 | R68: 1 | S68: =+Q68*R68 -> 107766.01 | U68: 0 | W68: 0
A69: Fijo | B69: Sueldos | C69: Sueldo | D69: Miguel Jesus | E69: 7859.4716 | F69: 6450.4407 | G69: 6555.9515 | H69: 6693.4514 | I69: 9226.9465 | J69: 6321.8667 | K69: 12605.402 | L69: 0 | M69: 0 | N69: 0 | O69: 0 | P69: 0 | Q69: =+SUM(E69:P69) -> 55713.531 | R69: 1 | S69: =+Q69*R69 -> 55713.531 | U69: =+IF(P69>0,1,0) -> 0 | W69: =+IF(P69>0,1,0) -> 0
A70: Fijo | B70: Sueldos | C70: Sueldo | D70: Nelson Rumino | E70: 8571.5704 | F70: 8217.194 | G70: 8208.0735 | H70: 5202.6789 | I70: 9345.9367 | J70: 0 | K70: 0 | L70: 0 | M70: 0 | N70: 0 | O70: 0 | P70: 0 | Q70: =+SUM(E70:P70) -> 39545.453 | R70: 1 | S70: =+Q70*R70 -> 39545.453 | U70: =+IF(P70>0,1,0) -> 0 | W70: =+IF(P70>0,1,0) -> 0
A71: Fijo | B71: Sueldos | C71: Sueldo | D71: Nicolás Ayarza D. | E71: 2947.789 | F71: 2825.1313 | G71: 4206.8493 | H71: 4151.3789 | I71: 4233.1904 | J71: 4337.9801 | K71: 4333.4784 | L71: 4449.8019 | M71: 4531.7376 | N71: 4126.6661 | O71: 4030.0378 | P71: 4312.2767 | Q71: =+SUM(E71:P71) -> 48486.317 | R71: 1 | S71: =+Q71*R71 -> 48486.317 | U71: =+IF(P71>0,1,0) -> 1
A72: Fijo | B72: Sueldos | C72: Sueldo | D72: Nicolás Sanzana | E72: 1938.2542 | F72: 1857.877 | G72: 2243.653 | H72: 2215.5565 | I72: 2260.8933 | J72: 2318.0773 | K72: 2360.6434 | L72: 2386.5227 | M72: 2388.0888 | N72: 2221.8622 | O72: 2172.5817 | P72: 2448.8362 | Q72: =+SUM(E72:P72) -> 26812.846 | R72: 1 | S72: =+Q72*R72 -> 26812.846 | U72: =+IF(P72>0,1,0) -> 1
A73: Fijo | B73: Sueldos | C73: Sueldo | D73: Nilcélio José Dos Santos | E73: 2829.304 | F73: 2609.6521 | G73: 3831.9996 | H73: 2879.8682 | I73: 1881.46 | J73: 3098.1 | K73: 4489.222 | L73: 2622.9914 | M73: 2724.3547 | N73: 2292.3891 | O73: 4295.2801 | P73: 3585.5581 | Q73: =+SUM(E73:P73) -> 37140.179 | R73: 0 | S73: =+Q73*R73 -> 0 | U73: 0 | W73: 0
A74: Fijo | B74: Sueldos | C74: Sueldo | D74: Olesya Dashavskaya | E74: 3341.2793 | F74: 3225.9169 | G74: 3130.9925 | H74: 3092.3157 | I74: 3155.957 | J74: 3447.4363 | K74: 3341.4649 | L74: 3754.8482 | M74: 3457.0857 | N74: 3177.1164 | O74: 3104.7693 | P74: 3458.5523 | Q74: =+SUM(E74:P74) -> 39687.734 | R74: 0 | S74: =+Q74*R74 -> 0 | U74: 0 | W74: =+IF(P74>0,1,0) -> 1
A75: Fijo | B75: Sueldos | C75: Sueldo | D75: Omar Meléndez Huamán | E75: 1966.9552 | F75: 1975.2 | G75: 2015.5872 | H75: 0 | I75: 0 | J75: 0 | K75: 0 | L75: 0 | M75: 0 | N75: 0 | O75: 0 | P75: 0 | Q75: =+SUM(E75:P75) -> 5957.7424 | R75: 1 | S75: =+Q75*R75 -> 5957.7424 | U75: =+IF(P75>0,1,0) -> 0 | W75: =+IF(P75>0,1,0) -> 0
A76: Fijo | B76: Sueldos | C76: Sueldo | D76: Oscar Cáceres servicios | E76: 0 | F76: 0 | G76: 6729.0529 | H76: 0 | I76: 0 | J76: 0 | K76: 0 | L76: 0 | M76: 0 | N76: 0 | O76: 0 | P76: 0 | Q76: =+SUM(E76:P76) -> 6729.0529 | R76: 0 | S76: =+Q76*R76 -> 0 | U76: =+IF(P76>0,1,0) -> 0 | W76: =+IF(P76>0,1,0) -> 0
A77: Fijo | B77: Sueldos | C77: Sueldo | D77: Osvaldo Ulloa | E77: 1462.6464 | F77: 720.92549 | G77: 0 | H77: 561.93443 | I77: 0 | J77: 0 | K77: 0 | L77: 0 | M77: 0 | N77: 0 | O77: 0 | P77: 0 | Q77: =+SUM(E77:P77) -> 2745.5063 | R77: 0 | S77: =+Q77*R77 -> 0 | U77: =+IF(P77>0,1,0) -> 0 | W77: =+IF(P77>0,1,0) -> 0
A78: Fijo | B78: Sueldos | C78: Sueldo | D78: Pablo Quiero | E78: 6116.6473 | F78: 5859.2992 | G78: 5868.7329 | H78: 5770.9611 | I78: 5886.5524 | J78: 6034.1019 | K78: 5965.323 | L78: 6181.7069 | M78: 6249.5378 | N78: 5733.3651 | O78: 5600.9214 | P78: 5820.3729 | Q78: =+SUM(E78:P78) -> 71087.522 | R78: 1 | S78: =+Q78*R78 -> 71087.522 | U78: =+IF(P78>0,1,0) -> 1
A79: Fijo | B79: Sueldos | C79: Sueldo | D79: Paolo Tito | E79: 1994.709 | F79: 1637.1014 | G79: 1663.8797 | H79: 1698.8277 | I79: 6991.7565 | J79: 0 | K79: 0 | L79: 0 | M79: 0 | N79: 0 | O79: 274 | P79: 0 | Q79: =+SUM(E79:P79) -> 14260.274 | R79: 1 | S79: =+Q79*R79 -> 14260.274 | U79: =+IF(P79>0,1,0) -> 0 | W79: =+IF(P79>0,1,0) -> 0
A80: Fijo | B80: Sueldos | C80: Sueldo | D80: Pedro Aguiluz P. | E80: 2955.3281 | F80: 2832.3588 | G80: 4206.8493 | H80: 4151.3955 | I80: 4233.2229 | J80: 4338.0264 | K80: 4333.526 | L80: 4449.8699 | M80: 4531.8154 | N80: 4135.1181 | O80: 4038.3857 | P80: 4441.1686 | Q80: =+SUM(E80:P80) -> 48647.065 | R80: 0 | S80: =+Q80*R80 -> 0 | U80: =+IF(P80>0,1,0) -> 1
A81: Fijo | B81: Sueldos | C81: Sueldo | D81: Pedro Ccanto | E81: 655.65172 | F81: 658.4 | G81: 671.8624 | H81: 669.52 | I81: 666.13 | J81: 654.96 | K81: 0 | L81: 0 | M81: 0 | N81: 0 | O81: 0 | P81: 0 | Q81: =+SUM(E81:P81) -> 3976.5241 | R81: 1 | S81: =+Q81*R81 -> 3976.5241 | U81: =+IF(P81>0,1,0) -> 0 | W81: =+IF(P81>0,1,0) -> 0
A82: Fijo | B82: Sueldos | C82: Sueldo | D82: Ricardo Miranda | E82: 9705.5518 | F82: 9689.2921 | G82: 9152.7915 | H82: 9549.1047 | I82: 10598.236 | J82: 0 | K82: 16952.004 | L82: 10605.981 | M82: 9094.1616 | N82: 15822.168 | O82: 13212.968 | P82: 13223.502 | Q82: =+SUM(E82:P82) -> 127605.76 | R82: 1 | S82: =+Q82*R82 -> 127605.76 | U82: 0 | W82: =+IF(P82>0,1,0) -> 1
A83: Fijo | B83: Sueldos | C83: Sueldo | D83: Rodrigo Cori Córdova | E83: 9029.0693 | F83: 6945.5798 | G83: 7059.1897 | H83: 7206.1373 | I83: 9933.6704 | J83: 6806.0767 | K83: 13571.932 | L83: 11704.079 | M83: 6955.7861 | N83: 13704.458 | O83: 13633.857 | P83: 14460.863 | Q83: =+SUM(E83:P83) -> 121010.7 | R83: 1 | S83: =+Q83*R83 -> 121010.7 | U83: =+IF(P83>0,1,0) -> 1
A84: Fijo | B84: Sueldos | C84: Sueldo | D84: Rodrigo Pinto H. | E84: 0 | F84: 3372.6944 | G84: 0 | H84: 0 | I84: 0 | J84: 0 | K84: 0 | L84: 0 | M84: 0 | N84: 0 | O84: 0 | P84: 0 | Q84: =+SUM(E84:P84) -> 3372.6944 | R84: 1 | S84: =+Q84*R84 -> 3372.6944 | U84: =+IF(P84>0,1,0) -> 0 | W84: =+IF(P84>0,1,0) -> 0
A85: Fijo | B85: Sueldos | C85: Sueldo | D85: Roxana Avilés | E85: 1882.588 | F85: 1803.9649 | G85: 1806.7268 | H85: 1783.4191 | I85: 1819.1622 | J85: 1864.6137 | K85: 1921.339 | L85: 1910.8177 | M85: 1931.1291 | N85: 2260.7647 | O85: 2210.6205 | P85: 2045.9159 | Q85: =+SUM(E85:P85) -> 23241.062 | R85: 0 | S85: =+Q85*R85 -> 0 | U85: =+IF(P85>0,1,0) -> 1
A86: Fijo | B86: Sueldos | C86: Sueldo | D86: Sebastián González | E86: 1607.8029 | F86: 1541.0876 | G86: 1544.3975 | H86: 513.72151 | I86: 0 | J86: 0 | K86: 0 | L86: 0 | M86: 0 | N86: 0 | O86: 0 | P86: 0 | Q86: =+SUM(E86:P86) -> 5207.0095 | R86: 1 | S86: =+Q86*R86 -> 5207.0095 | U86: =+IF(P86>0,1,0) -> 0 | W86: =+IF(P86>0,1,0) -> 0
A87: Fijo | B87: Sueldos | C87: Sueldo | D87: Thalia Rimac | E87: 675.02842 | F87: 554.01063 | G87: 563.06825 | H87: 574.89325 | I87: 2217.0896 | J87: 0 | K87: 0 | L87: 0 | M87: 0 | N87: 0 | O87: 0 | P87: 0 | Q87: =+SUM(E87:P87) -> 4584.0901 | R87: 1 | S87: =+Q87*R87 -> 4584.0901 | U87: =+IF(P87>0,1,0) -> 0 | W87: =+IF(P87>0,1,0) -> 0
A88: Fijo | B88: Sueldos | C88: Sueldo | D88: Victor Arias | E88: 3478.5661 | F88: 2854.9355 | G88: 2901.6341 | H88: 2962.5717 | I88: 4083.919 | J88: 2798.1089 | K88: 5587.9321 | L88: 4820.2371 | M88: 2863.9713 | N88: 4406.9688 | O88: 5173.1396 | P88: 5490.1396 | Q88: =+SUM(E88:P88) -> 47422.124 | R88: 0 | S88: =+Q88*R88 -> 0 | U88: =+IF(P88>0,1,0) -> 1
A89: Fijo | B89: Sueldos | C89: Sueldo | D89: Victor Mohana Tapia | E89: 2200.2998 | F89: 1799.0398 | G89: 2524.1096 | H89: 2467.2148 | I89: 2517.6787 | J89: 2581.33 | K89: 2614.7413 | L89: 2655.4243 | M89: 2625.4619 | N89: 2467.1972 | O89: 2410.9698 | P89: 2683.0602 | Q89: =+SUM(E89:P89) -> 29546.527 | R89: 1 | S89: =+Q89*R89 -> 29546.527 | U89: =+IF(P89>0,1,0) -> 1
A90: Fijo | B90: Sueldos | C90: Sueldo | D90: VILLANUEVA CRISTOBAL PAOLO CESAR | E90: 1192.3895 | F90: 978.6202 | G90: 0 | H90: 0 | I90: 0 | J90: 0 | K90: 0 | L90: 0 | M90: 0 | N90: 0 | O90: 0 | P90: 0 | Q90: =+SUM(E90:P90) -> 2171.0097 | R90: 1 | S90: =+Q90*R90 -> 2171.0097 | U90: =+IF(P90>0,1,0) -> 0 | W90: =+IF(P90>0,1,0) -> 0
A91: Fijo | B91: Sueldos | C91: Sueldo | D91: Walter Lupinta | E91: 1835.82 | F91: 1843.6 | G91: 1881.2147 | H91: 0 | I91: 0 | J91: 0 | K91: 0 | L91: 0 | M91: 0 | N91: 0 | O91: 0 | P91: 0 | Q91: =+SUM(E91:P91) -> 5560.6347 | R91: 1 | S91: =+Q91*R91 -> 5560.6347 | U91: =+IF(P91>0,1,0) -> 0 | W91: =+IF(P91>0,1,0) -> 0
A92: Fijo | B92: Sueldos | C92: Sueldo | D92: Yosep Aviles | E92: 1180.1731 | F92: 1185.1 | G92: 1209.3523 | H92: 0 | I92: 0 | J92: 0 | K92: 0 | L92: 0 | M92: 0 | N92: 0 | O92: 0 | P92: 0 | Q92: =+SUM(E92:P92) -> 3574.6254 | R92: 1 | S92: =+Q92*R92 -> 3574.6254 | U92: =+IF(P92>0,1,0) -> 0 | W92: =+IF(P92>0,1,0) -> 0
A93: Fijo | B93: Sueldos | C93: Sueldo | D93: Cristóbal Ventura | E93: 0 | F93: 0 | G93: 0 | H93: 0 | I93: 2056.2749 | J93: 1580.6023 | K93: 1584.3983 | L93: 1634.3019 | M93: 1652.3532 | N93: 1500.5437 | O93: 2962.9778 | P93: 1726.8078 | Q93: =+SUM(E93:P93) -> 14698.26 | R93: 1 | S93: =+Q93*R93 -> 14698.26 | U93: 0 | W93: =+IF(P93>0,1,0) -> 1
A94: Fijo | B94: Sueldos | C94: Sueldo | D94: Gonzalo Parada Provisión | E94: 0 | F94: 0 | G94: 0 | H94: 0 | I94: 0 | J94: 0 | K94: 0 | L94: 0 | M94: 0 | N94: 0 | O94: 0 | P94: 0 | Q94: =+SUM(E94:P94) -> 0 | R94: 0 | S94: =+Q94*R94 -> 0 | U94: =+IF(P94>0,1,0) -> 0 | W94: =+IF(P94>0,1,0) -> 0
A95: Fijo | B95: Sueldos | C95: Sueldo | D95: Javier Salazar | E95: 0 | F95: 0 | G95: 0 | H95: 0 | I95: 0 | J95: 0 | K95: 547.95406 | L95: 1627.9381 | M95: 1636.0101 | N95: 1515.7717 | O95: 1482.169 | P95: 1650.2545 | Q95: =+SUM(E95:P95) -> 8460.0975 | R95: 1 | S95: =+Q95*R95 -> 8460.0975 | U95: =+IF(P95>0,1,0) -> 1
A96: Fijo | B96: Sueldos | C96: Sueldo | D96: Edson Susanibar | E96: 0 | F96: 0 | G96: 0 | H96: 0 | I96: 0 | J96: 196.49 | K96: 481 | L96: 471.57 | M96: 477 | N96: 479 | O96: 0 | P96: 0 | Q96: =+SUM(E96:P96) -> 2105.06 | R96: 1 | S96: =+Q96*R96 -> 2105.06 | U96: =+IF(P96>0,1,0) -> 0 | W96: =+IF(P96>0,1,0) -> 0
A97: Fijo | B97: Sueldos | C97: Sueldo | D97: Eduardo Sanchez | E97: 0 | F97: 0 | G97: 0 | H97: 0 | I97: 0 | J97: 0 | K97: 0 | L97: 1199.7126 | M97: 5141.6884 | N97: 7819.3331 | O97: 9071.2287 | P97: 9716.1582 | Q97: =+SUM(E97:P97) -> 32948.121 | R97: 1 | S97: =+Q97*R97 -> 32948.121 | U97: =+IF(P97>0,1,0) -> 1
A98: Fijo | B98: Sueldos | C98: Sueldo | D98: Max Le Clerc | E98: 2059.2952 | F98: 2047.8241 | G98: 1922.5866 | H98: 2126.3823 | I98: 2250.0888 | J98: 0 | K98: 3847.0988 | L98: 1902.8023 | M98: 2241.0612 | N98: 0 | O98: 0 | P98: 0 | Q98: =+SUM(E98:P98) -> 18397.139 | R98: 0 | S98: =+Q98*R98 -> 0 | U98: =+IF(P98>0,1,0) -> 0 | W98: =+IF(P98>0,1,0) -> 0
A99: Fijo | B99: Sueldos | C99: Sueldo | D99: Rodrigo Báez | E99: 0 | F99: 0 | G99: 0 | H99: 0 | I99: 0 | J99: 0 | K99: 0 | L99: 0 | M99: 7567.3929 | N99: 6949.0928 | O99: 6791.0936 | P99: 6820.6214 | Q99: =+SUM(E99:P99) -> 28128.201 | R99: 1 | S99: =+Q99*R99 -> 28128.201 | U99: =+IF(P99>0,1,0) -> 1
A100: Fijo | B100: Sueldos | C100: Sueldo | D100: Maria Célia P. Fonseca | E100: 1531.846 | F100: 1546.9079 | G100: 2115.5404 | H100: 1599.2618 | I100: 1060.36 | J100: 1558.91 | K100: 1362.778 | L100: 1463.2386 | M100: 1558.6453 | N100: 1258.6109 | O100: 2365.7199 | P100: 1980.4419 | Q100: =+SUM(E100:P100) -> 19402.261 | R100: 0 | S100: =+Q100*R100 -> 0 | U100: =+IF(P100>0,1,0) -> 1
A101: Fijo | B101: Sueldos | C101: Sueldo | D101: Antônio Alberto Fróes Schettino | E101: 2802.86 | F101: 2844.04 | G101: 2846.91 | H101: 2881.39 | I101: 2950.14 | J101: 2720.9 | K101: 2788 | L101: 2956.01 | M101: 2946 | N101: 2695 | O101: 2806 | P101: 3034 | Q101: =+SUM(E101:P101) -> 34271.25 | R101: 0 | S101: =+Q101*R101 -> 0 | U101: =+IF(P101>0,1,0) -> 1
A102: Fijo | B102: Sueldos | C102: Sueldo | D102: Mateo Villanueva | E102: 0 | F102: 0 | G102: 0 | H102: 0 | I102: 0 | J102: 0 | K102: 0 | L102: 838.3 | M102: 848 | N102: 852 | O102: 848 | P102: 858 | Q102: =+SUM(E102:P102) -> 4244.3 | R102: 1 | S102: =+Q102*R102 -> 4244.3 | U102: =+IF(P102>0,1,0) -> 1
...

Sheet Hoja2
A1: Nombre | B1: 45292 | C1: 45323 | D1: 45352 | E1: 45383 | F1: 45413 | G1: 45444 | H1: 45474 | I1: 45505 | J1: 45536 | K1: 45566 | L1: 45597 | M1: 45627
A2: Patricio Vegara (EEUU) | B2: 42.198646 | C2: 0 | D2: 13.886803 | E2: 0 | F2: 0 | G2: 22.741378 | H2: 0 | I2: 7.5692946 | J2: 0 | K2: 1.1561931 | L2: 34.823875 | M2: 15.173832
A3: SERVICIO ASESORIA MINERA - Comissão Antonio | B3: 0 | C3: 35.36673 | D3: 0 | E3: 0 | F3: 35.57758 | G3: 2.10623 | H3: 0 | I3: 0 | J3: 0 | K3: 28.516 | L3: 0 | M3: 6.115
B4: =+B2+B3 -> 42.198646 | C4: =+C2+C3 -> 35.36673 | D4: =+D2+D3 -> 13.886803 | E4: =+E2+E3 -> 0 | F4: =+F2+F3 -> 35.57758 | G4: =+G2+G3 -> 24.847608 | H4: =+H2+H3 -> 0 | I4: =+I2+I3 -> 7.5692946 | ... M4: =+M2+M3 -> 21.288832 | O4: 1000
A6: Total valores | B6: 42.198646 | C6: 35.36673 | D6: 13.886803 | E6: 0 | F6: 35.57758 | G6: 24.847608 | H6: 0 | I6: 7.5692946 | J6: 0 | K6: 29.672193 | L6: 34.823875 | M6: 21.288832
A9: Externo Fijo | B9: 4375.7069 | C9: 3900.039 | D9: 7037.4952 | E9: 2996.3265 | F9: 7545.7184 | G9: 4977.1768 | H9: 15134.918 | I9: 4103.9086 | J9: 3849.295 | K9: 4361.7377 | L9: 3517.1534 | M9: 4471.8915
A10: Externo Variable | B10: 16376.394 | C10: 3919.8297 | D10: 4429.4877 | E10: 0 | F10: 2898.5785 | G10: 654.96 | H10: 208.13136 | I10: 865.67588 | J10: 284.10677 | K10: 4776.9715 | L10: 5076.5286 | M10: 5675.3676
A11: Total | B11: =+B9+B10 -> 20752.101 | C11: =+C9+C10 -> 7819.8687 | D11: =+D9+D10 -> 11466.983 | E11: =+E9+E10 -> 2996.3265 | F11: =+F9+F10 -> 10444.297 | G11: =+G9+G10 -> 5632.1368 | H11: =+H9+H10 -> 15343.05 | I11: =+I9+I10 -> 4969.5845 | ... M11: =+M9+M10 -> 10147.259
A13: Total valores | B13: 20.752101 | C13: 7.8198687 | D13: 11.466983 | E13: 2.9963265 | F13: 10.444297 | G13: 5.6321368 | H13: 15.34305 | I13: 4.9695845 | J13: 4.1334018 | K13: 9.1387092 | L13: 8.593682 | M13: 10.147259
A15: Extras personas | B15: 129.39817 | C15: 40.431764 | D15: 19.643364 | E15: 12.341404 | F15: 18.451806 | G15: 6.0272542 | H15: 5.0827933 | I15: 4.9271873 | J15: 4.7191498 | K15: 29.951058 | L15: 28.926818 | M15: 13.829525
A16: Viajes | B16: 70.94038 | C16: 15.541723 | D16: 6.4251697 | E16: 19.654064 | F16: 11.217311 | G16: 6.643918 | H16: 10.766462 | I16: 12.765451 | J16: 12.095977 | K16: 8.7212621 | L16: 1.4406731 | M16: 16.0338
A17: Compañía | B17: 12.901351 | C17: 5.280059 | D17: 2.6626843 | E17: 2.6842877 | F17: 6.9208513 | G17: 0 | H17: 5.6590789 | I17: 5.7457512 | J17: 2.7826217 | K17: 5.5199495 | L17: 13.346371 | M17: 12.612711
A18: Comercial | B18: 1.146288 | C18: 0.86461015 | D18: 1.7211988 | E18: 0 | F18: 2.3744771 | G18: 0.89949032 | H18: 0.88847647 | I18: 0.89579525 | J18: 1.1306291 | K18: 0.89204442 | L18: 2.3638329 | M18: 1.1941192
A19: Bancarios | B19: 1.010502 | C19: 0.71911981 | D19: 0.47228157 | E19: 0.36444023 | F19: 0.81385956 | G19: 1.6420746 | H19: 2.1692001 | I19: 1.1940144 | J19: 1.1280279 | K19: 0.86412444 | L19: 1.5538837 | M19: 1.5701245
A20: Total | B20: =+SUM(B15:B19) -> 215.39669 | C20: =+SUM(C15:C19) -> 62.837275 | D20: =+SUM(D15:D19) -> 30.924698 | E20: =+SUM(E15:E19) -> 35.044196 | F20: =+SUM(F15:F19) -> 39.778305 | G20: =+SUM(G15:G19) -> 15.212737 | H20: =+SUM(H15:H19) -> 24.566011 | I20: =+SUM(I15:I19) -> 25.528199 | ... M20: =+SUM(M15:M19) -> 45.24028
A22: Otros | B22: 215.39669 | C22: 62.837275 | D22: 30.924698 | E22: 35.044196 | F22: 39.778305 | G22: 15.212737 | H22: 24.566011 | I22: 25.528199 | J22: 21.856405 | K22: 45.948439 | L22: 47.631579 | M22: 45.24028

Sheet Gasto Diciembre (2)
A1: Clasificación 1 | B1: (Varios elementos)
A2: Clasificación 3 | B2: (Varios elementos)
A3: Detalle | B3: (Todas)
A4: País | B4: (Todas)
A6: Suma de Valor USD | B6: Meses (Atributo)
A7: Clasificación 2 | B7: ene | C7: feb | D7: mar | E7: abr | F7: may | G7: jun | H7: jul | I7: ago | J7: sept | K7: oct | L7: nov | M7: dic | N7: Total | O7: Media
A8: Sueldos | B8: 302505.26 | C8: 278500.6 | D8: 288865 | E8: 271765.18 | F8: 312956.31 | G8: 233211.48 | H8: 335851.32 | I8: 306407.84 | J8: 272021.74 | K8: 294766.03 | L8: 275863.38 | M8: 316828.87 | N8: =+SUM(B8:M8) -> 3489543 | O8: =+AVERAGE(B8:M8) -> 290795.25
A9: Externo | B9: 123393.41 | C9: 95218.967 | D9: 63271.157 | E9: 9534.9993 | F9: 90110.012 | G9: 101187.94 | H9: 53135.335 | I9: 107301.65 | J9: 31039.189 | K9: 98333.95 | L9: 78622.169 | M9: 97664.797 | N9: =+SUM(B9:M9) -> 948813.57 | O9: =+AVERAGE(B9:M9) -> 79067.798
A10: Oficina | B10: 46734.79 | C10: 35698.197 | D10: 25091.045 | E10: 34665.023 | F10: 46509.808 | G10: 36712.331 | H10: 41599.82 | I10: 37109.385 | J10: 43959.913 | K10: 47609.466 | L10: 42586.413 | M10: 70662.434 | N10: =+SUM(B10:M10) -> 508938.63 | O10: =+AVERAGE(B10:M10) -> 42411.552
A11: Extras personas | B11: 129398.17 | C11: 40431.764 | D11: 19643.364 | E11: 12341.404 | F11: 18451.806 | G11: 6027.2542 | H11: 5082.7933 | I11: 4927.1873 | J11: 4719.1498 | K11: 29951.058 | L11: 28926.818 | M11: 13829.525 | N11: =+SUM(B11:M11) -> 313730.29 | O11: =+AVERAGE(B11:M11) -> 26144.191
A12: Viajes | B12: 70940.38 | C12: 15541.723 | D12: 6425.1697 | E12: 19654.064 | F12: 11217.311 | G12: 6643.918 | H12: 10766.462 | I12: 12765.451 | J12: 12095.977 | K12: 8721.2621 | L12: 1440.6731 | M12: 16033.8 | N12: =+SUM(B12:M12) -> 192246.19 | O12: =+AVERAGE(B12:M12) -> 16020.516
A13: Compañía | B13: 12901.351 | C13: 5280.059 | D13: 2662.6843 | E13: 2684.2877 | F13: 6920.8513 | G13: 0 | H13: 5659.0789 | I13: 5745.7512 | J13: 2782.6217 | K13: 5519.9495 | L13: 13346.371 | M13: 12612.711 | N13: =+SUM(B13:M13) -> 76115.717 | O13: =+AVERAGE(B13:M13) -> 6342.9764
A14: Comercial | B14: 1146.288 | C14: 864.61015 | D14: 1721.1988 | E14: 0 | F14: 2374.4771 | G14: 899.49032 | H14: 888.47647 | I14: 895.79525 | J14: 1130.6291 | K14: 892.04442 | L14: 2363.8329 | M14: 1194.1192 | N14: =+SUM(B14:M14) -> 14370.962 | O14: =+AVERAGE(B14:M14) -> 1197.5801
A15: Bancarios | B15: 1010.502 | C15: 719.11981 | D15: 472.28157 | E15: 364.44023 | F15: 813.85956 | G15: 1642.0746 | H15: 2169.2001 | I15: 1194.0144 | J15: 1128.0279 | K15: 864.12444 | L15: 1553.8837 | M15: 1570.1245 | N15: =+SUM(B15:M15) -> 13501.653 | O15: =+AVERAGE(B15:M15) -> 1125.1377
A16: Total general | B16: 688030.16 | C16: 472255.04 | D16: 408151.9 | E16: 351009.4 | F16: 489354.43 | G16: 386324.49 | H16: 455152.49 | I16: 476347.08 | J16: 368877.24 | K16: 486657.89 | L16: 444703.54 | M16: 530396.38 | N16: =+SUM(B16:M16) -> 5557260 | O16: =+AVERAGE(B16:M16) -> 463105
A21: Clasificación 1 | B21: (Varios elementos)
A22: Clasificación 2 | B22: (Varios elementos)
A23: Clasificación 3 | B23: (Varios elementos)
A24: Detalle | B24: (Todas)
A26: Suma de Valor USD | B26: Meses (Atributo)
A27: País | B27: ene | C27: feb | D27: mar | E27: abr | F27: may | G27: jun | H27: jul | I27: ago | J27: sept | K27: oct | L27: nov | M27: dic | N27: Total | O27: Media
A28: Chile | B28: 476290.51 | C28: 313314.92 | D28: 275868.55 | E28: 231521.27 | F28: 317170.05 | G28: 288144.94 | H28: 292127.49 | I28: 299217.79 | J28: 267600.24 | K28: 356054.44 | L28: 318274.54 | M28: 334876.96 | N28: =+SUM(B28:M28) -> 3770461.7 | O28: =+AVERAGE(B28:M28) -> 314205.14
A29: Perú | B29: 167140.16 | C29: 109669.78 | D29: 119903.77 | E29: 98132.41 | F29: 125258.63 | G29: 82824.806 | H29: 139674 | I29: 152094.22 | J29: 73594 | K29: 88148.45 | L29: 112788 | M29: 159182.62 | N29: =+SUM(B29:M29) -> 1428410.9 | O29: =+AVERAGE(B29:M29) -> 119034.24
A30: Brasil | B30: 44599.49 | C30: 49270.34 | D30: 12379.58 | E30: 21355.715 | F30: 46925.75 | G30: 15354.74 | H30: 23351 | I30: 25035.07 | J30: 27683 | K30: 42455 | L30: 13641 | M30: 36336.8 | N30: =+SUM(B30:M30) -> 358387.48 | O30: =+AVERAGE(B30:M30) -> 29865.624
A31: Total general | B31: 688030.16 | C31: 472255.04 | D31: 408151.9 | E31: 351009.4 | F31: 489354.43 | G31: 386324.49 | H31: 455152.49 | I31: 476347.08 | J31: 368877.24 | K31: 486657.89 | L31: 444703.54 | M31: 530396.38 | N31: =+SUM(B31:M31) -> 5557260 | O31: =+AVERAGE(B31:M31) -> 463105

Sheet Gasto Noviembre
A1: Clasificación 1 | B1: (Varios elementos)
A2: Clasificación 3 | B2: (Varios elementos)
A3: Detalle | B3: (Todas)
A4: País | B4: (Todas)
A6: Suma de Valor USD | B6: Meses (Atributo)
A7: Clasificación 2 | B7: ene | C7: feb | D7: mar | E7: abr | F7: may | G7: jun | H7: jul | I7: ago | J7: sept | K7: oct | L7: nov | M7: dic | N7: Total | O7: Media
A8: Sueldos | B8: 302505.26 | C8: 278500.6 | D8: 288865 | E8: 271765.18 | F8: 312956.31 | G8: 233211.48 | H8: 335851.32 | I8: 306407.84 | J8: 272021.74 | K8: 269052.92 | L8: 275863.38 | M8: 312827.46 | N8: =+SUM(B8:M8) -> 3459828.5 | O8: =+AVERAGE(B8:M8) -> 288319.04
A9: Externo | B9: 123393.41 | C9: 95218.967 | D9: 63271.157 | E9: 9534.9993 | F9: 90110.012 | G9: 101187.94 | H9: 53135.335 | I9: 107301.65 | J9: 31039.189 | K9: 98333.95 | L9: 78622.169 | M9: 5188.6714 | N9: =+SUM(B9:M9) -> 856337.45 | O9: =+AVERAGE(B9:M9) -> 71361.454
A10: Oficina | B10: 46734.79 | C10: 35698.197 | D10: 25091.045 | E10: 34665.023 | F10: 46509.808 | G10: 36712.331 | H10: 41599.82 | I10: 37109.385 | J10: 43959.913 | K10: 47609.466 | L10: 42586.413 | M10: 36316.393 | N10: =+SUM(B10:M10) -> 474592.58 | O10: =+AVERAGE(B10:M10) -> 39549.382
A11: Extras personas | B11: 129398.17 | C11: 40431.764 | D11: 19643.364 | E11: 12341.404 | F11: 18451.806 | G11: 6027.2542 | H11: 5082.7933 | I11: 4927.1873 | J11: 4719.1498 | K11: 29510.339 | L11: 29568.391 | M11: 3949.8842 | N11: =+SUM(B11:M11) -> 304051.51 | O11: =+AVERAGE(B11:M11) -> 25337.626
A12: Viajes | B12: 70940.38 | C12: 15541.723 | D12: 6425.1697 | E12: 19654.064 | F12: 11217.311 | G12: 6643.918 | H12: 10766.462 | I12: 12765.451 | J12: 12095.977 | K12: 8598.2621 | L12: 1440.6731 | M12: 8082 | N12: =+SUM(B12:M12) -> 184171.39 | O12: =+AVERAGE(B12:M12) -> 15347.616
A13: Compañía | B13: 12901.351 | C13: 5280.059 | D13: 2662.6843 | E13: 2684.2877 | F13: 6920.8513 | G13: 0 | H13: 5659.0789 | I13: 5745.7512 | J13: 2782.6217 | K13: 2759.9747 | L13: 13346.371 | M13: 3260.6503 | N13: =+SUM(B13:M13) -> 64003.681 | O13: =+AVERAGE(B13:M13) -> 5333.6401
A14: Comercial | B14: 1146.288 | C14: 864.61015 | D14: 1721.1988 | E14: 0 | F14: 2374.4771 | G14: 899.49032 | H14: 888.47647 | I14: 895.79525 | J14: 1130.6291 | K14: 892.04442 | L14: 2363.8329 | M14: 882.53679 | N14: =+SUM(B14:M14) -> 14059.379 | O14: =+AVERAGE(B14:M14) -> 1171.6149
A15: Bancarios | B15: 1010.502 | C15: 719.11981 | D15: 472.28157 | E15: 364.44023 | F15: 813.85956 | G15: 1642.0746 | H15: 2169.2001 | I15: 1194.0144 | J15: 1128.0279 | K15: 864.12444 | L15: 1479.8837 | M15: 779.89359 | N15: =+SUM(B15:M15) -> 12637.422 | O15: =+AVERAGE(B15:M15) -> 1053.1185
A16: Total general | B16: 688030.16 | C16: 472255.04 | D16: 408151.9 | E16: 351009.4 | F16: 489354.43 | G16: 386324.49 | H16: 455152.49 | I16: 476347.08 | J16: 368877.24 | K16: 457621.08 | L16: 445271.11 | M16: 371287.49 | N16: =+SUM(B16:M16) -> 5369681.9 | O16: =+AVERAGE(B16:M16) -> 447473.49
A21: Clasificación 1 | B21: (Varios elementos)
A22: Clasificación 2 | B22: (Varios elementos)
A23: Clasificación 3 | B23: (Varios elementos)
A24: Detalle | B24: (Todas)
A26: Suma de Valor USD | B26: Meses (Atributo)
A27: País | B27: ene | C27: feb | D27: mar | E27: abr | F27: may | G27: jun | H27: jul | I27: ago | J27: sept | K27: oct | L27: nov | M27: dic | N27: Total | O27: Media
A28: Chile | B28: 476290.51 | C28: 313314.92 | D28: 275868.55 | E28: 231521.27 | F28: 317170.05 | G28: 288144.94 | H28: 292127.49 | I28: 299217.79 | J28: 267600.24 | K28: 327140.63 | L28: 318916.11 | M28: 239929.63 | N28: =+SUM(B28:M28) -> 3647242.1 | O28: =+AVERAGE(B28:M28) -> 303936.84
A29: Perú | B29: 167140.16 | C29: 109669.78 | D29: 119903.77 | E29: 98132.41 | F29: 125258.63 | G29: 82824.806 | H29: 139674 | I29: 152094.22 | J29: 73594 | K29: 88148.45 | L29: 112714 | M29: 113440.86 | N29: =+SUM(B29:M29) -> 1382595.1 | O29: =+AVERAGE(B29:M29) -> 115216.26
A30: Brasil | B30: 44599.49 | C30: 49270.34 | D30: 12379.58 | E30: 21355.715 | F30: 46925.75 | G30: 15354.74 | H30: 23351 | I30: 25035.07 | J30: 27683 | K30: 42332 | L30: 13641 | M30: 17917 | N30: =+SUM(B30:M30) -> 339844.68 | O30: =+AVERAGE(B30:M30) -> 28320.39
A31: Total general | B31: 688030.16 | C31: 472255.04 | D31: 408151.9 | E31: 351009.4 | F31: 489354.43 | G31: 386324.49 | H31: 455152.49 | I31: 476347.08 | J31: 368877.24 | K31: 457621.08 | L31: 445271.11 | M31: 371287.49 | N31: =+SUM(B31:M31) -> 5369681.9 | O31: =+AVERAGE(B31:M31) -> 447473.49

Sheet Gasto Octubre
A1: Clasificación 1 | B1: (Varios elementos)
A2: Clasificación 3 | B2: (Varios elementos)
A3: Detalle | B3: (Todas)
A4: País | B4: (Todas)
A6: Suma de Valor USD | B6: Meses (Atributo)
A7: Clasificación 2 | B7: ene | C7: feb | D7: mar | E7: abr | F7: may | G7: jun | H7: jul | I7: ago | J7: sept | K7: oct | L7: nov | M7: dic | N7: Total | O7: Media
A8: Sueldos | B8: 302505.26 | C8: 278500.6 | D8: 288865 | E8: 271765.18 | F8: 312956.31 | G8: 233211.48 | H8: 335851.32 | I8: 306407.84 | J8: 272021.74 | K8: 269052.92 | L8: 258876.35 | M8: 300252.04 | N8: =+SUM(B8:M8) -> 3430266.1 | O8: =+AVERAGE(B8:M8) -> 285855.51
A9: Externo | B9: 123393.41 | C9: 95218.967 | D9: 63271.157 | E9: 9534.9993 | F9: 90110.012 | G9: 101187.94 | H9: 53135.335 | I9: 107301.65 | J9: 31039.189 | K9: 98333.95 | L9: 4140.952 | M9: 4140.952 | N9: =+SUM(B9:M9) -> 780808.51 | O9: =+AVERAGE(B9:M9) -> 65067.376
A10: Oficina | B10: 46734.79 | C10: 35698.197 | D10: 25091.045 | E10: 34665.023 | F10: 76691.808 | G10: 36712.331 | H10: 41599.82 | I10: 37109.385 | J10: 43959.913 | K10: 47609.466 | L10: 40818.03 | M10: 37699.649 | N10: =+SUM(B10:M10) -> 504389.46 | O10: =+AVERAGE(B10:M10) -> 42032.455
A11: Extras personas | B11: 129398.17 | C11: 40431.764 | D11: 19643.364 | E11: 12341.404 | F11: 18451.806 | G11: 6027.2542 | H11: 5082.7933 | I11: 4927.1873 | J11: 4719.1498 | K11: 29510.339 | L11: 4002.1661 | M11: 4002.1661 | N11: =+SUM(B11:M11) -> 278537.56 | O11: =+AVERAGE(B11:M11) -> 23211.464
A12: Viajes | B12: 70940.38 | C12: 15541.723 | D12: 6425.1697 | E12: 19654.064 | F12: 11217.311 | G12: 6643.918 | H12: 10766.462 | I12: 12765.451 | J12: 12095.977 | K12: 8598.2621 | L12: 8082 | M12: 8082 | N12: =+SUM(B12:M12) -> 190812.72 | O12: =+AVERAGE(B12:M12) -> 15901.06
A13: Compañía | B13: 12901.351 | C13: 5280.059 | D13: 2662.6843 | E13: 2684.2877 | F13: 6920.8513 | G13: 0 | H13: 5659.0789 | I13: 5745.7512 | J13: 2782.6217 | K13: 2759.9747 | L13: 3309.3863 | M13: 3309.3863 | N13: =+SUM(B13:M13) -> 54015.433 | O13: =+AVERAGE(B13:M13) -> 4501.2861
A14: Comercial | B14: 1146.288 | C14: 864.61015 | D14: 1721.1988 | E14: 0 | F14: 2374.4771 | G14: 899.49032 | H14: 888.47647 | I14: 895.79525 | J14: 1130.6291 | K14: 892.04442 | L14: 895.72782 | M14: 895.72782 | N14: =+SUM(B14:M14) -> 12604.465 | O14: =+AVERAGE(B14:M14) -> 1050.3721
A15: Bancarios | B15: 1010.502 | C15: 719.11981 | D15: 472.28157 | E15: 364.44023 | F15: 813.85956 | G15: 1642.0746 | H15: 2169.2001 | I15: 1194.0144 | J15: 1128.0279 | K15: 864.12444 | L15: 799.0607 | M15: 799.0607 | N15: =+SUM(B15:M15) -> 11975.766 | O15: =+AVERAGE(B15:M15) -> 997.9805
A16: Total general | B16: 688030.16 | C16: 472255.04 | D16: 408151.9 | E16: 351009.4 | F16: 519536.43 | G16: 386324.49 | H16: 455152.49 | I16: 476347.08 | J16: 368877.24 | K16: 457621.08 | L16: 320923.68 | M16: 359180.98 | N16: =+SUM(B16:M16) -> 5263410 | O16: =+AVERAGE(B16:M16) -> 438617.5
A21: Clasificación 1 | B21: (Varios elementos)
A22: Clasificación 2 | B22: (Varios elementos)
A23: Clasificación 3 | B23: (Varios elementos)
A24: Detalle | B24: (Todas)
A26: Suma de Valor USD | B26: Meses (Atributo)
A27: País | B27: ene | C27: feb | D27: mar | E27: abr | F27: may | G27: jun | H27: jul | I27: ago | J27: sept | K27: oct | L27: nov | M27: dic | N27: Total | O27: Media
A28: Chile | B28: 476290.51 | C28: 313314.92 | D28: 275868.55 | E28: 231521.27 | F28: 317170.05 | G28: 288144.94 | H28: 292127.49 | I28: 299217.79 | J28: 267600.24 | K28: 327140.63 | L28: 216906.81 | M28: 232176.12 | N28: =+SUM(B28:M28) -> 3537479.3 | O28: =+AVERAGE(B28:M28) -> 294789.94
A29: Perú | B29: 167140.16 | C29: 109669.78 | D29: 119903.77 | E29: 98132.41 | F29: 155440.63 | G29: 82824.806 | H29: 139674 | I29: 152094.22 | J29: 73594 | K29: 88148.45 | L29: 87997.868 | M29: 110985.86 | N29: =+SUM(B29:M29) -> 1385606 | O29: =+AVERAGE(B29:M29) -> 115467.16
A30: Brasil | B30: 44599.49 | C30: 49270.34 | D30: 12379.58 | E30: 21355.715 | F30: 46925.75 | G30: 15354.74 | H30: 23351 | I30: 25035.07 | J30: 27683 | K30: 42332 | L30: 16019 | M30: 16019 | N30: =+SUM(B30:M30) -> 340324.68 | O30: =+AVERAGE(B30:M30) -> 28360.39
A31: Total general | B31: 688030.16 | C31: 472255.04 | D31: 408151.9 | E31: 351009.4 | F31: 519536.43 | G31: 386324.49 | H31: 455152.49 | I31: 476347.08 | J31: 368877.24 | K31: 457621.08 | L31: 320923.68 | M31: 359180.98 | N31: =+SUM(B31:M31) -> 5263410 | O31: =+AVERAGE(B31:M31) -> 438617.5

Sheet Gasto Octubre (2)
A1: Clasificación 0 | B1: (Todas)
A2: Clasificación 1 | B2: (Varios elementos)
A3: País | B3: (Todas)
A5: Suma de Valor USD | D5: Meses (Atributo)
A6: Clasificación 2 | B6: Clasificación 3 | C6: Detalle | D6: ene | E6: feb | F6: mar | G6: abr | H6: may | I6: jun | J6: jul | K6: ago | L6: sept | M6: oct | N6: nov | O6: dic | P6: Total | Q6: Media
A7: Sueldos | D7: 302505.26 | E7: 278500.6 | F7: 288865 | G7: 271765.18 | H7: 312956.31 | I7: 233211.48 | J7: 335851.32 | K7: 306407.84 | L7: 272021.74 | M7: 269052.92 | N7: 258876.35 | O7: 300252.04 | P7: =+SUM(D7:O7) -> 3430266.1 | Q7: =+AVERAGE(D7:O7) -> 285855.51
A8: Externo | D8: 123393.41 | E8: 95218.967 | F8: 63271.157 | G8: 9534.9993 | H8: 90110.012 | I8: 101187.94 | J8: 53135.335 | K8: 107301.65 | L8: 31039.189 | M8: 98333.95 | N8: 4140.952 | O8: 4140.952 | P8: =+SUM(D8:O8) -> 780808.51 | Q8: =+AVERAGE(D8:O8) -> 65067.376
A9: Oficina | D9: 46734.79 | E9: 35698.197 | F9: 25091.045 | G9: 34665.023 | H9: 76691.808 | I9: 36712.331 | J9: 41599.82 | K9: 37109.385 | L9: 43959.913 | M9: 47609.466 | N9: 40818.03 | O9: 37699.649 | P9: =+SUM(D9:O9) -> 504389.46 | Q9: =+AVERAGE(D9:O9) -> 42032.455
A10: Extras personas | D10: 129398.17 | E10: 40431.764 | F10: 19643.364 | G10: 12341.404 | H10: 18451.806 | I10: 6027.2542 | J10: 5082.7933 | K10: 4927.1873 | L10: 4719.1498 | M10: 29510.339 | N10: 4002.1661 | O10: 4002.1661 | P10: =+SUM(D10:O10) -> 278537.56 | Q10: =+AVERAGE(D10:O10) -> 23211.464
A11: Viajes | D11: 70940.38 | E11: 15541.723 | F11: 6425.1697 | G11: 19654.064 | H11: 11217.311 | I11: 6643.918 | J11: 10766.462 | K11: 12765.451 | L11: 12095.977 | M11: 8598.2621 | N11: 8082 | O11: 8082 | P11: =+SUM(D11:O11) -> 190812.72 | Q11: =+AVERAGE(D11:O11) -> 15901.06
A12: Compañía | D12: 12901.351 | E12: 5280.059 | F12: 2662.6843 | G12: 2684.2877 | H12: 6920.8513 | I12: 0 | J12: 5659.0789 | K12: 5745.7512 | L12: 2782.6217 | M12: 2759.9747 | N12: 3309.3863 | O12: 3309.3863 | P12: =+SUM(D12:O12) -> 54015.433 | Q12: =+AVERAGE(D12:O12) -> 4501.2861
A13: Comercial | D13: 1146.288 | E13: 864.61015 | F13: 1721.1988 | G13: 0 | H13: 2374.4771 | I13: 899.49032 | J13: 888.47647 | K13: 895.79525 | L13: 1130.6291 | M13: 892.04442 | N13: 895.72782 | O13: 895.72782 | P13: =+SUM(D13:O13) -> 12604.465 | Q13: =+AVERAGE(D13:O13) -> 1050.3721
A14: Bancarios | D14: 1010.502 | E14: 719.11981 | F14: 472.28157 | G14: 364.44023 | H14: 813.85956 | I14: 1642.0746 | J14: 2169.2001 | K14: 1194.0144 | L14: 1128.0279 | M14: 864.12444 | N14: 799.0607 | O14: 799.0607 | P14: =+SUM(D14:O14) -> 11975.766 | Q14: =+AVERAGE(D14:O14) -> 997.9805
A15: Total general | D15: 688030.16 | E15: 472255.04 | F15: 408151.9 | G15: 351009.4 | H15: 519536.43 | I15: 386324.49 | J15: 455152.49 | K15: 476347.08 | L15: 368877.24 | M15: 457621.08 | N15: 320923.68 | O15: 359180.98 | P15: =+SUM(D15:O15) -> 5263410 | Q15: =+AVERAGE(D15:O15) -> 438617.5
D17: =+SUM($D$15:D15) -> 688030.16 | E17: =+SUM($D$15:E15) -> 1160285.2 | F17: =+SUM($D$15:F15) -> 1568437.1 | G17: =+SUM($D$15:G15) -> 1919446.5 | H17: =+SUM($D$15:H15) -> 2438982.9 | I17: =+SUM($D$15:I15) -> 2825307.4 | J17: =+SUM($D$15:J15) -> 3280459.9 | K17: =+SUM($D$15:K15) -> 3756807 | ... O17: =+SUM($D$15:O15) -> 5263410

Sheet Gasto total_Análisis
C3: Gasto Proyectado REDCO sin EEUU
O4: =+O8-N8 -> 28.076021
C5: Item | D5: ene | E5: feb | F5: mar | G5: abr | H5: may | I5: jun | J5: jul | K5: ago | L5: sept | M5: oct | N5: nov | O5: dic | P5: Total | Q5: Promedio
C6: ='Gasto Septiembre'!A9 -> Sueldos | D6: =('Gasto Diciembre (2)'!B8)/1000 -> 302.50526 | E6: =('Gasto Diciembre (2)'!C8)/1000 -> 278.5006 | F6: =('Gasto Diciembre (2)'!D8)/1000 -> 288.865 | G6: =('Gasto Diciembre (2)'!E8)/1000 -> 271.76518 | H6: =('Gasto Diciembre (2)'!F8)/1000 -> 312.95631 | I6: =('Gasto Diciembre (2)'!G8)/1000 -> 233.21148 | J6: =('Gasto Diciembre (2)'!H8)/1000 -> 335.85132 | K6: =('Gasto Diciembre (2)'!I8)/1000 -> 306.40784 | ... O6: =('Gasto Diciembre (2)'!M8)/1000 -> 316.82887 | P6: =+SUM(D6:O6) -> 3489.543 | Q6: =+AVERAGE(D6:O6) -> 290.79525
C7: ='Gasto Septiembre'!A10 -> Externo | D7: =('Gasto Diciembre (2)'!B9)/1000 -> 123.39341 | E7: =('Gasto Diciembre (2)'!C9)/1000 -> 95.218967 | F7: =('Gasto Diciembre (2)'!D9)/1000 -> 63.271157 | G7: =('Gasto Diciembre (2)'!E9)/1000 -> 9.5349993 | H7: =('Gasto Diciembre (2)'!F9)/1000 -> 90.110012 | I7: =('Gasto Diciembre (2)'!G9)/1000 -> 101.18794 | J7: =('Gasto Diciembre (2)'!H9)/1000 -> 53.135335 | K7: =('Gasto Diciembre (2)'!I9)/1000 -> 107.30165 | ... O7: =('Gasto Diciembre (2)'!M9)/1000 -> 97.664797 | P7: =+SUM(D7:O7) -> 948.81357 | Q7: =+AVERAGE(D7:O7) -> 79.067798
C8: ='Gasto Septiembre'!A11 -> Oficina | D8: =('Gasto Diciembre (2)'!B10)/1000 -> 46.73479 | E8: =('Gasto Diciembre (2)'!C10)/1000 -> 35.698197 | F8: =('Gasto Diciembre (2)'!D10)/1000 -> 25.091045 | G8: =('Gasto Diciembre (2)'!E10)/1000 -> 34.665023 | H8: =('Gasto Diciembre (2)'!F10)/1000 -> 46.509808 | I8: =('Gasto Diciembre (2)'!G10)/1000 -> 36.712331 | J8: =('Gasto Diciembre (2)'!H10)/1000 -> 41.59982 | K8: =('Gasto Diciembre (2)'!I10)/1000 -> 37.109385 | ... O8: =('Gasto Diciembre (2)'!M10)/1000 -> 70.662434 | P8: =+SUM(D8:O8) -> 508.93863 | Q8: =+AVERAGE(D8:O8) -> 42.411552
C9: ='Gasto Septiembre'!A12 -> Extras personas | D9: =('Gasto Diciembre (2)'!B11)/1000 -> 129.39817 | E9: =('Gasto Diciembre (2)'!C11)/1000 -> 40.431764 | F9: =('Gasto Diciembre (2)'!D11)/1000 -> 19.643364 | G9: =('Gasto Diciembre (2)'!E11)/1000 -> 12.341404 | H9: =('Gasto Diciembre (2)'!F11)/1000 -> 18.451806 | I9: =('Gasto Diciembre (2)'!G11)/1000 -> 6.0272542 | J9: =('Gasto Diciembre (2)'!H11)/1000 -> 5.0827933 | K9: =('Gasto Diciembre (2)'!I11)/1000 -> 4.9271873 | ... O9: =('Gasto Diciembre (2)'!M11)/1000 -> 13.829525 | P9: =+SUM(D9:O9) -> 313.73029 | Q9: =+AVERAGE(D9:O9) -> 26.144191
C10: ='Gasto Septiembre'!A13 -> Viajes | D10: =('Gasto Diciembre (2)'!B12)/1000 -> 70.94038 | E10: =('Gasto Diciembre (2)'!C12)/1000 -> 15.541723 | F10: =('Gasto Diciembre (2)'!D12)/1000 -> 6.4251697 | G10: =('Gasto Diciembre (2)'!E12)/1000 -> 19.654064 | H10: =('Gasto Diciembre (2)'!F12)/1000 -> 11.217311 | I10: =('Gasto Diciembre (2)'!G12)/1000 -> 6.643918 | J10: =('Gasto Diciembre (2)'!H12)/1000 -> 10.766462 | K10: =('Gasto Diciembre (2)'!I12)/1000 -> 12.765451 | ... O10: =('Gasto Diciembre (2)'!M12)/1000 -> 16.0338 | P10: =+SUM(D10:O10) -> 192.24619 | Q10: =+AVERAGE(D10:O10) -> 16.020516
C11: ='Gasto Septiembre'!A14 -> Compañía | D11: =('Gasto Diciembre (2)'!B13)/1000 -> 12.901351 | E11: =('Gasto Diciembre (2)'!C13)/1000 -> 5.280059 | F11: =('Gasto Diciembre (2)'!D13)/1000 -> 2.6626843 | G11: =('Gasto Diciembre (2)'!E13)/1000 -> 2.6842877 | H11: =('Gasto Diciembre (2)'!F13)/1000 -> 6.9208513 | I11: =('Gasto Diciembre (2)'!G13)/1000 -> 0 | J11: =('Gasto Diciembre (2)'!H13)/1000 -> 5.6590789 | K11: =('Gasto Diciembre (2)'!I13)/1000 -> 5.7457512 | ... O11: =('Gasto Diciembre (2)'!M13)/1000 -> 12.612711 | P11: =+SUM(D11:O11) -> 76.115717 | Q11: =+AVERAGE(D11:O11) -> 6.3429764
C12: ='Gasto Septiembre'!A15 -> Comercial | D12: =('Gasto Diciembre (2)'!B14)/1000 -> 1.146288 | E12: =('Gasto Diciembre (2)'!C14)/1000 -> 0.86461015 | F12: =('Gasto Diciembre (2)'!D14)/1000 -> 1.7211988 | G12: =('Gasto Diciembre (2)'!E14)/1000 -> 0 | H12: =('Gasto Diciembre (2)'!F14)/1000 -> 2.3744771 | I12: =('Gasto Diciembre (2)'!G14)/1000 -> 0.89949032 | J12: =('Gasto Diciembre (2)'!H14)/1000 -> 0.88847647 | K12: =('Gasto Diciembre (2)'!I14)/1000 -> 0.89579525 | ... O12: =('Gasto Diciembre (2)'!M14)/1000 -> 1.1941192 | P12: =+SUM(D12:O12) -> 14.370962 | Q12: =+AVERAGE(D12:O12) -> 1.1975801
C13: ='Gasto Septiembre'!A16 -> Bancarios | D13: =('Gasto Diciembre (2)'!B15)/1000 -> 1.010502 | E13: =('Gasto Diciembre (2)'!C15)/1000 -> 0.71911981 | F13: =('Gasto Diciembre (2)'!D15)/1000 -> 0.47228157 | G13: =('Gasto Diciembre (2)'!E15)/1000 -> 0.36444023 | H13: =('Gasto Diciembre (2)'!F15)/1000 -> 0.81385956 | I13: =('Gasto Diciembre (2)'!G15)/1000 -> 1.6420746 | J13: =('Gasto Diciembre (2)'!H15)/1000 -> 2.1692001 | K13: =('Gasto Diciembre (2)'!I15)/1000 -> 1.1940144 | ... O13: =('Gasto Diciembre (2)'!M15)/1000 -> 1.5701245 | P13: =+SUM(D13:O13) -> 13.501653 | Q13: =+AVERAGE(D13:O13) -> 1.1251377
C14: Total | D14: =+SUM(D6:D13) -> 688.03016 | E14: =+SUM(E6:E13) -> 472.25504 | F14: =+SUM(F6:F13) -> 408.1519 | G14: =+SUM(G6:G13) -> 351.0094 | H14: =+SUM(H6:H13) -> 489.35443 | I14: =+SUM(I6:I13) -> 386.32449 | J14: =+SUM(J6:J13) -> 455.15249 | K14: =+SUM(K6:K13) -> 476.34708 | ... Q14: =+SUM(Q6:Q13) -> 463.105
C15: Acumulado | D15: =+SUM($D$14:D14) -> 688.03016 | E15: =+SUM($D$14:E14) -> 1160.2852 | F15: =+SUM($D$14:F14) -> 1568.4371 | G15: =+SUM($D$14:G14) -> 1919.4465 | H15: =+SUM($D$14:H14) -> 2408.8009 | I15: =+SUM($D$14:I14) -> 2795.1254 | J15: =+SUM($D$14:J14) -> 3250.2779 | K15: =+SUM($D$14:K14) -> 3726.625 | ... O15: =+SUM($D$14:O14) -> 5557.26
D16: =+D15/$O$15 -> 0.12380744 | E16: =+E15/$O$15 -> 0.20878728 | F16: =+F15/$O$15 -> 0.28223209 | G16: =+G15/$O$15 -> 0.3453944 | H16: =+H15/$O$15 -> 0.43345118 | I16: =+I15/$O$15 -> 0.50296826 | J16: =+J15/$O$15 -> 0.58487058 | K16: =+K15/$O$15 -> 0.67058676 | ... O16: =+O15/$O$15 -> 1
C18: Sueldo/total | D18: =+D6/D14 -> 0.43966861 | E18: =+E6/E14 -> 0.58972499 | F18: =+F6/F14 -> 0.70773896 | G18: =+G6/G14 -> 0.77423904 | H18: =+H6/H14 -> 0.63952892 | I18: =+I6/I14 -> 0.60366736 | J18: =+J6/J14 -> 0.73788748 | K18: =+K6/K14 -> 0.64324494 | ... M18: =+M6/M14 -> 0.60569456
C19: Externo/total | D19: =+D7/D14 -> 0.17934303 | E19: =+E7/E14 -> 0.20162615 | F19: =+F7/F14 -> 0.15501865 | G19: =+G7/G14 -> 0.027164513 | H19: =+H7/H14 -> 0.18414058 | I19: =+I7/I14 -> 0.26192473 | J19: =+J7/J14 -> 0.11674183 | K19: =+K7/K14 -> 0.22525938 | ... M19: =+M7/M14 -> 0.20205971
C20: Oficina/total | D20: =+D8/D14 -> 0.067925497 | E20: =+E8/E14 -> 0.075590928 | F20: =+F8/F14 -> 0.061474772 | G20: =+G8/G14 -> 0.098758104 | H20: =+H8/H14 -> 0.095043192 | I20: =+I8/I14 -> 0.095029779 | J20: =+J8/J14 -> 0.091397546 | K20: =+K8/K14 -> 0.07790409 | ... M20: =+M8/M14 -> 0.097829435
C23: Item | D23: ene | E23: feb | F23: mar | G23: abr | H23: may | I23: jun | J23: jul | K23: ago | L23: sept | M23: oct | N23: nov | O23: dic | P23: Total | Q23: Promedio
C24: ='Gasto Septiembre'!A30 -> Chile | D24: =('Gasto Diciembre (2)'!B28)/1000 -> 476.29051 | E24: =('Gasto Diciembre (2)'!C28)/1000 -> 313.31492 | F24: =('Gasto Diciembre (2)'!D28)/1000 -> 275.86855 | G24: =('Gasto Diciembre (2)'!E28)/1000 -> 231.52127 | H24: =('Gasto Diciembre (2)'!F28)/1000 -> 317.17005 | I24: =('Gasto Diciembre (2)'!G28)/1000 -> 288.14494 | J24: =('Gasto Diciembre (2)'!H28)/1000 -> 292.12749 | K24: =('Gasto Diciembre (2)'!I28)/1000 -> 299.21779 | ... O24: =('Gasto Diciembre (2)'!M28)/1000 -> 334.87696 | P24: =+SUM(D24:O24) -> 3770.4617 | Q24: =+AVERAGE(D24:O24) -> 314.20514
C25: ='Gasto Septiembre'!A31 -> Perú | D25: =('Gasto Diciembre (2)'!B29)/1000 -> 167.14016 | E25: =('Gasto Diciembre (2)'!C29)/1000 -> 109.66978 | F25: =('Gasto Diciembre (2)'!D29)/1000 -> 119.90377 | G25: =('Gasto Diciembre (2)'!E29)/1000 -> 98.13241 | H25: =('Gasto Diciembre (2)'!F29)/1000 -> 125.25863 | I25: =('Gasto Diciembre (2)'!G29)/1000 -> 82.824806 | J25: =('Gasto Diciembre (2)'!H29)/1000 -> 139.674 | K25: =('Gasto Diciembre (2)'!I29)/1000 -> 152.09422 | ... O25: =('Gasto Diciembre (2)'!M29)/1000 -> 159.18262 | P25: =+SUM(D25:O25) -> 1428.4109 | Q25: =+AVERAGE(D25:O25) -> 119.03424
C26: ='Gasto Septiembre'!A32 -> Brasil | D26: =('Gasto Diciembre (2)'!B30)/1000 -> 44.59949 | E26: =('Gasto Diciembre (2)'!C30)/1000 -> 49.27034 | F26: =('Gasto Diciembre (2)'!D30)/1000 -> 12.37958 | G26: =('Gasto Diciembre (2)'!E30)/1000 -> 21.355715 | H26: =('Gasto Diciembre (2)'!F30)/1000 -> 46.92575 | I26: =('Gasto Diciembre (2)'!G30)/1000 -> 15.35474 | J26: =('Gasto Diciembre (2)'!H30)/1000 -> 23.351 | K26: =('Gasto Diciembre (2)'!I30)/1000 -> 25.03507 | ... O26: =('Gasto Diciembre (2)'!M30)/1000 -> 36.3368 | P26: =+SUM(D26:O26) -> 358.38748 | Q26: =+AVERAGE(D26:O26) -> 29.865624
C27: Total | D27: =+SUM(D24:D26) -> 688.03016 | E27: =+SUM(E24:E26) -> 472.25504 | F27: =+SUM(F24:F26) -> 408.1519 | G27: =+SUM(G24:G26) -> 351.0094 | H27: =+SUM(H24:H26) -> 489.35443 | I27: =+SUM(I24:I26) -> 386.32449 | J27: =+SUM(J24:J26) -> 455.15249 | K27: =+SUM(K24:K26) -> 476.34708 | ... Q27: =+SUM(Q24:Q26) -> 463.105
C28: Acumulado | D28: =+SUM($D$27:D27) -> 688.03016 | E28: =+SUM($D$27:E27) -> 1160.2852 | F28: =+SUM($D$27:F27) -> 1568.4371 | G28: =+SUM($D$27:G27) -> 1919.4465 | H28: =+SUM($D$27:H27) -> 2408.8009 | I28: =+SUM($D$27:I27) -> 2795.1254 | J28: =+SUM($D$27:J27) -> 3250.2779 | K28: =+SUM($D$27:K27) -> 3726.625 | ... O28: =+SUM($D$27:O27) -> 5557.26
D29: =+D28/$O$28 -> 0.12380744 | E29: =+E28/$O$28 -> 0.20878728 | F29: =+F28/$O$28 -> 0.28223209 | G29: =+G28/$O$28 -> 0.3453944 | H29: =+H28/$O$28 -> 0.43345118 | I29: =+I28/$O$28 -> 0.50296826 | J29: =+J28/$O$28 -> 0.58487058 | K29: =+K28/$O$28 -> 0.67058676 | ... O29: =+O28/$O$28 -> 1
E31: =+(E27-D27)/D27 -> -0.31361288 | F31: =+(F27-E27)/E27 -> -0.13573839 | G31: =+(G27-F27)/F27 -> -0.14000304 | H31: =+(H27-G27)/G27 -> 0.39413486 | I31: =+(I27-H27)/H27 -> -0.21054258 | J31: =+(J27-I27)/I27 -> 0.17816111 | K31: =+(K27-J27)/J27 -> 0.0465659 | L31: =+(L27-K27)/K27 -> -0.22561245 | ... O31: =+(O27-N27)/N27 -> 0.19269656
C37: Gasto Proyectado REDCO con EEUU
C39: Item | D39: ene | E39: feb | F39: mar | G39: abr | H39: may | I39: jun | J39: jul | K39: ago | L39: sept | M39: oct | N39: nov | O39: dic | P39: Total | Q39: Promedio
C40: Chile | D40: =+D24 -> 476.29051 | E40: =+E24 -> 313.31492 | F40: =+F24 -> 275.86855 | G40: =+G24 -> 231.52127 | H40: =+H24 -> 317.17005 | I40: =+I24 -> 288.14494 | J40: =+J24 -> 292.12749 | K40: =+K24 -> 299.21779 | ... O40: =+O24 -> 334.87696 | P40: =+SUM(D40:O40) -> 3770.4617 | Q40: =+AVERAGE(D40:O40) -> 314.20514
C41: Perú | D41: =+D25 -> 167.14016 | E41: =+E25 -> 109.66978 | F41: =+F25 -> 119.90377 | G41: =+G25 -> 98.13241 | H41: =+H25 -> 125.25863 | I41: =+I25 -> 82.824806 | J41: =+J25 -> 139.674 | K41: =+K25 -> 152.09422 | ... O41: =+O25 -> 159.18262 | P41: =+SUM(D41:O41) -> 1428.4109 | Q41: =+AVERAGE(D41:O41) -> 119.03424
C42: Brasil | D42: =+D26 -> 44.59949 | E42: =+E26 -> 49.27034 | F42: =+F26 -> 12.37958 | G42: =+G26 -> 21.355715 | H42: =+H26 -> 46.92575 | I42: =+I26 -> 15.35474 | J42: =+J26 -> 23.351 | K42: =+K26 -> 25.03507 | ... O42: =+O26 -> 36.3368 | P42: =+SUM(D42:O42) -> 358.38748 | Q42: =+AVERAGE(D42:O42) -> 29.865624
C43: EEUU | D43: 0 | E43: 0 | F43: 29.806 | G43: 0 | H43: =+(32809+600)/1000 -> 33.409 | I43: 8.512 | J43: 71.468 | K43: =44.749+17.214 -> 61.963 | L43: 14.9 | M43: =4.77+27.585 -> 32.355 | N43: 7.5 | O43: =+(1600+17+6667+1000+17+22318+17+17+118000+17+1000)/1000 -> 150.67 | P43: =+SUM(D43:O43) -> 410.583 | Q43: =+AVERAGE(D43:O43) -> 34.21525
C44: Total | D44: =+SUM(D40:D43) -> 688.03016 | E44: =+SUM(E40:E43) -> 472.25504 | F44: =+SUM(F40:F43) -> 437.9579 | G44: =+SUM(G40:G43) -> 351.0094 | H44: =+SUM(H40:H43) -> 522.76343 | I44: =+SUM(I40:I43) -> 394.83649 | J44: =+SUM(J40:J43) -> 526.62049 | K44: =+SUM(K40:K43) -> 538.31008 | ... Q44: =+SUM(Q40:Q43) -> 497.32025
C47: Item | D47: ene | E47: feb | F47: mar | G47: abr | H47: may | I47: jun | J47: jul | K47: ago | L47: sept | M47: oct | N47: nov | O47: dic | P47: Total | Q47: Promedio
C48: Sueldos | D48: =+D6 -> 302.50526 | E48: =+E6 -> 278.5006 | F48: =+F6 -> 288.865 | G48: =+G6 -> 271.76518 | H48: =+H6 -> 312.95631 | I48: =+I6 -> 233.21148 | J48: =+J6 -> 335.85132 | K48: =+K6 -> 306.40784 | ... O48: =+O6 -> 316.82887 | P48: =+SUM(D48:O48) -> 3489.543 | Q48: =+AVERAGE(D48:O48) -> 290.79525
C49: Externo | D49: =+D7+D43 -> 123.39341 | E49: =+E7+E43 -> 95.218967 | F49: =+F7+F43 -> 93.077157 | G49: =+G7+G43 -> 9.5349993 | H49: =+H7+H43 -> 123.51901 | I49: =+I7+I43 -> 109.69994 | J49: =+J7+J43 -> 124.60333 | K49: =+K7+K43 -> 169.26465 | ... O49: =+O7+O43 -> 248.3348 | P49: =+SUM(D49:O49) -> 1359.3966 | Q49: =+AVERAGE(D49:O49) -> 113.28305
C50: Oficina | D50: =+D8 -> 46.73479 | E50: =+E8 -> 35.698197 | F50: =+F8 -> 25.091045 | G50: =+G8 -> 34.665023 | H50: =+H8 -> 46.509808 | I50: =+I8 -> 36.712331 | J50: =+J8 -> 41.59982 | K50: =+K8 -> 37.109385 | ... O50: =+O8 -> 70.662434 | P50: =+SUM(D50:O50) -> 508.93863 | Q50: =+AVERAGE(D50:O50) -> 42.411552
C51: Extras personas | D51: =+D9 -> 129.39817 | E51: =+E9 -> 40.431764 | F51: =+F9 -> 19.643364 | G51: =+G9 -> 12.341404 | H51: =+H9 -> 18.451806 | I51: =+I9 -> 6.0272542 | J51: =+J9 -> 5.0827933 | K51: =+K9 -> 4.9271873 | ... O51: =+O9 -> 13.829525 | P51: =+SUM(D51:O51) -> 313.73029 | Q51: =+AVERAGE(D51:O51) -> 26.144191
C52: Viajes | D52: =+D10 -> 70.94038 | E52: =+E10 -> 15.541723 | F52: =+F10 -> 6.4251697 | G52: =+G10 -> 19.654064 | H52: =+H10 -> 11.217311 | I52: =+I10 -> 6.643918 | J52: =+J10 -> 10.766462 | K52: =+K10 -> 12.765451 | ... O52: =+O10 -> 16.0338 | P52: =+SUM(D52:O52) -> 192.24619 | Q52: =+AVERAGE(D52:O52) -> 16.020516
C53: Compañía | D53: =+D11 -> 12.901351 | E53: =+E11 -> 5.280059 | F53: =+F11 -> 2.6626843 | G53: =+G11 -> 2.6842877 | H53: =+H11 -> 6.9208513 | I53: =+I11 -> 0 | J53: =+J11 -> 5.6590789 | K53: =+K11 -> 5.7457512 | ... O53: =+O11 -> 12.612711 | P53: =+SUM(D53:O53) -> 76.115717 | Q53: =+AVERAGE(D53:O53) -> 6.3429764
C54: Comercial | D54: =+D12 -> 1.146288 | E54: =+E12 -> 0.86461015 | F54: =+F12 -> 1.7211988 | G54: =+G12 -> 0 | H54: =+H12 -> 2.3744771 | I54: =+I12 -> 0.89949032 | J54: =+J12 -> 0.88847647 | K54: =+K12 -> 0.89579525 | ... O54: =+O12 -> 1.1941192 | P54: =+SUM(D54:O54) -> 14.370962 | Q54: =+AVERAGE(D54:O54) -> 1.1975801
C55: Bancarios | D55: =+D13 -> 1.010502 | E55: =+E13 -> 0.71911981 | F55: =+F13 -> 0.47228157 | G55: =+G13 -> 0.36444023 | H55: =+H13 -> 0.81385956 | I55: =+I13 -> 1.6420746 | J55: =+J13 -> 2.1692001 | K55: =+K13 -> 1.1940144 | ... O55: =+O13 -> 1.5701245 | P55: =+SUM(D55:O55) -> 13.501653 | Q55: =+AVERAGE(D55:O55) -> 1.1251377
C56: Total | D56: =+SUM(D48:D55) -> 688.03016 | E56: =+SUM(E48:E55) -> 472.25504 | F56: =+SUM(F48:F55) -> 437.9579 | G56: =+SUM(G48:G55) -> 351.0094 | H56: =+SUM(H48:H55) -> 522.76343 | I56: =+SUM(I48:I55) -> 394.83649 | J56: =+SUM(J48:J55) -> 526.62049 | K56: =+SUM(K48:K55) -> 538.31008 | ... Q56: =+SUM(Q48:Q55) -> 497.32025
C57: Acumulado | D57: =+SUM($D$56:D56) -> 688.03016 | E57: =+SUM($D$56:E56) -> 1160.2852 | F57: =+SUM($D$56:F56) -> 1598.2431 | G57: =+SUM($D$56:G56) -> 1949.2525 | H57: =+SUM($D$56:H56) -> 2472.0159 | I57: =+SUM($D$56:I56) -> 2866.8524 | J57: =+SUM($D$56:J56) -> 3393.4729 | K57: =+SUM($D$56:K56) -> 3931.783 | ... O57: =+SUM($D$56:O56) -> 5967.843
P58: Externo | Q58: =+P49/$P$48 -> 0.38956292
P59: Oficina | Q59: =+P50/$P$48 -> 0.14584678
P60: Extras personas | Q60: =+P51/$P$48 -> 0.089905839
P61: Viajes | Q61: =+P52/$P$48 -> 0.055092082
P62: Compañía | Q62: =+P53/$P$48 -> 0.021812517
P63: Comercial | Q63: =+P54/$P$48 -> 0.0041182933
P64: Bancarios | Q64: =+P55/$P$48 -> 0.0038691751
C76: kUS$ | D76: =+Q56 -> 497.32025 | E76: Media
C77: kUS$ | D77: =+_xlfn.STDEV.P(D56:O56) -> 101.9718 | E77: Desviación Estandar (Gasto)
C78: % | D78: =+D77/D76 -> 0.20504253 | E78: Coeficiente de variación

Sheet Análisis gastos oct
B3: Análisis de gastos mes - Octubre
B4: Item | C4: Oct_Proy | D4: Oct_Act | E4: Dif. | F4: Var.% | H4: =+C4 -> Oct_Proy | I4: =+C13 -> 341.08351
B5: Sueldos | C5: =+'Gasto Septiembre'!K9/1000 -> 273.43923 | D5: =+'Gasto total_Análisis'!M48 -> 294.76603 | E5: =+D5-C5 -> 21.326807 | F5: =+E5/C5 -> 0.077994687 | H5: Externo | I5: 94.648997
B6: Externo | C6: =+'Gasto Septiembre'!K10/1000 -> 8.6849533 | D6: =+'Gasto total_Análisis'!M49 -> 130.68895 | E6: =+D6-C6 -> 122.004 | F6: =+E6/C6 -> 14.047744 | H6: Extras personas | I6: 25.945761
B7: Oficina | C7: =+'Gasto Septiembre'!K11/1000 -> 44.285529 | D7: =+'Gasto total_Análisis'!M50 -> 47.609466 | E7: =+D7-C7 -> 3.3239373 | F7: =+E7/C7 -> 0.075056964 | H7: Oficina | I7: 3.3239373
B8: Extras personas | C8: =+'Gasto Septiembre'!K12/1000 -> 3.5645782 | D8: =+'Gasto total_Análisis'!M51 -> 29.951058 | E8: =+D8-C8 -> 26.38648 | F8: =+E8/C8 -> 7.402413 | H8: Viajes | I8: 2.5982621
B9: Viajes | C9: =+'Gasto Septiembre'!K13/1000 -> 6 | D9: =+'Gasto total_Análisis'!M52 -> 8.7212621 | E9: =+D9-C9 -> 2.7212621 | F9: =+E9/C9 -> 0.45354369 | H9: Comercial | I9: -0.0073196549
B10: Compañía | C10: =+'Gasto Septiembre'!K14/1000 -> 3.322821 | D10: =+'Gasto total_Análisis'!M53 -> 5.5199495 | E10: =+D10-C10 -> 2.1971285 | F10: =+E10/C10 -> 0.66122386 | H10: Bancarios | I10: -0.022908708
B11: Comercial | C11: =+'Gasto Septiembre'!K15/1000 -> 0.89936408 | D11: =+'Gasto total_Análisis'!M54 -> 0.89204442 | E11: =+D11-C11 -> -0.0073196549 | F11: =+E11/C11 -> -0.0081387006 | H11: Compañía | I11: -0.56284623
B12: Bancarios | C12: =+'Gasto Septiembre'!K16/1000 -> 0.88703314 | D12: =+'Gasto total_Análisis'!M55 -> 0.86412444 | E12: =+D12-C12 -> -0.022908708 | F12: =+E12/C12 -> -0.025826214 | H12: Sueldos | I12: -4.3863039
B13: Total | C13: =+SUM(C5:C12) -> 341.08351 | D13: =+SUM(D5:D12) -> 519.01289 | E13: =+SUM(E5:E12) -> 177.92938 | F13: =+E13/C13 -> 0.5216593 | H13: =+D4 -> Oct_Act | I13: =+SUM(I4:I12) -> 462.62108
B16: Análisis de gastos proyectado año - 2024
B17: Item | C17: 2024_Proy | D17: 2024_Act | E17: Dif. | F17: Var.% | H17: =+C17 -> 2024_Proy | I17: =+C26 -> 5252.7427
B18: Sueldos | C18: =+'Gasto Septiembre'!N9/1000 -> 3423.6868 | D18: =+'Gasto total_Análisis'!P48 -> 3489.543 | E18: =+D18-C18 -> 65.856192 | F18: =+E18/C18 -> 0.01923546 | H18: Externo | I18: 318.00185
B19: Externo | C19: =+'Gasto Septiembre'!N10/1000 -> 729.23567 | D19: =+'Gasto total_Análisis'!P49 -> 1359.3966 | E19: =+D19-C19 -> 630.16091 | F19: =+E19/C19 -> 0.8641389 | H19: Extras personas | I19: 26.820936
B20: Oficina | C20: =+'Gasto Septiembre'!N11/1000 -> 585.02931 | D20: =+'Gasto total_Análisis'!P50 -> 508.93863 | E20: =+D20-C20 -> -76.090688 | F20: =+E20/C20 -> -0.13006303 | H20: Viajes | I20: 7.1372621
B21: Extras personas | C21: =+'Gasto Septiembre'!N12/1000 -> 251.71663 | D21: =+'Gasto total_Análisis'!P51 -> 313.73029 | E21: =+D21-C21 -> 62.013667 | F21: =+E21/C21 -> 0.24636301 | H21: Sueldos | I21: 6.5792267
B22: Viajes | C22: =+'Gasto Septiembre'!N13/1000 -> 183.67546 | D22: =+'Gasto total_Análisis'!P52 -> 192.24619 | E22: =+D22-C22 -> 8.5707353 | F22: =+E22/C22 -> 0.046662387 | H22: Comercial | I22: -0.014592167
B23: Compañía | C23: =+'Gasto Septiembre'!N14/1000 -> 54.605148 | D23: =+'Gasto total_Análisis'!P53 -> 76.115717 | E23: =+D23-C23 -> 21.510568 | F23: =+E23/C23 -> 0.39392931 | H23: Bancarios | I23: -0.19885359
B24: Comercial | C24: =+'Gasto Septiembre'!N15/1000 -> 12.619057 | D24: =+'Gasto total_Análisis'!P54 -> 14.370962 | E24: =+D24-C24 -> 1.7519043 | F24: =+E24/C24 -> 0.13883004 | H24: Compañía | I24: -0.5897155
B25: Bancarios | C25: =+'Gasto Septiembre'!N16/1000 -> 12.17462 | D25: =+'Gasto total_Análisis'!P55 -> 13.501653 | E25: =+D25-C25 -> 1.3270332 | F25: =+E25/C25 -> 0.10899998 | H25: Oficina | I25: -80.639856
B26: Total | C26: =+SUM(C18:C25) -> 5252.7427 | D26: =+SUM(D18:D25) -> 5967.843 | E26: =+SUM(E18:E25) -> 715.10032 | F26: =+E26/C26 -> 0.13613846 | H26: =+D17 -> 2024_Act | I26: =+SUM(I17:I25) -> 5529.839

Sheet Sueldos Septiembre
AW2: Patricio Vergara | AX2: Consultor
A3: Clasificación 0 | B3: (Todas) | AW3: Mateo Villanueva | AX3: Ingeniero de Proyectos
A4: Clasificación 1 | B4: (Varios elementos) | AW4: Gonzalo Diaz | AX4: Director de Proyecto
A5: País | B5: (Todas) | AW5: Cristian Villaroel | AX5: Director de Proyecto
A7: Suma de Valor USD | D7: Meses (Atributo) | Q7: Suma de Valor USD | T7: Meses (Atributo) | AG7: Suma de Valor USD | AJ7: Meses (Atributo)
A8: Clasificación 2 | B8: Clasificación 3 | C8: Detalle | D8: ene | E8: feb | F8: mar | G8: abr | H8: may | I8: jun | J8: jul | K8: ago | L8: sept | M8: oct | N8: nov | O8: dic | Q8: Clasificación 2 | R8: Clasificación 3 | S8: Detalle | T8: ene | U8: feb | V8: mar | W8: abr | X8: may | Y8: jun | Z8: jul | AA8: ago | AB8: sept | AC8: oct | AD8: nov | AE8: dic | AG8: Clasificación 2 | AH8: Clasificación 3 | AI8: Detalle | AJ8: ene | AK8: feb | AL8: mar | AM8: abr | AN8: may | AO8: jun | AP8: jul | AQ8: ago | AR8: sept | AS8: oct | AT8: nov | AU8: dic | AW8: Nombre | AX8: Cargo | AZ8: Cargos | BA8: #Cantidad
A9: Sueldos | B9: Sueldo | C9: Alejandro Espinosa | D9: 8612.8752 | E9: 8256.7911 | F9: 8277.5328 | G9: 8177.8985 | H9: 8346.2575 | I9: 8561.1387 | J9: 8384.322 | K9: 0 | L9: 12470.381 | M9: 0 | N9: 0 | O9: 0 | Q9: =A9 -> Sueldos | R9: =B9 -> Sueldo | S9: =C9 -> Alejandro Espinosa | T9: =+IF(D9>0,1,0) -> 1 | U9: =+IF(E9>0,1,0) -> 1 | V9: =+IF(F9>0,1,0) -> 1 | W9: =+IF(G9>0,1,0) -> 1 | X9: =+IF(H9>0,1,0) -> 1 | Y9: =+IF(I9>0,1,0) -> 1 | Z9: =+IF(J9>0,1,0) -> 1 | AA9: =+IF(K9>0,1,0) -> 0 | ... AE9: =+IF(O9>0,1,0) -> 0 | AG9: Sueldos | AH9: Sueldo | AI9: Alejandro Espinosa | AJ9: 8612.8752 | AK9: 8256.7911 | AL9: 8277.5328 | AM9: 8177.8985 | AN9: 8346.2575 | AO9: 8561.1387 | AP9: 8384.322 | AQ9: 0 | AR9: 12470.381 | AS9: 0 | AT9: 0 | AU9: 0 | AW9: =+IF(AD9=1,S9," ") | AZ9: Gerente Ingeniería | BA9: =+COUNTIF(AX:AX,AZ9) -> 1
A10: Sueldos | B10: Sueldo | C10: Alex Figueroa | D10: 8425.1203 | E10: 8065.6523 | F10: 8084.2266 | G10: 9000.5222 | H10: 9188.1821 | I10: 9427.2681 | J10: 9215.5727 | K10: 9646.0851 | L10: 9698.6681 | M10: 9539.8864 | N10: 9793.536 | O10: 11092.296 | Q10: =A10 -> Sueldos | R10: =B10 -> Sueldo | S10: =C10 -> Alex Figueroa | T10: =+IF(D10>0,1,0) -> 1 | U10: =+IF(E10>0,1,0) -> 1 | V10: =+IF(F10>0,1,0) -> 1 | W10: =+IF(G10>0,1,0) -> 1 | X10: =+IF(H10>0,1,0) -> 1 | Y10: =+IF(I10>0,1,0) -> 1 | Z10: =+IF(J10>0,1,0) -> 1 | AA10: =+IF(K10>0,1,0) -> 1 | ... AE10: =+IF(O10>0,1,0) -> 1 | AG10: Sueldos | AH10: Sueldo | AI10: Alex Figueroa | AJ10: 8425.1203 | AK10: 8065.6523 | AL10: 8084.2266 | AM10: 9000.5222 | AN10: 9188.1821 | AO10: 9427.2681 | AP10: 9215.5727 | AQ10: 9646.0851 | AR10: 9698.6681 | AS10: 9539.8864 | AT10: 9793.536 | AU10: 11092.296 | AW10: =+IF(AD10=1,S10," ") -> Alex Figueroa | AX10: Director de Proyecto | AZ10: Consultor | BA10: =+COUNTIF(AX:AX,AZ10) -> 3
A11: Sueldos | B11: Sueldo | C11: Alex Pacheco C. | D11: 2947.9802 | E11: 2825.3146 | F11: 2831.856 | G11: 2796.9641 | H11: 2854.5881 | I11: 2927.2905 | J11: 2944.313 | K11: 3029.1555 | L11: 3023.0005 | M11: 2963.8557 | N11: 3042.6597 | O11: 3446.159 | Q11: =A11 -> Sueldos | R11: =B11 -> Sueldo | S11: =C11 -> Alex Pacheco C. | T11: =+IF(D11>0,1,0) -> 1 | U11: =+IF(E11>0,1,0) -> 1 | V11: =+IF(F11>0,1,0) -> 1 | W11: =+IF(G11>0,1,0) -> 1 | X11: =+IF(H11>0,1,0) -> 1 | Y11: =+IF(I11>0,1,0) -> 1 | Z11: =+IF(J11>0,1,0) -> 1 | AA11: =+IF(K11>0,1,0) -> 1 | ... AE11: =+IF(O11>0,1,0) -> 1 | AG11: Sueldos | AH11: Sueldo | AI11: Alex Pacheco C. | AJ11: 2947.9802 | AK11: 2825.3146 | AL11: 2831.856 | AM11: 2796.9641 | AN11: 2854.5881 | AO11: 2927.2905 | AP11: 2944.313 | AQ11: 3029.1555 | AR11: 3023.0005 | AS11: 2963.8557 | AT11: 3042.6597 | AU11: 3446.159 | AW11: =+IF(AD11=1,S11," ") -> Alex Pacheco C. | AX11: Ingeniero Senior | AZ11: Director de Proyecto | BA11: =+COUNTIF(AX:AX,AZ11) -> 5
A12: Sueldos | B12: Sueldo | C12: Americo Zuzunaga | D12: 15627.149 | E12: 12771.726 | F12: 12720.817 | G12: 13033.347 | H12: 18057.936 | I12: 12583.422 | J12: 24597.319 | K12: 21641.216 | L12: 12712.144 | M12: 32706.012 | N12: 0 | O12: 0 | Q12: =A12 -> Sueldos | R12: =B12 -> Sueldo | S12: =C12 -> Americo Zuzunaga | T12: =+IF(D12>0,1,0) -> 1 | U12: =+IF(E12>0,1,0) -> 1 | V12: =+IF(F12>0,1,0) -> 1 | W12: =+IF(G12>0,1,0) -> 1 | X12: =+IF(H12>0,1,0) -> 1 | Y12: =+IF(I12>0,1,0) -> 1 | Z12: =+IF(J12>0,1,0) -> 1 | AA12: =+IF(K12>0,1,0) -> 1 | ... AE12: =+IF(O12>0,1,0) -> 0 | AG12: Sueldos | AH12: Sueldo | AI12: Americo Zuzunaga | AJ12: 15627.149 | AK12: 12771.726 | AL12: 12720.817 | AM12: 13033.347 | AN12: 18057.936 | AO12: 12583.422 | AP12: 24597.319 | AQ12: 21641.216 | AR12: 12712.144 | AS12: 32706.012 | AT12: 0 | AU12: 0 | AW12: =+IF(AD12=1,S12," ") | AZ12: Ingeniero Principal | BA12: =+COUNTIF(AX:AX,AZ12) -> 8
A13: Sueldos | B13: Sueldo | C13: Andree del Castillo | D13: 3378.5173 | E13: 2772.8232 | F13: 2818.1787 | G13: 2877.3642 | H13: 3966.4574 | I13: 3082.1981 | J13: 13291.234 | K13: 0 | L13: 0 | M13: 0 | N13: 0 | O13: 0 | Q13: =A13 -> Sueldos | R13: =B13 -> Sueldo | S13: =C13 -> Andree del Castillo | T13: =+IF(D13>0,1,0) -> 1 | U13: =+IF(E13>0,1,0) -> 1 | V13: =+IF(F13>0,1,0) -> 1 | W13: =+IF(G13>0,1,0) -> 1 | X13: =+IF(H13>0,1,0) -> 1 | Y13: =+IF(I13>0,1,0) -> 1 | Z13: =+IF(J13>0,1,0) -> 1 | AA13: =+IF(K13>0,1,0) -> 0 | ... AE13: =+IF(O13>0,1,0) -> 0 | AG13: Sueldos | AH13: Sueldo | AI13: Andree del Castillo | AJ13: 3378.5173 | AK13: 2772.8232 | AL13: 2818.1787 | AM13: 2877.3642 | AN13: 3966.4574 | AO13: 3082.1981 | AP13: 13291.234 | AQ13: 0 | AR13: 0 | AS13: 0 | AT13: 0 | AU13: 0 | AW13: =+IF(AD13=1,S13," ") | AZ13: Ingeniero Senior | BA13: =+COUNTIF(AX:AX,AZ13) -> 7
A14: Sueldos | B14: Sueldo | C14: Andrés Budini M. | D14: 3630.5471 | E14: 3477.3079 | F14: 1991.6571 | G14: 3438.5715 | H14: 3509.267 | I14: 3598.4542 | J14: 3608.7223 | K14: 3694.1883 | L14: 3770.5848 | M14: 3643.5943 | N14: 0 | O14: 0 | Q14: =A14 -> Sueldos | R14: =B14 -> Sueldo | S14: =C14 -> Andrés Budini M. | T14: =+IF(D14>0,1,0) -> 1 | U14: =+IF(E14>0,1,0) -> 1 | V14: =+IF(F14>0,1,0) -> 1 | W14: =+IF(G14>0,1,0) -> 1 | X14: =+IF(H14>0,1,0) -> 1 | Y14: =+IF(I14>0,1,0) -> 1 | Z14: =+IF(J14>0,1,0) -> 1 | AA14: =+IF(K14>0,1,0) -> 1 | ... AE14: =+IF(O14>0,1,0) -> 0 | AG14: Sueldos | AH14: Sueldo | AI14: Andrés Budini M. | AJ14: 3630.5471 | AK14: 3477.3079 | AL14: 1991.6571 | AM14: 3438.5715 | AN14: 3509.267 | AO14: 3598.4542 | AP14: 3608.7223 | AQ14: 3694.1883 | AR14: 3770.5848 | AS14: 3643.5943 | AT14: 0 | AU14: 0 | AW14: =+IF(AD14=1,S14," ") | AZ14: Ingeniero de Proyectos | BA14: =+COUNTIF(AX:AX,AZ14) -> 22
A15: Sueldos | B15: Sueldo | C15: Angelo Patri Carbajal | D15: 655.65172 | E15: 658.4 | F15: 671.8624 | G15: 334.76 | H15: 0 | I15: 0 | J15: 0 | K15: 0 | L15: 0 | M15: 0 | N15: 0 | O15: 0 | Q15: =A15 -> Sueldos | R15: =B15 -> Sueldo | S15: =C15 -> Angelo Patri Carbajal | T15: =+IF(D15>0,1,0) -> 1 | U15: =+IF(E15>0,1,0) -> 1 | V15: =+IF(F15>0,1,0) -> 1 | W15: =+IF(G15>0,1,0) -> 1 | X15: =+IF(H15>0,1,0) -> 0 | Y15: =+IF(I15>0,1,0) -> 0 | Z15: =+IF(J15>0,1,0) -> 0 | AA15: =+IF(K15>0,1,0) -> 0 | ... AE15: =+IF(O15>0,1,0) -> 0 | AG15: Sueldos | AH15: Sueldo | AI15: Angelo Patri Carbajal | AJ15: 655.65172 | AK15: 658.4 | AL15: 671.8624 | AM15: 334.76 | AN15: 0 | AO15: 0 | AP15: 0 | AQ15: 0 | AR15: 0 | AS15: 0 | AT15: 0 | AU15: 0 | AW15: =+IF(AD15=1,S15," ")
A16: Sueldos | B16: Sueldo | C16: Antonio Schettino | D16: 2802.86 | E16: 2844.04 | F16: 2846.91 | G16: 2881.39 | H16: 2950.14 | I16: 2720.9 | J16: 2788 | K16: 2956.01 | L16: 2946 | M16: 2946 | N16: 2946 | O16: 2946 | Q16: =A16 -> Sueldos | R16: =B16 -> Sueldo | S16: =C16 -> Antonio Schettino | T16: =+IF(D16>0,1,0) -> 1 | U16: =+IF(E16>0,1,0) -> 1 | V16: =+IF(F16>0,1,0) -> 1 | W16: =+IF(G16>0,1,0) -> 1 | X16: =+IF(H16>0,1,0) -> 1 | Y16: =+IF(I16>0,1,0) -> 1 | Z16: =+IF(J16>0,1,0) -> 1 | AA16: =+IF(K16>0,1,0) -> 1 | ... AE16: =+IF(O16>0,1,0) -> 1 | AG16: Sueldos | AH16: Sueldo | AI16: Antonio Schettino | AJ16: 2802.86 | AK16: 2844.04 | AL16: 2846.91 | AM16: 2881.39 | AN16: 2950.14 | AO16: 2720.9 | AP16: 2788 | AQ16: 2956.01 | AR16: 2946 | AS16: 2946 | AT16: 2946 | AU16: 2946 | AW16: =+IF(AD16=1,S16," ") -> Antonio Schettino | AX16: Country Manager | AZ16: Total | BA16: =SUBTOTAL(9,BA9:BA14) -> 46
A17: Sueldos | B17: Sueldo | C17: Arnold Tadeo | D17: 3002.0235 | E17: 1495.2351 | F17: 1519.6929 | G17: 1551.6122 | H17: 2138.8881 | I17: 1465.4653 | J17: 2922.7402 | K17: 2520.336 | L17: 1497.0419 | M17: 1476.0628 | N17: 2325.6785 | O17: 3234.5095 | Q17: =A17 -> Sueldos | R17: =B17 -> Sueldo | S17: =C17 -> Arnold Tadeo | T17: =+IF(D17>0,1,0) -> 1 | U17: =+IF(E17>0,1,0) -> 1 | V17: =+IF(F17>0,1,0) -> 1 | W17: =+IF(G17>0,1,0) -> 1 | X17: =+IF(H17>0,1,0) -> 1 | Y17: =+IF(I17>0,1,0) -> 1 | Z17: =+IF(J17>0,1,0) -> 1 | AA17: =+IF(K17>0,1,0) -> 1 | ... AE17: =+IF(O17>0,1,0) -> 1 | AG17: Sueldos | AH17: Sueldo | AI17: Arnold Tadeo | AJ17: 3002.0235 | AK17: 1495.2351 | AL17: 1519.6929 | AM17: 1551.6122 | AN17: 2138.8881 | AO17: 1465.4653 | AP17: 2922.7402 | AQ17: 2520.336 | AR17: 1497.0419 | AS17: 1476.0628 | AT17: 2325.6785 | AU17: 3234.5095 | AW17: =+IF(AD17=1,S17," ") -> Arnold Tadeo | AX17: Ingeniero de Proyectos
A18: Sueldos | B18: Sueldo | C18: CARLOS CARMELO HIDALGO | D18: 4101.7571 | E18: 0 | F18: 0 | G18: 0 | H18: 0 | I18: 0 | J18: 0 | K18: 0 | L18: 0 | M18: 0 | N18: 0 | O18: 0 | Q18: =A18 -> Sueldos | R18: =B18 -> Sueldo | S18: =C18 -> CARLOS CARMELO HIDALGO | T18: =+IF(D18>0,1,0) -> 1 | U18: =+IF(E18>0,1,0) -> 0 | V18: =+IF(F18>0,1,0) -> 0 | W18: =+IF(G18>0,1,0) -> 0 | X18: =+IF(H18>0,1,0) -> 0 | Y18: =+IF(I18>0,1,0) -> 0 | Z18: =+IF(J18>0,1,0) -> 0 | AA18: =+IF(K18>0,1,0) -> 0 | ... AE18: =+IF(O18>0,1,0) -> 0 | AG18: Sueldos | AH18: Sueldo | AI18: CARLOS CARMELO HIDALGO | AJ18: 4101.7571 | AK18: 0 | AL18: 0 | AM18: 0 | AN18: 0 | AO18: 0 | AP18: 0 | AQ18: 0 | AR18: 0 | AS18: 0 | AT18: 0 | AU18: 0 | AW18: =+IF(AD18=1,S18," ")
A19: Sueldos | B19: Sueldo | C19: Carlos Catalán | D19: 3582.3951 | E19: 2930.091 | F19: 2960.0891 | G19: 3022.2491 | H19: 4166.1994 | I19: 2854.4678 | J19: 6129.0731 | K19: 5367.0215 | L19: 2946.2263 | M19: 2875.1055 | N19: 4530.0044 | O19: 6782.8625 | Q19: =A19 -> Sueldos | R19: =B19 -> Sueldo | S19: =C19 -> Carlos Catalán | T19: =+IF(D19>0,1,0) -> 1 | U19: =+IF(E19>0,1,0) -> 1 | V19: =+IF(F19>0,1,0) -> 1 | W19: =+IF(G19>0,1,0) -> 1 | X19: =+IF(H19>0,1,0) -> 1 | Y19: =+IF(I19>0,1,0) -> 1 | Z19: =+IF(J19>0,1,0) -> 1 | AA19: =+IF(K19>0,1,0) -> 1 | ... AE19: =+IF(O19>0,1,0) -> 1 | AG19: Sueldos | AH19: Sueldo | AI19: Carlos Catalán | AJ19: 3582.3951 | AK19: 2930.091 | AL19: 2960.0891 | AM19: 3022.2491 | AN19: 4166.1994 | AO19: 2854.4678 | AP19: 6129.0731 | AQ19: 5367.0215 | AR19: 2946.2263 | AS19: 2875.1055 | AT19: 4530.0044 | AU19: 6782.8625 | AW19: =+IF(AD19=1,S19," ") -> Carlos Catalán | AX19: Ingeniero Senior
A20: Sueldos | B20: Sueldo | C20: Carlos Morante | D20: 3867.8791 | E20: 3174.4532 | F20: 3226.3782 | G20: 3294.14 | H20: 4540.9759 | I20: 3111.2584 | J20: 0 | K20: 0 | L20: 0 | M20: 0 | N20: 0 | O20: 0 | Q20: =A20 -> Sueldos | R20: =B20 -> Sueldo | S20: =C20 -> Carlos Morante | T20: =+IF(D20>0,1,0) -> 1 | U20: =+IF(E20>0,1,0) -> 1 | V20: =+IF(F20>0,1,0) -> 1 | W20: =+IF(G20>0,1,0) -> 1 | X20: =+IF(H20>0,1,0) -> 1 | Y20: =+IF(I20>0,1,0) -> 1 | Z20: =+IF(J20>0,1,0) -> 0 | AA20: =+IF(K20>0,1,0) -> 0 | ... AE20: =+IF(O20>0,1,0) -> 0 | AG20: Sueldos | AH20: Sueldo | AI20: Carlos Morante | AJ20: 3867.8791 | AK20: 3174.4532 | AL20: 3226.3782 | AM20: 3294.14 | AN20: 4540.9759 | AO20: 3111.2584 | AP20: 0 | AQ20: 0 | AR20: 0 | AS20: 0 | AT20: 0 | AU20: 0 | AW20: =+IF(AD20=1,S20," ")
A21: Sueldos | B21: Sueldo | C21: Claudio Hernandez | D21: 10340.278 | E21: 9912.7777 | F21: 9941.9923 | G21: 9825.5356 | H21: 10030.851 | I21: 10291.81 | J21: 10050.912 | K21: 10530.224 | L21: 10562.402 | M21: 10414.811 | N21: 10691.724 | O21: 12109.596 | Q21: =A21 -> Sueldos | R21: =B21 -> Sueldo | S21: =C21 -> Claudio Hernandez | T21: =+IF(D21>0,1,0) -> 1 | U21: =+IF(E21>0,1,0) -> 1 | V21: =+IF(F21>0,1,0) -> 1 | W21: =+IF(G21>0,1,0) -> 1 | X21: =+IF(H21>0,1,0) -> 1 | Y21: =+IF(I21>0,1,0) -> 1 | Z21: =+IF(J21>0,1,0) -> 1 | AA21: =+IF(K21>0,1,0) -> 1 | ... AE21: =+IF(O21>0,1,0) -> 1 | AG21: Sueldos | AH21: Sueldo | AI21: Claudio Hernandez | AJ21: 10340.278 | AK21: 9912.7777 | AL21: 9941.9923 | AM21: 9825.5356 | AN21: 10030.851 | AO21: 10291.81 | AP21: 10050.912 | AQ21: 10530.224 | AR21: 10562.402 | AS21: 10414.811 | AT21: 10691.724 | AU21: 12109.596 | AW21: =+IF(AD21=1,S21," ") -> Claudio Hernandez | AX21: Director de Proyecto
A22: Sueldos | B22: Sueldo | C22: Clinton Yahuira | D22: 655.65172 | E22: 658.4 | F22: 671.8624 | G22: 669.52 | H22: 666.13 | I22: 654.96 | J22: 668 | K22: 654.96 | L22: 0 | M22: 0 | N22: 0 | O22: 0 | Q22: =A22 -> Sueldos | R22: =B22 -> Sueldo | S22: =C22 -> Clinton Yahuira | T22: =+IF(D22>0,1,0) -> 1 | U22: =+IF(E22>0,1,0) -> 1 | V22: =+IF(F22>0,1,0) -> 1 | W22: =+IF(G22>0,1,0) -> 1 | X22: =+IF(H22>0,1,0) -> 1 | Y22: =+IF(I22>0,1,0) -> 1 | Z22: =+IF(J22>0,1,0) -> 1 | AA22: =+IF(K22>0,1,0) -> 1 | ... AE22: =+IF(O22>0,1,0) -> 0 | AG22: Sueldos | AH22: Sueldo | AI22: Clinton Yahuira | AJ22: 655.65172 | AK22: 658.4 | AL22: 671.8624 | AM22: 669.52 | AN22: 666.13 | AO22: 654.96 | AP22: 668 | AQ22: 654.96 | AR22: 0 | AS22: 0 | AT22: 0 | AU22: 0 | AW22: =+IF(AD22=1,S22," ")
A23: Sueldos | B23: Sueldo | C23: Cristián Alarcón | D23: 2214.8278 | E23: 2123.0161 | F23: 2524.1096 | G23: 2492.4647 | H23: 2543.443 | I23: 2451.1332 | J23: 2490.2273 | K23: 2842.5992 | L23: 2682.7516 | M23: 2640.8006 | N23: 2711.0151 | O23: 3070.5337 | Q23: =A23 -> Sueldos | R23: =B23 -> Sueldo | S23: =C23 -> Cristián Alarcón | T23: =+IF(D23>0,1,0) -> 1 | U23: =+IF(E23>0,1,0) -> 1 | V23: =+IF(F23>0,1,0) -> 1 | W23: =+IF(G23>0,1,0) -> 1 | X23: =+IF(H23>0,1,0) -> 1 | Y23: =+IF(I23>0,1,0) -> 1 | Z23: =+IF(J23>0,1,0) -> 1 | AA23: =+IF(K23>0,1,0) -> 1 | ... AE23: =+IF(O23>0,1,0) -> 1 | AG23: Sueldos | AH23: Sueldo | AI23: Cristián Alarcón | AJ23: 2214.8278 | AK23: 2123.0161 | AL23: 2524.1096 | AM23: 2492.4647 | AN23: 2543.443 | AO23: 2451.1332 | AP23: 2490.2273 | AQ23: 2842.5992 | AR23: 2682.7516 | AS23: 2640.8006 | AT23: 2711.0151 | AU23: 3070.5337 | AW23: =+IF(AD23=1,S23," ") -> Cristián Alarcón | AX23: Ingeniero de Proyectos
A24: Sueldos | B24: Sueldo | C24: Cristián García | D24: 7950.2818 | E24: 8123.8317 | F24: 0 | G24: 0 | H24: 0 | I24: 0 | J24: 0 | K24: 0 | L24: 0 | M24: 0 | N24: 0 | O24: 0 | Q24: =A24 -> Sueldos | R24: =B24 -> Sueldo | S24: =C24 -> Cristián García | T24: =+IF(D24>0,1,0) -> 1 | U24: =+IF(E24>0,1,0) -> 1 | V24: =+IF(F24>0,1,0) -> 0 | W24: =+IF(G24>0,1,0) -> 0 | X24: =+IF(H24>0,1,0) -> 0 | Y24: =+IF(I24>0,1,0) -> 0 | Z24: =+IF(J24>0,1,0) -> 0 | AA24: =+IF(K24>0,1,0) -> 0 | ... AE24: =+IF(O24>0,1,0) -> 0 | AG24: Sueldos | AH24: Sueldo | AI24: Cristián García | AJ24: 7950.2818 | AK24: 8123.8317 | AL24: 0 | AM24: 0 | AN24: 0 | AO24: 0 | AP24: 0 | AQ24: 0 | AR24: 0 | AS24: 0 | AT24: 0 | AU24: 0 | AW24: =+IF(AD24=1,S24," ")
A25: Sueldos | B25: Sueldo | C25: Cristian Quezada | D25: 0 | E25: 0 | F25: 8988.0921 | G25: 9037.1248 | H25: 9562.8774 | I25: 9618.1163 | J25: 9327.9782 | K25: 9841.642 | L25: 9929.0624 | M25: 9777.7761 | N25: 0 | O25: 0 | Q25: =A25 -> Sueldos | R25: =B25 -> Sueldo | S25: =C25 -> Cristian Quezada | T25: =+IF(D25>0,1,0) -> 0 | U25: =+IF(E25>0,1,0) -> 0 | V25: =+IF(F25>0,1,0) -> 1 | W25: =+IF(G25>0,1,0) -> 1 | X25: =+IF(H25>0,1,0) -> 1 | Y25: =+IF(I25>0,1,0) -> 1 | Z25: =+IF(J25>0,1,0) -> 1 | AA25: =+IF(K25>0,1,0) -> 1 | ... AE25: =+IF(O25>0,1,0) -> 0 | AG25: Sueldos | AH25: Sueldo | AI25: Cristian Quezada | AJ25: 0 | AK25: 0 | AL25: 8988.0921 | AM25: 9037.1248 | AN25: 9562.8774 | AO25: 9618.1163 | AP25: 9327.9782 | AQ25: 9841.642 | AR25: 9929.0624 | AS25: 9777.7761 | AT25: 0 | AU25: 0 | AW25: =+IF(AD25=1,S25," ")
A26: Sueldos | B26: Sueldo | C26: Cristóbal García Wallis practicante | D26: 157.80001 | E26: 296.7861 | F26: 204.3325 | G26: 0 | H26: 0 | I26: 0 | J26: 0 | K26: 0 | L26: 0 | M26: 0 | N26: 0 | O26: 0 | Q26: =A26 -> Sueldos | R26: =B26 -> Sueldo | S26: =C26 -> Cristóbal García Wallis practicante | T26: =+IF(D26>0,1,0) -> 1 | U26: =+IF(E26>0,1,0) -> 1 | V26: =+IF(F26>0,1,0) -> 1 | W26: =+IF(G26>0,1,0) -> 0 | X26: =+IF(H26>0,1,0) -> 0 | Y26: =+IF(I26>0,1,0) -> 0 | Z26: =+IF(J26>0,1,0) -> 0 | AA26: =+IF(K26>0,1,0) -> 0 | ... AE26: =+IF(O26>0,1,0) -> 0 | AG26: Sueldos | AH26: Sueldo | AI26: Cristóbal García Wallis practicante | AJ26: 157.80001 | AK26: 296.7861 | AL26: 204.3325 | AM26: 0 | AN26: 0 | AO26: 0 | AP26: 0 | AQ26: 0 | AR26: 0 | AS26: 0 | AT26: 0 | AU26: 0 | AW26: =+IF(AD26=1,S26," ")
A27: Sueldos | B27: Sueldo | C27: Daniela Oyarzo E. | D27: 1900.1613 | E27: 1821.3576 | F27: 2524.1096 | G27: 2492.4647 | H27: 2543.443 | I27: 2607.743 | J27: 2641.543 | K27: 2682.6035 | L27: 2682.7516 | M27: 2640.8006 | N27: 2711.0151 | O27: 3070.5337 | Q27: =A27 -> Sueldos | R27: =B27 -> Sueldo | S27: =C27 -> Daniela Oyarzo E. | T27: =+IF(D27>0,1,0) -> 1 | U27: =+IF(E27>0,1,0) -> 1 | V27: =+IF(F27>0,1,0) -> 1 | W27: =+IF(G27>0,1,0) -> 1 | X27: =+IF(H27>0,1,0) -> 1 | Y27: =+IF(I27>0,1,0) -> 1 | Z27: =+IF(J27>0,1,0) -> 1 | AA27: =+IF(K27>0,1,0) -> 1 | ... AE27: =+IF(O27>0,1,0) -> 1 | AG27: Sueldos | AH27: Sueldo | AI27: Daniela Oyarzo E. | AJ27: 1900.1613 | AK27: 1821.3576 | AL27: 2524.1096 | AM27: 2492.4647 | AN27: 2543.443 | AO27: 2607.743 | AP27: 2641.543 | AQ27: 2682.6035 | AR27: 2682.7516 | AS27: 2640.8006 | AT27: 2711.0151 | AU27: 3070.5337 | AW27: =+IF(AD27=1,S27," ") -> Daniela Oyarzo E. | AX27: Ingeniero de Proyectos
A28: Sueldos | B28: Sueldo | C28: Diego Muñoz | D28: 1940.7741 | E28: 1860.2927 | F28: 1511.9865 | G28: 2215.5565 | H28: 2260.8933 | I28: 2318.0773 | J28: 3719.6206 | K28: 2386.5479 | L28: 2388.6901 | M28: 2347.4355 | N28: 2409.8499 | O28: 2729.4298 | Q28: =A28 -> Sueldos | R28: =B28 -> Sueldo | S28: =C28 -> Diego Muñoz | T28: =+IF(D28>0,1,0) -> 1 | U28: =+IF(E28>0,1,0) -> 1 | V28: =+IF(F28>0,1,0) -> 1 | W28: =+IF(G28>0,1,0) -> 1 | X28: =+IF(H28>0,1,0) -> 1 | Y28: =+IF(I28>0,1,0) -> 1 | Z28: =+IF(J28>0,1,0) -> 1 | AA28: =+IF(K28>0,1,0) -> 1 | ... AE28: =+IF(O28>0,1,0) -> 1 | AG28: Sueldos | AH28: Sueldo | AI28: Diego Muñoz | AJ28: 1940.7741 | AK28: 1860.2927 | AL28: 1511.9865 | AM28: 2215.5565 | AN28: 2260.8933 | AO28: 2318.0773 | AP28: 3719.6206 | AQ28: 2386.5479 | AR28: 2388.6901 | AS28: 2347.4355 | AT28: 2409.8499 | AU28: 2729.4298 | AW28: =+IF(AD28=1,S28," ") -> Diego Muñoz | AX28: Ingeniero de Proyectos
A29: Sueldos | B29: Sueldo | C29: Diego Troncoso | D29: 1616.1771 | E29: 1549.1156 | F29: 1552.441 | G29: 1533.0899 | H29: 1564.5228 | I29: 1078.9067 | J29: 0 | K29: 0 | L29: 0 | M29: 0 | N29: 0 | O29: 0 | Q29: =A29 -> Sueldos | R29: =B29 -> Sueldo | S29: =C29 -> Diego Troncoso | T29: =+IF(D29>0,1,0) -> 1 | U29: =+IF(E29>0,1,0) -> 1 | V29: =+IF(F29>0,1,0) -> 1 | W29: =+IF(G29>0,1,0) -> 1 | X29: =+IF(H29>0,1,0) -> 1 | Y29: =+IF(I29>0,1,0) -> 1 | Z29: =+IF(J29>0,1,0) -> 0 | AA29: =+IF(K29>0,1,0) -> 0 | ... AE29: =+IF(O29>0,1,0) -> 0 | AG29: Sueldos | AH29: Sueldo | AI29: Diego Troncoso | AJ29: 1616.1771 | AK29: 1549.1156 | AL29: 1552.441 | AM29: 1533.0899 | AN29: 1564.5228 | AO29: 1078.9067 | AP29: 0 | AQ29: 0 | AR29: 0 | AS29: 0 | AT29: 0 | AU29: 0 | AW29: =+IF(AD29=1,S29," ")
A30: Sueldos | B30: Sueldo | C30: Eduardo Cuevas | D30: 2585.6758 | E30: 2478.5321 | F30: 3505.7078 | G30: 3458.9533 | H30: 3526.4912 | I30: 3613.3574 | J30: 3633.3522 | K30: 3709.3411 | L30: 3796.5793 | M30: 3661.4779 | N30: 3758.8305 | O30: 4257.3041 | Q30: =A30 -> Sueldos | R30: =B30 -> Sueldo | S30: =C30 -> Eduardo Cuevas | T30: =+IF(D30>0,1,0) -> 1 | U30: =+IF(E30>0,1,0) -> 1 | V30: =+IF(F30>0,1,0) -> 1 | W30: =+IF(G30>0,1,0) -> 1 | X30: =+IF(H30>0,1,0) -> 1 | Y30: =+IF(I30>0,1,0) -> 1 | Z30: =+IF(J30>0,1,0) -> 1 | AA30: =+IF(K30>0,1,0) -> 1 | ... AE30: =+IF(O30>0,1,0) -> 1 | AG30: Sueldos | AH30: Sueldo | AI30: Eduardo Cuevas | AJ30: 2585.6758 | AK30: 2478.5321 | AL30: 3505.7078 | AM30: 3458.9533 | AN30: 3526.4912 | AO30: 3613.3574 | AP30: 3633.3522 | AQ30: 3709.3411 | AR30: 3796.5793 | AS30: 3661.4779 | AT30: 3758.8305 | AU30: 4257.3041 | AW30: =+IF(AD30=1,S30," ") -> Eduardo Cuevas | AX30: Finanzas
A31: Sueldos | B31: Sueldo | C31: Eduardo Lama | D31: 2045.6334 | E31: 2054.3 | F31: 2096.2107 | G31: 2088.91 | H31: 2078.34 | I31: 2043.49 | J31: 2084 | K31: 2043.49 | L31: 2518 | M31: 2096.2107 | N31: 2096.2107 | O31: 2096.2107 | Q31: =A31 -> Sueldos | R31: =B31 -> Sueldo | S31: =C31 -> Eduardo Lama | T31: =+IF(D31>0,1,0) -> 1 | U31: =+IF(E31>0,1,0) -> 1 | V31: =+IF(F31>0,1,0) -> 1 | W31: =+IF(G31>0,1,0) -> 1 | X31: =+IF(H31>0,1,0) -> 1 | Y31: =+IF(I31>0,1,0) -> 1 | Z31: =+IF(J31>0,1,0) -> 1 | AA31: =+IF(K31>0,1,0) -> 1 | ... AE31: =+IF(O31>0,1,0) -> 1 | AG31: Sueldos | AH31: Sueldo | AI31: Eduardo Lama | AJ31: 2045.6334 | AK31: 2054.3 | AL31: 2096.2107 | AM31: 2088.91 | AN31: 2078.34 | AO31: 2043.49 | AP31: 2084 | AQ31: 2043.49 | AR31: 2518 | AS31: 2096.2107 | AT31: 2096.2107 | AU31: 2096.2107 | AW31: =+IF(AD31=1,S31," ") -> Eduardo Lama | AX31: Gerente REDCO Perú
A32: Sueldos | B32: Sueldo | C32: Edward Torres | D32: 1683.1014 | E32: 1381.3582 | F32: 1403.9533 | G32: 1433.4381 | H32: 1976.0055 | I32: 1353.8577 | J32: 2699.9175 | K32: 2328.3911 | L32: 1383.3804 | M32: 1363.6461 | N32: 2148.5552 | O32: 2987.9182 | Q32: =A32 -> Sueldos | R32: =B32 -> Sueldo | S32: =C32 -> Edward Torres | T32: =+IF(D32>0,1,0) -> 1 | U32: =+IF(E32>0,1,0) -> 1 | V32: =+IF(F32>0,1,0) -> 1 | W32: =+IF(G32>0,1,0) -> 1 | X32: =+IF(H32>0,1,0) -> 1 | Y32: =+IF(I32>0,1,0) -> 1 | Z32: =+IF(J32>0,1,0) -> 1 | AA32: =+IF(K32>0,1,0) -> 1 | ... AE32: =+IF(O32>0,1,0) -> 1 | AG32: Sueldos | AH32: Sueldo | AI32: Edward Torres | AJ32: 1683.1014 | AK32: 1381.3582 | AL32: 1403.9533 | AM32: 1433.4381 | AN32: 1976.0055 | AO32: 1353.8577 | AP32: 2699.9175 | AQ32: 2328.3911 | AR32: 1383.3804 | AS32: 1363.6461 | AT32: 2148.5552 | AU32: 2987.9182 | AW32: =+IF(AD32=1,S32," ") -> Edward Torres | AX32: Ingeniero de Proyectos
A33: Sueldos | B33: Sueldo | C33: Emilio Sánchez | D33: 6440.2135 | E33: 6173.9543 | F33: 6184.0531 | G33: 5690.3406 | H33: 6233.7735 | I33: 5411.6844 | J33: 8398.601 | K33: 6548.0607 | L33: 6594.0449 | M33: 6472.3892 | N33: 6644.4792 | O33: 7525.6303 | Q33: =A33 -> Sueldos | R33: =B33 -> Sueldo | S33: =C33 -> Emilio Sánchez | T33: =+IF(D33>0,1,0) -> 1 | U33: =+IF(E33>0,1,0) -> 1 | V33: =+IF(F33>0,1,0) -> 1 | W33: =+IF(G33>0,1,0) -> 1 | X33: =+IF(H33>0,1,0) -> 1 | Y33: =+IF(I33>0,1,0) -> 1 | Z33: =+IF(J33>0,1,0) -> 1 | AA33: =+IF(K33>0,1,0) -> 1 | ... AE33: =+IF(O33>0,1,0) -> 1 | AG33: Sueldos | AH33: Sueldo | AI33: Emilio Sánchez | AJ33: 6440.2135 | AK33: 6173.9543 | AL33: 6184.0531 | AM33: 5690.3406 | AN33: 6233.7735 | AO33: 5411.6844 | AP33: 8398.601 | AQ33: 6548.0607 | AR33: 6594.0449 | AS33: 6472.3892 | AT33: 6644.4792 | AU33: 7525.6303 | AW33: =+IF(AD33=1,S33," ") -> Emilio Sánchez | AX33: Ingeniero Senior
A34: Sueldos | B34: Sueldo | C34: Fabián González Recabarren | D34: 1606.9736 | E34: 1541.8742 | F34: 1545.1856 | G34: 1525.9263 | H34: 1557.2132 | I34: 2542.2702 | J34: 0 | K34: 0 | L34: 0 | M34: 0 | N34: 0 | O34: 0 | Q34: =A34 -> Sueldos | R34: =B34 -> Sueldo | S34: =C34 -> Fabián González Recabarren | T34: =+IF(D34>0,1,0) -> 1 | U34: =+IF(E34>0,1,0) -> 1 | V34: =+IF(F34>0,1,0) -> 1 | W34: =+IF(G34>0,1,0) -> 1 | X34: =+IF(H34>0,1,0) -> 1 | Y34: =+IF(I34>0,1,0) -> 1 | Z34: =+IF(J34>0,1,0) -> 0 | AA34: =+IF(K34>0,1,0) -> 0 | ... AE34: =+IF(O34>0,1,0) -> 0 | AG34: Sueldos | AH34: Sueldo | AI34: Fabián González Recabarren | AJ34: 1606.9736 | AK34: 1541.8742 | AL34: 1545.1856 | AM34: 1525.9263 | AN34: 1557.2132 | AO34: 2542.2702 | AP34: 0 | AQ34: 0 | AR34: 0 | AS34: 0 | AT34: 0 | AU34: 0 | AW34: =+IF(AD34=1,S34," ")
A35: Sueldos | B35: Sueldo | C35: Felipe Espinosa Practica en informática nov.23 | D35: 0 | E35: 0 | F35: 0 | G35: 308.17135 | H35: 0 | I35: 0 | J35: 0 | K35: 0 | L35: 0 | M35: 0 | N35: 0 | O35: 0 | Q35: =A35 -> Sueldos | R35: =B35 -> Sueldo | S35: =C35 -> Felipe Espinosa Practica en informática nov.23 | T35: =+IF(D35>0,1,0) -> 0 | U35: =+IF(E35>0,1,0) -> 0 | V35: =+IF(F35>0,1,0) -> 0 | W35: =+IF(G35>0,1,0) -> 1 | X35: =+IF(H35>0,1,0) -> 0 | Y35: =+IF(I35>0,1,0) -> 0 | Z35: =+IF(J35>0,1,0) -> 0 | AA35: =+IF(K35>0,1,0) -> 0 | ... AE35: =+IF(O35>0,1,0) -> 0 | AG35: Sueldos | AH35: Sueldo | AI35: Felipe Espinosa Practica en informática nov.23 | AJ35: 0 | AK35: 0 | AL35: 0 | AM35: 308.17135 | AN35: 0 | AO35: 0 | AP35: 0 | AQ35: 0 | AR35: 0 | AS35: 0 | AT35: 0 | AU35: 0 | AW35: =+IF(AD35=1,S35," ")
A36: Sueldos | B36: Sueldo | C36: Felipe Lira A. | D36: 4374.5966 | E36: 4190.4798 | F36: 4627.5343 | G36: 4568.267 | H36: 4659.6313 | I36: 4776.4984 | J36: 4749.4501 | K36: 4897.0997 | L36: 3767.3152 | M36: 4837.9921 | N36: 4966.6263 | O36: 5625.2706 | Q36: =A36 -> Sueldos | R36: =B36 -> Sueldo | S36: =C36 -> Felipe Lira A. | T36: =+IF(D36>0,1,0) -> 1 | U36: =+IF(E36>0,1,0) -> 1 | V36: =+IF(F36>0,1,0) -> 1 | W36: =+IF(G36>0,1,0) -> 1 | X36: =+IF(H36>0,1,0) -> 1 | Y36: =+IF(I36>0,1,0) -> 1 | Z36: =+IF(J36>0,1,0) -> 1 | AA36: =+IF(K36>0,1,0) -> 1 | ... AE36: =+IF(O36>0,1,0) -> 1 | AG36: Sueldos | AH36: Sueldo | AI36: Felipe Lira A. | AJ36: 4374.5966 | AK36: 4190.4798 | AL36: 4627.5343 | AM36: 4568.267 | AN36: 4659.6313 | AO36: 4776.4984 | AP36: 4749.4501 | AQ36: 4897.0997 | AR36: 3767.3152 | AS36: 4837.9921 | AT36: 4966.6263 | AU36: 5625.2706 | AW36: =+IF(AD36=1,S36," ") -> Felipe Lira A. | AX36: Ingeniero Senior
A37: Sueldos | B37: Sueldo | C37: Felipe Matamoros C. | D37: 4537.6827 | E37: 4348.7199 | F37: 4423.2777 | G37: 4366.3829 | H37: 4453.4068 | I37: 4564.9059 | J37: 5700.3997 | K37: 0 | L37: 0 | M37: 0 | N37: 0 | O37: 0 | Q37: =A37 -> Sueldos | R37: =B37 -> Sueldo | S37: =C37 -> Felipe Matamoros C. | T37: =+IF(D37>0,1,0) -> 1 | U37: =+IF(E37>0,1,0) -> 1 | V37: =+IF(F37>0,1,0) -> 1 | W37: =+IF(G37>0,1,0) -> 1 | X37: =+IF(H37>0,1,0) -> 1 | Y37: =+IF(I37>0,1,0) -> 1 | Z37: =+IF(J37>0,1,0) -> 1 | AA37: =+IF(K37>0,1,0) -> 0 | ... AE37: =+IF(O37>0,1,0) -> 0 | AG37: Sueldos | AH37: Sueldo | AI37: Felipe Matamoros C. | AJ37: 4537.6827 | AK37: 4348.7199 | AL37: 4423.2777 | AM37: 4366.3829 | AN37: 4453.4068 | AO37: 4564.9059 | AP37: 5700.3997 | AQ37: 0 | AR37: 0 | AS37: 0 | AT37: 0 | AU37: 0 | AW37: =+IF(AD37=1,S37," ")
A38: Sueldos | B38: Sueldo | C38: Felipe Rojas Z. | D38: 8782.9384 | E38: 8366.8112 | F38: 8373.8724 | G38: 8271.4672 | H38: 8440.0669 | I38: 8656.0283 | J38: 8389.7375 | K38: 8842.8204 | L38: 8926.0301 | M38: 8763.1348 | N38: 8996.132 | O38: 10189.145 | Q38: =A38 -> Sueldos | R38: =B38 -> Sueldo | S38: =C38 -> Felipe Rojas Z. | T38: =+IF(D38>0,1,0) -> 1 | U38: =+IF(E38>0,1,0) -> 1 | V38: =+IF(F38>0,1,0) -> 1 | W38: =+IF(G38>0,1,0) -> 1 | X38: =+IF(H38>0,1,0) -> 1 | Y38: =+IF(I38>0,1,0) -> 1 | Z38: =+IF(J38>0,1,0) -> 1 | AA38: =+IF(K38>0,1,0) -> 1 | ... AE38: =+IF(O38>0,1,0) -> 1 | AG38: Sueldos | AH38: Sueldo | AI38: Felipe Rojas Z. | AJ38: 8782.9384 | AK38: 8366.8112 | AL38: 8373.8724 | AM38: 8271.4672 | AN38: 8440.0669 | AO38: 8656.0283 | AP38: 8389.7375 | AQ38: 8842.8204 | AR38: 8926.0301 | AS38: 8763.1348 | AT38: 8996.132 | AU38: 10189.145 | AW38: =+IF(AD38=1,S38," ") -> Felipe Rojas Z. | AX38: Consultor
A39: Sueldos | B39: Sueldo | C39: Fernando Caballero | D39: 3560.658 | E39: 1415.3235 | F39: 0 | G39: 0 | H39: 0 | I39: 0 | J39: 0 | K39: 0 | L39: 0 | M39: 0 | N39: 0 | O39: 0 | Q39: =A39 -> Sueldos | R39: =B39 -> Sueldo | S39: =C39 -> Fernando Caballero | T39: =+IF(D39>0,1,0) -> 1 | U39: =+IF(E39>0,1,0) -> 1 | V39: =+IF(F39>0,1,0) -> 0 | W39: =+IF(G39>0,1,0) -> 0 | X39: =+IF(H39>0,1,0) -> 0 | Y39: =+IF(I39>0,1,0) -> 0 | Z39: =+IF(J39>0,1,0) -> 0 | AA39: =+IF(K39>0,1,0) -> 0 | ... AE39: =+IF(O39>0,1,0) -> 0 | AG39: Sueldos | AH39: Sueldo | AI39: Fernando Caballero | AJ39: 3560.658 | AK39: 1415.3235 | AL39: 0 | AM39: 0 | AN39: 0 | AO39: 0 | AP39: 0 | AQ39: 0 | AR39: 0 | AS39: 0 | AT39: 0 | AU39: 0 | AW39: =+IF(AD39=1,S39," ")
A40: Sueldos | B40: Sueldo | C40: Francisco Bello Moreno | D40: 2360.8092 | E40: 2262.9608 | F40: 3085.0228 | G40: 3046.9277 | H40: 1593.0391 | I40: 3188.769 | J40: 3198.1772 | K40: 3275.6527 | L40: 6341.147 | M40: 0 | N40: 0 | O40: 0 | Q40: =A40 -> Sueldos | R40: =B40 -> Sueldo | S40: =C40 -> Francisco Bello Moreno | T40: =+IF(D40>0,1,0) -> 1 | U40: =+IF(E40>0,1,0) -> 1 | V40: =+IF(F40>0,1,0) -> 1 | W40: =+IF(G40>0,1,0) -> 1 | X40: =+IF(H40>0,1,0) -> 1 | Y40: =+IF(I40>0,1,0) -> 1 | Z40: =+IF(J40>0,1,0) -> 1 | AA40: =+IF(K40>0,1,0) -> 1 | ... AE40: =+IF(O40>0,1,0) -> 0 | AG40: Sueldos | AH40: Sueldo | AI40: Francisco Bello Moreno | AJ40: 2360.8092 | AK40: 2262.9608 | AL40: 3085.0228 | AM40: 3046.9277 | AN40: 1593.0391 | AO40: 3188.769 | AP40: 3198.1772 | AQ40: 3275.6527 | AR40: 6341.147 | AS40: 0 | AT40: 0 | AU40: 0 | AW40: =+IF(AD40=1,S40," ")
A41: Sueldos | B41: Sueldo | C41: Freddy Díaz | D41: 5083.8147 | E41: 4873.6334 | F41: 4887.8345 | G41: 4825.3029 | H41: 4915.4108 | I41: 6517.6964 | J41: 6426.1494 | K41: 6689.0507 | L41: 6729.9375 | M41: 6600.7144 | N41: 6776.2164 | O41: 7674.8377 | Q41: =A41 -> Sueldos | R41: =B41 -> Sueldo | S41: =C41 -> Freddy Díaz | T41: =+IF(D41>0,1,0) -> 1 | U41: =+IF(E41>0,1,0) -> 1 | V41: =+IF(F41>0,1,0) -> 1 | W41: =+IF(G41>0,1,0) -> 1 | X41: =+IF(H41>0,1,0) -> 1 | Y41: =+IF(I41>0,1,0) -> 1 | Z41: =+IF(J41>0,1,0) -> 1 | AA41: =+IF(K41>0,1,0) -> 1 | ... AE41: =+IF(O41>0,1,0) -> 1 | AG41: Sueldos | AH41: Sueldo | AI41: Freddy Díaz | AJ41: 5083.8147 | AK41: 4873.6334 | AL41: 4887.8345 | AM41: 4825.3029 | AN41: 4915.4108 | AO41: 6517.6964 | AP41: 6426.1494 | AQ41: 6689.0507 | AR41: 6729.9375 | AS41: 6600.7144 | AT41: 6776.2164 | AU41: 7674.8377 | AW41: =+IF(AD41=1,S41," ") -> Freddy Díaz | AX41: Ingeniero Principal
A42: Sueldos | B42: Sueldo | C42: Gerson Alfaro | D42: 2947.5685 | E42: 2824.92 | F42: 4206.8493 | G42: 4151.3789 | H42: 4233.1904 | I42: 4337.9801 | J42: 4333.4784 | K42: 4449.8019 | L42: 4531.7376 | M42: 4395.228 | N42: 4512.0897 | O42: 5110.4561 | Q42: =A42 -> Sueldos | R42: =B42 -> Sueldo | S42: =C42 -> Gerson Alfaro | T42: =+IF(D42>0,1,0) -> 1 | U42: =+IF(E42>0,1,0) -> 1 | V42: =+IF(F42>0,1,0) -> 1 | W42: =+IF(G42>0,1,0) -> 1 | X42: =+IF(H42>0,1,0) -> 1 | Y42: =+IF(I42>0,1,0) -> 1 | Z42: =+IF(J42>0,1,0) -> 1 | AA42: =+IF(K42>0,1,0) -> 1 | ... AE42: =+IF(O42>0,1,0) -> 1 | AG42: Sueldos | AH42: Sueldo | AI42: Gerson Alfaro | AJ42: 2947.5685 | AK42: 2824.92 | AL42: 4206.8493 | AM42: 4151.3789 | AN42: 4233.1904 | AO42: 4337.9801 | AP42: 4333.4784 | AQ42: 4449.8019 | AR42: 4531.7376 | AS42: 4395.228 | AT42: 4512.0897 | AU42: 5110.4561 | AW42: =+IF(AD42=1,S42," ") -> Gerson Alfaro | AX42: Ingeniero Principal
A43: Sueldos | B43: Sueldo | C43: Gino Espinoza | D43: 2466.5056 | E43: 2024.3153 | F43: 2057.4273 | G43: 2100.6381 | H43: 2895.7281 | I43: 1984.0207 | J43: 3955.8276 | K43: 3411.674 | L43: 2027.9609 | M43: 1998.3589 | N43: 3148.6061 | O43: 4377.7965 | Q43: =A43 -> Sueldos | R43: =B43 -> Sueldo | S43: =C43 -> Gino Espinoza | T43: =+IF(D43>0,1,0) -> 1 | U43: =+IF(E43>0,1,0) -> 1 | V43: =+IF(F43>0,1,0) -> 1 | W43: =+IF(G43>0,1,0) -> 1 | X43: =+IF(H43>0,1,0) -> 1 | Y43: =+IF(I43>0,1,0) -> 1 | Z43: =+IF(J43>0,1,0) -> 1 | AA43: =+IF(K43>0,1,0) -> 1 | ... AE43: =+IF(O43>0,1,0) -> 1 | AG43: Sueldos | AH43: Sueldo | AI43: Gino Espinoza | AJ43: 2466.5056 | AK43: 2024.3153 | AL43: 2057.4273 | AM43: 2100.6381 | AN43: 2895.7281 | AO43: 1984.0207 | AP43: 3955.8276 | AQ43: 3411.674 | AR43: 2027.9609 | AS43: 1998.3589 | AT43: 3148.6061 | AU43: 4377.7965 | AW43: =+IF(AD43=1,S43," ") -> Gino Espinoza | AX43: Ingeniero de Proyectos
A44: Sueldos | B44: Sueldo | C44: Gladys Myriam Muñoz | D44: 799.46255 | E44: 753.45014 | F44: 727.39971 | G44: 733.30139 | H44: 3490.7308 | I44: 807.42053 | J44: 774.24805 | K44: 851.05925 | L44: 1238.6737 | M44: 761.16647 | N44: 761.16647 | O44: 1085.0671 | Q44: =A44 -> Sueldos | R44: =B44 -> Sueldo | S44: =C44 -> Gladys Myriam Muñoz | T44: =+IF(D44>0,1,0) -> 1 | U44: =+IF(E44>0,1,0) -> 1 | V44: =+IF(F44>0,1,0) -> 1 | W44: =+IF(G44>0,1,0) -> 1 | X44: =+IF(H44>0,1,0) -> 1 | Y44: =+IF(I44>0,1,0) -> 1 | Z44: =+IF(J44>0,1,0) -> 1 | AA44: =+IF(K44>0,1,0) -> 1 | ... AE44: =+IF(O44>0,1,0) -> 1 | AG44: Sueldos | AH44: Sueldo | AI44: Gladys Myriam Muñoz | AJ44: 799.46255 | AK44: 753.45014 | AL44: 727.39971 | AM44: 733.30139 | AN44: 3490.7308 | AO44: 807.42053 | AP44: 774.24805 | AQ44: 851.05925 | AR44: 1238.6737 | AS44: 761.16647 | AT44: 761.16647 | AU44: 1085.0671 | AW44: =+IF(AD44=1,S44," ") -> Gladys Myriam Muñoz | AX44: Administrativo
A45: Sueldos | B45: Sueldo | C45: Grace Ramon | D45: 157.80001 | E45: 296.7861 | F45: 1043.2699 | G45: 1384.8318 | H45: 1413.2443 | I45: 1449.086 | J45: 1481.5545 | K45: 1499.0632 | L45: 1500.7383 | M45: 1467.3403 | N45: 1506.3544 | O45: 1706.1181 | Q45: =A45 -> Sueldos | R45: =B45 -> Sueldo | S45: =C45 -> Grace Ramon | T45: =+IF(D45>0,1,0) -> 1 | U45: =+IF(E45>0,1,0) -> 1 | V45: =+IF(F45>0,1,0) -> 1 | W45: =+IF(G45>0,1,0) -> 1 | X45: =+IF(H45>0,1,0) -> 1 | Y45: =+IF(I45>0,1,0) -> 1 | Z45: =+IF(J45>0,1,0) -> 1 | AA45: =+IF(K45>0,1,0) -> 1 | ... AE45: =+IF(O45>0,1,0) -> 1 | AG45: Sueldos | AH45: Sueldo | AI45: Grace Ramon | AJ45: 157.80001 | AK45: 296.7861 | AL45: 1043.2699 | AM45: 1384.8318 | AN45: 1413.2443 | AO45: 1449.086 | AP45: 1481.5545 | AQ45: 1499.0632 | AR45: 1500.7383 | AS45: 1467.3403 | AT45: 1506.3544 | AU45: 1706.1181 | AW45: =+IF(AD45=1,S45," ") -> Grace Ramon | AX45: Ingeniero de Proyectos
A46: Sueldos | B46: Sueldo | C46: Guillermo Ricaldi | D46: 472.06924 | E46: 474.1 | F46: 483.74093 | G46: 482.06 | H46: 479.62 | I46: 0 | J46: 0 | K46: 0 | L46: 0 | M46: 0 | N46: 0 | O46: 0 | Q46: =A46 -> Sueldos | R46: =B46 -> Sueldo | S46: =C46 -> Guillermo Ricaldi | T46: =+IF(D46>0,1,0) -> 1 | U46: =+IF(E46>0,1,0) -> 1 | V46: =+IF(F46>0,1,0) -> 1 | W46: =+IF(G46>0,1,0) -> 1 | X46: =+IF(H46>0,1,0) -> 1 | Y46: =+IF(I46>0,1,0) -> 0 | Z46: =+IF(J46>0,1,0) -> 0 | AA46: =+IF(K46>0,1,0) -> 0 | ... AE46: =+IF(O46>0,1,0) -> 0 | AG46: Sueldos | AH46: Sueldo | AI46: Guillermo Ricaldi | AJ46: 472.06924 | AK46: 474.1 | AL46: 483.74093 | AM46: 482.06 | AN46: 479.62 | AO46: 0 | AP46: 0 | AQ46: 0 | AR46: 0 | AS46: 0 | AT46: 0 | AU46: 0 | AW46: =+IF(AD46=1,S46," ")
A47: Sueldos | B47: Sueldo | C47: Ignacio González | D47: 1607.4686 | E47: 1411.7378 | F47: 1544.075 | G47: 474.45315 | H47: 0 | I47: 0 | J47: 0 | K47: 0 | L47: 0 | M47: 0 | N47: 0 | O47: 0 | Q47: =A47 -> Sueldos | R47: =B47 -> Sueldo | S47: =C47 -> Ignacio González | T47: =+IF(D47>0,1,0) -> 1 | U47: =+IF(E47>0,1,0) -> 1 | V47: =+IF(F47>0,1,0) -> 1 | W47: =+IF(G47>0,1,0) -> 1 | X47: =+IF(H47>0,1,0) -> 0 | Y47: =+IF(I47>0,1,0) -> 0 | Z47: =+IF(J47>0,1,0) -> 0 | AA47: =+IF(K47>0,1,0) -> 0 | ... AE47: =+IF(O47>0,1,0) -> 0 | AG47: Sueldos | AH47: Sueldo | AI47: Ignacio González | AJ47: 1607.4686 | AK47: 1411.7378 | AL47: 1544.075 | AM47: 474.45315 | AN47: 0 | AO47: 0 | AP47: 0 | AQ47: 0 | AR47: 0 | AS47: 0 | AT47: 0 | AU47: 0 | AW47: =+IF(AD47=1,S47," ")
A48: Sueldos | B48: Sueldo | C48: Isidora Figueroa | D48: 1801.6705 | E48: 1726.4404 | F48: 2243.653 | G48: 1983.776 | H48: 2102.277 | I48: 2154.9123 | J48: 2848.995 | K48: 2297.787 | L48: 2385.6853 | M48: 2182.7477 | N48: 2240.7833 | O48: 2537.9426 | Q48: =A48 -> Sueldos | R48: =B48 -> Sueldo | S48: =C48 -> Isidora Figueroa | T48: =+IF(D48>0,1,0) -> 1 | U48: =+IF(E48>0,1,0) -> 1 | V48: =+IF(F48>0,1,0) -> 1 | W48: =+IF(G48>0,1,0) -> 1 | X48: =+IF(H48>0,1,0) -> 1 | Y48: =+IF(I48>0,1,0) -> 1 | Z48: =+IF(J48>0,1,0) -> 1 | AA48: =+IF(K48>0,1,0) -> 1 | ... AE48: =+IF(O48>0,1,0) -> 1 | AG48: Sueldos | AH48: Sueldo | AI48: Isidora Figueroa | AJ48: 1801.6705 | AK48: 1726.4404 | AL48: 2243.653 | AM48: 1983.776 | AN48: 2102.277 | AO48: 2154.9123 | AP48: 2848.995 | AQ48: 2297.787 | AR48: 2385.6853 | AS48: 2182.7477 | AT48: 2240.7833 | AU48: 2537.9426 | AW48: =+IF(AD48=1,S48," ") -> Isidora Figueroa | AX48: Ingeniero de Proyectos
A49: Sueldos | B49: Sueldo | C49: Ismael Leyton Aliste practicante | D49: 157.80001 | E49: 296.7861 | F49: 204.3325 | G49: 0 | H49: 0 | I49: 0 | J49: 0 | K49: 0 | L49: 0 | M49: 0 | N49: 0 | O49: 0 | Q49: =A49 -> Sueldos | R49: =B49 -> Sueldo | S49: =C49 -> Ismael Leyton Aliste practicante | T49: =+IF(D49>0,1,0) -> 1 | U49: =+IF(E49>0,1,0) -> 1 | V49: =+IF(F49>0,1,0) -> 1 | W49: =+IF(G49>0,1,0) -> 0 | X49: =+IF(H49>0,1,0) -> 0 | Y49: =+IF(I49>0,1,0) -> 0 | Z49: =+IF(J49>0,1,0) -> 0 | AA49: =+IF(K49>0,1,0) -> 0 | ... AE49: =+IF(O49>0,1,0) -> 0 | AG49: Sueldos | AH49: Sueldo | AI49: Ismael Leyton Aliste practicante | AJ49: 157.80001 | AK49: 296.7861 | AL49: 204.3325 | AM49: 0 | AN49: 0 | AO49: 0 | AP49: 0 | AQ49: 0 | AR49: 0 | AS49: 0 | AT49: 0 | AU49: 0 | AW49: =+IF(AD49=1,S49," ")
A50: Sueldos | B50: Sueldo | C50: Jarold Orna | D50: 1704.6945 | E50: 1514.2693 | F50: 2605.5226 | G50: 2669.4747 | H50: 3679.8886 | I50: 2521.2884 | J50: 5026.5344 | K50: 4336.1613 | L50: 2576.8264 | M50: 3583.8616 | N50: 5646.7176 | O50: 5562.7158 | Q50: =A50 -> Sueldos | R50: =B50 -> Sueldo | S50: =C50 -> Jarold Orna | T50: =+IF(D50>0,1,0) -> 1 | U50: =+IF(E50>0,1,0) -> 1 | V50: =+IF(F50>0,1,0) -> 1 | W50: =+IF(G50>0,1,0) -> 1 | X50: =+IF(H50>0,1,0) -> 1 | Y50: =+IF(I50>0,1,0) -> 1 | Z50: =+IF(J50>0,1,0) -> 1 | AA50: =+IF(K50>0,1,0) -> 1 | ... AE50: =+IF(O50>0,1,0) -> 1 | AG50: Sueldos | AH50: Sueldo | AI50: Jarold Orna | AJ50: 1704.6945 | AK50: 1514.2693 | AL50: 2605.5226 | AM50: 2669.4747 | AN50: 3679.8886 | AO50: 2521.2884 | AP50: 5026.5344 | AQ50: 4336.1613 | AR50: 2576.8264 | AS50: 3583.8616 | AT50: 5646.7176 | AU50: 5562.7158 | AW50: =+IF(AD50=1,S50," ") -> Jarold Orna | AX50: Ingeniero de Proyectos
A51: Sueldos | B51: Sueldo | C51: Jessica Rojas | D51: 3345.9327 | E51: 2746.0803 | F51: 2790.9983 | G51: 2849.6109 | H51: 3928.1958 | I51: 2691.4163 | J51: 0 | K51: 0 | L51: 0 | M51: 0 | N51: 0 | O51: 0 | Q51: =A51 -> Sueldos | R51: =B51 -> Sueldo | S51: =C51 -> Jessica Rojas | T51: =+IF(D51>0,1,0) -> 1 | U51: =+IF(E51>0,1,0) -> 1 | V51: =+IF(F51>0,1,0) -> 1 | W51: =+IF(G51>0,1,0) -> 1 | X51: =+IF(H51>0,1,0) -> 1 | Y51: =+IF(I51>0,1,0) -> 1 | Z51: =+IF(J51>0,1,0) -> 0 | AA51: =+IF(K51>0,1,0) -> 0 | ... AE51: =+IF(O51>0,1,0) -> 0 | AG51: Sueldos | AH51: Sueldo | AI51: Jessica Rojas | AJ51: 3345.9327 | AK51: 2746.0803 | AL51: 2790.9983 | AM51: 2849.6109 | AN51: 3928.1958 | AO51: 2691.4163 | AP51: 0 | AQ51: 0 | AR51: 0 | AS51: 0 | AT51: 0 | AU51: 0 | AW51: =+IF(AD51=1,S51," ")
A52: Sueldos | B52: Sueldo | C52: Jhonatan Huaynate | D52: 1442.4338 | E52: 1448.5 | F52: 1478.0973 | G52: 1472.95 | H52: 1465.49 | I52: 1440.92 | J52: 1470 | K52: 1440.92 | L52: 1640.6143 | M52: 3072.6971 | N52: 3990.5422 | O52: 4991.2229 | Q52: =A52 -> Sueldos | R52: =B52 -> Sueldo | S52: =C52 -> Jhonatan Huaynate | T52: =+IF(D52>0,1,0) -> 1 | U52: =+IF(E52>0,1,0) -> 1 | V52: =+IF(F52>0,1,0) -> 1 | W52: =+IF(G52>0,1,0) -> 1 | X52: =+IF(H52>0,1,0) -> 1 | Y52: =+IF(I52>0,1,0) -> 1 | Z52: =+IF(J52>0,1,0) -> 1 | AA52: =+IF(K52>0,1,0) -> 1 | ... AE52: =+IF(O52>0,1,0) -> 1 | AG52: Sueldos | AH52: Sueldo | AI52: Jhonatan Huaynate | AJ52: 1442.4338 | AK52: 1448.5 | AL52: 1478.0973 | AM52: 1472.95 | AN52: 1465.49 | AO52: 1440.92 | AP52: 1470 | AQ52: 1440.92 | AR52: 1640.6143 | AS52: 3072.6971 | AT52: 3990.5422 | AU52: 4991.2229 | AW52: =+IF(AD52=1,S52," ") -> Jhonatan Huaynate | AX52: Ingeniero de Proyectos
A53: Sueldos | B53: Sueldo | C53: Jhonatan Mandujano | D53: 2066.9563 | E53: 1696.3964 | F53: 1724.1446 | G53: 1859.9352 | H53: 2563.9294 | I53: 1756.6901 | J53: 3501.5007 | K53: 3021.1901 | L53: 1794.6556 | M53: 1674.6447 | N53: 2638.5633 | O53: 3875.0064 | Q53: =A53 -> Sueldos | R53: =B53 -> Sueldo | S53: =C53 -> Jhonatan Mandujano | T53: =+IF(D53>0,1,0) -> 1 | U53: =+IF(E53>0,1,0) -> 1 | V53: =+IF(F53>0,1,0) -> 1 | W53: =+IF(G53>0,1,0) -> 1 | X53: =+IF(H53>0,1,0) -> 1 | Y53: =+IF(I53>0,1,0) -> 1 | Z53: =+IF(J53>0,1,0) -> 1 | AA53: =+IF(K53>0,1,0) -> 1 | ... AE53: =+IF(O53>0,1,0) -> 1 | AG53: Sueldos | AH53: Sueldo | AI53: Jhonatan Mandujano | AJ53: 2066.9563 | AK53: 1696.3964 | AL53: 1724.1446 | AM53: 1859.9352 | AN53: 2563.9294 | AO53: 1756.6901 | AP53: 3501.5007 | AQ53: 3021.1901 | AR53: 1794.6556 | AS53: 1674.6447 | AT53: 2638.5633 | AU53: 3875.0064 | AW53: =+IF(AD53=1,S53," ") -> Jhonatan Mandujano | AX53: Ingeniero Senior
A54: Sueldos | B54: Sueldo | C54: Joél Pérez | D54: 1608.1299 | E54: 1541.3997 | F54: 1544.7102 | G54: 1525.4569 | H54: 1556.7343 | I54: 1596.1891 | J54: 1653.6324 | K54: 1638.0232 | L54: 1635.0798 | M54: 1616.3228 | N54: 1659.2981 | O54: 1879.3443 | Q54: =A54 -> Sueldos | R54: =B54 -> Sueldo | S54: =C54 -> Joél Pérez | T54: =+IF(D54>0,1,0) -> 1 | U54: =+IF(E54>0,1,0) -> 1 | V54: =+IF(F54>0,1,0) -> 1 | W54: =+IF(G54>0,1,0) -> 1 | X54: =+IF(H54>0,1,0) -> 1 | Y54: =+IF(I54>0,1,0) -> 1 | Z54: =+IF(J54>0,1,0) -> 1 | AA54: =+IF(K54>0,1,0) -> 1 | ... AE54: =+IF(O54>0,1,0) -> 1 | AG54: Sueldos | AH54: Sueldo | AI54: Joél Pérez | AJ54: 1608.1299 | AK54: 1541.3997 | AL54: 1544.7102 | AM54: 1525.4569 | AN54: 1556.7343 | AO54: 1596.1891 | AP54: 1653.6324 | AQ54: 1638.0232 | AR54: 1635.0798 | AS54: 1616.3228 | AT54: 1659.2981 | AU54: 1879.3443 | AW54: =+IF(AD54=1,S54," ") -> Joél Pérez | AX54: Ingeniero de Proyectos
A55: Sueldos | B55: Sueldo | C55: Johnny Pacheco | D55: 3413.9611 | E55: 2801.9127 | F55: 2847.744 | G55: 2907.5556 | H55: 4008.0756 | I55: 2746.1319 | J55: 5475.0738 | K55: 4722.8516 | L55: 2807.1405 | M55: 2765.9858 | N55: 4358.0759 | O55: 6059.1009 | Q55: =A55 -> Sueldos | R55: =B55 -> Sueldo | S55: =C55 -> Johnny Pacheco | T55: =+IF(D55>0,1,0) -> 1 | U55: =+IF(E55>0,1,0) -> 1 | V55: =+IF(F55>0,1,0) -> 1 | W55: =+IF(G55>0,1,0) -> 1 | X55: =+IF(H55>0,1,0) -> 1 | Y55: =+IF(I55>0,1,0) -> 1 | Z55: =+IF(J55>0,1,0) -> 1 | AA55: =+IF(K55>0,1,0) -> 1 | ... AE55: =+IF(O55>0,1,0) -> 1 | AG55: Sueldos | AH55: Sueldo | AI55: Johnny Pacheco | AJ55: 3413.9611 | AK55: 2801.9127 | AL55: 2847.744 | AM55: 2907.5556 | AN55: 4008.0756 | AO55: 2746.1319 | AP55: 5475.0738 | AQ55: 4722.8516 | AR55: 2807.1405 | AS55: 2765.9858 | AT55: 4358.0759 | AU55: 6059.1009 | AW55: =+IF(AD55=1,S55," ") -> Johnny Pacheco | AX55: Ingeniero Senior
A56: Sueldos | B56: Sueldo | C56: Jonathan Galvez | D56: 1899.7832 | E56: 1820.9965 | F56: 1824.8457 | G56: 1802.0481 | H56: 1838.9605 | I56: 1885.5217 | J56: 1942.8791 | K56: 1944.6447 | L56: 1941.9936 | M56: 1909.352 | N56: 1960.1185 | O56: 2220.0577 | Q56: =A56 -> Sueldos | R56: =B56 -> Sueldo | S56: =C56 -> Jonathan Galvez | T56: =+IF(D56>0,1,0) -> 1 | U56: =+IF(E56>0,1,0) -> 1 | V56: =+IF(F56>0,1,0) -> 1 | W56: =+IF(G56>0,1,0) -> 1 | X56: =+IF(H56>0,1,0) -> 1 | Y56: =+IF(I56>0,1,0) -> 1 | Z56: =+IF(J56>0,1,0) -> 1 | AA56: =+IF(K56>0,1,0) -> 1 | ... AE56: =+IF(O56>0,1,0) -> 1 | AG56: Sueldos | AH56: Sueldo | AI56: Jonathan Galvez | AJ56: 1899.7832 | AK56: 1820.9965 | AL56: 1824.8457 | AM56: 1802.0481 | AN56: 1838.9605 | AO56: 1885.5217 | AP56: 1942.8791 | AQ56: 1944.6447 | AR56: 1941.9936 | AS56: 1909.352 | AT56: 1960.1185 | AU56: 2220.0577 | AW56: =+IF(AD56=1,S56," ") -> Jonathan Galvez | AX56: Ingeniero de Proyectos
A57: Sueldos | B57: Sueldo | C57: Jorman Barrera | D57: 6027.8688 | E57: 4765.172 | F57: 4843.1167 | G57: 4943.5177 | H57: 6814.6612 | I57: 4669.0712 | J57: 9309.3617 | K57: 8030.164 | L57: 4772.2884 | M57: 4704.0717 | N57: 7411.7161 | O57: 10302.393 | Q57: =A57 -> Sueldos | R57: =B57 -> Sueldo | S57: =C57 -> Jorman Barrera | T57: =+IF(D57>0,1,0) -> 1 | U57: =+IF(E57>0,1,0) -> 1 | V57: =+IF(F57>0,1,0) -> 1 | W57: =+IF(G57>0,1,0) -> 1 | X57: =+IF(H57>0,1,0) -> 1 | Y57: =+IF(I57>0,1,0) -> 1 | Z57: =+IF(J57>0,1,0) -> 1 | AA57: =+IF(K57>0,1,0) -> 1 | ... AE57: =+IF(O57>0,1,0) -> 1 | AG57: Sueldos | AH57: Sueldo | AI57: Jorman Barrera | AJ57: 6027.8688 | AK57: 4765.172 | AL57: 4843.1167 | AM57: 4943.5177 | AN57: 6814.6612 | AO57: 4669.0712 | AP57: 9309.3617 | AQ57: 8030.164 | AR57: 4772.2884 | AS57: 4704.0717 | AT57: 7411.7161 | AU57: 10302.393 | AW57: =+IF(AD57=1,S57," ") -> Jorman Barrera | AX57: Ingeniero Principal
A58: Sueldos | B58: Sueldo | C58: Jose Mamani | D58: 655.65172 | E58: 658.4 | F58: 1084.1172 | G58: 1080.34 | H58: 1074.87 | I58: 1056.85 | J58: 1078 | K58: 2062.35 | L58: 0 | M58: 0 | N58: 0 | O58: 0 | Q58: =A58 -> Sueldos | R58: =B58 -> Sueldo | S58: =C58 -> Jose Mamani | T58: =+IF(D58>0,1,0) -> 1 | U58: =+IF(E58>0,1,0) -> 1 | V58: =+IF(F58>0,1,0) -> 1 | W58: =+IF(G58>0,1,0) -> 1 | X58: =+IF(H58>0,1,0) -> 1 | Y58: =+IF(I58>0,1,0) -> 1 | Z58: =+IF(J58>0,1,0) -> 1 | AA58: =+IF(K58>0,1,0) -> 1 | ... AE58: =+IF(O58>0,1,0) -> 0 | AG58: Sueldos | AH58: Sueldo | AI58: Jose Mamani | AJ58: 655.65172 | AK58: 658.4 | AL58: 1084.1172 | AM58: 1080.34 | AN58: 1074.87 | AO58: 1056.85 | AP58: 1078 | AQ58: 2062.35 | AR58: 0 | AS58: 0 | AT58: 0 | AU58: 0 | AW58: =+IF(AD58=1,S58," ")
A59: Sueldos | B59: Sueldo | C59: José Pizarro Aranguiz | D59: 1608.1299 | E59: 1541.3997 | F59: 1822.968 | G59: 1800.1942 | H59: 1837.0688 | I59: 2463.6785 | J59: 2485.6878 | K59: 2517.8079 | L59: 2523.7331 | M59: 2493.6032 | N59: 2559.904 | O59: 2899.3831 | Q59: =A59 -> Sueldos | R59: =B59 -> Sueldo | S59: =C59 -> José Pizarro Aranguiz | T59: =+IF(D59>0,1,0) -> 1 | U59: =+IF(E59>0,1,0) -> 1 | V59: =+IF(F59>0,1,0) -> 1 | W59: =+IF(G59>0,1,0) -> 1 | X59: =+IF(H59>0,1,0) -> 1 | Y59: =+IF(I59>0,1,0) -> 1 | Z59: =+IF(J59>0,1,0) -> 1 | AA59: =+IF(K59>0,1,0) -> 1 | ... AE59: =+IF(O59>0,1,0) -> 1 | AG59: Sueldos | AH59: Sueldo | AI59: José Pizarro Aranguiz | AJ59: 1608.1299 | AK59: 1541.3997 | AL59: 1822.968 | AM59: 1800.1942 | AN59: 1837.0688 | AO59: 2463.6785 | AP59: 2485.6878 | AQ59: 2517.8079 | AR59: 2523.7331 | AS59: 2493.6032 | AT59: 2559.904 | AU59: 2899.3831 | AW59: =+IF(AD59=1,S59," ") -> José Pizarro Aranguiz | AX59: Ingeniero de Proyectos
A60: Sueldos | B60: Sueldo | C60: Josue Tello Olivas | D60: 813.01 | E60: 816.4 | F60: 833.10938 | G60: 207.55 | H60: 0 | I60: 0 | J60: 0 | K60: 0 | L60: 0 | M60: 0 | N60: 0 | O60: 0 | Q60: =A60 -> Sueldos | R60: =B60 -> Sueldo | S60: =C60 -> Josue Tello Olivas | T60: =+IF(D60>0,1,0) -> 1 | U60: =+IF(E60>0,1,0) -> 1 | V60: =+IF(F60>0,1,0) -> 1 | W60: =+IF(G60>0,1,0) -> 1 | X60: =+IF(H60>0,1,0) -> 0 | Y60: =+IF(I60>0,1,0) -> 0 | Z60: =+IF(J60>0,1,0) -> 0 | AA60: =+IF(K60>0,1,0) -> 0 | ... AE60: =+IF(O60>0,1,0) -> 0 | AG60: Sueldos | AH60: Sueldo | AI60: Josue Tello Olivas | AJ60: 813.01 | AK60: 816.4 | AL60: 833.10938 | AM60: 207.55 | AN60: 0 | AO60: 0 | AP60: 0 | AQ60: 0 | AR60: 0 | AS60: 0 | AT60: 0 | AU60: 0 | AW60: =+IF(AD60=1,S60," ")
A61: Sueldos | B61: Sueldo | C61: Juan Pablo Vera | D61: 1954.0567 | E61: 1308.9424 | F61: 0 | G61: 0 | H61: 0 | I61: 0 | J61: 0 | K61: 0 | L61: 0 | M61: 0 | N61: 0 | O61: 0 | Q61: =A61 -> Sueldos | R61: =B61 -> Sueldo | S61: =C61 -> Juan Pablo Vera | T61: =+IF(D61>0,1,0) -> 1 | U61: =+IF(E61>0,1,0) -> 1 | V61: =+IF(F61>0,1,0) -> 0 | W61: =+IF(G61>0,1,0) -> 0 | X61: =+IF(H61>0,1,0) -> 0 | Y61: =+IF(I61>0,1,0) -> 0 | Z61: =+IF(J61>0,1,0) -> 0 | AA61: =+IF(K61>0,1,0) -> 0 | ... AE61: =+IF(O61>0,1,0) -> 0 | AG61: Sueldos | AH61: Sueldo | AI61: Juan Pablo Vera | AJ61: 1954.0567 | AK61: 1308.9424 | AL61: 0 | AM61: 0 | AN61: 0 | AO61: 0 | AP61: 0 | AQ61: 0 | AR61: 0 | AS61: 0 | AT61: 0 | AU61: 0 | AW61: =+IF(AD61=1,S61," ")
A62: Sueldos | B62: Sueldo | C62: Julio Herrera | D62: 3224.2443 | E62: 3090.157 | F62: 3097.2087 | G62: 3058.9594 | H62: 3121.9211 | I62: 3148.9039 | J62: 0 | K62: 0 | L62: 0 | M62: 0 | N62: 0 | O62: 0 | Q62: =A62 -> Sueldos | R62: =B62 -> Sueldo | S62: =C62 -> Julio Herrera | T62: =+IF(D62>0,1,0) -> 1 | U62: =+IF(E62>0,1,0) -> 1 | V62: =+IF(F62>0,1,0) -> 1 | W62: =+IF(G62>0,1,0) -> 1 | X62: =+IF(H62>0,1,0) -> 1 | Y62: =+IF(I62>0,1,0) -> 1 | Z62: =+IF(J62>0,1,0) -> 0 | AA62: =+IF(K62>0,1,0) -> 0 | ... AE62: =+IF(O62>0,1,0) -> 0 | AG62: Sueldos | AH62: Sueldo | AI62: Julio Herrera | AJ62: 3224.2443 | AK62: 3090.157 | AL62: 3097.2087 | AM62: 3058.9594 | AN62: 3121.9211 | AO62: 3148.9039 | AP62: 0 | AQ62: 0 | AR62: 0 | AS62: 0 | AT62: 0 | AU62: 0 | AW62: =+IF(AD62=1,S62," ")
A63: Sueldos | B63: Sueldo | C63: Kevin Rios | D63: 3790.2846 | E63: 4848.606 | F63: 3161.653 | G63: 3228.0533 | H63: 5143.8773 | I63: 3524.35 | J63: 7026.1518 | K63: 6061.2462 | L63: 3601.2756 | M63: 3070.8825 | N63: 4838.4699 | O63: 7775.6327 | Q63: =A63 -> Sueldos | R63: =B63 -> Sueldo | S63: =C63 -> Kevin Rios | T63: =+IF(D63>0,1,0) -> 1 | U63: =+IF(E63>0,1,0) -> 1 | V63: =+IF(F63>0,1,0) -> 1 | W63: =+IF(G63>0,1,0) -> 1 | X63: =+IF(H63>0,1,0) -> 1 | Y63: =+IF(I63>0,1,0) -> 1 | Z63: =+IF(J63>0,1,0) -> 1 | AA63: =+IF(K63>0,1,0) -> 1 | ... AE63: =+IF(O63>0,1,0) -> 1 | AG63: Sueldos | AH63: Sueldo | AI63: Kevin Rios | AJ63: 3790.2846 | AK63: 4848.606 | AL63: 3161.653 | AM63: 3228.0533 | AN63: 5143.8773 | AO63: 3524.35 | AP63: 7026.1518 | AQ63: 6061.2462 | AR63: 3601.2756 | AS63: 3070.8825 | AT63: 4838.4699 | AU63: 7775.6327 | AW63: =+IF(AD63=1,S63," ") -> Kevin Rios | AX63: Ingeniero Principal
A64: Sueldos | B64: Sueldo | C64: Lincoln Esteban Perez | D64: 655.65172 | E64: 658.4 | F64: 671.8624 | G64: 167.38 | H64: 0 | I64: 0 | J64: 0 | K64: 0 | L64: 0 | M64: 0 | N64: 0 | O64: 0 | Q64: =A64 -> Sueldos | R64: =B64 -> Sueldo | S64: =C64 -> Lincoln Esteban Perez | T64: =+IF(D64>0,1,0) -> 1 | U64: =+IF(E64>0,1,0) -> 1 | V64: =+IF(F64>0,1,0) -> 1 | W64: =+IF(G64>0,1,0) -> 1 | X64: =+IF(H64>0,1,0) -> 0 | Y64: =+IF(I64>0,1,0) -> 0 | Z64: =+IF(J64>0,1,0) -> 0 | AA64: =+IF(K64>0,1,0) -> 0 | ... AE64: =+IF(O64>0,1,0) -> 0 | AG64: Sueldos | AH64: Sueldo | AI64: Lincoln Esteban Perez | AJ64: 655.65172 | AK64: 658.4 | AL64: 671.8624 | AM64: 167.38 | AN64: 0 | AO64: 0 | AP64: 0 | AQ64: 0 | AR64: 0 | AS64: 0 | AT64: 0 | AU64: 0 | AW64: =+IF(AD64=1,S64," ")
A65: Sueldos | B65: Sueldo | C65: Luis Camasca | D65: 1294.2706 | E65: 1062.2362 | F65: 1079.6114 | G65: 0 | H65: 0 | I65: 0 | J65: 0 | K65: 0 | L65: 0 | M65: 0 | N65: 0 | O65: 0 | Q65: =A65 -> Sueldos | R65: =B65 -> Sueldo | S65: =C65 -> Luis Camasca | T65: =+IF(D65>0,1,0) -> 1 | U65: =+IF(E65>0,1,0) -> 1 | V65: =+IF(F65>0,1,0) -> 1 | W65: =+IF(G65>0,1,0) -> 0 | X65: =+IF(H65>0,1,0) -> 0 | Y65: =+IF(I65>0,1,0) -> 0 | Z65: =+IF(J65>0,1,0) -> 0 | AA65: =+IF(K65>0,1,0) -> 0 | ... AE65: =+IF(O65>0,1,0) -> 0 | AG65: Sueldos | AH65: Sueldo | AI65: Luis Camasca | AJ65: 1294.2706 | AK65: 1062.2362 | AL65: 1079.6114 | AM65: 0 | AN65: 0 | AO65: 0 | AP65: 0 | AQ65: 0 | AR65: 0 | AS65: 0 | AT65: 0 | AU65: 0 | AW65: =+IF(AD65=1,S65," ")
A66: Sueldos | B66: Sueldo | C66: Luis Chumpitaz | D66: 367.16496 | E66: 368.7 | F66: 376.24295 | G66: 374.93 | H66: 373.03 | I66: 366.78 | J66: 855 | K66: 838.35 | L66: 848 | M66: 376.24295 | N66: 376.24295 | O66: 376.24295 | Q66: =A66 -> Sueldos | R66: =B66 -> Sueldo | S66: =C66 -> Luis Chumpitaz | T66: =+IF(D66>0,1,0) -> 1 | U66: =+IF(E66>0,1,0) -> 1 | V66: =+IF(F66>0,1,0) -> 1 | W66: =+IF(G66>0,1,0) -> 1 | X66: =+IF(H66>0,1,0) -> 1 | Y66: =+IF(I66>0,1,0) -> 1 | Z66: =+IF(J66>0,1,0) -> 1 | AA66: =+IF(K66>0,1,0) -> 1 | ... AE66: =+IF(O66>0,1,0) -> 1 | AG66: Sueldos | AH66: Sueldo | AI66: Luis Chumpitaz | AJ66: 367.16496 | AK66: 368.7 | AL66: 376.24295 | AM66: 374.93 | AN66: 373.03 | AO66: 366.78 | AP66: 855 | AQ66: 838.35 | AR66: 848 | AS66: 376.24295 | AT66: 376.24295 | AU66: 376.24295 | AW66: =+IF(AD66=1,S66," ") -> Luis Chumpitaz | AX66: Ingeniero de Proyectos
A67: Sueldos | B67: Sueldo | C67: Marcelo Mendoza | D67: 1900.1613 | E67: 1821.3576 | F67: 1825.2075 | G67: 1802.4053 | H67: 1839.3249 | I67: 1885.8954 | J67: 1944.1036 | K67: 1789.7951 | L67: 1945.5428 | M67: 1909.7304 | N67: 1960.507 | O67: 2220.4977 | Q67: =A67 -> Sueldos | R67: =B67 -> Sueldo | S67: =C67 -> Marcelo Mendoza | T67: =+IF(D67>0,1,0) -> 1 | U67: =+IF(E67>0,1,0) -> 1 | V67: =+IF(F67>0,1,0) -> 1 | W67: =+IF(G67>0,1,0) -> 1 | X67: =+IF(H67>0,1,0) -> 1 | Y67: =+IF(I67>0,1,0) -> 1 | Z67: =+IF(J67>0,1,0) -> 1 | AA67: =+IF(K67>0,1,0) -> 1 | ... AE67: =+IF(O67>0,1,0) -> 1 | AG67: Sueldos | AH67: Sueldo | AI67: Marcelo Mendoza | AJ67: 1900.1613 | AK67: 1821.3576 | AL67: 1825.2075 | AM67: 1802.4053 | AN67: 1839.3249 | AO67: 1885.8954 | AP67: 1944.1036 | AQ67: 1789.7951 | AR67: 1945.5428 | AS67: 1909.7304 | AT67: 1960.507 | AU67: 2220.4977 | AW67: =+IF(AD67=1,S67," ") -> Marcelo Mendoza | AX67: Ingeniero de Proyectos
A68: Sueldos | B68: Sueldo | C68: Maria Célia Fonseca | D68: 1531.846 | E68: 1546.9079 | F68: 2115.5404 | G68: 1599.2618 | H68: 1060.36 | I68: 1558.91 | J68: 1362.778 | K68: 1463.2386 | L68: 1558.6453 | M68: 1558.6453 | N68: 1558.6453 | O68: 1558.6453 | Q68: =A68 -> Sueldos | R68: =B68 -> Sueldo | S68: =C68 -> Maria Célia Fonseca | T68: =+IF(D68>0,1,0) -> 1 | U68: =+IF(E68>0,1,0) -> 1 | V68: =+IF(F68>0,1,0) -> 1 | W68: =+IF(G68>0,1,0) -> 1 | X68: =+IF(H68>0,1,0) -> 1 | Y68: =+IF(I68>0,1,0) -> 1 | Z68: =+IF(J68>0,1,0) -> 1 | AA68: =+IF(K68>0,1,0) -> 1 | ... AE68: =+IF(O68>0,1,0) -> 1 | AG68: Sueldos | AH68: Sueldo | AI68: Maria Célia Fonseca | AJ68: 1531.846 | AK68: 1546.9079 | AL68: 2115.5404 | AM68: 1599.2618 | AN68: 1060.36 | AO68: 1558.91 | AP68: 1362.778 | AQ68: 1463.2386 | AR68: 1558.6453 | AS68: 1558.6453 | AT68: 1558.6453 | AU68: 1558.6453 | AW68: =+IF(AD68=1,S68," ") -> Maria Célia Fonseca | AX68: Administrativo
A69: Sueldos | B69: Sueldo | C69: Matías Cid Uslar | D69: 928.23769 | E69: 1486.1762 | F69: 1485.2394 | G69: 1465.9216 | H69: 1495.1102 | I69: 1532.3384 | J69: 1603.47 | K69: 1924.1712 | L69: 1956.9501 | M69: 1552.3399 | N69: 1593.614 | O69: 1804.9496 | Q69: =A69 -> Sueldos | R69: =B69 -> Sueldo | S69: =C69 -> Matías Cid Uslar | T69: =+IF(D69>0,1,0) -> 1 | U69: =+IF(E69>0,1,0) -> 1 | V69: =+IF(F69>0,1,0) -> 1 | W69: =+IF(G69>0,1,0) -> 1 | X69: =+IF(H69>0,1,0) -> 1 | Y69: =+IF(I69>0,1,0) -> 1 | Z69: =+IF(J69>0,1,0) -> 1 | AA69: =+IF(K69>0,1,0) -> 1 | ... AE69: =+IF(O69>0,1,0) -> 1 | AG69: Sueldos | AH69: Sueldo | AI69: Matías Cid Uslar | AJ69: 928.23769 | AK69: 1486.1762 | AL69: 1485.2394 | AM69: 1465.9216 | AN69: 1495.1102 | AO69: 1532.3384 | AP69: 1603.47 | AQ69: 1924.1712 | AR69: 1956.9501 | AS69: 1552.3399 | AT69: 1593.614 | AU69: 1804.9496 | AW69: =+IF(AD69=1,S69," ") -> Matías Cid Uslar | AX69: Ingeniero de Proyectos
A70: Sueldos | B70: Sueldo | C70: Matías Fuentes B. | D70: 10427.76 | E70: 9983.5296 | F70: 10086.708 | G70: 9968.5089 | H70: 10176.831 | I70: 10441.538 | J70: 10945.563 | K70: 12068.867 | L70: 11352.381 | M70: 10566.378 | N70: 10847.321 | O70: 12285.827 | Q70: =A70 -> Sueldos | R70: =B70 -> Sueldo | S70: =C70 -> Matías Fuentes B. | T70: =+IF(D70>0,1,0) -> 1 | U70: =+IF(E70>0,1,0) -> 1 | V70: =+IF(F70>0,1,0) -> 1 | W70: =+IF(G70>0,1,0) -> 1 | X70: =+IF(H70>0,1,0) -> 1 | Y70: =+IF(I70>0,1,0) -> 1 | Z70: =+IF(J70>0,1,0) -> 1 | AA70: =+IF(K70>0,1,0) -> 1 | ... AE70: =+IF(O70>0,1,0) -> 1 | AG70: Sueldos | AH70: Sueldo | AI70: Matías Fuentes B. | AJ70: 10427.76 | AK70: 9983.5296 | AL70: 10086.708 | AM70: 9968.5089 | AN70: 10176.831 | AO70: 10441.538 | AP70: 10945.563 | AQ70: 12068.867 | AR70: 11352.381 | AS70: 10566.378 | AT70: 10847.321 | AU70: 12285.827 | AW70: =+IF(AD70=1,S70," ") -> Matías Fuentes B. | AX70: Gerente Ingeniería
A71: Sueldos | B71: Sueldo | C71: Mauricio Melendez | D71: 6756.0611 | E71: 6512.7914 | F71: 8230.7512 | G71: 8132.7126 | H71: 8260.3497 | I71: 8477.7067 | J71: 8303.7475 | K71: 8676.4372 | L71: 8709.3315 | M71: 8576.5385 | N71: 8804.5744 | O71: 9972.1844 | Q71: =A71 -> Sueldos | R71: =B71 -> Sueldo | S71: =C71 -> Mauricio Melendez | T71: =+IF(D71>0,1,0) -> 1 | U71: =+IF(E71>0,1,0) -> 1 | V71: =+IF(F71>0,1,0) -> 1 | W71: =+IF(G71>0,1,0) -> 1 | X71: =+IF(H71>0,1,0) -> 1 | Y71: =+IF(I71>0,1,0) -> 1 | Z71: =+IF(J71>0,1,0) -> 1 | AA71: =+IF(K71>0,1,0) -> 1 | ... AE71: =+IF(O71>0,1,0) -> 1 | AG71: Sueldos | AH71: Sueldo | AI71: Mauricio Melendez | AJ71: 6756.0611 | AK71: 6512.7914 | AL71: 8230.7512 | AM71: 8132.7126 | AN71: 8260.3497 | AO71: 8477.7067 | AP71: 8303.7475 | AQ71: 8676.4372 | AR71: 8709.3315 | AS71: 8576.5385 | AT71: 8804.5744 | AU71: 9972.1844 | AW71: =+IF(AD71=1,S71," ") -> Mauricio Melendez | AX71: Consultor
A72: Sueldos | B72: Sueldo | C72: Miguel Jesus | D72: 7859.4716 | E72: 6450.4407 | F72: 6555.9515 | G72: 6693.4514 | H72: 9226.9465 | I72: 6321.8667 | J72: 12605.402 | K72: 0 | L72: 0 | M72: 0 | N72: 0 | O72: 0 | Q72: =A72 -> Sueldos | R72: =B72 -> Sueldo | S72: =C72 -> Miguel Jesus | T72: =+IF(D72>0,1,0) -> 1 | U72: =+IF(E72>0,1,0) -> 1 | V72: =+IF(F72>0,1,0) -> 1 | W72: =+IF(G72>0,1,0) -> 1 | X72: =+IF(H72>0,1,0) -> 1 | Y72: =+IF(I72>0,1,0) -> 1 | Z72: =+IF(J72>0,1,0) -> 1 | AA72: =+IF(K72>0,1,0) -> 0 | ... AE72: =+IF(O72>0,1,0) -> 0 | AG72: Sueldos | AH72: Sueldo | AI72: Miguel Jesus | AJ72: 7859.4716 | AK72: 6450.4407 | AL72: 6555.9515 | AM72: 6693.4514 | AN72: 9226.9465 | AO72: 6321.8667 | AP72: 12605.402 | AQ72: 0 | AR72: 0 | AS72: 0 | AT72: 0 | AU72: 0 | AW72: =+IF(AD72=1,S72," ")
A73: Sueldos | B73: Sueldo | C73: Nelson Rumino | D73: 8571.5704 | E73: 8217.194 | F73: 8208.0735 | G73: 5202.6789 | H73: 9345.9367 | I73: 0 | J73: 0 | K73: 0 | L73: 0 | M73: 0 | N73: 0 | O73: 0 | Q73: =A73 -> Sueldos | R73: =B73 -> Sueldo | S73: =C73 -> Nelson Rumino | T73: =+IF(D73>0,1,0) -> 1 | U73: =+IF(E73>0,1,0) -> 1 | V73: =+IF(F73>0,1,0) -> 1 | W73: =+IF(G73>0,1,0) -> 1 | X73: =+IF(H73>0,1,0) -> 1 | Y73: =+IF(I73>0,1,0) -> 0 | Z73: =+IF(J73>0,1,0) -> 0 | AA73: =+IF(K73>0,1,0) -> 0 | ... AE73: =+IF(O73>0,1,0) -> 0 | AG73: Sueldos | AH73: Sueldo | AI73: Nelson Rumino | AJ73: 8571.5704 | AK73: 8217.194 | AL73: 8208.0735 | AM73: 5202.6789 | AN73: 9345.9367 | AO73: 0 | AP73: 0 | AQ73: 0 | AR73: 0 | AS73: 0 | AT73: 0 | AU73: 0 | AW73: =+IF(AD73=1,S73," ")
A74: Sueldos | B74: Sueldo | C74: Nicolás Ayarza D. | D74: 2947.789 | E74: 2825.1313 | F74: 4206.8493 | G74: 4151.3789 | H74: 4233.1904 | I74: 4337.9801 | J74: 4333.4784 | K74: 4449.8019 | L74: 4531.7376 | M74: 4395.228 | N74: 4512.0897 | O74: 5110.4561 | Q74: =A74 -> Sueldos | R74: =B74 -> Sueldo | S74: =C74 -> Nicolás Ayarza D. | T74: =+IF(D74>0,1,0) -> 1 | U74: =+IF(E74>0,1,0) -> 1 | V74: =+IF(F74>0,1,0) -> 1 | W74: =+IF(G74>0,1,0) -> 1 | X74: =+IF(H74>0,1,0) -> 1 | Y74: =+IF(I74>0,1,0) -> 1 | Z74: =+IF(J74>0,1,0) -> 1 | AA74: =+IF(K74>0,1,0) -> 1 | ... AE74: =+IF(O74>0,1,0) -> 1 | AG74: Sueldos | AH74: Sueldo | AI74: Nicolás Ayarza D. | AJ74: 2947.789 | AK74: 2825.1313 | AL74: 4206.8493 | AM74: 4151.3789 | AN74: 4233.1904 | AO74: 4337.9801 | AP74: 4333.4784 | AQ74: 4449.8019 | AR74: 4531.7376 | AS74: 4395.228 | AT74: 4512.0897 | AU74: 5110.4561 | AW74: =+IF(AD74=1,S74," ") -> Nicolás Ayarza D. | AX74: Ingeniero Principal
A75: Sueldos | B75: Sueldo | C75: Nicolás Sanzana | D75: 1938.2542 | E75: 1857.877 | F75: 2243.653 | G75: 2215.5565 | H75: 2260.8933 | I75: 2318.0773 | J75: 2360.6434 | K75: 2386.5227 | L75: 2388.0888 | M75: 2347.4355 | N75: 2409.8499 | O75: 2729.4298 | Q75: =A75 -> Sueldos | R75: =B75 -> Sueldo | S75: =C75 -> Nicolás Sanzana | T75: =+IF(D75>0,1,0) -> 1 | U75: =+IF(E75>0,1,0) -> 1 | V75: =+IF(F75>0,1,0) -> 1 | W75: =+IF(G75>0,1,0) -> 1 | X75: =+IF(H75>0,1,0) -> 1 | Y75: =+IF(I75>0,1,0) -> 1 | Z75: =+IF(J75>0,1,0) -> 1 | AA75: =+IF(K75>0,1,0) -> 1 | ... AE75: =+IF(O75>0,1,0) -> 1 | AG75: Sueldos | AH75: Sueldo | AI75: Nicolás Sanzana | AJ75: 1938.2542 | AK75: 1857.877 | AL75: 2243.653 | AM75: 2215.5565 | AN75: 2260.8933 | AO75: 2318.0773 | AP75: 2360.6434 | AQ75: 2386.5227 | AR75: 2388.0888 | AS75: 2347.4355 | AT75: 2409.8499 | AU75: 2729.4298 | AW75: =+IF(AD75=1,S75," ") -> Nicolás Sanzana | AX75: Ingeniero de Proyectos
A76: Sueldos | B76: Sueldo | C76: Nilcélio José Dos Santos | D76: 2829.304 | E76: 2609.6521 | F76: 3831.9996 | G76: 2879.8682 | H76: 1881.46 | I76: 3098.1 | J76: 4489.222 | K76: 2622.9914 | L76: 2724.3547 | M76: 2724.3547 | N76: 2724.3547 | O76: 2724.3547 | Q76: =A76 -> Sueldos | R76: =B76 -> Sueldo | S76: =C76 -> Nilcélio José Dos Santos | T76: =+IF(D76>0,1,0) -> 1 | U76: =+IF(E76>0,1,0) -> 1 | V76: =+IF(F76>0,1,0) -> 1 | W76: =+IF(G76>0,1,0) -> 1 | X76: =+IF(H76>0,1,0) -> 1 | Y76: =+IF(I76>0,1,0) -> 1 | Z76: =+IF(J76>0,1,0) -> 1 | AA76: =+IF(K76>0,1,0) -> 1 | ... AE76: =+IF(O76>0,1,0) -> 1 | AG76: Sueldos | AH76: Sueldo | AI76: Nilcélio José Dos Santos | AJ76: 2829.304 | AK76: 2609.6521 | AL76: 3831.9996 | AM76: 2879.8682 | AN76: 1881.46 | AO76: 3098.1 | AP76: 4489.222 | AQ76: 2622.9914 | AR76: 2724.3547 | AS76: 2724.3547 | AT76: 2724.3547 | AU76: 2724.3547 | AW76: =+IF(AD76=1,S76," ") -> Nilcélio José Dos Santos | AX76: Administrativo
A77: Sueldos | B77: Sueldo | C77: Olesya Dashavskaya | D77: 3341.2793 | E77: 3225.9169 | F77: 3130.9925 | G77: 3092.3157 | H77: 3155.957 | I77: 3447.4363 | J77: 3341.4649 | K77: 3754.8482 | L77: 3457.0857 | M77: 3276.7604 | N77: 3363.884 | O77: 3809.9822 | Q77: =A77 -> Sueldos | R77: =B77 -> Sueldo | S77: =C77 -> Olesya Dashavskaya | T77: =+IF(D77>0,1,0) -> 1 | U77: =+IF(E77>0,1,0) -> 1 | V77: =+IF(F77>0,1,0) -> 1 | W77: =+IF(G77>0,1,0) -> 1 | X77: =+IF(H77>0,1,0) -> 1 | Y77: =+IF(I77>0,1,0) -> 1 | Z77: =+IF(J77>0,1,0) -> 1 | AA77: =+IF(K77>0,1,0) -> 1 | ... AE77: =+IF(O77>0,1,0) -> 1 | AG77: Sueldos | AH77: Sueldo | AI77: Olesya Dashavskaya | AJ77: 3341.2793 | AK77: 3225.9169 | AL77: 3130.9925 | AM77: 3092.3157 | AN77: 3155.957 | AO77: 3447.4363 | AP77: 3341.4649 | AQ77: 3754.8482 | AR77: 3457.0857 | AS77: 3276.7604 | AT77: 3363.884 | AU77: 3809.9822 | AW77: =+IF(AD77=1,S77," ") -> Olesya Dashavskaya | AX77: Country Manager
